Workbook

Sheet CPD PITSS
B2: CONSULTORIA EN PROYECTOS DINAMICOS S DE RL DE CV
B3: Lista de Raya (forma tabular)
B4: Periodo 9 al 9 QNA SEITON del 01/05/2019 al 15/05/2019
B5: Reg Pat IMSS: Z2940859106
B6: RFC: CPD -150911-FA3
B7: 1 | C7: =+B7+1 -> 2 | D7: =+C7+1 -> 3 | E7: =+D7+1 -> 4 | F7: =+E7+1 -> 5 | G7: =+F7+1 -> 6 | H7: =+G7+1 -> 7 | I7: =+H7+1 -> 8 | J7: =+I7+1 -> 9 | ... V7: =+U7+1 -> 21
A8: Código | B8: Empleado | C8: Dias Laborados | D8: Dias Vacaciones | E8: Salario Diario | F8: Salario Diario Integrado | G8: Sueldo | H8: Vacaciones a tiempo | I8: Prima de vacaciones a tiempo | J8: Ayuda de Transporte | K8: Ayuda Alimentaria | L8: Ayuda de Renta | M8: *TOTAL* *PERCEPCIONES* | N8: Seguro de vivienda Infonavit | O8: Préstamo Infonavit (vsm) | P8: Subsidio al Empleo (sp) | Q8: I.S.R. (sp) | R8: I.M.S.S. | S8: Deduccion General | T8: Ajuste al neto | U8: *TOTAL* *DEDUCCIONES* | V8: *NETO* | W8: Invalidez y Vida | X8: Cesantia y Vejez | Y8: Enf. y Mat. Patron | Z8: 2% Fondo retiro SAR (8) | AA8: 2% Impuesto estatal | AB8: Riesgo de trabajo (9) | AC8: I.M.S.S. empresa | AD8: Infonavit empresa | AE8: Guarderia I.M.S.S. (7) | AF8: Banco | AG8: Aguinaldo | AH8: infonavit | AI8: subtotal 1 | AJ8: comision | AK8: subtotal 2 | AL8: costo patrimonial | AM8: 2% sobre nomina | AN8: importe de factura | AO8: iva
A9: SEI0009 | B9: Gutierrez Gutierrez Luis Arturo | C9: 15 | D9: 0 | E9: 141.67 | F9: 150.25 | G9: 2125.05 | H9: 0 | I9: 0 | J9: 212.51 | K9: 212.51 | L9: 212.51 | M9: 2762.58 | N9: 0 | O9: 0 | P9: -65.5 | Q9: 0 | R9: 53.52 | S9: 0 | T9: -0.04 | U9: -12.02 | V9: 2774.6 | W9: 39.44 | X9: 70.99 | Y9: 297.98 | Z9: 372.78 | AA9: 55.25 | AB9: 11.27 | AC9: 408.41 | AD9: 112.69 | AE9: 350.24 | AF9: 110 | AG9: =((20/365.24)*15)*($E9*1.3) -> 151.27396 | AH9: =N9+O9 -> 0 | AI9: =V9+S9+AH9 -> 2774.6 | AJ9: =AI9*2% -> 55.492 | AK9: =AI9+AJ9 -> 2830.092 | AL9: =R9+W9+X9+Y9+AB9+Z9+AD9+AE9 -> 1308.91 | AM9: =AL9*2% -> 26.1782 | AN9: =AK9+AL9+AM9 -> 4165.1802 | AO9: =AN9*0.16 -> 666.42883
A10: SEI0026 | B10: Patricio Aguilar Jhonattan Cristian | C10: 15 | D10: 0 | E10: 150 | F10: 159.07 | G10: 2250 | H10: 0 | I10: 0 | J10: 225 | K10: 225 | L10: 225 | M10: 2925 | N10: 0 | O10: 0 | P10: -43.57 | Q10: 0 | R10: 56.67 | S10: 0 | T10: -0.1 | U10: 13 | V10: 2912 | W10: 41.76 | X10: 75.16 | Y10: 300.29 | Z10: 375.42 | AA10: 58.5 | AB10: 11.93 | AC10: 417.21 | AD10: 119.31 | AE10: 351.56 | AF10: 110 | AG10: =((20/365.24)*15)*($E10*1.3) -> 160.16866 | AH10: =N10+O10 -> 0 | AI10: =V10+S10+AH10 -> 2912 | AJ10: =AI10*2% -> 58.24 | AK10: =AI10+AJ10 -> 2970.24 | AL10: =R10+W10+X10+Y10+AB10+Z10+AD10+AE10 -> 1332.1 | AM10: =AL10*2% -> 26.642 | AN10: =AK10+AL10+AM10 -> 4328.982 | AO10: =AN10*0.16 -> 692.63712
A11: SEI0040 | B11: Mora Ramirez Acal Aldo Isidro | C11: 15 | D11: 0 | E11: 216.67 | F11: 229.79 | G11: 3250.05 | H11: 0 | I11: 0 | J11: 325.01 | K11: 325.01 | L11: 325.01 | M11: 4225.08 | N11: 0 | O11: 0 | P11: 0 | Q11: 107.17 | R11: 81.87 | S11: 0 | T11: 0.04 | U11: 189.08 | V11: 4036 | W11: 60.32 | X11: 108.58 | Y11: 318.86 | Z11: 396.64 | AA11: 84.5 | AB11: 17.23 | AC11: 487.76 | AD11: 172.34 | AE11: 362.17 | AF11: 110 | AG11: =((20/365.24)*15)*($E11*1.3) -> 231.35828 | AH11: =N11+O11 -> 0 | AI11: =V11+S11+AH11 -> 4036 | AJ11: =AI11*2% -> 80.72 | AK11: =AI11+AJ11 -> 4116.72 | AL11: =R11+W11+X11+Y11+AB11+Z11+AD11+AE11 -> 1518.01 | AM11: =AL11*2% -> 30.3602 | AN11: =AK11+AL11+AM11 -> 5665.0902 | AO11: =AN11*0.16 -> 906.41443
A12: SEI0041 | B12: Vazquez Perez Miguel Angel | C12: 15 | D12: 0 | E12: 283.33 | F12: 300.49 | G12: 4249.95 | H12: 0 | I12: 0 | J12: 425 | K12: 425 | L12: 425 | M12: 5524.95 | N12: 0 | O12: 0 | P12: 0 | Q12: 341.06 | R12: 109.87 | S12: 0 | T12: 0.02 | U12: 450.95 | V12: 5074 | W12: 78.88 | X12: 141.98 | Y12: 345.18 | Z12: 417.85 | AA12: 110.5 | AB12: 22.54 | AC12: 566.04 | AD12: 225.37 | AE12: 372.77 | AF12: 110 | AG12: =((20/365.24)*15)*($E12*1.3) -> 302.53724 | AH12: =N12+O12 -> 0 | AI12: =V12+S12+AH12 -> 5074 | AJ12: =AI12*2% -> 101.48 | AK12: =AI12+AJ12 -> 5175.48 | AL12: =R12+W12+X12+Y12+AB12+Z12+AD12+AE12 -> 1714.44 | AM12: =AL12*2% -> 34.2888 | AN12: =AK12+AL12+AM12 -> 6924.2088 | AO12: =AN12*0.16 -> 1107.8734
A13: SEI0088 | B13: Morgado Fernandez Martin | C13: 15 | D13: 0 | E13: 273.33 | F13: 289.87 | G13: 4099.95 | H13: 0 | I13: 0 | J13: 410 | K13: 410 | L13: 410 | M13: 5329.95 | N13: 0 | O13: 0 | P13: 0 | Q13: 324.74 | R13: 105.46 | S13: 0 | T13: -0.05 | U13: 430.15 | V13: 4899.8 | W13: 76.09 | X13: 136.96 | Y13: 340.64 | Z13: 414.66 | AA13: 106.6 | AB13: 21.74 | AC13: 553.69 | AD13: 217.4 | AE13: 371.18 | AF13: 110 | AG13: =((20/365.24)*15)*($E13*1.3) -> 291.85933 | AH13: =N13+O13 -> 0 | AI13: =V13+S13+AH13 -> 4899.8 | AJ13: =AI13*2% -> 97.996 | AK13: =AI13+AJ13 -> 4997.796 | AL13: =R13+W13+X13+Y13+AB13+Z13+AD13+AE13 -> 1684.13 | AM13: =AL13*2% -> 33.6826 | AN13: =AK13+AL13+AM13 -> 6715.6086 | AO13: =AN13*0.16 -> 1074.4974
A14: SEI0097 | B14: Arreola Jimenez Jose Nieves | C14: 13 | D14: 2 | E14: 185.83 | F14: 197.07 | G14: 2415.79 | H14: 371.66 | I14: 111.5 | J14: 278.75 | K14: 278.75 | L14: 278.75 | M14: 3735.2 | N14: 15 | O14: 1508.27 | P14: 0 | Q14: 36.57 | R14: 70.22 | S14: 0 | T14: -0.06 | U14: 1630 | V14: 2105.2 | W14: 51.73 | X14: 93.12 | Y14: 310.27 | Z14: 386.82 | AA14: 74.7 | AB14: 14.78 | AC14: 455.12 | AD14: 147.8 | AE14: 357.26 | AF14: 110 | AG14: =((20/365.24)*15)*($E14*1.3) -> 198.42761 | AH14: =N14+O14 -> 1523.27 | AI14: =V14+S14+AH14 -> 3628.47 | AJ14: =AI14*2% -> 72.5694 | AK14: =AI14+AJ14 -> 3701.0394 | AL14: =R14+W14+X14+Y14+AB14+Z14+AD14+AE14 -> 1432 | AM14: =AL14*2% -> 28.64 | AN14: =AK14+AL14+AM14 -> 5161.6794 | AO14: =AN14*0.16 -> 825.8687
A15: SEI0099 | B15: Garcia Villicaña Ricardo Pascual | C15: 15 | D15: 0 | E15: 273.33 | F15: 289.87 | G15: 4099.95 | H15: 0 | I15: 0 | J15: 410 | K15: 410 | L15: 410 | M15: 5329.95 | N15: 0 | O15: 0 | P15: 0 | Q15: 324.74 | R15: 105.46 | S15: 175.43 | T15: 0.12 | U15: 605.75 | V15: =+M15-U15 -> 4724.2 | W15: 76.09 | X15: 136.96 | Y15: 340.64 | Z15: 414.66 | AA15: 106.6 | AB15: 21.74 | AC15: 553.69 | AD15: 217.4 | AE15: 371.18 | AF15: 110 | AG15: =((20/365.24)*15)*($E15*1.3) -> 291.85933 | AH15: =N15+O15 -> 0 | AI15: =V15+S15+AH15 -> 4899.63 | AJ15: =AI15*2% -> 97.9926 | AK15: =AI15+AJ15 -> 4997.6226 | AL15: =R15+W15+X15+Y15+AB15+Z15+AD15+AE15 -> 1684.13 | AM15: =AL15*2% -> 33.6826 | AN15: =AK15+AL15+AM15 -> 6715.4352 | AO15: =AN15*0.16 -> 1074.4696
A16: SEI0108 | B16: Caballero Diaz Francisco Javier | C16: 15 | D16: 0 | E16: 185.83 | F16: 197.07 | G16: 2787.45 | H16: 0 | I16: 0 | J16: 278.75 | K16: 278.75 | L16: 278.75 | M16: 3623.7 | N16: 15 | O16: 1750.48 | P16: 0 | Q16: 36.57 | R16: 70.22 | S16: 0 | T16: 0.03 | U16: 1872.3 | V16: 1751.4 | W16: 51.73 | X16: 93.12 | Y16: 310.27 | Z16: 386.82 | AA16: 72.47 | AB16: 14.78 | AC16: 455.12 | AD16: 147.8 | AE16: 357.26 | AF16: 110 | AG16: =((20/365.24)*15)*($E16*1.3) -> 198.42761 | AH16: =N16+O16 -> 1765.48 | AI16: =V16+S16+AH16 -> 3516.88 | AJ16: =AI16*2% -> 70.3376 | AK16: =AI16+AJ16 -> 3587.2176 | AL16: =R16+W16+X16+Y16+AB16+Z16+AD16+AE16 -> 1432 | AM16: =AL16*2% -> 28.64 | AN16: =AK16+AL16+AM16 -> 5047.8576 | AO16: =AN16*0.16 -> 807.65722
A17: SEI0116 | B17: Casillas Cardona Cesar Alejandro | C17: 15 | D17: 0 | E17: 220.83 | F17: 234.19 | G17: 3312.45 | H17: 0 | I17: 0 | J17: 331.25 | K17: 331.25 | L17: 331.25 | M17: 4306.2 | N17: 15 | O17: 1010.9 | P17: 0 | Q17: 113.96 | R17: 83.43 | S17: 0 | T17: -0.09 | U17: 1223.2 | V17: 3083 | W17: 61.47 | X17: 110.65 | Y17: 320.01 | Z17: 397.96 | AA17: 86.12 | AB17: 17.56 | AC17: 492.13 | AD17: 175.64 | AE17: 362.83 | AF17: 110 | AG17: =((20/365.24)*15)*($E17*1.3) -> 235.8003 | AH17: =N17+O17 -> 1025.9 | AI17: =V17+S17+AH17 -> 4108.9 | AJ17: =AI17*2% -> 82.178 | AK17: =AI17+AJ17 -> 4191.078 | AL17: =R17+W17+X17+Y17+AB17+Z17+AD17+AE17 -> 1529.55 | AM17: =AL17*2% -> 30.591 | AN17: =AK17+AL17+AM17 -> 5751.219 | AO17: =AN17*0.16 -> 920.19504
A18: SEI0117 | B18: Mariscal Romero Luis Adrian | C18: 15 | D18: 0 | E18: 264.58 | F18: 276.54 | G18: 3968.7 | H18: 0 | I18: 0 | J18: 396.87 | K18: 396.87 | L18: 396.87 | M18: 5159.31 | N18: 15 | O18: 1604.18 | P18: 0 | Q18: 310.46 | R18: 99.91 | S18: 0 | T18: -0.04 | U18: 2029.51 | V18: 3129.8 | W18: 72.59 | X18: 130.66 | Y18: 334.94 | Z18: 410.66 | AA18: 103.19 | AB18: 20.74 | AC18: 538.19 | AD18: 207.4 | AE18: 369.18 | AF18: 110 | AG18: =((20/365.24)*15)*($E18*1.3) -> 282.51615 | AH18: =N18+O18 -> 1619.18 | AI18: =V18+S18+AH18 -> 4748.98 | AJ18: =AI18*2% -> 94.9796 | AK18: =AI18+AJ18 -> 4843.9596 | AL18: =R18+W18+X18+Y18+AB18+Z18+AD18+AE18 -> 1646.08 | AM18: =AL18*2% -> 32.9216 | AN18: =AK18+AL18+AM18 -> 6522.9612 | AO18: =AN18*0.16 -> 1043.6738
A19: SEI0118 | B19: Arroyo Ramirez Hector Hugo | C19: 15 | D19: 0 | E19: 238.33 | F19: 252.75 | G19: 3574.95 | H19: 0 | I19: 238.33 | J19: 357.5 | K19: 357.5 | L19: 357.5 | M19: 4885.78 | N19: 15 | O19: 1372 | P19: 0 | Q19: 160.25 | R19: 90.05 | S19: 255.4 | T19: 0.08 | U19: 1892.78 | V19: =+M19-U19 -> 2993 | W19: 66.35 | X19: 119.42 | Y19: 324.89 | Z19: 403.52 | AA19: 97.72 | AB19: 18.96 | AC19: 510.66 | AD19: 189.56 | AE19: 365.61 | AF19: 110 | AG19: =((20/365.24)*15)*($E19*1.3) -> 254.48664 | AH19: =N19+O19 -> 1387 | AI19: =V19+S19+AH19 -> 4635.4 | AJ19: =AI19*2% -> 92.708 | AK19: =AI19+AJ19 -> 4728.108 | AL19: =R19+W19+X19+Y19+AB19+Z19+AD19+AE19 -> 1578.36 | AM19: =AL19*2% -> 31.5672 | AN19: =AK19+AL19+AM19 -> 6338.0352 | AO19: =AN19*0.16 -> 1014.0856
A20: SEI0127 | B20: Hernandez Ochoa Eduardo | C20: 15 | D20: 0 | E20: 273.33 | F20: 289.87 | G20: 4099.95 | H20: 0 | I20: 0 | J20: 410 | K20: 410 | L20: 410 | M20: 5329.95 | N20: 0 | O20: 0 | P20: 0 | Q20: 324.74 | R20: 105.46 | S20: 0 | T20: 0.15 | U20: 430.35 | V20: 4899.6 | W20: 76.09 | X20: 136.96 | Y20: 340.64 | Z20: 414.66 | AA20: 106.6 | AB20: 21.74 | AC20: 553.69 | AD20: 217.4 | AE20: 371.18 | AF20: 110 | AG20: =((20/365.24)*15)*($E20*1.3) -> 291.85933 | AH20: =N20+O20 -> 0 | AI20: =V20+S20+AH20 -> 4899.6 | AJ20: =AI20*2% -> 97.992 | AK20: =AI20+AJ20 -> 4997.592 | AL20: =R20+W20+X20+Y20+AB20+Z20+AD20+AE20 -> 1684.13 | AM20: =AL20*2% -> 33.6826 | AN20: =AK20+AL20+AM20 -> 6715.4046 | AO20: =AN20*0.16 -> 1074.4647
A21: SEI0173 | B21: Nieto Ortiz Jose Luis | C21: 15 | D21: 0 | E21: 185.83 | F21: 197.07 | G21: 2787.45 | H21: 0 | I21: 0 | J21: 278.75 | K21: 278.75 | L21: 278.75 | M21: 3623.7 | N21: 15 | O21: 2080.03 | P21: 0 | Q21: 36.57 | R21: 70.22 | S21: 0 | T21: 0.08 | U21: 2201.9 | V21: 1421.8 | W21: 51.73 | X21: 93.12 | Y21: 310.27 | Z21: 386.82 | AA21: 72.47 | AB21: 14.78 | AC21: 455.12 | AD21: 147.8 | AE21: 357.26 | AF21: 110 | AG21: =((20/365.24)*15)*($E21*1.3) -> 198.42761 | AH21: =N21+O21 -> 2095.03 | AI21: =V21+S21+AH21 -> 3516.83 | AJ21: =AI21*2% -> 70.3366 | AK21: =AI21+AJ21 -> 3587.1666 | AL21: =R21+W21+X21+Y21+AB21+Z21+AD21+AE21 -> 1432 | AM21: =AL21*2% -> 28.64 | AN21: =AK21+AL21+AM21 -> 5047.8066 | AO21: =AN21*0.16 -> 807.64906
A22: SEI0221 | B22: Rogel Teran Marco Antonio | C22: 14 | D22: 1 | E22: 1060.83 | F22: 1125.06 | G22: 14851.62 | H22: 1060.83 | I22: 318.25 | J22: 1591.25 | K22: 1591.25 | L22: 1591.25 | M22: 21004.45 | N22: 0 | O22: 0 | P22: 0 | Q22: 2846.24 | R22: 453.09 | S22: 0 | T22: 0.12 | U22: 3299.45 | V22: 17705 | W22: 295.33 | X22: 531.59 | Y22: 697.68 | Z22: 665.22 | AA22: 420.09 | AB22: 84.38 | AC22: 1524.6 | AD22: 843.79 | AE22: 496.46 | AF22: 110 | AG22: =((20/365.24)*15)*($E22*1.3) -> 1132.7448 | AH22: =N22+O22 -> 0 | AI22: =V22+S22+AH22 -> 17705 | AJ22: =AI22*2% -> 354.1 | AK22: =AI22+AJ22 -> 18059.1 | AL22: =R22+W22+X22+Y22+AB22+Z22+AD22+AE22 -> 4067.54 | AM22: =AL22*2% -> 81.3508 | AN22: =AK22+AL22+AM22 -> 22207.991 | AO22: =AN22*0.16 -> 3553.2785
A23: SEI0401 | B23: De La Torre Zambara Francisco Ernesto | C23: 13 | D23: 2 | E23: 185.83 | F23: 197.07 | G23: 2415.79 | H23: 371.66 | I23: 111.5 | J23: 278.75 | K23: 278.75 | L23: 278.75 | M23: 3735.2 | N23: 0 | O23: 0 | P23: 0 | Q23: 36.57 | R23: 70.22 | S23: 0 | T23: 0.01 | U23: 106.8 | V23: 3628.4 | W23: 51.73 | X23: 93.12 | Y23: 310.27 | Z23: 386.82 | AA23: 74.7 | AB23: 14.78 | AC23: 455.12 | AD23: 147.8 | AE23: 357.26 | AF23: 110 | AG23: =((20/365.24)*15)*($E23*1.3) -> 198.42761 | AH23: =N23+O23 -> 0 | AI23: =V23+S23+AH23 -> 3628.4 | AJ23: =AI23*2% -> 72.568 | AK23: =AI23+AJ23 -> 3700.968 | AL23: =R23+W23+X23+Y23+AB23+Z23+AD23+AE23 -> 1432 | AM23: =AL23*2% -> 28.64 | AN23: =AK23+AL23+AM23 -> 5161.608 | AO23: =AN23*0.16 -> 825.85728
A24: SEI0425 | B24: Carbajal Cabuto Jose Luis | C24: 15 | D24: 0 | E24: 185.83 | F24: 197.07 | G24: 2787.45 | H24: 0 | I24: 0 | J24: 278.75 | K24: 278.75 | L24: 278.75 | M24: 3623.7 | N24: 15 | O24: 1443.16 | P24: 0 | Q24: 36.57 | R24: 70.22 | S24: 0 | T24: -0.05 | U24: 1564.9 | V24: 2058.8 | W24: 51.73 | X24: 93.12 | Y24: 310.27 | Z24: 386.82 | AA24: 72.47 | AB24: 14.78 | AC24: 455.12 | AD24: 147.8 | AE24: 357.26 | AF24: 110 | AG24: =((20/365.24)*15)*($E24*1.3) -> 198.42761 | AH24: =N24+O24 -> 1458.16 | AI24: =V24+S24+AH24 -> 3516.96 | AJ24: =AI24*2% -> 70.3392 | AK24: =AI24+AJ24 -> 3587.2992 | AL24: =R24+W24+X24+Y24+AB24+Z24+AD24+AE24 -> 1432 | AM24: =AL24*2% -> 28.64 | AN24: =AK24+AL24+AM24 -> 5047.9392 | AO24: =AN24*0.16 -> 807.67027
A25: SEI0435 | B25: Benavides Herrera Alejandra | C25: 15 | D25: 0 | E25: 166.67 | F25: 176.76 | G25: 2500.05 | H25: 0 | I25: 0 | J25: 250.01 | K25: 250.01 | L25: 250.01 | M25: 3250.08 | N25: 0 | O25: 0 | P25: -9.62 | Q25: 0 | R25: 62.97 | S25: 0 | T25: -0.07 | U25: 53.28 | V25: 3196.8 | W25: 46.4 | X25: 83.52 | Y25: 304.94 | Z25: 380.73 | AA25: 65 | AB25: 13.26 | AC25: 434.86 | AD25: 132.57 | AE25: 354.21 | AF25: 110 | AG25: =((20/365.24)*15)*($E25*1.3) -> 177.96873 | AH25: =N25+O25 -> 0 | AI25: =V25+S25+AH25 -> 3196.8 | AJ25: =AI25*2% -> 63.936 | AK25: =AI25+AJ25 -> 3260.736 | AL25: =R25+W25+X25+Y25+AB25+Z25+AD25+AE25 -> 1378.6 | AM25: =AL25*2% -> 27.572 | AN25: =AK25+AL25+AM25 -> 4666.908 | AO25: =AN25*0.16 -> 746.70528
A26: SEI0442 | B26: Sierra Escamilla Daniela | C26: 15 | D26: 0 | E26: 216.67 | F26: 229.79 | G26: 3250.05 | H26: 0 | I26: 0 | J26: 325.01 | K26: 325.01 | L26: 325.01 | M26: 4225.08 | N26: 0 | O26: 0 | P26: 0 | Q26: 107.17 | R26: 81.87 | S26: 0 | T26: 0.04 | U26: 189.08 | V26: 4036 | W26: 60.32 | X26: 108.58 | Y26: 318.86 | Z26: 396.64 | AA26: 84.5 | AB26: 17.23 | AC26: 487.76 | AD26: 172.34 | AE26: 362.17 | AF26: 110 | AG26: =((20/365.24)*15)*($E26*1.3) -> 231.35828 | AH26: =N26+O26 -> 0 | AI26: =V26+S26+AH26 -> 4036 | AJ26: =AI26*2% -> 80.72 | AK26: =AI26+AJ26 -> 4116.72 | AL26: =R26+W26+X26+Y26+AB26+Z26+AD26+AE26 -> 1518.01 | AM26: =AL26*2% -> 30.3602 | AN26: =AK26+AL26+AM26 -> 5665.0902 | AO26: =AN26*0.16 -> 906.41443
C27: ============= | D27: ============= | E27: ============= | F27: ============= | G27: ============= | H27: ============= | I27: ============= | J27: ============= | K27: ============= | L27: ============= | M27: ============= | N27: ============= | O27: ============= | P27: ============= | Q27: ============= | R27: ============= | S27: ============= | T27: ============= | U27: ============= | V27: ============= | W27: ============= | X27: ============= | Y27: ============= | Z27: ============= | AA27: ============= | AB27: ============= | AC27: ============= | AD27: ============= | AE27: ============= | AF27: ============= | AG27: =============
A28: Total Gral. | C28: =SUM(C9:C26) -> 265 | D28: =SUM(D9:D26) -> 5 | E28: =SUM(E9:E26) -> 4708.72 | F28: =SUM(F9:F26) -> 4989.65 | G28: =SUM(G9:G26) -> 68826.65 | H28: =SUM(H9:H26) -> 1804.15 | I28: =SUM(I9:I26) -> 779.58 | J28: =SUM(J9:J26) -> 7063.16 | ... AG28: =SUM(AG9:AG26) -> 5027.929
L31: FACTURACION PITS
L32: Devengado Salario | M32: =+V28 -> 74429.4
L33: RETORNOS | M33: =+S28 -> 430.83
L34: Infonavit | M34: =+N28+O28+S28 -> 11304.85
L35: Prestamo Prospera | M35: 0
L36: Subtotal 1 | M36: =SUM(M32:M35) -> 86165.08
L37: Comision | M37: =+M36*2% -> 1723.3016
L38: Subtotal 2 | M38: =+M36+M37 -> 87888.382
L39: Costo Patronal Imss | M39: =+R28+W28+X28+Y28+AB28+Z28+AD28+AE28 -> 29803.99
L40: 2% Sobre Nomina | M40: =+M28*2% -> 1851.9972
L41: Importe de Factura | M41: =+M38+M39+M40 -> 119544.37
L42: IVA | M42: =+M41*16% -> 19127.099
L43: TOTAL | M43: =+M41+M42 -> 138671.47
L45: PROVISION AGUINALDO
L46: FACTURACION PITS
L47: Subtotal 1 | M47: =+AG28 -> 5027.929
L48: Comision | M48: =+M47*2% -> 100.55858
L49: Subtotal 2 | M49: =+M47+M48 -> 5128.4876
L50: 2% Sobre Nomina | M50: =+M47*2% -> 100.55858
L51: Importe de Factura | M51: =+M49+M50 -> 5229.0462
L52: IVA | M52: =+M51*16% -> 836.64739
L53: TOTAL | M53: =+M51+M52 -> 6065.6936

Sheet IP PITSS
B2: IP INNOVACION EN PROYECTOS S DE RL DE CV
B3: Lista de Raya (forma tabular)
B4: Periodo 9 al 9 QNA SEITON del 01/05/2019 al 15/05/2019
B5: Reg Pat IMSS: R1363592103
B6: RFC: IIP -150923-DT7
A8: Código | B8: Empleado | C8: Dias Laborados | D8: Dias Vacaciones | E8: Salario Diario | F8: Salario Diario Integrado | G8: Sueldo | H8: Vacaciones a tiempo | I8: Prima de vacaciones a tiempo | J8: *TOTAL* *PERCEPCIONES* | K8: Seguro de vivienda Infonavit | L8: Préstamo Infonavit (vsm) | M8: Préstamo Infonavit (cf) | N8: Subsidio al Empleo (sp) | O8: I.S.R. (sp) | P8: I.M.S.S. | Q8: Préstamo FONACOT | R8: Deduccion general | S8: Ajuste al neto | T8: *TOTAL* *DEDUCCIONES* | U8: *NETO* | V8: Invalidez y Vida | W8: Cesantia y Vejez | X8: Enf. y Mat. Patron | Y8: 2% Fondo retiro SAR (8) | Z8: 2% Impuesto estatal | AA8: Riesgo de trabajo (9) | AB8: I.M.S.S. empresa | AC8: Infonavit empresa | AD8: Guarderia I.M.S.S. (7) | AE8: Banco | AF8: Aguinaldo | AG8: subtotal 1 | AH8: comision | AI8: subtotal 2 | AJ8: costo patronal imss | AK8: 2% sobre nomina | AL8: importe de factura | AM8: iva | AN8: total
A9: SEI0010 | B9: Torres Ricardez Alfredo | C9: 15 | D9: 0 | E9: 266.67 | F9: 278.72 | G9: 4000.05 | H9: 0 | I9: 0 | J9: 4000.05 | K9: 0 | L9: 0 | M9: 0 | N9: 0 | O9: 313.87 | P9: 100.81 | Q9: 0 | R9: 0 | S9: -0.03 | T9: 414.65 | U9: =+J9-T9 -> 3585.4 | V9: 73.16 | W9: 131.7 | X9: 335.88 | Y9: 273.62 | Z9: 80 | AA9: 33.3 | AB9: 540.74 | AC9: 209.04 | AD9: 231.81 | AE9: 110 | AF9: =((20/365.24)*15)*E9 -> 219.0368 | AG9: =U9+R9+K9+L9+M9+Q9 -> 3585.4 | AH9: =AG9*2% -> 71.708 | AI9: =AG9+AH9 -> 3657.108 | AJ9: =P9+V9+W9+X9+Y9+AA9+AC9+AD9 -> 1389.32 | AK9: =J9*2% -> 80.001 | AL9: =AI9+AJ9+AK9 -> 5126.429 | AM9: =AL9*16% -> 820.22864 | AN9: =AL9+AM9 -> 5946.6576
A10: SEI0014 | B10: Montoya Portillo Carlos Alberto | C10: 15 | D10: 0 | E10: 266.67 | F10: 278.72 | G10: 4000.05 | H10: 0 | I10: 0 | J10: 4000.05 | K10: 0 | L10: 0 | M10: 0 | N10: 0 | O10: 313.87 | P10: 100.81 | Q10: 0 | R10: 0 | S10: -0.03 | T10: 414.65 | U10: =+J10-T10 -> 3585.4 | V10: 73.16 | W10: 131.7 | X10: 335.88 | Y10: 273.62 | Z10: 80 | AA10: 33.3 | AB10: 540.74 | AC10: 209.04 | AD10: 231.81 | AE10: 110 | AF10: =((20/365.24)*15)*E10 -> 219.0368 | AG10: =U10+R10+K10+L10+M10+Q10 -> 3585.4 | AH10: =AG10*2% -> 71.708 | AI10: =AG10+AH10 -> 3657.108 | AJ10: =P10+V10+W10+X10+Y10+AA10+AC10+AD10 -> 1389.32 | AK10: =J10*2% -> 80.001 | AL10: =AI10+AJ10+AK10 -> 5126.429 | AM10: =AL10*16% -> 820.22864 | AN10: =AL10+AM10 -> 5946.6576
A11: SEI0015 | B11: Cota Jaramillo Miguel Angel | C11: 15 | D11: 0 | E11: 200 | F11: 209.04 | G11: 3000 | H11: 0 | I11: 0 | J11: 3000 | K11: 0 | L11: 0 | M11: 0 | N11: 0 | O11: 59.69 | P11: 74.48 | Q11: 0 | R11: 0 | S11: 0.03 | T11: 134.2 | U11: =+J11-T11 -> 2865.8 | V11: 54.87 | W11: 98.77 | X11: 313.41 | Y11: 252.71 | Z11: 60 | AA11: 24.98 | AB11: 467.05 | AC11: 156.78 | AD11: 221.36 | AE11: 110 | AF11: =((20/365.24)*15)*E11 -> 164.27554 | AG11: =U11+R11+K11+L11+M11+Q11 -> 2865.8 | AH11: =AG11*2% -> 57.316 | AI11: =AG11+AH11 -> 2923.116 | AJ11: =P11+V11+W11+X11+Y11+AA11+AC11+AD11 -> 1197.36 | AK11: =J11*2% -> 60 | AL11: =AI11+AJ11+AK11 -> 4180.476 | AM11: =AL11*16% -> 668.87616 | AN11: =AL11+AM11 -> 4849.3522
A12: SEI0016 | B12: Negrete Bejar Aide Sarai | C12: 15 | D12: 0 | E12: 154 | F12: 160.96 | G12: 2310 | H12: 0 | I12: 0 | J12: 2310 | K12: 15 | L12: 956.31 | M12: 0 | N12: -39.73 | O12: 0 | P12: 57.34 | Q12: 0 | R12: 0 | S12: -0.12 | T12: 988.8 | U12: =+J12-T12 -> 1321.2 | V12: 42.25 | W12: 76.05 | X12: 300.79 | Y12: 238.29 | Z12: 46.2 | AA12: 19.23 | AB12: 419.09 | AC12: 120.72 | AD12: 214.14 | AE12: 110 | AF12: =((20/365.24)*15)*E12 -> 126.49217 | AG12: =U12+R12+K12+L12+M12+Q12 -> 2292.51 | AH12: =AG12*2% -> 45.8502 | AI12: =AG12+AH12 -> 2338.3602 | AJ12: =P12+V12+W12+X12+Y12+AA12+AC12+AD12 -> 1068.81 | AK12: =J12*2% -> 46.2 | AL12: =AI12+AJ12+AK12 -> 3453.3702 | AM12: =AL12*16% -> 552.53923 | AN12: =AL12+AM12 -> 4005.9094
A13: SEI0017 | B13: Muñoz Reyes Luis Eduardo | C13: 15 | D13: 0 | E13: 266.67 | F13: 278.72 | G13: 4000.05 | H13: 0 | I13: 0 | J13: 4000.05 | K13: 15 | L13: 849.56 | M13: 0 | N13: 0 | O13: 313.87 | P13: 100.81 | Q13: 0 | R13: 0 | S13: 0.01 | T13: 1279.25 | U13: =+J13-T13 -> 2720.8 | V13: 73.16 | W13: 131.7 | X13: 335.88 | Y13: 273.62 | Z13: 80 | AA13: 33.3 | AB13: 540.74 | AC13: 209.04 | AD13: 231.81 | AE13: 110 | AF13: =((20/365.24)*15)*E13 -> 219.0368 | AG13: =U13+R13+K13+L13+M13+Q13 -> 3585.36 | AH13: =AG13*2% -> 71.7072 | AI13: =AG13+AH13 -> 3657.0672 | AJ13: =P13+V13+W13+X13+Y13+AA13+AC13+AD13 -> 1389.32 | AK13: =J13*2% -> 80.001 | AL13: =AI13+AJ13+AK13 -> 5126.3882 | AM13: =AL13*16% -> 820.22211 | AN13: =AL13+AM13 -> 5946.6103
A14: SEI0019 | B14: Gonzalez Rasgado Miguel Isaias | C14: 15 | D14: 0 | E14: 400 | F14: 424.2 | G14: 6000 | H14: 0 | I14: 0 | J14: 6000 | K14: 0 | L14: 0 | M14: 0 | N14: 0 | O14: 643.38 | P14: 161.36 | Q14: 0 | R14: 0 | S14: 0.06 | T14: 804.8 | U14: =+J14-T14 -> 5195.2 | V14: 111.35 | W14: 200.43 | X14: 398.06 | Y14: 317.26 | Z14: 120 | AA14: 50.69 | AB14: 709.84 | AC14: 318.15 | AD14: 253.63 | AE14: 110 | AF14: =((20/365.24)*15)*E14 -> 328.55109 | AG14: =U14+R14+K14+L14+M14+Q14 -> 5195.2 | AH14: =AG14*2% -> 103.904 | AI14: =AG14+AH14 -> 5299.104 | AJ14: =P14+V14+W14+X14+Y14+AA14+AC14+AD14 -> 1810.93 | AK14: =J14*2% -> 120 | AL14: =AI14+AJ14+AK14 -> 7230.034 | AM14: =AL14*16% -> 1156.8054 | AN14: =AL14+AM14 -> 8386.8394
A15: SEI0020 | B15: Mar Marquez Cesar Eduardo | C15: 15 | D15: 0 | E15: 266.67 | F15: 278.72 | G15: 4000.05 | H15: 0 | I15: 0 | J15: 4000.05 | K15: 0 | L15: 0 | M15: 0 | N15: 0 | O15: 313.87 | P15: 100.81 | Q15: 0 | R15: 0 | S15: -0.03 | T15: 414.65 | U15: =+J15-T15 -> 3585.4 | V15: 73.16 | W15: 131.7 | X15: 335.88 | Y15: 273.62 | Z15: 80 | AA15: 33.3 | AB15: 540.74 | AC15: 209.04 | AD15: 231.81 | AE15: 110 | AF15: =((20/365.24)*15)*E15 -> 219.0368 | AG15: =U15+R15+K15+L15+M15+Q15 -> 3585.4 | AH15: =AG15*2% -> 71.708 | AI15: =AG15+AH15 -> 3657.108 | AJ15: =P15+V15+W15+X15+Y15+AA15+AC15+AD15 -> 1389.32 | AK15: =J15*2% -> 80.001 | AL15: =AI15+AJ15+AK15 -> 5126.429 | AM15: =AL15*16% -> 820.22864 | AN15: =AL15+AM15 -> 5946.6576
A16: SEI0021 | B16: Velez Rodriguez Jaime | C16: 15 | D16: 0 | E16: 200 | F16: 212.1 | G16: 3000 | H16: 0 | I16: 0 | J16: 3000 | K16: 15 | L16: 1317.81 | M16: 0 | N16: 0 | O16: 59.69 | P16: 75.55 | Q16: 0 | R16: 0 | S16: -0.05 | T16: 1468 | U16: =+J16-T16 -> 1532 | V16: 55.68 | W16: 100.22 | X16: 314.22 | Y16: 253.63 | Z16: 60 | AA16: 25.34 | AB16: 470.12 | AC16: 159.08 | AD16: 221.82 | AE16: 110 | AF16: =((20/365.24)*15)*E16 -> 164.27554 | AG16: =U16+R16+K16+L16+M16+Q16 -> 2864.81 | AH16: =AG16*2% -> 57.2962 | AI16: =AG16+AH16 -> 2922.1062 | AJ16: =P16+V16+W16+X16+Y16+AA16+AC16+AD16 -> 1205.54 | AK16: =J16*2% -> 60 | AL16: =AI16+AJ16+AK16 -> 4187.6462 | AM16: =AL16*16% -> 670.02339 | AN16: =AL16+AM16 -> 4857.6696
A17: SEI0022 | B17: Najera Lopez Raul | C17: 15 | D17: 0 | E17: 333.33 | F17: 353.5 | G17: 4999.95 | H17: 0 | I17: 0 | J17: 4999.95 | K17: 0 | L17: 0 | M17: 0 | N17: 0 | O17: 461.63 | P17: 131.93 | Q17: 0 | R17: 0 | S17: -0.01 | T17: 593.55 | U17: =+J17-T17 -> 4406.4 | V17: 92.79 | W17: 167.03 | X17: 367.84 | Y17: 296.05 | Z17: 100 | AA17: 42.24 | AB17: 627.66 | AC17: 265.12 | AD17: 243.02 | AE17: 110 | AF17: =((20/365.24)*15)*E17 -> 273.78984 | AG17: =U17+R17+K17+L17+M17+Q17 -> 4406.4 | AH17: =AG17*2% -> 88.128 | AI17: =AG17+AH17 -> 4494.528 | AJ17: =P17+V17+W17+X17+Y17+AA17+AC17+AD17 -> 1606.02 | AK17: =J17*2% -> 99.999 | AL17: =AI17+AJ17+AK17 -> 6200.547 | AM17: =AL17*16% -> 992.08752 | AN17: =AL17+AM17 -> 7192.6345
A18: SEI0023 | B18: Puente Murguia Luis Felipe | C18: 15 | D18: 0 | E18: 233.33 | F18: 247.45 | G18: 3499.95 | H18: 0 | I18: 0 | J18: 3499.95 | K18: 0 | L18: 0 | M18: 0 | N18: 0 | O18: 134.36 | P18: 88.16 | Q18: 0 | R18: 0 | S18: 0.03 | T18: 222.55 | U18: =+J18-T18 -> 3277.4 | V18: 64.95 | W18: 116.92 | X18: 323.49 | Y18: 264.23 | Z18: 70 | AA18: 29.57 | AB18: 505.36 | AC18: 185.58 | AD18: 227.12 | AE18: 110 | AF18: =((20/365.24)*15)*E18 -> 191.65206 | AG18: =U18+R18+K18+L18+M18+Q18 -> 3277.4 | AH18: =AG18*2% -> 65.548 | AI18: =AG18+AH18 -> 3342.948 | AJ18: =P18+V18+W18+X18+Y18+AA18+AC18+AD18 -> 1300.02 | AK18: =J18*2% -> 69.999 | AL18: =AI18+AJ18+AK18 -> 4712.967 | AM18: =AL18*16% -> 754.07472 | AN18: =AL18+AM18 -> 5467.0417
A19: SEI0029 | B19: Arceo Garcia Manuel Federico | C19: 14 | D19: 1 | E19: 200 | F19: 212.1 | G19: 2800 | H19: 200 | I19: 60 | J19: 3060 | K19: 0 | L19: 0 | M19: 0 | N19: 0 | O19: 59.69 | P19: 75.55 | Q19: 600 | R19: 0 | S19: -0.04 | T19: 735.2 | U19: =+J19-T19 -> 2324.8 | V19: 55.68 | W19: 100.22 | X19: 314.22 | Y19: 253.63 | Z19: 61.2 | AA19: 25.34 | AB19: 470.12 | AC19: 159.08 | AD19: 221.82 | AE19: 110 | AF19: =((20/365.24)*15)*E19 -> 164.27554 | AG19: =U19+R19+K19+L19+M19+Q19 -> 2924.8 | AH19: =AG19*2% -> 58.496 | AI19: =AG19+AH19 -> 2983.296 | AJ19: =P19+V19+W19+X19+Y19+AA19+AC19+AD19 -> 1205.54 | AK19: =J19*2% -> 61.2 | AL19: =AI19+AJ19+AK19 -> 4250.036 | AM19: =AL19*16% -> 680.00576 | AN19: =AL19+AM19 -> 4930.0418
A20: SEI0364 | B20: Dominguez Lopez Mayeli Del Pilar | C20: 15 | D20: 0 | E20: 266.67 | F20: 282.81 | G20: 4000.05 | H20: 0 | I20: 0 | J20: 4000.05 | K20: 0 | L20: 0 | M20: 0 | N20: 0 | O20: 313.87 | P20: 102.51 | Q20: 0 | R20: 0 | S20: -0.13 | T20: 416.25 | U20: =+J20-T20 -> 3583.8 | V20: 74.24 | W20: 133.63 | X20: 337.62 | Y20: 274.84 | Z20: 80 | AA20: 33.79 | AB20: 545.49 | AC20: 212.11 | AD20: 232.42 | AE20: 110 | AF20: =((20/365.24)*15)*E20 -> 219.0368 | AG20: =U20+R20+K20+L20+M20+Q20 -> 3583.8 | AH20: =AG20*2% -> 71.676 | AI20: =AG20+AH20 -> 3655.476 | AJ20: =P20+V20+W20+X20+Y20+AA20+AC20+AD20 -> 1401.16 | AK20: =J20*2% -> 80.001 | AL20: =AI20+AJ20+AK20 -> 5136.637 | AM20: =AL20*16% -> 821.86192 | AN20: =AL20+AM20 -> 5958.4989
... A64: SEI0506 | B64: Mejia Duarte Jose Luis | C64: 15 | D64: 0 | E64: 166.67 | F64: 176.76 | G64: 2500.05 | H64: 0 | I64: 0 | J64: 2500.05 | K64: 0 | L64: 0 | M64: 0 | N64: -9.62 | O64: 0 | P64: 62.97 | Q64: 0 | R64: 0 | S64: 0.1 | T64: 53.45 | U64: =+J64-T64 -> 2446.6 | V64: 46.4 | W64: 83.52 | X64: 304.94 | Y64: 243.03 | Z64: 50 | AA64: 21.12 | AB64: 434.86 | AC64: 132.57 | AD64: 216.51 | AE64: 110 | AF64: =((20/365.24)*15)*E64 -> 136.89903 | AG64: =U64+R64+K64+L64+M64+Q64 -> 2446.6 | AH64: =AG64*2% -> 48.932 | AI64: =AG64+AH64 -> 2495.532 | AJ64: =P64+V64+W64+X64+Y64+AA64+AC64+AD64 -> 1111.06 | AK64: =J64*2% -> 50.001 | AL64: =AI64+AJ64+AK64 -> 3656.593 | AM64: =AL64*16% -> 585.05488 | AN64: =AL64+AM64 -> 4241.6479
A65: SEI0508 | B65: Cerro Garcia Elvis | C65: 15 | D65: 0 | E65: 166.67 | F65: 177.03 | G65: 2500.05 | H65: 0 | I65: 0 | J65: 2500.05 | K65: 0 | L65: 0 | M65: 0 | N65: -9.62 | O65: 0 | P65: 63.07 | Q65: 0 | R65: 0 | S65: - | T65: 53.45 | U65: =+J65-T65 -> 2446.6 | V65: 46.47 | W65: 83.65 | X65: 305.01 | Y65: 243.11 | Z65: 50 | AA65: 21.15 | AB65: 435.13 | AC65: 132.77 | AD65: 216.55 | AE65: 110 | AF65: =((20/365.24)*15)*E65 -> 136.89903 | AG65: =U65+R65+K65+L65+M65+Q65 -> 2446.6 | AH65: =AG65*2% -> 48.932 | AI65: =AG65+AH65 -> 2495.532 | AJ65: =P65+V65+W65+X65+Y65+AA65+AC65+AD65 -> 1111.78 | AK65: =J65*2% -> 50.001 | AL65: =AI65+AJ65+AK65 -> 3657.313 | AM65: =AL65*16% -> 585.17008 | AN65: =AL65+AM65 -> 4242.4831
A66: SEI0509 | B66: Gutierrez Castillo Jose De Jesus | C66: 15 | D66: 0 | E66: 200 | F66: 209.04 | G66: 3000 | H66: 0 | I66: 0 | J66: 3000 | K66: 0 | L66: 0 | M66: 0 | N66: 0 | O66: 59.69 | P66: 74.48 | Q66: 0 | R66: 0 | S66: 0.03 | T66: 134.2 | U66: =+J66-T66 -> 2865.8 | V66: 54.87 | W66: 98.77 | X66: 313.41 | Y66: 252.71 | Z66: 60 | AA66: 24.98 | AB66: 467.05 | AC66: 156.78 | AD66: 221.36 | AE66: 110 | AF66: =((20/365.24)*15)*E66 -> 164.27554 | AG66: =U66+R66+K66+L66+M66+Q66 -> 2865.8 | AH66: =AG66*2% -> 57.316 | AI66: =AG66+AH66 -> 2923.116 | AJ66: =P66+V66+W66+X66+Y66+AA66+AC66+AD66 -> 1197.36 | AK66: =J66*2% -> 60 | AL66: =AI66+AJ66+AK66 -> 4180.476 | AM66: =AL66*16% -> 668.87616 | AN66: =AL66+AM66 -> 4849.3522
A67: SEI0511 | B67: Lizaran Maceda Jose Guadalupe | C67: 15 | D67: 0 | E67: 166.67 | F67: 175.8 | G67: 2500.05 | H67: 0 | I67: 0 | J67: 2500.05 | K67: 0 | L67: 0 | M67: 0 | N67: -9.62 | O67: 0 | P67: 62.63 | Q67: 0 | R67: 0 | S67: -0.16 | T67: 52.85 | U67: =+J67-T67 -> 2447.2 | V67: 46.15 | W67: 83.07 | X67: 304.69 | Y67: 242.74 | Z67: 50 | AA67: 21.01 | AB67: 433.91 | AC67: 131.85 | AD67: 216.37 | AE67: 110 | AF67: =((20/365.24)*15)*E67 -> 136.89903 | AG67: =U67+R67+K67+L67+M67+Q67 -> 2447.2 | AH67: =AG67*2% -> 48.944 | AI67: =AG67+AH67 -> 2496.144 | AJ67: =P67+V67+W67+X67+Y67+AA67+AC67+AD67 -> 1108.51 | AK67: =J67*2% -> 50.001 | AL67: =AI67+AJ67+AK67 -> 3654.655 | AM67: =AL67*16% -> 584.7448 | AN67: =AL67+AM67 -> 4239.3998
A68: SEI0513 | B68: Mendez Rivera Ivan Israel | C68: 15 | D68: 0 | E68: 166.66 | F68: 174.19 | G68: 2499.9 | H68: 0 | I68: 0 | J68: 2499.9 | K68: 15 | L68: 398.9 | M68: 0 | N68: -9.64 | O68: 0 | P68: 62.06 | Q68: 0 | R68: 0 | S68: -0.02 | T68: 466.3 | U68: =+J68-T68 -> 2033.6 | V68: 45.73 | W68: 82.31 | X68: 304.27 | Y68: 242.26 | Z68: 50 | AA68: 20.81 | AB68: 432.31 | AC68: 130.65 | AD68: 216.13 | AE68: 110 | AF68: =((20/365.24)*15)*E68 -> 136.89081 | AG68: =U68+R68+K68+L68+M68+Q68 -> 2447.5 | AH68: =AG68*2% -> 48.95 | AI68: =AG68+AH68 -> 2496.45 | AJ68: =P68+V68+W68+X68+Y68+AA68+AC68+AD68 -> 1104.22 | AK68: =J68*2% -> 49.998 | AL68: =AI68+AJ68+AK68 -> 3650.668 | AM68: =AL68*16% -> 584.10688 | AN68: =AL68+AM68 -> 4234.7749
A69: SEI0517 | B69: Macias Torres Enrique | C69: 15 | D69: 0 | E69: 256.67 | F69: 272.21 | G69: 3850.05 | H69: 0 | I69: 0 | J69: 3850.05 | K69: 0 | L69: 0 | M69: 0 | N69: 0 | O69: 297.55 | P69: 98.1 | Q69: 0 | R69: 0 | S69: - | T69: 395.65 | U69: =+J69-T69 -> 3454.4 | V69: 71.46 | W69: 128.62 | X69: 333.08 | Y69: 271.66 | Z69: 77 | AA69: 32.53 | AB69: 533.16 | AC69: 204.16 | AD69: 230.83 | AE69: 110 | AF69: =((20/365.24)*15)*E69 -> 210.82302 | AG69: =U69+R69+K69+L69+M69+Q69 -> 3454.4 | AH69: =AG69*2% -> 69.088 | AI69: =AG69+AH69 -> 3523.488 | AJ69: =P69+V69+W69+X69+Y69+AA69+AC69+AD69 -> 1370.44 | AK69: =J69*2% -> 77.001 | AL69: =AI69+AJ69+AK69 -> 4970.929 | AM69: =AL69*16% -> 795.34864 | AN69: =AL69+AM69 -> 5766.2776
A70: SEI0519 | B70: Palacios Vega Luis Rosendo | C70: 15 | D70: 0 | E70: 166.67 | F70: 174.2 | G70: 2500.05 | H70: 0 | I70: 0 | J70: 2500.05 | K70: 0 | L70: 0 | M70: 0 | N70: -9.62 | O70: 0 | P70: 62.06 | Q70: 0 | R70: 0 | S70: 0.01 | T70: 52.45 | U70: =+J70-T70 -> 2447.6 | V70: 45.73 | W70: 82.31 | X70: 304.27 | Y70: 242.26 | Z70: 50 | AA70: 20.82 | AB70: 432.31 | AC70: 130.65 | AD70: 216.13 | AE70: 110 | AF70: =((20/365.24)*15)*E70 -> 136.89903 | AG70: =U70+R70+K70+L70+M70+Q70 -> 2447.6 | AH70: =AG70*2% -> 48.952 | AI70: =AG70+AH70 -> 2496.552 | AJ70: =P70+V70+W70+X70+Y70+AA70+AC70+AD70 -> 1104.23 | AK70: =J70*2% -> 50.001 | AL70: =AI70+AJ70+AK70 -> 3650.783 | AM70: =AL70*16% -> 584.12528 | AN70: =AL70+AM70 -> 4234.9083
A71: SEI0521 | B71: Rondero Savin Jacinto | C71: 15 | D71: 0 | E71: 233.33 | F71: 243.88 | G71: 3499.95 | H71: 0 | I71: 0 | J71: 3499.95 | K71: 0 | L71: 0 | M71: 0 | N71: 0 | O71: 134.36 | P71: 86.88 | Q71: 0 | R71: 0 | S71: -0.09 | T71: 221.15 | U71: =+J71-T71 -> 3278.8 | V71: 64.02 | W71: 115.23 | X71: 322.56 | Y71: 263.16 | Z71: 70 | AA71: 29.14 | AB71: 501.81 | AC71: 182.91 | AD71: 226.58 | AE71: 110 | AF71: =((20/365.24)*15)*E71 -> 191.65206 | AG71: =U71+R71+K71+L71+M71+Q71 -> 3278.8 | AH71: =AG71*2% -> 65.576 | AI71: =AG71+AH71 -> 3344.376 | AJ71: =P71+V71+W71+X71+Y71+AA71+AC71+AD71 -> 1290.48 | AK71: =J71*2% -> 69.999 | AL71: =AI71+AJ71+AK71 -> 4704.855 | AM71: =AL71*16% -> 752.7768 | AN71: =AL71+AM71 -> 5457.6318
A72: SEI0523 | B72: Hernandez Rodriguez Jorge | C72: 15 | D72: 0 | E72: 233.33 | F72: 247.46 | G72: 3499.95 | H72: 0 | I72: 0 | J72: 3499.95 | K72: 15 | L72: 1401.51 | M72: 0 | N72: 0 | O72: 134.36 | P72: 88.16 | Q72: 0 | R72: 0 | S72: 0.12 | T72: 1639.15 | U72: =+J72-T72 -> 1860.8 | V72: 64.96 | W72: 116.92 | X72: 323.5 | Y72: 264.24 | Z72: 70 | AA72: 29.57 | AB72: 505.38 | AC72: 185.6 | AD72: 227.12 | AE72: 110 | AF72: =((20/365.24)*15)*E72 -> 191.65206 | AG72: =U72+R72+K72+L72+M72+Q72 -> 3277.31 | AH72: =AG72*2% -> 65.5462 | AI72: =AG72+AH72 -> 3342.8562 | AJ72: =P72+V72+W72+X72+Y72+AA72+AC72+AD72 -> 1300.07 | AK72: =J72*2% -> 69.999 | AL72: =AI72+AJ72+AK72 -> 4712.9252 | AM72: =AL72*16% -> 754.06803 | AN72: =AL72+AM72 -> 5466.9932
A73: SEI0524 | B73: Orea Gonzalez Concepcion Esteban | C73: 15 | D73: 0 | E73: 210 | F73: 222.72 | G73: 3150 | H73: 0 | I73: 0 | J73: 3150 | K73: 0 | L73: 0 | M73: 0 | N73: 0 | O73: 96.29 | P73: 79.34 | Q73: 0 | R73: 0 | S73: 0.17 | T73: 175.8 | U73: =+J73-T73 -> 2974.2 | V73: 58.46 | W73: 105.24 | X73: 317.01 | Y73: 256.82 | Z73: 63 | AA73: 26.61 | AB73: 480.71 | AC73: 167.04 | AD73: 223.41 | AE73: 110 | AF73: =((20/365.24)*15)*E73 -> 172.48932 | AG73: =U73+R73+K73+L73+M73+Q73 -> 2974.2 | AH73: =AG73*2% -> 59.484 | AI73: =AG73+AH73 -> 3033.684 | AJ73: =P73+V73+W73+X73+Y73+AA73+AC73+AD73 -> 1233.93 | AK73: =J73*2% -> 63 | AL73: =AI73+AJ73+AK73 -> 4330.614 | AM73: =AL73*16% -> 692.89824 | AN73: =AL73+AM73 -> 5023.5122
A74: SEI0525 | B74: Lizaran Maceda Jesus | C74: 15 | D74: 0 | E74: 210 | F74: 222.72 | G74: 3150 | H74: 0 | I74: 0 | J74: 3150 | K74: 15 | L74: 0 | M74: 303.54 | N74: 0 | O74: 96.29 | P74: 79.34 | Q74: 0 | R74: 0 | S74: 0.03 | T74: 494.2 | U74: =+J74-T74 -> 2655.8 | V74: 58.46 | W74: 105.24 | X74: 317.01 | Y74: 256.82 | Z74: 63 | AA74: 26.61 | AB74: 480.71 | AC74: 167.04 | AD74: 223.41 | AE74: 110 | AF74: =((20/365.24)*15)*E74 -> 172.48932 | AG74: =U74+R74+K74+L74+M74+Q74 -> 2974.34 | AH74: =AG74*2% -> 59.4868 | AI74: =AG74+AH74 -> 3033.8268 | AJ74: =P74+V74+W74+X74+Y74+AA74+AC74+AD74 -> 1233.93 | AK74: =J74*2% -> 63 | AL74: =AI74+AJ74+AK74 -> 4330.7568 | AM74: =AL74*16% -> 692.92109 | AN74: =AL74+AM74 -> 5023.6779
A75: SEI0527 | B75: Alejandro Peña Deivi | C75: 15 | D75: 0 | E75: 210 | F75: 222.72 | G75: 3150 | H75: 0 | I75: 0 | J75: 3150 | K75: 0 | L75: 0 | M75: 0 | N75: 0 | O75: 96.29 | P75: 79.34 | Q75: 0 | R75: 0 | S75: -0.03 | T75: 175.6 | U75: =+J75-T75 -> 2974.4 | V75: 58.46 | W75: 105.24 | X75: 317.01 | Y75: 256.82 | Z75: 63 | AA75: 26.61 | AB75: 480.71 | AC75: 167.04 | AD75: 223.41 | AE75: 110 | AF75: =((20/365.24)*15)*E75 -> 172.48932 | AG75: =U75+R75+K75+L75+M75+Q75 -> 2974.4 | AH75: =AG75*2% -> 59.488 | AI75: =AG75+AH75 -> 3033.888 | AJ75: =P75+V75+W75+X75+Y75+AA75+AC75+AD75 -> 1233.93 | AK75: =J75*2% -> 63 | AL75: =AI75+AJ75+AK75 -> 4330.818 | AM75: =AL75*16% -> 692.93088 | AN75: =AL75+AM75 -> 5023.7489
A76: SEI0528 | B76: Casas Chavarria Rafael | C76: 15 | D76: 0 | E76: 210 | F76: 222.72 | G76: 3150 | H76: 0 | I76: 0 | J76: 3150 | K76: 15 | L76: 0 | M76: 942.33 | N76: 0 | O76: 96.29 | P76: 79.34 | Q76: 0 | R76: 0 | S76: 0.04 | T76: 1133 | U76: =+J76-T76 -> 2017 | V76: 58.46 | W76: 105.24 | X76: 317.01 | Y76: 256.82 | Z76: 63 | AA76: 26.61 | AB76: 480.71 | AC76: 167.04 | AD76: 223.41 | AE76: 110 | AF76: =((20/365.24)*15)*E76 -> 172.48932 | AG76: =U76+R76+K76+L76+M76+Q76 -> 2974.33 | AH76: =AG76*2% -> 59.4866 | AI76: =AG76+AH76 -> 3033.8166 | AJ76: =P76+V76+W76+X76+Y76+AA76+AC76+AD76 -> 1233.93 | AK76: =J76*2% -> 63 | AL76: =AI76+AJ76+AK76 -> 4330.7466 | AM76: =AL76*16% -> 692.91946 | AN76: =AL76+AM76 -> 5023.6661
A77: SEI0530 | B77: Del Pilar Mendez Lucio | C77: 15 | D77: 0 | E77: 200 | F77: 209.04 | G77: 3000 | H77: 0 | I77: 0 | J77: 3000 | K77: 15 | L77: 0 | M77: 1575.59 | N77: 0 | O77: 59.69 | P77: 74.48 | Q77: 0 | R77: 0 | S77: 0.04 | T77: 1724.8 | U77: =+J77-T77 -> 1275.2 | V77: 54.87 | W77: 98.77 | X77: 313.41 | Y77: 252.71 | Z77: 60 | AA77: 24.98 | AB77: 467.05 | AC77: 156.78 | AD77: 221.36 | AE77: 110 | AF77: =((20/365.24)*15)*E77 -> 164.27554 | AG77: =U77+R77+K77+L77+M77+Q77 -> 2865.79 | AH77: =AG77*2% -> 57.3158 | AI77: =AG77+AH77 -> 2923.1058 | AJ77: =P77+V77+W77+X77+Y77+AA77+AC77+AD77 -> 1197.36 | AK77: =J77*2% -> 60 | AL77: =AI77+AJ77+AK77 -> 4180.4658 | AM77: =AL77*16% -> 668.87453 | AN77: =AL77+AM77 -> 4849.3403
A78: SEI0534 | B78: Gonzalez Ramirez Paul | C78: 15 | D78: 0 | E78: 200 | F78: 209.04 | G78: 3000 | H78: 0 | I78: 0 | J78: 3000 | K78: 0 | L78: 0 | M78: 0 | N78: 0 | O78: 59.69 | P78: 74.48 | Q78: 0 | R78: 0 | S78: 0.03 | T78: 134.2 | U78: =+J78-T78 -> 2865.8 | V78: 54.87 | W78: 98.77 | X78: 313.41 | Y78: 252.71 | Z78: 60 | AA78: 24.98 | AB78: 467.05 | AC78: 156.78 | AD78: 221.36 | AE78: 110 | AF78: =((20/365.24)*15)*E78 -> 164.27554 | AG78: =U78+R78+K78+L78+M78+Q78 -> 2865.8 | AH78: =AG78*2% -> 57.316 | AI78: =AG78+AH78 -> 2923.116 | AJ78: =P78+V78+W78+X78+Y78+AA78+AC78+AD78 -> 1197.36 | AK78: =J78*2% -> 60 | AL78: =AI78+AJ78+AK78 -> 4180.476 | AM78: =AL78*16% -> 668.87616 | AN78: =AL78+AM78 -> 4849.3522
A79: SEI0535 | B79: Alejandro Vazquez Erasmo Miguel | C79: 15 | D79: 0 | E79: 200 | F79: 212.11 | G79: 3000 | H79: 0 | I79: 0 | J79: 3000 | K79: 15 | L79: 0 | M79: 466.28 | N79: 0 | O79: 59.69 | P79: 75.56 | Q79: 0 | R79: 0 | S79: 0.07 | T79: 616.6 | U79: =+J79-T79 -> 2383.4 | V79: 55.68 | W79: 100.22 | X79: 314.22 | Y79: 253.63 | Z79: 60 | AA79: 25.34 | AB79: 470.12 | AC79: 159.08 | AD79: 221.82 | AE79: 110 | AF79: =((20/365.24)*15)*E79 -> 164.27554 | AG79: =U79+R79+K79+L79+M79+Q79 -> 2864.68 | AH79: =AG79*2% -> 57.2936 | AI79: =AG79+AH79 -> 2921.9736 | AJ79: =P79+V79+W79+X79+Y79+AA79+AC79+AD79 -> 1205.55 | AK79: =J79*2% -> 60 | AL79: =AI79+AJ79+AK79 -> 4187.5236 | AM79: =AL79*16% -> 670.00378 | AN79: =AL79+AM79 -> 4857.5274
A80: SEI0536 | B80: Hernandez Ojeda Julio Cesar | C80: 15 | D80: 0 | E80: 116.67 | F80: 123.73 | G80: 1750.05 | H80: 0 | I80: 0 | J80: 1750.05 | K80: 15 | L80: 0 | M80: 836.5 | N80: -89.5 | O80: 0 | P80: 44.08 | Q80: 0 | R80: 0 | S80: -0.03 | T80: 806.05 | U80: =+J80-T80 -> 944 | V80: 32.48 | W80: 58.46 | X80: 291.02 | Y80: 227.12 | Z80: 35 | AA80: 14.78 | AB80: 381.96 | AC80: 92.8 | AD80: 208.56 | AE80: 110 | AF80: =((20/365.24)*15)*E80 -> 95.830139 | AG80: =U80+R80+K80+L80+M80+Q80 -> 1795.5 | AH80: =AG80*2% -> 35.91 | AI80: =AG80+AH80 -> 1831.41 | AJ80: =P80+V80+W80+X80+Y80+AA80+AC80+AD80 -> 969.3 | AK80: =J80*2% -> 35.001 | AL80: =AI80+AJ80+AK80 -> 2835.711 | AM80: =AL80*16% -> 453.71376 | AN80: =AL80+AM80 -> 3289.4248
A81: SEI0537 | B81: Serrano Esquivel Armando | C81: 15 | D81: 0 | E81: 116.67 | F81: 123.73 | G81: 1750.05 | H81: 0 | I81: 0 | J81: 1750.05 | K81: 15 | L81: 721.52 | M81: 0 | N81: -89.5 | O81: 0 | P81: 44.08 | Q81: 0 | R81: 0 | S81: -0.05 | T81: 691.05 | U81: =+J81-T81 -> 1059 | V81: 32.48 | W81: 58.46 | X81: 291.02 | Y81: 227.12 | Z81: 35 | AA81: 14.78 | AB81: 381.96 | AC81: 92.8 | AD81: 208.56 | AE81: 110 | AF81: =((20/365.24)*15)*E81 -> 95.830139 | AG81: =U81+R81+K81+L81+M81+Q81 -> 1795.52 | AH81: =AG81*2% -> 35.9104 | AI81: =AG81+AH81 -> 1831.4304 | AJ81: =P81+V81+W81+X81+Y81+AA81+AC81+AD81 -> 969.3 | AK81: =J81*2% -> 35.001 | AL81: =AI81+AJ81+AK81 -> 2835.7314 | AM81: =AL81*16% -> 453.71702 | AN81: =AL81+AM81 -> 3289.4484
... A87: SEI0547 | B87: Aguilar Garcia Rosa Paola | C87: 15 | D87: 0 | E87: 166.67 | F87: 176.76 | G87: 2500.05 | H87: 0 | I87: 0 | J87: 2500.05 | K87: 0 | L87: 0 | M87: 0 | N87: -9.62 | O87: 0 | P87: 62.97 | Q87: 0 | R87: 0 | S87: 0.1 | T87: 53.45 | U87: =+J87-T87 -> 2446.6 | V87: 46.4 | W87: 83.52 | X87: 304.94 | Y87: 243.03 | Z87: 50 | AA87: 21.12 | AB87: 434.86 | AC87: 132.57 | AD87: 216.51 | AE87: 110 | AF87: =((20/365.24)*15)*E87 -> 136.89903 | AG87: =U87+R87+K87+L87+M87+Q87 -> 2446.6 | AH87: =AG87*2% -> 48.932 | AI87: =AG87+AH87 -> 2495.532 | AJ87: =P87+V87+W87+X87+Y87+AA87+AC87+AD87 -> 1111.06 | AK87: =J87*2% -> 50.001 | AL87: =AI87+AJ87+AK87 -> 3656.593 | AM87: =AL87*16% -> 585.05488 | AN87: =AL87+AM87 -> 4241.6479
A88: SEI0548 | B88: Jauregui Madera Jorge Silvestre | C88: 14 | D88: 0 | E88: 200 | F88: 209.04 | G88: 2800 | H88: 0 | I88: 0 | J88: =+G88 -> 2800 | K88: 0 | L88: 0 | M88: 0 | N88: 0 | O88: 37.93 | P88: 70.81 | Q88: 0 | R88: 0 | S88: 0.06 | T88: 108.8 | U88: =+J88-T88 -> 2691.2 | V88: 54.87 | W88: 98.77 | X88: 313.41 | Y88: 252.71 | Z88: 60 | AA88: 24.98 | AB88: 467.05 | AC88: 156.78 | AD88: 221.36 | AE88: 110 | AF88: =((20/365.24)*15)*E88 -> 164.27554 | AG88: =U88+R88+K88+L88+M88+Q88 -> 2691.2 | AH88: =AG88*2% -> 53.824 | AI88: =AG88+AH88 -> 2745.024 | AJ88: =P88+V88+W88+X88+Y88+AA88+AC88+AD88 -> 1193.69 | AK88: =J88*2% -> 56 | AL88: =AI88+AJ88+AK88 -> 3994.714 | AM88: =AL88*16% -> 639.15424 | AN88: =AL88+AM88 -> 4633.8682
A89: SEI0549 | B89: Hinojosa Guerrero Alejandro | C89: 3 | D89: 0 | E89: 210 | F89: 219.83 | G89: 630 | H89: 0 | I89: 0 | J89: 630 | K89: 0 | L89: 0 | M89: 0 | N89: -173.3 | O89: 0 | P89: 15.66 | Q89: 0 | R89: 0 | S89: 0.04 | T89: -157.6 | U89: =+J89-T89 -> 787.6 | V89: 11.54 | W89: 20.77 | X89: 63.25 | Y89: 203.19 | Z89: 12.6 | AA89: 5.25 | AB89: 95.56 | AC89: 32.97 | AD89: 196.59 | AE89: 0 | AF89: =((20/365.24)*15)*E89 -> 172.48932 | AG89: =U89+R89+K89+L89+M89+Q89 -> 787.6 | AH89: =AG89*2% -> 15.752 | AI89: =AG89+AH89 -> 803.352 | AJ89: =P89+V89+W89+X89+Y89+AA89+AC89+AD89 -> 549.22 | AK89: =J89*2% -> 12.6 | AL89: =AI89+AJ89+AK89 -> 1365.172 | AM89: =AL89*16% -> 218.42752 | AN89: =AL89+AM89 -> 1583.5995
A90: SEI479 | B90: Cruz Perez Alejandro Nezahualcoyotl | C90: 15 | D90: 0 | E90: 266.67 | F90: 282.81 | G90: 4000.05 | H90: 0 | I90: 0 | J90: 4000.05 | K90: 0 | L90: 0 | M90: 0 | N90: 0 | O90: 313.87 | P90: 102.51 | Q90: 0 | R90: 0 | S90: -0.13 | T90: 416.25 | U90: =+J90-T90 -> 3583.8 | V90: 74.24 | W90: 133.63 | X90: 337.62 | Y90: 274.84 | Z90: 80 | AA90: 33.79 | AB90: 545.49 | AC90: 212.11 | AD90: 232.42 | AE90: 110 | AF90: =((20/365.24)*15)*E90 -> 219.0368 | AG90: =U90+R90+K90+L90+M90+Q90 -> 3583.8 | AH90: =AG90*2% -> 71.676 | AI90: =AG90+AH90 -> 3655.476 | AJ90: =P90+V90+W90+X90+Y90+AA90+AC90+AD90 -> 1401.16 | AK90: =J90*2% -> 80.001 | AL90: =AI90+AJ90+AK90 -> 5136.637 | AM90: =AL90*16% -> 821.86192 | AN90: =AL90+AM90 -> 5958.4989
C91: ============= | D91: ============= | E91: ============= | F91: ============= | G91: ============= | H91: ============= | I91: ============= | J91: ============= | K91: ============= | L91: ============= | M91: ============= | N91: ============= | O91: ============= | P91: ============= | Q91: ============= | R91: ============= | S91: ============= | T91: ============= | U91: ============= | V91: ============= | W91: ============= | X91: ============= | Y91: ============= | Z91: ============= | AA91: ============= | AB91: ============= | AC91: ============= | AD91: ============= | AE91: ============= | AF91: =============
A92: Total Gral. | C92: =SUM(C9:C90) -> 1212 | D92: =SUM(D9:D90) -> 5 | E92: =SUM(E9:E90) -> 19588.93 | F92: =SUM(F9:F90) -> 20657.98 | G92: =SUM(G9:G90) -> 290014.04 | H92: =SUM(H9:H90) -> 1100.01 | I92: =SUM(I9:I90) -> 330 | J92: =SUM(J9:J90) -> 291444.05 | ... AF92: =SUM(AF9:AF90) -> 16089.911
I95: FACTURACION PITS
I96: Devengado Salario | J96: =+U92 -> 233360.8
I97: RETORNOS | J97: =+R92 -> 3501.6
I98: Infonavit | J98: =+K92+L92+M92 -> 29408.52
I99: Prestamo Prospera | J99: 0
I100: Subtotal 1 | J100: =SUM(J96:J99) -> 266270.92
I101: Comision | J101: =+J100*2% -> 5325.4184
I102: Subtotal 2 | J102: =+J100+J101 -> 271596.34
I103: Costo Patronal Imss | J103: =+P92+V92+W92+X92+Y92+AA92+AC92+AD92 -> 107363.09
I104: 2% Sobre Nomina | J104: =+J92*2% -> 5828.881
I105: Importe de Factura | J105: =+J102+J103+J104 -> 384788.31
I106: IVA | J106: =+J105*16% -> 61566.13
I107: TOTAL | J107: =+J105+J106 -> 446354.44
I109: PROVISION AGUINALDO
I110: FACTURACION PITS
I111: Subtotal 1 | J111: =+AF92 -> 16089.911
I112: Comision | J112: =+J111*2% -> 321.79821
I113: Subtotal 2 | J113: =+J111+J112 -> 16411.709
I114: 2% Sobre Nomina | J114: =+J111*2% -> 321.79821
I115: Importe de Factura | J115: =+J113+J114 -> 16733.507
I116: IVA | J116: =+J115*16% -> 2677.3611
I117: TOTAL | J117: =+J115+J116 -> 19410.868

Sheet SIND PITS
D1: SINDICATO | J1: PRIMA VACACIONAL
A2: CLAVE | B2: EMPRESA | C2: NOMBRE | D2: SUELDO SINDICATO | E2: BONO | F2: COMISION | G2: prima vacaciones | H2: TOTAL | J2: DIAS DE VACACIONES | K2: SUELDO NETO MENSUAL | L2: MONTO PRIMA TOTAL | M2: MENOS PRIMA IMSS | N2: PRIMA A PAGAR SINDICATO | P2: comision | Q2: subtotal | R2: iva
A3: SEI0097 | B3: CONSULTORIA | C3: Arreola Jimenez Jose Nieves | D3: 1557.96 | E3: 420 | F3: 320 | G3: =+N3 -> 91.5 | H3: =SUM(D3:G3) -> 2389.46 | J3: =VLOOKUP($C3,'CPD PITSS'!$B$9:$V$26,3,0) -> 2 | K3: 10150 | L3: =(((+K3/30)*J3)*30%) -> 203 | M3: =VLOOKUP($C3,'CPD PITSS'!$B$9:$V$26,8,0) -> 111.5 | N3: =+L3-M3 -> 91.5 | O3: SEI0097 | P3: =H3*2% -> 47.7892 | Q3: =H3+P3 -> 2437.2492 | R3: =Q3*16% -> 389.95987
A4: SEI0118 | B4: CONSULTORIA | C4: Arroyo Ramirez Hector Hugo | D4: 2104.9 | G4: =+N4 -> 281.67 | H4: =SUM(D4:G4) -> 2386.57 | J4: 4 | K4: 13000 | L4: =(((+K4/30)*J4)*30%) -> 520 | M4: =VLOOKUP($C4,'CPD PITSS'!$B$9:$V$26,8,0) -> 238.33 | N4: =+L4-M4 -> 281.67 | O4: SEI0118 | P4: =H4*2% -> 47.7314 | Q4: =H4+P4 -> 2434.3014 | R4: =Q4*16% -> 389.48822
A5: SEI0377 | B5: CONSULTORIA | C5: Benavides Herrera Alejandra | D5: 16803.4 | G5: =+N5 -> 0 | H5: =SUM(D5:G5) -> 16803.4 | J5: =VLOOKUP(C5,'CPD PITSS'!$B$9:$V$26,3,0) -> 0 | K5: 40000 | L5: =(((+K5/30)*J5)*30%) -> 0 | M5: =VLOOKUP($C5,'CPD PITSS'!$B$9:$V$26,8,0) -> 0 | N5: =+L5-M5 -> 0 | O5: SEI0377 | P5: =H5*2% -> 336.068 | Q5: =H5+P5 -> 17139.468 | R5: =Q5*16% -> 2742.3149
A6: SEI0108 | B6: CONSULTORIA | C6: Caballero Diaz Francisco Javier | D6: 1558.09 | E6: 330 | F6: 320 | G6: =+N6 -> 0 | H6: =SUM(D6:G6) -> 2208.09 | J6: =VLOOKUP(C6,'CPD PITSS'!$B$9:$V$26,3,0) -> 0 | K6: 10150 | L6: =(((+K6/30)*J6)*30%) -> 0 | M6: =VLOOKUP($C6,'CPD PITSS'!$B$9:$V$26,8,0) -> 0 | N6: =+L6-M6 -> 0 | O6: SEI0108 | P6: =H6*2% -> 44.1618 | Q6: =H6+P6 -> 2252.2518 | R6: =Q6*16% -> 360.36029
A7: SEI0425 | B7: CONSULTORIA | C7: Carbajal Cabuto Jose Luis | D7: 1608.1 | E7: 270 | G7: =+N7 -> 0 | H7: =SUM(D7:G7) -> 1878.1 | J7: =VLOOKUP(C7,'CPD PITSS'!$B$9:$V$26,3,0) -> 0 | K7: 10250 | L7: =(((+K7/30)*J7)*30%) -> 0 | M7: =VLOOKUP($C7,'CPD PITSS'!$B$9:$V$26,8,0) -> 0 | N7: =+L7-M7 -> 0 | O7: SEI0453 | P7: =H7*2% -> 37.562 | Q7: =H7+P7 -> 1915.662 | R7: =Q7*16% -> 306.50592
A8: SEI0116 | B8: CONSULTORIA | C8: Casillas Cardona Cesar Alejandro | D8: 1891.2 | G8: =+N8 -> 0 | H8: =SUM(D8:G8) -> 1891.2 | J8: =VLOOKUP(C8,'CPD PITSS'!$B$9:$V$26,3,0) -> 0 | K8: 12000 | L8: =(((+K8/30)*J8)*30%) -> 0 | M8: =VLOOKUP($C8,'CPD PITSS'!$B$9:$V$26,8,0) -> 0 | N8: =+L8-M8 -> 0 | O8: SEI0116 | P8: =H8*2% -> 37.824 | Q8: =H8+P8 -> 1929.024 | R8: =Q8*16% -> 308.64384
A9: SEI0401 | B9: CONSULTORIA | C9: De La Torre Zambara Francisco Ernesto | D9: 1558 | E9: 270 | F9: 320 | G9: =+N9 -> 91.5 | H9: =SUM(D9:G9) -> 2239.5 | J9: =VLOOKUP(C9,'CPD PITSS'!$B$9:$V$26,3,0) -> 2 | K9: 10150 | L9: =(((+K9/30)*J9)*30%) -> 203 | M9: =VLOOKUP($C9,'CPD PITSS'!$B$9:$V$26,8,0) -> 111.5 | N9: =+L9-M9 -> 91.5 | O9: SEI0401 | P9: =H9*2% -> 44.79 | Q9: =H9+P9 -> 2284.29 | R9: =Q9*16% -> 365.4864
A10: SEI0099 | B10: CONSULTORIA | C10: Garcia Villicaña Ricardo Pascual | D10: 2600.37 | E10: 150 | G10: =+N10 -> 0 | H10: =SUM(D10:G10) -> 2750.37 | J10: =VLOOKUP(C10,'CPD PITSS'!$B$9:$V$26,3,0) -> 0 | K10: 15000 | L10: =(((+K10/30)*J10)*30%) -> 0 | M10: =VLOOKUP($C10,'CPD PITSS'!$B$9:$V$26,8,0) -> 0 | N10: =+L10-M10 -> 0 | O10: SEI0099 | P10: =H10*2% -> 55.0074 | Q10: =H10+P10 -> 2805.3774 | R10: =Q10*16% -> 448.86038
A11: SEI0009 | B11: CONSULTORIA | C11: Gutierrez Gutierrez Luis Arturo | D11: 1475.4 | E11: 100 | G11: =+N11 -> 0 | H11: =SUM(D11:G11) -> 1575.4 | J11: =VLOOKUP(C11,'CPD PITSS'!$B$9:$V$26,3,0) -> 0 | K11: 8500 | L11: =(((+K11/30)*J11)*30%) -> 0 | M11: =VLOOKUP($C11,'CPD PITSS'!$B$9:$V$26,8,0) -> 0 | N11: =+L11-M11 -> 0 | O11: SEI0009 | P11: =H11*2% -> 31.508 | Q11: =H11+P11 -> 1606.908 | R11: =Q11*16% -> 257.10528
A12: SEI0127 | B12: CONSULTORIA | C12: Hernandez Ochoa Eduardo | D12: 2600.2 | E12: 337.5 | G12: =+N12 -> 0 | H12: =SUM(D12:G12) -> 2937.7 | J12: =VLOOKUP(C12,'CPD PITSS'!$B$9:$V$26,3,0) -> 0 | K12: 15000 | L12: =(((+K12/30)*J12)*30%) -> 0 | M12: =VLOOKUP($C12,'CPD PITSS'!$B$9:$V$26,8,0) -> 0 | N12: =+L12-M12 -> 0 | O12: SEI0127 | P12: =H12*2% -> 58.754 | Q12: =H12+P12 -> 2996.454 | R12: =Q12*16% -> 479.43264
A13: SEI0117 | B13: CONSULTORIA | C13: Mariscal Romero Luis Adrian | D13: 2751 | E13: 165 | G13: =+N13 -> 0 | H13: =SUM(D13:G13) -> 2916 | J13: =VLOOKUP(C13,'CPD PITSS'!$B$9:$V$26,3,0) -> 0 | K13: 15000 | L13: =(((+K13/30)*J13)*30%) -> 0 | M13: =VLOOKUP($C13,'CPD PITSS'!$B$9:$V$26,8,0) -> 0 | N13: =+L13-M13 -> 0 | O13: SEI0117 | P13: =H13*2% -> 58.32 | Q13: =H13+P13 -> 2974.32 | R13: =Q13*16% -> 475.8912
A14: SEI0040 | B14: CONSULTORIA | C14: Mora Ramirez Acal Aldo Isidro | D14: 2464 | E14: 1000 | G14: =+N14 -> 0 | H14: =SUM(D14:G14) -> 3464 | J14: =VLOOKUP(C14,'CPD PITSS'!$B$9:$V$26,3,0) -> 0 | K14: 13000 | L14: =(((+K14/30)*J14)*30%) -> 0 | M14: =VLOOKUP($C14,'CPD PITSS'!$B$9:$V$26,8,0) -> 0 | N14: =+L14-M14 -> 0 | O14: SEI0040 | P14: =H14*2% -> 69.28 | Q14: =H14+P14 -> 3533.28 | R14: =Q14*16% -> 565.3248
A15: SEI0088 | B15: CONSULTORIA | C15: Morgado Fernandez Martin | D15: 2600.4 | E15: 337.5 | G15: =+N15 -> 0 | H15: =SUM(D15:G15) -> 2937.9 | J15: =VLOOKUP(C15,'CPD PITSS'!$B$9:$V$26,3,0) -> 0 | K15: 15000 | L15: =(((+K15/30)*J15)*30%) -> 0 | M15: =VLOOKUP($C15,'CPD PITSS'!$B$9:$V$26,8,0) -> 0 | N15: =+L15-M15 -> 0 | O15: SEI0088 | P15: =H15*2% -> 58.758 | Q15: =H15+P15 -> 2996.658 | R15: =Q15*16% -> 479.46528
A16: SEI0173 | B16: CONSULTORIA | C16: Nieto Ortiz Jose Luis | D16: 1483.13 | E16: 20 | G16: =+N16 -> 0 | H16: =SUM(D16:G16) -> 1503.13 | J16: =VLOOKUP(C16,'CPD PITSS'!$B$9:$V$26,3,0) -> 0 | K16: 10000 | L16: =(((+K16/30)*J16)*30%) -> 0 | M16: =VLOOKUP($C16,'CPD PITSS'!$B$9:$V$26,8,0) -> 0 | N16: =+L16-M16 -> 0 | O16: SEI0173 | P16: =H16*2% -> 30.0626 | Q16: =H16+P16 -> 1533.1926 | R16: =Q16*16% -> 245.31082
A17: SEI0026 | B17: CONSULTORIA | C17: Patricio Aguilar Jhonattan Cristian | D17: 1588 | E17: 400 | G17: =+N17 -> 0 | H17: =SUM(D17:G17) -> 1988 | J17: =VLOOKUP(C17,'CPD PITSS'!$B$9:$V$26,3,0) -> 0 | K17: 9000 | L17: =(((+K17/30)*J17)*30%) -> 0 | M17: =VLOOKUP($C17,'CPD PITSS'!$B$9:$V$26,8,0) -> 0 | N17: =+L17-M17 -> 0 | O17: SEI0026 | P17: =H17*2% -> 39.76 | Q17: =H17+P17 -> 2027.76 | R17: =Q17*16% -> 324.4416
A18: SEI0221 | B18: CONSULTORIA | C18: Rogel Teran Marco Antonio | D18: 12613.2 | G18: =+N18 -> 281.75 | H18: =SUM(D18:G18) -> 12894.95 | J18: =VLOOKUP(C18,'CPD PITSS'!$B$9:$V$26,3,0) -> 1 | K18: 60000 | L18: =(((+K18/30)*J18)*30%) -> 600 | M18: =VLOOKUP($C18,'CPD PITSS'!$B$9:$V$26,8,0) -> 318.25 | N18: =+L18-M18 -> 281.75 | O18: SEI0221 | P18: =H18*2% -> 257.899 | Q18: =H18+P18 -> 13152.849 | R18: =Q18*16% -> 2104.4558
A19: SEI0442 | B19: CONSULTORIA | C19: Sierra Escamilla Daniela | D19: 2464 | E19: 1000 | G19: =+N19 -> 0 | H19: =SUM(D19:G19) -> 3464 | J19: =VLOOKUP(C19,'CPD PITSS'!$B$9:$V$26,3,0) -> 0 | K19: 13000 | L19: =(((+K19/30)*J19)*30%) -> 0 | M19: =VLOOKUP($C19,'CPD PITSS'!$B$9:$V$26,8,0) -> 0 | N19: =+L19-M19 -> 0 | O19: SEI0618 | P19: =H19*2% -> 69.28 | Q19: =H19+P19 -> 3533.28 | R19: =Q19*16% -> 565.3248
A20: SEI0041 | B20: CONSULTORIA | C20: Vazquez Perez Miguel Angel | D20: 4176 | E20: 750 | G20: =+N20 -> 0 | H20: =SUM(D20:G20) -> 4926 | J20: =VLOOKUP(C20,'CPD PITSS'!$B$9:$V$26,3,0) -> 0 | K20: 18500 | L20: =(((+K20/30)*J20)*30%) -> 0 | M20: =VLOOKUP($C20,'CPD PITSS'!$B$9:$V$26,8,0) -> 0 | N20: =+L20-M20 -> 0 | O20: SEI0041 | P20: =H20*2% -> 98.52 | Q20: =H20+P20 -> 5024.52 | R20: =Q20*16% -> 803.9232
A21: SEI0544 | B21: IP INNOVACION | C21: Aguilar Aguirre Alfonso | D21: 135.2 | H21: =SUM(D21:G21) -> 135.2 | J21: =VLOOKUP(C21,'IP PITSS'!$B$9:$U$90,3,0) -> 0 | K21: 6000 | L21: =(((+K21/30)*J21)*30%) -> 0 | M21: =VLOOKUP(C21,'IP PITSS'!$B$9:$I$90,8,0) -> 0 | N21: =+L21-M21 -> 0 | O21: SEI0652 | P21: =H21*2% -> 2.704 | Q21: =H21+P21 -> 137.904 | R21: =Q21*16% -> 22.06464
A22: SEI0431 | B22: IP INNOVACION | C22: Alcaraz Conde Zabdi Guadalupe | D22: 135.14 | E22: 455 | G22: =+N22 -> 0 | H22: =SUM(D22:G22) -> 590.14 | J22: =VLOOKUP(C22,'IP PITSS'!$B$9:$U$90,3,0) -> 0 | K22: 6000 | L22: =(((+K22/30)*J22)*30%) -> 0 | M22: =VLOOKUP(C22,'IP PITSS'!$B$9:$I$90,8,0) -> 0 | N22: =+L22-M22 -> 0 | O22: SEI0456 | P22: =H22*2% -> 11.8028 | Q22: =H22+P22 -> 601.9428 | R22: =Q22*16% -> 96.310848
A23: SEI0527 | B23: IP INNOVACION | C23: Alejandro Peña Deivi | D23: 175.6 | E23: 1068.75 | G23: =+N23 -> 0 | H23: =SUM(D23:G23) -> 1244.35 | J23: =VLOOKUP(C23,'IP PITSS'!$B$9:$U$90,3,0) -> 0 | K23: 6300 | L23: =(((+K23/30)*J23)*30%) -> 0 | M23: =VLOOKUP(C23,'IP PITSS'!$B$9:$I$90,8,0) -> 0 | N23: =+L23-M23 -> 0 | O23: SEI0628 | P23: =H23*2% -> 24.887 | Q23: =H23+P23 -> 1269.237 | R23: =Q23*16% -> 203.07792
A24: SEI0535 | B24: IP INNOVACION | C24: Alejandro Vazquez Erasmo Miguel | D24: 3135.32 | E24: 750 | G24: =+N24 -> 0 | H24: =SUM(D24:G24) -> 3885.32 | J24: =VLOOKUP(C24,'IP PITSS'!$B$9:$U$90,3,0) -> 0 | K24: 12000 | L24: =(((+K24/30)*J24)*30%) -> 0 | M24: =VLOOKUP(C24,'IP PITSS'!$B$9:$I$90,8,0) -> 0 | N24: =+L24-M24 -> 0 | O24: SEI0638 | P24: =H24*2% -> 77.7064 | Q24: =H24+P24 -> 3963.0264 | R24: =Q24*16% -> 634.08422
A25: SEI0029 | B25: IP INNOVACION | C25: Arceo Garcia Manuel Federico | D25: 255.2 | E25: 455 | G25: =+N25 -> 0 | H25: =SUM(D25:G25) -> 710.2 | J25: =VLOOKUP(C25,'IP PITSS'!$B$9:$U$90,3,0) -> 1 | K25: 6000 | L25: =(((+K25/30)*J25)*30%) -> 60 | M25: =VLOOKUP(C25,'IP PITSS'!$B$9:$I$90,8,0) -> 60 | N25: =+L25-M25 -> 0 | O25: SEI0029 | P25: =H25*2% -> 14.204 | Q25: =H25+P25 -> 724.404 | R25: =Q25*16% -> 115.90464
A26: SEI0472 | B26: IP INNOVACION | C26: Arzate Gil Juan Sebastian | D26: 416.5 | E26: 480 | G26: =+N26 -> 0 | H26: =SUM(D26:G26) -> 896.5 | J26: =VLOOKUP(C26,'IP PITSS'!$B$9:$U$90,3,0) -> 0 | K26: 8000 | L26: =(((+K26/30)*J26)*30%) -> 0 | M26: =VLOOKUP(C26,'IP PITSS'!$B$9:$I$90,8,0) -> 0 | N26: =+L26-M26 -> 0 | O26: SEI0550 | P26: =H26*2% -> 17.93 | Q26: =H26+P26 -> 914.43 | R26: =Q26*16% -> 146.3088
A27: SEI0528 | B27: IP INNOVACION | C27: Casas Chavarria Rafael | D27: 175.67 | E27: 675 | G27: =+N27 -> 0 | H27: =SUM(D27:G27) -> 850.67 | J27: =VLOOKUP(C27,'IP PITSS'!$B$9:$U$90,3,0) -> 0 | K27: 6300 | L27: =(((+K27/30)*J27)*30%) -> 0 | M27: =VLOOKUP(C27,'IP PITSS'!$B$9:$I$90,8,0) -> 0 | N27: =+L27-M27 -> 0 | O27: SEI0629 | P27: =H27*2% -> 17.0134 | Q27: =H27+P27 -> 867.6834 | R27: =Q27*16% -> 138.82934
A28: SEI0460 | B28: IP INNOVACION | C28: Castellon Ramos Rene | D28: 384.855 | E28: 135 | G28: =+N28 -> 0 | H28: =SUM(D28:G28) -> 519.855 | J28: =VLOOKUP(C28,'IP PITSS'!$B$9:$U$90,3,0) -> 0 | K28: 7505.99 | L28: =(((+K28/30)*J28)*30%) -> 0 | M28: =VLOOKUP(C28,'IP PITSS'!$B$9:$I$90,8,0) -> 0 | N28: =+L28-M28 -> 0 | O28: SEI0499 | P28: =H28*2% -> 10.3971 | Q28: =H28+P28 -> 530.2521 | R28: =Q28*16% -> 84.840336
A29: SEI0443 | B29: IP INNOVACION | C29: Castillo Nungaray Nestor Roman | D29: 135.2 | E29: 450 | G29: =+N29 -> 0 | H29: =SUM(D29:G29) -> 585.2 | J29: =VLOOKUP(C29,'IP PITSS'!$B$9:$U$90,3,0) -> 0 | K29: 6000 | L29: =(((+K29/30)*J29)*30%) -> 0 | M29: =VLOOKUP(C29,'IP PITSS'!$B$9:$I$90,8,0) -> 0 | N29: =+L29-M29 -> 0 | O29: SEI0468 | P29: =H29*2% -> 11.704 | Q29: =H29+P29 -> 596.904 | R29: =Q29*16% -> 95.50464
A30: SEI0490 | B30: IP INNOVACION | C30: Castillo Ramirez Hector Ivan | D30: 4001.2 | E30: 437.5 | F30: 840 | G30: =+N30 -> 0 | H30: =SUM(D30:G30) -> 5278.7 | J30: =VLOOKUP(C30,'IP PITSS'!$B$9:$U$90,3,0) -> 0 | K30: 14000 | L30: =(((+K30/30)*J30)*30%) -> 0 | M30: =VLOOKUP(C30,'IP PITSS'!$B$9:$I$90,8,0) -> 0 | N30: =+L30-M30 -> 0 | O30: SEI0448 | P30: =H30*2% -> 105.574 | Q30: =H30+P30 -> 5384.274 | R30: =Q30*16% -> 861.48384
A31: SEI0508 | B31: IP INNOVACION | C31: Cerro Garcia Elvis | D31: 2553.4 | E31: 400 | G31: =+N31 -> 0 | H31: =SUM(D31:G31) -> 2953.4 | J31: =VLOOKUP(C31,'IP PITSS'!$B$9:$U$90,3,0) -> 0 | K31: 10000 | L31: =(((+K31/30)*J31)*30%) -> 0 | M31: =VLOOKUP(C31,'IP PITSS'!$B$9:$I$90,8,0) -> 0 | N31: =+L31-M31 -> 0 | O31: SEI0513 | P31: =H31*2% -> 59.068 | Q31: =H31+P31 -> 3012.468 | R31: =Q31*16% -> 481.99488
A32: SEI0499 | B32: IP INNOVACION | C32: Chavez Dominguez Salvador | D32: 2667.4 | E32: 750 | F32: 400 | G32: =+N32 -> 0 | H32: =SUM(D32:G32) -> 3817.4 | J32: =VLOOKUP(C32,'IP PITSS'!$B$9:$U$90,3,0) -> 0 | K32: 12000 | L32: =(((+K32/30)*J32)*30%) -> 0 | M32: =VLOOKUP(C32,'IP PITSS'!$B$9:$I$90,8,0) -> 0 | N32: =+L32-M32 -> 0 | O32: SEI0483 | P32: =H32*2% -> 76.348 | Q32: =H32+P32 -> 3893.748 | R32: =Q32*16% -> 622.99968
A33: SEI0541 | B33: IP INNOVACION | C33: Chavez Govea Edgar Aram | D33: 222.6 | E33: 250 | G33: =+N33 -> 0 | H33: =SUM(D33:G33) -> 472.6 | J33: =VLOOKUP(C33,'IP PITSS'!$B$9:$U$90,3,0) -> 0 | K33: 7000 | L33: =(((+K33/30)*J33)*30%) -> 0 | M33: =VLOOKUP(C33,'IP PITSS'!$B$9:$I$90,8,0) -> 0 | N33: =+L33-M33 -> 0 | O33: SEI0644 | P33: =H33*2% -> 9.452 | Q33: =H33+P33 -> 482.052 | R33: =Q33*16% -> 77.12832
A34: SEI0442 | B34: IP INNOVACION | C34: Chavez Pedraza Samuel | D34: 1047.8 | E34: 687.5 | G34: =+N34 -> 0 | H34: =SUM(D34:G34) -> 1735.3 | J34: =VLOOKUP(C34,'IP PITSS'!$B$9:$U$90,3,0) -> 0 | K34: 14000 | L34: =(((+K34/30)*J34)*30%) -> 0 | M34: =VLOOKUP(C34,'IP PITSS'!$B$9:$I$90,8,0) -> 0 | N34: =+L34-M34 -> 0 | O34: SEI0467 | P34: =H34*2% -> 34.706 | Q34: =H34+P34 -> 1770.006 | R34: =Q34*16% -> 283.20096
A35: SEI0462 | B35: IP INNOVACION | C35: Chavez Saucedo Jorge Arturo | D35: 334.6 | E35: 450 | G35: =+N35 -> 0 | H35: =SUM(D35:G35) -> 784.6 | J35: =VLOOKUP(C35,'IP PITSS'!$B$9:$U$90,3,0) -> 1 | K35: 8000 | L35: =(((+K35/30)*J35)*30%) -> 80 | M35: =VLOOKUP(C35,'IP PITSS'!$B$9:$I$90,8,0) -> 80 | N35: =+L35-M35 -> 0 | O35: SEI0516 | P35: =H35*2% -> 15.692 | Q35: =H35+P35 -> 800.292 | R35: =Q35*16% -> 128.04672
A36: SEI0456 | B36: IP INNOVACION | C36: Chavira Garcia David Fernando | D36: 593.6 | E36: 110 | G36: =+N36 -> 0 | H36: =SUM(D36:G36) -> 703.6 | J36: =VLOOKUP(C36,'IP PITSS'!$B$9:$U$90,3,0) -> 0 | K36: 10000 | L36: =(((+K36/30)*J36)*30%) -> 0 | M36: =VLOOKUP(C36,'IP PITSS'!$B$9:$I$90,8,0) -> 0 | N36: =+L36-M36 -> 0 | O36: SEI0495 | P36: =H36*2% -> 14.072 | Q36: =H36+P36 -> 717.672 | R36: =Q36*16% -> 114.82752
A37: SEI0538 | B37: IP INNOVACION | C37: Coronado Vega Carlos Eduardo | D37: 0 | G37: =+N37 -> 0 | H37: =SUM(D37:G37) -> 0 | J37: 0 | K37: 6300 | L37: =(((+K37/30)*J37)*30%) -> 0 | M37: 0 | N37: =+L37-M37 -> 0 | O37: SEI0642 | P37: =H37*2% -> 0 | Q37: =H37+P37 -> 0 | R37: =Q37*16% -> 0
A38: SEI0015 | B38: IP INNOVACION | C38: Cota Jaramillo Miguel Angel | D38: 554.2 | E38: 225 | G38: =+N38 -> 0 | H38: =SUM(D38:G38) -> 779.2 | J38: =VLOOKUP(C38,'IP PITSS'!$B$9:$U$90,3,0) -> 0 | K38: 6000 | L38: =(((+K38/30)*J38)*30%) -> 0 | M38: =VLOOKUP(C38,'IP PITSS'!$B$9:$I$90,8,0) -> 0 | N38: =+L38-M38 -> 0 | O38: SEI0015 | P38: =H38*2% -> 15.584 | Q38: =H38+P38 -> 794.784 | R38: =Q38*16% -> 127.16544
A39: SEI0413 | B39: IP INNOVACION | C39: Courtenay Gutierrez Barry Vladimir | D39: 52.35 | E39: 250 | G39: =+N39 -> 0 | H39: =SUM(D39:G39) -> 302.35 | J39: =VLOOKUP(C39,'IP PITSS'!$B$9:$U$90,3,0) -> 0 | K39: 5000 | L39: =(((+K39/30)*J39)*30%) -> 0 | M39: =VLOOKUP(C39,'IP PITSS'!$B$9:$I$90,8,0) -> 0 | N39: =+L39-M39 -> 0 | O39: SEI0436 | P39: =H39*2% -> 6.047 | Q39: =H39+P39 -> 308.397 | R39: =Q39*16% -> 49.34352
A40: SEI0501 | B40: IP INNOVACION | C40: Cruz Herrera Roberto | D40: 1667.37 | E40: 465 | G40: =+N40 -> 0 | H40: =SUM(D40:G40) -> 2132.37 | J40: =VLOOKUP(C40,'IP PITSS'!$B$9:$U$90,3,0) -> 0 | K40: 10000 | L40: =(((+K40/30)*J40)*30%) -> 0 | M40: =VLOOKUP(C40,'IP PITSS'!$B$9:$I$90,8,0) -> 0 | N40: =+L40-M40 -> 0 | O40: SEI0485 | P40: =H40*2% -> 42.6474 | Q40: =H40+P40 -> 2175.0174 | R40: =Q40*16% -> 348.00278
A41: SEI479 | B41: IP INNOVACION | C41: Cruz Perez Alejandro Nezahualcoyotl | D41: 416.2 | E41: 480 | G41: =+N41 -> 0 | H41: =SUM(D41:G41) -> 896.2 | J41: =VLOOKUP(C41,'IP PITSS'!$B$9:$U$90,3,0) -> 0 | K41: 8000 | L41: =(((+K41/30)*J41)*30%) -> 0 | M41: =VLOOKUP(C41,'IP PITSS'!$B$9:$I$90,8,0) -> 0 | N41: =+L41-M41 -> 0 | O41: SEI0606 | P41: =H41*2% -> 17.924 | Q41: =H41+P41 -> 914.124 | R41: =Q41*16% -> 146.25984
A42: SEI0530 | B42: IP INNOVACION | C42: Del Pilar Mendez Lucio | D42: 134.21 | E42: 225 | G42: =+N42 -> 0 | H42: =SUM(D42:G42) -> 359.21 | J42: =VLOOKUP(C42,'IP PITSS'!$B$9:$U$90,3,0) -> 0 | K42: 6000 | L42: =(((+K42/30)*J42)*30%) -> 0 | M42: =VLOOKUP(C42,'IP PITSS'!$B$9:$I$90,8,0) -> 0 | N42: =+L42-M42 -> 0 | O42: SEI0630 | P42: =H42*2% -> 7.1842 | Q42: =H42+P42 -> 366.3942 | R42: =Q42*16% -> 58.623072
A43: SEI0543 | B43: IP INNOVACION | C43: Diaz Ortiz Hiram Guillermo | D43: 174.46 | E43: 590.63 | G43: =+N43 -> 0 | H43: =SUM(D43:G43) -> 765.09 | J43: =VLOOKUP(C43,'IP PITSS'!$B$9:$U$90,3,0) -> 0 | K43: 6300 | L43: =(((+K43/30)*J43)*30%) -> 0 | M43: =VLOOKUP(C43,'IP PITSS'!$B$9:$I$90,8,0) -> 0 | N43: =+L43-M43 -> 0 | O43: SEI0646 | P43: =H43*2% -> 15.3018 | Q43: =H43+P43 -> 780.3918 | R43: =Q43*16% -> 124.86269
A44: SEI0364 | B44: IP INNOVACION | C44: Dominguez Lopez Mayeli Del Pilar | D44: 1416.2 | E44: 718.75 | G44: =+N44 -> 0 | H44: =SUM(D44:G44) -> 2134.95 | J44: =VLOOKUP(C44,'IP PITSS'!$B$9:$U$90,3,0) -> 0 | K44: 10000 | L44: =(((+K44/30)*J44)*30%) -> 0 | M44: =VLOOKUP(C44,'IP PITSS'!$B$9:$I$90,8,0) -> 0 | N44: =+L44-M44 -> 0 | O44: SEI0364 | P44: =H44*2% -> 42.699 | Q44: =H44+P44 -> 2177.649 | R44: =Q44*16% -> 348.42384
A45: SEI0474 | B45: IP INNOVACION | C45: Enriquez Zamora Jessica Del Rocio | D45: 135.2 | E45: 455 | G45: =+N45 -> 0 | H45: =SUM(D45:G45) -> 590.2 | J45: =VLOOKUP(C45,'IP PITSS'!$B$9:$U$90,3,0) -> 1 | K45: 6000 | L45: =(((+K45/30)*J45)*30%) -> 60 | M45: =VLOOKUP(C45,'IP PITSS'!$B$9:$I$90,8,0) -> 60 | N45: =+L45-M45 -> 0 | O45: SEI0600 | P45: =H45*2% -> 11.804 | Q45: =H45+P45 -> 602.004 | R45: =Q45*16% -> 96.32064
A46: SEI0489 | B46: IP INNOVACION | C46: Escobedo Olivares Juan Guadalupe | D46: 3721.4 | E46: 375 | G46: =+N46 -> 0 | H46: =SUM(D46:G46) -> 4096.4 | J46: =VLOOKUP(C46,'IP PITSS'!$B$9:$U$90,3,0) -> 0 | K46: 14000 | L46: =(((+K46/30)*J46)*30%) -> 0 | M46: =VLOOKUP(C46,'IP PITSS'!$B$9:$I$90,8,0) -> 0 | N46: =+L46-M46 -> 0 | O46: SEI0447 | P46: =H46*2% -> 81.928 | Q46: =H46+P46 -> 4178.328 | R46: =Q46*16% -> 668.53248
A47: SEI0449 | B47: IP INNOVACION | C47: Flores Cerrillos Jorge Humberto | D47: 416.2 | E47: 130 | G47: =+N47 -> 0 | H47: =SUM(D47:G47) -> 546.2 | J47: =VLOOKUP(C47,'IP PITSS'!$B$9:$U$90,3,0) -> 0 | K47: 8000 | L47: =(((+K47/30)*J47)*30%) -> 0 | M47: =VLOOKUP(C47,'IP PITSS'!$B$9:$I$90,8,0) -> 0 | N47: =+L47-M47 -> 0 | O47: SEI0474 | P47: =H47*2% -> 10.924 | Q47: =H47+P47 -> 557.124 | R47: =Q47*16% -> 89.13984
A48: SEI0461 | B48: IP INNOVACION | C48: Flores Franco Marco | D48: 451.005 | E48: 412 | G48: =+N48 -> 0 | H48: =SUM(D48:G48) -> 863.005 | J48: =VLOOKUP(C48,'IP PITSS'!$B$9:$U$90,3,0) -> 0 | K48: 8500.01 | L48: =(((+K48/30)*J48)*30%) -> 0 | M48: =VLOOKUP(C48,'IP PITSS'!$B$9:$I$90,8,0) -> 0 | N48: =+L48-M48 -> 0 | O48: SEI0500 | P48: =H48*2% -> 17.2601 | Q48: =H48+P48 -> 880.2651 | R48: =Q48*16% -> 140.84242
A49: SEI0500 | B49: IP INNOVACION | C49: Garcia Gutierrez Jose Juan | D49: 3135.2 | E49: 225 | G49: =+N49 -> 0 | H49: =SUM(D49:G49) -> 3360.2 | J49: =VLOOKUP(C49,'IP PITSS'!$B$9:$U$90,3,0) -> 0 | K49: 12000 | L49: =(((+K49/30)*J49)*30%) -> 0 | M49: =VLOOKUP(C49,'IP PITSS'!$B$9:$I$90,8,0) -> 0 | N49: =+L49-M49 -> 0 | O49: SEI0484 | P49: =H49*2% -> 67.204 | Q49: =H49+P49 -> 3427.404 | R49: =Q49*16% -> 548.38464
... A52: SEI0457 | B52: IP INNOVACION | C52: Guerrero Lara Cesar Adrian | D52: 416.35 | E52: 275 | G52: =+N52 -> 0 | H52: =SUM(D52:G52) -> 691.35 | J52: =VLOOKUP(C52,'IP PITSS'!$B$9:$U$90,3,0) -> 0 | K52: 8000 | L52: =(((+K52/30)*J52)*30%) -> 0 | M52: =VLOOKUP(C52,'IP PITSS'!$B$9:$I$90,8,0) -> 0 | N52: =+L52-M52 -> 0 | O52: SEI0496 | P52: =H52*2% -> 13.827 | Q52: =H52+P52 -> 705.177 | R52: =Q52*16% -> 112.82832
A53: SEI0509 | B53: IP INNOVACION | C53: Gutierrez Castillo Jose De Jesus | D53: 284.2 | E53: 281.25 | G53: =+N53 -> 0 | H53: =SUM(D53:G53) -> 565.45 | J53: ='IP PITSS'!$D$66 -> 0 | K53: 6300 | L53: =(((+K53/30)*J53)*30%) -> 0 | M53: 0 | N53: =+L53-M53 -> 0 | O53: SEI0610 | P53: =H53*2% -> 11.309 | Q53: =H53+P53 -> 576.759 | R53: =Q53*16% -> 92.28144
A54: SEI0483 | B54: IP INNOVACION | C54: Gutierrez Muñoz Carlos Alejandro | D54: 2884.91 | E54: 225 | G54: =+N54 -> 0 | H54: =SUM(D54:G54) -> 3109.91 | J54: =VLOOKUP(C54,'IP PITSS'!$B$9:$U$90,3,0) -> 0 | K54: 12000 | L54: =(((+K54/30)*J54)*30%) -> 0 | M54: =VLOOKUP(C54,'IP PITSS'!$B$9:$I$90,8,0) -> 0 | N54: =+L54-M54 -> 0 | O54: SEI0095 | P54: =H54*2% -> 62.1982 | Q54: =H54+P54 -> 3172.1082 | R54: =Q54*16% -> 507.53731
A55: SEI0476 | B55: IP INNOVACION | C55: Hernandez Garcia Manuel Alejandro | D55: 414.6 | E55: 120 | G55: =+N55 -> 0 | H55: =SUM(D55:G55) -> 534.6 | J55: =VLOOKUP(C55,'IP PITSS'!$B$9:$U$90,3,0) -> 0 | K55: 8000 | L55: =(((+K55/30)*J55)*30%) -> 0 | M55: =VLOOKUP(C55,'IP PITSS'!$B$9:$I$90,8,0) -> 0 | N55: =+L55-M55 -> 0 | O55: SEI0602 | P55: =H55*2% -> 10.692 | Q55: =H55+P55 -> 545.292 | R55: =Q55*16% -> 87.24672
A56: SEI0536 | B56: IP INNOVACION | C56: Hernandez Ojeda Julio Cesar | D56: 1704.5 | E56: 125 | G56: =+N56 -> 0 | H56: =SUM(D56:G56) -> 1829.5 | J56: =VLOOKUP(C56,'IP PITSS'!$B$9:$U$90,3,0) -> 0 | K56: 7000 | L56: =(((+K56/30)*J56)*30%) -> 0 | M56: =VLOOKUP(C56,'IP PITSS'!$B$9:$I$90,8,0) -> 0 | N56: =+L56-M56 -> 0 | O56: SEI0640 | P56: =H56*2% -> 36.59 | Q56: =H56+P56 -> 1866.09 | R56: =Q56*16% -> 298.5744
A57: SEI0523 | B57: IP INNOVACION | C57: Hernandez Rodriguez Jorge | D57: 222.69 | E57: 550 | F57: 400 | G57: =+N57 -> 0 | H57: =SUM(D57:G57) -> 1172.69 | J57: =VLOOKUP(C57,'IP PITSS'!$B$9:$U$90,3,0) -> 0 | K57: 7000 | L57: =(((+K57/30)*J57)*30%) -> 0 | M57: =VLOOKUP(C57,'IP PITSS'!$B$9:$I$90,8,0) -> 0 | N57: =+L57-M57 -> 0 | O57: SEI0624 | P57: =H57*2% -> 23.4538 | Q57: =H57+P57 -> 1196.1438 | R57: =Q57*16% -> 191.38301
A58: SEI0464 | B58: IP INNOVACION | C58: Hueramo Hueramo Jesus Daniel | D58: 1450.88 | F58: 800 | G58: =+N58 -> 0 | H58: =SUM(D58:G58) -> 2250.88 | J58: =VLOOKUP(C58,'IP PITSS'!$B$9:$U$90,3,0) -> 0 | K58: 8500.01 | L58: =(((+K58/30)*J58)*30%) -> 0 | M58: =VLOOKUP(C58,'IP PITSS'!$B$9:$I$90,8,0) -> 0 | N58: =+L58-M58 -> 0 | O58: SEI 502 | P58: =H58*2% -> 45.0176 | Q58: =H58+P58 -> 2295.8976 | R58: =Q58*16% -> 367.34362
A59: SEI0511 | B59: IP INNOVACION | C59: Lizaran Maceda Jose Guadalupe | D59: 52.8 | E59: 160 | G59: =+N59 -> 0 | H59: =SUM(D59:G59) -> 212.8 | J59: =VLOOKUP(C59,'IP PITSS'!$B$9:$U$90,3,0) -> 0 | K59: 5000 | L59: =(((+K59/30)*J59)*30%) -> 0 | M59: =VLOOKUP(C59,'IP PITSS'!$B$9:$I$90,8,0) -> 0 | N59: =+L59-M59 -> 0 | O59: SEI0517 | P59: =H59*2% -> 4.256 | Q59: =H59+P59 -> 217.056 | R59: =Q59*16% -> 34.72896
A60: SEI0525 | B60: IP INNOVACION | C60: Lizaran Maceda Jesus | D60: 175.66 | G60: =+N60 -> 0 | H60: =SUM(D60:G60) -> 175.66 | J60: =VLOOKUP(C60,'IP PITSS'!$B$9:$U$90,3,0) -> 0 | K60: 6300 | L60: =(((+K60/30)*J60)*30%) -> 0 | M60: =VLOOKUP(C60,'IP PITSS'!$B$9:$I$90,8,0) -> 0 | N60: =+L60-M60 -> 0 | O60: SEI0626 | P60: =H60*2% -> 3.5132 | Q60: =H60+P60 -> 179.1732 | R60: =Q60*16% -> 28.667712
A61: SEI0438 | B61: IP INNOVACION | C61: Lopez Terron Roberto Porfirio | D61: 1047.8 | E61: 562.5 | G61: =+N61 -> 0 | H61: =SUM(D61:G61) -> 1610.3 | J61: =VLOOKUP(C61,'IP PITSS'!$B$9:$U$90,3,0) -> 0 | K61: 14000 | L61: =(((+K61/30)*J61)*30%) -> 0 | M61: =VLOOKUP(C61,'IP PITSS'!$B$9:$I$90,8,0) -> 0 | N61: =+L61-M61 -> 0 | O61: SEI0463 | P61: =H61*2% -> 32.206 | Q61: =H61+P61 -> 1642.506 | R61: =Q61*16% -> 262.80096
A62: SEI0517 | B62: IP INNOVACION | C62: Macias Torres Enrique | D62: 6520.6 | E62: 1938 | G62: =+N62 -> 0 | H62: =SUM(D62:G62) -> 8458.6 | J62: =VLOOKUP(C62,'IP PITSS'!$B$9:$U$90,3,0) -> 0 | K62: 19950 | L62: =(((+K62/30)*J62)*30%) -> 0 | M62: =VLOOKUP(C62,'IP PITSS'!$B$9:$I$90,8,0) -> 0 | N62: =+L62-M62 -> 0 | O62: SEI0120 | P62: =H62*2% -> 169.172 | Q62: =H62+P62 -> 8627.772 | R62: =Q62*16% -> 1380.4435
A63: SEI0020 | B63: IP INNOVACION | C63: Mar Marquez Cesar Eduardo | D63: 414.6 | E63: 165 | G63: =+N63 -> 0 | H63: =SUM(D63:G63) -> 579.6 | J63: =VLOOKUP(C63,'IP PITSS'!$B$9:$U$90,3,0) -> 0 | K63: 8000 | L63: =(((+K63/30)*J63)*30%) -> 0 | M63: =VLOOKUP(C63,'IP PITSS'!$B$9:$I$90,8,0) -> 0 | N63: =+L63-M63 -> 0 | O63: SEI0020 | P63: =H63*2% -> 11.592 | Q63: =H63+P63 -> 591.192 | R63: =Q63*16% -> 94.59072
A64: SEI0444 | B64: IP INNOVACION | C64: Marquez Hernandez Rogelio | D64: 416.4 | E64: 120 | G64: =+N64 -> 0 | H64: =SUM(D64:G64) -> 536.4 | J64: =VLOOKUP(C64,'IP PITSS'!$B$9:$U$90,3,0) -> 0 | K64: 8000 | L64: =(((+K64/30)*J64)*30%) -> 0 | M64: =VLOOKUP(C64,'IP PITSS'!$B$9:$I$90,8,0) -> 0 | N64: =+L64-M64 -> 0 | O64: SEI0469 | P64: =H64*2% -> 10.728 | Q64: =H64+P64 -> 547.128 | R64: =Q64*16% -> 87.54048
A65: SEI0428 | B65: IP INNOVACION | C65: Martinez Hernandez J. Antonio | D65: 416.2 | E65: 240 | G65: =+N65 -> 0 | H65: =SUM(D65:G65) -> 656.2 | J65: =VLOOKUP(C65,'IP PITSS'!$B$9:$U$90,3,0) -> 0 | K65: 8000 | L65: =(((+K65/30)*J65)*30%) -> 0 | M65: =VLOOKUP(C65,'IP PITSS'!$B$9:$I$90,8,0) -> 0 | N65: =+L65-M65 -> 0 | O65: SEI0452 | P65: =H65*2% -> 13.124 | Q65: =H65+P65 -> 669.324 | R65: =Q65*16% -> 107.09184
A66: SEI0504 | B66: IP INNOVACION | C66: Martinez Malo Cesar | D66: 1694.13 | E66: 225 | G66: =+N66 -> 0 | H66: =SUM(D66:G66) -> 1919.13 | J66: =VLOOKUP(C66,'IP PITSS'!$B$9:$U$90,3,0) -> 0 | K66: 9000 | L66: =(((+K66/30)*J66)*30%) -> 0 | M66: =VLOOKUP(C66,'IP PITSS'!$B$9:$I$90,8,0) -> 0 | N66: =+L66-M66 -> 0 | O66: SEI0488 | P66: =H66*2% -> 38.3826 | Q66: =H66+P66 -> 1957.5126 | R66: =Q66*16% -> 313.20202
A67: SEI0469 | B67: IP INNOVACION | C67: Martinez Morales Jose Martin | D67: 1047.6 | E67: 125 | G67: =+N67 -> 0 | H67: =SUM(D67:G67) -> 1172.6 | J67: =VLOOKUP(C67,'IP PITSS'!$B$9:$U$90,3,0) -> 0 | K67: 14000 | L67: =(((+K67/30)*J67)*30%) -> 0 | M67: =VLOOKUP(C67,'IP PITSS'!$B$9:$I$90,8,0) -> 0 | N67: =+L67-M67 -> 0 | O67: SEI0511 | P67: =H67*2% -> 23.452 | Q67: =H67+P67 -> 1196.052 | R67: =Q67*16% -> 191.36832
A68: SEI0493 | B68: IP INNOVACION | C68: Martinez Morales Tomas | D68: 3339.32 | E68: 412.5 | F68: 1880 | G68: =+N68 -> 0 | H68: =SUM(D68:G68) -> 5631.82 | J68: =VLOOKUP(C68,'IP PITSS'!$B$9:$U$90,3,0) -> 0 | K68: 15000 | L68: =(((+K68/30)*J68)*30%) -> 0 | M68: =VLOOKUP(C68,'IP PITSS'!$B$9:$I$90,8,0) -> 0 | N68: =+L68-M68 -> 0 | O68: SEI0477 | P68: =H68*2% -> 112.6364 | Q68: =H68+P68 -> 5744.4564 | R68: =Q68*16% -> 919.11302
A69: SEI0503 | B69: IP INNOVACION | C69: Martinez Rodriguez Paulo Cesar | D69: 2502.4 | E69: 160 | G69: =+N69 -> 50 | H69: =SUM(D69:G69) -> 2712.4 | J69: =VLOOKUP(C69,'IP PITSS'!$B$9:$U$90,3,0) -> 1 | K69: 10000 | L69: =(((+K69/30)*J69)*30%) -> 100 | M69: =VLOOKUP(C69,'IP PITSS'!$B$9:$I$90,8,0) -> 50 | N69: =+L69-M69 -> 50 | O69: SEI0487 | P69: =H69*2% -> 54.248 | Q69: =H69+P69 -> 2766.648 | R69: =Q69*16% -> 442.66368
A70: SEI0458 | B70: IP INNOVACION | C70: Martinez Zamora Gerardo Mario | D70: 549.815 | E70: 625 | G70: =+N70 -> 0 | H70: =SUM(D70:G70) -> 1174.815 | J70: =VLOOKUP(C70,'IP PITSS'!$B$9:$U$90,3,0) -> 0 | K70: 9550.01 | L70: =(((+K70/30)*J70)*30%) -> 0 | M70: =VLOOKUP(C70,'IP PITSS'!$B$9:$I$90,8,0) -> 0 | N70: =+L70-M70 -> 0 | O70: SEI0497 | P70: =H70*2% -> 23.4963 | Q70: =H70+P70 -> 1198.3113 | R70: =Q70*16% -> 191.72981
A71: SEI0494 | B71: IP INNOVACION | C71: Medellin Colunga Ruben Dario | D71: 4339.39 | E71: 281.25 | F71: 1160 | G71: =+N71 -> 0 | H71: =SUM(D71:G71) -> 5780.64 | J71: =VLOOKUP(C71,'IP PITSS'!$B$9:$U$90,3,0) -> 0 | K71: 17000 | L71: =(((+K71/30)*J71)*30%) -> 0 | M71: =VLOOKUP(C71,'IP PITSS'!$B$9:$I$90,8,0) -> 0 | N71: =+L71-M71 -> 0 | O71: SEI0478 | P71: =H71*2% -> 115.6128 | Q71: =H71+P71 -> 5896.2528 | R71: =Q71*16% -> 943.40045
A72: SEI0506 | B72: IP INNOVACION | C72: Mejia Duarte Jose Luis | D72: 3553.4 | E72: 500 | G72: =+N72 -> 0 | H72: =SUM(D72:G72) -> 4053.4 | J72: ='IP PITSS'!$D$64 -> 0 | K72: 12000 | L72: =(((+K72/30)*J72)*30%) -> 0 | M72: 0 | N72: =+L72-M72 -> 0 | O72: SEI0506 | P72: =H72*2% -> 81.068 | Q72: =H72+P72 -> 4134.468 | R72: =Q72*16% -> 661.51488
A73: SEI0513 | B73: IP INNOVACION | C73: Mendez Rivera Ivan Israel | D73: 52.5 | E73: 310 | G73: =+N73 -> 0 | H73: =SUM(D73:G73) -> 362.5 | J73: =VLOOKUP(C73,'IP PITSS'!$B$9:$U$90,3,0) -> 0 | K73: 5000 | L73: =(((+K73/30)*J73)*30%) -> 0 | M73: =VLOOKUP(C73,'IP PITSS'!$B$9:$I$90,8,0) -> 0 | N73: =+L73-M73 -> 0 | O73: SEI0612 | P73: =H73*2% -> 7.25 | Q73: =H73+P73 -> 369.75 | R73: =Q73*16% -> 59.16
A74: SEI0488 | B74: IP INNOVACION | C74: Mireles Casillas Brenda Cristina | D74: 2262.2 | G74: =+N74 -> 0 | H74: =SUM(D74:G74) -> 2262.2 | J74: =VLOOKUP(C74,'IP PITSS'!$B$9:$U$90,3,0) -> 0 | K74: 9000 | L74: =(((+K74/30)*J74)*30%) -> 0 | M74: =VLOOKUP(C74,'IP PITSS'!$B$9:$I$90,8,0) -> 0 | N74: =+L74-M74 -> 0 | O74: SEI0446 | P74: =H74*2% -> 45.244 | Q74: =H74+P74 -> 2307.444 | R74: =Q74*16% -> 369.19104
B75: IP INNOVACION | C75: Marin Avila Hector | D75: 706.8 | E75: 500 | G75: =+N75 -> 0 | H75: =+D75+E75+F75+G75 -> 1206.8 | J75: =VLOOKUP(C75,'IP PITSS'!$B$9:$U$90,3,0) -> 0 | K75: 8800 | L75: =(((+K75/30)*J75)*30%) -> 0 | M75: =VLOOKUP(C75,'IP PITSS'!$B$9:$I$90,8,0) -> 0 | N75: =+L75-M75 -> 0 | O75: SEI0445 | P75: =H75*2% -> 24.136 | Q75: =H75+P75 -> 1230.936 | R75: =Q75*16% -> 196.94976
A76: SEI0485 | B76: IP INNOVACION | C76: Molina Ramirez Gerardo Daniel | D76: 2262.37 | E76: 300 | G76: =+N76 -> 0 | H76: =SUM(D76:G76) -> 2562.37 | J76: =VLOOKUP(C76,'IP PITSS'!$B$9:$U$90,3,0) -> 0 | K76: 9000 | L76: =(((+K76/30)*J76)*30%) -> 0 | M76: =VLOOKUP(C76,'IP PITSS'!$B$9:$I$90,8,0) -> 0 | N76: =+L76-M76 -> 0 | O76: SEI0033 | P76: =H76*2% -> 51.2474 | Q76: =H76+P76 -> 2613.6174 | R76: =Q76*16% -> 418.17878
A77: SEI0014 | B77: IP INNOVACION | C77: Montoya Portillo Carlos Alberto | D77: 414.6 | E77: 225 | G77: 0 | H77: =SUM(D77:G77) -> 639.6 | J77: =VLOOKUP(C77,'IP PITSS'!$B$9:$U$90,3,0) -> 0 | K77: 8000 | L77: =(((+K77/30)*J77)*30%) -> 0 | M77: =VLOOKUP(C77,'IP PITSS'!$B$9:$I$90,8,0) -> 0 | N77: =+L77-M77 -> 0 | O77: SEI0014 | P77: =H77*2% -> 12.792 | Q77: =H77+P77 -> 652.392 | R77: =Q77*16% -> 104.38272
A78: SEI0540 | B78: IP INNOVACION | C78: Morales Martinez Eduardo | D78: 175.8 | E78: 843.75 | G78: =+N78 -> 0 | H78: =SUM(D78:G78) -> 1019.55 | J78: =VLOOKUP(C78,'IP PITSS'!$B$9:$U$90,3,0) -> 0 | K78: 6300 | L78: =(((+K78/30)*J78)*30%) -> 0 | M78: =VLOOKUP(C78,'IP PITSS'!$B$9:$I$90,8,0) -> 0 | N78: =+L78-M78 -> 0 | O78: SEI0648 | P78: =H78*2% -> 20.391 | Q78: =H78+P78 -> 1039.941 | R78: =Q78*16% -> 166.39056
A79: SEI0475 | B79: IP INNOVACION | C79: Moreno Quiroga Ana Sarahi | D79: 336.4 | E79: 1500 | G79: =+N79 -> 0 | H79: =SUM(D79:G79) -> 1836.4 | J79: =VLOOKUP(C79,'IP PITSS'!$B$9:$U$90,3,0) -> 1 | K79: 8000 | L79: =(((+K79/30)*J79)*30%) -> 80 | M79: =VLOOKUP(C79,'IP PITSS'!$B$9:$I$90,8,0) -> 80 | N79: =+L79-M79 -> 0 | O79: SEI0601 | P79: =H79*2% -> 36.728 | Q79: =H79+P79 -> 1873.128 | R79: =Q79*16% -> 299.70048
A80: SEI0017 | B80: IP INNOVACION | C80: Muñoz Reyes Luis Eduardo | D80: 414.64 | E80: 200 | G80: =+N80 -> 0 | H80: =SUM(D80:G80) -> 614.64 | J80: =VLOOKUP(C80,'IP PITSS'!$B$9:$U$90,3,0) -> 0 | K80: 8000 | L80: =(((+K80/30)*J80)*30%) -> 0 | M80: =VLOOKUP(C80,'IP PITSS'!$B$9:$I$90,8,0) -> 0 | N80: =+L80-M80 -> 0 | O80: SEI0017 | P80: =H80*2% -> 12.2928 | Q80: =H80+P80 -> 626.9328 | R80: =Q80*16% -> 100.30925
A81: SEI0022 | B81: IP INNOVACION | C81: Najera Lopez Raul | D81: 593.6 | E81: 90 | F81: 1440 | G81: =+N81 -> 0 | H81: =SUM(D81:G81) -> 2123.6 | J81: =VLOOKUP(C81,'IP PITSS'!$B$9:$U$90,3,0) -> 0 | K81: 10000 | L81: =(((+K81/30)*J81)*30%) -> 0 | M81: =VLOOKUP(C81,'IP PITSS'!$B$9:$I$90,8,0) -> 0 | N81: =+L81-M81 -> 0 | O81: SEI0022 | P81: =H81*2% -> 42.472 | Q81: =H81+P81 -> 2166.072 | R81: =Q81*16% -> 346.57152
B82: IP INNOVACION | C82: Negrete Bejar Aide Sarai | D82: 392.29 | E82: 2642.92 | G82: =+N82 -> 0 | H82: =SUM(D82:G82) -> 3035.21 | J82: =VLOOKUP(C82,'IP PITSS'!$B$9:$U$90,3,0) -> 0 | K82: 5000 | M82: =VLOOKUP(C82,'IP PITSS'!$B$9:$I$90,8,0) -> 0 | O82: SEI0016 | P82: =H82*2% -> 60.7042 | Q82: =H82+P82 -> 3095.9142 | R82: =Q82*16% -> 495.34627
A83: SEI0524 | B83: IP INNOVACION | C83: Orea Gonzalez Concepcion Esteban | D83: 175.8 | E83: 900 | G83: =+N83 -> 0 | H83: =SUM(D83:G83) -> 1075.8 | J83: =VLOOKUP(C83,'IP PITSS'!$B$9:$U$90,3,0) -> 0 | K83: 6300 | L83: =(((+K83/30)*J83)*30%) -> 0 | M83: =VLOOKUP(C83,'IP PITSS'!$B$9:$I$90,8,0) -> 0 | N83: =+L83-M83 -> 0 | O83: SEI0625 | P83: =H83*2% -> 21.516 | Q83: =H83+P83 -> 1097.316 | R83: =Q83*16% -> 175.57056
A84: SEI0424 | B84: IP INNOVACION | C84: Palacios Ramos Jesus | D84: 416.4 | E84: 330 | G84: =+N84 -> 0 | H84: =SUM(D84:G84) -> 746.4 | J84: =VLOOKUP(C84,'IP PITSS'!$B$9:$U$90,3,0) -> 0 | K84: 8000 | L84: =(((+K84/30)*J84)*30%) -> 0 | M84: =VLOOKUP(C84,'IP PITSS'!$B$9:$I$90,8,0) -> 0 | N84: =+L84-M84 -> 0 | O84: SEI0424 | P84: =H84*2% -> 14.928 | Q84: =H84+P84 -> 761.328 | R84: =Q84*16% -> 121.81248
A85: SEI0519 | B85: IP INNOVACION | C85: Palacios Vega Luis Rosendo | D85: 52.4 | E85: 70 | G85: =+N85 -> 0 | H85: =SUM(D85:G85) -> 122.4 | J85: =VLOOKUP(C85,'IP PITSS'!$B$9:$U$90,3,0) -> 0 | K85: 5000 | L85: =(((+K85/30)*J85)*30%) -> 0 | M85: =VLOOKUP(C85,'IP PITSS'!$B$9:$I$90,8,0) -> 0 | N85: =+L85-M85 -> 0 | O85: SEI0519 | P85: =H85*2% -> 2.448 | Q85: =H85+P85 -> 124.848 | R85: =Q85*16% -> 19.97568
A86: SEI0505 | B86: IP INNOVACION | C86: Perez Balboa Cesar | D86: 2838.88 | E86: 110 | G86: =+N86 -> 0 | H86: =SUM(D86:G86) -> 2948.88 | J86: =VLOOKUP(C86,'IP PITSS'!$B$9:$U$90,3,0) -> 0 | K86: 10000 | L86: =(((+K86/30)*J86)*30%) -> 0 | M86: =VLOOKUP(C86,'IP PITSS'!$B$9:$I$90,8,0) -> 0 | N86: =+L86-M86 -> 0 | O86: SEI0489 | P86: =H86*2% -> 58.9776 | Q86: =H86+P86 -> 3007.8576 | R86: =Q86*16% -> 481.25722
A87: SEI0455 | B87: IP INNOVACION | C87: Perez Garcia Andres Alvaro | D87: 416.4 | E87: 60 | G87: =+N87 -> 0 | H87: =SUM(D87:G87) -> 476.4 | J87: =VLOOKUP(C87,'IP PITSS'!$B$9:$U$90,3,0) -> 0 | K87: 8000 | L87: =(((+K87/30)*J87)*30%) -> 0 | M87: =VLOOKUP(C87,'IP PITSS'!$B$9:$I$90,8,0) -> 0 | N87: =+L87-M87 -> 0 | O87: SEI0494 | P87: =H87*2% -> 9.528 | Q87: =H87+P87 -> 485.928 | R87: =Q87*16% -> 77.74848
A88: SEI0023 | B88: IP INNOVACION | C88: Puente Murguia Luis Felipe | D88: 222.6 | E88: 75 | G88: =+N88 -> 0 | H88: =SUM(D88:G88) -> 297.6 | J88: =VLOOKUP(C88,'IP PITSS'!$B$9:$U$90,3,0) -> 0 | K88: 7000 | L88: =(((+K88/30)*J88)*30%) -> 0 | M88: =VLOOKUP(C88,'IP PITSS'!$B$9:$I$90,8,0) -> 0 | N88: =+L88-M88 -> 0 | O88: SEI0023 | P88: =H88*2% -> 5.952 | Q88: =H88+P88 -> 303.552 | R88: =Q88*16% -> 48.56832
A89: SEI0521 | B89: IP INNOVACION | C89: Rondero Savin Jacinto | D89: 221.2 | G89: =+N89 -> 0 | H89: =SUM(D89:G89) -> 221.2 | J89: =VLOOKUP(C89,'IP PITSS'!$B$9:$U$90,3,0) -> 0 | K89: 7000 | L89: =(((+K89/30)*J89)*30%) -> 0 | M89: =VLOOKUP(C89,'IP PITSS'!$B$9:$I$90,8,0) -> 0 | N89: =+L89-M89 -> 0 | O89: SEI0622 | P89: =H89*2% -> 4.424 | Q89: =H89+P89 -> 225.624 | R89: =Q89*16% -> 36.09984
A90: SEI0465 | B90: IP INNOVACION | C90: Sandoval Garcia Luis | D90: 416.4 | E90: 180 | G90: =+N90 -> 0 | H90: =SUM(D90:G90) -> 596.4 | J90: =VLOOKUP(C90,'IP PITSS'!$B$9:$U$90,3,0) -> 0 | K90: 8000 | L90: =(((+K90/30)*J90)*30%) -> 0 | M90: =VLOOKUP(C90,'IP PITSS'!$B$9:$I$90,8,0) -> 0 | N90: =+L90-M90 -> 0 | O90: SEI0503 | P90: =H90*2% -> 11.928 | Q90: =H90+P90 -> 608.328 | R90: =Q90*16% -> 97.33248
A91: SEI0477 | B91: IP INNOVACION | C91: Sandoval Medina Demetrio | D91: 414.6 | E91: 480 | G91: =+N91 -> 0 | H91: =SUM(D91:G91) -> 894.6 | J91: =VLOOKUP(C91,'IP PITSS'!$B$9:$U$90,3,0) -> 0 | K91: 8000 | L91: =(((+K91/30)*J91)*30%) -> 0 | M91: =VLOOKUP(C91,'IP PITSS'!$B$9:$I$90,8,0) -> 0 | N91: =+L91-M91 -> 0 | O91: SEI0603 | P91: =H91*2% -> 17.892 | Q91: =H91+P91 -> 912.492 | R91: =Q91*16% -> 145.99872
A92: SEI0537 | B92: IP INNOVACION | C92: Serrano Esquivel Armando | D92: 1704.48 | E92: 750 | G92: =+N92 -> 0 | H92: =SUM(D92:G92) -> 2454.48 | J92: =VLOOKUP(C92,'IP PITSS'!$B$9:$U$90,3,0) -> 0 | K92: 7000 | L92: =(((+K92/30)*J92)*30%) -> 0 | M92: =VLOOKUP(C92,'IP PITSS'!$B$9:$I$90,8,0) -> 0 | N92: =+L92-M92 -> 0 | O92: SEI0641 | P92: =H92*2% -> 49.0896 | Q92: =H92+P92 -> 2503.5696 | R92: =Q92*16% -> 400.57114
A93: SEI0498 | B93: IP INNOVACION | C93: Tenorio Alvarez Alberto Antonio | D93: 1667.46 | E93: 165 | F93: 320 | G93: =+N93 -> 0 | H93: =SUM(D93:G93) -> 2152.46 | J93: =VLOOKUP(C93,'IP PITSS'!$B$9:$U$90,3,0) -> 0 | K93: 10000 | L93: =(((+K93/30)*J93)*30%) -> 0 | M93: =VLOOKUP(C93,'IP PITSS'!$B$9:$I$90,8,0) -> 0 | N93: =+L93-M93 -> 0 | O93: SEI0482 | P93: =H93*2% -> 43.0492 | Q93: =H93+P93 -> 2195.5092 | R93: =Q93*16% -> 351.28147
A94: SEI0495 | B94: IP INNOVACION | C94: Torres Perez Carlos Alberto | D94: 1917.4 | E94: 1200 | F94: 2000 | G94: =+N94 -> 0 | H94: =SUM(D94:G94) -> 5117.4 | J94: =VLOOKUP(C94,'IP PITSS'!$B$9:$U$90,3,0) -> 0 | K94: 10500 | L94: =(((+K94/30)*J94)*30%) -> 0 | M94: =VLOOKUP(C94,'IP PITSS'!$B$9:$I$90,8,0) -> 0 | N94: =+L94-M94 -> 0 | O94: SEI0479 | P94: =H94*2% -> 102.348 | Q94: =H94+P94 -> 5219.748 | R94: =Q94*16% -> 835.15968
A95: SEI0010 | B95: IP INNOVACION | C95: Torres Ricardez Alfredo | D95: 414.6 | E95: 225 | G95: =+N95 -> 0 | H95: =SUM(D95:G95) -> 639.6 | J95: =VLOOKUP(C95,'IP PITSS'!$B$9:$U$90,3,0) -> 0 | K95: 8000 | L95: =(((+K95/30)*J95)*30%) -> 0 | M95: =VLOOKUP(C95,'IP PITSS'!$B$9:$I$90,8,0) -> 0 | N95: =+L95-M95 -> 0 | O95: SEI0010 | P95: =H95*2% -> 12.792 | Q95: =H95+P95 -> 652.392 | R95: =Q95*16% -> 104.38272
A96: SEI0473 | B96: IP INNOVACION | C96: Torres Velazquez Juan Antonio | D96: 416.2 | E96: 510 | G96: =+N96 -> 0 | H96: =SUM(D96:G96) -> 926.2 | J96: =VLOOKUP(C96,'IP PITSS'!$B$9:$U$90,3,0) -> 0 | K96: 8000 | L96: =(((+K96/30)*J96)*30%) -> 0 | M96: =VLOOKUP(C96,'IP PITSS'!$B$9:$I$90,8,0) -> 0 | N96: =+L96-M96 -> 0 | O96: SEI0604 | P96: =H96*2% -> 18.524 | Q96: =H96+P96 -> 944.724 | R96: =Q96*16% -> 151.15584
A97: SEI0497 | B97: IP INNOVACION | C97: Treviño Alvarez Jorge Alberto | D97: 2667.23 | F97: 760 | G97: =+N97 -> 0 | H97: =SUM(D97:G97) -> 3427.23 | J97: =VLOOKUP(C97,'IP PITSS'!$B$9:$U$90,3,0) -> 0 | K97: 12000 | L97: =(((+K97/30)*J97)*30%) -> 0 | M97: =VLOOKUP(C97,'IP PITSS'!$B$9:$I$90,8,0) -> 0 | N97: =+L97-M97 -> 0 | O97: SEI0481 | P97: =H97*2% -> 68.5446 | Q97: =H97+P97 -> 3495.7746 | R97: =Q97*16% -> 559.32394
A98: SEI0467 | B98: IP INNOVACION | C98: Vaca Valdez Guillermo | D98: 656.26 | E98: 270 | G98: =+N98 -> 0 | H98: =SUM(D98:G98) -> 926.26 | J98: =VLOOKUP(C98,'IP PITSS'!$B$9:$U$90,3,0) -> 0 | K98: 8000 | L98: =(((+K98/30)*J98)*30%) -> 0 | M98: =VLOOKUP(C98,'IP PITSS'!$B$9:$I$90,8,0) -> 0 | N98: =+L98-M98 -> 0 | O98: SEI0505 | P98: =H98*2% -> 18.5252 | Q98: =H98+P98 -> 944.7852 | R98: =Q98*16% -> 151.16563
A99: SEI0545 | B99: IP INNOVACION | C99: Vallarta Fonseca Mayra Karina | D99: 135.21 | G99: =+N99 -> 0 | H99: =SUM(D99:G99) -> 135.21 | J99: =VLOOKUP(C99,'IP PITSS'!$B$9:$U$90,3,0) -> 0 | K99: 6000 | L99: =(((+K99/30)*J99)*30%) -> 0 | M99: =VLOOKUP(C99,'IP PITSS'!$B$9:$I$90,8,0) -> 0 | N99: =+L99-M99 -> 0 | O99: SEI0653 | P99: =H99*2% -> 2.7042 | Q99: =H99+P99 -> 137.9142 | R99: =Q99*16% -> 22.066272
A100: SEI0021 | B100: IP INNOVACION | C100: Velez Rodriguez Jaime | D100: 1135.19 | G100: =+N100 -> 0 | H100: =SUM(D100:G100) -> 1135.19 | J100: =VLOOKUP(C100,'IP PITSS'!$B$9:$U$90,3,0) -> 0 | K100: 8000 | L100: =(((+K100/30)*J100)*30%) -> 0 | M100: =VLOOKUP(C100,'IP PITSS'!$B$9:$I$90,8,0) -> 0 | N100: =+L100-M100 -> 0 | O100: SEI0021 | P100: =H100*2% -> 22.7038 | Q100: =H100+P100 -> 1157.8938 | R100: =Q100*16% -> 185.26301
B101: IP INNOVACION | C101: Aguilar Garcia Rosa Paola | D101: 53.4 | G101: =+N101 -> 0 | H101: =SUM(D101:G101) -> 53.4 | J101: =VLOOKUP(C101,'IP PITSS'!$B$9:$U$90,3,0) -> 0 | K101: 5000 | L101: =(((+K101/30)*J101)*30%) -> 0 | M101: =VLOOKUP(C101,'IP PITSS'!$B$9:$I$90,8,0) -> 0 | N101: =+L101-M101 -> 0 | O101: SEI0654 | P101: =H101*2% -> 1.068 | Q101: =H101+P101 -> 54.468 | R101: =Q101*16% -> 8.71488
B102: IP INNOVACION | C102: Jauregui Madera Jorge Silvestre | D102: 308.8 | E102: 325 | G102: =+N102 -> 0 | H102: =SUM(D102:G102) -> 633.8 | J102: =VLOOKUP(C102,'IP PITSS'!$B$9:$U$90,3,0) -> 0 | M102: =VLOOKUP(C102,'IP PITSS'!$B$9:$I$90,8,0) -> 0 | O102: SEI0656 | P102: =H102*2% -> 12.676 | Q102: =H102+P102 -> 646.476 | R102: =Q102*16% -> 103.43616
...

Sheet RESUMEN PITS
F1: SINDICATO
A2: CLAVE | B2: EMPRESA | C2: NOMBRE | D2: NETO CPD | F2: SUELDO SINDICATO | G2: BONO | H2: COMISION | I2: PRIMA VACACIONAL SINDICATO | J2: B | K2: NETO A PAGAR | L2: NETO MENSUAL | M2: NETO QUINCENAL SEITON | N2: C | O2: prima vacacional | P2: COMISION Y PRIMA VACACIONAL | Q2: INFONAVIT | R2: FONACOT | S2: DESCUENTOS | T2: D | U2: TOTAL GENERAL | V2: DIFERENCIAS | W2: OBSERVACIONES | Y2: total
A3: SEI0009 | B3: CONSULTORIA | C3: Gutierrez Gutierrez Luis Arturo | D3: =VLOOKUP(C3,'CPD PITSS'!B9:V26,21,0) -> 2774.6 | F3: =VLOOKUP($C3,'SIND PITS'!$C$3:$G$20,2,0) -> 1475.4 | G3: =VLOOKUP($C3,'SIND PITS'!$C$3:$G$20,3,0) -> 100 | H3: =VLOOKUP($C3,'SIND PITS'!$C$3:$G$20,4,0) -> 0 | I3: =VLOOKUP($C3,'SIND PITS'!$C$3:$G$20,5,0) -> 0 | K3: =SUM(D3:I3) -> 4350 | L3: 8500 | M3: =+L3/2 -> 4250 | O3: =VLOOKUP($C3,'CPD PITSS'!$B$9:$V$26,8,0) -> 0 | P3: =+G3+H3+I3 -> 100 | Q3: =(VLOOKUP($C3,'CPD PITSS'!$B$9:$V$26,13,0))+(VLOOKUP($C3,'CPD PITSS'!$B$9:$V$26,14,0)) -> 0 | S3: 0 | U3: =+K3-O3-P3+Q3+R3+S3 -> 4250 | V3: =+M3-U3 -> 0 | X3: SEI0009 | Y3: =IFERROR(OFFSET('CPD PITSS'!$AN$8,MATCH('RESUMEN PITS'!C3,'CPD PITSS'!$B$9:$B$26,0),0),0)+IFERROR(OFFSET('IP PITSS'!$AL$8,MATCH('RESUMEN PITS'!C3,'IP PITSS'!$B$9:$B$90,0),0),0)+IFERROR(OFFSET('SIND PITS'!$Q$2,MATCH('RESUMEN PITS'!C3,'SIND PITS'!$C$3:$C$103,0),0),0) -> 5772.0882
A4: SEI0026 | B4: CONSULTORIA | C4: Patricio Aguilar Jhonattan Cristian | D4: =VLOOKUP(C4,'CPD PITSS'!B10:V27,21,0) -> 2912 | F4: =VLOOKUP($C4,'SIND PITS'!$C$3:$G$20,2,0) -> 1588 | G4: =VLOOKUP($C4,'SIND PITS'!$C$3:$G$20,3,0) -> 400 | H4: =VLOOKUP($C4,'SIND PITS'!$C$3:$G$20,4,0) -> 0 | I4: =VLOOKUP($C4,'SIND PITS'!$C$3:$G$20,5,0) -> 0 | K4: =SUM(D4:I4) -> 4900 | L4: 9000 | M4: =+L4/2 -> 4500 | O4: =VLOOKUP($C4,'CPD PITSS'!$B$9:$V$26,8,0) -> 0 | P4: =+G4+H4+I4 -> 400 | Q4: =(VLOOKUP($C4,'CPD PITSS'!$B$9:$V$26,13,0))+(VLOOKUP($C4,'CPD PITSS'!$B$9:$V$26,14,0)) -> 0 | S4: 0 | U4: =+K4-O4-P4+Q4+R4+S4 -> 4500 | V4: =+M4-U4 -> 0 | X4: SEI0026 | Y4: =IFERROR(OFFSET('CPD PITSS'!$AN$8,MATCH('RESUMEN PITS'!C4,'CPD PITSS'!$B$9:$B$26,0),0),0)+IFERROR(OFFSET('IP PITSS'!$AL$8,MATCH('RESUMEN PITS'!C4,'IP PITSS'!$B$9:$B$90,0),0),0)+IFERROR(OFFSET('SIND PITS'!$Q$2,MATCH('RESUMEN PITS'!C4,'SIND PITS'!$C$3:$C$103,0),0),0) -> 6356.742
A5: SEI0040 | B5: CONSULTORIA | C5: Mora Ramirez Acal Aldo Isidro | D5: =VLOOKUP(C5,'CPD PITSS'!B11:V28,21,0) -> 4036 | F5: =VLOOKUP($C5,'SIND PITS'!$C$3:$G$20,2,0) -> 2464 | G5: =VLOOKUP($C5,'SIND PITS'!$C$3:$G$20,3,0) -> 1000 | H5: =VLOOKUP($C5,'SIND PITS'!$C$3:$G$20,4,0) -> 0 | I5: =VLOOKUP($C5,'SIND PITS'!$C$3:$G$20,5,0) -> 0 | K5: =SUM(D5:I5) -> 7500 | L5: 13000 | M5: =+L5/2 -> 6500 | O5: =VLOOKUP($C5,'CPD PITSS'!$B$9:$V$26,8,0) -> 0 | P5: =+G5+H5+I5 -> 1000 | Q5: =(VLOOKUP($C5,'CPD PITSS'!$B$9:$V$26,13,0))+(VLOOKUP($C5,'CPD PITSS'!$B$9:$V$26,14,0)) -> 0 | S5: 0 | U5: =+K5-O5-P5+Q5+R5+S5 -> 6500 | V5: =+M5-U5 -> 0 | X5: SEI0040 | Y5: =IFERROR(OFFSET('CPD PITSS'!$AN$8,MATCH('RESUMEN PITS'!C5,'CPD PITSS'!$B$9:$B$26,0),0),0)+IFERROR(OFFSET('IP PITSS'!$AL$8,MATCH('RESUMEN PITS'!C5,'IP PITSS'!$B$9:$B$90,0),0),0)+IFERROR(OFFSET('SIND PITS'!$Q$2,MATCH('RESUMEN PITS'!C5,'SIND PITS'!$C$3:$C$103,0),0),0) -> 9198.3702
A6: SEI0041 | B6: CONSULTORIA | C6: Vazquez Perez Miguel Angel | D6: =VLOOKUP(C6,'CPD PITSS'!B12:V29,21,0) -> 5074 | F6: =VLOOKUP($C6,'SIND PITS'!$C$3:$G$20,2,0) -> 4176 | G6: =VLOOKUP($C6,'SIND PITS'!$C$3:$G$20,3,0) -> 750 | H6: =VLOOKUP($C6,'SIND PITS'!$C$3:$G$20,4,0) -> 0 | I6: =VLOOKUP($C6,'SIND PITS'!$C$3:$G$20,5,0) -> 0 | K6: =SUM(D6:I6) -> 10000 | L6: 18500 | M6: =+L6/2 -> 9250 | O6: =VLOOKUP($C6,'CPD PITSS'!$B$9:$V$26,8,0) -> 0 | P6: =+G6+H6+I6 -> 750 | Q6: =(VLOOKUP($C6,'CPD PITSS'!$B$9:$V$26,13,0))+(VLOOKUP($C6,'CPD PITSS'!$B$9:$V$26,14,0)) -> 0 | S6: 0 | U6: =+K6-O6-P6+Q6+R6+S6 -> 9250 | V6: =+M6-U6 -> 0 | X6: SEI0041 | Y6: =IFERROR(OFFSET('CPD PITSS'!$AN$8,MATCH('RESUMEN PITS'!C6,'CPD PITSS'!$B$9:$B$26,0),0),0)+IFERROR(OFFSET('IP PITSS'!$AL$8,MATCH('RESUMEN PITS'!C6,'IP PITSS'!$B$9:$B$90,0),0),0)+IFERROR(OFFSET('SIND PITS'!$Q$2,MATCH('RESUMEN PITS'!C6,'SIND PITS'!$C$3:$C$103,0),0),0) -> 11948.729
A7: SEI0088 | B7: CONSULTORIA | C7: Morgado Fernandez Martin | D7: =VLOOKUP(C7,'CPD PITSS'!B13:V30,21,0) -> 4899.8 | F7: =VLOOKUP($C7,'SIND PITS'!$C$3:$G$20,2,0) -> 2600.4 | G7: =VLOOKUP($C7,'SIND PITS'!$C$3:$G$20,3,0) -> 337.5 | H7: =VLOOKUP($C7,'SIND PITS'!$C$3:$G$20,4,0) -> 0 | I7: =VLOOKUP($C7,'SIND PITS'!$C$3:$G$20,5,0) -> 0 | K7: =SUM(D7:I7) -> 7837.7 | L7: 15000 | M7: =+L7/2 -> 7500 | O7: =VLOOKUP($C7,'CPD PITSS'!$B$9:$V$26,8,0) -> 0 | P7: =+G7+H7+I7 -> 337.5 | Q7: =(VLOOKUP($C7,'CPD PITSS'!$B$9:$V$26,13,0))+(VLOOKUP($C7,'CPD PITSS'!$B$9:$V$26,14,0)) -> 0 | S7: 0 | U7: =+K7-O7-P7+Q7+R7+S7 -> 7500.2 | V7: =+M7-U7 -> -0.2 | X7: SEI0088 | Y7: =IFERROR(OFFSET('CPD PITSS'!$AN$8,MATCH('RESUMEN PITS'!C7,'CPD PITSS'!$B$9:$B$26,0),0),0)+IFERROR(OFFSET('IP PITSS'!$AL$8,MATCH('RESUMEN PITS'!C7,'IP PITSS'!$B$9:$B$90,0),0),0)+IFERROR(OFFSET('SIND PITS'!$Q$2,MATCH('RESUMEN PITS'!C7,'SIND PITS'!$C$3:$C$103,0),0),0) -> 9712.2666
A8: SEI0097 | B8: CONSULTORIA | C8: Arreola Jimenez Jose Nieves | D8: =VLOOKUP(C8,'CPD PITSS'!B14:V31,21,0) -> 2105.2 | F8: =VLOOKUP($C8,'SIND PITS'!$C$3:$G$20,2,0) -> 1557.96 | G8: =VLOOKUP($C8,'SIND PITS'!$C$3:$G$20,3,0) -> 420 | H8: =VLOOKUP($C8,'SIND PITS'!$C$3:$G$20,4,0) -> 320 | I8: =VLOOKUP($C8,'SIND PITS'!$C$3:$G$20,5,0) -> 91.5 | K8: =SUM(D8:I8) -> 4494.66 | L8: 10150 | M8: =+L8/2 -> 5075 | O8: =VLOOKUP($C8,'CPD PITSS'!$B$9:$V$26,8,0) -> 111.5 | P8: =+G8+H8+I8 -> 831.5 | Q8: =(VLOOKUP($C8,'CPD PITSS'!$B$9:$V$26,13,0))+(VLOOKUP($C8,'CPD PITSS'!$B$9:$V$26,14,0)) -> 1523.27 | S8: 0 | U8: =+K8-O8-P8+Q8+R8+S8 -> 5074.93 | V8: =+M8-U8 -> 0.07 | X8: SEI0097 | Y8: =IFERROR(OFFSET('CPD PITSS'!$AN$8,MATCH('RESUMEN PITS'!C8,'CPD PITSS'!$B$9:$B$26,0),0),0)+IFERROR(OFFSET('IP PITSS'!$AL$8,MATCH('RESUMEN PITS'!C8,'IP PITSS'!$B$9:$B$90,0),0),0)+IFERROR(OFFSET('SIND PITS'!$Q$2,MATCH('RESUMEN PITS'!C8,'SIND PITS'!$C$3:$C$103,0),0),0) -> 7598.9286
A9: SEI0099 | B9: CONSULTORIA | C9: Garcia Villicaña Ricardo Pascual | D9: =VLOOKUP(C9,'CPD PITSS'!B15:V32,21,0) -> 4724.2 | F9: =VLOOKUP($C9,'SIND PITS'!$C$3:$G$20,2,0) -> 2600.37 | G9: =VLOOKUP($C9,'SIND PITS'!$C$3:$G$20,3,0) -> 150 | H9: =VLOOKUP($C9,'SIND PITS'!$C$3:$G$20,4,0) -> 0 | I9: =VLOOKUP($C9,'SIND PITS'!$C$3:$G$20,5,0) -> 0 | K9: =SUM(D9:I9) -> 7474.57 | L9: 15000 | M9: =+L9/2 -> 7500 | O9: =VLOOKUP($C9,'CPD PITSS'!$B$9:$V$26,8,0) -> 0 | P9: =+G9+H9+I9 -> 150 | Q9: =(VLOOKUP($C9,'CPD PITSS'!$B$9:$V$26,13,0))+(VLOOKUP($C9,'CPD PITSS'!$B$9:$V$26,14,0)) -> 0 | S9: =+'CPD PITSS'!S15 -> 175.43 | U9: =+K9-O9-P9+Q9+R9+S9 -> 7500 | V9: =+M9-U9 -> 0 | X9: SEI0099 | Y9: =IFERROR(OFFSET('CPD PITSS'!$AN$8,MATCH('RESUMEN PITS'!C9,'CPD PITSS'!$B$9:$B$26,0),0),0)+IFERROR(OFFSET('IP PITSS'!$AL$8,MATCH('RESUMEN PITS'!C9,'IP PITSS'!$B$9:$B$90,0),0),0)+IFERROR(OFFSET('SIND PITS'!$Q$2,MATCH('RESUMEN PITS'!C9,'SIND PITS'!$C$3:$C$103,0),0),0) -> 9520.8126
A10: SEI0108 | B10: CONSULTORIA | C10: Caballero Diaz Francisco Javier | D10: =VLOOKUP(C10,'CPD PITSS'!B16:V33,21,0) -> 1751.4 | F10: =VLOOKUP($C10,'SIND PITS'!$C$3:$G$20,2,0) -> 1558.09 | G10: =VLOOKUP($C10,'SIND PITS'!$C$3:$G$20,3,0) -> 330 | H10: =VLOOKUP($C10,'SIND PITS'!$C$3:$G$20,4,0) -> 320 | I10: =VLOOKUP($C10,'SIND PITS'!$C$3:$G$20,5,0) -> 0 | K10: =SUM(D10:I10) -> 3959.49 | L10: 10150 | M10: =+L10/2 -> 5075 | O10: =VLOOKUP($C10,'CPD PITSS'!$B$9:$V$26,8,0) -> 0 | P10: =+G10+H10+I10 -> 650 | Q10: =(VLOOKUP($C10,'CPD PITSS'!$B$9:$V$26,13,0))+(VLOOKUP($C10,'CPD PITSS'!$B$9:$V$26,14,0)) -> 1765.48 | S10: 0 | U10: =+K10-O10-P10+Q10+R10+S10 -> 5074.97 | V10: =+M10-U10 -> 0.03 | X10: SEI0108 | Y10: =IFERROR(OFFSET('CPD PITSS'!$AN$8,MATCH('RESUMEN PITS'!C10,'CPD PITSS'!$B$9:$B$26,0),0),0)+IFERROR(OFFSET('IP PITSS'!$AL$8,MATCH('RESUMEN PITS'!C10,'IP PITSS'!$B$9:$B$90,0),0),0)+IFERROR(OFFSET('SIND PITS'!$Q$2,MATCH('RESUMEN PITS'!C10,'SIND PITS'!$C$3:$C$103,0),0),0) -> 7300.1094
A11: SEI0116 | B11: CONSULTORIA | C11: Casillas Cardona Cesar Alejandro | D11: =VLOOKUP(C11,'CPD PITSS'!B17:V34,21,0) -> 3083 | F11: =VLOOKUP($C11,'SIND PITS'!$C$3:$G$20,2,0) -> 1891.2 | G11: =VLOOKUP($C11,'SIND PITS'!$C$3:$G$20,3,0) -> 0 | H11: =VLOOKUP($C11,'SIND PITS'!$C$3:$G$20,4,0) -> 0 | I11: =VLOOKUP($C11,'SIND PITS'!$C$3:$G$20,5,0) -> 0 | K11: =SUM(D11:I11) -> 4974.2 | L11: 12000 | M11: =+L11/2 -> 6000 | O11: =VLOOKUP($C11,'CPD PITSS'!$B$9:$V$26,8,0) -> 0 | P11: =+G11+H11+I11 -> 0 | Q11: =(VLOOKUP($C11,'CPD PITSS'!$B$9:$V$26,13,0))+(VLOOKUP($C11,'CPD PITSS'!$B$9:$V$26,14,0)) -> 1025.9 | S11: 0 | U11: =+K11-O11-P11+Q11+R11+S11 -> 6000.1 | V11: =+M11-U11 -> -0.1 | X11: SEI0116 | Y11: =IFERROR(OFFSET('CPD PITSS'!$AN$8,MATCH('RESUMEN PITS'!C11,'CPD PITSS'!$B$9:$B$26,0),0),0)+IFERROR(OFFSET('IP PITSS'!$AL$8,MATCH('RESUMEN PITS'!C11,'IP PITSS'!$B$9:$B$90,0),0),0)+IFERROR(OFFSET('SIND PITS'!$Q$2,MATCH('RESUMEN PITS'!C11,'SIND PITS'!$C$3:$C$103,0),0),0) -> 7680.243
A12: SEI0117 | B12: CONSULTORIA | C12: Mariscal Romero Luis Adrian | D12: =VLOOKUP(C12,'CPD PITSS'!B18:V35,21,0) -> 3129.8 | F12: =VLOOKUP($C12,'SIND PITS'!$C$3:$G$20,2,0) -> 2751 | G12: =VLOOKUP($C12,'SIND PITS'!$C$3:$G$20,3,0) -> 165 | H12: =VLOOKUP($C12,'SIND PITS'!$C$3:$G$20,4,0) -> 0 | I12: =VLOOKUP($C12,'SIND PITS'!$C$3:$G$20,5,0) -> 0 | K12: =SUM(D12:I12) -> 6045.8 | L12: 15000 | M12: =+L12/2 -> 7500 | O12: =VLOOKUP($C12,'CPD PITSS'!$B$9:$V$26,8,0) -> 0 | P12: =+G12+H12+I12 -> 165 | Q12: =(VLOOKUP($C12,'CPD PITSS'!$B$9:$V$26,13,0))+(VLOOKUP($C12,'CPD PITSS'!$B$9:$V$26,14,0)) -> 1619.18 | S12: 0 | U12: =+K12-O12-P12+Q12+R12+S12 -> 7499.98 | V12: =+M12-U12 -> 0.02 | X12: SEI0117 | Y12: =IFERROR(OFFSET('CPD PITSS'!$AN$8,MATCH('RESUMEN PITS'!C12,'CPD PITSS'!$B$9:$B$26,0),0),0)+IFERROR(OFFSET('IP PITSS'!$AL$8,MATCH('RESUMEN PITS'!C12,'IP PITSS'!$B$9:$B$90,0),0),0)+IFERROR(OFFSET('SIND PITS'!$Q$2,MATCH('RESUMEN PITS'!C12,'SIND PITS'!$C$3:$C$103,0),0),0) -> 9497.2812
A13: SEI0118 | B13: CONSULTORIA | C13: Arroyo Ramirez Hector Hugo | D13: =VLOOKUP(C13,'CPD PITSS'!B19:V36,21,0) -> 2993 | F13: =VLOOKUP($C13,'SIND PITS'!$C$3:$G$20,2,0) -> 2104.9 | G13: =VLOOKUP($C13,'SIND PITS'!$C$3:$G$20,3,0) -> 0 | H13: =VLOOKUP($C13,'SIND PITS'!$C$3:$G$20,4,0) -> 0 | I13: =VLOOKUP($C13,'SIND PITS'!$C$3:$G$20,5,0) -> 281.67 | K13: =SUM(D13:I13) -> 5379.57 | L13: 13000 | M13: =+L13/2 -> 6500 | O13: =VLOOKUP($C13,'CPD PITSS'!$B$9:$V$26,8,0) -> 238.33 | P13: =+G13+H13+I13 -> 281.67 | Q13: =(VLOOKUP($C13,'CPD PITSS'!$B$9:$V$26,13,0))+(VLOOKUP($C13,'CPD PITSS'!$B$9:$V$26,14,0)) -> 1387 | S13: =+'CPD PITSS'!S19 -> 255.4 | U13: =+K13-O13-P13+Q13+R13+S13 -> 6501.97 | V13: =+M13-U13 -> -1.97 | X13: SEI0118 | Y13: =IFERROR(OFFSET('CPD PITSS'!$AN$8,MATCH('RESUMEN PITS'!C13,'CPD PITSS'!$B$9:$B$26,0),0),0)+IFERROR(OFFSET('IP PITSS'!$AL$8,MATCH('RESUMEN PITS'!C13,'IP PITSS'!$B$9:$B$90,0),0),0)+IFERROR(OFFSET('SIND PITS'!$Q$2,MATCH('RESUMEN PITS'!C13,'SIND PITS'!$C$3:$C$103,0),0),0) -> 8772.3366
A14: SEI0127 | B14: CONSULTORIA | C14: Hernandez Ochoa Eduardo | D14: =VLOOKUP(C14,'CPD PITSS'!B20:V37,21,0) -> 4899.6 | F14: =VLOOKUP($C14,'SIND PITS'!$C$3:$G$20,2,0) -> 2600.2 | G14: =VLOOKUP($C14,'SIND PITS'!$C$3:$G$20,3,0) -> 337.5 | H14: =VLOOKUP($C14,'SIND PITS'!$C$3:$G$20,4,0) -> 0 | I14: =VLOOKUP($C14,'SIND PITS'!$C$3:$G$20,5,0) -> 0 | K14: =SUM(D14:I14) -> 7837.3 | L14: 15000 | M14: =+L14/2 -> 7500 | O14: =VLOOKUP($C14,'CPD PITSS'!$B$9:$V$26,8,0) -> 0 | P14: =+G14+H14+I14 -> 337.5 | Q14: =(VLOOKUP($C14,'CPD PITSS'!$B$9:$V$26,13,0))+(VLOOKUP($C14,'CPD PITSS'!$B$9:$V$26,14,0)) -> 0 | S14: 0 | U14: =+K14-O14-P14+Q14+R14+S14 -> 7499.8 | V14: =+M14-U14 -> 0.2 | X14: SEI0127 | Y14: =IFERROR(OFFSET('CPD PITSS'!$AN$8,MATCH('RESUMEN PITS'!C14,'CPD PITSS'!$B$9:$B$26,0),0),0)+IFERROR(OFFSET('IP PITSS'!$AL$8,MATCH('RESUMEN PITS'!C14,'IP PITSS'!$B$9:$B$90,0),0),0)+IFERROR(OFFSET('SIND PITS'!$Q$2,MATCH('RESUMEN PITS'!C14,'SIND PITS'!$C$3:$C$103,0),0),0) -> 9711.8586
A15: SEI0173 | B15: CONSULTORIA | C15: Nieto Ortiz Jose Luis | D15: =VLOOKUP(C15,'CPD PITSS'!B21:V38,21,0) -> 1421.8 | F15: =VLOOKUP($C15,'SIND PITS'!$C$3:$G$20,2,0) -> 1483.13 | G15: =VLOOKUP($C15,'SIND PITS'!$C$3:$G$20,3,0) -> 20 | H15: =VLOOKUP($C15,'SIND PITS'!$C$3:$G$20,4,0) -> 0 | I15: =VLOOKUP($C15,'SIND PITS'!$C$3:$G$20,5,0) -> 0 | K15: =SUM(D15:I15) -> 2924.93 | L15: 10000 | M15: =+L15/2 -> 5000 | O15: =VLOOKUP($C15,'CPD PITSS'!$B$9:$V$26,8,0) -> 0 | P15: =+G15+H15+I15 -> 20 | Q15: =(VLOOKUP($C15,'CPD PITSS'!$B$9:$V$26,13,0))+(VLOOKUP($C15,'CPD PITSS'!$B$9:$V$26,14,0)) -> 2095.03 | S15: 0 | U15: =+K15-O15-P15+Q15+R15+S15 -> 4999.96 | V15: =+M15-U15 -> 0.04 | X15: SEI0173 | Y15: =IFERROR(OFFSET('CPD PITSS'!$AN$8,MATCH('RESUMEN PITS'!C15,'CPD PITSS'!$B$9:$B$26,0),0),0)+IFERROR(OFFSET('IP PITSS'!$AL$8,MATCH('RESUMEN PITS'!C15,'IP PITSS'!$B$9:$B$90,0),0),0)+IFERROR(OFFSET('SIND PITS'!$Q$2,MATCH('RESUMEN PITS'!C15,'SIND PITS'!$C$3:$C$103,0),0),0) -> 6580.9992
A16: SEI0221 | B16: CONSULTORIA | C16: Rogel Teran Marco Antonio | D16: =VLOOKUP(C16,'CPD PITSS'!B22:V39,21,0) -> 17705 | F16: =VLOOKUP($C16,'SIND PITS'!$C$3:$G$20,2,0) -> 12613.2 | G16: =VLOOKUP($C16,'SIND PITS'!$C$3:$G$20,3,0) -> 0 | H16: =VLOOKUP($C16,'SIND PITS'!$C$3:$G$20,4,0) -> 0 | I16: =VLOOKUP($C16,'SIND PITS'!$C$3:$G$20,5,0) -> 281.75 | K16: =SUM(D16:I16) -> 30599.95 | L16: 60000 | M16: =+L16/2 -> 30000 | O16: =VLOOKUP($C16,'CPD PITSS'!$B$9:$V$26,8,0) -> 318.25 | P16: =+G16+H16+I16 -> 281.75 | Q16: =(VLOOKUP($C16,'CPD PITSS'!$B$9:$V$26,13,0))+(VLOOKUP($C16,'CPD PITSS'!$B$9:$V$26,14,0)) -> 0 | S16: 0 | U16: =+K16-O16-P16+Q16+R16+S16 -> 29999.95 | V16: =+M16-U16 -> 0.05 | X16: SEI0221 | Y16: =IFERROR(OFFSET('CPD PITSS'!$AN$8,MATCH('RESUMEN PITS'!C16,'CPD PITSS'!$B$9:$B$26,0),0),0)+IFERROR(OFFSET('IP PITSS'!$AL$8,MATCH('RESUMEN PITS'!C16,'IP PITSS'!$B$9:$B$90,0),0),0)+IFERROR(OFFSET('SIND PITS'!$Q$2,MATCH('RESUMEN PITS'!C16,'SIND PITS'!$C$3:$C$103,0),0),0) -> 35360.84
A17: SEI0401 | B17: CONSULTORIA | C17: De La Torre Zambara Francisco Ernesto | D17: =VLOOKUP(C17,'CPD PITSS'!B23:V40,21,0) -> 3628.4 | F17: =VLOOKUP($C17,'SIND PITS'!$C$3:$G$20,2,0) -> 1558 | G17: =VLOOKUP($C17,'SIND PITS'!$C$3:$G$20,3,0) -> 270 | H17: =VLOOKUP($C17,'SIND PITS'!$C$3:$G$20,4,0) -> 320 | I17: =VLOOKUP($C17,'SIND PITS'!$C$3:$G$20,5,0) -> 91.5 | K17: =SUM(D17:I17) -> 5867.9 | L17: 10150 | M17: =+L17/2 -> 5075 | O17: =VLOOKUP($C17,'CPD PITSS'!$B$9:$V$26,8,0) -> 111.5 | P17: =+G17+H17+I17 -> 681.5 | Q17: =(VLOOKUP($C17,'CPD PITSS'!$B$9:$V$26,13,0))+(VLOOKUP($C17,'CPD PITSS'!$B$9:$V$26,14,0)) -> 0 | S17: 0 | U17: =+K17-O17-P17+Q17+R17+S17 -> 5074.9 | V17: =+M17-U17 -> 0.1 | X17: SEI0401 | Y17: =IFERROR(OFFSET('CPD PITSS'!$AN$8,MATCH('RESUMEN PITS'!C17,'CPD PITSS'!$B$9:$B$26,0),0),0)+IFERROR(OFFSET('IP PITSS'!$AL$8,MATCH('RESUMEN PITS'!C17,'IP PITSS'!$B$9:$B$90,0),0),0)+IFERROR(OFFSET('SIND PITS'!$Q$2,MATCH('RESUMEN PITS'!C17,'SIND PITS'!$C$3:$C$103,0),0),0) -> 7445.898
A18: SEI0425 | B18: CONSULTORIA | C18: Carbajal Cabuto Jose Luis | D18: =VLOOKUP(C18,'CPD PITSS'!B24:V41,21,0) -> 2058.8 | F18: =VLOOKUP($C18,'SIND PITS'!$C$3:$G$20,2,0) -> 1608.1 | G18: =VLOOKUP($C18,'SIND PITS'!$C$3:$G$20,3,0) -> 270 | H18: =VLOOKUP($C18,'SIND PITS'!$C$3:$G$20,4,0) -> 0 | I18: =VLOOKUP($C18,'SIND PITS'!$C$3:$G$20,5,0) -> 0 | K18: =SUM(D18:I18) -> 3936.9 | L18: 10250 | M18: =+L18/2 -> 5125 | O18: =VLOOKUP($C18,'CPD PITSS'!$B$9:$V$26,8,0) -> 0 | P18: =+G18+H18+I18 -> 270 | Q18: =(VLOOKUP($C18,'CPD PITSS'!$B$9:$V$26,13,0))+(VLOOKUP($C18,'CPD PITSS'!$B$9:$V$26,14,0)) -> 1458.16 | S18: 0 | U18: =+K18-O18-P18+Q18+R18+S18 -> 5125.06 | V18: =+M18-U18 -> -0.06 | X18: SEI0453 | Y18: =IFERROR(OFFSET('CPD PITSS'!$AN$8,MATCH('RESUMEN PITS'!C18,'CPD PITSS'!$B$9:$B$26,0),0),0)+IFERROR(OFFSET('IP PITSS'!$AL$8,MATCH('RESUMEN PITS'!C18,'IP PITSS'!$B$9:$B$90,0),0),0)+IFERROR(OFFSET('SIND PITS'!$Q$2,MATCH('RESUMEN PITS'!C18,'SIND PITS'!$C$3:$C$103,0),0),0) -> 6963.6012
A19: SEI0435 | B19: CONSULTORIA | C19: Benavides Herrera Alejandra | D19: =VLOOKUP(C19,'CPD PITSS'!B25:V42,21,0) -> 3196.8 | F19: =VLOOKUP($C19,'SIND PITS'!$C$3:$G$20,2,0) -> 16803.4 | G19: =VLOOKUP($C19,'SIND PITS'!$C$3:$G$20,3,0) -> 0 | H19: =VLOOKUP($C19,'SIND PITS'!$C$3:$G$20,4,0) -> 0 | I19: =VLOOKUP($C19,'SIND PITS'!$C$3:$G$20,5,0) -> 0 | K19: =SUM(D19:I19) -> 20000.2 | L19: 40000 | M19: =+L19/2 -> 20000 | O19: =VLOOKUP($C19,'CPD PITSS'!$B$9:$V$26,8,0) -> 0 | P19: =+G19+H19+I19 -> 0 | Q19: =(VLOOKUP($C19,'CPD PITSS'!$B$9:$V$26,13,0))+(VLOOKUP($C19,'CPD PITSS'!$B$9:$V$26,14,0)) -> 0 | S19: 0 | U19: =+K19-O19-P19+Q19+R19+S19 -> 20000.2 | V19: =+M19-U19 -> -0.2 | X19: SEI0377 | Y19: =IFERROR(OFFSET('CPD PITSS'!$AN$8,MATCH('RESUMEN PITS'!C19,'CPD PITSS'!$B$9:$B$26,0),0),0)+IFERROR(OFFSET('IP PITSS'!$AL$8,MATCH('RESUMEN PITS'!C19,'IP PITSS'!$B$9:$B$90,0),0),0)+IFERROR(OFFSET('SIND PITS'!$Q$2,MATCH('RESUMEN PITS'!C19,'SIND PITS'!$C$3:$C$103,0),0),0) -> 21806.376
A20: SEI0442 | B20: CONSULTORIA | C20: Sierra Escamilla Daniela | D20: =VLOOKUP(C20,'CPD PITSS'!B26:V43,21,0) -> 4036 | F20: =VLOOKUP($C20,'SIND PITS'!$C$3:$G$20,2,0) -> 2464 | G20: =VLOOKUP($C20,'SIND PITS'!$C$3:$G$20,3,0) -> 1000 | H20: =VLOOKUP($C20,'SIND PITS'!$C$3:$G$20,4,0) -> 0 | I20: =VLOOKUP($C20,'SIND PITS'!$C$3:$G$20,5,0) -> 0 | K20: =SUM(D20:I20) -> 7500 | L20: 13000 | M20: =+L20/2 -> 6500 | O20: =VLOOKUP($C20,'CPD PITSS'!$B$9:$V$26,8,0) -> 0 | P20: =+G20+H20+I20 -> 1000 | Q20: =(VLOOKUP($C20,'CPD PITSS'!$B$9:$V$26,13,0))+(VLOOKUP($C20,'CPD PITSS'!$B$9:$V$26,14,0)) -> 0 | S20: 0 | U20: =+K20-O20-P20+Q20+R20+S20 -> 6500 | V20: =+M20-U20 -> 0 | X20: SEI0618 | Y20: =IFERROR(OFFSET('CPD PITSS'!$AN$8,MATCH('RESUMEN PITS'!C20,'CPD PITSS'!$B$9:$B$26,0),0),0)+IFERROR(OFFSET('IP PITSS'!$AL$8,MATCH('RESUMEN PITS'!C20,'IP PITSS'!$B$9:$B$90,0),0),0)+IFERROR(OFFSET('SIND PITS'!$Q$2,MATCH('RESUMEN PITS'!C20,'SIND PITS'!$C$3:$C$103,0),0),0) -> 9198.3702
A21: SEI0010 | B21: IP INNOVACION | C21: Torres Ricardez Alfredo | D21: =VLOOKUP(C21,'IP PITSS'!$B$9:$U$90,21,0) -> #REF! | F21: =VLOOKUP(C21,'SIND PITS'!$C$3:$D$100,2,0) -> 414.6 | G21: =VLOOKUP(C21,'SIND PITS'!$C$3:$E$100,3,0) -> 225 | H21: =VLOOKUP(C21,'SIND PITS'!$C$3:$F$100,4,0) -> 0 | I21: =VLOOKUP(C21,'SIND PITS'!$C$3:$G$100,5,0) -> 0 | K21: =SUM(D21:I21) -> #REF! | L21: 8000 | M21: =+L21/2 -> 4000 | O21: =VLOOKUP(C21,'[1]IP PITS'!$B$6:$I$87,8,0) -> 0 | P21: =+G21+H21+I21 -> 225 | Q21: =(VLOOKUP(C21,'IP PITSS'!$B$9:$M$90,10,0))+(VLOOKUP(C21,'IP PITSS'!$B$9:$M$90,11,0))+(VLOOKUP(C21,'IP PITSS'!$B$9:$M$90,12,0)) -> 0 | R21: =VLOOKUP(C21,'IP PITSS'!$B$9:$Q$90,17,0) -> #REF! | S21: =VLOOKUP(C21,'IP PITSS'!$B$9:$R$90,18,0) -> #REF! | U21: =+K21-O21-P21+Q21+R21+S21 -> #REF! | V21: =+M21-U21 -> #REF! | X21: SEI0010 | Y21: =IFERROR(OFFSET('CPD PITSS'!$AN$8,MATCH('RESUMEN PITS'!C21,'CPD PITSS'!$B$9:$B$26,0),0),0)+IFERROR(OFFSET('IP PITSS'!$AL$8,MATCH('RESUMEN PITS'!C21,'IP PITSS'!$B$9:$B$90,0),0),0)+IFERROR(OFFSET('SIND PITS'!$Q$2,MATCH('RESUMEN PITS'!C21,'SIND PITS'!$C$3:$C$103,0),0),0) -> 5778.821
A22: SEI0014 | B22: IP INNOVACION | C22: Montoya Portillo Carlos Alberto | D22: =VLOOKUP(C22,'IP PITSS'!$B$9:$U$90,21,0) -> #REF! | F22: =VLOOKUP(C22,'SIND PITS'!$C$3:$D$100,2,0) -> 414.6 | G22: =VLOOKUP(C22,'SIND PITS'!$C$3:$E$100,3,0) -> 225 | H22: =VLOOKUP(C22,'SIND PITS'!$C$3:$F$100,4,0) -> 0 | I22: =VLOOKUP(C22,'SIND PITS'!$C$3:$G$100,5,0) -> 0 | K22: =SUM(D22:I22) -> #REF! | L22: 8000 | M22: =+L22/2 -> 4000 | O22: =VLOOKUP(C22,'[1]IP PITS'!$B$6:$I$87,8,0) -> 0 | P22: =+G22+H22+I22 -> 225 | Q22: =(VLOOKUP(C22,'IP PITSS'!$B$9:$M$90,10,0))+(VLOOKUP(C22,'IP PITSS'!$B$9:$M$90,11,0))+(VLOOKUP(C22,'IP PITSS'!$B$9:$M$90,12,0)) -> 0 | R22: =VLOOKUP(C22,'IP PITSS'!$B$9:$Q$90,17,0) -> #REF! | S22: =VLOOKUP(C22,'IP PITSS'!$B$9:$R$90,18,0) -> #REF! | U22: =+K22-O22-P22+Q22+R22+S22 -> #REF! | V22: =+M22-U22 -> #REF! | X22: SEI0014 | Y22: =IFERROR(OFFSET('CPD PITSS'!$AN$8,MATCH('RESUMEN PITS'!C22,'CPD PITSS'!$B$9:$B$26,0),0),0)+IFERROR(OFFSET('IP PITSS'!$AL$8,MATCH('RESUMEN PITS'!C22,'IP PITSS'!$B$9:$B$90,0),0),0)+IFERROR(OFFSET('SIND PITS'!$Q$2,MATCH('RESUMEN PITS'!C22,'SIND PITS'!$C$3:$C$103,0),0),0) -> 5778.821
A23: SEI0017 | B23: IP INNOVACION | C23: Muñoz Reyes Luis Eduardo | D23: =VLOOKUP(C23,'IP PITSS'!$B$9:$U$90,21,0) -> #REF! | F23: =VLOOKUP(C23,'SIND PITS'!$C$3:$D$100,2,0) -> 414.64 | G23: =VLOOKUP(C23,'SIND PITS'!$C$3:$E$100,3,0) -> 200 | H23: =VLOOKUP(C23,'SIND PITS'!$C$3:$F$100,4,0) -> 0 | I23: =VLOOKUP(C23,'SIND PITS'!$C$3:$G$100,5,0) -> 0 | K23: =SUM(D23:I23) -> #REF! | L23: 8000 | M23: =+L23/2 -> 4000 | O23: =VLOOKUP(C23,'[1]IP PITS'!$B$6:$I$87,8,0) -> 0 | P23: =+G23+H23+I23 -> 200 | Q23: =(VLOOKUP(C23,'IP PITSS'!$B$9:$M$90,10,0))+(VLOOKUP(C23,'IP PITSS'!$B$9:$M$90,11,0))+(VLOOKUP(C23,'IP PITSS'!$B$9:$M$90,12,0)) -> 864.56 | R23: =VLOOKUP(C23,'IP PITSS'!$B$9:$Q$90,17,0) -> #REF! | S23: =VLOOKUP(C23,'IP PITSS'!$B$9:$R$90,18,0) -> #REF! | U23: =+K23-O23-P23+Q23+R23+S23 -> #REF! | V23: =+M23-U23 -> #REF! | X23: SEI0017 | Y23: =IFERROR(OFFSET('CPD PITSS'!$AN$8,MATCH('RESUMEN PITS'!C23,'CPD PITSS'!$B$9:$B$26,0),0),0)+IFERROR(OFFSET('IP PITSS'!$AL$8,MATCH('RESUMEN PITS'!C23,'IP PITSS'!$B$9:$B$90,0),0),0)+IFERROR(OFFSET('SIND PITS'!$Q$2,MATCH('RESUMEN PITS'!C23,'SIND PITS'!$C$3:$C$103,0),0),0) -> 5753.321
A24: SEI0019 | B24: IP INNOVACION | C24: Gonzalez Rasgado Miguel Isaias | D24: =VLOOKUP(C24,'IP PITSS'!$B$9:$U$90,21,0) -> #REF! | F24: =VLOOKUP(C24,'SIND PITS'!$C$3:$D$100,2,0) -> 1367.3 | G24: =VLOOKUP(C24,'SIND PITS'!$C$3:$E$100,3,0) -> 390.63 | H24: =VLOOKUP(C24,'SIND PITS'!$C$3:$F$100,4,0) -> 0 | I24: =VLOOKUP(C24,'SIND PITS'!$C$3:$G$100,5,0) -> 0 | K24: =SUM(D24:I24) -> #REF! | L24: 13125 | M24: =+L24/2 -> 6562.5 | O24: =VLOOKUP(C24,'[1]IP PITS'!$B$6:$I$87,8,0) -> 0 | P24: =+G24+H24+I24 -> 390.63 | Q24: =(VLOOKUP(C24,'IP PITSS'!$B$9:$M$90,10,0))+(VLOOKUP(C24,'IP PITSS'!$B$9:$M$90,11,0))+(VLOOKUP(C24,'IP PITSS'!$B$9:$M$90,12,0)) -> 0 | R24: =VLOOKUP(C24,'IP PITSS'!$B$9:$Q$90,17,0) -> #REF! | S24: =VLOOKUP(C24,'IP PITSS'!$B$9:$R$90,18,0) -> #REF! | U24: =+K24-O24-P24+Q24+R24+S24 -> #REF! | V24: =+M24-U24 -> #REF! | X24: SEI0019 | Y24: =IFERROR(OFFSET('CPD PITSS'!$AN$8,MATCH('RESUMEN PITS'!C24,'CPD PITSS'!$B$9:$B$26,0),0),0)+IFERROR(OFFSET('IP PITSS'!$AL$8,MATCH('RESUMEN PITS'!C24,'IP PITSS'!$B$9:$B$90,0),0),0)+IFERROR(OFFSET('SIND PITS'!$Q$2,MATCH('RESUMEN PITS'!C24,'SIND PITS'!$C$3:$C$103,0),0),0) -> 9023.1226
A25: SEI0020 | B25: IP INNOVACION | C25: Mar Marquez Cesar Eduardo | D25: =VLOOKUP(C25,'IP PITSS'!$B$9:$U$90,21,0) -> #REF! | F25: =VLOOKUP(C25,'SIND PITS'!$C$3:$D$100,2,0) -> 414.6 | G25: =VLOOKUP(C25,'SIND PITS'!$C$3:$E$100,3,0) -> 165 | H25: =VLOOKUP(C25,'SIND PITS'!$C$3:$F$100,4,0) -> 0 | I25: =VLOOKUP(C25,'SIND PITS'!$C$3:$G$100,5,0) -> 0 | K25: =SUM(D25:I25) -> #REF! | L25: 8000 | M25: =+L25/2 -> 4000 | O25: =VLOOKUP(C25,'[1]IP PITS'!$B$6:$I$87,8,0) -> 0 | P25: =+G25+H25+I25 -> 165 | Q25: =(VLOOKUP(C25,'IP PITSS'!$B$9:$M$90,10,0))+(VLOOKUP(C25,'IP PITSS'!$B$9:$M$90,11,0))+(VLOOKUP(C25,'IP PITSS'!$B$9:$M$90,12,0)) -> 0 | R25: =VLOOKUP(C25,'IP PITSS'!$B$9:$Q$90,17,0) -> #REF! | S25: =VLOOKUP(C25,'IP PITSS'!$B$9:$R$90,18,0) -> #REF! | U25: =+K25-O25-P25+Q25+R25+S25 -> #REF! | V25: =+M25-U25 -> #REF! | X25: SEI0020 | Y25: =IFERROR(OFFSET('CPD PITSS'!$AN$8,MATCH('RESUMEN PITS'!C25,'CPD PITSS'!$B$9:$B$26,0),0),0)+IFERROR(OFFSET('IP PITSS'!$AL$8,MATCH('RESUMEN PITS'!C25,'IP PITSS'!$B$9:$B$90,0),0),0)+IFERROR(OFFSET('SIND PITS'!$Q$2,MATCH('RESUMEN PITS'!C25,'SIND PITS'!$C$3:$C$103,0),0),0) -> 5717.621
A26: SEI0021 | B26: IP INNOVACION | C26: Velez Rodriguez Jaime | D26: =VLOOKUP(C26,'IP PITSS'!$B$9:$U$90,21,0) -> #REF! | F26: =VLOOKUP(C26,'SIND PITS'!$C$3:$D$100,2,0) -> 1135.19 | G26: =VLOOKUP(C26,'SIND PITS'!$C$3:$E$100,3,0) -> 0 | H26: =VLOOKUP(C26,'SIND PITS'!$C$3:$F$100,4,0) -> 0 | I26: =VLOOKUP(C26,'SIND PITS'!$C$3:$G$100,5,0) -> 0 | K26: =SUM(D26:I26) -> #REF! | L26: 8000 | M26: =+L26/2 -> 4000 | O26: =VLOOKUP(C26,'[1]IP PITS'!$B$6:$I$87,8,0) -> 0 | P26: =+G26+H26+I26 -> 0 | Q26: =(VLOOKUP(C26,'IP PITSS'!$B$9:$M$90,10,0))+(VLOOKUP(C26,'IP PITSS'!$B$9:$M$90,11,0))+(VLOOKUP(C26,'IP PITSS'!$B$9:$M$90,12,0)) -> 1332.81 | R26: =VLOOKUP(C26,'IP PITSS'!$B$9:$Q$90,17,0) -> #REF! | S26: =VLOOKUP(C26,'IP PITSS'!$B$9:$R$90,18,0) -> #REF! | U26: =+K26-O26-P26+Q26+R26+S26 -> #REF! | V26: =+M26-U26 -> #REF! | X26: SEI0021 | Y26: =IFERROR(OFFSET('CPD PITSS'!$AN$8,MATCH('RESUMEN PITS'!C26,'CPD PITSS'!$B$9:$B$26,0),0),0)+IFERROR(OFFSET('IP PITSS'!$AL$8,MATCH('RESUMEN PITS'!C26,'IP PITSS'!$B$9:$B$90,0),0),0)+IFERROR(OFFSET('SIND PITS'!$Q$2,MATCH('RESUMEN PITS'!C26,'SIND PITS'!$C$3:$C$103,0),0),0) -> 5345.54
A27: SEI0022 | B27: IP INNOVACION | C27: Najera Lopez Raul | D27: =VLOOKUP(C27,'IP PITSS'!$B$9:$U$90,21,0) -> #REF! | F27: =VLOOKUP(C27,'SIND PITS'!$C$3:$D$100,2,0) -> 593.6 | G27: =VLOOKUP(C27,'SIND PITS'!$C$3:$E$100,3,0) -> 90 | H27: =VLOOKUP(C27,'SIND PITS'!$C$3:$F$100,4,0) -> 1440 | I27: =VLOOKUP(C27,'SIND PITS'!$C$3:$G$100,5,0) -> 0 | K27: =SUM(D27:I27) -> #REF! | L27: 10000 | M27: =+L27/2 -> 5000 | O27: =VLOOKUP(C27,'[1]IP PITS'!$B$6:$I$87,8,0) -> 0 | P27: =+G27+H27+I27 -> 1530 | Q27: =(VLOOKUP(C27,'IP PITSS'!$B$9:$M$90,10,0))+(VLOOKUP(C27,'IP PITSS'!$B$9:$M$90,11,0))+(VLOOKUP(C27,'IP PITSS'!$B$9:$M$90,12,0)) -> 0 | R27: =VLOOKUP(C27,'IP PITSS'!$B$9:$Q$90,17,0) -> #REF! | S27: =VLOOKUP(C27,'IP PITSS'!$B$9:$R$90,18,0) -> #REF! | U27: =+K27-O27-P27+Q27+R27+S27 -> #REF! | V27: =+M27-U27 -> #REF! | X27: SEI0022 | Y27: =IFERROR(OFFSET('CPD PITSS'!$AN$8,MATCH('RESUMEN PITS'!C27,'CPD PITSS'!$B$9:$B$26,0),0),0)+IFERROR(OFFSET('IP PITSS'!$AL$8,MATCH('RESUMEN PITS'!C27,'IP PITSS'!$B$9:$B$90,0),0),0)+IFERROR(OFFSET('SIND PITS'!$Q$2,MATCH('RESUMEN PITS'!C27,'SIND PITS'!$C$3:$C$103,0),0),0) -> 8366.619
A28: SEI0023 | B28: IP INNOVACION | C28: Puente Murguia Luis Felipe | D28: =VLOOKUP(C28,'IP PITSS'!$B$9:$U$90,21,0) -> #REF! | F28: =VLOOKUP(C28,'SIND PITS'!$C$3:$D$100,2,0) -> 222.6 | G28: =VLOOKUP(C28,'SIND PITS'!$C$3:$E$100,3,0) -> 75 | H28: =VLOOKUP(C28,'SIND PITS'!$C$3:$F$100,4,0) -> 0 | I28: =VLOOKUP(C28,'SIND PITS'!$C$3:$G$100,5,0) -> 0 | K28: =SUM(D28:I28) -> #REF! | L28: 7000 | M28: =+L28/2 -> 3500 | O28: =VLOOKUP(C28,'[1]IP PITS'!$B$6:$I$87,8,0) -> 0 | P28: =+G28+H28+I28 -> 75 | Q28: =(VLOOKUP(C28,'IP PITSS'!$B$9:$M$90,10,0))+(VLOOKUP(C28,'IP PITSS'!$B$9:$M$90,11,0))+(VLOOKUP(C28,'IP PITSS'!$B$9:$M$90,12,0)) -> 0 | R28: =VLOOKUP(C28,'IP PITSS'!$B$9:$Q$90,17,0) -> #REF! | S28: =VLOOKUP(C28,'IP PITSS'!$B$9:$R$90,18,0) -> #REF! | U28: =+K28-O28-P28+Q28+R28+S28 -> #REF! | V28: =+M28-U28 -> #REF! | X28: SEI0023 | Y28: =IFERROR(OFFSET('CPD PITSS'!$AN$8,MATCH('RESUMEN PITS'!C28,'CPD PITSS'!$B$9:$B$26,0),0),0)+IFERROR(OFFSET('IP PITSS'!$AL$8,MATCH('RESUMEN PITS'!C28,'IP PITSS'!$B$9:$B$90,0),0),0)+IFERROR(OFFSET('SIND PITS'!$Q$2,MATCH('RESUMEN PITS'!C28,'SIND PITS'!$C$3:$C$103,0),0),0) -> 5016.519
A29: SEI0029 | B29: IP INNOVACION | C29: Arceo Garcia Manuel Federico | D29: =VLOOKUP(C29,'IP PITSS'!$B$9:$U$90,21,0) -> #REF! | F29: =VLOOKUP(C29,'SIND PITS'!$C$3:$D$100,2,0) -> 255.2 | G29: =VLOOKUP(C29,'SIND PITS'!$C$3:$E$100,3,0) -> 455 | H29: =VLOOKUP(C29,'SIND PITS'!$C$3:$F$100,4,0) -> 0 | I29: =VLOOKUP(C29,'SIND PITS'!$C$3:$G$100,5,0) -> 0 | K29: =SUM(D29:I29) -> #REF! | L29: 6000 | M29: =+L29/2 -> 3000 | O29: =VLOOKUP(C29,'[1]IP PITS'!$B$6:$I$87,8,0) -> 180 | P29: =+G29+H29+I29 -> 455 | Q29: =(VLOOKUP(C29,'IP PITSS'!$B$9:$M$90,10,0))+(VLOOKUP(C29,'IP PITSS'!$B$9:$M$90,11,0))+(VLOOKUP(C29,'IP PITSS'!$B$9:$M$90,12,0)) -> 0 | R29: =VLOOKUP(C29,'IP PITSS'!$B$9:$Q$90,17,0) -> #REF! | S29: =VLOOKUP(C29,'IP PITSS'!$B$9:$R$90,18,0) -> #REF! | U29: =+K29-O29-P29+Q29+R29+S29 -> #REF! | V29: =+M29-U29 -> #REF! | X29: SEI0029 | Y29: =IFERROR(OFFSET('CPD PITSS'!$AN$8,MATCH('RESUMEN PITS'!C29,'CPD PITSS'!$B$9:$B$26,0),0),0)+IFERROR(OFFSET('IP PITSS'!$AL$8,MATCH('RESUMEN PITS'!C29,'IP PITSS'!$B$9:$B$90,0),0),0)+IFERROR(OFFSET('SIND PITS'!$Q$2,MATCH('RESUMEN PITS'!C29,'SIND PITS'!$C$3:$C$103,0),0),0) -> 4974.44
A30: SEI0364 | B30: IP INNOVACION | C30: Dominguez Lopez Mayeli Del Pilar | D30: =VLOOKUP(C30,'IP PITSS'!$B$9:$U$90,21,0) -> #REF! | F30: =VLOOKUP(C30,'SIND PITS'!$C$3:$D$100,2,0) -> 1416.2 | G30: =VLOOKUP(C30,'SIND PITS'!$C$3:$E$100,3,0) -> 718.75 | H30: =VLOOKUP(C30,'SIND PITS'!$C$3:$F$100,4,0) -> 0 | I30: =VLOOKUP(C30,'SIND PITS'!$C$3:$G$100,5,0) -> 0 | K30: =SUM(D30:I30) -> #REF! | L30: 10000 | M30: =+L30/2 -> 5000 | O30: =VLOOKUP(C30,'[1]IP PITS'!$B$6:$I$87,8,0) -> 0 | P30: =+G30+H30+I30 -> 718.75 | Q30: =(VLOOKUP(C30,'IP PITSS'!$B$9:$M$90,10,0))+(VLOOKUP(C30,'IP PITSS'!$B$9:$M$90,11,0))+(VLOOKUP(C30,'IP PITSS'!$B$9:$M$90,12,0)) -> 0 | R30: =VLOOKUP(C30,'IP PITSS'!$B$9:$Q$90,17,0) -> #REF! | S30: =VLOOKUP(C30,'IP PITSS'!$B$9:$R$90,18,0) -> #REF! | U30: =+K30-O30-P30+Q30+R30+S30 -> #REF! | V30: =+M30-U30 -> #REF! | X30: SEI0364 | Y30: =IFERROR(OFFSET('CPD PITSS'!$AN$8,MATCH('RESUMEN PITS'!C30,'CPD PITSS'!$B$9:$B$26,0),0),0)+IFERROR(OFFSET('IP PITSS'!$AL$8,MATCH('RESUMEN PITS'!C30,'IP PITSS'!$B$9:$B$90,0),0),0)+IFERROR(OFFSET('SIND PITS'!$Q$2,MATCH('RESUMEN PITS'!C30,'SIND PITS'!$C$3:$C$103,0),0),0) -> 7314.286
A31: SEI0413 | B31: IP INNOVACION | C31: Courtenay Gutierrez Barry Vladimir | D31: =VLOOKUP(C31,'IP PITSS'!$B$9:$U$90,21,0) -> #REF! | F31: =VLOOKUP(C31,'SIND PITS'!$C$3:$D$100,2,0) -> 52.35 | G31: =VLOOKUP(C31,'SIND PITS'!$C$3:$E$100,3,0) -> 250 | H31: =VLOOKUP(C31,'SIND PITS'!$C$3:$F$100,4,0) -> 0 | I31: =VLOOKUP(C31,'SIND PITS'!$C$3:$G$100,5,0) -> 0 | K31: =SUM(D31:I31) -> #REF! | L31: 5000 | M31: =+L31/2 -> 2500 | O31: =VLOOKUP(C31,'[1]IP PITS'!$B$6:$I$87,8,0) -> 0 | P31: =+G31+H31+I31 -> 250 | Q31: =(VLOOKUP(C31,'IP PITSS'!$B$9:$M$90,10,0))+(VLOOKUP(C31,'IP PITSS'!$B$9:$M$90,11,0))+(VLOOKUP(C31,'IP PITSS'!$B$9:$M$90,12,0)) -> 0 | R31: =VLOOKUP(C31,'IP PITSS'!$B$9:$Q$90,17,0) -> #REF! | S31: =VLOOKUP(C31,'IP PITSS'!$B$9:$R$90,18,0) -> #REF! | U31: =+K31-O31-P31+Q31+R31+S31 -> #REF! | V31: =+M31-U31 -> #REF! | X31: SEI0436 | Y31: =IFERROR(OFFSET('CPD PITSS'!$AN$8,MATCH('RESUMEN PITS'!C31,'CPD PITSS'!$B$9:$B$26,0),0),0)+IFERROR(OFFSET('IP PITSS'!$AL$8,MATCH('RESUMEN PITS'!C31,'IP PITSS'!$B$9:$B$90,0),0),0)+IFERROR(OFFSET('SIND PITS'!$Q$2,MATCH('RESUMEN PITS'!C31,'SIND PITS'!$C$3:$C$103,0),0),0) -> 3959.231
A32: SEI0421 | B32: IP INNOVACION | C32: Marin Avila Hector | D32: =VLOOKUP(C32,'IP PITSS'!$B$9:$U$90,21,0) -> #REF! | F32: =VLOOKUP(C32,'SIND PITS'!$C$3:$D$100,2,0) -> 706.8 | G32: =VLOOKUP(C32,'SIND PITS'!$C$3:$E$100,3,0) -> 500 | H32: =VLOOKUP(C32,'SIND PITS'!$C$3:$F$100,4,0) -> 0 | I32: =VLOOKUP(C32,'SIND PITS'!$C$3:$G$100,5,0) -> 0 | K32: =+D32+F32+G32+H32+I32 -> #REF! | L32: 8800 | M32: =+L32/2 -> 4400 | O32: =VLOOKUP(C32,'[1]IP PITS'!$B$6:$I$87,8,0) -> 0 | P32: =+G32+H32+I32 -> 500 | Q32: =(VLOOKUP(C32,'IP PITSS'!$B$9:$M$90,10,0))+(VLOOKUP(C32,'IP PITSS'!$B$9:$M$90,11,0))+(VLOOKUP(C32,'IP PITSS'!$B$9:$M$90,12,0)) -> 0 | R32: =VLOOKUP(C32,'IP PITSS'!$B$9:$Q$90,17,0) -> #REF! | S32: =VLOOKUP(C32,'IP PITSS'!$B$9:$R$90,18,0) -> #REF! | T32: =VLOOKUP(C32,'[2]IP SEITON'!$B$6:$R$31,17,0) -> #N/A | U32: =+K32-O32-P32+Q32+R32+S32 -> #REF! | V32: =+M32-U32 -> #REF! | Y32: =IFERROR(OFFSET('CPD PITSS'!$AN$8,MATCH('RESUMEN PITS'!C32,'CPD PITSS'!$B$9:$B$26,0),0),0)+IFERROR(OFFSET('IP PITSS'!$AL$8,MATCH('RESUMEN PITS'!C32,'IP PITSS'!$B$9:$B$90,0),0),0)+IFERROR(OFFSET('SIND PITS'!$Q$2,MATCH('RESUMEN PITS'!C32,'SIND PITS'!$C$3:$C$103,0),0),0) -> 6495.04
A33: SEI0424 | B33: IP INNOVACION | C33: Palacios Ramos Jesus | D33: =VLOOKUP(C33,'IP PITSS'!$B$9:$U$90,21,0) -> #REF! | F33: =VLOOKUP(C33,'SIND PITS'!$C$3:$D$100,2,0) -> 416.4 | G33: =VLOOKUP(C33,'SIND PITS'!$C$3:$E$100,3,0) -> 330 | H33: =VLOOKUP(C33,'SIND PITS'!$C$3:$F$100,4,0) -> 0 | I33: =VLOOKUP(C33,'SIND PITS'!$C$3:$G$100,5,0) -> 0 | K33: =SUM(D33:I33) -> #REF! | L33: 8000 | M33: =+L33/2 -> 4000 | O33: =VLOOKUP(C33,'[1]IP PITS'!$B$6:$I$87,8,0) -> 0 | P33: =+G33+H33+I33 -> 330 | Q33: =(VLOOKUP(C33,'IP PITSS'!$B$9:$M$90,10,0))+(VLOOKUP(C33,'IP PITSS'!$B$9:$M$90,11,0))+(VLOOKUP(C33,'IP PITSS'!$B$9:$M$90,12,0)) -> 0 | R33: =VLOOKUP(C33,'IP PITSS'!$B$9:$Q$90,17,0) -> #REF! | S33: =VLOOKUP(C33,'IP PITSS'!$B$9:$R$90,18,0) -> #REF! | U33: =+K33-O33-P33+Q33+R33+S33 -> #REF! | V33: =+M33-U33 -> #REF! | X33: SEI0424 | Y33: =IFERROR(OFFSET('CPD PITSS'!$AN$8,MATCH('RESUMEN PITS'!C33,'CPD PITSS'!$B$9:$B$26,0),0),0)+IFERROR(OFFSET('IP PITSS'!$AL$8,MATCH('RESUMEN PITS'!C33,'IP PITSS'!$B$9:$B$90,0),0),0)+IFERROR(OFFSET('SIND PITS'!$Q$2,MATCH('RESUMEN PITS'!C33,'SIND PITS'!$C$3:$C$103,0),0),0) -> 5897.761
A34: SEI0428 | B34: IP INNOVACION | C34: Martinez Hernandez J. Antonio | D34: =VLOOKUP(C34,'IP PITSS'!$B$9:$U$90,21,0) -> #REF! | F34: =VLOOKUP(C34,'SIND PITS'!$C$3:$D$100,2,0) -> 416.2 | G34: =VLOOKUP(C34,'SIND PITS'!$C$3:$E$100,3,0) -> 240 | H34: =VLOOKUP(C34,'SIND PITS'!$C$3:$F$100,4,0) -> 0 | I34: =VLOOKUP(C34,'SIND PITS'!$C$3:$G$100,5,0) -> 0 | K34: =SUM(D34:I34) -> #REF! | L34: 8000 | M34: =+L34/2 -> 4000 | O34: =VLOOKUP(C34,'[1]IP PITS'!$B$6:$I$87,8,0) -> 0 | P34: =+G34+H34+I34 -> 240 | Q34: =(VLOOKUP(C34,'IP PITSS'!$B$9:$M$90,10,0))+(VLOOKUP(C34,'IP PITSS'!$B$9:$M$90,11,0))+(VLOOKUP(C34,'IP PITSS'!$B$9:$M$90,12,0)) -> 0 | R34: =VLOOKUP(C34,'IP PITSS'!$B$9:$Q$90,17,0) -> #REF! | S34: =VLOOKUP(C34,'IP PITSS'!$B$9:$R$90,18,0) -> #REF! | U34: =+K34-O34-P34+Q34+R34+S34 -> #REF! | V34: =+M34-U34 -> #REF! | X34: SEI0452 | Y34: =IFERROR(OFFSET('CPD PITSS'!$AN$8,MATCH('RESUMEN PITS'!C34,'CPD PITSS'!$B$9:$B$26,0),0),0)+IFERROR(OFFSET('IP PITSS'!$AL$8,MATCH('RESUMEN PITS'!C34,'IP PITSS'!$B$9:$B$90,0),0),0)+IFERROR(OFFSET('SIND PITS'!$Q$2,MATCH('RESUMEN PITS'!C34,'SIND PITS'!$C$3:$C$103,0),0),0) -> 5805.961
A35: SEI0431 | B35: IP INNOVACION | C35: Alcaraz Conde Zabdi Guadalupe | D35: =VLOOKUP(C35,'IP PITSS'!$B$9:$U$90,21,0) -> #REF! | F35: =VLOOKUP(C35,'SIND PITS'!$C$3:$D$100,2,0) -> 135.14 | G35: =VLOOKUP(C35,'SIND PITS'!$C$3:$E$100,3,0) -> 455 | H35: =VLOOKUP(C35,'SIND PITS'!$C$3:$F$100,4,0) -> 0 | I35: =VLOOKUP(C35,'SIND PITS'!$C$3:$G$100,5,0) -> 0 | K35: =SUM(D35:I35) -> #REF! | L35: 6000 | M35: =+L35/2 -> 3000 | O35: =VLOOKUP(C35,'[1]IP PITS'!$B$6:$I$87,8,0) -> 0 | P35: =+G35+H35+I35 -> 455 | Q35: =(VLOOKUP(C35,'IP PITSS'!$B$9:$M$90,10,0))+(VLOOKUP(C35,'IP PITSS'!$B$9:$M$90,11,0))+(VLOOKUP(C35,'IP PITSS'!$B$9:$M$90,12,0)) -> 1078.66 | R35: =VLOOKUP(C35,'IP PITSS'!$B$9:$Q$90,17,0) -> #REF! | S35: =VLOOKUP(C35,'IP PITSS'!$B$9:$R$90,18,0) -> #REF! | U35: =+K35-O35-P35+Q35+R35+S35 -> #REF! | V35: =+M35-U35 -> #REF! | X35: SEI0456 | Y35: =IFERROR(OFFSET('CPD PITSS'!$AN$8,MATCH('RESUMEN PITS'!C35,'CPD PITSS'!$B$9:$B$26,0),0),0)+IFERROR(OFFSET('IP PITSS'!$AL$8,MATCH('RESUMEN PITS'!C35,'IP PITSS'!$B$9:$B$90,0),0),0)+IFERROR(OFFSET('SIND PITS'!$Q$2,MATCH('RESUMEN PITS'!C35,'SIND PITS'!$C$3:$C$103,0),0),0) -> 4789.65
A36: SEI0438 | B36: IP INNOVACION | C36: Lopez Terron Roberto Porfirio | D36: =VLOOKUP(C36,'IP PITSS'!$B$9:$U$90,21,0) -> #REF! | F36: =VLOOKUP(C36,'SIND PITS'!$C$3:$D$100,2,0) -> 1047.8 | G36: =VLOOKUP(C36,'SIND PITS'!$C$3:$E$100,3,0) -> 562.5 | H36: =VLOOKUP(C36,'SIND PITS'!$C$3:$F$100,4,0) -> 0 | I36: =VLOOKUP(C36,'SIND PITS'!$C$3:$G$100,5,0) -> 0 | K36: =SUM(D36:I36) -> #REF! | L36: 14000 | M36: =+L36/2 -> 7000 | O36: =VLOOKUP(C36,'[1]IP PITS'!$B$6:$I$87,8,0) -> 0 | P36: =+G36+H36+I36 -> 562.5 | Q36: =(VLOOKUP(C36,'IP PITSS'!$B$9:$M$90,10,0))+(VLOOKUP(C36,'IP PITSS'!$B$9:$M$90,11,0))+(VLOOKUP(C36,'IP PITSS'!$B$9:$M$90,12,0)) -> 0 | R36: =VLOOKUP(C36,'IP PITSS'!$B$9:$Q$90,17,0) -> #REF! | S36: =VLOOKUP(C36,'IP PITSS'!$B$9:$R$90,18,0) -> #REF! | U36: =+K36-O36-P36+Q36+R36+S36 -> #REF! | V36: =+M36-U36 -> #REF! | W36: incapacidad 5 dias | X36: SEI0463 | Y36: =IFERROR(OFFSET('CPD PITSS'!$AN$8,MATCH('RESUMEN PITS'!C36,'CPD PITSS'!$B$9:$B$26,0),0),0)+IFERROR(OFFSET('IP PITSS'!$AL$8,MATCH('RESUMEN PITS'!C36,'IP PITSS'!$B$9:$B$90,0),0),0)+IFERROR(OFFSET('SIND PITS'!$Q$2,MATCH('RESUMEN PITS'!C36,'SIND PITS'!$C$3:$C$103,0),0),0) -> 9869.681
A37: SEI0442 | B37: IP INNOVACION | C37: Chavez Pedraza Samuel | D37: =VLOOKUP(C37,'IP PITSS'!$B$9:$U$90,21,0) -> #REF! | F37: =VLOOKUP(C37,'SIND PITS'!$C$3:$D$100,2,0) -> 1047.8 | G37: =VLOOKUP(C37,'SIND PITS'!$C$3:$E$100,3,0) -> 687.5 | H37: =VLOOKUP(C37,'SIND PITS'!$C$3:$F$100,4,0) -> 0 | I37: =VLOOKUP(C37,'SIND PITS'!$C$3:$G$100,5,0) -> 0 | K37: =SUM(D37:I37) -> #REF! | L37: 14000 | M37: =+L37/2 -> 7000 | O37: =VLOOKUP(C37,'[1]IP PITS'!$B$6:$I$87,8,0) -> 0 | P37: =+G37+H37+I37 -> 687.5 | Q37: =(VLOOKUP(C37,'IP PITSS'!$B$9:$M$90,10,0))+(VLOOKUP(C37,'IP PITSS'!$B$9:$M$90,11,0))+(VLOOKUP(C37,'IP PITSS'!$B$9:$M$90,12,0)) -> 0 | R37: =VLOOKUP(C37,'IP PITSS'!$B$9:$Q$90,17,0) -> #REF! | S37: =VLOOKUP(C37,'IP PITSS'!$B$9:$R$90,18,0) -> #REF! | U37: =+K37-O37-P37+Q37+R37+S37 -> #REF! | V37: =+M37-U37 -> #REF! | X37: SEI0467 | Y37: =IFERROR(OFFSET('CPD PITSS'!$AN$8,MATCH('RESUMEN PITS'!C37,'CPD PITSS'!$B$9:$B$26,0),0),0)+IFERROR(OFFSET('IP PITSS'!$AL$8,MATCH('RESUMEN PITS'!C37,'IP PITSS'!$B$9:$B$90,0),0),0)+IFERROR(OFFSET('SIND PITS'!$Q$2,MATCH('RESUMEN PITS'!C37,'SIND PITS'!$C$3:$C$103,0),0),0) -> 9997.181
A38: SEI0443 | B38: IP INNOVACION | C38: Castillo Nungaray Nestor Roman | D38: =VLOOKUP(C38,'IP PITSS'!$B$9:$U$90,21,0) -> #REF! | F38: =VLOOKUP(C38,'SIND PITS'!$C$3:$D$100,2,0) -> 135.2 | G38: =VLOOKUP(C38,'SIND PITS'!$C$3:$E$100,3,0) -> 450 | H38: =VLOOKUP(C38,'SIND PITS'!$C$3:$F$100,4,0) -> 0 | I38: =VLOOKUP(C38,'SIND PITS'!$C$3:$G$100,5,0) -> 0 | K38: =SUM(D38:I38) -> #REF! | L38: 6000 | M38: =+L38/2 -> 3000 | O38: =VLOOKUP(C38,'[1]IP PITS'!$B$6:$I$87,8,0) -> 0 | P38: =+G38+H38+I38 -> 450 | Q38: =(VLOOKUP(C38,'IP PITSS'!$B$9:$M$90,10,0))+(VLOOKUP(C38,'IP PITSS'!$B$9:$M$90,11,0))+(VLOOKUP(C38,'IP PITSS'!$B$9:$M$90,12,0)) -> 0 | R38: =VLOOKUP(C38,'IP PITSS'!$B$9:$Q$90,17,0) -> #REF! | S38: =VLOOKUP(C38,'IP PITSS'!$B$9:$R$90,18,0) -> #REF! | U38: =+K38-O38-P38+Q38+R38+S38 -> #REF! | V38: =+M38-U38 -> #REF! | X38: SEI0468 | Y38: =IFERROR(OFFSET('CPD PITSS'!$AN$8,MATCH('RESUMEN PITS'!C38,'CPD PITSS'!$B$9:$B$26,0),0),0)+IFERROR(OFFSET('IP PITSS'!$AL$8,MATCH('RESUMEN PITS'!C38,'IP PITSS'!$B$9:$B$90,0),0),0)+IFERROR(OFFSET('SIND PITS'!$Q$2,MATCH('RESUMEN PITS'!C38,'SIND PITS'!$C$3:$C$103,0),0),0) -> 4784.55
A39: SEI0444 | B39: IP INNOVACION | C39: Marquez Hernandez Rogelio | D39: =VLOOKUP(C39,'IP PITSS'!$B$9:$U$90,21,0) -> #REF! | F39: =VLOOKUP(C39,'SIND PITS'!$C$3:$D$100,2,0) -> 416.4 | G39: =VLOOKUP(C39,'SIND PITS'!$C$3:$E$100,3,0) -> 120 | H39: =VLOOKUP(C39,'SIND PITS'!$C$3:$F$100,4,0) -> 0 | I39: =VLOOKUP(C39,'SIND PITS'!$C$3:$G$100,5,0) -> 0 | K39: =SUM(D39:I39) -> #REF! | L39: 8000 | M39: =+L39/2 -> 4000 | O39: =VLOOKUP(C39,'[1]IP PITS'!$B$6:$I$87,8,0) -> 0 | P39: =+G39+H39+I39 -> 120 | Q39: =(VLOOKUP(C39,'IP PITSS'!$B$9:$M$90,10,0))+(VLOOKUP(C39,'IP PITSS'!$B$9:$M$90,11,0))+(VLOOKUP(C39,'IP PITSS'!$B$9:$M$90,12,0)) -> 0 | R39: =VLOOKUP(C39,'IP PITSS'!$B$9:$Q$90,17,0) -> #REF! | S39: =VLOOKUP(C39,'IP PITSS'!$B$9:$R$90,18,0) -> #REF! | U39: =+K39-O39-P39+Q39+R39+S39 -> #REF! | V39: =+M39-U39 -> #REF! | X39: SEI0469 | Y39: =IFERROR(OFFSET('CPD PITSS'!$AN$8,MATCH('RESUMEN PITS'!C39,'CPD PITSS'!$B$9:$B$26,0),0),0)+IFERROR(OFFSET('IP PITSS'!$AL$8,MATCH('RESUMEN PITS'!C39,'IP PITSS'!$B$9:$B$90,0),0),0)+IFERROR(OFFSET('SIND PITS'!$Q$2,MATCH('RESUMEN PITS'!C39,'SIND PITS'!$C$3:$C$103,0),0),0) -> 5683.561
A40: SEI0449 | B40: IP INNOVACION | C40: Flores Cerrillos Jorge Humberto | D40: =VLOOKUP(C40,'IP PITSS'!$B$9:$U$90,21,0) -> #REF! | F40: =VLOOKUP(C40,'SIND PITS'!$C$3:$D$100,2,0) -> 416.2 | G40: =VLOOKUP(C40,'SIND PITS'!$C$3:$E$100,3,0) -> 130 | H40: =VLOOKUP(C40,'SIND PITS'!$C$3:$F$100,4,0) -> 0 | I40: =VLOOKUP(C40,'SIND PITS'!$C$3:$G$100,5,0) -> 0 | K40: =SUM(D40:I40) -> #REF! | L40: 8000 | M40: =+L40/2 -> 4000 | O40: =VLOOKUP(C40,'[1]IP PITS'!$B$6:$I$87,8,0) -> 0 | P40: =+G40+H40+I40 -> 130 | Q40: =(VLOOKUP(C40,'IP PITSS'!$B$9:$M$90,10,0))+(VLOOKUP(C40,'IP PITSS'!$B$9:$M$90,11,0))+(VLOOKUP(C40,'IP PITSS'!$B$9:$M$90,12,0)) -> 0 | R40: =VLOOKUP(C40,'IP PITSS'!$B$9:$Q$90,17,0) -> #REF! | S40: =VLOOKUP(C40,'IP PITSS'!$B$9:$R$90,18,0) -> #REF! | U40: =+K40-O40-P40+Q40+R40+S40 -> #REF! | V40: =+M40-U40 -> #REF! | X40: SEI0474 | Y40: =IFERROR(OFFSET('CPD PITSS'!$AN$8,MATCH('RESUMEN PITS'!C40,'CPD PITSS'!$B$9:$B$26,0),0),0)+IFERROR(OFFSET('IP PITSS'!$AL$8,MATCH('RESUMEN PITS'!C40,'IP PITSS'!$B$9:$B$90,0),0),0)+IFERROR(OFFSET('SIND PITS'!$Q$2,MATCH('RESUMEN PITS'!C40,'SIND PITS'!$C$3:$C$103,0),0),0) -> 5693.761
A41: SEI0455 | B41: IP INNOVACION | C41: Perez Garcia Andres Alvaro | D41: =VLOOKUP(C41,'IP PITSS'!$B$9:$U$90,21,0) -> #REF! | F41: =VLOOKUP(C41,'SIND PITS'!$C$3:$D$100,2,0) -> 416.4 | G41: =VLOOKUP(C41,'SIND PITS'!$C$3:$E$100,3,0) -> 60 | H41: =VLOOKUP(C41,'SIND PITS'!$C$3:$F$100,4,0) -> 0 | I41: =VLOOKUP(C41,'SIND PITS'!$C$3:$G$100,5,0) -> 0 | K41: =SUM(D41:I41) -> #REF! | L41: 8000 | M41: =+L41/2 -> 4000 | O41: =VLOOKUP(C41,'[1]IP PITS'!$B$6:$I$87,8,0) -> 0 | P41: =+G41+H41+I41 -> 60 | Q41: =(VLOOKUP(C41,'IP PITSS'!$B$9:$M$90,10,0))+(VLOOKUP(C41,'IP PITSS'!$B$9:$M$90,11,0))+(VLOOKUP(C41,'IP PITSS'!$B$9:$M$90,12,0)) -> 0 | R41: =VLOOKUP(C41,'IP PITSS'!$B$9:$Q$90,17,0) -> #REF! | S41: =VLOOKUP(C41,'IP PITSS'!$B$9:$R$90,18,0) -> #REF! | U41: =+K41-O41-P41+Q41+R41+S41 -> #REF! | V41: =+M41-U41 -> #REF! | X41: SEI0494 | Y41: =IFERROR(OFFSET('CPD PITSS'!$AN$8,MATCH('RESUMEN PITS'!C41,'CPD PITSS'!$B$9:$B$26,0),0),0)+IFERROR(OFFSET('IP PITSS'!$AL$8,MATCH('RESUMEN PITS'!C41,'IP PITSS'!$B$9:$B$90,0),0),0)+IFERROR(OFFSET('SIND PITS'!$Q$2,MATCH('RESUMEN PITS'!C41,'SIND PITS'!$C$3:$C$103,0),0),0) -> 5622.36
A42: SEI0456 | B42: IP INNOVACION | C42: Chavira Garcia David Fernando | D42: =VLOOKUP(C42,'IP PITSS'!$B$9:$U$90,21,0) -> #REF! | F42: =VLOOKUP(C42,'SIND PITS'!$C$3:$D$100,2,0) -> 593.6 | G42: =VLOOKUP(C42,'SIND PITS'!$C$3:$E$100,3,0) -> 110 | H42: =VLOOKUP(C42,'SIND PITS'!$C$3:$F$100,4,0) -> 0 | I42: =VLOOKUP(C42,'SIND PITS'!$C$3:$G$100,5,0) -> 0 | K42: =SUM(D42:I42) -> #REF! | L42: 10000 | M42: =+L42/2 -> 5000 | O42: =VLOOKUP(C42,'[1]IP PITS'!$B$6:$I$87,8,0) -> 0 | P42: =+G42+H42+I42 -> 110 | Q42: =(VLOOKUP(C42,'IP PITSS'!$B$9:$M$90,10,0))+(VLOOKUP(C42,'IP PITSS'!$B$9:$M$90,11,0))+(VLOOKUP(C42,'IP PITSS'!$B$9:$M$90,12,0)) -> 0 | R42: =VLOOKUP(C42,'IP PITSS'!$B$9:$Q$90,17,0) -> #REF! | S42: =VLOOKUP(C42,'IP PITSS'!$B$9:$R$90,18,0) -> #REF! | U42: =+K42-O42-P42+Q42+R42+S42 -> #REF! | V42: =+M42-U42 -> #REF! | X42: SEI0495 | Y42: =IFERROR(OFFSET('CPD PITSS'!$AN$8,MATCH('RESUMEN PITS'!C42,'CPD PITSS'!$B$9:$B$26,0),0),0)+IFERROR(OFFSET('IP PITSS'!$AL$8,MATCH('RESUMEN PITS'!C42,'IP PITSS'!$B$9:$B$90,0),0),0)+IFERROR(OFFSET('SIND PITS'!$Q$2,MATCH('RESUMEN PITS'!C42,'SIND PITS'!$C$3:$C$103,0),0),0) -> 6918.3
A43: SEI0457 | B43: IP INNOVACION | C43: Guerrero Lara Cesar Adrian | D43: =VLOOKUP(C43,'IP PITSS'!$B$9:$U$90,21,0) -> #REF! | F43: =VLOOKUP(C43,'SIND PITS'!$C$3:$D$100,2,0) -> 416.35 | G43: =VLOOKUP(C43,'SIND PITS'!$C$3:$E$100,3,0) -> 275 | H43: =VLOOKUP(C43,'SIND PITS'!$C$3:$F$100,4,0) -> 0 | I43: =VLOOKUP(C43,'SIND PITS'!$C$3:$G$100,5,0) -> 0 | K43: =SUM(D43:I43) -> #REF! | L43: 8000 | M43: =+L43/2 -> 4000 | O43: =VLOOKUP(C43,'[1]IP PITS'!$B$6:$I$87,8,0) -> 0 | P43: =+G43+H43+I43 -> 275 | Q43: =(VLOOKUP(C43,'IP PITSS'!$B$9:$M$90,10,0))+(VLOOKUP(C43,'IP PITSS'!$B$9:$M$90,11,0))+(VLOOKUP(C43,'IP PITSS'!$B$9:$M$90,12,0)) -> 0 | R43: =VLOOKUP(C43,'IP PITSS'!$B$9:$Q$90,17,0) -> #REF! | S43: =VLOOKUP(C43,'IP PITSS'!$B$9:$R$90,18,0) -> #REF! | U43: =+K43-O43-P43+Q43+R43+S43 -> #REF! | V43: =+M43-U43 -> #REF! | X43: SEI0496 | Y43: =IFERROR(OFFSET('CPD PITSS'!$AN$8,MATCH('RESUMEN PITS'!C43,'CPD PITSS'!$B$9:$B$26,0),0),0)+IFERROR(OFFSET('IP PITSS'!$AL$8,MATCH('RESUMEN PITS'!C43,'IP PITSS'!$B$9:$B$90,0),0),0)+IFERROR(OFFSET('SIND PITS'!$Q$2,MATCH('RESUMEN PITS'!C43,'SIND PITS'!$C$3:$C$103,0),0),0) -> 5841.66
A44: SEI0458 | B44: IP INNOVACION | C44: Martinez Zamora Gerardo Mario | D44: =VLOOKUP(C44,'IP PITSS'!$B$9:$U$90,21,0) -> #REF! | F44: =VLOOKUP(C44,'SIND PITS'!$C$3:$D$100,2,0) -> 549.815 | G44: =VLOOKUP(C44,'SIND PITS'!$C$3:$E$100,3,0) -> 625 | H44: =VLOOKUP(C44,'SIND PITS'!$C$3:$F$100,4,0) -> 0 | I44: =VLOOKUP(C44,'SIND PITS'!$C$3:$G$100,5,0) -> 0 | K44: =SUM(D44:I44) -> #REF! | L44: 9550.01 | M44: =+L44/2 -> 4775.005 | O44: =VLOOKUP(C44,'[1]IP PITS'!$B$6:$I$87,8,0) -> 0 | P44: =+G44+H44+I44 -> 625 | Q44: =(VLOOKUP(C44,'IP PITSS'!$B$9:$M$90,10,0))+(VLOOKUP(C44,'IP PITSS'!$B$9:$M$90,11,0))+(VLOOKUP(C44,'IP PITSS'!$B$9:$M$90,12,0)) -> 1497.39 | R44: =VLOOKUP(C44,'IP PITSS'!$B$9:$Q$90,17,0) -> #REF! | S44: =VLOOKUP(C44,'IP PITSS'!$B$9:$R$90,18,0) -> #REF! | U44: =+K44-O44-P44+Q44+R44+S44 -> #REF! | V44: =+M44-U44 -> #REF! | X44: SEI0497 | Y44: =IFERROR(OFFSET('CPD PITSS'!$AN$8,MATCH('RESUMEN PITS'!C44,'CPD PITSS'!$B$9:$B$26,0),0),0)+IFERROR(OFFSET('IP PITSS'!$AL$8,MATCH('RESUMEN PITS'!C44,'IP PITSS'!$B$9:$B$90,0),0),0)+IFERROR(OFFSET('SIND PITS'!$Q$2,MATCH('RESUMEN PITS'!C44,'SIND PITS'!$C$3:$C$103,0),0),0) -> 7163.4751
A45: SEI0460 | B45: IP INNOVACION | C45: Castellon Ramos Rene | D45: =VLOOKUP(C45,'IP PITSS'!$B$9:$U$90,21,0) -> #REF! | F45: =VLOOKUP(C45,'SIND PITS'!$C$3:$D$100,2,0) -> 384.855 | G45: =VLOOKUP(C45,'SIND PITS'!$C$3:$E$100,3,0) -> 135 | H45: =VLOOKUP(C45,'SIND PITS'!$C$3:$F$100,4,0) -> 0 | I45: =VLOOKUP(C45,'SIND PITS'!$C$3:$G$100,5,0) -> 0 | K45: =SUM(D45:I45) -> #REF! | L45: 7505.99 | M45: =+L45/2 -> 3752.995 | O45: =VLOOKUP(C45,'[1]IP PITS'!$B$6:$I$87,8,0) -> 0 | P45: =+G45+H45+I45 -> 135 | Q45: =(VLOOKUP(C45,'IP PITSS'!$B$9:$M$90,10,0))+(VLOOKUP(C45,'IP PITSS'!$B$9:$M$90,11,0))+(VLOOKUP(C45,'IP PITSS'!$B$9:$M$90,12,0)) -> 1361.54 | R45: =VLOOKUP(C45,'IP PITSS'!$B$9:$Q$90,17,0) -> #REF! | S45: =VLOOKUP(C45,'IP PITSS'!$B$9:$R$90,18,0) -> #REF! | U45: =+K45-O45-P45+Q45+R45+S45 -> #REF! | V45: =+M45-U45 -> #REF! | X45: SEI0499 | Y45: =IFERROR(OFFSET('CPD PITSS'!$AN$8,MATCH('RESUMEN PITS'!C45,'CPD PITSS'!$B$9:$B$26,0),0),0)+IFERROR(OFFSET('IP PITSS'!$AL$8,MATCH('RESUMEN PITS'!C45,'IP PITSS'!$B$9:$B$90,0),0),0)+IFERROR(OFFSET('SIND PITS'!$Q$2,MATCH('RESUMEN PITS'!C45,'SIND PITS'!$C$3:$C$103,0),0),0) -> 5390.6949
A46: SEI0461 | B46: IP INNOVACION | C46: Flores Franco Marco | D46: =VLOOKUP(C46,'IP PITSS'!$B$9:$U$90,21,0) -> #REF! | F46: =VLOOKUP(C46,'SIND PITS'!$C$3:$D$100,2,0) -> 451.005 | G46: =VLOOKUP(C46,'SIND PITS'!$C$3:$E$100,3,0) -> 412 | H46: =VLOOKUP(C46,'SIND PITS'!$C$3:$F$100,4,0) -> 0 | I46: =VLOOKUP(C46,'SIND PITS'!$C$3:$G$100,5,0) -> 0 | K46: =SUM(D46:I46) -> #REF! | L46: 8500.01 | M46: =+L46/2 -> 4250.005 | O46: =VLOOKUP(C46,'[1]IP PITS'!$B$6:$I$87,8,0) -> 0 | P46: =+G46+H46+I46 -> 412 | Q46: =(VLOOKUP(C46,'IP PITSS'!$B$9:$M$90,10,0))+(VLOOKUP(C46,'IP PITSS'!$B$9:$M$90,11,0))+(VLOOKUP(C46,'IP PITSS'!$B$9:$M$90,12,0)) -> 0 | R46: =VLOOKUP(C46,'IP PITSS'!$B$9:$Q$90,17,0) -> #REF! | S46: =VLOOKUP(C46,'IP PITSS'!$B$9:$R$90,18,0) -> #REF! | U46: =+K46-O46-P46+Q46+R46+S46 -> #REF! | V46: =+M46-U46 -> #REF! | X46: SEI0500 | Y46: =IFERROR(OFFSET('CPD PITSS'!$AN$8,MATCH('RESUMEN PITS'!C46,'CPD PITSS'!$B$9:$B$26,0),0),0)+IFERROR(OFFSET('IP PITSS'!$AL$8,MATCH('RESUMEN PITS'!C46,'IP PITSS'!$B$9:$B$90,0),0),0)+IFERROR(OFFSET('SIND PITS'!$Q$2,MATCH('RESUMEN PITS'!C46,'SIND PITS'!$C$3:$C$103,0),0),0) -> 6292.6451
A47: SEI0462 | B47: IP INNOVACION | C47: Chavez Saucedo Jorge Arturo | D47: =VLOOKUP(C47,'IP PITSS'!$B$9:$U$90,21,0) -> #REF! | F47: =VLOOKUP(C47,'SIND PITS'!$C$3:$D$100,2,0) -> 334.6 | G47: =VLOOKUP(C47,'SIND PITS'!$C$3:$E$100,3,0) -> 450 | H47: =VLOOKUP(C47,'SIND PITS'!$C$3:$F$100,4,0) -> 0 | I47: =VLOOKUP(C47,'SIND PITS'!$C$3:$G$100,5,0) -> 0 | K47: =SUM(D47:I47) -> #REF! | L47: 8000 | M47: =+L47/2 -> 4000 | O47: =VLOOKUP(C47,'[1]IP PITS'!$B$6:$I$87,8,0) -> 0 | P47: =+G47+H47+I47 -> 450 | Q47: =(VLOOKUP(C47,'IP PITSS'!$B$9:$M$90,10,0))+(VLOOKUP(C47,'IP PITSS'!$B$9:$M$90,11,0))+(VLOOKUP(C47,'IP PITSS'!$B$9:$M$90,12,0)) -> 0 | R47: =VLOOKUP(C47,'IP PITSS'!$B$9:$Q$90,17,0) -> #REF! | S47: =VLOOKUP(C47,'IP PITSS'!$B$9:$R$90,18,0) -> #REF! | U47: =+K47-O47-P47+Q47+R47+S47 -> #REF! | V47: =+M47-U47 -> #REF! | X47: SEI0516 | Y47: =IFERROR(OFFSET('CPD PITSS'!$AN$8,MATCH('RESUMEN PITS'!C47,'CPD PITSS'!$B$9:$B$26,0),0),0)+IFERROR(OFFSET('IP PITSS'!$AL$8,MATCH('RESUMEN PITS'!C47,'IP PITSS'!$B$9:$B$90,0),0),0)+IFERROR(OFFSET('SIND PITS'!$Q$2,MATCH('RESUMEN PITS'!C47,'SIND PITS'!$C$3:$C$103,0),0),0) -> 6009.931
A48: SEI0464 | B48: IP INNOVACION | C48: Hueramo Hueramo Jesus Daniel | D48: =VLOOKUP(C48,'IP PITSS'!$B$9:$U$90,21,0) -> #REF! | F48: =VLOOKUP(C48,'SIND PITS'!$C$3:$D$100,2,0) -> 1450.88 | G48: =VLOOKUP(C48,'SIND PITS'!$C$3:$E$100,3,0) -> 0 | H48: =VLOOKUP(C48,'SIND PITS'!$C$3:$F$100,4,0) -> 800 | I48: =VLOOKUP(C48,'SIND PITS'!$C$3:$G$100,5,0) -> 0 | K48: =SUM(D48:I48) -> #REF! | L48: 10500 | M48: =+L48/2 -> 5250 | O48: =VLOOKUP(C48,'[1]IP PITS'!$B$6:$I$87,8,0) -> 0 | P48: =+G48+H48+I48 -> 800 | Q48: =(VLOOKUP(C48,'IP PITSS'!$B$9:$M$90,10,0))+(VLOOKUP(C48,'IP PITSS'!$B$9:$M$90,11,0))+(VLOOKUP(C48,'IP PITSS'!$B$9:$M$90,12,0)) -> 549.92 | R48: =VLOOKUP(C48,'IP PITSS'!$B$9:$Q$90,17,0) -> #REF! | S48: =VLOOKUP(C48,'IP PITSS'!$B$9:$R$90,18,0) -> #REF! | U48: =+K48-O48-P48+Q48+R48+S48 -> #REF! | V48: =+M48-U48 -> #REF! | X48: SEI 502 | Y48: =IFERROR(OFFSET('CPD PITSS'!$AN$8,MATCH('RESUMEN PITS'!C48,'CPD PITSS'!$B$9:$B$26,0),0),0)+IFERROR(OFFSET('IP PITSS'!$AL$8,MATCH('RESUMEN PITS'!C48,'IP PITSS'!$B$9:$B$90,0),0),0)+IFERROR(OFFSET('SIND PITS'!$Q$2,MATCH('RESUMEN PITS'!C48,'SIND PITS'!$C$3:$C$103,0),0),0) -> 7708.4
... A74: SEI0435 | B74: IP INNOVACION | C74: Cerro Garcia Elvis | D74: =VLOOKUP(C74,'IP PITSS'!$B$9:$U$90,21,0) -> #REF! | F74: =VLOOKUP(C74,'SIND PITS'!$C$3:$D$100,2,0) -> 2553.4 | G74: =VLOOKUP(C74,'SIND PITS'!$C$3:$E$100,3,0) -> 400 | H74: =VLOOKUP(C74,'SIND PITS'!$C$3:$F$100,4,0) -> 0 | I74: =VLOOKUP(C74,'SIND PITS'!$C$3:$G$100,5,0) -> 0 | K74: =SUM(D74:I74) -> #REF! | L74: 10000 | M74: =+L74/2 -> 5000 | O74: =VLOOKUP(C74,'[1]IP PITS'!$B$6:$I$87,8,0) -> 0 | P74: =+G74+H74+I74 -> 400 | Q74: =(VLOOKUP(C74,'IP PITSS'!$B$9:$M$90,10,0))+(VLOOKUP(C74,'IP PITSS'!$B$9:$M$90,11,0))+(VLOOKUP(C74,'IP PITSS'!$B$9:$M$90,12,0)) -> 0 | R74: =VLOOKUP(C74,'IP PITSS'!$B$9:$Q$90,17,0) -> #REF! | S74: =VLOOKUP(C74,'IP PITSS'!$B$9:$R$90,18,0) -> #REF! | U74: =+K74-O74-P74+Q74+R74+S74 -> #REF! | V74: =+M74-U74 -> #REF! | X74: SEI0513 | Y74: =IFERROR(OFFSET('CPD PITSS'!$AN$8,MATCH('RESUMEN PITS'!C74,'CPD PITSS'!$B$9:$B$26,0),0),0)+IFERROR(OFFSET('IP PITSS'!$AL$8,MATCH('RESUMEN PITS'!C74,'IP PITSS'!$B$9:$B$90,0),0),0)+IFERROR(OFFSET('SIND PITS'!$Q$2,MATCH('RESUMEN PITS'!C74,'SIND PITS'!$C$3:$C$103,0),0),0) -> 6669.781
A75: SEI0509 | B75: IP INNOVACION | C75: Gutierrez Castillo Jose De Jesus | D75: ='IP PITSS'!$U$66 -> 2865.8 | F75: =VLOOKUP(C75,'SIND PITS'!$C$3:$D$100,2,0) -> 284.2 | G75: =VLOOKUP(C75,'SIND PITS'!$C$3:$E$100,3,0) -> 281.25 | H75: =VLOOKUP(C75,'SIND PITS'!$C$3:$F$100,4,0) -> 0 | I75: =VLOOKUP(C75,'SIND PITS'!$C$3:$G$100,5,0) -> 0 | K75: =SUM(D75:I75) -> 3431.25 | L75: 6300 | M75: =+L75/2 -> 3150 | O75: =VLOOKUP(C75,'[1]IP PITS'!$B$6:$I$87,8,0) -> 0 | P75: =+G75+H75+I75 -> 281.25 | U75: =+K75-O75-P75+Q75+R75+S75 -> 3150 | V75: =+M75-U75 -> 0 | X75: SEI0610 | Y75: =IFERROR(OFFSET('CPD PITSS'!$AN$8,MATCH('RESUMEN PITS'!C75,'CPD PITSS'!$B$9:$B$26,0),0),0)+IFERROR(OFFSET('IP PITSS'!$AL$8,MATCH('RESUMEN PITS'!C75,'IP PITSS'!$B$9:$B$90,0),0),0)+IFERROR(OFFSET('SIND PITS'!$Q$2,MATCH('RESUMEN PITS'!C75,'SIND PITS'!$C$3:$C$103,0),0),0) -> 576.759
A76: SEI0433 | B76: IP INNOVACION | C76: Mejia Duarte Jose Luis | D76: ='IP PITSS'!$U$64 -> 2446.6 | F76: =VLOOKUP(C76,'SIND PITS'!$C$3:$D$100,2,0) -> 3553.4 | G76: =VLOOKUP(C76,'SIND PITS'!$C$3:$E$100,3,0) -> 500 | H76: =VLOOKUP(C76,'SIND PITS'!$C$3:$F$100,4,0) -> 0 | I76: =VLOOKUP(C76,'SIND PITS'!$C$3:$G$100,5,0) -> 0 | K76: =SUM(D76:I76) -> 6500 | L76: 12000 | M76: =+L76/2 -> 6000 | O76: =VLOOKUP(C76,'[1]IP PITS'!$B$6:$I$87,8,0) -> 0 | P76: =+G76+H76+I76 -> 500 | U76: =+K76-O76-P76+Q76+R76+S76 -> 6000 | V76: =+M76-U76 -> 0 | X76: SEI0506 | Y76: =IFERROR(OFFSET('CPD PITSS'!$AN$8,MATCH('RESUMEN PITS'!C76,'CPD PITSS'!$B$9:$B$26,0),0),0)+IFERROR(OFFSET('IP PITSS'!$AL$8,MATCH('RESUMEN PITS'!C76,'IP PITSS'!$B$9:$B$90,0),0),0)+IFERROR(OFFSET('SIND PITS'!$Q$2,MATCH('RESUMEN PITS'!C76,'SIND PITS'!$C$3:$C$103,0),0),0) -> 4134.468
A77: SEI0511 | B77: IP INNOVACION | C77: Lizaran Maceda Jose Guadalupe | D77: =VLOOKUP(C77,'IP PITSS'!$B$9:$U$90,21,0) -> #REF! | F77: =VLOOKUP(C77,'SIND PITS'!$C$3:$D$100,2,0) -> 52.8 | G77: =VLOOKUP(C77,'SIND PITS'!$C$3:$E$100,3,0) -> 160 | H77: =VLOOKUP(C77,'SIND PITS'!$C$3:$F$100,4,0) -> 0 | I77: =VLOOKUP(C77,'SIND PITS'!$C$3:$G$100,5,0) -> 0 | K77: =SUM(D77:I77) -> #REF! | L77: 5000 | M77: =+L77/2 -> 2500 | O77: =VLOOKUP(C77,'[1]IP PITS'!$B$6:$I$87,8,0) -> 0 | P77: =+G77+H77+I77 -> 160 | Q77: =(VLOOKUP(C77,'IP PITSS'!$B$9:$M$90,10,0))+(VLOOKUP(C77,'IP PITSS'!$B$9:$M$90,11,0))+(VLOOKUP(C77,'IP PITSS'!$B$9:$M$90,12,0)) -> 0 | R77: =VLOOKUP(C77,'IP PITSS'!$B$9:$Q$90,17,0) -> #REF! | S77: =VLOOKUP(C77,'IP PITSS'!$B$9:$R$90,18,0) -> #REF! | U77: =+K77-O77-P77+Q77+R77+S77 -> #REF! | V77: =+M77-U77 -> #REF! | X77: SEI0517 | Y77: =IFERROR(OFFSET('CPD PITSS'!$AN$8,MATCH('RESUMEN PITS'!C77,'CPD PITSS'!$B$9:$B$26,0),0),0)+IFERROR(OFFSET('IP PITSS'!$AL$8,MATCH('RESUMEN PITS'!C77,'IP PITSS'!$B$9:$B$90,0),0),0)+IFERROR(OFFSET('SIND PITS'!$Q$2,MATCH('RESUMEN PITS'!C77,'SIND PITS'!$C$3:$C$103,0),0),0) -> 3871.711
A78: SEI0513 | B78: IP INNOVACION | C78: Mendez Rivera Ivan Israel | D78: =VLOOKUP(C78,'IP PITSS'!$B$9:$U$90,21,0) -> #REF! | F78: =VLOOKUP(C78,'SIND PITS'!$C$3:$D$100,2,0) -> 52.5 | G78: =VLOOKUP(C78,'SIND PITS'!$C$3:$E$100,3,0) -> 310 | H78: =VLOOKUP(C78,'SIND PITS'!$C$3:$F$100,4,0) -> 0 | I78: =VLOOKUP(C78,'SIND PITS'!$C$3:$G$100,5,0) -> 0 | K78: =SUM(D78:I78) -> #REF! | L78: 5000 | M78: =+L78/2 -> 2500 | O78: =VLOOKUP(C78,'[1]IP PITS'!$B$6:$I$87,8,0) -> 0 | P78: =+G78+H78+I78 -> 310 | Q78: =(VLOOKUP(C78,'IP PITSS'!$B$9:$M$90,10,0))+(VLOOKUP(C78,'IP PITSS'!$B$9:$M$90,11,0))+(VLOOKUP(C78,'IP PITSS'!$B$9:$M$90,12,0)) -> 413.9 | R78: =VLOOKUP(C78,'IP PITSS'!$B$9:$Q$90,17,0) -> #REF! | S78: =VLOOKUP(C78,'IP PITSS'!$B$9:$R$90,18,0) -> #REF! | U78: =+K78-O78-P78+Q78+R78+S78 -> #REF! | V78: =+M78-U78 -> #REF! | X78: SEI0612 | Y78: =IFERROR(OFFSET('CPD PITSS'!$AN$8,MATCH('RESUMEN PITS'!C78,'CPD PITSS'!$B$9:$B$26,0),0),0)+IFERROR(OFFSET('IP PITSS'!$AL$8,MATCH('RESUMEN PITS'!C78,'IP PITSS'!$B$9:$B$90,0),0),0)+IFERROR(OFFSET('SIND PITS'!$Q$2,MATCH('RESUMEN PITS'!C78,'SIND PITS'!$C$3:$C$103,0),0),0) -> 4020.418
A79: SEI0517 | B79: IP INNOVACION | C79: Macias Torres Enrique | D79: =VLOOKUP(C79,'IP PITSS'!$B$9:$U$90,21,0) -> #REF! | F79: =VLOOKUP(C79,'SIND PITS'!$C$3:$D$100,2,0) -> 6520.6 | G79: =VLOOKUP(C79,'SIND PITS'!$C$3:$E$100,3,0) -> 1938 | H79: =VLOOKUP(C79,'SIND PITS'!$C$3:$F$100,4,0) -> 0 | I79: =VLOOKUP(C79,'SIND PITS'!$C$3:$G$100,5,0) -> 0 | K79: =SUM(D79:I79) -> #REF! | L79: 19950 | M79: =+L79/2 -> 9975 | O79: =VLOOKUP(C79,'[1]IP PITS'!$B$6:$I$87,8,0) -> 0 | P79: =+G79+H79+I79 -> 1938 | Q79: =(VLOOKUP(C79,'IP PITSS'!$B$9:$M$90,10,0))+(VLOOKUP(C79,'IP PITSS'!$B$9:$M$90,11,0))+(VLOOKUP(C79,'IP PITSS'!$B$9:$M$90,12,0)) -> 0 | R79: =VLOOKUP(C79,'IP PITSS'!$B$9:$Q$90,17,0) -> #REF! | S79: =VLOOKUP(C79,'IP PITSS'!$B$9:$R$90,18,0) -> #REF! | U79: =+K79-O79-P79+Q79+R79+S79 -> #REF! | V79: =+M79-U79 -> #REF! | X79: SEI0120 | Y79: =IFERROR(OFFSET('CPD PITSS'!$AN$8,MATCH('RESUMEN PITS'!C79,'CPD PITSS'!$B$9:$B$26,0),0),0)+IFERROR(OFFSET('IP PITSS'!$AL$8,MATCH('RESUMEN PITS'!C79,'IP PITSS'!$B$9:$B$90,0),0),0)+IFERROR(OFFSET('SIND PITS'!$Q$2,MATCH('RESUMEN PITS'!C79,'SIND PITS'!$C$3:$C$103,0),0),0) -> 13598.701
A80: SEI0519 | B80: IP INNOVACION | C80: Palacios Vega Luis Rosendo | D80: =VLOOKUP(C80,'IP PITSS'!$B$9:$U$90,21,0) -> #REF! | F80: =VLOOKUP(C80,'SIND PITS'!$C$3:$D$100,2,0) -> 52.4 | G80: =VLOOKUP(C80,'SIND PITS'!$C$3:$E$100,3,0) -> 70 | H80: =VLOOKUP(C80,'SIND PITS'!$C$3:$F$100,4,0) -> 0 | I80: =VLOOKUP(C80,'SIND PITS'!$C$3:$G$100,5,0) -> 0 | K80: =SUM(D80:I80) -> #REF! | L80: 5000 | M80: =+L80/2 -> 2500 | O80: =VLOOKUP(C80,'[1]IP PITS'!$B$6:$I$87,8,0) -> 0 | P80: =+G80+H80+I80 -> 70 | Q80: =(VLOOKUP(C80,'IP PITSS'!$B$9:$M$90,10,0))+(VLOOKUP(C80,'IP PITSS'!$B$9:$M$90,11,0))+(VLOOKUP(C80,'IP PITSS'!$B$9:$M$90,12,0)) -> 0 | R80: =VLOOKUP(C80,'IP PITSS'!$B$9:$Q$90,17,0) -> #REF! | S80: =VLOOKUP(C80,'IP PITSS'!$B$9:$R$90,18,0) -> #REF! | U80: =+K80-O80-P80+Q80+R80+S80 -> #REF! | V80: =+M80-U80 -> #REF! | X80: SEI0519 | Y80: =IFERROR(OFFSET('CPD PITSS'!$AN$8,MATCH('RESUMEN PITS'!C80,'CPD PITSS'!$B$9:$B$26,0),0),0)+IFERROR(OFFSET('IP PITSS'!$AL$8,MATCH('RESUMEN PITS'!C80,'IP PITSS'!$B$9:$B$90,0),0),0)+IFERROR(OFFSET('SIND PITS'!$Q$2,MATCH('RESUMEN PITS'!C80,'SIND PITS'!$C$3:$C$103,0),0),0) -> 3775.631
A81: SEI0521 | B81: IP INNOVACION | C81: Rondero Savin Jacinto | D81: =VLOOKUP(C81,'IP PITSS'!$B$9:$U$90,21,0) -> #REF! | F81: =VLOOKUP(C81,'SIND PITS'!$C$3:$D$100,2,0) -> 221.2 | G81: =VLOOKUP(C81,'SIND PITS'!$C$3:$E$100,3,0) -> 0 | H81: =VLOOKUP(C81,'SIND PITS'!$C$3:$F$100,4,0) -> 0 | I81: =VLOOKUP(C81,'SIND PITS'!$C$3:$G$100,5,0) -> 0 | K81: =SUM(D81:I81) -> #REF! | L81: 7000 | M81: =+L81/2 -> 3500 | O81: =VLOOKUP(C81,'[1]IP PITS'!$B$6:$I$87,8,0) -> 0 | P81: =+G81+H81+I81 -> 0 | Q81: =(VLOOKUP(C81,'IP PITSS'!$B$9:$M$90,10,0))+(VLOOKUP(C81,'IP PITSS'!$B$9:$M$90,11,0))+(VLOOKUP(C81,'IP PITSS'!$B$9:$M$90,12,0)) -> 0 | R81: =VLOOKUP(C81,'IP PITSS'!$B$9:$Q$90,17,0) -> #REF! | S81: =VLOOKUP(C81,'IP PITSS'!$B$9:$R$90,18,0) -> #REF! | U81: =+K81-O81-P81+Q81+R81+S81 -> #REF! | V81: =+M81-U81 -> #REF! | X81: SEI0622 | Y81: =IFERROR(OFFSET('CPD PITSS'!$AN$8,MATCH('RESUMEN PITS'!C81,'CPD PITSS'!$B$9:$B$26,0),0),0)+IFERROR(OFFSET('IP PITSS'!$AL$8,MATCH('RESUMEN PITS'!C81,'IP PITSS'!$B$9:$B$90,0),0),0)+IFERROR(OFFSET('SIND PITS'!$Q$2,MATCH('RESUMEN PITS'!C81,'SIND PITS'!$C$3:$C$103,0),0),0) -> 4930.479
A82: SEI0523 | B82: IP INNOVACION | C82: Hernandez Rodriguez Jorge | D82: =VLOOKUP(C82,'IP PITSS'!$B$9:$U$90,21,0) -> #REF! | F82: =VLOOKUP(C82,'SIND PITS'!$C$3:$D$100,2,0) -> 222.69 | G82: =VLOOKUP(C82,'SIND PITS'!$C$3:$E$100,3,0) -> 550 | H82: =VLOOKUP(C82,'SIND PITS'!$C$3:$F$100,4,0) -> 400 | I82: =VLOOKUP(C82,'SIND PITS'!$C$3:$G$100,5,0) -> 0 | K82: =SUM(D82:I82) -> #REF! | L82: 7000 | M82: =+L82/2 -> 3500 | O82: =VLOOKUP(C82,'[1]IP PITS'!$B$6:$I$87,8,0) -> 0 | P82: =+G82+H82+I82 -> 950 | Q82: =(VLOOKUP(C82,'IP PITSS'!$B$9:$M$90,10,0))+(VLOOKUP(C82,'IP PITSS'!$B$9:$M$90,11,0))+(VLOOKUP(C82,'IP PITSS'!$B$9:$M$90,12,0)) -> 1416.51 | R82: =VLOOKUP(C82,'IP PITSS'!$B$9:$Q$90,17,0) -> #REF! | S82: =VLOOKUP(C82,'IP PITSS'!$B$9:$R$90,18,0) -> #REF! | U82: =+K82-O82-P82+Q82+R82+S82 -> #REF! | V82: =+M82-U82 -> #REF! | X82: SEI0624 | Y82: =IFERROR(OFFSET('CPD PITSS'!$AN$8,MATCH('RESUMEN PITS'!C82,'CPD PITSS'!$B$9:$B$26,0),0),0)+IFERROR(OFFSET('IP PITSS'!$AL$8,MATCH('RESUMEN PITS'!C82,'IP PITSS'!$B$9:$B$90,0),0),0)+IFERROR(OFFSET('SIND PITS'!$Q$2,MATCH('RESUMEN PITS'!C82,'SIND PITS'!$C$3:$C$103,0),0),0) -> 5909.069
A83: SEI0524 | B83: IP INNOVACION | C83: Orea Gonzalez Concepcion Esteban | D83: =VLOOKUP(C83,'IP PITSS'!$B$9:$U$90,21,0) -> #REF! | F83: =VLOOKUP(C83,'SIND PITS'!$C$3:$D$100,2,0) -> 175.8 | G83: =VLOOKUP(C83,'SIND PITS'!$C$3:$E$100,3,0) -> 900 | H83: =VLOOKUP(C83,'SIND PITS'!$C$3:$F$100,4,0) -> 0 | I83: =VLOOKUP(C83,'SIND PITS'!$C$3:$G$100,5,0) -> 0 | K83: =SUM(D83:I83) -> #REF! | L83: 6300 | M83: =+L83/2 -> 3150 | O83: =VLOOKUP(C83,'[1]IP PITS'!$B$6:$I$87,8,0) -> 0 | P83: =+G83+H83+I83 -> 900 | Q83: =(VLOOKUP(C83,'IP PITSS'!$B$9:$M$90,10,0))+(VLOOKUP(C83,'IP PITSS'!$B$9:$M$90,11,0))+(VLOOKUP(C83,'IP PITSS'!$B$9:$M$90,12,0)) -> 0 | R83: =VLOOKUP(C83,'IP PITSS'!$B$9:$Q$90,17,0) -> #REF! | S83: =VLOOKUP(C83,'IP PITSS'!$B$9:$R$90,18,0) -> #REF! | U83: =+K83-O83-P83+Q83+R83+S83 -> #REF! | V83: =+M83-U83 -> #REF! | X83: SEI0625 | Y83: =IFERROR(OFFSET('CPD PITSS'!$AN$8,MATCH('RESUMEN PITS'!C83,'CPD PITSS'!$B$9:$B$26,0),0),0)+IFERROR(OFFSET('IP PITSS'!$AL$8,MATCH('RESUMEN PITS'!C83,'IP PITSS'!$B$9:$B$90,0),0),0)+IFERROR(OFFSET('SIND PITS'!$Q$2,MATCH('RESUMEN PITS'!C83,'SIND PITS'!$C$3:$C$103,0),0),0) -> 5427.93
A84: SEI0525 | B84: IP INNOVACION | C84: Lizaran Maceda Jesus | D84: =VLOOKUP(C84,'IP PITSS'!$B$9:$U$90,21,0) -> #REF! | F84: =VLOOKUP(C84,'SIND PITS'!$C$3:$D$100,2,0) -> 175.66 | G84: =VLOOKUP(C84,'SIND PITS'!$C$3:$E$100,3,0) -> 0 | H84: =VLOOKUP(C84,'SIND PITS'!$C$3:$F$100,4,0) -> 0 | I84: =VLOOKUP(C84,'SIND PITS'!$C$3:$G$100,5,0) -> 0 | K84: =SUM(D84:I84) -> #REF! | L84: 6300 | M84: =+L84/2 -> 3150 | O84: =VLOOKUP(C84,'[1]IP PITS'!$B$6:$I$87,8,0) -> 0 | P84: =+G84+H84+I84 -> 0 | Q84: =(VLOOKUP(C84,'IP PITSS'!$B$9:$M$90,10,0))+(VLOOKUP(C84,'IP PITSS'!$B$9:$M$90,11,0))+(VLOOKUP(C84,'IP PITSS'!$B$9:$M$90,12,0)) -> 318.54 | R84: =VLOOKUP(C84,'IP PITSS'!$B$9:$Q$90,17,0) -> #REF! | S84: =VLOOKUP(C84,'IP PITSS'!$B$9:$R$90,18,0) -> #REF! | U84: =+K84-O84-P84+Q84+R84+S84 -> #REF! | V84: =+M84-U84 -> #REF! | X84: SEI0626 | Y84: =IFERROR(OFFSET('CPD PITSS'!$AN$8,MATCH('RESUMEN PITS'!C84,'CPD PITSS'!$B$9:$B$26,0),0),0)+IFERROR(OFFSET('IP PITSS'!$AL$8,MATCH('RESUMEN PITS'!C84,'IP PITSS'!$B$9:$B$90,0),0),0)+IFERROR(OFFSET('SIND PITS'!$Q$2,MATCH('RESUMEN PITS'!C84,'SIND PITS'!$C$3:$C$103,0),0),0) -> 4509.93
A85: SEI0527 | B85: IP INNOVACION | C85: Alejandro Peña Deivi | D85: =VLOOKUP(C85,'IP PITSS'!$B$9:$U$90,21,0) -> #REF! | F85: =VLOOKUP(C85,'SIND PITS'!$C$3:$D$100,2,0) -> 175.6 | G85: =VLOOKUP(C85,'SIND PITS'!$C$3:$E$100,3,0) -> 1068.75 | H85: =VLOOKUP(C85,'SIND PITS'!$C$3:$F$100,4,0) -> 0 | I85: =VLOOKUP(C85,'SIND PITS'!$C$3:$G$100,5,0) -> 0 | K85: =SUM(D85:I85) -> #REF! | L85: 6300 | M85: =+L85/2 -> 3150 | O85: =VLOOKUP(C85,'[1]IP PITS'!$B$6:$I$87,8,0) -> 0 | P85: =+G85+H85+I85 -> 1068.75 | Q85: =(VLOOKUP(C85,'IP PITSS'!$B$9:$M$90,10,0))+(VLOOKUP(C85,'IP PITSS'!$B$9:$M$90,11,0))+(VLOOKUP(C85,'IP PITSS'!$B$9:$M$90,12,0)) -> 0 | R85: =VLOOKUP(C85,'IP PITSS'!$B$9:$Q$90,17,0) -> #REF! | S85: =VLOOKUP(C85,'IP PITSS'!$B$9:$R$90,18,0) -> #REF! | U85: =+K85-O85-P85+Q85+R85+S85 -> #REF! | V85: =+M85-U85 -> #REF! | X85: SEI0628 | Y85: =IFERROR(OFFSET('CPD PITSS'!$AN$8,MATCH('RESUMEN PITS'!C85,'CPD PITSS'!$B$9:$B$26,0),0),0)+IFERROR(OFFSET('IP PITSS'!$AL$8,MATCH('RESUMEN PITS'!C85,'IP PITSS'!$B$9:$B$90,0),0),0)+IFERROR(OFFSET('SIND PITS'!$Q$2,MATCH('RESUMEN PITS'!C85,'SIND PITS'!$C$3:$C$103,0),0),0) -> 5600.055
A86: SEI0528 | B86: IP INNOVACION | C86: Casas Chavarria Rafael | D86: =VLOOKUP(C86,'IP PITSS'!$B$9:$U$90,21,0) -> #REF! | F86: =VLOOKUP(C86,'SIND PITS'!$C$3:$D$100,2,0) -> 175.67 | G86: =VLOOKUP(C86,'SIND PITS'!$C$3:$E$100,3,0) -> 675 | H86: =VLOOKUP(C86,'SIND PITS'!$C$3:$F$100,4,0) -> 0 | I86: =VLOOKUP(C86,'SIND PITS'!$C$3:$G$100,5,0) -> 0 | K86: =SUM(D86:I86) -> #REF! | L86: 6300 | M86: =+L86/2 -> 3150 | O86: =VLOOKUP(C86,'[1]IP PITS'!$B$6:$I$87,8,0) -> 0 | P86: =+G86+H86+I86 -> 675 | Q86: =(VLOOKUP(C86,'IP PITSS'!$B$9:$M$90,10,0))+(VLOOKUP(C86,'IP PITSS'!$B$9:$M$90,11,0))+(VLOOKUP(C86,'IP PITSS'!$B$9:$M$90,12,0)) -> 957.33 | R86: =VLOOKUP(C86,'IP PITSS'!$B$9:$Q$90,17,0) -> #REF! | S86: =VLOOKUP(C86,'IP PITSS'!$B$9:$R$90,18,0) -> #REF! | U86: =+K86-O86-P86+Q86+R86+S86 -> #REF! | V86: =+M86-U86 -> #REF! | X86: SEI0629 | Y86: =IFERROR(OFFSET('CPD PITSS'!$AN$8,MATCH('RESUMEN PITS'!C86,'CPD PITSS'!$B$9:$B$26,0),0),0)+IFERROR(OFFSET('IP PITSS'!$AL$8,MATCH('RESUMEN PITS'!C86,'IP PITSS'!$B$9:$B$90,0),0),0)+IFERROR(OFFSET('SIND PITS'!$Q$2,MATCH('RESUMEN PITS'!C86,'SIND PITS'!$C$3:$C$103,0),0),0) -> 5198.43
A87: SEI0530 | B87: IP INNOVACION | C87: Del Pilar Mendez Lucio | D87: =VLOOKUP(C87,'IP PITSS'!$B$9:$U$90,21,0) -> #REF! | F87: =VLOOKUP(C87,'SIND PITS'!$C$3:$D$100,2,0) -> 134.21 | G87: =VLOOKUP(C87,'SIND PITS'!$C$3:$E$100,3,0) -> 225 | H87: =VLOOKUP(C87,'SIND PITS'!$C$3:$F$100,4,0) -> 0 | I87: =VLOOKUP(C87,'SIND PITS'!$C$3:$G$100,5,0) -> 0 | K87: =SUM(D87:I87) -> #REF! | L87: 6000 | M87: =+L87/2 -> 3000 | O87: =VLOOKUP(C87,'[1]IP PITS'!$B$6:$I$87,8,0) -> 0 | P87: =+G87+H87+I87 -> 225 | Q87: =(VLOOKUP(C87,'IP PITSS'!$B$9:$M$90,10,0))+(VLOOKUP(C87,'IP PITSS'!$B$9:$M$90,11,0))+(VLOOKUP(C87,'IP PITSS'!$B$9:$M$90,12,0)) -> 1590.59 | R87: =VLOOKUP(C87,'IP PITSS'!$B$9:$Q$90,17,0) -> #REF! | S87: =VLOOKUP(C87,'IP PITSS'!$B$9:$R$90,18,0) -> #REF! | U87: =+K87-O87-P87+Q87+R87+S87 -> #REF! | V87: =+M87-U87 -> #REF! | X87: SEI0630 | Y87: =IFERROR(OFFSET('CPD PITSS'!$AN$8,MATCH('RESUMEN PITS'!C87,'CPD PITSS'!$B$9:$B$26,0),0),0)+IFERROR(OFFSET('IP PITSS'!$AL$8,MATCH('RESUMEN PITS'!C87,'IP PITSS'!$B$9:$B$90,0),0),0)+IFERROR(OFFSET('SIND PITS'!$Q$2,MATCH('RESUMEN PITS'!C87,'SIND PITS'!$C$3:$C$103,0),0),0) -> 4546.86
A88: SEI0534 | B88: IP INNOVACION | C88: Gonzalez Ramirez Paul | D88: =VLOOKUP(C88,'IP PITSS'!$B$9:$U$90,21,0) -> #REF! | F88: =VLOOKUP(C88,'SIND PITS'!$C$3:$D$100,2,0) -> 134.2 | G88: =VLOOKUP(C88,'SIND PITS'!$C$3:$E$100,3,0) -> 130 | H88: =VLOOKUP(C88,'SIND PITS'!$C$3:$F$100,4,0) -> 0 | I88: =VLOOKUP(C88,'SIND PITS'!$C$3:$G$100,5,0) -> 0 | K88: =SUM(D88:I88) -> #REF! | L88: 6000 | M88: =+L88/2 -> 3000 | O88: =VLOOKUP(C88,'[1]IP PITS'!$B$6:$I$87,8,0) -> 0 | P88: =+G88+H88+I88 -> 130 | Q88: =(VLOOKUP(C88,'IP PITSS'!$B$9:$M$90,10,0))+(VLOOKUP(C88,'IP PITSS'!$B$9:$M$90,11,0))+(VLOOKUP(C88,'IP PITSS'!$B$9:$M$90,12,0)) -> 0 | R88: =VLOOKUP(C88,'IP PITSS'!$B$9:$Q$90,17,0) -> #REF! | S88: =VLOOKUP(C88,'IP PITSS'!$B$9:$R$90,18,0) -> #REF! | U88: =+K88-O88-P88+Q88+R88+S88 -> #REF! | V88: =+M88-U88 -> #REF! | X88: 0SEI0635 | Y88: =IFERROR(OFFSET('CPD PITSS'!$AN$8,MATCH('RESUMEN PITS'!C88,'CPD PITSS'!$B$9:$B$26,0),0),0)+IFERROR(OFFSET('IP PITSS'!$AL$8,MATCH('RESUMEN PITS'!C88,'IP PITSS'!$B$9:$B$90,0),0),0)+IFERROR(OFFSET('SIND PITS'!$Q$2,MATCH('RESUMEN PITS'!C88,'SIND PITS'!$C$3:$C$103,0),0),0) -> 4449.96
... A92: SEI0537 | B92: IP INNOVACION | C92: Serrano Esquivel Armando | D92: =VLOOKUP(C92,'IP PITSS'!$B$9:$U$90,21,0) -> #REF! | F92: =VLOOKUP(C92,'SIND PITS'!$C$3:$D$100,2,0) -> 1704.48 | G92: =VLOOKUP(C92,'SIND PITS'!$C$3:$E$100,3,0) -> 750 | H92: =VLOOKUP(C92,'SIND PITS'!$C$3:$F$100,4,0) -> 0 | I92: =VLOOKUP(C92,'SIND PITS'!$C$3:$G$100,5,0) -> 0 | K92: =SUM(D92:I92) -> #REF! | L92: 7000 | M92: =+L92/2 -> 3500 | O92: =VLOOKUP(C92,'[1]IP PITS'!$B$6:$I$87,8,0) -> 0 | P92: =+G92+H92+I92 -> 750 | Q92: =(VLOOKUP(C92,'IP PITSS'!$B$9:$M$90,10,0))+(VLOOKUP(C92,'IP PITSS'!$B$9:$M$90,11,0))+(VLOOKUP(C92,'IP PITSS'!$B$9:$M$90,12,0)) -> 736.52 | R92: =VLOOKUP(C92,'IP PITSS'!$B$9:$Q$90,17,0) -> #REF! | S92: =VLOOKUP(C92,'IP PITSS'!$B$9:$R$90,18,0) -> #REF! | U92: =+K92-O92-P92+Q92+R92+S92 -> #REF! | V92: =+M92-U92 -> #REF! | X92: SEI0641 | Y92: =IFERROR(OFFSET('CPD PITSS'!$AN$8,MATCH('RESUMEN PITS'!C92,'CPD PITSS'!$B$9:$B$26,0),0),0)+IFERROR(OFFSET('IP PITSS'!$AL$8,MATCH('RESUMEN PITS'!C92,'IP PITSS'!$B$9:$B$90,0),0),0)+IFERROR(OFFSET('SIND PITS'!$Q$2,MATCH('RESUMEN PITS'!C92,'SIND PITS'!$C$3:$C$103,0),0),0) -> 5339.301
A93: SEI0538 | B93: IP INNOVACION | C93: Coronado Vega Carlos Eduardo | D93: 0 | F93: 0 | G93: =VLOOKUP(C93,'SIND PITS'!$C$3:$E$100,3,0) -> 0 | H93: =VLOOKUP(C93,'SIND PITS'!$C$3:$F$100,4,0) -> 0 | I93: =VLOOKUP(C93,'SIND PITS'!$C$3:$G$100,5,0) -> 0 | K93: =SUM(D93:I93) -> 0 | L93: 6300 | M93: =+L93/2 -> 3150 | O93: =VLOOKUP(C93,'[1]IP PITS'!$B$6:$I$87,8,0) -> 0 | P93: =+G93+H93+I93 -> 0 | U93: =+K93-O93-P93+Q93+R93+S93 -> 0 | V93: 0 | W93: Proceso de Finiquito | X93: SEI0642 | Y93: =IFERROR(OFFSET('CPD PITSS'!$AN$8,MATCH('RESUMEN PITS'!C93,'CPD PITSS'!$B$9:$B$26,0),0),0)+IFERROR(OFFSET('IP PITSS'!$AL$8,MATCH('RESUMEN PITS'!C93,'IP PITSS'!$B$9:$B$90,0),0),0)+IFERROR(OFFSET('SIND PITS'!$Q$2,MATCH('RESUMEN PITS'!C93,'SIND PITS'!$C$3:$C$103,0),0),0) -> 0
A94: SEI0015 | B94: IP INNOVACION | C94: Cota Jaramillo Miguel Angel | D94: =VLOOKUP(C94,'IP PITSS'!$B$9:$U$90,21,0) -> #REF! | F94: =VLOOKUP(C94,'SIND PITS'!$C$3:$D$100,2,0) -> 554.2 | G94: =VLOOKUP(C94,'SIND PITS'!$C$3:$E$100,3,0) -> 225 | H94: =VLOOKUP(C94,'SIND PITS'!$C$3:$F$100,4,0) -> 0 | I94: =VLOOKUP(C94,'SIND PITS'!$C$3:$G$100,5,0) -> 0 | K94: =SUM(D94:I94) -> #REF! | L94: 6000 | M94: =+L94/2 -> 3000 | O94: =VLOOKUP(C94,'[1]IP PITS'!$B$6:$I$87,8,0) -> 420 | P94: =+G94+H94+I94 -> 225 | Q94: =(VLOOKUP(C94,'IP PITSS'!$B$9:$M$90,10,0))+(VLOOKUP(C94,'IP PITSS'!$B$9:$M$90,11,0))+(VLOOKUP(C94,'IP PITSS'!$B$9:$M$90,12,0)) -> 0 | R94: =VLOOKUP(C94,'IP PITSS'!$B$9:$Q$90,17,0) -> #REF! | S94: =VLOOKUP(C94,'IP PITSS'!$B$9:$R$90,18,0) -> #REF! | U94: =+K94-O94-P94+Q94+R94+S94 -> #REF! | V94: =+M94-U94 -> #REF! | X94: SEI0015 | Y94: =IFERROR(OFFSET('CPD PITSS'!$AN$8,MATCH('RESUMEN PITS'!C94,'CPD PITSS'!$B$9:$B$26,0),0),0)+IFERROR(OFFSET('IP PITSS'!$AL$8,MATCH('RESUMEN PITS'!C94,'IP PITSS'!$B$9:$B$90,0),0),0)+IFERROR(OFFSET('SIND PITS'!$Q$2,MATCH('RESUMEN PITS'!C94,'SIND PITS'!$C$3:$C$103,0),0),0) -> 4975.26
A95: SEI0540 | B95: IP INNOVACION | C95: Morales Martinez Eduardo | D95: =VLOOKUP(C95,'IP PITSS'!$B$9:$U$90,21,0) -> #REF! | F95: =VLOOKUP(C95,'SIND PITS'!$C$3:$D$100,2,0) -> 175.8 | G95: =VLOOKUP(C95,'SIND PITS'!$C$3:$E$100,3,0) -> 843.75 | H95: =VLOOKUP(C95,'SIND PITS'!$C$3:$F$100,4,0) -> 0 | I95: =VLOOKUP(C95,'SIND PITS'!$C$3:$G$100,5,0) -> 0 | K95: =SUM(D95:I95) -> #REF! | L95: 6300 | M95: =+L95/2 -> 3150 | O95: =VLOOKUP(C95,'[1]IP PITS'!$B$6:$I$87,8,0) -> 0 | P95: =+G95+H95+I95 -> 843.75 | Q95: =(VLOOKUP(C95,'IP PITSS'!$B$9:$M$90,10,0))+(VLOOKUP(C95,'IP PITSS'!$B$9:$M$90,11,0))+(VLOOKUP(C95,'IP PITSS'!$B$9:$M$90,12,0)) -> 0 | R95: =VLOOKUP(C95,'IP PITSS'!$B$9:$Q$90,17,0) -> #REF! | S95: =VLOOKUP(C95,'IP PITSS'!$B$9:$R$90,18,0) -> #REF! | U95: =+K95-O95-P95+Q95+R95+S95 -> #REF! | V95: =+M95-U95 -> #REF! | X95: SEI0648 | Y95: =IFERROR(OFFSET('CPD PITSS'!$AN$8,MATCH('RESUMEN PITS'!C95,'CPD PITSS'!$B$9:$B$26,0),0),0)+IFERROR(OFFSET('IP PITSS'!$AL$8,MATCH('RESUMEN PITS'!C95,'IP PITSS'!$B$9:$B$90,0),0),0)+IFERROR(OFFSET('SIND PITS'!$Q$2,MATCH('RESUMEN PITS'!C95,'SIND PITS'!$C$3:$C$103,0),0),0) -> 5370.555
A96: SEI0541 | B96: IP INNOVACION | C96: Chavez Govea Edgar Aram | D96: =VLOOKUP(C96,'IP PITSS'!$B$9:$U$90,21,0) -> #REF! | F96: =VLOOKUP(C96,'SIND PITS'!$C$3:$D$100,2,0) -> 222.6 | G96: =VLOOKUP(C96,'SIND PITS'!$C$3:$E$100,3,0) -> 250 | H96: =VLOOKUP(C96,'SIND PITS'!$C$3:$F$100,4,0) -> 0 | I96: =VLOOKUP(C96,'SIND PITS'!$C$3:$G$100,5,0) -> 0 | K96: =SUM(D96:I96) -> #REF! | L96: 7000 | M96: =+L96/2 -> 3500 | O96: =VLOOKUP(C96,'[1]IP PITS'!$B$6:$I$87,8,0) -> 0 | P96: =+G96+H96+I96 -> 250 | Q96: =(VLOOKUP(C96,'IP PITSS'!$B$9:$M$90,10,0))+(VLOOKUP(C96,'IP PITSS'!$B$9:$M$90,11,0))+(VLOOKUP(C96,'IP PITSS'!$B$9:$M$90,12,0)) -> 0 | R96: =VLOOKUP(C96,'IP PITSS'!$B$9:$Q$90,17,0) -> #REF! | S96: =VLOOKUP(C96,'IP PITSS'!$B$9:$R$90,18,0) -> #REF! | U96: =+K96-O96-P96+Q96+R96+S96 -> #REF! | V96: =+M96-U96 -> #REF! | X96: SEI0644 | Y96: =IFERROR(OFFSET('CPD PITSS'!$AN$8,MATCH('RESUMEN PITS'!C96,'CPD PITSS'!$B$9:$B$26,0),0),0)+IFERROR(OFFSET('IP PITSS'!$AL$8,MATCH('RESUMEN PITS'!C96,'IP PITSS'!$B$9:$B$90,0),0),0)+IFERROR(OFFSET('SIND PITS'!$Q$2,MATCH('RESUMEN PITS'!C96,'SIND PITS'!$C$3:$C$103,0),0),0) -> 5195.069
A97: SEI0543 | B97: IP INNOVACION | C97: Diaz Ortiz Hiram Guillermo | D97: =VLOOKUP(C97,'IP PITSS'!$B$9:$U$90,21,0) -> #REF! | F97: =VLOOKUP(C97,'SIND PITS'!$C$3:$D$100,2,0) -> 174.46 | G97: =VLOOKUP(C97,'SIND PITS'!$C$3:$E$100,3,0) -> 590.63 | H97: =VLOOKUP(C97,'SIND PITS'!$C$3:$F$100,4,0) -> 0 | I97: =VLOOKUP(C97,'SIND PITS'!$C$3:$G$100,5,0) -> 0 | K97: =SUM(D97:I97) -> #REF! | L97: 6300 | M97: =+L97/2 -> 3150 | O97: =VLOOKUP(C97,'[1]IP PITS'!$B$6:$I$87,8,0) -> 0 | P97: =+G97+H97+I97 -> 590.63 | Q97: =(VLOOKUP(C97,'IP PITSS'!$B$9:$M$90,10,0))+(VLOOKUP(C97,'IP PITSS'!$B$9:$M$90,11,0))+(VLOOKUP(C97,'IP PITSS'!$B$9:$M$90,12,0)) -> 1088.14 | R97: =VLOOKUP(C97,'IP PITSS'!$B$9:$Q$90,17,0) -> #REF! | S97: =VLOOKUP(C97,'IP PITSS'!$B$9:$R$90,18,0) -> #REF! | U97: =+K97-O97-P97+Q97+R97+S97 -> #REF! | V97: =+M97-U97 -> #REF! | X97: SEI0646 | Y97: =IFERROR(OFFSET('CPD PITSS'!$AN$8,MATCH('RESUMEN PITS'!C97,'CPD PITSS'!$B$9:$B$26,0),0),0)+IFERROR(OFFSET('IP PITSS'!$AL$8,MATCH('RESUMEN PITS'!C97,'IP PITSS'!$B$9:$B$90,0),0),0)+IFERROR(OFFSET('SIND PITS'!$Q$2,MATCH('RESUMEN PITS'!C97,'SIND PITS'!$C$3:$C$103,0),0),0) -> 5103.7526
A98: SEI0544 | B98: IP INNOVACION | C98: Aguilar Aguirre Alfonso | D98: =VLOOKUP(C98,'IP PITSS'!$B$9:$U$90,21,0) -> #REF! | F98: =VLOOKUP(C98,'SIND PITS'!$C$3:$D$100,2,0) -> 135.2 | G98: =VLOOKUP(C98,'SIND PITS'!$C$3:$E$100,3,0) -> 0 | H98: =VLOOKUP(C98,'SIND PITS'!$C$3:$F$100,4,0) -> 0 | I98: =VLOOKUP(C98,'SIND PITS'!$C$3:$G$100,5,0) -> 0 | K98: =SUM(D98:I98) -> #REF! | L98: 6000 | M98: =+L98/2 -> 3000 | O98: =VLOOKUP(C98,'[1]IP PITS'!$B$6:$I$87,8,0) -> 0 | P98: =+G98+H98+I98 -> 0 | Q98: =(VLOOKUP(C98,'IP PITSS'!$B$9:$M$90,10,0))+(VLOOKUP(C98,'IP PITSS'!$B$9:$M$90,11,0))+(VLOOKUP(C98,'IP PITSS'!$B$9:$M$90,12,0)) -> 0 | R98: =VLOOKUP(C98,'IP PITSS'!$B$9:$Q$90,17,0) -> #REF! | S98: =VLOOKUP(C98,'IP PITSS'!$B$9:$R$90,18,0) -> #REF! | U98: =+K98-O98-P98+Q98+R98+S98 -> #REF! | V98: =+M98-U98 -> #REF! | X98: SEI0652 | Y98: =IFERROR(OFFSET('CPD PITSS'!$AN$8,MATCH('RESUMEN PITS'!C98,'CPD PITSS'!$B$9:$B$26,0),0),0)+IFERROR(OFFSET('IP PITSS'!$AL$8,MATCH('RESUMEN PITS'!C98,'IP PITSS'!$B$9:$B$90,0),0),0)+IFERROR(OFFSET('SIND PITS'!$Q$2,MATCH('RESUMEN PITS'!C98,'SIND PITS'!$C$3:$C$103,0),0),0) -> 4325.55
A99: SEI0545 | B99: IP INNOVACION | C99: Vallarta Fonseca Mayra Karina | D99: =VLOOKUP(C99,'IP PITSS'!$B$9:$U$90,21,0) -> #REF! | F99: =VLOOKUP(C99,'SIND PITS'!$C$3:$D$100,2,0) -> 135.21 | G99: =VLOOKUP(C99,'SIND PITS'!$C$3:$E$100,3,0) -> 0 | H99: =VLOOKUP(C99,'SIND PITS'!$C$3:$F$100,4,0) -> 0 | I99: =VLOOKUP(C99,'SIND PITS'!$C$3:$G$100,5,0) -> 0 | K99: =SUM(D99:I99) -> #REF! | L99: 6000 | M99: =+L99/2 -> 3000 | O99: =VLOOKUP(C99,'[1]IP PITS'!$B$6:$I$87,8,0) -> 0 | P99: =+G99+H99+I99 -> 0 | Q99: =(VLOOKUP(C99,'IP PITSS'!$B$9:$M$90,10,0))+(VLOOKUP(C99,'IP PITSS'!$B$9:$M$90,11,0))+(VLOOKUP(C99,'IP PITSS'!$B$9:$M$90,12,0)) -> 619.79 | R99: =VLOOKUP(C99,'IP PITSS'!$B$9:$Q$90,17,0) -> #REF! | S99: =VLOOKUP(C99,'IP PITSS'!$B$9:$R$90,18,0) -> #REF! | U99: =+K99-O99-P99+Q99+R99+S99 -> #REF! | V99: =+M99-U99 -> #REF! | X99: SEI0653 | Y99: =IFERROR(OFFSET('CPD PITSS'!$AN$8,MATCH('RESUMEN PITS'!C99,'CPD PITSS'!$B$9:$B$26,0),0),0)+IFERROR(OFFSET('IP PITSS'!$AL$8,MATCH('RESUMEN PITS'!C99,'IP PITSS'!$B$9:$B$90,0),0),0)+IFERROR(OFFSET('SIND PITS'!$Q$2,MATCH('RESUMEN PITS'!C99,'SIND PITS'!$C$3:$C$103,0),0),0) -> 4325.55
A100: SEI0547 | B100: IP INNOVACION | C100: Aguilar Garcia Rosa Paola | D100: =VLOOKUP(C100,'IP PITSS'!$B$9:$U$90,21,0) -> #REF! | F100: =VLOOKUP(C100,'SIND PITS'!$C$101:$D$101,2,0) -> 53.4 | G100: =VLOOKUP(C100,'SIND PITS'!C101:E104,3,0) -> 0 | H100: =VLOOKUP(C100,'SIND PITS'!C101:F104,4,0) -> 0 | I100: =VLOOKUP(C100,'SIND PITS'!$C$101:$G$101,5,0) -> 0 | K100: =SUM(D100:I100) -> #REF! | L100: 5000 | M100: =+L100/2 -> 2500 | O100: =VLOOKUP(C100,'[1]IP PITS'!$B$6:$I$87,8,0) -> 0 | P100: =+G100+H100+I100 -> 0 | Q100: =(VLOOKUP(C100,'IP PITSS'!$B$9:$M$90,10,0))+(VLOOKUP(C100,'IP PITSS'!$B$9:$M$90,11,0))+(VLOOKUP(C100,'IP PITSS'!$B$9:$M$90,12,0)) -> 0 | R100: =VLOOKUP(C100,'IP PITSS'!$B$9:$Q$90,17,0) -> #REF! | S100: =VLOOKUP(C100,'IP PITSS'!$B$9:$R$90,18,0) -> #REF! | U100: =+K100-O100-P100+Q100+R100+S100 -> #REF! | V100: =+M100-U100 -> #REF! | Y100: =IFERROR(OFFSET('CPD PITSS'!$AN$8,MATCH('RESUMEN PITS'!C100,'CPD PITSS'!$B$9:$B$26,0),0),0)+IFERROR(OFFSET('IP PITSS'!$AL$8,MATCH('RESUMEN PITS'!C100,'IP PITSS'!$B$9:$B$90,0),0),0)+IFERROR(OFFSET('SIND PITS'!$Q$2,MATCH('RESUMEN PITS'!C100,'SIND PITS'!$C$3:$C$103,0),0),0) -> 3711.061
A101: SEI0548 | B101: IP INNOVACION | C101: Jauregui Madera Jorge Silvestre | D101: =VLOOKUP(C101,'IP PITSS'!$B$9:$U$90,21,0) -> #REF! | F101: =+'SIND PITS'!D102 -> 308.8 | G101: =VLOOKUP(C101,'SIND PITS'!C102:E106,3,0) -> 325 | H101: =VLOOKUP(C101,'SIND PITS'!C102:F106,4,0) -> 0 | I101: =+'SIND PITS'!G102 -> 0 | K101: =SUM(D101:I101) -> #REF! | L101: 6000 | M101: =+L101/2 -> 3000 | O101: =VLOOKUP(C101,'[1]IP PITS'!$B$6:$I$87,8,0) -> 0 | P101: =+G101+H101+I101 -> 325 | Q101: =(VLOOKUP(C101,'IP PITSS'!$B$9:$M$90,10,0))+(VLOOKUP(C101,'IP PITSS'!$B$9:$M$90,11,0))+(VLOOKUP(C101,'IP PITSS'!$B$9:$M$90,12,0)) -> 0 | R101: =VLOOKUP(C101,'IP PITSS'!$B$9:$Q$90,17,0) -> #REF! | S101: =VLOOKUP(C101,'IP PITSS'!$B$9:$R$90,18,0) -> #REF! | U101: =+K101-O101-P101+Q101+R101+S101 -> #REF! | V101: =+M101-U101 -> #REF! | W101: 1 P. S/sueldo | Y101: =IFERROR(OFFSET('CPD PITSS'!$AN$8,MATCH('RESUMEN PITS'!C101,'CPD PITSS'!$B$9:$B$26,0),0),0)+IFERROR(OFFSET('IP PITSS'!$AL$8,MATCH('RESUMEN PITS'!C101,'IP PITSS'!$B$9:$B$90,0),0),0)+IFERROR(OFFSET('SIND PITS'!$Q$2,MATCH('RESUMEN PITS'!C101,'SIND PITS'!$C$3:$C$103,0),0),0) -> 4641.19
B102: IP INNOVACION | C102: Negrete Bejar Aide Sarai | D102: =VLOOKUP(C102,'IP PITSS'!$B$9:$U$90,21,0) -> #REF! | F102: =VLOOKUP(C102,'SIND PITS'!$C$3:$D$100,2,0) -> 392.29 | G102: =VLOOKUP(C102,'SIND PITS'!$C$3:$E$100,3,0) -> 2642.92 | H102: =VLOOKUP(C102,'SIND PITS'!$C$3:$F$100,4,0) -> 0 | I102: =VLOOKUP(C102,'SIND PITS'!$C$3:$G$100,5,0) -> 0 | K102: =SUM(D102:I102) -> #REF! | L102: 5000 | M102: =+L102/2 -> 2500 | O102: =VLOOKUP(C102,'[1]IP PITS'!$B$6:$I$87,8,0) -> 184.8 | P102: =+G102+H102+I102 -> 2642.92 | Q102: =(VLOOKUP(C102,'IP PITSS'!$B$9:$M$90,10,0))+(VLOOKUP(C102,'IP PITSS'!$B$9:$M$90,11,0))+(VLOOKUP(C102,'IP PITSS'!$B$9:$M$90,12,0)) -> 971.31 | R102: =VLOOKUP(C102,'IP PITSS'!$B$9:$Q$90,17,0) -> #REF! | S102: =VLOOKUP(C102,'IP PITSS'!$B$9:$R$90,18,0) -> #REF! | U102: =+K102-O102-P102+Q102+R102+S102 -> #REF! | V102: =+M102-U102 -> #REF! | Y102: =IFERROR(OFFSET('CPD PITSS'!$AN$8,MATCH('RESUMEN PITS'!C102,'CPD PITSS'!$B$9:$B$26,0),0),0)+IFERROR(OFFSET('IP PITSS'!$AL$8,MATCH('RESUMEN PITS'!C102,'IP PITSS'!$B$9:$B$90,0),0),0)+IFERROR(OFFSET('SIND PITS'!$Q$2,MATCH('RESUMEN PITS'!C102,'SIND PITS'!$C$3:$C$103,0),0),0) -> 6549.2844
B103: IP INNOVACION | C103: Hinojosa Guerrero Alejandro | D103: =VLOOKUP(C103,'IP PITSS'!$B$9:$U$90,21,0) -> #REF! | F103: 0 | K103: =SUM(D103:I103) -> #REF! | L103: 6300 | M103: =+L103/2 -> 3150 | Q103: =(VLOOKUP(C103,'IP PITSS'!$B$9:$M$90,10,0))+(VLOOKUP(C103,'IP PITSS'!$B$9:$M$90,11,0))+(VLOOKUP(C103,'IP PITSS'!$B$9:$M$90,12,0)) -> 0 | R103: =VLOOKUP(C103,'IP PITSS'!$B$9:$Q$90,17,0) -> #REF! | S103: =VLOOKUP(C103,'IP PITSS'!$B$9:$R$90,18,0) -> #REF! | U103: =+K103-O103-P103+Q103+R103+S103 -> #REF! | V103: =+M103-U103 -> #REF! | W103: INGRESO13/05 | Y103: =IFERROR(OFFSET('CPD PITSS'!$AN$8,MATCH('RESUMEN PITS'!C103,'CPD PITSS'!$B$9:$B$26,0),0),0)+IFERROR(OFFSET('IP PITSS'!$AL$8,MATCH('RESUMEN PITS'!C103,'IP PITSS'!$B$9:$B$90,0),0),0)+IFERROR(OFFSET('SIND PITS'!$Q$2,MATCH('RESUMEN PITS'!C103,'SIND PITS'!$C$3:$C$103,0),0),0) -> 1365.172
C104: TOTAL GENERAL | D104: =SUBTOTAL(9,D3:D103) -> #REF! | F104: =SUBTOTAL(9,F3:F103) -> 151352.49 | G104: =SUBTOTAL(9,G3:G103) -> 37527.93 | H104: =SUBTOTAL(9,H3:H103) -> 10960 | I104: =SUBTOTAL(9,I3:I103) -> 796.42 | K104: =SUBTOTAL(9,K3:K103) -> #REF! | L104: =SUBTOTAL(9,L3:L103) -> 1015831 | M104: =SUBTOTAL(9,M3:M103) -> 507915.51 | O104: =SUBTOTAL(9,O3:O103) -> 2789.13 | P104: =SUBTOTAL(9,P3:P103) -> 49284.35 | Q104: =SUBTOTAL(9,Q3:Q103) -> 40282.54 | R104: =SUBTOTAL(9,R3:R103) -> #REF! | S104: =SUBTOTAL(9,S3:S103) -> #REF! | U104: =SUBTOTAL(9,U3:U103) -> #REF! | V104: =SUBTOTAL(9,V3:V103) -> #REF! | W104: =SUBTOTAL(9,W3:W102) -> 0 | X104: =SUBTOTAL(9,X3:X102) -> 0 | Z104: =SUM(Z3:Z101) -> 0 | AA104: =SUM(AA3:AA100) -> 0 | AB104: =SUM(AB3:AB100) -> 0 | AC104: =SUM(AC3:AC100) -> 0 | AD104: =SUM(AD3:AD100) -> 0 | AE104: =SUM(AE3:AE100) -> 0 | AF104: =SUM(AF3:AF90) -> 0
M106: =+M101/15 -> 200
F107: =+F101+D101+H107 -> #REF! | M107: =+M106*14 -> 2800

Sheet FACTURACION
D8: TOTAL FACTURACION NOMINA | H8: TOTAL PROV AGUINALDOS
D9: TOTAL CPD | E9: =+'CPD PITSS'!M43 -> 138671.47 | H9: TOTAL CPD | I9: =+'CPD PITSS'!M53 -> 6065.6936
D10: TOTAL IP | E10: =+'IP PITSS'!J107 -> 446354.44 | H10: TOTAL IP | I10: =+'IP PITSS'!J117 -> 19410.868
D11: TOTAL SINDICATO | E11: =+'SIND PITS'!H115 -> 237393.5
E12: =+E9+E10+E11 -> 822419.41 | I12: =+I9+I10+I11 -> 25476.562
D14: PORCENTAJES POR EMPRESA | F14: PEDIDO | H14: PORCENTAJES POR EMPRESA
D15: EM 4% | E15: =+E12*4% -> 32896.776 | F15: 49 | H15: EM 4% | I15: =+I12*4% -> 1019.0625
D16: CPD 12% | E16: =+E12*12% -> 98690.329 | F16: 49 | H16: CPD 12% | I16: =+I12*12% -> 3057.1874
D17: IP 11% | E17: =+E12*11% -> 90466.135 | F17: 39 | H17: IP 11% | I17: =+I12*11% -> 2802.4218
D18: ITA 73% | E18: =+E12*73% -> 600366.17 | F18: 107 | H18: ITA 73% | I18: =+I12*73% -> 18597.89
E19: =SUM(E15:E18) -> 822419.41 | I19: =SUM(I15:I18) -> 25476.562

Sheet ASIMILADOS
A1: CONSULTORIA EN PROYECTOS DINAMICOS
A2: CALCULO DE PAGO POR ASIMILADOS Y/O COMISIONES
D6: QUINCENAL | E6: FACTURACION
A7: Nombre | B7: SUELDO MENSUAL | C7: IMSS | D7: Asimilados | E7: Comision 2% | F7: SUBTOTAL | G7: IVA | H7: TOTAL
A8: PABLO BENAVIDES HERRERA | B8: 70000 | C8: 2865.8 | D8: =(B8/2)-C8 -> 32134.2 | E8: =+D8*0.02 -> 642.684 | F8: =+D8+E8 -> 32776.884 | G8: =F8*0.16 -> 5244.3014 | H8: =+F8+G8 -> 38021.185 | I8: SE FACTURA A PITSS
A10: TOTALES | B10: =SUM(B8:B8) -> 70000 | C10: =SUM(C8:C8) -> 2865.8 | D10: =SUM(D8:D8) -> 32134.2 | E10: =SUM(E8:E8) -> 642.684 | F10: =SUM(F8:F8) -> 32776.884 | G10: =SUM(G8:G8) -> 5244.3014 | H10: =SUM(H8:H8) -> 38021.185
