Workbook

Sheet CPD PITSS
B2: CONSULTORIA EN PROYECTOS DINAMICOS S DE RL DE CV
B3: Lista de Raya (forma tabular)
B4: Reg Pat IMSS: Z2940859106
B5: RFC: CPD -150911-FA3
B7: 1 | C7: =+B7+1 -> 2 | D7: =+C7+1 -> 3 | E7: =+D7+1 -> 4 | F7: =+E7+1 -> 5 | G7: =+F7+1 -> 6 | H7: =+G7+1 -> 7 | I7: =+H7+1 -> 8 | J7: =+I7+1 -> 9 | ... V7: =+U7+1 -> 21
A8: Código | B8: Empleado | C8: Dias Laborados | D8: Dias Vacaciones | E8: Salario Diario | F8: Salario Diario Integrado | G8: Sueldo | H8: Vacaciones a tiempo | I8: Prima de vacaciones a tiempo | J8: Ayuda de Transporte | K8: Ayuda Alimentaria | L8: Ayuda de Renta | M8: *TOTAL* *PERCEPCIONES* | N8: Seguro de vivienda Infonavit | O8: Préstamo Infonavit (vsm) | P8: Subsidio al Empleo (sp) | Q8: I.S.R. (sp) | R8: I.M.S.S. | S8: Deduccion General | T8: Ajuste al neto | U8: *TOTAL* *DEDUCCIONES* | V8: *NETO* | W8: Invalidez y Vida | X8: Cesantia y Vejez | Y8: Enf. y Mat. Patron | Z8: 2% Fondo retiro SAR (8) | AA8: 2% Impuesto estatal | AB8: Riesgo de trabajo (9) | AC8: I.M.S.S. empresa | AD8: Infonavit empresa | AE8: Guarderia I.M.S.S. (7) | AF8: Banco | AG8: Aguinaldo
A9: SEI0009 | B9: Gutierrez Gutierrez Luis Arturo | C9: 15 | D9: 0 | E9: 141.67 | F9: 150.25 | G9: 2125.05 | H9: 0 | I9: 0 | J9: 212.51 | K9: 212.51 | L9: 212.51 | M9: 2762.58 | N9: 0 | O9: 0 | P9: -65.5 | Q9: 0 | R9: 53.52 | S9: 0 | T9: -0.04 | U9: -12.02 | V9: 2774.6 | W9: 39.44 | X9: 70.99 | Y9: 297.98 | Z9: 183.93 | AA9: 55.25 | AB9: 11.27 | AC9: 408.41 | AD9: 112.69 | AE9: 161.39 | AF9: 110 | AG9: =((20/365.24)*15)*($E9*1.3) -> 151.27396
A10: SEI0026 | B10: Patricio Aguilar Jhonattan Cristian | C10: 15 | D10: 0 | E10: 150 | F10: 159.07 | G10: 2250 | H10: 0 | I10: 0 | J10: 225 | K10: 225 | L10: 225 | M10: 2925 | N10: 0 | O10: 0 | P10: -43.57 | Q10: 0 | R10: 56.67 | S10: 0 | T10: -0.1 | U10: 13 | V10: 2912 | W10: 41.76 | X10: 75.16 | Y10: 300.29 | Z10: 186.57 | AA10: 58.5 | AB10: 11.93 | AC10: 417.21 | AD10: 119.31 | AE10: 162.71 | AF10: 110 | AG10: =((20/365.24)*15)*($E10*1.3) -> 160.16866
A11: SEI0040 | B11: Mora Ramirez Acal Aldo Isidro | C11: 15 | D11: 0 | E11: 216.67 | F11: 229.79 | G11: 3250.05 | H11: 0 | I11: 0 | J11: 325.01 | K11: 325.01 | L11: 325.01 | M11: 4225.08 | N11: 0 | O11: 0 | P11: 0 | Q11: 107.17 | R11: 81.87 | S11: 0 | T11: 0.04 | U11: 189.08 | V11: 4036 | W11: 60.32 | X11: 108.58 | Y11: 318.86 | Z11: 207.79 | AA11: 84.5 | AB11: 17.23 | AC11: 487.76 | AD11: 172.34 | AE11: 173.32 | AF11: 110 | AG11: =((20/365.24)*15)*($E11*1.3) -> 231.35828
A12: SEI0041 | B12: Vazquez Perez Miguel Angel | C12: 15 | D12: 0 | E12: 283.33 | F12: 300.49 | G12: 4249.95 | H12: 0 | I12: 0 | J12: 425 | K12: 425 | L12: 425 | M12: 5524.95 | N12: 0 | O12: 0 | P12: 0 | Q12: 341.06 | R12: 109.87 | S12: 0 | T12: 0.02 | U12: 450.95 | V12: 5074 | W12: 78.88 | X12: 141.98 | Y12: 345.18 | Z12: 229 | AA12: 110.5 | AB12: 22.54 | AC12: 566.04 | AD12: 225.37 | AE12: 183.92 | AF12: 110 | AG12: =((20/365.24)*15)*($E12*1.3) -> 302.53724
A13: SEI0088 | B13: Morgado Fernandez Martin | C13: 15 | D13: 0 | E13: 273.33 | F13: 289.87 | G13: 4099.95 | H13: 0 | I13: 0 | J13: 410 | K13: 410 | L13: 410 | M13: 5329.95 | N13: 0 | O13: 0 | P13: 0 | Q13: 324.74 | R13: 105.46 | S13: 275.95 | T13: 0 | U13: 706.15 | V13: 4623.8 | W13: 76.09 | X13: 136.96 | Y13: 340.64 | Z13: 225.81 | AA13: 106.6 | AB13: 21.74 | AC13: 553.69 | AD13: 217.4 | AE13: 182.33 | AF13: 110 | AG13: =((20/365.24)*15)*($E13*1.3) -> 291.85933
A14: SEI0097 | B14: Arreola Jimenez Jose Nieves | C14: 15 | D14: 0 | E14: 185.83 | F14: 197.07 | G14: 2787.45 | H14: 0 | I14: 0 | J14: 278.75 | K14: 278.75 | L14: 278.75 | M14: 3623.7 | N14: 0 | O14: 1541.78 | P14: 0 | Q14: 36.57 | R14: 70.22 | S14: 308.55 | T14: -0.02 | U14: 1957.1 | V14: 1666.6 | W14: 51.73 | X14: 93.12 | Y14: 310.27 | Z14: 197.97 | AA14: 72.47 | AB14: 14.78 | AC14: 455.12 | AD14: 147.8 | AE14: 168.41 | AF14: 110 | AG14: =((20/365.24)*15)*($E14*1.3) -> 198.42761
A15: SEI0099 | B15: Garcia Villicaña Ricardo Pascual | C15: 15 | D15: 0 | E15: 273.33 | F15: 289.87 | G15: 4099.95 | H15: 0 | I15: 0 | J15: 410 | K15: 410 | L15: 410 | M15: 5329.95 | N15: 0 | O15: 0 | P15: 0 | Q15: 324.74 | R15: 105.46 | S15: 213.55 | T15: 0 | U15: 643.75 | V15: 4686.2 | W15: 76.09 | X15: 136.96 | Y15: 340.64 | Z15: 225.81 | AA15: 106.6 | AB15: 21.74 | AC15: 553.69 | AD15: 217.4 | AE15: 182.33 | AF15: 110 | AG15: =((20/365.24)*15)*($E15*1.3) -> 291.85933
A16: SEI0108 | B16: Caballero Diaz Francisco Javier | C16: 15 | D16: 0 | E16: 185.83 | F16: 197.07 | G16: 2787.45 | H16: 0 | I16: 0 | J16: 278.75 | K16: 278.75 | L16: 278.75 | M16: 3623.7 | N16: 0 | O16: 1789.38 | P16: 0 | Q16: 36.57 | R16: 70.22 | S16: 238.8 | T16: -0.07 | U16: 2134.9 | V16: 1488.8 | W16: 51.73 | X16: 93.12 | Y16: 310.27 | Z16: 197.97 | AA16: 72.47 | AB16: 14.78 | AC16: 455.12 | AD16: 147.8 | AE16: 168.41 | AF16: 110 | AG16: =((20/365.24)*15)*($E16*1.3) -> 198.42761
A17: SEI0116 | B17: Casillas Cardona Cesar Alejandro | C17: 10 | D17: 5 | E17: 220.83 | F17: 234.19 | G17: 2208.3 | H17: 1104.15 | I17: 331.25 | J17: 331.25 | K17: 331.25 | L17: 331.25 | M17: 4637.45 | N17: 0 | O17: 894.93 | P17: 0 | Q17: 113.96 | R17: 83.43 | S17: 0 | T17: -0.07 | U17: 1092.25 | V17: 3545.2 | W17: 61.47 | X17: 110.65 | Y17: 320.01 | Z17: 209.11 | AA17: 92.75 | AB17: 17.56 | AC17: 492.13 | AD17: 175.64 | AE17: 173.98 | AF17: 110 | AG17: =((20/365.24)*15)*($E17*1.3) -> 235.8003
A18: SEI0117 | B18: Mariscal Romero Luis Adrian | C18: 12 | D18: 3 | E18: 264.58 | F18: 276.54 | G18: 3174.96 | H18: 793.74 | I18: 238.12 | J18: 396.87 | K18: 396.87 | L18: 396.87 | M18: 5397.43 | N18: 0 | O18: 0 | P18: 0 | Q18: 310.46 | R18: 99.91 | S18: 0 | T18: -0.14 | U18: 410.23 | V18: 4987.2 | W18: 72.59 | X18: 130.66 | Y18: 334.94 | Z18: 221.81 | AA18: 107.95 | AB18: 20.74 | AC18: 538.19 | AD18: 207.4 | AE18: 180.33 | AF18: 110 | AG18: =((20/365.24)*15)*($E18*1.3) -> 282.51615
A19: SEI0118 | B19: Arroyo Ramirez Hector Hugo | C19: 14 | D19: 1 | E19: 238.33 | F19: 252.75 | G19: 3336.62 | H19: 238.33 | I19: 71.5 | J19: 357.5 | K19: 357.5 | L19: 357.5 | M19: 4718.95 | N19: 0 | O19: 1402.48 | P19: 0 | Q19: 160.25 | R19: 90.05 | S19: 0 | T19: -0.01 | U19: 1660.55 | V19: 3058.4 | W19: 66.35 | X19: 119.42 | Y19: 324.89 | Z19: 214.67 | AA19: 94.38 | AB19: 18.96 | AC19: 510.66 | AD19: 189.56 | AE19: 176.76 | AF19: 110 | AG19: =((20/365.24)*15)*($E19*1.3) -> 254.48664
A20: SEI0127 | B20: Hernandez Ochoa Eduardo | C20: 15 | D20: 0 | E20: 273.33 | F20: 289.87 | G20: 4099.95 | H20: 0 | I20: 0 | J20: 410 | K20: 410 | L20: 410 | M20: 5329.95 | N20: 0 | O20: 0 | P20: 0 | Q20: 324.74 | R20: 105.46 | S20: 0 | T20: -0.05 | U20: 430.15 | V20: 4899.8 | W20: 76.09 | X20: 136.96 | Y20: 340.64 | Z20: 225.81 | AA20: 106.6 | AB20: 21.74 | AC20: 553.69 | AD20: 217.4 | AE20: 182.33 | AF20: 110 | AG20: =((20/365.24)*15)*($E20*1.3) -> 291.85933
... A26: SEI0442 | B26: Sierra Escamilla Daniela | C26: 15 | D26: 0 | E26: 216.67 | F26: 229.79 | G26: 3250.05 | H26: 0 | I26: 0 | J26: 325.01 | K26: 325.01 | L26: 325.01 | M26: 4225.08 | N26: 0 | O26: 0 | P26: 0 | Q26: 107.17 | R26: 81.87 | S26: 0 | T26: 0.04 | U26: 189.08 | V26: 4036 | W26: 60.32 | X26: 108.58 | Y26: 318.86 | Z26: 207.79 | AA26: 84.5 | AB26: 17.23 | AC26: 487.76 | AD26: 172.34 | AE26: 173.32 | AF26: 110 | AG26: =((20/365.24)*15)*($E26*1.3) -> 231.35828
C27: ============= | D27: ============= | E27: ============= | F27: ============= | G27: ============= | H27: ============= | I27: ============= | J27: ============= | K27: ============= | L27: ============= | M27: ============= | N27: ============= | O27: ============= | P27: ============= | Q27: ============= | R27: ============= | S27: ============= | T27: ============= | U27: ============= | V27: ============= | W27: ============= | X27: ============= | Y27: ============= | Z27: ============= | AA27: ============= | AB27: ============= | AC27: ============= | AD27: ============= | AE27: ============= | AF27: ============= | AG27: =============
A28: Total Gral. | C28: =SUM(C9:C26) -> 252 | D28: =SUM(D9:D26) -> 18 | E28: =SUM(E9:E26) -> 4708.72 | F28: =SUM(F9:F26) -> 4989.65 | G28: =SUM(G9:G26) -> 66822.11 | H28: =SUM(H9:H26) -> 3808.69 | I28: =SUM(I9:I26) -> 1142.61 | J28: =SUM(J9:J26) -> 7063.16 | ... AG28: =SUM(AG9:AG26) -> 5027.929
A30: 18 | B30: Nomina
B31: Altas | L31: FACTURACION PITS | N31: VENTAS | O31: ADMON | P31: SERVICIO
B32: Bajas | L32: Devengado Salario | M32: =+V28 -> 75245.8 | O32: 28375.2 | P32: =M32-O32 -> 46870.6
A33: =+A30+A31-A32 -> 18 | B33: Total Nomina | L33: RETORNOS | M33: =+S28 -> 1614.38 | O33: =S22 -> 280.53 | P33: =M33-O33 -> 1333.85
L34: Infonavit | M34: =+N28+O28 -> 9230.05 | P34: =M34 -> 9230.05
L35: Prestamo Prospera | M35: 0
L36: Subtotal 1 | M36: =SUM(M32:M35) -> 86090.23 | N36: =SUM(N32:N35) -> 0 | O36: =SUM(O32:O35) -> 28655.73 | P36: =SUM(P32:P35) -> 57434.5
L37: Comision | M37: =+M36*2% -> 1721.8046 | O37: =O36*2% -> 573.1146 | P37: =P36*2% -> 1148.69
L38: Subtotal 2 | M38: =+M36+M37 -> 87812.035 | O38: =SUM(O36:O37) -> 29228.845 | P38: =SUM(P36:P37) -> 58583.19
L39: Costo Patronal Imss | M39: =+R28+W28+X28+Y28+AB28+Z28+AD28+AE28 -> 23005.39 | O39: 6971.36 | P39: =M39-O39 -> 16034.03
L40: 2% Sobre Nomina | M40: =+M28*2% -> 1859.2578 | O40: =32386.44*2% -> 647.7288 | P40: =M40-O40 -> 1211.529
L41: Importe de Factura | M41: =+M38+M39+M40 -> 112676.68 | O41: =SUM(O38:O40) -> 36847.933 | P41: =SUM(P38:P40) -> 75828.749
L42: IVA | M42: =+M41*16% -> 18028.269 | O42: =O41*16% -> 5895.6693 | P42: =P41*16% -> 12132.6
L43: TOTAL | M43: =+M41+M42 -> 130704.95 | O43: =O42+O41 -> 42743.603 | P43: =P42+P41 -> 87961.349
O44: =O41-O37 -> 36274.819 | P44: =P41-P37 -> 74680.059
L45: PROVISION AGUINALDO | O45: 0.73 | P45: 0.11 | Q45: 0.12 | R45: 0.04
L46: FACTURACION PITS | O46: ITA | P46: IP | Q46: CPD | R46: EM
L47: Subtotal 1 | M47: =+AG28 -> 5027.929 | N47: ADMON | O47: =O44*$O$45 -> 26480.618 | P47: =O44*$P$45 -> 3990.2301 | Q47: =O44*$Q$45 -> 4352.9783 | R47: =O44*$R$45 -> 1450.9928
L48: Comision | M48: =+M47*2% -> 100.55858 | N48: SERVICIO | O48: =P44*$O$45 -> 54516.443 | P48: =P44*$P$45 -> 8214.8065 | Q48: =P44*Q45 -> 8961.6071 | R48: =P44*$R$45 -> 2987.2024
L49: Subtotal 2 | M49: =+M47+M48 -> 5128.4876 | N49: VENTAS
L50: 2% Sobre Nomina | M50: =+M47*2% -> 100.55858 | N50: COMISIONES | O50: =M37*$O$45 -> 1256.9174 | P50: =M37*$P$45 -> 189.39851 | Q50: =M37*$Q$45 -> 206.61655 | R50: =M37*$R$45 -> 68.872184
L51: Importe de Factura | M51: =+M49+M50 -> 5229.0462 | N51: SUBTOTAL | O51: =SUM(O47:O50) -> 82253.978 | P51: =SUM(P47:P50) -> 12394.435 | Q51: =SUM(Q47:Q50) -> 13521.202 | R51: =SUM(R47:R50) -> 4507.0673
L52: IVA | M52: =+M51*16% -> 836.64739 | N52: IVA | O52: =O51*16% -> 13160.637 | P52: =P51*16% -> 1983.1096 | Q52: =Q51*16% -> 2163.3923 | R52: =R51*16% -> 721.13077
L53: TOTAL | M53: =+M51+M52 -> 6065.6936 | N53: TOTAL | O53: =SUM(O51:O52) -> 95414.615 | P53: =SUM(P51:P52) -> 14377.545 | Q53: =SUM(Q51:Q52) -> 15684.594 | R53: =SUM(R51:R52) -> 5228.1981

Sheet IP PITSS
B2: IP INNOVACION EN PROYECTOS S DE RL DE CV
B3: Lista de Raya (forma tabular)
B4: Reg Pat IMSS: R1363592103
B5: RFC: IIP -150923-DT7
A8: Código | B8: Empleado | C8: Dias Laborados | D8: Dias Vacaciones | E8: Salario Diario | F8: Salario Diario Integrado | G8: Sueldo | H8: Vacaciones a tiempo | I8: Prima de vacaciones a tiempo | J8: *TOTAL* *PERCEPCIONES* | K8: Seguro de vivienda Infonavit | L8: Préstamo Infonavit (vsm) | M8: Préstamo Infonavit (cf) | N8: Subsidio al Empleo (sp) | O8: I.S.R. (sp) | P8: I.M.S.S. | Q8: Préstamo FONACOT | R8: Deduccion general | S8: Ajuste al neto | T8: *TOTAL* *DEDUCCIONES* | U8: *NETO* | V8: Invalidez y Vida | W8: Cesantia y Vejez | X8: Enf. y Mat. Patron | Y8: 2% Fondo retiro SAR (8) | Z8: 2% Impuesto estatal | AA8: Riesgo de trabajo (9) | AB8: I.M.S.S. empresa | AC8: Infonavit empresa | AD8: Guarderia I.M.S.S. (7) | AE8: Banco | AF8: Aguinaldo
A9: SEI0010 | B9: Torres Ricardez Alfredo | C9: 15 | D9: 0 | E9: 266.67 | F9: 278.72 | G9: 4000.05 | H9: 0 | I9: 0 | J9: 4000.05 | K9: 0 | L9: 0 | M9: 0 | N9: 0 | O9: 313.87 | P9: 100.81 | Q9: 0 | R9: 250 | S9: -0.03 | T9: 664.65 | U9: 3335.4 | V9: 73.16 | W9: 131.7 | X9: 335.88 | Y9: 273.62 | Z9: 80 | AA9: 33.3 | AB9: 540.74 | AC9: 209.04 | AD9: 231.81 | AE9: 110 | AF9: =((20/365.24)*15)*E9 -> 219.0368
A10: SEI0014 | B10: Montoya Portillo Carlos Alberto | C10: 15 | D10: 0 | E10: 266.67 | F10: 278.72 | G10: 4000.05 | H10: 0 | I10: 0 | J10: 4000.05 | K10: 0 | L10: 0 | M10: 0 | N10: 0 | O10: 313.87 | P10: 100.81 | Q10: 0 | R10: 0 | S10: -0.03 | T10: 414.65 | U10: 3585.4 | V10: 73.16 | W10: 131.7 | X10: 335.88 | Y10: 273.62 | Z10: 80 | AA10: 33.3 | AB10: 540.74 | AC10: 209.04 | AD10: 231.81 | AE10: 110 | AF10: =((20/365.24)*15)*E10 -> 219.0368
A11: SEI0015 | B11: Cota Jaramillo Miguel Angel | C11: 15 | D11: 0 | E11: 200 | F11: 209.04 | G11: 3000 | H11: 0 | I11: 0 | J11: 3000 | K11: 0 | L11: 0 | M11: 0 | N11: 0 | O11: 59.69 | P11: 74.48 | Q11: 0 | R11: 1125 | S11: 0.03 | T11: 1259.2 | U11: 1740.8 | V11: 54.87 | W11: 98.77 | X11: 313.41 | Y11: 252.71 | Z11: 60 | AA11: 24.98 | AB11: 467.05 | AC11: 156.78 | AD11: 221.36 | AE11: 110 | AF11: =((20/365.24)*15)*E11 -> 164.27554
A12: SEI0016 | B12: Negrete Bejar Aide Sarai | C12: 15 | D12: 0 | E12: 154 | F12: 160.96 | G12: 2310 | H12: 0 | I12: 0 | J12: 2310 | K12: 0 | L12: 977.57 | M12: 0 | N12: -39.73 | O12: 0 | P12: 57.34 | Q12: 0 | R12: 0 | S12: 0.02 | T12: 995.2 | U12: 1314.8 | V12: 42.25 | W12: 76.05 | X12: 300.79 | Y12: 238.29 | Z12: 46.2 | AA12: 19.23 | AB12: 419.09 | AC12: 120.72 | AD12: 214.14 | AE12: 110 | AF12: =((20/365.24)*15)*E12 -> 126.49217
A13: SEI0017 | B13: Muñoz Reyes Luis Eduardo | C13: 15 | D13: 0 | E13: 266.67 | F13: 278.72 | G13: 4000.05 | H13: 0 | I13: 0 | J13: 4000.05 | K13: 0 | L13: 868.44 | M13: 0 | N13: 0 | O13: 313.87 | P13: 100.81 | Q13: 0 | R13: 0 | S13: -0.07 | T13: 1283.05 | U13: 2717 | V13: 73.16 | W13: 131.7 | X13: 335.88 | Y13: 273.62 | Z13: 80 | AA13: 33.3 | AB13: 540.74 | AC13: 209.04 | AD13: 231.81 | AE13: 110 | AF13: =((20/365.24)*15)*E13 -> 219.0368
A14: SEI0019 | B14: Gonzalez Rasgado Miguel Isaias | C14: 15 | D14: 0 | E14: 521.68 | F14: 553.24 | G14: 7825.2 | H14: 0 | I14: 0 | J14: 7825.2 | K14: 0 | L14: 0 | M14: 0 | N14: 0 | O14: 1033.24 | P14: 215.09 | Q14: 0 | R14: 0 | S14: -0.13 | T14: 1248.2 | U14: 6577 | V14: 145.23 | W14: 261.41 | X14: 453.23 | Y14: 355.97 | Z14: 156.5 | AA14: 66.11 | AB14: 859.87 | AC14: 414.93 | AD14: 272.99 | AE14: 110 | AF14: =((20/365.24)*15)*E14 -> 428.49633
A15: SEI0020 | B15: Mar Marquez Cesar Eduardo | C15: 15 | D15: 0 | E15: 266.67 | F15: 278.72 | G15: 4000.05 | H15: 0 | I15: 0 | J15: 4000.05 | K15: 0 | L15: 0 | M15: 0 | N15: 0 | O15: 313.87 | P15: 100.81 | Q15: 0 | R15: 0 | S15: -0.03 | T15: 414.65 | U15: 3585.4 | V15: 73.16 | W15: 131.7 | X15: 335.88 | Y15: 273.62 | Z15: 80 | AA15: 33.3 | AB15: 540.74 | AC15: 209.04 | AD15: 231.81 | AE15: 110 | AF15: =((20/365.24)*15)*E15 -> 219.0368
A16: SEI0021 | B16: Velez Rodriguez Jaime | C16: 15 | D16: 0 | E16: 200 | F16: 212.1 | G16: 3000 | H16: 0 | I16: 0 | J16: 3000 | K16: 0 | L16: 1347.1 | M16: 0 | N16: 0 | O16: 59.69 | P16: 75.55 | Q16: 0 | R16: 0 | S16: -0.14 | T16: 1482.2 | U16: 1517.8 | V16: 55.68 | W16: 100.22 | X16: 314.22 | Y16: 253.63 | Z16: 60 | AA16: 25.34 | AB16: 470.12 | AC16: 159.08 | AD16: 221.82 | AE16: 110 | AF16: =((20/365.24)*15)*E16 -> 164.27554
A17: SEI0022 | B17: Najera Lopez Raul | C17: 14 | D17: 0 | E17: 333.33 | F17: 353.5 | G17: 4666.62 | H17: 0 | I17: 0 | J17: 4666.62 | K17: 0 | L17: 0 | M17: 0 | N17: 0 | O17: 407.33 | P17: 125.75 | Q17: 0 | R17: 0 | S17: -0.06 | T17: 533.02 | U17: 4133.6 | V17: 92.79 | W17: 167.03 | X17: 367.84 | Y17: 296.05 | Z17: 93.33 | AA17: 42.24 | AB17: 627.66 | AC17: 265.12 | AD17: 243.02 | AE17: 110 | AF17: =((20/365.24)*15)*E17 -> 273.78984
A18: SEI0023 | B18: Puente Murguia Luis Felipe | C18: 15 | D18: 0 | E18: 233.33 | F18: 247.45 | G18: 3499.95 | H18: 0 | I18: 0 | J18: 3499.95 | K18: 0 | L18: 0 | M18: 0 | N18: 0 | O18: 134.36 | P18: 88.16 | Q18: 0 | R18: 0 | S18: -0.17 | T18: 222.35 | U18: 3277.6 | V18: 64.95 | W18: 116.92 | X18: 323.49 | Y18: 264.23 | Z18: 70 | AA18: 29.57 | AB18: 505.36 | AC18: 185.58 | AD18: 227.12 | AE18: 110 | AF18: =((20/365.24)*15)*E18 -> 191.65206
A19: SEI0029 | B19: Arceo Garcia Manuel Federico | C19: 15 | D19: 0 | E19: 200 | F19: 212.1 | G19: 3000 | H19: 0 | I19: 0 | J19: 3000 | K19: 0 | L19: 0 | M19: 0 | N19: 0 | O19: 59.69 | P19: 75.55 | Q19: 600 | R19: 0 | S19: -0.04 | T19: 735.2 | U19: 2264.8 | V19: 55.68 | W19: 100.22 | X19: 314.22 | Y19: 253.63 | Z19: 60 | AA19: 25.34 | AB19: 470.12 | AC19: 159.08 | AD19: 221.82 | AE19: 110 | AF19: =((20/365.24)*15)*E19 -> 164.27554
A20: SEI0364 | B20: Dominguez Lopez Mayeli Del Pilar | C20: 15 | D20: 0 | E20: 266.67 | F20: 282.81 | G20: 4000.05 | H20: 0 | I20: 0 | J20: 4000.05 | K20: 0 | L20: 0 | M20: 0 | N20: 0 | O20: 313.87 | P20: 102.51 | Q20: 0 | R20: 0 | S20: 0.07 | T20: 416.45 | U20: 3583.6 | V20: 74.24 | W20: 133.63 | X20: 337.62 | Y20: 274.84 | Z20: 80 | AA20: 33.79 | AB20: 545.49 | AC20: 212.11 | AD20: 232.42 | AE20: 110 | AF20: =((20/365.24)*15)*E20 -> 219.0368
... A93: SEI0554 | B93: Moreno Castillo Paulina Yamileth | C93: 6 | D93: 0 | E93: 200 | F93: 209.04 | G93: 1200 | H93: 0 | I93: 0 | J93: 1200 | K93: 0 | L93: 0 | M93: 0 | N93: -136.73 | O93: 0 | P93: 29.79 | Q93: 0 | R93: 0 | S93: -0.06 | T93: -107 | U93: 1307 | V93: 21.95 | W93: 39.51 | X93: 125.37 | Y93: 215.08 | Z93: 24 | AA93: 9.99 | AB93: 186.83 | AC93: 62.71 | AD93: 202.54 | AE93: 0 | AF93: =((20/365.24)*15)*E93 -> 164.27554
C94: ============= | D94: ============= | E94: ============= | F94: ============= | G94: ============= | H94: ============= | I94: ============= | J94: ============= | K94: ============= | L94: ============= | M94: ============= | N94: ============= | O94: ============= | P94: ============= | Q94: ============= | R94: ============= | S94: ============= | T94: ============= | U94: ============= | V94: ============= | W94: ============= | X94: ============= | Y94: ============= | Z94: ============= | AA94: ============= | AB94: ============= | AC94: ============= | AD94: ============= | AE94: ============= | AF94: =============
A95: Total Gral. | C95: =SUM(C9:C94) -> 1249 | D95: =SUM(D9:D94) -> 13 | E95: =SUM(E9:E94) -> 20330.61 | F95: =SUM(F9:F94) -> 21428.9 | G95: =SUM(G9:G94) -> 299308.23 | H95: =SUM(H9:H94) -> 2897.69 | I95: =SUM(I9:I94) -> 869.31 | J95: =SUM(J9:J94) -> 303075.23 | ... AF95: =SUM(AF9:AF94) -> 16699.11
A97: 83 | B97: Nomina
A98: 3 | B98: Altas | I98: FACTURACION PITS | K98: VENTAS | L98: ADMON | M98: SERVICIO
A99: 1 | B99: Bajas | I99: Devengado Salario | J99: =+U95 -> 238785.2 | K99: 1314.8 | M99: =J99-K99 -> 237470.4
A100: =+A97+A98-A99 -> 85 | B100: Total Nomina | I100: RETORNOS | J100: =+R95-R77 -> 5673.24 | K100: 0 | M100: =J100-K100-L100 -> 5673.24
I101: Infonavit | J101: =+K95+L95+M95 -> 32692.97 | K101: 977.57 | M101: =J101-K101 -> 31715.4
I102: Prestamo Prospera | J102: =+Q95 -> 1236.6 | M102: =J102 -> 1236.6
I103: Subtotal 1 | J103: =SUM(J99:J102) -> 278388.01 | K103: =SUM(K99:K102) -> 2292.37 | M103: =SUM(M99:M102) -> 276095.64
I104: Comision | J104: =+J103*2% -> 5567.7602 | K104: =K103*2% -> 45.8474 | L104: =L103*2% -> 0 | M104: =M103*2% -> 5521.9128
I105: Subtotal 2 | J105: =+J103+J104 -> 283955.77 | K105: =K103+K104 -> 2338.2174 | L105: =L103+L104 -> 0 | M105: =M103+M104 -> 281617.55
I106: Costo Patronal Imss | J106: =+P95+V95+W95+X95+Y95+AA95+AC95+AD95 -> 111385.54 | K106: 1068.81 | M106: =J106-K106 -> 110316.73
I107: 2% Sobre Nomina | J107: =+J95*2% -> 6061.5046 | K107: =2310*2% -> 46.2 | M107: =J107-K107 -> 6015.3046
I108: Importe de Factura | J108: =+J105+J106+J107 -> 401402.81 | K108: =SUM(K105:K107) -> 3453.2274 | M108: =SUM(M105:M107) -> 397949.59
I109: IVA | J109: =+J108*16% -> 64224.45 | K109: =K108*16% -> 552.51638 | L109: =L108*16% -> 0 | M109: =M108*16% -> 63671.934
I110: TOTAL | J110: =+J108+J109 -> 465627.27 | K110: =K109+K108 -> 4005.7438 | L110: =L109+L108 -> 0 | M110: =M109+M108 -> 461621.52
K111: =K108-K104 -> 3407.38 | M111: =M108-M104 -> 392427.67
I112: PROVISION AGUINALDO
I113: FACTURACION PITS | L113: 0.73 | M113: 0.11 | N113: 0.12 | O113: 0.04
I114: Subtotal 1 | J114: =+AF95 -> 16699.11 | L114: ITA | M114: IP | N114: CPD | O114: EM
I115: Comision | J115: =+J114*2% -> 333.9822 | K115: ADMON | L115: =L112*$O$45 -> 0 | M115: =L112*$P$45 -> 0 | N115: =L112*$Q$45 -> 0 | O115: =L112*$R$45 -> 0
I116: Subtotal 2 | J116: =+J114+J115 -> 17033.092 | K116: SERVICIO | L116: =M111*$L$113 -> 286472.2 | M116: =M111*$M$113 -> 43167.044 | N116: =M111*$N$113 -> 47091.321 | O116: =M111*$O$113 -> 15697.107
I117: 2% Sobre Nomina | J117: =+J114*2% -> 333.9822 | K117: VENTAS | L117: =K111*$L$113 -> 2487.3874 | M117: =K111*$M$113 -> 374.8118 | N117: =K111*$N$113 -> 408.8856 | O117: =K111*$O$113 -> 136.2952
I118: Importe de Factura | J118: =+J116+J117 -> 17367.075 | K118: COMISIONES | L118: =J104*$L$113 -> 4064.4649 | M118: =J104*$M$113 -> 612.45362 | N118: =J104*$N$113 -> 668.13122 | O118: =J104*$O$113 -> 222.71041
I119: IVA | J119: =+J118*16% -> 2778.7319 | K119: SUBTOTAL | L119: =SUM(L115:L118) -> 293024.05 | M119: =SUM(M115:M118) -> 44154.31 | N119: =SUM(N115:N118) -> 48168.338 | O119: =SUM(O115:O118) -> 16056.113
I120: TOTAL | J120: =+J118+J119 -> 20145.807 | K120: IVA | L120: =L119*16% -> 46883.849 | M120: =M119*16% -> 7064.6895 | N120: =N119*16% -> 7706.934 | O120: =O119*16% -> 2568.978
K121: TOTAL | L121: =SUM(L119:L120) -> 339907.9 | M121: =SUM(M119:M120) -> 51218.999 | N121: =SUM(N119:N120) -> 55875.272 | O121: =SUM(O119:O120) -> 18625.091

Sheet SIND PITS
C2: SINDICATO
C3: Lista de Raya (forma tabular)
D7: SINDICATO
A8: CLAVE | B8: EMPRESA | C8: NOMBRE | D8: SUELDO SINDICATO | E8: BONO | F8: COMISION | G8: prima vacaciones | H8: TOTAL | I8: CLAVE SINDICATO | J8: CUADRE
A9: SEI0097 | B9: IP INNOVACION | C9: Aguilar Aguirre Alfonso | D9: 135.2 | E9: 0 | F9: 0 | G9: =+VLOOKUP(C9,'EXTRAS Y FESTIVOS'!$B$9:T129,19,0) -> 0 | H9: =SUM(D9:G9) -> 135.2 | I9: SEI0652 | J9: =+VLOOKUP(C9,'RESUMEN PITS'!$C$9:W129,21,0) -> -54.055924
A10: SEI0118 | B10: IP INNOVACION | C10: Aguilar Garcia Rosa Paola | D10: 53.2 | E10: 0 | F10: 0 | G10: =+VLOOKUP(C10,'EXTRAS Y FESTIVOS'!$B$9:T206,19,0) -> 0 | H10: =SUM(D10:G10) -> 53.2 | I10: SEI0654 | J10: =+VLOOKUP(C10,'RESUMEN PITS'!$C$9:W206,21,0) -> -54.055924
A11: SEI0377 | B11: IP INNOVACION | C11: Alejandro Peña Deivi | D11: 175.8 | E11: 900 | F11: 0 | G11: =+VLOOKUP(C11,'EXTRAS Y FESTIVOS'!$B$9:T130,19,0) -> 0 | H11: =SUM(D11:G11) -> 1075.8 | I11: SEI0628 | J11: =+VLOOKUP(C11,'RESUMEN PITS'!$C$9:W130,21,0) -> -54.055924
A12: SEI0108 | B12: IP INNOVACION | C12: Alejandro Vazquez Erasmo Miguel | D12: 3135.25 | E12: 750 | F12: 0 | G12: =+VLOOKUP(C12,'EXTRAS Y FESTIVOS'!$B$9:T131,19,0) -> 0 | H12: =SUM(D12:G12) -> 3885.25 | I12: SEI0638 | J12: =+VLOOKUP(C12,'RESUMEN PITS'!$C$9:W131,21,0) -> -54.055924
A13: SEI0425 | B13: IP INNOVACION | C13: Arceo Garcia Manuel Federico | D13: 285.2 | E13: 1000 | F13: 0 | G13: =+VLOOKUP(C13,'EXTRAS Y FESTIVOS'!$B$9:T132,19,0) -> 0 | H13: =SUM(D13:G13) -> 1285.2 | I13: SEI0029 | J13: =+VLOOKUP(C13,'RESUMEN PITS'!$C$9:W132,21,0) -> -54.055924
A14: SEI0116 | B14: CONSULTORIA | C14: Arreola Jimenez Jose Nieves | D14: 1558.07 | E14: 420 | F14: 0 | G14: =+VLOOKUP(C14,'EXTRAS Y FESTIVOS'!$B$9:T108,19,0) -> 0 | H14: =SUM(D14:G14) -> 1978.07 | I14: SEI0097 | J14: =+VLOOKUP(C14,'RESUMEN PITS'!$C$9:W111,21,0) -> -54.055924
A15: SEI0401 | B15: CONSULTORIA | C15: Arroyo Ramirez Hector Hugo | D15: 2110.62 | E15: 0 | F15: 0 | G15: =+VLOOKUP(C15,'EXTRAS Y FESTIVOS'!$B$9:T112,19,0) -> 58.5 | H15: =SUM(D15:G15) -> 2169.12 | I15: SEI0118 | J15: =+VLOOKUP(C15,'RESUMEN PITS'!$C$9:W112,21,0) -> -54.055924
A16: SEI0099 | B16: IP INNOVACION | C16: Arzate Gil Juan Sebastian | D16: 416.4 | E16: 510 | F16: 0 | G16: =+VLOOKUP(C16,'EXTRAS Y FESTIVOS'!$B$9:T133,19,0) -> 0 | H16: =SUM(D16:G16) -> 926.4 | I16: SEI0550 | J16: =+VLOOKUP(C16,'RESUMEN PITS'!$C$9:W133,21,0) -> -54.055924
A17: SEI0009 | B17: CONSULTORIA | C17: Benavides Herrera Alejandra | D17: 16803.2 | E17: 0 | F17: 0 | G17: =+VLOOKUP(C17,'EXTRAS Y FESTIVOS'!$B$9:T113,19,0) -> 0 | H17: =SUM(D17:G17) -> 16803.2 | I17: SEI0377 | J17: =+VLOOKUP(C17,'RESUMEN PITS'!$C$9:W113,21,0) -> -54.055924
A18: SEI0127 | B18: CONSULTORIA | C18: Caballero Diaz Francisco Javier | D18: 1558.02 | E18: 210 | F18: 0 | G18: =+VLOOKUP(C18,'EXTRAS Y FESTIVOS'!$B$9:T114,19,0) -> 0 | H18: =SUM(D18:G18) -> 1768.02 | I18: SEI0108 | J18: =+VLOOKUP(C18,'RESUMEN PITS'!$C$9:W114,21,0) -> -54.055924
A19: SEI0117 | B19: CONSULTORIA | C19: Carbajal Cabuto Jose Luis | D19: 1607.97 | E19: 210 | F19: 0 | G19: =+VLOOKUP(C19,'EXTRAS Y FESTIVOS'!$B$9:T115,19,0) -> 0 | H19: =SUM(D19:G19) -> 1817.97 | I19: SEI0453 | J19: =+VLOOKUP(C19,'RESUMEN PITS'!$C$9:W115,21,0) -> -54.055924
A20: SEI0040 | B20: IP INNOVACION | C20: Casas Chavarria Rafael | D20: 175.52 | E20: 1350 | F20: 0 | G20: =+VLOOKUP(C20,'EXTRAS Y FESTIVOS'!$B$9:T134,19,0) -> 0 | H20: =SUM(D20:G20) -> 1525.52 | I20: SEI0629 | J20: =+VLOOKUP(C20,'RESUMEN PITS'!$C$9:W134,21,0) -> -54.055924
A21: SEI0088 | B21: CONSULTORIA | C21: Casillas Cardona Cesar Alejandro | D21: 1891.12 | E21: 0 | F21: 0 | G21: =+VLOOKUP(C21,'EXTRAS Y FESTIVOS'!$B$9:T116,19,0) -> 268.75 | H21: =SUM(D21:G21) -> 2159.87 | I21: SEI0116 | J21: =+VLOOKUP(C21,'RESUMEN PITS'!$C$9:W116,21,0) -> -54.055924
A22: SEI0173 | B22: IP INNOVACION | C22: Castellon Ramos Rene | D22: 384.785 | E22: 70 | F22: 0 | G22: =+VLOOKUP(C22,'EXTRAS Y FESTIVOS'!$B$9:T135,19,0) -> 0.0599 | H22: =SUM(D22:G22) -> 454.8449 | I22: SEI0499 | J22: =+VLOOKUP(C22,'RESUMEN PITS'!$C$9:W135,21,0) -> -54.055924
A23: SEI0026 | B23: IP INNOVACION | C23: Castillo Nungaray Nestor Roman | D23: 285.2 | E23: 800 | F23: 0 | G23: =+VLOOKUP(C23,'EXTRAS Y FESTIVOS'!$B$9:T136,19,0) -> 0 | H23: =SUM(D23:G23) -> 1085.2 | I23: SEI0468 | J23: =+VLOOKUP(C23,'RESUMEN PITS'!$C$9:W136,21,0) -> -54.055924
A24: SEI0221 | B24: IP INNOVACION | C24: Castillo Ramirez Hector Ivan | D24: 3721.4 | E24: 281.25 | F24: 0 | G24: =+VLOOKUP(C24,'EXTRAS Y FESTIVOS'!$B$9:T137,19,0) -> 0 | H24: =SUM(D24:G24) -> 4002.65 | I24: SEI0448 | J24: =+VLOOKUP(C24,'RESUMEN PITS'!$C$9:W137,21,0) -> -1414.5349
A25: SEI0442 | B25: IP INNOVACION | C25: Cerro Garcia Elvis | D25: 2553.4 | E25: 400 | F25: 0 | G25: =+VLOOKUP(C25,'EXTRAS Y FESTIVOS'!$B$9:T138,19,0) -> 0 | H25: =SUM(D25:G25) -> 2953.4 | I25: SEI0513 | J25: =+VLOOKUP(C25,'RESUMEN PITS'!$C$9:W138,21,0) -> -1414.5349
A26: SEI0041 | B26: IP INNOVACION | C26: Chavez Dominguez Salvador | D26: 2667.4 | E26: 500 | F26: 0 | G26: =+VLOOKUP(C26,'EXTRAS Y FESTIVOS'!$B$9:T139,19,0) -> 0 | H26: =SUM(D26:G26) -> 3167.4 | I26: SEI0483 | J26: =+VLOOKUP(C26,'RESUMEN PITS'!$C$9:W139,21,0) -> -1414.5349
A27: SEI0544 | B27: IP INNOVACION | C27: Chavez Govea Edgar Aram | D27: 222.6 | E27: 187.5 | F27: 0 | G27: =+VLOOKUP(C27,'EXTRAS Y FESTIVOS'!$B$9:T140,19,0) -> 0 | H27: =SUM(D27:G27) -> 410.1 | I27: SEI0644 | J27: =+VLOOKUP(C27,'RESUMEN PITS'!$C$9:W140,21,0) -> -1414.5349
A28: SEI0527 | B28: IP INNOVACION | C28: Chavez Pedraza Samuel | D28: 1047.8 | E28: 312.5 | F28: 0 | G28: =+VLOOKUP(C28,'EXTRAS Y FESTIVOS'!$B$9:T141,19,0) -> 0 | H28: =SUM(D28:G28) -> 1360.3 | I28: SEI0467 | J28: =+VLOOKUP(C28,'RESUMEN PITS'!$C$9:W141,21,0) -> -1414.5349
A29: SEI0535 | B29: IP INNOVACION | C29: Chavez Saucedo Jorge Arturo | D29: 414.6 | E29: 600 | F29: 0 | G29: =+VLOOKUP(C29,'EXTRAS Y FESTIVOS'!$B$9:T142,19,0) -> 0 | H29: =SUM(D29:G29) -> 1014.6 | I29: SEI0516 | J29: =+VLOOKUP(C29,'RESUMEN PITS'!$C$9:W142,21,0) -> -1414.5349
A30: SEI0029 | B30: IP INNOVACION | C30: Chavira Garcia David Fernando | D30: 593.6 | E30: 60 | F30: 0 | G30: =+VLOOKUP(C30,'EXTRAS Y FESTIVOS'!$B$9:T143,19,0) -> 0 | H30: =SUM(D30:G30) -> 653.6 | I30: SEI0495 | J30: =+VLOOKUP(C30,'RESUMEN PITS'!$C$9:W143,21,0) -> -1414.5349
A31: SEI0472 | B31: IP INNOVACION | C31: Cota Jaramillo Miguel Angel | D31: 134.2 | E31: 337.5 | F31: 0 | G31: =+VLOOKUP(C31,'EXTRAS Y FESTIVOS'!$B$9:T144,19,0) -> 0 | H31: =SUM(D31:G31) -> 471.7 | I31: SEI0015 | J31: =+VLOOKUP(C31,'RESUMEN PITS'!$C$9:W144,21,0) -> -1414.5349
A32: SEI0528 | B32: IP INNOVACION | C32: Courtenay Gutierrez Barry Vladimir | D32: 52.25 | E32: 250 | F32: 0 | G32: =+VLOOKUP(C32,'EXTRAS Y FESTIVOS'!$B$9:T145,19,0) -> 0 | H32: =SUM(D32:G32) -> 302.25 | I32: SEI0436 | J32: =+VLOOKUP(C32,'RESUMEN PITS'!$C$9:W145,21,0) -> -1414.5349
A33: SEI0460 | B33: IP INNOVACION | C33: Cruz Herrera Roberto | D33: 1667.49 | E33: 90 | F33: 0 | G33: =+VLOOKUP(C33,'EXTRAS Y FESTIVOS'!$B$9:T146,19,0) -> 0 | H33: =SUM(D33:G33) -> 1757.49 | I33: SEI0485 | J33: =+VLOOKUP(C33,'RESUMEN PITS'!$C$9:W146,21,0) -> -1414.5349
A34: SEI0443 | B34: IP INNOVACION | C34: Cruz Perez Alejandro Nezahualcoyotl | D34: 416.4 | E34: 570 | F34: 0 | G34: =+VLOOKUP(C34,'EXTRAS Y FESTIVOS'!$B$9:T147,19,0) -> 0 | H34: =SUM(D34:G34) -> 986.4 | I34: SEI0606 | J34: =+VLOOKUP(C34,'RESUMEN PITS'!$C$9:W147,21,0) -> -1414.5349
A35: SEI0490 | B35: CONSULTORIA | C35: De La Torre Zambara Francisco Ernesto | D35: 1558.2 | E35: 60 | F35: 0 | G35: =+VLOOKUP(C35,'EXTRAS Y FESTIVOS'!$B$9:T117,19,0) -> 0 | H35: =SUM(D35:G35) -> 1618.2 | I35: SEI0401 | J35: =+VLOOKUP(C35,'RESUMEN PITS'!$C$9:W117,21,0) -> -1414.5349
A36: SEI0508 | B36: IP INNOVACION | C36: Del Pilar Mendez Lucio | D36: 134.2 | E36: 363.75 | F36: 0 | G36: =+VLOOKUP(C36,'EXTRAS Y FESTIVOS'!$B$9:T148,19,0) -> 0 | H36: =SUM(D36:G36) -> 497.95 | I36: SEI0630 | J36: =+VLOOKUP(C36,'RESUMEN PITS'!$C$9:W148,21,0) -> -1414.5349
A37: SEI0499 | B37: IP INNOVACION | C37: Diaz Ortiz Hiram Guillermo | D37: 174.54 | E37: 56.25 | F37: 0 | G37: =+VLOOKUP(C37,'EXTRAS Y FESTIVOS'!$B$9:T149,19,0) -> 0 | H37: =SUM(D37:G37) -> 230.79 | I37: SEI0646 | J37: =+VLOOKUP(C37,'RESUMEN PITS'!$C$9:W149,21,0) -> -1414.5349
A38: SEI0541 | B38: IP INNOVACION | C38: Dominguez Lopez Mayeli Del Pilar | D38: 1416.4 | E38: 1087.5 | F38: 0 | G38: =+VLOOKUP(C38,'EXTRAS Y FESTIVOS'!$B$9:T150,19,0) -> 0 | H38: =SUM(D38:G38) -> 2503.9 | I38: SEI0364 | J38: =+VLOOKUP(C38,'RESUMEN PITS'!$C$9:W150,21,0) -> -1414.5349
A39: SEI0442 | B39: IP INNOVACION | C39: Escobedo Olivares Juan Guadalupe | D39: 3721.2 | E39: 125 | F39: 0 | G39: =+VLOOKUP(C39,'EXTRAS Y FESTIVOS'!$B$9:T151,19,0) -> 0 | H39: =SUM(D39:G39) -> 3846.2 | I39: SEI0447 | J39: =+VLOOKUP(C39,'RESUMEN PITS'!$C$9:W151,21,0) -> -1414.5349
A40: SEI0462 | B40: IP INNOVACION | C40: Flores Cerrillos Jorge Humberto | D40: 416.2 | E40: 130 | F40: 0 | G40: =+VLOOKUP(C40,'EXTRAS Y FESTIVOS'!$B$9:T152,19,0) -> 0 | H40: =SUM(D40:G40) -> 546.2 | I40: SEI0474 | J40: =+VLOOKUP(C40,'RESUMEN PITS'!$C$9:W152,21,0) -> -1414.5349
A41: SEI0456 | B41: IP INNOVACION | C41: Flores Franco Marco | D41: 451.005 | E41: 162.5 | F41: 0 | G41: =+VLOOKUP(C41,'EXTRAS Y FESTIVOS'!$B$9:T153,19,0) -> 0 | H41: =SUM(D41:G41) -> 613.505 | I41: SEI0500 | J41: =+VLOOKUP(C41,'RESUMEN PITS'!$C$9:W153,21,0) -> -1414.5349
A42: SEI0015 | B42: IP INNOVACION | C42: Garcia Gutierrez Jose Juan | D42: 3135.2 | E42: 0 | F42: 0 | G42: =+VLOOKUP(C42,'EXTRAS Y FESTIVOS'!$B$9:T154,19,0) -> 0 | H42: =SUM(D42:G42) -> 3135.2 | I42: SEI0484 | J42: =+VLOOKUP(C42,'RESUMEN PITS'!$C$9:W154,21,0) -> -1414.5349
A43: SEI0413 | B43: CONSULTORIA | C43: Garcia Villicaña Ricardo Pascual | D43: 2600.25 | E43: 0 | F43: 0 | G43: =+VLOOKUP(C43,'EXTRAS Y FESTIVOS'!$B$9:T118,19,0) -> 0 | H43: =SUM(D43:G43) -> 2600.25 | I43: SEI0099 | J43: =+VLOOKUP(C43,'RESUMEN PITS'!$C$9:W118,21,0) -> -1414.5349
A44: SEI0501 | B44: IP INNOVACION | C44: Gonzalez Ramirez Paul | D44: 134.1 | E44: 292.5 | F44: 0 | G44: =+VLOOKUP(C44,'EXTRAS Y FESTIVOS'!$B$9:T155,19,0) -> 0 | H44: =SUM(D44:G44) -> 426.6 | I44: 0SEI0635 | J44: =+VLOOKUP(C44,'RESUMEN PITS'!$C$9:W155,21,0) -> -1414.5349
A45: SEI479 | B45: IP INNOVACION | C45: Gonzalez Rasgado Miguel Isaias | D45: -14.5 | E45: 937.5 | F45: 0 | G45: =+VLOOKUP(C45,'EXTRAS Y FESTIVOS'!$B$9:T156,19,0) -> 0 | H45: =SUM(D45:G45) -> 923 | I45: SEI0019 | J45: =+VLOOKUP(C45,'RESUMEN PITS'!$C$9:W156,21,0) -> -1414.5349
A46: SEI0530 | B46: IP INNOVACION | C46: Guerrero Lara Cesar Adrian | D46: 416.4 | E46: 225 | F46: 0 | G46: =+VLOOKUP(C46,'EXTRAS Y FESTIVOS'!$B$9:T157,19,0) -> 0 | H46: =SUM(D46:G46) -> 641.4 | I46: SEI0496 | J46: =+VLOOKUP(C46,'RESUMEN PITS'!$C$9:W157,21,0) -> -1414.5349
A47: SEI0543 | B47: IP INNOVACION | C47: Gutierrez Castillo Jose De Jesus | D47: 284.23 | E47: 281.25 | F47: 0 | G47: =+VLOOKUP(C47,'EXTRAS Y FESTIVOS'!$B$9:T158,19,0) -> 0 | H47: =SUM(D47:G47) -> 565.48 | I47: SEI0610 | J47: =+VLOOKUP(C47,'RESUMEN PITS'!$C$9:W158,21,0) -> -1414.5349
A48: SEI0364 | B48: CONSULTORIA | C48: Gutierrez Gutierrez Luis Arturo | D48: 1475.4 | E48: 0 | F48: 0 | G48: =+VLOOKUP(C48,'EXTRAS Y FESTIVOS'!$B$9:T119,19,0) -> 0 | H48: =SUM(D48:G48) -> 1475.4 | I48: SEI0009 | J48: =+VLOOKUP(C48,'RESUMEN PITS'!$C$9:W119,21,0) -> -1414.5349
A49: SEI0489 | B49: IP INNOVACION | C49: Gutierrez Muñoz Carlos Alejandro | D49: 2885.04 | E49: 300 | F49: 0 | G49: =+VLOOKUP(C49,'EXTRAS Y FESTIVOS'!$B$9:T159,19,0) -> 0 | H49: =SUM(D49:G49) -> 3185.04 | I49: SEI0095 | J49: =+VLOOKUP(C49,'RESUMEN PITS'!$C$9:W159,21,0) -> -1414.5349
A50: SEI0449 | B50: IP INNOVACION | C50: Hernandez Garcia Manuel Alejandro | D50: 414.8 | E50: 255 | F50: 0 | G50: =+VLOOKUP(C50,'EXTRAS Y FESTIVOS'!$B$9:T160,19,0) -> 0 | H50: =SUM(D50:G50) -> 669.8 | I50: SEI0602 | J50: =+VLOOKUP(C50,'RESUMEN PITS'!$C$9:W160,21,0) -> -1414.5349
A51: SEI0461 | B51: CONSULTORIA | C51: Hernandez Ochoa Eduardo | D51: 2600.2 | E51: 337.5 | F51: 0 | G51: =+VLOOKUP(C51,'EXTRAS Y FESTIVOS'!$B$9:T120,19,0) -> 0 | H51: =SUM(D51:G51) -> 2937.7 | I51: SEI0127 | J51: =+VLOOKUP(C51,'RESUMEN PITS'!$C$9:W120,21,0) -> -1414.5349
A52: SEI0500 | B52: IP INNOVACION | C52: Hernandez Ojeda Julio Cesar | D52: 1704.51 | E52: 0 | F52: 0 | G52: =+VLOOKUP(C52,'EXTRAS Y FESTIVOS'!$B$9:T161,19,0) -> 0 | H52: =SUM(D52:G52) -> 1704.51 | I52: SEI0640 | J52: =+VLOOKUP(C52,'RESUMEN PITS'!$C$9:W161,21,0) -> -1414.5349
A53: SEI0534 | B53: IP INNOVACION | C53: Hernandez Rodriguez Jorge | D53: 222.74 | E53: 100 | F53: 0 | G53: =+VLOOKUP(C53,'EXTRAS Y FESTIVOS'!$B$9:T162,19,0) -> 0 | H53: =SUM(D53:G53) -> 322.74 | I53: SEI0624 | J53: =+VLOOKUP(C53,'RESUMEN PITS'!$C$9:W162,21,0) -> -1414.5349
A54: SEI0019 | B54: IP INNOVACION | C54: Hinojosa Guerrero Alejandro | D54: 174.6 | E54: 0 | F54: 0 | G54: =+VLOOKUP(C54,'EXTRAS Y FESTIVOS'!$B$9:T208,19,0) -> 0 | H54: =SUM(D54:G54) -> 174.6 | J54: =+VLOOKUP(C54,'RESUMEN PITS'!$C$9:W208,21,0) -> -1414.5349
A55: SEI0457 | B55: IP INNOVACION | C55: Hueramo Hueramo Jesus Daniel | D55: 1450.85 | E55: 112.5 | F55: 0 | G55: =+VLOOKUP(C55,'EXTRAS Y FESTIVOS'!$B$9:T163,19,0) -> 0 | H55: =SUM(D55:G55) -> 1563.35 | I55: SEI 502 | J55: =+VLOOKUP(C55,'RESUMEN PITS'!$C$9:W163,21,0) -> -1414.5349
A56: SEI0509 | B56: IP INNOVACION | C56: Jauregui Madera Jorge Silvestre | D56: 134.2 | E56: 487.5 | F56: 0 | G56: =+VLOOKUP(C56,'EXTRAS Y FESTIVOS'!$B$9:T207,19,0) -> 0 | H56: =SUM(D56:G56) -> 621.7 | I56: SEI0656 | J56: =+VLOOKUP(C56,'RESUMEN PITS'!$C$9:W207,21,0) -> -1414.5349
A57: SEI0483 | B57: IP INNOVACION | C57: Lizaran Maceda Jesus | D57: 175.71 | E57: 0 | F57: 0 | G57: =+VLOOKUP(C57,'EXTRAS Y FESTIVOS'!$B$9:T165,19,0) -> 0 | H57: =SUM(D57:G57) -> 175.71 | I57: SEI0626 | J57: =+VLOOKUP(C57,'RESUMEN PITS'!$C$9:W165,21,0) -> -1414.5349
A58: SEI0476 | B58: IP INNOVACION | C58: Lizaran Maceda Jose Guadalupe | D58: 53 | E58: 160 | F58: 0 | G58: =+VLOOKUP(C58,'EXTRAS Y FESTIVOS'!$B$9:T164,19,0) -> 0 | H58: =SUM(D58:G58) -> 213 | I58: SEI0517 | J58: =+VLOOKUP(C58,'RESUMEN PITS'!$C$9:W164,21,0) -> -1414.5349
A59: SEI0536 | B59: IP INNOVACION | C59: Lopez Blanco Luis Eduardo | D59: 174.4 | E59: 0 | F59: 0 | G59: =+VLOOKUP(C59,'EXTRAS Y FESTIVOS'!$B$9:T209,19,0) -> 0 | H59: =SUM(D59:G59) -> 174.4 | J59: =+VLOOKUP(C59,'RESUMEN PITS'!$C$9:W209,21,0) -> -1414.5349
A60: SEI0523 | B60: IP INNOVACION | C60: Lopez Terron Roberto Porfirio | D60: 1047.8 | E60: 187.5 | F60: 0 | G60: =+VLOOKUP(C60,'EXTRAS Y FESTIVOS'!$B$9:T166,19,0) -> 0 | H60: =SUM(D60:G60) -> 1235.3 | I60: SEI0463 | J60: =+VLOOKUP(C60,'RESUMEN PITS'!$C$9:W166,21,0) -> -1414.5349
A61: SEI0464 | B61: IP INNOVACION | C61: Macias Torres Enrique | D61: 6520.6 | E61: 2223 | F61: 0 | G61: =+VLOOKUP(C61,'EXTRAS Y FESTIVOS'!$B$9:T167,19,0) -> 0 | H61: =SUM(D61:G61) -> 8743.6 | I61: SEI0120 | J61: =+VLOOKUP(C61,'RESUMEN PITS'!$C$9:W167,21,0) -> -1414.5349
A62: SEI0511 | B62: IP INNOVACION | C62: Mar Marquez Cesar Eduardo | D62: 414.6 | E62: 220 | F62: 0 | G62: =+VLOOKUP(C62,'EXTRAS Y FESTIVOS'!$B$9:T168,19,0) -> 0 | H62: =SUM(D62:G62) -> 634.6 | I62: SEI0020 | J62: =+VLOOKUP(C62,'RESUMEN PITS'!$C$9:W168,21,0) -> -1414.5349
A63: SEI0525 | B63: IP INNOVACION | C63: Marin Avila Hector | D63: 707 | E63: 500 | F63: 0 | G63: =+VLOOKUP(C63,'EXTRAS Y FESTIVOS'!$B$9:T180,19,0) -> 0 | H63: =SUM(D63:G63) -> 1207 | I63: SEI0445 | J63: =+VLOOKUP(C63,'RESUMEN PITS'!$C$9:W180,21,0) -> -1414.5349
A64: SEI0438 | B64: CONSULTORIA | C64: Mariscal Romero Luis Adrian | D64: 2750.92 | E64: 0 | F64: 0 | G64: =+VLOOKUP(C64,'EXTRAS Y FESTIVOS'!$B$9:T121,19,0) -> 211.88 | H64: =SUM(D64:G64) -> 2962.8 | I64: SEI0117 | J64: =+VLOOKUP(C64,'RESUMEN PITS'!$C$9:W121,21,0) -> -1414.5349
A65: SEI0517 | B65: IP INNOVACION | C65: Marquez Hernandez Rogelio | D65: 416.4 | E65: 150 | F65: 0 | G65: =+VLOOKUP(C65,'EXTRAS Y FESTIVOS'!$B$9:T169,19,0) -> 0 | H65: =SUM(D65:G65) -> 566.4 | I65: SEI0469 | J65: =+VLOOKUP(C65,'RESUMEN PITS'!$C$9:W169,21,0) -> -1414.5349
A66: SEI0020 | B66: IP INNOVACION | C66: Martinez Hernandez J. Antonio | D66: 416.2 | E66: 120 | F66: 0 | G66: =+VLOOKUP(C66,'EXTRAS Y FESTIVOS'!$B$9:T170,19,0) -> 0 | H66: =SUM(D66:G66) -> 536.2 | I66: SEI0452 | J66: =+VLOOKUP(C66,'RESUMEN PITS'!$C$9:W170,21,0) -> -1414.5349
A67: SEI0444 | B67: IP INNOVACION | C67: Martinez Malo Cesar | D67: 1694.24 | E67: 262.5 | F67: 0 | G67: =+VLOOKUP(C67,'EXTRAS Y FESTIVOS'!$B$9:T171,19,0) -> 0 | H67: =SUM(D67:G67) -> 1956.74 | I67: SEI0488 | J67: =+VLOOKUP(C67,'RESUMEN PITS'!$C$9:W171,21,0) -> -2175.4699
A68: SEI0428 | B68: IP INNOVACION | C68: Martinez Morales Jose Martin | D68: 1047.8 | E68: 562.5 | F68: 0 | G68: =+VLOOKUP(C68,'EXTRAS Y FESTIVOS'!$B$9:T172,19,0) -> 0 | H68: =SUM(D68:G68) -> 1610.3 | I68: SEI0511 | J68: =+VLOOKUP(C68,'RESUMEN PITS'!$C$9:W172,21,0) -> -1212.5669
A69: SEI0504 | B69: IP INNOVACION | C69: Martinez Morales Tomas | D69: 3339.26 | E69: 262.5 | F69: 0 | G69: =+VLOOKUP(C69,'EXTRAS Y FESTIVOS'!$B$9:T173,19,0) -> 280.69 | H69: =SUM(D69:G69) -> 3882.45 | I69: SEI0477 | J69: =+VLOOKUP(C69,'RESUMEN PITS'!$C$9:W173,21,0) -> -1212.5669
A70: SEI0469 | B70: IP INNOVACION | C70: Martinez Rodriguez Paulo Cesar | D70: 2552.4 | E70: 250 | F70: 0 | G70: =+VLOOKUP(C70,'EXTRAS Y FESTIVOS'!$B$9:T174,19,0) -> 100 | H70: =SUM(D70:G70) -> 2902.4 | I70: SEI0487 | J70: =+VLOOKUP(C70,'RESUMEN PITS'!$C$9:W174,21,0) -> -1212.5669
A71: SEI0493 | B71: IP INNOVACION | C71: Martinez Zamora Gerardo Mario | D71: 550.075 | E71: 375 | F71: 0 | G71: =+VLOOKUP(C71,'EXTRAS Y FESTIVOS'!$B$9:T175,19,0) -> 0 | H71: =SUM(D71:G71) -> 925.075 | I71: SEI0497 | J71: =+VLOOKUP(C71,'RESUMEN PITS'!$C$9:W175,21,0) -> -1212.5669
A72: SEI0503 | B72: IP INNOVACION | C72: Medellin Colunga Ruben Dario | D72: 4339.43 | E72: 281.25 | F72: 0 | G72: =+VLOOKUP(C72,'EXTRAS Y FESTIVOS'!$B$9:T176,19,0) -> 0 | H72: =SUM(D72:G72) -> 4620.68 | I72: SEI0478 | J72: =+VLOOKUP(C72,'RESUMEN PITS'!$C$9:W176,21,0) -> -1212.5669
A73: SEI0458 | B73: IP INNOVACION | C73: Mejia Duarte Jose Luis | D73: 3553.2 | E73: 187.5 | F73: 0 | G73: =+VLOOKUP(C73,'EXTRAS Y FESTIVOS'!$B$9:T177,19,0) -> 0 | H73: =SUM(D73:G73) -> 3740.7 | I73: SEI0506 | J73: =+VLOOKUP(C73,'RESUMEN PITS'!$C$9:W177,21,0) -> -1212.5669
A74: SEI0494 | B74: IP INNOVACION | C74: Mendez Rivera Ivan Israel | D74: 52.57 | E74: 250 | F74: 0 | G74: =+VLOOKUP(C74,'EXTRAS Y FESTIVOS'!$B$9:T178,19,0) -> 0 | H74: =SUM(D74:G74) -> 302.57 | I74: SEI0612 | J74: =+VLOOKUP(C74,'RESUMEN PITS'!$C$9:W178,21,0) -> -1618.5039
A75: SEI0506 | B75: IP INNOVACION | C75: Mireles Casillas Brenda Cristina | D75: 2262.2 | E75: 0 | F75: 0 | G75: =+VLOOKUP(C75,'EXTRAS Y FESTIVOS'!$B$9:T179,19,0) -> 0 | H75: =SUM(D75:G75) -> 2262.2 | I75: SEI0446 | J75: =+VLOOKUP(C75,'RESUMEN PITS'!$C$9:W179,21,0) -> -1501.4969
A76: SEI0513 | B76: IP INNOVACION | C76: Molina Ramirez Gerardo Daniel | D76: 2262.37 | E76: 400 | F76: 0 | G76: =+VLOOKUP(C76,'EXTRAS Y FESTIVOS'!$B$9:T181,19,0) -> 225 | H76: =SUM(D76:G76) -> 2887.37 | I76: SEI0033 | J76: =+VLOOKUP(C76,'RESUMEN PITS'!$C$9:W181,21,0) -> -1501.4969
A77: SEI0488 | B77: IP INNOVACION | C77: Montoya Portillo Carlos Alberto | D77: 414.6 | E77: 175 | F77: 0 | G77: =+VLOOKUP(C77,'EXTRAS Y FESTIVOS'!$B$9:T182,19,0) -> 0 | H77: =SUM(D77:G77) -> 589.6 | I77: SEI0014 | J77: =+VLOOKUP(C77,'RESUMEN PITS'!$C$9:W182,21,0) -> -1501.4969
B78: CONSULTORIA | C78: Mora Ramirez Acal Aldo Isidro | D78: 2464 | E78: 1000 | F78: 0 | G78: =+VLOOKUP(C78,'EXTRAS Y FESTIVOS'!$B$9:T122,19,0) -> 0 | H78: =SUM(D78:G78) -> 3464 | I78: SEI0040 | J78: =+VLOOKUP(C78,'RESUMEN PITS'!$C$9:W122,21,0) -> -1501.4969
A79: SEI0485 | B79: IP INNOVACION | C79: Morales Martinez Eduardo | D79: 175.6 | E79: 843.75 | F79: 0 | G79: =+VLOOKUP(C79,'EXTRAS Y FESTIVOS'!$B$9:T183,19,0) -> 0 | H79: =SUM(D79:G79) -> 1019.35 | I79: SEI0648 | J79: =+VLOOKUP(C79,'RESUMEN PITS'!$C$9:W183,21,0) -> -1501.4969
A80: SEI0014 | B80: IP INNOVACION | C80: Moreno Castillo Paulina Yamileth | D80: 0 | E80: 0 | F80: 0 | G80: =+VLOOKUP(C80,'EXTRAS Y FESTIVOS'!$B$9:T213,19,0) -> 0 | H80: =SUM(D80:G80) -> 0 | J80: =+VLOOKUP(C80,'RESUMEN PITS'!$C$9:W213,21,0) -> -3408.4969
A81: SEI0540 | B81: IP INNOVACION | C81: Moreno Quiroga Ana Sarahi | D81: 416.2 | E81: =687.5+500 -> 1187.5 | F81: 0 | G81: =+VLOOKUP(C81,'EXTRAS Y FESTIVOS'!$B$9:T184,19,0) -> 0 | H81: =SUM(D81:G81) -> 1603.7 | I81: SEI0601 | J81: =+VLOOKUP(C81,'RESUMEN PITS'!$C$9:W184,21,0) -> -1501.4969
A82: SEI0475 | B82: CONSULTORIA | C82: Morgado Fernandez Martin | D82: 2600.25 | E82: 75 | F82: 0 | G82: =+VLOOKUP(C82,'EXTRAS Y FESTIVOS'!$B$9:T123,19,0) -> 0 | H82: =SUM(D82:G82) -> 2675.25 | I82: SEI0088 | J82: =+VLOOKUP(C82,'RESUMEN PITS'!$C$9:W123,21,0) -> -1501.4969
A83: SEI0017 | B83: IP INNOVACION | C83: Muñoz Reyes Luis Eduardo | D83: 414.56 | E83: 250 | F83: 0 | G83: =+VLOOKUP(C83,'EXTRAS Y FESTIVOS'!$B$9:T185,19,0) -> 0 | H83: =SUM(D83:G83) -> 664.56 | I83: SEI0017 | J83: =+VLOOKUP(C83,'RESUMEN PITS'!$C$9:W185,21,0) -> -1501.4969
A84: SEI0022 | B84: IP INNOVACION | C84: Najera Lopez Raul | D84: =866.4-333.33 -> 533.07 | E84: 150 | F84: 0 | G84: =+VLOOKUP(C84,'EXTRAS Y FESTIVOS'!$B$9:T186,19,0) -> 0 | H84: =SUM(D84:G84) -> 683.07 | I84: SEI0022 | J84: =+VLOOKUP(C84,'RESUMEN PITS'!$C$9:W186,21,0) -> -1834.8336
B85: IP INNOVACION | C85: Navarro Vargas Alberto | D85: =518-420 -> 98 | E85: 0 | F85: 0 | G85: =+VLOOKUP(C85,'EXTRAS Y FESTIVOS'!$B$9:T212,19,0) -> 0 | H85: =SUM(D85:G85) -> 98 | J85: =+VLOOKUP(C85,'RESUMEN PITS'!$C$9:W212,21,0) -> -1921.4969
A86: SEI0524 | B86: IP INNOVACION | C86: Negrete Bejar Aide Sarai | D86: 207.63 | E86: 3503.7 | F86: 0 | G86: =+VLOOKUP(C86,'EXTRAS Y FESTIVOS'!$B$9:T187,19,0) -> 0 | H86: =SUM(D86:G86) -> 3711.33 | I86: SEI0016 | J86: =+VLOOKUP(C86,'RESUMEN PITS'!$C$9:W187,21,0) -> -1501.4969
A87: SEI0424 | B87: CONSULTORIA | C87: Nieto Ortiz Jose Luis | D87: 1483.09 | E87: 30 | F87: 0 | G87: =+VLOOKUP(C87,'EXTRAS Y FESTIVOS'!$B$9:T124,19,0) -> 398.26 | H87: =SUM(D87:G87) -> 1911.35 | I87: SEI0173 | J87: =+VLOOKUP(C87,'RESUMEN PITS'!$C$9:W124,21,0) -> -1501.4969
A88: SEI0519 | B88: IP INNOVACION | C88: Orea Gonzalez Concepcion Esteban | D88: 175.6 | E88: 900 | F88: 0 | G88: =+VLOOKUP(C88,'EXTRAS Y FESTIVOS'!$B$9:T188,19,0) -> 0 | H88: =SUM(D88:G88) -> 1075.6 | I88: SEI0625 | J88: =+VLOOKUP(C88,'RESUMEN PITS'!$C$9:W188,21,0) -> -1350.9859
A89: SEI0505 | B89: IP INNOVACION | C89: Palacios Ramos Jesus | D89: 416.4 | E89: 210 | F89: 0 | G89: =+VLOOKUP(C89,'EXTRAS Y FESTIVOS'!$B$9:T189,19,0) -> 0 | H89: =SUM(D89:G89) -> 626.4 | I89: SEI0424 | J89: =+VLOOKUP(C89,'RESUMEN PITS'!$C$9:W189,21,0) -> -1342.3659
A90: SEI0455 | B90: IP INNOVACION | C90: Palacios Vega Luis Rosendo | D90: 52.4 | E90: 140 | F90: 0 | G90: =+VLOOKUP(C90,'EXTRAS Y FESTIVOS'!$B$9:T190,19,0) -> 0 | H90: =SUM(D90:G90) -> 192.4 | I90: SEI0519 | J90: =+VLOOKUP(C90,'RESUMEN PITS'!$C$9:W190,21,0) -> -1342.3659
A91: SEI0023 | B91: CONSULTORIA | C91: Patricio Aguilar Jhonattan Cristian | D91: 1588 | E91: 400 | F91: 0 | G91: =+VLOOKUP(C91,'EXTRAS Y FESTIVOS'!$B$9:T125,19,0) -> 0 | H91: =SUM(D91:G91) -> 1988 | I91: SEI0026 | J91: =+VLOOKUP(C91,'RESUMEN PITS'!$C$9:W125,21,0) -> -1342.3659
A92: SEI0521 | B92: IP INNOVACION | C92: Perez Balboa Cesar | D92: 2194.04 | E92: 110 | F92: 0 | G92: =+VLOOKUP(C92,'EXTRAS Y FESTIVOS'!$B$9:T191,19,0) -> 0 | H92: =SUM(D92:G92) -> 2304.04 | I92: SEI0489 | J92: =+VLOOKUP(C92,'RESUMEN PITS'!$C$9:W191,21,0) -> -1342.3659
A93: SEI0465 | B93: IP INNOVACION | C93: Perez Garcia Andres Alvaro | D93: 416.4 | E93: 315 | F93: 0 | G93: =+VLOOKUP(C93,'EXTRAS Y FESTIVOS'!$B$9:T192,19,0) -> 0 | H93: =SUM(D93:G93) -> 731.4 | I93: SEI0494 | J93: =+VLOOKUP(C93,'RESUMEN PITS'!$C$9:W192,21,0) -> -1342.3659
A94: SEI0477 | B94: IP INNOVACION | C94: Puente Murguia Luis Felipe | D94: 222.4 | E94: 131.25 | F94: 0 | G94: =+VLOOKUP(C94,'EXTRAS Y FESTIVOS'!$B$9:T193,19,0) -> 0 | H94: =SUM(D94:G94) -> 353.65 | I94: SEI0023 | J94: =+VLOOKUP(C94,'RESUMEN PITS'!$C$9:W193,21,0) -> -1342.3659
A95: SEI0537 | B95: CONSULTORIA | C95: Rogel Teran Marco Antonio | D95: 12613.07 | E95: 0 | F95: 0 | G95: =+VLOOKUP(C95,'EXTRAS Y FESTIVOS'!$B$9:T126,19,0) -> 0 | H95: =SUM(D95:G95) -> 12613.07 | I95: SEI0221 | J95: =+VLOOKUP(C95,'RESUMEN PITS'!$C$9:W126,21,0) -> -1342.3659
A96: SEI0498 | B96: IP INNOVACION | C96: Rondero Savin Jacinto | D96: 221.2 | E96: 0 | F96: 0 | G96: =+VLOOKUP(C96,'EXTRAS Y FESTIVOS'!$B$9:T194,19,0) -> 0 | H96: =SUM(D96:G96) -> 221.2 | I96: SEI0622 | J96: =+VLOOKUP(C96,'RESUMEN PITS'!$C$9:W194,21,0) -> -1342.3659
A97: SEI0495 | B97: IP INNOVACION | C97: Rubio Ventura Juan Eduardo | D97: =307.4-200 -> 107.4 | E97: 0 | F97: 0 | G97: =+VLOOKUP(C97,'EXTRAS Y FESTIVOS'!$B$9:T211,19,0) -> 0 | H97: =SUM(D97:G97) -> 107.4 | J97: =+VLOOKUP(C97,'RESUMEN PITS'!$C$9:W211,21,0) -> -1452.9259
A98: SEI0010 | B98: IP INNOVACION | C98: Sandoval Garcia Luis | D98: 416.4 | E98: 180 | F98: 0 | G98: =+VLOOKUP(C98,'EXTRAS Y FESTIVOS'!$B$9:T195,19,0) -> 0 | H98: =SUM(D98:G98) -> 596.4 | I98: SEI0503 | J98: =+VLOOKUP(C98,'RESUMEN PITS'!$C$9:W195,21,0) -> -784.99592
A99: SEI0473 | B99: IP INNOVACION | C99: Sandoval Medina Demetrio | D99: 414.6 | E99: 510 | F99: 0 | G99: =+VLOOKUP(C99,'EXTRAS Y FESTIVOS'!$B$9:T196,19,0) -> 0 | H99: =SUM(D99:G99) -> 924.6 | I99: SEI0603 | J99: =+VLOOKUP(C99,'RESUMEN PITS'!$C$9:W196,21,0) -> -784.99592
A100: SEI0497 | B100: IP INNOVACION | C100: Serrano Esquivel Armando | D100: 1704.59 | E100: 437.5 | F100: 0 | G100: =+VLOOKUP(C100,'EXTRAS Y FESTIVOS'!$B$9:T197,19,0) -> 0 | H100: =SUM(D100:G100) -> 2142.09 | I100: SEI0641 | J100: =+VLOOKUP(C100,'RESUMEN PITS'!$C$9:W197,21,0) -> -784.99592
A101: SEI0467 | B101: CONSULTORIA | C101: Sierra Escamilla Daniela | D101: 2464 | E101: 1000 | F101: 0 | G101: =+VLOOKUP(C101,'EXTRAS Y FESTIVOS'!$B$9:T127,19,0) -> 0 | H101: =SUM(D101:G101) -> 3464 | I101: SEI0618 | J101: =+VLOOKUP(C101,'RESUMEN PITS'!$C$9:W127,21,0) -> -784.99592
A102: SEI0545 | B102: IP INNOVACION | C102: Tenorio Alvarez Alberto Antonio | D102: 1667.55 | E102: 285 | F102: 0 | G102: =+VLOOKUP(C102,'EXTRAS Y FESTIVOS'!$B$9:T198,19,0) -> 0 | H102: =SUM(D102:G102) -> 1952.55 | I102: SEI0482 | J102: =+VLOOKUP(C102,'RESUMEN PITS'!$C$9:W198,21,0) -> -784.99592
A103: SEI0021 | B103: IP INNOVACION | C103: Torres Perez Carlos Alberto | D103: 1917.4 | E103: 1406.25 | F103: 0 | G103: =+VLOOKUP(C103,'EXTRAS Y FESTIVOS'!$B$9:T199,19,0) -> 0 | H103: =SUM(D103:G103) -> 3323.65 | I103: SEI0479 | J103: =+VLOOKUP(C103,'RESUMEN PITS'!$C$9:W199,21,0) -> -784.99592
B104: IP INNOVACION | C104: Torres Ricardez Alfredo | D104: 414.6 | E104: 175 | F104: 0 | G104: =+VLOOKUP(C104,'EXTRAS Y FESTIVOS'!$B$9:T200,19,0) -> 0 | H104: =SUM(D104:G104) -> 589.6 | I104: SEI0010 | J104: =+VLOOKUP(C104,'RESUMEN PITS'!$C$9:W200,21,0) -> -784.99592
...

Sheet EXTRAS Y FESTIVOS
B2: HORAS EXTRAS Y DIAS FESTIVOS
A8: Clave | B8: Nombre | C8: DIAS LABORADOS | D8: SDI | E8: Sueldo Mensual | F8: Sueldo quincenal | G8: Sueldo diario con bonos | I8: Faltas | J8: Monto | L8: DIAS VACACIONES | M8: Total de Vacaciones | N8: VACACIONES IMSS | O8: VACACIONES SINDICATO | Q8: PRIMA VACACIONAL | R8: Total de Prima vacacional | S8: PRIMA IMSS | T8: PRIMA SINDICATO | W8: VACACIONES PAGADAS | X8: Total | Y8: IMSS | Z8: SINDICATO | AA8: Total de Prima vacacional | AB8: PRIMA IMSS | AC8: PRIMA SINDICATO | AD8: INCAPACIDAD | AE8: TOTAL | AF8: IMSS | AG8: SINDICATO
A9: CONSULTORIA | B9: Arreola Jimenez Jose Nieves | C9: =+VLOOKUP(B9,'CPD PITSS'!$B$9:C26,2,0) -> 15 | D9: =+VLOOKUP(B9,'CPD PITSS'!$B$9:F26,5,0) -> 197.07 | E9: 10150 | F9: =+E9/2 -> 5075 | G9: =+F9/15 -> 338.33333 | I9: =15-C9 -> 0 | J9: =+I9*G9 -> 0 | L9: =+VLOOKUP(B9,'CPD PITSS'!$B$9:AG27,3,0) -> 0 | M9: =+G9*L9 -> 0 | N9: =+VLOOKUP(B9,'CPD PITSS'!$B$9:AH27,7,0) -> 0 | O9: =+M9-N9 -> 0 | Q9: =+VLOOKUP(B9,'CPD PITSS'!$B$9:AK27,3,0) -> 0 | R9: =+G9*Q9*30% -> 0 | S9: =+VLOOKUP(B9,'CPD PITSS'!$B$9:AM27,8,0) -> 0 | T9: =+R9-S9 -> 0 | W9: 0 | X9: =+G9*W9 -> 0 | Y9: 0 | Z9: =+X9-Y9 -> 0 | AA9: =+X9*0.25 -> 0 | AB9: 0 | AC9: =+AA9-AB9 -> 0 | AD9: 0 | AE9: =+G9*AD9 -> 0 | AF9: =+AD9*D9 -> 0 | AG9: =+AE9-AF9 -> 0
A10: CONSULTORIA | B10: Arroyo Ramirez Hector Hugo | C10: =+VLOOKUP(B10,'CPD PITSS'!$B$9:C27,2,0) -> 14 | D10: =+VLOOKUP(B10,'CPD PITSS'!$B$9:F27,5,0) -> 252.75 | E10: 13000 | F10: =+E10/2 -> 6500 | G10: =+F10/15 -> 433.33333 | I10: 0 | J10: =+I10*G10 -> 0 | L10: =+VLOOKUP(B10,'CPD PITSS'!$B$9:AG28,3,0) -> 1 | M10: =+G10*L10 -> 433.33333 | N10: =+VLOOKUP(B10,'CPD PITSS'!$B$9:AH28,7,0) -> 238.33 | O10: =+M10-N10 -> 195.00333 | Q10: =+VLOOKUP(B10,'CPD PITSS'!$B$9:AK28,3,0) -> 1 | R10: =+G10*Q10*30% -> 130 | S10: =+VLOOKUP(B10,'CPD PITSS'!$B$9:AM28,8,0) -> 71.5 | T10: =+R10-S10 -> 58.5 | AD10: 0 | AE10: =+G10*AD10 -> 0 | AF10: =+AD10*D10 -> 0 | AG10: =+AE10-AF10 -> 0
A11: CONSULTORIA | B11: Benavides Herrera Alejandra | C11: =+VLOOKUP(B11,'CPD PITSS'!$B$9:C28,2,0) -> 15 | D11: =+VLOOKUP(B11,'CPD PITSS'!$B$9:F28,5,0) -> 176.76 | E11: 40000 | F11: =+E11/2 -> 20000 | G11: =+F11/15 -> 1333.3333 | I11: =15-C11 -> 0 | J11: =+I11*G11 -> 0 | L11: =+VLOOKUP(B11,'CPD PITSS'!$B$9:AG29,3,0) -> 0 | M11: =+G11*L11 -> 0 | N11: =+VLOOKUP(B11,'CPD PITSS'!$B$9:AH29,7,0) -> 0 | O11: =+M11-N11 -> 0 | Q11: =+VLOOKUP(B11,'CPD PITSS'!$B$9:AK29,3,0) -> 0 | R11: =+G11*Q11*30% -> 0 | S11: =+VLOOKUP(B11,'CPD PITSS'!$B$9:AM29,8,0) -> 0 | T11: =+R11-S11 -> 0 | AD11: 0 | AE11: =+G11*AD11 -> 0 | AF11: =+AD11*D11 -> 0 | AG11: =+AE11-AF11 -> 0
A12: CONSULTORIA | B12: Caballero Diaz Francisco Javier | C12: =+VLOOKUP(B12,'CPD PITSS'!$B$9:C29,2,0) -> 15 | D12: =+VLOOKUP(B12,'CPD PITSS'!$B$9:F29,5,0) -> 197.07 | E12: 10150 | F12: =+E12/2 -> 5075 | G12: =+F12/15 -> 338.33333 | I12: =15-C12 -> 0 | J12: =+I12*G12 -> 0 | L12: =+VLOOKUP(B12,'CPD PITSS'!$B$9:AG30,3,0) -> 0 | M12: =+G12*L12 -> 0 | N12: =+VLOOKUP(B12,'CPD PITSS'!$B$9:AH30,7,0) -> 0 | O12: =+M12-N12 -> 0 | Q12: =+VLOOKUP(B12,'CPD PITSS'!$B$9:AK30,3,0) -> 0 | R12: =+G12*Q12*30% -> 0 | S12: =+VLOOKUP(B12,'CPD PITSS'!$B$9:AM30,8,0) -> 0 | T12: =+R12-S12 -> 0 | AD12: 0 | AE12: =+G12*AD12 -> 0 | AF12: =+AD12*D12 -> 0 | AG12: =+AE12-AF12 -> 0
A13: CONSULTORIA | B13: Carbajal Cabuto Jose Luis | C13: =+VLOOKUP(B13,'CPD PITSS'!$B$9:C30,2,0) -> 15 | D13: =+VLOOKUP(B13,'CPD PITSS'!$B$9:F30,5,0) -> 197.07 | E13: 10250 | F13: =+E13/2 -> 5125 | G13: =+F13/15 -> 341.66667 | I13: =15-C13 -> 0 | J13: =+I13*G13 -> 0 | L13: =+VLOOKUP(B13,'CPD PITSS'!$B$9:AG31,3,0) -> 0 | M13: =+G13*L13 -> 0 | N13: =+VLOOKUP(B13,'CPD PITSS'!$B$9:AH31,7,0) -> 0 | O13: =+M13-N13 -> 0 | Q13: =+VLOOKUP(B13,'CPD PITSS'!$B$9:AK31,3,0) -> 0 | R13: =+G13*Q13*30% -> 0 | S13: =+VLOOKUP(B13,'CPD PITSS'!$B$9:AM31,8,0) -> 0 | T13: =+R13-S13 -> 0 | AD13: 0 | AE13: =+G13*AD13 -> 0 | AF13: =+AD13*D13 -> 0 | AG13: =+AE13-AF13 -> 0
A14: CONSULTORIA | B14: Casillas Cardona Cesar Alejandro | C14: =+VLOOKUP(B14,'CPD PITSS'!$B$9:C31,2,0) -> 10 | D14: =+VLOOKUP(B14,'CPD PITSS'!$B$9:F31,5,0) -> 234.19 | E14: 12000 | F14: =+E14/2 -> 6000 | G14: =+F14/15 -> 400 | I14: 0 | J14: =+I14*G14 -> 0 | L14: =+VLOOKUP(B14,'CPD PITSS'!$B$9:AG32,3,0) -> 5 | M14: =+G14*L14 -> 2000 | N14: =+VLOOKUP(B14,'CPD PITSS'!$B$9:AH32,7,0) -> 1104.15 | O14: =+M14-N14 -> 895.85 | Q14: =+VLOOKUP(B14,'CPD PITSS'!$B$9:AK32,3,0) -> 5 | R14: =+G14*Q14*30% -> 600 | S14: =+VLOOKUP(B14,'CPD PITSS'!$B$9:AM32,8,0) -> 331.25 | T14: =+R14-S14 -> 268.75 | AD14: 0 | AE14: =+G14*AD14 -> 0 | AF14: =+AD14*D14 -> 0 | AG14: =+AE14-AF14 -> 0
A15: CONSULTORIA | B15: De La Torre Zambara Francisco Ernesto | C15: =+VLOOKUP(B15,'CPD PITSS'!$B$9:C32,2,0) -> 15 | D15: =+VLOOKUP(B15,'CPD PITSS'!$B$9:F32,5,0) -> 197.07 | E15: 10150 | F15: =+E15/2 -> 5075 | G15: =+F15/15 -> 338.33333 | I15: =15-C15 -> 0 | J15: =+I15*G15 -> 0 | L15: =+VLOOKUP(B15,'CPD PITSS'!$B$9:AG33,3,0) -> 0 | M15: =+G15*L15 -> 0 | N15: =+VLOOKUP(B15,'CPD PITSS'!$B$9:AH33,7,0) -> 0 | O15: =+M15-N15 -> 0 | Q15: =+VLOOKUP(B15,'CPD PITSS'!$B$9:AK33,3,0) -> 0 | R15: =+G15*Q15*30% -> 0 | S15: =+VLOOKUP(B15,'CPD PITSS'!$B$9:AM33,8,0) -> 0 | T15: =+R15-S15 -> 0 | AD15: 0 | AE15: =+G15*AD15 -> 0 | AF15: =+AD15*D15 -> 0 | AG15: =+AE15-AF15 -> 0
A16: CONSULTORIA | B16: Garcia Villicaña Ricardo Pascual | C16: =+VLOOKUP(B16,'CPD PITSS'!$B$9:C33,2,0) -> 15 | D16: =+VLOOKUP(B16,'CPD PITSS'!$B$9:F33,5,0) -> 289.87 | E16: 15000 | F16: =+E16/2 -> 7500 | G16: =+F16/15 -> 500 | I16: =15-C16 -> 0 | J16: =+I16*G16 -> 0 | L16: =+VLOOKUP(B16,'CPD PITSS'!$B$9:AG34,3,0) -> 0 | M16: =+G16*L16 -> 0 | N16: =+VLOOKUP(B16,'CPD PITSS'!$B$9:AH34,7,0) -> 0 | O16: =+M16-N16 -> 0 | Q16: =+VLOOKUP(B16,'CPD PITSS'!$B$9:AK34,3,0) -> 0 | R16: =+G16*Q16*30% -> 0 | S16: =+VLOOKUP(B16,'CPD PITSS'!$B$9:AM34,8,0) -> 0 | T16: =+R16-S16 -> 0 | AD16: 0 | AE16: =+G16*AD16 -> 0 | AF16: =+AD16*D16 -> 0 | AG16: =+AE16-AF16 -> 0
A17: CONSULTORIA | B17: Gutierrez Gutierrez Luis Arturo | C17: =+VLOOKUP(B17,'CPD PITSS'!$B$9:C34,2,0) -> 15 | D17: =+VLOOKUP(B17,'CPD PITSS'!$B$9:F34,5,0) -> 150.25 | E17: 8500 | F17: =+E17/2 -> 4250 | G17: =+F17/15 -> 283.33333 | I17: =15-C17 -> 0 | J17: =+I17*G17 -> 0 | L17: =+VLOOKUP(B17,'CPD PITSS'!$B$9:AG35,3,0) -> 0 | M17: =+G17*L17 -> 0 | N17: =+VLOOKUP(B17,'CPD PITSS'!$B$9:AH35,7,0) -> 0 | O17: =+M17-N17 -> 0 | Q17: =+VLOOKUP(B17,'CPD PITSS'!$B$9:AK35,3,0) -> 0 | R17: =+G17*Q17*30% -> 0 | S17: =+VLOOKUP(B17,'CPD PITSS'!$B$9:AM35,8,0) -> 0 | T17: =+R17-S17 -> 0 | AD17: 0 | AE17: =+G17*AD17 -> 0 | AF17: =+AD17*D17 -> 0 | AG17: =+AE17-AF17 -> 0
A18: CONSULTORIA | B18: Hernandez Ochoa Eduardo | C18: =+VLOOKUP(B18,'CPD PITSS'!$B$9:C35,2,0) -> 15 | D18: =+VLOOKUP(B18,'CPD PITSS'!$B$9:F35,5,0) -> 289.87 | E18: 15000 | F18: =+E18/2 -> 7500 | G18: =+F18/15 -> 500 | I18: =15-C18 -> 0 | J18: =+I18*G18 -> 0 | L18: =+VLOOKUP(B18,'CPD PITSS'!$B$9:AG36,3,0) -> 0 | M18: =+G18*L18 -> 0 | N18: =+VLOOKUP(B18,'CPD PITSS'!$B$9:AH36,7,0) -> 0 | O18: =+M18-N18 -> 0 | Q18: =+VLOOKUP(B18,'CPD PITSS'!$B$9:AK36,3,0) -> 0 | R18: =+G18*Q18*30% -> 0 | S18: =+VLOOKUP(B18,'CPD PITSS'!$B$9:AM36,8,0) -> 0 | T18: =+R18-S18 -> 0 | AD18: 0 | AE18: =+G18*AD18 -> 0 | AF18: =+AD18*D18 -> 0 | AG18: =+AE18-AF18 -> 0
A19: CONSULTORIA | B19: Mariscal Romero Luis Adrian | C19: =+VLOOKUP(B19,'CPD PITSS'!$B$9:C36,2,0) -> 12 | D19: =+VLOOKUP(B19,'CPD PITSS'!$B$9:F36,5,0) -> 276.54 | E19: 15000 | F19: =+E19/2 -> 7500 | G19: =+F19/15 -> 500 | I19: 0 | J19: =+I19*G19 -> 0 | L19: =+VLOOKUP(B19,'CPD PITSS'!$B$9:AG37,3,0) -> 3 | M19: =+G19*L19 -> 1500 | N19: =+VLOOKUP(B19,'CPD PITSS'!$B$9:AH37,7,0) -> 793.74 | O19: =+M19-N19 -> 706.26 | Q19: =+VLOOKUP(B19,'CPD PITSS'!$B$9:AK37,3,0) -> 3 | R19: =+G19*Q19*30% -> 450 | S19: =+VLOOKUP(B19,'CPD PITSS'!$B$9:AM37,8,0) -> 238.12 | T19: =+R19-S19 -> 211.88 | AD19: 0 | AE19: =+G19*AD19 -> 0 | AF19: =+AD19*D19 -> 0 | AG19: =+AE19-AF19 -> 0
A20: CONSULTORIA | B20: Mora Ramirez Acal Aldo Isidro | C20: =+VLOOKUP(B20,'CPD PITSS'!$B$9:C37,2,0) -> 15 | D20: =+VLOOKUP(B20,'CPD PITSS'!$B$9:F37,5,0) -> 229.79 | E20: 13000 | F20: =+E20/2 -> 6500 | G20: =+F20/15 -> 433.33333 | I20: =15-C20 -> 0 | J20: =+I20*G20 -> 0 | L20: =+VLOOKUP(B20,'CPD PITSS'!$B$9:AG38,3,0) -> 0 | M20: =+G20*L20 -> 0 | N20: =+VLOOKUP(B20,'CPD PITSS'!$B$9:AH38,7,0) -> 0 | O20: =+M20-N20 -> 0 | Q20: =+VLOOKUP(B20,'CPD PITSS'!$B$9:AK38,3,0) -> 0 | R20: =+G20*Q20*30% -> 0 | S20: =+VLOOKUP(B20,'CPD PITSS'!$B$9:AM38,8,0) -> 0 | T20: =+R20-S20 -> 0 | AD20: 0 | AE20: =+G20*AD20 -> 0 | AF20: =+AD20*D20 -> 0 | AG20: =+AE20-AF20 -> 0
A21: CONSULTORIA | B21: Morgado Fernandez Martin | C21: =+VLOOKUP(B21,'CPD PITSS'!$B$9:C38,2,0) -> 15 | D21: =+VLOOKUP(B21,'CPD PITSS'!$B$9:F38,5,0) -> 289.87 | E21: 15000 | F21: =+E21/2 -> 7500 | G21: =+F21/15 -> 500 | I21: =15-C21 -> 0 | J21: =+I21*G21 -> 0 | L21: =+VLOOKUP(B21,'CPD PITSS'!$B$9:AG39,3,0) -> 0 | M21: =+G21*L21 -> 0 | N21: =+VLOOKUP(B21,'CPD PITSS'!$B$9:AH39,7,0) -> 0 | O21: =+M21-N21 -> 0 | Q21: =+VLOOKUP(B21,'CPD PITSS'!$B$9:AK39,3,0) -> 0 | R21: =+G21*Q21*30% -> 0 | S21: =+VLOOKUP(B21,'CPD PITSS'!$B$9:AM39,8,0) -> 0 | T21: =+R21-S21 -> 0 | AD21: 0 | AE21: =+G21*AD21 -> 0 | AF21: =+AD21*D21 -> 0 | AG21: =+AE21-AF21 -> 0
A22: CONSULTORIA | B22: Nieto Ortiz Jose Luis | C22: =+VLOOKUP(B22,'CPD PITSS'!$B$9:C39,2,0) -> 6 | D22: =+VLOOKUP(B22,'CPD PITSS'!$B$9:F39,5,0) -> 197.07 | E22: 10000 | F22: =+E22/2 -> 5000 | G22: =+F22/15 -> 333.33333 | I22: 0 | J22: =+I22*G22 -> 0 | L22: =+VLOOKUP(B22,'CPD PITSS'!$B$9:AG40,3,0) -> 9 | M22: =+G22*L22 -> 3000 | N22: =+VLOOKUP(B22,'CPD PITSS'!$B$9:AH40,7,0) -> 1672.47 | O22: =+M22-N22 -> 1327.53 | Q22: =+VLOOKUP(B22,'CPD PITSS'!$B$9:AK40,3,0) -> 9 | R22: =+G22*Q22*30% -> 900 | S22: =+VLOOKUP(B22,'CPD PITSS'!$B$9:AM40,8,0) -> 501.74 | T22: =+R22-S22 -> 398.26 | AD22: 0 | AE22: =+G22*AD22 -> 0 | AF22: =+AD22*D22 -> 0 | AG22: =+AE22-AF22 -> 0
A23: CONSULTORIA | B23: Patricio Aguilar Jhonattan Cristian | C23: =+VLOOKUP(B23,'CPD PITSS'!$B$9:C40,2,0) -> 15 | D23: =+VLOOKUP(B23,'CPD PITSS'!$B$9:F40,5,0) -> 159.07 | E23: 9000 | F23: =+E23/2 -> 4500 | G23: =+F23/15 -> 300 | I23: =15-C23 -> 0 | J23: =+I23*G23 -> 0 | L23: =+VLOOKUP(B23,'CPD PITSS'!$B$9:AG41,3,0) -> 0 | M23: =+G23*L23 -> 0 | N23: =+VLOOKUP(B23,'CPD PITSS'!$B$9:AH41,7,0) -> 0 | O23: =+M23-N23 -> 0 | Q23: =+VLOOKUP(B23,'CPD PITSS'!$B$9:AK41,3,0) -> 0 | R23: =+G23*Q23*30% -> 0 | S23: =+VLOOKUP(B23,'CPD PITSS'!$B$9:AM41,8,0) -> 0 | T23: =+R23-S23 -> 0 | AD23: 0 | AE23: =+G23*AD23 -> 0 | AF23: =+AD23*D23 -> 0 | AG23: =+AE23-AF23 -> 0
A24: CONSULTORIA | B24: Rogel Teran Marco Antonio | C24: =+VLOOKUP(B24,'CPD PITSS'!$B$9:C41,2,0) -> 15 | D24: =+VLOOKUP(B24,'CPD PITSS'!$B$9:F41,5,0) -> 1125.06 | E24: 60000 | F24: =+E24/2 -> 30000 | G24: =+F24/15 -> 2000 | I24: =15-C24 -> 0 | J24: =+I24*G24 -> 0 | L24: =+VLOOKUP(B24,'CPD PITSS'!$B$9:AG42,3,0) -> 0 | M24: =+G24*L24 -> 0 | N24: =+VLOOKUP(B24,'CPD PITSS'!$B$9:AH42,7,0) -> 0 | O24: =+M24-N24 -> 0 | Q24: =+VLOOKUP(B24,'CPD PITSS'!$B$9:AK42,3,0) -> 0 | R24: =+G24*Q24*30% -> 0 | S24: =+VLOOKUP(B24,'CPD PITSS'!$B$9:AM42,8,0) -> 0 | T24: =+R24-S24 -> 0 | AD24: 0 | AE24: =+G24*AD24 -> 0 | AF24: =+AD24*D24 -> 0 | AG24: =+AE24-AF24 -> 0
A25: CONSULTORIA | B25: Sierra Escamilla Daniela | C25: =+VLOOKUP(B25,'CPD PITSS'!$B$9:C42,2,0) -> 15 | D25: =+VLOOKUP(B25,'CPD PITSS'!$B$9:F42,5,0) -> 229.79 | E25: 13000 | F25: =+E25/2 -> 6500 | G25: =+F25/15 -> 433.33333 | I25: =15-C25 -> 0 | J25: =+I25*G25 -> 0 | L25: =+VLOOKUP(B25,'CPD PITSS'!$B$9:AG43,3,0) -> 0 | M25: =+G25*L25 -> 0 | N25: =+VLOOKUP(B25,'CPD PITSS'!$B$9:AH43,7,0) -> 0 | O25: =+M25-N25 -> 0 | Q25: =+VLOOKUP(B25,'CPD PITSS'!$B$9:AK43,3,0) -> 0 | R25: =+G25*Q25*30% -> 0 | S25: =+VLOOKUP(B25,'CPD PITSS'!$B$9:AM43,8,0) -> 0 | T25: =+R25-S25 -> 0 | AD25: 0 | AE25: =+G25*AD25 -> 0 | AF25: =+AD25*D25 -> 0 | AG25: =+AE25-AF25 -> 0
A26: CONSULTORIA | B26: Vazquez Perez Miguel Angel | C26: =+VLOOKUP(B26,'CPD PITSS'!$B$9:C43,2,0) -> 15 | D26: =+VLOOKUP(B26,'CPD PITSS'!$B$9:F43,5,0) -> 300.49 | E26: 18500 | F26: =+E26/2 -> 9250 | G26: =+F26/15 -> 616.66667 | I26: =15-C26 -> 0 | J26: =+I26*G26 -> 0 | L26: =+VLOOKUP(B26,'CPD PITSS'!$B$9:AG44,3,0) -> 0 | M26: =+G26*L26 -> 0 | N26: =+VLOOKUP(B26,'CPD PITSS'!$B$9:AH44,7,0) -> 0 | O26: =+M26-N26 -> 0 | Q26: =+VLOOKUP(B26,'CPD PITSS'!$B$9:AK44,3,0) -> 0 | R26: =+G26*Q26*30% -> 0 | S26: =+VLOOKUP(B26,'CPD PITSS'!$B$9:AM44,8,0) -> 0 | T26: =+R26-S26 -> 0 | AD26: 0 | AE26: =+G26*AD26 -> 0 | AF26: =+AD26*D26 -> 0 | AG26: =+AE26-AF26 -> 0
A27: IP INNOVACION | B27: Aguilar Aguirre Alfonso | C27: =+VLOOKUP(B27,'IP PITSS'!$B$9:C93,2,0) -> 15 | D27: =+VLOOKUP(B27,'IP PITSS'!$B$9:F93,5,0) -> 212.11 | E27: 6000 | F27: =+E27/2 -> 3000 | G27: =+F27/15 -> 200 | I27: =15-C27 -> 0 | J27: =+I27*G27 -> 0 | L27: =+VLOOKUP(B27,'IP PITSS'!$B$9:AF94,3,0) -> 0 | M27: =+G27*L27 -> 0 | N27: =+VLOOKUP(B27,'IP PITSS'!$B$9:AG94,7,0) -> 0 | O27: =+M27-N27 -> 0 | Q27: =+VLOOKUP(B27,'IP PITSS'!$B$9:AJ94,3,0) -> 0 | R27: =+G27*Q27*30% -> 0 | S27: =+VLOOKUP(B27,'IP PITSS'!$B$9:AL94,8,0) -> 0 | T27: =+R27-S27 -> 0 | AD27: 0 | AE27: =+G27*AD27 -> 0 | AF27: =+AD27*D27 -> 0 | AG27: =+AE27-AF27 -> 0
A28: IP INNOVACION | B28: Alejandro Peña Deivi | C28: =+VLOOKUP(B28,'IP PITSS'!$B$9:C94,2,0) -> 15 | D28: =+VLOOKUP(B28,'IP PITSS'!$B$9:F94,5,0) -> 222.72 | E28: 6300 | F28: =+E28/2 -> 3150 | G28: =+F28/15 -> 210 | I28: =15-C28 -> 0 | J28: =+I28*G28 -> 0 | L28: =+VLOOKUP(B28,'IP PITSS'!$B$9:AF95,3,0) -> 0 | M28: =+G28*L28 -> 0 | N28: =+VLOOKUP(B28,'IP PITSS'!$B$9:AG95,7,0) -> 0 | O28: =+M28-N28 -> 0 | Q28: =+VLOOKUP(B28,'IP PITSS'!$B$9:AJ95,3,0) -> 0 | R28: =+G28*Q28*30% -> 0 | S28: =+VLOOKUP(B28,'IP PITSS'!$B$9:AL95,8,0) -> 0 | T28: =+R28-S28 -> 0 | AD28: 0 | AE28: =+G28*AD28 -> 0 | AF28: =+AD28*D28 -> 0 | AG28: =+AE28-AF28 -> 0
A29: IP INNOVACION | B29: Alejandro Vazquez Erasmo Miguel | C29: =+VLOOKUP(B29,'IP PITSS'!$B$9:C95,2,0) -> 15 | D29: =+VLOOKUP(B29,'IP PITSS'!$B$9:F95,5,0) -> 212.11 | E29: 12000 | F29: =+E29/2 -> 6000 | G29: =+F29/15 -> 400 | I29: =15-C29 -> 0 | J29: =+I29*G29 -> 0 | L29: =+VLOOKUP(B29,'IP PITSS'!$B$9:AF96,3,0) -> 0 | M29: =+G29*L29 -> 0 | N29: =+VLOOKUP(B29,'IP PITSS'!$B$9:AG96,7,0) -> 0 | O29: =+M29-N29 -> 0 | Q29: =+VLOOKUP(B29,'IP PITSS'!$B$9:AJ96,3,0) -> 0 | R29: =+G29*Q29*30% -> 0 | S29: =+VLOOKUP(B29,'IP PITSS'!$B$9:AL96,8,0) -> 0 | T29: =+R29-S29 -> 0 | AD29: 0 | AE29: =+G29*AD29 -> 0 | AF29: =+AD29*D29 -> 0 | AG29: =+AE29-AF29 -> 0
A30: IP INNOVACION | B30: Arceo Garcia Manuel Federico | C30: =+VLOOKUP(B30,'IP PITSS'!$B$9:C96,2,0) -> 15 | D30: =+VLOOKUP(B30,'IP PITSS'!$B$9:F96,5,0) -> 212.1 | E30: 6300 | F30: =+E30/2 -> 3150 | G30: =+F30/15 -> 210 | I30: =15-C30 -> 0 | J30: =+I30*G30 -> 0 | L30: =+VLOOKUP(B30,'IP PITSS'!$B$9:AF97,3,0) -> 0 | M30: =+G30*L30 -> 0 | N30: =+VLOOKUP(B30,'IP PITSS'!$B$9:AG97,7,0) -> 0 | O30: =+M30-N30 -> 0 | Q30: =+VLOOKUP(B30,'IP PITSS'!$B$9:AJ97,3,0) -> 0 | R30: =+G30*Q30*30% -> 0 | S30: =+VLOOKUP(B30,'IP PITSS'!$B$9:AL97,8,0) -> 0 | T30: =+R30-S30 -> 0 | AD30: 0 | AE30: =+G30*AD30 -> 0 | AF30: =+AD30*D30 -> 0 | AG30: =+AE30-AF30 -> 0
A31: IP INNOVACION | B31: Arzate Gil Juan Sebastian | C31: =+VLOOKUP(B31,'IP PITSS'!$B$9:C97,2,0) -> 15 | D31: =+VLOOKUP(B31,'IP PITSS'!$B$9:F97,5,0) -> 282.81 | E31: 8000 | F31: =+E31/2 -> 4000 | G31: =+F31/15 -> 266.66667 | I31: =15-C31 -> 0 | J31: =+I31*G31 -> 0 | L31: =+VLOOKUP(B31,'IP PITSS'!$B$9:AF98,3,0) -> 0 | M31: =+G31*L31 -> 0 | N31: =+VLOOKUP(B31,'IP PITSS'!$B$9:AG98,7,0) -> 0 | O31: =+M31-N31 -> 0 | Q31: =+VLOOKUP(B31,'IP PITSS'!$B$9:AJ98,3,0) -> 0 | R31: =+G31*Q31*30% -> 0 | S31: =+VLOOKUP(B31,'IP PITSS'!$B$9:AL98,8,0) -> 0 | T31: =+R31-S31 -> 0 | AD31: 0 | AE31: =+G31*AD31 -> 0 | AF31: =+AD31*D31 -> 0 | AG31: =+AE31-AF31 -> 0
A32: IP INNOVACION | B32: Casas Chavarria Rafael | C32: =+VLOOKUP(B32,'IP PITSS'!$B$9:C98,2,0) -> 15 | D32: =+VLOOKUP(B32,'IP PITSS'!$B$9:F98,5,0) -> 222.72 | E32: 6300 | F32: =+E32/2 -> 3150 | G32: =+F32/15 -> 210 | I32: =15-C32 -> 0 | J32: =+I32*G32 -> 0 | L32: =+VLOOKUP(B32,'IP PITSS'!$B$9:AF99,3,0) -> 0 | M32: =+G32*L32 -> 0 | N32: =+VLOOKUP(B32,'IP PITSS'!$B$9:AG99,7,0) -> 0 | O32: =+M32-N32 -> 0 | Q32: =+VLOOKUP(B32,'IP PITSS'!$B$9:AJ99,3,0) -> 0 | R32: =+G32*Q32*30% -> 0 | S32: =+VLOOKUP(B32,'IP PITSS'!$B$9:AL99,8,0) -> 0 | T32: =+R32-S32 -> 0 | AD32: 0 | AE32: =+G32*AD32 -> 0 | AF32: =+AD32*D32 -> 0 | AG32: =+AE32-AF32 -> 0
A33: IP INNOVACION | B33: Castellon Ramos Rene | C33: =+VLOOKUP(B33,'IP PITSS'!$B$9:C99,2,0) -> 14 | D33: =+VLOOKUP(B33,'IP PITSS'!$B$9:F99,5,0) -> 265.14 | E33: 7505.99 | F33: =+E33/2 -> 3752.995 | G33: =+F33/15 -> 250.19967 | I33: 0 | J33: =+I33*G33 -> 0 | L33: =+VLOOKUP(B33,'IP PITSS'!$B$9:AF100,3,0) -> 1 | M33: =+G33*L33 -> 250.19967 | N33: =+VLOOKUP(B33,'IP PITSS'!$B$9:AG100,7,0) -> 250 | O33: =+M33-N33 -> 0.19966667 | Q33: =+VLOOKUP(B33,'IP PITSS'!$B$9:AJ100,3,0) -> 1 | R33: =+G33*Q33*30% -> 75.0599 | S33: =+VLOOKUP(B33,'IP PITSS'!$B$9:AL100,8,0) -> 75 | T33: =+R33-S33 -> 0.0599 | AD33: 0 | AE33: =+G33*AD33 -> 0 | AF33: =+AD33*D33 -> 0 | AG33: =+AE33-AF33 -> 0
A34: IP INNOVACION | B34: Castillo Nungaray Nestor Roman | C34: =+VLOOKUP(B34,'IP PITSS'!$B$9:C100,2,0) -> 15 | D34: =+VLOOKUP(B34,'IP PITSS'!$B$9:F100,5,0) -> 212.11 | E34: 6300 | F34: =+E34/2 -> 3150 | G34: =+F34/15 -> 210 | I34: =15-C34 -> 0 | J34: =+I34*G34 -> 0 | L34: =+VLOOKUP(B34,'IP PITSS'!$B$9:AF101,3,0) -> 0 | M34: =+G34*L34 -> 0 | N34: =+VLOOKUP(B34,'IP PITSS'!$B$9:AG101,7,0) -> 0 | O34: =+M34-N34 -> 0 | Q34: =+VLOOKUP(B34,'IP PITSS'!$B$9:AJ101,3,0) -> 0 | R34: =+G34*Q34*30% -> 0 | S34: =+VLOOKUP(B34,'IP PITSS'!$B$9:AL101,8,0) -> 0 | T34: =+R34-S34 -> 0 | AD34: 0 | AE34: =+G34*AD34 -> 0 | AF34: =+AD34*D34 -> 0 | AG34: =+AE34-AF34 -> 0
A35: IP INNOVACION | B35: Castillo Ramirez Hector Ivan | C35: =+VLOOKUP(B35,'IP PITSS'!$B$9:C101,2,0) -> 15 | D35: =+VLOOKUP(B35,'IP PITSS'!$B$9:F101,5,0) -> 243.88 | E35: 14000 | F35: =+E35/2 -> 7000 | G35: =+F35/15 -> 466.66667 | I35: =15-C35 -> 0 | J35: =+I35*G35 -> 0 | L35: =+VLOOKUP(B35,'IP PITSS'!$B$9:AF102,3,0) -> 0 | M35: =+G35*L35 -> 0 | N35: =+VLOOKUP(B35,'IP PITSS'!$B$9:AG102,7,0) -> 0 | O35: =+M35-N35 -> 0 | Q35: =+VLOOKUP(B35,'IP PITSS'!$B$9:AJ102,3,0) -> 0 | R35: =+G35*Q35*30% -> 0 | S35: =+VLOOKUP(B35,'IP PITSS'!$B$9:AL102,8,0) -> 0 | T35: =+R35-S35 -> 0 | AD35: 0 | AE35: =+G35*AD35 -> 0 | AF35: =+AD35*D35 -> 0 | AG35: =+AE35-AF35 -> 0
A36: IP INNOVACION | B36: Cerro Garcia Elvis | C36: =+VLOOKUP(B36,'IP PITSS'!$B$9:C102,2,0) -> 15 | D36: =+VLOOKUP(B36,'IP PITSS'!$B$9:F102,5,0) -> 177.03 | E36: 10000 | F36: =+E36/2 -> 5000 | G36: =+F36/15 -> 333.33333 | I36: =15-C36 -> 0 | J36: =+I36*G36 -> 0 | L36: =+VLOOKUP(B36,'IP PITSS'!$B$9:AF103,3,0) -> 0 | M36: =+G36*L36 -> 0 | N36: =+VLOOKUP(B36,'IP PITSS'!$B$9:AG103,7,0) -> 0 | O36: =+M36-N36 -> 0 | Q36: =+VLOOKUP(B36,'IP PITSS'!$B$9:AJ103,3,0) -> 0 | R36: =+G36*Q36*30% -> 0 | S36: =+VLOOKUP(B36,'IP PITSS'!$B$9:AL103,8,0) -> 0 | T36: =+R36-S36 -> 0 | AD36: 0 | AE36: =+G36*AD36 -> 0 | AF36: =+AD36*D36 -> 0 | AG36: =+AE36-AF36 -> 0
A37: IP INNOVACION | B37: Chavez Dominguez Salvador | C37: =+VLOOKUP(B37,'IP PITSS'!$B$9:C103,2,0) -> 15 | D37: =+VLOOKUP(B37,'IP PITSS'!$B$9:F103,5,0) -> 249.64 | E37: 12000 | F37: =+E37/2 -> 6000 | G37: =+F37/15 -> 400 | I37: =15-C37 -> 0 | J37: =+I37*G37 -> 0 | L37: =+VLOOKUP(B37,'IP PITSS'!$B$9:AF104,3,0) -> 0 | M37: =+G37*L37 -> 0 | N37: =+VLOOKUP(B37,'IP PITSS'!$B$9:AG104,7,0) -> 0 | O37: =+M37-N37 -> 0 | Q37: =+VLOOKUP(B37,'IP PITSS'!$B$9:AJ104,3,0) -> 0 | R37: =+G37*Q37*30% -> 0 | S37: =+VLOOKUP(B37,'IP PITSS'!$B$9:AL104,8,0) -> 0 | T37: =+R37-S37 -> 0 | AD37: 0 | AE37: =+G37*AD37 -> 0 | AF37: =+AD37*D37 -> 0 | AG37: =+AE37-AF37 -> 0
A38: IP INNOVACION | B38: Chavez Govea Edgar Aram | C38: =+VLOOKUP(B38,'IP PITSS'!$B$9:C104,2,0) -> 15 | D38: =+VLOOKUP(B38,'IP PITSS'!$B$9:F104,5,0) -> 247.46 | E38: 7000 | F38: =+E38/2 -> 3500 | G38: =+F38/15 -> 233.33333 | I38: =15-C38 -> 0 | J38: =+I38*G38 -> 0 | L38: =+VLOOKUP(B38,'IP PITSS'!$B$9:AF105,3,0) -> 0 | M38: =+G38*L38 -> 0 | N38: =+VLOOKUP(B38,'IP PITSS'!$B$9:AG105,7,0) -> 0 | O38: =+M38-N38 -> 0 | Q38: =+VLOOKUP(B38,'IP PITSS'!$B$9:AJ105,3,0) -> 0 | R38: =+G38*Q38*30% -> 0 | S38: =+VLOOKUP(B38,'IP PITSS'!$B$9:AL105,8,0) -> 0 | T38: =+R38-S38 -> 0 | AD38: 0 | AE38: =+G38*AD38 -> 0 | AF38: =+AD38*D38 -> 0 | AG38: =+AE38-AF38 -> 0
A39: IP INNOVACION | B39: Chavez Pedraza Samuel | C39: =+VLOOKUP(B39,'IP PITSS'!$B$9:C105,2,0) -> 15 | D39: =+VLOOKUP(B39,'IP PITSS'!$B$9:F105,5,0) -> 494.92 | E39: 14000 | F39: =+E39/2 -> 7000 | G39: =+F39/15 -> 466.66667 | I39: =15-C39 -> 0 | J39: =+I39*G39 -> 0 | L39: =+VLOOKUP(B39,'IP PITSS'!$B$9:AF106,3,0) -> 0 | M39: =+G39*L39 -> 0 | N39: =+VLOOKUP(B39,'IP PITSS'!$B$9:AG106,7,0) -> 0 | O39: =+M39-N39 -> 0 | Q39: =+VLOOKUP(B39,'IP PITSS'!$B$9:AJ106,3,0) -> 0 | R39: =+G39*Q39*30% -> 0 | S39: =+VLOOKUP(B39,'IP PITSS'!$B$9:AL106,8,0) -> 0 | T39: =+R39-S39 -> 0 | AD39: 0 | AE39: =+G39*AD39 -> 0 | AF39: =+AD39*D39 -> 0 | AG39: =+AE39-AF39 -> 0
A40: IP INNOVACION | B40: Chavez Saucedo Jorge Arturo | C40: =+VLOOKUP(B40,'IP PITSS'!$B$9:C106,2,0) -> 15 | D40: =+VLOOKUP(B40,'IP PITSS'!$B$9:F106,5,0) -> 278.72 | E40: 8000 | F40: =+E40/2 -> 4000 | G40: =+F40/15 -> 266.66667 | I40: =15-C40 -> 0 | J40: =+I40*G40 -> 0 | L40: =+VLOOKUP(B40,'IP PITSS'!$B$9:AF107,3,0) -> 0 | M40: =+G40*L40 -> 0 | N40: =+VLOOKUP(B40,'IP PITSS'!$B$9:AG107,7,0) -> 0 | O40: =+M40-N40 -> 0 | Q40: =+VLOOKUP(B40,'IP PITSS'!$B$9:AJ107,3,0) -> 0 | R40: =+G40*Q40*30% -> 0 | S40: =+VLOOKUP(B40,'IP PITSS'!$B$9:AL107,8,0) -> 0 | T40: =+R40-S40 -> 0 | AD40: 0 | AE40: =+G40*AD40 -> 0 | AF40: =+AD40*D40 -> 0 | AG40: =+AE40-AF40 -> 0
A41: IP INNOVACION | B41: Chavira Garcia David Fernando | C41: =+VLOOKUP(B41,'IP PITSS'!$B$9:C107,2,0) -> 15 | D41: =+VLOOKUP(B41,'IP PITSS'!$B$9:F107,5,0) -> 353.52 | E41: 10000 | F41: =+E41/2 -> 5000 | G41: =+F41/15 -> 333.33333 | I41: =15-C41 -> 0 | J41: =+I41*G41 -> 0 | L41: =+VLOOKUP(B41,'IP PITSS'!$B$9:AF108,3,0) -> 0 | M41: =+G41*L41 -> 0 | N41: =+VLOOKUP(B41,'IP PITSS'!$B$9:AG108,7,0) -> 0 | O41: =+M41-N41 -> 0 | Q41: =+VLOOKUP(B41,'IP PITSS'!$B$9:AJ108,3,0) -> 0 | R41: =+G41*Q41*30% -> 0 | S41: =+VLOOKUP(B41,'IP PITSS'!$B$9:AL108,8,0) -> 0 | T41: =+R41-S41 -> 0 | AD41: 0 | AE41: =+G41*AD41 -> 0 | AF41: =+AD41*D41 -> 0 | AG41: =+AE41-AF41 -> 0
A42: IP INNOVACION | B42: Cota Jaramillo Miguel Angel | C42: =+VLOOKUP(B42,'IP PITSS'!$B$9:C108,2,0) -> 15 | D42: =+VLOOKUP(B42,'IP PITSS'!$B$9:F108,5,0) -> 209.04 | E42: 6000 | F42: =+E42/2 -> 3000 | G42: =+F42/15 -> 200 | I42: =15-C42 -> 0 | J42: =+I42*G42 -> 0 | L42: =+VLOOKUP(B42,'IP PITSS'!$B$9:AF109,3,0) -> 0 | M42: =+G42*L42 -> 0 | N42: =+VLOOKUP(B42,'IP PITSS'!$B$9:AG109,7,0) -> 0 | O42: =+M42-N42 -> 0 | Q42: =+VLOOKUP(B42,'IP PITSS'!$B$9:AJ109,3,0) -> 0 | R42: =+G42*Q42*30% -> 0 | S42: =+VLOOKUP(B42,'IP PITSS'!$B$9:AL109,8,0) -> 0 | T42: =+R42-S42 -> 0 | AD42: 0 | AE42: =+G42*AD42 -> 0 | AF42: =+AD42*D42 -> 0 | AG42: =+AE42-AF42 -> 0
A43: IP INNOVACION | B43: Courtenay Gutierrez Barry Vladimir | C43: =+VLOOKUP(B43,'IP PITSS'!$B$9:C109,2,0) -> 15 | D43: =+VLOOKUP(B43,'IP PITSS'!$B$9:F109,5,0) -> 174.2 | E43: 5000 | F43: =+E43/2 -> 2500 | G43: =+F43/15 -> 166.66667 | I43: =15-C43 -> 0 | J43: =+I43*G43 -> 0 | L43: =+VLOOKUP(B43,'IP PITSS'!$B$9:AF110,3,0) -> 0 | M43: =+G43*L43 -> 0 | N43: =+VLOOKUP(B43,'IP PITSS'!$B$9:AG110,7,0) -> 0 | O43: =+M43-N43 -> 0 | Q43: =+VLOOKUP(B43,'IP PITSS'!$B$9:AJ110,3,0) -> 0 | R43: =+G43*Q43*30% -> 0 | S43: =+VLOOKUP(B43,'IP PITSS'!$B$9:AL110,8,0) -> 0 | T43: =+R43-S43 -> 0 | AD43: 0 | AE43: =+G43*AD43 -> 0 | AF43: =+AD43*D43 -> 0 | AG43: =+AE43-AF43 -> 0
A44: IP INNOVACION | B44: Cruz Herrera Roberto | C44: =+VLOOKUP(B44,'IP PITSS'!$B$9:C110,2,0) -> 15 | D44: =+VLOOKUP(B44,'IP PITSS'!$B$9:F110,5,0) -> 249.64 | E44: 10000 | F44: =+E44/2 -> 5000 | G44: =+F44/15 -> 333.33333 | I44: =15-C44 -> 0 | J44: =+I44*G44 -> 0 | L44: =+VLOOKUP(B44,'IP PITSS'!$B$9:AF111,3,0) -> 0 | M44: =+G44*L44 -> 0 | N44: =+VLOOKUP(B44,'IP PITSS'!$B$9:AG111,7,0) -> 0 | O44: =+M44-N44 -> 0 | Q44: =+VLOOKUP(B44,'IP PITSS'!$B$9:AJ111,3,0) -> 0 | R44: =+G44*Q44*30% -> 0 | S44: =+VLOOKUP(B44,'IP PITSS'!$B$9:AL111,8,0) -> 0 | T44: =+R44-S44 -> 0 | AD44: 0 | AE44: =+G44*AD44 -> 0 | AF44: =+AD44*D44 -> 0 | AG44: =+AE44-AF44 -> 0
A45: IP INNOVACION | B45: Cruz Perez Alejandro Nezahualcoyotl | C45: =+VLOOKUP(B45,'IP PITSS'!$B$9:C111,2,0) -> 15 | D45: =+VLOOKUP(B45,'IP PITSS'!$B$9:F111,5,0) -> 282.81 | E45: 8000 | F45: =+E45/2 -> 4000 | G45: =+F45/15 -> 266.66667 | I45: =15-C45 -> 0 | J45: =+I45*G45 -> 0 | L45: =+VLOOKUP(B45,'IP PITSS'!$B$9:AF112,3,0) -> 0 | M45: =+G45*L45 -> 0 | N45: =+VLOOKUP(B45,'IP PITSS'!$B$9:AG112,7,0) -> 0 | O45: =+M45-N45 -> 0 | Q45: =+VLOOKUP(B45,'IP PITSS'!$B$9:AJ112,3,0) -> 0 | R45: =+G45*Q45*30% -> 0 | S45: =+VLOOKUP(B45,'IP PITSS'!$B$9:AL112,8,0) -> 0 | T45: =+R45-S45 -> 0 | AD45: 0 | AE45: =+G45*AD45 -> 0 | AF45: =+AD45*D45 -> 0 | AG45: =+AE45-AF45 -> 0
... A70: IP INNOVACION | B70: Martinez Morales Jose Martin | C70: =+VLOOKUP(B70,'IP PITSS'!$B$9:C136,2,0) -> 15 | D70: =+VLOOKUP(B70,'IP PITSS'!$B$9:F136,5,0) -> 494.92 | E70: 14000 | F70: =+E70/2 -> 7000 | G70: =+F70/15 -> 466.66667 | I70: =15-C70 -> 0 | J70: =+I70*G70 -> 0 | L70: =+VLOOKUP(B70,'IP PITSS'!$B$9:AF137,3,0) -> 0 | M70: =+G70*L70 -> 0 | N70: =+VLOOKUP(B70,'IP PITSS'!$B$9:AG137,7,0) -> 0 | O70: =+M70-N70 -> 0 | Q70: =+VLOOKUP(B70,'IP PITSS'!$B$9:AJ137,3,0) -> 0 | R70: =+G70*Q70*30% -> 0 | S70: =+VLOOKUP(B70,'IP PITSS'!$B$9:AL137,8,0) -> 0 | T70: =+R70-S70 -> 0 | AD70: 0 | AE70: =+G70*AD70 -> 0 | AF70: =+AD70*D70 -> 0 | AG70: =+AE70-AF70 -> 0
A71: IP INNOVACION | B71: Martinez Morales Tomas | C71: =+VLOOKUP(B71,'IP PITSS'!$B$9:C137,2,0) -> 10 | D71: =+VLOOKUP(B71,'IP PITSS'!$B$9:F137,5,0) -> 327.01 | E71: 15000 | F71: =+E71/2 -> 7500 | G71: =+F71/15 -> 500 | I71: 0 | J71: =+I71*G71 -> 0 | L71: =+VLOOKUP(B71,'IP PITSS'!$B$9:AF138,3,0) -> 5 | M71: =+G71*L71 -> 2500 | N71: =+VLOOKUP(B71,'IP PITSS'!$B$9:AG138,7,0) -> 1564.35 | O71: =+M71-N71 -> 935.65 | Q71: =+VLOOKUP(B71,'IP PITSS'!$B$9:AJ138,3,0) -> 5 | R71: =+G71*Q71*30% -> 750 | S71: =+VLOOKUP(B71,'IP PITSS'!$B$9:AL138,8,0) -> 469.31 | T71: =+R71-S71 -> 280.69 | AD71: 0 | AE71: =+G71*AD71 -> 0 | AF71: =+AD71*D71 -> 0 | AG71: =+AE71-AF71 -> 0
A72: IP INNOVACION | B72: Martinez Rodriguez Paulo Cesar | C72: =+VLOOKUP(B72,'IP PITSS'!$B$9:C138,2,0) -> 13 | D72: =+VLOOKUP(B72,'IP PITSS'!$B$9:F138,5,0) -> 174.2 | E72: 10000 | F72: =+E72/2 -> 5000 | G72: =+F72/15 -> 333.33333 | I72: 0 | J72: =+I72*G72 -> 0 | L72: =+VLOOKUP(B72,'IP PITSS'!$B$9:AF139,3,0) -> 2 | M72: =+G72*L72 -> 666.66667 | N72: =+VLOOKUP(B72,'IP PITSS'!$B$9:AG139,7,0) -> 333.34 | O72: =+M72-N72 -> 333.32667 | Q72: =+VLOOKUP(B72,'IP PITSS'!$B$9:AJ139,3,0) -> 2 | R72: =+G72*Q72*30% -> 200 | S72: =+VLOOKUP(B72,'IP PITSS'!$B$9:AL139,8,0) -> 100 | T72: =+R72-S72 -> 100 | AD72: 0 | AE72: =+G72*AD72 -> 0 | AF72: =+AD72*D72 -> 0 | AG72: =+AE72-AF72 -> 0
A73: IP INNOVACION | B73: Martinez Zamora Gerardo Mario | C73: =+VLOOKUP(B73,'IP PITSS'!$B$9:C139,2,0) -> 15 | D73: =+VLOOKUP(B73,'IP PITSS'!$B$9:F139,5,0) -> 337.61 | E73: 9550.01 | F73: =+E73/2 -> 4775.005 | G73: =+F73/15 -> 318.33367 | I73: =15-C73 -> 0 | J73: =+I73*G73 -> 0 | L73: =+VLOOKUP(B73,'IP PITSS'!$B$9:AF140,3,0) -> 0 | M73: =+G73*L73 -> 0 | N73: =+VLOOKUP(B73,'IP PITSS'!$B$9:AG140,7,0) -> 0 | O73: =+M73-N73 -> 0 | Q73: =+VLOOKUP(B73,'IP PITSS'!$B$9:AJ140,3,0) -> 0 | R73: =+G73*Q73*30% -> 0 | S73: =+VLOOKUP(B73,'IP PITSS'!$B$9:AL140,8,0) -> 0 | T73: =+R73-S73 -> 0 | AD73: 0 | AE73: =+G73*AD73 -> 0 | AF73: =+AD73*D73 -> 0 | AG73: =+AE73-AF73 -> 0
A74: IP INNOVACION | B74: Medellin Colunga Ruben Dario | C74: =+VLOOKUP(B74,'IP PITSS'!$B$9:C140,2,0) -> 15 | D74: =+VLOOKUP(B74,'IP PITSS'!$B$9:F140,5,0) -> 327.01 | E74: 17000 | F74: =+E74/2 -> 8500 | G74: =+F74/15 -> 566.66667 | I74: =15-C74 -> 0 | J74: =+I74*G74 -> 0 | L74: =+VLOOKUP(B74,'IP PITSS'!$B$9:AF141,3,0) -> 0 | M74: =+G74*L74 -> 0 | N74: =+VLOOKUP(B74,'IP PITSS'!$B$9:AG141,7,0) -> 0 | O74: =+M74-N74 -> 0 | Q74: =+VLOOKUP(B74,'IP PITSS'!$B$9:AJ141,3,0) -> 0 | R74: =+G74*Q74*30% -> 0 | S74: =+VLOOKUP(B74,'IP PITSS'!$B$9:AL141,8,0) -> 0 | T74: =+R74-S74 -> 0 | AD74: 0 | AE74: =+G74*AD74 -> 0 | AF74: =+AD74*D74 -> 0 | AG74: =+AE74-AF74 -> 0
A75: IP INNOVACION | B75: Mejia Duarte Jose Luis | C75: =+VLOOKUP(B75,'IP PITSS'!$B$9:C141,2,0) -> 15 | D75: =+VLOOKUP(B75,'IP PITSS'!$B$9:F141,5,0) -> 176.76 | E75: 12000 | F75: =+E75/2 -> 6000 | G75: =+F75/15 -> 400 | I75: =15-C75 -> 0 | J75: =+I75*G75 -> 0 | L75: =+VLOOKUP(B75,'IP PITSS'!$B$9:AF142,3,0) -> 0 | M75: =+G75*L75 -> 0 | N75: =+VLOOKUP(B75,'IP PITSS'!$B$9:AG142,7,0) -> 0 | O75: =+M75-N75 -> 0 | Q75: =+VLOOKUP(B75,'IP PITSS'!$B$9:AJ142,3,0) -> 0 | R75: =+G75*Q75*30% -> 0 | S75: =+VLOOKUP(B75,'IP PITSS'!$B$9:AL142,8,0) -> 0 | T75: =+R75-S75 -> 0 | AD75: 0 | AE75: =+G75*AD75 -> 0 | AF75: =+AD75*D75 -> 0 | AG75: =+AE75-AF75 -> 0
A76: IP INNOVACION | B76: Mendez Rivera Ivan Israel | C76: =+VLOOKUP(B76,'IP PITSS'!$B$9:C142,2,0) -> 15 | D76: =+VLOOKUP(B76,'IP PITSS'!$B$9:F142,5,0) -> 174.19 | E76: 5000 | F76: =+E76/2 -> 2500 | G76: =+F76/15 -> 166.66667 | I76: =15-C76 -> 0 | J76: =+I76*G76 -> 0 | L76: =+VLOOKUP(B76,'IP PITSS'!$B$9:AF143,3,0) -> 0 | M76: =+G76*L76 -> 0 | N76: =+VLOOKUP(B76,'IP PITSS'!$B$9:AG143,7,0) -> 0 | O76: =+M76-N76 -> 0 | Q76: =+VLOOKUP(B76,'IP PITSS'!$B$9:AJ143,3,0) -> 0 | R76: =+G76*Q76*30% -> 0 | S76: =+VLOOKUP(B76,'IP PITSS'!$B$9:AL143,8,0) -> 0 | T76: =+R76-S76 -> 0 | AD76: 0 | AE76: =+G76*AD76 -> 0 | AF76: =+AD76*D76 -> 0 | AG76: =+AE76-AF76 -> 0
A77: IP INNOVACION | B77: Mireles Casillas Brenda Cristina | C77: =+VLOOKUP(B77,'IP PITSS'!$B$9:C143,2,0) -> 15 | D77: =+VLOOKUP(B77,'IP PITSS'!$B$9:F143,5,0) -> 156.78 | E77: 9000 | F77: =+E77/2 -> 4500 | G77: =+F77/15 -> 300 | I77: =15-C77 -> 0 | J77: =+I77*G77 -> 0 | L77: =+VLOOKUP(B77,'IP PITSS'!$B$9:AF144,3,0) -> 0 | M77: =+G77*L77 -> 0 | N77: =+VLOOKUP(B77,'IP PITSS'!$B$9:AG144,7,0) -> 0 | O77: =+M77-N77 -> 0 | Q77: =+VLOOKUP(B77,'IP PITSS'!$B$9:AJ144,3,0) -> 0 | R77: =+G77*Q77*30% -> 0 | S77: =+VLOOKUP(B77,'IP PITSS'!$B$9:AL144,8,0) -> 0 | T77: =+R77-S77 -> 0 | AD77: 0 | AE77: =+G77*AD77 -> 0 | AF77: =+AD77*D77 -> 0 | AG77: =+AE77-AF77 -> 0
A78: IP INNOVACION | B78: Marin Avila Hector | C78: =+VLOOKUP(B78,'IP PITSS'!$B$9:C144,2,0) -> 15 | D78: =+VLOOKUP(B78,'IP PITSS'!$B$9:F144,5,0) -> 287.43 | E78: 8800 | F78: =+E78/2 -> 4400 | G78: =+F78/15 -> 293.33333 | I78: =15-C78 -> 0 | J78: =+I78*G78 -> 0 | L78: =+VLOOKUP(B78,'IP PITSS'!$B$9:AF145,3,0) -> 0 | M78: =+G78*L78 -> 0 | N78: =+VLOOKUP(B78,'IP PITSS'!$B$9:AG145,7,0) -> 0 | O78: =+M78-N78 -> 0 | Q78: =+VLOOKUP(B78,'IP PITSS'!$B$9:AJ145,3,0) -> 0 | R78: =+G78*Q78*30% -> 0 | S78: =+VLOOKUP(B78,'IP PITSS'!$B$9:AL145,8,0) -> 0 | T78: =+R78-S78 -> 0 | AD78: 0 | AE78: =+G78*AD78 -> 0 | AF78: =+AD78*D78 -> 0 | AG78: =+AE78-AF78 -> 0
A79: IP INNOVACION | B79: Molina Ramirez Gerardo Daniel | C79: =+VLOOKUP(B79,'IP PITSS'!$B$9:C145,2,0) -> 10 | D79: =+VLOOKUP(B79,'IP PITSS'!$B$9:F145,5,0) -> 156.78 | E79: 9000 | F79: =+E79/2 -> 4500 | G79: =+F79/15 -> 300 | I79: 0 | J79: =+I79*G79 -> 0 | L79: =+VLOOKUP(B79,'IP PITSS'!$B$9:AF146,3,0) -> 5 | M79: =+G79*L79 -> 1500 | N79: =+VLOOKUP(B79,'IP PITSS'!$B$9:AG146,7,0) -> 750 | O79: =+M79-N79 -> 750 | Q79: =+VLOOKUP(B79,'IP PITSS'!$B$9:AJ146,3,0) -> 5 | R79: =+G79*Q79*30% -> 450 | S79: =+VLOOKUP(B79,'IP PITSS'!$B$9:AL146,8,0) -> 225 | T79: =+R79-S79 -> 225 | AD79: 0 | AE79: =+G79*AD79 -> 0 | AF79: =+AD79*D79 -> 0 | AG79: =+AE79-AF79 -> 0
A80: IP INNOVACION | B80: Montoya Portillo Carlos Alberto | C80: =+VLOOKUP(B80,'IP PITSS'!$B$9:C146,2,0) -> 15 | D80: =+VLOOKUP(B80,'IP PITSS'!$B$9:F146,5,0) -> 278.72 | E80: 8000 | F80: =+E80/2 -> 4000 | G80: =+F80/15 -> 266.66667 | I80: =15-C80 -> 0 | J80: =+I80*G80 -> 0 | L80: =+VLOOKUP(B80,'IP PITSS'!$B$9:AF147,3,0) -> 0 | M80: =+G80*L80 -> 0 | N80: =+VLOOKUP(B80,'IP PITSS'!$B$9:AG147,7,0) -> 0 | O80: =+M80-N80 -> 0 | Q80: =+VLOOKUP(B80,'IP PITSS'!$B$9:AJ147,3,0) -> 0 | R80: =+G80*Q80*30% -> 0 | S80: =+VLOOKUP(B80,'IP PITSS'!$B$9:AL147,8,0) -> 0 | T80: =+R80-S80 -> 0 | AD80: 0 | AE80: =+G80*AD80 -> 0 | AF80: =+AD80*D80 -> 0 | AG80: =+AE80-AF80 -> 0
A81: IP INNOVACION | B81: Morales Martinez Eduardo | C81: =+VLOOKUP(B81,'IP PITSS'!$B$9:C147,2,0) -> 15 | D81: =+VLOOKUP(B81,'IP PITSS'!$B$9:F147,5,0) -> 222.72 | E81: 6300 | F81: =+E81/2 -> 3150 | G81: =+F81/15 -> 210 | I81: =15-C81 -> 0 | J81: =+I81*G81 -> 0 | L81: =+VLOOKUP(B81,'IP PITSS'!$B$9:AF148,3,0) -> 0 | M81: =+G81*L81 -> 0 | N81: =+VLOOKUP(B81,'IP PITSS'!$B$9:AG148,7,0) -> 0 | O81: =+M81-N81 -> 0 | Q81: =+VLOOKUP(B81,'IP PITSS'!$B$9:AJ148,3,0) -> 0 | R81: =+G81*Q81*30% -> 0 | S81: =+VLOOKUP(B81,'IP PITSS'!$B$9:AL148,8,0) -> 0 | T81: =+R81-S81 -> 0 | AD81: 0 | AE81: =+G81*AD81 -> 0 | AF81: =+AD81*D81 -> 0 | AG81: =+AE81-AF81 -> 0
A82: IP INNOVACION | B82: Moreno Quiroga Ana Sarahi | C82: =+VLOOKUP(B82,'IP PITSS'!$B$9:C148,2,0) -> 15 | D82: =+VLOOKUP(B82,'IP PITSS'!$B$9:F148,5,0) -> 282.81 | E82: 8000 | F82: =+E82/2 -> 4000 | G82: =+F82/15 -> 266.66667 | I82: =15-C82 -> 0 | J82: =+I82*G82 -> 0 | L82: =+VLOOKUP(B82,'IP PITSS'!$B$9:AF149,3,0) -> 0 | M82: =+G82*L82 -> 0 | N82: =+VLOOKUP(B82,'IP PITSS'!$B$9:AG149,7,0) -> 0 | O82: =+M82-N82 -> 0 | Q82: =+VLOOKUP(B82,'IP PITSS'!$B$9:AJ149,3,0) -> 0 | R82: =+G82*Q82*30% -> 0 | S82: =+VLOOKUP(B82,'IP PITSS'!$B$9:AL149,8,0) -> 0 | T82: =+R82-S82 -> 0 | AD82: 0 | AE82: =+G82*AD82 -> 0 | AF82: =+AD82*D82 -> 0 | AG82: =+AE82-AF82 -> 0
A83: IP INNOVACION | B83: Muñoz Reyes Luis Eduardo | C83: =+VLOOKUP(B83,'IP PITSS'!$B$9:C149,2,0) -> 15 | D83: =+VLOOKUP(B83,'IP PITSS'!$B$9:F149,5,0) -> 278.72 | E83: 8000 | F83: =+E83/2 -> 4000 | G83: =+F83/15 -> 266.66667 | I83: =15-C83 -> 0 | J83: =+I83*G83 -> 0 | L83: =+VLOOKUP(B83,'IP PITSS'!$B$9:AF150,3,0) -> 0 | M83: =+G83*L83 -> 0 | N83: =+VLOOKUP(B83,'IP PITSS'!$B$9:AG150,7,0) -> 0 | O83: =+M83-N83 -> 0 | Q83: =+VLOOKUP(B83,'IP PITSS'!$B$9:AJ150,3,0) -> 0 | R83: =+G83*Q83*30% -> 0 | S83: =+VLOOKUP(B83,'IP PITSS'!$B$9:AL150,8,0) -> 0 | T83: =+R83-S83 -> 0 | AD83: 0 | AE83: =+G83*AD83 -> 0 | AF83: =+AD83*D83 -> 0 | AG83: =+AE83-AF83 -> 0
A84: IP INNOVACION | B84: Najera Lopez Raul | C84: =+VLOOKUP(B84,'IP PITSS'!$B$9:C150,2,0) -> 14 | D84: =+VLOOKUP(B84,'IP PITSS'!$B$9:F150,5,0) -> 353.5 | E84: 10000 | F84: =+E84/2 -> 5000 | G84: =+F84/15 -> 333.33333 | I84: =15-C84 -> 1 | J84: =+I84*G84 -> 333.33333 | L84: =+VLOOKUP(B84,'IP PITSS'!$B$9:AF151,3,0) -> 0 | M84: =+G84*L84 -> 0 | N84: =+VLOOKUP(B84,'IP PITSS'!$B$9:AG151,7,0) -> 0 | O84: =+M84-N84 -> 0 | Q84: =+VLOOKUP(B84,'IP PITSS'!$B$9:AJ151,3,0) -> 0 | R84: =+G84*Q84*30% -> 0 | S84: =+VLOOKUP(B84,'IP PITSS'!$B$9:AL151,8,0) -> 0 | T84: =+R84-S84 -> 0 | AD84: 0 | AE84: =+G84*AD84 -> 0 | AF84: =+AD84*D84 -> 0 | AG84: =+AE84-AF84 -> 0
A85: IP INNOVACION | B85: Negrete Bejar Aide Sarai | C85: =+VLOOKUP(B85,'IP PITSS'!$B$9:C151,2,0) -> 15 | D85: =+VLOOKUP(B85,'IP PITSS'!$B$9:F151,5,0) -> 160.96 | E85: 5000 | F85: =+E85/2 -> 2500 | G85: =+F85/15 -> 166.66667 | I85: =15-C85 -> 0 | J85: =+I85*G85 -> 0 | L85: =+VLOOKUP(B85,'IP PITSS'!$B$9:AF152,3,0) -> 0 | M85: =+G85*L85 -> 0 | N85: =+VLOOKUP(B85,'IP PITSS'!$B$9:AG152,7,0) -> 0 | O85: =+M85-N85 -> 0 | Q85: =+VLOOKUP(B85,'IP PITSS'!$B$9:AJ152,3,0) -> 0 | R85: =+G85*Q85*30% -> 0 | S85: =+VLOOKUP(B85,'IP PITSS'!$B$9:AL152,8,0) -> 0 | T85: =+R85-S85 -> 0 | AD85: 0 | AE85: =+G85*AD85 -> 0 | AF85: =+AD85*D85 -> 0 | AG85: =+AE85-AF85 -> 0
A86: IP INNOVACION | B86: Orea Gonzalez Concepcion Esteban | C86: =+VLOOKUP(B86,'IP PITSS'!$B$9:C152,2,0) -> 15 | D86: =+VLOOKUP(B86,'IP PITSS'!$B$9:F152,5,0) -> 222.72 | E86: 6300 | F86: =+E86/2 -> 3150 | G86: =+F86/15 -> 210 | I86: =15-C86 -> 0 | J86: =+I86*G86 -> 0 | L86: =+VLOOKUP(B86,'IP PITSS'!$B$9:AF153,3,0) -> 0 | M86: =+G86*L86 -> 0 | N86: =+VLOOKUP(B86,'IP PITSS'!$B$9:AG153,7,0) -> 0 | O86: =+M86-N86 -> 0 | Q86: =+VLOOKUP(B86,'IP PITSS'!$B$9:AJ153,3,0) -> 0 | R86: =+G86*Q86*30% -> 0 | S86: =+VLOOKUP(B86,'IP PITSS'!$B$9:AL153,8,0) -> 0 | T86: =+R86-S86 -> 0 | AD86: 0 | AE86: =+G86*AD86 -> 0 | AF86: =+AD86*D86 -> 0 | AG86: =+AE86-AF86 -> 0
A87: IP INNOVACION | B87: Palacios Ramos Jesus | C87: =+VLOOKUP(B87,'IP PITSS'!$B$9:C153,2,0) -> 15 | D87: =+VLOOKUP(B87,'IP PITSS'!$B$9:F153,5,0) -> 282.81 | E87: 8000 | F87: =+E87/2 -> 4000 | G87: =+F87/15 -> 266.66667 | I87: =15-C87 -> 0 | J87: =+I87*G87 -> 0 | L87: =+VLOOKUP(B87,'IP PITSS'!$B$9:AF154,3,0) -> 0 | M87: =+G87*L87 -> 0 | N87: =+VLOOKUP(B87,'IP PITSS'!$B$9:AG154,7,0) -> 0 | O87: =+M87-N87 -> 0 | Q87: =+VLOOKUP(B87,'IP PITSS'!$B$9:AJ154,3,0) -> 0 | R87: =+G87*Q87*30% -> 0 | S87: =+VLOOKUP(B87,'IP PITSS'!$B$9:AL154,8,0) -> 0 | T87: =+R87-S87 -> 0 | AD87: 0 | AE87: =+G87*AD87 -> 0 | AF87: =+AD87*D87 -> 0 | AG87: =+AE87-AF87 -> 0
A88: IP INNOVACION | B88: Palacios Vega Luis Rosendo | C88: =+VLOOKUP(B88,'IP PITSS'!$B$9:C154,2,0) -> 15 | D88: =+VLOOKUP(B88,'IP PITSS'!$B$9:F154,5,0) -> 174.2 | E88: 5000 | F88: =+E88/2 -> 2500 | G88: =+F88/15 -> 166.66667 | I88: =15-C88 -> 0 | J88: =+I88*G88 -> 0 | L88: =+VLOOKUP(B88,'IP PITSS'!$B$9:AF155,3,0) -> 0 | M88: =+G88*L88 -> 0 | N88: =+VLOOKUP(B88,'IP PITSS'!$B$9:AG155,7,0) -> 0 | O88: =+M88-N88 -> 0 | Q88: =+VLOOKUP(B88,'IP PITSS'!$B$9:AJ155,3,0) -> 0 | R88: =+G88*Q88*30% -> 0 | S88: =+VLOOKUP(B88,'IP PITSS'!$B$9:AL155,8,0) -> 0 | T88: =+R88-S88 -> 0 | AD88: 0 | AE88: =+G88*AD88 -> 0 | AF88: =+AD88*D88 -> 0 | AG88: =+AE88-AF88 -> 0
A89: IP INNOVACION | B89: Perez Balboa Cesar | C89: =+VLOOKUP(B89,'IP PITSS'!$B$9:C155,2,0) -> 15 | D89: =+VLOOKUP(B89,'IP PITSS'!$B$9:F155,5,0) -> 204.21 | E89: 10000 | F89: =+E89/2 -> 5000 | G89: =+F89/15 -> 333.33333 | I89: =15-C89 -> 0 | J89: =+I89*G89 -> 0 | L89: =+VLOOKUP(B89,'IP PITSS'!$B$9:AF156,3,0) -> 0 | M89: =+G89*L89 -> 0 | N89: =+VLOOKUP(B89,'IP PITSS'!$B$9:AG156,7,0) -> 0 | O89: =+M89-N89 -> 0 | Q89: =+VLOOKUP(B89,'IP PITSS'!$B$9:AJ156,3,0) -> 0 | R89: =+G89*Q89*30% -> 0 | S89: =+VLOOKUP(B89,'IP PITSS'!$B$9:AL156,8,0) -> 0 | T89: =+R89-S89 -> 0 | AD89: 0 | AE89: =+G89*AD89 -> 0 | AF89: =+AD89*D89 -> 0 | AG89: =+AE89-AF89 -> 0
A90: IP INNOVACION | B90: Perez Garcia Andres Alvaro | C90: =+VLOOKUP(B90,'IP PITSS'!$B$9:C156,2,0) -> 15 | D90: =+VLOOKUP(B90,'IP PITSS'!$B$9:F156,5,0) -> 282.81 | E90: 8000 | F90: =+E90/2 -> 4000 | G90: =+F90/15 -> 266.66667 | I90: =15-C90 -> 0 | J90: =+I90*G90 -> 0 | L90: =+VLOOKUP(B90,'IP PITSS'!$B$9:AF157,3,0) -> 0 | M90: =+G90*L90 -> 0 | N90: =+VLOOKUP(B90,'IP PITSS'!$B$9:AG157,7,0) -> 0 | O90: =+M90-N90 -> 0 | Q90: =+VLOOKUP(B90,'IP PITSS'!$B$9:AJ157,3,0) -> 0 | R90: =+G90*Q90*30% -> 0 | S90: =+VLOOKUP(B90,'IP PITSS'!$B$9:AL157,8,0) -> 0 | T90: =+R90-S90 -> 0 | AD90: 0 | AE90: =+G90*AD90 -> 0 | AF90: =+AD90*D90 -> 0 | AG90: =+AE90-AF90 -> 0
A91: IP INNOVACION | B91: Puente Murguia Luis Felipe | C91: =+VLOOKUP(B91,'IP PITSS'!$B$9:C157,2,0) -> 15 | D91: =+VLOOKUP(B91,'IP PITSS'!$B$9:F157,5,0) -> 247.45 | E91: 7000 | F91: =+E91/2 -> 3500 | G91: =+F91/15 -> 233.33333 | I91: =15-C91 -> 0 | J91: =+I91*G91 -> 0 | L91: =+VLOOKUP(B91,'IP PITSS'!$B$9:AF158,3,0) -> 0 | M91: =+G91*L91 -> 0 | N91: =+VLOOKUP(B91,'IP PITSS'!$B$9:AG158,7,0) -> 0 | O91: =+M91-N91 -> 0 | Q91: =+VLOOKUP(B91,'IP PITSS'!$B$9:AJ158,3,0) -> 0 | R91: =+G91*Q91*30% -> 0 | S91: =+VLOOKUP(B91,'IP PITSS'!$B$9:AL158,8,0) -> 0 | T91: =+R91-S91 -> 0 | AD91: 0 | AE91: =+G91*AD91 -> 0 | AF91: =+AD91*D91 -> 0 | AG91: =+AE91-AF91 -> 0
... A111: IP INNOVACION | B111: Moreno Castillo Paulina Yamileth | C111: =+VLOOKUP(B111,'IP PITSS'!$B$9:C177,2,0) -> 6 | D111: =+VLOOKUP(B111,'IP PITSS'!$B$9:F177,5,0) -> 209.04 | E111: 6000 | F111: =+E111/2 -> 3000 | G111: =+F111/15 -> 200 | I111: =15-C111 -> 9 | J111: =+I111*G111 -> 1800 | L111: =+VLOOKUP(B111,'IP PITSS'!$B$9:AF178,3,0) -> 0 | M111: =+G111*L111 -> 0 | N111: =+VLOOKUP(B111,'IP PITSS'!$B$9:AG178,7,0) -> 0 | O111: =+M111-N111 -> 0 | Q111: =+VLOOKUP(B111,'IP PITSS'!$B$9:AJ178,3,0) -> 0 | R111: =+G111*Q111*30% -> 0 | S111: =+VLOOKUP(B111,'IP PITSS'!$B$9:AL178,8,0) -> 0 | T111: =+R111-S111 -> 0 | AD111: 0 | AE111: =+G111*AD111 -> 0 | AF111: =+AD111*D111 -> 0 | AG111: =+AE111-AF111 -> 0
A112: TOTAL | C112: ----------------------- | D112: ----------------------- | E112: ----------------------- | F112: ----------------------- | G112: ----------------------- | H112: ----------------------- | I112: ----------------------- | J112: ----------------------- | K112: ----------------------- | L112: ----------------------- | M112: ----------------------- | N112: ----------------------- | O112: ----------------------- | Q112: ----------------------- | R112: ----------------------- | S112: ----------------------- | T112: ----------------------- | U112: ----------------------- | V112: ----------------------- | W112: ----------------------- | X112: ----------------------- | Y112: ----------------------- | Z112: ----------------------- | AA112: ----------------------- | AB112: ----------------------- | AC112: ----------------------- | AD112: ----------------------- | AE112: ----------------------- | AF112: ----------------------- | AG112: ----------------------- | AH112: -----------------------
C113: =+SUM(C9:C112) -> 1501 | D113: =+SUM(D9:D112) -> 26418.55 | E113: =+SUM(E9:E112) -> 1028731 | F113: =+SUM(F9:F112) -> 514365.51 | G113: =+SUM(G9:G112) -> 34291.034 | H113: =+SUM(H9:H112) -> 0 | I113: =+SUM(I9:I112) -> 13 | J113: =+SUM(J9:J112) -> 2753.3333 | ... O113: =+SUM(O9:O112) -> 5143.8197 | Q113: =+SUM(Q9:Q112) -> 31 | R113: =+SUM(R9:R112) -> 3555.0599 | S113: =+SUM(S9:S112) -> 2011.92 | T113: =+SUM(T9:T112) -> 1543.1399 | U113: =+SUM(U9:U112) -> 0 | V113: =+SUM(V9:V112) -> 0 | W113: =+SUM(W9:W112) -> 0 | X113: =+SUM(X9:X112) -> 0 | ... AH113: =+SUM(AH9:AH112) -> 0

Sheet RESUMEN PITS
B2: RESUMEN
B3: Lista de Raya (forma tabular)
F7: SINDICATO
A8: CLAVE | B8: EMPRESA | C8: NOMBRE | D8: NETO IMSS | F8: SUELDO SINDICATO | G8: BONO | H8: COMISION | I8: PRIMA VACACIONAL SINDICATO | J8: B | K8: NETO A PAGAR | L8: NETO MENSUAL | M8: NETO QUINCENAL SEITON | N8: C | O8: prima vacacional | P8: COMISION Y PRIMA VACACIONAL | Q8: INFONAVIT | R8: FONACOT | S8: FALTAS | T8: DESCUENTOS | U8: D | V8: TOTAL GENERAL | W8: DIFERENCIAS | X8: OBSERVACIONES
A9: SEI0009 | B9: CONSULTORIA | C9: Gutierrez Gutierrez Luis Arturo | D9: =+VLOOKUP(C9,'CPD PITSS'!$B$9:V27,21,0) -> 2774.6 | F9: =VLOOKUP(C9,'SIND PITS'!$C$9:$H$113,2,0) -> 1475.4 | G9: =VLOOKUP(C9,'SIND PITS'!$C$9:$E$113,3,0) -> 0 | H9: =VLOOKUP(C9,'SIND PITS'!$C$9:$F$113,4,0) -> 0 | I9: =VLOOKUP(C9,'SIND PITS'!$C$9:$G$113,5,0) -> 0 | K9: =SUM(D9:I9) -> 4250 | L9: 8500 | M9: =+L9/2 -> 4250 | O9: =+VLOOKUP(C9,'CPD PITSS'!$B$9:I27,8,0) -> 0 | P9: =+G9+H9+I9 -> 0 | Q9: =(VLOOKUP($C9,'CPD PITSS'!$B$9:V26,13,0))+(VLOOKUP($C9,'CPD PITSS'!$B$9:V26,14,0)) -> 0 | R9: 0 | S9: =+VLOOKUP(C9,'EXTRAS Y FESTIVOS'!$B$9:J111,9,0) -> 0 | T9: =VLOOKUP(C9,'CPD PITSS'!$B$9:S26,18,0) -> 0 | V9: =+K9-O9-P9+Q9+R9+T9+S9+IFERROR(VLOOKUP('RESUMEN PITS'!C9,'IP PITSS'!$B$9:$M$93,10),0)+IFERROR(VLOOKUP('RESUMEN PITS'!C9,'IP PITSS'!$B$9:$M$93,11),0)+IFERROR(VLOOKUP('RESUMEN PITS'!C9,'IP PITSS'!$B$9:$M$93,12),0)+VLOOKUP("Comision",'IP PITSS'!$I$99:$J$110,2)/COUNT($F$9:$F$111)+IFERROR(VLOOKUP('RESUMEN PITS'!C9,'IP PITSS'!$B$9:$AD$93,15),0)+IFERROR(VLOOKUP('RESUMEN PITS'!C9,'IP PITSS'!$B$9:$AD$93,21),0)+IFERROR(VLOOKUP('RESUMEN PITS'!C9,'IP PITSS'!$B$9:$AD$93,22),0)+IFERROR(VLOOKUP('RESUMEN PITS'!C9,'IP PITSS'!$B$9:$AD$93,23),0)+IFERROR(VLOOKUP('RESUMEN PITS'!C9,'IP PITSS'!$B$9:$AD$93,24),0)+IFERROR(VLOOKUP('RESUMEN PITS'!C9,'IP PITSS'!$B$9:$AD$93,26),0)+IFERROR(VLOOKUP('RESUMEN PITS'!C9,'IP PITSS'!$B$9:$AD$93,28),0)+IFERROR(VLOOKUP('RESUMEN PITS'!C9,'IP PITSS'!$B$9:$AD$93,29),0)+IFERROR(VLOOKUP('RESUMEN PITS'!C9,'IP PITSS'!$B$9:$AD$93,9),0)*2% -> 5664.5349 | W9: =+M9-V9-S9 -> -1414.5349 | Y9: SEI0009 | Z9: =SUM(V9:V111) -> 631029.97
A10: SEI0026 | B10: CONSULTORIA | C10: Patricio Aguilar Jhonattan Cristian | D10: =+VLOOKUP(C10,'CPD PITSS'!$B$9:V28,21,0) -> 2912 | F10: =VLOOKUP(C10,'SIND PITS'!$C$9:$H$113,2,0) -> 1588 | G10: =VLOOKUP(C10,'SIND PITS'!$C$9:$E$113,3,0) -> 400 | H10: =VLOOKUP(C10,'SIND PITS'!$C$9:$F$113,4,0) -> 0 | I10: =VLOOKUP(C10,'SIND PITS'!$C$9:$G$113,5,0) -> 0 | K10: =SUM(D10:I10) -> 4900 | L10: 9000 | M10: =+L10/2 -> 4500 | O10: =+VLOOKUP(C10,'CPD PITSS'!$B$9:I28,8,0) -> 0 | P10: =+G10+H10+I10 -> 400 | Q10: =(VLOOKUP($C10,'CPD PITSS'!$B$9:V27,13,0))+(VLOOKUP($C10,'CPD PITSS'!$B$9:V27,14,0)) -> 0 | R10: 0 | S10: =+VLOOKUP(C10,'EXTRAS Y FESTIVOS'!$B$9:J112,9,0) -> 0 | T10: =VLOOKUP(C10,'CPD PITSS'!$B$9:S27,18,0) -> 0 | V10: =+K10-O10-P10+Q10+R10+T10+S10+IFERROR(VLOOKUP('RESUMEN PITS'!C10,'IP PITSS'!$B$9:$M$93,10),0)+IFERROR(VLOOKUP('RESUMEN PITS'!C10,'IP PITSS'!$B$9:$M$93,11),0)+IFERROR(VLOOKUP('RESUMEN PITS'!C10,'IP PITSS'!$B$9:$M$93,12),0)+VLOOKUP("Comision",'IP PITSS'!$I$99:$J$110,2)/COUNT($F$9:$F$111)+IFERROR(VLOOKUP('RESUMEN PITS'!C10,'IP PITSS'!$B$9:$AD$93,15),0)+IFERROR(VLOOKUP('RESUMEN PITS'!C10,'IP PITSS'!$B$9:$AD$93,21),0)+IFERROR(VLOOKUP('RESUMEN PITS'!C10,'IP PITSS'!$B$9:$AD$93,22),0)+IFERROR(VLOOKUP('RESUMEN PITS'!C10,'IP PITSS'!$B$9:$AD$93,23),0)+IFERROR(VLOOKUP('RESUMEN PITS'!C10,'IP PITSS'!$B$9:$AD$93,24),0)+IFERROR(VLOOKUP('RESUMEN PITS'!C10,'IP PITSS'!$B$9:$AD$93,26),0)+IFERROR(VLOOKUP('RESUMEN PITS'!C10,'IP PITSS'!$B$9:$AD$93,28),0)+IFERROR(VLOOKUP('RESUMEN PITS'!C10,'IP PITSS'!$B$9:$AD$93,29),0)+IFERROR(VLOOKUP('RESUMEN PITS'!C10,'IP PITSS'!$B$9:$AD$93,9),0)*2% -> 5842.3659 | W10: =+M10-V10-S10 -> -1342.3659 | Y10: SEI0026
A11: SEI0040 | B11: CONSULTORIA | C11: Mora Ramirez Acal Aldo Isidro | D11: =+VLOOKUP(C11,'CPD PITSS'!$B$9:V29,21,0) -> 4036 | F11: =VLOOKUP(C11,'SIND PITS'!$C$9:$H$113,2,0) -> 2464 | G11: =VLOOKUP(C11,'SIND PITS'!$C$9:$E$113,3,0) -> 1000 | H11: =VLOOKUP(C11,'SIND PITS'!$C$9:$F$113,4,0) -> 0 | I11: =VLOOKUP(C11,'SIND PITS'!$C$9:$G$113,5,0) -> 0 | K11: =SUM(D11:I11) -> 7500 | L11: 13000 | M11: =+L11/2 -> 6500 | O11: =+VLOOKUP(C11,'CPD PITSS'!$B$9:I29,8,0) -> 0 | P11: =+G11+H11+I11 -> 1000 | Q11: =(VLOOKUP($C11,'CPD PITSS'!$B$9:V28,13,0))+(VLOOKUP($C11,'CPD PITSS'!$B$9:V28,14,0)) -> 0 | R11: 0 | S11: =+VLOOKUP(C11,'EXTRAS Y FESTIVOS'!$B$9:J113,9,0) -> 0 | T11: =VLOOKUP(C11,'CPD PITSS'!$B$9:S28,18,0) -> 0 | V11: =+K11-O11-P11+Q11+R11+T11+S11+IFERROR(VLOOKUP('RESUMEN PITS'!C11,'IP PITSS'!$B$9:$M$93,10),0)+IFERROR(VLOOKUP('RESUMEN PITS'!C11,'IP PITSS'!$B$9:$M$93,11),0)+IFERROR(VLOOKUP('RESUMEN PITS'!C11,'IP PITSS'!$B$9:$M$93,12),0)+VLOOKUP("Comision",'IP PITSS'!$I$99:$J$110,2)/COUNT($F$9:$F$111)+IFERROR(VLOOKUP('RESUMEN PITS'!C11,'IP PITSS'!$B$9:$AD$93,15),0)+IFERROR(VLOOKUP('RESUMEN PITS'!C11,'IP PITSS'!$B$9:$AD$93,21),0)+IFERROR(VLOOKUP('RESUMEN PITS'!C11,'IP PITSS'!$B$9:$AD$93,22),0)+IFERROR(VLOOKUP('RESUMEN PITS'!C11,'IP PITSS'!$B$9:$AD$93,23),0)+IFERROR(VLOOKUP('RESUMEN PITS'!C11,'IP PITSS'!$B$9:$AD$93,24),0)+IFERROR(VLOOKUP('RESUMEN PITS'!C11,'IP PITSS'!$B$9:$AD$93,26),0)+IFERROR(VLOOKUP('RESUMEN PITS'!C11,'IP PITSS'!$B$9:$AD$93,28),0)+IFERROR(VLOOKUP('RESUMEN PITS'!C11,'IP PITSS'!$B$9:$AD$93,29),0)+IFERROR(VLOOKUP('RESUMEN PITS'!C11,'IP PITSS'!$B$9:$AD$93,9),0)*2% -> 8001.4969 | W11: =+M11-V11-S11 -> -1501.4969 | Y11: SEI0040
A12: SEI0041 | B12: CONSULTORIA | C12: Vazquez Perez Miguel Angel | D12: =+VLOOKUP(C12,'CPD PITSS'!$B$9:V30,21,0) -> 5074 | F12: =VLOOKUP(C12,'SIND PITS'!$C$9:$H$113,2,0) -> 4176 | G12: =VLOOKUP(C12,'SIND PITS'!$C$9:$E$113,3,0) -> 750 | H12: =VLOOKUP(C12,'SIND PITS'!$C$9:$F$113,4,0) -> 0 | I12: =VLOOKUP(C12,'SIND PITS'!$C$9:$G$113,5,0) -> 0 | K12: =SUM(D12:I12) -> 10000 | L12: 18500 | M12: =+L12/2 -> 9250 | O12: =+VLOOKUP(C12,'CPD PITSS'!$B$9:I30,8,0) -> 0 | P12: =+G12+H12+I12 -> 750 | Q12: =(VLOOKUP($C12,'CPD PITSS'!$B$9:V29,13,0))+(VLOOKUP($C12,'CPD PITSS'!$B$9:V29,14,0)) -> 0 | R12: 0 | S12: =+VLOOKUP(C12,'EXTRAS Y FESTIVOS'!$B$9:J114,9,0) -> 0 | T12: =VLOOKUP(C12,'CPD PITSS'!$B$9:S29,18,0) -> 0 | V12: =+K12-O12-P12+Q12+R12+T12+S12+IFERROR(VLOOKUP('RESUMEN PITS'!C12,'IP PITSS'!$B$9:$M$93,10),0)+IFERROR(VLOOKUP('RESUMEN PITS'!C12,'IP PITSS'!$B$9:$M$93,11),0)+IFERROR(VLOOKUP('RESUMEN PITS'!C12,'IP PITSS'!$B$9:$M$93,12),0)+VLOOKUP("Comision",'IP PITSS'!$I$99:$J$110,2)/COUNT($F$9:$F$111)+IFERROR(VLOOKUP('RESUMEN PITS'!C12,'IP PITSS'!$B$9:$AD$93,15),0)+IFERROR(VLOOKUP('RESUMEN PITS'!C12,'IP PITSS'!$B$9:$AD$93,21),0)+IFERROR(VLOOKUP('RESUMEN PITS'!C12,'IP PITSS'!$B$9:$AD$93,22),0)+IFERROR(VLOOKUP('RESUMEN PITS'!C12,'IP PITSS'!$B$9:$AD$93,23),0)+IFERROR(VLOOKUP('RESUMEN PITS'!C12,'IP PITSS'!$B$9:$AD$93,24),0)+IFERROR(VLOOKUP('RESUMEN PITS'!C12,'IP PITSS'!$B$9:$AD$93,26),0)+IFERROR(VLOOKUP('RESUMEN PITS'!C12,'IP PITSS'!$B$9:$AD$93,28),0)+IFERROR(VLOOKUP('RESUMEN PITS'!C12,'IP PITSS'!$B$9:$AD$93,29),0)+IFERROR(VLOOKUP('RESUMEN PITS'!C12,'IP PITSS'!$B$9:$AD$93,9),0)*2% -> 10034.996 | W12: =+M12-V12-S12 -> -784.99592 | Y12: SEI0041
A13: SEI0088 | B13: CONSULTORIA | C13: Morgado Fernandez Martin | D13: =+VLOOKUP(C13,'CPD PITSS'!$B$9:V31,21,0) -> 4623.8 | F13: =VLOOKUP(C13,'SIND PITS'!$C$9:$H$113,2,0) -> 2600.25 | G13: =VLOOKUP(C13,'SIND PITS'!$C$9:$E$113,3,0) -> 75 | H13: =VLOOKUP(C13,'SIND PITS'!$C$9:$F$113,4,0) -> 0 | I13: =VLOOKUP(C13,'SIND PITS'!$C$9:$G$113,5,0) -> 0 | K13: =SUM(D13:I13) -> 7299.05 | L13: 15000 | M13: =+L13/2 -> 7500 | O13: =+VLOOKUP(C13,'CPD PITSS'!$B$9:I31,8,0) -> 0 | P13: =+G13+H13+I13 -> 75 | Q13: =(VLOOKUP($C13,'CPD PITSS'!$B$9:V30,13,0))+(VLOOKUP($C13,'CPD PITSS'!$B$9:V30,14,0)) -> 0 | R13: 0 | S13: =+VLOOKUP(C13,'EXTRAS Y FESTIVOS'!$B$9:J115,9,0) -> 0 | T13: =VLOOKUP(C13,'CPD PITSS'!$B$9:S30,18,0) -> 275.95 | V13: =+K13-O13-P13+Q13+R13+T13+S13+IFERROR(VLOOKUP('RESUMEN PITS'!C13,'IP PITSS'!$B$9:$M$93,10),0)+IFERROR(VLOOKUP('RESUMEN PITS'!C13,'IP PITSS'!$B$9:$M$93,11),0)+IFERROR(VLOOKUP('RESUMEN PITS'!C13,'IP PITSS'!$B$9:$M$93,12),0)+VLOOKUP("Comision",'IP PITSS'!$I$99:$J$110,2)/COUNT($F$9:$F$111)+IFERROR(VLOOKUP('RESUMEN PITS'!C13,'IP PITSS'!$B$9:$AD$93,15),0)+IFERROR(VLOOKUP('RESUMEN PITS'!C13,'IP PITSS'!$B$9:$AD$93,21),0)+IFERROR(VLOOKUP('RESUMEN PITS'!C13,'IP PITSS'!$B$9:$AD$93,22),0)+IFERROR(VLOOKUP('RESUMEN PITS'!C13,'IP PITSS'!$B$9:$AD$93,23),0)+IFERROR(VLOOKUP('RESUMEN PITS'!C13,'IP PITSS'!$B$9:$AD$93,24),0)+IFERROR(VLOOKUP('RESUMEN PITS'!C13,'IP PITSS'!$B$9:$AD$93,26),0)+IFERROR(VLOOKUP('RESUMEN PITS'!C13,'IP PITSS'!$B$9:$AD$93,28),0)+IFERROR(VLOOKUP('RESUMEN PITS'!C13,'IP PITSS'!$B$9:$AD$93,29),0)+IFERROR(VLOOKUP('RESUMEN PITS'!C13,'IP PITSS'!$B$9:$AD$93,9),0)*2% -> 9001.4969 | W13: =+M13-V13-S13 -> -1501.4969 | Y13: SEI0088
A14: SEI0097 | B14: CONSULTORIA | C14: Arreola Jimenez Jose Nieves | D14: =+VLOOKUP(C14,'CPD PITSS'!$B$9:V32,21,0) -> 1666.6 | F14: =VLOOKUP(C14,'SIND PITS'!$C$9:$H$113,2,0) -> 1558.07 | G14: =VLOOKUP(C14,'SIND PITS'!$C$9:$E$113,3,0) -> 420 | H14: =VLOOKUP(C14,'SIND PITS'!$C$9:$F$113,4,0) -> 0 | I14: =VLOOKUP(C14,'SIND PITS'!$C$9:$G$113,5,0) -> 0 | K14: =SUM(D14:I14) -> 3644.67 | L14: 10150 | M14: =+L14/2 -> 5075 | O14: =+VLOOKUP(C14,'CPD PITSS'!$B$9:I32,8,0) -> 0 | P14: =+G14+H14+I14 -> 420 | Q14: =(VLOOKUP($C14,'CPD PITSS'!$B$9:V31,13,0))+(VLOOKUP($C14,'CPD PITSS'!$B$9:V31,14,0)) -> 1541.78 | R14: 0 | S14: =+VLOOKUP(C14,'EXTRAS Y FESTIVOS'!$B$9:J116,9,0) -> 0 | T14: =VLOOKUP(C14,'CPD PITSS'!$B$9:S31,18,0) -> 308.55 | V14: =+K14-O14-P14+Q14+R14+T14+S14+IFERROR(VLOOKUP('RESUMEN PITS'!C14,'IP PITSS'!$B$9:$M$93,10),0)+IFERROR(VLOOKUP('RESUMEN PITS'!C14,'IP PITSS'!$B$9:$M$93,11),0)+IFERROR(VLOOKUP('RESUMEN PITS'!C14,'IP PITSS'!$B$9:$M$93,12),0)+VLOOKUP("Comision",'IP PITSS'!$I$99:$J$110,2)/COUNT($F$9:$F$111)+IFERROR(VLOOKUP('RESUMEN PITS'!C14,'IP PITSS'!$B$9:$AD$93,15),0)+IFERROR(VLOOKUP('RESUMEN PITS'!C14,'IP PITSS'!$B$9:$AD$93,21),0)+IFERROR(VLOOKUP('RESUMEN PITS'!C14,'IP PITSS'!$B$9:$AD$93,22),0)+IFERROR(VLOOKUP('RESUMEN PITS'!C14,'IP PITSS'!$B$9:$AD$93,23),0)+IFERROR(VLOOKUP('RESUMEN PITS'!C14,'IP PITSS'!$B$9:$AD$93,24),0)+IFERROR(VLOOKUP('RESUMEN PITS'!C14,'IP PITSS'!$B$9:$AD$93,26),0)+IFERROR(VLOOKUP('RESUMEN PITS'!C14,'IP PITSS'!$B$9:$AD$93,28),0)+IFERROR(VLOOKUP('RESUMEN PITS'!C14,'IP PITSS'!$B$9:$AD$93,29),0)+IFERROR(VLOOKUP('RESUMEN PITS'!C14,'IP PITSS'!$B$9:$AD$93,9),0)*2% -> 5129.0559 | W14: =+M14-V14-S14 -> -54.055924 | Y14: SEI0097
A15: SEI0099 | B15: CONSULTORIA | C15: Garcia Villicaña Ricardo Pascual | D15: =+VLOOKUP(C15,'CPD PITSS'!$B$9:V33,21,0) -> 4686.2 | F15: =VLOOKUP(C15,'SIND PITS'!$C$9:$H$113,2,0) -> 2600.25 | G15: =VLOOKUP(C15,'SIND PITS'!$C$9:$E$113,3,0) -> 0 | H15: =VLOOKUP(C15,'SIND PITS'!$C$9:$F$113,4,0) -> 0 | I15: =VLOOKUP(C15,'SIND PITS'!$C$9:$G$113,5,0) -> 0 | K15: =SUM(D15:I15) -> 7286.45 | L15: 15000 | M15: =+L15/2 -> 7500 | O15: =+VLOOKUP(C15,'CPD PITSS'!$B$9:I33,8,0) -> 0 | P15: =+G15+H15+I15 -> 0 | Q15: =(VLOOKUP($C15,'CPD PITSS'!$B$9:V32,13,0))+(VLOOKUP($C15,'CPD PITSS'!$B$9:V32,14,0)) -> 0 | R15: 0 | S15: =+VLOOKUP(C15,'EXTRAS Y FESTIVOS'!$B$9:J117,9,0) -> 0 | T15: =VLOOKUP(C15,'CPD PITSS'!$B$9:S32,18,0) -> 213.55 | V15: =+K15-O15-P15+Q15+R15+T15+S15+IFERROR(VLOOKUP('RESUMEN PITS'!C15,'IP PITSS'!$B$9:$M$93,10),0)+IFERROR(VLOOKUP('RESUMEN PITS'!C15,'IP PITSS'!$B$9:$M$93,11),0)+IFERROR(VLOOKUP('RESUMEN PITS'!C15,'IP PITSS'!$B$9:$M$93,12),0)+VLOOKUP("Comision",'IP PITSS'!$I$99:$J$110,2)/COUNT($F$9:$F$111)+IFERROR(VLOOKUP('RESUMEN PITS'!C15,'IP PITSS'!$B$9:$AD$93,15),0)+IFERROR(VLOOKUP('RESUMEN PITS'!C15,'IP PITSS'!$B$9:$AD$93,21),0)+IFERROR(VLOOKUP('RESUMEN PITS'!C15,'IP PITSS'!$B$9:$AD$93,22),0)+IFERROR(VLOOKUP('RESUMEN PITS'!C15,'IP PITSS'!$B$9:$AD$93,23),0)+IFERROR(VLOOKUP('RESUMEN PITS'!C15,'IP PITSS'!$B$9:$AD$93,24),0)+IFERROR(VLOOKUP('RESUMEN PITS'!C15,'IP PITSS'!$B$9:$AD$93,26),0)+IFERROR(VLOOKUP('RESUMEN PITS'!C15,'IP PITSS'!$B$9:$AD$93,28),0)+IFERROR(VLOOKUP('RESUMEN PITS'!C15,'IP PITSS'!$B$9:$AD$93,29),0)+IFERROR(VLOOKUP('RESUMEN PITS'!C15,'IP PITSS'!$B$9:$AD$93,9),0)*2% -> 8914.5349 | W15: =+M15-V15-S15 -> -1414.5349 | Y15: SEI0099
A16: SEI0108 | B16: CONSULTORIA | C16: Caballero Diaz Francisco Javier | D16: =+VLOOKUP(C16,'CPD PITSS'!$B$9:V34,21,0) -> 1488.8 | F16: =VLOOKUP(C16,'SIND PITS'!$C$9:$H$113,2,0) -> 1558.02 | G16: =VLOOKUP(C16,'SIND PITS'!$C$9:$E$113,3,0) -> 210 | H16: =VLOOKUP(C16,'SIND PITS'!$C$9:$F$113,4,0) -> 0 | I16: =VLOOKUP(C16,'SIND PITS'!$C$9:$G$113,5,0) -> 0 | K16: =SUM(D16:I16) -> 3256.82 | L16: 10150 | M16: =+L16/2 -> 5075 | O16: =+VLOOKUP(C16,'CPD PITSS'!$B$9:I34,8,0) -> 0 | P16: =+G16+H16+I16 -> 210 | Q16: =(VLOOKUP($C16,'CPD PITSS'!$B$9:V33,13,0))+(VLOOKUP($C16,'CPD PITSS'!$B$9:V33,14,0)) -> 1789.38 | R16: 0 | S16: =+VLOOKUP(C16,'EXTRAS Y FESTIVOS'!$B$9:J118,9,0) -> 0 | T16: =VLOOKUP(C16,'CPD PITSS'!$B$9:S33,18,0) -> 238.8 | V16: =+K16-O16-P16+Q16+R16+T16+S16+IFERROR(VLOOKUP('RESUMEN PITS'!C16,'IP PITSS'!$B$9:$M$93,10),0)+IFERROR(VLOOKUP('RESUMEN PITS'!C16,'IP PITSS'!$B$9:$M$93,11),0)+IFERROR(VLOOKUP('RESUMEN PITS'!C16,'IP PITSS'!$B$9:$M$93,12),0)+VLOOKUP("Comision",'IP PITSS'!$I$99:$J$110,2)/COUNT($F$9:$F$111)+IFERROR(VLOOKUP('RESUMEN PITS'!C16,'IP PITSS'!$B$9:$AD$93,15),0)+IFERROR(VLOOKUP('RESUMEN PITS'!C16,'IP PITSS'!$B$9:$AD$93,21),0)+IFERROR(VLOOKUP('RESUMEN PITS'!C16,'IP PITSS'!$B$9:$AD$93,22),0)+IFERROR(VLOOKUP('RESUMEN PITS'!C16,'IP PITSS'!$B$9:$AD$93,23),0)+IFERROR(VLOOKUP('RESUMEN PITS'!C16,'IP PITSS'!$B$9:$AD$93,24),0)+IFERROR(VLOOKUP('RESUMEN PITS'!C16,'IP PITSS'!$B$9:$AD$93,26),0)+IFERROR(VLOOKUP('RESUMEN PITS'!C16,'IP PITSS'!$B$9:$AD$93,28),0)+IFERROR(VLOOKUP('RESUMEN PITS'!C16,'IP PITSS'!$B$9:$AD$93,29),0)+IFERROR(VLOOKUP('RESUMEN PITS'!C16,'IP PITSS'!$B$9:$AD$93,9),0)*2% -> 5129.0559 | W16: =+M16-V16-S16 -> -54.055924 | Y16: SEI0108
A17: SEI0116 | B17: CONSULTORIA | C17: Casillas Cardona Cesar Alejandro | D17: =+VLOOKUP(C17,'CPD PITSS'!$B$9:V35,21,0) -> 3545.2 | F17: =VLOOKUP(C17,'SIND PITS'!$C$9:$H$113,2,0) -> 1891.12 | G17: =VLOOKUP(C17,'SIND PITS'!$C$9:$E$113,3,0) -> 0 | H17: =VLOOKUP(C17,'SIND PITS'!$C$9:$F$113,4,0) -> 0 | I17: =VLOOKUP(C17,'SIND PITS'!$C$9:$G$113,5,0) -> 268.75 | K17: =SUM(D17:I17) -> 5705.07 | L17: 12000 | M17: =+L17/2 -> 6000 | O17: =+VLOOKUP(C17,'CPD PITSS'!$B$9:I35,8,0) -> 331.25 | P17: =+G17+H17+I17 -> 268.75 | Q17: =(VLOOKUP($C17,'CPD PITSS'!$B$9:V34,13,0))+(VLOOKUP($C17,'CPD PITSS'!$B$9:V34,14,0)) -> 894.93 | R17: 0 | S17: =+VLOOKUP(C17,'EXTRAS Y FESTIVOS'!$B$9:J119,9,0) -> 0 | T17: =VLOOKUP(C17,'CPD PITSS'!$B$9:S34,18,0) -> 0 | V17: =+K17-O17-P17+Q17+R17+T17+S17+IFERROR(VLOOKUP('RESUMEN PITS'!C17,'IP PITSS'!$B$9:$M$93,10),0)+IFERROR(VLOOKUP('RESUMEN PITS'!C17,'IP PITSS'!$B$9:$M$93,11),0)+IFERROR(VLOOKUP('RESUMEN PITS'!C17,'IP PITSS'!$B$9:$M$93,12),0)+VLOOKUP("Comision",'IP PITSS'!$I$99:$J$110,2)/COUNT($F$9:$F$111)+IFERROR(VLOOKUP('RESUMEN PITS'!C17,'IP PITSS'!$B$9:$AD$93,15),0)+IFERROR(VLOOKUP('RESUMEN PITS'!C17,'IP PITSS'!$B$9:$AD$93,21),0)+IFERROR(VLOOKUP('RESUMEN PITS'!C17,'IP PITSS'!$B$9:$AD$93,22),0)+IFERROR(VLOOKUP('RESUMEN PITS'!C17,'IP PITSS'!$B$9:$AD$93,23),0)+IFERROR(VLOOKUP('RESUMEN PITS'!C17,'IP PITSS'!$B$9:$AD$93,24),0)+IFERROR(VLOOKUP('RESUMEN PITS'!C17,'IP PITSS'!$B$9:$AD$93,26),0)+IFERROR(VLOOKUP('RESUMEN PITS'!C17,'IP PITSS'!$B$9:$AD$93,28),0)+IFERROR(VLOOKUP('RESUMEN PITS'!C17,'IP PITSS'!$B$9:$AD$93,29),0)+IFERROR(VLOOKUP('RESUMEN PITS'!C17,'IP PITSS'!$B$9:$AD$93,9),0)*2% -> 6054.0559 | W17: =+M17-V17-S17 -> -54.055924 | Y17: SEI0116
A18: SEI0117 | B18: CONSULTORIA | C18: Mariscal Romero Luis Adrian | D18: =+VLOOKUP(C18,'CPD PITSS'!$B$9:V36,21,0) -> 4987.2 | F18: =VLOOKUP(C18,'SIND PITS'!$C$9:$H$113,2,0) -> 2750.92 | G18: =VLOOKUP(C18,'SIND PITS'!$C$9:$E$113,3,0) -> 0 | H18: =VLOOKUP(C18,'SIND PITS'!$C$9:$F$113,4,0) -> 0 | I18: =VLOOKUP(C18,'SIND PITS'!$C$9:$G$113,5,0) -> 211.88 | K18: =SUM(D18:I18) -> 7950 | L18: 15000 | M18: =+L18/2 -> 7500 | O18: =+VLOOKUP(C18,'CPD PITSS'!$B$9:I36,8,0) -> 238.12 | P18: =+G18+H18+I18 -> 211.88 | Q18: =(VLOOKUP($C18,'CPD PITSS'!$B$9:V35,13,0))+(VLOOKUP($C18,'CPD PITSS'!$B$9:V35,14,0)) -> 0 | R18: 0 | S18: =+VLOOKUP(C18,'EXTRAS Y FESTIVOS'!$B$9:J120,9,0) -> 0 | T18: =VLOOKUP(C18,'CPD PITSS'!$B$9:S35,18,0) -> 0 | V18: =+K18-O18-P18+Q18+R18+T18+S18+IFERROR(VLOOKUP('RESUMEN PITS'!C18,'IP PITSS'!$B$9:$M$93,10),0)+IFERROR(VLOOKUP('RESUMEN PITS'!C18,'IP PITSS'!$B$9:$M$93,11),0)+IFERROR(VLOOKUP('RESUMEN PITS'!C18,'IP PITSS'!$B$9:$M$93,12),0)+VLOOKUP("Comision",'IP PITSS'!$I$99:$J$110,2)/COUNT($F$9:$F$111)+IFERROR(VLOOKUP('RESUMEN PITS'!C18,'IP PITSS'!$B$9:$AD$93,15),0)+IFERROR(VLOOKUP('RESUMEN PITS'!C18,'IP PITSS'!$B$9:$AD$93,21),0)+IFERROR(VLOOKUP('RESUMEN PITS'!C18,'IP PITSS'!$B$9:$AD$93,22),0)+IFERROR(VLOOKUP('RESUMEN PITS'!C18,'IP PITSS'!$B$9:$AD$93,23),0)+IFERROR(VLOOKUP('RESUMEN PITS'!C18,'IP PITSS'!$B$9:$AD$93,24),0)+IFERROR(VLOOKUP('RESUMEN PITS'!C18,'IP PITSS'!$B$9:$AD$93,26),0)+IFERROR(VLOOKUP('RESUMEN PITS'!C18,'IP PITSS'!$B$9:$AD$93,28),0)+IFERROR(VLOOKUP('RESUMEN PITS'!C18,'IP PITSS'!$B$9:$AD$93,29),0)+IFERROR(VLOOKUP('RESUMEN PITS'!C18,'IP PITSS'!$B$9:$AD$93,9),0)*2% -> 8914.5349 | W18: =+M18-V18-S18 -> -1414.5349 | Y18: SEI0117
A19: SEI0118 | B19: CONSULTORIA | C19: Arroyo Ramirez Hector Hugo | D19: =+VLOOKUP(C19,'CPD PITSS'!$B$9:V37,21,0) -> 3058.4 | F19: =VLOOKUP(C19,'SIND PITS'!$C$9:$H$113,2,0) -> 2110.62 | G19: =VLOOKUP(C19,'SIND PITS'!$C$9:$E$113,3,0) -> 0 | H19: =VLOOKUP(C19,'SIND PITS'!$C$9:$F$113,4,0) -> 0 | I19: =VLOOKUP(C19,'SIND PITS'!$C$9:$G$113,5,0) -> 58.5 | K19: =SUM(D19:I19) -> 5227.52 | L19: 13000 | M19: =+L19/2 -> 6500 | O19: =+VLOOKUP(C19,'CPD PITSS'!$B$9:I37,8,0) -> 71.5 | P19: =+G19+H19+I19 -> 58.5 | Q19: =(VLOOKUP($C19,'CPD PITSS'!$B$9:V36,13,0))+(VLOOKUP($C19,'CPD PITSS'!$B$9:V36,14,0)) -> 1402.48 | R19: 0 | S19: =+VLOOKUP(C19,'EXTRAS Y FESTIVOS'!$B$9:J121,9,0) -> 0 | T19: =VLOOKUP(C19,'CPD PITSS'!$B$9:S36,18,0) -> 0 | V19: =+K19-O19-P19+Q19+R19+T19+S19+IFERROR(VLOOKUP('RESUMEN PITS'!C19,'IP PITSS'!$B$9:$M$93,10),0)+IFERROR(VLOOKUP('RESUMEN PITS'!C19,'IP PITSS'!$B$9:$M$93,11),0)+IFERROR(VLOOKUP('RESUMEN PITS'!C19,'IP PITSS'!$B$9:$M$93,12),0)+VLOOKUP("Comision",'IP PITSS'!$I$99:$J$110,2)/COUNT($F$9:$F$111)+IFERROR(VLOOKUP('RESUMEN PITS'!C19,'IP PITSS'!$B$9:$AD$93,15),0)+IFERROR(VLOOKUP('RESUMEN PITS'!C19,'IP PITSS'!$B$9:$AD$93,21),0)+IFERROR(VLOOKUP('RESUMEN PITS'!C19,'IP PITSS'!$B$9:$AD$93,22),0)+IFERROR(VLOOKUP('RESUMEN PITS'!C19,'IP PITSS'!$B$9:$AD$93,23),0)+IFERROR(VLOOKUP('RESUMEN PITS'!C19,'IP PITSS'!$B$9:$AD$93,24),0)+IFERROR(VLOOKUP('RESUMEN PITS'!C19,'IP PITSS'!$B$9:$AD$93,26),0)+IFERROR(VLOOKUP('RESUMEN PITS'!C19,'IP PITSS'!$B$9:$AD$93,28),0)+IFERROR(VLOOKUP('RESUMEN PITS'!C19,'IP PITSS'!$B$9:$AD$93,29),0)+IFERROR(VLOOKUP('RESUMEN PITS'!C19,'IP PITSS'!$B$9:$AD$93,9),0)*2% -> 6554.0559 | W19: =+M19-V19-S19 -> -54.055924 | Y19: SEI0118
A20: SEI0127 | B20: CONSULTORIA | C20: Hernandez Ochoa Eduardo | D20: =+VLOOKUP(C20,'CPD PITSS'!$B$9:V38,21,0) -> 4899.8 | F20: =VLOOKUP(C20,'SIND PITS'!$C$9:$H$113,2,0) -> 2600.2 | G20: =VLOOKUP(C20,'SIND PITS'!$C$9:$E$113,3,0) -> 337.5 | H20: =VLOOKUP(C20,'SIND PITS'!$C$9:$F$113,4,0) -> 0 | I20: =VLOOKUP(C20,'SIND PITS'!$C$9:$G$113,5,0) -> 0 | K20: =SUM(D20:I20) -> 7837.5 | L20: 15000 | M20: =+L20/2 -> 7500 | O20: =+VLOOKUP(C20,'CPD PITSS'!$B$9:I38,8,0) -> 0 | P20: =+G20+H20+I20 -> 337.5 | Q20: =(VLOOKUP($C20,'CPD PITSS'!$B$9:V37,13,0))+(VLOOKUP($C20,'CPD PITSS'!$B$9:V37,14,0)) -> 0 | R20: 0 | S20: =+VLOOKUP(C20,'EXTRAS Y FESTIVOS'!$B$9:J122,9,0) -> 0 | T20: =VLOOKUP(C20,'CPD PITSS'!$B$9:S37,18,0) -> 0 | V20: =+K20-O20-P20+Q20+R20+T20+S20+IFERROR(VLOOKUP('RESUMEN PITS'!C20,'IP PITSS'!$B$9:$M$93,10),0)+IFERROR(VLOOKUP('RESUMEN PITS'!C20,'IP PITSS'!$B$9:$M$93,11),0)+IFERROR(VLOOKUP('RESUMEN PITS'!C20,'IP PITSS'!$B$9:$M$93,12),0)+VLOOKUP("Comision",'IP PITSS'!$I$99:$J$110,2)/COUNT($F$9:$F$111)+IFERROR(VLOOKUP('RESUMEN PITS'!C20,'IP PITSS'!$B$9:$AD$93,15),0)+IFERROR(VLOOKUP('RESUMEN PITS'!C20,'IP PITSS'!$B$9:$AD$93,21),0)+IFERROR(VLOOKUP('RESUMEN PITS'!C20,'IP PITSS'!$B$9:$AD$93,22),0)+IFERROR(VLOOKUP('RESUMEN PITS'!C20,'IP PITSS'!$B$9:$AD$93,23),0)+IFERROR(VLOOKUP('RESUMEN PITS'!C20,'IP PITSS'!$B$9:$AD$93,24),0)+IFERROR(VLOOKUP('RESUMEN PITS'!C20,'IP PITSS'!$B$9:$AD$93,26),0)+IFERROR(VLOOKUP('RESUMEN PITS'!C20,'IP PITSS'!$B$9:$AD$93,28),0)+IFERROR(VLOOKUP('RESUMEN PITS'!C20,'IP PITSS'!$B$9:$AD$93,29),0)+IFERROR(VLOOKUP('RESUMEN PITS'!C20,'IP PITSS'!$B$9:$AD$93,9),0)*2% -> 8914.5349 | W20: =+M20-V20-S20 -> -1414.5349 | Y20: SEI0127
A21: SEI0173 | B21: CONSULTORIA | C21: Nieto Ortiz Jose Luis | D21: =+VLOOKUP(C21,'CPD PITSS'!$B$9:V39,21,0) -> 1595.4 | F21: =VLOOKUP(C21,'SIND PITS'!$C$9:$H$113,2,0) -> 1483.09 | G21: =VLOOKUP(C21,'SIND PITS'!$C$9:$E$113,3,0) -> 30 | H21: =VLOOKUP(C21,'SIND PITS'!$C$9:$F$113,4,0) -> 0 | I21: =VLOOKUP(C21,'SIND PITS'!$C$9:$G$113,5,0) -> 398.26 | K21: =SUM(D21:I21) -> 3506.75 | L21: 10000 | M21: =+L21/2 -> 5000 | O21: =+VLOOKUP(C21,'CPD PITSS'!$B$9:I39,8,0) -> 501.74 | P21: =+G21+H21+I21 -> 428.26 | Q21: =(VLOOKUP($C21,'CPD PITSS'!$B$9:V38,13,0))+(VLOOKUP($C21,'CPD PITSS'!$B$9:V38,14,0)) -> 2126.25 | R21: 0 | S21: =+VLOOKUP(C21,'EXTRAS Y FESTIVOS'!$B$9:J123,9,0) -> 0 | T21: =VLOOKUP(C21,'CPD PITSS'!$B$9:S38,18,0) -> 297 | V21: =+K21-O21-P21+Q21+R21+T21+S21+IFERROR(VLOOKUP('RESUMEN PITS'!C21,'IP PITSS'!$B$9:$M$93,10),0)+IFERROR(VLOOKUP('RESUMEN PITS'!C21,'IP PITSS'!$B$9:$M$93,11),0)+IFERROR(VLOOKUP('RESUMEN PITS'!C21,'IP PITSS'!$B$9:$M$93,12),0)+VLOOKUP("Comision",'IP PITSS'!$I$99:$J$110,2)/COUNT($F$9:$F$111)+IFERROR(VLOOKUP('RESUMEN PITS'!C21,'IP PITSS'!$B$9:$AD$93,15),0)+IFERROR(VLOOKUP('RESUMEN PITS'!C21,'IP PITSS'!$B$9:$AD$93,21),0)+IFERROR(VLOOKUP('RESUMEN PITS'!C21,'IP PITSS'!$B$9:$AD$93,22),0)+IFERROR(VLOOKUP('RESUMEN PITS'!C21,'IP PITSS'!$B$9:$AD$93,23),0)+IFERROR(VLOOKUP('RESUMEN PITS'!C21,'IP PITSS'!$B$9:$AD$93,24),0)+IFERROR(VLOOKUP('RESUMEN PITS'!C21,'IP PITSS'!$B$9:$AD$93,26),0)+IFERROR(VLOOKUP('RESUMEN PITS'!C21,'IP PITSS'!$B$9:$AD$93,28),0)+IFERROR(VLOOKUP('RESUMEN PITS'!C21,'IP PITSS'!$B$9:$AD$93,29),0)+IFERROR(VLOOKUP('RESUMEN PITS'!C21,'IP PITSS'!$B$9:$AD$93,9),0)*2% -> 6501.4969 | W21: =+M21-V21-S21 -> -1501.4969 | Y21: SEI0173
... A26: SEI0442 | B26: CONSULTORIA | C26: Sierra Escamilla Daniela | D26: =+VLOOKUP(C26,'CPD PITSS'!$B$9:V44,21,0) -> 4036 | F26: =VLOOKUP(C26,'SIND PITS'!$C$9:$H$113,2,0) -> 2464 | G26: =VLOOKUP(C26,'SIND PITS'!$C$9:$E$113,3,0) -> 1000 | H26: =VLOOKUP(C26,'SIND PITS'!$C$9:$F$113,4,0) -> 0 | I26: =VLOOKUP(C26,'SIND PITS'!$C$9:$G$113,5,0) -> 0 | K26: =SUM(D26:I26) -> 7500 | L26: 13000 | M26: =+L26/2 -> 6500 | O26: =+VLOOKUP(C26,'CPD PITSS'!$B$9:I44,8,0) -> 0 | P26: =+G26+H26+I26 -> 1000 | Q26: =(VLOOKUP($C26,'CPD PITSS'!$B$9:V43,13,0))+(VLOOKUP($C26,'CPD PITSS'!$B$9:V43,14,0)) -> 0 | R26: 0 | S26: =+VLOOKUP(C26,'EXTRAS Y FESTIVOS'!$B$9:J128,9,0) -> 0 | T26: =VLOOKUP(C26,'CPD PITSS'!$B$9:S43,18,0) -> 0 | V26: =+K26-O26-P26+Q26+R26+T26+S26+IFERROR(VLOOKUP('RESUMEN PITS'!C26,'IP PITSS'!$B$9:$M$93,10),0)+IFERROR(VLOOKUP('RESUMEN PITS'!C26,'IP PITSS'!$B$9:$M$93,11),0)+IFERROR(VLOOKUP('RESUMEN PITS'!C26,'IP PITSS'!$B$9:$M$93,12),0)+VLOOKUP("Comision",'IP PITSS'!$I$99:$J$110,2)/COUNT($F$9:$F$111)+IFERROR(VLOOKUP('RESUMEN PITS'!C26,'IP PITSS'!$B$9:$AD$93,15),0)+IFERROR(VLOOKUP('RESUMEN PITS'!C26,'IP PITSS'!$B$9:$AD$93,21),0)+IFERROR(VLOOKUP('RESUMEN PITS'!C26,'IP PITSS'!$B$9:$AD$93,22),0)+IFERROR(VLOOKUP('RESUMEN PITS'!C26,'IP PITSS'!$B$9:$AD$93,23),0)+IFERROR(VLOOKUP('RESUMEN PITS'!C26,'IP PITSS'!$B$9:$AD$93,24),0)+IFERROR(VLOOKUP('RESUMEN PITS'!C26,'IP PITSS'!$B$9:$AD$93,26),0)+IFERROR(VLOOKUP('RESUMEN PITS'!C26,'IP PITSS'!$B$9:$AD$93,28),0)+IFERROR(VLOOKUP('RESUMEN PITS'!C26,'IP PITSS'!$B$9:$AD$93,29),0)+IFERROR(VLOOKUP('RESUMEN PITS'!C26,'IP PITSS'!$B$9:$AD$93,9),0)*2% -> 7284.9959 | W26: =+M26-V26-S26 -> -784.99592 | Y26: SEI0618
A27: SEI0010 | B27: IP INNOVACION | C27: Torres Ricardez Alfredo | D27: =+VLOOKUP(C27,'IP PITSS'!$B$9:U94,20,0) -> 3335.4 | F27: =VLOOKUP(C27,'SIND PITS'!$C$9:$H$113,2,0) -> 414.6 | G27: =VLOOKUP(C27,'SIND PITS'!$C$9:$E$113,3,0) -> 175 | H27: =VLOOKUP(C27,'SIND PITS'!$C$9:$F$113,4,0) -> 0 | I27: =VLOOKUP(C27,'SIND PITS'!$C$9:$G$113,5,0) -> 0 | K27: =SUM(D27:I27) -> 3925 | L27: 8000 | M27: =+L27/2 -> 4000 | O27: =+VLOOKUP(C27,'IP PITSS'!$B$9:I94,8,0) -> 0 | P27: =+G27+H27+I27 -> 175 | Q27: =+(VLOOKUP(C27,'IP PITSS'!$B$9:L94,11,0))+VLOOKUP('RESUMEN PITS'!C27,'IP PITSS'!$B$9:M94,12,0)+VLOOKUP(C27,'IP PITSS'!$B$9:K94,10,0) -> 0 | R27: =VLOOKUP(C27,'IP PITSS'!$B$9:Q90,16,0) -> 0 | S27: =+VLOOKUP(C27,'EXTRAS Y FESTIVOS'!$B$9:J129,9,0) -> 0 | T27: =VLOOKUP(C27,'IP PITSS'!$B$9:R90,17,0) -> 250 | V27: =+K27-O27-P27+Q27+R27+T27+S27+IFERROR(VLOOKUP('RESUMEN PITS'!C27,'IP PITSS'!$B$9:$M$93,10),0)+IFERROR(VLOOKUP('RESUMEN PITS'!C27,'IP PITSS'!$B$9:$M$93,11),0)+IFERROR(VLOOKUP('RESUMEN PITS'!C27,'IP PITSS'!$B$9:$M$93,12),0)+VLOOKUP("Comision",'IP PITSS'!$I$99:$J$110,2)/COUNT($F$9:$F$111)+IFERROR(VLOOKUP('RESUMEN PITS'!C27,'IP PITSS'!$B$9:$AD$93,15),0)+IFERROR(VLOOKUP('RESUMEN PITS'!C27,'IP PITSS'!$B$9:$AD$93,21),0)+IFERROR(VLOOKUP('RESUMEN PITS'!C27,'IP PITSS'!$B$9:$AD$93,22),0)+IFERROR(VLOOKUP('RESUMEN PITS'!C27,'IP PITSS'!$B$9:$AD$93,23),0)+IFERROR(VLOOKUP('RESUMEN PITS'!C27,'IP PITSS'!$B$9:$AD$93,24),0)+IFERROR(VLOOKUP('RESUMEN PITS'!C27,'IP PITSS'!$B$9:$AD$93,26),0)+IFERROR(VLOOKUP('RESUMEN PITS'!C27,'IP PITSS'!$B$9:$AD$93,28),0)+IFERROR(VLOOKUP('RESUMEN PITS'!C27,'IP PITSS'!$B$9:$AD$93,29),0)+IFERROR(VLOOKUP('RESUMEN PITS'!C27,'IP PITSS'!$B$9:$AD$93,9),0)*2% -> 4784.9959 | W27: =+M27-V27-S27 -> -784.99592 | Y27: SEI0010
A28: SEI0014 | B28: IP INNOVACION | C28: Montoya Portillo Carlos Alberto | D28: =+VLOOKUP(C28,'IP PITSS'!$B$9:U95,20,0) -> 3585.4 | F28: =VLOOKUP(C28,'SIND PITS'!$C$9:$H$113,2,0) -> 414.6 | G28: =VLOOKUP(C28,'SIND PITS'!$C$9:$E$113,3,0) -> 175 | H28: =VLOOKUP(C28,'SIND PITS'!$C$9:$F$113,4,0) -> 0 | I28: =VLOOKUP(C28,'SIND PITS'!$C$9:$G$113,5,0) -> 0 | K28: =SUM(D28:I28) -> 4175 | L28: 8000 | M28: =+L28/2 -> 4000 | O28: =+VLOOKUP(C28,'IP PITSS'!$B$9:I95,8,0) -> 0 | P28: =+G28+H28+I28 -> 175 | Q28: =+(VLOOKUP(C28,'IP PITSS'!$B$9:L95,11,0))+VLOOKUP('RESUMEN PITS'!C28,'IP PITSS'!$B$9:M95,12,0)+VLOOKUP(C28,'IP PITSS'!$B$9:K95,10,0) -> 0 | R28: =VLOOKUP(C28,'IP PITSS'!$B$9:Q91,16,0) -> 0 | S28: =+VLOOKUP(C28,'EXTRAS Y FESTIVOS'!$B$9:J130,9,0) -> 0 | T28: =VLOOKUP(C28,'IP PITSS'!$B$9:R91,17,0) -> 0 | V28: =+K28-O28-P28+Q28+R28+T28+S28+IFERROR(VLOOKUP('RESUMEN PITS'!C28,'IP PITSS'!$B$9:$M$93,10),0)+IFERROR(VLOOKUP('RESUMEN PITS'!C28,'IP PITSS'!$B$9:$M$93,11),0)+IFERROR(VLOOKUP('RESUMEN PITS'!C28,'IP PITSS'!$B$9:$M$93,12),0)+VLOOKUP("Comision",'IP PITSS'!$I$99:$J$110,2)/COUNT($F$9:$F$111)+IFERROR(VLOOKUP('RESUMEN PITS'!C28,'IP PITSS'!$B$9:$AD$93,15),0)+IFERROR(VLOOKUP('RESUMEN PITS'!C28,'IP PITSS'!$B$9:$AD$93,21),0)+IFERROR(VLOOKUP('RESUMEN PITS'!C28,'IP PITSS'!$B$9:$AD$93,22),0)+IFERROR(VLOOKUP('RESUMEN PITS'!C28,'IP PITSS'!$B$9:$AD$93,23),0)+IFERROR(VLOOKUP('RESUMEN PITS'!C28,'IP PITSS'!$B$9:$AD$93,24),0)+IFERROR(VLOOKUP('RESUMEN PITS'!C28,'IP PITSS'!$B$9:$AD$93,26),0)+IFERROR(VLOOKUP('RESUMEN PITS'!C28,'IP PITSS'!$B$9:$AD$93,28),0)+IFERROR(VLOOKUP('RESUMEN PITS'!C28,'IP PITSS'!$B$9:$AD$93,29),0)+IFERROR(VLOOKUP('RESUMEN PITS'!C28,'IP PITSS'!$B$9:$AD$93,9),0)*2% -> 5501.4969 | W28: =+M28-V28-S28 -> -1501.4969 | Y28: SEI0014
A29: SEI0017 | B29: IP INNOVACION | C29: Muñoz Reyes Luis Eduardo | D29: =+VLOOKUP(C29,'IP PITSS'!$B$9:U96,20,0) -> 2717 | F29: =VLOOKUP(C29,'SIND PITS'!$C$9:$H$113,2,0) -> 414.56 | G29: =VLOOKUP(C29,'SIND PITS'!$C$9:$E$113,3,0) -> 250 | H29: =VLOOKUP(C29,'SIND PITS'!$C$9:$F$113,4,0) -> 0 | I29: =VLOOKUP(C29,'SIND PITS'!$C$9:$G$113,5,0) -> 0 | K29: =SUM(D29:I29) -> 3381.56 | L29: 8000 | M29: =+L29/2 -> 4000 | O29: =+VLOOKUP(C29,'IP PITSS'!$B$9:I96,8,0) -> 0 | P29: =+G29+H29+I29 -> 250 | Q29: =+(VLOOKUP(C29,'IP PITSS'!$B$9:L96,11,0))+VLOOKUP('RESUMEN PITS'!C29,'IP PITSS'!$B$9:M96,12,0)+VLOOKUP(C29,'IP PITSS'!$B$9:K96,10,0) -> 868.44 | R29: =VLOOKUP(C29,'IP PITSS'!$B$9:Q92,16,0) -> 0 | S29: =+VLOOKUP(C29,'EXTRAS Y FESTIVOS'!$B$9:J131,9,0) -> 0 | T29: =VLOOKUP(C29,'IP PITSS'!$B$9:R92,17,0) -> 0 | V29: =+K29-O29-P29+Q29+R29+T29+S29+IFERROR(VLOOKUP('RESUMEN PITS'!C29,'IP PITSS'!$B$9:$M$93,10),0)+IFERROR(VLOOKUP('RESUMEN PITS'!C29,'IP PITSS'!$B$9:$M$93,11),0)+IFERROR(VLOOKUP('RESUMEN PITS'!C29,'IP PITSS'!$B$9:$M$93,12),0)+VLOOKUP("Comision",'IP PITSS'!$I$99:$J$110,2)/COUNT($F$9:$F$111)+IFERROR(VLOOKUP('RESUMEN PITS'!C29,'IP PITSS'!$B$9:$AD$93,15),0)+IFERROR(VLOOKUP('RESUMEN PITS'!C29,'IP PITSS'!$B$9:$AD$93,21),0)+IFERROR(VLOOKUP('RESUMEN PITS'!C29,'IP PITSS'!$B$9:$AD$93,22),0)+IFERROR(VLOOKUP('RESUMEN PITS'!C29,'IP PITSS'!$B$9:$AD$93,23),0)+IFERROR(VLOOKUP('RESUMEN PITS'!C29,'IP PITSS'!$B$9:$AD$93,24),0)+IFERROR(VLOOKUP('RESUMEN PITS'!C29,'IP PITSS'!$B$9:$AD$93,26),0)+IFERROR(VLOOKUP('RESUMEN PITS'!C29,'IP PITSS'!$B$9:$AD$93,28),0)+IFERROR(VLOOKUP('RESUMEN PITS'!C29,'IP PITSS'!$B$9:$AD$93,29),0)+IFERROR(VLOOKUP('RESUMEN PITS'!C29,'IP PITSS'!$B$9:$AD$93,9),0)*2% -> 5501.4969 | W29: =+M29-V29-S29 -> -1501.4969 | Y29: SEI0017
A30: SEI0019 | B30: IP INNOVACION | C30: Gonzalez Rasgado Miguel Isaias | D30: =+VLOOKUP(C30,'IP PITSS'!$B$9:U97,20,0) -> 6577 | F30: =VLOOKUP(C30,'SIND PITS'!$C$9:$H$113,2,0) -> -14.5 | G30: =VLOOKUP(C30,'SIND PITS'!$C$9:$E$113,3,0) -> 937.5 | H30: =VLOOKUP(C30,'SIND PITS'!$C$9:$F$113,4,0) -> 0 | I30: =VLOOKUP(C30,'SIND PITS'!$C$9:$G$113,5,0) -> 0 | K30: =SUM(D30:I30) -> 7500 | L30: 13125 | M30: =+L30/2 -> 6562.5 | O30: =+VLOOKUP(C30,'IP PITSS'!$B$9:I97,8,0) -> 0 | P30: =+G30+H30+I30 -> 937.5 | Q30: =+(VLOOKUP(C30,'IP PITSS'!$B$9:L97,11,0))+VLOOKUP('RESUMEN PITS'!C30,'IP PITSS'!$B$9:M97,12,0)+VLOOKUP(C30,'IP PITSS'!$B$9:K97,10,0) -> 0 | R30: =VLOOKUP(C30,'IP PITSS'!$B$9:Q93,16,0) -> 0 | S30: =+VLOOKUP(C30,'EXTRAS Y FESTIVOS'!$B$9:J132,9,0) -> 0 | T30: =VLOOKUP(C30,'IP PITSS'!$B$9:R93,17,0) -> 0 | V30: =+K30-O30-P30+Q30+R30+T30+S30+IFERROR(VLOOKUP('RESUMEN PITS'!C30,'IP PITSS'!$B$9:$M$93,10),0)+IFERROR(VLOOKUP('RESUMEN PITS'!C30,'IP PITSS'!$B$9:$M$93,11),0)+IFERROR(VLOOKUP('RESUMEN PITS'!C30,'IP PITSS'!$B$9:$M$93,12),0)+VLOOKUP("Comision",'IP PITSS'!$I$99:$J$110,2)/COUNT($F$9:$F$111)+IFERROR(VLOOKUP('RESUMEN PITS'!C30,'IP PITSS'!$B$9:$AD$93,15),0)+IFERROR(VLOOKUP('RESUMEN PITS'!C30,'IP PITSS'!$B$9:$AD$93,21),0)+IFERROR(VLOOKUP('RESUMEN PITS'!C30,'IP PITSS'!$B$9:$AD$93,22),0)+IFERROR(VLOOKUP('RESUMEN PITS'!C30,'IP PITSS'!$B$9:$AD$93,23),0)+IFERROR(VLOOKUP('RESUMEN PITS'!C30,'IP PITSS'!$B$9:$AD$93,24),0)+IFERROR(VLOOKUP('RESUMEN PITS'!C30,'IP PITSS'!$B$9:$AD$93,26),0)+IFERROR(VLOOKUP('RESUMEN PITS'!C30,'IP PITSS'!$B$9:$AD$93,28),0)+IFERROR(VLOOKUP('RESUMEN PITS'!C30,'IP PITSS'!$B$9:$AD$93,29),0)+IFERROR(VLOOKUP('RESUMEN PITS'!C30,'IP PITSS'!$B$9:$AD$93,9),0)*2% -> 7977.0349 | W30: =+M30-V30-S30 -> -1414.5349 | Y30: SEI0019
A31: SEI0020 | B31: IP INNOVACION | C31: Mar Marquez Cesar Eduardo | D31: =+VLOOKUP(C31,'IP PITSS'!$B$9:U98,20,0) -> 3585.4 | F31: =VLOOKUP(C31,'SIND PITS'!$C$9:$H$113,2,0) -> 414.6 | G31: =VLOOKUP(C31,'SIND PITS'!$C$9:$E$113,3,0) -> 220 | H31: =VLOOKUP(C31,'SIND PITS'!$C$9:$F$113,4,0) -> 0 | I31: =VLOOKUP(C31,'SIND PITS'!$C$9:$G$113,5,0) -> 0 | K31: =SUM(D31:I31) -> 4220 | L31: 8000 | M31: =+L31/2 -> 4000 | O31: =+VLOOKUP(C31,'IP PITSS'!$B$9:I98,8,0) -> 0 | P31: =+G31+H31+I31 -> 220 | Q31: =+(VLOOKUP(C31,'IP PITSS'!$B$9:L98,11,0))+VLOOKUP('RESUMEN PITS'!C31,'IP PITSS'!$B$9:M98,12,0)+VLOOKUP(C31,'IP PITSS'!$B$9:K98,10,0) -> 0 | R31: =VLOOKUP(C31,'IP PITSS'!$B$9:Q94,16,0) -> 0 | S31: =+VLOOKUP(C31,'EXTRAS Y FESTIVOS'!$B$9:J133,9,0) -> 0 | T31: =VLOOKUP(C31,'IP PITSS'!$B$9:R94,17,0) -> 0 | V31: =+K31-O31-P31+Q31+R31+T31+S31+IFERROR(VLOOKUP('RESUMEN PITS'!C31,'IP PITSS'!$B$9:$M$93,10),0)+IFERROR(VLOOKUP('RESUMEN PITS'!C31,'IP PITSS'!$B$9:$M$93,11),0)+IFERROR(VLOOKUP('RESUMEN PITS'!C31,'IP PITSS'!$B$9:$M$93,12),0)+VLOOKUP("Comision",'IP PITSS'!$I$99:$J$110,2)/COUNT($F$9:$F$111)+IFERROR(VLOOKUP('RESUMEN PITS'!C31,'IP PITSS'!$B$9:$AD$93,15),0)+IFERROR(VLOOKUP('RESUMEN PITS'!C31,'IP PITSS'!$B$9:$AD$93,21),0)+IFERROR(VLOOKUP('RESUMEN PITS'!C31,'IP PITSS'!$B$9:$AD$93,22),0)+IFERROR(VLOOKUP('RESUMEN PITS'!C31,'IP PITSS'!$B$9:$AD$93,23),0)+IFERROR(VLOOKUP('RESUMEN PITS'!C31,'IP PITSS'!$B$9:$AD$93,24),0)+IFERROR(VLOOKUP('RESUMEN PITS'!C31,'IP PITSS'!$B$9:$AD$93,26),0)+IFERROR(VLOOKUP('RESUMEN PITS'!C31,'IP PITSS'!$B$9:$AD$93,28),0)+IFERROR(VLOOKUP('RESUMEN PITS'!C31,'IP PITSS'!$B$9:$AD$93,29),0)+IFERROR(VLOOKUP('RESUMEN PITS'!C31,'IP PITSS'!$B$9:$AD$93,9),0)*2% -> 5414.5349 | W31: =+M31-V31-S31 -> -1414.5349 | Y31: SEI0020
A32: SEI0021 | B32: IP INNOVACION | C32: Velez Rodriguez Jaime | D32: =+VLOOKUP(C32,'IP PITSS'!$B$9:U99,20,0) -> 1517.8 | F32: =VLOOKUP(C32,'SIND PITS'!$C$9:$H$113,2,0) -> 1135.1 | G32: =VLOOKUP(C32,'SIND PITS'!$C$9:$E$113,3,0) -> 315 | H32: =VLOOKUP(C32,'SIND PITS'!$C$9:$F$113,4,0) -> 0 | I32: =VLOOKUP(C32,'SIND PITS'!$C$9:$G$113,5,0) -> 0 | K32: =SUM(D32:I32) -> 2967.9 | L32: 8000 | M32: =+L32/2 -> 4000 | O32: =+VLOOKUP(C32,'IP PITSS'!$B$9:I99,8,0) -> 0 | P32: =+G32+H32+I32 -> 315 | Q32: =+(VLOOKUP(C32,'IP PITSS'!$B$9:L99,11,0))+VLOOKUP('RESUMEN PITS'!C32,'IP PITSS'!$B$9:M99,12,0)+VLOOKUP(C32,'IP PITSS'!$B$9:K99,10,0) -> 1347.1 | R32: =VLOOKUP(C32,'IP PITSS'!$B$9:Q95,16,0) -> 0 | S32: =+VLOOKUP(C32,'EXTRAS Y FESTIVOS'!$B$9:J134,9,0) -> 0 | T32: =VLOOKUP(C32,'IP PITSS'!$B$9:R95,17,0) -> 0 | V32: =+K32-O32-P32+Q32+R32+T32+S32+IFERROR(VLOOKUP('RESUMEN PITS'!C32,'IP PITSS'!$B$9:$M$93,10),0)+IFERROR(VLOOKUP('RESUMEN PITS'!C32,'IP PITSS'!$B$9:$M$93,11),0)+IFERROR(VLOOKUP('RESUMEN PITS'!C32,'IP PITSS'!$B$9:$M$93,12),0)+VLOOKUP("Comision",'IP PITSS'!$I$99:$J$110,2)/COUNT($F$9:$F$111)+IFERROR(VLOOKUP('RESUMEN PITS'!C32,'IP PITSS'!$B$9:$AD$93,15),0)+IFERROR(VLOOKUP('RESUMEN PITS'!C32,'IP PITSS'!$B$9:$AD$93,21),0)+IFERROR(VLOOKUP('RESUMEN PITS'!C32,'IP PITSS'!$B$9:$AD$93,22),0)+IFERROR(VLOOKUP('RESUMEN PITS'!C32,'IP PITSS'!$B$9:$AD$93,23),0)+IFERROR(VLOOKUP('RESUMEN PITS'!C32,'IP PITSS'!$B$9:$AD$93,24),0)+IFERROR(VLOOKUP('RESUMEN PITS'!C32,'IP PITSS'!$B$9:$AD$93,26),0)+IFERROR(VLOOKUP('RESUMEN PITS'!C32,'IP PITSS'!$B$9:$AD$93,28),0)+IFERROR(VLOOKUP('RESUMEN PITS'!C32,'IP PITSS'!$B$9:$AD$93,29),0)+IFERROR(VLOOKUP('RESUMEN PITS'!C32,'IP PITSS'!$B$9:$AD$93,9),0)*2% -> 4784.9959 | W32: =+M32-V32-S32 -> -784.99592 | Y32: SEI0021
A33: SEI0022 | B33: IP INNOVACION | C33: Najera Lopez Raul | D33: =+VLOOKUP(C33,'IP PITSS'!$B$9:U100,20,0) -> 4133.6 | F33: =VLOOKUP(C33,'SIND PITS'!$C$9:$H$113,2,0) -> 533.07 | G33: =VLOOKUP(C33,'SIND PITS'!$C$9:$E$113,3,0) -> 150 | H33: =VLOOKUP(C33,'SIND PITS'!$C$9:$F$113,4,0) -> 0 | I33: =VLOOKUP(C33,'SIND PITS'!$C$9:$G$113,5,0) -> 0 | K33: =SUM(D33:I33) -> 4816.67 | L33: 10000 | M33: =+L33/2 -> 5000 | O33: =+VLOOKUP(C33,'IP PITSS'!$B$9:I100,8,0) -> 0 | P33: =+G33+H33+I33 -> 150 | Q33: =+(VLOOKUP(C33,'IP PITSS'!$B$9:L100,11,0))+VLOOKUP('RESUMEN PITS'!C33,'IP PITSS'!$B$9:M100,12,0)+VLOOKUP(C33,'IP PITSS'!$B$9:K100,10,0) -> 0 | R33: =VLOOKUP(C33,'IP PITSS'!$B$9:Q96,16,0) -> 0 | S33: =+VLOOKUP(C33,'EXTRAS Y FESTIVOS'!$B$9:J135,9,0) -> 333.33333 | T33: =VLOOKUP(C33,'IP PITSS'!$B$9:R96,17,0) -> 0 | V33: =+K33-O33-P33+Q33+R33+T33+S33+IFERROR(VLOOKUP('RESUMEN PITS'!C33,'IP PITSS'!$B$9:$M$93,10),0)+IFERROR(VLOOKUP('RESUMEN PITS'!C33,'IP PITSS'!$B$9:$M$93,11),0)+IFERROR(VLOOKUP('RESUMEN PITS'!C33,'IP PITSS'!$B$9:$M$93,12),0)+VLOOKUP("Comision",'IP PITSS'!$I$99:$J$110,2)/COUNT($F$9:$F$111)+IFERROR(VLOOKUP('RESUMEN PITS'!C33,'IP PITSS'!$B$9:$AD$93,15),0)+IFERROR(VLOOKUP('RESUMEN PITS'!C33,'IP PITSS'!$B$9:$AD$93,21),0)+IFERROR(VLOOKUP('RESUMEN PITS'!C33,'IP PITSS'!$B$9:$AD$93,22),0)+IFERROR(VLOOKUP('RESUMEN PITS'!C33,'IP PITSS'!$B$9:$AD$93,23),0)+IFERROR(VLOOKUP('RESUMEN PITS'!C33,'IP PITSS'!$B$9:$AD$93,24),0)+IFERROR(VLOOKUP('RESUMEN PITS'!C33,'IP PITSS'!$B$9:$AD$93,26),0)+IFERROR(VLOOKUP('RESUMEN PITS'!C33,'IP PITSS'!$B$9:$AD$93,28),0)+IFERROR(VLOOKUP('RESUMEN PITS'!C33,'IP PITSS'!$B$9:$AD$93,29),0)+IFERROR(VLOOKUP('RESUMEN PITS'!C33,'IP PITSS'!$B$9:$AD$93,9),0)*2% -> 6501.5003 | W33: =+M33-V33-S33 -> -1834.8336 | X33: 1 PERMISO SIN GOCE | Y33: SEI0022
A34: SEI0023 | B34: IP INNOVACION | C34: Puente Murguia Luis Felipe | D34: =+VLOOKUP(C34,'IP PITSS'!$B$9:U101,20,0) -> 3277.6 | F34: =VLOOKUP(C34,'SIND PITS'!$C$9:$H$113,2,0) -> 222.4 | G34: =VLOOKUP(C34,'SIND PITS'!$C$9:$E$113,3,0) -> 131.25 | H34: =VLOOKUP(C34,'SIND PITS'!$C$9:$F$113,4,0) -> 0 | I34: =VLOOKUP(C34,'SIND PITS'!$C$9:$G$113,5,0) -> 0 | K34: =SUM(D34:I34) -> 3631.25 | L34: 7000 | M34: =+L34/2 -> 3500 | O34: =+VLOOKUP(C34,'IP PITSS'!$B$9:I101,8,0) -> 0 | P34: =+G34+H34+I34 -> 131.25 | Q34: =+(VLOOKUP(C34,'IP PITSS'!$B$9:L101,11,0))+VLOOKUP('RESUMEN PITS'!C34,'IP PITSS'!$B$9:M101,12,0)+VLOOKUP(C34,'IP PITSS'!$B$9:K101,10,0) -> 0 | R34: =VLOOKUP(C34,'IP PITSS'!$B$9:Q97,16,0) -> 0 | S34: =+VLOOKUP(C34,'EXTRAS Y FESTIVOS'!$B$9:J136,9,0) -> 0 | T34: =VLOOKUP(C34,'IP PITSS'!$B$9:R97,17,0) -> 0 | V34: =+K34-O34-P34+Q34+R34+T34+S34+IFERROR(VLOOKUP('RESUMEN PITS'!C34,'IP PITSS'!$B$9:$M$93,10),0)+IFERROR(VLOOKUP('RESUMEN PITS'!C34,'IP PITSS'!$B$9:$M$93,11),0)+IFERROR(VLOOKUP('RESUMEN PITS'!C34,'IP PITSS'!$B$9:$M$93,12),0)+VLOOKUP("Comision",'IP PITSS'!$I$99:$J$110,2)/COUNT($F$9:$F$111)+IFERROR(VLOOKUP('RESUMEN PITS'!C34,'IP PITSS'!$B$9:$AD$93,15),0)+IFERROR(VLOOKUP('RESUMEN PITS'!C34,'IP PITSS'!$B$9:$AD$93,21),0)+IFERROR(VLOOKUP('RESUMEN PITS'!C34,'IP PITSS'!$B$9:$AD$93,22),0)+IFERROR(VLOOKUP('RESUMEN PITS'!C34,'IP PITSS'!$B$9:$AD$93,23),0)+IFERROR(VLOOKUP('RESUMEN PITS'!C34,'IP PITSS'!$B$9:$AD$93,24),0)+IFERROR(VLOOKUP('RESUMEN PITS'!C34,'IP PITSS'!$B$9:$AD$93,26),0)+IFERROR(VLOOKUP('RESUMEN PITS'!C34,'IP PITSS'!$B$9:$AD$93,28),0)+IFERROR(VLOOKUP('RESUMEN PITS'!C34,'IP PITSS'!$B$9:$AD$93,29),0)+IFERROR(VLOOKUP('RESUMEN PITS'!C34,'IP PITSS'!$B$9:$AD$93,9),0)*2% -> 4842.3659 | W34: =+M34-V34-S34 -> -1342.3659 | Y34: SEI0023
A35: SEI0029 | B35: IP INNOVACION | C35: Arceo Garcia Manuel Federico | D35: =+VLOOKUP(C35,'IP PITSS'!$B$9:U102,20,0) -> 2264.8 | F35: =VLOOKUP(C35,'SIND PITS'!$C$9:$H$113,2,0) -> 285.2 | G35: =VLOOKUP(C35,'SIND PITS'!$C$9:$E$113,3,0) -> 1000 | H35: =VLOOKUP(C35,'SIND PITS'!$C$9:$F$113,4,0) -> 0 | I35: =VLOOKUP(C35,'SIND PITS'!$C$9:$G$113,5,0) -> 0 | K35: =SUM(D35:I35) -> 3550 | L35: 6300 | M35: =+L35/2 -> 3150 | O35: =+VLOOKUP(C35,'IP PITSS'!$B$9:I102,8,0) -> 0 | P35: =+G35+H35+I35 -> 1000 | Q35: =+(VLOOKUP(C35,'IP PITSS'!$B$9:L102,11,0))+VLOOKUP('RESUMEN PITS'!C35,'IP PITSS'!$B$9:M102,12,0)+VLOOKUP(C35,'IP PITSS'!$B$9:K102,10,0) -> 0 | R35: =VLOOKUP(C35,'IP PITSS'!$B$9:Q98,16,0) -> 600 | S35: =+VLOOKUP(C35,'EXTRAS Y FESTIVOS'!$B$9:J137,9,0) -> 0 | T35: =VLOOKUP(C35,'IP PITSS'!$B$9:R98,17,0) -> 0 | V35: =+K35-O35-P35+Q35+R35+T35+S35+IFERROR(VLOOKUP('RESUMEN PITS'!C35,'IP PITSS'!$B$9:$M$93,10),0)+IFERROR(VLOOKUP('RESUMEN PITS'!C35,'IP PITSS'!$B$9:$M$93,11),0)+IFERROR(VLOOKUP('RESUMEN PITS'!C35,'IP PITSS'!$B$9:$M$93,12),0)+VLOOKUP("Comision",'IP PITSS'!$I$99:$J$110,2)/COUNT($F$9:$F$111)+IFERROR(VLOOKUP('RESUMEN PITS'!C35,'IP PITSS'!$B$9:$AD$93,15),0)+IFERROR(VLOOKUP('RESUMEN PITS'!C35,'IP PITSS'!$B$9:$AD$93,21),0)+IFERROR(VLOOKUP('RESUMEN PITS'!C35,'IP PITSS'!$B$9:$AD$93,22),0)+IFERROR(VLOOKUP('RESUMEN PITS'!C35,'IP PITSS'!$B$9:$AD$93,23),0)+IFERROR(VLOOKUP('RESUMEN PITS'!C35,'IP PITSS'!$B$9:$AD$93,24),0)+IFERROR(VLOOKUP('RESUMEN PITS'!C35,'IP PITSS'!$B$9:$AD$93,26),0)+IFERROR(VLOOKUP('RESUMEN PITS'!C35,'IP PITSS'!$B$9:$AD$93,28),0)+IFERROR(VLOOKUP('RESUMEN PITS'!C35,'IP PITSS'!$B$9:$AD$93,29),0)+IFERROR(VLOOKUP('RESUMEN PITS'!C35,'IP PITSS'!$B$9:$AD$93,9),0)*2% -> 3204.0559 | W35: =+M35-V35-S35 -> -54.055924 | Y35: SEI0029
A36: SEI0364 | B36: IP INNOVACION | C36: Dominguez Lopez Mayeli Del Pilar | D36: =+VLOOKUP(C36,'IP PITSS'!$B$9:U103,20,0) -> 3583.6 | F36: =VLOOKUP(C36,'SIND PITS'!$C$9:$H$113,2,0) -> 1416.4 | G36: =VLOOKUP(C36,'SIND PITS'!$C$9:$E$113,3,0) -> 1087.5 | H36: =VLOOKUP(C36,'SIND PITS'!$C$9:$F$113,4,0) -> 0 | I36: =VLOOKUP(C36,'SIND PITS'!$C$9:$G$113,5,0) -> 0 | K36: =SUM(D36:I36) -> 6087.5 | L36: 10000 | M36: =+L36/2 -> 5000 | O36: =+VLOOKUP(C36,'IP PITSS'!$B$9:I103,8,0) -> 0 | P36: =+G36+H36+I36 -> 1087.5 | Q36: =+(VLOOKUP(C36,'IP PITSS'!$B$9:L103,11,0))+VLOOKUP('RESUMEN PITS'!C36,'IP PITSS'!$B$9:M103,12,0)+VLOOKUP(C36,'IP PITSS'!$B$9:K103,10,0) -> 0 | R36: =VLOOKUP(C36,'IP PITSS'!$B$9:Q99,16,0) -> 0 | S36: =+VLOOKUP(C36,'EXTRAS Y FESTIVOS'!$B$9:J138,9,0) -> 0 | T36: =VLOOKUP(C36,'IP PITSS'!$B$9:R99,17,0) -> 0 | V36: =+K36-O36-P36+Q36+R36+T36+S36+IFERROR(VLOOKUP('RESUMEN PITS'!C36,'IP PITSS'!$B$9:$M$93,10),0)+IFERROR(VLOOKUP('RESUMEN PITS'!C36,'IP PITSS'!$B$9:$M$93,11),0)+IFERROR(VLOOKUP('RESUMEN PITS'!C36,'IP PITSS'!$B$9:$M$93,12),0)+VLOOKUP("Comision",'IP PITSS'!$I$99:$J$110,2)/COUNT($F$9:$F$111)+IFERROR(VLOOKUP('RESUMEN PITS'!C36,'IP PITSS'!$B$9:$AD$93,15),0)+IFERROR(VLOOKUP('RESUMEN PITS'!C36,'IP PITSS'!$B$9:$AD$93,21),0)+IFERROR(VLOOKUP('RESUMEN PITS'!C36,'IP PITSS'!$B$9:$AD$93,22),0)+IFERROR(VLOOKUP('RESUMEN PITS'!C36,'IP PITSS'!$B$9:$AD$93,23),0)+IFERROR(VLOOKUP('RESUMEN PITS'!C36,'IP PITSS'!$B$9:$AD$93,24),0)+IFERROR(VLOOKUP('RESUMEN PITS'!C36,'IP PITSS'!$B$9:$AD$93,26),0)+IFERROR(VLOOKUP('RESUMEN PITS'!C36,'IP PITSS'!$B$9:$AD$93,28),0)+IFERROR(VLOOKUP('RESUMEN PITS'!C36,'IP PITSS'!$B$9:$AD$93,29),0)+IFERROR(VLOOKUP('RESUMEN PITS'!C36,'IP PITSS'!$B$9:$AD$93,9),0)*2% -> 6414.5349 | W36: =+M36-V36-S36 -> -1414.5349 | Y36: SEI0364
A37: SEI0413 | B37: IP INNOVACION | C37: Courtenay Gutierrez Barry Vladimir | D37: =+VLOOKUP(C37,'IP PITSS'!$B$9:U104,20,0) -> 2234 | F37: =VLOOKUP(C37,'SIND PITS'!$C$9:$H$113,2,0) -> 52.25 | G37: =VLOOKUP(C37,'SIND PITS'!$C$9:$E$113,3,0) -> 250 | H37: =VLOOKUP(C37,'SIND PITS'!$C$9:$F$113,4,0) -> 0 | I37: =VLOOKUP(C37,'SIND PITS'!$C$9:$G$113,5,0) -> 0 | K37: =SUM(D37:I37) -> 2536.25 | L37: 5000 | M37: =+L37/2 -> 2500 | O37: =+VLOOKUP(C37,'IP PITSS'!$B$9:I104,8,0) -> 0 | P37: =+G37+H37+I37 -> 250 | Q37: =+(VLOOKUP(C37,'IP PITSS'!$B$9:L104,11,0))+VLOOKUP('RESUMEN PITS'!C37,'IP PITSS'!$B$9:M104,12,0)+VLOOKUP(C37,'IP PITSS'!$B$9:K104,10,0) -> 0 | R37: =VLOOKUP(C37,'IP PITSS'!$B$9:Q100,16,0) -> 0 | S37: =+VLOOKUP(C37,'EXTRAS Y FESTIVOS'!$B$9:J139,9,0) -> 0 | T37: =VLOOKUP(C37,'IP PITSS'!$B$9:R100,17,0) -> 213.75 | V37: =+K37-O37-P37+Q37+R37+T37+S37+IFERROR(VLOOKUP('RESUMEN PITS'!C37,'IP PITSS'!$B$9:$M$93,10),0)+IFERROR(VLOOKUP('RESUMEN PITS'!C37,'IP PITSS'!$B$9:$M$93,11),0)+IFERROR(VLOOKUP('RESUMEN PITS'!C37,'IP PITSS'!$B$9:$M$93,12),0)+VLOOKUP("Comision",'IP PITSS'!$I$99:$J$110,2)/COUNT($F$9:$F$111)+IFERROR(VLOOKUP('RESUMEN PITS'!C37,'IP PITSS'!$B$9:$AD$93,15),0)+IFERROR(VLOOKUP('RESUMEN PITS'!C37,'IP PITSS'!$B$9:$AD$93,21),0)+IFERROR(VLOOKUP('RESUMEN PITS'!C37,'IP PITSS'!$B$9:$AD$93,22),0)+IFERROR(VLOOKUP('RESUMEN PITS'!C37,'IP PITSS'!$B$9:$AD$93,23),0)+IFERROR(VLOOKUP('RESUMEN PITS'!C37,'IP PITSS'!$B$9:$AD$93,24),0)+IFERROR(VLOOKUP('RESUMEN PITS'!C37,'IP PITSS'!$B$9:$AD$93,26),0)+IFERROR(VLOOKUP('RESUMEN PITS'!C37,'IP PITSS'!$B$9:$AD$93,28),0)+IFERROR(VLOOKUP('RESUMEN PITS'!C37,'IP PITSS'!$B$9:$AD$93,29),0)+IFERROR(VLOOKUP('RESUMEN PITS'!C37,'IP PITSS'!$B$9:$AD$93,9),0)*2% -> 3914.5349 | W37: =+M37-V37-S37 -> -1414.5349 | Y37: SEI0436
A38: SEI0421 | B38: IP INNOVACION | C38: Marin Avila Hector | D38: =+VLOOKUP(C38,'IP PITSS'!$B$9:U105,20,0) -> 3693 | F38: =VLOOKUP(C38,'SIND PITS'!$C$9:$H$113,2,0) -> 707 | G38: =VLOOKUP(C38,'SIND PITS'!$C$9:$E$113,3,0) -> 500 | H38: =VLOOKUP(C38,'SIND PITS'!$C$9:$F$113,4,0) -> 0 | I38: =VLOOKUP(C38,'SIND PITS'!$C$9:$G$113,5,0) -> 0 | K38: =SUM(D38:I38) -> 4900 | L38: 8800 | M38: =+L38/2 -> 4400 | O38: =+VLOOKUP(C38,'IP PITSS'!$B$9:I105,8,0) -> 0 | P38: =+G38+H38+I38 -> 500 | Q38: =+(VLOOKUP(C38,'IP PITSS'!$B$9:L105,11,0))+VLOOKUP('RESUMEN PITS'!C38,'IP PITSS'!$B$9:M105,12,0)+VLOOKUP(C38,'IP PITSS'!$B$9:K105,10,0) -> 0 | R38: =VLOOKUP(C38,'IP PITSS'!$B$9:Q101,16,0) -> 0 | S38: =+VLOOKUP(C38,'EXTRAS Y FESTIVOS'!$B$9:J140,9,0) -> 0 | T38: =VLOOKUP(C38,'IP PITSS'!$B$9:R101,17,0) -> 0 | V38: =+K38-O38-P38+Q38+R38+T38+S38+IFERROR(VLOOKUP('RESUMEN PITS'!C38,'IP PITSS'!$B$9:$M$93,10),0)+IFERROR(VLOOKUP('RESUMEN PITS'!C38,'IP PITSS'!$B$9:$M$93,11),0)+IFERROR(VLOOKUP('RESUMEN PITS'!C38,'IP PITSS'!$B$9:$M$93,12),0)+VLOOKUP("Comision",'IP PITSS'!$I$99:$J$110,2)/COUNT($F$9:$F$111)+IFERROR(VLOOKUP('RESUMEN PITS'!C38,'IP PITSS'!$B$9:$AD$93,15),0)+IFERROR(VLOOKUP('RESUMEN PITS'!C38,'IP PITSS'!$B$9:$AD$93,21),0)+IFERROR(VLOOKUP('RESUMEN PITS'!C38,'IP PITSS'!$B$9:$AD$93,22),0)+IFERROR(VLOOKUP('RESUMEN PITS'!C38,'IP PITSS'!$B$9:$AD$93,23),0)+IFERROR(VLOOKUP('RESUMEN PITS'!C38,'IP PITSS'!$B$9:$AD$93,24),0)+IFERROR(VLOOKUP('RESUMEN PITS'!C38,'IP PITSS'!$B$9:$AD$93,26),0)+IFERROR(VLOOKUP('RESUMEN PITS'!C38,'IP PITSS'!$B$9:$AD$93,28),0)+IFERROR(VLOOKUP('RESUMEN PITS'!C38,'IP PITSS'!$B$9:$AD$93,29),0)+IFERROR(VLOOKUP('RESUMEN PITS'!C38,'IP PITSS'!$B$9:$AD$93,9),0)*2% -> 5814.5349 | W38: =+M38-V38-S38 -> -1414.5349
A39: SEI0424 | B39: IP INNOVACION | C39: Palacios Ramos Jesus | D39: =+VLOOKUP(C39,'IP PITSS'!$B$9:U106,20,0) -> 3583.6 | F39: =VLOOKUP(C39,'SIND PITS'!$C$9:$H$113,2,0) -> 416.4 | G39: =VLOOKUP(C39,'SIND PITS'!$C$9:$E$113,3,0) -> 210 | H39: =VLOOKUP(C39,'SIND PITS'!$C$9:$F$113,4,0) -> 0 | I39: =VLOOKUP(C39,'SIND PITS'!$C$9:$G$113,5,0) -> 0 | K39: =SUM(D39:I39) -> 4210 | L39: 8000 | M39: =+L39/2 -> 4000 | O39: =+VLOOKUP(C39,'IP PITSS'!$B$9:I106,8,0) -> 0 | P39: =+G39+H39+I39 -> 210 | Q39: =+(VLOOKUP(C39,'IP PITSS'!$B$9:L106,11,0))+VLOOKUP('RESUMEN PITS'!C39,'IP PITSS'!$B$9:M106,12,0)+VLOOKUP(C39,'IP PITSS'!$B$9:K106,10,0) -> 0 | R39: =VLOOKUP(C39,'IP PITSS'!$B$9:Q102,16,0) -> 0 | S39: =+VLOOKUP(C39,'EXTRAS Y FESTIVOS'!$B$9:J141,9,0) -> 0 | T39: =VLOOKUP(C39,'IP PITSS'!$B$9:R102,17,0) -> 0 | V39: =+K39-O39-P39+Q39+R39+T39+S39+IFERROR(VLOOKUP('RESUMEN PITS'!C39,'IP PITSS'!$B$9:$M$93,10),0)+IFERROR(VLOOKUP('RESUMEN PITS'!C39,'IP PITSS'!$B$9:$M$93,11),0)+IFERROR(VLOOKUP('RESUMEN PITS'!C39,'IP PITSS'!$B$9:$M$93,12),0)+VLOOKUP("Comision",'IP PITSS'!$I$99:$J$110,2)/COUNT($F$9:$F$111)+IFERROR(VLOOKUP('RESUMEN PITS'!C39,'IP PITSS'!$B$9:$AD$93,15),0)+IFERROR(VLOOKUP('RESUMEN PITS'!C39,'IP PITSS'!$B$9:$AD$93,21),0)+IFERROR(VLOOKUP('RESUMEN PITS'!C39,'IP PITSS'!$B$9:$AD$93,22),0)+IFERROR(VLOOKUP('RESUMEN PITS'!C39,'IP PITSS'!$B$9:$AD$93,23),0)+IFERROR(VLOOKUP('RESUMEN PITS'!C39,'IP PITSS'!$B$9:$AD$93,24),0)+IFERROR(VLOOKUP('RESUMEN PITS'!C39,'IP PITSS'!$B$9:$AD$93,26),0)+IFERROR(VLOOKUP('RESUMEN PITS'!C39,'IP PITSS'!$B$9:$AD$93,28),0)+IFERROR(VLOOKUP('RESUMEN PITS'!C39,'IP PITSS'!$B$9:$AD$93,29),0)+IFERROR(VLOOKUP('RESUMEN PITS'!C39,'IP PITSS'!$B$9:$AD$93,9),0)*2% -> 5342.3659 | W39: =+M39-V39-S39 -> -1342.3659 | Y39: SEI0424
A40: SEI0428 | B40: IP INNOVACION | C40: Martinez Hernandez J. Antonio | D40: =+VLOOKUP(C40,'IP PITSS'!$B$9:U107,20,0) -> 3583.8 | F40: =VLOOKUP(C40,'SIND PITS'!$C$9:$H$113,2,0) -> 416.2 | G40: =VLOOKUP(C40,'SIND PITS'!$C$9:$E$113,3,0) -> 120 | H40: =VLOOKUP(C40,'SIND PITS'!$C$9:$F$113,4,0) -> 0 | I40: =VLOOKUP(C40,'SIND PITS'!$C$9:$G$113,5,0) -> 0 | K40: =SUM(D40:I40) -> 4120 | L40: 8000 | M40: =+L40/2 -> 4000 | O40: =+VLOOKUP(C40,'IP PITSS'!$B$9:I107,8,0) -> 0 | P40: =+G40+H40+I40 -> 120 | Q40: =+(VLOOKUP(C40,'IP PITSS'!$B$9:L107,11,0))+VLOOKUP('RESUMEN PITS'!C40,'IP PITSS'!$B$9:M107,12,0)+VLOOKUP(C40,'IP PITSS'!$B$9:K107,10,0) -> 0 | R40: =VLOOKUP(C40,'IP PITSS'!$B$9:Q103,16,0) -> 0 | S40: =+VLOOKUP(C40,'EXTRAS Y FESTIVOS'!$B$9:J142,9,0) -> 0 | T40: =VLOOKUP(C40,'IP PITSS'!$B$9:R103,17,0) -> 0 | V40: =+K40-O40-P40+Q40+R40+T40+S40+IFERROR(VLOOKUP('RESUMEN PITS'!C40,'IP PITSS'!$B$9:$M$93,10),0)+IFERROR(VLOOKUP('RESUMEN PITS'!C40,'IP PITSS'!$B$9:$M$93,11),0)+IFERROR(VLOOKUP('RESUMEN PITS'!C40,'IP PITSS'!$B$9:$M$93,12),0)+VLOOKUP("Comision",'IP PITSS'!$I$99:$J$110,2)/COUNT($F$9:$F$111)+IFERROR(VLOOKUP('RESUMEN PITS'!C40,'IP PITSS'!$B$9:$AD$93,15),0)+IFERROR(VLOOKUP('RESUMEN PITS'!C40,'IP PITSS'!$B$9:$AD$93,21),0)+IFERROR(VLOOKUP('RESUMEN PITS'!C40,'IP PITSS'!$B$9:$AD$93,22),0)+IFERROR(VLOOKUP('RESUMEN PITS'!C40,'IP PITSS'!$B$9:$AD$93,23),0)+IFERROR(VLOOKUP('RESUMEN PITS'!C40,'IP PITSS'!$B$9:$AD$93,24),0)+IFERROR(VLOOKUP('RESUMEN PITS'!C40,'IP PITSS'!$B$9:$AD$93,26),0)+IFERROR(VLOOKUP('RESUMEN PITS'!C40,'IP PITSS'!$B$9:$AD$93,28),0)+IFERROR(VLOOKUP('RESUMEN PITS'!C40,'IP PITSS'!$B$9:$AD$93,29),0)+IFERROR(VLOOKUP('RESUMEN PITS'!C40,'IP PITSS'!$B$9:$AD$93,9),0)*2% -> 5414.5349 | W40: =+M40-V40-S40 -> -1414.5349 | Y40: SEI0452
A41: SEI0438 | B41: IP INNOVACION | C41: Lopez Terron Roberto Porfirio | D41: =+VLOOKUP(C41,'IP PITSS'!$B$9:U108,20,0) -> 5952.2 | F41: =VLOOKUP(C41,'SIND PITS'!$C$9:$H$113,2,0) -> 1047.8 | G41: =VLOOKUP(C41,'SIND PITS'!$C$9:$E$113,3,0) -> 187.5 | H41: =VLOOKUP(C41,'SIND PITS'!$C$9:$F$113,4,0) -> 0 | I41: =VLOOKUP(C41,'SIND PITS'!$C$9:$G$113,5,0) -> 0 | K41: =SUM(D41:I41) -> 7187.5 | L41: 14000 | M41: =+L41/2 -> 7000 | O41: =+VLOOKUP(C41,'IP PITSS'!$B$9:I108,8,0) -> 0 | P41: =+G41+H41+I41 -> 187.5 | Q41: =+(VLOOKUP(C41,'IP PITSS'!$B$9:L108,11,0))+VLOOKUP('RESUMEN PITS'!C41,'IP PITSS'!$B$9:M108,12,0)+VLOOKUP(C41,'IP PITSS'!$B$9:K108,10,0) -> 0 | R41: =VLOOKUP(C41,'IP PITSS'!$B$9:Q104,16,0) -> 0 | S41: =+VLOOKUP(C41,'EXTRAS Y FESTIVOS'!$B$9:J143,9,0) -> 0 | T41: =VLOOKUP(C41,'IP PITSS'!$B$9:R104,17,0) -> 0 | V41: =+K41-O41-P41+Q41+R41+T41+S41+IFERROR(VLOOKUP('RESUMEN PITS'!C41,'IP PITSS'!$B$9:$M$93,10),0)+IFERROR(VLOOKUP('RESUMEN PITS'!C41,'IP PITSS'!$B$9:$M$93,11),0)+IFERROR(VLOOKUP('RESUMEN PITS'!C41,'IP PITSS'!$B$9:$M$93,12),0)+VLOOKUP("Comision",'IP PITSS'!$I$99:$J$110,2)/COUNT($F$9:$F$111)+IFERROR(VLOOKUP('RESUMEN PITS'!C41,'IP PITSS'!$B$9:$AD$93,15),0)+IFERROR(VLOOKUP('RESUMEN PITS'!C41,'IP PITSS'!$B$9:$AD$93,21),0)+IFERROR(VLOOKUP('RESUMEN PITS'!C41,'IP PITSS'!$B$9:$AD$93,22),0)+IFERROR(VLOOKUP('RESUMEN PITS'!C41,'IP PITSS'!$B$9:$AD$93,23),0)+IFERROR(VLOOKUP('RESUMEN PITS'!C41,'IP PITSS'!$B$9:$AD$93,24),0)+IFERROR(VLOOKUP('RESUMEN PITS'!C41,'IP PITSS'!$B$9:$AD$93,26),0)+IFERROR(VLOOKUP('RESUMEN PITS'!C41,'IP PITSS'!$B$9:$AD$93,28),0)+IFERROR(VLOOKUP('RESUMEN PITS'!C41,'IP PITSS'!$B$9:$AD$93,29),0)+IFERROR(VLOOKUP('RESUMEN PITS'!C41,'IP PITSS'!$B$9:$AD$93,9),0)*2% -> 8414.5349 | W41: =+M41-V41-S41 -> -1414.5349 | Y41: SEI0463
A42: SEI0442 | B42: IP INNOVACION | C42: Chavez Pedraza Samuel | D42: =+VLOOKUP(C42,'IP PITSS'!$B$9:U109,20,0) -> 5952.2 | F42: =VLOOKUP(C42,'SIND PITS'!$C$9:$H$113,2,0) -> 1047.8 | G42: =VLOOKUP(C42,'SIND PITS'!$C$9:$E$113,3,0) -> 312.5 | H42: =VLOOKUP(C42,'SIND PITS'!$C$9:$F$113,4,0) -> 0 | I42: =VLOOKUP(C42,'SIND PITS'!$C$9:$G$113,5,0) -> 0 | K42: =SUM(D42:I42) -> 7312.5 | L42: 14000 | M42: =+L42/2 -> 7000 | O42: =+VLOOKUP(C42,'IP PITSS'!$B$9:I109,8,0) -> 0 | P42: =+G42+H42+I42 -> 312.5 | Q42: =+(VLOOKUP(C42,'IP PITSS'!$B$9:L109,11,0))+VLOOKUP('RESUMEN PITS'!C42,'IP PITSS'!$B$9:M109,12,0)+VLOOKUP(C42,'IP PITSS'!$B$9:K109,10,0) -> 0 | R42: =VLOOKUP(C42,'IP PITSS'!$B$9:Q105,16,0) -> 0 | S42: =+VLOOKUP(C42,'EXTRAS Y FESTIVOS'!$B$9:J144,9,0) -> 0 | T42: =VLOOKUP(C42,'IP PITSS'!$B$9:R105,17,0) -> 0 | V42: =+K42-O42-P42+Q42+R42+T42+S42+IFERROR(VLOOKUP('RESUMEN PITS'!C42,'IP PITSS'!$B$9:$M$93,10),0)+IFERROR(VLOOKUP('RESUMEN PITS'!C42,'IP PITSS'!$B$9:$M$93,11),0)+IFERROR(VLOOKUP('RESUMEN PITS'!C42,'IP PITSS'!$B$9:$M$93,12),0)+VLOOKUP("Comision",'IP PITSS'!$I$99:$J$110,2)/COUNT($F$9:$F$111)+IFERROR(VLOOKUP('RESUMEN PITS'!C42,'IP PITSS'!$B$9:$AD$93,15),0)+IFERROR(VLOOKUP('RESUMEN PITS'!C42,'IP PITSS'!$B$9:$AD$93,21),0)+IFERROR(VLOOKUP('RESUMEN PITS'!C42,'IP PITSS'!$B$9:$AD$93,22),0)+IFERROR(VLOOKUP('RESUMEN PITS'!C42,'IP PITSS'!$B$9:$AD$93,23),0)+IFERROR(VLOOKUP('RESUMEN PITS'!C42,'IP PITSS'!$B$9:$AD$93,24),0)+IFERROR(VLOOKUP('RESUMEN PITS'!C42,'IP PITSS'!$B$9:$AD$93,26),0)+IFERROR(VLOOKUP('RESUMEN PITS'!C42,'IP PITSS'!$B$9:$AD$93,28),0)+IFERROR(VLOOKUP('RESUMEN PITS'!C42,'IP PITSS'!$B$9:$AD$93,29),0)+IFERROR(VLOOKUP('RESUMEN PITS'!C42,'IP PITSS'!$B$9:$AD$93,9),0)*2% -> 8414.5349 | W42: =+M42-V42-S42 -> -1414.5349 | Y42: SEI0467
A43: SEI0443 | B43: IP INNOVACION | C43: Castillo Nungaray Nestor Roman | D43: =+VLOOKUP(C43,'IP PITSS'!$B$9:U110,20,0) -> 2864.8 | F43: =VLOOKUP(C43,'SIND PITS'!$C$9:$H$113,2,0) -> 285.2 | G43: =VLOOKUP(C43,'SIND PITS'!$C$9:$E$113,3,0) -> 800 | H43: =VLOOKUP(C43,'SIND PITS'!$C$9:$F$113,4,0) -> 0 | I43: =VLOOKUP(C43,'SIND PITS'!$C$9:$G$113,5,0) -> 0 | K43: =SUM(D43:I43) -> 3950 | L43: 6300 | M43: =+L43/2 -> 3150 | O43: =+VLOOKUP(C43,'IP PITSS'!$B$9:I110,8,0) -> 0 | P43: =+G43+H43+I43 -> 800 | Q43: =+(VLOOKUP(C43,'IP PITSS'!$B$9:L110,11,0))+VLOOKUP('RESUMEN PITS'!C43,'IP PITSS'!$B$9:M110,12,0)+VLOOKUP(C43,'IP PITSS'!$B$9:K110,10,0) -> 0 | R43: =VLOOKUP(C43,'IP PITSS'!$B$9:Q106,16,0) -> 0 | S43: =+VLOOKUP(C43,'EXTRAS Y FESTIVOS'!$B$9:J145,9,0) -> 0 | T43: =VLOOKUP(C43,'IP PITSS'!$B$9:R106,17,0) -> 0 | V43: =+K43-O43-P43+Q43+R43+T43+S43+IFERROR(VLOOKUP('RESUMEN PITS'!C43,'IP PITSS'!$B$9:$M$93,10),0)+IFERROR(VLOOKUP('RESUMEN PITS'!C43,'IP PITSS'!$B$9:$M$93,11),0)+IFERROR(VLOOKUP('RESUMEN PITS'!C43,'IP PITSS'!$B$9:$M$93,12),0)+VLOOKUP("Comision",'IP PITSS'!$I$99:$J$110,2)/COUNT($F$9:$F$111)+IFERROR(VLOOKUP('RESUMEN PITS'!C43,'IP PITSS'!$B$9:$AD$93,15),0)+IFERROR(VLOOKUP('RESUMEN PITS'!C43,'IP PITSS'!$B$9:$AD$93,21),0)+IFERROR(VLOOKUP('RESUMEN PITS'!C43,'IP PITSS'!$B$9:$AD$93,22),0)+IFERROR(VLOOKUP('RESUMEN PITS'!C43,'IP PITSS'!$B$9:$AD$93,23),0)+IFERROR(VLOOKUP('RESUMEN PITS'!C43,'IP PITSS'!$B$9:$AD$93,24),0)+IFERROR(VLOOKUP('RESUMEN PITS'!C43,'IP PITSS'!$B$9:$AD$93,26),0)+IFERROR(VLOOKUP('RESUMEN PITS'!C43,'IP PITSS'!$B$9:$AD$93,28),0)+IFERROR(VLOOKUP('RESUMEN PITS'!C43,'IP PITSS'!$B$9:$AD$93,29),0)+IFERROR(VLOOKUP('RESUMEN PITS'!C43,'IP PITSS'!$B$9:$AD$93,9),0)*2% -> 3204.0559 | W43: =+M43-V43-S43 -> -54.055924 | Y43: SEI0468
A44: SEI0444 | B44: IP INNOVACION | C44: Marquez Hernandez Rogelio | D44: =+VLOOKUP(C44,'IP PITSS'!$B$9:U111,20,0) -> 3142.6 | F44: =VLOOKUP(C44,'SIND PITS'!$C$9:$H$113,2,0) -> 416.4 | G44: =VLOOKUP(C44,'SIND PITS'!$C$9:$E$113,3,0) -> 150 | H44: =VLOOKUP(C44,'SIND PITS'!$C$9:$F$113,4,0) -> 0 | I44: =VLOOKUP(C44,'SIND PITS'!$C$9:$G$113,5,0) -> 0 | K44: =SUM(D44:I44) -> 3709 | L44: 8000 | M44: =+L44/2 -> 4000 | O44: =+VLOOKUP(C44,'IP PITSS'!$B$9:I111,8,0) -> 0 | P44: =+G44+H44+I44 -> 150 | Q44: =+(VLOOKUP(C44,'IP PITSS'!$B$9:L111,11,0))+VLOOKUP('RESUMEN PITS'!C44,'IP PITSS'!$B$9:M111,12,0)+VLOOKUP(C44,'IP PITSS'!$B$9:K111,10,0) -> 0 | R44: =VLOOKUP(C44,'IP PITSS'!$B$9:Q107,16,0) -> 0 | S44: =+VLOOKUP(C44,'EXTRAS Y FESTIVOS'!$B$9:J146,9,0) -> 0 | T44: =VLOOKUP(C44,'IP PITSS'!$B$9:R107,17,0) -> 441 | V44: =+K44-O44-P44+Q44+R44+T44+S44+IFERROR(VLOOKUP('RESUMEN PITS'!C44,'IP PITSS'!$B$9:$M$93,10),0)+IFERROR(VLOOKUP('RESUMEN PITS'!C44,'IP PITSS'!$B$9:$M$93,11),0)+IFERROR(VLOOKUP('RESUMEN PITS'!C44,'IP PITSS'!$B$9:$M$93,12),0)+VLOOKUP("Comision",'IP PITSS'!$I$99:$J$110,2)/COUNT($F$9:$F$111)+IFERROR(VLOOKUP('RESUMEN PITS'!C44,'IP PITSS'!$B$9:$AD$93,15),0)+IFERROR(VLOOKUP('RESUMEN PITS'!C44,'IP PITSS'!$B$9:$AD$93,21),0)+IFERROR(VLOOKUP('RESUMEN PITS'!C44,'IP PITSS'!$B$9:$AD$93,22),0)+IFERROR(VLOOKUP('RESUMEN PITS'!C44,'IP PITSS'!$B$9:$AD$93,23),0)+IFERROR(VLOOKUP('RESUMEN PITS'!C44,'IP PITSS'!$B$9:$AD$93,24),0)+IFERROR(VLOOKUP('RESUMEN PITS'!C44,'IP PITSS'!$B$9:$AD$93,26),0)+IFERROR(VLOOKUP('RESUMEN PITS'!C44,'IP PITSS'!$B$9:$AD$93,28),0)+IFERROR(VLOOKUP('RESUMEN PITS'!C44,'IP PITSS'!$B$9:$AD$93,29),0)+IFERROR(VLOOKUP('RESUMEN PITS'!C44,'IP PITSS'!$B$9:$AD$93,9),0)*2% -> 5414.5349 | W44: =+M44-V44-S44 -> -1414.5349 | Y44: SEI0469
A45: SEI0449 | B45: IP INNOVACION | C45: Flores Cerrillos Jorge Humberto | D45: =+VLOOKUP(C45,'IP PITSS'!$B$9:U112,20,0) -> 3583.8 | F45: =VLOOKUP(C45,'SIND PITS'!$C$9:$H$113,2,0) -> 416.2 | G45: =VLOOKUP(C45,'SIND PITS'!$C$9:$E$113,3,0) -> 130 | H45: =VLOOKUP(C45,'SIND PITS'!$C$9:$F$113,4,0) -> 0 | I45: =VLOOKUP(C45,'SIND PITS'!$C$9:$G$113,5,0) -> 0 | K45: =SUM(D45:I45) -> 4130 | L45: 8000 | M45: =+L45/2 -> 4000 | O45: =+VLOOKUP(C45,'IP PITSS'!$B$9:I112,8,0) -> 0 | P45: =+G45+H45+I45 -> 130 | Q45: =+(VLOOKUP(C45,'IP PITSS'!$B$9:L112,11,0))+VLOOKUP('RESUMEN PITS'!C45,'IP PITSS'!$B$9:M112,12,0)+VLOOKUP(C45,'IP PITSS'!$B$9:K112,10,0) -> 0 | R45: =VLOOKUP(C45,'IP PITSS'!$B$9:Q108,16,0) -> 0 | S45: =+VLOOKUP(C45,'EXTRAS Y FESTIVOS'!$B$9:J147,9,0) -> 0 | T45: =VLOOKUP(C45,'IP PITSS'!$B$9:R108,17,0) -> 0 | V45: =+K45-O45-P45+Q45+R45+T45+S45+IFERROR(VLOOKUP('RESUMEN PITS'!C45,'IP PITSS'!$B$9:$M$93,10),0)+IFERROR(VLOOKUP('RESUMEN PITS'!C45,'IP PITSS'!$B$9:$M$93,11),0)+IFERROR(VLOOKUP('RESUMEN PITS'!C45,'IP PITSS'!$B$9:$M$93,12),0)+VLOOKUP("Comision",'IP PITSS'!$I$99:$J$110,2)/COUNT($F$9:$F$111)+IFERROR(VLOOKUP('RESUMEN PITS'!C45,'IP PITSS'!$B$9:$AD$93,15),0)+IFERROR(VLOOKUP('RESUMEN PITS'!C45,'IP PITSS'!$B$9:$AD$93,21),0)+IFERROR(VLOOKUP('RESUMEN PITS'!C45,'IP PITSS'!$B$9:$AD$93,22),0)+IFERROR(VLOOKUP('RESUMEN PITS'!C45,'IP PITSS'!$B$9:$AD$93,23),0)+IFERROR(VLOOKUP('RESUMEN PITS'!C45,'IP PITSS'!$B$9:$AD$93,24),0)+IFERROR(VLOOKUP('RESUMEN PITS'!C45,'IP PITSS'!$B$9:$AD$93,26),0)+IFERROR(VLOOKUP('RESUMEN PITS'!C45,'IP PITSS'!$B$9:$AD$93,28),0)+IFERROR(VLOOKUP('RESUMEN PITS'!C45,'IP PITSS'!$B$9:$AD$93,29),0)+IFERROR(VLOOKUP('RESUMEN PITS'!C45,'IP PITSS'!$B$9:$AD$93,9),0)*2% -> 5414.5349 | W45: =+M45-V45-S45 -> -1414.5349 | Y45: SEI0474
A46: SEI0455 | B46: IP INNOVACION | C46: Perez Garcia Andres Alvaro | D46: =+VLOOKUP(C46,'IP PITSS'!$B$9:U113,20,0) -> 3333.6 | F46: =VLOOKUP(C46,'SIND PITS'!$C$9:$H$113,2,0) -> 416.4 | G46: =VLOOKUP(C46,'SIND PITS'!$C$9:$E$113,3,0) -> 315 | H46: =VLOOKUP(C46,'SIND PITS'!$C$9:$F$113,4,0) -> 0 | I46: =VLOOKUP(C46,'SIND PITS'!$C$9:$G$113,5,0) -> 0 | K46: =SUM(D46:I46) -> 4065 | L46: 8000 | M46: =+L46/2 -> 4000 | O46: =+VLOOKUP(C46,'IP PITSS'!$B$9:I113,8,0) -> 0 | P46: =+G46+H46+I46 -> 315 | Q46: =+(VLOOKUP(C46,'IP PITSS'!$B$9:L113,11,0))+VLOOKUP('RESUMEN PITS'!C46,'IP PITSS'!$B$9:M113,12,0)+VLOOKUP(C46,'IP PITSS'!$B$9:K113,10,0) -> 0 | R46: =VLOOKUP(C46,'IP PITSS'!$B$9:Q109,16,0) -> 0 | S46: =+VLOOKUP(C46,'EXTRAS Y FESTIVOS'!$B$9:J148,9,0) -> 0 | T46: =VLOOKUP(C46,'IP PITSS'!$B$9:R109,17,0) -> 250 | V46: =+K46-O46-P46+Q46+R46+T46+S46+IFERROR(VLOOKUP('RESUMEN PITS'!C46,'IP PITSS'!$B$9:$M$93,10),0)+IFERROR(VLOOKUP('RESUMEN PITS'!C46,'IP PITSS'!$B$9:$M$93,11),0)+IFERROR(VLOOKUP('RESUMEN PITS'!C46,'IP PITSS'!$B$9:$M$93,12),0)+VLOOKUP("Comision",'IP PITSS'!$I$99:$J$110,2)/COUNT($F$9:$F$111)+IFERROR(VLOOKUP('RESUMEN PITS'!C46,'IP PITSS'!$B$9:$AD$93,15),0)+IFERROR(VLOOKUP('RESUMEN PITS'!C46,'IP PITSS'!$B$9:$AD$93,21),0)+IFERROR(VLOOKUP('RESUMEN PITS'!C46,'IP PITSS'!$B$9:$AD$93,22),0)+IFERROR(VLOOKUP('RESUMEN PITS'!C46,'IP PITSS'!$B$9:$AD$93,23),0)+IFERROR(VLOOKUP('RESUMEN PITS'!C46,'IP PITSS'!$B$9:$AD$93,24),0)+IFERROR(VLOOKUP('RESUMEN PITS'!C46,'IP PITSS'!$B$9:$AD$93,26),0)+IFERROR(VLOOKUP('RESUMEN PITS'!C46,'IP PITSS'!$B$9:$AD$93,28),0)+IFERROR(VLOOKUP('RESUMEN PITS'!C46,'IP PITSS'!$B$9:$AD$93,29),0)+IFERROR(VLOOKUP('RESUMEN PITS'!C46,'IP PITSS'!$B$9:$AD$93,9),0)*2% -> 5342.3659 | W46: =+M46-V46-S46 -> -1342.3659 | Y46: SEI0494
A47: SEI0456 | B47: IP INNOVACION | C47: Chavira Garcia David Fernando | D47: =+VLOOKUP(C47,'IP PITSS'!$B$9:U114,20,0) -> 4406.4 | F47: =VLOOKUP(C47,'SIND PITS'!$C$9:$H$113,2,0) -> 593.6 | G47: =VLOOKUP(C47,'SIND PITS'!$C$9:$E$113,3,0) -> 60 | H47: =VLOOKUP(C47,'SIND PITS'!$C$9:$F$113,4,0) -> 0 | I47: =VLOOKUP(C47,'SIND PITS'!$C$9:$G$113,5,0) -> 0 | K47: =SUM(D47:I47) -> 5060 | L47: 10000 | M47: =+L47/2 -> 5000 | O47: =+VLOOKUP(C47,'IP PITSS'!$B$9:I114,8,0) -> 0 | P47: =+G47+H47+I47 -> 60 | Q47: =+(VLOOKUP(C47,'IP PITSS'!$B$9:L114,11,0))+VLOOKUP('RESUMEN PITS'!C47,'IP PITSS'!$B$9:M114,12,0)+VLOOKUP(C47,'IP PITSS'!$B$9:K114,10,0) -> 0 | R47: =VLOOKUP(C47,'IP PITSS'!$B$9:Q110,16,0) -> 0 | S47: =+VLOOKUP(C47,'EXTRAS Y FESTIVOS'!$B$9:J149,9,0) -> 0 | T47: =VLOOKUP(C47,'IP PITSS'!$B$9:R110,17,0) -> 0 | V47: =+K47-O47-P47+Q47+R47+T47+S47+IFERROR(VLOOKUP('RESUMEN PITS'!C47,'IP PITSS'!$B$9:$M$93,10),0)+IFERROR(VLOOKUP('RESUMEN PITS'!C47,'IP PITSS'!$B$9:$M$93,11),0)+IFERROR(VLOOKUP('RESUMEN PITS'!C47,'IP PITSS'!$B$9:$M$93,12),0)+VLOOKUP("Comision",'IP PITSS'!$I$99:$J$110,2)/COUNT($F$9:$F$111)+IFERROR(VLOOKUP('RESUMEN PITS'!C47,'IP PITSS'!$B$9:$AD$93,15),0)+IFERROR(VLOOKUP('RESUMEN PITS'!C47,'IP PITSS'!$B$9:$AD$93,21),0)+IFERROR(VLOOKUP('RESUMEN PITS'!C47,'IP PITSS'!$B$9:$AD$93,22),0)+IFERROR(VLOOKUP('RESUMEN PITS'!C47,'IP PITSS'!$B$9:$AD$93,23),0)+IFERROR(VLOOKUP('RESUMEN PITS'!C47,'IP PITSS'!$B$9:$AD$93,24),0)+IFERROR(VLOOKUP('RESUMEN PITS'!C47,'IP PITSS'!$B$9:$AD$93,26),0)+IFERROR(VLOOKUP('RESUMEN PITS'!C47,'IP PITSS'!$B$9:$AD$93,28),0)+IFERROR(VLOOKUP('RESUMEN PITS'!C47,'IP PITSS'!$B$9:$AD$93,29),0)+IFERROR(VLOOKUP('RESUMEN PITS'!C47,'IP PITSS'!$B$9:$AD$93,9),0)*2% -> 6414.5349 | W47: =+M47-V47-S47 -> -1414.5349 | Y47: SEI0495
A48: SEI0457 | B48: IP INNOVACION | C48: Guerrero Lara Cesar Adrian | D48: =+VLOOKUP(C48,'IP PITSS'!$B$9:U115,20,0) -> 3583.6 | F48: =VLOOKUP(C48,'SIND PITS'!$C$9:$H$113,2,0) -> 416.4 | G48: =VLOOKUP(C48,'SIND PITS'!$C$9:$E$113,3,0) -> 225 | H48: =VLOOKUP(C48,'SIND PITS'!$C$9:$F$113,4,0) -> 0 | I48: =VLOOKUP(C48,'SIND PITS'!$C$9:$G$113,5,0) -> 0 | K48: =SUM(D48:I48) -> 4225 | L48: 8000 | M48: =+L48/2 -> 4000 | O48: =+VLOOKUP(C48,'IP PITSS'!$B$9:I115,8,0) -> 0 | P48: =+G48+H48+I48 -> 225 | Q48: =+(VLOOKUP(C48,'IP PITSS'!$B$9:L115,11,0))+VLOOKUP('RESUMEN PITS'!C48,'IP PITSS'!$B$9:M115,12,0)+VLOOKUP(C48,'IP PITSS'!$B$9:K115,10,0) -> 0 | R48: =VLOOKUP(C48,'IP PITSS'!$B$9:Q111,16,0) -> 0 | S48: =+VLOOKUP(C48,'EXTRAS Y FESTIVOS'!$B$9:J150,9,0) -> 0 | T48: =VLOOKUP(C48,'IP PITSS'!$B$9:R111,17,0) -> 0 | V48: =+K48-O48-P48+Q48+R48+T48+S48+IFERROR(VLOOKUP('RESUMEN PITS'!C48,'IP PITSS'!$B$9:$M$93,10),0)+IFERROR(VLOOKUP('RESUMEN PITS'!C48,'IP PITSS'!$B$9:$M$93,11),0)+IFERROR(VLOOKUP('RESUMEN PITS'!C48,'IP PITSS'!$B$9:$M$93,12),0)+VLOOKUP("Comision",'IP PITSS'!$I$99:$J$110,2)/COUNT($F$9:$F$111)+IFERROR(VLOOKUP('RESUMEN PITS'!C48,'IP PITSS'!$B$9:$AD$93,15),0)+IFERROR(VLOOKUP('RESUMEN PITS'!C48,'IP PITSS'!$B$9:$AD$93,21),0)+IFERROR(VLOOKUP('RESUMEN PITS'!C48,'IP PITSS'!$B$9:$AD$93,22),0)+IFERROR(VLOOKUP('RESUMEN PITS'!C48,'IP PITSS'!$B$9:$AD$93,23),0)+IFERROR(VLOOKUP('RESUMEN PITS'!C48,'IP PITSS'!$B$9:$AD$93,24),0)+IFERROR(VLOOKUP('RESUMEN PITS'!C48,'IP PITSS'!$B$9:$AD$93,26),0)+IFERROR(VLOOKUP('RESUMEN PITS'!C48,'IP PITSS'!$B$9:$AD$93,28),0)+IFERROR(VLOOKUP('RESUMEN PITS'!C48,'IP PITSS'!$B$9:$AD$93,29),0)+IFERROR(VLOOKUP('RESUMEN PITS'!C48,'IP PITSS'!$B$9:$AD$93,9),0)*2% -> 5414.5349 | W48: =+M48-V48-S48 -> -1414.5349 | Y48: SEI0496
A49: SEI0458 | B49: IP INNOVACION | C49: Martinez Zamora Gerardo Mario | D49: =+VLOOKUP(C49,'IP PITSS'!$B$9:U116,20,0) -> 2709.6 | F49: =VLOOKUP(C49,'SIND PITS'!$C$9:$H$113,2,0) -> 550.075 | G49: =VLOOKUP(C49,'SIND PITS'!$C$9:$E$113,3,0) -> 375 | H49: =VLOOKUP(C49,'SIND PITS'!$C$9:$F$113,4,0) -> 0 | I49: =VLOOKUP(C49,'SIND PITS'!$C$9:$G$113,5,0) -> 0 | K49: =SUM(D49:I49) -> 3634.675 | L49: 9550.01 | M49: =+L49/2 -> 4775.005 | O49: =+VLOOKUP(C49,'IP PITSS'!$B$9:I116,8,0) -> 0 | P49: =+G49+H49+I49 -> 375 | Q49: =+(VLOOKUP(C49,'IP PITSS'!$B$9:L116,11,0))+VLOOKUP('RESUMEN PITS'!C49,'IP PITSS'!$B$9:M116,12,0)+VLOOKUP(C49,'IP PITSS'!$B$9:K116,10,0) -> 1515.33 | R49: =VLOOKUP(C49,'IP PITSS'!$B$9:Q112,16,0) -> 0 | S49: =+VLOOKUP(C49,'EXTRAS Y FESTIVOS'!$B$9:J151,9,0) -> 0 | T49: =VLOOKUP(C49,'IP PITSS'!$B$9:R112,17,0) -> 0 | V49: =+K49-O49-P49+Q49+R49+T49+S49+IFERROR(VLOOKUP('RESUMEN PITS'!C49,'IP PITSS'!$B$9:$M$93,10),0)+IFERROR(VLOOKUP('RESUMEN PITS'!C49,'IP PITSS'!$B$9:$M$93,11),0)+IFERROR(VLOOKUP('RESUMEN PITS'!C49,'IP PITSS'!$B$9:$M$93,12),0)+VLOOKUP("Comision",'IP PITSS'!$I$99:$J$110,2)/COUNT($F$9:$F$111)+IFERROR(VLOOKUP('RESUMEN PITS'!C49,'IP PITSS'!$B$9:$AD$93,15),0)+IFERROR(VLOOKUP('RESUMEN PITS'!C49,'IP PITSS'!$B$9:$AD$93,21),0)+IFERROR(VLOOKUP('RESUMEN PITS'!C49,'IP PITSS'!$B$9:$AD$93,22),0)+IFERROR(VLOOKUP('RESUMEN PITS'!C49,'IP PITSS'!$B$9:$AD$93,23),0)+IFERROR(VLOOKUP('RESUMEN PITS'!C49,'IP PITSS'!$B$9:$AD$93,24),0)+IFERROR(VLOOKUP('RESUMEN PITS'!C49,'IP PITSS'!$B$9:$AD$93,26),0)+IFERROR(VLOOKUP('RESUMEN PITS'!C49,'IP PITSS'!$B$9:$AD$93,28),0)+IFERROR(VLOOKUP('RESUMEN PITS'!C49,'IP PITSS'!$B$9:$AD$93,29),0)+IFERROR(VLOOKUP('RESUMEN PITS'!C49,'IP PITSS'!$B$9:$AD$93,9),0)*2% -> 5987.5719 | W49: =+M49-V49-S49 -> -1212.5669 | Y49: SEI0497
A50: SEI0460 | B50: IP INNOVACION | C50: Castellon Ramos Rene | D50: =+VLOOKUP(C50,'IP PITSS'!$B$9:U117,20,0) -> 1884.6 | F50: =VLOOKUP(C50,'SIND PITS'!$C$9:$H$113,2,0) -> 384.785 | G50: =VLOOKUP(C50,'SIND PITS'!$C$9:$E$113,3,0) -> 70 | H50: =VLOOKUP(C50,'SIND PITS'!$C$9:$F$113,4,0) -> 0 | I50: =VLOOKUP(C50,'SIND PITS'!$C$9:$G$113,5,0) -> 0.0599 | K50: =SUM(D50:I50) -> 2339.4449 | L50: 7505.99 | M50: =+L50/2 -> 3752.995 | O50: =+VLOOKUP(C50,'IP PITSS'!$B$9:I117,8,0) -> 75 | P50: =+G50+H50+I50 -> 70.0599 | Q50: =+(VLOOKUP(C50,'IP PITSS'!$B$9:L117,11,0))+VLOOKUP('RESUMEN PITS'!C50,'IP PITSS'!$B$9:M117,12,0)+VLOOKUP(C50,'IP PITSS'!$B$9:K117,10,0) -> 1373.01 | R50: =VLOOKUP(C50,'IP PITSS'!$B$9:Q113,16,0) -> 0 | S50: =+VLOOKUP(C50,'EXTRAS Y FESTIVOS'!$B$9:J152,9,0) -> 0 | T50: =VLOOKUP(C50,'IP PITSS'!$B$9:R113,17,0) -> 185.6 | V50: =+K50-O50-P50+Q50+R50+T50+S50+IFERROR(VLOOKUP('RESUMEN PITS'!C50,'IP PITSS'!$B$9:$M$93,10),0)+IFERROR(VLOOKUP('RESUMEN PITS'!C50,'IP PITSS'!$B$9:$M$93,11),0)+IFERROR(VLOOKUP('RESUMEN PITS'!C50,'IP PITSS'!$B$9:$M$93,12),0)+VLOOKUP("Comision",'IP PITSS'!$I$99:$J$110,2)/COUNT($F$9:$F$111)+IFERROR(VLOOKUP('RESUMEN PITS'!C50,'IP PITSS'!$B$9:$AD$93,15),0)+IFERROR(VLOOKUP('RESUMEN PITS'!C50,'IP PITSS'!$B$9:$AD$93,21),0)+IFERROR(VLOOKUP('RESUMEN PITS'!C50,'IP PITSS'!$B$9:$AD$93,22),0)+IFERROR(VLOOKUP('RESUMEN PITS'!C50,'IP PITSS'!$B$9:$AD$93,23),0)+IFERROR(VLOOKUP('RESUMEN PITS'!C50,'IP PITSS'!$B$9:$AD$93,24),0)+IFERROR(VLOOKUP('RESUMEN PITS'!C50,'IP PITSS'!$B$9:$AD$93,26),0)+IFERROR(VLOOKUP('RESUMEN PITS'!C50,'IP PITSS'!$B$9:$AD$93,28),0)+IFERROR(VLOOKUP('RESUMEN PITS'!C50,'IP PITSS'!$B$9:$AD$93,29),0)+IFERROR(VLOOKUP('RESUMEN PITS'!C50,'IP PITSS'!$B$9:$AD$93,9),0)*2% -> 3807.0509 | W50: =+M50-V50-S50 -> -54.055924 | Y50: SEI0499
... A102: SEI0545 | B102: IP INNOVACION | C102: Vallarta Fonseca Mayra Karina | D102: =+VLOOKUP(C102,'IP PITSS'!$B$9:U169,20,0) -> 1576 | F102: =VLOOKUP(C102,'SIND PITS'!$C$9:$H$113,2,0) -> 135.22 | G102: =VLOOKUP(C102,'SIND PITS'!$C$9:$E$113,3,0) -> 390 | H102: =VLOOKUP(C102,'SIND PITS'!$C$9:$F$113,4,0) -> 0 | I102: =VLOOKUP(C102,'SIND PITS'!$C$9:$G$113,5,0) -> 0 | K102: =SUM(D102:I102) -> 2101.22 | L102: 6000 | M102: =+L102/2 -> 3000 | O102: =+VLOOKUP(C102,'IP PITSS'!$B$9:I169,8,0) -> 0 | P102: =+G102+H102+I102 -> 390 | Q102: =+(VLOOKUP(C102,'IP PITSS'!$B$9:L169,11,0))+VLOOKUP('RESUMEN PITS'!C102,'IP PITSS'!$B$9:M169,12,0)+VLOOKUP(C102,'IP PITSS'!$B$9:K169,10,0) -> 652.18 | R102: =VLOOKUP(C102,'IP PITSS'!$B$9:Q165,16,0) -> 636.6 | S102: =+VLOOKUP(C102,'EXTRAS Y FESTIVOS'!$B$9:J204,9,0) -> 0 | T102: =VLOOKUP(C102,'IP PITSS'!$B$9:R165,17,0) -> 0 | V102: =+K102-O102-P102+Q102+R102+T102+S102+IFERROR(VLOOKUP('RESUMEN PITS'!C102,'IP PITSS'!$B$9:$M$93,10),0)+IFERROR(VLOOKUP('RESUMEN PITS'!C102,'IP PITSS'!$B$9:$M$93,11),0)+IFERROR(VLOOKUP('RESUMEN PITS'!C102,'IP PITSS'!$B$9:$M$93,12),0)+VLOOKUP("Comision",'IP PITSS'!$I$99:$J$110,2)/COUNT($F$9:$F$111)+IFERROR(VLOOKUP('RESUMEN PITS'!C102,'IP PITSS'!$B$9:$AD$93,15),0)+IFERROR(VLOOKUP('RESUMEN PITS'!C102,'IP PITSS'!$B$9:$AD$93,21),0)+IFERROR(VLOOKUP('RESUMEN PITS'!C102,'IP PITSS'!$B$9:$AD$93,22),0)+IFERROR(VLOOKUP('RESUMEN PITS'!C102,'IP PITSS'!$B$9:$AD$93,23),0)+IFERROR(VLOOKUP('RESUMEN PITS'!C102,'IP PITSS'!$B$9:$AD$93,24),0)+IFERROR(VLOOKUP('RESUMEN PITS'!C102,'IP PITSS'!$B$9:$AD$93,26),0)+IFERROR(VLOOKUP('RESUMEN PITS'!C102,'IP PITSS'!$B$9:$AD$93,28),0)+IFERROR(VLOOKUP('RESUMEN PITS'!C102,'IP PITSS'!$B$9:$AD$93,29),0)+IFERROR(VLOOKUP('RESUMEN PITS'!C102,'IP PITSS'!$B$9:$AD$93,9),0)*2% -> 3784.9959 | W102: =+M102-V102-S102 -> -784.99592 | Y102: SEI0653
A103: SEI0547 | B103: IP INNOVACION | C103: Aguilar Garcia Rosa Paola | D103: =+VLOOKUP(C103,'IP PITSS'!$B$9:U170,20,0) -> 2446.8 | F103: =VLOOKUP(C103,'SIND PITS'!$C$9:$H$113,2,0) -> 53.2 | G103: =VLOOKUP(C103,'SIND PITS'!$C$9:$E$113,3,0) -> 0 | H103: =VLOOKUP(C103,'SIND PITS'!$C$9:$F$113,4,0) -> 0 | I103: =VLOOKUP(C103,'SIND PITS'!$C$9:$G$113,5,0) -> 0 | K103: =SUM(D103:I103) -> 2500 | L103: 5000 | M103: =+L103/2 -> 2500 | O103: =+VLOOKUP(C103,'IP PITSS'!$B$9:I170,8,0) -> 0 | P103: =+G103+H103+I103 -> 0 | Q103: =+(VLOOKUP(C103,'IP PITSS'!$B$9:L170,11,0))+VLOOKUP('RESUMEN PITS'!C103,'IP PITSS'!$B$9:M170,12,0)+VLOOKUP(C103,'IP PITSS'!$B$9:K170,10,0) -> 0 | R103: =VLOOKUP(C103,'IP PITSS'!$B$9:Q166,16,0) -> 0 | S103: =+VLOOKUP(C103,'EXTRAS Y FESTIVOS'!$B$9:J205,9,0) -> 0 | T103: =VLOOKUP(C103,'IP PITSS'!$B$9:R166,17,0) -> 0 | V103: =+K103-O103-P103+Q103+R103+T103+S103+IFERROR(VLOOKUP('RESUMEN PITS'!C103,'IP PITSS'!$B$9:$M$93,10),0)+IFERROR(VLOOKUP('RESUMEN PITS'!C103,'IP PITSS'!$B$9:$M$93,11),0)+IFERROR(VLOOKUP('RESUMEN PITS'!C103,'IP PITSS'!$B$9:$M$93,12),0)+VLOOKUP("Comision",'IP PITSS'!$I$99:$J$110,2)/COUNT($F$9:$F$111)+IFERROR(VLOOKUP('RESUMEN PITS'!C103,'IP PITSS'!$B$9:$AD$93,15),0)+IFERROR(VLOOKUP('RESUMEN PITS'!C103,'IP PITSS'!$B$9:$AD$93,21),0)+IFERROR(VLOOKUP('RESUMEN PITS'!C103,'IP PITSS'!$B$9:$AD$93,22),0)+IFERROR(VLOOKUP('RESUMEN PITS'!C103,'IP PITSS'!$B$9:$AD$93,23),0)+IFERROR(VLOOKUP('RESUMEN PITS'!C103,'IP PITSS'!$B$9:$AD$93,24),0)+IFERROR(VLOOKUP('RESUMEN PITS'!C103,'IP PITSS'!$B$9:$AD$93,26),0)+IFERROR(VLOOKUP('RESUMEN PITS'!C103,'IP PITSS'!$B$9:$AD$93,28),0)+IFERROR(VLOOKUP('RESUMEN PITS'!C103,'IP PITSS'!$B$9:$AD$93,29),0)+IFERROR(VLOOKUP('RESUMEN PITS'!C103,'IP PITSS'!$B$9:$AD$93,9),0)*2% -> 2554.0559 | W103: =+M103-V103-S103 -> -54.055924
A104: SEI0548 | B104: IP INNOVACION | C104: Jauregui Madera Jorge Silvestre | D104: =+VLOOKUP(C104,'IP PITSS'!$B$9:U171,20,0) -> 2865.8 | F104: =VLOOKUP(C104,'SIND PITS'!$C$9:$H$113,2,0) -> 134.2 | G104: =VLOOKUP(C104,'SIND PITS'!$C$9:$E$113,3,0) -> 487.5 | H104: =VLOOKUP(C104,'SIND PITS'!$C$9:$F$113,4,0) -> 0 | I104: =VLOOKUP(C104,'SIND PITS'!$C$9:$G$113,5,0) -> 0 | K104: =SUM(D104:I104) -> 3487.5 | L104: 6000 | M104: =+L104/2 -> 3000 | O104: =+VLOOKUP(C104,'IP PITSS'!$B$9:I171,8,0) -> 0 | P104: =+G104+H104+I104 -> 487.5 | Q104: =+(VLOOKUP(C104,'IP PITSS'!$B$9:L171,11,0))+VLOOKUP('RESUMEN PITS'!C104,'IP PITSS'!$B$9:M171,12,0)+VLOOKUP(C104,'IP PITSS'!$B$9:K171,10,0) -> 0 | R104: =VLOOKUP(C104,'IP PITSS'!$B$9:Q167,16,0) -> 0 | S104: =+VLOOKUP(C104,'EXTRAS Y FESTIVOS'!$B$9:J206,9,0) -> 0 | T104: =VLOOKUP(C104,'IP PITSS'!$B$9:R167,17,0) -> 0 | V104: =+K104-O104-P104+Q104+R104+T104+S104+IFERROR(VLOOKUP('RESUMEN PITS'!C104,'IP PITSS'!$B$9:$M$93,10),0)+IFERROR(VLOOKUP('RESUMEN PITS'!C104,'IP PITSS'!$B$9:$M$93,11),0)+IFERROR(VLOOKUP('RESUMEN PITS'!C104,'IP PITSS'!$B$9:$M$93,12),0)+VLOOKUP("Comision",'IP PITSS'!$I$99:$J$110,2)/COUNT($F$9:$F$111)+IFERROR(VLOOKUP('RESUMEN PITS'!C104,'IP PITSS'!$B$9:$AD$93,15),0)+IFERROR(VLOOKUP('RESUMEN PITS'!C104,'IP PITSS'!$B$9:$AD$93,21),0)+IFERROR(VLOOKUP('RESUMEN PITS'!C104,'IP PITSS'!$B$9:$AD$93,22),0)+IFERROR(VLOOKUP('RESUMEN PITS'!C104,'IP PITSS'!$B$9:$AD$93,23),0)+IFERROR(VLOOKUP('RESUMEN PITS'!C104,'IP PITSS'!$B$9:$AD$93,24),0)+IFERROR(VLOOKUP('RESUMEN PITS'!C104,'IP PITSS'!$B$9:$AD$93,26),0)+IFERROR(VLOOKUP('RESUMEN PITS'!C104,'IP PITSS'!$B$9:$AD$93,28),0)+IFERROR(VLOOKUP('RESUMEN PITS'!C104,'IP PITSS'!$B$9:$AD$93,29),0)+IFERROR(VLOOKUP('RESUMEN PITS'!C104,'IP PITSS'!$B$9:$AD$93,9),0)*2% -> 4414.5349 | W104: =+M104-V104-S104 -> -1414.5349
A105: SEI0016 | B105: IP INNOVACION | C105: Negrete Bejar Aide Sarai | D105: =+VLOOKUP(C105,'IP PITSS'!$B$9:U172,20,0) -> 1314.8 | F105: =VLOOKUP(C105,'SIND PITS'!$C$9:$H$113,2,0) -> 207.63 | G105: =VLOOKUP(C105,'SIND PITS'!$C$9:$E$113,3,0) -> 3503.7 | H105: =VLOOKUP(C105,'SIND PITS'!$C$9:$F$113,4,0) -> 0 | I105: =VLOOKUP(C105,'SIND PITS'!$C$9:$G$113,5,0) -> 0 | K105: =SUM(D105:I105) -> 5026.13 | L105: 5000 | M105: =+L105/2 -> 2500 | O105: =+VLOOKUP(C105,'IP PITSS'!$B$9:I172,8,0) -> 0 | P105: =+G105+H105+I105 -> 3503.7 | Q105: =+(VLOOKUP(C105,'IP PITSS'!$B$9:L172,11,0))+VLOOKUP('RESUMEN PITS'!C105,'IP PITSS'!$B$9:M172,12,0)+VLOOKUP(C105,'IP PITSS'!$B$9:K172,10,0) -> 977.57 | R105: =VLOOKUP(C105,'IP PITSS'!$B$9:Q168,16,0) -> 0 | S105: =+VLOOKUP(C105,'EXTRAS Y FESTIVOS'!$B$9:J207,9,0) -> 0 | T105: =VLOOKUP(C105,'IP PITSS'!$B$9:R168,17,0) -> 0 | V105: =+K105-O105-P105+Q105+R105+T105+S105+IFERROR(VLOOKUP('RESUMEN PITS'!C105,'IP PITSS'!$B$9:$M$93,10),0)+IFERROR(VLOOKUP('RESUMEN PITS'!C105,'IP PITSS'!$B$9:$M$93,11),0)+IFERROR(VLOOKUP('RESUMEN PITS'!C105,'IP PITSS'!$B$9:$M$93,12),0)+VLOOKUP("Comision",'IP PITSS'!$I$99:$J$110,2)/COUNT($F$9:$F$111)+IFERROR(VLOOKUP('RESUMEN PITS'!C105,'IP PITSS'!$B$9:$AD$93,15),0)+IFERROR(VLOOKUP('RESUMEN PITS'!C105,'IP PITSS'!$B$9:$AD$93,21),0)+IFERROR(VLOOKUP('RESUMEN PITS'!C105,'IP PITSS'!$B$9:$AD$93,22),0)+IFERROR(VLOOKUP('RESUMEN PITS'!C105,'IP PITSS'!$B$9:$AD$93,23),0)+IFERROR(VLOOKUP('RESUMEN PITS'!C105,'IP PITSS'!$B$9:$AD$93,24),0)+IFERROR(VLOOKUP('RESUMEN PITS'!C105,'IP PITSS'!$B$9:$AD$93,26),0)+IFERROR(VLOOKUP('RESUMEN PITS'!C105,'IP PITSS'!$B$9:$AD$93,28),0)+IFERROR(VLOOKUP('RESUMEN PITS'!C105,'IP PITSS'!$B$9:$AD$93,29),0)+IFERROR(VLOOKUP('RESUMEN PITS'!C105,'IP PITSS'!$B$9:$AD$93,9),0)*2% -> 4001.4969 | W105: =+M105-V105-S105 -> -1501.4969
A106: SEI0549 | B106: IP INNOVACION | C106: Hinojosa Guerrero Alejandro | D106: =+VLOOKUP(C106,'IP PITSS'!$B$9:U173,20,0) -> 2975.4 | F106: =VLOOKUP(C106,'SIND PITS'!$C$9:$H$113,2,0) -> 174.6 | G106: =VLOOKUP(C106,'SIND PITS'!$C$9:$E$113,3,0) -> 0 | H106: =VLOOKUP(C106,'SIND PITS'!$C$9:$F$113,4,0) -> 0 | I106: =VLOOKUP(C106,'SIND PITS'!$C$9:$G$113,5,0) -> 0 | K106: =SUM(D106:I106) -> 3150 | L106: 6300 | M106: =+L106/2 -> 3150 | O106: =+VLOOKUP(C106,'IP PITSS'!$B$9:I173,8,0) -> 0 | P106: =+G106+H106+I106 -> 0 | Q106: =+(VLOOKUP(C106,'IP PITSS'!$B$9:L173,11,0))+VLOOKUP('RESUMEN PITS'!C106,'IP PITSS'!$B$9:M173,12,0)+VLOOKUP(C106,'IP PITSS'!$B$9:K173,10,0) -> 0 | R106: =VLOOKUP(C106,'IP PITSS'!$B$9:Q169,16,0) -> 0 | S106: =+VLOOKUP(C106,'EXTRAS Y FESTIVOS'!$B$9:J208,9,0) -> 0 | T106: =VLOOKUP(C106,'IP PITSS'!$B$9:R169,17,0) -> 0 | V106: =+K106-O106-P106+Q106+R106+T106+S106+IFERROR(VLOOKUP('RESUMEN PITS'!C106,'IP PITSS'!$B$9:$M$93,10),0)+IFERROR(VLOOKUP('RESUMEN PITS'!C106,'IP PITSS'!$B$9:$M$93,11),0)+IFERROR(VLOOKUP('RESUMEN PITS'!C106,'IP PITSS'!$B$9:$M$93,12),0)+VLOOKUP("Comision",'IP PITSS'!$I$99:$J$110,2)/COUNT($F$9:$F$111)+IFERROR(VLOOKUP('RESUMEN PITS'!C106,'IP PITSS'!$B$9:$AD$93,15),0)+IFERROR(VLOOKUP('RESUMEN PITS'!C106,'IP PITSS'!$B$9:$AD$93,21),0)+IFERROR(VLOOKUP('RESUMEN PITS'!C106,'IP PITSS'!$B$9:$AD$93,22),0)+IFERROR(VLOOKUP('RESUMEN PITS'!C106,'IP PITSS'!$B$9:$AD$93,23),0)+IFERROR(VLOOKUP('RESUMEN PITS'!C106,'IP PITSS'!$B$9:$AD$93,24),0)+IFERROR(VLOOKUP('RESUMEN PITS'!C106,'IP PITSS'!$B$9:$AD$93,26),0)+IFERROR(VLOOKUP('RESUMEN PITS'!C106,'IP PITSS'!$B$9:$AD$93,28),0)+IFERROR(VLOOKUP('RESUMEN PITS'!C106,'IP PITSS'!$B$9:$AD$93,29),0)+IFERROR(VLOOKUP('RESUMEN PITS'!C106,'IP PITSS'!$B$9:$AD$93,9),0)*2% -> 4564.5349 | W106: =+M106-V106-S106 -> -1414.5349
A107: SEI0550 | B107: IP INNOVACION | C107: Lopez Blanco Luis Eduardo | D107: =+VLOOKUP(C107,'IP PITSS'!$B$9:U174,20,0) -> 2975.6 | F107: =VLOOKUP(C107,'SIND PITS'!$C$9:$H$113,2,0) -> 174.4 | G107: =VLOOKUP(C107,'SIND PITS'!$C$9:$E$113,3,0) -> 0 | H107: =VLOOKUP(C107,'SIND PITS'!$C$9:$F$113,4,0) -> 0 | I107: =VLOOKUP(C107,'SIND PITS'!$C$9:$G$113,5,0) -> 0 | K107: =SUM(D107:I107) -> 3150 | L107: 6300 | M107: =+L107/2 -> 3150 | O107: =+VLOOKUP(C107,'IP PITSS'!$B$9:I174,8,0) -> 0 | P107: =+G107+H107+I107 -> 0 | Q107: =+(VLOOKUP(C107,'IP PITSS'!$B$9:L174,11,0))+VLOOKUP('RESUMEN PITS'!C107,'IP PITSS'!$B$9:M174,12,0)+VLOOKUP(C107,'IP PITSS'!$B$9:K174,10,0) -> 0 | R107: =VLOOKUP(C107,'IP PITSS'!$B$9:Q170,16,0) -> 0 | S107: =+VLOOKUP(C107,'EXTRAS Y FESTIVOS'!$B$9:J209,9,0) -> 0 | T107: =VLOOKUP(C107,'IP PITSS'!$B$9:R170,17,0) -> 0 | V107: =+K107-O107-P107+Q107+R107+T107+S107+IFERROR(VLOOKUP('RESUMEN PITS'!C107,'IP PITSS'!$B$9:$M$93,10),0)+IFERROR(VLOOKUP('RESUMEN PITS'!C107,'IP PITSS'!$B$9:$M$93,11),0)+IFERROR(VLOOKUP('RESUMEN PITS'!C107,'IP PITSS'!$B$9:$M$93,12),0)+VLOOKUP("Comision",'IP PITSS'!$I$99:$J$110,2)/COUNT($F$9:$F$111)+IFERROR(VLOOKUP('RESUMEN PITS'!C107,'IP PITSS'!$B$9:$AD$93,15),0)+IFERROR(VLOOKUP('RESUMEN PITS'!C107,'IP PITSS'!$B$9:$AD$93,21),0)+IFERROR(VLOOKUP('RESUMEN PITS'!C107,'IP PITSS'!$B$9:$AD$93,22),0)+IFERROR(VLOOKUP('RESUMEN PITS'!C107,'IP PITSS'!$B$9:$AD$93,23),0)+IFERROR(VLOOKUP('RESUMEN PITS'!C107,'IP PITSS'!$B$9:$AD$93,24),0)+IFERROR(VLOOKUP('RESUMEN PITS'!C107,'IP PITSS'!$B$9:$AD$93,26),0)+IFERROR(VLOOKUP('RESUMEN PITS'!C107,'IP PITSS'!$B$9:$AD$93,28),0)+IFERROR(VLOOKUP('RESUMEN PITS'!C107,'IP PITSS'!$B$9:$AD$93,29),0)+IFERROR(VLOOKUP('RESUMEN PITS'!C107,'IP PITSS'!$B$9:$AD$93,9),0)*2% -> 4564.5349 | W107: =+M107-V107-S107 -> -1414.5349
A108: SEI0551 | B108: IP INNOVACION | C108: Vallarta Fonseca Maria Esmeralda | D108: =+VLOOKUP(C108,'IP PITSS'!$B$9:U175,20,0) -> 2475.8 | F108: =VLOOKUP(C108,'SIND PITS'!$C$9:$H$113,2,0) -> 134.2 | G108: =VLOOKUP(C108,'SIND PITS'!$C$9:$E$113,3,0) -> 0 | H108: =VLOOKUP(C108,'SIND PITS'!$C$9:$F$113,4,0) -> 0 | I108: =VLOOKUP(C108,'SIND PITS'!$C$9:$G$113,5,0) -> 0 | K108: =SUM(D108:I108) -> 2610 | L108: 6000 | M108: =+L108/2 -> 3000 | O108: =+VLOOKUP(C108,'IP PITSS'!$B$9:I175,8,0) -> 0 | P108: =+G108+H108+I108 -> 0 | Q108: =+(VLOOKUP(C108,'IP PITSS'!$B$9:L175,11,0))+VLOOKUP('RESUMEN PITS'!C108,'IP PITSS'!$B$9:M175,12,0)+VLOOKUP(C108,'IP PITSS'!$B$9:K175,10,0) -> 0 | R108: =VLOOKUP(C108,'IP PITSS'!$B$9:Q171,16,0) -> 0 | S108: =+VLOOKUP(C108,'EXTRAS Y FESTIVOS'!$B$9:J210,9,0) -> 0 | T108: =VLOOKUP(C108,'IP PITSS'!$B$9:R171,17,0) -> 390 | V108: =+K108-O108-P108+Q108+R108+T108+S108+IFERROR(VLOOKUP('RESUMEN PITS'!C108,'IP PITSS'!$B$9:$M$93,10),0)+IFERROR(VLOOKUP('RESUMEN PITS'!C108,'IP PITSS'!$B$9:$M$93,11),0)+IFERROR(VLOOKUP('RESUMEN PITS'!C108,'IP PITSS'!$B$9:$M$93,12),0)+VLOOKUP("Comision",'IP PITSS'!$I$99:$J$110,2)/COUNT($F$9:$F$111)+IFERROR(VLOOKUP('RESUMEN PITS'!C108,'IP PITSS'!$B$9:$AD$93,15),0)+IFERROR(VLOOKUP('RESUMEN PITS'!C108,'IP PITSS'!$B$9:$AD$93,21),0)+IFERROR(VLOOKUP('RESUMEN PITS'!C108,'IP PITSS'!$B$9:$AD$93,22),0)+IFERROR(VLOOKUP('RESUMEN PITS'!C108,'IP PITSS'!$B$9:$AD$93,23),0)+IFERROR(VLOOKUP('RESUMEN PITS'!C108,'IP PITSS'!$B$9:$AD$93,24),0)+IFERROR(VLOOKUP('RESUMEN PITS'!C108,'IP PITSS'!$B$9:$AD$93,26),0)+IFERROR(VLOOKUP('RESUMEN PITS'!C108,'IP PITSS'!$B$9:$AD$93,28),0)+IFERROR(VLOOKUP('RESUMEN PITS'!C108,'IP PITSS'!$B$9:$AD$93,29),0)+IFERROR(VLOOKUP('RESUMEN PITS'!C108,'IP PITSS'!$B$9:$AD$93,9),0)*2% -> 3784.9959 | W108: =+M108-V108-S108 -> -784.99592
A109: SEI0552 | B109: IP INNOVACION | C109: Rubio Ventura Juan Eduardo | D109: =+VLOOKUP(C109,'IP PITSS'!$B$9:U176,20,0) -> 2692.6 | F109: =VLOOKUP(C109,'SIND PITS'!$C$9:$H$113,2,0) -> 107.4 | G109: =VLOOKUP(C109,'SIND PITS'!$C$9:$E$113,3,0) -> 0 | H109: =VLOOKUP(C109,'SIND PITS'!$C$9:$F$113,4,0) -> 0 | I109: =VLOOKUP(C109,'SIND PITS'!$C$9:$G$113,5,0) -> 0 | K109: =SUM(D109:I109) -> 2800 | L109: 6000 | M109: =+L109/2 -> 3000 | O109: =+VLOOKUP(C109,'IP PITSS'!$B$9:I176,8,0) -> 0 | P109: =+G109+H109+I109 -> 0 | Q109: =+(VLOOKUP(C109,'IP PITSS'!$B$9:L176,11,0))+VLOOKUP('RESUMEN PITS'!C109,'IP PITSS'!$B$9:M176,12,0)+VLOOKUP(C109,'IP PITSS'!$B$9:K176,10,0) -> 0 | R109: =VLOOKUP(C109,'IP PITSS'!$B$9:Q172,16,0) -> 0 | S109: =+VLOOKUP(C109,'EXTRAS Y FESTIVOS'!$B$9:J211,9,0) -> 200 | T109: =VLOOKUP(C109,'IP PITSS'!$B$9:R172,17,0) -> 0 | V109: =+K109-O109-P109+Q109+R109+T109+S109+IFERROR(VLOOKUP('RESUMEN PITS'!C109,'IP PITSS'!$B$9:$M$93,10),0)+IFERROR(VLOOKUP('RESUMEN PITS'!C109,'IP PITSS'!$B$9:$M$93,11),0)+IFERROR(VLOOKUP('RESUMEN PITS'!C109,'IP PITSS'!$B$9:$M$93,12),0)+VLOOKUP("Comision",'IP PITSS'!$I$99:$J$110,2)/COUNT($F$9:$F$111)+IFERROR(VLOOKUP('RESUMEN PITS'!C109,'IP PITSS'!$B$9:$AD$93,15),0)+IFERROR(VLOOKUP('RESUMEN PITS'!C109,'IP PITSS'!$B$9:$AD$93,21),0)+IFERROR(VLOOKUP('RESUMEN PITS'!C109,'IP PITSS'!$B$9:$AD$93,22),0)+IFERROR(VLOOKUP('RESUMEN PITS'!C109,'IP PITSS'!$B$9:$AD$93,23),0)+IFERROR(VLOOKUP('RESUMEN PITS'!C109,'IP PITSS'!$B$9:$AD$93,24),0)+IFERROR(VLOOKUP('RESUMEN PITS'!C109,'IP PITSS'!$B$9:$AD$93,26),0)+IFERROR(VLOOKUP('RESUMEN PITS'!C109,'IP PITSS'!$B$9:$AD$93,28),0)+IFERROR(VLOOKUP('RESUMEN PITS'!C109,'IP PITSS'!$B$9:$AD$93,29),0)+IFERROR(VLOOKUP('RESUMEN PITS'!C109,'IP PITSS'!$B$9:$AD$93,9),0)*2% -> 4252.9259 | W109: =+M109-V109-S109 -> -1452.9259 | X109: INGRESO 17/06/2019
A110: SEI0553 | B110: IP INNOVACION | C110: Navarro Vargas Alberto | D110: =+VLOOKUP(C110,'IP PITSS'!$B$9:U177,20,0) -> 2632 | F110: =VLOOKUP(C110,'SIND PITS'!$C$9:$H$113,2,0) -> 98 | G110: =VLOOKUP(C110,'SIND PITS'!$C$9:$E$113,3,0) -> 0 | H110: =VLOOKUP(C110,'SIND PITS'!$C$9:$F$113,4,0) -> 0 | I110: =VLOOKUP(C110,'SIND PITS'!$C$9:$G$113,5,0) -> 0 | K110: =SUM(D110:I110) -> 2730 | L110: 6300 | M110: =+L110/2 -> 3150 | O110: =+VLOOKUP(C110,'IP PITSS'!$B$9:I177,8,0) -> 0 | P110: =+G110+H110+I110 -> 0 | Q110: =+(VLOOKUP(C110,'IP PITSS'!$B$9:L177,11,0))+VLOOKUP('RESUMEN PITS'!C110,'IP PITSS'!$B$9:M177,12,0)+VLOOKUP(C110,'IP PITSS'!$B$9:K177,10,0) -> 0 | R110: =VLOOKUP(C110,'IP PITSS'!$B$9:Q173,16,0) -> 0 | S110: =+VLOOKUP(C110,'EXTRAS Y FESTIVOS'!$B$9:J212,9,0) -> 420 | T110: =VLOOKUP(C110,'IP PITSS'!$B$9:R173,17,0) -> 0 | V110: =+K110-O110-P110+Q110+R110+T110+S110+IFERROR(VLOOKUP('RESUMEN PITS'!C110,'IP PITSS'!$B$9:$M$93,10),0)+IFERROR(VLOOKUP('RESUMEN PITS'!C110,'IP PITSS'!$B$9:$M$93,11),0)+IFERROR(VLOOKUP('RESUMEN PITS'!C110,'IP PITSS'!$B$9:$M$93,12),0)+VLOOKUP("Comision",'IP PITSS'!$I$99:$J$110,2)/COUNT($F$9:$F$111)+IFERROR(VLOOKUP('RESUMEN PITS'!C110,'IP PITSS'!$B$9:$AD$93,15),0)+IFERROR(VLOOKUP('RESUMEN PITS'!C110,'IP PITSS'!$B$9:$AD$93,21),0)+IFERROR(VLOOKUP('RESUMEN PITS'!C110,'IP PITSS'!$B$9:$AD$93,22),0)+IFERROR(VLOOKUP('RESUMEN PITS'!C110,'IP PITSS'!$B$9:$AD$93,23),0)+IFERROR(VLOOKUP('RESUMEN PITS'!C110,'IP PITSS'!$B$9:$AD$93,24),0)+IFERROR(VLOOKUP('RESUMEN PITS'!C110,'IP PITSS'!$B$9:$AD$93,26),0)+IFERROR(VLOOKUP('RESUMEN PITS'!C110,'IP PITSS'!$B$9:$AD$93,28),0)+IFERROR(VLOOKUP('RESUMEN PITS'!C110,'IP PITSS'!$B$9:$AD$93,29),0)+IFERROR(VLOOKUP('RESUMEN PITS'!C110,'IP PITSS'!$B$9:$AD$93,9),0)*2% -> 4651.4969 | W110: =+M110-V110-S110 -> -1921.4969 | X110: INGRESO 18/06/2019
A111: SEI0554 | B111: IP INNOVACION | C111: Moreno Castillo Paulina Yamileth | D111: =+VLOOKUP(C111,'IP PITSS'!$B$9:U178,20,0) -> 1307 | F111: =VLOOKUP(C111,'SIND PITS'!$C$9:$H$113,2,0) -> 0 | G111: =VLOOKUP(C111,'SIND PITS'!$C$9:$E$113,3,0) -> 0 | H111: =VLOOKUP(C111,'SIND PITS'!$C$9:$F$113,4,0) -> 0 | I111: =VLOOKUP(C111,'SIND PITS'!$C$9:$G$113,5,0) -> 0 | K111: =SUM(D111:I111) -> 1307 | L111: 6000 | M111: =+L111/2 -> 3000 | O111: =+VLOOKUP(C111,'IP PITSS'!$B$9:I178,8,0) -> 0 | P111: =+G111+H111+I111 -> 0 | Q111: =+(VLOOKUP(C111,'IP PITSS'!$B$9:L178,11,0))+VLOOKUP('RESUMEN PITS'!C111,'IP PITSS'!$B$9:M178,12,0)+VLOOKUP(C111,'IP PITSS'!$B$9:K178,10,0) -> 0 | R111: =VLOOKUP(C111,'IP PITSS'!$B$9:Q174,16,0) -> 0 | S111: =+VLOOKUP(C111,'EXTRAS Y FESTIVOS'!$B$9:J213,9,0) -> 1800 | T111: =VLOOKUP(C111,'IP PITSS'!$B$9:R174,17,0) -> 0 | V111: =+K111-O111-P111+Q111+R111+T111+S111+IFERROR(VLOOKUP('RESUMEN PITS'!C111,'IP PITSS'!$B$9:$M$93,10),0)+IFERROR(VLOOKUP('RESUMEN PITS'!C111,'IP PITSS'!$B$9:$M$93,11),0)+IFERROR(VLOOKUP('RESUMEN PITS'!C111,'IP PITSS'!$B$9:$M$93,12),0)+VLOOKUP("Comision",'IP PITSS'!$I$99:$J$110,2)/COUNT($F$9:$F$111)+IFERROR(VLOOKUP('RESUMEN PITS'!C111,'IP PITSS'!$B$9:$AD$93,15),0)+IFERROR(VLOOKUP('RESUMEN PITS'!C111,'IP PITSS'!$B$9:$AD$93,21),0)+IFERROR(VLOOKUP('RESUMEN PITS'!C111,'IP PITSS'!$B$9:$AD$93,22),0)+IFERROR(VLOOKUP('RESUMEN PITS'!C111,'IP PITSS'!$B$9:$AD$93,23),0)+IFERROR(VLOOKUP('RESUMEN PITS'!C111,'IP PITSS'!$B$9:$AD$93,24),0)+IFERROR(VLOOKUP('RESUMEN PITS'!C111,'IP PITSS'!$B$9:$AD$93,26),0)+IFERROR(VLOOKUP('RESUMEN PITS'!C111,'IP PITSS'!$B$9:$AD$93,28),0)+IFERROR(VLOOKUP('RESUMEN PITS'!C111,'IP PITSS'!$B$9:$AD$93,29),0)+IFERROR(VLOOKUP('RESUMEN PITS'!C111,'IP PITSS'!$B$9:$AD$93,9),0)*2% -> 4608.4969 | W111: =+M111-V111-S111 -> -3408.4969 | X111: INGRESO 25/06/2019
D112: ============= | E112: ============= | F112: ============= | G112: ============= | H112: ============= | I112: ============= | J112: ============= | K112: ============= | L112: ============= | M112: ============= | N112: ============= | O112: ============= | P112: ============= | Q112: ============= | R112: ============= | S112: ============= | T112: ============= | U112: ============= | V112: =+K112-O112-P112+Q112+R112+T112+S112+IFERROR(VLOOKUP('RESUMEN PITS'!C112,'IP PITSS'!$B$9:$M$93,10),0)+IFERROR(VLOOKUP('RESUMEN PITS'!C112,'IP PITSS'!$B$9:$M$93,11),0)+IFERROR(VLOOKUP('RESUMEN PITS'!C112,'IP PITSS'!$B$9:$M$93,12),0)+VLOOKUP("Comision",'IP PITSS'!$I$99:$J$110,2)/COUNT($F$9:$F$111)+IFERROR(VLOOKUP('RESUMEN PITS'!C112,'IP PITSS'!$B$9:$AD$93,15),0)+IFERROR(VLOOKUP('RESUMEN PITS'!C112,'IP PITSS'!$B$9:$AD$93,21),0)+IFERROR(VLOOKUP('RESUMEN PITS'!C112,'IP PITSS'!$B$9:$AD$93,22),0)+IFERROR(VLOOKUP('RESUMEN PITS'!C112,'IP PITSS'!$B$9:$AD$93,23),0)+IFERROR(VLOOKUP('RESUMEN PITS'!C112,'IP PITSS'!$B$9:$AD$93,24),0)+IFERROR(VLOOKUP('RESUMEN PITS'!C112,'IP PITSS'!$B$9:$AD$93,26),0)+IFERROR(VLOOKUP('RESUMEN PITS'!C112,'IP PITSS'!$B$9:$AD$93,28),0)+IFERROR(VLOOKUP('RESUMEN PITS'!C112,'IP PITSS'!$B$9:$AD$93,29),0)+IFERROR(VLOOKUP('RESUMEN PITS'!C112,'IP PITSS'!$B$9:$AD$93,9),0)*2% -> #VALUE! | W112: ============= | X112: ============= | Y112: =============
C113: TOTAL GENERAL | D113: =SUBTOTAL(9,D9:D112) -> 314031 | E113: =SUBTOTAL(9,E9:E112) -> 0 | F113: =SUBTOTAL(9,F9:F112) -> 148780.36 | G113: =SUBTOTAL(9,G9:G112) -> 37014.2 | H113: =SUBTOTAL(9,H9:H112) -> 0 | I113: =SUBTOTAL(9,I9:I112) -> 1543.1399 | J113: =SUBTOTAL(9,J9:J112) -> 0 | K113: =SUBTOTAL(9,K9:K112) -> 501368.69 | ... U113: =SUBTOTAL(9,U9:U112) -> 0 | V113: =+K113-O113-P113+Q113+R113+T113+S113+IFERROR(VLOOKUP('RESUMEN PITS'!C113,'IP PITSS'!$B$9:$M$93,10),0)+IFERROR(VLOOKUP('RESUMEN PITS'!C113,'IP PITSS'!$B$9:$M$93,11),0)+IFERROR(VLOOKUP('RESUMEN PITS'!C113,'IP PITSS'!$B$9:$M$93,12),0)+VLOOKUP("Comision",'IP PITSS'!$I$99:$J$110,2)/COUNT($F$9:$F$111)+IFERROR(VLOOKUP('RESUMEN PITS'!C113,'IP PITSS'!$B$9:$AD$93,15),0)+IFERROR(VLOOKUP('RESUMEN PITS'!C113,'IP PITSS'!$B$9:$AD$93,21),0)+IFERROR(VLOOKUP('RESUMEN PITS'!C113,'IP PITSS'!$B$9:$AD$93,22),0)+IFERROR(VLOOKUP('RESUMEN PITS'!C113,'IP PITSS'!$B$9:$AD$93,23),0)+IFERROR(VLOOKUP('RESUMEN PITS'!C113,'IP PITSS'!$B$9:$AD$93,24),0)+IFERROR(VLOOKUP('RESUMEN PITS'!C113,'IP PITSS'!$B$9:$AD$93,26),0)+IFERROR(VLOOKUP('RESUMEN PITS'!C113,'IP PITSS'!$B$9:$AD$93,28),0)+IFERROR(VLOOKUP('RESUMEN PITS'!C113,'IP PITSS'!$B$9:$AD$93,29),0)+IFERROR(VLOOKUP('RESUMEN PITS'!C113,'IP PITSS'!$B$9:$AD$93,9),0)*2% -> 515257.5 | W113: =SUBTOTAL(9,W9:W112) -> -119417.79 | X113: =SUBTOTAL(9,X9:X112) -> 0 | Y113: =SUBTOTAL(9,Y9:Y112) -> 0
Q114: =+Q113-'IP PITSS'!K95-'IP PITSS'!L95-'IP PITSS'!M95-'CPD PITSS'!N28-'CPD PITSS'!O28 -> 0 | R114: =+R113-'IP PITSS'!Q95 -> 0 | T114: =+T113-'CPD PITSS'!S28-'IP PITSS'!R95 -> 0
F116: =+F104+D104+H116 -> 3000

Sheet FACTURACION
D8: TOTAL FACTURACION NOMINA | H8: TOTAL PROV AGUINALDOS
D9: TOTAL CPD | E9: =+'CPD PITSS'!M41 -> 112676.68 | H9: TOTAL CPD | I9: =+'CPD PITSS'!M53 -> 6065.6936
D10: TOTAL IP | E10: =+'IP PITSS'!J108 -> 401402.81 | H10: TOTAL IP | I10: =+'IP PITSS'!J120 -> 20145.807
D11: TOTAL SINDICATO | E11: =+'SIND PITS'!H122 -> 193000.42
E12: =+E9+E10+E11 -> 707079.91 | I12: =+I9+I10+I11 -> 26211.5
D14: PORCENTAJES POR EMPRESA | H14: PORCENTAJES POR EMPRESA
D15: EM 4% | E15: =+E12*4% -> 28283.197 | H15: EM 4% | I15: =+I12*4% -> 1048.46
D16: CPD 12% | E16: =+E12*12% -> 84849.59 | H16: CPD 12% | I16: =+I12*12% -> 3145.38
D17: IP 11% | E17: =+E12*11% -> 77778.791 | H17: IP 11% | I17: =+I12*11% -> 2883.265
D18: ITA 73% | E18: =+E12*73% -> 516168.34 | H18: ITA 73% | I18: =+I12*73% -> 19134.395
E19: =SUM(E15:E18) -> 707079.91 | I19: =SUM(I15:I18) -> 26211.5
G23: 0.73 | H23: 0.11 | I23: 0.12 | J23: 0.04
G24: ITA | H24: IP | I24: CPD | J24: EM
F25: ADMON | G25: ='CPD PITSS'!O47+'SIND PITS'!P117 -> 56607.915 | H25: ='CPD PITSS'!P47+'SIND PITS'!Q117 -> 8529.9598 | I25: ='CPD PITSS'!Q47+'SIND PITS'!R117 -> 9305.4107 | J25: ='CPD PITSS'!R47+'SIND PITS'!S117 -> 3101.8036
F26: SERVICIO | G26: ='CPD PITSS'!O48+'SIND PITS'!P118+'IP PITSS'!L116 -> 446279.83 | H26: ='CPD PITSS'!P48+'IP PITSS'!M116+'SIND PITS'!Q118 -> 67247.645 | I26: ='CPD PITSS'!Q48+'IP PITSS'!N116+'SIND PITS'!R118 -> 73361.067 | J26: ='CPD PITSS'!R48+'IP PITSS'!O116+'SIND PITS'!S118 -> 24453.689
F27: VENTAS | G27: ='IP PITSS'!L117+'SIND PITS'!P119 -> 5196.6583 | H27: ='IP PITSS'!M117+'SIND PITS'!Q119 -> 783.0581 | I27: ='IP PITSS'!N117+'SIND PITS'!R119 -> 854.2452 | J27: ='IP PITSS'!O117+'SIND PITS'!S119 -> 284.7484
F28: COMISIONES | G28: ='CPD PITSS'!O50+'IP PITSS'!L118+'SIND PITS'!P120 -> 8083.9373 | H28: ='CPD PITSS'!P50+'IP PITSS'!M118+'SIND PITS'!Q120 -> 1218.1275 | I28: ='CPD PITSS'!Q50+'IP PITSS'!N118+'SIND PITS'!R120 -> 1328.8664 | J28: ='CPD PITSS'!R50+'IP PITSS'!O118+'SIND PITS'!S120 -> 442.95547
F29: SUBTOTAL | G29: =SUM(G25:G28) -> 516168.34 | H29: =SUM(H25:H28) -> 77778.791 | I29: =SUM(I25:I28) -> 84849.59 | J29: =SUM(J25:J28) -> 28283.197 | K29: =SUM(G29:J29) -> 707079.91
F30: IVA | G30: =G29*16% -> 82586.934 | H30: =H29*16% -> 12444.606 | I30: =I29*16% -> 13575.934 | J30: =J29*16% -> 4525.3114 | K30: =SUM(G30:J30) -> 113132.79
F31: TOTAL | G31: =SUM(G29:G30) -> 598755.27 | H31: =SUM(H29:H30) -> 90223.397 | I31: =SUM(I29:I30) -> 98425.524 | J31: =SUM(J29:J30) -> 32808.508 | K31: =SUM(G31:J31) -> 820212.7

Sheet ASIMILADOS
A1: CONSULTORIA EN PROYECTOS DINAMICOS
A2: CALCULO DE PAGO POR ASIMILADOS Y/O COMISIONES
D6: QUINCENAL | E6: FACTURACION
A7: Nombre | B7: SUELDO MENSUAL | C7: IMSS | D7: Asimilados | E7: Comision 2% | F7: SUBTOTAL | G7: IVA | H7: TOTAL
A8: PABLO BENAVIDES HERRERA | B8: 70000 | C8: 2865.8 | D8: =(B8/2)-C8 -> 32134.2 | E8: =+D8*0.02 -> 642.684 | F8: =+D8+E8 -> 32776.884 | G8: =F8*0.16 -> 5244.3014 | H8: =+F8+G8 -> 38021.185 | I8: SE FACTURA A PITSS
A10: TOTALES | B10: =SUM(B8:B8) -> 70000 | C10: =SUM(C8:C8) -> 2865.8 | D10: =SUM(D8:D8) -> 32134.2 | E10: =SUM(E8:E8) -> 642.684 | F10: =SUM(F8:F8) -> 32776.884 | G10: =SUM(G8:G8) -> 5244.3014 | H10: =SUM(H8:H8) -> 38021.185
