Workbook

Sheet CPD PITSS
B2: CONSULTORIA EN PROYECTOS DINAMICOS S DE RL DE CV
B3: Lista de Raya (forma tabular)
B5: Reg Pat IMSS: Z2940859106
B6: RFC: CPD -150911-FA3
B7: 1 | C7: =+B7+1 -> 2 | D7: =+C7+1 -> 3 | E7: =+D7+1 -> 4 | F7: =+E7+1 -> 5 | G7: =+F7+1 -> 6 | H7: =+G7+1 -> 7 | I7: =+H7+1 -> 8 | J7: =+I7+1 -> 9 | ... V7: =+U7+1 -> 21
A8: Código | B8: Empleado | C8: Dias Laborados | D8: Dias Vacaciones | E8: Salario Diario | F8: Salario Diario Integrado | G8: Sueldo | H8: Vacaciones a tiempo | I8: Prima de vacaciones a tiempo | J8: Ayuda de Transporte | K8: Ayuda Alimentaria | L8: Ayuda de Renta | M8: *TOTAL* *PERCEPCIONES* | N8: Seguro de vivienda Infonavit | O8: Préstamo Infonavit (vsm) | P8: Subsidio al Empleo (sp) | Q8: I.S.R. (sp) | R8: I.M.S.S. | S8: Deduccion General | T8: Ajuste al neto | U8: *TOTAL* *DEDUCCIONES* | V8: *NETO* | W8: Invalidez y Vida | X8: Cesantia y Vejez | Y8: Enf. y Mat. Patron | Z8: 2% Fondo retiro SAR (8) | AA8: 2% Impuesto estatal | AB8: Riesgo de trabajo (9) | AC8: I.M.S.S. empresa | AD8: Infonavit empresa | AE8: Guarderia I.M.S.S. (7) | AF8: Banco | AG8: Aguinaldo
A10: SEI0009 | B10: Gutierrez Gutierrez Luis Arturo | C10: 15 | D10: 0 | E10: 141.67 | F10: 150.25 | G10: 2125.05 | H10: 0 | I10: 0 | J10: 212.51 | K10: 212.51 | L10: 212.51 | M10: 2762.58 | O10: 0 | P10: -65.5 | Q10: 0 | R10: 53.52 | S10: 0 | T10: 0.16 | U10: -11.82 | V10: 2774.4 | W10: 39.44 | X10: 70.99 | Y10: 297.98 | Z10: 183.93 | AA10: 55.25 | AB10: 11.27 | AC10: 408.41 | AD10: 112.69 | AE10: 161.39 | AF10: 110 | AG10: =((20/365.24)*15)*($E10*1.3) -> 151.27396
A11: SEI0026 | B11: Patricio Aguilar Jhonattan Cristian | C11: 15 | D11: 0 | E11: 150 | F11: 159.07 | G11: 2250 | H11: 0 | I11: 0 | J11: 225 | K11: 225 | L11: 225 | M11: 2925 | O11: 0 | P11: -43.57 | Q11: 0 | R11: 56.67 | S11: 0 | T11: 0.1 | U11: 13.2 | V11: 2911.8 | W11: 41.76 | X11: 75.16 | Y11: 300.29 | Z11: 186.57 | AA11: 58.5 | AB11: 11.93 | AC11: 417.21 | AD11: 119.31 | AE11: 162.71 | AF11: 110 | AG11: =((20/365.24)*15)*($E11*1.3) -> 160.16866
A12: SEI0040 | B12: Mora Ramirez Acal Aldo Isidro | C12: 12 | D12: 3 | E12: 216.67 | F12: 229.79 | G12: 2600.04 | H12: 650.01 | I12: 195 | J12: 325.01 | K12: 325.01 | L12: 325.01 | M12: 4420.08 | O12: 0 | P12: 0 | Q12: 107.17 | R12: 81.87 | S12: 0 | T12: 0.04 | U12: 189.08 | V12: 4231 | W12: 60.32 | X12: 108.58 | Y12: 318.86 | Z12: 207.79 | AA12: 88.4 | AB12: 17.23 | AC12: 487.76 | AD12: 172.34 | AE12: 173.32 | AF12: 110 | AG12: =((20/365.24)*15)*($E12*1.3) -> 231.35828
A13: SEI0041 | B13: Vazquez Perez Miguel Angel | C13: 15 | D13: 0 | E13: 283.33 | F13: 300.49 | G13: 4249.95 | H13: 0 | I13: 0 | J13: 425 | K13: 425 | L13: 425 | M13: 5524.95 | O13: 0 | P13: 0 | Q13: 341.06 | R13: 109.87 | S13: 0 | T13: 0.02 | U13: 450.95 | V13: 5074 | W13: 78.88 | X13: 141.98 | Y13: 345.18 | Z13: 229 | AA13: 110.5 | AB13: 22.54 | AC13: 566.04 | AD13: 225.37 | AE13: 183.92 | AF13: 110 | AG13: =((20/365.24)*15)*($E13*1.3) -> 302.53724
A14: SEI0088 | B14: Morgado Fernandez Martin | C14: 15 | D14: 0 | E14: 273.33 | F14: 289.87 | G14: 4099.95 | H14: 0 | I14: 0 | J14: 410 | K14: 410 | L14: 410 | M14: 5329.95 | O14: 0 | P14: 0 | Q14: 324.74 | R14: 105.46 | S14: 275.95 | T14: 0 | U14: 706.15 | V14: 4623.8 | W14: 76.09 | X14: 136.96 | Y14: 340.64 | Z14: 225.81 | AA14: 106.6 | AB14: 21.74 | AC14: 553.69 | AD14: 217.4 | AE14: 182.33 | AF14: 110 | AG14: =((20/365.24)*15)*($E14*1.3) -> 291.85933
A15: SEI0097 | B15: Arreola Jimenez Jose Nieves | C15: 15 | D15: 0 | E15: 185.83 | F15: 197.07 | G15: 2787.45 | H15: 0 | I15: 0 | J15: 278.75 | K15: 278.75 | L15: 278.75 | M15: 3623.7 | O15: 1541.78 | P15: 0 | Q15: 36.57 | R15: 70.22 | S15: 0 | T15: -0.07 | U15: 1648.5 | V15: 1975.2 | W15: 51.73 | X15: 93.12 | Y15: 310.27 | Z15: 197.97 | AA15: 72.47 | AB15: 14.78 | AC15: 455.12 | AD15: 147.8 | AE15: 168.41 | AF15: 110 | AG15: =((20/365.24)*15)*($E15*1.3) -> 198.42761
A16: SEI0099 | B16: Garcia Villicaña Ricardo Pascual | C16: 15 | D16: 0 | E16: 273.33 | F16: 289.87 | G16: 4099.95 | H16: 0 | I16: 0 | J16: 410 | K16: 410 | L16: 410 | M16: 5329.95 | O16: 0 | P16: 0 | Q16: 324.74 | R16: 105.46 | S16: 0 | T16: -0.05 | U16: 430.15 | V16: 4899.8 | W16: 76.09 | X16: 136.96 | Y16: 340.64 | Z16: 225.81 | AA16: 106.6 | AB16: 21.74 | AC16: 553.69 | AD16: 217.4 | AE16: 182.33 | AF16: 110 | AG16: =((20/365.24)*15)*($E16*1.3) -> 291.85933
A17: SEI0108 | B17: Caballero Diaz Francisco Javier | C17: 9 | D17: 6 | E17: 185.83 | F17: 197.07 | G17: 1672.47 | H17: 1114.98 | I17: 334.49 | J17: 278.75 | K17: 278.75 | L17: 278.75 | M17: 3958.19 | O17: 1789.38 | P17: 0 | Q17: 36.57 | R17: 70.22 | S17: 238.8 | T17: 0.02 | U17: 2134.99 | V17: 1823.2 | W17: 51.73 | X17: 93.12 | Y17: 310.27 | Z17: 197.97 | AA17: 79.16 | AB17: 14.78 | AC17: 455.12 | AD17: 147.8 | AE17: 168.41 | AF17: 110 | AG17: =((20/365.24)*15)*($E17*1.3) -> 198.42761
A18: SEI0116 | B18: Casillas Cardona Cesar Alejandro | C18: 13 | D18: 2 | E18: 220.83 | F18: 234.19 | G18: 2870.79 | H18: 441.66 | I18: 132.5 | J18: 331.25 | K18: 331.25 | L18: 331.25 | M18: 4438.7 | O18: 894.93 | P18: 0 | Q18: 113.96 | R18: 83.43 | S18: 0 | T18: -0.02 | U18: 1092.3 | V18: 3346.4 | W18: 61.47 | X18: 110.65 | Y18: 320.01 | Z18: 209.11 | AA18: 88.77 | AB18: 17.56 | AC18: 492.13 | AD18: 175.64 | AE18: 173.98 | AF18: 110 | AG18: =((20/365.24)*15)*($E18*1.3) -> 235.8003
A19: SEI0117 | B19: Mariscal Romero Luis Adrian | C19: 15 | D19: 0 | E19: 264.58 | F19: 276.54 | G19: 3968.7 | H19: 0 | I19: 0 | J19: 396.87 | K19: 396.87 | L19: 396.87 | M19: 5159.31 | O19: 1639.72 | P19: 0 | Q19: 310.46 | R19: 99.91 | S19: 0 | T19: 0.02 | U19: 2050.11 | V19: 3109.2 | W19: 72.59 | X19: 130.66 | Y19: 334.94 | Z19: 221.81 | AA19: 103.19 | AB19: 20.74 | AC19: 538.19 | AD19: 207.4 | AE19: 180.33 | AF19: 110 | AG19: =((20/365.24)*15)*($E19*1.3) -> 282.51615
A20: SEI0118 | B20: Arroyo Ramirez Hector Hugo | C20: 15 | D20: 0 | E20: 238.33 | F20: 252.75 | G20: 3574.95 | H20: 0 | I20: 0 | J20: 357.5 | K20: 357.5 | L20: 357.5 | M20: 4647.45 | O20: 1402.48 | P20: 0 | Q20: 160.25 | R20: 90.05 | S20: 255.4 | T20: -0.13 | U20: 1908.05 | V20: 2739.4 | W20: 66.35 | X20: 119.42 | Y20: 324.89 | Z20: 214.67 | AA20: 92.95 | AB20: 18.96 | AC20: 510.66 | AD20: 189.56 | AE20: 176.76 | AF20: 110 | AG20: =((20/365.24)*15)*($E20*1.3) -> 254.48664
A21: SEI0127 | B21: Hernandez Ochoa Eduardo | C21: 15 | D21: 0 | E21: 273.33 | F21: 289.87 | G21: 4099.95 | H21: 0 | I21: 0 | J21: 410 | K21: 410 | L21: 410 | M21: 5329.95 | O21: 0 | P21: 0 | Q21: 324.74 | R21: 105.46 | S21: 0 | T21: -0.05 | U21: 430.15 | V21: 4899.8 | W21: 76.09 | X21: 136.96 | Y21: 340.64 | Z21: 225.81 | AA21: 106.6 | AB21: 21.74 | AC21: 553.69 | AD21: 217.4 | AE21: 182.33 | AF21: 110 | AG21: =((20/365.24)*15)*($E21*1.3) -> 291.85933
... A27: SEI0442 | B27: Sierra Escamilla Daniela | C27: 15 | D27: 0 | E27: 216.67 | F27: 229.79 | G27: 3250.05 | H27: 0 | I27: 0 | J27: 325.01 | K27: 325.01 | L27: 325.01 | M27: 4225.08 | O27: 0 | P27: 0 | Q27: 107.17 | R27: 81.87 | S27: 0 | T27: -0.16 | U27: 188.88 | V27: 4036.2 | W27: 60.32 | X27: 108.58 | Y27: 318.86 | Z27: 207.79 | AA27: 84.5 | AB27: 17.23 | AC27: 487.76 | AD27: 172.34 | AE27: 173.32 | AF27: 110 | AG27: =((20/365.24)*15)*($E27*1.3) -> 231.35828
C28: ============= | D28: ============= | E28: ============= | F28: ============= | G28: ============= | H28: ============= | I28: ============= | J28: ============= | K28: ============= | L28: ============= | M28: ============= | N28: ============= | O28: ============= | P28: ============= | Q28: ============= | R28: ============= | S28: ============= | T28: ============= | U28: ============= | V28: ============= | W28: ============= | X28: ============= | Y28: ============= | Z28: ============= | AA28: ============= | AB28: ============= | AC28: ============= | AD28: ============= | AE28: ============= | AF28: ============= | AG28: =============
A29: Total Gral. | C29: =SUM(C10:C27) -> 252 | D29: =SUM(D10:D27) -> 18 | E29: =SUM(E10:E27) -> 4708.72 | F29: =SUM(F10:F27) -> 4989.65 | G29: =SUM(G10:G27) -> 67123.34 | H29: =SUM(H10:H27) -> 3507.46 | I29: =SUM(I10:I27) -> 1052.23 | J29: =SUM(J10:J27) -> 7063.16 | ... AG29: =SUM(AG10:AG27) -> 5027.929
A31: 18 | B31: Nomina
B32: Altas | L32: FACTURACION PITS | N32: VENTAS | O32: ADMINISTRACION | P32: SERVICIO
B33: Bajas | L33: Devengado Salario | M33: =+V29 -> 74070.2 | N33: =V23 -> 17386.8 | O33: =V27+V13+V12 -> 13341.2 | P33: =M33-O33-N33 -> 43342.2
A34: =+A31+A32-A33 -> 18 | B34: Total Nomina | L34: RETORNOS | M34: =+S29 -> 1067.15 | P34: =M34 -> 1067.15
L35: Infonavit | M35: =+N29+O29 -> 10869.77 | N35: 0 | O35: 0 | P35: =M35 -> 10869.77
L36: Prestamo Prospera | M36: 0
L37: Subtotal 1 | M37: =SUM(M33:M36) -> 86007.12 | N37: =SUM(N33:N36) -> 17386.8 | O37: =SUM(O33:O36) -> 13341.2 | P37: =SUM(P33:P36) -> 55279.12
L38: Comision | M38: =+M37*2% -> 1720.1424 | N38: =N37*2% -> 347.736 | O38: =O37*2% -> 266.824 | P38: =P37*2% -> 1105.5824
L39: Subtotal 2 | M39: =+M37+M38 -> 87727.262 | N39: =N38+N37 -> 17734.536 | O39: =O38+O37 -> 13608.024 | P39: =P38+P37 -> 56384.702
L40: Costo Patronal Imss | M40: =+R29+W29+X29+Y29+AB29+Z29+AD29+AE29 -> 23005.39 | N40: =R23+W23+X23+Y23+Z23+AB23+AD23+AE23 -> 3689.84 | O40: =R27+R13+R12+W12+W13+X12+X13+Y12+Y13+Z12+Z13+Z27+Y27+X27+W27+AB27+AD27+AE27+AB13+AB12+AD12+AD13+AE12+AE13 -> 3617.36 | P40: =M40-N40-O40 -> 15698.19
L41: 2% Sobre Nomina | M41: =+M29*2% -> 1857.4502 | N41: =M23*2% -> 413.724 | O41: =14170.11*2% -> 283.4022 | P41: =M41-O41-N41 -> 1160.324
L42: Importe de Factura | M42: =+M39+M40+M41 -> 112590.1 | N42: =N41+N40+N39 -> 21838.1 | O42: =O41+O40+O39 -> 17508.786 | P42: =P41+P40+P39 -> 73243.216
L43: IVA | M43: =+M42*16% -> 18014.416 | N43: =N42*0.16 -> 3494.096 | O43: =O42*0.16 -> 2801.4058 | P43: =P42*0.16 -> 11718.915
L44: TOTAL | M44: =+M42+M43 -> 130604.52 | N44: =N43+N42 -> 25332.196 | O44: =O43+O42 -> 20310.192 | P44: =P43+P42 -> 84962.131
N45: =N42-N38 -> 21490.364 | O45: =O42-O38 -> 17241.962 | P45: =P42-P38 -> 72137.634
L46: PROVISION AGUINALDO | P46: 0.73 | Q46: 0.11 | R46: 0.12 | S46: 0.04
L47: FACTURACION PITS | P47: ITA | Q47: IP | R47: CPD | S47: EM
L48: Subtotal 1 | M48: =+AG29 -> 5027.929 | O48: SERVICIO | P48: =P45*$P$46 -> 52660.473 | Q48: =P45*$Q$46 -> 7935.1397 | R48: =P45*$R$46 -> 8656.5161 | S48: =P45*$S$46 -> 2885.5054
L49: Comision | M49: =+M48*2% -> 100.55858 | O49: ADMINISTRACION | P49: =O45*$P$46 -> 12586.632 | Q49: =O45*$Q$46 -> 1896.6158 | R49: =O45*$R$46 -> 2069.0355 | S49: =O45*$S$46 -> 689.67849
L50: Subtotal 2 | M50: =+M48+M49 -> 5128.4876 | O50: VENTAS | P50: =N45*$P$46 -> 15687.966 | Q50: =N45*$Q$46 -> 2363.94 | R50: =N45*$R$46 -> 2578.8437 | S50: =N45*$S$46 -> 859.61456
L51: 2% Sobre Nomina | M51: =+M48*2% -> 100.55858 | O51: COMISION | P51: =M38*$P$46 -> 1255.704 | Q51: =M38*$Q$46 -> 189.21566 | R51: =M38*$R$46 -> 206.41709 | S51: =M38*$S$46 -> 68.805696
L52: Importe de Factura | M52: =+M50+M51 -> 5229.0462 | O52: SUBTOTAL | P52: =SUM(P48:P51) -> 82190.775 | Q52: =SUM(Q48:Q51) -> 12384.911 | R52: =SUM(R48:R51) -> 13510.812 | S52: =SUM(S48:S51) -> 4503.6041
L53: IVA | M53: =+M52*16% -> 836.64739 | O53: IVA | P53: =P52*16% -> 13150.524 | Q53: =Q52*16% -> 1981.5858 | R53: =R52*16% -> 2161.73 | S53: =S52*16% -> 720.57666
L54: TOTAL | M54: =+M52+M53 -> 6065.6936 | O54: TOTAL | P54: =P53+P52 -> 95341.299 | Q54: =Q53+Q52 -> 14366.497 | R54: =R53+R52 -> 15672.542 | S54: =S53+S52 -> 5224.1808

Sheet IP PITSS
B2: IP INNOVACION EN PROYECTOS S DE RL DE CV
B3: Lista de Raya (forma tabular)
B5: Reg Pat IMSS: R1363592103
B6: RFC: IIP -150923-DT7
A8: Código | B8: Empleado | C8: Dias Laborados | D8: Dias Vacaciones | E8: Salario Diario | F8: Salario Diario Integrado | G8: Sueldo | H8: Vacaciones a tiempo | I8: Prima de vacaciones a tiempo | J8: *TOTAL* *PERCEPCIONES* | K8: Seguro de vivienda Infonavit | L8: Préstamo Infonavit (vsm) | M8: Préstamo Infonavit (cf) | N8: Subsidio al Empleo (sp) | O8: I.S.R. (sp) | P8: I.M.S.S. | Q8: Préstamo FONACOT | R8: Deduccion general | S8: Ajuste al neto | T8: *TOTAL* *DEDUCCIONES* | U8: *NETO* | V8: Invalidez y Vida | W8: Cesantia y Vejez | X8: Enf. y Mat. Patron | Y8: 2% Fondo retiro SAR (8) | Z8: 2% Impuesto estatal | AA8: Riesgo de trabajo (9) | AB8: I.M.S.S. empresa | AC8: Infonavit empresa | AD8: Guarderia I.M.S.S. (7) | AE8: Banco | AF8: Aguinaldo
A10: SEI0010 | B10: Torres Ricardez Alfredo | C10: 15 | D10: 0 | E10: 266.67 | F10: 278.72 | G10: 4000.05 | H10: 0 | I10: 0 | J10: 4000.05 | L10: 0 | M10: 0 | N10: 0 | O10: 313.87 | P10: 100.81 | Q10: 0 | R10: 0 | S10: -0.03 | T10: 414.65 | U10: 3585.4 | V10: 73.16 | W10: 131.7 | X10: 335.88 | Y10: 273.62 | Z10: 80 | AA10: 33.3 | AB10: 540.74 | AC10: 209.04 | AD10: 231.81 | AE10: 110 | AF10: =((20/365.24)*15)*E10 -> 219.0368
A11: SEI0014 | B11: Montoya Portillo Carlos Alberto | C11: 15 | D11: 0 | E11: 266.67 | F11: 278.72 | G11: 4000.05 | H11: 0 | I11: 0 | J11: 4000.05 | L11: 0 | M11: 0 | N11: 0 | O11: 313.87 | P11: 100.81 | Q11: 0 | R11: 0 | S11: 0.17 | T11: 414.85 | U11: 3585.2 | V11: 73.16 | W11: 131.7 | X11: 335.88 | Y11: 273.62 | Z11: 80 | AA11: 33.3 | AB11: 540.74 | AC11: 209.04 | AD11: 231.81 | AE11: 110 | AF11: =((20/365.24)*15)*E11 -> 219.0368
A12: SEI0015 | B12: Cota Jaramillo Miguel Angel | C12: 15 | D12: 0 | E12: 200 | F12: 209.04 | G12: 3000 | H12: 0 | I12: 0 | J12: 3000 | L12: 0 | M12: 0 | N12: 0 | O12: 59.69 | P12: 74.48 | Q12: 0 | R12: 0 | S12: -0.17 | T12: 134 | U12: 2866 | V12: 54.87 | W12: 98.77 | X12: 313.41 | Y12: 252.71 | Z12: 60 | AA12: 24.98 | AB12: 467.05 | AC12: 156.78 | AD12: 221.36 | AE12: 110 | AF12: =((20/365.24)*15)*E12 -> 164.27554
A13: SEI0016 | B13: Negrete Bejar Aide Sarai | C13: 15 | D13: 0 | E13: 154 | F13: 160.96 | G13: 2310 | H13: 0 | I13: 0 | J13: 2310 | L13: 977.57 | M13: 0 | N13: -39.73 | O13: 0 | P13: 57.34 | Q13: 0 | R13: 0 | S13: 0.02 | T13: 995.2 | U13: 1314.8 | V13: 42.25 | W13: 76.05 | X13: 300.79 | Y13: 238.29 | Z13: 46.2 | AA13: 19.23 | AB13: 419.09 | AC13: 120.72 | AD13: 214.14 | AE13: 110 | AF13: =((20/365.24)*15)*E13 -> 126.49217
A14: SEI0017 | B14: Muñoz Reyes Luis Eduardo | C14: 15 | D14: 0 | E14: 266.67 | F14: 278.72 | G14: 4000.05 | H14: 0 | I14: 0 | J14: 4000.05 | L14: 868.44 | M14: 0 | N14: 0 | O14: 313.87 | P14: 100.81 | Q14: 0 | R14: 0 | S14: 0.13 | T14: 1283.25 | U14: 2716.8 | V14: 73.16 | W14: 131.7 | X14: 335.88 | Y14: 273.62 | Z14: 80 | AA14: 33.3 | AB14: 540.74 | AC14: 209.04 | AD14: 231.81 | AE14: 110 | AF14: =((20/365.24)*15)*E14 -> 219.0368
A15: SEI0019 | B15: Gonzalez Rasgado Miguel Isaias | C15: 15 | D15: 0 | E15: 521.68 | F15: 553.24 | G15: 7825.2 | H15: 0 | I15: 0 | J15: 7825.2 | L15: 0 | M15: 0 | N15: 0 | O15: 1033.24 | P15: 215.09 | Q15: 0 | R15: 0 | S15: 0.07 | T15: 1248.4 | U15: 6576.8 | V15: 145.23 | W15: 261.41 | X15: 453.23 | Y15: 355.97 | Z15: 156.5 | AA15: 66.11 | AB15: 859.87 | AC15: 414.93 | AD15: 272.99 | AE15: 110 | AF15: =((20/365.24)*15)*E15 -> 428.49633
A16: SEI0020 | B16: Mar Marquez Cesar Eduardo | C16: 15 | D16: 0 | E16: 266.67 | F16: 278.72 | G16: 4000.05 | H16: 0 | I16: 0 | J16: 4000.05 | L16: 0 | M16: 0 | N16: 0 | O16: 313.87 | P16: 100.81 | Q16: 0 | R16: 0 | S16: -0.03 | T16: 414.65 | U16: 3585.4 | V16: 73.16 | W16: 131.7 | X16: 335.88 | Y16: 273.62 | Z16: 80 | AA16: 33.3 | AB16: 540.74 | AC16: 209.04 | AD16: 231.81 | AE16: 110 | AF16: =((20/365.24)*15)*E16 -> 219.0368
A17: SEI0021 | B17: Velez Rodriguez Jaime | C17: 15 | D17: 0 | E17: 200 | F17: 212.1 | G17: 3000 | H17: 0 | I17: 0 | J17: 3000 | L17: 1347.1 | M17: 0 | N17: 0 | O17: 59.69 | P17: 75.55 | Q17: 0 | R17: 0 | S17: 0.06 | T17: 1482.4 | U17: 1517.6 | V17: 55.68 | W17: 100.22 | X17: 314.22 | Y17: 253.63 | Z17: 60 | AA17: 25.34 | AB17: 470.12 | AC17: 159.08 | AD17: 221.82 | AE17: 110 | AF17: =((20/365.24)*15)*E17 -> 164.27554
A18: SEI0022 | B18: Najera Lopez Raul | C18: 15 | D18: 0 | E18: 333.33 | F18: 353.5 | G18: 4999.95 | H18: 0 | I18: 0 | J18: 4999.95 | L18: 0 | M18: 0 | N18: 0 | O18: 461.63 | P18: 131.93 | Q18: 0 | R18: 0 | S18: -0.01 | T18: 593.55 | U18: 4406.4 | V18: 92.79 | W18: 167.03 | X18: 367.84 | Y18: 296.05 | Z18: 100 | AA18: 42.24 | AB18: 627.66 | AC18: 265.12 | AD18: 243.02 | AE18: 110 | AF18: =((20/365.24)*15)*E18 -> 273.78984
A19: SEI0023 | B19: Puente Murguia Luis Felipe | C19: 15 | D19: 0 | E19: 233.33 | F19: 247.45 | G19: 3499.95 | H19: 0 | I19: 0 | J19: 3499.95 | L19: 0 | M19: 0 | N19: 0 | O19: 134.36 | P19: 88.16 | Q19: 0 | R19: 0 | S19: 0.03 | T19: 222.55 | U19: 3277.4 | V19: 64.95 | W19: 116.92 | X19: 323.49 | Y19: 264.23 | Z19: 70 | AA19: 29.57 | AB19: 505.36 | AC19: 185.58 | AD19: 227.12 | AE19: 110 | AF19: =((20/365.24)*15)*E19 -> 191.65206
A20: SEI0029 | B20: Arceo Garcia Manuel Federico | C20: 13 | D20: 1 | E20: 200 | F20: 212.1 | G20: 2600 | H20: 200 | I20: 60 | J20: 2860 | L20: 0 | M20: 0 | N20: 0 | O20: 37.93 | P20: 71.85 | Q20: 600 | R20: 0 | S20: 0.02 | T20: 709.8 | U20: 2150.2 | V20: 55.68 | W20: 100.22 | X20: 314.22 | Y20: 253.63 | Z20: 57.2 | AA20: 25.34 | AB20: 470.12 | AC20: 159.08 | AD20: 221.82 | AE20: 110 | AF20: =((20/365.24)*15)*E20 -> 164.27554
A21: SEI0364 | B21: Dominguez Lopez Mayeli Del Pilar | C21: 15 | D21: 0 | E21: 266.67 | F21: 282.81 | G21: 4000.05 | H21: 0 | I21: 0 | J21: 4000.05 | L21: 0 | M21: 0 | N21: 0 | O21: 313.87 | P21: 102.51 | Q21: 0 | R21: 1666.67 | S21: 0 | T21: 2083.05 | U21: 1917 | V21: 74.24 | W21: 133.63 | X21: 337.62 | Y21: 274.84 | Z21: 80 | AA21: 33.79 | AB21: 545.49 | AC21: 212.11 | AD21: 232.42 | AE21: 110 | AF21: =((20/365.24)*15)*E21 -> 219.0368
... A91: SEI479 | B91: Cruz Perez Alejandro Nezahualcoyotl | C91: 15 | D91: 0 | E91: 266.67 | F91: 282.81 | G91: 4000.05 | H91: 0 | I91: 0 | J91: 4000.05 | L91: 0 | M91: 0 | N91: 0 | O91: 313.87 | P91: 102.51 | Q91: 0 | R91: 0 | S91: 0.07 | T91: 416.45 | U91: 3583.6 | V91: 74.24 | W91: 133.63 | X91: 337.62 | Y91: 274.84 | Z91: 80 | AA91: 33.79 | AB91: 545.49 | AC91: 212.11 | AD91: 232.42 | AE91: 110 | AF91: =((20/365.24)*15)*E91 -> 219.0368
C92: ============= | D92: ============= | E92: ============= | F92: ============= | G92: ============= | H92: ============= | I92: ============= | J92: ============= | K92: ============= | L92: ============= | M92: ============= | N92: ============= | O92: ============= | P92: ============= | Q92: ============= | R92: ============= | S92: ============= | T92: ============= | U92: ============= | V92: ============= | W92: ============= | X92: ============= | Y92: ============= | Z92: ============= | AA92: ============= | AB92: ============= | AC92: ============= | AD92: ============= | AE92: ============= | AF92: =============
A93: Total Gral. | C93: =SUM(C10:C91) -> 1222 | D93: =SUM(D10:D91) -> 7 | E93: =SUM(E10:E91) -> 19720.61 | F93: =SUM(F10:F91) -> 20791.33 | G93: =SUM(G10:G91) -> 293892.73 | H93: =SUM(H10:H91) -> 1716.52 | I93: =SUM(I10:I91) -> 514.96 | J93: =SUM(J10:J91) -> 296124.21 | ... AF93: =SUM(AF10:AF91) -> 16198.07
A95: 83 | B95: Nomina
A96: 0 | B96: Altas | I96: FACTURACION PITS | K96: VENTAS | L96: ADMINISTRACION | M96: SERVICIO
A97: 1 | B97: Bajas | I97: Devengado Salario | J97: =+U93 -> 232670.6 | K97: =U13 -> 1314.8 | L97: 0 | M97: =J97-L97-K97 -> 231355.8
A98: =+A95+A96-A97 -> 82 | B98: Total Nomina | I98: RETORNOS | J98: =+R93-R77 -> 4900.61 | M98: =J98 -> 4900.61
I99: Infonavit | J99: =+K93+L93+M93 -> 32692.87 | K99: =L13 -> 977.57 | L99: 0 | M99: =J99-K99 -> 31715.3
I100: Prestamo Prospera | J100: =+Q93 -> 1236.6 | M100: =J100 -> 1236.6
I101: Subtotal 1 | J101: =SUM(J97:J100) -> 271500.68 | K101: =SUM(K97:K100) -> 2292.37 | L101: =SUM(L97:L100) -> 0 | M101: =SUM(M97:M100) -> 269208.31
I102: Comision | J102: =+J101*2% -> 5430.0136 | K102: =K101*2% -> 45.8474 | L102: =L101*2% -> 0 | M102: =M101*2% -> 5384.1662
I103: Subtotal 2 | J103: =+J101+J102 -> 276930.69 | K103: =K102+K101 -> 2338.2174 | L103: =L102+L101 -> 0 | M103: =M102+M101 -> 274592.48
I104: Costo Patronal Imss | J104: =+P93+V93+W93+X93+Y93+AA93+AC93+AD93 -> 108425.64 | K104: =P13+V13+W13+X13+Y13+AA13+AC13+AD13 -> 1068.81 | L104: 0 | M104: =J104-K104-L104 -> 107356.83
I105: 2% Sobre Nomina | J105: =+J93*2% -> 5922.4842 | K105: =J13*2% -> 46.2 | L105: 0 | M105: =J105-L105-K105 -> 5876.2842
I106: Importe de Factura | J106: =+J103+J104+J105 -> 391278.82 | K106: =K105+K104+K103 -> 3453.2274 | L106: 0 | M106: =M105+M104+M103 -> 387825.59
I107: IVA | J107: =+J106*16% -> 62604.611 | K107: =K106*0.16 -> 552.51638 | L107: =L106*0.16 -> 0 | M107: =M106*0.16 -> 62052.094
I108: TOTAL | J108: =+J106+J107 -> 453883.43 | K108: =K107+K106 -> 4005.7438 | L108: =L107+L106 -> 0 | M108: =M107+M106 -> 449877.68
K109: =K106-K102 -> 3407.38 | L109: =L106-L102 -> 0 | M109: =M106-M102 -> 382441.42
I110: PROVISION AGUINALDO
I111: FACTURACION PITS
I112: Subtotal 1 | J112: =+AF93 -> 16198.07 | L112: 0.73 | M112: 0.11 | N112: 0.12 | O112: 0.04
I113: Comision | J113: =+J112*2% -> 323.9614 | L113: ITA | M113: IP | N113: CPD | O113: EM
I114: Subtotal 2 | J114: =+J112+J113 -> 16522.031 | K114: SERVICIO | L114: =M109*$L$112 -> 279182.24 | M114: =M109*$M$112 -> 42068.557 | N114: =M109*$N$112 -> 45892.971 | O114: =M109*$O$112 -> 15297.657
I115: 2% Sobre Nomina | J115: =+J112*2% -> 323.9614 | K115: ADMINISTRACION | L115: =K111*$P$46 -> 0 | M115: =K111*$Q$46 -> 0 | N115: =K111*$R$46 -> 0 | O115: =K111*$S$46 -> 0
I116: Importe de Factura | J116: =+J114+J115 -> 16845.993 | K116: VENTAS | L116: =K109*$L$112 -> 2487.3874 | M116: =K109*$M$112 -> 374.8118 | N116: =K109*$N$112 -> 408.8856 | O116: =K109*$O$112 -> 136.2952
I117: IVA | J117: =+J116*16% -> 2695.3588 | K117: COMISION | L117: =J102*$L$112 -> 3963.9099 | M117: =J102*$M$112 -> 597.3015 | N117: =J102*$N$112 -> 651.60163 | O117: =J102*$O$112 -> 217.20054
I118: TOTAL | J118: =+J116+J117 -> 19541.351 | K118: SUBTOTAL | L118: =SUM(L114:L117) -> 285633.54 | M118: =SUM(M114:M117) -> 43040.67 | N118: =SUM(N114:N117) -> 46953.458 | O118: =SUM(O114:O117) -> 15651.153
K119: IVA | L119: =L118*16% -> 45701.366 | M119: =M118*16% -> 6886.5072 | N119: =N118*16% -> 7512.5533 | O119: =O118*16% -> 2504.1844
K120: TOTAL | L120: =L119+L118 -> 331334.9 | M120: =M119+M118 -> 49927.177 | N120: =N119+N118 -> 54466.011 | O120: =O119+O118 -> 18155.337

Sheet SIND PITS
D1: SINDICATO | J1: PRIMA VACACIONAL
A2: CLAVE | B2: EMPRESA | C2: NOMBRE | D2: SUELDO SINDICATO | E2: BONO | F2: COMISION | G2: prima vacaciones | H2: TOTAL | J2: DIAS DE VACACIONES | K2: SUELDO NETO MENSUAL | L2: MONTO PRIMA TOTAL | M2: MENOS PRIMA IMSS | N2: PRIMA A PAGAR SINDICATO
A3: SEI0097 | B3: CONSULTORIA | C3: Arreola Jimenez Jose Nieves | D3: 1558.02 | E3: 420 | F3: 0 | G3: =+N3 -> 0 | H3: =SUM(D3:G3) -> 1978.02 | J3: =VLOOKUP($C3,'CPD PITSS'!$B$10:$V$27,3,0) -> 0 | K3: 10150 | L3: =(((+K3/30)*J3)*30%) -> 0 | M3: =VLOOKUP($C3,'CPD PITSS'!$B$10:$V$27,8,0) -> 0 | N3: =+L3-M3 -> 0 | O3: SEI0097 | P3: =VLOOKUP(C3,'RESUMEN PITS'!$C$3:$V$102,20,0) -> -56.562642 | Q3: =+D3+P3 -> 1501.4574
A4: SEI0118 | B4: CONSULTORIA | C4: Arroyo Ramirez Hector Hugo | D4: 2102.72 | F4: 0 | G4: =+N4 -> 0 | H4: =SUM(D4:G4) -> 2102.72 | J4: =VLOOKUP($C4,'CPD PITSS'!$B$10:$V$27,3,0) -> 0 | K4: 13000 | L4: =(((+K4/30)*J4)*30%) -> 0 | M4: =VLOOKUP($C4,'CPD PITSS'!$B$10:$V$27,8,0) -> 0 | N4: =+L4-M4 -> 0 | O4: SEI0118 | P4: =VLOOKUP(C4,'RESUMEN PITS'!$C$3:$V$102,20,0) -> -56.562642 | Q4: =+D4+P4 -> 2046.1574
A5: SEI0377 | B5: CONSULTORIA | C5: Benavides Herrera Alejandra | D5: 16803.4 | F5: 0 | G5: =+N5 -> 0 | H5: =SUM(D5:G5) -> 16803.4 | J5: =VLOOKUP($C5,'CPD PITSS'!$B$10:$V$27,3,0) -> 0 | K5: 40000 | L5: =(((+K5/30)*J5)*30%) -> 0 | M5: =VLOOKUP($C5,'CPD PITSS'!$B$10:$V$27,8,0) -> 0 | N5: =+L5-M5 -> 0 | O5: SEI0377 | P5: =VLOOKUP(C5,'RESUMEN PITS'!$C$3:$V$102,20,0) -> -56.562642 | Q5: =+D5+P5 -> 16746.837
A6: SEI0108 | B6: CONSULTORIA | C6: Caballero Diaz Francisco Javier | D6: 1558.11 | E6: 210 | F6: 0 | G6: =+N6 -> 274.51 | H6: =SUM(D6:G6) -> 2042.62 | J6: =VLOOKUP($C6,'CPD PITSS'!$B$10:$V$27,3,0) -> 6 | K6: 10150 | L6: =(((+K6/30)*J6)*30%) -> 609 | M6: =VLOOKUP($C6,'CPD PITSS'!$B$10:$V$27,8,0) -> 334.49 | N6: =+L6-M6 -> 274.51 | O6: SEI0108 | P6: =VLOOKUP(C6,'RESUMEN PITS'!$C$3:$V$102,20,0) -> -56.562642 | Q6: =+D6+P6 -> 1501.5474
A7: SEI0425 | B7: CONSULTORIA | C7: Carbajal Cabuto Jose Luis | D7: 1608.06 | E7: 210 | F7: 0 | G7: =+N7 -> 280.51 | H7: =SUM(D7:G7) -> 2098.57 | J7: =VLOOKUP($C7,'CPD PITSS'!$B$10:$V$27,3,0) -> 6 | K7: 10250 | L7: =(((+K7/30)*J7)*30%) -> 615 | M7: =VLOOKUP($C7,'CPD PITSS'!$B$10:$V$27,8,0) -> 334.49 | N7: =+L7-M7 -> 280.51 | O7: SEI0453 | P7: =VLOOKUP(C7,'RESUMEN PITS'!$C$3:$V$102,20,0) -> -56.562642 | Q7: =+D7+P7 -> 1551.4974
A8: SEI0116 | B8: CONSULTORIA | C8: Casillas Cardona Cesar Alejandro | D8: 1891.17 | F8: 0 | G8: =+N8 -> 107.5 | H8: =SUM(D8:G8) -> 1998.67 | J8: =VLOOKUP($C8,'CPD PITSS'!$B$10:$V$27,3,0) -> 2 | K8: 12000 | L8: =(((+K8/30)*J8)*30%) -> 240 | M8: =VLOOKUP($C8,'CPD PITSS'!$B$10:$V$27,8,0) -> 132.5 | N8: =+L8-M8 -> 107.5 | O8: SEI0116 | P8: =VLOOKUP(C8,'RESUMEN PITS'!$C$3:$V$102,20,0) -> -56.562642 | Q8: =+D8+P8 -> 1834.6074
A9: SEI0401 | B9: CONSULTORIA | C9: De La Torre Zambara Francisco Ernesto | D9: 1557.95 | E9: 60 | F9: 0 | G9: =+N9 -> 45.75 | H9: =SUM(D9:G9) -> 1663.7 | J9: =VLOOKUP($C9,'CPD PITSS'!$B$10:$V$27,3,0) -> 1 | K9: 10150 | L9: =(((+K9/30)*J9)*30%) -> 101.5 | M9: =VLOOKUP($C9,'CPD PITSS'!$B$10:$V$27,8,0) -> 55.75 | N9: =+L9-M9 -> 45.75 | O9: SEI0401 | P9: =VLOOKUP(C9,'RESUMEN PITS'!$C$3:$V$102,20,0) -> -56.562642 | Q9: =+D9+P9 -> 1501.3874
A10: SEI0099 | B10: CONSULTORIA | C10: Garcia Villicaña Ricardo Pascual | D10: 2600.2 | F10: 0 | G10: =+N10 -> 0 | H10: =SUM(D10:G10) -> 2600.2 | J10: =VLOOKUP($C10,'CPD PITSS'!$B$10:$V$27,3,0) -> 0 | K10: 15000 | L10: =(((+K10/30)*J10)*30%) -> 0 | M10: =VLOOKUP($C10,'CPD PITSS'!$B$10:$V$27,8,0) -> 0 | N10: =+L10-M10 -> 0 | O10: SEI0099 | P10: =VLOOKUP(C10,'RESUMEN PITS'!$C$3:$V$102,20,0) -> -1417.0416 | Q10: =+D10+P10 -> 1183.1584
A11: SEI0009 | B11: CONSULTORIA | C11: Gutierrez Gutierrez Luis Arturo | D11: 1475.6 | F11: 0 | G11: =+N11 -> 0 | H11: =SUM(D11:G11) -> 1475.6 | J11: =VLOOKUP($C11,'CPD PITSS'!$B$10:$V$27,3,0) -> 0 | K11: 8500 | L11: =(((+K11/30)*J11)*30%) -> 0 | M11: =VLOOKUP($C11,'CPD PITSS'!$B$10:$V$27,8,0) -> 0 | N11: =+L11-M11 -> 0 | O11: SEI0009 | P11: =VLOOKUP(C11,'RESUMEN PITS'!$C$3:$V$102,20,0) -> -1417.0416 | Q11: =+D11+P11 -> 58.558358
A12: SEI0127 | B12: CONSULTORIA | C12: Hernandez Ochoa Eduardo | D12: 2600.2 | E12: 337.5 | F12: 0 | G12: =+N12 -> 0 | H12: =SUM(D12:G12) -> 2937.7 | J12: =VLOOKUP($C12,'CPD PITSS'!$B$10:$V$27,3,0) -> 0 | K12: 15000 | L12: =(((+K12/30)*J12)*30%) -> 0 | M12: =VLOOKUP($C12,'CPD PITSS'!$B$10:$V$27,8,0) -> 0 | N12: =+L12-M12 -> 0 | O12: SEI0127 | P12: =VLOOKUP(C12,'RESUMEN PITS'!$C$3:$V$102,20,0) -> -1417.0416 | Q12: =+D12+P12 -> 1183.1584
A13: SEI0117 | B13: CONSULTORIA | C13: Mariscal Romero Luis Adrian | D13: 2751.08 | F13: 0 | G13: =+N13 -> 0 | H13: =SUM(D13:G13) -> 2751.08 | J13: =VLOOKUP($C13,'CPD PITSS'!$B$10:$V$27,3,0) -> 0 | K13: 15000 | L13: =(((+K13/30)*J13)*30%) -> 0 | M13: =VLOOKUP($C13,'CPD PITSS'!$B$10:$V$27,8,0) -> 0 | N13: =+L13-M13 -> 0 | O13: SEI0117 | P13: =VLOOKUP(C13,'RESUMEN PITS'!$C$3:$V$102,20,0) -> -1915.9536 | Q13: =+D13+P13 -> 835.12636
A14: SEI0040 | B14: CONSULTORIA | C14: Mora Ramirez Acal Aldo Isidro | D14: 2464 | E14: 1000 | F14: 0 | G14: =+N14 -> 195 | H14: =SUM(D14:G14) -> 3659 | J14: =VLOOKUP($C14,'CPD PITSS'!$B$10:$V$27,3,0) -> 3 | K14: 13000 | L14: =(((+K14/30)*J14)*30%) -> 390 | M14: =VLOOKUP($C14,'CPD PITSS'!$B$10:$V$27,8,0) -> 195 | N14: =+L14-M14 -> 195 | O14: SEI0040 | P14: =VLOOKUP(C14,'RESUMEN PITS'!$C$3:$V$102,20,0) -> -1915.9536 | Q14: =+D14+P14 -> 548.04636
A15: SEI0088 | B15: CONSULTORIA | C15: Morgado Fernandez Martin | D15: 2600.25 | E15: 75 | F15: 0 | G15: =+N15 -> 0 | H15: =SUM(D15:G15) -> 2675.25 | J15: =VLOOKUP($C15,'CPD PITSS'!$B$10:$V$27,3,0) -> 0 | K15: 15000 | L15: =(((+K15/30)*J15)*30%) -> 0 | M15: =VLOOKUP($C15,'CPD PITSS'!$B$10:$V$27,8,0) -> 0 | N15: =+L15-M15 -> 0 | O15: SEI0088 | P15: =VLOOKUP(C15,'RESUMEN PITS'!$C$3:$V$102,20,0) -> -1344.8726 | Q15: =+D15+P15 -> 1255.3774
A16: SEI0173 | B16: CONSULTORIA | C16: Nieto Ortiz Jose Luis | D16: 1483.15 | E16: 30 | F16: 0 | G16: =+N16 -> 0 | H16: =SUM(D16:G16) -> 1513.15 | J16: =VLOOKUP($C16,'CPD PITSS'!$B$10:$V$27,3,0) -> 0 | K16: 10000 | L16: =(((+K16/30)*J16)*30%) -> 0 | M16: =VLOOKUP($C16,'CPD PITSS'!$B$10:$V$27,8,0) -> 0 | N16: =+L16-M16 -> 0 | O16: SEI0173 | P16: =VLOOKUP(C16,'RESUMEN PITS'!$C$3:$V$102,20,0) -> -1344.8726 | Q16: =+D16+P16 -> 138.27736
A17: SEI0026 | B17: CONSULTORIA | C17: Patricio Aguilar Jhonattan Cristian | D17: 1588.2 | E17: 400 | F17: 0 | G17: =+N17 -> 0 | H17: =SUM(D17:G17) -> 1988.2 | J17: =VLOOKUP($C17,'CPD PITSS'!$B$10:$V$27,3,0) -> 0 | K17: 9000 | L17: =(((+K17/30)*J17)*30%) -> 0 | M17: =VLOOKUP($C17,'CPD PITSS'!$B$10:$V$27,8,0) -> 0 | N17: =+L17-M17 -> 0 | O17: SEI0026 | P17: =VLOOKUP(C17,'RESUMEN PITS'!$C$3:$V$102,20,0) -> -1344.8726 | Q17: =+D17+P17 -> 243.32736
A18: SEI0221 | B18: CONSULTORIA | C18: Rogel Teran Marco Antonio | D18: 12613.2 | F18: 0 | G18: =+N18 -> 0 | H18: =SUM(D18:G18) -> 12613.2 | J18: =VLOOKUP($C18,'CPD PITSS'!$B$10:$V$27,3,0) -> 0 | K18: 60000 | L18: =(((+K18/30)*J18)*30%) -> 0 | M18: =VLOOKUP($C18,'CPD PITSS'!$B$10:$V$27,8,0) -> 0 | N18: =+L18-M18 -> 0 | O18: SEI0221 | P18: =VLOOKUP(C18,'RESUMEN PITS'!$C$3:$V$102,20,0) -> -1344.8726 | Q18: =+D18+P18 -> 11268.327
A19: SEI0442 | B19: CONSULTORIA | C19: Sierra Escamilla Daniela | D19: 2463.8 | E19: 1000 | F19: 0 | G19: =+N19 -> 0 | H19: =SUM(D19:G19) -> 3463.8 | J19: =VLOOKUP($C19,'CPD PITSS'!$B$10:$V$27,3,0) -> 0 | K19: 13000 | L19: =(((+K19/30)*J19)*30%) -> 0 | M19: =VLOOKUP($C19,'CPD PITSS'!$B$10:$V$27,8,0) -> 0 | N19: =+L19-M19 -> 0 | O19: SEI0618 | P19: =VLOOKUP(C19,'RESUMEN PITS'!$C$3:$V$102,20,0) -> -1344.8726 | Q19: =+D19+P19 -> 1118.9274
A20: SEI0041 | B20: CONSULTORIA | C20: Vazquez Perez Miguel Angel | D20: 4176 | E20: 750 | F20: 0 | G20: =+N20 -> 0 | H20: =SUM(D20:G20) -> 4926 | J20: =VLOOKUP($C20,'CPD PITSS'!$B$10:$V$27,3,0) -> 0 | K20: 18500 | L20: =(((+K20/30)*J20)*30%) -> 0 | M20: =VLOOKUP($C20,'CPD PITSS'!$B$10:$V$27,8,0) -> 0 | N20: =+L20-M20 -> 0 | O20: SEI0041 | P20: =VLOOKUP(C20,'RESUMEN PITS'!$C$3:$V$102,20,0) -> -1537.7236 | Q20: =+D20+P20 -> 2638.2764
A21: SEI0544 | B21: IP INNOVACION | C21: Aguilar Aguirre Alfonso | D21: 135.2 | F21: 0 | H21: =SUM(D21:G21) -> 135.2 | J21: =VLOOKUP(C21,'IP PITSS'!$B$10:$U$91,3,0) -> 0 | K21: 6000 | L21: =(((+K21/30)*J21)*30%) -> 0 | M21: =VLOOKUP(C21,'IP PITSS'!$B$10:$I$91,8,0) -> 0 | N21: =+L21-M21 -> 0 | O21: SEI0652 | P21: =VLOOKUP(C21,'RESUMEN PITS'!$C$3:$V$102,20,0) -> -56.562642 | Q21: =+D21+P21 -> 78.637358
A22: SEI0527 | B22: IP INNOVACION | C22: Alejandro Peña Deivi | D22: 175.6 | E22: 900 | F22: 0 | G22: =+N22 -> 0 | H22: =SUM(D22:G22) -> 1075.6 | J22: =VLOOKUP(C22,'IP PITSS'!$B$10:$U$91,3,0) -> 0 | K22: 6300 | L22: =(((+K22/30)*J22)*30%) -> 0 | M22: =VLOOKUP(C22,'IP PITSS'!$B$10:$I$91,8,0) -> 0 | N22: =+L22-M22 -> 0 | O22: SEI0628 | P22: =VLOOKUP(C22,'RESUMEN PITS'!$C$3:$V$102,20,0) -> -56.562642 | Q22: =+D22+P22 -> 119.03736
A23: SEI0535 | B23: IP INNOVACION | C23: Alejandro Vazquez Erasmo Miguel | D23: 3135.15 | E23: 750 | F23: 0 | G23: =+N23 -> 0 | H23: =SUM(D23:G23) -> 3885.15 | J23: =VLOOKUP(C23,'IP PITSS'!$B$10:$U$91,3,0) -> 0 | K23: 12000 | L23: =(((+K23/30)*J23)*30%) -> 0 | M23: =VLOOKUP(C23,'IP PITSS'!$B$10:$I$91,8,0) -> 0 | N23: =+L23-M23 -> 0 | O23: SEI0638 | P23: =VLOOKUP(C23,'RESUMEN PITS'!$C$3:$V$102,20,0) -> -56.562642 | Q23: =+D23+P23 -> 3078.5874
A24: SEI0029 | B24: IP INNOVACION | C24: Arceo Garcia Manuel Federico | D24: =309.8-210+150 -> 249.8 | E24: 1000 | F24: 0 | G24: =+N24 -> 3 | H24: =SUM(D24:G24) -> 1252.8 | J24: =VLOOKUP(C24,'IP PITSS'!$B$10:$U$91,3,0) -> 1 | K24: 6300 | L24: =(((+K24/30)*J24)*30%) -> 63 | M24: =VLOOKUP(C24,'IP PITSS'!$B$10:$I$91,8,0) -> 60 | N24: =+L24-M24 -> 3 | O24: SEI0029 | P24: =VLOOKUP(C24,'RESUMEN PITS'!$C$3:$V$102,20,0) -> 153.43736 | Q24: =+D24+P24 -> 403.23736
A25: SEI0472 | B25: IP INNOVACION | C25: Arzate Gil Juan Sebastian | D25: 416.4 | E25: 510 | F25: 0 | G25: =+N25 -> 0 | H25: =SUM(D25:G25) -> 926.4 | J25: =VLOOKUP(C25,'IP PITSS'!$B$10:$U$91,3,0) -> 0 | K25: 8000 | L25: =(((+K25/30)*J25)*30%) -> 0 | M25: =VLOOKUP(C25,'IP PITSS'!$B$10:$I$91,8,0) -> 0 | N25: =+L25-M25 -> 0 | O25: SEI0550 | P25: =VLOOKUP(C25,'RESUMEN PITS'!$C$3:$V$102,20,0) -> -56.562642 | Q25: =+D25+P25 -> 359.83736
A26: SEI0528 | B26: IP INNOVACION | C26: Casas Chavarria Rafael | D26: 175.72 | E26: 1350 | F26: 0 | G26: =+N26 -> 0 | H26: =SUM(D26:G26) -> 1525.72 | J26: =VLOOKUP(C26,'IP PITSS'!$B$10:$U$91,3,0) -> 0 | K26: 6300 | L26: =(((+K26/30)*J26)*30%) -> 0 | M26: =VLOOKUP(C26,'IP PITSS'!$B$10:$I$91,8,0) -> 0 | N26: =+L26-M26 -> 0 | O26: SEI0629 | P26: =VLOOKUP(C26,'RESUMEN PITS'!$C$3:$V$102,20,0) -> -56.562642 | Q26: =+D26+P26 -> 119.15736
A27: SEI0460 | B27: IP INNOVACION | C27: Castellon Ramos Rene | D27: 384.785 | E27: 70 | F27: 0 | G27: =+N27 -> 0 | H27: =SUM(D27:G27) -> 454.785 | J27: =VLOOKUP(C27,'IP PITSS'!$B$10:$U$91,3,0) -> 0 | K27: 7505.99 | L27: =(((+K27/30)*J27)*30%) -> 0 | M27: =VLOOKUP(C27,'IP PITSS'!$B$10:$I$91,8,0) -> 0 | N27: =+L27-M27 -> 0 | O27: SEI0499 | P27: =VLOOKUP(C27,'RESUMEN PITS'!$C$3:$V$102,20,0) -> -56.562642 | Q27: =+D27+P27 -> 328.22236
A28: SEI0443 | B28: IP INNOVACION | C28: Castillo Nungaray Nestor Roman | D28: =135.2+150 -> 285.2 | E28: 800 | F28: 0 | G28: =+N28 -> 0 | H28: =SUM(D28:G28) -> 1085.2 | J28: =VLOOKUP(C28,'IP PITSS'!$B$10:$U$91,3,0) -> 0 | K28: 6300 | L28: =(((+K28/30)*J28)*30%) -> 0 | M28: =VLOOKUP(C28,'IP PITSS'!$B$10:$I$91,8,0) -> 0 | N28: =+L28-M28 -> 0 | O28: SEI0468 | P28: =VLOOKUP(C28,'RESUMEN PITS'!$C$3:$V$102,20,0) -> -56.562642 | Q28: =+D28+P28 -> 228.63736
A29: SEI0490 | B29: IP INNOVACION | C29: Castillo Ramirez Hector Ivan | D29: 3721.2 | E29: 281.25 | F29: 0 | G29: =+N29 -> 0 | H29: =SUM(D29:G29) -> 4002.45 | J29: =VLOOKUP(C29,'IP PITSS'!$B$10:$U$91,3,0) -> 0 | K29: 14000 | L29: =(((+K29/30)*J29)*30%) -> 0 | M29: =VLOOKUP(C29,'IP PITSS'!$B$10:$I$91,8,0) -> 0 | N29: =+L29-M29 -> 0 | O29: SEI0448 | P29: =VLOOKUP(C29,'RESUMEN PITS'!$C$3:$V$102,20,0) -> -56.562642 | Q29: =+D29+P29 -> 3664.6374
A30: SEI0508 | B30: IP INNOVACION | C30: Cerro Garcia Elvis | D30: 2553.4 | E30: 400 | F30: 0 | G30: =+N30 -> 0 | H30: =SUM(D30:G30) -> 2953.4 | J30: =VLOOKUP(C30,'IP PITSS'!$B$10:$U$91,3,0) -> 0 | K30: 10000 | L30: =(((+K30/30)*J30)*30%) -> 0 | M30: =VLOOKUP(C30,'IP PITSS'!$B$10:$I$91,8,0) -> 0 | N30: =+L30-M30 -> 0 | O30: SEI0513 | P30: =VLOOKUP(C30,'RESUMEN PITS'!$C$3:$V$102,20,0) -> -56.562642 | Q30: =+D30+P30 -> 2496.8374
A31: SEI0499 | B31: IP INNOVACION | C31: Chavez Dominguez Salvador | D31: 2667.4 | E31: 500 | F31: 0 | G31: =+N31 -> 0 | H31: =SUM(D31:G31) -> 3167.4 | J31: =VLOOKUP(C31,'IP PITSS'!$B$10:$U$91,3,0) -> 0 | K31: 12000 | L31: =(((+K31/30)*J31)*30%) -> 0 | M31: =VLOOKUP(C31,'IP PITSS'!$B$10:$I$91,8,0) -> 0 | N31: =+L31-M31 -> 0 | O31: SEI0483 | P31: =VLOOKUP(C31,'RESUMEN PITS'!$C$3:$V$102,20,0) -> -56.562642 | Q31: =+D31+P31 -> 2610.8374
A32: SEI0541 | B32: IP INNOVACION | C32: Chavez Govea Edgar Aram | D32: 222.6 | E32: 187.5 | F32: 0 | G32: =+N32 -> 0 | H32: =SUM(D32:G32) -> 410.1 | J32: =VLOOKUP(C32,'IP PITSS'!$B$10:$U$91,3,0) -> 0 | K32: 7000 | L32: =(((+K32/30)*J32)*30%) -> 0 | M32: =VLOOKUP(C32,'IP PITSS'!$B$10:$I$91,8,0) -> 0 | N32: =+L32-M32 -> 0 | O32: SEI0644 | P32: =VLOOKUP(C32,'RESUMEN PITS'!$C$3:$V$102,20,0) -> -56.562642 | Q32: =+D32+P32 -> 166.03736
A33: SEI0442 | B33: IP INNOVACION | C33: Chavez Pedraza Samuel | D33: 1047.8 | E33: 312.5 | F33: 0 | G33: =+N33 -> 0 | H33: =SUM(D33:G33) -> 1360.3 | J33: =VLOOKUP(C33,'IP PITSS'!$B$10:$U$91,3,0) -> 0 | K33: 14000 | L33: =(((+K33/30)*J33)*30%) -> 0 | M33: =VLOOKUP(C33,'IP PITSS'!$B$10:$I$91,8,0) -> 0 | N33: =+L33-M33 -> 0 | O33: SEI0467 | P33: =VLOOKUP(C33,'RESUMEN PITS'!$C$3:$V$102,20,0) -> -56.562642 | Q33: =+D33+P33 -> 991.23736
A34: SEI0462 | B34: IP INNOVACION | C34: Chavez Saucedo Jorge Arturo | D34: 414.6 | E34: 600 | F34: 0 | G34: =+N34 -> 0 | H34: =SUM(D34:G34) -> 1014.6 | J34: =VLOOKUP(C34,'IP PITSS'!$B$10:$U$91,3,0) -> 0 | K34: 8000 | L34: =(((+K34/30)*J34)*30%) -> 0 | M34: =VLOOKUP(C34,'IP PITSS'!$B$10:$I$91,8,0) -> 0 | N34: =+L34-M34 -> 0 | O34: SEI0516 | P34: =VLOOKUP(C34,'RESUMEN PITS'!$C$3:$V$102,20,0) -> -56.562642 | Q34: =+D34+P34 -> 358.03736
A35: SEI0456 | B35: IP INNOVACION | C35: Chavira Garcia David Fernando | D35: 593.6 | E35: 60 | F35: 0 | G35: =+N35 -> 0 | H35: =SUM(D35:G35) -> 653.6 | J35: =VLOOKUP(C35,'IP PITSS'!$B$10:$U$91,3,0) -> 0 | K35: 10000 | L35: =(((+K35/30)*J35)*30%) -> 0 | M35: =VLOOKUP(C35,'IP PITSS'!$B$10:$I$91,8,0) -> 0 | N35: =+L35-M35 -> 0 | O35: SEI0495 | P35: =VLOOKUP(C35,'RESUMEN PITS'!$C$3:$V$102,20,0) -> -56.562642 | Q35: =+D35+P35 -> 537.03736
A36: SEI0015 | B36: IP INNOVACION | C36: Cota Jaramillo Miguel Angel | D36: 134 | E36: 337.5 | F36: 0 | G36: =+N36 -> 0 | H36: =SUM(D36:G36) -> 471.5 | J36: =VLOOKUP(C36,'IP PITSS'!$B$10:$U$91,3,0) -> 0 | K36: 6000 | L36: =(((+K36/30)*J36)*30%) -> 0 | M36: =VLOOKUP(C36,'IP PITSS'!$B$10:$I$91,8,0) -> 0 | N36: =+L36-M36 -> 0 | O36: SEI0015 | P36: =VLOOKUP(C36,'RESUMEN PITS'!$C$3:$V$102,20,0) -> -56.562642 | Q36: =+D36+P36 -> 77.437358
A37: SEI0413 | B37: IP INNOVACION | C37: Courtenay Gutierrez Barry Vladimir | D37: 52.4 | E37: 250 | F37: 2800 | G37: =+N37 -> 0 | H37: =SUM(D37:G37) -> 3102.4 | J37: =VLOOKUP(C37,'IP PITSS'!$B$10:$U$91,3,0) -> 0 | K37: 5000 | L37: =(((+K37/30)*J37)*30%) -> 0 | M37: =VLOOKUP(C37,'IP PITSS'!$B$10:$I$91,8,0) -> 0 | N37: =+L37-M37 -> 0 | O37: SEI0436 | P37: =VLOOKUP(C37,'RESUMEN PITS'!$C$3:$V$102,20,0) -> -56.562642 | Q37: =+D37+P37 -> -4.1626417
A38: SEI0501 | B38: IP INNOVACION | C38: Cruz Herrera Roberto | D38: 1667.29 | E38: 90 | F38: 0 | G38: =+N38 -> 0 | H38: =SUM(D38:G38) -> 1757.29 | J38: =VLOOKUP(C38,'IP PITSS'!$B$10:$U$91,3,0) -> 0 | K38: 10000 | L38: =(((+K38/30)*J38)*30%) -> 0 | M38: =VLOOKUP(C38,'IP PITSS'!$B$10:$I$91,8,0) -> 0 | N38: =+L38-M38 -> 0 | O38: SEI0485 | P38: =VLOOKUP(C38,'RESUMEN PITS'!$C$3:$V$102,20,0) -> -56.562642 | Q38: =+D38+P38 -> 1610.7274
A39: SEI479 | B39: IP INNOVACION | C39: Cruz Perez Alejandro Nezahualcoyotl | D39: 416.4 | E39: 570 | F39: 0 | G39: =+N39 -> 0 | H39: =SUM(D39:G39) -> 986.4 | J39: =VLOOKUP(C39,'IP PITSS'!$B$10:$U$91,3,0) -> 0 | K39: 8000 | L39: =(((+K39/30)*J39)*30%) -> 0 | M39: =VLOOKUP(C39,'IP PITSS'!$B$10:$I$91,8,0) -> 0 | N39: =+L39-M39 -> 0 | O39: SEI0606 | P39: =VLOOKUP(C39,'RESUMEN PITS'!$C$3:$V$102,20,0) -> -56.562642 | Q39: =+D39+P39 -> 359.83736
A40: SEI0530 | B40: IP INNOVACION | C40: Del Pilar Mendez Lucio | D40: 134 | E40: 363.75 | F40: 0 | G40: =+N40 -> 0 | H40: =SUM(D40:G40) -> 497.75 | J40: =VLOOKUP(C40,'IP PITSS'!$B$10:$U$91,3,0) -> 0 | K40: 6000 | L40: =(((+K40/30)*J40)*30%) -> 0 | M40: =VLOOKUP(C40,'IP PITSS'!$B$10:$I$91,8,0) -> 0 | N40: =+L40-M40 -> 0 | O40: SEI0630 | P40: =VLOOKUP(C40,'RESUMEN PITS'!$C$3:$V$102,20,0) -> -56.562642 | Q40: =+D40+P40 -> 77.437358
... A45: SEI0461 | B45: IP INNOVACION | C45: Flores Franco Marco | D45: 451.005 | E45: 162.5 | F45: 0 | G45: =+N45 -> 0 | H45: =SUM(D45:G45) -> 613.505 | J45: =VLOOKUP(C45,'IP PITSS'!$B$10:$U$91,3,0) -> 0 | K45: 8500.01 | L45: =(((+K45/30)*J45)*30%) -> 0 | M45: =VLOOKUP(C45,'IP PITSS'!$B$10:$I$91,8,0) -> 0 | N45: =+L45-M45 -> 0 | O45: SEI0500 | P45: =VLOOKUP(C45,'RESUMEN PITS'!$C$3:$V$102,20,0) -> -1417.0416 | Q45: =+D45+P45 -> -966.03664
A46: SEI0500 | B46: IP INNOVACION | C46: Garcia Gutierrez Jose Juan | D46: 3135.4 | F46: 0 | G46: =+N46 -> 0 | H46: =SUM(D46:G46) -> 3135.4 | J46: =VLOOKUP(C46,'IP PITSS'!$B$10:$U$91,3,0) -> 0 | K46: 12000 | L46: =(((+K46/30)*J46)*30%) -> 0 | M46: =VLOOKUP(C46,'IP PITSS'!$B$10:$I$91,8,0) -> 0 | N46: =+L46-M46 -> 0 | O46: SEI0484 | P46: =VLOOKUP(C46,'RESUMEN PITS'!$C$3:$V$102,20,0) -> -1417.0416 | Q46: =+D46+P46 -> 1718.3584
A47: SEI0534 | B47: IP INNOVACION | C47: Gonzalez Ramirez Paul | D47: 134.2 | E47: 292.5 | F47: 0 | G47: =+N47 -> 0 | H47: =SUM(D47:G47) -> 426.7 | J47: =VLOOKUP(C47,'IP PITSS'!$B$10:$U$91,3,0) -> 0 | K47: 6000 | L47: =(((+K47/30)*J47)*30%) -> 0 | M47: =VLOOKUP(C47,'IP PITSS'!$B$10:$I$91,8,0) -> 0 | N47: =+L47-M47 -> 0 | O47: 0SEI0635 | P47: =VLOOKUP(C47,'RESUMEN PITS'!$C$3:$V$102,20,0) -> -1417.0416 | Q47: =+D47+P47 -> -1282.8416
A48: SEI0019 | B48: IP INNOVACION | C48: Gonzalez Rasgado Miguel Isaias | D48: 0 | E48: 937.5 | F48: 0 | G48: =+N48 -> 0 | H48: =SUM(D48:G48) -> 937.5 | J48: =VLOOKUP(C48,'IP PITSS'!$B$10:$U$91,3,0) -> 0 | K48: 13125 | L48: =(((+K48/30)*J48)*30%) -> 0 | M48: =VLOOKUP(C48,'IP PITSS'!$B$10:$I$91,8,0) -> 0 | N48: =+L48-M48 -> 0 | O48: SEI0019 | P48: =VLOOKUP(C48,'RESUMEN PITS'!$C$3:$V$102,20,0) -> -1431.3416 | Q48: =+D48+P48 -> -1431.3416
A49: SEI0457 | B49: IP INNOVACION | C49: Guerrero Lara Cesar Adrian | D49: 416.4 | E49: 225 | F49: 0 | G49: =+N49 -> 0 | H49: =SUM(D49:G49) -> 641.4 | J49: =VLOOKUP(C49,'IP PITSS'!$B$10:$U$91,3,0) -> 0 | K49: 8000 | L49: =(((+K49/30)*J49)*30%) -> 0 | M49: =VLOOKUP(C49,'IP PITSS'!$B$10:$I$91,8,0) -> 0 | N49: =+L49-M49 -> 0 | O49: SEI0496 | P49: =VLOOKUP(C49,'RESUMEN PITS'!$C$3:$V$102,20,0) -> -1417.0416 | Q49: =+D49+P49 -> -1000.6416
A50: SEI0509 | B50: IP INNOVACION | C50: Gutierrez Castillo Jose De Jesus | D50: 284.03 | E50: 281.25 | F50: 0 | G50: =+N50 -> 0 | H50: =SUM(D50:G50) -> 565.28 | J50: =VLOOKUP(C50,'IP PITSS'!$B$10:$U$91,3,0) -> 0 | K50: 6300 | L50: =(((+K50/30)*J50)*30%) -> 0 | M50: 0 | N50: =+L50-M50 -> 0 | O50: SEI0610 | P50: =VLOOKUP(C50,'RESUMEN PITS'!$C$3:$V$102,20,0) -> -1417.0416 | Q50: =+D50+P50 -> -1133.0116
A51: SEI0483 | B51: IP INNOVACION | C51: Gutierrez Muñoz Carlos Alejandro | D51: 2884.84 | E51: 300 | F51: 0 | G51: =+N51 -> 0 | H51: =SUM(D51:G51) -> 3184.84 | J51: =VLOOKUP(C51,'IP PITSS'!$B$10:$U$91,3,0) -> 0 | K51: 12000 | L51: =(((+K51/30)*J51)*30%) -> 0 | M51: =VLOOKUP(C51,'IP PITSS'!$B$10:$I$91,8,0) -> 0 | N51: =+L51-M51 -> 0 | O51: SEI0095 | P51: =VLOOKUP(C51,'RESUMEN PITS'!$C$3:$V$102,20,0) -> -1417.0416 | Q51: =+D51+P51 -> 1467.7984
A52: SEI0476 | B52: IP INNOVACION | C52: Hernandez Garcia Manuel Alejandro | D52: 414.6 | E52: 255 | F52: 0 | G52: =+N52 -> 0 | H52: =SUM(D52:G52) -> 669.6 | J52: =VLOOKUP(C52,'IP PITSS'!$B$10:$U$91,3,0) -> 0 | K52: 8000 | L52: =(((+K52/30)*J52)*30%) -> 0 | M52: =VLOOKUP(C52,'IP PITSS'!$B$10:$I$91,8,0) -> 0 | N52: =+L52-M52 -> 0 | O52: SEI0602 | P52: =VLOOKUP(C52,'RESUMEN PITS'!$C$3:$V$102,20,0) -> -1417.0416 | Q52: =+D52+P52 -> -1002.4416
A53: SEI0536 | B53: IP INNOVACION | C53: Hernandez Ojeda Julio Cesar | D53: 1704.51 | F53: 0 | G53: =+N53 -> 0 | H53: =SUM(D53:G53) -> 1704.51 | J53: =VLOOKUP(C53,'IP PITSS'!$B$10:$U$91,3,0) -> 0 | K53: 7000 | L53: =(((+K53/30)*J53)*30%) -> 0 | M53: =VLOOKUP(C53,'IP PITSS'!$B$10:$I$91,8,0) -> 0 | N53: =+L53-M53 -> 0 | O53: SEI0640 | P53: =VLOOKUP(C53,'RESUMEN PITS'!$C$3:$V$102,20,0) -> -1417.0416 | Q53: =+D53+P53 -> 287.46836
A54: SEI0523 | B54: IP INNOVACION | C54: Hernandez Rodriguez Jorge | D54: 222.54 | E54: 100 | F54: 0 | G54: =+N54 -> 0 | H54: =SUM(D54:G54) -> 322.54 | J54: =VLOOKUP(C54,'IP PITSS'!$B$10:$U$91,3,0) -> 0 | K54: 7000 | L54: =(((+K54/30)*J54)*30%) -> 0 | M54: =VLOOKUP(C54,'IP PITSS'!$B$10:$I$91,8,0) -> 0 | N54: =+L54-M54 -> 0 | O54: SEI0624 | P54: =VLOOKUP(C54,'RESUMEN PITS'!$C$3:$V$102,20,0) -> -2859.2916 | Q54: =+D54+P54 -> -2636.7516
A55: SEI0464 | B55: IP INNOVACION | C55: Hueramo Hueramo Jesus Daniel | D55: 1451.05 | E55: 112.5 | F55: 0 | G55: =+N55 -> 0 | H55: =SUM(D55:G55) -> 1563.55 | J55: =VLOOKUP(C55,'IP PITSS'!$B$10:$U$91,3,0) -> 0 | K55: 8500.01 | L55: =(((+K55/30)*J55)*30%) -> 0 | M55: =VLOOKUP(C55,'IP PITSS'!$B$10:$I$91,8,0) -> 0 | N55: =+L55-M55 -> 0 | O55: SEI 502 | P55: =VLOOKUP(C55,'RESUMEN PITS'!$C$3:$V$102,20,0) -> -1915.9536 | Q55: =+D55+P55 -> -464.90364
A56: SEI0511 | B56: IP INNOVACION | C56: Lizaran Maceda Jose Guadalupe | D56: 53 | E56: 160 | F56: 0 | G56: =+N56 -> 0 | H56: =SUM(D56:G56) -> 213 | J56: =VLOOKUP(C56,'IP PITSS'!$B$10:$U$91,3,0) -> 0 | K56: 5000 | L56: =(((+K56/30)*J56)*30%) -> 0 | M56: =VLOOKUP(C56,'IP PITSS'!$B$10:$I$91,8,0) -> 0 | N56: =+L56-M56 -> 0 | O56: SEI0517 | P56: =VLOOKUP(C56,'RESUMEN PITS'!$C$3:$V$102,20,0) -> -1915.9536 | Q56: =+D56+P56 -> -1862.9536
A57: SEI0525 | B57: IP INNOVACION | C57: Lizaran Maceda Jesus | D57: 175.51 | F57: 0 | G57: =+N57 -> 0 | H57: =SUM(D57:G57) -> 175.51 | J57: =VLOOKUP(C57,'IP PITSS'!$B$10:$U$91,3,0) -> 0 | K57: 6300 | L57: =(((+K57/30)*J57)*30%) -> 0 | M57: =VLOOKUP(C57,'IP PITSS'!$B$10:$I$91,8,0) -> 0 | N57: =+L57-M57 -> 0 | O57: SEI0626 | P57: =VLOOKUP(C57,'RESUMEN PITS'!$C$3:$V$102,20,0) -> -1915.9536 | Q57: =+D57+P57 -> -1740.4436
A58: SEI0438 | B58: IP INNOVACION | C58: Lopez Terron Roberto Porfirio | D58: 1047.8 | E58: 187.5 | F58: 0 | G58: =+N58 -> 0 | H58: =SUM(D58:G58) -> 1235.3 | J58: =VLOOKUP(C58,'IP PITSS'!$B$10:$U$91,3,0) -> 0 | K58: 14000 | L58: =(((+K58/30)*J58)*30%) -> 0 | M58: =VLOOKUP(C58,'IP PITSS'!$B$10:$I$91,8,0) -> 0 | N58: =+L58-M58 -> 0 | O58: SEI0463 | P58: =VLOOKUP(C58,'RESUMEN PITS'!$C$3:$V$102,20,0) -> -1915.9536 | Q58: =+D58+P58 -> -868.15364
A59: SEI0517 | B59: IP INNOVACION | C59: Macias Torres Enrique | D59: 6520.6 | E59: 2223 | F59: 0 | G59: =+N59 -> 0 | H59: =SUM(D59:G59) -> 8743.6 | J59: =VLOOKUP(C59,'IP PITSS'!$B$10:$U$91,3,0) -> 0 | K59: 19950 | L59: =(((+K59/30)*J59)*30%) -> 0 | M59: =VLOOKUP(C59,'IP PITSS'!$B$10:$I$91,8,0) -> 0 | N59: =+L59-M59 -> 0 | O59: SEI0120 | P59: =VLOOKUP(C59,'RESUMEN PITS'!$C$3:$V$102,20,0) -> -1915.9536 | Q59: =+D59+P59 -> 4604.6464
A60: SEI0020 | B60: IP INNOVACION | C60: Mar Marquez Cesar Eduardo | D60: 414.6 | E60: 220 | F60: 0 | G60: =+N60 -> 0 | H60: =SUM(D60:G60) -> 634.6 | J60: =VLOOKUP(C60,'IP PITSS'!$B$10:$U$91,3,0) -> 0 | K60: 8000 | L60: =(((+K60/30)*J60)*30%) -> 0 | M60: =VLOOKUP(C60,'IP PITSS'!$B$10:$I$91,8,0) -> 0 | N60: =+L60-M60 -> 0 | O60: SEI0020 | P60: =VLOOKUP(C60,'RESUMEN PITS'!$C$3:$V$102,20,0) -> -1915.9536 | Q60: =+D60+P60 -> -1501.3536
A61: SEI0444 | B61: IP INNOVACION | C61: Marquez Hernandez Rogelio | D61: 416.4 | E61: 150 | F61: 0 | G61: =+N61 -> 0 | H61: =SUM(D61:G61) -> 566.4 | J61: =VLOOKUP(C61,'IP PITSS'!$B$10:$U$91,3,0) -> 0 | K61: 8000 | L61: =(((+K61/30)*J61)*30%) -> 0 | M61: =VLOOKUP(C61,'IP PITSS'!$B$10:$I$91,8,0) -> 0 | N61: =+L61-M61 -> 0 | O61: SEI0469 | P61: =VLOOKUP(C61,'RESUMEN PITS'!$C$3:$V$102,20,0) -> -1915.9536 | Q61: =+D61+P61 -> -1499.5536
A62: SEI0428 | B62: IP INNOVACION | C62: Martinez Hernandez J. Antonio | D62: 416.4 | E62: 120 | F62: 0 | G62: =+N62 -> 0 | H62: =SUM(D62:G62) -> 536.4 | J62: =VLOOKUP(C62,'IP PITSS'!$B$10:$U$91,3,0) -> 0 | K62: 8000 | L62: =(((+K62/30)*J62)*30%) -> 0 | M62: =VLOOKUP(C62,'IP PITSS'!$B$10:$I$91,8,0) -> 0 | N62: =+L62-M62 -> 0 | O62: SEI0452 | P62: =VLOOKUP(C62,'RESUMEN PITS'!$C$3:$V$102,20,0) -> -1915.9536 | Q62: =+D62+P62 -> -1499.5536
A63: SEI0504 | B63: IP INNOVACION | C63: Martinez Malo Cesar | D63: 1694.24 | E63: 262.5 | F63: 0 | G63: =+N63 -> 0 | H63: =SUM(D63:G63) -> 1956.74 | J63: =VLOOKUP(C63,'IP PITSS'!$B$10:$U$91,3,0) -> 0 | K63: 9000 | L63: =(((+K63/30)*J63)*30%) -> 0 | M63: =VLOOKUP(C63,'IP PITSS'!$B$10:$I$91,8,0) -> 0 | N63: =+L63-M63 -> 0 | O63: SEI0488 | P63: =VLOOKUP(C63,'RESUMEN PITS'!$C$3:$V$102,20,0) -> -1915.9536 | Q63: =+D63+P63 -> -221.71364
A64: SEI0469 | B64: IP INNOVACION | C64: Martinez Morales Jose Martin | D64: 1047.6 | E64: 562.5 | F64: 0 | G64: =+N64 -> 0 | H64: =SUM(D64:G64) -> 1610.1 | J64: =VLOOKUP(C64,'IP PITSS'!$B$10:$U$91,3,0) -> 0 | K64: 14000 | L64: =(((+K64/30)*J64)*30%) -> 0 | M64: =VLOOKUP(C64,'IP PITSS'!$B$10:$I$91,8,0) -> 0 | N64: =+L64-M64 -> 0 | O64: SEI0511 | P64: =VLOOKUP(C64,'RESUMEN PITS'!$C$3:$V$102,20,0) -> -1915.9536 | Q64: =+D64+P64 -> -868.35364
A65: SEI0493 | B65: IP INNOVACION | C65: Martinez Morales Tomas | D65: 3339.55 | E65: 262.5 | F65: 0 | G65: =+N65 -> 0 | H65: =SUM(D65:G65) -> 3602.05 | J65: =VLOOKUP(C65,'IP PITSS'!$B$10:$U$91,3,0) -> 0 | K65: 15000 | L65: =(((+K65/30)*J65)*30%) -> 0 | M65: =VLOOKUP(C65,'IP PITSS'!$B$10:$I$91,8,0) -> 0 | N65: =+L65-M65 -> 0 | O65: SEI0477 | P65: =VLOOKUP(C65,'RESUMEN PITS'!$C$3:$V$102,20,0) -> -1915.9536 | Q65: =+D65+P65 -> 1423.5964
A66: SEI0503 | B66: IP INNOVACION | C66: Martinez Rodriguez Paulo Cesar | D66: 2552.4 | E66: 250 | F66: 0 | G66: =+N66 -> 0 | H66: =SUM(D66:G66) -> 2802.4 | J66: =VLOOKUP(C66,'IP PITSS'!$B$10:$U$91,3,0) -> 0 | K66: 10000 | L66: =(((+K66/30)*J66)*30%) -> 0 | M66: =VLOOKUP(C66,'IP PITSS'!$B$10:$I$91,8,0) -> 0 | N66: =+L66-M66 -> 0 | O66: SEI0487 | P66: =VLOOKUP(C66,'RESUMEN PITS'!$C$3:$V$102,20,0) -> -1915.9536 | Q66: =+D66+P66 -> 636.44636
A67: SEI0458 | B67: IP INNOVACION | C67: Martinez Zamora Gerardo Mario | D67: 549.875 | E67: 375 | F67: 0 | G67: =+N67 -> 0 | H67: =SUM(D67:G67) -> 924.875 | J67: =VLOOKUP(C67,'IP PITSS'!$B$10:$U$91,3,0) -> 0 | K67: 9550.01 | L67: =(((+K67/30)*J67)*30%) -> 0 | M67: =VLOOKUP(C67,'IP PITSS'!$B$10:$I$91,8,0) -> 0 | N67: =+L67-M67 -> 0 | O67: SEI0497 | P67: =VLOOKUP(C67,'RESUMEN PITS'!$C$3:$V$102,20,0) -> -1915.9536 | Q67: =+D67+P67 -> -1366.0786
A68: SEI0494 | B68: IP INNOVACION | C68: Medellin Colunga Ruben Dario | D68: 4339.23 | E68: 281.25 | F68: 0 | G68: =+N68 -> 0 | H68: =SUM(D68:G68) -> 4620.48 | J68: =VLOOKUP(C68,'IP PITSS'!$B$10:$U$91,3,0) -> 0 | K68: 17000 | L68: =(((+K68/30)*J68)*30%) -> 0 | M68: =VLOOKUP(C68,'IP PITSS'!$B$10:$I$91,8,0) -> 0 | N68: =+L68-M68 -> 0 | O68: SEI0478 | P68: =VLOOKUP(C68,'RESUMEN PITS'!$C$3:$V$102,20,0) -> -1915.9536 | Q68: =+D68+P68 -> 2423.2764
A69: SEI0506 | B69: IP INNOVACION | C69: Mejia Duarte Jose Luis | D69: 3553.4 | E69: 187.5 | F69: 0 | G69: =+N69 -> 0 | H69: =SUM(D69:G69) -> 3740.9 | J69: =VLOOKUP(C69,'IP PITSS'!$B$10:$U$91,3,0) -> 0 | K69: 12000 | L69: =(((+K69/30)*J69)*30%) -> 0 | M69: 0 | N69: =+L69-M69 -> 0 | O69: SEI0506 | P69: =VLOOKUP(C69,'RESUMEN PITS'!$C$3:$V$102,20,0) -> -1915.9536 | Q69: =+D69+P69 -> 1637.4464
A70: SEI0513 | B70: IP INNOVACION | C70: Mendez Rivera Ivan Israel | D70: 52.57 | E70: 250 | F70: 0 | G70: =+N70 -> 0 | H70: =SUM(D70:G70) -> 302.57 | J70: =VLOOKUP(C70,'IP PITSS'!$B$10:$U$91,3,0) -> 0 | K70: 5000 | L70: =(((+K70/30)*J70)*30%) -> 0 | M70: =VLOOKUP(C70,'IP PITSS'!$B$10:$I$91,8,0) -> 0 | N70: =+L70-M70 -> 0 | O70: SEI0612 | P70: =VLOOKUP(C70,'RESUMEN PITS'!$C$3:$V$102,20,0) -> -1915.9536 | Q70: =+D70+P70 -> -1863.3836
A71: SEI0488 | B71: IP INNOVACION | C71: Mireles Casillas Brenda Cristina | D71: 2262.4 | F71: 0 | G71: =+N71 -> 0 | H71: =SUM(D71:G71) -> 2262.4 | J71: =VLOOKUP(C71,'IP PITSS'!$B$10:$U$91,3,0) -> 0 | K71: 9000 | L71: =(((+K71/30)*J71)*30%) -> 0 | M71: =VLOOKUP(C71,'IP PITSS'!$B$10:$I$91,8,0) -> 0 | N71: =+L71-M71 -> 0 | O71: SEI0446 | P71: =VLOOKUP(C71,'RESUMEN PITS'!$C$3:$V$102,20,0) -> -1915.9536 | Q71: =+D71+P71 -> 346.44636
B72: IP INNOVACION | C72: Marin Avila Hector | D72: 707 | E72: 500 | F72: 0 | G72: =+N72 -> 0 | H72: =+D72+E72+F72+G72 -> 1207 | J72: =VLOOKUP(C72,'IP PITSS'!$B$10:$U$91,3,0) -> 0 | K72: 8800 | L72: =(((+K72/30)*J72)*30%) -> 0 | M72: =VLOOKUP(C72,'IP PITSS'!$B$10:$I$91,8,0) -> 0 | N72: =+L72-M72 -> 0 | O72: SEI0445 | P72: =VLOOKUP(C72,'RESUMEN PITS'!$C$3:$V$102,20,0) -> -1915.9536 | Q72: =+D72+P72 -> -1208.9536
A73: SEI0485 | B73: IP INNOVACION | C73: Molina Ramirez Gerardo Daniel | D73: 2262.17 | E73: 400 | F73: 0 | G73: =+N73 -> 0 | H73: =SUM(D73:G73) -> 2662.17 | J73: =VLOOKUP(C73,'IP PITSS'!$B$10:$U$91,3,0) -> 0 | K73: 9000 | L73: =(((+K73/30)*J73)*30%) -> 0 | M73: =VLOOKUP(C73,'IP PITSS'!$B$10:$I$91,8,0) -> 0 | N73: =+L73-M73 -> 0 | O73: SEI0033 | P73: =VLOOKUP(C73,'RESUMEN PITS'!$C$3:$V$102,20,0) -> -1915.9536 | Q73: =+D73+P73 -> 346.21636
A74: SEI0014 | B74: IP INNOVACION | C74: Montoya Portillo Carlos Alberto | D74: 414.8 | E74: 175 | F74: 0 | G74: 0 | H74: =SUM(D74:G74) -> 589.8 | J74: =VLOOKUP(C74,'IP PITSS'!$B$10:$U$91,3,0) -> 0 | K74: 8000 | L74: =(((+K74/30)*J74)*30%) -> 0 | M74: =VLOOKUP(C74,'IP PITSS'!$B$10:$I$91,8,0) -> 0 | N74: =+L74-M74 -> 0 | O74: SEI0014 | P74: =VLOOKUP(C74,'RESUMEN PITS'!$C$3:$V$102,20,0) -> -1915.9536 | Q74: =+D74+P74 -> -1501.1536
A75: SEI0540 | B75: IP INNOVACION | C75: Morales Martinez Eduardo | D75: 175.6 | E75: 843.75 | F75: 0 | G75: =+N75 -> 0 | H75: =SUM(D75:G75) -> 1019.35 | J75: =VLOOKUP(C75,'IP PITSS'!$B$10:$U$91,3,0) -> 0 | K75: 6300 | L75: =(((+K75/30)*J75)*30%) -> 0 | M75: =VLOOKUP(C75,'IP PITSS'!$B$10:$I$91,8,0) -> 0 | N75: =+L75-M75 -> 0 | O75: SEI0648 | P75: =VLOOKUP(C75,'RESUMEN PITS'!$C$3:$V$102,20,0) -> -1353.4926 | Q75: =+D75+P75 -> -1177.8926
A76: SEI0475 | B76: IP INNOVACION | C76: Moreno Quiroga Ana Sarahi | D76: 416.4 | E76: 687.5 | F76: 0 | G76: =+N76 -> 0 | H76: =SUM(D76:G76) -> 1103.9 | J76: =VLOOKUP(C76,'IP PITSS'!$B$10:$U$91,3,0) -> 0 | K76: 8000 | L76: =(((+K76/30)*J76)*30%) -> 0 | M76: =VLOOKUP(C76,'IP PITSS'!$B$10:$I$91,8,0) -> 0 | N76: =+L76-M76 -> 0 | O76: SEI0601 | P76: =VLOOKUP(C76,'RESUMEN PITS'!$C$3:$V$102,20,0) -> -1344.8726 | Q76: =+D76+P76 -> -928.47264
A77: SEI0017 | B77: IP INNOVACION | C77: Muñoz Reyes Luis Eduardo | D77: 414.76 | E77: 250 | F77: 0 | G77: =+N77 -> 0 | H77: =SUM(D77:G77) -> 664.76 | J77: =VLOOKUP(C77,'IP PITSS'!$B$10:$U$91,3,0) -> 0 | K77: 8000 | L77: =(((+K77/30)*J77)*30%) -> 0 | M77: =VLOOKUP(C77,'IP PITSS'!$B$10:$I$91,8,0) -> 0 | N77: =+L77-M77 -> 0 | O77: SEI0017 | P77: =VLOOKUP(C77,'RESUMEN PITS'!$C$3:$V$102,20,0) -> -1344.8726 | Q77: =+D77+P77 -> -930.11264
A78: SEI0022 | B78: IP INNOVACION | C78: Najera Lopez Raul | D78: 593.6 | E78: 150 | F78: 0 | G78: =+N78 -> 0 | H78: =SUM(D78:G78) -> 743.6 | J78: =VLOOKUP(C78,'IP PITSS'!$B$10:$U$91,3,0) -> 0 | K78: 10000 | L78: =(((+K78/30)*J78)*30%) -> 0 | M78: =VLOOKUP(C78,'IP PITSS'!$B$10:$I$91,8,0) -> 0 | N78: =+L78-M78 -> 0 | O78: SEI0022 | P78: =VLOOKUP(C78,'RESUMEN PITS'!$C$3:$V$102,20,0) -> -1344.8726 | Q78: =+D78+P78 -> -751.27264
B79: IP INNOVACION | C79: Negrete Bejar Aide Sarai | D79: 207.63 | E79: 3503.7 | F79: 0 | G79: =+N79 -> 0 | H79: =SUM(D79:G79) -> 3711.33 | J79: =VLOOKUP(C79,'IP PITSS'!$B$10:$U$91,3,0) -> 0 | K79: 5000 | M79: =VLOOKUP(C79,'IP PITSS'!$B$10:$I$91,8,0) -> 0 | O79: SEI0016 | P79: =VLOOKUP(C79,'RESUMEN PITS'!$C$3:$V$102,20,0) -> -1344.8726 | Q79: =+D79+P79 -> -1137.2426
A80: SEI0524 | B80: IP INNOVACION | C80: Orea Gonzalez Concepcion Esteban | D80: 175.6 | E80: 900 | F80: 0 | G80: =+N80 -> 0 | H80: =SUM(D80:G80) -> 1075.6 | J80: =VLOOKUP(C80,'IP PITSS'!$B$10:$U$91,3,0) -> 0 | K80: 6300 | L80: =(((+K80/30)*J80)*30%) -> 0 | M80: =VLOOKUP(C80,'IP PITSS'!$B$10:$I$91,8,0) -> 0 | N80: =+L80-M80 -> 0 | O80: SEI0625 | P80: =VLOOKUP(C80,'RESUMEN PITS'!$C$3:$V$102,20,0) -> -1344.8726 | Q80: =+D80+P80 -> -1169.2726
A81: SEI0424 | B81: IP INNOVACION | C81: Palacios Ramos Jesus | D81: 416.4 | E81: 210 | F81: 0 | G81: =+N81 -> 0 | H81: =SUM(D81:G81) -> 626.4 | J81: =VLOOKUP(C81,'IP PITSS'!$B$10:$U$91,3,0) -> 0 | K81: 8000 | L81: =(((+K81/30)*J81)*30%) -> 0 | M81: =VLOOKUP(C81,'IP PITSS'!$B$10:$I$91,8,0) -> 0 | N81: =+L81-M81 -> 0 | O81: SEI0424 | P81: =VLOOKUP(C81,'RESUMEN PITS'!$C$3:$V$102,20,0) -> -1344.8726 | Q81: =+D81+P81 -> -928.47264
A82: SEI0519 | B82: IP INNOVACION | C82: Palacios Vega Luis Rosendo | D82: 52.4 | E82: 140 | F82: 0 | G82: =+N82 -> 0 | H82: =SUM(D82:G82) -> 192.4 | J82: =VLOOKUP(C82,'IP PITSS'!$B$10:$U$91,3,0) -> 0 | K82: 5000 | L82: =(((+K82/30)*J82)*30%) -> 0 | M82: =VLOOKUP(C82,'IP PITSS'!$B$10:$I$91,8,0) -> 0 | N82: =+L82-M82 -> 0 | O82: SEI0519 | P82: =VLOOKUP(C82,'RESUMEN PITS'!$C$3:$V$102,20,0) -> -1344.8726 | Q82: =+D82+P82 -> -1292.4726
A83: SEI0505 | B83: IP INNOVACION | C83: Perez Balboa Cesar | D83: 2194.26 | E83: 110 | F83: 0 | G83: =+N83 -> 0 | H83: =SUM(D83:G83) -> 2304.26 | J83: =VLOOKUP(C83,'IP PITSS'!$B$10:$U$91,3,0) -> 0 | K83: 10000 | L83: =(((+K83/30)*J83)*30%) -> 0 | M83: =VLOOKUP(C83,'IP PITSS'!$B$10:$I$91,8,0) -> 0 | N83: =+L83-M83 -> 0 | O83: SEI0489 | P83: =VLOOKUP(C83,'RESUMEN PITS'!$C$3:$V$102,20,0) -> -1344.8726 | Q83: =+D83+P83 -> 849.38736
A84: SEI0455 | B84: IP INNOVACION | C84: Perez Garcia Andres Alvaro | D84: 416.4 | E84: 315 | F84: 0 | G84: =+N84 -> 0 | H84: =SUM(D84:G84) -> 731.4 | J84: =VLOOKUP(C84,'IP PITSS'!$B$10:$U$91,3,0) -> 3 | K84: 8000 | L84: =(((+K84/30)*J84)*30%) -> 240 | M84: =VLOOKUP(C84,'IP PITSS'!$B$10:$I$91,8,0) -> 240 | N84: =+L84-M84 -> 0 | O84: SEI0494 | P84: =VLOOKUP(C84,'RESUMEN PITS'!$C$3:$V$102,20,0) -> -1344.8726 | Q84: =+D84+P84 -> -928.47264
A85: SEI0023 | B85: IP INNOVACION | C85: Puente Murguia Luis Felipe | D85: 222.6 | E85: 131.25 | F85: 0 | G85: =+N85 -> 0 | H85: =SUM(D85:G85) -> 353.85 | J85: =VLOOKUP(C85,'IP PITSS'!$B$10:$U$91,3,0) -> 0 | K85: 7000 | L85: =(((+K85/30)*J85)*30%) -> 0 | M85: =VLOOKUP(C85,'IP PITSS'!$B$10:$I$91,8,0) -> 0 | N85: =+L85-M85 -> 0 | O85: SEI0023 | P85: =VLOOKUP(C85,'RESUMEN PITS'!$C$3:$V$102,20,0) -> -1344.8726 | Q85: =+D85+P85 -> -1122.2726
A86: SEI0521 | B86: IP INNOVACION | C86: Rondero Savin Jacinto | D86: 221.2 | F86: 0 | G86: =+N86 -> 0 | H86: =SUM(D86:G86) -> 221.2 | J86: =VLOOKUP(C86,'IP PITSS'!$B$10:$U$91,3,0) -> 0 | K86: 7000 | L86: =(((+K86/30)*J86)*30%) -> 0 | M86: =VLOOKUP(C86,'IP PITSS'!$B$10:$I$91,8,0) -> 0 | N86: =+L86-M86 -> 0 | O86: SEI0622 | P86: =VLOOKUP(C86,'RESUMEN PITS'!$C$3:$V$102,20,0) -> -1344.8726 | Q86: =+D86+P86 -> -1123.6726
A87: SEI0465 | B87: IP INNOVACION | C87: Sandoval Garcia Luis | D87: 416.2 | E87: 180 | F87: 0 | G87: =+N87 -> 0 | H87: =SUM(D87:G87) -> 596.2 | J87: =VLOOKUP(C87,'IP PITSS'!$B$10:$U$91,3,0) -> 0 | K87: 8000 | L87: =(((+K87/30)*J87)*30%) -> 0 | M87: =VLOOKUP(C87,'IP PITSS'!$B$10:$I$91,8,0) -> 0 | N87: =+L87-M87 -> 0 | O87: SEI0503 | P87: =VLOOKUP(C87,'RESUMEN PITS'!$C$3:$V$102,20,0) -> -1344.8726 | Q87: =+D87+P87 -> -928.67264
A88: SEI0477 | B88: IP INNOVACION | C88: Sandoval Medina Demetrio | D88: 414.6 | E88: 510 | F88: 0 | G88: =+N88 -> 0 | H88: =SUM(D88:G88) -> 924.6 | J88: =VLOOKUP(C88,'IP PITSS'!$B$10:$U$91,3,0) -> 0 | K88: 8000 | L88: =(((+K88/30)*J88)*30%) -> 0 | M88: =VLOOKUP(C88,'IP PITSS'!$B$10:$I$91,8,0) -> 0 | N88: =+L88-M88 -> 0 | O88: SEI0603 | P88: =VLOOKUP(C88,'RESUMEN PITS'!$C$3:$V$102,20,0) -> -1344.8726 | Q88: =+D88+P88 -> -930.27264
A89: SEI0537 | B89: IP INNOVACION | C89: Serrano Esquivel Armando | D89: 1704.59 | E89: 437.5 | F89: 0 | G89: =+N89 -> 0 | H89: =SUM(D89:G89) -> 2142.09 | J89: =VLOOKUP(C89,'IP PITSS'!$B$10:$U$91,3,0) -> 0 | K89: 7000 | L89: =(((+K89/30)*J89)*30%) -> 0 | M89: =VLOOKUP(C89,'IP PITSS'!$B$10:$I$91,8,0) -> 0 | N89: =+L89-M89 -> 0 | O89: SEI0641 | P89: =VLOOKUP(C89,'RESUMEN PITS'!$C$3:$V$102,20,0) -> -1344.8726 | Q89: =+D89+P89 -> 359.71736
A90: SEI0498 | B90: IP INNOVACION | C90: Tenorio Alvarez Alberto Antonio | D90: 1667.24 | E90: 285 | F90: 0 | G90: =+N90 -> 85.04 | H90: =SUM(D90:G90) -> 2037.28 | J90: =VLOOKUP(C90,'IP PITSS'!$B$10:$U$91,3,0) -> 3 | K90: 10000 | L90: =(((+K90/30)*J90)*30%) -> 300 | M90: =VLOOKUP(C90,'IP PITSS'!$B$10:$I$91,8,0) -> 214.96 | N90: =+L90-M90 -> 85.04 | O90: SEI0482 | P90: =VLOOKUP(C90,'RESUMEN PITS'!$C$3:$V$102,20,0) -> -1344.8726 | Q90: =+D90+P90 -> 322.36736
A91: SEI0495 | B91: IP INNOVACION | C91: Torres Perez Carlos Alberto | D91: 1917.4 | E91: 1406.25 | F91: 0 | G91: =+N91 -> 0 | H91: =SUM(D91:G91) -> 3323.65 | J91: =VLOOKUP(C91,'IP PITSS'!$B$10:$U$91,3,0) -> 0 | K91: 10500 | L91: =(((+K91/30)*J91)*30%) -> 0 | M91: =VLOOKUP(C91,'IP PITSS'!$B$10:$I$91,8,0) -> 0 | N91: =+L91-M91 -> 0 | O91: SEI0479 | P91: =VLOOKUP(C91,'RESUMEN PITS'!$C$3:$V$102,20,0) -> -1344.8726 | Q91: =+D91+P91 -> 572.52736
A92: SEI0010 | B92: IP INNOVACION | C92: Torres Ricardez Alfredo | D92: 414.6 | E92: 175 | F92: 0 | G92: =+N92 -> 0 | H92: =SUM(D92:G92) -> 589.6 | J92: =VLOOKUP(C92,'IP PITSS'!$B$10:$U$91,3,0) -> 0 | K92: 8000 | L92: =(((+K92/30)*J92)*30%) -> 0 | M92: =VLOOKUP(C92,'IP PITSS'!$B$10:$I$91,8,0) -> 0 | N92: =+L92-M92 -> 0 | O92: SEI0010 | P92: =VLOOKUP(C92,'RESUMEN PITS'!$C$3:$V$102,20,0) -> -1344.8726 | Q92: =+D92+P92 -> -930.27264
A93: SEI0473 | B93: IP INNOVACION | C93: Torres Velazquez Juan Antonio | D93: 416.4 | E93: 360 | F93: 0 | G93: =+N93 -> 0 | H93: =SUM(D93:G93) -> 776.4 | J93: =VLOOKUP(C93,'IP PITSS'!$B$10:$U$91,3,0) -> 0 | K93: 8000 | L93: =(((+K93/30)*J93)*30%) -> 0 | M93: =VLOOKUP(C93,'IP PITSS'!$B$10:$I$91,8,0) -> 0 | N93: =+L93-M93 -> 0 | O93: SEI0604 | P93: =VLOOKUP(C93,'RESUMEN PITS'!$C$3:$V$102,20,0) -> -1344.8726 | Q93: =+D93+P93 -> -928.47264
A94: SEI0497 | B94: IP INNOVACION | C94: Treviño Alvarez Jorge Alberto | D94: 2667.34 | F94: 0 | G94: =+N94 -> 0 | H94: =SUM(D94:G94) -> 2667.34 | J94: =VLOOKUP(C94,'IP PITSS'!$B$10:$U$91,3,0) -> 0 | K94: 12000 | L94: =(((+K94/30)*J94)*30%) -> 0 | M94: =VLOOKUP(C94,'IP PITSS'!$B$10:$I$91,8,0) -> 0 | N94: =+L94-M94 -> 0 | O94: SEI0481 | P94: =VLOOKUP(C94,'RESUMEN PITS'!$C$3:$V$102,20,0) -> -1344.8726 | Q94: =+D94+P94 -> 1322.4674
A95: SEI0467 | B95: IP INNOVACION | C95: Vaca Valdez Guillermo | D95: 416.21 | E95: 270 | F95: 0 | G95: =+N95 -> 0 | H95: =SUM(D95:G95) -> 686.21 | J95: =VLOOKUP(C95,'IP PITSS'!$B$10:$U$91,3,0) -> 0 | K95: 8000 | L95: =(((+K95/30)*J95)*30%) -> 0 | M95: =VLOOKUP(C95,'IP PITSS'!$B$10:$I$91,8,0) -> 0 | N95: =+L95-M95 -> 0 | O95: SEI0505 | P95: =VLOOKUP(C95,'RESUMEN PITS'!$C$3:$V$102,20,0) -> -1344.8726 | Q95: =+D95+P95 -> -928.66264
A96: SEI0545 | B96: IP INNOVACION | C96: Vallarta Fonseca Mayra Karina | D96: 135.22 | F96: 0 | G96: =+N96 -> 0 | H96: =SUM(D96:G96) -> 135.22 | J96: =VLOOKUP(C96,'IP PITSS'!$B$10:$U$91,3,0) -> 0 | K96: 6000 | L96: =(((+K96/30)*J96)*30%) -> 0 | M96: =VLOOKUP(C96,'IP PITSS'!$B$10:$I$91,8,0) -> 0 | N96: =+L96-M96 -> 0 | O96: SEI0653 | P96: =VLOOKUP(C96,'RESUMEN PITS'!$C$3:$V$102,20,0) -> -1537.7236 | Q96: =+D96+P96 -> -1402.5036
A97: SEI0021 | B97: IP INNOVACION | C97: Velez Rodriguez Jaime | D97: 1135.3 | F97: 0 | G97: =+N97 -> 0 | H97: =SUM(D97:G97) -> 1135.3 | J97: =VLOOKUP(C97,'IP PITSS'!$B$10:$U$91,3,0) -> 0 | K97: 8000 | L97: =(((+K97/30)*J97)*30%) -> 0 | M97: =VLOOKUP(C97,'IP PITSS'!$B$10:$I$91,8,0) -> 0 | N97: =+L97-M97 -> 0 | O97: SEI0021 | P97: =VLOOKUP(C97,'RESUMEN PITS'!$C$3:$V$102,20,0) -> -1537.7236 | Q97: =+D97+P97 -> -402.42364
B98: IP INNOVACION | C98: Aguilar Garcia Rosa Paola | D98: 53.4 | F98: 0 | G98: =+N98 -> 0 | H98: =SUM(D98:G98) -> 53.4 | J98: =VLOOKUP(C98,'IP PITSS'!$B$10:$U$91,3,0) -> 0 | K98: 5000 | L98: =(((+K98/30)*J98)*30%) -> 0 | M98: =VLOOKUP(C98,'IP PITSS'!$B$10:$I$91,8,0) -> 0 | N98: =+L98-M98 -> 0 | O98: SEI0654 | P98: =VLOOKUP(C98,'RESUMEN PITS'!$C$3:$V$102,20,0) -> -56.562642 | Q98: =+D98+P98 -> -3.1626417
B99: IP INNOVACION | C99: Jauregui Madera Jorge Silvestre | D99: 134.2 | E99: 487.5 | F99: 0 | G99: =+N99 -> 0 | H99: =SUM(D99:G99) -> 621.7 | J99: =VLOOKUP(C99,'IP PITSS'!$B$10:$U$91,3,0) -> 0 | K99: 6000 | L99: =(((+K99/30)*J99)*30%) -> 0 | M99: =VLOOKUP(C99,'IP PITSS'!$B$10:$I$91,8,0) -> 0 | N99: =+L99-M99 -> 0 | O99: SEI0656 | P99: =VLOOKUP(C99,'RESUMEN PITS'!$C$3:$V$102,20,0) -> -1915.9536 | Q99: =+D99+P99 -> -1781.7536
B100: IP INNOVACION | C100: Hinojosa Guerrero Alejandro | D100: 174.6 | F100: 0 | G100: =+N100 -> 0 | H100: =SUM(D100:G100) -> 174.6 | J100: =VLOOKUP(C100,'IP PITSS'!$B$10:$U$91,3,0) -> 0 | K100: 6300 | L100: =(((+K100/30)*J100)*30%) -> 0 | M100: =VLOOKUP(C100,'IP PITSS'!$B$10:$I$91,8,0) -> 0 | N100: =+L100-M100 -> 0 | P100: =VLOOKUP(C100,'RESUMEN PITS'!$C$3:$V$102,20,0) -> -1915.9536 | Q100: =+D100+P100 -> -1741.3536
B101: IP INNOVACION | C101: Lopez Blanco Luis Eduardo | D101: 174.6 | F101: 0 | G101: =+N101 -> 0 | H101: =SUM(D101:G101) -> 174.6 | J101: =VLOOKUP(C101,'IP PITSS'!$B$10:$U$91,3,0) -> 0 | K101: 6300 | L101: =(((+K101/30)*J101)*30%) -> 0 | M101: =VLOOKUP(C101,'IP PITSS'!$B$10:$I$91,8,0) -> 0 | N101: =+L101-M101 -> 0 | P101: =VLOOKUP(C101,'RESUMEN PITS'!$C$3:$V$102,20,0) -> -1915.9536 | Q101: =+D101+P101 -> -1741.3536
B102: IP INNOVACION | C102: Vallarta Fonseca Maria Esmeralda | D102: 134.2 | E102: 390 | F102: 0 | G102: =+N102 -> 0 | H102: =SUM(D102:G102) -> 524.2 | J102: =VLOOKUP(C102,'IP PITSS'!$B$10:$U$91,3,0) -> 0 | K102: 6000 | L102: =(((+K102/30)*J102)*30%) -> 0 | M102: =VLOOKUP(C102,'IP PITSS'!$B$10:$I$91,8,0) -> 0 | N102: =+L102-M102 -> 0 | P102: =VLOOKUP(C102,'RESUMEN PITS'!$C$3:$V$102,20,0) -> -1313.9226 | Q102: =+D102+P102 -> -1179.7226
C103: AMEZCUA MAÑAGA TANIA | F103: 1160 | H103: =SUM(D103:G103) -> 1160
D104: =SUBTOTAL(9,D3:D103) -> 148607.19 | E104: =SUBTOTAL(9,E3:E103) -> 36199.2 | F104: =SUBTOTAL(9,F3:F103) -> 3960 | G104: =SUBTOTAL(9,G3:G103) -> 991.31 | H104: =SUBTOTAL(9,H3:H103) -> 189757.7 | I104: =SUBTOTAL(9,I3:I102) -> 0 | J104: =SUBTOTAL(9,J3:J102) -> 25 | K104: =SUBTOTAL(9,K3:K102) -> 1008431 | L104: =SUBTOTAL(9,L3:L102) -> 2558.5 | M104: =SUBTOTAL(9,M3:M102) -> 1567.19 | N104: =SUBTOTAL(9,N3:N102) -> 991.31 | O104: =SUBTOTAL(9,O3:O102) -> 0
...

Sheet RESUMEN PITS
F1: SINDICATO
A2: CLAVE | B2: EMPRESA | C2: NOMBRE | D2: NETO IMSS | F2: SUELDO SINDICATO | G2: BONO | H2: COMISION | I2: PRIMA VACACIONAL SINDICATO | J2: B | K2: NETO A PAGAR | L2: NETO MENSUAL | M2: NETO QUINCENAL SEITON | N2: C | O2: prima vacacional | P2: COMISION Y PRIMA VACACIONAL | Q2: INFONAVIT | R2: FONACOT | S2: DESCUENTOS | T2: D | U2: TOTAL GENERAL | V2: DIFERENCIAS | W2: OBSERVACIONES
A3: SEI0009 | B3: CONSULTORIA | C3: Gutierrez Gutierrez Luis Arturo | D3: =VLOOKUP(C3,'CPD PITSS'!B10:V27,21,0) -> 2774.4 | F3: =VLOOKUP(C3,'SIND PITS'!$C$3:$H$104,2,0) -> 1475.6 | G3: =VLOOKUP(C3,'SIND PITS'!$C$3:$E$104,3,0) -> 0 | H3: =VLOOKUP(C3,'SIND PITS'!$C$3:$F$104,4,0) -> 0 | I3: =VLOOKUP(C3,'SIND PITS'!$C$3:$G$104,5,0) -> 0 | K3: =SUM(D3:I3) -> 4250 | L3: 8500 | M3: =+L3/2 -> 4250 | O3: =VLOOKUP($C3,'CPD PITSS'!$B$10:$V$27,8,0) -> 0 | P3: =+G3+H3+I3 -> 0 | Q3: =(VLOOKUP($C3,'CPD PITSS'!$B$10:$V$27,13,0))+(VLOOKUP($C3,'CPD PITSS'!$B$10:$V$27,14,0)) -> 0 | S3: =VLOOKUP(C3,'CPD PITSS'!$B$10:$S$27,18,0) -> 0 | U3: =+K3-O3-P3+Q3+R3+S3+IFERROR(VLOOKUP('RESUMEN PITS'!C3,'IP PITSS'!$B$10:$M$91,10),0)+IFERROR(VLOOKUP('RESUMEN PITS'!C3,'IP PITSS'!$B$10:$M$91,11),0)+IFERROR(VLOOKUP('RESUMEN PITS'!C3,'IP PITSS'!$B$10:$M$91,12),0)+VLOOKUP("Comision",'IP PITSS'!$I$97:$J$108,2)/COUNT($F$9:$F$111)+IFERROR(VLOOKUP('RESUMEN PITS'!C3,'IP PITSS'!$B$10:$AD$91,15),0)+IFERROR(VLOOKUP('RESUMEN PITS'!C3,'IP PITSS'!$B$10:$AD$91,21),0)+IFERROR(VLOOKUP('RESUMEN PITS'!C3,'IP PITSS'!$B$10:$AD$91,22),0)+IFERROR(VLOOKUP('RESUMEN PITS'!C3,'IP PITSS'!$B$10:$AD$91,23),0)+IFERROR(VLOOKUP('RESUMEN PITS'!C3,'IP PITSS'!$B$10:$AD$91,24),0)+IFERROR(VLOOKUP('RESUMEN PITS'!C3,'IP PITSS'!$B$10:$AD$91,26),0)+IFERROR(VLOOKUP('RESUMEN PITS'!C3,'IP PITSS'!$B$10:$AD$91,28),0)+IFERROR(VLOOKUP('RESUMEN PITS'!C3,'IP PITSS'!$B$10:$AD$91,29),0)+IFERROR(VLOOKUP('RESUMEN PITS'!C3,'IP PITSS'!$B$10:$AD$91,9),0)*2% -> 5667.0416 | V3: =+M3-U3 -> -1417.0416 | X3: SEI0009
A4: SEI0026 | B4: CONSULTORIA | C4: Patricio Aguilar Jhonattan Cristian | D4: =VLOOKUP(C4,'CPD PITSS'!B11:V28,21,0) -> 2911.8 | F4: =VLOOKUP(C4,'SIND PITS'!$C$3:$H$104,2,0) -> 1588.2 | G4: =VLOOKUP(C4,'SIND PITS'!$C$3:$E$104,3,0) -> 400 | H4: =VLOOKUP(C4,'SIND PITS'!$C$3:$F$104,4,0) -> 0 | I4: =VLOOKUP(C4,'SIND PITS'!$C$3:$G$104,5,0) -> 0 | K4: =SUM(D4:I4) -> 4900 | L4: 9000 | M4: =+L4/2 -> 4500 | O4: =VLOOKUP($C4,'CPD PITSS'!$B$10:$V$27,8,0) -> 0 | P4: =+G4+H4+I4 -> 400 | Q4: =(VLOOKUP($C4,'CPD PITSS'!$B$10:$V$27,13,0))+(VLOOKUP($C4,'CPD PITSS'!$B$10:$V$27,14,0)) -> 0 | S4: =VLOOKUP(C4,'CPD PITSS'!$B$10:$S$27,18,0) -> 0 | U4: =+K4-O4-P4+Q4+R4+S4+IFERROR(VLOOKUP('RESUMEN PITS'!C4,'IP PITSS'!$B$10:$M$91,10),0)+IFERROR(VLOOKUP('RESUMEN PITS'!C4,'IP PITSS'!$B$10:$M$91,11),0)+IFERROR(VLOOKUP('RESUMEN PITS'!C4,'IP PITSS'!$B$10:$M$91,12),0)+VLOOKUP("Comision",'IP PITSS'!$I$97:$J$108,2)/COUNT($F$9:$F$111)+IFERROR(VLOOKUP('RESUMEN PITS'!C4,'IP PITSS'!$B$10:$AD$91,15),0)+IFERROR(VLOOKUP('RESUMEN PITS'!C4,'IP PITSS'!$B$10:$AD$91,21),0)+IFERROR(VLOOKUP('RESUMEN PITS'!C4,'IP PITSS'!$B$10:$AD$91,22),0)+IFERROR(VLOOKUP('RESUMEN PITS'!C4,'IP PITSS'!$B$10:$AD$91,23),0)+IFERROR(VLOOKUP('RESUMEN PITS'!C4,'IP PITSS'!$B$10:$AD$91,24),0)+IFERROR(VLOOKUP('RESUMEN PITS'!C4,'IP PITSS'!$B$10:$AD$91,26),0)+IFERROR(VLOOKUP('RESUMEN PITS'!C4,'IP PITSS'!$B$10:$AD$91,28),0)+IFERROR(VLOOKUP('RESUMEN PITS'!C4,'IP PITSS'!$B$10:$AD$91,29),0)+IFERROR(VLOOKUP('RESUMEN PITS'!C4,'IP PITSS'!$B$10:$AD$91,9),0)*2% -> 5844.8726 | V4: =+M4-U4 -> -1344.8726 | X4: SEI0026
A5: SEI0040 | B5: CONSULTORIA | C5: Mora Ramirez Acal Aldo Isidro | D5: =VLOOKUP(C5,'CPD PITSS'!B12:V29,21,0) -> 4231 | F5: =VLOOKUP(C5,'SIND PITS'!$C$3:$H$104,2,0) -> 2464 | G5: =VLOOKUP(C5,'SIND PITS'!$C$3:$E$104,3,0) -> 1000 | H5: =VLOOKUP(C5,'SIND PITS'!$C$3:$F$104,4,0) -> 0 | I5: =VLOOKUP(C5,'SIND PITS'!$C$3:$G$104,5,0) -> 195 | K5: =SUM(D5:I5) -> 7890 | L5: 13000 | M5: =+L5/2 -> 6500 | O5: =VLOOKUP($C5,'CPD PITSS'!$B$10:$V$27,8,0) -> 195 | P5: =+G5+H5+I5 -> 1195 | Q5: =(VLOOKUP($C5,'CPD PITSS'!$B$10:$V$27,13,0))+(VLOOKUP($C5,'CPD PITSS'!$B$10:$V$27,14,0)) -> 0 | S5: =VLOOKUP(C5,'CPD PITSS'!$B$10:$S$27,18,0) -> 0 | U5: =+K5-O5-P5+Q5+R5+S5+IFERROR(VLOOKUP('RESUMEN PITS'!C5,'IP PITSS'!$B$10:$M$91,10),0)+IFERROR(VLOOKUP('RESUMEN PITS'!C5,'IP PITSS'!$B$10:$M$91,11),0)+IFERROR(VLOOKUP('RESUMEN PITS'!C5,'IP PITSS'!$B$10:$M$91,12),0)+VLOOKUP("Comision",'IP PITSS'!$I$97:$J$108,2)/COUNT($F$9:$F$111)+IFERROR(VLOOKUP('RESUMEN PITS'!C5,'IP PITSS'!$B$10:$AD$91,15),0)+IFERROR(VLOOKUP('RESUMEN PITS'!C5,'IP PITSS'!$B$10:$AD$91,21),0)+IFERROR(VLOOKUP('RESUMEN PITS'!C5,'IP PITSS'!$B$10:$AD$91,22),0)+IFERROR(VLOOKUP('RESUMEN PITS'!C5,'IP PITSS'!$B$10:$AD$91,23),0)+IFERROR(VLOOKUP('RESUMEN PITS'!C5,'IP PITSS'!$B$10:$AD$91,24),0)+IFERROR(VLOOKUP('RESUMEN PITS'!C5,'IP PITSS'!$B$10:$AD$91,26),0)+IFERROR(VLOOKUP('RESUMEN PITS'!C5,'IP PITSS'!$B$10:$AD$91,28),0)+IFERROR(VLOOKUP('RESUMEN PITS'!C5,'IP PITSS'!$B$10:$AD$91,29),0)+IFERROR(VLOOKUP('RESUMEN PITS'!C5,'IP PITSS'!$B$10:$AD$91,9),0)*2% -> 8415.9536 | V5: =+M5-U5 -> -1915.9536 | X5: SEI0040
A6: SEI0041 | B6: CONSULTORIA | C6: Vazquez Perez Miguel Angel | D6: =VLOOKUP(C6,'CPD PITSS'!B13:V30,21,0) -> 5074 | F6: =VLOOKUP(C6,'SIND PITS'!$C$3:$H$104,2,0) -> 4176 | G6: =VLOOKUP(C6,'SIND PITS'!$C$3:$E$104,3,0) -> 750 | H6: =VLOOKUP(C6,'SIND PITS'!$C$3:$F$104,4,0) -> 0 | I6: =VLOOKUP(C6,'SIND PITS'!$C$3:$G$104,5,0) -> 0 | K6: =SUM(D6:I6) -> 10000 | L6: 18500 | M6: =+L6/2 -> 9250 | O6: =VLOOKUP($C6,'CPD PITSS'!$B$10:$V$27,8,0) -> 0 | P6: =+G6+H6+I6 -> 750 | Q6: =(VLOOKUP($C6,'CPD PITSS'!$B$10:$V$27,13,0))+(VLOOKUP($C6,'CPD PITSS'!$B$10:$V$27,14,0)) -> 0 | S6: =VLOOKUP(C6,'CPD PITSS'!$B$10:$S$27,18,0) -> 0 | U6: =+K6-O6-P6+Q6+R6+S6+IFERROR(VLOOKUP('RESUMEN PITS'!C6,'IP PITSS'!$B$10:$M$91,10),0)+IFERROR(VLOOKUP('RESUMEN PITS'!C6,'IP PITSS'!$B$10:$M$91,11),0)+IFERROR(VLOOKUP('RESUMEN PITS'!C6,'IP PITSS'!$B$10:$M$91,12),0)+VLOOKUP("Comision",'IP PITSS'!$I$97:$J$108,2)/COUNT($F$9:$F$111)+IFERROR(VLOOKUP('RESUMEN PITS'!C6,'IP PITSS'!$B$10:$AD$91,15),0)+IFERROR(VLOOKUP('RESUMEN PITS'!C6,'IP PITSS'!$B$10:$AD$91,21),0)+IFERROR(VLOOKUP('RESUMEN PITS'!C6,'IP PITSS'!$B$10:$AD$91,22),0)+IFERROR(VLOOKUP('RESUMEN PITS'!C6,'IP PITSS'!$B$10:$AD$91,23),0)+IFERROR(VLOOKUP('RESUMEN PITS'!C6,'IP PITSS'!$B$10:$AD$91,24),0)+IFERROR(VLOOKUP('RESUMEN PITS'!C6,'IP PITSS'!$B$10:$AD$91,26),0)+IFERROR(VLOOKUP('RESUMEN PITS'!C6,'IP PITSS'!$B$10:$AD$91,28),0)+IFERROR(VLOOKUP('RESUMEN PITS'!C6,'IP PITSS'!$B$10:$AD$91,29),0)+IFERROR(VLOOKUP('RESUMEN PITS'!C6,'IP PITSS'!$B$10:$AD$91,9),0)*2% -> 10787.724 | V6: =+M6-U6 -> -1537.7236 | X6: SEI0041
A7: SEI0088 | B7: CONSULTORIA | C7: Morgado Fernandez Martin | D7: =VLOOKUP(C7,'CPD PITSS'!B14:V31,21,0) -> 4623.8 | F7: =VLOOKUP(C7,'SIND PITS'!$C$3:$H$104,2,0) -> 2600.25 | G7: =VLOOKUP(C7,'SIND PITS'!$C$3:$E$104,3,0) -> 75 | H7: =VLOOKUP(C7,'SIND PITS'!$C$3:$F$104,4,0) -> 0 | I7: =VLOOKUP(C7,'SIND PITS'!$C$3:$G$104,5,0) -> 0 | K7: =SUM(D7:I7) -> 7299.05 | L7: 15000 | M7: =+L7/2 -> 7500 | O7: =VLOOKUP($C7,'CPD PITSS'!$B$10:$V$27,8,0) -> 0 | P7: =+G7+H7+I7 -> 75 | Q7: =(VLOOKUP($C7,'CPD PITSS'!$B$10:$V$27,13,0))+(VLOOKUP($C7,'CPD PITSS'!$B$10:$V$27,14,0)) -> 0 | S7: =VLOOKUP(C7,'CPD PITSS'!$B$10:$S$27,18,0) -> 275.95 | U7: =+K7-O7-P7+Q7+R7+S7+IFERROR(VLOOKUP('RESUMEN PITS'!C7,'IP PITSS'!$B$10:$M$91,10),0)+IFERROR(VLOOKUP('RESUMEN PITS'!C7,'IP PITSS'!$B$10:$M$91,11),0)+IFERROR(VLOOKUP('RESUMEN PITS'!C7,'IP PITSS'!$B$10:$M$91,12),0)+VLOOKUP("Comision",'IP PITSS'!$I$97:$J$108,2)/COUNT($F$9:$F$111)+IFERROR(VLOOKUP('RESUMEN PITS'!C7,'IP PITSS'!$B$10:$AD$91,15),0)+IFERROR(VLOOKUP('RESUMEN PITS'!C7,'IP PITSS'!$B$10:$AD$91,21),0)+IFERROR(VLOOKUP('RESUMEN PITS'!C7,'IP PITSS'!$B$10:$AD$91,22),0)+IFERROR(VLOOKUP('RESUMEN PITS'!C7,'IP PITSS'!$B$10:$AD$91,23),0)+IFERROR(VLOOKUP('RESUMEN PITS'!C7,'IP PITSS'!$B$10:$AD$91,24),0)+IFERROR(VLOOKUP('RESUMEN PITS'!C7,'IP PITSS'!$B$10:$AD$91,26),0)+IFERROR(VLOOKUP('RESUMEN PITS'!C7,'IP PITSS'!$B$10:$AD$91,28),0)+IFERROR(VLOOKUP('RESUMEN PITS'!C7,'IP PITSS'!$B$10:$AD$91,29),0)+IFERROR(VLOOKUP('RESUMEN PITS'!C7,'IP PITSS'!$B$10:$AD$91,9),0)*2% -> 8844.8726 | V7: =+M7-U7 -> -1344.8726 | X7: SEI0088
A8: SEI0097 | B8: CONSULTORIA | C8: Arreola Jimenez Jose Nieves | D8: =VLOOKUP(C8,'CPD PITSS'!B15:V32,21,0) -> 1975.2 | F8: =VLOOKUP(C8,'SIND PITS'!$C$3:$H$104,2,0) -> 1558.02 | G8: =VLOOKUP(C8,'SIND PITS'!$C$3:$E$104,3,0) -> 420 | H8: =VLOOKUP(C8,'SIND PITS'!$C$3:$F$104,4,0) -> 0 | I8: =VLOOKUP(C8,'SIND PITS'!$C$3:$G$104,5,0) -> 0 | K8: =SUM(D8:I8) -> 3953.22 | L8: 10150 | M8: =+L8/2 -> 5075 | O8: =VLOOKUP($C8,'CPD PITSS'!$B$10:$V$27,8,0) -> 0 | P8: =+G8+H8+I8 -> 420 | Q8: =(VLOOKUP($C8,'CPD PITSS'!$B$10:$V$27,13,0))+(VLOOKUP($C8,'CPD PITSS'!$B$10:$V$27,14,0)) -> 1541.78 | S8: =VLOOKUP(C8,'CPD PITSS'!$B$10:$S$27,18,0) -> 0 | U8: =+K8-O8-P8+Q8+R8+S8+IFERROR(VLOOKUP('RESUMEN PITS'!C8,'IP PITSS'!$B$10:$M$91,10),0)+IFERROR(VLOOKUP('RESUMEN PITS'!C8,'IP PITSS'!$B$10:$M$91,11),0)+IFERROR(VLOOKUP('RESUMEN PITS'!C8,'IP PITSS'!$B$10:$M$91,12),0)+VLOOKUP("Comision",'IP PITSS'!$I$97:$J$108,2)/COUNT($F$9:$F$111)+IFERROR(VLOOKUP('RESUMEN PITS'!C8,'IP PITSS'!$B$10:$AD$91,15),0)+IFERROR(VLOOKUP('RESUMEN PITS'!C8,'IP PITSS'!$B$10:$AD$91,21),0)+IFERROR(VLOOKUP('RESUMEN PITS'!C8,'IP PITSS'!$B$10:$AD$91,22),0)+IFERROR(VLOOKUP('RESUMEN PITS'!C8,'IP PITSS'!$B$10:$AD$91,23),0)+IFERROR(VLOOKUP('RESUMEN PITS'!C8,'IP PITSS'!$B$10:$AD$91,24),0)+IFERROR(VLOOKUP('RESUMEN PITS'!C8,'IP PITSS'!$B$10:$AD$91,26),0)+IFERROR(VLOOKUP('RESUMEN PITS'!C8,'IP PITSS'!$B$10:$AD$91,28),0)+IFERROR(VLOOKUP('RESUMEN PITS'!C8,'IP PITSS'!$B$10:$AD$91,29),0)+IFERROR(VLOOKUP('RESUMEN PITS'!C8,'IP PITSS'!$B$10:$AD$91,9),0)*2% -> 5131.5626 | V8: =+M8-U8 -> -56.562642 | X8: SEI0097
A9: SEI0099 | B9: CONSULTORIA | C9: Garcia Villicaña Ricardo Pascual | D9: =VLOOKUP(C9,'CPD PITSS'!B16:V33,21,0) -> 4899.8 | F9: =VLOOKUP(C9,'SIND PITS'!$C$3:$H$104,2,0) -> 2600.2 | G9: =VLOOKUP(C9,'SIND PITS'!$C$3:$E$104,3,0) -> 0 | H9: =VLOOKUP(C9,'SIND PITS'!$C$3:$F$104,4,0) -> 0 | I9: =VLOOKUP(C9,'SIND PITS'!$C$3:$G$104,5,0) -> 0 | K9: =SUM(D9:I9) -> 7500 | L9: 15000 | M9: =+L9/2 -> 7500 | O9: =VLOOKUP($C9,'CPD PITSS'!$B$10:$V$27,8,0) -> 0 | P9: =+G9+H9+I9 -> 0 | Q9: =(VLOOKUP($C9,'CPD PITSS'!$B$10:$V$27,13,0))+(VLOOKUP($C9,'CPD PITSS'!$B$10:$V$27,14,0)) -> 0 | S9: =VLOOKUP(C9,'CPD PITSS'!$B$10:$S$27,18,0) -> 0 | U9: =+K9-O9-P9+Q9+R9+S9+IFERROR(VLOOKUP('RESUMEN PITS'!C9,'IP PITSS'!$B$10:$M$91,10),0)+IFERROR(VLOOKUP('RESUMEN PITS'!C9,'IP PITSS'!$B$10:$M$91,11),0)+IFERROR(VLOOKUP('RESUMEN PITS'!C9,'IP PITSS'!$B$10:$M$91,12),0)+VLOOKUP("Comision",'IP PITSS'!$I$97:$J$108,2)/COUNT($F$9:$F$111)+IFERROR(VLOOKUP('RESUMEN PITS'!C9,'IP PITSS'!$B$10:$AD$91,15),0)+IFERROR(VLOOKUP('RESUMEN PITS'!C9,'IP PITSS'!$B$10:$AD$91,21),0)+IFERROR(VLOOKUP('RESUMEN PITS'!C9,'IP PITSS'!$B$10:$AD$91,22),0)+IFERROR(VLOOKUP('RESUMEN PITS'!C9,'IP PITSS'!$B$10:$AD$91,23),0)+IFERROR(VLOOKUP('RESUMEN PITS'!C9,'IP PITSS'!$B$10:$AD$91,24),0)+IFERROR(VLOOKUP('RESUMEN PITS'!C9,'IP PITSS'!$B$10:$AD$91,26),0)+IFERROR(VLOOKUP('RESUMEN PITS'!C9,'IP PITSS'!$B$10:$AD$91,28),0)+IFERROR(VLOOKUP('RESUMEN PITS'!C9,'IP PITSS'!$B$10:$AD$91,29),0)+IFERROR(VLOOKUP('RESUMEN PITS'!C9,'IP PITSS'!$B$10:$AD$91,9),0)*2% -> 8917.0416 | V9: =+M9-U9 -> -1417.0416 | X9: SEI0099
A10: SEI0108 | B10: CONSULTORIA | C10: Caballero Diaz Francisco Javier | D10: =VLOOKUP(C10,'CPD PITSS'!B17:V34,21,0) -> 1823.2 | F10: =VLOOKUP(C10,'SIND PITS'!$C$3:$H$104,2,0) -> 1558.11 | G10: =VLOOKUP(C10,'SIND PITS'!$C$3:$E$104,3,0) -> 210 | H10: =VLOOKUP(C10,'SIND PITS'!$C$3:$F$104,4,0) -> 0 | I10: =VLOOKUP(C10,'SIND PITS'!$C$3:$G$104,5,0) -> 274.51 | K10: =SUM(D10:I10) -> 3865.82 | L10: 10150 | M10: =+L10/2 -> 5075 | O10: =VLOOKUP($C10,'CPD PITSS'!$B$10:$V$27,8,0) -> 334.49 | P10: =+G10+H10+I10 -> 484.51 | Q10: =(VLOOKUP($C10,'CPD PITSS'!$B$10:$V$27,13,0))+(VLOOKUP($C10,'CPD PITSS'!$B$10:$V$27,14,0)) -> 1789.38 | S10: =VLOOKUP(C10,'CPD PITSS'!$B$10:$S$27,18,0) -> 238.8 | U10: =+K10-O10-P10+Q10+R10+S10+IFERROR(VLOOKUP('RESUMEN PITS'!C10,'IP PITSS'!$B$10:$M$91,10),0)+IFERROR(VLOOKUP('RESUMEN PITS'!C10,'IP PITSS'!$B$10:$M$91,11),0)+IFERROR(VLOOKUP('RESUMEN PITS'!C10,'IP PITSS'!$B$10:$M$91,12),0)+VLOOKUP("Comision",'IP PITSS'!$I$97:$J$108,2)/COUNT($F$9:$F$111)+IFERROR(VLOOKUP('RESUMEN PITS'!C10,'IP PITSS'!$B$10:$AD$91,15),0)+IFERROR(VLOOKUP('RESUMEN PITS'!C10,'IP PITSS'!$B$10:$AD$91,21),0)+IFERROR(VLOOKUP('RESUMEN PITS'!C10,'IP PITSS'!$B$10:$AD$91,22),0)+IFERROR(VLOOKUP('RESUMEN PITS'!C10,'IP PITSS'!$B$10:$AD$91,23),0)+IFERROR(VLOOKUP('RESUMEN PITS'!C10,'IP PITSS'!$B$10:$AD$91,24),0)+IFERROR(VLOOKUP('RESUMEN PITS'!C10,'IP PITSS'!$B$10:$AD$91,26),0)+IFERROR(VLOOKUP('RESUMEN PITS'!C10,'IP PITSS'!$B$10:$AD$91,28),0)+IFERROR(VLOOKUP('RESUMEN PITS'!C10,'IP PITSS'!$B$10:$AD$91,29),0)+IFERROR(VLOOKUP('RESUMEN PITS'!C10,'IP PITSS'!$B$10:$AD$91,9),0)*2% -> 5131.5626 | V10: =+M10-U10 -> -56.562642 | X10: SEI0108
A11: SEI0116 | B11: CONSULTORIA | C11: Casillas Cardona Cesar Alejandro | D11: =VLOOKUP(C11,'CPD PITSS'!B18:V35,21,0) -> 3346.4 | F11: =VLOOKUP(C11,'SIND PITS'!$C$3:$H$104,2,0) -> 1891.17 | G11: =VLOOKUP(C11,'SIND PITS'!$C$3:$E$104,3,0) -> 0 | H11: =VLOOKUP(C11,'SIND PITS'!$C$3:$F$104,4,0) -> 0 | I11: =VLOOKUP(C11,'SIND PITS'!$C$3:$G$104,5,0) -> 107.5 | K11: =SUM(D11:I11) -> 5345.07 | L11: 12000 | M11: =+L11/2 -> 6000 | O11: =VLOOKUP($C11,'CPD PITSS'!$B$10:$V$27,8,0) -> 132.5 | P11: =+G11+H11+I11 -> 107.5 | Q11: =(VLOOKUP($C11,'CPD PITSS'!$B$10:$V$27,13,0))+(VLOOKUP($C11,'CPD PITSS'!$B$10:$V$27,14,0)) -> 894.93 | S11: =VLOOKUP(C11,'CPD PITSS'!$B$10:$S$27,18,0) -> 0 | U11: =+K11-O11-P11+Q11+R11+S11+IFERROR(VLOOKUP('RESUMEN PITS'!C11,'IP PITSS'!$B$10:$M$91,10),0)+IFERROR(VLOOKUP('RESUMEN PITS'!C11,'IP PITSS'!$B$10:$M$91,11),0)+IFERROR(VLOOKUP('RESUMEN PITS'!C11,'IP PITSS'!$B$10:$M$91,12),0)+VLOOKUP("Comision",'IP PITSS'!$I$97:$J$108,2)/COUNT($F$9:$F$111)+IFERROR(VLOOKUP('RESUMEN PITS'!C11,'IP PITSS'!$B$10:$AD$91,15),0)+IFERROR(VLOOKUP('RESUMEN PITS'!C11,'IP PITSS'!$B$10:$AD$91,21),0)+IFERROR(VLOOKUP('RESUMEN PITS'!C11,'IP PITSS'!$B$10:$AD$91,22),0)+IFERROR(VLOOKUP('RESUMEN PITS'!C11,'IP PITSS'!$B$10:$AD$91,23),0)+IFERROR(VLOOKUP('RESUMEN PITS'!C11,'IP PITSS'!$B$10:$AD$91,24),0)+IFERROR(VLOOKUP('RESUMEN PITS'!C11,'IP PITSS'!$B$10:$AD$91,26),0)+IFERROR(VLOOKUP('RESUMEN PITS'!C11,'IP PITSS'!$B$10:$AD$91,28),0)+IFERROR(VLOOKUP('RESUMEN PITS'!C11,'IP PITSS'!$B$10:$AD$91,29),0)+IFERROR(VLOOKUP('RESUMEN PITS'!C11,'IP PITSS'!$B$10:$AD$91,9),0)*2% -> 6056.5626 | V11: =+M11-U11 -> -56.562642 | X11: SEI0116
A12: SEI0117 | B12: CONSULTORIA | C12: Mariscal Romero Luis Adrian | D12: =VLOOKUP(C12,'CPD PITSS'!B19:V36,21,0) -> 3109.2 | F12: =VLOOKUP(C12,'SIND PITS'!$C$3:$H$104,2,0) -> 2751.08 | G12: =VLOOKUP(C12,'SIND PITS'!$C$3:$E$104,3,0) -> 0 | H12: =VLOOKUP(C12,'SIND PITS'!$C$3:$F$104,4,0) -> 0 | I12: =VLOOKUP(C12,'SIND PITS'!$C$3:$G$104,5,0) -> 0 | K12: =SUM(D12:I12) -> 5860.28 | L12: 15000 | M12: =+L12/2 -> 7500 | O12: =VLOOKUP($C12,'CPD PITSS'!$B$10:$V$27,8,0) -> 0 | P12: =+G12+H12+I12 -> 0 | Q12: =(VLOOKUP($C12,'CPD PITSS'!$B$10:$V$27,13,0))+(VLOOKUP($C12,'CPD PITSS'!$B$10:$V$27,14,0)) -> 1639.72 | S12: =VLOOKUP(C12,'CPD PITSS'!$B$10:$S$27,18,0) -> 0 | U12: =+K12-O12-P12+Q12+R12+S12+IFERROR(VLOOKUP('RESUMEN PITS'!C12,'IP PITSS'!$B$10:$M$91,10),0)+IFERROR(VLOOKUP('RESUMEN PITS'!C12,'IP PITSS'!$B$10:$M$91,11),0)+IFERROR(VLOOKUP('RESUMEN PITS'!C12,'IP PITSS'!$B$10:$M$91,12),0)+VLOOKUP("Comision",'IP PITSS'!$I$97:$J$108,2)/COUNT($F$9:$F$111)+IFERROR(VLOOKUP('RESUMEN PITS'!C12,'IP PITSS'!$B$10:$AD$91,15),0)+IFERROR(VLOOKUP('RESUMEN PITS'!C12,'IP PITSS'!$B$10:$AD$91,21),0)+IFERROR(VLOOKUP('RESUMEN PITS'!C12,'IP PITSS'!$B$10:$AD$91,22),0)+IFERROR(VLOOKUP('RESUMEN PITS'!C12,'IP PITSS'!$B$10:$AD$91,23),0)+IFERROR(VLOOKUP('RESUMEN PITS'!C12,'IP PITSS'!$B$10:$AD$91,24),0)+IFERROR(VLOOKUP('RESUMEN PITS'!C12,'IP PITSS'!$B$10:$AD$91,26),0)+IFERROR(VLOOKUP('RESUMEN PITS'!C12,'IP PITSS'!$B$10:$AD$91,28),0)+IFERROR(VLOOKUP('RESUMEN PITS'!C12,'IP PITSS'!$B$10:$AD$91,29),0)+IFERROR(VLOOKUP('RESUMEN PITS'!C12,'IP PITSS'!$B$10:$AD$91,9),0)*2% -> 9415.9536 | V12: =+M12-U12 -> -1915.9536 | X12: SEI0117
A13: SEI0118 | B13: CONSULTORIA | C13: Arroyo Ramirez Hector Hugo | D13: =VLOOKUP(C13,'CPD PITSS'!B20:V37,21,0) -> 2739.4 | F13: =VLOOKUP(C13,'SIND PITS'!$C$3:$H$104,2,0) -> 2102.72 | G13: =VLOOKUP(C13,'SIND PITS'!$C$3:$E$104,3,0) -> 0 | H13: =VLOOKUP(C13,'SIND PITS'!$C$3:$F$104,4,0) -> 0 | I13: =VLOOKUP(C13,'SIND PITS'!$C$3:$G$104,5,0) -> 0 | K13: =SUM(D13:I13) -> 4842.12 | L13: 13000 | M13: =+L13/2 -> 6500 | O13: =VLOOKUP($C13,'CPD PITSS'!$B$10:$V$27,8,0) -> 0 | P13: =+G13+H13+I13 -> 0 | Q13: =(VLOOKUP($C13,'CPD PITSS'!$B$10:$V$27,13,0))+(VLOOKUP($C13,'CPD PITSS'!$B$10:$V$27,14,0)) -> 1402.48 | S13: =VLOOKUP(C13,'CPD PITSS'!$B$10:$S$27,18,0) -> 255.4 | U13: =+K13-O13-P13+Q13+R13+S13+IFERROR(VLOOKUP('RESUMEN PITS'!C13,'IP PITSS'!$B$10:$M$91,10),0)+IFERROR(VLOOKUP('RESUMEN PITS'!C13,'IP PITSS'!$B$10:$M$91,11),0)+IFERROR(VLOOKUP('RESUMEN PITS'!C13,'IP PITSS'!$B$10:$M$91,12),0)+VLOOKUP("Comision",'IP PITSS'!$I$97:$J$108,2)/COUNT($F$9:$F$111)+IFERROR(VLOOKUP('RESUMEN PITS'!C13,'IP PITSS'!$B$10:$AD$91,15),0)+IFERROR(VLOOKUP('RESUMEN PITS'!C13,'IP PITSS'!$B$10:$AD$91,21),0)+IFERROR(VLOOKUP('RESUMEN PITS'!C13,'IP PITSS'!$B$10:$AD$91,22),0)+IFERROR(VLOOKUP('RESUMEN PITS'!C13,'IP PITSS'!$B$10:$AD$91,23),0)+IFERROR(VLOOKUP('RESUMEN PITS'!C13,'IP PITSS'!$B$10:$AD$91,24),0)+IFERROR(VLOOKUP('RESUMEN PITS'!C13,'IP PITSS'!$B$10:$AD$91,26),0)+IFERROR(VLOOKUP('RESUMEN PITS'!C13,'IP PITSS'!$B$10:$AD$91,28),0)+IFERROR(VLOOKUP('RESUMEN PITS'!C13,'IP PITSS'!$B$10:$AD$91,29),0)+IFERROR(VLOOKUP('RESUMEN PITS'!C13,'IP PITSS'!$B$10:$AD$91,9),0)*2% -> 6556.5626 | V13: =+M13-U13 -> -56.562642 | X13: SEI0118
A14: SEI0127 | B14: CONSULTORIA | C14: Hernandez Ochoa Eduardo | D14: =VLOOKUP(C14,'CPD PITSS'!B21:V38,21,0) -> 4899.8 | F14: =VLOOKUP(C14,'SIND PITS'!$C$3:$H$104,2,0) -> 2600.2 | G14: =VLOOKUP(C14,'SIND PITS'!$C$3:$E$104,3,0) -> 337.5 | H14: =VLOOKUP(C14,'SIND PITS'!$C$3:$F$104,4,0) -> 0 | I14: =VLOOKUP(C14,'SIND PITS'!$C$3:$G$104,5,0) -> 0 | K14: =SUM(D14:I14) -> 7837.5 | L14: 15000 | M14: =+L14/2 -> 7500 | O14: =VLOOKUP($C14,'CPD PITSS'!$B$10:$V$27,8,0) -> 0 | P14: =+G14+H14+I14 -> 337.5 | Q14: =(VLOOKUP($C14,'CPD PITSS'!$B$10:$V$27,13,0))+(VLOOKUP($C14,'CPD PITSS'!$B$10:$V$27,14,0)) -> 0 | S14: =VLOOKUP(C14,'CPD PITSS'!$B$10:$S$27,18,0) -> 0 | U14: =+K14-O14-P14+Q14+R14+S14+IFERROR(VLOOKUP('RESUMEN PITS'!C14,'IP PITSS'!$B$10:$M$91,10),0)+IFERROR(VLOOKUP('RESUMEN PITS'!C14,'IP PITSS'!$B$10:$M$91,11),0)+IFERROR(VLOOKUP('RESUMEN PITS'!C14,'IP PITSS'!$B$10:$M$91,12),0)+VLOOKUP("Comision",'IP PITSS'!$I$97:$J$108,2)/COUNT($F$9:$F$111)+IFERROR(VLOOKUP('RESUMEN PITS'!C14,'IP PITSS'!$B$10:$AD$91,15),0)+IFERROR(VLOOKUP('RESUMEN PITS'!C14,'IP PITSS'!$B$10:$AD$91,21),0)+IFERROR(VLOOKUP('RESUMEN PITS'!C14,'IP PITSS'!$B$10:$AD$91,22),0)+IFERROR(VLOOKUP('RESUMEN PITS'!C14,'IP PITSS'!$B$10:$AD$91,23),0)+IFERROR(VLOOKUP('RESUMEN PITS'!C14,'IP PITSS'!$B$10:$AD$91,24),0)+IFERROR(VLOOKUP('RESUMEN PITS'!C14,'IP PITSS'!$B$10:$AD$91,26),0)+IFERROR(VLOOKUP('RESUMEN PITS'!C14,'IP PITSS'!$B$10:$AD$91,28),0)+IFERROR(VLOOKUP('RESUMEN PITS'!C14,'IP PITSS'!$B$10:$AD$91,29),0)+IFERROR(VLOOKUP('RESUMEN PITS'!C14,'IP PITSS'!$B$10:$AD$91,9),0)*2% -> 8917.0416 | V14: =+M14-U14 -> -1417.0416 | X14: SEI0127
... A20: SEI0442 | B20: CONSULTORIA | C20: Sierra Escamilla Daniela | D20: =VLOOKUP(C20,'CPD PITSS'!B27:V44,21,0) -> 4036.2 | F20: =VLOOKUP(C20,'SIND PITS'!$C$3:$H$104,2,0) -> 2463.8 | G20: =VLOOKUP(C20,'SIND PITS'!$C$3:$E$104,3,0) -> 1000 | H20: =VLOOKUP(C20,'SIND PITS'!$C$3:$F$104,4,0) -> 0 | I20: =VLOOKUP(C20,'SIND PITS'!$C$3:$G$104,5,0) -> 0 | K20: =SUM(D20:I20) -> 7500 | L20: 13000 | M20: =+L20/2 -> 6500 | O20: =VLOOKUP($C20,'CPD PITSS'!$B$10:$V$27,8,0) -> 0 | P20: =+G20+H20+I20 -> 1000 | Q20: =(VLOOKUP($C20,'CPD PITSS'!$B$10:$V$27,13,0))+(VLOOKUP($C20,'CPD PITSS'!$B$10:$V$27,14,0)) -> 0 | S20: =VLOOKUP(C20,'CPD PITSS'!$B$10:$S$27,18,0) -> 0 | U20: =+K20-O20-P20+Q20+R20+S20+IFERROR(VLOOKUP('RESUMEN PITS'!C20,'IP PITSS'!$B$10:$M$91,10),0)+IFERROR(VLOOKUP('RESUMEN PITS'!C20,'IP PITSS'!$B$10:$M$91,11),0)+IFERROR(VLOOKUP('RESUMEN PITS'!C20,'IP PITSS'!$B$10:$M$91,12),0)+VLOOKUP("Comision",'IP PITSS'!$I$97:$J$108,2)/COUNT($F$9:$F$111)+IFERROR(VLOOKUP('RESUMEN PITS'!C20,'IP PITSS'!$B$10:$AD$91,15),0)+IFERROR(VLOOKUP('RESUMEN PITS'!C20,'IP PITSS'!$B$10:$AD$91,21),0)+IFERROR(VLOOKUP('RESUMEN PITS'!C20,'IP PITSS'!$B$10:$AD$91,22),0)+IFERROR(VLOOKUP('RESUMEN PITS'!C20,'IP PITSS'!$B$10:$AD$91,23),0)+IFERROR(VLOOKUP('RESUMEN PITS'!C20,'IP PITSS'!$B$10:$AD$91,24),0)+IFERROR(VLOOKUP('RESUMEN PITS'!C20,'IP PITSS'!$B$10:$AD$91,26),0)+IFERROR(VLOOKUP('RESUMEN PITS'!C20,'IP PITSS'!$B$10:$AD$91,28),0)+IFERROR(VLOOKUP('RESUMEN PITS'!C20,'IP PITSS'!$B$10:$AD$91,29),0)+IFERROR(VLOOKUP('RESUMEN PITS'!C20,'IP PITSS'!$B$10:$AD$91,9),0)*2% -> 7844.8726 | V20: =+M20-U20 -> -1344.8726 | X20: SEI0618
A21: SEI0010 | B21: IP INNOVACION | C21: Torres Ricardez Alfredo | D21: =VLOOKUP(C21,'IP PITSS'!$B$10:$U$91,20,0) -> 3585.4 | F21: =VLOOKUP(C21,'SIND PITS'!$C$3:$H$104,2,0) -> 414.6 | G21: =VLOOKUP(C21,'SIND PITS'!$C$3:$E$104,3,0) -> 175 | H21: =VLOOKUP(C21,'SIND PITS'!$C$3:$F$104,4,0) -> 0 | I21: =VLOOKUP(C21,'SIND PITS'!$C$3:$G$104,5,0) -> 0 | K21: =SUM(D21:I21) -> 4175 | L21: 8000 | M21: =+L21/2 -> 4000 | O21: =VLOOKUP(C21,'IP PITSS'!$B$10:$I$91,8,0) -> 0 | P21: =+G21+H21+I21 -> 175 | Q21: =VLOOKUP(C21,'IP PITSS'!$B$10:$K$91,10,0)+VLOOKUP('RESUMEN PITS'!C21,'IP PITSS'!$B$10:$L$91,11,0)+VLOOKUP('RESUMEN PITS'!C21,'IP PITSS'!$B$10:$M$91,12,0) -> 0 | R21: =VLOOKUP(C21,'IP PITSS'!$B$10:$Q$91,16,0) -> 0 | S21: =VLOOKUP(C21,'IP PITSS'!$B$10:$R$91,17,0) -> 0 | U21: =+K21-O21-P21+Q21+R21+S21+IFERROR(VLOOKUP('RESUMEN PITS'!C21,'IP PITSS'!$B$10:$M$91,10),0)+IFERROR(VLOOKUP('RESUMEN PITS'!C21,'IP PITSS'!$B$10:$M$91,11),0)+IFERROR(VLOOKUP('RESUMEN PITS'!C21,'IP PITSS'!$B$10:$M$91,12),0)+VLOOKUP("Comision",'IP PITSS'!$I$97:$J$108,2)/COUNT($F$9:$F$111)+IFERROR(VLOOKUP('RESUMEN PITS'!C21,'IP PITSS'!$B$10:$AD$91,15),0)+IFERROR(VLOOKUP('RESUMEN PITS'!C21,'IP PITSS'!$B$10:$AD$91,21),0)+IFERROR(VLOOKUP('RESUMEN PITS'!C21,'IP PITSS'!$B$10:$AD$91,22),0)+IFERROR(VLOOKUP('RESUMEN PITS'!C21,'IP PITSS'!$B$10:$AD$91,23),0)+IFERROR(VLOOKUP('RESUMEN PITS'!C21,'IP PITSS'!$B$10:$AD$91,24),0)+IFERROR(VLOOKUP('RESUMEN PITS'!C21,'IP PITSS'!$B$10:$AD$91,26),0)+IFERROR(VLOOKUP('RESUMEN PITS'!C21,'IP PITSS'!$B$10:$AD$91,28),0)+IFERROR(VLOOKUP('RESUMEN PITS'!C21,'IP PITSS'!$B$10:$AD$91,29),0)+IFERROR(VLOOKUP('RESUMEN PITS'!C21,'IP PITSS'!$B$10:$AD$91,9),0)*2% -> 5344.8726 | V21: =+M21-U21 -> -1344.8726 | X21: SEI0010
A22: SEI0014 | B22: IP INNOVACION | C22: Montoya Portillo Carlos Alberto | D22: =VLOOKUP(C22,'IP PITSS'!$B$10:$U$91,20,0) -> 3585.2 | F22: =VLOOKUP(C22,'SIND PITS'!$C$3:$H$104,2,0) -> 414.8 | G22: =VLOOKUP(C22,'SIND PITS'!$C$3:$E$104,3,0) -> 175 | H22: =VLOOKUP(C22,'SIND PITS'!$C$3:$F$104,4,0) -> 0 | I22: =VLOOKUP(C22,'SIND PITS'!$C$3:$G$104,5,0) -> 0 | K22: =SUM(D22:I22) -> 4175 | L22: 8000 | M22: =+L22/2 -> 4000 | O22: =VLOOKUP(C22,'IP PITSS'!$B$10:$I$91,8,0) -> 0 | P22: =+G22+H22+I22 -> 175 | Q22: =VLOOKUP(C22,'IP PITSS'!$B$10:$K$91,10,0)+VLOOKUP('RESUMEN PITS'!C22,'IP PITSS'!$B$10:$L$91,11,0)+VLOOKUP('RESUMEN PITS'!C22,'IP PITSS'!$B$10:$M$91,12,0) -> 0 | R22: =VLOOKUP(C22,'IP PITSS'!$B$10:$Q$91,16,0) -> 0 | S22: =VLOOKUP(C22,'IP PITSS'!$B$10:$R$91,17,0) -> 0 | U22: =+K22-O22-P22+Q22+R22+S22+IFERROR(VLOOKUP('RESUMEN PITS'!C22,'IP PITSS'!$B$10:$M$91,10),0)+IFERROR(VLOOKUP('RESUMEN PITS'!C22,'IP PITSS'!$B$10:$M$91,11),0)+IFERROR(VLOOKUP('RESUMEN PITS'!C22,'IP PITSS'!$B$10:$M$91,12),0)+VLOOKUP("Comision",'IP PITSS'!$I$97:$J$108,2)/COUNT($F$9:$F$111)+IFERROR(VLOOKUP('RESUMEN PITS'!C22,'IP PITSS'!$B$10:$AD$91,15),0)+IFERROR(VLOOKUP('RESUMEN PITS'!C22,'IP PITSS'!$B$10:$AD$91,21),0)+IFERROR(VLOOKUP('RESUMEN PITS'!C22,'IP PITSS'!$B$10:$AD$91,22),0)+IFERROR(VLOOKUP('RESUMEN PITS'!C22,'IP PITSS'!$B$10:$AD$91,23),0)+IFERROR(VLOOKUP('RESUMEN PITS'!C22,'IP PITSS'!$B$10:$AD$91,24),0)+IFERROR(VLOOKUP('RESUMEN PITS'!C22,'IP PITSS'!$B$10:$AD$91,26),0)+IFERROR(VLOOKUP('RESUMEN PITS'!C22,'IP PITSS'!$B$10:$AD$91,28),0)+IFERROR(VLOOKUP('RESUMEN PITS'!C22,'IP PITSS'!$B$10:$AD$91,29),0)+IFERROR(VLOOKUP('RESUMEN PITS'!C22,'IP PITSS'!$B$10:$AD$91,9),0)*2% -> 5915.9536 | V22: =+M22-U22 -> -1915.9536 | X22: SEI0014
A23: SEI0017 | B23: IP INNOVACION | C23: Muñoz Reyes Luis Eduardo | D23: =VLOOKUP(C23,'IP PITSS'!$B$10:$U$91,20,0) -> 2716.8 | F23: =VLOOKUP(C23,'SIND PITS'!$C$3:$H$104,2,0) -> 414.76 | G23: =VLOOKUP(C23,'SIND PITS'!$C$3:$E$104,3,0) -> 250 | H23: =VLOOKUP(C23,'SIND PITS'!$C$3:$F$104,4,0) -> 0 | I23: =VLOOKUP(C23,'SIND PITS'!$C$3:$G$104,5,0) -> 0 | K23: =SUM(D23:I23) -> 3381.56 | L23: 8000 | M23: =+L23/2 -> 4000 | O23: =VLOOKUP(C23,'IP PITSS'!$B$10:$I$91,8,0) -> 0 | P23: =+G23+H23+I23 -> 250 | Q23: =VLOOKUP(C23,'IP PITSS'!$B$10:$K$91,10,0)+VLOOKUP('RESUMEN PITS'!C23,'IP PITSS'!$B$10:$L$91,11,0)+VLOOKUP('RESUMEN PITS'!C23,'IP PITSS'!$B$10:$M$91,12,0) -> 868.44 | R23: =VLOOKUP(C23,'IP PITSS'!$B$10:$Q$91,16,0) -> 0 | S23: =VLOOKUP(C23,'IP PITSS'!$B$10:$R$91,17,0) -> 0 | U23: =+K23-O23-P23+Q23+R23+S23+IFERROR(VLOOKUP('RESUMEN PITS'!C23,'IP PITSS'!$B$10:$M$91,10),0)+IFERROR(VLOOKUP('RESUMEN PITS'!C23,'IP PITSS'!$B$10:$M$91,11),0)+IFERROR(VLOOKUP('RESUMEN PITS'!C23,'IP PITSS'!$B$10:$M$91,12),0)+VLOOKUP("Comision",'IP PITSS'!$I$97:$J$108,2)/COUNT($F$9:$F$111)+IFERROR(VLOOKUP('RESUMEN PITS'!C23,'IP PITSS'!$B$10:$AD$91,15),0)+IFERROR(VLOOKUP('RESUMEN PITS'!C23,'IP PITSS'!$B$10:$AD$91,21),0)+IFERROR(VLOOKUP('RESUMEN PITS'!C23,'IP PITSS'!$B$10:$AD$91,22),0)+IFERROR(VLOOKUP('RESUMEN PITS'!C23,'IP PITSS'!$B$10:$AD$91,23),0)+IFERROR(VLOOKUP('RESUMEN PITS'!C23,'IP PITSS'!$B$10:$AD$91,24),0)+IFERROR(VLOOKUP('RESUMEN PITS'!C23,'IP PITSS'!$B$10:$AD$91,26),0)+IFERROR(VLOOKUP('RESUMEN PITS'!C23,'IP PITSS'!$B$10:$AD$91,28),0)+IFERROR(VLOOKUP('RESUMEN PITS'!C23,'IP PITSS'!$B$10:$AD$91,29),0)+IFERROR(VLOOKUP('RESUMEN PITS'!C23,'IP PITSS'!$B$10:$AD$91,9),0)*2% -> 5344.8726 | V23: =+M23-U23 -> -1344.8726 | X23: SEI0017
A24: SEI0019 | B24: IP INNOVACION | C24: Gonzalez Rasgado Miguel Isaias | D24: =VLOOKUP(C24,'IP PITSS'!$B$10:$U$91,20,0) -> 6576.8 | F24: =VLOOKUP(C24,'SIND PITS'!$C$3:$H$104,2,0) -> 0 | G24: =VLOOKUP(C24,'SIND PITS'!$C$3:$E$104,3,0) -> 937.5 | H24: =VLOOKUP(C24,'SIND PITS'!$C$3:$F$104,4,0) -> 0 | I24: =VLOOKUP(C24,'SIND PITS'!$C$3:$G$104,5,0) -> 0 | K24: =SUM(D24:I24) -> 7514.3 | L24: 13125 | M24: =+L24/2 -> 6562.5 | O24: =VLOOKUP(C24,'IP PITSS'!$B$10:$I$91,8,0) -> 0 | P24: =+G24+H24+I24 -> 937.5 | Q24: =VLOOKUP(C24,'IP PITSS'!$B$10:$K$91,10,0)+VLOOKUP('RESUMEN PITS'!C24,'IP PITSS'!$B$10:$L$91,11,0)+VLOOKUP('RESUMEN PITS'!C24,'IP PITSS'!$B$10:$M$91,12,0) -> 0 | R24: =VLOOKUP(C24,'IP PITSS'!$B$10:$Q$91,16,0) -> 0 | S24: =VLOOKUP(C24,'IP PITSS'!$B$10:$R$91,17,0) -> 0 | U24: =+K24-O24-P24+Q24+R24+S24+IFERROR(VLOOKUP('RESUMEN PITS'!C24,'IP PITSS'!$B$10:$M$91,10),0)+IFERROR(VLOOKUP('RESUMEN PITS'!C24,'IP PITSS'!$B$10:$M$91,11),0)+IFERROR(VLOOKUP('RESUMEN PITS'!C24,'IP PITSS'!$B$10:$M$91,12),0)+VLOOKUP("Comision",'IP PITSS'!$I$97:$J$108,2)/COUNT($F$9:$F$111)+IFERROR(VLOOKUP('RESUMEN PITS'!C24,'IP PITSS'!$B$10:$AD$91,15),0)+IFERROR(VLOOKUP('RESUMEN PITS'!C24,'IP PITSS'!$B$10:$AD$91,21),0)+IFERROR(VLOOKUP('RESUMEN PITS'!C24,'IP PITSS'!$B$10:$AD$91,22),0)+IFERROR(VLOOKUP('RESUMEN PITS'!C24,'IP PITSS'!$B$10:$AD$91,23),0)+IFERROR(VLOOKUP('RESUMEN PITS'!C24,'IP PITSS'!$B$10:$AD$91,24),0)+IFERROR(VLOOKUP('RESUMEN PITS'!C24,'IP PITSS'!$B$10:$AD$91,26),0)+IFERROR(VLOOKUP('RESUMEN PITS'!C24,'IP PITSS'!$B$10:$AD$91,28),0)+IFERROR(VLOOKUP('RESUMEN PITS'!C24,'IP PITSS'!$B$10:$AD$91,29),0)+IFERROR(VLOOKUP('RESUMEN PITS'!C24,'IP PITSS'!$B$10:$AD$91,9),0)*2% -> 7993.8416 | V24: =+M24-U24 -> -1431.3416 | X24: SEI0019
A25: SEI0020 | B25: IP INNOVACION | C25: Mar Marquez Cesar Eduardo | D25: =VLOOKUP(C25,'IP PITSS'!$B$10:$U$91,20,0) -> 3585.4 | F25: =VLOOKUP(C25,'SIND PITS'!$C$3:$H$104,2,0) -> 414.6 | G25: =VLOOKUP(C25,'SIND PITS'!$C$3:$E$104,3,0) -> 220 | H25: =VLOOKUP(C25,'SIND PITS'!$C$3:$F$104,4,0) -> 0 | I25: =VLOOKUP(C25,'SIND PITS'!$C$3:$G$104,5,0) -> 0 | K25: =SUM(D25:I25) -> 4220 | L25: 8000 | M25: =+L25/2 -> 4000 | O25: =VLOOKUP(C25,'IP PITSS'!$B$10:$I$91,8,0) -> 0 | P25: =+G25+H25+I25 -> 220 | Q25: =VLOOKUP(C25,'IP PITSS'!$B$10:$K$91,10,0)+VLOOKUP('RESUMEN PITS'!C25,'IP PITSS'!$B$10:$L$91,11,0)+VLOOKUP('RESUMEN PITS'!C25,'IP PITSS'!$B$10:$M$91,12,0) -> 0 | R25: =VLOOKUP(C25,'IP PITSS'!$B$10:$Q$91,16,0) -> 0 | S25: =VLOOKUP(C25,'IP PITSS'!$B$10:$R$91,17,0) -> 0 | U25: =+K25-O25-P25+Q25+R25+S25+IFERROR(VLOOKUP('RESUMEN PITS'!C25,'IP PITSS'!$B$10:$M$91,10),0)+IFERROR(VLOOKUP('RESUMEN PITS'!C25,'IP PITSS'!$B$10:$M$91,11),0)+IFERROR(VLOOKUP('RESUMEN PITS'!C25,'IP PITSS'!$B$10:$M$91,12),0)+VLOOKUP("Comision",'IP PITSS'!$I$97:$J$108,2)/COUNT($F$9:$F$111)+IFERROR(VLOOKUP('RESUMEN PITS'!C25,'IP PITSS'!$B$10:$AD$91,15),0)+IFERROR(VLOOKUP('RESUMEN PITS'!C25,'IP PITSS'!$B$10:$AD$91,21),0)+IFERROR(VLOOKUP('RESUMEN PITS'!C25,'IP PITSS'!$B$10:$AD$91,22),0)+IFERROR(VLOOKUP('RESUMEN PITS'!C25,'IP PITSS'!$B$10:$AD$91,23),0)+IFERROR(VLOOKUP('RESUMEN PITS'!C25,'IP PITSS'!$B$10:$AD$91,24),0)+IFERROR(VLOOKUP('RESUMEN PITS'!C25,'IP PITSS'!$B$10:$AD$91,26),0)+IFERROR(VLOOKUP('RESUMEN PITS'!C25,'IP PITSS'!$B$10:$AD$91,28),0)+IFERROR(VLOOKUP('RESUMEN PITS'!C25,'IP PITSS'!$B$10:$AD$91,29),0)+IFERROR(VLOOKUP('RESUMEN PITS'!C25,'IP PITSS'!$B$10:$AD$91,9),0)*2% -> 5915.9536 | V25: =+M25-U25 -> -1915.9536 | X25: SEI0020
A26: SEI0021 | B26: IP INNOVACION | C26: Velez Rodriguez Jaime | D26: =VLOOKUP(C26,'IP PITSS'!$B$10:$U$91,20,0) -> 1517.6 | F26: =VLOOKUP(C26,'SIND PITS'!$C$3:$H$104,2,0) -> 1135.3 | G26: =VLOOKUP(C26,'SIND PITS'!$C$3:$E$104,3,0) -> 0 | H26: =VLOOKUP(C26,'SIND PITS'!$C$3:$F$104,4,0) -> 0 | I26: =VLOOKUP(C26,'SIND PITS'!$C$3:$G$104,5,0) -> 0 | K26: =SUM(D26:I26) -> 2652.9 | L26: 8000 | M26: =+L26/2 -> 4000 | O26: =VLOOKUP(C26,'IP PITSS'!$B$10:$I$91,8,0) -> 0 | P26: =+G26+H26+I26 -> 0 | Q26: =VLOOKUP(C26,'IP PITSS'!$B$10:$K$91,10,0)+VLOOKUP('RESUMEN PITS'!C26,'IP PITSS'!$B$10:$L$91,11,0)+VLOOKUP('RESUMEN PITS'!C26,'IP PITSS'!$B$10:$M$91,12,0) -> 1347.1 | R26: =VLOOKUP(C26,'IP PITSS'!$B$10:$Q$91,16,0) -> 0 | S26: =VLOOKUP(C26,'IP PITSS'!$B$10:$R$91,17,0) -> 0 | U26: =+K26-O26-P26+Q26+R26+S26+IFERROR(VLOOKUP('RESUMEN PITS'!C26,'IP PITSS'!$B$10:$M$91,10),0)+IFERROR(VLOOKUP('RESUMEN PITS'!C26,'IP PITSS'!$B$10:$M$91,11),0)+IFERROR(VLOOKUP('RESUMEN PITS'!C26,'IP PITSS'!$B$10:$M$91,12),0)+VLOOKUP("Comision",'IP PITSS'!$I$97:$J$108,2)/COUNT($F$9:$F$111)+IFERROR(VLOOKUP('RESUMEN PITS'!C26,'IP PITSS'!$B$10:$AD$91,15),0)+IFERROR(VLOOKUP('RESUMEN PITS'!C26,'IP PITSS'!$B$10:$AD$91,21),0)+IFERROR(VLOOKUP('RESUMEN PITS'!C26,'IP PITSS'!$B$10:$AD$91,22),0)+IFERROR(VLOOKUP('RESUMEN PITS'!C26,'IP PITSS'!$B$10:$AD$91,23),0)+IFERROR(VLOOKUP('RESUMEN PITS'!C26,'IP PITSS'!$B$10:$AD$91,24),0)+IFERROR(VLOOKUP('RESUMEN PITS'!C26,'IP PITSS'!$B$10:$AD$91,26),0)+IFERROR(VLOOKUP('RESUMEN PITS'!C26,'IP PITSS'!$B$10:$AD$91,28),0)+IFERROR(VLOOKUP('RESUMEN PITS'!C26,'IP PITSS'!$B$10:$AD$91,29),0)+IFERROR(VLOOKUP('RESUMEN PITS'!C26,'IP PITSS'!$B$10:$AD$91,9),0)*2% -> 5537.7236 | V26: =+M26-U26 -> -1537.7236 | X26: SEI0021
A27: SEI0022 | B27: IP INNOVACION | C27: Najera Lopez Raul | D27: =VLOOKUP(C27,'IP PITSS'!$B$10:$U$91,20,0) -> 4406.4 | F27: =VLOOKUP(C27,'SIND PITS'!$C$3:$H$104,2,0) -> 593.6 | G27: =VLOOKUP(C27,'SIND PITS'!$C$3:$E$104,3,0) -> 150 | H27: =VLOOKUP(C27,'SIND PITS'!$C$3:$F$104,4,0) -> 0 | I27: =VLOOKUP(C27,'SIND PITS'!$C$3:$G$104,5,0) -> 0 | K27: =SUM(D27:I27) -> 5150 | L27: 10000 | M27: =+L27/2 -> 5000 | O27: =VLOOKUP(C27,'IP PITSS'!$B$10:$I$91,8,0) -> 0 | P27: =+G27+H27+I27 -> 150 | Q27: =VLOOKUP(C27,'IP PITSS'!$B$10:$K$91,10,0)+VLOOKUP('RESUMEN PITS'!C27,'IP PITSS'!$B$10:$L$91,11,0)+VLOOKUP('RESUMEN PITS'!C27,'IP PITSS'!$B$10:$M$91,12,0) -> 0 | R27: =VLOOKUP(C27,'IP PITSS'!$B$10:$Q$91,16,0) -> 0 | S27: =VLOOKUP(C27,'IP PITSS'!$B$10:$R$91,17,0) -> 0 | U27: =+K27-O27-P27+Q27+R27+S27+IFERROR(VLOOKUP('RESUMEN PITS'!C27,'IP PITSS'!$B$10:$M$91,10),0)+IFERROR(VLOOKUP('RESUMEN PITS'!C27,'IP PITSS'!$B$10:$M$91,11),0)+IFERROR(VLOOKUP('RESUMEN PITS'!C27,'IP PITSS'!$B$10:$M$91,12),0)+VLOOKUP("Comision",'IP PITSS'!$I$97:$J$108,2)/COUNT($F$9:$F$111)+IFERROR(VLOOKUP('RESUMEN PITS'!C27,'IP PITSS'!$B$10:$AD$91,15),0)+IFERROR(VLOOKUP('RESUMEN PITS'!C27,'IP PITSS'!$B$10:$AD$91,21),0)+IFERROR(VLOOKUP('RESUMEN PITS'!C27,'IP PITSS'!$B$10:$AD$91,22),0)+IFERROR(VLOOKUP('RESUMEN PITS'!C27,'IP PITSS'!$B$10:$AD$91,23),0)+IFERROR(VLOOKUP('RESUMEN PITS'!C27,'IP PITSS'!$B$10:$AD$91,24),0)+IFERROR(VLOOKUP('RESUMEN PITS'!C27,'IP PITSS'!$B$10:$AD$91,26),0)+IFERROR(VLOOKUP('RESUMEN PITS'!C27,'IP PITSS'!$B$10:$AD$91,28),0)+IFERROR(VLOOKUP('RESUMEN PITS'!C27,'IP PITSS'!$B$10:$AD$91,29),0)+IFERROR(VLOOKUP('RESUMEN PITS'!C27,'IP PITSS'!$B$10:$AD$91,9),0)*2% -> 6344.8726 | V27: =+M27-U27 -> -1344.8726 | X27: SEI0022
A28: SEI0023 | B28: IP INNOVACION | C28: Puente Murguia Luis Felipe | D28: =VLOOKUP(C28,'IP PITSS'!$B$10:$U$91,20,0) -> 3277.4 | F28: =VLOOKUP(C28,'SIND PITS'!$C$3:$H$104,2,0) -> 222.6 | G28: =VLOOKUP(C28,'SIND PITS'!$C$3:$E$104,3,0) -> 131.25 | H28: =VLOOKUP(C28,'SIND PITS'!$C$3:$F$104,4,0) -> 0 | I28: =VLOOKUP(C28,'SIND PITS'!$C$3:$G$104,5,0) -> 0 | K28: =SUM(D28:I28) -> 3631.25 | L28: 7000 | M28: =+L28/2 -> 3500 | O28: =VLOOKUP(C28,'IP PITSS'!$B$10:$I$91,8,0) -> 0 | P28: =+G28+H28+I28 -> 131.25 | Q28: =VLOOKUP(C28,'IP PITSS'!$B$10:$K$91,10,0)+VLOOKUP('RESUMEN PITS'!C28,'IP PITSS'!$B$10:$L$91,11,0)+VLOOKUP('RESUMEN PITS'!C28,'IP PITSS'!$B$10:$M$91,12,0) -> 0 | R28: =VLOOKUP(C28,'IP PITSS'!$B$10:$Q$91,16,0) -> 0 | S28: =VLOOKUP(C28,'IP PITSS'!$B$10:$R$91,17,0) -> 0 | U28: =+K28-O28-P28+Q28+R28+S28+IFERROR(VLOOKUP('RESUMEN PITS'!C28,'IP PITSS'!$B$10:$M$91,10),0)+IFERROR(VLOOKUP('RESUMEN PITS'!C28,'IP PITSS'!$B$10:$M$91,11),0)+IFERROR(VLOOKUP('RESUMEN PITS'!C28,'IP PITSS'!$B$10:$M$91,12),0)+VLOOKUP("Comision",'IP PITSS'!$I$97:$J$108,2)/COUNT($F$9:$F$111)+IFERROR(VLOOKUP('RESUMEN PITS'!C28,'IP PITSS'!$B$10:$AD$91,15),0)+IFERROR(VLOOKUP('RESUMEN PITS'!C28,'IP PITSS'!$B$10:$AD$91,21),0)+IFERROR(VLOOKUP('RESUMEN PITS'!C28,'IP PITSS'!$B$10:$AD$91,22),0)+IFERROR(VLOOKUP('RESUMEN PITS'!C28,'IP PITSS'!$B$10:$AD$91,23),0)+IFERROR(VLOOKUP('RESUMEN PITS'!C28,'IP PITSS'!$B$10:$AD$91,24),0)+IFERROR(VLOOKUP('RESUMEN PITS'!C28,'IP PITSS'!$B$10:$AD$91,26),0)+IFERROR(VLOOKUP('RESUMEN PITS'!C28,'IP PITSS'!$B$10:$AD$91,28),0)+IFERROR(VLOOKUP('RESUMEN PITS'!C28,'IP PITSS'!$B$10:$AD$91,29),0)+IFERROR(VLOOKUP('RESUMEN PITS'!C28,'IP PITSS'!$B$10:$AD$91,9),0)*2% -> 4844.8726 | V28: =+M28-U28 -> -1344.8726 | X28: SEI0023
A29: SEI0029 | B29: IP INNOVACION | C29: Arceo Garcia Manuel Federico | D29: =VLOOKUP(C29,'IP PITSS'!$B$10:$U$91,20,0) -> 2150.2 | F29: =VLOOKUP(C29,'SIND PITS'!$C$3:$H$104,2,0) -> 249.8 | G29: =VLOOKUP(C29,'SIND PITS'!$C$3:$E$104,3,0) -> 1000 | H29: =VLOOKUP(C29,'SIND PITS'!$C$3:$F$104,4,0) -> 0 | I29: =VLOOKUP(C29,'SIND PITS'!$C$3:$G$104,5,0) -> 3 | K29: =SUM(D29:I29) -> 3403 | L29: 6300 | M29: =+L29/2 -> 3150 | O29: =VLOOKUP(C29,'IP PITSS'!$B$10:$I$91,8,0) -> 60 | P29: =+G29+H29+I29 -> 1003 | Q29: =VLOOKUP(C29,'IP PITSS'!$B$10:$K$91,10,0)+VLOOKUP('RESUMEN PITS'!C29,'IP PITSS'!$B$10:$L$91,11,0)+VLOOKUP('RESUMEN PITS'!C29,'IP PITSS'!$B$10:$M$91,12,0) -> 0 | R29: =VLOOKUP(C29,'IP PITSS'!$B$10:$Q$91,16,0) -> 600 | S29: =VLOOKUP(C29,'IP PITSS'!$B$10:$R$91,17,0) -> 0 | U29: =+K29-O29-P29+Q29+R29+S29+IFERROR(VLOOKUP('RESUMEN PITS'!C29,'IP PITSS'!$B$10:$M$91,10),0)+IFERROR(VLOOKUP('RESUMEN PITS'!C29,'IP PITSS'!$B$10:$M$91,11),0)+IFERROR(VLOOKUP('RESUMEN PITS'!C29,'IP PITSS'!$B$10:$M$91,12),0)+VLOOKUP("Comision",'IP PITSS'!$I$97:$J$108,2)/COUNT($F$9:$F$111)+IFERROR(VLOOKUP('RESUMEN PITS'!C29,'IP PITSS'!$B$10:$AD$91,15),0)+IFERROR(VLOOKUP('RESUMEN PITS'!C29,'IP PITSS'!$B$10:$AD$91,21),0)+IFERROR(VLOOKUP('RESUMEN PITS'!C29,'IP PITSS'!$B$10:$AD$91,22),0)+IFERROR(VLOOKUP('RESUMEN PITS'!C29,'IP PITSS'!$B$10:$AD$91,23),0)+IFERROR(VLOOKUP('RESUMEN PITS'!C29,'IP PITSS'!$B$10:$AD$91,24),0)+IFERROR(VLOOKUP('RESUMEN PITS'!C29,'IP PITSS'!$B$10:$AD$91,26),0)+IFERROR(VLOOKUP('RESUMEN PITS'!C29,'IP PITSS'!$B$10:$AD$91,28),0)+IFERROR(VLOOKUP('RESUMEN PITS'!C29,'IP PITSS'!$B$10:$AD$91,29),0)+IFERROR(VLOOKUP('RESUMEN PITS'!C29,'IP PITSS'!$B$10:$AD$91,9),0)*2% -> 2996.5626 | V29: =+M29-U29 -> 153.43736 | W29: 1 falta | X29: SEI0029
A30: SEI0364 | B30: IP INNOVACION | C30: Dominguez Lopez Mayeli Del Pilar | D30: =VLOOKUP(C30,'IP PITSS'!$B$10:$U$91,20,0) -> 1917 | F30: =VLOOKUP(C30,'SIND PITS'!$C$3:$H$104,2,0) -> 1416.33 | G30: =VLOOKUP(C30,'SIND PITS'!$C$3:$E$104,3,0) -> 1087.5 | H30: =VLOOKUP(C30,'SIND PITS'!$C$3:$F$104,4,0) -> 0 | I30: =VLOOKUP(C30,'SIND PITS'!$C$3:$G$104,5,0) -> 0 | K30: =SUM(D30:I30) -> 4420.83 | L30: 10000 | M30: =+L30/2 -> 5000 | O30: =VLOOKUP(C30,'IP PITSS'!$B$10:$I$91,8,0) -> 0 | P30: =+G30+H30+I30 -> 1087.5 | Q30: =VLOOKUP(C30,'IP PITSS'!$B$10:$K$91,10,0)+VLOOKUP('RESUMEN PITS'!C30,'IP PITSS'!$B$10:$L$91,11,0)+VLOOKUP('RESUMEN PITS'!C30,'IP PITSS'!$B$10:$M$91,12,0) -> 0 | R30: =VLOOKUP(C30,'IP PITSS'!$B$10:$Q$91,16,0) -> 0 | S30: =VLOOKUP(C30,'IP PITSS'!$B$10:$R$91,17,0) -> 1666.67 | U30: =+K30-O30-P30+Q30+R30+S30+IFERROR(VLOOKUP('RESUMEN PITS'!C30,'IP PITSS'!$B$10:$M$91,10),0)+IFERROR(VLOOKUP('RESUMEN PITS'!C30,'IP PITSS'!$B$10:$M$91,11),0)+IFERROR(VLOOKUP('RESUMEN PITS'!C30,'IP PITSS'!$B$10:$M$91,12),0)+VLOOKUP("Comision",'IP PITSS'!$I$97:$J$108,2)/COUNT($F$9:$F$111)+IFERROR(VLOOKUP('RESUMEN PITS'!C30,'IP PITSS'!$B$10:$AD$91,15),0)+IFERROR(VLOOKUP('RESUMEN PITS'!C30,'IP PITSS'!$B$10:$AD$91,21),0)+IFERROR(VLOOKUP('RESUMEN PITS'!C30,'IP PITSS'!$B$10:$AD$91,22),0)+IFERROR(VLOOKUP('RESUMEN PITS'!C30,'IP PITSS'!$B$10:$AD$91,23),0)+IFERROR(VLOOKUP('RESUMEN PITS'!C30,'IP PITSS'!$B$10:$AD$91,24),0)+IFERROR(VLOOKUP('RESUMEN PITS'!C30,'IP PITSS'!$B$10:$AD$91,26),0)+IFERROR(VLOOKUP('RESUMEN PITS'!C30,'IP PITSS'!$B$10:$AD$91,28),0)+IFERROR(VLOOKUP('RESUMEN PITS'!C30,'IP PITSS'!$B$10:$AD$91,29),0)+IFERROR(VLOOKUP('RESUMEN PITS'!C30,'IP PITSS'!$B$10:$AD$91,9),0)*2% -> 5056.5626 | V30: =+M30-U30 -> -56.562642 | X30: SEI0364
A31: SEI0413 | B31: IP INNOVACION | C31: Courtenay Gutierrez Barry Vladimir | D31: =VLOOKUP(C31,'IP PITSS'!$B$10:$U$91,20,0) -> 2447.6 | F31: =VLOOKUP(C31,'SIND PITS'!$C$3:$H$104,2,0) -> 52.4 | G31: =VLOOKUP(C31,'SIND PITS'!$C$3:$E$104,3,0) -> 250 | H31: =VLOOKUP(C31,'SIND PITS'!$C$3:$F$104,4,0) -> 2800 | I31: =VLOOKUP(C31,'SIND PITS'!$C$3:$G$104,5,0) -> 0 | K31: =SUM(D31:I31) -> 5550 | L31: 5000 | M31: =+L31/2 -> 2500 | O31: =VLOOKUP(C31,'IP PITSS'!$B$10:$I$91,8,0) -> 0 | P31: =+G31+H31+I31 -> 3050 | Q31: =VLOOKUP(C31,'IP PITSS'!$B$10:$K$91,10,0)+VLOOKUP('RESUMEN PITS'!C31,'IP PITSS'!$B$10:$L$91,11,0)+VLOOKUP('RESUMEN PITS'!C31,'IP PITSS'!$B$10:$M$91,12,0) -> 0 | R31: =VLOOKUP(C31,'IP PITSS'!$B$10:$Q$91,16,0) -> 0 | S31: =VLOOKUP(C31,'IP PITSS'!$B$10:$R$91,17,0) -> 0 | U31: =+K31-O31-P31+Q31+R31+S31+IFERROR(VLOOKUP('RESUMEN PITS'!C31,'IP PITSS'!$B$10:$M$91,10),0)+IFERROR(VLOOKUP('RESUMEN PITS'!C31,'IP PITSS'!$B$10:$M$91,11),0)+IFERROR(VLOOKUP('RESUMEN PITS'!C31,'IP PITSS'!$B$10:$M$91,12),0)+VLOOKUP("Comision",'IP PITSS'!$I$97:$J$108,2)/COUNT($F$9:$F$111)+IFERROR(VLOOKUP('RESUMEN PITS'!C31,'IP PITSS'!$B$10:$AD$91,15),0)+IFERROR(VLOOKUP('RESUMEN PITS'!C31,'IP PITSS'!$B$10:$AD$91,21),0)+IFERROR(VLOOKUP('RESUMEN PITS'!C31,'IP PITSS'!$B$10:$AD$91,22),0)+IFERROR(VLOOKUP('RESUMEN PITS'!C31,'IP PITSS'!$B$10:$AD$91,23),0)+IFERROR(VLOOKUP('RESUMEN PITS'!C31,'IP PITSS'!$B$10:$AD$91,24),0)+IFERROR(VLOOKUP('RESUMEN PITS'!C31,'IP PITSS'!$B$10:$AD$91,26),0)+IFERROR(VLOOKUP('RESUMEN PITS'!C31,'IP PITSS'!$B$10:$AD$91,28),0)+IFERROR(VLOOKUP('RESUMEN PITS'!C31,'IP PITSS'!$B$10:$AD$91,29),0)+IFERROR(VLOOKUP('RESUMEN PITS'!C31,'IP PITSS'!$B$10:$AD$91,9),0)*2% -> 2556.5626 | V31: =+M31-U31 -> -56.562642 | X31: SEI0436
A32: SEI0421 | B32: IP INNOVACION | C32: Marin Avila Hector | D32: =VLOOKUP(C32,'IP PITSS'!$B$10:$U$91,20,0) -> 3693 | F32: =VLOOKUP(C32,'SIND PITS'!$C$3:$H$104,2,0) -> 707 | G32: =VLOOKUP(C32,'SIND PITS'!$C$3:$E$104,3,0) -> 500 | H32: =VLOOKUP(C32,'SIND PITS'!$C$3:$F$104,4,0) -> 0 | I32: =VLOOKUP(C32,'SIND PITS'!$C$3:$G$104,5,0) -> 0 | K32: =+D32+F32+G32+H32+I32 -> 4900 | L32: 8800 | M32: =+L32/2 -> 4400 | O32: =VLOOKUP(C32,'IP PITSS'!$B$10:$I$91,8,0) -> 0 | P32: =+G32+H32+I32 -> 500 | Q32: =VLOOKUP(C32,'IP PITSS'!$B$10:$K$91,10,0)+VLOOKUP('RESUMEN PITS'!C32,'IP PITSS'!$B$10:$L$91,11,0)+VLOOKUP('RESUMEN PITS'!C32,'IP PITSS'!$B$10:$M$91,12,0) -> 0 | R32: =VLOOKUP(C32,'IP PITSS'!$B$10:$Q$91,16,0) -> 0 | S32: =VLOOKUP(C32,'IP PITSS'!$B$10:$R$91,17,0) -> 0 | U32: =+K32-O32-P32+Q32+R32+S32+IFERROR(VLOOKUP('RESUMEN PITS'!C32,'IP PITSS'!$B$10:$M$91,10),0)+IFERROR(VLOOKUP('RESUMEN PITS'!C32,'IP PITSS'!$B$10:$M$91,11),0)+IFERROR(VLOOKUP('RESUMEN PITS'!C32,'IP PITSS'!$B$10:$M$91,12),0)+VLOOKUP("Comision",'IP PITSS'!$I$97:$J$108,2)/COUNT($F$9:$F$111)+IFERROR(VLOOKUP('RESUMEN PITS'!C32,'IP PITSS'!$B$10:$AD$91,15),0)+IFERROR(VLOOKUP('RESUMEN PITS'!C32,'IP PITSS'!$B$10:$AD$91,21),0)+IFERROR(VLOOKUP('RESUMEN PITS'!C32,'IP PITSS'!$B$10:$AD$91,22),0)+IFERROR(VLOOKUP('RESUMEN PITS'!C32,'IP PITSS'!$B$10:$AD$91,23),0)+IFERROR(VLOOKUP('RESUMEN PITS'!C32,'IP PITSS'!$B$10:$AD$91,24),0)+IFERROR(VLOOKUP('RESUMEN PITS'!C32,'IP PITSS'!$B$10:$AD$91,26),0)+IFERROR(VLOOKUP('RESUMEN PITS'!C32,'IP PITSS'!$B$10:$AD$91,28),0)+IFERROR(VLOOKUP('RESUMEN PITS'!C32,'IP PITSS'!$B$10:$AD$91,29),0)+IFERROR(VLOOKUP('RESUMEN PITS'!C32,'IP PITSS'!$B$10:$AD$91,9),0)*2% -> 6315.9536 | V32: =+M32-U32 -> -1915.9536
A33: SEI0424 | B33: IP INNOVACION | C33: Palacios Ramos Jesus | D33: =VLOOKUP(C33,'IP PITSS'!$B$10:$U$91,20,0) -> 3583.6 | F33: =VLOOKUP(C33,'SIND PITS'!$C$3:$H$104,2,0) -> 416.4 | G33: =VLOOKUP(C33,'SIND PITS'!$C$3:$E$104,3,0) -> 210 | H33: =VLOOKUP(C33,'SIND PITS'!$C$3:$F$104,4,0) -> 0 | I33: =VLOOKUP(C33,'SIND PITS'!$C$3:$G$104,5,0) -> 0 | K33: =SUM(D33:I33) -> 4210 | L33: 8000 | M33: =+L33/2 -> 4000 | O33: =VLOOKUP(C33,'IP PITSS'!$B$10:$I$91,8,0) -> 0 | P33: =+G33+H33+I33 -> 210 | Q33: =VLOOKUP(C33,'IP PITSS'!$B$10:$K$91,10,0)+VLOOKUP('RESUMEN PITS'!C33,'IP PITSS'!$B$10:$L$91,11,0)+VLOOKUP('RESUMEN PITS'!C33,'IP PITSS'!$B$10:$M$91,12,0) -> 0 | R33: =VLOOKUP(C33,'IP PITSS'!$B$10:$Q$91,16,0) -> 0 | S33: =VLOOKUP(C33,'IP PITSS'!$B$10:$R$91,17,0) -> 0 | U33: =+K33-O33-P33+Q33+R33+S33+IFERROR(VLOOKUP('RESUMEN PITS'!C33,'IP PITSS'!$B$10:$M$91,10),0)+IFERROR(VLOOKUP('RESUMEN PITS'!C33,'IP PITSS'!$B$10:$M$91,11),0)+IFERROR(VLOOKUP('RESUMEN PITS'!C33,'IP PITSS'!$B$10:$M$91,12),0)+VLOOKUP("Comision",'IP PITSS'!$I$97:$J$108,2)/COUNT($F$9:$F$111)+IFERROR(VLOOKUP('RESUMEN PITS'!C33,'IP PITSS'!$B$10:$AD$91,15),0)+IFERROR(VLOOKUP('RESUMEN PITS'!C33,'IP PITSS'!$B$10:$AD$91,21),0)+IFERROR(VLOOKUP('RESUMEN PITS'!C33,'IP PITSS'!$B$10:$AD$91,22),0)+IFERROR(VLOOKUP('RESUMEN PITS'!C33,'IP PITSS'!$B$10:$AD$91,23),0)+IFERROR(VLOOKUP('RESUMEN PITS'!C33,'IP PITSS'!$B$10:$AD$91,24),0)+IFERROR(VLOOKUP('RESUMEN PITS'!C33,'IP PITSS'!$B$10:$AD$91,26),0)+IFERROR(VLOOKUP('RESUMEN PITS'!C33,'IP PITSS'!$B$10:$AD$91,28),0)+IFERROR(VLOOKUP('RESUMEN PITS'!C33,'IP PITSS'!$B$10:$AD$91,29),0)+IFERROR(VLOOKUP('RESUMEN PITS'!C33,'IP PITSS'!$B$10:$AD$91,9),0)*2% -> 5344.8726 | V33: =+M33-U33 -> -1344.8726 | X33: SEI0424
A34: SEI0428 | B34: IP INNOVACION | C34: Martinez Hernandez J. Antonio | D34: =VLOOKUP(C34,'IP PITSS'!$B$10:$U$91,20,0) -> 3583.6 | F34: =VLOOKUP(C34,'SIND PITS'!$C$3:$H$104,2,0) -> 416.4 | G34: =VLOOKUP(C34,'SIND PITS'!$C$3:$E$104,3,0) -> 120 | H34: =VLOOKUP(C34,'SIND PITS'!$C$3:$F$104,4,0) -> 0 | I34: =VLOOKUP(C34,'SIND PITS'!$C$3:$G$104,5,0) -> 0 | K34: =SUM(D34:I34) -> 4120 | L34: 8000 | M34: =+L34/2 -> 4000 | O34: =VLOOKUP(C34,'IP PITSS'!$B$10:$I$91,8,0) -> 0 | P34: =+G34+H34+I34 -> 120 | Q34: =VLOOKUP(C34,'IP PITSS'!$B$10:$K$91,10,0)+VLOOKUP('RESUMEN PITS'!C34,'IP PITSS'!$B$10:$L$91,11,0)+VLOOKUP('RESUMEN PITS'!C34,'IP PITSS'!$B$10:$M$91,12,0) -> 0 | R34: =VLOOKUP(C34,'IP PITSS'!$B$10:$Q$91,16,0) -> 0 | S34: =VLOOKUP(C34,'IP PITSS'!$B$10:$R$91,17,0) -> 0 | U34: =+K34-O34-P34+Q34+R34+S34+IFERROR(VLOOKUP('RESUMEN PITS'!C34,'IP PITSS'!$B$10:$M$91,10),0)+IFERROR(VLOOKUP('RESUMEN PITS'!C34,'IP PITSS'!$B$10:$M$91,11),0)+IFERROR(VLOOKUP('RESUMEN PITS'!C34,'IP PITSS'!$B$10:$M$91,12),0)+VLOOKUP("Comision",'IP PITSS'!$I$97:$J$108,2)/COUNT($F$9:$F$111)+IFERROR(VLOOKUP('RESUMEN PITS'!C34,'IP PITSS'!$B$10:$AD$91,15),0)+IFERROR(VLOOKUP('RESUMEN PITS'!C34,'IP PITSS'!$B$10:$AD$91,21),0)+IFERROR(VLOOKUP('RESUMEN PITS'!C34,'IP PITSS'!$B$10:$AD$91,22),0)+IFERROR(VLOOKUP('RESUMEN PITS'!C34,'IP PITSS'!$B$10:$AD$91,23),0)+IFERROR(VLOOKUP('RESUMEN PITS'!C34,'IP PITSS'!$B$10:$AD$91,24),0)+IFERROR(VLOOKUP('RESUMEN PITS'!C34,'IP PITSS'!$B$10:$AD$91,26),0)+IFERROR(VLOOKUP('RESUMEN PITS'!C34,'IP PITSS'!$B$10:$AD$91,28),0)+IFERROR(VLOOKUP('RESUMEN PITS'!C34,'IP PITSS'!$B$10:$AD$91,29),0)+IFERROR(VLOOKUP('RESUMEN PITS'!C34,'IP PITSS'!$B$10:$AD$91,9),0)*2% -> 5915.9536 | V34: =+M34-U34 -> -1915.9536 | X34: SEI0452
A35: SEI0438 | B35: IP INNOVACION | C35: Lopez Terron Roberto Porfirio | D35: =VLOOKUP(C35,'IP PITSS'!$B$10:$U$91,20,0) -> 5952.2 | F35: =VLOOKUP(C35,'SIND PITS'!$C$3:$H$104,2,0) -> 1047.8 | G35: =VLOOKUP(C35,'SIND PITS'!$C$3:$E$104,3,0) -> 187.5 | H35: =VLOOKUP(C35,'SIND PITS'!$C$3:$F$104,4,0) -> 0 | I35: =VLOOKUP(C35,'SIND PITS'!$C$3:$G$104,5,0) -> 0 | K35: =SUM(D35:I35) -> 7187.5 | L35: 14000 | M35: =+L35/2 -> 7000 | O35: =VLOOKUP(C35,'IP PITSS'!$B$10:$I$91,8,0) -> 0 | P35: =+G35+H35+I35 -> 187.5 | Q35: =VLOOKUP(C35,'IP PITSS'!$B$10:$K$91,10,0)+VLOOKUP('RESUMEN PITS'!C35,'IP PITSS'!$B$10:$L$91,11,0)+VLOOKUP('RESUMEN PITS'!C35,'IP PITSS'!$B$10:$M$91,12,0) -> 0 | R35: =VLOOKUP(C35,'IP PITSS'!$B$10:$Q$91,16,0) -> 0 | S35: =VLOOKUP(C35,'IP PITSS'!$B$10:$R$91,17,0) -> 0 | U35: =+K35-O35-P35+Q35+R35+S35+IFERROR(VLOOKUP('RESUMEN PITS'!C35,'IP PITSS'!$B$10:$M$91,10),0)+IFERROR(VLOOKUP('RESUMEN PITS'!C35,'IP PITSS'!$B$10:$M$91,11),0)+IFERROR(VLOOKUP('RESUMEN PITS'!C35,'IP PITSS'!$B$10:$M$91,12),0)+VLOOKUP("Comision",'IP PITSS'!$I$97:$J$108,2)/COUNT($F$9:$F$111)+IFERROR(VLOOKUP('RESUMEN PITS'!C35,'IP PITSS'!$B$10:$AD$91,15),0)+IFERROR(VLOOKUP('RESUMEN PITS'!C35,'IP PITSS'!$B$10:$AD$91,21),0)+IFERROR(VLOOKUP('RESUMEN PITS'!C35,'IP PITSS'!$B$10:$AD$91,22),0)+IFERROR(VLOOKUP('RESUMEN PITS'!C35,'IP PITSS'!$B$10:$AD$91,23),0)+IFERROR(VLOOKUP('RESUMEN PITS'!C35,'IP PITSS'!$B$10:$AD$91,24),0)+IFERROR(VLOOKUP('RESUMEN PITS'!C35,'IP PITSS'!$B$10:$AD$91,26),0)+IFERROR(VLOOKUP('RESUMEN PITS'!C35,'IP PITSS'!$B$10:$AD$91,28),0)+IFERROR(VLOOKUP('RESUMEN PITS'!C35,'IP PITSS'!$B$10:$AD$91,29),0)+IFERROR(VLOOKUP('RESUMEN PITS'!C35,'IP PITSS'!$B$10:$AD$91,9),0)*2% -> 8915.9536 | V35: =+M35-U35 -> -1915.9536 | X35: SEI0463
A36: SEI0442 | B36: IP INNOVACION | C36: Chavez Pedraza Samuel | D36: =VLOOKUP(C36,'IP PITSS'!$B$10:$U$91,20,0) -> 5952.2 | F36: =VLOOKUP(C36,'SIND PITS'!$C$3:$H$104,2,0) -> 1047.8 | G36: =VLOOKUP(C36,'SIND PITS'!$C$3:$E$104,3,0) -> 312.5 | H36: =VLOOKUP(C36,'SIND PITS'!$C$3:$F$104,4,0) -> 0 | I36: =VLOOKUP(C36,'SIND PITS'!$C$3:$G$104,5,0) -> 0 | K36: =SUM(D36:I36) -> 7312.5 | L36: 14000 | M36: =+L36/2 -> 7000 | O36: =VLOOKUP(C36,'IP PITSS'!$B$10:$I$91,8,0) -> 0 | P36: =+G36+H36+I36 -> 312.5 | Q36: =VLOOKUP(C36,'IP PITSS'!$B$10:$K$91,10,0)+VLOOKUP('RESUMEN PITS'!C36,'IP PITSS'!$B$10:$L$91,11,0)+VLOOKUP('RESUMEN PITS'!C36,'IP PITSS'!$B$10:$M$91,12,0) -> 0 | R36: =VLOOKUP(C36,'IP PITSS'!$B$10:$Q$91,16,0) -> 0 | S36: =VLOOKUP(C36,'IP PITSS'!$B$10:$R$91,17,0) -> 0 | U36: =+K36-O36-P36+Q36+R36+S36+IFERROR(VLOOKUP('RESUMEN PITS'!C36,'IP PITSS'!$B$10:$M$91,10),0)+IFERROR(VLOOKUP('RESUMEN PITS'!C36,'IP PITSS'!$B$10:$M$91,11),0)+IFERROR(VLOOKUP('RESUMEN PITS'!C36,'IP PITSS'!$B$10:$M$91,12),0)+VLOOKUP("Comision",'IP PITSS'!$I$97:$J$108,2)/COUNT($F$9:$F$111)+IFERROR(VLOOKUP('RESUMEN PITS'!C36,'IP PITSS'!$B$10:$AD$91,15),0)+IFERROR(VLOOKUP('RESUMEN PITS'!C36,'IP PITSS'!$B$10:$AD$91,21),0)+IFERROR(VLOOKUP('RESUMEN PITS'!C36,'IP PITSS'!$B$10:$AD$91,22),0)+IFERROR(VLOOKUP('RESUMEN PITS'!C36,'IP PITSS'!$B$10:$AD$91,23),0)+IFERROR(VLOOKUP('RESUMEN PITS'!C36,'IP PITSS'!$B$10:$AD$91,24),0)+IFERROR(VLOOKUP('RESUMEN PITS'!C36,'IP PITSS'!$B$10:$AD$91,26),0)+IFERROR(VLOOKUP('RESUMEN PITS'!C36,'IP PITSS'!$B$10:$AD$91,28),0)+IFERROR(VLOOKUP('RESUMEN PITS'!C36,'IP PITSS'!$B$10:$AD$91,29),0)+IFERROR(VLOOKUP('RESUMEN PITS'!C36,'IP PITSS'!$B$10:$AD$91,9),0)*2% -> 7056.5626 | V36: =+M36-U36 -> -56.562642 | X36: SEI0467
A37: SEI0443 | B37: IP INNOVACION | C37: Castillo Nungaray Nestor Roman | D37: =VLOOKUP(C37,'IP PITSS'!$B$10:$U$91,20,0) -> 2864.8 | F37: =VLOOKUP(C37,'SIND PITS'!$C$3:$H$104,2,0) -> 285.2 | G37: =VLOOKUP(C37,'SIND PITS'!$C$3:$E$104,3,0) -> 800 | H37: =VLOOKUP(C37,'SIND PITS'!$C$3:$F$104,4,0) -> 0 | I37: =VLOOKUP(C37,'SIND PITS'!$C$3:$G$104,5,0) -> 0 | K37: =SUM(D37:I37) -> 3950 | L37: 6300 | M37: =+L37/2 -> 3150 | O37: =VLOOKUP(C37,'IP PITSS'!$B$10:$I$91,8,0) -> 0 | P37: =+G37+H37+I37 -> 800 | Q37: =VLOOKUP(C37,'IP PITSS'!$B$10:$K$91,10,0)+VLOOKUP('RESUMEN PITS'!C37,'IP PITSS'!$B$10:$L$91,11,0)+VLOOKUP('RESUMEN PITS'!C37,'IP PITSS'!$B$10:$M$91,12,0) -> 0 | R37: =VLOOKUP(C37,'IP PITSS'!$B$10:$Q$91,16,0) -> 0 | S37: =VLOOKUP(C37,'IP PITSS'!$B$10:$R$91,17,0) -> 0 | U37: =+K37-O37-P37+Q37+R37+S37+IFERROR(VLOOKUP('RESUMEN PITS'!C37,'IP PITSS'!$B$10:$M$91,10),0)+IFERROR(VLOOKUP('RESUMEN PITS'!C37,'IP PITSS'!$B$10:$M$91,11),0)+IFERROR(VLOOKUP('RESUMEN PITS'!C37,'IP PITSS'!$B$10:$M$91,12),0)+VLOOKUP("Comision",'IP PITSS'!$I$97:$J$108,2)/COUNT($F$9:$F$111)+IFERROR(VLOOKUP('RESUMEN PITS'!C37,'IP PITSS'!$B$10:$AD$91,15),0)+IFERROR(VLOOKUP('RESUMEN PITS'!C37,'IP PITSS'!$B$10:$AD$91,21),0)+IFERROR(VLOOKUP('RESUMEN PITS'!C37,'IP PITSS'!$B$10:$AD$91,22),0)+IFERROR(VLOOKUP('RESUMEN PITS'!C37,'IP PITSS'!$B$10:$AD$91,23),0)+IFERROR(VLOOKUP('RESUMEN PITS'!C37,'IP PITSS'!$B$10:$AD$91,24),0)+IFERROR(VLOOKUP('RESUMEN PITS'!C37,'IP PITSS'!$B$10:$AD$91,26),0)+IFERROR(VLOOKUP('RESUMEN PITS'!C37,'IP PITSS'!$B$10:$AD$91,28),0)+IFERROR(VLOOKUP('RESUMEN PITS'!C37,'IP PITSS'!$B$10:$AD$91,29),0)+IFERROR(VLOOKUP('RESUMEN PITS'!C37,'IP PITSS'!$B$10:$AD$91,9),0)*2% -> 3206.5626 | V37: =+M37-U37 -> -56.562642 | X37: SEI0468
A38: SEI0444 | B38: IP INNOVACION | C38: Marquez Hernandez Rogelio | D38: =VLOOKUP(C38,'IP PITSS'!$B$10:$U$91,20,0) -> 3142.6 | F38: =VLOOKUP(C38,'SIND PITS'!$C$3:$H$104,2,0) -> 416.4 | G38: =VLOOKUP(C38,'SIND PITS'!$C$3:$E$104,3,0) -> 150 | H38: =VLOOKUP(C38,'SIND PITS'!$C$3:$F$104,4,0) -> 0 | I38: =VLOOKUP(C38,'SIND PITS'!$C$3:$G$104,5,0) -> 0 | K38: =SUM(D38:I38) -> 3709 | L38: 8000 | M38: =+L38/2 -> 4000 | O38: =VLOOKUP(C38,'IP PITSS'!$B$10:$I$91,8,0) -> 0 | P38: =+G38+H38+I38 -> 150 | Q38: =VLOOKUP(C38,'IP PITSS'!$B$10:$K$91,10,0)+VLOOKUP('RESUMEN PITS'!C38,'IP PITSS'!$B$10:$L$91,11,0)+VLOOKUP('RESUMEN PITS'!C38,'IP PITSS'!$B$10:$M$91,12,0) -> 0 | R38: =VLOOKUP(C38,'IP PITSS'!$B$10:$Q$91,16,0) -> 0 | S38: =VLOOKUP(C38,'IP PITSS'!$B$10:$R$91,17,0) -> 441 | U38: =+K38-O38-P38+Q38+R38+S38+IFERROR(VLOOKUP('RESUMEN PITS'!C38,'IP PITSS'!$B$10:$M$91,10),0)+IFERROR(VLOOKUP('RESUMEN PITS'!C38,'IP PITSS'!$B$10:$M$91,11),0)+IFERROR(VLOOKUP('RESUMEN PITS'!C38,'IP PITSS'!$B$10:$M$91,12),0)+VLOOKUP("Comision",'IP PITSS'!$I$97:$J$108,2)/COUNT($F$9:$F$111)+IFERROR(VLOOKUP('RESUMEN PITS'!C38,'IP PITSS'!$B$10:$AD$91,15),0)+IFERROR(VLOOKUP('RESUMEN PITS'!C38,'IP PITSS'!$B$10:$AD$91,21),0)+IFERROR(VLOOKUP('RESUMEN PITS'!C38,'IP PITSS'!$B$10:$AD$91,22),0)+IFERROR(VLOOKUP('RESUMEN PITS'!C38,'IP PITSS'!$B$10:$AD$91,23),0)+IFERROR(VLOOKUP('RESUMEN PITS'!C38,'IP PITSS'!$B$10:$AD$91,24),0)+IFERROR(VLOOKUP('RESUMEN PITS'!C38,'IP PITSS'!$B$10:$AD$91,26),0)+IFERROR(VLOOKUP('RESUMEN PITS'!C38,'IP PITSS'!$B$10:$AD$91,28),0)+IFERROR(VLOOKUP('RESUMEN PITS'!C38,'IP PITSS'!$B$10:$AD$91,29),0)+IFERROR(VLOOKUP('RESUMEN PITS'!C38,'IP PITSS'!$B$10:$AD$91,9),0)*2% -> 5915.9536 | V38: =+M38-U38 -> -1915.9536 | X38: SEI0469
A39: SEI0449 | B39: IP INNOVACION | C39: Flores Cerrillos Jorge Humberto | D39: =VLOOKUP(C39,'IP PITSS'!$B$10:$U$91,20,0) -> 3583.6 | F39: =VLOOKUP(C39,'SIND PITS'!$C$3:$H$104,2,0) -> 416.4 | G39: =VLOOKUP(C39,'SIND PITS'!$C$3:$E$104,3,0) -> 130 | H39: =VLOOKUP(C39,'SIND PITS'!$C$3:$F$104,4,0) -> 0 | I39: =VLOOKUP(C39,'SIND PITS'!$C$3:$G$104,5,0) -> 0 | K39: =SUM(D39:I39) -> 4130 | L39: 8000 | M39: =+L39/2 -> 4000 | O39: =VLOOKUP(C39,'IP PITSS'!$B$10:$I$91,8,0) -> 0 | P39: =+G39+H39+I39 -> 130 | Q39: =VLOOKUP(C39,'IP PITSS'!$B$10:$K$91,10,0)+VLOOKUP('RESUMEN PITS'!C39,'IP PITSS'!$B$10:$L$91,11,0)+VLOOKUP('RESUMEN PITS'!C39,'IP PITSS'!$B$10:$M$91,12,0) -> 0 | R39: =VLOOKUP(C39,'IP PITSS'!$B$10:$Q$91,16,0) -> 0 | S39: =VLOOKUP(C39,'IP PITSS'!$B$10:$R$91,17,0) -> 0 | U39: =+K39-O39-P39+Q39+R39+S39+IFERROR(VLOOKUP('RESUMEN PITS'!C39,'IP PITSS'!$B$10:$M$91,10),0)+IFERROR(VLOOKUP('RESUMEN PITS'!C39,'IP PITSS'!$B$10:$M$91,11),0)+IFERROR(VLOOKUP('RESUMEN PITS'!C39,'IP PITSS'!$B$10:$M$91,12),0)+VLOOKUP("Comision",'IP PITSS'!$I$97:$J$108,2)/COUNT($F$9:$F$111)+IFERROR(VLOOKUP('RESUMEN PITS'!C39,'IP PITSS'!$B$10:$AD$91,15),0)+IFERROR(VLOOKUP('RESUMEN PITS'!C39,'IP PITSS'!$B$10:$AD$91,21),0)+IFERROR(VLOOKUP('RESUMEN PITS'!C39,'IP PITSS'!$B$10:$AD$91,22),0)+IFERROR(VLOOKUP('RESUMEN PITS'!C39,'IP PITSS'!$B$10:$AD$91,23),0)+IFERROR(VLOOKUP('RESUMEN PITS'!C39,'IP PITSS'!$B$10:$AD$91,24),0)+IFERROR(VLOOKUP('RESUMEN PITS'!C39,'IP PITSS'!$B$10:$AD$91,26),0)+IFERROR(VLOOKUP('RESUMEN PITS'!C39,'IP PITSS'!$B$10:$AD$91,28),0)+IFERROR(VLOOKUP('RESUMEN PITS'!C39,'IP PITSS'!$B$10:$AD$91,29),0)+IFERROR(VLOOKUP('RESUMEN PITS'!C39,'IP PITSS'!$B$10:$AD$91,9),0)*2% -> 5417.0416 | V39: =+M39-U39 -> -1417.0416 | X39: SEI0474
A40: SEI0455 | B40: IP INNOVACION | C40: Perez Garcia Andres Alvaro | D40: =VLOOKUP(C40,'IP PITSS'!$B$10:$U$91,20,0) -> 3573.6 | F40: =VLOOKUP(C40,'SIND PITS'!$C$3:$H$104,2,0) -> 416.4 | G40: =VLOOKUP(C40,'SIND PITS'!$C$3:$E$104,3,0) -> 315 | H40: =VLOOKUP(C40,'SIND PITS'!$C$3:$F$104,4,0) -> 0 | I40: =VLOOKUP(C40,'SIND PITS'!$C$3:$G$104,5,0) -> 0 | K40: =SUM(D40:I40) -> 4305 | L40: 8000 | M40: =+L40/2 -> 4000 | O40: =VLOOKUP(C40,'IP PITSS'!$B$10:$I$91,8,0) -> 240 | P40: =+G40+H40+I40 -> 315 | Q40: =VLOOKUP(C40,'IP PITSS'!$B$10:$K$91,10,0)+VLOOKUP('RESUMEN PITS'!C40,'IP PITSS'!$B$10:$L$91,11,0)+VLOOKUP('RESUMEN PITS'!C40,'IP PITSS'!$B$10:$M$91,12,0) -> 0 | R40: =VLOOKUP(C40,'IP PITSS'!$B$10:$Q$91,16,0) -> 0 | S40: =VLOOKUP(C40,'IP PITSS'!$B$10:$R$91,17,0) -> 250 | U40: =+K40-O40-P40+Q40+R40+S40+IFERROR(VLOOKUP('RESUMEN PITS'!C40,'IP PITSS'!$B$10:$M$91,10),0)+IFERROR(VLOOKUP('RESUMEN PITS'!C40,'IP PITSS'!$B$10:$M$91,11),0)+IFERROR(VLOOKUP('RESUMEN PITS'!C40,'IP PITSS'!$B$10:$M$91,12),0)+VLOOKUP("Comision",'IP PITSS'!$I$97:$J$108,2)/COUNT($F$9:$F$111)+IFERROR(VLOOKUP('RESUMEN PITS'!C40,'IP PITSS'!$B$10:$AD$91,15),0)+IFERROR(VLOOKUP('RESUMEN PITS'!C40,'IP PITSS'!$B$10:$AD$91,21),0)+IFERROR(VLOOKUP('RESUMEN PITS'!C40,'IP PITSS'!$B$10:$AD$91,22),0)+IFERROR(VLOOKUP('RESUMEN PITS'!C40,'IP PITSS'!$B$10:$AD$91,23),0)+IFERROR(VLOOKUP('RESUMEN PITS'!C40,'IP PITSS'!$B$10:$AD$91,24),0)+IFERROR(VLOOKUP('RESUMEN PITS'!C40,'IP PITSS'!$B$10:$AD$91,26),0)+IFERROR(VLOOKUP('RESUMEN PITS'!C40,'IP PITSS'!$B$10:$AD$91,28),0)+IFERROR(VLOOKUP('RESUMEN PITS'!C40,'IP PITSS'!$B$10:$AD$91,29),0)+IFERROR(VLOOKUP('RESUMEN PITS'!C40,'IP PITSS'!$B$10:$AD$91,9),0)*2% -> 5344.8726 | V40: =+M40-U40 -> -1344.8726 | X40: SEI0494
A41: SEI0456 | B41: IP INNOVACION | C41: Chavira Garcia David Fernando | D41: =VLOOKUP(C41,'IP PITSS'!$B$10:$U$91,20,0) -> 4406.4 | F41: =VLOOKUP(C41,'SIND PITS'!$C$3:$H$104,2,0) -> 593.6 | G41: =VLOOKUP(C41,'SIND PITS'!$C$3:$E$104,3,0) -> 60 | H41: =VLOOKUP(C41,'SIND PITS'!$C$3:$F$104,4,0) -> 0 | I41: =VLOOKUP(C41,'SIND PITS'!$C$3:$G$104,5,0) -> 0 | K41: =SUM(D41:I41) -> 5060 | L41: 10000 | M41: =+L41/2 -> 5000 | O41: =VLOOKUP(C41,'IP PITSS'!$B$10:$I$91,8,0) -> 0 | P41: =+G41+H41+I41 -> 60 | Q41: =VLOOKUP(C41,'IP PITSS'!$B$10:$K$91,10,0)+VLOOKUP('RESUMEN PITS'!C41,'IP PITSS'!$B$10:$L$91,11,0)+VLOOKUP('RESUMEN PITS'!C41,'IP PITSS'!$B$10:$M$91,12,0) -> 0 | R41: =VLOOKUP(C41,'IP PITSS'!$B$10:$Q$91,16,0) -> 0 | S41: =VLOOKUP(C41,'IP PITSS'!$B$10:$R$91,17,0) -> 0 | U41: =+K41-O41-P41+Q41+R41+S41+IFERROR(VLOOKUP('RESUMEN PITS'!C41,'IP PITSS'!$B$10:$M$91,10),0)+IFERROR(VLOOKUP('RESUMEN PITS'!C41,'IP PITSS'!$B$10:$M$91,11),0)+IFERROR(VLOOKUP('RESUMEN PITS'!C41,'IP PITSS'!$B$10:$M$91,12),0)+VLOOKUP("Comision",'IP PITSS'!$I$97:$J$108,2)/COUNT($F$9:$F$111)+IFERROR(VLOOKUP('RESUMEN PITS'!C41,'IP PITSS'!$B$10:$AD$91,15),0)+IFERROR(VLOOKUP('RESUMEN PITS'!C41,'IP PITSS'!$B$10:$AD$91,21),0)+IFERROR(VLOOKUP('RESUMEN PITS'!C41,'IP PITSS'!$B$10:$AD$91,22),0)+IFERROR(VLOOKUP('RESUMEN PITS'!C41,'IP PITSS'!$B$10:$AD$91,23),0)+IFERROR(VLOOKUP('RESUMEN PITS'!C41,'IP PITSS'!$B$10:$AD$91,24),0)+IFERROR(VLOOKUP('RESUMEN PITS'!C41,'IP PITSS'!$B$10:$AD$91,26),0)+IFERROR(VLOOKUP('RESUMEN PITS'!C41,'IP PITSS'!$B$10:$AD$91,28),0)+IFERROR(VLOOKUP('RESUMEN PITS'!C41,'IP PITSS'!$B$10:$AD$91,29),0)+IFERROR(VLOOKUP('RESUMEN PITS'!C41,'IP PITSS'!$B$10:$AD$91,9),0)*2% -> 5056.5626 | V41: =+M41-U41 -> -56.562642 | X41: SEI0495
A42: SEI0457 | B42: IP INNOVACION | C42: Guerrero Lara Cesar Adrian | D42: =VLOOKUP(C42,'IP PITSS'!$B$10:$U$91,20,0) -> 3583.6 | F42: =VLOOKUP(C42,'SIND PITS'!$C$3:$H$104,2,0) -> 416.4 | G42: =VLOOKUP(C42,'SIND PITS'!$C$3:$E$104,3,0) -> 225 | H42: =VLOOKUP(C42,'SIND PITS'!$C$3:$F$104,4,0) -> 0 | I42: =VLOOKUP(C42,'SIND PITS'!$C$3:$G$104,5,0) -> 0 | K42: =SUM(D42:I42) -> 4225 | L42: 8000 | M42: =+L42/2 -> 4000 | O42: =VLOOKUP(C42,'IP PITSS'!$B$10:$I$91,8,0) -> 0 | P42: =+G42+H42+I42 -> 225 | Q42: =VLOOKUP(C42,'IP PITSS'!$B$10:$K$91,10,0)+VLOOKUP('RESUMEN PITS'!C42,'IP PITSS'!$B$10:$L$91,11,0)+VLOOKUP('RESUMEN PITS'!C42,'IP PITSS'!$B$10:$M$91,12,0) -> 0 | R42: =VLOOKUP(C42,'IP PITSS'!$B$10:$Q$91,16,0) -> 0 | S42: =VLOOKUP(C42,'IP PITSS'!$B$10:$R$91,17,0) -> 0 | U42: =+K42-O42-P42+Q42+R42+S42+IFERROR(VLOOKUP('RESUMEN PITS'!C42,'IP PITSS'!$B$10:$M$91,10),0)+IFERROR(VLOOKUP('RESUMEN PITS'!C42,'IP PITSS'!$B$10:$M$91,11),0)+IFERROR(VLOOKUP('RESUMEN PITS'!C42,'IP PITSS'!$B$10:$M$91,12),0)+VLOOKUP("Comision",'IP PITSS'!$I$97:$J$108,2)/COUNT($F$9:$F$111)+IFERROR(VLOOKUP('RESUMEN PITS'!C42,'IP PITSS'!$B$10:$AD$91,15),0)+IFERROR(VLOOKUP('RESUMEN PITS'!C42,'IP PITSS'!$B$10:$AD$91,21),0)+IFERROR(VLOOKUP('RESUMEN PITS'!C42,'IP PITSS'!$B$10:$AD$91,22),0)+IFERROR(VLOOKUP('RESUMEN PITS'!C42,'IP PITSS'!$B$10:$AD$91,23),0)+IFERROR(VLOOKUP('RESUMEN PITS'!C42,'IP PITSS'!$B$10:$AD$91,24),0)+IFERROR(VLOOKUP('RESUMEN PITS'!C42,'IP PITSS'!$B$10:$AD$91,26),0)+IFERROR(VLOOKUP('RESUMEN PITS'!C42,'IP PITSS'!$B$10:$AD$91,28),0)+IFERROR(VLOOKUP('RESUMEN PITS'!C42,'IP PITSS'!$B$10:$AD$91,29),0)+IFERROR(VLOOKUP('RESUMEN PITS'!C42,'IP PITSS'!$B$10:$AD$91,9),0)*2% -> 5417.0416 | V42: =+M42-U42 -> -1417.0416 | X42: SEI0496
A43: SEI0458 | B43: IP INNOVACION | C43: Martinez Zamora Gerardo Mario | D43: =VLOOKUP(C43,'IP PITSS'!$B$10:$U$91,20,0) -> 2709.8 | F43: =VLOOKUP(C43,'SIND PITS'!$C$3:$H$104,2,0) -> 549.875 | G43: =VLOOKUP(C43,'SIND PITS'!$C$3:$E$104,3,0) -> 375 | H43: =VLOOKUP(C43,'SIND PITS'!$C$3:$F$104,4,0) -> 0 | I43: =VLOOKUP(C43,'SIND PITS'!$C$3:$G$104,5,0) -> 0 | K43: =SUM(D43:I43) -> 3634.675 | L43: 9550.01 | M43: =+L43/2 -> 4775.005 | O43: =VLOOKUP(C43,'IP PITSS'!$B$10:$I$91,8,0) -> 0 | P43: =+G43+H43+I43 -> 375 | Q43: =VLOOKUP(C43,'IP PITSS'!$B$10:$K$91,10,0)+VLOOKUP('RESUMEN PITS'!C43,'IP PITSS'!$B$10:$L$91,11,0)+VLOOKUP('RESUMEN PITS'!C43,'IP PITSS'!$B$10:$M$91,12,0) -> 1515.33 | R43: =VLOOKUP(C43,'IP PITSS'!$B$10:$Q$91,16,0) -> 0 | S43: =VLOOKUP(C43,'IP PITSS'!$B$10:$R$91,17,0) -> 0 | U43: =+K43-O43-P43+Q43+R43+S43+IFERROR(VLOOKUP('RESUMEN PITS'!C43,'IP PITSS'!$B$10:$M$91,10),0)+IFERROR(VLOOKUP('RESUMEN PITS'!C43,'IP PITSS'!$B$10:$M$91,11),0)+IFERROR(VLOOKUP('RESUMEN PITS'!C43,'IP PITSS'!$B$10:$M$91,12),0)+VLOOKUP("Comision",'IP PITSS'!$I$97:$J$108,2)/COUNT($F$9:$F$111)+IFERROR(VLOOKUP('RESUMEN PITS'!C43,'IP PITSS'!$B$10:$AD$91,15),0)+IFERROR(VLOOKUP('RESUMEN PITS'!C43,'IP PITSS'!$B$10:$AD$91,21),0)+IFERROR(VLOOKUP('RESUMEN PITS'!C43,'IP PITSS'!$B$10:$AD$91,22),0)+IFERROR(VLOOKUP('RESUMEN PITS'!C43,'IP PITSS'!$B$10:$AD$91,23),0)+IFERROR(VLOOKUP('RESUMEN PITS'!C43,'IP PITSS'!$B$10:$AD$91,24),0)+IFERROR(VLOOKUP('RESUMEN PITS'!C43,'IP PITSS'!$B$10:$AD$91,26),0)+IFERROR(VLOOKUP('RESUMEN PITS'!C43,'IP PITSS'!$B$10:$AD$91,28),0)+IFERROR(VLOOKUP('RESUMEN PITS'!C43,'IP PITSS'!$B$10:$AD$91,29),0)+IFERROR(VLOOKUP('RESUMEN PITS'!C43,'IP PITSS'!$B$10:$AD$91,9),0)*2% -> 6690.9586 | V43: =+M43-U43 -> -1915.9536 | X43: SEI0497
A44: SEI0460 | B44: IP INNOVACION | C44: Castellon Ramos Rene | D44: =VLOOKUP(C44,'IP PITSS'!$B$10:$U$91,20,0) -> 1995.2 | F44: =VLOOKUP(C44,'SIND PITS'!$C$3:$H$104,2,0) -> 384.785 | G44: =VLOOKUP(C44,'SIND PITS'!$C$3:$E$104,3,0) -> 70 | H44: =VLOOKUP(C44,'SIND PITS'!$C$3:$F$104,4,0) -> 0 | I44: =VLOOKUP(C44,'SIND PITS'!$C$3:$G$104,5,0) -> 0 | K44: =SUM(D44:I44) -> 2449.985 | L44: 7505.99 | M44: =+L44/2 -> 3752.995 | O44: =VLOOKUP(C44,'IP PITSS'!$B$10:$I$91,8,0) -> 0 | P44: =+G44+H44+I44 -> 70 | Q44: =VLOOKUP(C44,'IP PITSS'!$B$10:$K$91,10,0)+VLOOKUP('RESUMEN PITS'!C44,'IP PITSS'!$B$10:$L$91,11,0)+VLOOKUP('RESUMEN PITS'!C44,'IP PITSS'!$B$10:$M$91,12,0) -> 1373.01 | R44: =VLOOKUP(C44,'IP PITSS'!$B$10:$Q$91,16,0) -> 0 | S44: =VLOOKUP(C44,'IP PITSS'!$B$10:$R$91,17,0) -> 0 | U44: =+K44-O44-P44+Q44+R44+S44+IFERROR(VLOOKUP('RESUMEN PITS'!C44,'IP PITSS'!$B$10:$M$91,10),0)+IFERROR(VLOOKUP('RESUMEN PITS'!C44,'IP PITSS'!$B$10:$M$91,11),0)+IFERROR(VLOOKUP('RESUMEN PITS'!C44,'IP PITSS'!$B$10:$M$91,12),0)+VLOOKUP("Comision",'IP PITSS'!$I$97:$J$108,2)/COUNT($F$9:$F$111)+IFERROR(VLOOKUP('RESUMEN PITS'!C44,'IP PITSS'!$B$10:$AD$91,15),0)+IFERROR(VLOOKUP('RESUMEN PITS'!C44,'IP PITSS'!$B$10:$AD$91,21),0)+IFERROR(VLOOKUP('RESUMEN PITS'!C44,'IP PITSS'!$B$10:$AD$91,22),0)+IFERROR(VLOOKUP('RESUMEN PITS'!C44,'IP PITSS'!$B$10:$AD$91,23),0)+IFERROR(VLOOKUP('RESUMEN PITS'!C44,'IP PITSS'!$B$10:$AD$91,24),0)+IFERROR(VLOOKUP('RESUMEN PITS'!C44,'IP PITSS'!$B$10:$AD$91,26),0)+IFERROR(VLOOKUP('RESUMEN PITS'!C44,'IP PITSS'!$B$10:$AD$91,28),0)+IFERROR(VLOOKUP('RESUMEN PITS'!C44,'IP PITSS'!$B$10:$AD$91,29),0)+IFERROR(VLOOKUP('RESUMEN PITS'!C44,'IP PITSS'!$B$10:$AD$91,9),0)*2% -> 3809.5576 | V44: =+M44-U44 -> -56.562642 | X44: SEI0499
... A96: SEI0545 | B96: IP INNOVACION | C96: Vallarta Fonseca Mayra Karina | D96: =VLOOKUP(C96,'IP PITSS'!$B$10:$U$91,20,0) -> 1576 | F96: =VLOOKUP(C96,'SIND PITS'!$C$3:$H$104,2,0) -> 135.22 | G96: =VLOOKUP(C96,'SIND PITS'!$C$3:$E$104,3,0) -> 0 | H96: =VLOOKUP(C96,'SIND PITS'!$C$3:$F$104,4,0) -> 0 | I96: =VLOOKUP(C96,'SIND PITS'!$C$3:$G$104,5,0) -> 0 | K96: =SUM(D96:I96) -> 1711.22 | L96: 6000 | M96: =+L96/2 -> 3000 | O96: =VLOOKUP(C96,'IP PITSS'!$B$10:$I$91,8,0) -> 0 | P96: =+G96+H96+I96 -> 0 | Q96: =VLOOKUP(C96,'IP PITSS'!$B$10:$K$91,10,0)+VLOOKUP('RESUMEN PITS'!C96,'IP PITSS'!$B$10:$L$91,11,0)+VLOOKUP('RESUMEN PITS'!C96,'IP PITSS'!$B$10:$M$91,12,0) -> 652.18 | R96: =VLOOKUP(C96,'IP PITSS'!$B$10:$Q$91,16,0) -> 636.6 | S96: =VLOOKUP(C96,'IP PITSS'!$B$10:$R$91,17,0) -> 0 | U96: =+K96-O96-P96+Q96+R96+S96+IFERROR(VLOOKUP('RESUMEN PITS'!C96,'IP PITSS'!$B$10:$M$91,10),0)+IFERROR(VLOOKUP('RESUMEN PITS'!C96,'IP PITSS'!$B$10:$M$91,11),0)+IFERROR(VLOOKUP('RESUMEN PITS'!C96,'IP PITSS'!$B$10:$M$91,12),0)+VLOOKUP("Comision",'IP PITSS'!$I$97:$J$108,2)/COUNT($F$9:$F$111)+IFERROR(VLOOKUP('RESUMEN PITS'!C96,'IP PITSS'!$B$10:$AD$91,15),0)+IFERROR(VLOOKUP('RESUMEN PITS'!C96,'IP PITSS'!$B$10:$AD$91,21),0)+IFERROR(VLOOKUP('RESUMEN PITS'!C96,'IP PITSS'!$B$10:$AD$91,22),0)+IFERROR(VLOOKUP('RESUMEN PITS'!C96,'IP PITSS'!$B$10:$AD$91,23),0)+IFERROR(VLOOKUP('RESUMEN PITS'!C96,'IP PITSS'!$B$10:$AD$91,24),0)+IFERROR(VLOOKUP('RESUMEN PITS'!C96,'IP PITSS'!$B$10:$AD$91,26),0)+IFERROR(VLOOKUP('RESUMEN PITS'!C96,'IP PITSS'!$B$10:$AD$91,28),0)+IFERROR(VLOOKUP('RESUMEN PITS'!C96,'IP PITSS'!$B$10:$AD$91,29),0)+IFERROR(VLOOKUP('RESUMEN PITS'!C96,'IP PITSS'!$B$10:$AD$91,9),0)*2% -> 4537.7236 | V96: =+M96-U96 -> -1537.7236 | X96: SEI0653
A97: SEI0547 | B97: IP INNOVACION | C97: Aguilar Garcia Rosa Paola | D97: =VLOOKUP(C97,'IP PITSS'!$B$10:$U$91,20,0) -> 2446.6 | F97: =VLOOKUP(C97,'SIND PITS'!$C$3:$H$104,2,0) -> 53.4 | G97: =VLOOKUP(C97,'SIND PITS'!$C$3:$E$104,3,0) -> 0 | H97: =VLOOKUP(C97,'SIND PITS'!$C$3:$F$104,4,0) -> 0 | I97: =VLOOKUP(C97,'SIND PITS'!$C$3:$G$104,5,0) -> 0 | K97: =SUM(D97:I97) -> 2500 | L97: 5000 | M97: =+L97/2 -> 2500 | O97: =VLOOKUP(C97,'IP PITSS'!$B$10:$I$91,8,0) -> 0 | P97: =+G97+H97+I97 -> 0 | Q97: =VLOOKUP(C97,'IP PITSS'!$B$10:$K$91,10,0)+VLOOKUP('RESUMEN PITS'!C97,'IP PITSS'!$B$10:$L$91,11,0)+VLOOKUP('RESUMEN PITS'!C97,'IP PITSS'!$B$10:$M$91,12,0) -> 0 | R97: =VLOOKUP(C97,'IP PITSS'!$B$10:$Q$91,16,0) -> 0 | S97: =VLOOKUP(C97,'IP PITSS'!$B$10:$R$91,17,0) -> 0 | U97: =+K97-O97-P97+Q97+R97+S97+IFERROR(VLOOKUP('RESUMEN PITS'!C97,'IP PITSS'!$B$10:$M$91,10),0)+IFERROR(VLOOKUP('RESUMEN PITS'!C97,'IP PITSS'!$B$10:$M$91,11),0)+IFERROR(VLOOKUP('RESUMEN PITS'!C97,'IP PITSS'!$B$10:$M$91,12),0)+VLOOKUP("Comision",'IP PITSS'!$I$97:$J$108,2)/COUNT($F$9:$F$111)+IFERROR(VLOOKUP('RESUMEN PITS'!C97,'IP PITSS'!$B$10:$AD$91,15),0)+IFERROR(VLOOKUP('RESUMEN PITS'!C97,'IP PITSS'!$B$10:$AD$91,21),0)+IFERROR(VLOOKUP('RESUMEN PITS'!C97,'IP PITSS'!$B$10:$AD$91,22),0)+IFERROR(VLOOKUP('RESUMEN PITS'!C97,'IP PITSS'!$B$10:$AD$91,23),0)+IFERROR(VLOOKUP('RESUMEN PITS'!C97,'IP PITSS'!$B$10:$AD$91,24),0)+IFERROR(VLOOKUP('RESUMEN PITS'!C97,'IP PITSS'!$B$10:$AD$91,26),0)+IFERROR(VLOOKUP('RESUMEN PITS'!C97,'IP PITSS'!$B$10:$AD$91,28),0)+IFERROR(VLOOKUP('RESUMEN PITS'!C97,'IP PITSS'!$B$10:$AD$91,29),0)+IFERROR(VLOOKUP('RESUMEN PITS'!C97,'IP PITSS'!$B$10:$AD$91,9),0)*2% -> 2556.5626 | V97: =+M97-U97 -> -56.562642
A98: SEI0548 | B98: IP INNOVACION | C98: Jauregui Madera Jorge Silvestre | D98: =VLOOKUP(C98,'IP PITSS'!$B$10:$U$91,20,0) -> 2865.8 | F98: =VLOOKUP(C98,'SIND PITS'!$C$3:$H$104,2,0) -> 134.2 | G98: =VLOOKUP(C98,'SIND PITS'!$C$3:$E$104,3,0) -> 487.5 | H98: =VLOOKUP(C98,'SIND PITS'!$C$3:$F$104,4,0) -> 0 | I98: =VLOOKUP(C98,'SIND PITS'!$C$3:$G$104,5,0) -> 0 | K98: =SUM(D98:I98) -> 3487.5 | L98: 6000 | M98: =+L98/2 -> 3000 | O98: =VLOOKUP(C98,'IP PITSS'!$B$10:$I$91,8,0) -> 0 | P98: =+G98+H98+I98 -> 487.5 | Q98: =VLOOKUP(C98,'IP PITSS'!$B$10:$K$91,10,0)+VLOOKUP('RESUMEN PITS'!C98,'IP PITSS'!$B$10:$L$91,11,0)+VLOOKUP('RESUMEN PITS'!C98,'IP PITSS'!$B$10:$M$91,12,0) -> 0 | R98: =VLOOKUP(C98,'IP PITSS'!$B$10:$Q$91,16,0) -> 0 | S98: =VLOOKUP(C98,'IP PITSS'!$B$10:$R$91,17,0) -> 0 | U98: =+K98-O98-P98+Q98+R98+S98+IFERROR(VLOOKUP('RESUMEN PITS'!C98,'IP PITSS'!$B$10:$M$91,10),0)+IFERROR(VLOOKUP('RESUMEN PITS'!C98,'IP PITSS'!$B$10:$M$91,11),0)+IFERROR(VLOOKUP('RESUMEN PITS'!C98,'IP PITSS'!$B$10:$M$91,12),0)+VLOOKUP("Comision",'IP PITSS'!$I$97:$J$108,2)/COUNT($F$9:$F$111)+IFERROR(VLOOKUP('RESUMEN PITS'!C98,'IP PITSS'!$B$10:$AD$91,15),0)+IFERROR(VLOOKUP('RESUMEN PITS'!C98,'IP PITSS'!$B$10:$AD$91,21),0)+IFERROR(VLOOKUP('RESUMEN PITS'!C98,'IP PITSS'!$B$10:$AD$91,22),0)+IFERROR(VLOOKUP('RESUMEN PITS'!C98,'IP PITSS'!$B$10:$AD$91,23),0)+IFERROR(VLOOKUP('RESUMEN PITS'!C98,'IP PITSS'!$B$10:$AD$91,24),0)+IFERROR(VLOOKUP('RESUMEN PITS'!C98,'IP PITSS'!$B$10:$AD$91,26),0)+IFERROR(VLOOKUP('RESUMEN PITS'!C98,'IP PITSS'!$B$10:$AD$91,28),0)+IFERROR(VLOOKUP('RESUMEN PITS'!C98,'IP PITSS'!$B$10:$AD$91,29),0)+IFERROR(VLOOKUP('RESUMEN PITS'!C98,'IP PITSS'!$B$10:$AD$91,9),0)*2% -> 4915.9536 | V98: =+M98-U98 -> -1915.9536
B99: IP INNOVACION | C99: Negrete Bejar Aide Sarai | D99: =VLOOKUP(C99,'IP PITSS'!$B$10:$U$91,20,0) -> 1314.8 | F99: =VLOOKUP(C99,'SIND PITS'!$C$3:$H$104,2,0) -> 207.63 | G99: =VLOOKUP(C99,'SIND PITS'!$C$3:$E$104,3,0) -> 3503.7 | H99: =VLOOKUP(C99,'SIND PITS'!$C$3:$F$104,4,0) -> 0 | I99: =VLOOKUP(C99,'SIND PITS'!$C$3:$G$104,5,0) -> 0 | K99: =SUM(D99:I99) -> 5026.13 | L99: 5000 | M99: =+L99/2 -> 2500 | O99: =VLOOKUP(C99,'IP PITSS'!$B$10:$I$91,8,0) -> 0 | P99: =+G99+H99+I99 -> 3503.7 | Q99: =VLOOKUP(C99,'IP PITSS'!$B$10:$K$91,10,0)+VLOOKUP('RESUMEN PITS'!C99,'IP PITSS'!$B$10:$L$91,11,0)+VLOOKUP('RESUMEN PITS'!C99,'IP PITSS'!$B$10:$M$91,12,0) -> 977.57 | R99: =VLOOKUP(C99,'IP PITSS'!$B$10:$Q$91,16,0) -> 0 | S99: =VLOOKUP(C99,'IP PITSS'!$B$10:$R$91,17,0) -> 0 | U99: =+K99-O99-P99+Q99+R99+S99+IFERROR(VLOOKUP('RESUMEN PITS'!C99,'IP PITSS'!$B$10:$M$91,10),0)+IFERROR(VLOOKUP('RESUMEN PITS'!C99,'IP PITSS'!$B$10:$M$91,11),0)+IFERROR(VLOOKUP('RESUMEN PITS'!C99,'IP PITSS'!$B$10:$M$91,12),0)+VLOOKUP("Comision",'IP PITSS'!$I$97:$J$108,2)/COUNT($F$9:$F$111)+IFERROR(VLOOKUP('RESUMEN PITS'!C99,'IP PITSS'!$B$10:$AD$91,15),0)+IFERROR(VLOOKUP('RESUMEN PITS'!C99,'IP PITSS'!$B$10:$AD$91,21),0)+IFERROR(VLOOKUP('RESUMEN PITS'!C99,'IP PITSS'!$B$10:$AD$91,22),0)+IFERROR(VLOOKUP('RESUMEN PITS'!C99,'IP PITSS'!$B$10:$AD$91,23),0)+IFERROR(VLOOKUP('RESUMEN PITS'!C99,'IP PITSS'!$B$10:$AD$91,24),0)+IFERROR(VLOOKUP('RESUMEN PITS'!C99,'IP PITSS'!$B$10:$AD$91,26),0)+IFERROR(VLOOKUP('RESUMEN PITS'!C99,'IP PITSS'!$B$10:$AD$91,28),0)+IFERROR(VLOOKUP('RESUMEN PITS'!C99,'IP PITSS'!$B$10:$AD$91,29),0)+IFERROR(VLOOKUP('RESUMEN PITS'!C99,'IP PITSS'!$B$10:$AD$91,9),0)*2% -> 3844.8726 | V99: =+M99-U99 -> -1344.8726
B100: IP INNOVACION | C100: Hinojosa Guerrero Alejandro | D100: =VLOOKUP(C100,'IP PITSS'!$B$10:$U$91,20,0) -> 2975.4 | F100: =VLOOKUP(C100,'SIND PITS'!$C$3:$H$104,2,0) -> 174.6 | G100: =VLOOKUP(C100,'SIND PITS'!$C$3:$E$104,3,0) -> 0 | H100: =VLOOKUP(C100,'SIND PITS'!$C$3:$F$104,4,0) -> 0 | I100: =VLOOKUP(C100,'SIND PITS'!$C$3:$G$104,5,0) -> 0 | K100: =SUM(D100:I100) -> 3150 | L100: 6300 | M100: =+L100/2 -> 3150 | O100: =VLOOKUP(C100,'IP PITSS'!$B$10:$I$91,8,0) -> 0 | P100: =+G100+H100+I100 -> 0 | Q100: =VLOOKUP(C100,'IP PITSS'!$B$10:$K$91,10,0)+VLOOKUP('RESUMEN PITS'!C100,'IP PITSS'!$B$10:$L$91,11,0)+VLOOKUP('RESUMEN PITS'!C100,'IP PITSS'!$B$10:$M$91,12,0) -> 0 | R100: =VLOOKUP(C100,'IP PITSS'!$B$10:$Q$91,16,0) -> 0 | S100: =VLOOKUP(C100,'IP PITSS'!$B$10:$R$91,17,0) -> 0 | U100: =+K100-O100-P100+Q100+R100+S100+IFERROR(VLOOKUP('RESUMEN PITS'!C100,'IP PITSS'!$B$10:$M$91,10),0)+IFERROR(VLOOKUP('RESUMEN PITS'!C100,'IP PITSS'!$B$10:$M$91,11),0)+IFERROR(VLOOKUP('RESUMEN PITS'!C100,'IP PITSS'!$B$10:$M$91,12),0)+VLOOKUP("Comision",'IP PITSS'!$I$97:$J$108,2)/COUNT($F$9:$F$111)+IFERROR(VLOOKUP('RESUMEN PITS'!C100,'IP PITSS'!$B$10:$AD$91,15),0)+IFERROR(VLOOKUP('RESUMEN PITS'!C100,'IP PITSS'!$B$10:$AD$91,21),0)+IFERROR(VLOOKUP('RESUMEN PITS'!C100,'IP PITSS'!$B$10:$AD$91,22),0)+IFERROR(VLOOKUP('RESUMEN PITS'!C100,'IP PITSS'!$B$10:$AD$91,23),0)+IFERROR(VLOOKUP('RESUMEN PITS'!C100,'IP PITSS'!$B$10:$AD$91,24),0)+IFERROR(VLOOKUP('RESUMEN PITS'!C100,'IP PITSS'!$B$10:$AD$91,26),0)+IFERROR(VLOOKUP('RESUMEN PITS'!C100,'IP PITSS'!$B$10:$AD$91,28),0)+IFERROR(VLOOKUP('RESUMEN PITS'!C100,'IP PITSS'!$B$10:$AD$91,29),0)+IFERROR(VLOOKUP('RESUMEN PITS'!C100,'IP PITSS'!$B$10:$AD$91,9),0)*2% -> 5065.9536 | V100: =+M100-U100 -> -1915.9536
A101: SEI0550 | B101: IP INNOVACION | C101: Lopez Blanco Luis Eduardo | D101: =VLOOKUP(C101,'IP PITSS'!$B$10:$U$91,20,0) -> 2975.4 | F101: =VLOOKUP(C101,'SIND PITS'!$C$3:$H$104,2,0) -> 174.6 | G101: =VLOOKUP(C101,'SIND PITS'!$C$3:$E$104,3,0) -> 0 | H101: =VLOOKUP(C101,'SIND PITS'!$C$3:$F$104,4,0) -> 0 | I101: =VLOOKUP(C101,'SIND PITS'!$C$3:$G$104,5,0) -> 0 | K101: =SUM(D101:I101) -> 3150 | L101: 6300 | M101: =+L101/2 -> 3150 | O101: =VLOOKUP(C101,'IP PITSS'!$B$10:$I$91,8,0) -> 0 | P101: =+G101+H101+I101 -> 0 | Q101: =VLOOKUP(C101,'IP PITSS'!$B$10:$K$91,10,0)+VLOOKUP('RESUMEN PITS'!C101,'IP PITSS'!$B$10:$L$91,11,0)+VLOOKUP('RESUMEN PITS'!C101,'IP PITSS'!$B$10:$M$91,12,0) -> 0 | R101: =VLOOKUP(C101,'IP PITSS'!$B$10:$Q$91,16,0) -> 0 | S101: =VLOOKUP(C101,'IP PITSS'!$B$10:$R$91,17,0) -> 0 | U101: =+K101-O101-P101+Q101+R101+S101+IFERROR(VLOOKUP('RESUMEN PITS'!C101,'IP PITSS'!$B$10:$M$91,10),0)+IFERROR(VLOOKUP('RESUMEN PITS'!C101,'IP PITSS'!$B$10:$M$91,11),0)+IFERROR(VLOOKUP('RESUMEN PITS'!C101,'IP PITSS'!$B$10:$M$91,12),0)+VLOOKUP("Comision",'IP PITSS'!$I$97:$J$108,2)/COUNT($F$9:$F$111)+IFERROR(VLOOKUP('RESUMEN PITS'!C101,'IP PITSS'!$B$10:$AD$91,15),0)+IFERROR(VLOOKUP('RESUMEN PITS'!C101,'IP PITSS'!$B$10:$AD$91,21),0)+IFERROR(VLOOKUP('RESUMEN PITS'!C101,'IP PITSS'!$B$10:$AD$91,22),0)+IFERROR(VLOOKUP('RESUMEN PITS'!C101,'IP PITSS'!$B$10:$AD$91,23),0)+IFERROR(VLOOKUP('RESUMEN PITS'!C101,'IP PITSS'!$B$10:$AD$91,24),0)+IFERROR(VLOOKUP('RESUMEN PITS'!C101,'IP PITSS'!$B$10:$AD$91,26),0)+IFERROR(VLOOKUP('RESUMEN PITS'!C101,'IP PITSS'!$B$10:$AD$91,28),0)+IFERROR(VLOOKUP('RESUMEN PITS'!C101,'IP PITSS'!$B$10:$AD$91,29),0)+IFERROR(VLOOKUP('RESUMEN PITS'!C101,'IP PITSS'!$B$10:$AD$91,9),0)*2% -> 5065.9536 | V101: =+M101-U101 -> -1915.9536
A102: SEI0551 | B102: IP INNOVACION | C102: Vallarta Fonseca Maria Esmeralda | D102: =VLOOKUP(C102,'IP PITSS'!$B$10:$U$91,20,0) -> 2865.8 | F102: =VLOOKUP(C102,'SIND PITS'!$C$3:$H$104,2,0) -> 134.2 | G102: =VLOOKUP(C102,'SIND PITS'!$C$3:$E$104,3,0) -> 390 | H102: =VLOOKUP(C102,'SIND PITS'!$C$3:$F$104,4,0) -> 0 | I102: =VLOOKUP(C102,'SIND PITS'!$C$3:$G$104,5,0) -> 0 | K102: =SUM(D102:I102) -> 3390 | L102: 6000 | M102: =+L102/2 -> 3000 | O102: =VLOOKUP(C102,'IP PITSS'!$B$10:$I$91,8,0) -> 0 | P102: =+G102+H102+I102 -> 390 | Q102: =VLOOKUP(C102,'IP PITSS'!$B$10:$K$91,10,0)+VLOOKUP('RESUMEN PITS'!C102,'IP PITSS'!$B$10:$L$91,11,0)+VLOOKUP('RESUMEN PITS'!C102,'IP PITSS'!$B$10:$M$91,12,0) -> 0 | R102: =VLOOKUP(C102,'IP PITSS'!$B$10:$Q$91,16,0) -> 0 | S102: =VLOOKUP(C102,'IP PITSS'!$B$10:$R$91,17,0) -> 0 | U102: =+K102-O102-P102+Q102+R102+S102+IFERROR(VLOOKUP('RESUMEN PITS'!C102,'IP PITSS'!$B$10:$M$91,10),0)+IFERROR(VLOOKUP('RESUMEN PITS'!C102,'IP PITSS'!$B$10:$M$91,11),0)+IFERROR(VLOOKUP('RESUMEN PITS'!C102,'IP PITSS'!$B$10:$M$91,12),0)+VLOOKUP("Comision",'IP PITSS'!$I$97:$J$108,2)/COUNT($F$9:$F$111)+IFERROR(VLOOKUP('RESUMEN PITS'!C102,'IP PITSS'!$B$10:$AD$91,15),0)+IFERROR(VLOOKUP('RESUMEN PITS'!C102,'IP PITSS'!$B$10:$AD$91,21),0)+IFERROR(VLOOKUP('RESUMEN PITS'!C102,'IP PITSS'!$B$10:$AD$91,22),0)+IFERROR(VLOOKUP('RESUMEN PITS'!C102,'IP PITSS'!$B$10:$AD$91,23),0)+IFERROR(VLOOKUP('RESUMEN PITS'!C102,'IP PITSS'!$B$10:$AD$91,24),0)+IFERROR(VLOOKUP('RESUMEN PITS'!C102,'IP PITSS'!$B$10:$AD$91,26),0)+IFERROR(VLOOKUP('RESUMEN PITS'!C102,'IP PITSS'!$B$10:$AD$91,28),0)+IFERROR(VLOOKUP('RESUMEN PITS'!C102,'IP PITSS'!$B$10:$AD$91,29),0)+IFERROR(VLOOKUP('RESUMEN PITS'!C102,'IP PITSS'!$B$10:$AD$91,9),0)*2% -> 4313.9226 | V102: =+M102-U102 -> -1313.9226
C103: TOTAL GENERAL | D103: =SUBTOTAL(9,D3:D102) -> 306740.8 | E103: =SUBTOTAL(9,E3:E102) -> 0 | F103: =SUBTOTAL(9,F3:F102) -> 148607.2 | G103: =SUBTOTAL(9,G3:G102) -> 36199.2 | H103: =SUBTOTAL(9,H3:H102) -> 2800 | I103: =SUBTOTAL(9,I3:I102) -> 991.31 | J103: =SUBTOTAL(9,J3:J102) -> 0 | K103: =SUBTOTAL(9,K3:K102) -> 495338.51 | ... T103: =SUBTOTAL(9,T3:T102) -> 0 | U103: =+K103-O103-P103+Q103+R103+S103+IFERROR(VLOOKUP('RESUMEN PITS'!C103,'IP PITSS'!$B$10:$M$91,10),0)+IFERROR(VLOOKUP('RESUMEN PITS'!C103,'IP PITSS'!$B$10:$M$91,11),0)+IFERROR(VLOOKUP('RESUMEN PITS'!C103,'IP PITSS'!$B$10:$M$91,12),0)+VLOOKUP("Comision",'IP PITSS'!$I$97:$J$108,2)/COUNT($F$9:$F$111)+IFERROR(VLOOKUP('RESUMEN PITS'!C103,'IP PITSS'!$B$10:$AD$91,15),0)+IFERROR(VLOOKUP('RESUMEN PITS'!C103,'IP PITSS'!$B$10:$AD$91,21),0)+IFERROR(VLOOKUP('RESUMEN PITS'!C103,'IP PITSS'!$B$10:$AD$91,22),0)+IFERROR(VLOOKUP('RESUMEN PITS'!C103,'IP PITSS'!$B$10:$AD$91,23),0)+IFERROR(VLOOKUP('RESUMEN PITS'!C103,'IP PITSS'!$B$10:$AD$91,24),0)+IFERROR(VLOOKUP('RESUMEN PITS'!C103,'IP PITSS'!$B$10:$AD$91,26),0)+IFERROR(VLOOKUP('RESUMEN PITS'!C103,'IP PITSS'!$B$10:$AD$91,28),0)+IFERROR(VLOOKUP('RESUMEN PITS'!C103,'IP PITSS'!$B$10:$AD$91,29),0)+IFERROR(VLOOKUP('RESUMEN PITS'!C103,'IP PITSS'!$B$10:$AD$91,9),0)*2% -> 506364.68 | V103: =SUBTOTAL(9,V3:V102) -> -113000.3 | W103: =SUBTOTAL(9,W3:W99) -> 0 | X103: =SUBTOTAL(9,X3:X99) -> 0 | Y103: =SUM(Y3:Y98) -> 0 | Z103: =SUM(Z3:Z98) -> 0 | AA103: =SUM(AA3:AA97) -> 0 | AB103: =SUM(AB3:AB97) -> 0 | AC103: =SUM(AC3:AC97) -> 0 | AD103: =SUM(AD3:AD97) -> 0 | AE103: =SUM(AE3:AE97) -> 0 | AF103: =SUM(AF3:AF88) -> 0
Q104: =+Q103-'IP PITSS'!K93-'IP PITSS'!L93-'IP PITSS'!M93-'CPD PITSS'!N29-'CPD PITSS'!O29 -> 0 | R104: =+R103-'IP PITSS'!Q93 -> 0 | S104: =+S103-'CPD PITSS'!S29-'IP PITSS'!R93 -> 0
F106: =+F98+D98+H106 -> 3000

Sheet Hoja1
A4: Lopez Blanco Luis Eduardo
E5: Sueldo quincenal
A6: Sueldo mensual | D6: 6300 | E6: 15na. Junio | F6: =D6/2 -> 3150
A7: Bono por actividad y desempeño | D7: 2700 | E7: BONO varia / y en esta quincena no obtuvo bono.
A8: Sueldo total | D8: =D7+D6 -> 9000
E9: PAGADO | F9: =F6 -> 3150

Sheet FACTURACION
D8: TOTAL FACTURACION NOMINA | H8: TOTAL PROV AGUINALDOS
D9: TOTAL CPD | E9: =+'CPD PITSS'!M42 -> 112590.1 | H9: TOTAL CPD | I9: =+'CPD PITSS'!M54 -> 6065.6936
D10: TOTAL IP | E10: =+'IP PITSS'!J106 -> 391278.82 | H10: TOTAL IP | I10: =+'IP PITSS'!J118 -> 19541.351
D11: TOTAL SINDICATO | E11: =+'SIND PITS'!H115 -> 193552.86
E12: =+E9+E10+E11 -> 697421.78 | I12: =+I9+I10+I11 -> 25607.045
D14: PORCENTAJES POR EMPRESA | H14: PORCENTAJES POR EMPRESA
D15: EM 4% | E15: =+E12*4% -> 27896.871 | H15: EM 4% | I15: =+I12*4% -> 1024.2818
D16: CPD 12% | E16: =+E12*12% -> 83690.614 | H16: CPD 12% | I16: =+I12*12% -> 3072.8454
D17: IP 11% | E17: =+E12*11% -> 76716.396 | H17: IP 11% | I17: =+I12*11% -> 2816.7749
D18: ITA 73% | E18: =+E12*73% -> 509117.9 | H18: ITA 73% | I18: =+I12*73% -> 18693.143
E19: =SUM(E15:E18) -> 697421.78 | I19: =SUM(I15:I18) -> 25607.045
F25: 0.73 | G25: 0.11 | H25: 0.12 | I25: 0.04
F26: ITA | G26: IP | H26: CPD | I26: EM
E27: SERVICIO | F27: ='SIND PITS'!K125+'IP PITSS'!L114+'CPD PITSS'!P48 -> 449653.31 | G27: ='SIND PITS'!L125+'IP PITSS'!M114+'CPD PITSS'!Q48 -> 67755.978 | H27: ='SIND PITS'!M125+'IP PITSS'!N114+'CPD PITSS'!R48 -> 73915.612 | I27: ='SIND PITS'!N125+'IP PITSS'!O114+'CPD PITSS'!S48 -> 24638.537
E28: ADMINISTRACION | F28: ='SIND PITS'!K126+'CPD PITSS'!P49 -> 21382.256 | G28: ='SIND PITS'!L126+'CPD PITSS'!Q49 -> 3221.9838 | H28: ='SIND PITS'!M126+'CPD PITSS'!R49 -> 3514.8915 | I28: ='SIND PITS'!N126+'CPD PITSS'!S49 -> 1171.6305
E29: VENTAS | F29: ='SIND PITS'!K127+'IP PITSS'!L116+'CPD PITSS'!P50 -> 30092.26 | G29: ='SIND PITS'!L127+'IP PITSS'!M116+'CPD PITSS'!Q50 -> 4534.4501 | H29: ='SIND PITS'!M127+'IP PITSS'!N116+'CPD PITSS'!R50 -> 4946.6729 | I29: ='SIND PITS'!N127+'IP PITSS'!O116+'CPD PITSS'!S50 -> 1648.891
E30: COMISION | F30: ='SIND PITS'!K128+'IP PITSS'!L117+'CPD PITSS'!P51 -> 7990.0764 | G30: ='SIND PITS'!L128+'IP PITSS'!M117+'CPD PITSS'!Q51 -> 1203.9841 | H30: ='SIND PITS'!M128+'IP PITSS'!N117+'CPD PITSS'!R51 -> 1313.4372 | I30: ='SIND PITS'!N128+'IP PITSS'!O117+'CPD PITSS'!S51 -> 437.8124
E31: SUBTOTAL | F31: =SUM(F27:F30) -> 509117.9 | G31: =SUM(G27:G30) -> 76716.396 | H31: =SUM(H27:H30) -> 83690.614 | I31: =SUM(I27:I30) -> 27896.871 | J31: =SUM(F31:I31) -> 697421.78
E32: IVA | F32: =F31*16% -> 81458.864 | G32: =G31*16% -> 12274.623 | H32: =H31*16% -> 13390.498 | I32: =I31*16% -> 4463.4994 | J32: =SUM(F32:I32) -> 111587.48
E33: TOTAL | F33: =F32+F31 -> 590576.76 | G33: =G32+G31 -> 88991.019 | H33: =H32+H31 -> 97081.112 | I33: =I32+I31 -> 32360.371 | J33: =SUM(F33:I33) -> 809009.26

Sheet ASIMILADOS
A1: CONSULTORIA EN PROYECTOS DINAMICOS
A2: CALCULO DE PAGO POR ASIMILADOS Y/O COMISIONES
D6: QUINCENAL | E6: FACTURACION
A7: Nombre | B7: SUELDO MENSUAL | C7: IMSS | D7: Asimilados | E7: Comision 2% | F7: SUBTOTAL | G7: IVA | H7: TOTAL
A8: PABLO BENAVIDES HERRERA | B8: 70000 | C8: 2865.8 | D8: =(B8/2)-C8 -> 32134.2 | E8: =+D8*0.02 -> 642.684 | F8: =+D8+E8 -> 32776.884 | G8: =F8*0.16 -> 5244.3014 | H8: =+F8+G8 -> 38021.185 | I8: SE FACTURA A PITSS
A10: TOTALES | B10: =SUM(B8:B8) -> 70000 | C10: =SUM(C8:C8) -> 2865.8 | D10: =SUM(D8:D8) -> 32134.2 | E10: =SUM(E8:E8) -> 642.684 | F10: =SUM(F8:F8) -> 32776.884 | G10: =SUM(G8:G8) -> 5244.3014 | H10: =SUM(H8:H8) -> 38021.185
