Workbook

Sheet FACTURACION SINDICATO
B2: codigo | C2: empres | D2: nombre | E2: PAGO POR SINDICATO | F2: comision y bono | G2: prima vacaciones | H2: TOTAL | I2: CC
B3: SEI0097 | C3: SEITON - (CONSULTORIA II) | D3: Arreola Jimenez Jose Nieves | E3: 1558.05 | F3: 2975 | G3: 0 | H3: 4533.05 | I3: AA
B4: SEI0118 | C4: SEITON - (CONSULTORIA II) | D4: Arroyo Ramirez Hector Hugo | E4: 2103.54 | G4: 234 | H4: 2337.54 | I4: AA
B5: SEI0108 | C5: SEITON - (CONSULTORIA II) | D5: Caballero Diaz Francisco Javier | E5: 1558.01 | G5: 0 | H5: 1558.01 | I5: AA
B6: SEI0425 | C6: SEITON - (CONSULTORIA II) | D6: Carbajal Cabuto Jose Luis | E6: 1608.07 | G6: 0 | H6: 1608.07 | I6: AA
B7: SEI0116 | C7: SEITON - (CONSULTORIA II) | D7: Casillas Cardona Cesar Alejandro | E7: 1891.22 | G7: 0 | H7: 1891.22 | I7: AA
B8: SEI0401 | C8: SEITON - (CONSULTORIA II) | D8: De La Torre Zambara Francisco Ernesto | E8: 78.08 | G8: 0 | H8: 78.08 | I8: AA
B9: SEI0119 | C9: SEITON - (CONSULTORIA II) | D9: Dominguez Lopez Maria De Jesus | E9: 0 | G9: 0 | H9: 0 | I9: AA
B10: SEI0099 | C10: SEITON - (CONSULTORIA II) | D10: Garcia Villicaña Ricardo Pascual | E10: 2600.8 | F10: 600 | G10: 0 | H10: 3200.8 | I10: AA
B11: SEI0009 | C11: SEITON - (CONSULTORIA II) | D11: Gutierrez Gutierrez Luis Arturo | E11: 1474.6 | G11: 0 | H11: 1474.6 | I11: AA
B12: SEI0127 | C12: SEITON - (CONSULTORIA II) | D12: Hernandez Ochoa Eduardo | E12: 2601 | G12: 0 | H12: 2601 | I12: AA
B13: SEI0088 | C13: SEITON - (CONSULTORIA II) | D13: Morgado Fernandez Martin | E13: 2601 | F13: 1125 | G13: 0 | H13: 3726 | I13: AA
B14: SEI0173 | C14: SEITON - (CONSULTORIA II) | D14: Nieto Ortiz Jose Luis | E14: 1483.15 | F14: 1232 | G14: 0 | H14: 2715.15 | I14: AA
B15: SEI0026 | C15: SEITON - (CONSULTORIA II) | D15: Patricio Aguilar Jhonattan Cristian | E15: 1588 | G15: 0 | H15: 1588 | I15: AA
B16: SEI0027 | C16: SEITON - (CONSULTORIA II) | D16: Tavares Guzman Jose Enrique | E16: 2378.2 | G16: 0 | H16: 2378.2 | I16: AA
B17: SEI032 | C17: SEITON - (CONSULTORIA II) | D17: Camarena Quiroz Erick Frank | E17: 1588 | F17: 225 | G17: 0 | H17: 1813 | I17: AA
B18: SEI0438 | C18: SEITON - (CONSULTORIA II) | D18: Valdes Arrioja Karla Naborina | E18: 1803.2 | H18: 1803.2 | I18: AA
B19: SEI0482 | C19: SEITON (IP INNOVA II) | D19: Camarillo Canela Reynaldo | E19: 2236.64 | F19: 2150 | G19: 0 | H19: 4386.64 | I19: AA
B20: SEI0485 | C20: SEITON (IP INNOVA II) | D20: Molina Ramirez Gerardo Daniel | E20: 2271.77 | G20: 0 | H20: 2271.77 | I20: AA
B21: SEI0488 | C21: SEITON (IP INNOVA II) | D21: Mireles Casillas Brenda Cristina | E21: 2257 | G21: 0 | H21: 2257 | I21: AA
B22: SEI0489 | C22: SEITON (IP INNOVA II) | D22: Escobedo Olivares Juan Guadalupe | E22: 3723.8 | G22: 0 | H22: 3723.8 | I22: AA
B23: SEI0490 | C23: SEITON (IP INNOVA II) | D23: Castillo Ramirez Hector Ivan | E23: 3753.78 | F23: 1280 | G23: 0 | H23: 5033.78 | I23: AA
B24: SEI0492 | C24: SEITON (IP INNOVA II) | D24: Cadena Ramirez Hugo | E24: 2513.4 | G24: 0 | H24: 2513.4 | I24: AA
B25: SEI0493 | C25: SEITON (IP INNOVA II) | D25: Martinez Morales Tomas | E25: 3397.14 | F25: 1320 | G25: 0 | H25: 4717.14 | I25: AA
B26: SEI0494 | C26: SEITON (IP INNOVA II) | D26: Medellin Colunga Ruben Dario | E26: 4412.14 | F26: 2320 | G26: 0 | H26: 6732.14 | I26: AA
B27: SEI0495 | C27: SEITON (IP INNOVA II) | D27: Torres Perez Carlos Alberto | E27: 1685.3 | F27: 4495 | G27: 0 | H27: 6180.3 | I27: AA
B28: SEI0496 | C28: SEITON (IP INNOVA II) | D28: Velazquez Herrera Nayeli | E28: 3382.26 | F28: 950 | G28: 56.14 | H28: 4388.4 | I28: AA
B29: SEI0497 | C29: SEITON (IP INNOVA II) | D29: Treviño Alvarez Jorge Alberto | E29: 2700.29 | F29: 680 | G29: 0 | H29: 3380.29 | I29: AA
B30: SEI0498 | C30: SEITON (IP INNOVA II) | D30: Tenorio Alvarez Alberto Antonio | E30: 1685.2 | G30: 0 | H30: 1685.2 | I30: AA
B31: SEI0499 | C31: SEITON (IP INNOVA II) | D31: Chavez Dominguez Salvador | E31: 2685.2 | G31: 0 | H31: 2685.2 | I31: AA
B32: SEI0500 | C32: SEITON (IP INNOVA II) | D32: Garcia Gutierrez Jose Juan | E32: 1685.2 | G32: 0 | H32: 1685.2 | I32: AA
B33: SEI0501 | C33: SEITON (IP INNOVA II) | D33: Cruz Herrera Roberto | E33: 1670.2 | G33: 0 | H33: 1670.2 | I33: AA
B34: SEI0502 | C34: SEITON (IP INNOVA II) | D34: Dominguez Escamilla Victor Hugo | E34: 2700.14 | G34: 0 | H34: 2700.14 | I34: AA
B35: SEI0503 | C35: SEITON (IP INNOVA II) | D35: Martinez Rodriguez Paulo Cesar | E35: 2554.8 | G35: 0 | H35: 2554.8 | I35: AA
B36: SEI0504 | C36: SEITON (IP INNOVA II) | D36: Martinez Malo Cesar | E36: 1711.46 | G36: 0 | H36: 1711.46 | I36: AA
B37: SEI0505 | C37: SEITON (IP INNOVA II) | D37: Perez Balboa Cesar | E37: 2211.65 | G37: 0 | H37: 2211.65 | I37: AA
B38: SEI0506 | C38: SEITON (IP INNOVA II) | D38: Mejia Duarte Jose Luis | E38: 2570.57 | G38: 0 | H38: 2570.57 | I38: AA
B39: SEI0507 | C39: SEITON (IP INNOVA II) | D39: Diaz Saldierna Leonel Gonzalo | E39: 2585.53 | G39: 0 | H39: 2585.53 | I39: AA
B40: SEI0508 | C40: SEITON (IP INNOVA II) | D40: Cerro Garcia Elvis | E40: 2570.6 | F40: 2125 | G40: 0 | H40: 4695.6 | I40: AA
B41: SEI0078 | C41: SEITON (IP INNOVA II) | D41: Aguilar Leal Karina Livier | E41: 952.25 | F41: 16065.1 | G41: 10 | H41: 17027.35 | I41: AA
B42: SEI0126 | C42: SEITON (IP INNOVA II) | D42: Alonso Flores Beda | E42: 1102.59 | G42: 0 | H42: 1102.59 | I42: AA
B43: SEI0029 | C43: SEITON (IP INNOVA II) | D43: Arceo Garcia Manuel Federico | E43: 152.5 | G43: 0 | H43: 152.5 | I43: AA
B44: SEI0003 | C44: SEITON (IP INNOVA II) | D44: Arellano Lopez Adriana Isela | E44: 231.8 | G44: 0 | H44: 231.8 | I44: AA
B45: SEI0230 | C45: SEITON (IP INNOVA II) | D45: Bueno Herrera Mariana Guadalupe | E45: 1452.1 | F45: 2269.72 | G45: 0 | H45: 3721.82 | I45: AA
B46: SEI0013 | C46: SEITON (IP INNOVA II) | D46: Castillo Sanchez Miguel Angel | E46: 1549.97 | F46: 960 | G46: 0 | H46: 2509.97 | I46: AA
B47: SEI0031 | C47: SEITON (IP INNOVA II) | D47: Contreras Zetina Victor Hugo | E47: 233.2 | G47: 0 | H47: 233.2 | I47: AA
B48: SEI0015 | C48: SEITON (IP INNOVA II) | D48: Cota Jaramillo Miguel Angel | E48: 151.4 | G48: 0 | H48: 151.4 | I48: AA
B49: SEI0413 | C49: SEITON (IP INNOVA II) | D49: Courtenay Gutierrez Barry Vladimir | E49: 69.74 | F49: 3360 | G49: 0 | H49: 3429.74 | I49: AA
B50: SEI0364 | C50: SEITON (IP INNOVA II) | D50: Dominguez Lopez Mayeli Del Pilar | E50: 1437.13 | G50: 0 | H50: 1437.13 | I50: AA
B51: SEI0018 | C51: SEITON (IP INNOVA II) | D51: Dominguez Mendez Victor Manuel | E51: 550 | G51: 0 | H51: 550 | I51: AA
B52: SEI0037 | C52: SEITON (IP INNOVA II) | D52: Gomez Oliveros Alin | E52: 602.6 | F52: 1843.07 | G52: 0 | H52: 2445.67 | I52: AA
B53: SEI0019 | C53: SEITON (IP INNOVA II) | D53: Gonzalez Rasgado Miguel Isaias | E53: 896.4 | G53: 0 | H53: 896.4 | I53: AA
B54: SEI0081 | C54: SEITON (IP INNOVA II) | D54: Guizar Perez Sergio | E54: 904.8 | G54: 0 | H54: 904.8 | I54: AA
B55: SEI0012 | C55: SEITON (IP INNOVA II) | D55: Hernandez Renteria Javier Fernando | E55: 550 | G55: 0 | H55: 550 | I55: AA
B56: SEI0332 | C56: SEITON (IP INNOVA II) | D56: Lara Campos Maximino | E56: 1475.2 | G56: 0 | H56: 1475.2 | I56: AA
B57: SEI0020 | C57: SEITON (IP INNOVA II) | D57: Mar Marquez Cesar Eduardo | E57: 435.4 | G57: 0 | H57: 435.4 | I57: AA
B58: SEI0376 | C58: SEITON (IP INNOVA II) | D58: Marquez Alcaraz Martin | E58: 977.35 | G58: 0 | H58: 977.35 | I58: AA
B59: SEI0030 | C59: SEITON (IP INNOVA II) | D59: Marquez Altamirano Marco Antonio | E59: 452.2 | F59: 260 | G59: 0 | H59: 712.2 | I59: AA
B60: SEI0014 | C60: SEITON (IP INNOVA II) | D60: Montoya Portillo Carlos Alberto | E60: 450.4 | F60: 1550 | G60: 0 | H60: 2000.4 | I60: AA
B61: SEI0017 | C61: SEITON (IP INNOVA II) | D61: Muñoz Reyes Luis Eduardo | E61: 465.38 | G61: 0 | H61: 465.38 | I61: AA
B62: SEI0022 | C62: SEITON (IP INNOVA II) | D62: Najera Lopez Raul | E62: 656.13 | F62: 1120 | G62: 0 | H62: 1776.13 | I62: AA
B63: SEI0016 | C63: SEITON (IP INNOVA II) | D63: Negrete Bejar Aide Sarai | E63: 14.8 | G63: 0 | H63: 14.8 | I63: AA
B64: SEI0109 | C64: SEITON (IP INNOVA II) | D64: Negrete Renteria Jose Luis | E64: 1169.97 | G64: 0 | H64: 1169.97 | I64: AA
B65: SEI0023 | C65: SEITON (IP INNOVA II) | D65: Puente Murguia Luis Felipe | E65: 240.2 | G65: 0 | H65: 240.2 | I65: AA
B66: SEI0100 | C66: SEITON (IP INNOVA II) | D66: Quinto Valle Martin | E66: 641.2 | F66: 350 | G66: 0 | H66: 991.2 | I66: AA
B67: SEI0146 | C67: SEITON (IP INNOVA II) | D67: Ramirez Vera Maria Del Carmen | E67: 1467.19 | G67: 0 | H67: 1467.19 | I67: AA
B68: SEI0345 | C68: SEITON (IP INNOVA II) | D68: Rodriguez Diaz Cesar Salvador | E68: 992.07 | G68: 0 | H68: 992.07 | I68: AA
B69: SEI0412 | C69: SEITON (IP INNOVA II) | D69: Rojo Avelar Adrian | E69: 917.5 | G69: 0 | H69: 917.5 | I69: AA
B70: SEI0133 | C70: SEITON (IP INNOVA II) | D70: Romero Mayoral Lorenzo | E70: 2202.21 | G70: 0 | H70: 2202.21 | I70: AA
B71: SEI0010 | C71: SEITON (IP INNOVA II) | D71: Torres Ricardez Alfredo | E71: 450.4 | G71: 0 | H71: 450.4 | I71: AA
B72: SEI0021 | C72: SEITON (IP INNOVA II) | D72: Velez Rodriguez Jaime | E72: 1167.55 | G72: 20 | H72: 1187.55 | I72: AA
B73: SEI0421 | C73: SEITON (IP INNOVA II) | D73: Marin Avila Hector | E73: 734.1 | F73: 1325 | G73: 5.5 | H73: 2064.6 | I73: AA
B74: SEI0422 | C74: SEITON (IP INNOVA II) | D74: Mulgado Guzman Ernesto | E74: 755.07 | F74: 1275 | G74: 0 | H74: 2030.07 | I74: AA
B75: SEI0424 | C75: SEITON (IP INNOVA II) | D75: Palacios Ramos Jesus | E75: 452.2 | F75: 1375 | G75: 0 | H75: 1827.2 | I75: AA
B76: SEI0429 | C76: SEITON (IP INNOVA II) | D76: Torres Gomez Valeria | E76: 22.6 | G76: 0 | H76: 22.6 | I76: AA
B77: SEI0431 | C77: SEITON (IP INNOVA II) | D77: Alcaraz Conde Zabdi Guadalupe | E77: 152.5 | G77: 0 | H77: 152.5 | I77: AA
B78: SEI0428 | C78: SEITON (IP INNOVA II) | D78: Martinez Hernandez J. Antonio | E78: 452.2 | F78: 2900 | G78: 0 | H78: 3352.2 | I78: AA
B79: SEI0433 | C79: SEITON (IP INNOVA II) | D79: Garza Herrera Yareci Anel | E79: 452.4 | G79: 0 | H79: 452.4 | I79: AA
B80: SEI0438 | C80: SEITON (IP INNOVA II) | D80: Lopez Terron Roberto Porfirio | E80: 1139.4 | G80: 0 | H80: 1139.4 | I80: AA
B81: SEI0441 | C81: SEITON (IP INNOVA II) | D81: Ramirez Romero Jose Luis | E81: 1139.4 | G81: 0 | H81: 1139.4 | I81: AA
B82: SEI0442 | C82: SEITON (IP INNOVA II) | D82: Chavez Pedraza Samuel | E82: 1139.4 | G82: 0 | H82: 1139.4 | I82: AA
B83: SEI0443 | C83: SEITON (IP INNOVA II) | D83: Castillo Nungaray Nestor Roman | E83: 152.4 | G83: 0 | H83: 152.4 | I83: AA
B84: SEI0444 | C84: SEITON (IP INNOVA II) | D84: Marquez Hernandez Rogelio | E84: 452.2 | F84: 3050 | G84: 0 | H84: 3502.2 | I84: AA
B85: SEI0448 | C85: SEITON (IP INNOVA II) | D85: Picazo Gutierrez Jose Alfonso | E85: 70.6 | G85: 0 | H85: 70.6 | I85: AA
B86: SEI0449 | C86: SEITON (IP INNOVA II) | D86: Flores Cerrillos Jorge Humberto | E86: 452.2 | G86: 0 | H86: 452.2 | I86: AA
B87: SEI0451 | C87: SEITON (IP INNOVA II) | D87: Hurtado Avalos J.jesus | E87: 137.6 | G87: 0 | H87: 137.6 | I87: AA
B88: SEI0452 | C88: SEITON (IP INNOVA II) | D88: Leija Arevalo Guadalupe | E88: 248.205 | G88: 0 | H88: 248.205 | I88: AA
B89: SEI0453 | C89: SEITON (IP INNOVA II) | D89: Mora Cavazos Roberto Manuel | E89: 452.2 | G89: 0 | H89: 452.2 | I89: AA
B90: SEI0454 | C90: SEITON (IP INNOVA II) | D90: Martinez Rivera Maria Teresa | E90: 442.8 | G90: 0 | H90: 442.8 | I90: AA
B91: SEI0455 | C91: SEITON (IP INNOVA II) | D91: Perez Garcia Andres Alvaro | E91: 452.2 | F91: 860 | G91: 0 | H91: 1312.2 | I91: AA
B92: SEI0456 | C92: SEITON (IP INNOVA II) | D92: Chavira Garcia David Fernando | E92: 656.2 | G92: 0 | H92: 656.2 | I92: AA
B93: SEI0457 | C93: SEITON (IP INNOVA II) | D93: Guerrero Lara Cesar Adrian | E93: 437.2 | G93: 0 | H93: 437.2 | I93: AA
B94: SEI0458 | C94: SEITON (IP INNOVA II) | D94: Martinez Zamora Gerardo Mario | E94: 609.225 | F94: 1550 | G94: 0 | H94: 2159.225 | I94: AA
B95: SEI0460 | C95: SEITON (IP INNOVA II) | D95: Castellon Ramos Rene | E95: 422.955 | F95: 1875 | G95: 0 | H95: 2297.955 | I95: AA
B96: SEI0461 | C96: SEITON (IP INNOVA II) | D96: Flores Franco Marco | E96: 499.655 | F96: 125 | G96: 0 | H96: 624.655 | I96: AA
B97: SEI0462 | C97: SEITON (IP INNOVA II) | D97: Chavez Saucedo Jorge Arturo | E97: 450.6 | H97: 450.6 | I97: AA
B98: SEI0463 | C98: SEITON (IP INNOVA II) | D98: Hernandez Rangel Daniel | E98: 436.95 | F98: 4510 | G98: 0 | H98: 4946.95 | I98: AA
B99: SEI0464 | C99: SEITON (IP INNOVA II) | D99: Hueramo Hueramo Jesus Daniel | E99: 514.685 | G99: 0 | H99: 514.685 | I99: AA
B100: SEI0465 | C100: SEITON (IP INNOVA II) | D100: Sandoval Garcia Luis | E100: 437.2 | G100: 0 | H100: 437.2 | I100: AA
B101: SEI0467 | C101: SEITON (IP INNOVA II) | D101: Vaca Valdez Guillermo | E101: 452.2 | G101: 0 | H101: 452.2 | I101: AA
...

Sheet CPD
B2: CONSULTORIA EN PROYECTOS DINAMICOS S DE RL DE CV
B3: Lista de Raya (forma tabular)
B4: Reg Pat IMSS: Z2940859106
B5: RFC: CPD -150911-FA3
A8: Código | B8: Empleado | C8: Dias Laborados | D8: Dias Vacaciones | E8: Salario Diario | F8: Salario Diario Integrado | G8: Sueldo | H8: Vacaciones a tiempo | I8: Prima de vacaciones a tiempo | J8: Ayuda de Transporte | K8: Ayuda Alimentaria | L8: Ayuda de Renta | M8: *TOTAL* *PERCEPCIONES* | N8: I.S.R. (sp) | O8: Subsidio al Empleo (sp) | P8: I.M.S.S. | Q8: Préstamo Infonavit | R8: Préstamo Infonavit (vsm) | S8: Préstamo Infonavit (cf) | T8: Seguro de vivienda Infonavit | U8: Prestamo Empresa | V8: Deduccion general | W8: Ajuste al neto | X8: *TOTAL* *DEDUCCIONES* | Y8: *NETO* | Z8: Ret. Inv. Y Vida | AA8: Ret. Cesantia | AB8: Ret. Enf. y Mat. obrero | AC8: Subs al Empleo acreditado | AD8: I.S.R. antes de Subs al Empleo | AE8: isr 2 | AF8: Invalidez y Vida | AG8: Cesantia y Vejez | AH8: Enf. y Mat. Patron | AI8: Total Percepciones | AJ8: 2% Fondo retiro SAR (8) | AK8: 2% Impuesto estatal | AL8: Riesgo de trabajo (9) | AM8: I.M.S.S. empresa | AN8: Infonavit empresa | AO8: Guarderia I.M.S.S. (7) | AP8: Proporcion Aguinaldo | AQ8: FACTURACION
A9: SEI0009 | B9: Gutierrez Gutierrez Luis Arturo | C9: 15 | D9: 0 | E9: 141.67 | F9: 150.25 | G9: 2125.05 | H9: 0 | I9: 0 | J9: 212.51 | K9: 212.51 | L9: 212.51 | M9: 2762.58 | N9: 0 | O9: -65.5 | P9: 53.52 | Q9: 0 | R9: 0 | V9: 0 | W9: 0.16 | X9: -11.82 | Y9: 2774.4 | Z9: 14.09 | AA9: 25.35 | AB9: 14.08 | AC9: -188.71 | AD9: 123.22 | AF9: 39.44 | AG9: 70.99 | AH9: 297.98 | AI9: 2762.58 | AJ9: 240.44 | AK9: 55.25 | AL9: 12.91 | AM9: 408.41 | AN9: 112.69 | AO9: 217.9 | AP9: 151.27396 | AQ9: PITSS
A10: SEI0010 | B10: Compean Tobias Braulio Gerardo | C10: 15 | D10: 0 | E10: 300 | F10: 313.56 | G10: 4500 | H10: 0 | I10: 0 | J10: 450 | K10: 450 | L10: 450 | M10: 5850 | N10: 380.67 | O10: 0 | P10: 115.32 | Q10: 0 | R10: 1320.68 | V10: 0 | W10: -0.07 | X10: 1816.6 | Y10: 4033.4 | Z10: 29.4 | AA10: 52.91 | AB10: 33.01 | AC10: 0 | AD10: 380.67 | AF10: 82.31 | AG10: 148.16 | AH10: 350.77 | AI10: 5850 | AJ10: 289.43 | AK10: 117 | AL10: 26.95 | AM10: 581.24 | AN10: 235.17 | AO10: 242.39 | AP10: 320.33731 | AQ10: SEITON
A11: SEI0026 | B11: Patricio Aguilar Jhonattan Cristian | C11: 15 | D11: 0 | E11: 150 | F11: 159.07 | G11: 2250 | H11: 0 | I11: 0 | J11: 225 | K11: 225 | L11: 225 | M11: 2925 | N11: 0 | O11: -43.57 | P11: 56.67 | Q11: 0 | R11: 0 | V11: 0 | W11: 0.1 | X11: 13.2 | Y11: 2911.8 | Z11: 14.91 | AA11: 26.84 | AB11: 14.92 | AC11: -174.78 | AD11: 131.21 | AF11: 41.76 | AG11: 75.16 | AH11: 300.29 | AI11: 2925 | AJ11: 243.08 | AK11: 58.5 | AL11: 13.67 | AM11: 417.21 | AN11: 119.31 | AO11: 219.22 | AP11: 160.16866 | AQ11: PITSS
A12: SEI0039 | B12: Benavides Herrera Pablo | C12: 15 | D12: 0 | E12: 666.67 | F12: 696.81 | G12: 10000.05 | H12: 0 | I12: 0 | J12: 1000 | K12: 1000 | L12: 1000 | M12: 13000.05 | N12: 1497.79 | O12: 0 | P12: 274.85 | Q12: 0 | R12: 0 | V12: 0 | W12: 0.01 | X12: 1772.65 | Y12: 11227.4 | Z12: 65.33 | AA12: 117.59 | AB12: 91.93 | AC12: 0 | AD12: 1497.79 | AF12: 182.91 | AG12: 329.24 | AH12: 514.6 | AI12: 13000.05 | AJ12: 404.4 | AK12: 260 | AL12: 59.88 | AM12: 1026.75 | AN12: 522.61 | AO12: 299.88 | AP12: 711.86425 | AQ12: PITSS
A13: SEI0040 | B13: Mora Ramirez Acal Aldo Isidro | C13: 15 | D13: 0 | E13: 216.67 | F13: 229.79 | G13: 3250.05 | H13: 0 | I13: 0 | J13: 325.01 | K13: 325.01 | L13: 325.01 | M13: 4225.08 | N13: 107.17 | O13: 0 | P13: 81.87 | Q13: 0 | R13: 0 | V13: 0 | W13: 0.04 | X13: 189.08 | Y13: 4036 | Z13: 21.54 | AA13: 38.78 | AB13: 21.55 | AC13: -125.1 | AD13: 232.27 | AF13: 60.32 | AG13: 108.58 | AH13: 318.86 | AI13: 4225.08 | AJ13: 264.3 | AK13: 84.5 | AL13: 19.75 | AM13: 487.76 | AN13: 172.34 | AO13: 229.83 | AP13: 231.35828 | AQ13: PITSS
A14: SEI0041 | B14: Vazquez Perez Miguel Angel | C14: 15 | D14: 0 | E14: 283.33 | F14: 300.49 | G14: 4249.95 | H14: 0 | I14: 0 | J14: 425 | K14: 425 | L14: 425 | M14: 5524.95 | N14: 341.06 | O14: 0 | P14: 109.87 | Q14: 0 | R14: 0 | V14: 0 | W14: 0.02 | X14: 450.95 | Y14: 5074 | Z14: 28.17 | AA14: 50.71 | AB14: 30.99 | AC14: 0 | AD14: 341.06 | AF14: 78.88 | AG14: 141.98 | AH14: 345.18 | AI14: 5524.95 | AJ14: 285.51 | AK14: 110.5 | AL14: 25.82 | AM14: 566.04 | AN14: 225.37 | AO14: 240.43 | AP14: 302.53724 | AQ14: PITSS
A15: SEI0088 | B15: Morgado Fernandez Martin | C15: 15 | D15: 0 | E15: 273.33 | F15: 289.87 | G15: 4099.95 | H15: 0 | I15: 0 | J15: 410 | K15: 410 | L15: 410 | M15: 5329.95 | N15: 324.74 | O15: 0 | P15: 105.46 | Q15: 0 | R15: 0 | V15: 0 | W15: 0.15 | X15: 430.35 | Y15: 4899.6 | Z15: 27.18 | AA15: 48.92 | AB15: 29.36 | AC15: 0 | AD15: 324.74 | AF15: 76.09 | AG15: 136.96 | AH15: 340.64 | AI15: 5329.95 | AJ15: 282.32 | AK15: 106.6 | AL15: 24.91 | AM15: 553.69 | AN15: 217.4 | AO15: 238.84 | AP15: 291.85933 | AQ15: PITSS
A16: SEI0097 | B16: Arreola Jimenez Jose Nieves | C16: 15 | D16: 0 | E16: 185.83 | F16: 197.07 | G16: 2787.45 | H16: 0 | I16: 0 | J16: 278.75 | K16: 278.75 | L16: 278.75 | M16: 3623.7 | N16: 36.57 | O16: 0 | P16: 70.22 | Q16: 0 | R16: 1559.39 | V16: 224.7 | W16: -0.18 | X16: 1890.7 | Y16: 1733 | Z16: 18.48 | AA16: 33.26 | AB16: 18.48 | AC16: -145.38 | AD16: 181.94 | AF16: 51.73 | AG16: 93.12 | AH16: 310.27 | AI16: 3623.7 | AJ16: 254.48 | AK16: 72.47 | AL16: 16.94 | AM16: 455.12 | AN16: 147.8 | AO16: 224.92 | AP16: 198.42761 | AQ16: PITSS
A17: SEI0099 | B17: Garcia Villicaña Ricardo Pascual | C17: 14 | D17: 1 | E17: 273.33 | F17: 289.87 | G17: 3826.62 | H17: 273.33 | I17: 82 | J17: 410 | K17: 410 | L17: 410 | M17: 5411.95 | N17: 324.74 | O17: 0 | P17: 105.46 | Q17: 0 | R17: 0 | V17: 0 | W17: 0.15 | X17: 430.35 | Y17: 4981.6 | Z17: 27.18 | AA17: 48.92 | AB17: 29.36 | AC17: 0 | AD17: 324.74 | AF17: 76.09 | AG17: 136.96 | AH17: 340.64 | AI17: 5411.95 | AJ17: 282.32 | AK17: 108.24 | AL17: 24.91 | AM17: 553.69 | AN17: 217.4 | AO17: 238.84 | AP17: 291.85933 | AQ17: PITSS
A18: SEI0108 | B18: Caballero Diaz Francisco Javier | C18: 15 | D18: 0 | E18: 185.83 | F18: 197.07 | G18: 2787.45 | H18: 0 | I18: 0 | J18: 278.75 | K18: 278.75 | L18: 278.75 | M18: 3623.7 | N18: 36.57 | O18: 0 | P18: 70.22 | Q18: 0 | R18: 1809.82 | V18: 0 | W18: 0.09 | X18: 1916.7 | Y18: 1707 | Z18: 18.48 | AA18: 33.26 | AB18: 18.48 | AC18: -145.38 | AD18: 181.94 | AF18: 51.73 | AG18: 93.12 | AH18: 310.27 | AI18: 3623.7 | AJ18: 254.48 | AK18: 72.47 | AL18: 16.94 | AM18: 455.12 | AN18: 147.8 | AO18: 224.92 | AP18: 198.42761 | AQ18: PITSS
A19: SEI0116 | B19: Casillas Cardona Cesar Alejandro | C19: 15 | D19: 0 | E19: 220.83 | F19: 234.19 | G19: 3312.45 | H19: 0 | I19: 0 | J19: 331.25 | K19: 331.25 | L19: 331.25 | M19: 4306.2 | N19: 113.96 | O19: 0 | P19: 83.43 | Q19: 0 | R19: 1045.17 | V19: 0 | W19: -0.16 | X19: 1242.4 | Y19: 3063.8 | Z19: 21.96 | AA19: 39.52 | AB19: 21.95 | AC19: -125.1 | AD19: 239.06 | AF19: 61.47 | AG19: 110.65 | AH19: 320.01 | AI19: 4306.2 | AJ19: 265.62 | AK19: 86.12 | AL19: 20.13 | AM19: 492.13 | AN19: 175.64 | AO19: 230.49 | AP19: 235.8003 | AQ19: PITSS
A20: SEI0117 | B20: Mariscal Romero Luis Adrian | C20: 15 | D20: 0 | E20: 264.58 | F20: 276.54 | G20: 3968.7 | H20: 0 | I20: 0 | J20: 396.87 | K20: 396.87 | L20: 396.87 | M20: 5159.31 | N20: 310.46 | O20: 0 | P20: 99.91 | Q20: 0 | R20: 1658.56 | V20: 396 | W20: -0.02 | X20: 2464.91 | Y20: 2694.4 | Z20: 25.93 | AA20: 46.67 | AB20: 27.31 | AC20: 0 | AD20: 310.46 | AF20: 72.59 | AG20: 130.66 | AH20: 334.94 | AI20: 5159.31 | AJ20: 278.32 | AK20: 103.19 | AL20: 23.76 | AM20: 538.19 | AN20: 207.4 | AO20: 236.84 | AP20: 282.51615 | AQ20: PITSS
... A37: SEI0448 | B37: Rodriguez Chavez Oswaldo Emmanuel | C37: 15 | D37: 0 | E37: 233.33 | F37: 247.46 | G37: 3499.95 | H37: 0 | I37: 0 | J37: 350 | K37: 350 | L37: 350 | M37: 4549.95 | N37: 134.36 | O37: 0 | P37: 88.16 | Q37: 0 | R37: 0 | V37: 0 | W37: 0.03 | X37: 222.55 | Y37: 4327.4 | Z37: 23.2 | AA37: 41.76 | AB37: 23.2 | AC37: -125.1 | AD37: 259.46 | AF37: 64.96 | AG37: 116.92 | AH37: 323.5 | AI37: 4549.95 | AJ37: 269.6 | AK37: 91 | AL37: 21.27 | AM37: 505.38 | AN37: 185.6 | AO37: 232.48 | AP37: 249.14768 | AQ37: SEITON
A38: Total Depto | C38: ----------------------- | D38: ----------------------- | E38: ----------------------- | F38: ----------------------- | G38: ----------------------- | H38: ----------------------- | I38: ----------------------- | J38: ----------------------- | K38: ----------------------- | L38: ----------------------- | M38: ----------------------- | N38: ----------------------- | O38: ----------------------- | P38: ----------------------- | Q38: ----------------------- | R38: ----------------------- | S38: ----------------------- | T38: ----------------------- | U38: ----------------------- | V38: ----------------------- | W38: ----------------------- | X38: ----------------------- | Y38: ----------------------- | Z38: ----------------------- | AA38: ----------------------- | AB38: ----------------------- | AC38: ----------------------- | AD38: ----------------------- | AF38: ----------------------- | AG38: ----------------------- | AH38: ----------------------- | AI38: ----------------------- | AJ38: ----------------------- | AK38: ----------------------- | AL38: ----------------------- | AM38: ----------------------- | AN38: ----------------------- | AO38: -----------------------
A39: =SUM(A9:A38) -> 0 | B39: =SUM(B9:B38) -> 0 | C39: =SUM(C9:C38) -> 432 | D39: =SUM(D9:D38) -> 3 | E39: =SUM(E9:E38) -> 7674.55 | F39: =SUM(F9:F38) -> 8118.17 | G39: =SUM(G9:G38) -> 114511.58 | H39: =SUM(H9:H38) -> 606.67 | ... AP39: =SUM(AP9:AP38) -> 8194.8157
A41: 30 | B41: Nomina
A42: 0 | B42: Altas
A43: 1 | B43: Bajas
A44: =+A41+A42-A43 -> 29 | B44: Total Nomina | L44: Devengado Salario | M44: =+Y39 -> 121000.4
L45: RETORNOS | M45: =+V39 -> 2029.52
L46: Infonavit | M46: =+S39+R39+Q39+T39 -> 15253.11
L47: Prestamo Prospera | M47: =+U39 -> 0
L48: Subtotal 1 | M48: =SUM(M44:M47) -> 138283.03
L49: Comision | M49: =+M48*2% -> 2765.6606
L50: Subtotal 2 | M50: =+M48+M49 -> 141048.69
L51: Costo Patronal Imss | M51: =+P39+AF39+AG39+AH39+AJ39+AL39+AN39+AO39 -> 40641.15
L52: 2% Sobre Nomina | M52: =+M39*2% -> 2990.4412
L53: Importe de Factura | M53: =+M50+M51+M52 -> 184680.28
L54: IVA | M54: =+M53*16% -> 29548.845
L55: TOTAL | M55: =+M53+M54 -> 214229.13

Sheet FAC-CPD
C2: CONSULTORIA EN PROYECTOS DINAMICOS S DE RL DE CV
C3: Lista de Raya (forma tabular)
C4: Reg Pat IMSS: Z2940859106
C5: RFC: CPD -150911-FA3
B8: Código | C8: Empleado | D8: Dias Laborados | E8: Dias Vacaciones | F8: Salario Diario | G8: Salario Diario Integrado | H8: Sueldo | I8: Vacaciones a tiempo | J8: Prima de vacaciones a tiempo | K8: Ayuda de Transporte | L8: Ayuda Alimentaria | M8: Ayuda de Renta | N8: *TOTAL* *PERCEPCIONES* | O8: I.S.R. (sp) | P8: Subsidio al Empleo (sp) | Q8: I.M.S.S. | R8: Préstamo Infonavit | S8: Préstamo Infonavit (vsm) | T8: Préstamo Infonavit (cf) | U8: Seguro de vivienda Infonavit | V8: Prestamo Empresa | W8: Deduccion general | X8: Ajuste al neto | Y8: *TOTAL* *DEDUCCIONES* | Z8: *NETO* | AA8: Ret. Inv. Y Vida | AB8: Ret. Cesantia | AC8: Ret. Enf. y Mat. obrero | AD8: Subs al Empleo acreditado | AE8: I.S.R. antes de Subs al Empleo | AF8: isr 2 | AG8: Invalidez y Vida | AH8: Cesantia y Vejez | AI8: Enf. y Mat. Patron | AJ8: Total Percepciones | AK8: 2% Fondo retiro SAR (8) | AL8: 2% Impuesto estatal | AM8: Riesgo de trabajo (9) | AN8: I.M.S.S. empresa | AO8: Infonavit empresa | AP8: Guarderia I.M.S.S. (7) | AQ8: Proporcion Aguinaldo | AR8: FACTURACION
B9: SEI0009 | C9: Gutierrez Gutierrez Luis Arturo | D9: 15 | E9: 0 | F9: 141.67 | G9: 150.25 | H9: 2125.05 | I9: 0 | J9: 0 | K9: 212.51 | L9: 212.51 | M9: 212.51 | N9: 2762.58 | O9: 0 | P9: -65.5 | Q9: 53.52 | R9: 0 | S9: 0 | W9: 0 | X9: 0.16 | Y9: -11.82 | Z9: 2774.4 | AA9: 14.09 | AB9: 25.35 | AC9: 14.08 | AD9: -188.71 | AE9: 123.22 | AG9: 39.44 | AH9: 70.99 | AI9: 297.98 | AJ9: 2762.58 | AK9: 240.44 | AL9: 55.25 | AM9: 12.91 | AN9: 408.41 | AO9: 112.69 | AP9: 217.9 | AQ9: 151.27396 | AR9: PITSS
B10: SEI0026 | C10: Patricio Aguilar Jhonattan Cristian | D10: 15 | E10: 0 | F10: 150 | G10: 159.07 | H10: 2250 | I10: 0 | J10: 0 | K10: 225 | L10: 225 | M10: 225 | N10: 2925 | O10: 0 | P10: -43.57 | Q10: 56.67 | R10: 0 | S10: 0 | W10: 0 | X10: 0.1 | Y10: 13.2 | Z10: 2911.8 | AA10: 14.91 | AB10: 26.84 | AC10: 14.92 | AD10: -174.78 | AE10: 131.21 | AG10: 41.76 | AH10: 75.16 | AI10: 300.29 | AJ10: 2925 | AK10: 243.08 | AL10: 58.5 | AM10: 13.67 | AN10: 417.21 | AO10: 119.31 | AP10: 219.22 | AQ10: 160.16866 | AR10: PITSS
B11: SEI0039 | C11: Benavides Herrera Pablo | D11: 15 | E11: 0 | F11: 666.67 | G11: 696.81 | H11: 10000.05 | I11: 0 | J11: 0 | K11: 1000 | L11: 1000 | M11: 1000 | N11: 13000.05 | O11: 1497.79 | P11: 0 | Q11: 274.85 | R11: 0 | S11: 0 | W11: 0 | X11: 0.01 | Y11: 1772.65 | Z11: 11227.4 | AA11: 65.33 | AB11: 117.59 | AC11: 91.93 | AD11: 0 | AE11: 1497.79 | AG11: 182.91 | AH11: 329.24 | AI11: 514.6 | AJ11: 13000.05 | AK11: 404.4 | AL11: 260 | AM11: 59.88 | AN11: 1026.75 | AO11: 522.61 | AP11: 299.88 | AQ11: 711.86425 | AR11: PITSS
B12: SEI0040 | C12: Mora Ramirez Acal Aldo Isidro | D12: 15 | E12: 0 | F12: 216.67 | G12: 229.79 | H12: 3250.05 | I12: 0 | J12: 0 | K12: 325.01 | L12: 325.01 | M12: 325.01 | N12: 4225.08 | O12: 107.17 | P12: 0 | Q12: 81.87 | R12: 0 | S12: 0 | W12: 0 | X12: 0.04 | Y12: 189.08 | Z12: 4036 | AA12: 21.54 | AB12: 38.78 | AC12: 21.55 | AD12: -125.1 | AE12: 232.27 | AG12: 60.32 | AH12: 108.58 | AI12: 318.86 | AJ12: 4225.08 | AK12: 264.3 | AL12: 84.5 | AM12: 19.75 | AN12: 487.76 | AO12: 172.34 | AP12: 229.83 | AQ12: 231.35828 | AR12: PITSS
B13: SEI0041 | C13: Vazquez Perez Miguel Angel | D13: 15 | E13: 0 | F13: 283.33 | G13: 300.49 | H13: 4249.95 | I13: 0 | J13: 0 | K13: 425 | L13: 425 | M13: 425 | N13: 5524.95 | O13: 341.06 | P13: 0 | Q13: 109.87 | R13: 0 | S13: 0 | W13: 0 | X13: 0.02 | Y13: 450.95 | Z13: 5074 | AA13: 28.17 | AB13: 50.71 | AC13: 30.99 | AD13: 0 | AE13: 341.06 | AG13: 78.88 | AH13: 141.98 | AI13: 345.18 | AJ13: 5524.95 | AK13: 285.51 | AL13: 110.5 | AM13: 25.82 | AN13: 566.04 | AO13: 225.37 | AP13: 240.43 | AQ13: 302.53724 | AR13: PITSS
B14: SEI0088 | C14: Morgado Fernandez Martin | D14: 15 | E14: 0 | F14: 273.33 | G14: 289.87 | H14: 4099.95 | I14: 0 | J14: 0 | K14: 410 | L14: 410 | M14: 410 | N14: 5329.95 | O14: 324.74 | P14: 0 | Q14: 105.46 | R14: 0 | S14: 0 | W14: 0 | X14: 0.15 | Y14: 430.35 | Z14: 4899.6 | AA14: 27.18 | AB14: 48.92 | AC14: 29.36 | AD14: 0 | AE14: 324.74 | AG14: 76.09 | AH14: 136.96 | AI14: 340.64 | AJ14: 5329.95 | AK14: 282.32 | AL14: 106.6 | AM14: 24.91 | AN14: 553.69 | AO14: 217.4 | AP14: 238.84 | AQ14: 291.85933 | AR14: PITSS
B15: SEI0097 | C15: Arreola Jimenez Jose Nieves | D15: 15 | E15: 0 | F15: 185.83 | G15: 197.07 | H15: 2787.45 | I15: 0 | J15: 0 | K15: 278.75 | L15: 278.75 | M15: 278.75 | N15: 3623.7 | O15: 36.57 | P15: 0 | Q15: 70.22 | R15: 0 | S15: 1559.39 | W15: 224.7 | X15: -0.18 | Y15: 1890.7 | Z15: 1733 | AA15: 18.48 | AB15: 33.26 | AC15: 18.48 | AD15: -145.38 | AE15: 181.94 | AG15: 51.73 | AH15: 93.12 | AI15: 310.27 | AJ15: 3623.7 | AK15: 254.48 | AL15: 72.47 | AM15: 16.94 | AN15: 455.12 | AO15: 147.8 | AP15: 224.92 | AQ15: 198.42761 | AR15: PITSS
B16: SEI0099 | C16: Garcia Villicaña Ricardo Pascual | D16: 14 | E16: 1 | F16: 273.33 | G16: 289.87 | H16: 3826.62 | I16: 273.33 | J16: 82 | K16: 410 | L16: 410 | M16: 410 | N16: 5411.95 | O16: 324.74 | P16: 0 | Q16: 105.46 | R16: 0 | S16: 0 | W16: 0 | X16: 0.15 | Y16: 430.35 | Z16: 4981.6 | AA16: 27.18 | AB16: 48.92 | AC16: 29.36 | AD16: 0 | AE16: 324.74 | AG16: 76.09 | AH16: 136.96 | AI16: 340.64 | AJ16: 5411.95 | AK16: 282.32 | AL16: 108.24 | AM16: 24.91 | AN16: 553.69 | AO16: 217.4 | AP16: 238.84 | AQ16: 291.85933 | AR16: PITSS
B17: SEI0108 | C17: Caballero Diaz Francisco Javier | D17: 15 | E17: 0 | F17: 185.83 | G17: 197.07 | H17: 2787.45 | I17: 0 | J17: 0 | K17: 278.75 | L17: 278.75 | M17: 278.75 | N17: 3623.7 | O17: 36.57 | P17: 0 | Q17: 70.22 | R17: 0 | S17: 1809.82 | W17: 0 | X17: 0.09 | Y17: 1916.7 | Z17: 1707 | AA17: 18.48 | AB17: 33.26 | AC17: 18.48 | AD17: -145.38 | AE17: 181.94 | AG17: 51.73 | AH17: 93.12 | AI17: 310.27 | AJ17: 3623.7 | AK17: 254.48 | AL17: 72.47 | AM17: 16.94 | AN17: 455.12 | AO17: 147.8 | AP17: 224.92 | AQ17: 198.42761 | AR17: PITSS
B18: SEI0116 | C18: Casillas Cardona Cesar Alejandro | D18: 15 | E18: 0 | F18: 220.83 | G18: 234.19 | H18: 3312.45 | I18: 0 | J18: 0 | K18: 331.25 | L18: 331.25 | M18: 331.25 | N18: 4306.2 | O18: 113.96 | P18: 0 | Q18: 83.43 | R18: 0 | S18: 1045.17 | W18: 0 | X18: -0.16 | Y18: 1242.4 | Z18: 3063.8 | AA18: 21.96 | AB18: 39.52 | AC18: 21.95 | AD18: -125.1 | AE18: 239.06 | AG18: 61.47 | AH18: 110.65 | AI18: 320.01 | AJ18: 4306.2 | AK18: 265.62 | AL18: 86.12 | AM18: 20.13 | AN18: 492.13 | AO18: 175.64 | AP18: 230.49 | AQ18: 235.8003 | AR18: PITSS
B19: SEI0117 | C19: Mariscal Romero Luis Adrian | D19: 15 | E19: 0 | F19: 264.58 | G19: 276.54 | H19: 3968.7 | I19: 0 | J19: 0 | K19: 396.87 | L19: 396.87 | M19: 396.87 | N19: 5159.31 | O19: 310.46 | P19: 0 | Q19: 99.91 | R19: 0 | S19: 1658.56 | W19: 396 | X19: -0.02 | Y19: 2464.91 | Z19: 2694.4 | AA19: 25.93 | AB19: 46.67 | AC19: 27.31 | AD19: 0 | AE19: 310.46 | AG19: 72.59 | AH19: 130.66 | AI19: 334.94 | AJ19: 5159.31 | AK19: 278.32 | AL19: 103.19 | AM19: 23.76 | AN19: 538.19 | AO19: 207.4 | AP19: 236.84 | AQ19: 282.51615 | AR19: PITSS
B20: SEI0118 | C20: Arroyo Ramirez Hector Hugo | D20: 15 | E20: 0 | F20: 238.33 | G20: 252.75 | H20: 3574.95 | I20: 0 | J20: 285.99 | K20: 357.5 | L20: 357.5 | M20: 357.5 | N20: 4933.44 | O20: 160.25 | P20: 0 | Q20: 90.05 | R20: 0 | S20: 1418.5 | W20: 678.02 | X20: 0.02 | Y20: 2346.84 | Z20: 2586.6 | AA20: 23.7 | AB20: 42.65 | AC20: 23.7 | AD20: -107.37 | AE20: 267.62 | AG20: 66.35 | AH20: 119.42 | AI20: 324.89 | AJ20: 4933.44 | AK20: 271.18 | AL20: 98.67 | AM20: 21.72 | AN20: 510.66 | AO20: 189.56 | AP20: 233.27 | AQ20: 254.48664 | AR20: PITSS
... B29: SEI0445 | C29: Muñoz Melgoza Gabriel | D29: 15 | E29: 0 | F29: 256.67 | G29: 272.21 | H29: 3850.05 | I29: 0 | J29: 0 | K29: 385.01 | L29: 385.01 | M29: 385.01 | N29: 5005.08 | O29: 297.55 | P29: 0 | Q29: 98.1 | R29: 0 | S29: 0 | W29: 0 | X29: 0.03 | Y29: 395.68 | Z29: 4609.4 | AA29: 25.52 | AB29: 45.94 | AC29: 26.64 | AD29: 0 | AE29: 297.55 | AG29: 71.46 | AH29: 128.62 | AI29: 333.08 | AJ29: 5005.08 | AK29: 277.02 | AL29: 100.1 | AM29: 23.39 | AN29: 533.16 | AO29: 204.16 | AP29: 236.19 | AQ29: 274.06993 | AR29: PITSS
A30: Total PITSS | B30: =SUBTOTAL(9,B9:B29) -> 0 | C30: =SUBTOTAL(9,C9:C29) -> 0 | D30: =SUBTOTAL(9,D9:D29) -> 314 | E30: =SUBTOTAL(9,E9:E29) -> 1 | F30: =SUBTOTAL(9,F9:F29) -> 5852.89 | G30: =SUBTOTAL(9,G9:G29) -> 6192.87 | H30: =SUBTOTAL(9,H9:H29) -> 87520.02 | I30: =SUBTOTAL(9,I9:I29) -> 273.33 | ... AR30: =SUBTOTAL(9,AR9:AR29) -> 0
B31: SEI0010 | C31: Compean Tobias Braulio Gerardo | D31: 15 | E31: 0 | F31: 300 | G31: 313.56 | H31: 4500 | I31: 0 | J31: 0 | K31: 450 | L31: 450 | M31: 450 | N31: 5850 | O31: 380.67 | P31: 0 | Q31: 115.32 | R31: 0 | S31: 1320.68 | W31: 0 | X31: -0.07 | Y31: 1816.6 | Z31: 4033.4 | AA31: 29.4 | AB31: 52.91 | AC31: 33.01 | AD31: 0 | AE31: 380.67 | AG31: 82.31 | AH31: 148.16 | AI31: 350.77 | AJ31: 5850 | AK31: 289.43 | AL31: 117 | AM31: 26.95 | AN31: 581.24 | AO31: 235.17 | AP31: 242.39 | AQ31: 320.33731 | AR31: SEITON
B32: SEI0119 | C32: Dominguez Lopez Maria De Jesus | D32: 15 | E32: 0 | F32: 238.33 | G32: 252.76 | H32: 3574.95 | I32: 0 | J32: 0 | K32: 357.5 | L32: 357.5 | M32: 357.5 | N32: 4647.45 | O32: 160.25 | P32: 0 | Q32: 90.05 | R32: 947.85 | S32: 0 | W32: 0 | X32: 0.1 | Y32: 1198.25 | Z32: 3449.2 | AA32: 23.7 | AB32: 42.65 | AC32: 23.7 | AD32: -107.37 | AE32: 267.62 | AG32: 66.35 | AH32: 119.43 | AI32: 324.89 | AJ32: 4647.45 | AK32: 271.19 | AL32: 92.95 | AM32: 21.72 | AN32: 510.67 | AO32: 189.57 | AP32: 233.27 | AQ32: 254.48664 | AR32: SEITON
B33: SEI0147 | C33: Diaz Munguia Martha Liliana | D33: 15 | E33: 0 | F33: 308.33 | G33: 327 | H33: 4624.95 | I33: 0 | J33: 0 | K33: 462.5 | L33: 462.5 | M33: 462.5 | N33: 6012.45 | O33: 400.66 | P33: 0 | Q33: 120.9 | R33: 0 | S33: 413.05 | W33: 0 | X33: 0.04 | Y33: 934.65 | Z33: 5077.8 | AA33: 30.66 | AB33: 55.18 | AC33: 35.06 | AD33: 0 | AE33: 400.66 | AG33: 85.84 | AH33: 154.51 | AI33: 356.51 | AJ33: 6012.45 | AK33: 293.46 | AL33: 120.25 | AM33: 28.1 | AN33: 596.86 | AO33: 245.25 | AP33: 244.41 | AQ33: 329.23201 | AR33: SEITON
B34: SEI032 | C34: Camarena Quiroz Erick Frank | D34: 15 | E34: 0 | F34: 150 | G34: 159.07 | H34: 2250 | I34: 0 | J34: 0 | K34: 225 | L34: 225 | M34: 225 | N34: 2925 | O34: 0 | P34: -43.57 | Q34: 56.67 | R34: 0 | S34: 0 | W34: 0 | X34: -0.1 | Y34: 13 | Z34: 2912 | AA34: 14.91 | AB34: 26.84 | AC34: 14.92 | AD34: -174.78 | AE34: 131.21 | AG34: 41.76 | AH34: 75.16 | AI34: 300.29 | AJ34: 2925 | AK34: 243.08 | AL34: 58.5 | AM34: 13.67 | AN34: 417.21 | AO34: 119.3 | AP34: 219.22 | AQ34: 160.16866 | AR34: SEITON
B35: SEI0437 | C35: Leal Montaño Diego | D35: 13 | E35: 2 | F35: 166.67 | G35: 176.76 | H35: 2166.71 | I35: 333.34 | J35: 100 | K35: 250.01 | L35: 250.01 | M35: 250.01 | N35: 3350.08 | O35: 0 | P35: -9.62 | Q35: 62.97 | R35: 0 | S35: 392.72 | W35: 0 | X35: 0.01 | Y35: 446.08 | Z35: 2904 | AA35: 16.57 | AB35: 29.83 | AC35: 16.57 | AD35: -160.3 | AE35: 150.67 | AG35: 46.4 | AH35: 83.52 | AI35: 304.94 | AJ35: 3250.08 | AK35: 248.39 | AL35: 65 | AM35: 15.19 | AN35: 434.86 | AO35: 132.57 | AP35: 221.87 | AQ35: 177.96873 | AR35: SEITON
B36: SEI0440 | C36: Leija Arevalo Guadalupe | D36: 15 | E36: 0 | F36: 133.33 | G36: 139.36 | H36: 1999.95 | I36: 0 | J36: 0 | K36: 0 | L36: 0 | M36: 0 | N36: 1999.95 | O36: 0 | P36: -73.5 | Q36: 49.65 | R36: 0 | S36: 1044.75 | W36: 0 | X36: 0.05 | Y36: 1020.95 | Z36: 979 | AA36: 13.06 | AB36: 23.52 | AC36: 13.07 | AD36: -188.71 | AE36: 115.21 | AG36: 36.58 | AH36: 65.85 | AI36: 295.12 | AJ36: 1999.95 | AK36: 237.17 | AL36: 40 | AM36: 11.98 | AN36: 397.55 | AO36: 104.52 | AP36: 216.26 | AQ36: 142.36858 | AR36: SEITON
B37: SEI0447 | C37: Oliver Olague Vicente | D37: 15 | E37: 0 | F37: 291.67 | G37: 309.33 | H37: 4375.05 | I37: 0 | J37: 0 | K37: 437.51 | L37: 437.51 | M37: 437.51 | N37: 5687.58 | O37: 360.68 | P37: 0 | Q37: 113.55 | R37: 0 | S37: 0 | W37: 0 | X37: 0.15 | Y37: 474.38 | Z37: 5213.2 | AA37: 29 | AB37: 52.2 | AC37: 32.35 | AD37: 0 | AE37: 360.68 | AG37: 81.2 | AH37: 146.16 | AI37: 348.96 | AJ37: 5687.58 | AK37: 288.16 | AL37: 113.75 | AM37: 26.58 | AN37: 576.32 | AO37: 232 | AP37: 241.76 | AQ37: 311.44261 | AR37: SEITON
B38: SEI0448 | C38: Rodriguez Chavez Oswaldo Emmanuel | D38: 15 | E38: 0 | F38: 233.33 | G38: 247.46 | H38: 3499.95 | I38: 0 | J38: 0 | K38: 350 | L38: 350 | M38: 350 | N38: 4549.95 | O38: 134.36 | P38: 0 | Q38: 88.16 | R38: 0 | S38: 0 | W38: 0 | X38: 0.03 | Y38: 222.55 | Z38: 4327.4 | AA38: 23.2 | AB38: 41.76 | AC38: 23.2 | AD38: -125.1 | AE38: 259.46 | AG38: 64.96 | AH38: 116.92 | AI38: 323.5 | AJ38: 4549.95 | AK38: 269.6 | AL38: 91 | AM38: 21.27 | AN38: 505.38 | AO38: 185.6 | AP38: 232.48 | AQ38: 249.14768 | AR38: SEITON
A39: Total SEITON | B39: =SUBTOTAL(9,B31:B38) -> 0 | C39: =SUBTOTAL(9,C31:C38) -> 0 | D39: =SUBTOTAL(9,D31:D38) -> 118 | E39: =SUBTOTAL(9,E31:E38) -> 2 | F39: =SUBTOTAL(9,F31:F38) -> 1821.66 | G39: =SUBTOTAL(9,G31:G38) -> 1925.3 | H39: =SUBTOTAL(9,H31:H38) -> 26991.56 | I39: =SUBTOTAL(9,I31:I38) -> 333.34 | ... AR39: =SUBTOTAL(9,AR31:AR38) -> 0
B40: Total Depto | D40: ----------------------- | E40: ----------------------- | F40: ----------------------- | G40: ----------------------- | H40: ----------------------- | I40: ----------------------- | J40: ----------------------- | K40: ----------------------- | L40: ----------------------- | M40: ----------------------- | N40: ----------------------- | O40: ----------------------- | P40: ----------------------- | Q40: ----------------------- | R40: ----------------------- | S40: ----------------------- | T40: ----------------------- | U40: ----------------------- | V40: ----------------------- | W40: ----------------------- | X40: ----------------------- | Y40: ----------------------- | Z40: ----------------------- | AA40: ----------------------- | AB40: ----------------------- | AC40: ----------------------- | AD40: ----------------------- | AE40: ----------------------- | AF40: ----------------------- | AG40: ----------------------- | AH40: ----------------------- | AI40: ----------------------- | AJ40: ----------------------- | AK40: ----------------------- | AL40: ----------------------- | AM40: ----------------------- | AN40: ----------------------- | AO40: ----------------------- | AP40: -----------------------
B41: =SUM(B9:B40) -> 0 | C41: =SUM(C9:C40) -> 0 | D41: =+D30+D39 -> 432 | E41: =+E30+E39 -> 3 | F41: =+F30+F39 -> 7674.55 | G41: =+G30+G39 -> 8118.17 | H41: =+H30+H39 -> 114511.58 | I41: =+I30+I39 -> 606.67 | J41: =+J30+J39 -> 467.99 | K41: =+K30+K39 -> 11311.94 | ... AR41: =+AR30+AR39 -> 0
M42: FACTURACION PITS | O42: FACTURACION SEITON
B43: 30 | C43: Nomina | M43: Devengado Salario | N43: =+Z30 -> 92104.4 | O43: Devengado Salario | P43: =+Z39 -> 28896
B44: 0 | C44: Altas | M44: RETORNOS | N44: =+W30 -> 2029.52 | O44: RETORNOS | P44: =+W39 -> 0
B45: 1 | C45: Bajas | M45: Infonavit | N45: =+T30+S30+R30+U30 -> 11134.06 | O45: Infonavit | P45: =+T39+S39+R39+U39 -> 4119.05
B46: =+B43+B44-B45 -> 29 | C46: Total Nomina | M46: Prestamo Prospera | N46: =+V30 -> 0 | O46: Prestamo Prospera | P46: =+W39 -> 0
M47: Subtotal 1 | N47: =SUM(N43:N46) -> 105267.98 | O47: Subtotal 1 | P47: =SUM(P43:P46) -> 33015.05
M48: Comision | N48: =+N47*2% -> 2105.3596 | O48: Comision | P48: =+P47*2% -> 660.301
M49: Subtotal 2 | N49: =+N47+N48 -> 107373.34 | O49: Subtotal 2 | P49: =+P47+P48 -> 33675.351
M50: Costo Patronal Imss | N50: =+Q30+AG30+AH30+AI30+AK30+AM30+AO30+AP30 -> 30322.21 | O50: Costo Patronal Imss | P50: =+Q39+AG39+AH39+AI39+AK39+AM39+AO39+AP39 -> 10318.94
M51: 2% Sobre Nomina | N51: =+N30*2% -> 2289.992 | O51: 2% Sobre Nomina | P51: =+N39*2% -> 700.4492
M52: Importe de Factura | N52: =+N49+N50+N51 -> 139985.54 | O52: Importe de Factura | P52: =+P49+P50+P51 -> 44694.74
M53: IVA | N53: =+N52*16% -> 22397.687 | O53: IVA | P53: =+P52*16% -> 7151.1584
M54: TOTAL | N54: =+N52+N53 -> 162383.23 | O54: TOTAL | P54: =+P52+P53 -> 51845.899
M55: PROVISION DE AGUINALDO
M56: FACTURACION PITS | O56: FACTURACION SEITON
M57: Subtotal 1 | N57: =+AQ30 -> 6249.6635 | O57: Subtotal 1 | P57: =+AQ39 -> 1945.1522
M58: Comision | N58: =+N57*2% -> 124.99327 | O58: Comision | P58: =+P57*2% -> 38.903045
M59: Subtotal 2 | N59: =+N57+N58 -> 6374.6568 | O59: Subtotal 2 | P59: =+P57+P58 -> 1984.0553
M60: 2% Sobre Nomina | N60: =+N57*2% -> 124.99327 | O60: 2% Sobre Nomina | P60: =+P57*2% -> 38.903045
M61: Importe de Factura | N61: =+N59+N60 -> 6499.65 | O61: Importe de Factura | P61: =+P59+P60 -> 2022.9583
M62: IVA | N62: =+N61*16% -> 1039.944 | O62: IVA | P62: =+P61*16% -> 323.67333
M63: TOTAL | N63: =+N61+N62 -> 7539.5941 | O63: TOTAL | P63: =+P61+P62 -> 2346.6316

Sheet IP
B2: IP INNOVACION EN PROYECTOS S DE RL DE CV
B3: Lista de Raya (forma tabular)
B4: Reg Pat IMSS: Z2942442109
B5: RFC: IIP -150923-DT7
A8: Código | B8: Empleado | C8: Dias Laborados | D8: Dias Vacaciones | E8: Salario Diario | F8: Salario Diario Integrado | G8: Sueldo | H8: Vacaciones a tiempo | I8: Prima de vacaciones a tiempo | J8: *TOTAL* *PERCEPCIONES* | K8: I.S.R. (sp) | L8: Subsidio al Empleo (sp) | M8: I.M.S.S. | N8: Préstamo Infonavit (vsm) | O8: Préstamo Infonavit (cf) | P8: Seguro de vivienda Infonavit | Q8: Prestamo FONACOT | R8: Deduccion general | S8: Aportación voluntaria SAR | T8: Ajuste al neto | U8: *TOTAL* *DEDUCCIONES* | V8: *NETO* | W8: Ret. Inv. Y Vida | X8: Ret. Cesantia | Y8: Ret. Enf. y Mat. obrero | Z8: Subs al Empleo acreditado | AA8: I.S.R. antes de Subs al Empleo | AB8: isr 2 | AC8: Invalidez y Vida | AD8: Cesantia y Vejez | AE8: Enf. y Mat. Patron | AF8: Total Percepciones | AG8: 2% Fondo retiro SAR (8) | AH8: 2% Impuesto estatal | AI8: Riesgo de trabajo (9) | AJ8: I.M.S.S. empresa | AK8: Infonavit empresa | AL8: Guarderia I.M.S.S. (7) | AM8: Proporcion Aguinaldo | AN8: CC
A9: SEI0010 | B9: Torres Ricardez Alfredo | C9: 15 | D9: 0 | E9: 266.67 | F9: 278.72 | G9: 4000.05 | H9: 0 | I9: 0 | J9: 4000.05 | K9: 313.87 | L9: 0 | M9: 100.81 | N9: 0 | O9: 0 | Q9: 0 | R9: 0 | S9: 0 | T9: 0.17 | U9: 414.85 | V9: 3585.2 | W9: 26.13 | X9: 47.03 | Y9: 27.65 | Z9: 0 | AA9: 313.87 | AC9: 73.16 | AD9: 131.7 | AE9: 335.88 | AF9: 4000.05 | AG9: 266.64 | AH9: 80 | AI9: 47.27 | AJ9: 540.74 | AK9: 209.04 | AL9: 224.83 | AM9: 219.0368 | AN9: PITSS
A10: SEI0014 | B10: Montoya Portillo Carlos Alberto | C10: 15 | D10: 0 | E10: 266.67 | F10: 278.72 | G10: 4000.05 | H10: 0 | I10: 0 | J10: 4000.05 | K10: 313.87 | L10: 0 | M10: 100.81 | N10: 0 | O10: 0 | Q10: 0 | R10: 0 | S10: 0 | T10: -0.03 | U10: 414.65 | V10: 3585.4 | W10: 26.13 | X10: 47.03 | Y10: 27.65 | Z10: 0 | AA10: 313.87 | AC10: 73.16 | AD10: 131.7 | AE10: 335.88 | AF10: 4000.05 | AG10: 266.64 | AH10: 80 | AI10: 47.27 | AJ10: 540.74 | AK10: 209.04 | AL10: 224.83 | AM10: 219.0368 | AN10: PITSS
A11: SEI0015 | B11: Cota Jaramillo Miguel Angel | C11: 15 | D11: 0 | E11: 200 | F11: 209.04 | G11: 3000 | H11: 0 | I11: 0 | J11: 3000 | K11: 59.69 | L11: 0 | M11: 74.48 | N11: 0 | O11: 0 | Q11: 0 | R11: 0 | S11: 0 | T11: 0.03 | U11: 134.2 | V11: 2865.8 | W11: 19.6 | X11: 35.28 | Y11: 19.6 | Z11: -145.38 | AA11: 205.07 | AC11: 54.87 | AD11: 98.77 | AE11: 313.41 | AF11: 3000 | AG11: 245.73 | AH11: 60 | AI11: 35.45 | AJ11: 467.05 | AK11: 156.78 | AL11: 214.38 | AM11: 164.27554 | AN11: PITSS
A12: SEI0016 | B12: Negrete Bejar Aide Sarai | C12: 15 | D12: 0 | E12: 154 | F12: 160.96 | G12: 2310 | H12: 0 | I12: 0 | J12: 2310 | K12: 0 | L12: -39.73 | M12: 57.34 | N12: 1188.73 | O12: 0 | Q12: 0 | R12: 0 | S12: 0 | T12: 0.06 | U12: 1206.4 | V12: 1103.6 | W12: 15.09 | X12: 27.16 | Y12: 15.09 | Z12: -174.78 | AA12: 135.05 | AC12: 42.25 | AD12: 76.05 | AE12: 300.79 | AF12: 2310 | AG12: 231.31 | AH12: 46.2 | AI12: 27.3 | AJ12: 419.09 | AK12: 120.72 | AL12: 207.16 | AM12: 126.49217 | AN12: SEITON
A13: SEI0017 | B13: Muñoz Reyes Luis Eduardo | C13: 15 | D13: 0 | E13: 266.67 | F13: 278.72 | G13: 4000.05 | H13: 0 | I13: 0 | J13: 4000.05 | K13: 313.87 | L13: 0 | M13: 100.81 | N13: 878.36 | O13: 0 | Q13: 0 | R13: 0 | S13: 0 | T13: 0.01 | U13: 1293.05 | V13: 2707 | W13: 26.13 | X13: 47.03 | Y13: 27.65 | Z13: 0 | AA13: 313.87 | AC13: 73.16 | AD13: 131.7 | AE13: 335.88 | AF13: 4000.05 | AG13: 266.64 | AH13: 80 | AI13: 47.27 | AJ13: 540.74 | AK13: 209.04 | AL13: 224.83 | AM13: 219.0368 | AN13: PITSS
A14: SEI0018 | B14: Dominguez Mendez Victor Manuel | C14: 15 | D14: 0 | E14: 300 | F14: 313.56 | G14: 4500 | H14: 0 | I14: 0 | J14: 4500 | K14: 380.67 | L14: 0 | M14: 115.32 | N14: 0 | O14: 0 | Q14: 0 | R14: 0 | S14: 0 | T14: 0.01 | U14: 496 | V14: 4004 | W14: 29.4 | X14: 52.91 | Y14: 33.01 | Z14: 0 | AA14: 380.67 | AC14: 82.31 | AD14: 148.16 | AE14: 350.76 | AF14: 4500 | AG14: 277.09 | AH14: 90 | AI14: 53.18 | AJ14: 581.23 | AK14: 235.17 | AL14: 230.05 | AM14: 246.41332 | AN14: PITSS
A15: SEI0019 | B15: Gonzalez Rasgado Miguel Isaias | C15: 13 | D15: 2 | E15: 400 | F15: 424.2 | G15: 5200 | H15: 800 | I15: 240 | J15: 6240 | K15: 643.38 | L15: 0 | M15: 161.36 | N15: 0 | O15: 0 | Q15: 0 | R15: 0 | S15: 0 | T15: 0.06 | U15: 804.8 | V15: 5435.2 | W15: 39.77 | X15: 71.58 | Y15: 50.01 | Z15: 0 | AA15: 643.38 | AC15: 111.35 | AD15: 200.43 | AE15: 398.06 | AF15: 6240 | AG15: 310.28 | AH15: 124.8 | AI15: 71.94 | AJ15: 709.84 | AK15: 318.15 | AL15: 246.65 | AM15: 328.55109 | AN15: PITSS
A16: SEI0020 | B16: Mar Marquez Cesar Eduardo | C16: 15 | D16: 0 | E16: 266.67 | F16: 278.72 | G16: 4000.05 | H16: 0 | I16: 0 | J16: 4000.05 | K16: 313.87 | L16: 0 | M16: 100.81 | N16: 0 | O16: 0 | Q16: 0 | R16: 0 | S16: 0 | T16: -0.03 | U16: 414.65 | V16: 3585.4 | W16: 26.13 | X16: 47.03 | Y16: 27.65 | Z16: 0 | AA16: 313.87 | AC16: 73.16 | AD16: 131.7 | AE16: 335.88 | AF16: 4000.05 | AG16: 266.64 | AH16: 80 | AI16: 47.27 | AJ16: 540.74 | AK16: 209.04 | AL16: 224.83 | AM16: 219.0368 | AN16: PITSS
A17: SEI0021 | B17: Velez Rodriguez Jaime | C17: 15 | D17: 0 | E17: 200 | F17: 212.1 | G17: 3000 | H17: 0 | I17: 0 | J17: 3000 | K17: 59.69 | L17: 0 | M17: 75.55 | N17: 1362.48 | O17: 0 | Q17: 0 | R17: 0 | S17: 0 | T17: -0.12 | U17: 1497.6 | V17: 1502.4 | W17: 19.88 | X17: 35.79 | Y17: 19.88 | Z17: -145.38 | AA17: 205.07 | AC17: 55.68 | AD17: 100.22 | AE17: 314.22 | AF17: 3000 | AG17: 246.65 | AH17: 60 | AI17: 35.97 | AJ17: 470.12 | AK17: 159.08 | AL17: 214.84 | AM17: 164.27554 | AN17: PITSS
A18: SEI0022 | B18: Najera Lopez Raul | C18: 15 | D18: 0 | E18: 333.33 | F18: 353.5 | G18: 4999.95 | H18: 0 | I18: 0 | J18: 4999.95 | K18: 461.63 | L18: 0 | M18: 131.93 | N18: 0 | O18: 0 | Q18: 0 | R18: 0 | S18: 0 | T18: -0.01 | U18: 593.55 | V18: 4406.4 | W18: 33.14 | X18: 59.65 | Y18: 39.14 | Z18: 0 | AA18: 461.63 | AC18: 92.79 | AD18: 167.03 | AE18: 367.84 | AF18: 4999.95 | AG18: 289.07 | AH18: 100 | AI18: 59.95 | AJ18: 627.66 | AK18: 265.12 | AL18: 236.04 | AM18: 273.78984 | AN18: PITSS
A19: SEI0023 | B19: Puente Murguia Luis Felipe | C19: 15 | D19: 0 | E19: 233.33 | F19: 247.45 | G19: 3499.95 | H19: 0 | I19: 0 | J19: 3499.95 | K19: 134.36 | L19: 0 | M19: 88.16 | N19: 0 | O19: 0 | Q19: 0 | R19: 0 | S19: 0 | T19: 0.03 | U19: 222.55 | V19: 3277.4 | W19: 23.2 | X19: 41.76 | Y19: 23.2 | Z19: -125.1 | AA19: 259.46 | AC19: 64.95 | AD19: 116.92 | AE19: 323.49 | AF19: 3499.95 | AG19: 257.25 | AH19: 70 | AI19: 41.97 | AJ19: 505.36 | AK19: 185.58 | AL19: 220.14 | AM19: 191.65206 | AN19: PITSS
A20: SEI0028 | B20: Jimenez Alcaraz Elizabeth | C20: 15 | D20: 0 | E20: 200 | F20: 212.11 | G20: 3000 | H20: 0 | I20: 0 | J20: 3000 | K20: 59.69 | L20: 0 | M20: 75.56 | N20: 0 | O20: 0 | Q20: 0 | R20: 0 | S20: 0 | T20: -0.05 | U20: 135.2 | V20: 2864.8 | W20: 19.89 | X20: 35.79 | Y20: 19.88 | Z20: -145.38 | AA20: 205.07 | AC20: 55.68 | AD20: 100.22 | AE20: 314.22 | AF20: 3000 | AG20: 246.65 | AH20: 60 | AI20: 35.97 | AJ20: 470.12 | AK20: 159.08 | AL20: 214.84 | AM20: 164.27554 | AN20: PITSS
... A117: SEI479 | B117: Cruz Perez Alejandro Nezahualcoyotl | C117: 15 | D117: 0 | E117: 266.67 | F117: 282.81 | G117: 4000.05 | H117: 0 | I117: 0 | J117: 4000.05 | K117: 313.87 | L117: 0 | M117: 102.51 | N117: 0 | O117: 0 | Q117: 0 | R117: 0 | S117: 0 | T117: 0.07 | U117: 416.45 | V117: 3583.6 | W117: 26.51 | X117: 47.72 | Y117: 28.28 | Z117: 0 | AA117: 313.87 | AC117: 74.24 | AD117: 133.63 | AE117: 337.62 | AF117: 4000.05 | AG117: 267.86 | AH117: 80 | AI117: 47.96 | AJ117: 545.49 | AK117: 212.11 | AL117: 225.44 | AM117: 219.0368 | AN117: PITSS
A118: Total Depto | C118: ----------------------- | D118: ----------------------- | E118: ----------------------- | F118: ----------------------- | G118: ----------------------- | H118: ----------------------- | I118: ----------------------- | J118: ----------------------- | K118: ----------------------- | L118: ----------------------- | M118: ----------------------- | N118: ----------------------- | O118: ----------------------- | P118: ----------------------- | Q118: ----------------------- | R118: ----------------------- | S118: ----------------------- | T118: ----------------------- | U118: ----------------------- | V118: ----------------------- | W118: ----------------------- | X118: ----------------------- | Y118: ----------------------- | Z118: ----------------------- | AA118: ----------------------- | AC118: ----------------------- | AD118: ----------------------- | AE118: ----------------------- | AF118: ----------------------- | AG118: ----------------------- | AH118: ----------------------- | AI118: ----------------------- | AJ118: ----------------------- | AK118: ----------------------- | AL118: ----------------------- | AM118: -----------------------
A119: =SUM(A9:A118) -> 0 | B119: =SUM(B9:B118) -> 0 | C119: =SUM(C9:C118) -> 1601 | D119: =SUM(D9:D118) -> 20 | E119: =SUM(E9:E118) -> 26931.83 | F119: =SUM(F9:F118) -> 28414.15 | G119: =SUM(G9:G118) -> 397676.68 | H119: =SUM(H9:H118) -> 4500.82 | ... AA119: =SUM(AA9:AA118) -> 32286.74 | AC119: =SUM(AC9:AC118) -> 7439.29 | AD119: =SUM(AD9:AD118) -> 13390.65 | AE119: =SUM(AE9:AE118) -> 36006.34 | AF119: =SUM(AF9:AF118) -> 404965.69 | AG119: =SUM(AG9:AG118) -> 28451.06 | AH119: =SUM(AH9:AH118) -> 8099.28 | AI119: =SUM(AI9:AI118) -> 4806.25 | AJ119: =SUM(AJ9:AJ118) -> 56836.28 | ... AM119: =SUM(AM9:AM118) -> 22121.205
A121: 107 | B121: Nomina | I121: Devengado Salario | J121: =+V119 -> 319330.2
A122: 2 | B122: Altas | I122: Retornos | J122: =+R119 -> 7146.18
A123: 0 | B123: Bajas | I123: Infonavit | J123: =+N119+O119+P119 -> 39195.6
A124: =+A121+A122-A123 -> 109 | B124: Total Nomina | I124: Prestamo Prospera | J124: =+Q119 -> 4763.93
I125: aportacion voluntaria | J125: =+S119 -> 500
I126: Subtotal 1 | J126: =SUM(J121:J125) -> 370935.91
I127: Comision | J127: =+J126*2% -> 7418.7182
I128: Subtotal 2 | J128: =+J126+J127 -> 378354.63
I129: Costo Patronal Imss | J129: =+M119+AC119+AD119+AE119+AG119+AI119+AL119+AK119 -> 145834.12
I130: 2% Sobre Nomina | J130: =+J119*2% -> 8107.1186
I131: Importe de Factura | J131: =+J128+J129+J130 -> 532295.87
I132: certificacion de cheque | J132: 0
I133: IVA | J133: =(+J131+J132)*0.16 -> 85167.339
I134: TOTAL | J134: =+J131+J132+J133 -> 617463.21

Sheet FAC-IP
C2: IP INNOVACION EN PROYECTOS S DE RL DE CV
C3: Lista de Raya (forma tabular)
C4: Reg Pat IMSS: Z2942442109
C5: RFC: IIP -150923-DT7
B8: Código | C8: Empleado | D8: Dias Laborados | E8: Dias Vacaciones | F8: Salario Diario | G8: Salario Diario Integrado | H8: Sueldo | I8: Vacaciones a tiempo | J8: Prima de vacaciones a tiempo | K8: *TOTAL* *PERCEPCIONES* | L8: I.S.R. (sp) | M8: Subsidio al Empleo (sp) | N8: I.M.S.S. | O8: Préstamo Infonavit (vsm) | P8: Préstamo Infonavit (cf) | Q8: Seguro de vivienda Infonavit | R8: Prestamo FONACOT | S8: Deduccion general | T8: Aportación voluntaria SAR | U8: Ajuste al neto | V8: *TOTAL* *DEDUCCIONES* | W8: *NETO* | X8: Ret. Inv. Y Vida | Y8: Ret. Cesantia | Z8: Ret. Enf. y Mat. obrero | AA8: Subs al Empleo acreditado | AB8: I.S.R. antes de Subs al Empleo | AC8: isr 2 | AD8: Invalidez y Vida | AE8: Cesantia y Vejez | AF8: Enf. y Mat. Patron | AG8: Total Percepciones | AH8: 2% Fondo retiro SAR (8) | AI8: 2% Impuesto estatal | AJ8: Riesgo de trabajo (9) | AK8: I.M.S.S. empresa | AL8: Infonavit empresa | AM8: Guarderia I.M.S.S. (7) | AN8: Proporcion Aguinaldo | AO8: FACTURACION
B9: SEI0010 | C9: Torres Ricardez Alfredo | D9: 15 | E9: 0 | F9: 266.67 | G9: 278.72 | H9: 4000.05 | I9: 0 | J9: 0 | K9: 4000.05 | L9: 313.87 | M9: 0 | N9: 100.81 | O9: 0 | P9: 0 | R9: 0 | S9: 0 | T9: 0 | U9: 0.17 | V9: 414.85 | W9: 3585.2 | X9: 26.13 | Y9: 47.03 | Z9: 27.65 | AA9: 0 | AB9: 313.87 | AD9: 73.16 | AE9: 131.7 | AF9: 335.88 | AG9: 4000.05 | AH9: 266.64 | AI9: 80 | AJ9: 47.27 | AK9: 540.74 | AL9: 209.04 | AM9: 224.83 | AN9: 219.0368 | AO9: PITSS
B10: SEI0014 | C10: Montoya Portillo Carlos Alberto | D10: 15 | E10: 0 | F10: 266.67 | G10: 278.72 | H10: 4000.05 | I10: 0 | J10: 0 | K10: 4000.05 | L10: 313.87 | M10: 0 | N10: 100.81 | O10: 0 | P10: 0 | R10: 0 | S10: 0 | T10: 0 | U10: -0.03 | V10: 414.65 | W10: 3585.4 | X10: 26.13 | Y10: 47.03 | Z10: 27.65 | AA10: 0 | AB10: 313.87 | AD10: 73.16 | AE10: 131.7 | AF10: 335.88 | AG10: 4000.05 | AH10: 266.64 | AI10: 80 | AJ10: 47.27 | AK10: 540.74 | AL10: 209.04 | AM10: 224.83 | AN10: 219.0368 | AO10: PITSS
B11: SEI0015 | C11: Cota Jaramillo Miguel Angel | D11: 15 | E11: 0 | F11: 200 | G11: 209.04 | H11: 3000 | I11: 0 | J11: 0 | K11: 3000 | L11: 59.69 | M11: 0 | N11: 74.48 | O11: 0 | P11: 0 | R11: 0 | S11: 0 | T11: 0 | U11: 0.03 | V11: 134.2 | W11: 2865.8 | X11: 19.6 | Y11: 35.28 | Z11: 19.6 | AA11: -145.38 | AB11: 205.07 | AD11: 54.87 | AE11: 98.77 | AF11: 313.41 | AG11: 3000 | AH11: 245.73 | AI11: 60 | AJ11: 35.45 | AK11: 467.05 | AL11: 156.78 | AM11: 214.38 | AN11: 164.27554 | AO11: PITSS
B12: SEI0017 | C12: Muñoz Reyes Luis Eduardo | D12: 15 | E12: 0 | F12: 266.67 | G12: 278.72 | H12: 4000.05 | I12: 0 | J12: 0 | K12: 4000.05 | L12: 313.87 | M12: 0 | N12: 100.81 | O12: 878.36 | P12: 0 | R12: 0 | S12: 0 | T12: 0 | U12: 0.01 | V12: 1293.05 | W12: 2707 | X12: 26.13 | Y12: 47.03 | Z12: 27.65 | AA12: 0 | AB12: 313.87 | AD12: 73.16 | AE12: 131.7 | AF12: 335.88 | AG12: 4000.05 | AH12: 266.64 | AI12: 80 | AJ12: 47.27 | AK12: 540.74 | AL12: 209.04 | AM12: 224.83 | AN12: 219.0368 | AO12: PITSS
B13: SEI0018 | C13: Dominguez Mendez Victor Manuel | D13: 15 | E13: 0 | F13: 300 | G13: 313.56 | H13: 4500 | I13: 0 | J13: 0 | K13: 4500 | L13: 380.67 | M13: 0 | N13: 115.32 | O13: 0 | P13: 0 | R13: 0 | S13: 0 | T13: 0 | U13: 0.01 | V13: 496 | W13: 4004 | X13: 29.4 | Y13: 52.91 | Z13: 33.01 | AA13: 0 | AB13: 380.67 | AD13: 82.31 | AE13: 148.16 | AF13: 350.76 | AG13: 4500 | AH13: 277.09 | AI13: 90 | AJ13: 53.18 | AK13: 581.23 | AL13: 235.17 | AM13: 230.05 | AN13: 246.41332 | AO13: PITSS
B14: SEI0019 | C14: Gonzalez Rasgado Miguel Isaias | D14: 13 | E14: 2 | F14: 400 | G14: 424.2 | H14: 5200 | I14: 800 | J14: 240 | K14: 6240 | L14: 643.38 | M14: 0 | N14: 161.36 | O14: 0 | P14: 0 | R14: 0 | S14: 0 | T14: 0 | U14: 0.06 | V14: 804.8 | W14: 5435.2 | X14: 39.77 | Y14: 71.58 | Z14: 50.01 | AA14: 0 | AB14: 643.38 | AD14: 111.35 | AE14: 200.43 | AF14: 398.06 | AG14: 6240 | AH14: 310.28 | AI14: 124.8 | AJ14: 71.94 | AK14: 709.84 | AL14: 318.15 | AM14: 246.65 | AN14: 328.55109 | AO14: PITSS
B15: SEI0020 | C15: Mar Marquez Cesar Eduardo | D15: 15 | E15: 0 | F15: 266.67 | G15: 278.72 | H15: 4000.05 | I15: 0 | J15: 0 | K15: 4000.05 | L15: 313.87 | M15: 0 | N15: 100.81 | O15: 0 | P15: 0 | R15: 0 | S15: 0 | T15: 0 | U15: -0.03 | V15: 414.65 | W15: 3585.4 | X15: 26.13 | Y15: 47.03 | Z15: 27.65 | AA15: 0 | AB15: 313.87 | AD15: 73.16 | AE15: 131.7 | AF15: 335.88 | AG15: 4000.05 | AH15: 266.64 | AI15: 80 | AJ15: 47.27 | AK15: 540.74 | AL15: 209.04 | AM15: 224.83 | AN15: 219.0368 | AO15: PITSS
B16: SEI0021 | C16: Velez Rodriguez Jaime | D16: 15 | E16: 0 | F16: 200 | G16: 212.1 | H16: 3000 | I16: 0 | J16: 0 | K16: 3000 | L16: 59.69 | M16: 0 | N16: 75.55 | O16: 1362.48 | P16: 0 | R16: 0 | S16: 0 | T16: 0 | U16: -0.12 | V16: 1497.6 | W16: 1502.4 | X16: 19.88 | Y16: 35.79 | Z16: 19.88 | AA16: -145.38 | AB16: 205.07 | AD16: 55.68 | AE16: 100.22 | AF16: 314.22 | AG16: 3000 | AH16: 246.65 | AI16: 60 | AJ16: 35.97 | AK16: 470.12 | AL16: 159.08 | AM16: 214.84 | AN16: 164.27554 | AO16: PITSS
B17: SEI0022 | C17: Najera Lopez Raul | D17: 15 | E17: 0 | F17: 333.33 | G17: 353.5 | H17: 4999.95 | I17: 0 | J17: 0 | K17: 4999.95 | L17: 461.63 | M17: 0 | N17: 131.93 | O17: 0 | P17: 0 | R17: 0 | S17: 0 | T17: 0 | U17: -0.01 | V17: 593.55 | W17: 4406.4 | X17: 33.14 | Y17: 59.65 | Z17: 39.14 | AA17: 0 | AB17: 461.63 | AD17: 92.79 | AE17: 167.03 | AF17: 367.84 | AG17: 4999.95 | AH17: 289.07 | AI17: 100 | AJ17: 59.95 | AK17: 627.66 | AL17: 265.12 | AM17: 236.04 | AN17: 273.78984 | AO17: PITSS
B18: SEI0023 | C18: Puente Murguia Luis Felipe | D18: 15 | E18: 0 | F18: 233.33 | G18: 247.45 | H18: 3499.95 | I18: 0 | J18: 0 | K18: 3499.95 | L18: 134.36 | M18: 0 | N18: 88.16 | O18: 0 | P18: 0 | R18: 0 | S18: 0 | T18: 0 | U18: 0.03 | V18: 222.55 | W18: 3277.4 | X18: 23.2 | Y18: 41.76 | Z18: 23.2 | AA18: -125.1 | AB18: 259.46 | AD18: 64.95 | AE18: 116.92 | AF18: 323.49 | AG18: 3499.95 | AH18: 257.25 | AI18: 70 | AJ18: 41.97 | AK18: 505.36 | AL18: 185.58 | AM18: 220.14 | AN18: 191.65206 | AO18: PITSS
B19: SEI0029 | C19: Arceo Garcia Manuel Federico | D19: 15 | E19: 0 | F19: 200 | G19: 212.1 | H19: 3000 | I19: 0 | J19: 0 | K19: 3000 | L19: 59.69 | M19: 0 | N19: 75.55 | O19: 0 | P19: 0 | R19: 1800 | S19: 0 | T19: 0 | U19: -0.04 | V19: 1935.2 | W19: 1064.8 | X19: 19.88 | Y19: 35.79 | Z19: 19.88 | AA19: -145.38 | AB19: 205.07 | AD19: 55.68 | AE19: 100.22 | AF19: 314.22 | AG19: 3000 | AH19: 246.65 | AI19: 60 | AJ19: 35.97 | AK19: 470.12 | AL19: 159.08 | AM19: 214.84 | AN19: 164.27554 | AO19: PITSS
B20: SEI0364 | C20: Dominguez Lopez Mayeli Del Pilar | D20: 15 | E20: 0 | F20: 266.67 | G20: 282.81 | H20: 4000.05 | I20: 0 | J20: 0 | K20: 4000.05 | L20: 313.87 | M20: 0 | N20: 102.51 | O20: 0 | P20: 0 | R20: 0 | S20: 1666.67 | T20: 0 | U20: 0 | V20: 2083.05 | W20: 1917 | X20: 26.51 | Y20: 47.72 | Z20: 28.28 | AA20: 0 | AB20: 313.87 | AD20: 74.24 | AE20: 133.63 | AF20: 337.62 | AG20: 4000.05 | AH20: 267.86 | AI20: 80 | AJ20: 47.96 | AK20: 545.49 | AL20: 212.11 | AM20: 225.44 | AN20: 219.0368 | AO20: PITSS
... B88: SEI479 | C88: Cruz Perez Alejandro Nezahualcoyotl | D88: 15 | E88: 0 | F88: 266.67 | G88: 282.81 | H88: 4000.05 | I88: 0 | J88: 0 | K88: 4000.05 | L88: 313.87 | M88: 0 | N88: 102.51 | O88: 0 | P88: 0 | R88: 0 | S88: 0 | T88: 0 | U88: 0.07 | V88: 416.45 | W88: 3583.6 | X88: 26.51 | Y88: 47.72 | Z88: 28.28 | AA88: 0 | AB88: 313.87 | AD88: 74.24 | AE88: 133.63 | AF88: 337.62 | AG88: 4000.05 | AH88: 267.86 | AI88: 80 | AJ88: 47.96 | AK88: 545.49 | AL88: 212.11 | AM88: 225.44 | AN88: 219.0368 | AO88: PITSS
A89: Total PITSS | B89: =SUBTOTAL(9,B9:B88) -> 0 | C89: =SUBTOTAL(9,C9:C88) -> 0 | D89: =SUBTOTAL(9,D9:D88) -> 1181 | E89: =SUBTOTAL(9,E9:E88) -> 6 | F89: =SUBTOTAL(9,F9:F88) -> 19133.77 | G89: =SUBTOTAL(9,G9:G88) -> 20176.62 | H89: =SUBTOTAL(9,H9:H88) -> 283739.98 | I89: =SUBTOTAL(9,I9:I88) -> 1666.67 | ... AO89: =SUBTOTAL(9,AO9:AO88) -> 0
B90: SEI0522 | C90: Peña Lopez Abigail | D90: 15 | E90: 0 | F90: 230 | G90: 243.93 | H90: 3450 | I90: 0 | J90: 0 | K90: 3450 | L90: 128.93 | M90: 0 | N90: 86.9 | O90: 0 | P90: 0 | R90: 0 | S90: 0 | T90: 0 | U90: 0.17 | V90: 216 | W90: 3234 | X90: 22.87 | Y90: 41.16 | Z90: 22.87 | AA90: -125.1 | AB90: 254.03 | AD90: 64.03 | AE90: 115.26 | AF90: 322.57 | AG90: 3450 | AH90: 256.2 | AI90: 69 | AJ90: 41.37 | AK90: 501.86 | AL90: 182.95 | AM90: 219.61 | AN90: 188.91688 | AO90: SEITON
B91: SEI0028 | C91: Jimenez Alcaraz Elizabeth | D91: 15 | E91: 0 | F91: 200 | G91: 212.11 | H91: 3000 | I91: 0 | J91: 0 | K91: 3000 | L91: 59.69 | M91: 0 | N91: 75.56 | O91: 0 | P91: 0 | R91: 0 | S91: 0 | T91: 0 | U91: -0.05 | V91: 135.2 | W91: 2864.8 | X91: 19.89 | Y91: 35.79 | Z91: 19.88 | AA91: -145.38 | AB91: 205.07 | AD91: 55.68 | AE91: 100.22 | AF91: 314.22 | AG91: 3000 | AH91: 246.65 | AI91: 60 | AJ91: 35.97 | AK91: 470.12 | AL91: 159.08 | AM91: 214.84 | AN91: 164.27554 | AO91: SEITON
B92: SEI0016 | C92: Negrete Bejar Aide Sarai | D92: 15 | E92: 0 | F92: 154 | G92: 160.96 | H92: 2310 | I92: 0 | J92: 0 | K92: 2310 | L92: 0 | M92: -39.73 | N92: 57.34 | O92: 1188.73 | P92: 0 | R92: 0 | S92: 0 | T92: 0 | U92: 0.06 | V92: 1206.4 | W92: 1103.6 | X92: 15.09 | Y92: 27.16 | Z92: 15.09 | AA92: -174.78 | AB92: 135.05 | AD92: 42.25 | AE92: 76.05 | AF92: 300.79 | AG92: 2310 | AH92: 231.31 | AI92: 46.2 | AJ92: 27.3 | AK92: 419.09 | AL92: 120.72 | AM92: 207.16 | AN92: 126.49217 | AO92: SEITON
B93: SEI0031 | C93: Contreras Zetina Victor Hugo | D93: 15 | E93: 0 | F93: 230 | G93: 243.91 | H93: 3450 | I93: 0 | J93: 0 | K93: 3450 | L93: 128.93 | M93: 0 | N93: 86.9 | O93: 0 | P93: 0 | R93: 0 | S93: 0 | T93: 0 | U93: -0.03 | V93: 215.8 | W93: 3234.2 | X93: 22.87 | Y93: 41.16 | Z93: 22.87 | AA93: -125.1 | AB93: 254.03 | AD93: 64.03 | AE93: 115.25 | AF93: 322.57 | AG93: 3450 | AH93: 256.19 | AI93: 69 | AJ93: 41.37 | AK93: 501.85 | AL93: 182.93 | AM93: 219.61 | AN93: 188.91688 | AO93: SEITON
B94: SEI0037 | C94: Gomez Oliveros Alin | D94: 15 | E94: 0 | F94: 200 | G94: 212.11 | H94: 3000 | I94: 0 | J94: 0 | K94: 3000 | L94: 59.69 | M94: 0 | N94: 75.56 | O94: 0 | P94: 0 | R94: 0 | S94: 0 | T94: 0 | U94: -0.05 | V94: 135.2 | W94: 2864.8 | X94: 19.89 | Y94: 35.79 | Z94: 19.88 | AA94: -145.38 | AB94: 205.07 | AD94: 55.68 | AE94: 100.22 | AF94: 314.22 | AG94: 3000 | AH94: 246.65 | AI94: 60 | AJ94: 35.97 | AK94: 470.12 | AL94: 159.08 | AM94: 214.84 | AN94: 164.27554 | AO94: SEITON
B95: SEI0078 | C95: Aguilar Leal Karina Livier | D95: 15 | E95: 0 | F95: 266.67 | G95: 282.81 | H95: 4000.05 | I95: 0 | J95: 0 | K95: 4000.05 | L95: 313.87 | M95: 0 | N95: 102.51 | O95: 0 | P95: 0 | R95: 0 | S95: 0 | T95: 0 | U95: 0.07 | V95: 416.45 | W95: 3583.6 | X95: 26.51 | Y95: 47.72 | Z95: 28.28 | AA95: 0 | AB95: 313.87 | AD95: 74.24 | AE95: 133.63 | AF95: 337.62 | AG95: 4000.05 | AH95: 267.86 | AI95: 80 | AJ95: 47.96 | AK95: 545.49 | AL95: 212.11 | AM95: 225.44 | AN95: 219.0368 | AO95: SEITON
B96: SEI0079 | C96: Amezcua Contreras Martha Frine | D96: 15 | E96: 0 | F96: 566.67 | G96: 600.98 | H96: 8500.05 | I96: 0 | J96: 0 | K96: 8500.05 | L96: 1177.39 | M96: 0 | N96: 234.96 | O96: 0 | P96: 0 | R96: 0 | S96: 0 | T96: 0 | U96: 0.1 | V96: 1412.45 | W96: 7087.6 | X96: 56.34 | Y96: 101.42 | Z96: 77.2 | AA96: 0 | AB96: 1177.39 | AD96: 157.76 | AE96: 283.96 | AF96: 473.63 | AG96: 8500.05 | AH96: 363.31 | AI96: 170 | AJ96: 101.92 | AK96: 915.35 | AL96: 450.74 | AM96: 273.17 | AN96: 465.45011 | AO96: SEITON
B97: SEI0081 | C97: Guizar Perez Sergio | D97: 15 | E97: 0 | F97: 250 | G97: 265.14 | H97: 3750 | I97: 0 | J97: 0 | K97: 3750 | L97: 286.67 | M97: 0 | N97: 95.15 | O97: 0 | P97: 0 | R97: 0 | S97: 0 | T97: 0 | U97: -0.02 | V97: 381.8 | W97: 3368.2 | X97: 24.86 | Y97: 44.74 | Z97: 25.55 | AA97: 0 | AB97: 286.67 | AD97: 69.6 | AE97: 125.28 | AF97: 330.07 | AG97: 3750 | AH97: 262.56 | AI97: 75 | AJ97: 44.97 | AK97: 524.95 | AL97: 198.86 | AM97: 222.79 | AN97: 205.34443 | AO97: SEITON
B98: SEI0100 | C98: Quinto Valle Martin | D98: 15 | E98: 0 | F98: 333.33 | G98: 353.52 | H98: 4999.95 | I98: 0 | J98: 0 | K98: 4999.95 | L98: 461.63 | M98: 0 | N98: 131.95 | O98: 0 | P98: 0 | R98: 0 | S98: 0 | T98: 500 | U98: -0.03 | V98: 1093.55 | W98: 3906.4 | X98: 33.14 | Y98: 59.66 | Z98: 39.15 | AA98: 0 | AB98: 461.63 | AD98: 92.8 | AE98: 167.04 | AF98: 367.85 | AG98: 4999.95 | AH98: 289.08 | AI98: 100 | AJ98: 59.96 | AK98: 627.69 | AL98: 265.14 | AM98: 236.05 | AN98: 273.78984 | AO98: SEITON
B99: SEI0109 | C99: Negrete Renteria Jose Luis | D99: 15 | E99: 0 | F99: 281.67 | G99: 298.72 | H99: 4225.05 | I99: 0 | J99: 0 | K99: 4225.05 | L99: 338.35 | M99: 0 | N99: 109.14 | O99: 1642.17 | P99: 0 | R99: 0 | S99: 0 | T99: 0 | U99: -0.01 | V99: 2089.65 | W99: 2135.4 | X99: 28.01 | Y99: 50.41 | Z99: 30.72 | AA99: 0 | AB99: 338.35 | AD99: 78.41 | AE99: 141.15 | AF99: 344.43 | AG99: 4225.05 | AH99: 272.64 | AI99: 84.5 | AJ99: 50.66 | AK99: 563.99 | AL99: 224.04 | AM99: 227.83 | AN99: 231.35746 | AO99: SEITON
B100: SEI0126 | C100: Alonso Flores Beda | D100: 15 | E100: 0 | F100: 341.35 | G100: 357.25 | H100: 5120.25 | I100: 0 | J100: 0 | K100: 5120.25 | L100: 483.19 | M100: 0 | N100: 133.51 | O100: 0 | P100: 0 | R100: 0 | S100: 0 | T100: 0 | U100: 0.15 | V100: 616.85 | W100: 4503.4 | X100: 33.49 | Y100: 60.29 | Z100: 39.73 | AA100: 0 | AB100: 483.19 | AD100: 93.78 | AE100: 168.8 | AF100: 369.44 | AG100: 5120.25 | AH100: 290.19 | AI100: 102.41 | AJ100: 60.59 | AK100: 632.02 | AL100: 267.94 | AM100: 236.61 | AN100: 280.37729 | AO100: SEITON
B101: SEI0133 | C101: Romero Mayoral Lorenzo | D101: 13 | E101: 2 | F101: 266.67 | G101: 282.81 | H101: 3466.71 | I101: 533.34 | J101: 160 | K101: 4160.05 | L101: 313.87 | M101: 0 | N101: 102.51 | O101: 1090.32 | P101: 0 | R101: 0 | S101: 0 | T101: 0 | U101: -0.05 | V101: 1506.65 | W101: 2653.4 | X101: 26.51 | Y101: 47.72 | Z101: 28.28 | AA101: 0 | AB101: 313.87 | AD101: 74.24 | AE101: 133.63 | AF101: 337.62 | AG101: 4160.05 | AH101: 267.86 | AI101: 83.2 | AJ101: 47.96 | AK101: 545.49 | AL101: 212.11 | AM101: 225.44 | AN101: 219.0368 | AO101: SEITON
... B118: SEI0518 | C118: Amezcua Magaña Tania Estefania | D118: 15 | E118: 0 | F118: 233.33 | G118: 243.88 | H118: 3499.95 | I118: 0 | J118: 0 | K118: 3499.95 | L118: 134.36 | M118: 0 | N118: 86.88 | O118: 0 | P118: 0 | R118: 0 | S118: 0 | T118: 0 | U118: 0.11 | V118: 221.35 | W118: 3278.6 | X118: 22.86 | Y118: 41.15 | Z118: 22.87 | AA118: -125.1 | AB118: 259.46 | AD118: 64.02 | AE118: 115.23 | AF118: 322.56 | AG118: 3499.95 | AH118: 256.18 | AI118: 70 | AJ118: 41.36 | AK118: 501.81 | AL118: 182.91 | AM118: 219.6 | AN118: 191.65206 | AO118: SEITON
A119: Total SEITON | B119: =SUBTOTAL(9,B92:B118) -> 0 | C119: =SUBTOTAL(9,C92:C118) -> 0 | D119: =SUBTOTAL(9,D90:D118) -> 420 | E119: =SUBTOTAL(9,E90:E118) -> 14 | F119: =SUBTOTAL(9,F90:F118) -> 7798.06 | G119: =SUBTOTAL(9,G90:G118) -> 8237.53 | H119: =SUBTOTAL(9,H90:H118) -> 113936.7 | I119: =SUBTOTAL(9,I90:I118) -> 2834.15 | J119: =SUBTOTAL(9,J90:J118) -> 850.24 | K119: =SUBTOTAL(9,K90:K118) -> 117621.09 | ... AN119: =SUBTOTAL(9,AN90:AN118) -> 6405.1528 | AO119: =SUBTOTAL(9,AO92:AO118) -> 0
B120: Total Depto | D120: ----------------------- | E120: ----------------------- | F120: ----------------------- | G120: ----------------------- | H120: ----------------------- | I120: ----------------------- | J120: ----------------------- | K120: ----------------------- | L120: ----------------------- | M120: ----------------------- | N120: ----------------------- | O120: ----------------------- | P120: ----------------------- | Q120: ----------------------- | R120: ----------------------- | S120: ----------------------- | T120: ----------------------- | U120: ----------------------- | V120: ----------------------- | W120: ----------------------- | X120: ----------------------- | Y120: ----------------------- | Z120: ----------------------- | AA120: ----------------------- | AB120: ----------------------- | AD120: ----------------------- | AE120: ----------------------- | AF120: ----------------------- | AG120: ----------------------- | AH120: ----------------------- | AI120: ----------------------- | AJ120: ----------------------- | AK120: ----------------------- | AL120: ----------------------- | AM120: ----------------------- | AN120: -----------------------
B121: =SUM(B9:B120) -> 0 | C121: =SUM(C9:C120) -> 0 | D121: =+D89+D119 -> 1601 | E121: =+E89+E119 -> 20 | F121: =+F89+F119 -> 26931.83 | G121: =+G89+G119 -> 28414.15 | H121: =+H89+H119 -> 397676.68 | I121: =+I89+I119 -> 4500.82 | J121: =+J89+J119 -> 3178.43 | K121: =+K89+K119 -> 405355.93 | ... AO121: =+AO89+AO119 -> 0
J122: FACTURACION PITS | L122: FACTURACION SEITON
B123: 107 | C123: Nomina | J123: Devengado Salario | K123: =+W89 -> 224113 | L123: Devengado Salario | M123: =+W119 -> 95217.2
B124: 2 | C124: Altas | J124: Retornos | K124: =+S89 -> 7146.18 | L124: Retornos | M124: =+S119 -> 0
B125: 0 | C125: Bajas | J125: Infonavit | K125: =+O89+P89+Q89 -> 28576.72 | L125: Infonavit | M125: =+O119+P119+Q119 -> 10618.88
B126: =+B123+B124-B125 -> 109 | C126: Total Nomina | J126: Prestamo Fonacot | K126: =+R89 -> 4763.93 | L126: Prestamo Fonacot | M126: =+R119 -> 0
J127: aportacion voluntaria | K127: =+T89 -> 0 | L127: aportacion voluntaria | M127: =+T119 -> 500
J128: Subtotal 1 | K128: =SUM(K123:K127) -> 264599.83 | L128: Subtotal 1 | M128: =SUM(M123:M127) -> 106336.08
J129: Comision | K129: =+K128*2% -> 5291.9966 | L129: Comision | M129: =+M128*2% -> 2126.7216
J130: Subtotal 2 | K130: =+K128+K129 -> 269891.83 | L130: Subtotal 2 | M130: =+M128+M129 -> 108462.8
J131: Costo Patronal Imss | K131: =+N89+AD89+AE89+AF89+AH89+AJ89+AM89+AL89 -> 104995.27 | L131: Costo Patronal Imss | M131: =+N119+AD119+AE119+AF119+AH119+AL119+AJ119+AM119 -> 40838.85
J132: 2% Sobre Nomina | K132: =+K89*2% -> 5754.6968 | L132: 2% Sobre Nomina | M132: =+K119*2% -> 2352.4218
J133: Importe de Factura | K133: =+K130+K131+K132 -> 380641.79 | L133: Importe de Factura | M133: =+M130+M131+M132 -> 151654.07
J134: certificacion de cheque | K134: 0 | L134: certificacion de cheque | M134: 0
J135: IVA | K135: =(+K133+K134)*0.16 -> 60902.687 | L135: IVA | M135: =(+M133+M134)*0.16 -> 24264.652
J136: TOTAL | K136: =+K133+K134+K135 -> 441544.48 | L136: TOTAL | M136: =+M133+M134+M135 -> 175918.73
J137: PROVISION DE AGUINALDO
J138: FACTURACION PITS | L138: FACTURACION SEITON
J139: Subtotal 1 | K139: =+AN89 -> 15716.052 | L139: Subtotal 1 | M139: =+AN119 -> 6405.1528
J140: Comision | K140: =+K139*2% -> 314.32105 | L140: Comision | M140: =+M139*2% -> 128.10306
J141: Subtotal 2 | K141: =+K139+K140 -> 16030.374 | L141: Subtotal 2 | M141: =+M139+M140 -> 6533.2558
J142: 2% Sobre Nomina | K142: =+K139*2% -> 314.32105 | L142: 2% Sobre Nomina | M142: =+M139*2% -> 128.10306
J143: Importe de Factura | K143: =+K141+K142 -> 16344.695 | L143: Importe de Factura | M143: =+M141+M142 -> 6661.3589
J144: IVA | K144: =+K143*16% -> 2615.1511 | L144: IVA | M144: =+M143*16% -> 1065.8174
J145: TOTAL | K145: =+K143+K144 -> 18959.846 | L145: TOTAL | M145: =+M143+M144 -> 7727.1763

Sheet SINDICATO
A5: 1 | B5: 2 | C5: 3 | F5: 4 | G5: 5 | H5: 6
A6: CLAVE | B6: EMPRESA | C6: NOMBRE | F6: PAGO POR SINDICATO | G6: comision y bono | H6: prima vacaciones | I6: TOTAL | J6: DIAS DE VACACIONES | K6: SUELDO NETO MENSUAL | L6: MONTO PRIMA TOTAL | M6: MENOS PRIMA IMSS | N6: PRIMA A PAGAR SINDICATO | Q6: FACTURACION
A7: SEI0097 | B7: SEITON - (CONSULTORIA II) | C7: Arreola Jimenez Jose Nieves | F7: 1557.91 | G7: 432.22 | H7: =+N7 -> 0 | I7: =+F7+G7+H7 -> 1990.13 | J7: =VLOOKUP(C7,CPD!$B$9:$D$37,3,0) -> 0 | K7: =VLOOKUP(C7,RESUMEN!$C$4:$L$121,10,) -> 10150 | L7: =(((+K7/30)*J7)*30%) -> 0 | M7: =VLOOKUP(C7,CPD!$B$9:$I$37,8,0) -> 0 | N7: =+L7-M7 -> 0 | O7: =VLOOKUP(C7,RESUMEN!$C$4:$Z$133,24,0) -> 0 | Q7: PITSS
A8: SEI0118 | B8: SEITON - (CONSULTORIA II) | C8: Arroyo Ramirez Hector Hugo | F8: 2102.87 | G8: 200 | H8: =+N8 -> 234.01 | I8: =+F8+G8+H8 -> 2536.88 | J8: 4 | K8: =VLOOKUP(C8,RESUMEN!$C$4:$L$121,10,) -> 13000 | L8: =(((+K8/30)*J8)*30%) -> 520 | M8: =VLOOKUP(C8,CPD!$B$9:$I$37,8,0) -> 285.99 | N8: =+L8-M8 -> 234.01 | O8: =VLOOKUP(C8,RESUMEN!$C$4:$Z$133,24,0) -> 0 | Q8: PITSS
A9: SEI0039 | B9: SEITON - (CONSULTORIA II) | C9: Benavides Herrera Pablo | F9: 23772.6 | H9: =+N9 -> 0 | I9: =+F9+G9+H9 -> 23772.6 | J9: =VLOOKUP(C9,CPD!$B$9:$D$37,3,0) -> 0 | K9: =VLOOKUP(C9,RESUMEN!$C$4:$L$121,10,) -> 70000 | L9: =(((+K9/30)*J9)*30%) -> 0 | M9: =VLOOKUP(C9,CPD!$B$9:$I$37,8,0) -> 0 | N9: =+L9-M9 -> 0 | O9: =VLOOKUP(C9,RESUMEN!$C$4:$Z$133,24,0) -> 0 | Q9: PITSS
A10: SEI0108 | B10: SEITON - (CONSULTORIA II) | C10: Caballero Diaz Francisco Javier | F10: 1558.18 | G10: 366.93 | H10: =+N10 -> 0 | I10: =+F10+G10+H10 -> 1925.11 | J10: =VLOOKUP(C10,CPD!$B$9:$D$37,3,0) -> 0 | K10: =VLOOKUP(C10,RESUMEN!$C$4:$L$121,10,) -> 10150 | L10: =(((+K10/30)*J10)*30%) -> 0 | M10: =VLOOKUP(C10,CPD!$B$9:$I$37,8,0) -> 0 | N10: =+L10-M10 -> 0 | O10: =VLOOKUP(C10,RESUMEN!$C$4:$Z$133,24,0) -> 0 | Q10: PITSS
A11: SEI0425 | B11: SEITON - (CONSULTORIA II) | C11: Carbajal Cabuto Jose Luis | F11: 1608.12 | G11: =297.08+480 -> 777.08 | H11: =+N11 -> 0 | I11: =+F11+G11+H11 -> 2385.2 | J11: =VLOOKUP(C11,CPD!$B$9:$D$37,3,0) -> 0 | K11: =VLOOKUP(C11,RESUMEN!$C$4:$L$121,10,) -> 10250 | L11: =(((+K11/30)*J11)*30%) -> 0 | M11: =VLOOKUP(C11,CPD!$B$9:$I$37,8,0) -> 0 | N11: =+L11-M11 -> 0 | O11: =VLOOKUP(C11,RESUMEN!$C$4:$Z$133,24,0) -> 0 | Q11: PITSS
A12: SEI0116 | B12: SEITON - (CONSULTORIA II) | C12: Casillas Cardona Cesar Alejandro | F12: 1891.03 | H12: =+N12 -> 0 | I12: =+F12+G12+H12 -> 1891.03 | J12: =VLOOKUP(C12,CPD!$B$9:$D$37,3,0) -> 0 | K12: =VLOOKUP(C12,RESUMEN!$C$4:$L$121,10,) -> 12000 | L12: =(((+K12/30)*J12)*30%) -> 0 | M12: =VLOOKUP(C12,CPD!$B$9:$I$37,8,0) -> 0 | N12: =+L12-M12 -> 0 | O12: =VLOOKUP(C12,RESUMEN!$C$4:$Z$133,24,0) -> 0 | Q12: PITSS
A13: SEI0010 | B13: SEITON - (CONSULTORIA II) | C13: Compean Tobias Braulio Gerardo | F13: 3645.92 | G13: 2000 | H13: =+N13 -> 0 | I13: =+F13+G13+H13 -> 5645.92 | J13: =VLOOKUP(C13,CPD!$B$9:$D$37,3,0) -> 0 | K13: =VLOOKUP(C13,RESUMEN!$C$4:$L$121,10,) -> 18000 | L13: =(((+K13/30)*J13)*30%) -> 0 | M13: =VLOOKUP(C13,CPD!$B$9:$I$37,8,0) -> 0 | N13: =+L13-M13 -> 0 | O13: =VLOOKUP(C13,RESUMEN!$C$4:$Z$133,24,0) -> 0 | Q13: SEITON
A14: SEI0401 | B14: SEITON - (CONSULTORIA II) | C14: De La Torre Zambara Francisco Ernesto | F14: 1558 | G14: 393.43 | H14: =+N14 -> 0 | I14: =+F14+G14+H14 -> 1951.43 | J14: =VLOOKUP(C14,CPD!$B$9:$D$37,3,0) -> 0 | K14: =VLOOKUP(C14,RESUMEN!$C$4:$L$121,10,) -> 10150 | L14: =(((+K14/30)*J14)*30%) -> 0 | M14: =VLOOKUP(C14,CPD!$B$9:$I$37,8,0) -> 0 | N14: =+L14-M14 -> 0 | O14: =VLOOKUP(C14,RESUMEN!$C$4:$Z$133,24,0) -> 0 | Q14: PITSS
A15: SEI0147 | B15: SEITON - (CONSULTORIA II) | C15: Diaz Munguia Martha Liliana | F15: 7009.15 | H15: =+N15 -> 0 | I15: =+F15+G15+H15 -> 7009.15 | J15: =VLOOKUP(C15,CPD!$B$9:$D$37,3,0) -> 0 | K15: =VLOOKUP(C15,RESUMEN!$C$4:$L$121,10,) -> 25000 | L15: =(((+K15/30)*J15)*30%) -> 0 | M15: =VLOOKUP(C15,CPD!$B$9:$I$37,8,0) -> 0 | N15: =+L15-M15 -> 0 | O15: =VLOOKUP(C15,RESUMEN!$C$4:$Z$133,24,0) -> 0 | Q15: SEITON
A16: SEI0119 | B16: SEITON - (CONSULTORIA II) | C16: Dominguez Lopez Maria De Jesus | F16: 2102.95 | H16: =+N16 -> 0 | I16: =+F16+G16+H16 -> 2102.95 | J16: =VLOOKUP(C16,CPD!$B$9:$D$37,3,0) -> 0 | K16: 13000 | L16: =(((+K16/30)*J16)*30%) -> 0 | M16: =VLOOKUP(C16,CPD!$B$9:$I$37,8,0) -> 0 | N16: =+L16-M16 -> 0 | O16: =VLOOKUP(C16,RESUMEN!$C$4:$Z$133,24,0) -> 0 | Q16: SEITON
A17: SEI0099 | B17: SEITON - (CONSULTORIA II) | C17: Garcia Villicaña Ricardo Pascual | F17: 2600.4 | G17: =141.47+750 -> 891.47 | H17: =+N17 -> 68 | I17: =+F17+G17+H17 -> 3559.87 | J17: =VLOOKUP(C17,CPD!$B$9:$D$37,3,0) -> 1 | K17: =VLOOKUP(C17,RESUMEN!$C$4:$L$121,10,) -> 15000 | L17: =(((+K17/30)*J17)*30%) -> 150 | M17: =VLOOKUP(C17,CPD!$B$9:$I$37,8,0) -> 82 | N17: =+L17-M17 -> 68 | O17: =VLOOKUP(C17,RESUMEN!$C$4:$Z$133,24,0) -> 0 | Q17: PITSS
A18: SEI0009 | B18: SEITON - (CONSULTORIA II) | C18: Gutierrez Gutierrez Luis Arturo | F18: 1475.6 | G18: 304.07 | H18: =+N18 -> 0 | I18: =+F18+G18+H18 -> 1779.67 | J18: =VLOOKUP(C18,CPD!$B$9:$D$37,3,0) -> 0 | K18: =VLOOKUP(C18,RESUMEN!$C$4:$L$121,10,) -> 8500 | L18: =(((+K18/30)*J18)*30%) -> 0 | M18: =VLOOKUP(C18,CPD!$B$9:$I$37,8,0) -> 0 | N18: =+L18-M18 -> 0 | O18: =VLOOKUP(C18,RESUMEN!$C$4:$Z$133,24,0) -> 0 | Q18: PITSS
A19: SEI0127 | B19: SEITON - (CONSULTORIA II) | C19: Hernandez Ochoa Eduardo | F19: 2600.2 | G19: 371.43 | H19: =+N19 -> 0 | I19: =+F19+G19+H19 -> 2971.63 | J19: =VLOOKUP(C19,CPD!$B$9:$D$37,3,0) -> 0 | K19: =VLOOKUP(C19,RESUMEN!$C$4:$L$121,10,) -> 15000 | L19: =(((+K19/30)*J19)*30%) -> 0 | M19: =VLOOKUP(C19,CPD!$B$9:$I$37,8,0) -> 0 | N19: =+L19-M19 -> 0 | O19: =VLOOKUP(C19,RESUMEN!$C$4:$Z$133,24,0) -> 0 | Q19: PITSS
A20: SEI0117 | B20: SEITON - (CONSULTORIA II) | C20: Mariscal Romero Luis Adrian | F20: 2751.04 | G20: 150 | H20: =+N20 -> 0 | I20: =+F20+G20+H20 -> 2901.04 | J20: =VLOOKUP(C20,CPD!$B$9:$D$37,3,0) -> 0 | K20: =VLOOKUP(C20,RESUMEN!$C$4:$L$121,10,) -> 15000 | L20: =(((+K20/30)*J20)*30%) -> 0 | M20: =VLOOKUP(C20,CPD!$B$9:$I$37,8,0) -> 0 | N20: =+L20-M20 -> 0 | O20: =VLOOKUP(C20,RESUMEN!$C$4:$Z$133,24,0) -> 0 | Q20: PITSS
A21: SEI0040 | B21: SEITON - (CONSULTORIA II) | C21: Mora Ramirez Acal Aldo Isidro | F21: 2464 | H21: =+N21 -> 0 | I21: =+F21+G21+H21 -> 2464 | J21: =VLOOKUP(C21,CPD!$B$9:$D$37,3,0) -> 0 | K21: =VLOOKUP(C21,RESUMEN!$C$4:$L$121,10,) -> 13000 | L21: =(((+K21/30)*J21)*30%) -> 0 | M21: =VLOOKUP(C21,CPD!$B$9:$I$37,8,0) -> 0 | N21: =+L21-M21 -> 0 | O21: =VLOOKUP(C21,RESUMEN!$C$4:$Z$133,24,0) -> 0 | Q21: PITSS
A22: SEI0088 | B22: SEITON - (CONSULTORIA II) | C22: Morgado Fernandez Martin | F22: 2600.4 | G22: 356.25 | H22: =+N22 -> 0 | I22: =+F22+G22+H22 -> 2956.65 | J22: =VLOOKUP(C22,CPD!$B$9:$D$37,3,0) -> 0 | K22: =VLOOKUP(C22,RESUMEN!$C$4:$L$121,10,) -> 15000 | L22: =(((+K22/30)*J22)*30%) -> 0 | M22: =VLOOKUP(C22,CPD!$B$9:$I$37,8,0) -> 0 | N22: =+L22-M22 -> 0 | O22: =VLOOKUP(C22,RESUMEN!$C$4:$Z$133,24,0) -> 0 | Q22: PITSS
A23: SEI0173 | B23: SEITON - (CONSULTORIA II) | C23: Nieto Ortiz Jose Luis | F23: 1483.06 | G23: 103.16 | H23: =+N23 -> 0 | I23: =+F23+G23+H23 -> 1586.22 | J23: =VLOOKUP(C23,CPD!$B$9:$D$37,3,0) -> 0 | K23: =VLOOKUP(C23,RESUMEN!$C$4:$L$121,10,) -> 10000 | L23: =(((+K23/30)*J23)*30%) -> 0 | M23: =VLOOKUP(C23,CPD!$B$9:$I$37,8,0) -> 0 | N23: =+L23-M23 -> 0 | O23: =VLOOKUP(C23,RESUMEN!$C$4:$Z$133,24,0) -> 0 | Q23: PITSS
A24: SEI0026 | B24: SEITON - (CONSULTORIA II) | C24: Patricio Aguilar Jhonattan Cristian | F24: 1588.2 | G24: 400 | H24: =+N24 -> 0 | I24: =+F24+G24+H24 -> 1988.2 | J24: =VLOOKUP(C24,CPD!$B$9:$D$37,3,0) -> 0 | K24: =VLOOKUP(C24,RESUMEN!$C$4:$L$121,10,) -> 9000 | L24: =(((+K24/30)*J24)*30%) -> 0 | M24: =VLOOKUP(C24,CPD!$B$9:$I$37,8,0) -> 0 | N24: =+L24-M24 -> 0 | O24: =VLOOKUP(C24,RESUMEN!$C$4:$Z$133,24,0) -> 0 | Q24: PITSS
A25: SEI0221 | B25: SEITON - (CONSULTORIA II) | C25: Rogel Teran Marco Antonio | F25: 12613.2 | H25: =+N25 -> 0 | I25: =+F25+G25+H25 -> 12613.2 | J25: =VLOOKUP(C25,CPD!$B$9:$D$37,3,0) -> 0 | K25: =VLOOKUP(C25,RESUMEN!$C$4:$L$121,10,) -> 60000 | L25: =(((+K25/30)*J25)*30%) -> 0 | M25: =VLOOKUP(C25,CPD!$B$9:$I$37,8,0) -> 0 | N25: =+L25-M25 -> 0 | O25: =VLOOKUP(C25,RESUMEN!$C$4:$Z$133,24,0) -> 0 | Q25: PITSS
A26: SEI0222 | B26: SEITON - (CONSULTORIA II) | C26: Saucedo Duran Jesus Alfredo | F26: 1891.2 | H26: =+N26 -> 0 | I26: =+F26+G26+H26 -> 1891.2 | J26: =VLOOKUP(C26,CPD!$B$9:$D$37,3,0) -> 0 | K26: =VLOOKUP(C26,RESUMEN!$C$4:$L$121,10,) -> 12000 | L26: =(((+K26/30)*J26)*30%) -> 0 | M26: =VLOOKUP(C26,CPD!$B$9:$I$37,8,0) -> 0 | N26: =+L26-M26 -> 0 | O26: =VLOOKUP(C26,RESUMEN!$C$4:$Z$133,24,0) -> 0 | Q26: PITSS
A27: SEI0041 | B27: SEITON - (CONSULTORIA II) | C27: Vazquez Perez Miguel Angel | F27: 4176 | H27: =+N27 -> 0 | I27: =+F27+G27+H27 -> 4176 | J27: =VLOOKUP(C27,CPD!$B$9:$D$37,3,0) -> 0 | K27: =VLOOKUP(C27,RESUMEN!$C$4:$L$121,10,) -> 18500 | L27: =(((+K27/30)*J27)*30%) -> 0 | M27: =VLOOKUP(C27,CPD!$B$9:$I$37,8,0) -> 0 | N27: =+L27-M27 -> 0 | O27: =VLOOKUP(C27,RESUMEN!$C$4:$Z$133,24,0) -> 0 | Q27: PITSS
A28: SEI0377 | B28: SEITON - (CONSULTORIA II) | C28: Benavides Herrera Alejandra | F28: 16803.4 | H28: =+N28 -> 0 | I28: =+F28+G28+H28 -> 16803.4 | J28: =VLOOKUP(C28,CPD!$B$9:$D$37,3,0) -> 0 | K28: =VLOOKUP(C28,RESUMEN!$C$4:$L$121,10,) -> 40000 | L28: =(((+K28/30)*J28)*30%) -> 0 | M28: =VLOOKUP(C28,CPD!$B$9:$I$37,8,0) -> 0 | N28: =+L28-M28 -> 0 | O28: =VLOOKUP(C28,RESUMEN!$C$4:$Z$133,24,0) -> 0 | Q28: PITSS
A29: SEI032 | B29: SEITON - (CONSULTORIA II) | C29: Camarena Quiroz Erick Frank | F29: 1588 | H29: =+N29 -> 0 | I29: =+F29+G29+H29 -> 1588 | J29: =VLOOKUP(C29,CPD!$B$9:$D$37,3,0) -> 0 | K29: =VLOOKUP(C29,RESUMEN!$C$4:$L$121,10,) -> 9000 | L29: =(((+K29/30)*J29)*30%) -> 0 | M29: =VLOOKUP(C29,CPD!$B$9:$I$37,8,0) -> 0 | N29: =+L29-M29 -> 0 | O29: =VLOOKUP(C29,RESUMEN!$C$4:$Z$133,24,0) -> 0 | Q29: SEITON
A30: SEI0437 | B30: SEITON - (CONSULTORIA II) | C30: Leal Montaño Diego | F30: 1803.28 | G30: =1810+1000 -> 2810 | H30: =+N30 -> 100 | I30: =+F30+G30+H30 -> 4713.28 | J30: =VLOOKUP(C30,CPD!$B$9:$D$37,3,0) -> 2 | K30: =VLOOKUP(C30,RESUMEN!$C$4:$L$121,10,) -> 10000 | L30: =(((+K30/30)*J30)*30%) -> 200 | M30: =VLOOKUP(C30,CPD!$B$9:$I$37,8,0) -> 100 | N30: =+L30-M30 -> 100 | O30: =VLOOKUP(C30,RESUMEN!$C$4:$Z$133,24,0) -> 0 | Q30: SEITON
A31: SEI0440 | B31: SEITON - (CONSULTORIA II) | C31: Leija Arevalo Guadalupe | F31: 0 | H31: =+N31 -> 0 | I31: =+F31+G31+H31 -> 0 | J31: =VLOOKUP(C31,CPD!$B$9:$D$37,3,0) -> 0 | K31: =VLOOKUP(C31,RESUMEN!$C$4:$L$121,10,) -> 4000 | L31: =(((+K31/30)*J31)*30%) -> 0 | M31: =VLOOKUP(C31,CPD!$B$9:$I$37,8,0) -> 0 | N31: =+L31-M31 -> 0 | O31: =VLOOKUP(C31,RESUMEN!$C$4:$Z$133,24,0) -> -23.75 | Q31: PITSS
A32: SEI0442 | B32: SEITON - (CONSULTORIA II) | C32: Sierra Escamilla Daniela | F32: 2464 | H32: =+N32 -> 0 | I32: =+F32+G32+H32 -> 2464 | J32: =VLOOKUP(C32,CPD!$B$9:$D$37,3,0) -> 0 | K32: =VLOOKUP(C32,RESUMEN!$C$4:$L$121,10,) -> 13000 | L32: =(((+K32/30)*J32)*30%) -> 0 | M32: =VLOOKUP(C32,CPD!$B$9:$I$37,8,0) -> 0 | N32: =+L32-M32 -> 0 | O32: =VLOOKUP(C32,RESUMEN!$C$4:$Z$133,24,0) -> 0 | Q32: PITSS
A33: SEI0445 | B33: SEITON - (CONSULTORIA II) | C33: Muñoz Melgoza Gabriel | F33: 3090.6 | G33: 616 | H33: =+N33 -> 0 | I33: =+F33+G33+H33 -> 3706.6 | J33: =VLOOKUP(C33,CPD!$B$9:$D$37,3,0) -> 0 | K33: 15400 | M33: =VLOOKUP(C33,CPD!$B$9:$I$37,8,0) -> 0 | O33: =VLOOKUP(C33,RESUMEN!$C$4:$Z$133,24,0) -> 0 | Q33: PITSS
A34: SEI0447 | B34: SEITON - (CONSULTORIA II) | C34: Oliver Olague Vicente | F34: 3286.8 | H34: =+N34 -> 0 | I34: =+F34+G34+H34 -> 3286.8 | J34: =VLOOKUP(C34,CPD!$B$9:$D$37,3,0) -> 0 | K34: 17000 | M34: =VLOOKUP(C34,CPD!$B$9:$I$37,8,0) -> 0 | O34: =VLOOKUP(C34,RESUMEN!$C$4:$Z$133,24,0) -> 0 | Q34: SEITON
A35: SEI0448 | B35: SEITON - (CONSULTORIA II) | C35: Rodriguez Chavez Oswaldo Emmanuel | F35: 2672.6 | G35: 1200 | H35: =+N35 -> 0 | I35: =+F35+G35+H35 -> 3872.6 | J35: =VLOOKUP(C35,CPD!$B$9:$D$37,3,0) -> 0 | K35: 14000 | M35: =VLOOKUP(C35,CPD!$B$9:$I$37,8,0) -> 0 | O35: =VLOOKUP(C35,RESUMEN!$C$4:$Z$133,24,0) -> -1200
A36: SEI0482 | B36: SEITON (IP INNOVA II) | C36: Camarillo Canela Reynaldo | F36: 2219.28 | G36: =1000+480 -> 1480 | H36: =+N36 -> 295.76 | I36: =+F36+G36+H36 -> 3995.04 | J36: =VLOOKUP(C36,IP!$B$9:$D$117,3,0) -> 7 | K36: =VLOOKUP(C36,RESUMEN!$C$35:$L$137,10,0) -> 9800 | L36: =(((+K36/30)*J36)*30%) -> 686 | M36: =VLOOKUP(C36,IP!$B$9:$I$117,8,0) -> 390.24 | N36: =+L36-M36 -> 295.76 | O36: =VLOOKUP(C36,RESUMEN!$C$35:$Z$141,24,0) -> 0.04 | Q36: SEITON
A37: SEI0483 | B37: SEITON (IP INNOVA II) | C37: Gutierrez Muñoz Carlos Alejandro | F37: 2884.99 | H37: =+N37 -> 0 | I37: =+F37+G37+H37 -> 2884.99 | J37: =VLOOKUP(C37,IP!$B$9:$D$117,3,0) -> 0 | K37: =VLOOKUP(C37,RESUMEN!$C$35:$L$137,10,0) -> 12000 | L37: =(((+K37/30)*J37)*30%) -> 0 | M37: =VLOOKUP(C37,IP!$B$9:$I$117,8,0) -> 0 | N37: =+L37-M37 -> 0 | O37: =VLOOKUP(C37,RESUMEN!$C$35:$Z$141,24,0) -> 0 | Q37: PITSS
A38: SEI0485 | B38: SEITON (IP INNOVA II) | C38: Molina Ramirez Gerardo Daniel | F38: 2262.25 | G38: 333.34 | H38: =+N38 -> 0 | I38: =+F38+G38+H38 -> 2595.59 | J38: =VLOOKUP(C38,IP!$B$9:$D$117,3,0) -> 0 | K38: =VLOOKUP(C38,RESUMEN!$C$35:$L$137,10,0) -> 9000 | L38: =(((+K38/30)*J38)*30%) -> 0 | M38: =VLOOKUP(C38,IP!$B$9:$I$117,8,0) -> 0 | N38: =+L38-M38 -> 0 | O38: =VLOOKUP(C38,RESUMEN!$C$35:$Z$141,24,0) -> 0 | Q38: PITSS
A39: SEI0488 | B39: SEITON (IP INNOVA II) | C39: Mireles Casillas Brenda Cristina | F39: 2262.2 | H39: =+N39 -> 0 | I39: =+F39+G39+H39 -> 2262.2 | J39: =VLOOKUP(C39,IP!$B$9:$D$117,3,0) -> 0 | K39: =VLOOKUP(C39,RESUMEN!$C$35:$L$137,10,0) -> 9000 | L39: =(((+K39/30)*J39)*30%) -> 0 | M39: =VLOOKUP(C39,IP!$B$9:$I$117,8,0) -> 0 | N39: =+L39-M39 -> 0 | O39: =VLOOKUP(C39,RESUMEN!$C$35:$Z$141,24,0) -> 0 | Q39: PITSS
A40: SEI0489 | B40: SEITON (IP INNOVA II) | C40: Escobedo Olivares Juan Guadalupe | F40: 3721.2 | G40: 166.67 | H40: =+N40 -> 0 | I40: =+F40+G40+H40 -> 3887.87 | J40: =VLOOKUP(C40,IP!$B$9:$D$117,3,0) -> 0 | K40: =VLOOKUP(C40,RESUMEN!$C$35:$L$137,10,0) -> 14000 | L40: =(((+K40/30)*J40)*30%) -> 0 | M40: =VLOOKUP(C40,IP!$B$9:$I$117,8,0) -> 0 | N40: =+L40-M40 -> 0 | O40: =VLOOKUP(C40,RESUMEN!$C$35:$Z$141,24,0) -> 0 | Q40: PITSS
A41: SEI0490 | B41: SEITON (IP INNOVA II) | C41: Castillo Ramirez Hector Ivan | F41: 3721.3 | G41: 208.34 | H41: =+N41 -> 0 | I41: =+F41+G41+H41 -> 3929.64 | J41: =VLOOKUP(C41,IP!$B$9:$D$117,3,0) -> 0 | K41: =VLOOKUP(C41,RESUMEN!$C$35:$L$137,10,0) -> 14000 | L41: =(((+K41/30)*J41)*30%) -> 0 | M41: =VLOOKUP(C41,IP!$B$9:$I$117,8,0) -> 0 | N41: =+L41-M41 -> 0 | O41: =VLOOKUP(C41,RESUMEN!$C$35:$Z$141,24,0) -> 0 | Q41: PITSS
A42: SEI0493 | B42: SEITON (IP INNOVA II) | C42: Martinez Morales Tomas | F42: 3339.44 | G42: 168.75 | H42: =+N42 -> 0 | I42: =+F42+G42+H42 -> 3508.19 | J42: =VLOOKUP(C42,IP!$B$9:$D$117,3,0) -> 0 | K42: =VLOOKUP(C42,RESUMEN!$C$35:$L$137,10,0) -> 15000 | L42: =(((+K42/30)*J42)*30%) -> 0 | M42: =VLOOKUP(C42,IP!$B$9:$I$117,8,0) -> 0 | N42: =+L42-M42 -> 0 | O42: =VLOOKUP(C42,RESUMEN!$C$35:$Z$141,24,0) -> 0 | Q42: PITSS
A43: SEI0494 | B43: SEITON (IP INNOVA II) | C43: Medellin Colunga Ruben Dario | F43: 4339.38 | G43: =267.86+1928 -> 2195.86 | H43: =+N43 -> 0 | I43: =+F43+G43+H43 -> 6535.24 | J43: =VLOOKUP(C43,IP!$B$9:$D$117,3,0) -> 0 | K43: =VLOOKUP(C43,RESUMEN!$C$35:$L$137,10,0) -> 17000 | L43: =(((+K43/30)*J43)*30%) -> 0 | M43: =VLOOKUP(C43,IP!$B$9:$I$117,8,0) -> 0 | N43: =+L43-M43 -> 0 | O43: =VLOOKUP(C43,RESUMEN!$C$35:$Z$141,24,0) -> 0 | Q43: PITSS
A44: SEI0495 | B44: SEITON (IP INNOVA II) | C44: Torres Perez Carlos Alberto | F44: =1667.4+250 -> 1917.4 | G44: =1071.43+3788 -> 4859.43 | H44: =+N44 -> 0 | I44: =+F44+G44+H44 -> 6776.83 | J44: =VLOOKUP(C44,IP!$B$9:$D$117,3,0) -> 0 | K44: =VLOOKUP(C44,RESUMEN!$C$35:$L$137,10,0) -> 10500 | L44: =(((+K44/30)*J44)*30%) -> 0 | M44: =VLOOKUP(C44,IP!$B$9:$I$117,8,0) -> 0 | N44: =+L44-M44 -> 0 | O44: =VLOOKUP(C44,RESUMEN!$C$35:$Z$141,24,0) -> 0 | Q44: PITSS
A45: SEI0496 | B45: SEITON (IP INNOVA II) | C45: Velazquez Herrera Nayeli | F45: 3339.4 | H45: =+N45 -> 0 | I45: =+F45+G45+H45 -> 3339.4 | J45: =VLOOKUP(C45,IP!$B$9:$D$117,3,0) -> 0 | K45: =VLOOKUP(C45,RESUMEN!$C$35:$L$137,10,0) -> 15000 | L45: =(((+K45/30)*J45)*30%) -> 0 | M45: =VLOOKUP(C45,IP!$B$9:$I$117,8,0) -> 0 | N45: =+L45-M45 -> 0 | O45: =VLOOKUP(C45,RESUMEN!$C$35:$Z$141,24,0) -> 0 | Q45: SEITON
A46: SEI0497 | B46: SEITON (IP INNOVA II) | C46: Treviño Alvarez Jorge Alberto | F46: 2667.33 | G46: 2060.4 | H46: =+N46 -> 0 | I46: =+F46+G46+H46 -> 4727.73 | J46: =VLOOKUP(C46,IP!$B$9:$D$117,3,0) -> 0 | K46: =VLOOKUP(C46,RESUMEN!$C$35:$L$137,10,0) -> 12000 | L46: =(((+K46/30)*J46)*30%) -> 0 | M46: =VLOOKUP(C46,IP!$B$9:$I$117,8,0) -> 0 | N46: =+L46-M46 -> 0 | O46: =VLOOKUP(C46,RESUMEN!$C$35:$Z$141,24,0) -> 0 | Q46: PITSS
A47: SEI0498 | B47: SEITON (IP INNOVA II) | C47: Tenorio Alvarez Alberto Antonio | F47: 1667.57 | G47: 503.94 | H47: =+N47 -> 226.79 | I47: =+F47+G47+H47 -> 2398.3 | J47: 8 | K47: =VLOOKUP(C47,RESUMEN!$C$35:$L$137,10,0) -> 10000 | L47: =(((+K47/30)*J47)*30%) -> 800 | M47: =VLOOKUP(C47,IP!$B$9:$I$117,8,0) -> 573.21 | N47: =+L47-M47 -> 226.79 | O47: =VLOOKUP(C47,RESUMEN!$C$35:$Z$141,24,0) -> 0 | Q47: PITSS
A48: SEI0499 | B48: SEITON (IP INNOVA II) | C48: Chavez Dominguez Salvador | F48: 2667.4 | G48: 1054.35 | H48: =+N48 -> 0 | I48: =+F48+G48+H48 -> 3721.75 | J48: =VLOOKUP(C48,IP!$B$9:$D$117,3,0) -> 0 | K48: =VLOOKUP(C48,RESUMEN!$C$35:$L$137,10,0) -> 12000 | L48: =(((+K48/30)*J48)*30%) -> 0 | M48: =VLOOKUP(C48,IP!$B$9:$I$117,8,0) -> 0 | N48: =+L48-M48 -> 0 | O48: =VLOOKUP(C48,RESUMEN!$C$35:$Z$141,24,0) -> 0 | Q48: PITSS
A49: SEI0501 | B49: SEITON (IP INNOVA II) | C49: Cruz Herrera Roberto | F49: 1667.43 | G49: 309.43 | H49: =+N49 -> 0 | I49: =+F49+G49+H49 -> 1976.86 | J49: =VLOOKUP(C49,IP!$B$9:$D$117,3,0) -> 0 | K49: =VLOOKUP(C49,RESUMEN!$C$35:$L$137,10,0) -> 10000 | L49: =(((+K49/30)*J49)*30%) -> 0 | M49: =VLOOKUP(C49,IP!$B$9:$I$117,8,0) -> 0 | N49: =+L49-M49 -> 0 | O49: =VLOOKUP(C49,RESUMEN!$C$35:$Z$141,24,0) -> 0 | Q49: PITSS
A50: SEI0502 | B50: SEITON (IP INNOVA II) | C50: Dominguez Escamilla Victor Hugo | F50: 2667.48 | H50: =+N50 -> 0 | I50: =+F50+G50+H50 -> 2667.48 | J50: =VLOOKUP(C50,IP!$B$9:$D$117,3,0) -> 0 | K50: =VLOOKUP(C50,RESUMEN!$C$35:$L$137,10,0) -> 12000 | L50: =(((+K50/30)*J50)*30%) -> 0 | M50: =VLOOKUP(C50,IP!$B$9:$I$117,8,0) -> 0 | N50: =+L50-M50 -> 0 | O50: =VLOOKUP(C50,RESUMEN!$C$35:$Z$141,24,0) -> 0 | Q50: PITSS
A51: SEI0503 | B51: SEITON (IP INNOVA II) | C51: Martinez Rodriguez Paulo Cesar | F51: 2552.4 | G51: 250 | H51: =+N51 -> 0 | I51: =+F51+G51+H51 -> 2802.4 | J51: =VLOOKUP(C51,IP!$B$9:$D$117,3,0) -> 0 | K51: =VLOOKUP(C51,RESUMEN!$C$35:$L$137,10,0) -> 10000 | L51: =(((+K51/30)*J51)*30%) -> 0 | M51: =VLOOKUP(C51,IP!$B$9:$I$117,8,0) -> 0 | N51: =+L51-M51 -> 0 | O51: =VLOOKUP(C51,RESUMEN!$C$35:$Z$141,24,0) -> 0 | Q51: PITSS
A52: SEI0504 | B52: SEITON (IP INNOVA II) | C52: Martinez Malo Cesar | F52: 1694.21 | G52: 401.85 | H52: =+N52 -> 0 | I52: =+F52+G52+H52 -> 2096.06 | J52: =VLOOKUP(C52,IP!$B$9:$D$117,3,0) -> 0 | K52: =VLOOKUP(C52,RESUMEN!$C$35:$L$137,10,0) -> 9000 | L52: =(((+K52/30)*J52)*30%) -> 0 | M52: =VLOOKUP(C52,IP!$B$9:$I$117,8,0) -> 0 | N52: =+L52-M52 -> 0 | O52: =VLOOKUP(C52,RESUMEN!$C$35:$Z$141,24,0) -> 0 | Q52: PITSS
A53: SEI0505 | B53: SEITON (IP INNOVA II) | C53: Perez Balboa Cesar | F53: 2194.19 | G53: 44.22 | H53: =+N53 -> 0 | I53: =+F53+G53+H53 -> 2238.41 | J53: =VLOOKUP(C53,IP!$B$9:$D$117,3,0) -> 0 | K53: =VLOOKUP(C53,RESUMEN!$C$35:$L$137,10,0) -> 10000 | L53: =(((+K53/30)*J53)*30%) -> 0 | M53: =VLOOKUP(C53,IP!$B$9:$I$117,8,0) -> 0 | N53: =+L53-M53 -> 0 | O53: =VLOOKUP(C53,RESUMEN!$C$35:$Z$141,24,0) -> 0 | Q53: PITSS
A54: SEI0508 | B54: SEITON (IP INNOVA II) | C54: Cerro Garcia Elvis | F54: 2553.4 | G54: 300 | H54: =+N54 -> 0 | I54: =+F54+G54+H54 -> 2853.4 | J54: =VLOOKUP(C54,IP!$B$9:$D$117,3,0) -> 0 | K54: =VLOOKUP(C54,RESUMEN!$C$35:$L$137,10,0) -> 10000 | L54: =(((+K54/30)*J54)*30%) -> 0 | M54: =VLOOKUP(C54,IP!$B$9:$I$117,8,0) -> 0 | N54: =+L54-M54 -> 0 | O54: =VLOOKUP(C54,RESUMEN!$C$35:$Z$141,24,0) -> 0 | Q54: PITSS
A55: SEI0078 | B55: SEITON (IP INNOVA II) | C55: Aguilar Leal Karina Livier | F55: 917 | G55: 27481.6 | H55: =+N55 -> 0 | I55: =+F55+G55+H55 -> 28398.6 | J55: =VLOOKUP(C55,IP!$B$9:$D$117,3,0) -> 0 | K55: =VLOOKUP(C55,RESUMEN!$C$35:$L$137,10,0) -> 9000 | L55: =(((+K55/30)*J55)*30%) -> 0 | M55: =VLOOKUP(C55,IP!$B$9:$I$117,8,0) -> 0 | N55: =+L55-M55 -> 0 | O55: =VLOOKUP(C55,RESUMEN!$C$35:$Z$141,24,0) -> 0 | Q55: SEITON
A56: SEI0126 | B56: SEITON (IP INNOVA II) | C56: Alonso Flores Beda | F56: 0 | H56: 0 | I56: =+F56+G56+H56 -> 0 | J56: =VLOOKUP(C56,IP!$B$9:$D$117,3,0) -> 0 | K56: =VLOOKUP(C56,RESUMEN!$C$35:$L$137,10,0) -> 9000 | L56: =(((+K56/30)*J56)*30%) -> 0 | M56: =VLOOKUP(C56,IP!$B$9:$I$117,8,0) -> 0 | N56: =+L56-M56 -> 0 | O56: =VLOOKUP(C56,RESUMEN!$C$35:$Z$141,24,0) -> -3.4 | Q56: SEITON
A57: SEI0079 | B57: SEITON (IP INNOVA II) | C57: Amezcua Contreras Martha Frine | F57: 2162.4 | G57: 750 | H57: =+N57 -> 0 | I57: =+F57+G57+H57 -> 2912.4 | J57: =VLOOKUP(C57,IP!$B$9:$D$117,3,0) -> 0 | K57: =VLOOKUP(C57,RESUMEN!$C$35:$L$137,10,0) -> 18500 | L57: =(((+K57/30)*J57)*30%) -> 0 | M57: =VLOOKUP(C57,IP!$B$9:$I$117,8,0) -> 0 | N57: =+L57-M57 -> 0 | O57: =VLOOKUP(C57,RESUMEN!$C$35:$Z$141,24,0) -> 0 | Q57: SEITON
A58: SEI0029 | B58: SEITON (IP INNOVA II) | C58: Arceo Garcia Manuel Federico | F58: 135.2 | G58: 1000 | H58: =+N58 -> 0 | I58: =+F58+G58+H58 -> 1135.2 | J58: =VLOOKUP(C58,IP!$B$9:$D$117,3,0) -> 0 | K58: =VLOOKUP(C58,RESUMEN!$C$35:$L$137,10,0) -> 6000 | L58: =(((+K58/30)*J58)*30%) -> 0 | M58: =VLOOKUP(C58,IP!$B$9:$I$117,8,0) -> 0 | N58: =+L58-M58 -> 0 | O58: =VLOOKUP(C58,RESUMEN!$C$35:$Z$141,24,0) -> 0 | Q58: PITSS
A59: SEI0230 | B59: SEITON (IP INNOVA II) | C59: Bueno Herrera Mariana Guadalupe | F59: 2716.4 | G59: 4835.03 | H59: =+N59 -> 0 | I59: =+F59+G59+H59 -> 7551.43 | J59: =VLOOKUP(C59,IP!$B$9:$D$117,3,0) -> 0 | K59: =VLOOKUP(C59,RESUMEN!$C$35:$L$137,10,0) -> 12600 | L59: =(((+K59/30)*J59)*30%) -> 0 | M59: =VLOOKUP(C59,IP!$B$9:$I$117,8,0) -> 0 | N59: =+L59-M59 -> 0 | O59: =VLOOKUP(C59,RESUMEN!$C$35:$Z$141,24,0) -> 0 | Q59: SEITON
A60: SEI0031 | B60: SEITON (IP INNOVA II) | C60: Contreras Zetina Victor Hugo | F60: 215.8 | H60: =+N60 -> 0 | I60: =+F60+G60+H60 -> 215.8 | J60: =VLOOKUP(C60,IP!$B$9:$D$117,3,0) -> 0 | K60: =VLOOKUP(C60,RESUMEN!$C$35:$L$137,10,0) -> 6900 | L60: =(((+K60/30)*J60)*30%) -> 0 | M60: =VLOOKUP(C60,IP!$B$9:$I$117,8,0) -> 0 | N60: =+L60-M60 -> 0 | O60: =VLOOKUP(C60,RESUMEN!$C$35:$Z$141,24,0) -> 0 | Q60: PITSS
A61: SEI0413 | B61: SEITON (IP INNOVA II) | C61: Courtenay Gutierrez Barry Vladimir | F61: 52.47 | G61: =291.43+4060 -> 4351.43 | H61: =+N61 -> 0 | I61: =+F61+G61+H61 -> 4403.9 | J61: =VLOOKUP(C61,IP!$B$9:$D$117,3,0) -> 0 | K61: =VLOOKUP(C61,RESUMEN!$C$35:$L$137,10,0) -> 5000 | L61: =(((+K61/30)*J61)*30%) -> 0 | M61: =VLOOKUP(C61,IP!$B$9:$I$117,8,0) -> 0 | N61: =+L61-M61 -> 0 | O61: =VLOOKUP(C61,RESUMEN!$C$35:$Z$141,24,0) -> 0 | Q61: PITSS
A62: SEI0364 | B62: SEITON (IP INNOVA II) | C62: Dominguez Lopez Mayeli Del Pilar | F62: 1416.33 | G62: 211.25 | H62: =+N62 -> 0 | I62: =+F62+G62+H62 -> 1627.58 | J62: =VLOOKUP(C62,IP!$B$9:$D$117,3,0) -> 0 | K62: =VLOOKUP(C62,RESUMEN!$C$35:$L$137,10,0) -> 10000 | L62: =(((+K62/30)*J62)*30%) -> 0 | M62: =VLOOKUP(C62,IP!$B$9:$I$117,8,0) -> 0 | N62: =+L62-M62 -> 0 | O62: =VLOOKUP(C62,RESUMEN!$C$35:$Z$141,24,0) -> 0 | Q62: PITSS
A63: SEI0018 | B63: SEITON (IP INNOVA II) | C63: Dominguez Mendez Victor Manuel | F63: 496 | G63: =162.81+276 -> 438.81 | H63: =+N63 -> 0 | I63: =+F63+G63+H63 -> 934.81 | J63: =VLOOKUP(C63,IP!$B$9:$D$117,3,0) -> 0 | K63: =VLOOKUP(C63,RESUMEN!$C$35:$L$137,10,0) -> 9000 | L63: =(((+K63/30)*J63)*30%) -> 0 | M63: =VLOOKUP(C63,IP!$B$9:$I$117,8,0) -> 0 | N63: =+L63-M63 -> 0 | O63: =VLOOKUP(C63,RESUMEN!$C$35:$Z$141,24,0) -> 0 | Q63: PITSS
A64: SEI0037 | B64: SEITON (IP INNOVA II) | C64: Gomez Oliveros Alin | F64: =585.2+1550 -> 2135.2 | G64: 9882.23 | H64: =+N64 -> 0 | I64: =+F64+G64+H64 -> 12017.43 | J64: =VLOOKUP(C64,IP!$B$9:$D$117,3,0) -> 0 | K64: =VLOOKUP(C64,RESUMEN!$C$35:$L$137,10,0) -> 10000 | L64: =(((+K64/30)*J64)*30%) -> 0 | M64: =VLOOKUP(C64,IP!$B$9:$I$117,8,0) -> 0 | N64: =+L64-M64 -> 0 | O64: =VLOOKUP(C64,RESUMEN!$C$35:$Z$141,24,0) -> 0 | Q64: SEITON
A65: SEI0019 | B65: SEITON (IP INNOVA II) | C65: Gonzalez Rasgado Miguel Isaias | F65: 804.8 | G65: =500+480 -> 980 | H65: =+N65 -> 0 | I65: =+F65+G65+H65 -> 1784.8 | J65: =VLOOKUP(C65,IP!$B$9:$D$117,3,0) -> 2 | K65: =VLOOKUP(C65,RESUMEN!$C$35:$L$137,10,0) -> 12000 | L65: =(((+K65/30)*J65)*30%) -> 240 | M65: =VLOOKUP(C65,IP!$B$9:$I$117,8,0) -> 240 | N65: =+L65-M65 -> 0 | O65: =VLOOKUP(C65,RESUMEN!$C$35:$Z$141,24,0) -> 0 | Q65: PITSS
A66: SEI0081 | B66: SEITON (IP INNOVA II) | C66: Guizar Perez Sergio | F66: 881.8 | G66: 250 | H66: =+N66 -> 0 | I66: =+F66+G66+H66 -> 1131.8 | J66: =VLOOKUP(C66,IP!$B$9:$D$117,3,0) -> 0 | K66: =VLOOKUP(C66,RESUMEN!$C$35:$L$137,10,0) -> 8500 | L66: =(((+K66/30)*J66)*30%) -> 0 | M66: =VLOOKUP(C66,IP!$B$9:$I$117,8,0) -> 0 | N66: =+L66-M66 -> 0 | O66: =VLOOKUP(C66,RESUMEN!$C$35:$Z$141,24,0) -> 0 | Q66: SEITON
A67: SEI0332 | B67: SEITON (IP INNOVA II) | C67: Lara Campos Maximino | F67: 0 | H67: =+N67 -> 0 | I67: =+F67+G67+H67 -> 0 | J67: =VLOOKUP(C67,IP!$B$9:$D$117,3,0) -> 0 | K67: =VLOOKUP(C67,RESUMEN!$C$35:$L$137,10,0) -> 9500 | L67: =(((+K67/30)*J67)*30%) -> 0 | M67: =VLOOKUP(C67,IP!$B$9:$I$117,8,0) -> 0 | N67: =+L67-M67 -> 0 | O67: =VLOOKUP(C67,RESUMEN!$C$35:$Z$141,24,0) -> -3.8 | Q67: SEITON
A68: SEI0020 | B68: SEITON (IP INNOVA II) | C68: Mar Marquez Cesar Eduardo | F68: 414.6 | G68: =192.5+1000 -> 1192.5 | H68: =+N68 -> 0 | I68: =+F68+G68+H68 -> 1607.1 | J68: =VLOOKUP(C68,IP!$B$9:$D$117,3,0) -> 0 | K68: =VLOOKUP(C68,RESUMEN!$C$35:$L$137,10,0) -> 8000 | L68: =(((+K68/30)*J68)*30%) -> 0 | M68: =VLOOKUP(C68,IP!$B$9:$I$117,8,0) -> 0 | N68: =+L68-M68 -> 0 | O68: =VLOOKUP(C68,RESUMEN!$C$35:$Z$141,24,0) -> 0 | Q68: PITSS
A69: SEI0376 | B69: SEITON (IP INNOVA II) | C69: Marquez Alcaraz Martin | F69: 941.18 | G69: 275 | H69: =+N69 -> 0 | I69: =+F69+G69+H69 -> 1216.18 | J69: =VLOOKUP(C69,IP!$B$9:$D$117,3,0) -> 0 | K69: =VLOOKUP(C69,RESUMEN!$C$35:$L$137,10,0) -> 9050 | L69: =(((+K69/30)*J69)*30%) -> 0 | M69: =VLOOKUP(C69,IP!$B$9:$I$117,8,0) -> 0 | N69: =+L69-M69 -> 0 | O69: =VLOOKUP(C69,RESUMEN!$C$35:$Z$141,24,0) -> 0 | Q69: SEITON
A70: SEI0014 | B70: SEITON (IP INNOVA II) | C70: Montoya Portillo Carlos Alberto | F70: 414.6 | G70: 196.43 | H70: 0 | I70: =+F70+G70+H70 -> 611.03 | J70: =VLOOKUP(C70,IP!$B$9:$D$117,3,0) -> 0 | K70: =VLOOKUP(C70,RESUMEN!$C$35:$L$137,10,0) -> 8000 | L70: =(((+K70/30)*J70)*30%) -> 0 | M70: =VLOOKUP(C70,IP!$B$9:$I$117,8,0) -> 0 | N70: =+L70-M70 -> 0 | O70: =VLOOKUP(C70,RESUMEN!$C$35:$Z$141,24,0) -> 0 | Q70: PITSS
A71: SEI0017 | B71: SEITON (IP INNOVA II) | C71: Muñoz Reyes Luis Eduardo | F71: 414.64 | G71: 283.34 | H71: =+N71 -> 0 | I71: =+F71+G71+H71 -> 697.98 | J71: =VLOOKUP(C71,IP!$B$9:$D$117,3,0) -> 0 | K71: =VLOOKUP(C71,RESUMEN!$C$35:$L$137,10,0) -> 8000 | L71: =(((+K71/30)*J71)*30%) -> 0 | M71: =VLOOKUP(C71,IP!$B$9:$I$117,8,0) -> 0 | N71: =+L71-M71 -> 0 | O71: =VLOOKUP(C71,RESUMEN!$C$35:$Z$141,24,0) -> 0 | Q71: PITSS
A72: SEI0022 | B72: SEITON (IP INNOVA II) | C72: Najera Lopez Raul | F72: 593.6 | G72: =271.72+560 -> 831.72 | H72: =+N72 -> 0 | I72: =+F72+G72+H72 -> 1425.32 | J72: =VLOOKUP(C72,IP!$B$9:$D$117,3,0) -> 0 | K72: =VLOOKUP(C72,RESUMEN!$C$35:$L$137,10,0) -> 10000 | L72: =(((+K72/30)*J72)*30%) -> 0 | M72: =VLOOKUP(C72,IP!$B$9:$I$117,8,0) -> 0 | N72: =+L72-M72 -> 0 | O72: =VLOOKUP(C72,RESUMEN!$C$35:$Z$141,24,0) -> 0 | Q72: PITSS
A73: SEI0016 | B73: SEITON (IP INNOVA II) | C73: Negrete Bejar Aide Sarai | F73: 17.67 | G73: 1190.43 | H73: =+N73 -> 0 | I73: =+F73+G73+H73 -> 1208.1 | J73: =VLOOKUP(C73,IP!$B$9:$D$117,3,0) -> 0 | K73: =VLOOKUP(C73,RESUMEN!$C$35:$L$137,10,0) -> 4620 | L73: =(((+K73/30)*J73)*30%) -> 0 | M73: =VLOOKUP(C73,IP!$B$9:$I$117,8,0) -> 0 | N73: =+L73-M73 -> 0 | O73: =VLOOKUP(C73,RESUMEN!$C$35:$Z$141,24,0) -> 0 | Q73: SEITON
A74: SEI0109 | B74: SEITON (IP INNOVA II) | C74: Negrete Renteria Jose Luis | F74: 1122.43 | G74: 500 | H74: =+N74 -> 0 | I74: =+F74+G74+H74 -> 1622.43 | J74: =VLOOKUP(C74,IP!$B$9:$D$117,3,0) -> 0 | K74: =VLOOKUP(C74,RESUMEN!$C$35:$L$137,10,0) -> 9800 | L74: =(((+K74/30)*J74)*30%) -> 0 | M74: =VLOOKUP(C74,IP!$B$9:$I$117,8,0) -> 0 | N74: =+L74-M74 -> 0 | O74: =VLOOKUP(C74,RESUMEN!$C$35:$Z$141,24,0) -> 0 | Q74: SEITON
A75: SEI0023 | B75: SEITON (IP INNOVA II) | C75: Puente Murguia Luis Felipe | F75: 222.6 | G75: =103.4+450 -> 553.4 | H75: =+N75 -> 0 | I75: =+F75+G75+H75 -> 776 | J75: =VLOOKUP(C75,IP!$B$9:$D$117,3,0) -> 0 | K75: =VLOOKUP(C75,RESUMEN!$C$35:$L$137,10,0) -> 7000 | L75: =(((+K75/30)*J75)*30%) -> 0 | M75: =VLOOKUP(C75,IP!$B$9:$I$117,8,0) -> 0 | N75: =+L75-M75 -> 0 | O75: =VLOOKUP(C75,RESUMEN!$C$35:$Z$141,24,0) -> 0 | Q75: PITSS
A76: SEI0100 | B76: SEITON (IP INNOVA II) | C76: Quinto Valle Martin | F76: 593.6 | G76: 500 | H76: =+N76 -> 0 | I76: =+F76+G76+H76 -> 1093.6 | J76: =VLOOKUP(C76,IP!$B$9:$D$117,3,0) -> 0 | K76: =VLOOKUP(C76,RESUMEN!$C$35:$L$137,10,0) -> 10000 | L76: =(((+K76/30)*J76)*30%) -> 0 | M76: =VLOOKUP(C76,IP!$B$9:$I$117,8,0) -> 0 | N76: =+L76-M76 -> 0 | O76: =VLOOKUP(C76,RESUMEN!$C$35:$Z$141,24,0) -> 0 | Q76: SEITON
A77: SEI0146 | B77: SEITON (IP INNOVA II) | C77: Ramirez Vera Maria Del Carmen | F77: 1416.39 | H77: =+N77 -> 0 | I77: =+F77+G77+H77 -> 1416.39 | J77: =VLOOKUP(C77,IP!$B$9:$D$117,3,0) -> 0 | K77: =VLOOKUP(C77,RESUMEN!$C$35:$L$137,10,0) -> 10000 | L77: =(((+K77/30)*J77)*30%) -> 0 | M77: =VLOOKUP(C77,IP!$B$9:$I$117,8,0) -> 0 | N77: =+L77-M77 -> 0 | O77: =VLOOKUP(C77,RESUMEN!$C$35:$Z$141,24,0) -> 0 | Q77: SEITON
A78: SEI0345 | B78: SEITON (IP INNOVA II) | C78: Rodriguez Diaz Cesar Salvador | F78: 941.41 | G78: 275 | H78: =+N78 -> 0 | I78: =+F78+G78+H78 -> 1216.41 | J78: =VLOOKUP(C78,IP!$B$9:$D$117,3,0) -> 0 | K78: =VLOOKUP(C78,RESUMEN!$C$35:$L$137,10,0) -> 9050 | L78: =(((+K78/30)*J78)*30%) -> 0 | M78: =VLOOKUP(C78,IP!$B$9:$I$117,8,0) -> 0 | N78: =+L78-M78 -> 0 | O78: =VLOOKUP(C78,RESUMEN!$C$35:$Z$141,24,0) -> 0 | Q78: SEITON
A79: SEI0412 | B79: SEITON (IP INNOVA II) | C79: Rojo Avelar Adrian | F79: 885.22 | G79: 250 | H79: =+N79 -> 75 | I79: =+F79+G79+H79 -> 1210.22 | J79: =VLOOKUP(C79,IP!$B$9:$D$117,3,0) -> 5 | K79: =VLOOKUP(C79,RESUMEN!$C$35:$L$137,10,0) -> 7500 | L79: =(((+K79/30)*J79)*30%) -> 375 | M79: =VLOOKUP(C79,IP!$B$9:$I$117,8,0) -> 300 | N79: =+L79-M79 -> 75 | O79: =VLOOKUP(C79,RESUMEN!$C$35:$Z$141,24,0) -> 0 | Q79: SEITON
A80: SEI0133 | B80: SEITON (IP INNOVA II) | C80: Romero Mayoral Lorenzo | F80: 2166.28 | G80: 250 | H80: =+N80 -> 70 | I80: =+F80+G80+H80 -> 2486.28 | J80: =VLOOKUP(C80,IP!$B$9:$D$117,3,0) -> 2 | K80: =VLOOKUP(C80,RESUMEN!$C$35:$L$137,10,0) -> 11500 | L80: =(((+K80/30)*J80)*30%) -> 230 | M80: =VLOOKUP(C80,IP!$B$9:$I$117,8,0) -> 160 | N80: =+L80-M80 -> 70 | O80: =VLOOKUP(C80,RESUMEN!$C$35:$Z$141,24,0) -> 0 | Q80: SEITON
A81: SEI0010 | B81: SEITON (IP INNOVA II) | C81: Torres Ricardez Alfredo | F81: 414.8 | G81: 340.28 | H81: =+N81 -> 0 | I81: =+F81+G81+H81 -> 755.08 | J81: =VLOOKUP(C81,IP!$B$9:$D$117,3,0) -> 0 | K81: =VLOOKUP(C81,RESUMEN!$C$35:$L$137,10,0) -> 8000 | L81: =(((+K81/30)*J81)*30%) -> 0 | M81: =VLOOKUP(C81,IP!$B$9:$I$117,8,0) -> 0 | N81: =+L81-M81 -> 0 | O81: =VLOOKUP(C81,RESUMEN!$C$35:$Z$141,24,0) -> 0 | Q81: PITSS
A82: SEI0021 | B82: SEITON (IP INNOVA II) | C82: Velez Rodriguez Jaime | F82: 1135.12 | H82: =+N82 -> 0 | I82: =+F82+G82+H82 -> 1135.12 | J82: =VLOOKUP(C82,IP!$B$9:$D$117,3,0) -> 0 | K82: =VLOOKUP(C82,RESUMEN!$C$35:$L$137,10,0) -> 8000 | L82: =(((+K82/30)*J82)*30%) -> 0 | M82: =VLOOKUP(C82,IP!$B$9:$I$117,8,0) -> 0 | N82: =+L82-M82 -> 0 | O82: =VLOOKUP(C82,RESUMEN!$C$35:$Z$141,24,0) -> 0 | Q82: PITSS
A83: SEI0421 | B83: SEITON (IP INNOVA II) | C83: Marin Avila Hector | F83: 707 | H83: =+N83 -> 0 | I83: =+F83+G83+H83 -> 707 | J83: =VLOOKUP(C83,IP!$B$9:$D$117,3,0) -> 0 | K83: =VLOOKUP(C83,RESUMEN!$C$35:$L$137,10,0) -> 8800 | L83: =(((+K83/30)*J83)*30%) -> 0 | M83: =VLOOKUP(C83,IP!$B$9:$I$117,8,0) -> 0 | N83: =+L83-M83 -> 0 | O83: =VLOOKUP(C83,RESUMEN!$C$35:$Z$141,24,0) -> 0 | Q83: SEITON
A84: SEI0424 | B84: SEITON (IP INNOVA II) | C84: Palacios Ramos Jesus | F84: 416.4 | G84: 92.73 | H84: =+N84 -> 0 | I84: =+F84+G84+H84 -> 509.13 | J84: =VLOOKUP(C84,IP!$B$9:$D$117,3,0) -> 0 | K84: =VLOOKUP(C84,RESUMEN!$C$35:$L$137,10,0) -> 8000 | L84: =(((+K84/30)*J84)*30%) -> 0 | M84: =VLOOKUP(C84,IP!$B$9:$I$117,8,0) -> 0 | N84: =+L84-M84 -> 0 | O84: =VLOOKUP(C84,RESUMEN!$C$35:$Z$141,24,0) -> 0 | Q84: PITSS
A85: SEI0429 | B85: SEITON (IP INNOVA II) | C85: Torres Gomez Valeria | F85: 0 | H85: =+N85 -> 0 | I85: =+F85+G85+H85 -> 0 | J85: =VLOOKUP(C85,IP!$B$9:$D$117,3,0) -> 0 | K85: =VLOOKUP(C85,RESUMEN!$C$35:$L$137,10,0) -> 4500 | L85: =(((+K85/30)*J85)*30%) -> 0 | M85: =VLOOKUP(C85,IP!$B$9:$I$117,8,0) -> 0 | N85: =+L85-M85 -> 0 | O85: =VLOOKUP(C85,RESUMEN!$C$35:$Z$141,24,0) -> 136.8 | Q85: PITSS
A86: SEI0431 | B86: SEITON (IP INNOVA II) | C86: Alcaraz Conde Zabdi Guadalupe | F86: =309.89-200 -> 109.89 | G86: 1000 | H86: =+N86 -> 0 | I86: =+F86+G86+H86 -> 1109.89 | J86: =VLOOKUP(C86,IP!$B$9:$D$117,3,0) -> 0 | K86: =VLOOKUP(C86,RESUMEN!$C$35:$L$137,10,0) -> 6000 | L86: =(((+K86/30)*J86)*30%) -> 0 | M86: =VLOOKUP(C86,IP!$B$9:$I$117,8,0) -> 0 | N86: =+L86-M86 -> 0 | O86: =VLOOKUP(C86,RESUMEN!$C$35:$Z$141,24,0) -> 200 | Q86: PITSS
A87: SEI0428 | B87: SEITON (IP INNOVA II) | C87: Martinez Hernandez J. Antonio | F87: 416.2 | G87: 310 | H87: =+N87 -> 0 | I87: =+F87+G87+H87 -> 726.2 | J87: 4 | K87: =VLOOKUP(C87,RESUMEN!$C$35:$L$137,10,0) -> 8000 | L87: =(((+K87/30)*J87)*30%) -> 320 | M87: =VLOOKUP(C87,IP!$B$9:$I$117,8,0) -> 320 | N87: =+L87-M87 -> 0 | O87: =VLOOKUP(C87,RESUMEN!$C$35:$Z$141,24,0) -> 0 | Q87: PITSS
A88: SEI0438 | B88: SEITON (IP INNOVA II) | C88: Lopez Terron Roberto Porfirio | F88: 1047.6 | H88: =+N88 -> 0 | I88: =+F88+G88+H88 -> 1047.6 | J88: =VLOOKUP(C88,IP!$B$9:$D$117,3,0) -> 0 | K88: =VLOOKUP(C88,RESUMEN!$C$35:$L$137,10,0) -> 14000 | L88: =(((+K88/30)*J88)*30%) -> 0 | M88: =VLOOKUP(C88,IP!$B$9:$I$117,8,0) -> 0 | N88: =+L88-M88 -> 0 | O88: =VLOOKUP(C88,RESUMEN!$C$35:$Z$141,24,0) -> 0 | Q88: PITSS
A89: SEI0442 | B89: SEITON (IP INNOVA II) | C89: Chavez Pedraza Samuel | F89: 1047.8 | H89: =+N89 -> 0 | I89: =+F89+G89+H89 -> 1047.8 | J89: =VLOOKUP(C89,IP!$B$9:$D$117,3,0) -> 0 | K89: =VLOOKUP(C89,RESUMEN!$C$35:$L$137,10,0) -> 14000 | L89: =(((+K89/30)*J89)*30%) -> 0 | M89: =VLOOKUP(C89,IP!$B$9:$I$117,8,0) -> 0 | N89: =+L89-M89 -> 0 | O89: =VLOOKUP(C89,RESUMEN!$C$35:$Z$141,24,0) -> 0 | Q89: PITSS
A90: SEI0443 | B90: SEITON (IP INNOVA II) | C90: Castillo Nungaray Nestor Roman | F90: 135.2 | G90: 422.5 | H90: =+N90 -> 0 | I90: =+F90+G90+H90 -> 557.7 | J90: =VLOOKUP(C90,IP!$B$9:$D$117,3,0) -> 1 | K90: =VLOOKUP(C90,RESUMEN!$C$35:$L$137,10,0) -> 6000 | L90: =(((+K90/30)*J90)*30%) -> 60 | M90: =VLOOKUP(C90,IP!$B$9:$I$117,8,0) -> 60 | N90: =+L90-M90 -> 0 | O90: =VLOOKUP(C90,RESUMEN!$C$35:$Z$141,24,0) -> 0 | Q90: PITSS
A91: SEI0444 | B91: SEITON (IP INNOVA II) | C91: Marquez Hernandez Rogelio | F91: 416.4 | G91: =416.16+400 -> 816.16 | H91: =+N91 -> 0 | I91: =+F91+G91+H91 -> 1232.56 | J91: =VLOOKUP(C91,IP!$B$9:$D$117,3,0) -> 1 | K91: =VLOOKUP(C91,RESUMEN!$C$35:$L$137,10,0) -> 8000 | L91: =(((+K91/30)*J91)*30%) -> 80 | M91: =VLOOKUP(C91,IP!$B$9:$I$117,8,0) -> 80 | N91: =+L91-M91 -> 0 | O91: =VLOOKUP(C91,RESUMEN!$C$35:$Z$141,24,0) -> 0 | Q91: PITSS
A92: SEI0449 | B92: SEITON (IP INNOVA II) | C92: Flores Cerrillos Jorge Humberto | F92: 416.4 | G92: 294.82 | H92: =+N92 -> 0 | I92: =+F92+G92+H92 -> 711.22 | J92: =VLOOKUP(C92,IP!$B$9:$D$117,3,0) -> 0 | K92: =VLOOKUP(C92,RESUMEN!$C$35:$L$137,10,0) -> 8000 | L92: =(((+K92/30)*J92)*30%) -> 0 | M92: =VLOOKUP(C92,IP!$B$9:$I$117,8,0) -> 0 | N92: =+L92-M92 -> 0 | O92: =VLOOKUP(C92,RESUMEN!$C$35:$Z$141,24,0) -> 0 | Q92: PITSS
A93: SEI0451 | B93: SEITON (IP INNOVA II) | C93: Hurtado Avalos J.jesus | F93: 135.2 | H93: =+N93 -> 0 | I93: =+F93+G93+H93 -> 135.2 | J93: =VLOOKUP(C93,IP!$B$9:$D$117,3,0) -> 0 | K93: =VLOOKUP(C93,RESUMEN!$C$35:$L$137,10,0) -> 6000 | L93: =(((+K93/30)*J93)*30%) -> 0 | M93: =VLOOKUP(C93,IP!$B$9:$I$117,8,0) -> 0 | N93: =+L93-M93 -> 0 | O93: =VLOOKUP(C93,RESUMEN!$C$35:$Z$141,24,0) -> 0 | Q93: SEITON
A94: SEI0453 | B94: SEITON (IP INNOVA II) | C94: Mora Cavazos Roberto Manuel | F94: 416.4 | H94: =+N94 -> 0 | I94: =+F94+G94+H94 -> 416.4 | J94: =VLOOKUP(C94,IP!$B$9:$D$117,3,0) -> 0 | K94: =VLOOKUP(C94,RESUMEN!$C$35:$L$137,10,0) -> 8000 | L94: =(((+K94/30)*J94)*30%) -> 0 | M94: =VLOOKUP(C94,IP!$B$9:$I$117,8,0) -> 0 | N94: =+L94-M94 -> 0 | O94: =VLOOKUP(C94,RESUMEN!$C$35:$Z$141,24,0) -> 0 | Q94: PITSS
A95: SEI0454 | B95: SEITON (IP INNOVA II) | C95: Martinez Rivera Maria Teresa | F95: 0 | H95: =+N95 -> 0 | I95: =+F95+G95+H95 -> 0 | J95: =VLOOKUP(C95,IP!$B$9:$D$117,3,0) -> 0 | K95: =VLOOKUP(C95,RESUMEN!$C$35:$L$137,10,0) -> 9000 | L95: =(((+K95/30)*J95)*30%) -> 0 | M95: =VLOOKUP(C95,IP!$B$9:$I$117,8,0) -> 0 | N95: =+L95-M95 -> 0 | O95: =VLOOKUP(C95,RESUMEN!$C$35:$Z$141,24,0) -> -3.6 | Q95: SEITON
A96: SEI0455 | B96: SEITON (IP INNOVA II) | C96: Perez Garcia Andres Alvaro | F96: 416.36 | G96: 100 | H96: =+N96 -> 0 | I96: =+F96+G96+H96 -> 516.36 | J96: =VLOOKUP(C96,IP!$B$9:$D$117,3,0) -> 0 | K96: =VLOOKUP(C96,RESUMEN!$C$35:$L$137,10,0) -> 8000 | L96: =(((+K96/30)*J96)*30%) -> 0 | M96: =VLOOKUP(C96,IP!$B$9:$I$117,8,0) -> 0 | N96: =+L96-M96 -> 0 | O96: =VLOOKUP(C96,RESUMEN!$C$35:$Z$141,24,0) -> 0 | Q96: PITSS
A97: SEI0456 | B97: SEITON (IP INNOVA II) | C97: Chavira Garcia David Fernando | F97: 593.6 | G97: 131.91 | H97: =+N97 -> 0 | I97: =+F97+G97+H97 -> 725.51 | J97: =VLOOKUP(C97,IP!$B$9:$D$117,3,0) -> 0 | K97: =VLOOKUP(C97,RESUMEN!$C$35:$L$137,10,0) -> 10000 | L97: =(((+K97/30)*J97)*30%) -> 0 | M97: =VLOOKUP(C97,IP!$B$9:$I$117,8,0) -> 0 | N97: =+L97-M97 -> 0 | O97: =VLOOKUP(C97,RESUMEN!$C$35:$Z$141,24,0) -> 0 | Q97: PITSS
A98: SEI0457 | B98: SEITON (IP INNOVA II) | C98: Guerrero Lara Cesar Adrian | F98: 416.4 | G98: =358.34+1600 -> 1958.34 | H98: =+N98 -> 0 | I98: =+F98+G98+H98 -> 2374.74 | J98: =VLOOKUP(C98,IP!$B$9:$D$117,3,0) -> 0 | K98: =VLOOKUP(C98,RESUMEN!$C$35:$L$137,10,0) -> 8000 | L98: =(((+K98/30)*J98)*30%) -> 0 | M98: =VLOOKUP(C98,IP!$B$9:$I$117,8,0) -> 0 | N98: =+L98-M98 -> 0 | O98: =VLOOKUP(C98,RESUMEN!$C$35:$Z$141,24,0) -> 0 | Q98: PITSS
A99: SEI0458 | B99: SEITON (IP INNOVA II) | C99: Martinez Zamora Gerardo Mario | F99: 549.965 | G99: =778.57+2080 -> 2858.57 | H99: =+N99 -> 0 | I99: =+F99+G99+H99 -> 3408.535 | J99: =VLOOKUP(C99,IP!$B$9:$D$117,3,0) -> 0 | K99: =VLOOKUP(C99,RESUMEN!$C$35:$L$137,10,0) -> 9550.01 | L99: =(((+K99/30)*J99)*30%) -> 0 | M99: =VLOOKUP(C99,IP!$B$9:$I$117,8,0) -> 0 | N99: =+L99-M99 -> 0 | O99: =VLOOKUP(C99,RESUMEN!$C$35:$Z$141,24,0) -> 0 | Q99: PITSS
A100: SEI0460 | B100: SEITON (IP INNOVA II) | C100: Castellon Ramos Rene | F100: 384.795 | G100: =160+320 -> 480 | H100: =+N100 -> 0 | I100: =+F100+G100+H100 -> 864.795 | J100: =VLOOKUP(C100,IP!$B$9:$D$117,3,0) -> 0 | K100: =VLOOKUP(C100,RESUMEN!$C$35:$L$137,10,0) -> 7505.99 | L100: =(((+K100/30)*J100)*30%) -> 0 | M100: =VLOOKUP(C100,IP!$B$9:$I$117,8,0) -> 0 | N100: =+L100-M100 -> 0 | O100: =VLOOKUP(C100,RESUMEN!$C$35:$Z$141,24,0) -> 0 | Q100: PITSS
A101: SEI0461 | B101: SEITON (IP INNOVA II) | C101: Flores Franco Marco | F101: 450.985 | G101: 1155 | H101: =+N101 -> 0.0211 | I101: =+F101+G101+H101 -> 1606.0061 | J101: 11 | K101: =VLOOKUP(C101,RESUMEN!$C$35:$L$137,10,0) -> 8500.01 | L101: =(((+K101/30)*J101)*30%) -> 935.0011 | M101: =VLOOKUP(C101,IP!$B$9:$I$117,8,0) -> 934.98 | N101: =+L101-M101 -> 0.0211 | O101: =VLOOKUP(C101,RESUMEN!$C$35:$Z$141,24,0) -> 0 | Q101: PITSS
A102: SEI0462 | B102: SEITON (IP INNOVA II) | C102: Chavez Saucedo Jorge Arturo | F102: 414.6 | G102: 146.25 | H102: =+N102 -> 0 | I102: =+F102+G102+H102 -> 560.85 | J102: =VLOOKUP(C102,IP!$B$9:$D$117,3,0) -> 0 | K102: =VLOOKUP(C102,RESUMEN!$C$35:$L$137,10,0) -> 8000 | L102: =(((+K102/30)*J102)*30%) -> 0 | M102: =VLOOKUP(C102,IP!$B$9:$I$117,8,0) -> 0 | N102: =+L102-M102 -> 0 | O102: =VLOOKUP(C102,RESUMEN!$C$35:$Z$141,24,0) -> 0 | Q102: PITSS
A103: SEI0464 | B103: SEITON (IP INNOVA II) | C103: Hueramo Hueramo Jesus Daniel | F103: 450.955 | G103: =200.68+840 -> 1040.68 | H103: 84.99 | I103: =+F103+G103+H103 -> 1576.625 | J103: =VLOOKUP(C103,IP!$B$9:$D$117,3,0) -> 0 | K103: =VLOOKUP(C103,RESUMEN!$C$35:$L$137,10,0) -> 8500.01 | L103: =(((+K103/30)*J103)*30%) -> 0 | M103: =VLOOKUP(C103,IP!$B$9:$I$117,8,0) -> 0 | N103: =+L103-M103 -> 0 | O103: =VLOOKUP(C103,RESUMEN!$C$35:$Z$141,24,0) -> 0 | Q103: PITSS
A104: SEI0465 | B104: SEITON (IP INNOVA II) | C104: Sandoval Garcia Luis | F104: 416.4 | G104: 322.5 | H104: =+N104 -> 0 | I104: =+F104+G104+H104 -> 738.9 | J104: =VLOOKUP(C104,IP!$B$9:$D$117,3,0) -> 0 | K104: =VLOOKUP(C104,RESUMEN!$C$35:$L$137,10,0) -> 8000 | L104: =(((+K104/30)*J104)*30%) -> 0 | M104: =VLOOKUP(C104,IP!$B$9:$I$117,8,0) -> 0 | N104: =+L104-M104 -> 0 | O104: =VLOOKUP(C104,RESUMEN!$C$35:$Z$141,24,0) -> 0 | Q104: PITSS
...

Sheet FAC-SINDICATO
B5: 1 | C5: 2 | D5: 3 | E5: 4 | F5: 5 | G5: 6
B6: CLAVE | C6: EMPRESA | D6: NOMBRE | E6: PAGO POR SINDICATO | F6: comision y bono | G6: prima vacaciones | H6: TOTAL | I6: FACTURACION
B7: SEI0097 | C7: SEITON - (CONSULTORIA II) | D7: Arreola Jimenez Jose Nieves | E7: 1557.91 | F7: 432.22 | G7: 0 | H7: 1990.13 | I7: PITSS
B8: SEI0118 | C8: SEITON - (CONSULTORIA II) | D8: Arroyo Ramirez Hector Hugo | E8: 2102.87 | F8: 200 | G8: 234.01 | H8: 2536.88 | I8: PITSS
B9: SEI0039 | C9: SEITON - (CONSULTORIA II) | D9: Benavides Herrera Pablo | E9: 23772.6 | G9: 0 | H9: 23772.6 | I9: PITSS
B10: SEI0108 | C10: SEITON - (CONSULTORIA II) | D10: Caballero Diaz Francisco Javier | E10: 1558.18 | F10: 366.93 | G10: 0 | H10: 1925.11 | I10: PITSS
B11: SEI0425 | C11: SEITON - (CONSULTORIA II) | D11: Carbajal Cabuto Jose Luis | E11: 1608.12 | F11: 777.08 | G11: 0 | H11: 2385.2 | I11: PITSS
B12: SEI0116 | C12: SEITON - (CONSULTORIA II) | D12: Casillas Cardona Cesar Alejandro | E12: 1891.03 | G12: 0 | H12: 1891.03 | I12: PITSS
B13: SEI0401 | C13: SEITON - (CONSULTORIA II) | D13: De La Torre Zambara Francisco Ernesto | E13: 1558 | F13: 393.43 | G13: 0 | H13: 1951.43 | I13: PITSS
B14: SEI0099 | C14: SEITON - (CONSULTORIA II) | D14: Garcia Villicaña Ricardo Pascual | E14: 2600.4 | F14: 891.47 | G14: 68 | H14: 3559.87 | I14: PITSS
B15: SEI0009 | C15: SEITON - (CONSULTORIA II) | D15: Gutierrez Gutierrez Luis Arturo | E15: 1475.6 | F15: 304.07 | G15: 0 | H15: 1779.67 | I15: PITSS
B16: SEI0127 | C16: SEITON - (CONSULTORIA II) | D16: Hernandez Ochoa Eduardo | E16: 2600.2 | F16: 371.43 | G16: 0 | H16: 2971.63 | I16: PITSS
B17: SEI0117 | C17: SEITON - (CONSULTORIA II) | D17: Mariscal Romero Luis Adrian | E17: 2751.04 | F17: 150 | G17: 0 | H17: 2901.04 | I17: PITSS
B18: SEI0040 | C18: SEITON - (CONSULTORIA II) | D18: Mora Ramirez Acal Aldo Isidro | E18: 2464 | G18: 0 | H18: 2464 | I18: PITSS
B19: SEI0088 | C19: SEITON - (CONSULTORIA II) | D19: Morgado Fernandez Martin | E19: 2600.4 | F19: 356.25 | G19: 0 | H19: 2956.65 | I19: PITSS
B20: SEI0173 | C20: SEITON - (CONSULTORIA II) | D20: Nieto Ortiz Jose Luis | E20: 1483.06 | F20: 103.16 | G20: 0 | H20: 1586.22 | I20: PITSS
B21: SEI0026 | C21: SEITON - (CONSULTORIA II) | D21: Patricio Aguilar Jhonattan Cristian | E21: 1588.2 | F21: 400 | G21: 0 | H21: 1988.2 | I21: PITSS
B22: SEI0221 | C22: SEITON - (CONSULTORIA II) | D22: Rogel Teran Marco Antonio | E22: 12613.2 | G22: 0 | H22: 12613.2 | I22: PITSS
B23: SEI0222 | C23: SEITON - (CONSULTORIA II) | D23: Saucedo Duran Jesus Alfredo | E23: 1891.2 | G23: 0 | H23: 1891.2 | I23: PITSS
B24: SEI0041 | C24: SEITON - (CONSULTORIA II) | D24: Vazquez Perez Miguel Angel | E24: 4176 | G24: 0 | H24: 4176 | I24: PITSS
B25: SEI0377 | C25: SEITON - (CONSULTORIA II) | D25: Benavides Herrera Alejandra | E25: 16803.4 | G25: 0 | H25: 16803.4 | I25: PITSS
B26: SEI0442 | C26: SEITON - (CONSULTORIA II) | D26: Sierra Escamilla Daniela | E26: 2464 | G26: 0 | H26: 2464 | I26: PITSS
B27: SEI0445 | C27: SEITON - (CONSULTORIA II) | D27: Muñoz Melgoza Gabriel | E27: 3090.6 | F27: 616 | G27: 0 | H27: 3706.6 | I27: PITSS
B28: SEI0483 | C28: SEITON (IP INNOVA II) | D28: Gutierrez Muñoz Carlos Alejandro | E28: 2884.99 | G28: 0 | H28: 2884.99 | I28: PITSS
B29: SEI0485 | C29: SEITON (IP INNOVA II) | D29: Molina Ramirez Gerardo Daniel | E29: 2262.25 | F29: 333.34 | G29: 0 | H29: 2595.59 | I29: PITSS
B30: SEI0488 | C30: SEITON (IP INNOVA II) | D30: Mireles Casillas Brenda Cristina | E30: 2262.2 | G30: 0 | H30: 2262.2 | I30: PITSS
B31: SEI0489 | C31: SEITON (IP INNOVA II) | D31: Escobedo Olivares Juan Guadalupe | E31: 3721.2 | F31: 166.67 | G31: 0 | H31: 3887.87 | I31: PITSS
B32: SEI0490 | C32: SEITON (IP INNOVA II) | D32: Castillo Ramirez Hector Ivan | E32: 3721.3 | F32: 208.34 | G32: 0 | H32: 3929.64 | I32: PITSS
B33: SEI0493 | C33: SEITON (IP INNOVA II) | D33: Martinez Morales Tomas | E33: 3339.44 | F33: 168.75 | G33: 0 | H33: 3508.19 | I33: PITSS
B34: SEI0494 | C34: SEITON (IP INNOVA II) | D34: Medellin Colunga Ruben Dario | E34: 4339.38 | F34: 2195.86 | G34: 0 | H34: 6535.24 | I34: PITSS
B35: SEI0495 | C35: SEITON (IP INNOVA II) | D35: Torres Perez Carlos Alberto | E35: 1917.4 | F35: 4859.43 | G35: 0 | H35: 6776.83 | I35: PITSS
B36: SEI0497 | C36: SEITON (IP INNOVA II) | D36: Treviño Alvarez Jorge Alberto | E36: 2667.33 | F36: 2060.4 | G36: 0 | H36: 4727.73 | I36: PITSS
B37: SEI0498 | C37: SEITON (IP INNOVA II) | D37: Tenorio Alvarez Alberto Antonio | E37: 1667.57 | F37: 503.94 | G37: 226.79 | H37: 2398.3 | I37: PITSS
B38: SEI0499 | C38: SEITON (IP INNOVA II) | D38: Chavez Dominguez Salvador | E38: 2667.4 | F38: 1054.35 | G38: 0 | H38: 3721.75 | I38: PITSS
B39: SEI0501 | C39: SEITON (IP INNOVA II) | D39: Cruz Herrera Roberto | E39: 1667.43 | F39: 309.43 | G39: 0 | H39: 1976.86 | I39: PITSS
B40: SEI0502 | C40: SEITON (IP INNOVA II) | D40: Dominguez Escamilla Victor Hugo | E40: 2667.48 | G40: 0 | H40: 2667.48 | I40: PITSS
B41: SEI0503 | C41: SEITON (IP INNOVA II) | D41: Martinez Rodriguez Paulo Cesar | E41: 2552.4 | F41: 250 | G41: 0 | H41: 2802.4 | I41: PITSS
B42: SEI0504 | C42: SEITON (IP INNOVA II) | D42: Martinez Malo Cesar | E42: 1694.21 | F42: 401.85 | G42: 0 | H42: 2096.06 | I42: PITSS
B43: SEI0505 | C43: SEITON (IP INNOVA II) | D43: Perez Balboa Cesar | E43: 2194.19 | F43: 44.22 | G43: 0 | H43: 2238.41 | I43: PITSS
B44: SEI0508 | C44: SEITON (IP INNOVA II) | D44: Cerro Garcia Elvis | E44: 2553.4 | F44: 300 | G44: 0 | H44: 2853.4 | I44: PITSS
B45: SEI0029 | C45: SEITON (IP INNOVA II) | D45: Arceo Garcia Manuel Federico | E45: 135.2 | F45: 1000 | G45: 0 | H45: 1135.2 | I45: PITSS
B46: SEI0413 | C46: SEITON (IP INNOVA II) | D46: Courtenay Gutierrez Barry Vladimir | E46: 52.47 | F46: 4351.43 | G46: 0 | H46: 4403.9 | I46: PITSS
B47: SEI0364 | C47: SEITON (IP INNOVA II) | D47: Dominguez Lopez Mayeli Del Pilar | E47: 1416.33 | F47: 211.25 | G47: 0 | H47: 1627.58 | I47: PITSS
B48: SEI0018 | C48: SEITON (IP INNOVA II) | D48: Dominguez Mendez Victor Manuel | E48: 496 | F48: 438.81 | G48: 0 | H48: 934.81 | I48: PITSS
B49: SEI0019 | C49: SEITON (IP INNOVA II) | D49: Gonzalez Rasgado Miguel Isaias | E49: 804.8 | F49: 980 | G49: 0 | H49: 1784.8 | I49: PITSS
B50: SEI0020 | C50: SEITON (IP INNOVA II) | D50: Mar Marquez Cesar Eduardo | E50: 414.6 | F50: 1192.5 | G50: 0 | H50: 1607.1 | I50: PITSS
B51: SEI0014 | C51: SEITON (IP INNOVA II) | D51: Montoya Portillo Carlos Alberto | E51: 414.6 | F51: 196.43 | G51: 0 | H51: 611.03 | I51: PITSS
B52: SEI0017 | C52: SEITON (IP INNOVA II) | D52: Muñoz Reyes Luis Eduardo | E52: 414.64 | F52: 283.34 | G52: 0 | H52: 697.98 | I52: PITSS
... B55: SEI0010 | C55: SEITON (IP INNOVA II) | D55: Torres Ricardez Alfredo | E55: 414.8 | F55: 340.28 | G55: 0 | H55: 755.08 | I55: PITSS
B56: SEI0021 | C56: SEITON (IP INNOVA II) | D56: Velez Rodriguez Jaime | E56: 1135.12 | G56: 0 | H56: 1135.12 | I56: PITSS
B57: SEI0424 | C57: SEITON (IP INNOVA II) | D57: Palacios Ramos Jesus | E57: 416.4 | F57: 92.73 | G57: 0 | H57: 509.13 | I57: PITSS
B58: SEI0429 | C58: SEITON (IP INNOVA II) | D58: Torres Gomez Valeria | E58: 0 | G58: 0 | H58: 0 | I58: PITSS
B59: SEI0431 | C59: SEITON (IP INNOVA II) | D59: Alcaraz Conde Zabdi Guadalupe | E59: 109.89 | F59: 1000 | G59: 0 | H59: 1109.89 | I59: PITSS
B60: SEI0428 | C60: SEITON (IP INNOVA II) | D60: Martinez Hernandez J. Antonio | E60: 416.2 | F60: 310 | G60: 0 | H60: 726.2 | I60: PITSS
B61: SEI0438 | C61: SEITON (IP INNOVA II) | D61: Lopez Terron Roberto Porfirio | E61: 1047.6 | G61: 0 | H61: 1047.6 | I61: PITSS
B62: SEI0442 | C62: SEITON (IP INNOVA II) | D62: Chavez Pedraza Samuel | E62: 1047.8 | G62: 0 | H62: 1047.8 | I62: PITSS
B63: SEI0443 | C63: SEITON (IP INNOVA II) | D63: Castillo Nungaray Nestor Roman | E63: 135.2 | F63: 422.5 | G63: 0 | H63: 557.7 | I63: PITSS
B64: SEI0444 | C64: SEITON (IP INNOVA II) | D64: Marquez Hernandez Rogelio | E64: 416.4 | F64: 816.16 | G64: 0 | H64: 1232.56 | I64: PITSS
B65: SEI0449 | C65: SEITON (IP INNOVA II) | D65: Flores Cerrillos Jorge Humberto | E65: 416.4 | F65: 294.82 | G65: 0 | H65: 711.22 | I65: PITSS
B66: SEI0455 | C66: SEITON (IP INNOVA II) | D66: Perez Garcia Andres Alvaro | E66: 416.36 | F66: 100 | G66: 0 | H66: 516.36 | I66: PITSS
B67: SEI0456 | C67: SEITON (IP INNOVA II) | D67: Chavira Garcia David Fernando | E67: 593.6 | F67: 131.91 | G67: 0 | H67: 725.51 | I67: PITSS
B68: SEI0457 | C68: SEITON (IP INNOVA II) | D68: Guerrero Lara Cesar Adrian | E68: 416.4 | F68: 1958.34 | G68: 0 | H68: 2374.74 | I68: PITSS
B69: SEI0458 | C69: SEITON (IP INNOVA II) | D69: Martinez Zamora Gerardo Mario | E69: 549.965 | F69: 2858.57 | G69: 0 | H69: 3408.535 | I69: PITSS
B70: SEI0460 | C70: SEITON (IP INNOVA II) | D70: Castellon Ramos Rene | E70: 384.795 | F70: 480 | G70: 0 | H70: 864.795 | I70: PITSS
B71: SEI0461 | C71: SEITON (IP INNOVA II) | D71: Flores Franco Marco | E71: 450.985 | F71: 1155 | G71: 0.0211 | H71: 1606.0061 | I71: PITSS
B72: SEI0462 | C72: SEITON (IP INNOVA II) | D72: Chavez Saucedo Jorge Arturo | E72: 414.6 | F72: 146.25 | G72: 0 | H72: 560.85 | I72: PITSS
B73: SEI0464 | C73: SEITON (IP INNOVA II) | D73: Hueramo Hueramo Jesus Daniel | E73: 450.955 | F73: 1040.68 | G73: 84.99 | H73: 1576.625 | I73: PITSS
B74: SEI0465 | C74: SEITON (IP INNOVA II) | D74: Sandoval Garcia Luis | E74: 416.4 | F74: 322.5 | G74: 0 | H74: 738.9 | I74: PITSS
... B90: SEI0519 | C90: SEITON (IP INNOVA II) | D90: Palacios Vega Luis Rosendo | E90: 52.4 | F90: 940 | G90: 0 | H90: 992.4 | I90: PITSS
B91: SEI0521 | C91: SEITON (IP INNOVA II) | D91: Rondero Savin Jacinto | E91: 221.2 | G91: 0 | H91: 221.2 | I91: PITSS
B92: SEI0523 | C92: SEITON (IP INNOVA II) | D92: Hernandez Rodriguez Jorge | E92: 222.58 | F92: 1280 | G92: 0 | H92: 1502.58 | I92: PITSS
B93: SEI0524 | C93: SEITON (IP INNOVA II) | D93: Orea Gonzalez Concepcion Esteban | E93: 175.6 | F93: 618.75 | G93: 0 | H93: 794.35 | I93: PITSS
B94: SEI0525 | C94: SEITON (IP INNOVA II) | D94: Lizaran Maceda Jesus | E94: 175.57 | G94: 0 | H94: 175.57 | I94: PITSS
B95: SEI0526 | C95: SEITON (IP INNOVA II) | D95: Garcia Perez Javier | E95: 175.61 | F95: 468.75 | G95: 0 | H95: 644.36 | I95: PITSS
B96: SEI0527 | C96: SEITON (IP INNOVA II) | D96: Alejandro Peña Deivi | E96: 175.6 | F96: 281.25 | G96: 0 | H96: 456.85 | I96: PITSS
B97: SEI0528 | C97: SEITON (IP INNOVA II) | D97: Casas Chavarria Rafael | E97: 175.52 | G97: 0 | H97: 175.52 | I97: PITSS
B98: SEI0530 | C98: SEITON (IP INNOVA II) | D98: Del Pilar Mendez Lucio | E98: 134.16 | G98: 0 | H98: 134.16 | I98: PITSS
B99: SEI0531 | C99: SEITON (IP INNOVA II) | D99: Garcia Valderrama Jose De Jesus | E99: 134.2 | G99: 0 | H99: 134.2 | I99: PITSS
B100: SEI0533 | C100: SEITON (IP INNOVA II) | D100: Estavillo Ramirez Maria Jose | E100: 134.2 | F100: 1000 | G100: 0 | H100: 1134.2 | I100: PITSS
B101: SEI0534 | C101: SEITON (IP INNOVA II) | D101: Gonzalez Ramirez Paul | E101: 134.2 | F101: 292.5 | G101: 0 | H101: 426.7 | I101: PITSS
B102: SEI0500 | C102: SEITON (IP INNOVA II) | D102: Garcia Gutierrez Jose Juan | E102: 3135.4 | F102: 902.07 | G102: 0 | H102: 4037.47 | I102: PITSS
B103: SEI0535 | C103: SEITON (IP INNOVA II) | D103: Alejandro Vazquez Erasmo Miguel | E103: 3135.31 | F103: 892.386 | G103: 0 | H103: 4027.696 | I103: PITSS
B104: SEI0536 | C104: SEITON (IP INNOVA II) | D104: Hernandez Ojeda Julio Cesar | E104: 1704.55 | G104: 0 | H104: 1704.55 | I104: PITSS
B105: SEI0537 | C105: SEITON (IP INNOVA II) | D105: Serrano Esquivel Armando | E105: 1704.42 | G105: 0 | H105: 1704.42 | I105: PITSS
B106: SEI0538 | C106: SEITON (IP INNOVA II) | D106: Coronado Vega Carlos Eduardo | E106: 358.2 | G106: 0 | H106: 358.2 | I106: PITSS
B107: SEI0015 | C107: SEITON (IP INNOVA II) | D107: Cota Jaramillo Miguel Angel | E107: 134.2 | F107: 840.39 | G107: 0 | H107: 974.59 | I107: PITSS
A108: Total PITSS | B108: =SUBTOTAL(9,B7:B107) -> 0 | C108: =SUBTOTAL(9,C7:C107) -> 0 | D108: =SUBTOTAL(9,D7:D107) -> 0 | E108: =SUBTOTAL(9,E7:E107) -> 178794.58 | F108: =SUBTOTAL(9,F7:F107) -> 53496.816 | G108: =SUBTOTAL(9,G7:G107) -> 613.8111 | H108: =SUBTOTAL(9,H7:H107) -> 232905.21 | I108: =SUBTOTAL(9,I7:I107) -> 0
B109: SEI0028 | C109: SEITON (IP INNOVA II) | D109: Jimenez Alcaraz Elizabeth | E109: 585.2 | G109: 0 | H109: 585.2 | I109: SEITON
B110: SEI0522 | C110: SEITON (IP INNOVA II) | D110: Peña Lopez Abigail | E110: 216 | G110: 0 | H110: 216 | I110: SEITON
B111: SEI0010 | C111: SEITON - (CONSULTORIA II) | D111: Compean Tobias Braulio Gerardo | E111: 3645.92 | F111: 2000 | G111: 0 | H111: 5645.92 | I111: SEITON
B112: SEI0147 | C112: SEITON - (CONSULTORIA II) | D112: Diaz Munguia Martha Liliana | E112: 7009.15 | G112: 0 | H112: 7009.15 | I112: SEITON
B113: SEI0119 | C113: SEITON - (CONSULTORIA II) | D113: Dominguez Lopez Maria De Jesus | E113: 2102.95 | G113: 0 | H113: 2102.95 | I113: SEITON
B114: SEI032 | C114: SEITON - (CONSULTORIA II) | D114: Camarena Quiroz Erick Frank | E114: 1588 | G114: 0 | H114: 1588 | I114: SEITON
B115: SEI0437 | C115: SEITON - (CONSULTORIA II) | D115: Leal Montaño Diego | E115: 1803.28 | F115: 2810 | G115: 100 | H115: 4713.28 | I115: SEITON
B116: SEI0440 | C116: SEITON - (CONSULTORIA II) | D116: Leija Arevalo Guadalupe | E116: 0 | G116: 0 | H116: 0 | I116: SEITON
B117: SEI0447 | C117: SEITON - (CONSULTORIA II) | D117: Oliver Olague Vicente | E117: 3286.8 | G117: 0 | H117: 3286.8 | I117: SEITON
B118: SEI0448 | C118: SEITON - (CONSULTORIA II) | D118: Rodriguez Chavez Oswaldo Emmanuel | E118: 2672.6 | F118: 1200 | G118: 0 | H118: 3872.6 | I118: SEITON
B119: SEI0482 | C119: SEITON (IP INNOVA II) | D119: Camarillo Canela Reynaldo | E119: 2219.28 | F119: 1480 | G119: 295.76 | H119: 3995.04 | I119: SEITON
B120: SEI0496 | C120: SEITON (IP INNOVA II) | D120: Velazquez Herrera Nayeli | E120: 3339.4 | G120: 0 | H120: 3339.4 | I120: SEITON
B121: SEI0078 | C121: SEITON (IP INNOVA II) | D121: Aguilar Leal Karina Livier | E121: 917 | F121: 27481.6 | G121: 0 | H121: 28398.6 | I121: SEITON
...

Sheet RESUMEN
A2: SUELDOS Y SALARIOS | G2: SINDICATO | K2: NETOS | O2: EXTRAS
B3: EMPRESA | C3: NOMBRE | D3: NETO CPD | E3: NETO IP | G3: PAGO SINDICATO | H3: COMISION | I3: PRIMA VACACIONAL SINDICATO | K3: NETO A PAGAR | L3: NETO MENSUAL | M3: NETO QUINCENAL SEITON | O3: prima vacacional | P3: COMISION Y PRIMA VACACIONAL | Q3: INFONAVIT | R3: INFONAVIT | S3: INFONAVIT | T3: INFONAVIT | U3: PRESTAMO | V3: APORTACION | W3: DESCUENTOS | Y3: TOTAL GENERAL | Z3: DIFERENCIAS | AA3: OBSERVACIONES
A4: SEI0009 | B4: SEITON - (CONSULTORIA II) | C4: Gutierrez Gutierrez Luis Arturo | D4: =VLOOKUP(C4,CPD!$B$9:$Y$37,24,0) -> 2774.4 | G4: =VLOOKUP(C4,SINDICATO!$C$7:$F$35,4,0) -> 1475.6 | H4: =VLOOKUP(C4,SINDICATO!$C$7:$G$35,5,0) -> 304.07 | I4: =VLOOKUP(C4,SINDICATO!$C$7:$H$34,6,0) -> 0 | K4: =+D4+E4+G4+H4+I4 -> 4554.07 | L4: =VLOOKUP(C4,ABC!$A$3:$B$88,2,0) -> 8500 | M4: =+L4/2 -> 4250 | O4: =VLOOKUP(C4,CPD!$B$9:$I$37,8,0) -> 0 | P4: =+H4+I4 -> 304.07 | Q4: =VLOOKUP(C4,CPD!$B$9:$R$37,17,0) -> 0 | R4: =VLOOKUP(C4,CPD!$B$9:$Q$37,16,0) -> 0 | S4: =VLOOKUP(C4,CPD!$B$9:$S$37,18,0) -> 0 | T4: =VLOOKUP(C4,CPD!$B$9:$T$37,19,0) -> 0 | W4: =VLOOKUP(C4,CPD!$B$9:$V$37,21,0) -> 0 | Y4: =+K4-O4-P4+Q4+R4+S4+T4+U4+V4+W4 -> 4250 | Z4: =+M4-Y4 -> 0
A5: SEI0010 | B5: SEITON - (CONSULTORIA II) | C5: Compean Tobias Braulio Gerardo | D5: =VLOOKUP(C5,CPD!$B$9:$Y$37,24,0) -> 4033.4 | G5: =VLOOKUP(C5,SINDICATO!$C$7:$F$35,4,0) -> 3645.92 | H5: =VLOOKUP(C5,SINDICATO!$C$7:$G$35,5,0) -> 2000 | I5: =VLOOKUP(C5,SINDICATO!$C$7:$H$34,6,0) -> 0 | K5: =+D5+E5+G5+H5+I5 -> 9679.32 | L5: =VLOOKUP(C5,ABC!$A$3:$B$88,2,0) -> 18000 | M5: =+L5/2 -> 9000 | O5: =VLOOKUP(C5,CPD!$B$9:$I$37,8,0) -> 0 | P5: =+H5+I5 -> 2000 | Q5: =VLOOKUP(C5,CPD!$B$9:$R$37,17,0) -> 1320.68 | R5: =VLOOKUP(C5,CPD!$B$9:$Q$37,16,0) -> 0 | S5: =VLOOKUP(C5,CPD!$B$9:$S$37,18,0) -> 0 | T5: =VLOOKUP(C5,CPD!$B$9:$T$37,19,0) -> 0 | W5: =VLOOKUP(C5,CPD!$B$9:$V$37,21,0) -> 0 | Y5: =+K5-O5-P5+Q5+R5+S5+T5+U5+V5+W5 -> 9000 | Z5: =+M5-Y5 -> 0
A6: SEI0026 | B6: SEITON - (CONSULTORIA II) | C6: Patricio Aguilar Jhonattan Cristian | D6: =VLOOKUP(C6,CPD!$B$9:$Y$37,24,0) -> 2911.8 | G6: =VLOOKUP(C6,SINDICATO!$C$7:$F$35,4,0) -> 1588.2 | H6: =VLOOKUP(C6,SINDICATO!$C$7:$G$35,5,0) -> 400 | I6: =VLOOKUP(C6,SINDICATO!$C$7:$H$34,6,0) -> 0 | K6: =+D6+E6+G6+H6+I6 -> 4900 | L6: =VLOOKUP(C6,ABC!$A$3:$B$88,2,0) -> 9000 | M6: =+L6/2 -> 4500 | O6: =VLOOKUP(C6,CPD!$B$9:$I$37,8,0) -> 0 | P6: =+H6+I6 -> 400 | Q6: =VLOOKUP(C6,CPD!$B$9:$R$37,17,0) -> 0 | R6: =VLOOKUP(C6,CPD!$B$9:$Q$37,16,0) -> 0 | S6: =VLOOKUP(C6,CPD!$B$9:$S$37,18,0) -> 0 | T6: =VLOOKUP(C6,CPD!$B$9:$T$37,19,0) -> 0 | W6: =VLOOKUP(C6,CPD!$B$9:$V$37,21,0) -> 0 | Y6: =+K6-O6-P6+Q6+R6+S6+T6+U6+V6+W6 -> 4500 | Z6: =+M6-Y6 -> 0
A7: SEI0039 | B7: SEITON - (CONSULTORIA II) | C7: Benavides Herrera Pablo | D7: =VLOOKUP(C7,CPD!$B$9:$Y$37,24,0) -> 11227.4 | G7: =VLOOKUP(C7,SINDICATO!$C$7:$F$35,4,0) -> 23772.6 | H7: =VLOOKUP(C7,SINDICATO!$C$7:$G$35,5,0) -> 0 | I7: =VLOOKUP(C7,SINDICATO!$C$7:$H$34,6,0) -> 0 | K7: =+D7+E7+G7+H7+I7 -> 35000 | L7: 70000 | M7: =+L7/2 -> 35000 | O7: =VLOOKUP(C7,CPD!$B$9:$I$37,8,0) -> 0 | P7: =+H7+I7 -> 0 | Q7: =VLOOKUP(C7,CPD!$B$9:$R$37,17,0) -> 0 | R7: =VLOOKUP(C7,CPD!$B$9:$Q$37,16,0) -> 0 | S7: =VLOOKUP(C7,CPD!$B$9:$S$37,18,0) -> 0 | T7: =VLOOKUP(C7,CPD!$B$9:$T$37,19,0) -> 0 | W7: =VLOOKUP(C7,CPD!$B$9:$V$37,21,0) -> 0 | Y7: =+K7-O7-P7+Q7+R7+S7+T7+U7+V7+W7 -> 35000 | Z7: =+M7-Y7 -> 0
A8: SEI0040 | B8: SEITON - (CONSULTORIA II) | C8: Mora Ramirez Acal Aldo Isidro | D8: =VLOOKUP(C8,CPD!$B$9:$Y$37,24,0) -> 4036 | G8: =VLOOKUP(C8,SINDICATO!$C$7:$F$35,4,0) -> 2464 | H8: =VLOOKUP(C8,SINDICATO!$C$7:$G$35,5,0) -> 0 | I8: =VLOOKUP(C8,SINDICATO!$C$7:$H$34,6,0) -> 0 | K8: =+D8+E8+G8+H8+I8 -> 6500 | L8: 13000 | M8: =+L8/2 -> 6500 | O8: =VLOOKUP(C8,CPD!$B$9:$I$37,8,0) -> 0 | P8: =+H8+I8 -> 0 | Q8: =VLOOKUP(C8,CPD!$B$9:$R$37,17,0) -> 0 | R8: =VLOOKUP(C8,CPD!$B$9:$Q$37,16,0) -> 0 | S8: =VLOOKUP(C8,CPD!$B$9:$S$37,18,0) -> 0 | T8: =VLOOKUP(C8,CPD!$B$9:$T$37,19,0) -> 0 | W8: =VLOOKUP(C8,CPD!$B$9:$V$37,21,0) -> 0 | Y8: =+K8-O8-P8+Q8+R8+S8+T8+U8+V8+W8 -> 6500 | Z8: =+M8-Y8 -> 0
A9: SEI0041 | B9: SEITON - (CONSULTORIA II) | C9: Vazquez Perez Miguel Angel | D9: =VLOOKUP(C9,CPD!$B$9:$Y$37,24,0) -> 5074 | G9: =VLOOKUP(C9,SINDICATO!$C$7:$F$35,4,0) -> 4176 | H9: =VLOOKUP(C9,SINDICATO!$C$7:$G$35,5,0) -> 0 | I9: =VLOOKUP(C9,SINDICATO!$C$7:$H$34,6,0) -> 0 | K9: =+D9+E9+G9+H9+I9 -> 9250 | L9: =VLOOKUP(C9,ABC!$A$3:$B$88,2,0) -> 18500 | M9: =+L9/2 -> 9250 | O9: =VLOOKUP(C9,CPD!$B$9:$I$37,8,0) -> 0 | P9: =+H9+I9 -> 0 | Q9: =VLOOKUP(C9,CPD!$B$9:$R$37,17,0) -> 0 | R9: =VLOOKUP(C9,CPD!$B$9:$Q$37,16,0) -> 0 | S9: =VLOOKUP(C9,CPD!$B$9:$S$37,18,0) -> 0 | T9: =VLOOKUP(C9,CPD!$B$9:$T$37,19,0) -> 0 | W9: =VLOOKUP(C9,CPD!$B$9:$V$37,21,0) -> 0 | Y9: =+K9-O9-P9+Q9+R9+S9+T9+U9+V9+W9 -> 9250 | Z9: =+M9-Y9 -> 0
A10: SEI0088 | B10: SEITON - (CONSULTORIA II) | C10: Morgado Fernandez Martin | D10: =VLOOKUP(C10,CPD!$B$9:$Y$37,24,0) -> 4899.6 | G10: =VLOOKUP(C10,SINDICATO!$C$7:$F$35,4,0) -> 2600.4 | H10: =VLOOKUP(C10,SINDICATO!$C$7:$G$35,5,0) -> 356.25 | I10: =VLOOKUP(C10,SINDICATO!$C$7:$H$34,6,0) -> 0 | K10: =+D10+E10+G10+H10+I10 -> 7856.25 | L10: =VLOOKUP(C10,ABC!$A$3:$B$88,2,0) -> 15000 | M10: =+L10/2 -> 7500 | O10: =VLOOKUP(C10,CPD!$B$9:$I$37,8,0) -> 0 | P10: =+H10+I10 -> 356.25 | Q10: =VLOOKUP(C10,CPD!$B$9:$R$37,17,0) -> 0 | R10: =VLOOKUP(C10,CPD!$B$9:$Q$37,16,0) -> 0 | S10: =VLOOKUP(C10,CPD!$B$9:$S$37,18,0) -> 0 | T10: =VLOOKUP(C10,CPD!$B$9:$T$37,19,0) -> 0 | W10: =VLOOKUP(C10,CPD!$B$9:$V$37,21,0) -> 0 | Y10: =+K10-O10-P10+Q10+R10+S10+T10+U10+V10+W10 -> 7500 | Z10: =+M10-Y10 -> 0
A11: SEI0097 | B11: SEITON - (CONSULTORIA II) | C11: Arreola Jimenez Jose Nieves | D11: =VLOOKUP(C11,CPD!$B$9:$Y$37,24,0) -> 1733 | G11: =VLOOKUP(C11,SINDICATO!$C$7:$F$35,4,0) -> 1557.91 | H11: =VLOOKUP(C11,SINDICATO!$C$7:$G$35,5,0) -> 432.22 | I11: =VLOOKUP(C11,SINDICATO!$C$7:$H$34,6,0) -> 0 | K11: =+D11+E11+G11+H11+I11 -> 3723.13 | L11: =VLOOKUP(C11,ABC!$A$3:$B$88,2,0) -> 10150 | M11: =+L11/2 -> 5075 | O11: =VLOOKUP(C11,CPD!$B$9:$I$37,8,0) -> 0 | P11: =+H11+I11 -> 432.22 | Q11: =VLOOKUP(C11,CPD!$B$9:$R$37,17,0) -> 1559.39 | R11: =VLOOKUP(C11,CPD!$B$9:$Q$37,16,0) -> 0 | S11: =VLOOKUP(C11,CPD!$B$9:$S$37,18,0) -> 0 | T11: =VLOOKUP(C11,CPD!$B$9:$T$37,19,0) -> 0 | W11: =VLOOKUP(C11,CPD!$B$9:$V$37,21,0) -> 224.7 | Y11: =+K11-O11-P11+Q11+R11+S11+T11+U11+V11+W11 -> 5075 | Z11: =+M11-Y11 -> 0
A12: SEI0099 | B12: SEITON - (CONSULTORIA II) | C12: Garcia Villicaña Ricardo Pascual | D12: =VLOOKUP(C12,CPD!$B$9:$Y$37,24,0) -> 4981.6 | G12: =VLOOKUP(C12,SINDICATO!$C$7:$F$35,4,0) -> 2600.4 | H12: =VLOOKUP(C12,SINDICATO!$C$7:$G$35,5,0) -> 891.47 | I12: =VLOOKUP(C12,SINDICATO!$C$7:$H$34,6,0) -> 68 | K12: =+D12+E12+G12+H12+I12 -> 8541.47 | L12: =VLOOKUP(C12,ABC!$A$3:$B$88,2,0) -> 15000 | M12: =+L12/2 -> 7500 | O12: =VLOOKUP(C12,CPD!$B$9:$I$37,8,0) -> 82 | P12: =+H12+I12 -> 959.47 | Q12: =VLOOKUP(C12,CPD!$B$9:$R$37,17,0) -> 0 | R12: =VLOOKUP(C12,CPD!$B$9:$Q$37,16,0) -> 0 | S12: =VLOOKUP(C12,CPD!$B$9:$S$37,18,0) -> 0 | T12: =VLOOKUP(C12,CPD!$B$9:$T$37,19,0) -> 0 | W12: =VLOOKUP(C12,CPD!$B$9:$V$37,21,0) -> 0 | Y12: =+K12-O12-P12+Q12+R12+S12+T12+U12+V12+W12 -> 7500 | Z12: =+M12-Y12 -> 0
A13: SEI0108 | B13: SEITON - (CONSULTORIA II) | C13: Caballero Diaz Francisco Javier | D13: =VLOOKUP(C13,CPD!$B$9:$Y$37,24,0) -> 1707 | G13: =VLOOKUP(C13,SINDICATO!$C$7:$F$35,4,0) -> 1558.18 | H13: =VLOOKUP(C13,SINDICATO!$C$7:$G$35,5,0) -> 366.93 | I13: =VLOOKUP(C13,SINDICATO!$C$7:$H$34,6,0) -> 0 | K13: =+D13+E13+G13+H13+I13 -> 3632.11 | L13: =VLOOKUP(C13,ABC!$A$3:$B$88,2,0) -> 10150 | M13: =+L13/2 -> 5075 | O13: =VLOOKUP(C13,CPD!$B$9:$I$37,8,0) -> 0 | P13: =+H13+I13 -> 366.93 | Q13: =VLOOKUP(C13,CPD!$B$9:$R$37,17,0) -> 1809.82 | R13: =VLOOKUP(C13,CPD!$B$9:$Q$37,16,0) -> 0 | S13: =VLOOKUP(C13,CPD!$B$9:$S$37,18,0) -> 0 | T13: =VLOOKUP(C13,CPD!$B$9:$T$37,19,0) -> 0 | W13: =VLOOKUP(C13,CPD!$B$9:$V$37,21,0) -> 0 | Y13: =+K13-O13-P13+Q13+R13+S13+T13+U13+V13+W13 -> 5075 | Z13: =+M13-Y13 -> 0
A14: SEI0116 | B14: SEITON - (CONSULTORIA II) | C14: Casillas Cardona Cesar Alejandro | D14: =VLOOKUP(C14,CPD!$B$9:$Y$37,24,0) -> 3063.8 | G14: =VLOOKUP(C14,SINDICATO!$C$7:$F$35,4,0) -> 1891.03 | H14: =VLOOKUP(C14,SINDICATO!$C$7:$G$35,5,0) -> 0 | I14: =VLOOKUP(C14,SINDICATO!$C$7:$H$34,6,0) -> 0 | K14: =+D14+E14+G14+H14+I14 -> 4954.83 | L14: =VLOOKUP(C14,ABC!$A$3:$B$88,2,0) -> 12000 | M14: =+L14/2 -> 6000 | O14: =VLOOKUP(C14,CPD!$B$9:$I$37,8,0) -> 0 | P14: =+H14+I14 -> 0 | Q14: =VLOOKUP(C14,CPD!$B$9:$R$37,17,0) -> 1045.17 | R14: =VLOOKUP(C14,CPD!$B$9:$Q$37,16,0) -> 0 | S14: =VLOOKUP(C14,CPD!$B$9:$S$37,18,0) -> 0 | T14: =VLOOKUP(C14,CPD!$B$9:$T$37,19,0) -> 0 | W14: =VLOOKUP(C14,CPD!$B$9:$V$37,21,0) -> 0 | Y14: =+K14-O14-P14+Q14+R14+S14+T14+U14+V14+W14 -> 6000 | Z14: =+M14-Y14 -> 0
A15: SEI0117 | B15: SEITON - (CONSULTORIA II) | C15: Mariscal Romero Luis Adrian | D15: =VLOOKUP(C15,CPD!$B$9:$Y$37,24,0) -> 2694.4 | G15: =VLOOKUP(C15,SINDICATO!$C$7:$F$35,4,0) -> 2751.04 | H15: =VLOOKUP(C15,SINDICATO!$C$7:$G$35,5,0) -> 150 | I15: =VLOOKUP(C15,SINDICATO!$C$7:$H$34,6,0) -> 0 | K15: =+D15+E15+G15+H15+I15 -> 5595.44 | L15: 15000 | M15: =+L15/2 -> 7500 | O15: =VLOOKUP(C15,CPD!$B$9:$I$37,8,0) -> 0 | P15: =+H15+I15 -> 150 | Q15: =VLOOKUP(C15,CPD!$B$9:$R$37,17,0) -> 1658.56 | R15: =VLOOKUP(C15,CPD!$B$9:$Q$37,16,0) -> 0 | S15: =VLOOKUP(C15,CPD!$B$9:$S$37,18,0) -> 0 | T15: =VLOOKUP(C15,CPD!$B$9:$T$37,19,0) -> 0 | W15: =VLOOKUP(C15,CPD!$B$9:$V$37,21,0) -> 396 | Y15: =+K15-O15-P15+Q15+R15+S15+T15+U15+V15+W15 -> 7500 | Z15: =+M15-Y15 -> 0
A16: SEI0118 | B16: SEITON - (CONSULTORIA II) | C16: Arroyo Ramirez Hector Hugo | D16: =VLOOKUP(C16,CPD!$B$9:$Y$37,24,0) -> 2586.6 | G16: =VLOOKUP(C16,SINDICATO!$C$7:$F$35,4,0) -> 2102.87 | H16: =VLOOKUP(C16,SINDICATO!$C$7:$G$35,5,0) -> 200 | I16: =VLOOKUP(C16,SINDICATO!$C$7:$H$34,6,0) -> 234.01 | K16: =+D16+E16+G16+H16+I16 -> 5123.48 | L16: =VLOOKUP(C16,ABC!$A$3:$B$88,2,0) -> 13000 | M16: =+L16/2 -> 6500 | O16: =VLOOKUP(C16,CPD!$B$9:$I$37,8,0) -> 285.99 | P16: =+H16+I16 -> 434.01 | Q16: =VLOOKUP(C16,CPD!$B$9:$R$37,17,0) -> 1418.5 | R16: =VLOOKUP(C16,CPD!$B$9:$Q$37,16,0) -> 0 | S16: =VLOOKUP(C16,CPD!$B$9:$S$37,18,0) -> 0 | T16: =VLOOKUP(C16,CPD!$B$9:$T$37,19,0) -> 0 | W16: =VLOOKUP(C16,CPD!$B$9:$V$37,21,0) -> 678.02 | Y16: =+K16-O16-P16+Q16+R16+S16+T16+U16+V16+W16 -> 6500 | Z16: =+M16-Y16 -> 0
A17: SEI0119 | B17: SEITON - (CONSULTORIA II) | C17: Dominguez Lopez Maria De Jesus | D17: =VLOOKUP(C17,CPD!$B$9:$Y$37,24,0) -> 3449.2 | G17: =VLOOKUP(C17,SINDICATO!$C$7:$F$35,4,0) -> 2102.95 | H17: =VLOOKUP(C17,SINDICATO!$C$7:$G$35,5,0) -> 0 | I17: =VLOOKUP(C17,SINDICATO!$C$7:$H$34,6,0) -> 0 | J17: 0 | K17: =+D17+E17+G17+H17+I17 -> 5552.15 | L17: 13000 | M17: =+L17/2 -> 6500 | O17: =VLOOKUP(C17,CPD!$B$9:$I$37,8,0) -> 0 | P17: =+H17+I17 -> 0 | Q17: =VLOOKUP(C17,CPD!$B$9:$R$37,17,0) -> 0 | R17: =VLOOKUP(C17,CPD!$B$9:$Q$37,16,0) -> 947.85 | S17: =VLOOKUP(C17,CPD!$B$9:$S$37,18,0) -> 0 | T17: =VLOOKUP(C17,CPD!$B$9:$T$37,19,0) -> 0 | W17: =VLOOKUP(C17,CPD!$B$9:$V$37,21,0) -> 0 | X17: 0 | Y17: =+K17-O17-P17+Q17+R17+S17+T17+U17+V17+W17 -> 6500 | Z17: =+M17-Y17 -> 0
A18: SEI0127 | B18: SEITON - (CONSULTORIA II) | C18: Hernandez Ochoa Eduardo | D18: =VLOOKUP(C18,CPD!$B$9:$Y$37,24,0) -> 4899.8 | G18: =VLOOKUP(C18,SINDICATO!$C$7:$F$35,4,0) -> 2600.2 | H18: =VLOOKUP(C18,SINDICATO!$C$7:$G$35,5,0) -> 371.43 | I18: =VLOOKUP(C18,SINDICATO!$C$7:$H$34,6,0) -> 0 | K18: =+D18+E18+G18+H18+I18 -> 7871.43 | L18: =VLOOKUP(C18,ABC!$A$3:$B$88,2,0) -> 15000 | M18: =+L18/2 -> 7500 | O18: =VLOOKUP(C18,CPD!$B$9:$I$37,8,0) -> 0 | P18: =+H18+I18 -> 371.43 | Q18: =VLOOKUP(C18,CPD!$B$9:$R$37,17,0) -> 0 | R18: =VLOOKUP(C18,CPD!$B$9:$Q$37,16,0) -> 0 | S18: =VLOOKUP(C18,CPD!$B$9:$S$37,18,0) -> 0 | T18: =VLOOKUP(C18,CPD!$B$9:$T$37,19,0) -> 0 | W18: =VLOOKUP(C18,CPD!$B$9:$V$37,21,0) -> 0 | Y18: =+K18-O18-P18+Q18+R18+S18+T18+U18+V18+W18 -> 7500 | Z18: =+M18-Y18 -> 0
A19: SEI0147 | B19: SEITON - (CONSULTORIA II) | C19: Diaz Munguia Martha Liliana | D19: =VLOOKUP(C19,CPD!$B$9:$Y$37,24,0) -> 5077.8 | G19: =VLOOKUP(C19,SINDICATO!$C$7:$F$35,4,0) -> 7009.15 | H19: =VLOOKUP(C19,SINDICATO!$C$7:$G$35,5,0) -> 0 | I19: =VLOOKUP(C19,SINDICATO!$C$7:$H$34,6,0) -> 0 | K19: =+D19+E19+G19+H19+I19 -> 12086.95 | L19: 25000 | M19: =+L19/2 -> 12500 | O19: =VLOOKUP(C19,CPD!$B$9:$I$37,8,0) -> 0 | P19: =+H19+I19 -> 0 | Q19: =VLOOKUP(C19,CPD!$B$9:$R$37,17,0) -> 413.05 | R19: =VLOOKUP(C19,CPD!$B$9:$Q$37,16,0) -> 0 | S19: =VLOOKUP(C19,CPD!$B$9:$S$37,18,0) -> 0 | T19: =VLOOKUP(C19,CPD!$B$9:$T$37,19,0) -> 0 | W19: =VLOOKUP(C19,CPD!$B$9:$V$37,21,0) -> 0 | Y19: =+K19-O19-P19+Q19+R19+S19+T19+U19+V19+W19 -> 12500 | Z19: =+M19-Y19 -> 0
A20: SEI0173 | B20: SEITON - (CONSULTORIA II) | C20: Nieto Ortiz Jose Luis | D20: =VLOOKUP(C20,CPD!$B$9:$Y$37,24,0) -> 1366.4 | G20: =VLOOKUP(C20,SINDICATO!$C$7:$F$35,4,0) -> 1483.06 | H20: =VLOOKUP(C20,SINDICATO!$C$7:$G$35,5,0) -> 103.16 | I20: =VLOOKUP(C20,SINDICATO!$C$7:$H$34,6,0) -> 0 | K20: =+D20+E20+G20+H20+I20 -> 2952.62 | L20: =VLOOKUP(C20,ABC!$A$3:$B$88,2,0) -> 10000 | M20: =+L20/2 -> 5000 | O20: =VLOOKUP(C20,CPD!$B$9:$I$37,8,0) -> 0 | P20: =+H20+I20 -> 103.16 | Q20: =VLOOKUP(C20,CPD!$B$9:$R$37,17,0) -> 2150.54 | R20: =VLOOKUP(C20,CPD!$B$9:$Q$37,16,0) -> 0 | S20: =VLOOKUP(C20,CPD!$B$9:$S$37,18,0) -> 0 | T20: =VLOOKUP(C20,CPD!$B$9:$T$37,19,0) -> 0 | W20: =VLOOKUP(C20,CPD!$B$9:$V$37,21,0) -> 0 | Y20: =+K20-O20-P20+Q20+R20+S20+T20+U20+V20+W20 -> 5000 | Z20: =+M20-Y20 -> 0
A21: SEI0221 | B21: SEITON - (CONSULTORIA II) | C21: Rogel Teran Marco Antonio | D21: =VLOOKUP(C21,CPD!$B$9:$Y$37,24,0) -> 16969.2 | G21: =VLOOKUP(C21,SINDICATO!$C$7:$F$35,4,0) -> 12613.2 | H21: =VLOOKUP(C21,SINDICATO!$C$7:$G$35,5,0) -> 0 | I21: =VLOOKUP(C21,SINDICATO!$C$7:$H$34,6,0) -> 0 | K21: =+D21+E21+G21+H21+I21 -> 29582.4 | L21: 60000 | M21: =+L21/2 -> 30000 | O21: =VLOOKUP(C21,CPD!$B$9:$I$37,8,0) -> 0 | P21: =+H21+I21 -> 0 | Q21: =VLOOKUP(C21,CPD!$B$9:$R$37,17,0) -> 0 | R21: =VLOOKUP(C21,CPD!$B$9:$Q$37,16,0) -> 0 | S21: =VLOOKUP(C21,CPD!$B$9:$S$37,18,0) -> 0 | T21: =VLOOKUP(C21,CPD!$B$9:$T$37,19,0) -> 0 | W21: =VLOOKUP(C21,CPD!$B$9:$V$37,21,0) -> 417.6 | Y21: =+K21-O21-P21+Q21+R21+S21+T21+U21+V21+W21 -> 30000 | Z21: =+M21-Y21 -> 0
A22: SEI0222 | B22: SEITON - (CONSULTORIA II) | C22: Saucedo Duran Jesus Alfredo | D22: =VLOOKUP(C22,CPD!$B$9:$Y$37,24,0) -> 4108.8 | G22: =VLOOKUP(C22,SINDICATO!$C$7:$F$35,4,0) -> 1891.2 | H22: =VLOOKUP(C22,SINDICATO!$C$7:$G$35,5,0) -> 0 | I22: =VLOOKUP(C22,SINDICATO!$C$7:$H$34,6,0) -> 0 | K22: =+D22+E22+G22+H22+I22 -> 6000 | L22: 12000 | M22: =+L22/2 -> 6000 | O22: =VLOOKUP(C22,CPD!$B$9:$I$37,8,0) -> 0 | P22: =+H22+I22 -> 0 | Q22: =VLOOKUP(C22,CPD!$B$9:$R$37,17,0) -> 0 | R22: =VLOOKUP(C22,CPD!$B$9:$Q$37,16,0) -> 0 | S22: =VLOOKUP(C22,CPD!$B$9:$S$37,18,0) -> 0 | T22: =VLOOKUP(C22,CPD!$B$9:$T$37,19,0) -> 0 | W22: =VLOOKUP(C22,CPD!$B$9:$V$37,21,0) -> 0 | Y22: =+K22-O22-P22+Q22+R22+S22+T22+U22+V22+W22 -> 6000 | Z22: =+M22-Y22 -> 0
A23: SEI032 | B23: SEITON - (CONSULTORIA II) | C23: Camarena Quiroz Erick Frank | D23: =VLOOKUP(C23,CPD!$B$9:$Y$37,24,0) -> 2912 | G23: =VLOOKUP(C23,SINDICATO!$C$7:$F$35,4,0) -> 1588 | H23: =VLOOKUP(C23,SINDICATO!$C$7:$G$35,5,0) -> 0 | I23: =VLOOKUP(C23,SINDICATO!$C$7:$H$34,6,0) -> 0 | K23: =+D23+E23+G23+H23+I23 -> 4500 | L23: =VLOOKUP(C23,ABC!$A$3:$B$88,2,0) -> 9000 | M23: =+L23/2 -> 4500 | O23: =VLOOKUP(C23,CPD!$B$9:$I$37,8,0) -> 0 | P23: =+H23+I23 -> 0 | Q23: =VLOOKUP(C23,CPD!$B$9:$R$37,17,0) -> 0 | R23: =VLOOKUP(C23,CPD!$B$9:$Q$37,16,0) -> 0 | S23: =VLOOKUP(C23,CPD!$B$9:$S$37,18,0) -> 0 | T23: =VLOOKUP(C23,CPD!$B$9:$T$37,19,0) -> 0 | W23: =VLOOKUP(C23,CPD!$B$9:$V$37,21,0) -> 0 | Y23: =+K23-O23-P23+Q23+R23+S23+T23+U23+V23+W23 -> 4500 | Z23: =+M23-Y23 -> 0
A24: SEI0401 | B24: SEITON - (CONSULTORIA II) | C24: De La Torre Zambara Francisco Ernesto | D24: =VLOOKUP(C24,CPD!$B$9:$Y$37,24,0) -> 3203.8 | G24: =VLOOKUP(C24,SINDICATO!$C$7:$F$35,4,0) -> 1558 | H24: =VLOOKUP(C24,SINDICATO!$C$7:$G$35,5,0) -> 393.43 | I24: =VLOOKUP(C24,SINDICATO!$C$7:$H$34,6,0) -> 0 | K24: =+D24+E24+G24+H24+I24 -> 5155.23 | L24: =VLOOKUP(C24,ABC!$A$3:$B$88,2,0) -> 10150 | M24: =+L24/2 -> 5075 | O24: =VLOOKUP(C24,CPD!$B$9:$I$37,8,0) -> 0 | P24: =+H24+I24 -> 393.43 | Q24: =VLOOKUP(C24,CPD!$B$9:$R$37,17,0) -> 0 | R24: =VLOOKUP(C24,CPD!$B$9:$Q$37,16,0) -> 0 | S24: =VLOOKUP(C24,CPD!$B$9:$S$37,18,0) -> 0 | T24: =VLOOKUP(C24,CPD!$B$9:$T$37,19,0) -> 0 | W24: =VLOOKUP(C24,CPD!$B$9:$V$37,21,0) -> 313.2 | Y24: =+K24-O24-P24+Q24+R24+S24+T24+U24+V24+W24 -> 5075 | Z24: =+M24-Y24 -> 0
A25: SEI0425 | B25: SEITON - (CONSULTORIA II) | C25: Carbajal Cabuto Jose Luis | D25: =VLOOKUP(C25,CPD!$B$9:$Y$37,24,0) -> 2024.8 | G25: =VLOOKUP(C25,SINDICATO!$C$7:$F$35,4,0) -> 1608.12 | H25: =VLOOKUP(C25,SINDICATO!$C$7:$G$35,5,0) -> 777.08 | I25: =VLOOKUP(C25,SINDICATO!$C$7:$H$34,6,0) -> 0 | K25: =+D25+E25+G25+H25+I25 -> 4410 | L25: =VLOOKUP(C25,ABC!$A$3:$B$88,2,0) -> 10250 | M25: =+L25/2 -> 5125 | O25: =VLOOKUP(C25,CPD!$B$9:$I$37,8,0) -> 0 | P25: =+H25+I25 -> 777.08 | Q25: =VLOOKUP(C25,CPD!$B$9:$R$37,17,0) -> 1492.08 | R25: =VLOOKUP(C25,CPD!$B$9:$Q$37,16,0) -> 0 | S25: =VLOOKUP(C25,CPD!$B$9:$S$37,18,0) -> 0 | T25: =VLOOKUP(C25,CPD!$B$9:$T$37,19,0) -> 0 | W25: =VLOOKUP(C25,CPD!$B$9:$V$37,21,0) -> 0 | Y25: =+K25-O25-P25+Q25+R25+S25+T25+U25+V25+W25 -> 5125 | Z25: =+M25-Y25 -> 0
A26: SEI0435 | B26: SEITON - (CONSULTORIA II) | C26: Benavides Herrera Alejandra | D26: =VLOOKUP(C26,CPD!$B$9:$Y$37,24,0) -> 3196.6 | G26: =VLOOKUP(C26,SINDICATO!$C$7:$F$35,4,0) -> 16803.4 | H26: =VLOOKUP(C26,SINDICATO!$C$7:$G$35,5,0) -> 0 | I26: =VLOOKUP(C26,SINDICATO!$C$7:$H$34,6,0) -> 0 | K26: =+D26+E26+G26+H26+I26 -> 20000 | L26: 40000 | M26: =+L26/2 -> 20000 | O26: =VLOOKUP(C26,CPD!$B$9:$I$37,8,0) -> 0 | P26: =+H26+I26 -> 0 | Q26: =VLOOKUP(C26,CPD!$B$9:$R$37,17,0) -> 0 | R26: =VLOOKUP(C26,CPD!$B$9:$Q$37,16,0) -> 0 | S26: =VLOOKUP(C26,CPD!$B$9:$S$37,18,0) -> 0 | T26: =VLOOKUP(C26,CPD!$B$9:$T$37,19,0) -> 0 | W26: =VLOOKUP(C26,CPD!$B$9:$V$37,21,0) -> 0 | Y26: =+K26-O26-P26+Q26+R26+S26+T26+U26+V26+W26 -> 20000 | Z26: =+M26-Y26 -> 0
A27: SEI0437 | B27: SEITON - (CONSULTORIA II) | C27: Leal Montaño Diego | D27: =VLOOKUP(C27,CPD!$B$9:$Y$37,24,0) -> 2904 | G27: =VLOOKUP(C27,SINDICATO!$C$7:$F$35,4,0) -> 1803.28 | H27: =VLOOKUP(C27,SINDICATO!$C$7:$G$35,5,0) -> 2810 | I27: =VLOOKUP(C27,SINDICATO!$C$7:$H$34,6,0) -> 100 | K27: =+D27+E27+G27+H27+I27 -> 7617.28 | L27: 10000 | M27: =+L27/2 -> 5000 | O27: =VLOOKUP(C27,CPD!$B$9:$I$37,8,0) -> 100 | P27: =+H27+I27 -> 2910 | Q27: =VLOOKUP(C27,CPD!$B$9:$R$37,17,0) -> 392.72 | R27: =VLOOKUP(C27,CPD!$B$9:$Q$37,16,0) -> 0 | S27: =VLOOKUP(C27,CPD!$B$9:$S$37,18,0) -> 0 | T27: =VLOOKUP(C27,CPD!$B$9:$T$37,19,0) -> 0 | W27: =VLOOKUP(C27,CPD!$B$9:$V$37,21,0) -> 0 | Y27: =+K27-O27-P27+Q27+R27+S27+T27+U27+V27+W27 -> 5000 | Z27: =+M27-Y27 -> 0
A28: SEI0440 | B28: SEITON - (CONSULTORIA II) | C28: Leija Arevalo Guadalupe | D28: =VLOOKUP(C28,CPD!$B$9:$Y$37,24,0) -> 979 | G28: =VLOOKUP(C28,SINDICATO!$C$7:$F$35,4,0) -> 0 | H28: =VLOOKUP(C28,SINDICATO!$C$7:$G$35,5,0) -> 0 | I28: =VLOOKUP(C28,SINDICATO!$C$7:$H$34,6,0) -> 0 | K28: =+D28+E28+G28+H28+I28 -> 979 | L28: 4000 | M28: =+L28/2 -> 2000 | O28: =VLOOKUP(C28,CPD!$B$9:$I$37,8,0) -> 0 | P28: =+H28+I28 -> 0 | Q28: =VLOOKUP(C28,CPD!$B$9:$R$37,17,0) -> 1044.75 | R28: =VLOOKUP(C28,CPD!$B$9:$Q$37,16,0) -> 0 | S28: =VLOOKUP(C28,CPD!$B$9:$S$37,18,0) -> 0 | T28: =VLOOKUP(C28,CPD!$B$9:$T$37,19,0) -> 0 | W28: =VLOOKUP(C28,CPD!$B$9:$V$37,21,0) -> 0 | Y28: =+K28-O28-P28+Q28+R28+S28+T28+U28+V28+W28 -> 2023.75 | Z28: =+M28-Y28 -> -23.75 | AA28: subsidio
A29: SEI0442 | B29: SEITON - (CONSULTORIA II) | C29: Sierra Escamilla Daniela | D29: =VLOOKUP(C29,CPD!$B$9:$Y$37,24,0) -> 4036 | G29: =VLOOKUP(C29,SINDICATO!$C$7:$F$35,4,0) -> 2464 | H29: =VLOOKUP(C29,SINDICATO!$C$7:$G$35,5,0) -> 0 | I29: =VLOOKUP(C29,SINDICATO!$C$7:$H$34,6,0) -> 0 | K29: =+D29+E29+G29+H29+I29 -> 6500 | L29: 13000 | M29: =+L29/2 -> 6500 | O29: =VLOOKUP(C29,CPD!$B$9:$I$37,8,0) -> 0 | P29: =+H29+I29 -> 0 | Q29: =VLOOKUP(C29,CPD!$B$9:$R$37,17,0) -> 0 | R29: =VLOOKUP(C29,CPD!$B$9:$Q$37,16,0) -> 0 | S29: =VLOOKUP(C29,CPD!$B$9:$S$37,18,0) -> 0 | T29: =VLOOKUP(C29,CPD!$B$9:$T$37,19,0) -> 0 | W29: =VLOOKUP(C29,CPD!$B$9:$V$37,21,0) -> 0 | Y29: =+K29-O29-P29+Q29+R29+S29+T29+U29+V29+W29 -> 6500 | Z29: =+M29-Y29 -> 0
A30: SEI0445 | B30: SEITON - (CONSULTORIA II) | C30: Muñoz Melgoza Gabriel | D30: =VLOOKUP(C30,CPD!$B$9:$Y$37,24,0) -> 4609.4 | G30: =VLOOKUP(C30,SINDICATO!$C$7:$F$35,4,0) -> 3090.6 | H30: =VLOOKUP(C30,SINDICATO!$C$7:$G$35,5,0) -> 616 | I30: =VLOOKUP(C30,SINDICATO!$C$7:$H$34,6,0) -> 0 | K30: =+D30+E30+G30+H30+I30 -> 8316 | L30: 15400 | M30: =+L30/2 -> 7700 | O30: =VLOOKUP(C30,CPD!$B$9:$I$37,8,0) -> 0 | P30: =+H30+I30 -> 616 | Q30: =VLOOKUP(C30,CPD!$B$9:$R$37,17,0) -> 0 | R30: =VLOOKUP(C30,CPD!$B$9:$Q$37,16,0) -> 0 | S30: =VLOOKUP(C30,CPD!$B$9:$S$37,18,0) -> 0 | T30: =VLOOKUP(C30,CPD!$B$9:$T$37,19,0) -> 0 | W30: =VLOOKUP(C30,CPD!$B$9:$V$37,21,0) -> 0 | Y30: =+K30-O30-P30+Q30+R30+S30+T30+U30+V30+W30 -> 7700 | Z30: =+M30-Y30 -> 0
A31: SEI0447 | B31: SEITON - (CONSULTORIA II) | C31: Oliver Olague Vicente | D31: =VLOOKUP(C31,CPD!$B$9:$Y$37,24,0) -> 5213.2 | G31: =VLOOKUP(C31,SINDICATO!$C$7:$F$35,4,0) -> 3286.8 | H31: =VLOOKUP(C31,SINDICATO!$C$7:$G$35,5,0) -> 0 | I31: =VLOOKUP(C31,SINDICATO!$C$7:$H$34,6,0) -> 0 | K31: =+D31+E31+G31+H31+I31 -> 8500 | L31: 17000 | M31: =+L31/2 -> 8500 | O31: =VLOOKUP(C31,CPD!$B$9:$I$37,8,0) -> 0 | P31: =+H31+I31 -> 0 | Q31: =VLOOKUP(C31,CPD!$B$9:$R$37,17,0) -> 0 | R31: =VLOOKUP(C31,CPD!$B$9:$Q$37,16,0) -> 0 | S31: =VLOOKUP(C31,CPD!$B$9:$S$37,18,0) -> 0 | T31: =VLOOKUP(C31,CPD!$B$9:$T$37,19,0) -> 0 | W31: =VLOOKUP(C31,CPD!$B$9:$V$37,21,0) -> 0 | Y31: =+K31-O31-P31+Q31+R31+S31+T31+U31+V31+W31 -> 8500 | Z31: =+M31-Y31 -> 0
A32: SEI0448 | B32: SEITON - (CONSULTORIA II) | C32: Rodriguez Chavez Oswaldo Emmanuel | D32: =VLOOKUP(C32,CPD!$B$9:$Y$37,24,0) -> 4327.4 | G32: =VLOOKUP(C32,SINDICATO!$C$7:$F$35,4,0) -> 2672.6 | H32: =VLOOKUP(C32,SINDICATO!$C$7:$G$35,5,0) -> 1200 | K32: =+D32+E32+G32+H32+I32 -> 8200 | L32: 14000 | M32: =+L32/2 -> 7000 | O32: =VLOOKUP(C32,CPD!$B$9:$I$37,8,0) -> 0 | Q32: =VLOOKUP(C32,CPD!$B$9:$R$37,17,0) -> 0 | R32: =VLOOKUP(C32,CPD!$B$9:$Q$37,16,0) -> 0 | S32: =VLOOKUP(C32,CPD!$B$9:$S$37,18,0) -> 0 | T32: =VLOOKUP(C32,CPD!$B$9:$T$37,19,0) -> 0 | W32: =VLOOKUP(C32,CPD!$B$9:$V$37,21,0) -> 0 | Y32: =+K32-O32-P32+Q32+R32+S32+T32+U32+V32+W32 -> 8200 | Z32: =+M32-Y32 -> -1200
C33: TOTAL GENERAL CONSULTORIA | D33: =SUM(D4:D32) -> 121000.4 | E33: =SUM(E4:E32) -> 0 | F33: =SUM(F4:F32) -> 0 | G33: =SUM(G4:G32) -> 114758.71 | H33: =SUM(H4:H32) -> 11372.04 | I33: =SUM(I4:I32) -> 402.01 | J33: =SUM(J4:J32) -> 0 | K33: =SUM(K4:K32) -> 247533.16 | ... Y33: =SUM(Y4:Y32) -> 253773.75 | Z33: =SUM(Z4:Z29) -> -23.75 | AA33: =SUM(AA4:AA29) -> 0 | AB33: =SUM(AB4:AB29) -> 0 | AC33: =SUM(AC4:AC29) -> 0 | AD33: =SUM(AD4:AD29) -> 0 | AE33: =SUM(AE4:AE29) -> 0 | AF33: =SUM(AF4:AF29) -> 0 | AG33: =SUM(AG4:AG29) -> 0 | AH33: =SUM(AH4:AH28) -> 0 | AI33: =SUM(AI4:AI28) -> 0 | AJ33: =SUM(AJ4:AJ28) -> 0 | AK33: =SUM(AK4:AK28) -> 0
K34: =+D34+E34+G34+H34+I34 -> 0
A35: SEI0010 | B35: SEITON (IP INNOVA II) | C35: Torres Ricardez Alfredo | E35: =VLOOKUP(C35,IP!$B$9:$V$117,21,0) -> 3585.2 | G35: =VLOOKUP(C35,SINDICATO!$C$36:$F$144,4,0) -> 414.8 | H35: =VLOOKUP(C35,SINDICATO!$C$36:$G$144,5,0) -> 340.28 | I35: =VLOOKUP(C35,SINDICATO!$C$36:$H$132,6,0) -> 0 | K35: =+D35+E35+G35+H35+I35 -> 4340.28 | L35: =VLOOKUP(C35,ABC!$A$3:$B$88,2,0) -> 8000 | M35: =+L35/2 -> 4000 | O35: =VLOOKUP(C35,IP!$B$9:$I$117,8,0) -> 0 | P35: =+H35+I35 -> 340.28 | Q35: =VLOOKUP(C35,IP!$B$9:$N$117,13,0) -> 0 | R35: =VLOOKUP(C35,IP!$B$9:$O$117,14,0) -> 0 | T35: =VLOOKUP(C35,IP!$B$9:$P$117,15,0) -> 0 | U35: =VLOOKUP(C35,IP!$B$9:$Q$117,16,0) -> 0 | V35: 0 | W35: =VLOOKUP(C35,IP!B$9:R$117,17,0) -> 0 | Y35: =+K35-O35-P35+Q35+R35+S35+T35+U35+V35+W35 -> 4000 | Z35: =+M35-Y35 -> 0
A36: SEI0014 | B36: SEITON (IP INNOVA II) | C36: Montoya Portillo Carlos Alberto | E36: =VLOOKUP(C36,IP!$B$9:$V$117,21,0) -> 3585.4 | G36: =VLOOKUP(C36,SINDICATO!$C$36:$F$144,4,0) -> 414.6 | H36: =VLOOKUP(C36,SINDICATO!$C$36:$G$144,5,0) -> 196.43 | I36: =VLOOKUP(C36,SINDICATO!$C$36:$H$132,6,0) -> 0 | K36: =+D36+E36+G36+H36+I36 -> 4196.43 | L36: 8000 | M36: =+L36/2 -> 4000 | O36: =VLOOKUP(C36,IP!$B$9:$I$117,8,0) -> 0 | P36: =+H36+I36 -> 196.43 | Q36: =VLOOKUP(C36,IP!$B$9:$N$117,13,0) -> 0 | R36: =VLOOKUP(C36,IP!$B$9:$O$117,14,0) -> 0 | T36: =VLOOKUP(C36,IP!$B$9:$P$117,15,0) -> 0 | U36: =VLOOKUP(C36,IP!$B$9:$Q$117,16,0) -> 0 | V36: 0 | W36: =VLOOKUP(C36,IP!B$9:R$117,17,0) -> 0 | Y36: =+K36-O36-P36+Q36+R36+S36+T36+U36+V36+W36 -> 4000 | Z36: =+M36-Y36 -> 0
A37: SEI0016 | B37: SEITON (IP INNOVA II) | C37: Negrete Bejar Aide Sarai | E37: =VLOOKUP(C37,IP!$B$9:$V$117,21,0) -> 1103.6 | G37: =VLOOKUP(C37,SINDICATO!$C$36:$F$144,4,0) -> 17.67 | H37: =VLOOKUP(C37,SINDICATO!$C$36:$G$144,5,0) -> 1190.43 | I37: =VLOOKUP(C37,SINDICATO!$C$36:$H$132,6,0) -> 0 | K37: =+D37+E37+G37+H37+I37 -> 2311.7 | L37: =VLOOKUP(C37,ABC!$A$3:$B$88,2,0) -> 4620 | M37: =+L37/2 -> 2310 | O37: =VLOOKUP(C37,IP!$B$9:$I$117,8,0) -> 0 | P37: =+H37+I37 -> 1190.43 | Q37: =VLOOKUP(C37,IP!$B$9:$N$117,13,0) -> 1188.73 | R37: =VLOOKUP(C37,IP!$B$9:$O$117,14,0) -> 0 | T37: =VLOOKUP(C37,IP!$B$9:$P$117,15,0) -> 0 | U37: =VLOOKUP(C37,IP!$B$9:$Q$117,16,0) -> 0 | V37: 0 | W37: =VLOOKUP(C37,IP!B$9:R$117,17,0) -> 0 | Y37: =+K37-O37-P37+Q37+R37+S37+T37+U37+V37+W37 -> 2310 | Z37: =+M37-Y37 -> 0
A38: SEI0017 | B38: SEITON (IP INNOVA II) | C38: Muñoz Reyes Luis Eduardo | E38: =VLOOKUP(C38,IP!$B$9:$V$117,21,0) -> 2707 | G38: =VLOOKUP(C38,SINDICATO!$C$36:$F$144,4,0) -> 414.64 | H38: =VLOOKUP(C38,SINDICATO!$C$36:$G$144,5,0) -> 283.34 | I38: =VLOOKUP(C38,SINDICATO!$C$36:$H$132,6,0) -> 0 | K38: =+D38+E38+G38+H38+I38 -> 3404.98 | L38: =VLOOKUP(C38,ABC!$A$3:$B$88,2,0) -> 8000 | M38: =+L38/2 -> 4000 | O38: =VLOOKUP(C38,IP!$B$9:$I$117,8,0) -> 0 | P38: =+H38+I38 -> 283.34 | Q38: =VLOOKUP(C38,IP!$B$9:$N$117,13,0) -> 878.36 | R38: =VLOOKUP(C38,IP!$B$9:$O$117,14,0) -> 0 | T38: =VLOOKUP(C38,IP!$B$9:$P$117,15,0) -> 0 | U38: =VLOOKUP(C38,IP!$B$9:$Q$117,16,0) -> 0 | V38: 0 | W38: =VLOOKUP(C38,IP!B$9:R$117,17,0) -> 0 | Y38: =+K38-O38-P38+Q38+R38+S38+T38+U38+V38+W38 -> 4000 | Z38: =+M38-Y38 -> 0
A39: SEI0018 | B39: SEITON (IP INNOVA II) | C39: Dominguez Mendez Victor Manuel | E39: =VLOOKUP(C39,IP!$B$9:$V$117,21,0) -> 4004 | G39: =VLOOKUP(C39,SINDICATO!$C$36:$F$144,4,0) -> 496 | H39: =VLOOKUP(C39,SINDICATO!$C$36:$G$144,5,0) -> 438.81 | I39: =VLOOKUP(C39,SINDICATO!$C$36:$H$132,6,0) -> 0 | K39: =+D39+E39+G39+H39+I39 -> 4938.81 | L39: =VLOOKUP(C39,ABC!$A$3:$B$88,2,0) -> 9000 | M39: =+L39/2 -> 4500 | O39: =VLOOKUP(C39,IP!$B$9:$I$117,8,0) -> 0 | P39: =+H39+I39 -> 438.81 | Q39: =VLOOKUP(C39,IP!$B$9:$N$117,13,0) -> 0 | R39: =VLOOKUP(C39,IP!$B$9:$O$117,14,0) -> 0 | T39: =VLOOKUP(C39,IP!$B$9:$P$117,15,0) -> 0 | U39: =VLOOKUP(C39,IP!$B$9:$Q$117,16,0) -> 0 | V39: 0 | W39: =VLOOKUP(C39,IP!B$9:R$117,17,0) -> 0 | Y39: =+K39-O39-P39+Q39+R39+S39+T39+U39+V39+W39 -> 4500 | Z39: =+M39-Y39 -> 0
A40: SEI0019 | B40: SEITON (IP INNOVA II) | C40: Gonzalez Rasgado Miguel Isaias | E40: =VLOOKUP(C40,IP!$B$9:$V$117,21,0) -> 5435.2 | G40: =VLOOKUP(C40,SINDICATO!$C$36:$F$144,4,0) -> 804.8 | H40: =VLOOKUP(C40,SINDICATO!$C$36:$G$144,5,0) -> 980 | I40: =VLOOKUP(C40,SINDICATO!$C$36:$H$132,6,0) -> 0 | K40: =+D40+E40+G40+H40+I40 -> 7220 | L40: =VLOOKUP(C40,ABC!$A$3:$B$88,2,0) -> 12000 | M40: =+L40/2 -> 6000 | O40: =VLOOKUP(C40,IP!$B$9:$I$117,8,0) -> 240 | P40: =+H40+I40 -> 980 | Q40: =VLOOKUP(C40,IP!$B$9:$N$117,13,0) -> 0 | R40: =VLOOKUP(C40,IP!$B$9:$O$117,14,0) -> 0 | T40: =VLOOKUP(C40,IP!$B$9:$P$117,15,0) -> 0 | U40: =VLOOKUP(C40,IP!$B$9:$Q$117,16,0) -> 0 | V40: 0 | W40: =VLOOKUP(C40,IP!B$9:R$117,17,0) -> 0 | Y40: =+K40-O40-P40+Q40+R40+S40+T40+U40+V40+W40 -> 6000 | Z40: =+M40-Y40 -> 0
A41: SEI0020 | B41: SEITON (IP INNOVA II) | C41: Mar Marquez Cesar Eduardo | E41: =VLOOKUP(C41,IP!$B$9:$V$117,21,0) -> 3585.4 | G41: =VLOOKUP(C41,SINDICATO!$C$36:$F$144,4,0) -> 414.6 | H41: =VLOOKUP(C41,SINDICATO!$C$36:$G$144,5,0) -> 1192.5 | I41: =VLOOKUP(C41,SINDICATO!$C$36:$H$132,6,0) -> 0 | K41: =+D41+E41+G41+H41+I41 -> 5192.5 | L41: 8000 | M41: =+L41/2 -> 4000 | O41: =VLOOKUP(C41,IP!$B$9:$I$117,8,0) -> 0 | P41: =+H41+I41 -> 1192.5 | Q41: =VLOOKUP(C41,IP!$B$9:$N$117,13,0) -> 0 | R41: =VLOOKUP(C41,IP!$B$9:$O$117,14,0) -> 0 | T41: =VLOOKUP(C41,IP!$B$9:$P$117,15,0) -> 0 | U41: =VLOOKUP(C41,IP!$B$9:$Q$117,16,0) -> 0 | V41: 0 | W41: =VLOOKUP(C41,IP!B$9:R$117,17,0) -> 0 | Y41: =+K41-O41-P41+Q41+R41+S41+T41+U41+V41+W41 -> 4000 | Z41: =+M41-Y41 -> 0
A42: SEI0021 | B42: SEITON (IP INNOVA II) | C42: Velez Rodriguez Jaime | E42: =VLOOKUP(C42,IP!$B$9:$V$117,21,0) -> 1502.4 | G42: =VLOOKUP(C42,SINDICATO!$C$36:$F$144,4,0) -> 1135.12 | H42: =VLOOKUP(C42,SINDICATO!$C$36:$G$144,5,0) -> 0 | I42: =VLOOKUP(C42,SINDICATO!$C$36:$H$132,6,0) -> 0 | K42: =+D42+E42+G42+H42+I42 -> 2637.52 | L42: 8000 | M42: =+L42/2 -> 4000 | O42: =VLOOKUP(C42,IP!$B$9:$I$117,8,0) -> 0 | P42: =+H42+I42 -> 0 | Q42: =VLOOKUP(C42,IP!$B$9:$N$117,13,0) -> 1362.48 | R42: =VLOOKUP(C42,IP!$B$9:$O$117,14,0) -> 0 | T42: =VLOOKUP(C42,IP!$B$9:$P$117,15,0) -> 0 | U42: =VLOOKUP(C42,IP!$B$9:$Q$117,16,0) -> 0 | V42: 0 | W42: =VLOOKUP(C42,IP!B$9:R$117,17,0) -> 0 | Y42: =+K42-O42-P42+Q42+R42+S42+T42+U42+V42+W42 -> 4000 | Z42: =+M42-Y42 -> 0
A43: SEI0022 | B43: SEITON (IP INNOVA II) | C43: Najera Lopez Raul | E43: =VLOOKUP(C43,IP!$B$9:$V$117,21,0) -> 4406.4 | G43: =VLOOKUP(C43,SINDICATO!$C$36:$F$144,4,0) -> 593.6 | H43: =VLOOKUP(C43,SINDICATO!$C$36:$G$144,5,0) -> 831.72 | I43: =VLOOKUP(C43,SINDICATO!$C$36:$H$132,6,0) -> 0 | K43: =+D43+E43+G43+H43+I43 -> 5831.72 | L43: =VLOOKUP(C43,ABC!$A$3:$B$88,2,0) -> 10000 | M43: =+L43/2 -> 5000 | O43: =VLOOKUP(C43,IP!$B$9:$I$117,8,0) -> 0 | P43: =+H43+I43 -> 831.72 | Q43: =VLOOKUP(C43,IP!$B$9:$N$117,13,0) -> 0 | R43: =VLOOKUP(C43,IP!$B$9:$O$117,14,0) -> 0 | T43: =VLOOKUP(C43,IP!$B$9:$P$117,15,0) -> 0 | U43: =VLOOKUP(C43,IP!$B$9:$Q$117,16,0) -> 0 | V43: 0 | W43: =VLOOKUP(C43,IP!B$9:R$117,17,0) -> 0 | Y43: =+K43-O43-P43+Q43+R43+S43+T43+U43+V43+W43 -> 5000 | Z43: =+M43-Y43 -> 0
A44: SEI0023 | B44: SEITON (IP INNOVA II) | C44: Puente Murguia Luis Felipe | E44: =VLOOKUP(C44,IP!$B$9:$V$117,21,0) -> 3277.4 | G44: =VLOOKUP(C44,SINDICATO!$C$36:$F$144,4,0) -> 222.6 | H44: =VLOOKUP(C44,SINDICATO!$C$36:$G$144,5,0) -> 553.4 | I44: =VLOOKUP(C44,SINDICATO!$C$36:$H$132,6,0) -> 0 | K44: =+D44+E44+G44+H44+I44 -> 4053.4 | L44: =VLOOKUP(C44,ABC!$A$3:$B$88,2,0) -> 7000 | M44: =+L44/2 -> 3500 | O44: =VLOOKUP(C44,IP!$B$9:$I$117,8,0) -> 0 | P44: =+H44+I44 -> 553.4 | Q44: =VLOOKUP(C44,IP!$B$9:$N$117,13,0) -> 0 | R44: =VLOOKUP(C44,IP!$B$9:$O$117,14,0) -> 0 | T44: =VLOOKUP(C44,IP!$B$9:$P$117,15,0) -> 0 | U44: =VLOOKUP(C44,IP!$B$9:$Q$117,16,0) -> 0 | V44: 0 | W44: =VLOOKUP(C44,IP!B$9:R$117,17,0) -> 0 | Y44: =+K44-O44-P44+Q44+R44+S44+T44+U44+V44+W44 -> 3500 | Z44: =+M44-Y44 -> 0
A45: SEI0029 | B45: SEITON (IP INNOVA II) | C45: Arceo Garcia Manuel Federico | E45: =VLOOKUP(C45,IP!$B$9:$V$117,21,0) -> 1064.8 | G45: =VLOOKUP(C45,SINDICATO!$C$36:$F$144,4,0) -> 135.2 | H45: =VLOOKUP(C45,SINDICATO!$C$36:$G$144,5,0) -> 1000 | I45: =VLOOKUP(C45,SINDICATO!$C$36:$H$132,6,0) -> 0 | K45: =+D45+E45+G45+H45+I45 -> 2200 | L45: =VLOOKUP(C45,ABC!$A$3:$B$88,2,0) -> 6000 | M45: =+L45/2 -> 3000 | O45: =VLOOKUP(C45,IP!$B$9:$I$117,8,0) -> 0 | P45: =+H45+I45 -> 1000 | Q45: =VLOOKUP(C45,IP!$B$9:$N$117,13,0) -> 0 | R45: =VLOOKUP(C45,IP!$B$9:$O$117,14,0) -> 0 | T45: =VLOOKUP(C45,IP!$B$9:$P$117,15,0) -> 0 | U45: =VLOOKUP(C45,IP!$B$9:$Q$117,16,0) -> 1800 | V45: 0 | W45: =VLOOKUP(C45,IP!B$9:R$117,17,0) -> 0 | Y45: =+K45-O45-P45+Q45+R45+S45+T45+U45+V45+W45 -> 3000 | Z45: =+M45-Y45 -> 0
A46: SEI0031 | B46: SEITON (IP INNOVA II) | C46: Contreras Zetina Victor Hugo | E46: =VLOOKUP(C46,IP!$B$9:$V$117,21,0) -> 3234.2 | G46: =VLOOKUP(C46,SINDICATO!$C$36:$F$144,4,0) -> 215.8 | H46: =VLOOKUP(C46,SINDICATO!$C$36:$G$144,5,0) -> 0 | I46: =VLOOKUP(C46,SINDICATO!$C$36:$H$132,6,0) -> 0 | K46: =+D46+E46+G46+H46+I46 -> 3450 | L46: =VLOOKUP(C46,ABC!$A$3:$B$88,2,0) -> 6900 | M46: =+L46/2 -> 3450 | O46: =VLOOKUP(C46,IP!$B$9:$I$117,8,0) -> 0 | P46: =+H46+I46 -> 0 | Q46: =VLOOKUP(C46,IP!$B$9:$N$117,13,0) -> 0 | R46: =VLOOKUP(C46,IP!$B$9:$O$117,14,0) -> 0 | T46: =VLOOKUP(C46,IP!$B$9:$P$117,15,0) -> 0 | U46: =VLOOKUP(C46,IP!$B$9:$Q$117,16,0) -> 0 | V46: 0 | W46: =VLOOKUP(C46,IP!B$9:R$117,17,0) -> 0 | Y46: =+K46-O46-P46+Q46+R46+S46+T46+U46+V46+W46 -> 3450 | Z46: =+M46-Y46 -> 0
A47: SEI0037 | B47: SEITON (IP INNOVA II) | C47: Gomez Oliveros Alin | E47: =VLOOKUP(C47,IP!$B$9:$V$117,21,0) -> 2864.8 | G47: =VLOOKUP(C47,SINDICATO!$C$36:$F$144,4,0) -> 2135.2 | H47: =VLOOKUP(C47,SINDICATO!$C$36:$G$144,5,0) -> 9882.23 | I47: =VLOOKUP(C47,SINDICATO!$C$36:$H$132,6,0) -> 0 | K47: =+D47+E47+G47+H47+I47 -> 14882.23 | L47: 10000 | M47: =+L47/2 -> 5000 | O47: =VLOOKUP(C47,IP!$B$9:$I$117,8,0) -> 0 | P47: =+H47+I47 -> 9882.23 | Q47: =VLOOKUP(C47,IP!$B$9:$N$117,13,0) -> 0 | R47: =VLOOKUP(C47,IP!$B$9:$O$117,14,0) -> 0 | T47: =VLOOKUP(C47,IP!$B$9:$P$117,15,0) -> 0 | U47: =VLOOKUP(C47,IP!$B$9:$Q$117,16,0) -> 0 | V47: 0 | W47: =VLOOKUP(C47,IP!B$9:R$117,17,0) -> 0 | Y47: =+K47-O47-P47+Q47+R47+S47+T47+U47+V47+W47 -> 5000 | Z47: =+M47-Y47 -> 0
A48: SEI0078 | B48: SEITON (IP INNOVA II) | C48: Aguilar Leal Karina Livier | E48: =VLOOKUP(C48,IP!$B$9:$V$117,21,0) -> 3583.6 | G48: =VLOOKUP(C48,SINDICATO!$C$36:$F$144,4,0) -> 917 | H48: =VLOOKUP(C48,SINDICATO!$C$36:$G$144,5,0) -> 27481.6 | I48: =VLOOKUP(C48,SINDICATO!$C$36:$H$132,6,0) -> 0 | K48: =+D48+E48+G48+H48+I48 -> 31982.2 | L48: 9000 | M48: =+L48/2 -> 4500 | O48: =VLOOKUP(C48,IP!$B$9:$I$117,8,0) -> 0 | P48: =+H48+I48 -> 27481.6 | Q48: =VLOOKUP(C48,IP!$B$9:$N$117,13,0) -> 0 | R48: =VLOOKUP(C48,IP!$B$9:$O$117,14,0) -> 0 | T48: =VLOOKUP(C48,IP!$B$9:$P$117,15,0) -> 0 | U48: =VLOOKUP(C48,IP!$B$9:$Q$117,16,0) -> 0 | V48: 0 | W48: =VLOOKUP(C48,IP!B$9:R$117,17,0) -> 0 | Y48: =+K48-O48-P48+Q48+R48+S48+T48+U48+V48+W48 -> 4500.6
A49: SEI0079 | B49: SEITON (IP INNOVA II) | C49: Amezcua Contreras Martha Frine | E49: =VLOOKUP(C49,IP!$B$9:$V$117,21,0) -> 7087.6 | G49: =VLOOKUP(C49,SINDICATO!$C$36:$F$144,4,0) -> 2162.4 | H49: =VLOOKUP(C49,SINDICATO!$C$36:$G$144,5,0) -> 750 | I49: =VLOOKUP(C49,SINDICATO!$C$36:$H$132,6,0) -> 0 | K49: =+D49+E49+G49+H49+I49 -> 10000 | L49: =VLOOKUP(C49,ABC!$A$3:$B$88,2,0) -> 18500 | M49: =+L49/2 -> 9250 | O49: =VLOOKUP(C49,IP!$B$9:$I$117,8,0) -> 0 | P49: =+H49+I49 -> 750 | Q49: =VLOOKUP(C49,IP!$B$9:$N$117,13,0) -> 0 | R49: =VLOOKUP(C49,IP!$B$9:$O$117,14,0) -> 0 | T49: =VLOOKUP(C49,IP!$B$9:$P$117,15,0) -> 0 | U49: =VLOOKUP(C49,IP!$B$9:$Q$117,16,0) -> 0 | V49: 0 | W49: =VLOOKUP(C49,IP!B$9:R$117,17,0) -> 0 | Y49: =+K49-O49-P49+Q49+R49+S49+T49+U49+V49+W49 -> 9250 | Z49: =+M49-Y49 -> 0
A50: SEI0081 | B50: SEITON (IP INNOVA II) | C50: Guizar Perez Sergio | E50: =VLOOKUP(C50,IP!$B$9:$V$117,21,0) -> 3368.2 | G50: =VLOOKUP(C50,SINDICATO!$C$36:$F$144,4,0) -> 881.8 | H50: =VLOOKUP(C50,SINDICATO!$C$36:$G$144,5,0) -> 250 | I50: =VLOOKUP(C50,SINDICATO!$C$36:$H$132,6,0) -> 0 | K50: =+D50+E50+G50+H50+I50 -> 4500 | L50: =VLOOKUP(C50,ABC!$A$3:$B$88,2,0) -> 8500 | M50: =+L50/2 -> 4250 | O50: =VLOOKUP(C50,IP!$B$9:$I$117,8,0) -> 0 | P50: =+H50+I50 -> 250 | Q50: =VLOOKUP(C50,IP!$B$9:$N$117,13,0) -> 0 | R50: =VLOOKUP(C50,IP!$B$9:$O$117,14,0) -> 0 | T50: =VLOOKUP(C50,IP!$B$9:$P$117,15,0) -> 0 | U50: =VLOOKUP(C50,IP!$B$9:$Q$117,16,0) -> 0 | V50: 0 | W50: =VLOOKUP(C50,IP!B$9:R$117,17,0) -> 0 | Y50: =+K50-O50-P50+Q50+R50+S50+T50+U50+V50+W50 -> 4250 | Z50: =+M50-Y50 -> 0
A51: SEI0100 | B51: SEITON (IP INNOVA II) | C51: Quinto Valle Martin | E51: =VLOOKUP(C51,IP!$B$9:$V$117,21,0) -> 3906.4 | G51: =VLOOKUP(C51,SINDICATO!$C$36:$F$144,4,0) -> 593.6 | H51: =VLOOKUP(C51,SINDICATO!$C$36:$G$144,5,0) -> 500 | I51: =VLOOKUP(C51,SINDICATO!$C$36:$H$132,6,0) -> 0 | K51: =+D51+E51+G51+H51+I51 -> 5000 | L51: =VLOOKUP(C51,ABC!$A$3:$B$88,2,0) -> 10000 | M51: =+L51/2 -> 5000 | O51: =VLOOKUP(C51,IP!$B$9:$I$117,8,0) -> 0 | P51: =+H51+I51 -> 500 | Q51: =VLOOKUP(C51,IP!$B$9:$N$117,13,0) -> 0 | R51: =VLOOKUP(C51,IP!$B$9:$O$117,14,0) -> 0 | T51: =VLOOKUP(C51,IP!$B$9:$P$117,15,0) -> 0 | U51: =VLOOKUP(C51,IP!$B$9:$Q$117,16,0) -> 0 | V51: 500 | W51: =VLOOKUP(C51,IP!B$9:R$117,17,0) -> 0 | Y51: =+K51-O51-P51+Q51+R51+S51+T51+U51+V51+W51 -> 5000 | Z51: =+M51-Y51 -> 0
A52: SEI0109 | B52: SEITON (IP INNOVA II) | C52: Negrete Renteria Jose Luis | E52: =VLOOKUP(C52,IP!$B$9:$V$117,21,0) -> 2135.4 | G52: =VLOOKUP(C52,SINDICATO!$C$36:$F$144,4,0) -> 1122.43 | H52: =VLOOKUP(C52,SINDICATO!$C$36:$G$144,5,0) -> 500 | I52: =VLOOKUP(C52,SINDICATO!$C$36:$H$132,6,0) -> 0 | K52: =+D52+E52+G52+H52+I52 -> 3757.83 | L52: =VLOOKUP(C52,ABC!$A$3:$B$88,2,0) -> 9800 | M52: =+L52/2 -> 4900 | O52: =VLOOKUP(C52,IP!$B$9:$I$117,8,0) -> 0 | P52: =+H52+I52 -> 500 | Q52: =VLOOKUP(C52,IP!$B$9:$N$117,13,0) -> 1642.17 | R52: =VLOOKUP(C52,IP!$B$9:$O$117,14,0) -> 0 | T52: =VLOOKUP(C52,IP!$B$9:$P$117,15,0) -> 0 | U52: =VLOOKUP(C52,IP!$B$9:$Q$117,16,0) -> 0 | V52: 0 | W52: =VLOOKUP(C52,IP!B$9:R$117,17,0) -> 0 | Y52: =+K52-O52-P52+Q52+R52+S52+T52+U52+V52+W52 -> 4900 | Z52: =+M52-Y52 -> 0
A53: SEI0126 | B53: SEITON (IP INNOVA II) | C53: Alonso Flores Beda | E53: =VLOOKUP(C53,IP!$B$9:$V$117,21,0) -> 4503.4 | G53: =VLOOKUP(C53,SINDICATO!$C$36:$F$144,4,0) -> 0 | H53: =VLOOKUP(C53,SINDICATO!$C$36:$G$144,5,0) -> 0 | I53: =VLOOKUP(C53,SINDICATO!$C$36:$H$132,6,0) -> 0 | K53: =+D53+E53+G53+H53+I53 -> 4503.4 | L53: 9000 | M53: =+L53/2 -> 4500 | O53: =VLOOKUP(C53,IP!$B$9:$I$117,8,0) -> 0 | P53: =+H53+I53 -> 0 | Q53: =VLOOKUP(C53,IP!$B$9:$N$117,13,0) -> 0 | R53: =VLOOKUP(C53,IP!$B$9:$O$117,14,0) -> 0 | T53: =VLOOKUP(C53,IP!$B$9:$P$117,15,0) -> 0 | U53: =VLOOKUP(C53,IP!$B$9:$Q$117,16,0) -> 0 | V53: 0 | W53: =VLOOKUP(C53,IP!B$9:R$117,17,0) -> 0 | Y53: =+K53-O53-P53+Q53+R53+S53+T53+U53+V53+W53 -> 4503.4 | Z53: =+M53-Y53 -> -3.4 | AA53: 100% IMSS
A54: SEI0133 | B54: SEITON (IP INNOVA II) | C54: Romero Mayoral Lorenzo | E54: =VLOOKUP(C54,IP!$B$9:$V$117,21,0) -> 2653.4 | G54: =VLOOKUP(C54,SINDICATO!$C$36:$F$144,4,0) -> 2166.28 | H54: =VLOOKUP(C54,SINDICATO!$C$36:$G$144,5,0) -> 250 | I54: =VLOOKUP(C54,SINDICATO!$C$36:$H$132,6,0) -> 70 | K54: =+D54+E54+G54+H54+I54 -> 5139.68 | L54: =VLOOKUP(C54,ABC!$A$3:$B$88,2,0) -> 11500 | M54: =+L54/2 -> 5750 | O54: =VLOOKUP(C54,IP!$B$9:$I$117,8,0) -> 160 | P54: =+H54+I54 -> 320 | Q54: =VLOOKUP(C54,IP!$B$9:$N$117,13,0) -> 1090.32 | R54: =VLOOKUP(C54,IP!$B$9:$O$117,14,0) -> 0 | T54: =VLOOKUP(C54,IP!$B$9:$P$117,15,0) -> 0 | U54: =VLOOKUP(C54,IP!$B$9:$Q$117,16,0) -> 0 | V54: 0 | W54: =VLOOKUP(C54,IP!B$9:R$117,17,0) -> 0 | Y54: =+K54-O54-P54+Q54+R54+S54+T54+U54+V54+W54 -> 5750 | Z54: =+M54-Y54 -> 0
A55: SEI0146 | B55: SEITON (IP INNOVA II) | C55: Ramirez Vera Maria Del Carmen | E55: =VLOOKUP(C55,IP!$B$9:$V$117,21,0) -> 2704 | G55: =VLOOKUP(C55,SINDICATO!$C$36:$F$144,4,0) -> 1416.39 | H55: =VLOOKUP(C55,SINDICATO!$C$36:$G$144,5,0) -> 0 | I55: =VLOOKUP(C55,SINDICATO!$C$36:$H$132,6,0) -> 0 | K55: =+D55+E55+G55+H55+I55 -> 4120.39 | L55: =VLOOKUP(C55,ABC!$A$3:$B$88,2,0) -> 10000 | M55: =+L55/2 -> 5000 | O55: =VLOOKUP(C55,IP!$B$9:$I$117,8,0) -> 0 | P55: =+H55+I55 -> 0 | Q55: =VLOOKUP(C55,IP!$B$9:$N$117,13,0) -> 879.61 | R55: =VLOOKUP(C55,IP!$B$9:$O$117,14,0) -> 0 | T55: =VLOOKUP(C55,IP!$B$9:$P$117,15,0) -> 0 | U55: =VLOOKUP(C55,IP!$B$9:$Q$117,16,0) -> 0 | V55: 0 | W55: =VLOOKUP(C55,IP!B$9:R$117,17,0) -> 0 | Y55: =+K55-O55-P55+Q55+R55+S55+T55+U55+V55+W55 -> 5000 | Z55: =+M55-Y55 -> 0
A56: SEI0230 | B56: SEITON (IP INNOVA II) | C56: Bueno Herrera Mariana Guadalupe | E56: =VLOOKUP(C56,IP!$B$9:$V$117,21,0) -> 3583.6 | G56: =VLOOKUP(C56,SINDICATO!$C$36:$F$144,4,0) -> 2716.4 | H56: =VLOOKUP(C56,SINDICATO!$C$36:$G$144,5,0) -> 4835.03 | I56: =VLOOKUP(C56,SINDICATO!$C$36:$H$132,6,0) -> 0 | K56: =+D56+E56+G56+H56+I56 -> 11135.03 | L56: 12600 | M56: =+L56/2 -> 6300 | O56: =VLOOKUP(C56,IP!$B$9:$I$117,8,0) -> 0 | P56: =+H56+I56 -> 4835.03 | Q56: =VLOOKUP(C56,IP!$B$9:$N$117,13,0) -> 0 | R56: =VLOOKUP(C56,IP!$B$9:$O$117,14,0) -> 0 | T56: =VLOOKUP(C56,IP!$B$9:$P$117,15,0) -> 0 | U56: =VLOOKUP(C56,IP!$B$9:$Q$117,16,0) -> 0 | V56: 0 | W56: =VLOOKUP(C56,IP!B$9:R$117,17,0) -> 0 | Y56: =+K56-O56-P56+Q56+R56+S56+T56+U56+V56+W56 -> 6300 | Z56: =+M56-Y56 -> 0
A57: SEI0332 | B57: SEITON (IP INNOVA II) | C57: Lara Campos Maximino | E57: =VLOOKUP(C57,IP!$B$9:$V$117,21,0) -> 4753.8 | G57: =VLOOKUP(C57,SINDICATO!$C$36:$F$144,4,0) -> 0 | H57: =VLOOKUP(C57,SINDICATO!$C$36:$G$144,5,0) -> 0 | I57: =VLOOKUP(C57,SINDICATO!$C$36:$H$132,6,0) -> 0 | K57: =+D57+E57+G57+H57+I57 -> 4753.8 | L57: =VLOOKUP(C57,ABC!$A$3:$B$88,2,0) -> 9500 | M57: =+L57/2 -> 4750 | O57: =VLOOKUP(C57,IP!$B$9:$I$117,8,0) -> 0 | P57: =+H57+I57 -> 0 | Q57: =VLOOKUP(C57,IP!$B$9:$N$117,13,0) -> 0 | R57: =VLOOKUP(C57,IP!$B$9:$O$117,14,0) -> 0 | T57: =VLOOKUP(C57,IP!$B$9:$P$117,15,0) -> 0 | U57: =VLOOKUP(C57,IP!$B$9:$Q$117,16,0) -> 0 | V57: 0 | W57: =VLOOKUP(C57,IP!B$9:R$117,17,0) -> 0 | Y57: =+K57-O57-P57+Q57+R57+S57+T57+U57+V57+W57 -> 4753.8 | Z57: =+M57-Y57 -> -3.8 | AA57: 100% IMSS
A58: SEI0345 | B58: SEITON (IP INNOVA II) | C58: Rodriguez Diaz Cesar Salvador | E58: =VLOOKUP(C58,IP!$B$9:$V$117,21,0) -> 3019.2 | G58: =VLOOKUP(C58,SINDICATO!$C$36:$F$144,4,0) -> 941.41 | H58: =VLOOKUP(C58,SINDICATO!$C$36:$G$144,5,0) -> 275 | I58: =VLOOKUP(C58,SINDICATO!$C$36:$H$132,6,0) -> 0 | K58: =+D58+E58+G58+H58+I58 -> 4235.61 | L58: 9050 | M58: =+L58/2 -> 4525 | O58: =VLOOKUP(C58,IP!$B$9:$I$117,8,0) -> 0 | P58: =+H58+I58 -> 275 | Q58: =VLOOKUP(C58,IP!$B$9:$N$117,13,0) -> 564.39 | R58: =VLOOKUP(C58,IP!$B$9:$O$117,14,0) -> 0 | T58: =VLOOKUP(C58,IP!$B$9:$P$117,15,0) -> 0 | U58: =VLOOKUP(C58,IP!$B$9:$Q$117,16,0) -> 0 | V58: 0 | W58: =VLOOKUP(C58,IP!B$9:R$117,17,0) -> 0 | Y58: =+K58-O58-P58+Q58+R58+S58+T58+U58+V58+W58 -> 4525 | Z58: =+M58-Y58 -> 0
A59: SEI0364 | B59: SEITON (IP INNOVA II) | C59: Dominguez Lopez Mayeli Del Pilar | E59: =VLOOKUP(C59,IP!$B$9:$V$117,21,0) -> 1917 | G59: =VLOOKUP(C59,SINDICATO!$C$36:$F$144,4,0) -> 1416.33 | H59: =VLOOKUP(C59,SINDICATO!$C$36:$G$144,5,0) -> 211.25 | I59: =VLOOKUP(C59,SINDICATO!$C$36:$H$132,6,0) -> 0 | K59: =+D59+E59+G59+H59+I59 -> 3544.58 | L59: =VLOOKUP(C59,ABC!$A$3:$B$88,2,0) -> 10000 | M59: =+L59/2 -> 5000 | O59: =VLOOKUP(C59,IP!$B$9:$I$117,8,0) -> 0 | P59: =+H59+I59 -> 211.25 | Q59: =VLOOKUP(C59,IP!$B$9:$N$117,13,0) -> 0 | R59: =VLOOKUP(C59,IP!$B$9:$O$117,14,0) -> 0 | T59: =VLOOKUP(C59,IP!$B$9:$P$117,15,0) -> 0 | U59: =VLOOKUP(C59,IP!$B$9:$Q$117,16,0) -> 0 | V59: 0 | W59: =VLOOKUP(C59,IP!B$9:R$117,17,0) -> 1666.67 | Y59: =+K59-O59-P59+Q59+R59+S59+T59+U59+V59+W59 -> 5000 | Z59: =+M59-Y59 -> 0
A60: SEI0376 | B60: SEITON (IP INNOVA II) | C60: Marquez Alcaraz Martin | E60: =VLOOKUP(C60,IP!$B$9:$V$117,21,0) -> 2240.4 | G60: =VLOOKUP(C60,SINDICATO!$C$36:$F$144,4,0) -> 941.18 | H60: =VLOOKUP(C60,SINDICATO!$C$36:$G$144,5,0) -> 275 | I60: =VLOOKUP(C60,SINDICATO!$C$36:$H$132,6,0) -> 0 | K60: =+D60+E60+G60+H60+I60 -> 3456.58 | L60: 9050 | M60: =+L60/2 -> 4525 | O60: =VLOOKUP(C60,IP!$B$9:$I$117,8,0) -> 0 | P60: =+H60+I60 -> 275 | Q60: =VLOOKUP(C60,IP!$B$9:$N$117,13,0) -> 0 | R60: =VLOOKUP(C60,IP!$B$9:$O$117,14,0) -> 1343.42 | T60: =VLOOKUP(C60,IP!$B$9:$P$117,15,0) -> 0 | U60: =VLOOKUP(C60,IP!$B$9:$Q$117,16,0) -> 0 | V60: 0 | W60: =VLOOKUP(C60,IP!B$9:R$117,17,0) -> 0 | Y60: =+K60-O60-P60+Q60+R60+S60+T60+U60+V60+W60 -> 4525 | Z60: =+M60-Y60 -> 0
A61: SEI0412 | B61: SEITON (IP INNOVA II) | C61: Rojo Avelar Adrian | E61: =VLOOKUP(C61,IP!$B$9:$V$117,21,0) -> 2087 | G61: =VLOOKUP(C61,SINDICATO!$C$36:$F$144,4,0) -> 885.22 | H61: =VLOOKUP(C61,SINDICATO!$C$36:$G$144,5,0) -> 250 | I61: =VLOOKUP(C61,SINDICATO!$C$36:$H$132,6,0) -> 75 | K61: =+D61+E61+G61+H61+I61 -> 3297.22 | L61: =VLOOKUP(C61,ABC!$A$3:$B$88,2,0) -> 7500 | M61: =+L61/2 -> 3750 | O61: =VLOOKUP(C61,IP!$B$9:$I$117,8,0) -> 300 | P61: =+H61+I61 -> 325 | Q61: =VLOOKUP(C61,IP!$B$9:$N$117,13,0) -> 1077.78 | R61: =VLOOKUP(C61,IP!$B$9:$O$117,14,0) -> 0 | T61: =VLOOKUP(C61,IP!$B$9:$P$117,15,0) -> 0 | U61: =VLOOKUP(C61,IP!$B$9:$Q$117,16,0) -> 0 | V61: 0 | W61: =VLOOKUP(C61,IP!B$9:R$117,17,0) -> 0 | Y61: =+K61-O61-P61+Q61+R61+S61+T61+U61+V61+W61 -> 3750 | Z61: =+M61-Y61 -> 0
A62: SEI0413 | B62: SEITON (IP INNOVA II) | C62: Courtenay Gutierrez Barry Vladimir | E62: =VLOOKUP(C62,IP!$B$9:$V$117,21,0) -> 2052.2 | G62: =VLOOKUP(C62,SINDICATO!$C$36:$F$144,4,0) -> 52.47 | H62: =VLOOKUP(C62,SINDICATO!$C$36:$G$144,5,0) -> 4351.43 | I62: =VLOOKUP(C62,SINDICATO!$C$36:$H$132,6,0) -> 0 | K62: =+D62+E62+G62+H62+I62 -> 6456.1 | L62: 5000 | M62: =+L62/2 -> 2500 | O62: =VLOOKUP(C62,IP!$B$9:$I$117,8,0) -> 0 | P62: =+H62+I62 -> 4351.43 | Q62: =VLOOKUP(C62,IP!$B$9:$N$117,13,0) -> 0 | R62: =VLOOKUP(C62,IP!$B$9:$O$117,14,0) -> 0 | T62: =VLOOKUP(C62,IP!$B$9:$P$117,15,0) -> 0 | U62: =VLOOKUP(C62,IP!$B$9:$Q$117,16,0) -> 0 | V62: 0 | W62: =VLOOKUP(C62,IP!B$9:R$117,17,0) -> 395.33 | Y62: =+K62-O62-P62+Q62+R62+S62+T62+U62+V62+W62 -> 2500 | Z62: =+M62-Y62 -> 0
A63: SEI0421 | B63: SEITON (IP INNOVA II) | C63: Marin Avila Hector | E63: =VLOOKUP(C63,IP!$B$9:$V$117,21,0) -> 3693 | G63: =VLOOKUP(C63,SINDICATO!$C$36:$F$144,4,0) -> 707 | H63: =VLOOKUP(C63,SINDICATO!$C$36:$G$144,5,0) -> 0 | I63: =VLOOKUP(C63,SINDICATO!$C$36:$H$132,6,0) -> 0 | K63: =+D63+E63+G63+H63+I63 -> 4400 | L63: 8800 | M63: =+L63/2 -> 4400 | O63: =VLOOKUP(C63,IP!$B$9:$I$117,8,0) -> 0 | P63: =+H63+I63 -> 0 | Q63: =VLOOKUP(C63,IP!$B$9:$N$117,13,0) -> 0 | R63: =VLOOKUP(C63,IP!$B$9:$O$117,14,0) -> 0 | T63: =VLOOKUP(C63,IP!$B$9:$P$117,15,0) -> 0 | U63: =VLOOKUP(C63,IP!$B$9:$Q$117,16,0) -> 0 | V63: 0 | W63: =VLOOKUP(C63,IP!B$9:R$117,17,0) -> 0 | Y63: =+K63-O63-P63+Q63+R63+S63+T63+U63+V63+W63 -> 4400 | Z63: =+M63-Y63 -> 0
A64: SEI0424 | B64: SEITON (IP INNOVA II) | C64: Palacios Ramos Jesus | E64: =VLOOKUP(C64,IP!$B$9:$V$117,21,0) -> 3583.6 | G64: =VLOOKUP(C64,SINDICATO!$C$36:$F$144,4,0) -> 416.4 | H64: =VLOOKUP(C64,SINDICATO!$C$36:$G$144,5,0) -> 92.73 | I64: =VLOOKUP(C64,SINDICATO!$C$36:$H$132,6,0) -> 0 | K64: =+D64+E64+G64+H64+I64 -> 4092.73 | L64: 8000 | M64: =+L64/2 -> 4000 | O64: =VLOOKUP(C64,IP!$B$9:$I$117,8,0) -> 0 | P64: =+H64+I64 -> 92.73 | Q64: =VLOOKUP(C64,IP!$B$9:$N$117,13,0) -> 0 | R64: =VLOOKUP(C64,IP!$B$9:$O$117,14,0) -> 0 | T64: =VLOOKUP(C64,IP!$B$9:$P$117,15,0) -> 0 | U64: =VLOOKUP(C64,IP!$B$9:$Q$117,16,0) -> 0 | V64: 0 | W64: =VLOOKUP(C64,IP!B$9:R$117,17,0) -> 0 | Y64: =+K64-O64-P64+Q64+R64+S64+T64+U64+V64+W64 -> 4000 | Z64: =+M64-Y64 -> 0
A65: SEI0428 | B65: SEITON (IP INNOVA II) | C65: Martinez Hernandez J. Antonio | E65: =VLOOKUP(C65,IP!$B$9:$V$117,21,0) -> 3903.8 | G65: =VLOOKUP(C65,SINDICATO!$C$36:$F$144,4,0) -> 416.2 | H65: =VLOOKUP(C65,SINDICATO!$C$36:$G$144,5,0) -> 310 | I65: =VLOOKUP(C65,SINDICATO!$C$36:$H$132,6,0) -> 0 | K65: =+D65+E65+G65+H65+I65 -> 4630 | L65: 8000 | M65: =+L65/2 -> 4000 | O65: =VLOOKUP(C65,IP!$B$9:$I$117,8,0) -> 320 | P65: =+H65+I65 -> 310 | Q65: =VLOOKUP(C65,IP!$B$9:$N$117,13,0) -> 0 | R65: =VLOOKUP(C65,IP!$B$9:$O$117,14,0) -> 0 | T65: =VLOOKUP(C65,IP!$B$9:$P$117,15,0) -> 0 | U65: =VLOOKUP(C65,IP!$B$9:$Q$117,16,0) -> 0 | V65: 0 | W65: =VLOOKUP(C65,IP!B$9:R$117,17,0) -> 0 | Y65: =+K65-O65-P65+Q65+R65+S65+T65+U65+V65+W65 -> 4000 | Z65: =+M65-Y65 -> 0
A66: SEI0429 | B66: SEITON (IP INNOVA II) | C66: Torres Gomez Valeria | E66: =VLOOKUP(C66,IP!$B$9:$V$117,21,0) -> 2113.2 | G66: =VLOOKUP(C66,SINDICATO!$C$36:$F$144,4,0) -> 0 | H66: =VLOOKUP(C66,SINDICATO!$C$36:$G$144,5,0) -> 0 | I66: =VLOOKUP(C66,SINDICATO!$C$36:$H$132,6,0) -> 0 | K66: =+D66+E66+G66+H66+I66 -> 2113.2 | L66: 4500 | M66: =+L66/2 -> 2250 | O66: =VLOOKUP(C66,IP!$B$9:$I$117,8,0) -> 0 | P66: =+H66+I66 -> 0 | Q66: =VLOOKUP(C66,IP!$B$9:$N$117,13,0) -> 0 | R66: =VLOOKUP(C66,IP!$B$9:$O$117,14,0) -> 0 | T66: =VLOOKUP(C66,IP!$B$9:$P$117,15,0) -> 0 | U66: =VLOOKUP(C66,IP!$B$9:$Q$117,16,0) -> 0 | V66: 0 | W66: =VLOOKUP(C66,IP!B$9:R$117,17,0) -> 0 | Y66: =+K66-O66-P66+Q66+R66+S66+T66+U66+V66+W66 -> 2113.2 | Z66: =+M66-Y66 -> 136.8 | AA66: 1PSS
A67: SEI0431 | B67: SEITON (IP INNOVA II) | C67: Alcaraz Conde Zabdi Guadalupe | E67: =VLOOKUP(C67,IP!$B$9:$V$117,21,0) -> 602.8 | G67: =VLOOKUP(C67,SINDICATO!$C$36:$F$144,4,0) -> 109.89 | H67: =VLOOKUP(C67,SINDICATO!$C$36:$G$144,5,0) -> 1000 | I67: =VLOOKUP(C67,SINDICATO!$C$36:$H$132,6,0) -> 0 | K67: =+D67+E67+G67+H67+I67 -> 1712.69 | L67: 6000 | M67: =+L67/2 -> 3000 | O67: =VLOOKUP(C67,IP!$B$9:$I$117,8,0) -> 0 | P67: =+H67+I67 -> 1000 | Q67: =VLOOKUP(C67,IP!$B$9:$N$117,13,0) -> 0 | R67: =VLOOKUP(C67,IP!$B$9:$O$117,14,0) -> 1487.31 | T67: =VLOOKUP(C67,IP!$B$9:$P$117,15,0) -> 0 | U67: =VLOOKUP(C67,IP!$B$9:$Q$117,16,0) -> 600 | V67: 0 | W67: =VLOOKUP(C67,IP!B$9:R$117,17,0) -> 0 | Y67: =+K67-O67-P67+Q67+R67+S67+T67+U67+V67+W67 -> 2800 | Z67: =+M67-Y67 -> 200 | AA67: 1PSS
A68: SEI0438 | B68: SEITON (IP INNOVA II) | C68: Lopez Terron Roberto Porfirio | E68: =VLOOKUP(C68,IP!$B$9:$V$117,21,0) -> 5952.4 | G68: =VLOOKUP(C68,SINDICATO!$C$36:$F$144,4,0) -> 1047.6 | H68: =VLOOKUP(C68,SINDICATO!$C$36:$G$144,5,0) -> 0 | I68: =VLOOKUP(C68,SINDICATO!$C$36:$H$132,6,0) -> 0 | K68: =+D68+E68+G68+H68+I68 -> 7000 | L68: 14000 | M68: =+L68/2 -> 7000 | O68: =VLOOKUP(C68,IP!$B$9:$I$117,8,0) -> 0 | P68: =+H68+I68 -> 0 | Q68: =VLOOKUP(C68,IP!$B$9:$N$117,13,0) -> 0 | R68: =VLOOKUP(C68,IP!$B$9:$O$117,14,0) -> 0 | T68: =VLOOKUP(C68,IP!$B$9:$P$117,15,0) -> 0 | U68: =VLOOKUP(C68,IP!$B$9:$Q$117,16,0) -> 0 | V68: 0 | W68: =VLOOKUP(C68,IP!B$9:R$117,17,0) -> 0 | Y68: =+K68-O68-P68+Q68+R68+S68+T68+U68+V68+W68 -> 7000 | Z68: =+M68-Y68 -> 0
A69: SEI0442 | B69: SEITON (IP INNOVA II) | C69: Chavez Pedraza Samuel | E69: =VLOOKUP(C69,IP!$B$9:$V$117,21,0) -> 5952.2 | G69: =VLOOKUP(C69,SINDICATO!$C$36:$F$144,4,0) -> 1047.8 | H69: =VLOOKUP(C69,SINDICATO!$C$36:$G$144,5,0) -> 0 | I69: =VLOOKUP(C69,SINDICATO!$C$36:$H$132,6,0) -> 0 | K69: =+D69+E69+G69+H69+I69 -> 7000 | L69: 14000 | M69: =+L69/2 -> 7000 | O69: =VLOOKUP(C69,IP!$B$9:$I$117,8,0) -> 0 | P69: =+H69+I69 -> 0 | Q69: =VLOOKUP(C69,IP!$B$9:$N$117,13,0) -> 0 | R69: =VLOOKUP(C69,IP!$B$9:$O$117,14,0) -> 0 | T69: =VLOOKUP(C69,IP!$B$9:$P$117,15,0) -> 0 | U69: =VLOOKUP(C69,IP!$B$9:$Q$117,16,0) -> 0 | V69: 0 | W69: =VLOOKUP(C69,IP!B$9:R$117,17,0) -> 0 | Y69: =+K69-O69-P69+Q69+R69+S69+T69+U69+V69+W69 -> 7000 | Z69: =+M69-Y69 -> 0
A70: SEI0443 | B70: SEITON (IP INNOVA II) | C70: Castillo Nungaray Nestor Roman | E70: =VLOOKUP(C70,IP!$B$9:$V$117,21,0) -> 2924.8 | G70: =VLOOKUP(C70,SINDICATO!$C$36:$F$144,4,0) -> 135.2 | H70: =VLOOKUP(C70,SINDICATO!$C$36:$G$144,5,0) -> 422.5 | I70: =VLOOKUP(C70,SINDICATO!$C$36:$H$132,6,0) -> 0 | K70: =+D70+E70+G70+H70+I70 -> 3482.5 | L70: 6000 | M70: =+L70/2 -> 3000 | O70: =VLOOKUP(C70,IP!$B$9:$I$117,8,0) -> 60 | P70: =+H70+I70 -> 422.5 | Q70: =VLOOKUP(C70,IP!$B$9:$N$117,13,0) -> 0 | R70: =VLOOKUP(C70,IP!$B$9:$O$117,14,0) -> 0 | T70: =VLOOKUP(C70,IP!$B$9:$P$117,15,0) -> 0 | U70: =VLOOKUP(C70,IP!$B$9:$Q$117,16,0) -> 0 | V70: 0 | W70: =VLOOKUP(C70,IP!B$9:R$117,17,0) -> 0 | Y70: =+K70-O70-P70+Q70+R70+S70+T70+U70+V70+W70 -> 3000 | Z70: =+M70-Y70 -> 0
A71: SEI0444 | B71: SEITON (IP INNOVA II) | C71: Marquez Hernandez Rogelio | E71: =VLOOKUP(C71,IP!$B$9:$V$117,21,0) -> 3663.6 | G71: =VLOOKUP(C71,SINDICATO!$C$36:$F$144,4,0) -> 416.4 | H71: =VLOOKUP(C71,SINDICATO!$C$36:$G$144,5,0) -> 816.16 | I71: =VLOOKUP(C71,SINDICATO!$C$36:$H$132,6,0) -> 0 | K71: =+D71+E71+G71+H71+I71 -> 4896.16 | L71: 8000 | M71: =+L71/2 -> 4000 | O71: =VLOOKUP(C71,IP!$B$9:$I$117,8,0) -> 80 | P71: =+H71+I71 -> 816.16 | Q71: =VLOOKUP(C71,IP!$B$9:$N$117,13,0) -> 0 | R71: =VLOOKUP(C71,IP!$B$9:$O$117,14,0) -> 0 | T71: =VLOOKUP(C71,IP!$B$9:$P$117,15,0) -> 0 | U71: =VLOOKUP(C71,IP!$B$9:$Q$117,16,0) -> 0 | V71: 0 | W71: =VLOOKUP(C71,IP!B$9:R$117,17,0) -> 0 | Y71: =+K71-O71-P71+Q71+R71+S71+T71+U71+V71+W71 -> 4000 | Z71: =+M71-Y71 -> 0
A72: SEI0449 | B72: SEITON (IP INNOVA II) | C72: Flores Cerrillos Jorge Humberto | E72: =VLOOKUP(C72,IP!$B$9:$V$117,21,0) -> 3583.6 | G72: =VLOOKUP(C72,SINDICATO!$C$36:$F$144,4,0) -> 416.4 | H72: =VLOOKUP(C72,SINDICATO!$C$36:$G$144,5,0) -> 294.82 | I72: =VLOOKUP(C72,SINDICATO!$C$36:$H$132,6,0) -> 0 | K72: =+D72+E72+G72+H72+I72 -> 4294.82 | L72: 8000 | M72: =+L72/2 -> 4000 | O72: =VLOOKUP(C72,IP!$B$9:$I$117,8,0) -> 0 | P72: =+H72+I72 -> 294.82 | Q72: =VLOOKUP(C72,IP!$B$9:$N$117,13,0) -> 0 | R72: =VLOOKUP(C72,IP!$B$9:$O$117,14,0) -> 0 | T72: =VLOOKUP(C72,IP!$B$9:$P$117,15,0) -> 0 | U72: =VLOOKUP(C72,IP!$B$9:$Q$117,16,0) -> 0 | V72: 0 | W72: =VLOOKUP(C72,IP!B$9:R$117,17,0) -> 0 | Y72: =+K72-O72-P72+Q72+R72+S72+T72+U72+V72+W72 -> 4000 | Z72: =+M72-Y72 -> 0
A73: SEI0451 | B73: SEITON (IP INNOVA II) | C73: Hurtado Avalos J.jesus | E73: =VLOOKUP(C73,IP!$B$9:$V$117,21,0) -> 2864.8 | G73: =VLOOKUP(C73,SINDICATO!$C$36:$F$144,4,0) -> 135.2 | H73: =VLOOKUP(C73,SINDICATO!$C$36:$G$144,5,0) -> 0 | I73: =VLOOKUP(C73,SINDICATO!$C$36:$H$132,6,0) -> 0 | K73: =+D73+E73+G73+H73+I73 -> 3000 | L73: 6000 | M73: =+L73/2 -> 3000 | O73: =VLOOKUP(C73,IP!$B$9:$I$117,8,0) -> 0 | P73: =+H73+I73 -> 0 | Q73: =VLOOKUP(C73,IP!$B$9:$N$117,13,0) -> 0 | R73: =VLOOKUP(C73,IP!$B$9:$O$117,14,0) -> 0 | T73: =VLOOKUP(C73,IP!$B$9:$P$117,15,0) -> 0 | U73: =VLOOKUP(C73,IP!$B$9:$Q$117,16,0) -> 0 | V73: 0 | W73: =VLOOKUP(C73,IP!B$9:R$117,17,0) -> 0 | Y73: =+K73-O73-P73+Q73+R73+S73+T73+U73+V73+W73 -> 3000 | Z73: =+M73-Y73 -> 0
A74: SEI0453 | B74: SEITON (IP INNOVA II) | C74: Mora Cavazos Roberto Manuel | E74: =VLOOKUP(C74,IP!$B$9:$V$117,21,0) -> 3583.6 | G74: =VLOOKUP(C74,SINDICATO!$C$36:$F$144,4,0) -> 416.4 | H74: =VLOOKUP(C74,SINDICATO!$C$36:$G$144,5,0) -> 0 | I74: =VLOOKUP(C74,SINDICATO!$C$36:$H$132,6,0) -> 0 | K74: =+D74+E74+G74+H74+I74 -> 4000 | L74: 8000 | M74: =+L74/2 -> 4000 | O74: =VLOOKUP(C74,IP!$B$9:$I$117,8,0) -> 0 | P74: =+H74+I74 -> 0 | Q74: =VLOOKUP(C74,IP!$B$9:$N$117,13,0) -> 0 | R74: =VLOOKUP(C74,IP!$B$9:$O$117,14,0) -> 0 | T74: =VLOOKUP(C74,IP!$B$9:$P$117,15,0) -> 0 | U74: =VLOOKUP(C74,IP!$B$9:$Q$117,16,0) -> 0 | V74: 0 | W74: =VLOOKUP(C74,IP!B$9:R$117,17,0) -> 0 | Y74: =+K74-O74-P74+Q74+R74+S74+T74+U74+V74+W74 -> 4000 | Z74: =+M74-Y74 -> 0
A75: SEI0454 | B75: SEITON (IP INNOVA II) | C75: Martinez Rivera Maria Teresa | E75: =VLOOKUP(C75,IP!$B$9:$V$117,21,0) -> 4503.6 | G75: =VLOOKUP(C75,SINDICATO!$C$36:$F$144,4,0) -> 0 | H75: =VLOOKUP(C75,SINDICATO!$C$36:$G$144,5,0) -> 0 | I75: =VLOOKUP(C75,SINDICATO!$C$36:$H$132,6,0) -> 0 | K75: =+D75+E75+G75+H75+I75 -> 4503.6 | L75: 9000 | M75: =+L75/2 -> 4500 | O75: =VLOOKUP(C75,IP!$B$9:$I$117,8,0) -> 0 | P75: =+H75+I75 -> 0 | Q75: =VLOOKUP(C75,IP!$B$9:$N$117,13,0) -> 0 | R75: =VLOOKUP(C75,IP!$B$9:$O$117,14,0) -> 0 | T75: =VLOOKUP(C75,IP!$B$9:$P$117,15,0) -> 0 | U75: =VLOOKUP(C75,IP!$B$9:$Q$117,16,0) -> 0 | V75: 0 | W75: =VLOOKUP(C75,IP!B$9:R$117,17,0) -> 0 | Y75: =+K75-O75-P75+Q75+R75+S75+T75+U75+V75+W75 -> 4503.6 | Z75: =+M75-Y75 -> -3.6 | AA75: 100% IMSS
A76: SEI0455 | B76: SEITON (IP INNOVA II) | C76: Perez Garcia Andres Alvaro | E76: =VLOOKUP(C76,IP!$B$9:$V$117,21,0) -> 2558.2 | G76: =VLOOKUP(C76,SINDICATO!$C$36:$F$144,4,0) -> 416.36 | H76: =VLOOKUP(C76,SINDICATO!$C$36:$G$144,5,0) -> 100 | I76: =VLOOKUP(C76,SINDICATO!$C$36:$H$132,6,0) -> 0 | K76: =+D76+E76+G76+H76+I76 -> 3074.56 | L76: 8000 | M76: =+L76/2 -> 4000 | O76: =VLOOKUP(C76,IP!$B$9:$I$117,8,0) -> 0 | P76: =+H76+I76 -> 100 | Q76: =VLOOKUP(C76,IP!$B$9:$N$117,13,0) -> 0 | R76: =VLOOKUP(C76,IP!$B$9:$O$117,14,0) -> 0 | T76: =VLOOKUP(C76,IP!$B$9:$P$117,15,0) -> 0 | U76: =VLOOKUP(C76,IP!$B$9:$Q$117,16,0) -> 0 | V76: 0 | W76: =VLOOKUP(C76,IP!B$9:R$117,17,0) -> 1025.44 | Y76: =+K76-O76-P76+Q76+R76+S76+T76+U76+V76+W76 -> 4000 | Z76: =+M76-Y76 -> 0
A77: SEI0456 | B77: SEITON (IP INNOVA II) | C77: Chavira Garcia David Fernando | E77: =VLOOKUP(C77,IP!$B$9:$V$117,21,0) -> 4406.4 | G77: =VLOOKUP(C77,SINDICATO!$C$36:$F$144,4,0) -> 593.6 | H77: =VLOOKUP(C77,SINDICATO!$C$36:$G$144,5,0) -> 131.91 | I77: =VLOOKUP(C77,SINDICATO!$C$36:$H$132,6,0) -> 0 | K77: =+D77+E77+G77+H77+I77 -> 5131.91 | L77: 10000 | M77: =+L77/2 -> 5000 | O77: =VLOOKUP(C77,IP!$B$9:$I$117,8,0) -> 0 | P77: =+H77+I77 -> 131.91 | Q77: =VLOOKUP(C77,IP!$B$9:$N$117,13,0) -> 0 | R77: =VLOOKUP(C77,IP!$B$9:$O$117,14,0) -> 0 | T77: =VLOOKUP(C77,IP!$B$9:$P$117,15,0) -> 0 | U77: =VLOOKUP(C77,IP!$B$9:$Q$117,16,0) -> 0 | V77: 0 | W77: =VLOOKUP(C77,IP!B$9:R$117,17,0) -> 0 | Y77: =+K77-O77-P77+Q77+R77+S77+T77+U77+V77+W77 -> 5000 | Z77: =+M77-Y77 -> 0
A78: SEI0457 | B78: SEITON (IP INNOVA II) | C78: Guerrero Lara Cesar Adrian | E78: =VLOOKUP(C78,IP!$B$9:$V$117,21,0) -> 3583.6 | G78: =VLOOKUP(C78,SINDICATO!$C$36:$F$144,4,0) -> 416.4 | H78: =VLOOKUP(C78,SINDICATO!$C$36:$G$144,5,0) -> 1958.34 | I78: =VLOOKUP(C78,SINDICATO!$C$36:$H$132,6,0) -> 0 | K78: =+D78+E78+G78+H78+I78 -> 5958.34 | L78: 8000 | M78: =+L78/2 -> 4000 | O78: =VLOOKUP(C78,IP!$B$9:$I$117,8,0) -> 0 | P78: =+H78+I78 -> 1958.34 | Q78: =VLOOKUP(C78,IP!$B$9:$N$117,13,0) -> 0 | R78: =VLOOKUP(C78,IP!$B$9:$O$117,14,0) -> 0 | T78: =VLOOKUP(C78,IP!$B$9:$P$117,15,0) -> 0 | U78: =VLOOKUP(C78,IP!$B$9:$Q$117,16,0) -> 0 | V78: 0 | W78: =VLOOKUP(C78,IP!B$9:R$117,17,0) -> 0 | Y78: =+K78-O78-P78+Q78+R78+S78+T78+U78+V78+W78 -> 4000 | Z78: =+M78-Y78 -> 0
A79: SEI0458 | B79: SEITON (IP INNOVA II) | C79: Martinez Zamora Gerardo Mario | E79: =VLOOKUP(C79,IP!$B$9:$V$117,21,0) -> 2692.4 | G79: =VLOOKUP(C79,SINDICATO!$C$36:$F$144,4,0) -> 549.965 | H79: =VLOOKUP(C79,SINDICATO!$C$36:$G$144,5,0) -> 2858.57 | I79: =VLOOKUP(C79,SINDICATO!$C$36:$H$132,6,0) -> 0 | K79: =+D79+E79+G79+H79+I79 -> 6100.935 | L79: 9550.01 | M79: =+L79/2 -> 4775.005 | O79: =VLOOKUP(C79,IP!$B$9:$I$117,8,0) -> 0 | P79: =+H79+I79 -> 2858.57 | Q79: =VLOOKUP(C79,IP!$B$9:$N$117,13,0) -> 1532.64 | R79: =VLOOKUP(C79,IP!$B$9:$O$117,14,0) -> 0 | T79: =VLOOKUP(C79,IP!$B$9:$P$117,15,0) -> 0 | U79: =VLOOKUP(C79,IP!$B$9:$Q$117,16,0) -> 0 | V79: 0 | W79: =VLOOKUP(C79,IP!B$9:R$117,17,0) -> 0 | Y79: =+K79-O79-P79+Q79+R79+S79+T79+U79+V79+W79 -> 4775.005 | Z79: =+M79-Y79 -> 0
A80: SEI0460 | B80: SEITON (IP INNOVA II) | C80: Castellon Ramos Rene | E80: =VLOOKUP(C80,IP!$B$9:$V$117,21,0) -> 3121 | G80: =VLOOKUP(C80,SINDICATO!$C$36:$F$144,4,0) -> 384.795 | H80: =VLOOKUP(C80,SINDICATO!$C$36:$G$144,5,0) -> 480 | I80: =VLOOKUP(C80,SINDICATO!$C$36:$H$132,6,0) -> 0 | K80: =+D80+E80+G80+H80+I80 -> 3985.795 | L80: 7505.99 | M80: =+L80/2 -> 3752.995 | O80: =VLOOKUP(C80,IP!$B$9:$I$117,8,0) -> 0 | P80: =+H80+I80 -> 480 | Q80: =VLOOKUP(C80,IP!$B$9:$N$117,13,0) -> 0 | R80: =VLOOKUP(C80,IP!$B$9:$O$117,14,0) -> 0 | T80: =VLOOKUP(C80,IP!$B$9:$P$117,15,0) -> 0 | U80: =VLOOKUP(C80,IP!$B$9:$Q$117,16,0) -> 0 | V80: 0 | W80: =VLOOKUP(C80,IP!B$9:R$117,17,0) -> 247.2 | Y80: =+K80-O80-P80+Q80+R80+S80+T80+U80+V80+W80 -> 3752.995 | Z80: =+M80-Y80 -> 0
A81: SEI0461 | B81: SEITON (IP INNOVA II) | C81: Flores Franco Marco | E81: =VLOOKUP(C81,IP!$B$9:$V$117,21,0) -> 4734 | G81: =VLOOKUP(C81,SINDICATO!$C$36:$F$144,4,0) -> 450.985 | H81: =VLOOKUP(C81,SINDICATO!$C$36:$G$144,5,0) -> 1155 | I81: =VLOOKUP(C81,SINDICATO!$C$36:$H$132,6,0) -> 0.0211 | K81: =+D81+E81+G81+H81+I81 -> 6340.0061 | L81: 8500.01 | M81: =+L81/2 -> 4250.005 | O81: =VLOOKUP(C81,IP!$B$9:$I$117,8,0) -> 934.98 | P81: =+H81+I81 -> 1155.0211 | Q81: =VLOOKUP(C81,IP!$B$9:$N$117,13,0) -> 0 | R81: =VLOOKUP(C81,IP!$B$9:$O$117,14,0) -> 0 | T81: =VLOOKUP(C81,IP!$B$9:$P$117,15,0) -> 0 | U81: =VLOOKUP(C81,IP!$B$9:$Q$117,16,0) -> 0 | V81: 0 | W81: =VLOOKUP(C81,IP!B$9:R$117,17,0) -> 0 | Y81: =+K81-O81-P81+Q81+R81+S81+T81+U81+V81+W81 -> 4250.005 | Z81: =+M81-Y81 -> 0
A82: SEI0462 | B82: SEITON (IP INNOVA II) | C82: Chavez Saucedo Jorge Arturo | E82: =VLOOKUP(C82,IP!$B$9:$V$117,21,0) -> 3585.4 | G82: =VLOOKUP(C82,SINDICATO!$C$36:$F$144,4,0) -> 414.6 | H82: =VLOOKUP(C82,SINDICATO!$C$36:$G$144,5,0) -> 146.25 | I82: =VLOOKUP(C82,SINDICATO!$C$36:$H$132,6,0) -> 0 | K82: =+D82+E82+G82+H82+I82 -> 4146.25 | L82: 8000 | M82: =+L82/2 -> 4000 | O82: =VLOOKUP(C82,IP!$B$9:$I$117,8,0) -> 0 | P82: =+H82+I82 -> 146.25 | Q82: =VLOOKUP(C82,IP!$B$9:$N$117,13,0) -> 0 | R82: =VLOOKUP(C82,IP!$B$9:$O$117,14,0) -> 0 | T82: =VLOOKUP(C82,IP!$B$9:$P$117,15,0) -> 0 | U82: =VLOOKUP(C82,IP!$B$9:$Q$117,16,0) -> 0 | W82: =VLOOKUP(C82,IP!B$9:R$117,17,0) -> 0 | Y82: =+K82-O82-P82+Q82+R82+S82+T82+U82+V82+W82 -> 4000 | Z82: =+M82-Y82 -> 0
A83: SEI0464 | B83: SEITON (IP INNOVA II) | C83: Hueramo Hueramo Jesus Daniel | E83: =VLOOKUP(C83,IP!$B$9:$V$117,21,0) -> 2746 | G83: =VLOOKUP(C83,SINDICATO!$C$36:$F$144,4,0) -> 450.955 | H83: =VLOOKUP(C83,SINDICATO!$C$36:$G$144,5,0) -> 1040.68 | I83: =VLOOKUP(C83,SINDICATO!$C$36:$H$132,6,0) -> 84.99 | K83: =+D83+E83+G83+H83+I83 -> 4322.625 | L83: 8500.01 | M83: =+L83/2 -> 4250.005 | O83: =VLOOKUP(C83,IP!$B$9:$I$117,8,0) -> 0 | P83: =+H83+I83 -> 1125.67 | Q83: =VLOOKUP(C83,IP!$B$9:$N$117,13,0) -> 0 | R83: =VLOOKUP(C83,IP!$B$9:$O$117,14,0) -> 553.05 | T83: =VLOOKUP(C83,IP!$B$9:$P$117,15,0) -> 0 | U83: =VLOOKUP(C83,IP!$B$9:$Q$117,16,0) -> 0 | V83: 0 | W83: =VLOOKUP(C83,IP!B$9:R$117,17,0) -> 500 | Y83: =+K83-O83-P83+Q83+R83+S83+T83+U83+V83+W83 -> 4250.005 | Z83: =+M83-Y83 -> 0
A84: SEI0465 | B84: SEITON (IP INNOVA II) | C84: Sandoval Garcia Luis | E84: =VLOOKUP(C84,IP!$B$9:$V$117,21,0) -> 3583.6 | G84: =VLOOKUP(C84,SINDICATO!$C$36:$F$144,4,0) -> 416.4 | H84: =VLOOKUP(C84,SINDICATO!$C$36:$G$144,5,0) -> 322.5 | I84: =VLOOKUP(C84,SINDICATO!$C$36:$H$132,6,0) -> 0 | K84: =+D84+E84+G84+H84+I84 -> 4322.5 | L84: 8000 | M84: =+L84/2 -> 4000 | O84: =VLOOKUP(C84,IP!$B$9:$I$117,8,0) -> 0 | P84: =+H84+I84 -> 322.5 | Q84: =VLOOKUP(C84,IP!$B$9:$N$117,13,0) -> 0 | R84: =VLOOKUP(C84,IP!$B$9:$O$117,14,0) -> 0 | T84: =VLOOKUP(C84,IP!$B$9:$P$117,15,0) -> 0 | U84: =VLOOKUP(C84,IP!$B$9:$Q$117,16,0) -> 0 | W84: =VLOOKUP(C84,IP!B$9:R$117,17,0) -> 0 | Y84: =+K84-O84-P84+Q84+R84+S84+T84+U84+V84+W84 -> 4000 | Z84: =+M84-Y84 -> 0
A85: SEI0467 | B85: SEITON (IP INNOVA II) | C85: Vaca Valdez Guillermo | E85: =VLOOKUP(C85,IP!$B$9:$V$117,21,0) -> 1729.6 | G85: =VLOOKUP(C85,SINDICATO!$C$36:$F$144,4,0) -> 416.27 | H85: =VLOOKUP(C85,SINDICATO!$C$36:$G$144,5,0) -> 123.08 | I85: =VLOOKUP(C85,SINDICATO!$C$36:$H$132,6,0) -> 0 | K85: =+D85+E85+G85+H85+I85 -> 2268.95 | L85: 8000 | M85: =+L85/2 -> 4000 | O85: =VLOOKUP(C85,IP!$B$9:$I$117,8,0) -> 0 | P85: =+H85+I85 -> 123.08 | Q85: =VLOOKUP(C85,IP!$B$9:$N$117,13,0) -> 1854.13 | R85: =VLOOKUP(C85,IP!$B$9:$O$117,14,0) -> 0 | T85: =VLOOKUP(C85,IP!$B$9:$P$117,15,0) -> 0 | U85: =VLOOKUP(C85,IP!$B$9:$Q$117,16,0) -> 0 | W85: =VLOOKUP(C85,IP!B$9:R$117,17,0) -> 0 | Y85: =+K85-O85-P85+Q85+R85+S85+T85+U85+V85+W85 -> 4000 | Z85: =+M85-Y85 -> 0
A86: SEI0468 | B86: SEITON (IP INNOVA II) | C86: Ramirez Vera Eustolia | E86: =VLOOKUP(C86,IP!$B$9:$V$117,21,0) -> 3433 | G86: =VLOOKUP(C86,SINDICATO!$C$36:$F$144,4,0) -> 0 | H86: =VLOOKUP(C86,SINDICATO!$C$36:$G$144,5,0) -> 0 | I86: =VLOOKUP(C86,SINDICATO!$C$36:$H$132,6,0) -> 0 | K86: =+D86+E86+G86+H86+I86 -> 3433 | L86: 7900 | M86: =+L86/2 -> 3950 | O86: =VLOOKUP(C86,IP!$B$9:$I$117,8,0) -> 0 | P86: =+H86+I86 -> 0 | Q86: =VLOOKUP(C86,IP!$B$9:$N$117,13,0) -> 571.83 | R86: =VLOOKUP(C86,IP!$B$9:$O$117,14,0) -> 0 | T86: =VLOOKUP(C86,IP!$B$9:$P$117,15,0) -> 0 | U86: =VLOOKUP(C86,IP!$B$9:$Q$117,16,0) -> 0 | W86: =VLOOKUP(C86,IP!B$9:R$117,17,0) -> 0 | Y86: =+K86-O86-P86+Q86+R86+S86+T86+U86+V86+W86 -> 4004.83 | Z86: =+M86-Y86 -> -54.83 | AA86: subsidio
A87: SEI0469 | B87: SEITON (IP INNOVA II) | C87: Martinez Morales Jose Martin | E87: =VLOOKUP(C87,IP!$B$9:$V$117,21,0) -> 5952.2 | G87: =VLOOKUP(C87,SINDICATO!$C$36:$F$144,4,0) -> 1047.8 | H87: =VLOOKUP(C87,SINDICATO!$C$36:$G$144,5,0) -> 178.57 | I87: =VLOOKUP(C87,SINDICATO!$C$36:$H$132,6,0) -> 0 | K87: =+D87+E87+G87+H87+I87 -> 7178.57 | L87: 14000 | M87: =+L87/2 -> 7000 | O87: =VLOOKUP(C87,IP!$B$9:$I$117,8,0) -> 0 | P87: =+H87+I87 -> 178.57 | Q87: =VLOOKUP(C87,IP!$B$9:$N$117,13,0) -> 0 | R87: =VLOOKUP(C87,IP!$B$9:$O$117,14,0) -> 0 | T87: =VLOOKUP(C87,IP!$B$9:$P$117,15,0) -> 0 | U87: =VLOOKUP(C87,IP!$B$9:$Q$117,16,0) -> 0 | W87: =VLOOKUP(C87,IP!B$9:R$117,17,0) -> 0 | Y87: =+K87-O87-P87+Q87+R87+S87+T87+U87+V87+W87 -> 7000 | Z87: =+M87-Y87 -> 0
A88: SEI0472 | B88: SEITON (IP INNOVA II) | C88: Arzate Gil Juan Sebastian | E88: =VLOOKUP(C88,IP!$B$9:$V$117,21,0) -> 3270 | G88: =VLOOKUP(C88,SINDICATO!$C$36:$F$144,4,0) -> 416.2 | H88: =VLOOKUP(C88,SINDICATO!$C$36:$G$144,5,0) -> 180 | I88: =VLOOKUP(C88,SINDICATO!$C$36:$H$132,6,0) -> 0 | K88: =+D88+E88+G88+H88+I88 -> 3866.2 | L88: 8000 | M88: =+L88/2 -> 4000 | O88: =VLOOKUP(C88,IP!$B$9:$I$117,8,0) -> 0 | P88: =+H88+I88 -> 180 | Q88: =VLOOKUP(C88,IP!$B$9:$N$117,13,0) -> 0 | R88: =VLOOKUP(C88,IP!$B$9:$O$117,14,0) -> 0 | T88: =VLOOKUP(C88,IP!$B$9:$P$117,15,0) -> 0 | U88: =VLOOKUP(C88,IP!$B$9:$Q$117,16,0) -> 0 | W88: =VLOOKUP(C88,IP!B$9:R$117,17,0) -> 313.8 | Y88: =+K88-O88-P88+Q88+R88+S88+T88+U88+V88+W88 -> 4000 | Z88: =+M88-Y88 -> 0
A89: SEI0473 | B89: SEITON (IP INNOVA II) | C89: Torres Velazquez Juan Antonio | E89: =VLOOKUP(C89,IP!$B$9:$V$117,21,0) -> 3583.6 | G89: =VLOOKUP(C89,SINDICATO!$C$36:$F$144,4,0) -> 416.4 | H89: =VLOOKUP(C89,SINDICATO!$C$36:$G$144,5,0) -> 770 | I89: =VLOOKUP(C89,SINDICATO!$C$36:$H$132,6,0) -> 0 | K89: =+D89+E89+G89+H89+I89 -> 4770 | L89: 8000 | M89: =+L89/2 -> 4000 | O89: =VLOOKUP(C89,IP!$B$9:$I$117,8,0) -> 0 | P89: =+H89+I89 -> 770 | Q89: =VLOOKUP(C89,IP!$B$9:$N$117,13,0) -> 0 | R89: =VLOOKUP(C89,IP!$B$9:$O$117,14,0) -> 0 | T89: =VLOOKUP(C89,IP!$B$9:$P$117,15,0) -> 0 | U89: =VLOOKUP(C89,IP!$B$9:$Q$117,16,0) -> 0 | W89: =VLOOKUP(C89,IP!B$9:R$117,17,0) -> 0 | Y89: =+K89-O89-P89+Q89+R89+S89+T89+U89+V89+W89 -> 4000 | Z89: =+M89-Y89 -> 0
A90: SEI0474 | B90: SEITON (IP INNOVA II) | C90: Enriquez Zamora Jessica Del Rocio | E90: =VLOOKUP(C90,IP!$B$9:$V$117,21,0) -> 2810.2 | G90: =VLOOKUP(C90,SINDICATO!$C$36:$F$144,4,0) -> 109.8 | H90: =VLOOKUP(C90,SINDICATO!$C$36:$G$144,5,0) -> 422.5 | I90: =VLOOKUP(C90,SINDICATO!$C$36:$H$132,6,0) -> 0 | K90: =+D90+E90+G90+H90+I90 -> 3342.5 | L90: 6000 | M90: =+L90/2 -> 3000 | O90: =VLOOKUP(C90,IP!$B$9:$I$117,8,0) -> 120 | P90: =+H90+I90 -> 422.5 | Q90: =VLOOKUP(C90,IP!$B$9:$N$117,13,0) -> 0 | R90: =VLOOKUP(C90,IP!$B$9:$O$117,14,0) -> 0 | T90: =VLOOKUP(C90,IP!$B$9:$P$117,15,0) -> 0 | U90: =VLOOKUP(C90,IP!$B$9:$Q$117,16,0) -> 0 | W90: =VLOOKUP(C90,IP!B$9:R$117,17,0) -> 0 | Y90: =+K90-O90-P90+Q90+R90+S90+T90+U90+V90+W90 -> 2800 | Z90: =+M90-Y90 -> 200 | AA90: 1PSS
A91: SEI0475 | B91: SEITON (IP INNOVA II) | C91: Moreno Quiroga Ana Sarahi | E91: =VLOOKUP(C91,IP!$B$9:$V$117,21,0) -> 3583.8 | G91: =VLOOKUP(C91,SINDICATO!$C$36:$F$144,4,0) -> 416.2 | H91: =VLOOKUP(C91,SINDICATO!$C$36:$G$144,5,0) -> 187.5 | I91: =VLOOKUP(C91,SINDICATO!$C$36:$H$132,6,0) -> 0 | K91: =+D91+E91+G91+H91+I91 -> 4187.5 | L91: 8000 | M91: =+L91/2 -> 4000 | O91: =VLOOKUP(C91,IP!$B$9:$I$117,8,0) -> 0 | P91: =+H91+I91 -> 187.5 | Q91: =VLOOKUP(C91,IP!$B$9:$N$117,13,0) -> 0 | R91: =VLOOKUP(C91,IP!$B$9:$O$117,14,0) -> 0 | T91: =VLOOKUP(C91,IP!$B$9:$P$117,15,0) -> 0 | U91: =VLOOKUP(C91,IP!$B$9:$Q$117,16,0) -> 0 | W91: =VLOOKUP(C91,IP!B$9:R$117,17,0) -> 0 | Y91: =+K91-O91-P91+Q91+R91+S91+T91+U91+V91+W91 -> 4000 | Z91: =+M91-Y91 -> 0
A92: SEI0476 | B92: SEITON (IP INNOVA II) | C92: Hernandez Garcia Manuel Alejandro | E92: =VLOOKUP(C92,IP!$B$9:$V$117,21,0) -> 3585.4 | G92: =VLOOKUP(C92,SINDICATO!$C$36:$F$144,4,0) -> 414.6 | H92: =VLOOKUP(C92,SINDICATO!$C$36:$G$144,5,0) -> 1308.8 | I92: =VLOOKUP(C92,SINDICATO!$C$36:$H$132,6,0) -> 0 | K92: =+D92+E92+G92+H92+I92 -> 5308.8 | L92: 8000 | M92: =+L92/2 -> 4000 | O92: =VLOOKUP(C92,IP!$B$9:$I$117,8,0) -> 0 | P92: =+H92+I92 -> 1308.8 | Q92: =VLOOKUP(C92,IP!$B$9:$N$117,13,0) -> 0 | R92: =VLOOKUP(C92,IP!$B$9:$O$117,14,0) -> 0 | T92: =VLOOKUP(C92,IP!$B$9:$P$117,15,0) -> 0 | U92: =VLOOKUP(C92,IP!$B$9:$Q$117,16,0) -> 0 | W92: =VLOOKUP(C92,IP!B$9:R$117,17,0) -> 0 | Y92: =+K92-O92-P92+Q92+R92+S92+T92+U92+V92+W92 -> 4000 | Z92: =+M92-Y92 -> 0
A93: SEI0477 | B93: SEITON (IP INNOVA II) | C93: Sandoval Medina Demetrio | E93: =VLOOKUP(C93,IP!$B$9:$V$117,21,0) -> 3585.2 | G93: =VLOOKUP(C93,SINDICATO!$C$36:$F$144,4,0) -> 414.8 | H93: =VLOOKUP(C93,SINDICATO!$C$36:$G$144,5,0) -> 270 | I93: =VLOOKUP(C93,SINDICATO!$C$36:$H$132,6,0) -> 0 | K93: =+D93+E93+G93+H93+I93 -> 4270 | L93: 8000 | M93: =+L93/2 -> 4000 | O93: =VLOOKUP(C93,IP!$B$9:$I$117,8,0) -> 0 | P93: =+H93+I93 -> 270 | Q93: =VLOOKUP(C93,IP!$B$9:$N$117,13,0) -> 0 | R93: =VLOOKUP(C93,IP!$B$9:$O$117,14,0) -> 0 | T93: =VLOOKUP(C93,IP!$B$9:$P$117,15,0) -> 0 | U93: =VLOOKUP(C93,IP!$B$9:$Q$117,16,0) -> 0 | W93: =VLOOKUP(C93,IP!B$9:R$117,17,0) -> 0 | Y93: =+K93-O93-P93+Q93+R93+S93+T93+U93+V93+W93 -> 4000 | Z93: =+M93-Y93 -> 0
A94: SEI0478 | B94: SEITON (IP INNOVA II) | C94: Leal Montaño Francisco | E94: =VLOOKUP(C94,IP!$B$9:$V$117,21,0) -> 1779 | G94: =VLOOKUP(C94,SINDICATO!$C$36:$F$144,4,0) -> 109.89 | H94: =VLOOKUP(C94,SINDICATO!$C$36:$G$144,5,0) -> 1000 | I94: =VLOOKUP(C94,SINDICATO!$C$36:$H$132,6,0) -> 0 | K94: =+D94+E94+G94+H94+I94 -> 2888.89 | L94: 6000 | M94: =+L94/2 -> 3000 | O94: =VLOOKUP(C94,IP!$B$9:$I$117,8,0) -> 0 | P94: =+H94+I94 -> 1000 | Q94: =VLOOKUP(C94,IP!$B$9:$N$117,13,0) -> 911.11 | R94: =VLOOKUP(C94,IP!$B$9:$O$117,14,0) -> 0 | T94: =VLOOKUP(C94,IP!$B$9:$P$117,15,0) -> 0 | U94: =VLOOKUP(C94,IP!$B$9:$Q$117,16,0) -> 0 | W94: =VLOOKUP(C94,IP!B$9:R$117,17,0) -> 0 | Y94: =+K94-O94-P94+Q94+R94+S94+T94+U94+V94+W94 -> 2800 | Z94: =+M94-Y94 -> 200 | AA94: 1PSS
A95: SEI479 | B95: SEITON (IP INNOVA II) | C95: Cruz Perez Alejandro Nezahualcoyotl | E95: =VLOOKUP(C95,IP!$B$9:$V$117,21,0) -> 3583.6 | G95: =VLOOKUP(C95,SINDICATO!$C$36:$F$144,4,0) -> 416.4 | H95: =VLOOKUP(C95,SINDICATO!$C$36:$G$144,5,0) -> 300 | I95: =VLOOKUP(C95,SINDICATO!$C$36:$H$132,6,0) -> 0 | K95: =+D95+E95+G95+H95+I95 -> 4300 | L95: 8000 | M95: =+L95/2 -> 4000 | O95: =VLOOKUP(C95,IP!$B$9:$I$117,8,0) -> 0 | P95: =+H95+I95 -> 300 | Q95: =VLOOKUP(C95,IP!$B$9:$N$117,13,0) -> 0 | R95: =VLOOKUP(C95,IP!$B$9:$O$117,14,0) -> 0 | T95: =VLOOKUP(C95,IP!$B$9:$P$117,15,0) -> 0 | U95: =VLOOKUP(C95,IP!$B$9:$Q$117,16,0) -> 0 | W95: =VLOOKUP(C95,IP!B$9:R$117,17,0) -> 0 | Y95: =+K95-O95-P95+Q95+R95+S95+T95+U95+V95+W95 -> 4000 | Z95: =+M95-Y95 -> 0
A96: SEI0415 | B96: SEITON (IP INNOVA II) | C96: Mireles Casillas Brenda Cristina | E96: =VLOOKUP(C96,IP!$B$9:$V$117,21,0) -> 2237.8 | G96: =VLOOKUP(C96,SINDICATO!$C$36:$F$144,4,0) -> 2262.2 | H96: =VLOOKUP(C96,SINDICATO!$C$36:$G$144,5,0) -> 0 | I96: =VLOOKUP(C96,SINDICATO!$C$36:$H$132,6,0) -> 0 | K96: =+D96+E96+G96+H96+I96 -> 4500 | L96: 9000 | M96: =+L96/2 -> 4500 | O96: =VLOOKUP(C96,IP!$B$9:$I$117,8,0) -> 0 | P96: =+H96+I96 -> 0 | Q96: =VLOOKUP(C96,IP!$B$9:$N$117,13,0) -> 0 | R96: =VLOOKUP(C96,IP!$B$9:$O$117,14,0) -> 0 | T96: =VLOOKUP(C96,IP!$B$9:$P$117,15,0) -> 0 | U96: =VLOOKUP(C96,IP!$B$9:$Q$117,16,0) -> 0 | V96: 0 | W96: =VLOOKUP(C96,IP!B$9:R$117,17,0) -> 0 | Y96: =+K96-O96-P96+Q96+R96+S96+T96+U96+V96+W96 -> 4500 | Z96: =+M96-Y96 -> 0
A97: SEI0033 | B97: SEITON (IP INNOVA II) | C97: Molina Ramirez Gerardo Daniel | E97: =VLOOKUP(C97,IP!$B$9:$V$117,21,0) -> 1465.6 | G97: =VLOOKUP(C97,SINDICATO!$C$36:$F$144,4,0) -> 2262.25 | H97: =VLOOKUP(C97,SINDICATO!$C$36:$G$144,5,0) -> 333.34 | I97: =VLOOKUP(C97,SINDICATO!$C$36:$H$132,6,0) -> 0 | K97: =+D97+E97+G97+H97+I97 -> 4061.19 | L97: =VLOOKUP(C97,ABC!$A$3:$B$88,2,0) -> 9000 | M97: =+L97/2 -> 4500 | O97: =VLOOKUP(C97,IP!$B$9:$I$117,8,0) -> 0 | P97: =+H97+I97 -> 333.34 | Q97: =VLOOKUP(C97,IP!$B$9:$N$117,13,0) -> 0 | R97: =VLOOKUP(C97,IP!$B$9:$O$117,14,0) -> 772.15 | T97: =VLOOKUP(C97,IP!$B$9:$P$117,15,0) -> 0 | U97: =VLOOKUP(C97,IP!$B$9:$Q$117,16,0) -> 0 | V97: 0 | W97: =VLOOKUP(C97,IP!B$9:R$117,17,0) -> 0 | Y97: =+K97-O97-P97+Q97+R97+S97+T97+U97+V97+W97 -> 4500 | Z97: =+M97-Y97 -> 0
A98: SEI0095 | B98: SEITON (IP INNOVA II) | C98: Gutierrez Muñoz Carlos Alejandro | E98: =VLOOKUP(C98,IP!$B$9:$V$117,21,0) -> 1074 | G98: =VLOOKUP(C98,SINDICATO!$C$36:$F$144,4,0) -> 2884.99 | H98: =VLOOKUP(C98,SINDICATO!$C$36:$G$144,5,0) -> 0 | I98: =VLOOKUP(C98,SINDICATO!$C$36:$H$132,6,0) -> 0 | K98: =+D98+E98+G98+H98+I98 -> 3958.99 | L98: =VLOOKUP(C98,ABC!$A$3:$B$88,2,0) -> 12000 | M98: =+L98/2 -> 6000 | O98: =VLOOKUP(C98,IP!$B$9:$I$117,8,0) -> 0 | P98: =+H98+I98 -> 0 | Q98: =VLOOKUP(C98,IP!$B$9:$N$117,13,0) -> 2041.01 | R98: =VLOOKUP(C98,IP!$B$9:$O$117,14,0) -> 0 | T98: =VLOOKUP(C98,IP!$B$9:$P$117,15,0) -> 0 | U98: =VLOOKUP(C98,IP!$B$9:$Q$117,16,0) -> 0 | V98: 0 | W98: =VLOOKUP(C98,IP!B$9:R$117,17,0) -> 0 | Y98: =+K98-O98-P98+Q98+R98+S98+T98+U98+V98+W98 -> 6000 | Z98: =+M98-Y98 -> 0
A99: SEI0096 | B99: SEITON (IP INNOVA II) | C99: Camarillo Canela Reynaldo | E99: =VLOOKUP(C99,IP!$B$9:$V$117,21,0) -> 1721.4 | G99: =VLOOKUP(C99,SINDICATO!$C$36:$F$144,4,0) -> 2219.28 | H99: =VLOOKUP(C99,SINDICATO!$C$36:$G$144,5,0) -> 1480 | I99: =VLOOKUP(C99,SINDICATO!$C$36:$H$132,6,0) -> 295.76 | K99: =+D99+E99+G99+H99+I99 -> 5716.44 | L99: =VLOOKUP(C99,ABC!$A$3:$B$88,2,0) -> 9800 | M99: =+L99/2 -> 4900 | O99: =VLOOKUP(C99,IP!$B$9:$I$117,8,0) -> 390.24 | P99: =+H99+I99 -> 1775.76 | Q99: =VLOOKUP(C99,IP!$B$9:$N$117,13,0) -> 1349.52 | R99: =VLOOKUP(C99,IP!$B$9:$O$117,14,0) -> 0 | T99: =VLOOKUP(C99,IP!$B$9:$P$117,15,0) -> 0 | U99: =VLOOKUP(C99,IP!$B$9:$Q$117,16,0) -> 0 | V99: 0 | W99: =VLOOKUP(C99,IP!B$9:R$117,17,0) -> 0 | Y99: =+K99-O99-P99+Q99+R99+S99+T99+U99+V99+W99 -> 4899.96 | Z99: =+M99-Y99 -> 0.04
A100: SEI0416 | B100: SEITON (IP INNOVA II) | C100: Escobedo Olivares Juan Guadalupe | E100: =VLOOKUP(C100,IP!$B$9:$V$117,21,0) -> 3278.8 | G100: =VLOOKUP(C100,SINDICATO!$C$36:$F$144,4,0) -> 3721.2 | H100: =VLOOKUP(C100,SINDICATO!$C$36:$G$144,5,0) -> 166.67 | I100: =VLOOKUP(C100,SINDICATO!$C$36:$H$132,6,0) -> 0 | K100: =+D100+E100+G100+H100+I100 -> 7166.67 | L100: 14000 | M100: =+L100/2 -> 7000 | O100: =VLOOKUP(C100,IP!$B$9:$I$117,8,0) -> 0 | P100: =+H100+I100 -> 166.67 | Q100: =VLOOKUP(C100,IP!$B$9:$N$117,13,0) -> 0 | R100: =VLOOKUP(C100,IP!$B$9:$O$117,14,0) -> 0 | T100: =VLOOKUP(C100,IP!$B$9:$P$117,15,0) -> 0 | U100: =VLOOKUP(C100,IP!$B$9:$Q$117,16,0) -> 0 | V100: 0 | W100: =VLOOKUP(C100,IP!B$9:R$117,17,0) -> 0 | Y100: =+K100-O100-P100+Q100+R100+S100+T100+U100+V100+W100 -> 7000 | Z100: =+M100-Y100 -> 0
A101: SEI0417 | B101: SEITON (IP INNOVA II) | C101: Castillo Ramirez Hector Ivan | E101: =VLOOKUP(C101,IP!$B$9:$V$117,21,0) -> 2369.2 | G101: =VLOOKUP(C101,SINDICATO!$C$36:$F$144,4,0) -> 3721.3 | H101: =VLOOKUP(C101,SINDICATO!$C$36:$G$144,5,0) -> 208.34 | I101: =VLOOKUP(C101,SINDICATO!$C$36:$H$132,6,0) -> 0 | K101: =+D101+E101+G101+H101+I101 -> 6298.84 | L101: 14000 | M101: =+L101/2 -> 7000 | O101: =VLOOKUP(C101,IP!$B$9:$I$117,8,0) -> 0 | P101: =+H101+I101 -> 208.34 | Q101: =VLOOKUP(C101,IP!$B$9:$N$117,13,0) -> 0 | R101: =VLOOKUP(C101,IP!$B$9:$O$117,14,0) -> 0 | T101: =VLOOKUP(C101,IP!$B$9:$P$117,15,0) -> 0 | U101: =VLOOKUP(C101,IP!$B$9:$Q$117,16,0) -> 0 | V101: 0 | W101: =VLOOKUP(C101,IP!B$9:R$117,17,0) -> 909.5 | Y101: =+K101-O101-P101+Q101+R101+S101+T101+U101+V101+W101 -> 7000 | Z101: =+M101-Y101 -> 0
...

Sheet NETOS
A5: CLAVE | B5: SUCURSAL | C5: NOMBRE | D5: NETO SALARIOS | E5: INFONAVIT | F5: NETO SINDICATO | G5: NETO A PAGAR
C6: ARCEO GARCIA MANUEL FEDERICO | D6: 2847.47 | F6: 152.53 | G6: =+F6+D6+E6 -> 3000
A7: SEI0003 | B7: SEITON (IP INNOVA II) | C7: ARELLANO LOPEZ ADRIANA ISELA | D7: 3215.9033 | E7: 0 | F7: 234.1 | G7: =+F7+D7+E7 -> 3450.0033
A8: SEI0097 | B8: SEITON - (CONSULTORIA II) | C8: ARREOLA JIMENEZ JOSE NIEVES | D8: 2105.51 | E8: 1394.18 | F8: 1000.31 | G8: =+F8+D8+E8 -> 4500
A9: SEI0118 | B9: SEITON - (CONSULTORIA II) | C9: ARROYO RAMIREZ HECTOR HUGO | D9: 3109.74 | E9: 1268.65 | F9: 1121.6 | G9: =+F9+D9+E9 -> 5499.99
A10: SEI0108 | B10: SEITON - (CONSULTORIA II) | C10: CABALLERO DIAZ FRANCISCO JAVIER | D10: 1882.39 | E10: 1617.3 | F10: 1000.31 | G10: =+F10+D10+E10 -> 4500
A11: SEI0425 | B11: SEITON - (CONSULTORIA II) | C11: CARBAJAL CABUTO JOSE LUIS | D11: 2165.48 | E11: 1334.21 | F11: 725.31 | G11: =+F11+D11+E11 -> 4225
A12: SEI0116 | B12: SEITON - (CONSULTORIA II) | C12: CASILLAS CARDONA CESAR ALEJANDRO | D12: 3156.22 | E12: 934.91 | F12: 907.87 | G12: =+F12+D12+E12 -> 4999
A13: SEI0013 | B13: SEITON (IP INNOVA II) | C13: CASTILLO SANCHEZ MIGUEL ANGEL | D13: 3947.3665 | E13: 0 | F13: 552.72 | G13: =+F13+D13+E13 -> 4500.0865
