Workbook

Sheet FACTURACION SINDICATO
B2: codigo | C2: empres | D2: nombre | E2: PAGO POR SINDICATO | F2: comision y bono | G2: prima vacaciones | H2: TOTAL | I2: CC
B3: SEI0097 | C3: SEITON - (CONSULTORIA II) | D3: Arreola Jimenez Jose Nieves | E3: 1558.05 | F3: 2975 | G3: 0 | H3: 4533.05 | I3: AA
B4: SEI0118 | C4: SEITON - (CONSULTORIA II) | D4: Arroyo Ramirez Hector Hugo | E4: 2103.54 | G4: 234 | H4: 2337.54 | I4: AA
B5: SEI0108 | C5: SEITON - (CONSULTORIA II) | D5: Caballero Diaz Francisco Javier | E5: 1558.01 | G5: 0 | H5: 1558.01 | I5: AA
B6: SEI0425 | C6: SEITON - (CONSULTORIA II) | D6: Carbajal Cabuto Jose Luis | E6: 1608.07 | G6: 0 | H6: 1608.07 | I6: AA
B7: SEI0116 | C7: SEITON - (CONSULTORIA II) | D7: Casillas Cardona Cesar Alejandro | E7: 1891.22 | G7: 0 | H7: 1891.22 | I7: AA
B8: SEI0401 | C8: SEITON - (CONSULTORIA II) | D8: De La Torre Zambara Francisco Ernesto | E8: 78.08 | G8: 0 | H8: 78.08 | I8: AA
B9: SEI0119 | C9: SEITON - (CONSULTORIA II) | D9: Dominguez Lopez Maria De Jesus | E9: 0 | G9: 0 | H9: 0 | I9: AA
B10: SEI0099 | C10: SEITON - (CONSULTORIA II) | D10: Garcia Villicaña Ricardo Pascual | E10: 2600.8 | F10: 600 | G10: 0 | H10: 3200.8 | I10: AA
B11: SEI0009 | C11: SEITON - (CONSULTORIA II) | D11: Gutierrez Gutierrez Luis Arturo | E11: 1474.6 | G11: 0 | H11: 1474.6 | I11: AA
B12: SEI0127 | C12: SEITON - (CONSULTORIA II) | D12: Hernandez Ochoa Eduardo | E12: 2601 | G12: 0 | H12: 2601 | I12: AA
B13: SEI0088 | C13: SEITON - (CONSULTORIA II) | D13: Morgado Fernandez Martin | E13: 2601 | F13: 1125 | G13: 0 | H13: 3726 | I13: AA
B14: SEI0173 | C14: SEITON - (CONSULTORIA II) | D14: Nieto Ortiz Jose Luis | E14: 1483.15 | F14: 1232 | G14: 0 | H14: 2715.15 | I14: AA
B15: SEI0026 | C15: SEITON - (CONSULTORIA II) | D15: Patricio Aguilar Jhonattan Cristian | E15: 1588 | G15: 0 | H15: 1588 | I15: AA
B16: SEI0027 | C16: SEITON - (CONSULTORIA II) | D16: Tavares Guzman Jose Enrique | E16: 2378.2 | G16: 0 | H16: 2378.2 | I16: AA
B17: SEI032 | C17: SEITON - (CONSULTORIA II) | D17: Camarena Quiroz Erick Frank | E17: 1588 | F17: 225 | G17: 0 | H17: 1813 | I17: AA
B18: SEI0438 | C18: SEITON - (CONSULTORIA II) | D18: Valdes Arrioja Karla Naborina | E18: 1803.2 | H18: 1803.2 | I18: AA
B19: SEI0482 | C19: SEITON (IP INNOVA II) | D19: Camarillo Canela Reynaldo | E19: 2236.64 | F19: 2150 | G19: 0 | H19: 4386.64 | I19: AA
B20: SEI0485 | C20: SEITON (IP INNOVA II) | D20: Molina Ramirez Gerardo Daniel | E20: 2271.77 | G20: 0 | H20: 2271.77 | I20: AA
B21: SEI0488 | C21: SEITON (IP INNOVA II) | D21: Mireles Casillas Brenda Cristina | E21: 2257 | G21: 0 | H21: 2257 | I21: AA
B22: SEI0489 | C22: SEITON (IP INNOVA II) | D22: Escobedo Olivares Juan Guadalupe | E22: 3723.8 | G22: 0 | H22: 3723.8 | I22: AA
B23: SEI0490 | C23: SEITON (IP INNOVA II) | D23: Castillo Ramirez Hector Ivan | E23: 3753.78 | F23: 1280 | G23: 0 | H23: 5033.78 | I23: AA
B24: SEI0492 | C24: SEITON (IP INNOVA II) | D24: Cadena Ramirez Hugo | E24: 2513.4 | G24: 0 | H24: 2513.4 | I24: AA
B25: SEI0493 | C25: SEITON (IP INNOVA II) | D25: Martinez Morales Tomas | E25: 3397.14 | F25: 1320 | G25: 0 | H25: 4717.14 | I25: AA
B26: SEI0494 | C26: SEITON (IP INNOVA II) | D26: Medellin Colunga Ruben Dario | E26: 4412.14 | F26: 2320 | G26: 0 | H26: 6732.14 | I26: AA
B27: SEI0495 | C27: SEITON (IP INNOVA II) | D27: Torres Perez Carlos Alberto | E27: 1685.3 | F27: 4495 | G27: 0 | H27: 6180.3 | I27: AA
B28: SEI0496 | C28: SEITON (IP INNOVA II) | D28: Velazquez Herrera Nayeli | E28: 3382.26 | F28: 950 | G28: 56.14 | H28: 4388.4 | I28: AA
B29: SEI0497 | C29: SEITON (IP INNOVA II) | D29: Treviño Alvarez Jorge Alberto | E29: 2700.29 | F29: 680 | G29: 0 | H29: 3380.29 | I29: AA
B30: SEI0498 | C30: SEITON (IP INNOVA II) | D30: Tenorio Alvarez Alberto Antonio | E30: 1685.2 | G30: 0 | H30: 1685.2 | I30: AA
B31: SEI0499 | C31: SEITON (IP INNOVA II) | D31: Chavez Dominguez Salvador | E31: 2685.2 | G31: 0 | H31: 2685.2 | I31: AA
B32: SEI0500 | C32: SEITON (IP INNOVA II) | D32: Garcia Gutierrez Jose Juan | E32: 1685.2 | G32: 0 | H32: 1685.2 | I32: AA
B33: SEI0501 | C33: SEITON (IP INNOVA II) | D33: Cruz Herrera Roberto | E33: 1670.2 | G33: 0 | H33: 1670.2 | I33: AA
B34: SEI0502 | C34: SEITON (IP INNOVA II) | D34: Dominguez Escamilla Victor Hugo | E34: 2700.14 | G34: 0 | H34: 2700.14 | I34: AA
B35: SEI0503 | C35: SEITON (IP INNOVA II) | D35: Martinez Rodriguez Paulo Cesar | E35: 2554.8 | G35: 0 | H35: 2554.8 | I35: AA
B36: SEI0504 | C36: SEITON (IP INNOVA II) | D36: Martinez Malo Cesar | E36: 1711.46 | G36: 0 | H36: 1711.46 | I36: AA
B37: SEI0505 | C37: SEITON (IP INNOVA II) | D37: Perez Balboa Cesar | E37: 2211.65 | G37: 0 | H37: 2211.65 | I37: AA
B38: SEI0506 | C38: SEITON (IP INNOVA II) | D38: Mejia Duarte Jose Luis | E38: 2570.57 | G38: 0 | H38: 2570.57 | I38: AA
B39: SEI0507 | C39: SEITON (IP INNOVA II) | D39: Diaz Saldierna Leonel Gonzalo | E39: 2585.53 | G39: 0 | H39: 2585.53 | I39: AA
B40: SEI0508 | C40: SEITON (IP INNOVA II) | D40: Cerro Garcia Elvis | E40: 2570.6 | F40: 2125 | G40: 0 | H40: 4695.6 | I40: AA
B41: SEI0078 | C41: SEITON (IP INNOVA II) | D41: Aguilar Leal Karina Livier | E41: 952.25 | F41: 16065.1 | G41: 10 | H41: 17027.35 | I41: AA
B42: SEI0126 | C42: SEITON (IP INNOVA II) | D42: Alonso Flores Beda | E42: 1102.59 | G42: 0 | H42: 1102.59 | I42: AA
B43: SEI0029 | C43: SEITON (IP INNOVA II) | D43: Arceo Garcia Manuel Federico | E43: 152.5 | G43: 0 | H43: 152.5 | I43: AA
B44: SEI0003 | C44: SEITON (IP INNOVA II) | D44: Arellano Lopez Adriana Isela | E44: 231.8 | G44: 0 | H44: 231.8 | I44: AA
B45: SEI0230 | C45: SEITON (IP INNOVA II) | D45: Bueno Herrera Mariana Guadalupe | E45: 1452.1 | F45: 2269.72 | G45: 0 | H45: 3721.82 | I45: AA
B46: SEI0013 | C46: SEITON (IP INNOVA II) | D46: Castillo Sanchez Miguel Angel | E46: 1549.97 | F46: 960 | G46: 0 | H46: 2509.97 | I46: AA
B47: SEI0031 | C47: SEITON (IP INNOVA II) | D47: Contreras Zetina Victor Hugo | E47: 233.2 | G47: 0 | H47: 233.2 | I47: AA
B48: SEI0015 | C48: SEITON (IP INNOVA II) | D48: Cota Jaramillo Miguel Angel | E48: 151.4 | G48: 0 | H48: 151.4 | I48: AA
B49: SEI0413 | C49: SEITON (IP INNOVA II) | D49: Courtenay Gutierrez Barry Vladimir | E49: 69.74 | F49: 3360 | G49: 0 | H49: 3429.74 | I49: AA
B50: SEI0364 | C50: SEITON (IP INNOVA II) | D50: Dominguez Lopez Mayeli Del Pilar | E50: 1437.13 | G50: 0 | H50: 1437.13 | I50: AA
B51: SEI0018 | C51: SEITON (IP INNOVA II) | D51: Dominguez Mendez Victor Manuel | E51: 550 | G51: 0 | H51: 550 | I51: AA
B52: SEI0037 | C52: SEITON (IP INNOVA II) | D52: Gomez Oliveros Alin | E52: 602.6 | F52: 1843.07 | G52: 0 | H52: 2445.67 | I52: AA
B53: SEI0019 | C53: SEITON (IP INNOVA II) | D53: Gonzalez Rasgado Miguel Isaias | E53: 896.4 | G53: 0 | H53: 896.4 | I53: AA
B54: SEI0081 | C54: SEITON (IP INNOVA II) | D54: Guizar Perez Sergio | E54: 904.8 | G54: 0 | H54: 904.8 | I54: AA
B55: SEI0012 | C55: SEITON (IP INNOVA II) | D55: Hernandez Renteria Javier Fernando | E55: 550 | G55: 0 | H55: 550 | I55: AA
B56: SEI0332 | C56: SEITON (IP INNOVA II) | D56: Lara Campos Maximino | E56: 1475.2 | G56: 0 | H56: 1475.2 | I56: AA
B57: SEI0020 | C57: SEITON (IP INNOVA II) | D57: Mar Marquez Cesar Eduardo | E57: 435.4 | G57: 0 | H57: 435.4 | I57: AA
B58: SEI0376 | C58: SEITON (IP INNOVA II) | D58: Marquez Alcaraz Martin | E58: 977.35 | G58: 0 | H58: 977.35 | I58: AA
B59: SEI0030 | C59: SEITON (IP INNOVA II) | D59: Marquez Altamirano Marco Antonio | E59: 452.2 | F59: 260 | G59: 0 | H59: 712.2 | I59: AA
B60: SEI0014 | C60: SEITON (IP INNOVA II) | D60: Montoya Portillo Carlos Alberto | E60: 450.4 | F60: 1550 | G60: 0 | H60: 2000.4 | I60: AA
B61: SEI0017 | C61: SEITON (IP INNOVA II) | D61: Muñoz Reyes Luis Eduardo | E61: 465.38 | G61: 0 | H61: 465.38 | I61: AA
B62: SEI0022 | C62: SEITON (IP INNOVA II) | D62: Najera Lopez Raul | E62: 656.13 | F62: 1120 | G62: 0 | H62: 1776.13 | I62: AA
B63: SEI0016 | C63: SEITON (IP INNOVA II) | D63: Negrete Bejar Aide Sarai | E63: 14.8 | G63: 0 | H63: 14.8 | I63: AA
B64: SEI0109 | C64: SEITON (IP INNOVA II) | D64: Negrete Renteria Jose Luis | E64: 1169.97 | G64: 0 | H64: 1169.97 | I64: AA
B65: SEI0023 | C65: SEITON (IP INNOVA II) | D65: Puente Murguia Luis Felipe | E65: 240.2 | G65: 0 | H65: 240.2 | I65: AA
B66: SEI0100 | C66: SEITON (IP INNOVA II) | D66: Quinto Valle Martin | E66: 641.2 | F66: 350 | G66: 0 | H66: 991.2 | I66: AA
B67: SEI0146 | C67: SEITON (IP INNOVA II) | D67: Ramirez Vera Maria Del Carmen | E67: 1467.19 | G67: 0 | H67: 1467.19 | I67: AA
B68: SEI0345 | C68: SEITON (IP INNOVA II) | D68: Rodriguez Diaz Cesar Salvador | E68: 992.07 | G68: 0 | H68: 992.07 | I68: AA
B69: SEI0412 | C69: SEITON (IP INNOVA II) | D69: Rojo Avelar Adrian | E69: 917.5 | G69: 0 | H69: 917.5 | I69: AA
B70: SEI0133 | C70: SEITON (IP INNOVA II) | D70: Romero Mayoral Lorenzo | E70: 2202.21 | G70: 0 | H70: 2202.21 | I70: AA
B71: SEI0010 | C71: SEITON (IP INNOVA II) | D71: Torres Ricardez Alfredo | E71: 450.4 | G71: 0 | H71: 450.4 | I71: AA
B72: SEI0021 | C72: SEITON (IP INNOVA II) | D72: Velez Rodriguez Jaime | E72: 1167.55 | G72: 20 | H72: 1187.55 | I72: AA
B73: SEI0421 | C73: SEITON (IP INNOVA II) | D73: Marin Avila Hector | E73: 734.1 | F73: 1325 | G73: 5.5 | H73: 2064.6 | I73: AA
B74: SEI0422 | C74: SEITON (IP INNOVA II) | D74: Mulgado Guzman Ernesto | E74: 755.07 | F74: 1275 | G74: 0 | H74: 2030.07 | I74: AA
B75: SEI0424 | C75: SEITON (IP INNOVA II) | D75: Palacios Ramos Jesus | E75: 452.2 | F75: 1375 | G75: 0 | H75: 1827.2 | I75: AA
B76: SEI0429 | C76: SEITON (IP INNOVA II) | D76: Torres Gomez Valeria | E76: 22.6 | G76: 0 | H76: 22.6 | I76: AA
B77: SEI0431 | C77: SEITON (IP INNOVA II) | D77: Alcaraz Conde Zabdi Guadalupe | E77: 152.5 | G77: 0 | H77: 152.5 | I77: AA
B78: SEI0428 | C78: SEITON (IP INNOVA II) | D78: Martinez Hernandez J. Antonio | E78: 452.2 | F78: 2900 | G78: 0 | H78: 3352.2 | I78: AA
B79: SEI0433 | C79: SEITON (IP INNOVA II) | D79: Garza Herrera Yareci Anel | E79: 452.4 | G79: 0 | H79: 452.4 | I79: AA
B80: SEI0438 | C80: SEITON (IP INNOVA II) | D80: Lopez Terron Roberto Porfirio | E80: 1139.4 | G80: 0 | H80: 1139.4 | I80: AA
B81: SEI0441 | C81: SEITON (IP INNOVA II) | D81: Ramirez Romero Jose Luis | E81: 1139.4 | G81: 0 | H81: 1139.4 | I81: AA
B82: SEI0442 | C82: SEITON (IP INNOVA II) | D82: Chavez Pedraza Samuel | E82: 1139.4 | G82: 0 | H82: 1139.4 | I82: AA
B83: SEI0443 | C83: SEITON (IP INNOVA II) | D83: Castillo Nungaray Nestor Roman | E83: 152.4 | G83: 0 | H83: 152.4 | I83: AA
B84: SEI0444 | C84: SEITON (IP INNOVA II) | D84: Marquez Hernandez Rogelio | E84: 452.2 | F84: 3050 | G84: 0 | H84: 3502.2 | I84: AA
B85: SEI0448 | C85: SEITON (IP INNOVA II) | D85: Picazo Gutierrez Jose Alfonso | E85: 70.6 | G85: 0 | H85: 70.6 | I85: AA
B86: SEI0449 | C86: SEITON (IP INNOVA II) | D86: Flores Cerrillos Jorge Humberto | E86: 452.2 | G86: 0 | H86: 452.2 | I86: AA
B87: SEI0451 | C87: SEITON (IP INNOVA II) | D87: Hurtado Avalos J.jesus | E87: 137.6 | G87: 0 | H87: 137.6 | I87: AA
B88: SEI0452 | C88: SEITON (IP INNOVA II) | D88: Leija Arevalo Guadalupe | E88: 248.205 | G88: 0 | H88: 248.205 | I88: AA
B89: SEI0453 | C89: SEITON (IP INNOVA II) | D89: Mora Cavazos Roberto Manuel | E89: 452.2 | G89: 0 | H89: 452.2 | I89: AA
B90: SEI0454 | C90: SEITON (IP INNOVA II) | D90: Martinez Rivera Maria Teresa | E90: 442.8 | G90: 0 | H90: 442.8 | I90: AA
B91: SEI0455 | C91: SEITON (IP INNOVA II) | D91: Perez Garcia Andres Alvaro | E91: 452.2 | F91: 860 | G91: 0 | H91: 1312.2 | I91: AA
B92: SEI0456 | C92: SEITON (IP INNOVA II) | D92: Chavira Garcia David Fernando | E92: 656.2 | G92: 0 | H92: 656.2 | I92: AA
B93: SEI0457 | C93: SEITON (IP INNOVA II) | D93: Guerrero Lara Cesar Adrian | E93: 437.2 | G93: 0 | H93: 437.2 | I93: AA
B94: SEI0458 | C94: SEITON (IP INNOVA II) | D94: Martinez Zamora Gerardo Mario | E94: 609.225 | F94: 1550 | G94: 0 | H94: 2159.225 | I94: AA
B95: SEI0460 | C95: SEITON (IP INNOVA II) | D95: Castellon Ramos Rene | E95: 422.955 | F95: 1875 | G95: 0 | H95: 2297.955 | I95: AA
B96: SEI0461 | C96: SEITON (IP INNOVA II) | D96: Flores Franco Marco | E96: 499.655 | F96: 125 | G96: 0 | H96: 624.655 | I96: AA
B97: SEI0462 | C97: SEITON (IP INNOVA II) | D97: Chavez Saucedo Jorge Arturo | E97: 450.6 | H97: 450.6 | I97: AA
B98: SEI0463 | C98: SEITON (IP INNOVA II) | D98: Hernandez Rangel Daniel | E98: 436.95 | F98: 4510 | G98: 0 | H98: 4946.95 | I98: AA
B99: SEI0464 | C99: SEITON (IP INNOVA II) | D99: Hueramo Hueramo Jesus Daniel | E99: 514.685 | G99: 0 | H99: 514.685 | I99: AA
B100: SEI0465 | C100: SEITON (IP INNOVA II) | D100: Sandoval Garcia Luis | E100: 437.2 | G100: 0 | H100: 437.2 | I100: AA
B101: SEI0467 | C101: SEITON (IP INNOVA II) | D101: Vaca Valdez Guillermo | E101: 452.2 | G101: 0 | H101: 452.2 | I101: AA
...

Sheet CPD PITS
B1: CONSULTORIA EN PROYECTOS DINAMICOS S DE RL DE CV
B2: Lista de Raya (forma tabular)
B3: Reg Pat IMSS: Z2940859106
B4: RFC: CPD -150911-FA3
A5: Código | B5: Empleado | C5: Dias Laborados | D5: Dias Vacaciones | E5: Salario Diario | F5: Salario Diario Integrado | G5: Sueldo | H5: Vacaciones a tiempo | I5: Prima de vacaciones a tiempo | J5: Ayuda de Transporte | K5: Ayuda Alimentaria | L5: Ayuda de Renta | M5: *TOTAL* *PERCEPCIONES* | N5: I.S.R. (sp) | O5: Subsidio al Empleo (sp) | P5: I.M.S.S. | Q5: Préstamo Infonavit | R5: Préstamo Infonavit (vsm) | S5: Deduccion general | T5: Ajuste al neto | U5: *TOTAL* *DEDUCCIONES* | V5: *NETO* | W5: Invalidez y Vida | X5: Cesantia y Vejez | Y5: Enf. y Mat. Patron | Z5: 2% Fondo retiro SAR (8) | AA5: 2% Impuesto estatal | AB5: Riesgo de trabajo (9) | AC5: I.M.S.S. empresa | AD5: Infonavit empresa | AE5: Guarderia I.M.S.S. (7) | AF5: Proporcion Aguinaldo | AG5: Banco
A6: SEI0009 | B6: Gutierrez Gutierrez Luis Arturo | C6: 15 | D6: 0 | E6: 141.67 | F6: 150.25 | G6: 2125.05 | H6: 0 | I6: 0 | J6: 212.51 | K6: 212.51 | L6: 212.51 | M6: 2762.58 | N6: 0 | O6: -65.5 | P6: 57.11 | Q6: 0 | R6: 0 | S6: 0 | T6: -0.03 | U6: -8.42 | V6: 2771 | W6: 42.07 | X6: 75.73 | Y6: 317.85 | Z6: 236.93 | AA6: 55.25 | AB6: 12.02 | AC6: 435.65 | AD6: 120.2 | AE6: 212.89 | AF6: 151.27396 | AG6: 12
A7: SEI0026 | B7: Patricio Aguilar Jhonattan Cristian | C7: 15 | D7: 0 | E7: 150 | F7: 159.07 | G7: 2250 | H7: 0 | I7: 0 | J7: 225 | K7: 225 | L7: 225 | M7: 2925 | N7: 0 | O7: -43.57 | P7: 60.44 | Q7: 0 | R7: 0 | S7: 0 | T7: -0.07 | U7: 16.8 | V7: 2908.2 | W7: 44.54 | X7: 80.17 | Y7: 320.32 | Z7: 239.75 | AA7: 58.5 | AB7: 12.73 | AC7: 445.03 | AD7: 127.26 | AE7: 214.3 | AF7: 160.16866 | AG7: 12
A8: SEI0040 | B8: Mora Ramirez Acal Aldo Isidro | C8: 15 | D8: 0 | E8: 216.67 | F8: 229.79 | G8: 3250.05 | H8: 0 | I8: 0 | J8: 325.01 | K8: 325.01 | L8: 325.01 | M8: 4225.08 | N8: 107.17 | O8: 0 | P8: 87.32 | Q8: 0 | R8: 0 | S8: 0 | T8: -0.01 | U8: 194.48 | V8: 4030.6 | W8: 64.34 | X8: 115.81 | Y8: 340.12 | Z8: 262.38 | AA8: 84.5 | AB8: 18.38 | AC8: 520.27 | AD8: 183.83 | AE8: 225.62 | AF8: 231.35828 | AG8: 12
A9: SEI0041 | B9: Vazquez Perez Miguel Angel | C9: 15 | D9: 0 | E9: 283.33 | F9: 300.49 | G9: 4249.95 | H9: 0 | I9: 0 | J9: 425 | K9: 425 | L9: 425 | M9: 5524.95 | N9: 341.06 | O9: 0 | P9: 117.2 | Q9: 0 | R9: 0 | S9: 0 | T9: -0.11 | U9: 458.15 | V9: 5066.8 | W9: 84.14 | X9: 151.45 | Y9: 368.19 | Z9: 285.01 | AA9: 110.5 | AB9: 24.04 | AC9: 603.78 | AD9: 240.39 | AE9: 236.93 | AF9: 302.53724 | AG9: 12
A10: SEI0088 | B10: Morgado Fernandez Martin | C10: 15 | D10: 0 | E10: 273.33 | F10: 289.87 | G10: 4099.95 | H10: 0 | I10: 0 | J10: 410 | K10: 410 | L10: 410 | M10: 5329.95 | N10: 324.74 | O10: 0 | P10: 112.48 | Q10: 0 | R10: 0 | S10: 0 | T10: -0.07 | U10: 437.15 | V10: 4892.8 | W10: 81.16 | X10: 146.09 | Y10: 363.36 | Z10: 281.61 | AA10: 106.6 | AB10: 23.19 | AC10: 590.61 | AD10: 231.89 | AE10: 235.23 | AF10: 291.85933 | AG10: 12
A11: SEI0097 | B11: Arreola Jimenez Jose Nieves | C11: 15 | D11: 0 | E11: 185.83 | F11: 197.07 | G11: 2787.45 | H11: 0 | I11: 0 | J11: 278.75 | K11: 278.75 | L11: 278.75 | M11: 3623.7 | N11: 36.57 | O11: 0 | P11: 74.88 | Q11: 0 | R11: 1574.29 | S11: 120 | T11: -0.04 | U11: 1805.7 | V11: 1818 | W11: 55.18 | X11: 99.32 | Y11: 330.96 | Z11: 251.91 | AA11: 72.47 | AB11: 15.77 | AC11: 485.46 | AD11: 157.66 | AE11: 220.38 | AF11: 198.42761 | AG11: 12
A12: SEI0099 | B12: Garcia Villicaña Ricardo Pascual | C12: 15 | D12: 0 | E12: 273.33 | F12: 289.87 | G12: 4099.95 | H12: 0 | I12: 0 | J12: 410 | K12: 410 | L12: 410 | M12: 5329.95 | N12: 324.74 | O12: 0 | P12: 112.48 | Q12: 0 | R12: 0 | S12: 0 | T12: -0.07 | U12: 437.15 | V12: 4892.8 | W12: 81.16 | X12: 146.09 | Y12: 363.36 | Z12: 281.61 | AA12: 106.6 | AB12: 23.19 | AC12: 590.61 | AD12: 231.89 | AE12: 235.23 | AF12: 291.85933 | AG12: 12
A13: SEI0108 | B13: Caballero Diaz Francisco Javier | C13: 15 | D13: 0 | E13: 185.83 | F13: 197.07 | G13: 2787.45 | H13: 0 | I13: 0 | J13: 278.75 | K13: 278.75 | L13: 278.75 | M13: 3623.7 | N13: 36.57 | O13: 0 | P13: 74.88 | Q13: 0 | R13: 1826.51 | S13: 0 | T13: -0.06 | U13: 1937.9 | V13: 1685.8 | W13: 55.18 | X13: 99.32 | Y13: 330.96 | Z13: 251.91 | AA13: 72.47 | AB13: 15.77 | AC13: 485.46 | AD13: 157.66 | AE13: 220.38 | AF13: 198.42761 | AG13: 12
A14: SEI0116 | B14: Casillas Cardona Cesar Alejandro | C14: 15 | D14: 0 | E14: 220.83 | F14: 234.19 | G14: 3312.45 | H14: 0 | I14: 0 | J14: 331.25 | K14: 331.25 | L14: 331.25 | M14: 4306.2 | N14: 113.96 | O14: 0 | P14: 88.99 | Q14: 0 | R14: 896.6 | S14: 0 | T14: 0.05 | U14: 1099.6 | V14: 3206.6 | W14: 65.57 | X14: 118.03 | Y14: 341.35 | Z14: 263.79 | AA14: 86.12 | AB14: 18.74 | AC14: 524.95 | AD14: 187.35 | AE14: 226.32 | AF14: 235.8003 | AG14: 12
A15: SEI0117 | B15: Mariscal Romero Luis Adrian | C15: 15 | D15: 0 | E15: 264.58 | F15: 276.54 | G15: 3968.7 | H15: 0 | I15: 0 | J15: 396.87 | K15: 396.87 | L15: 396.87 | M15: 5159.31 | N15: 310.46 | O15: 0 | P15: 106.56 | Q15: 0 | R15: 1674 | S15: 0 | T15: 0.09 | U15: 2091.11 | V15: 3068.2 | W15: 77.43 | X15: 139.38 | Y15: 357.27 | Z15: 277.34 | AA15: 103.19 | AB15: 22.12 | AC15: 574.08 | AD15: 221.23 | AE15: 233.1 | AF15: 282.51615 | AG15: 12
A16: SEI0118 | B16: Arroyo Ramirez Hector Hugo | C16: 15 | D16: 0 | E16: 238.33 | F16: 252.75 | G16: 3574.95 | H16: 0 | I16: 0 | J16: 357.5 | K16: 357.5 | L16: 357.5 | M16: 4647.45 | N16: 160.25 | O16: 0 | P16: 96.03 | Q16: 0 | R16: 1432.4 | S16: 268.35 | T16: 0.02 | U16: 1957.05 | V16: 2690.4 | W16: 70.77 | X16: 127.39 | Y16: 346.55 | Z16: 269.73 | AA16: 92.95 | AB16: 20.22 | AC16: 544.71 | AD16: 202.2 | AE16: 229.29 | AF16: 254.48664 | AG16: 12
A17: SEI0127 | B17: Hernandez Ochoa Eduardo | C17: 15 | D17: 0 | E17: 273.33 | F17: 289.87 | G17: 4099.95 | H17: 0 | I17: 0 | J17: 410 | K17: 410 | L17: 410 | M17: 5329.95 | N17: 324.74 | O17: 0 | P17: 112.48 | Q17: 0 | R17: 0 | S17: 0 | T17: 0.13 | U17: 437.35 | V17: 4892.6 | W17: 81.16 | X17: 146.09 | Y17: 363.36 | Z17: 281.61 | AA17: 106.6 | AB17: 23.19 | AC17: 590.61 | AD17: 231.89 | AE17: 235.23 | AF17: 291.85933 | AG17: 12
... A24: SEI0445 | B24: Muñoz Melgoza Gabriel | C24: 14 | D24: 0 | E24: 256.67 | F24: 272.21 | G24: 3593.38 | H24: 0 | I24: 0 | J24: 359.34 | K24: 359.34 | L24: 359.34 | M24: 4671.4 | N24: 162.25 | O24: 0 | P24: 99.88 | Q24: 0 | R24: 0 | S24: 0 | T24: 0.07 | U24: 262.2 | V24: 4409.2 | W24: 76.22 | X24: 137.19 | Y24: 355.3 | Z24: 275.96 | AA24: 93.43 | AB24: 21.78 | AC24: 568.71 | AD24: 217.77 | AE24: 232.4 | AF24: 274.06993 | AG24: 12
A25: Total Depto | C25: ----------------------- | D25: ----------------------- | E25: ----------------------- | F25: ----------------------- | G25: ----------------------- | H25: ----------------------- | I25: ----------------------- | J25: ----------------------- | K25: ----------------------- | L25: ----------------------- | M25: ----------------------- | N25: ----------------------- | O25: ----------------------- | P25: ----------------------- | Q25: ----------------------- | R25: ----------------------- | S25: ----------------------- | T25: ----------------------- | U25: ----------------------- | V25: ----------------------- | W25: ----------------------- | X25: ----------------------- | Y25: ----------------------- | Z25: ----------------------- | AA25: ----------------------- | AB25: ----------------------- | AC25: ----------------------- | AD25: ----------------------- | AF25: ----------------------- | AG25: -----------------------
A26: =SUM(A6:A25) -> 0 | B26: =SUM(B6:B25) -> 0 | C26: =SUM(C6:C25) -> 282 | D26: =SUM(D6:D25) -> 2 | E26: =SUM(E6:E25) -> 4965.39 | F26: =SUM(F6:F25) -> 5261.86 | G26: =SUM(G6:G25) -> 72977.52 | H26: =SUM(H6:H25) -> 1246.66 | ... AG26: =SUM(AG6:AG25) -> 228
A28: 19 | B28: Nomina | L28: FACTURACON PITS
A29: 0 | B29: Altas | L29: Devengado Salario | M29: =+Y26 -> 6901.43
A30: 0 | B30: Bajas | L30: RETORNOS | M30: =+V26 -> 77416.4
A31: =+A28+A29-A30 -> 19 | B31: Total Nomina | L31: Infonavit | M31: =+S26+R26+Q26+T26 -> 12199.17
L32: Prestamo Prospera | M32: =+U26 -> 19449.28
L33: Subtotal 1 | M33: =SUM(M29:M32) -> 115966.28
L34: Comision | M34: =+M33*2% -> 2319.3256
L35: Subtotal 2 | M35: =+M33+M34 -> 118285.61
L36: Costo Patronal Imss | M36: =+P26+W26+X26+Y26+AB26+Z26+AD26+AE26 -> 27422.3
L37: 2% Sobre Nomina | M37: =+M26*2% -> 1937.3136
L38: Importe de Factura | M38: =+M35+M36+M37 -> 147645.22
L39: IVA | M39: =+M38*16% -> 23623.235
L40: TOTAL | M40: =+M38+M39 -> 171268.45
L42: PROVISION AGUINALDO
L43: FACTURACION PITS
L44: Subtotal 1 | M44: =+AF26 -> 5301.999
L45: Comision | M45: =+M44*2% -> 106.03998
L46: Subtotal 2 | M46: =+M44+M45 -> 5408.0389
L47: 2% Sobre Nomina | M47: =+M44*2% -> 106.03998
L48: Importe de Factura | M48: =+M46+M47 -> 5514.0789
L49: IVA | M49: =+M48*16% -> 882.25263
L50: TOTAL | M50: =+M48+M49 -> 6396.3315

Sheet IP PITS
B1: IP INNOVACION EN PROYECTOS S DE RL DE CV
B2: Lista de Raya (forma tabular)
B3: Reg Pat IMSS: Z2942442109
B4: RFC: IIP -150923-DT7
A5: Código | B5: Empleado | C5: Dias Laborados | D5: Dias Vacaciones | E5: Salario Diario | F5: Salario Diario Integrado | G5: Sueldo | H5: Vacaciones a tiempo | I5: Prima de vacaciones a tiempo | J5: *TOTAL* *PERCEPCIONES* | K5: I.S.R. (sp) | L5: Subsidio al Empleo (sp) | M5: I.M.S.S. | N5: Préstamo Infonavit (vsm) | O5: Préstamo Infonavit (cf) | P5: Seguro de vivienda Infonavit | Q5: Préstamo FONACOT | R5: Deduccion general | S5: Aportación voluntaria Infonavit | T5: Ajuste al neto | U5: *TOTAL* *DEDUCCIONES* | V5: *NETO* | W5: Invalidez y Vida | X5: Cesantia y Vejez | Y5: Enf. y Mat. Patron | Z5: 2% Fondo retiro SAR (8) | AA5: 2% Impuesto estatal | AB5: Riesgo de trabajo (9) | AC5: I.M.S.S. empresa | AD5: Infonavit empresa | AE5: Guarderia I.M.S.S. (7) | AF5: PROVISION DE AGUINALDO | AG5: Banco
A6: SEI0010 | B6: Torres Ricardez Alfredo | C6: 15 | D6: 0 | E6: 266.67 | F6: 278.72 | G6: 4000.05 | H6: 0 | I6: 0 | J6: 4000.05 | K6: 313.87 | L6: 0 | M6: 107.53 | N6: 0 | O6: 0 | P6: 0 | Q6: 0 | R6: 0 | S6: 0 | T6: -0.15 | U6: 421.25 | V6: 3578.8 | W6: 78.04 | X6: 140.48 | Y6: 358.27 | Z6: 275.64 | AA6: 80 | AB6: 35.52 | AC6: 576.79 | AD6: 222.98 | AE6: 231.05 | AF6: 219.0368 | AG6: 12
A7: SEI0014 | B7: Montoya Portillo Carlos Alberto | C7: 15 | D7: 0 | E7: 266.67 | F7: 278.72 | G7: 4000.05 | H7: 0 | I7: 0 | J7: 4000.05 | K7: 313.87 | L7: 0 | M7: 107.53 | N7: 0 | O7: 0 | P7: 0 | Q7: 0 | R7: 0 | S7: 0 | T7: -0.15 | U7: 421.25 | V7: 3578.8 | W7: 78.04 | X7: 140.48 | Y7: 358.27 | Z7: 275.64 | AA7: 80 | AB7: 35.52 | AC7: 576.79 | AD7: 222.98 | AE7: 231.05 | AF7: 219.0368 | AG7: 12
A8: SEI0015 | B8: Cota Jaramillo Miguel Angel | C8: 15 | D8: 0 | E8: 200 | F8: 209.04 | G8: 3000 | H8: 0 | I8: 0 | J8: 3000 | K8: 59.69 | L8: 0 | M8: 79.43 | N8: 0 | O8: 0 | P8: 0 | Q8: 0 | R8: 0 | S8: 0 | T8: -0.12 | U8: 139 | V8: 2861 | W8: 58.53 | X8: 105.36 | Y8: 334.31 | Z8: 253.34 | AA8: 60 | AB8: 26.64 | AC8: 498.2 | AD8: 167.23 | AE8: 219.9 | AF8: 164.27554 | AG8: 12
A9: SEI0017 | B9: Muñoz Reyes Luis Eduardo | C9: 15 | D9: 0 | E9: 266.67 | F9: 278.72 | G9: 4000.05 | H9: 0 | I9: 0 | J9: 4000.05 | K9: 313.87 | L9: 0 | M9: 107.53 | N9: 877.59 | O9: 0 | P9: 0 | Q9: 0 | R9: 0 | S9: 0 | T9: 0.06 | U9: 1299.05 | V9: 2701 | W9: 78.04 | X9: 140.48 | Y9: 358.27 | Z9: 275.64 | AA9: 80 | AB9: 35.52 | AC9: 576.79 | AD9: 222.98 | AE9: 231.05 | AF9: 219.0368 | AG9: 12
A10: SEI0019 | B10: Gonzalez Rasgado Miguel Isaias | C10: 15 | D10: 0 | E10: 400 | F10: 424.2 | G10: 6000 | H10: 0 | I10: 0 | J10: 6000 | K10: 643.38 | L10: 0 | M10: 172.13 | N10: 0 | O10: 0 | P10: 0 | Q10: 0 | R10: 0 | S10: 0 | T10: 0.09 | U10: 815.6 | V10: 5184.4 | W10: 118.78 | X10: 213.8 | Y10: 424.61 | Z10: 322.19 | AA10: 120 | AB10: 54.07 | AC10: 757.19 | AD10: 339.36 | AE10: 254.32 | AF10: 328.55109 | AG10: 12
A11: SEI0020 | B11: Mar Marquez Cesar Eduardo | C11: 15 | D11: 0 | E11: 266.67 | F11: 278.72 | G11: 4000.05 | H11: 0 | I11: 0 | J11: 4000.05 | K11: 313.87 | L11: 0 | M11: 107.53 | N11: 0 | O11: 0 | P11: 0 | Q11: 0 | R11: 0 | S11: 0 | T11: 0.05 | U11: 421.45 | V11: 3578.6 | W11: 78.04 | X11: 140.48 | Y11: 358.27 | Z11: 275.64 | AA11: 80 | AB11: 35.52 | AC11: 576.79 | AD11: 222.98 | AE11: 231.05 | AF11: 219.0368 | AG11: 12
A12: SEI0021 | B12: Velez Rodriguez Jaime | C12: 14 | D12: 1 | E12: 200 | F12: 212.1 | G12: 2800 | H12: 200 | I12: 60 | J12: 3060 | K12: 59.69 | L12: 0 | M12: 80.6 | N12: 1359.23 | O12: 0 | P12: 0 | Q12: 0 | R12: 0 | S12: 0 | T12: 0.08 | U12: 1499.6 | V12: 1560.4 | W12: 59.39 | X12: 106.9 | Y12: 335.17 | Z12: 254.32 | AA12: 61.2 | AB12: 27.03 | AC12: 501.46 | AD12: 169.68 | AE12: 220.39 | AF12: 164.27554 | AG12: 12
A13: SEI0022 | B13: Najera Lopez Raul | C13: 15 | D13: 0 | E13: 333.33 | F13: 353.5 | G13: 4999.95 | H13: 0 | I13: 0 | J13: 4999.95 | K13: 461.63 | L13: 0 | M13: 140.73 | N13: 0 | O13: 0 | P13: 0 | Q13: 0 | R13: 0 | S13: 0 | T13: -0.01 | U13: 602.35 | V13: 4397.6 | W13: 98.98 | X13: 178.16 | Y13: 392.36 | Z13: 299.57 | AA13: 100 | AB13: 45.05 | AC13: 669.5 | AD13: 282.8 | AE13: 243.01 | AF13: 273.78984 | AG13: 12
A14: SEI0023 | B14: Puente Murguia Luis Felipe | C14: 15 | D14: 0 | E14: 233.33 | F14: 247.45 | G14: 3499.95 | H14: 0 | I14: 0 | J14: 3499.95 | K14: 134.36 | L14: 0 | M14: 94.03 | N14: 0 | O14: 0 | P14: 0 | Q14: 0 | R14: 0 | S14: 0 | T14: -0.04 | U14: 228.35 | V14: 3271.6 | W14: 69.28 | X14: 124.71 | Y14: 345.06 | Z14: 265.63 | AA14: 70 | AB14: 31.54 | AC14: 539.05 | AD14: 197.96 | AE14: 226.04 | AF14: 191.65206 | AG14: 12
A15: SEI0028 | B15: Jimenez Alcaraz Elizabeth | C15: 15 | D15: 0 | E15: 200 | F15: 212.11 | G15: 3000 | H15: 0 | I15: 0 | J15: 3000 | K15: 59.69 | L15: 0 | M15: 80.6 | N15: 0 | O15: 0 | P15: 0 | Q15: 0 | R15: 0 | S15: 0 | T15: 0.11 | U15: 140.4 | V15: 2859.6 | W15: 59.39 | X15: 106.9 | Y15: 335.17 | Z15: 254.33 | AA15: 60 | AB15: 27.03 | AC15: 501.46 | AD15: 169.69 | AE15: 220.39 | AF15: 164.27554 | AG15: 12
A16: SEI0029 | B16: Arceo Garcia Manuel Federico | C16: 15 | D16: 0 | E16: 200 | F16: 212.1 | G16: 3000 | H16: 0 | I16: 0 | J16: 3000 | K16: 59.69 | L16: 0 | M16: 80.6 | N16: 0 | O16: 0 | P16: 0 | Q16: 600 | R16: 0 | S16: 0 | T16: -0.09 | U16: 740.2 | V16: 2259.8 | W16: 59.39 | X16: 106.9 | Y16: 335.17 | Z16: 254.32 | AA16: 60 | AB16: 27.03 | AC16: 501.46 | AD16: 169.68 | AE16: 220.39 | AF16: 164.27554 | AG16: 12
A17: SEI0364 | B17: Dominguez Lopez Mayeli Del Pilar | C17: 15 | D17: 0 | E17: 266.67 | F17: 282.81 | G17: 4000.05 | H17: 0 | I17: 0 | J17: 4000.05 | K17: 313.87 | L17: 0 | M17: 109.35 | N17: 0 | O17: 0 | P17: 0 | Q17: 0 | R17: 1666.67 | S17: 0 | T17: 0.16 | U17: 2090.05 | V17: 1910 | W17: 79.19 | X17: 142.54 | Y17: 360.12 | Z17: 276.95 | AA17: 80 | AB17: 36.05 | AC17: 581.85 | AD17: 226.25 | AE17: 231.7 | AF17: 219.0368 | AG17: 12
... A86: SEI479 | B86: Cruz Perez Alejandro Nezahualcoyotl | C86: 15 | D86: 0 | E86: 266.67 | F86: 282.81 | G86: 4000.05 | H86: 0 | I86: 0 | J86: 4000.05 | K86: 313.87 | L86: 0 | M86: 109.35 | N86: 0 | O86: 0 | P86: 0 | Q86: 0 | R86: 0 | S86: 0 | T86: -0.17 | U86: 423.05 | V86: 3577 | W86: 79.19 | X86: 142.54 | Y86: 360.12 | Z86: 276.95 | AA86: 80 | AB86: 36.05 | AC86: 581.85 | AD86: 226.25 | AE86: 231.7 | AF86: 90.25 | AG86: 12
A87: Total Depto | C87: ----------------------- | D87: ----------------------- | E87: ----------------------- | F87: ----------------------- | G87: ----------------------- | H87: ----------------------- | I87: ----------------------- | J87: ----------------------- | K87: ----------------------- | L87: ----------------------- | M87: ----------------------- | N87: ----------------------- | O87: ----------------------- | P87: ----------------------- | Q87: ----------------------- | R87: ----------------------- | S87: ----------------------- | T87: ----------------------- | U87: ----------------------- | V87: ----------------------- | W87: ----------------------- | X87: ----------------------- | Y87: ----------------------- | Z87: ----------------------- | AA87: ----------------------- | AC87: ----------------------- | AD87: ----------------------- | AE87: ----------------------- | AF87: ----------------------- | AG87: -----------------------
A88: =SUM(A6:A87) -> 0 | B88: =SUM(B6:B87) -> 0 | C88: =SUM(C6:C87) -> 1205 | D88: =SUM(D6:D87) -> 3 | E88: =SUM(E6:E87) -> 19423.26 | F88: =SUM(F6:F87) -> 20494.83 | G88: =SUM(G6:G87) -> 289128.99 | H88: =SUM(H6:H87) -> 666.67 | ... AG88: =SUM(AG6:AG87) -> 972
A89: 82 | B89: Nomina | I89: FACTURACION PITS
A90: 2 | B90: Altas | I90: Devengado Salario | J90: =+V88 -> 226037
A91: 3 | B91: Bajas | I91: Retornos | J91: =+R88 -> 8698.25
A92: =+A89+A90-A91 -> 81 | B92: Total Nomina | I92: Infonavit | J92: =+N88+O88+P88 -> 29037.79
I93: Prestamo Prospera | J93: =+Q88 -> 2418.33
I94: aportacion voluntaria | J94: =+S88 -> 0
I95: Subtotal 1 | J95: =SUM(J90:J94) -> 266191.37
I96: Comision | J96: =+J95*2% -> 5323.8274
I97: Subtotal 2 | J97: =+J95+J96 -> 271515.2
I98: Costo Patronal Imss | J98: =+M88+W88+X88+Y88+AD88+AE88+AB88+Z88 -> 111282.82
I99: 2% Sobre Nomina | J99: =+J88*2% -> 5799.9132
I100: Importe de Factura | J100: =+J97+J98+J99 -> 388597.93
I101: certificacion de cheque | J101: 0
I102: IVA | J102: =(+J100+J101)*0.16 -> 62175.669
I103: TOTAL | J103: =+J100+J101+J102 -> 450773.6
I105: PROVISION AGUINALDO
I106: FACTURACION PITS
I107: Subtotal 1 | J107: =+AF88 -> 15836.012
I108: Comision | J108: =+J107*2% -> 316.72024
I109: Subtotal 2 | J109: =+J107+J108 -> 16152.732
I110: 2% Sobre Nomina | J110: =+J107*2% -> 316.72024
I111: Importe de Factura | J111: =+J109+J110 -> 16469.452
I112: IVA | J112: =+J111*16% -> 2635.1124
I113: TOTAL | J113: =+J111+J112 -> 19104.565

Sheet SIND PITS
D1: SINDICATO | J1: PRIMA VACACIONAL
A2: CLAVE | B2: EMPRESA | C2: NOMBRE | D2: SUELDO SINDICATO | E2: BONO | F2: COMISION | G2: prima vacaciones | H2: TOTAL | J2: DIAS DE VACACIONES | K2: SUELDO NETO MENSUAL | L2: MONTO PRIMA TOTAL | M2: MENOS PRIMA IMSS | N2: PRIMA A PAGAR SINDICATO
A3: SEI0544 | B3: IP INNOVACION | C3: Aguilar Aguirre Alfonso | D3: =290.2+630 -> 920.2 | H3: =SUM(D3:G3) -> 920.2 | J3: =VLOOKUP(C3,'IP PITS'!$B$6:$D$86,3,0) -> 0 | K3: 6000 | L3: =(((+K3/30)*J3)*30%) -> 0 | M3: =VLOOKUP(C3,'IP PITS'!$B$6:$I$86,8,0) -> 0 | N3: =+L3-M3 -> 0
A4: SEI0431 | B4: IP INNOVACION | C4: Alcaraz Conde Zabdi Guadalupe | D4: 1260.6 | E4: 292.5 | G4: =+N4 -> 0 | H4: =SUM(D4:G4) -> 1553.1 | J4: =VLOOKUP(C4,'IP PITS'!$B$6:$D$86,3,0) -> 0 | K4: 6000 | L4: =(((+K4/30)*J4)*30%) -> 0 | M4: =VLOOKUP(C4,'IP PITS'!$B$6:$I$86,8,0) -> 0 | N4: =+L4-M4 -> 0
A5: SEI0527 | B5: IP INNOVACION | C5: Alejandro Peña Deivi | D5: 180.8 | E5: 618.75 | G5: =+N5 -> 0 | H5: =SUM(D5:G5) -> 799.55 | J5: =VLOOKUP(C5,'IP PITS'!$B$6:$D$86,3,0) -> 0 | K5: 6300 | L5: =(((+K5/30)*J5)*30%) -> 0 | M5: =VLOOKUP(C5,'IP PITS'!$B$6:$I$86,8,0) -> 0 | N5: =+L5-M5 -> 0
A6: SEI0535 | B6: IP INNOVACION | C6: Alejandro Vazquez Erasmo Miguel | D6: 3618.2 | E6: 1750 | G6: =+N6 -> 0 | H6: =SUM(D6:G6) -> 5368.2 | J6: =VLOOKUP(C6,'IP PITS'!$B$6:$D$86,3,0) -> 0 | K6: 12000 | L6: =(((+K6/30)*J6)*30%) -> 0 | M6: =VLOOKUP(C6,'IP PITS'!$B$6:$I$86,8,0) -> 0 | N6: =+L6-M6 -> 0
A7: SEI0029 | B7: IP INNOVACION | C7: Arceo Garcia Manuel Federico | D7: 140.2 | E7: 487.5 | G7: =+N7 -> 0 | H7: =SUM(D7:G7) -> 627.7 | J7: =VLOOKUP(C7,'IP PITS'!$B$6:$D$86,3,0) -> 0 | K7: 6000 | L7: =(((+K7/30)*J7)*30%) -> 0 | M7: =VLOOKUP(C7,'IP PITS'!$B$6:$I$86,8,0) -> 0 | N7: =+L7-M7 -> 0
A8: SEI0097 | B8: CONSULTORIA | C8: Arreola Jimenez Jose Nieves | D8: 1562.71 | E8: 501 | G8: =+N8 -> 0 | H8: =SUM(D8:G8) -> 2063.71 | J8: =VLOOKUP(C8,'CPD PITS'!$B$6:$D$24,3,0) -> 0 | K8: 10150 | L8: =(((+K8/30)*J8)*30%) -> 0 | M8: =VLOOKUP(C8,'CPD PITS'!$B$6:$I$24,8,0) -> 0 | N8: =+L8-M8 -> 0
A9: SEI0118 | B9: CONSULTORIA | C9: Arroyo Ramirez Hector Hugo | D9: 2108.85 | G9: =+N9 -> 0 | H9: =SUM(D9:G9) -> 2108.85 | J9: =VLOOKUP(C9,'CPD PITS'!$B$6:$D$24,3,0) -> 0 | K9: 13000 | L9: =(((+K9/30)*J9)*30%) -> 0 | M9: =VLOOKUP(C9,'CPD PITS'!$B$6:$I$24,8,0) -> 0 | N9: =+L9-M9 -> 0
A10: SEI0472 | B10: IP INNOVACION | C10: Arzate Gil Juan Sebastian | D10: 423.3 | E10: 463 | G10: =+N10 -> 0 | H10: =SUM(D10:G10) -> 886.3 | J10: =VLOOKUP(C10,'IP PITS'!$B$6:$D$86,3,0) -> 0 | K10: 8000 | L10: =(((+K10/30)*J10)*30%) -> 0 | M10: =VLOOKUP(C10,'IP PITS'!$B$6:$I$86,8,0) -> 0 | N10: =+L10-M10 -> 0
A11: SEI0377 | B11: CONSULTORIA | C11: Benavides Herrera Alejandra | D11: 16807.6 | G11: =+N11 -> 0 | H11: =SUM(D11:G11) -> 16807.6 | J11: =VLOOKUP(C11,'CPD PITS'!$B$6:$D$24,3,0) -> 0 | K11: 40000 | L11: =(((+K11/30)*J11)*30%) -> 0 | M11: =VLOOKUP(C11,'CPD PITS'!$B$6:$I$24,8,0) -> 0 | N11: =+L11-M11 -> 0
A12: SEI0108 | B12: CONSULTORIA | C12: Caballero Diaz Francisco Javier | D12: 1562.69 | E12: 346 | G12: =+N12 -> 0 | H12: =SUM(D12:G12) -> 1908.69 | J12: =VLOOKUP(C12,'CPD PITS'!$B$6:$D$24,3,0) -> 0 | K12: 10150 | L12: =(((+K12/30)*J12)*30%) -> 0 | M12: =VLOOKUP(C12,'CPD PITS'!$B$6:$I$24,8,0) -> 0 | N12: =+L12-M12 -> 0
A13: SEI0425 | B13: CONSULTORIA | C13: Carbajal Cabuto Jose Luis | D13: 1612.9 | E13: 357 | G13: =+N13 -> 0 | H13: =SUM(D13:G13) -> 1969.9 | J13: =VLOOKUP(C13,'CPD PITS'!$B$6:$D$24,3,0) -> 0 | K13: 10250 | L13: =(((+K13/30)*J13)*30%) -> 0 | M13: =VLOOKUP(C13,'CPD PITS'!$B$6:$I$24,8,0) -> 0 | N13: =+L13-M13 -> 0
A14: SEI0528 | B14: IP INNOVACION | C14: Casas Chavarria Rafael | D14: 1142.8 | E14: 480 | G14: =+N14 -> 0 | H14: =SUM(D14:G14) -> 1622.8 | J14: =VLOOKUP(C14,'IP PITS'!$B$6:$D$86,3,0) -> 0 | K14: 6300 | L14: =(((+K14/30)*J14)*30%) -> 0 | M14: =VLOOKUP(C14,'IP PITS'!$B$6:$I$86,8,0) -> 0 | N14: =+L14-M14 -> 0
A15: SEI0116 | B15: CONSULTORIA | C15: Casillas Cardona Cesar Alejandro | D15: 1896.8 | G15: =+N15 -> 0 | H15: =SUM(D15:G15) -> 1896.8 | J15: =VLOOKUP(C15,'CPD PITS'!$B$6:$D$24,3,0) -> 0 | K15: 12000 | L15: =(((+K15/30)*J15)*30%) -> 0 | M15: =VLOOKUP(C15,'CPD PITS'!$B$6:$I$24,8,0) -> 0 | N15: =+L15-M15 -> 0
A16: SEI0460 | B16: IP INNOVACION | C16: Castellon Ramos Rene | D16: 1827.515 | E16: 150 | G16: =+N16 -> 0 | H16: =SUM(D16:G16) -> 1977.515 | J16: =VLOOKUP(C16,'IP PITS'!$B$6:$D$86,3,0) -> 0 | K16: 7505.99 | L16: =(((+K16/30)*J16)*30%) -> 0 | M16: =VLOOKUP(C16,'IP PITS'!$B$6:$I$86,8,0) -> 0 | N16: =+L16-M16 -> 0
A17: SEI0443 | B17: IP INNOVACION | C17: Castillo Nungaray Nestor Roman | D17: 140.4 | E17: 1500 | G17: =+N17 -> 0 | H17: =SUM(D17:G17) -> 1640.4 | J17: =VLOOKUP(C17,'IP PITS'!$B$6:$D$86,3,0) -> 1 | K17: 6000 | L17: =(((+K17/30)*J17)*30%) -> 60 | M17: =VLOOKUP(C17,'IP PITS'!$B$6:$I$86,8,0) -> 60 | N17: =+L17-M17 -> 0
A18: SEI0490 | B18: IP INNOVACION | C18: Castillo Ramirez Hector Ivan | D18: 3727.1 | E18: 208.5 | G18: =+N18 -> 0 | H18: =SUM(D18:G18) -> 3935.6 | J18: =VLOOKUP(C18,'IP PITS'!$B$6:$D$86,3,0) -> 0 | K18: 14000 | L18: =(((+K18/30)*J18)*30%) -> 0 | M18: =VLOOKUP(C18,'IP PITS'!$B$6:$I$86,8,0) -> 0 | N18: =+L18-M18 -> 0
A19: SEI0508 | B19: IP INNOVACION | C19: Cerro Garcia Elvis | D19: 2557.6 | E19: 200 | G19: =+N19 -> 0 | H19: =SUM(D19:G19) -> 2757.6 | J19: =VLOOKUP(C19,'IP PITS'!$B$6:$D$86,3,0) -> 0 | K19: 10000 | L19: =(((+K19/30)*J19)*30%) -> 0 | M19: =VLOOKUP(C19,'IP PITS'!$B$6:$I$86,8,0) -> 0 | N19: =+L19-M19 -> 0
A20: SEI0499 | B20: IP INNOVACION | C20: Chavez Dominguez Salvador | D20: 2673.4 | E20: 1054.5 | G20: =+N20 -> 0 | H20: =SUM(D20:G20) -> 3727.9 | J20: =VLOOKUP(C20,'IP PITS'!$B$6:$D$86,3,0) -> 0 | K20: 12000 | L20: =(((+K20/30)*J20)*30%) -> 0 | M20: =VLOOKUP(C20,'IP PITS'!$B$6:$I$86,8,0) -> 0 | N20: =+L20-M20 -> 0
A21: SEI0541 | B21: IP INNOVACION | C21: Chavez Govea Edgar Aram | D21: 228.6 | G21: =+N21 -> 0 | H21: =SUM(D21:G21) -> 228.6 | J21: =VLOOKUP(C21,'IP PITS'!$B$6:$D$86,3,0) -> 0 | K21: 7000 | L21: =(((+K21/30)*J21)*30%) -> 0 | M21: =VLOOKUP(C21,'IP PITS'!$B$6:$I$86,8,0) -> 0 | N21: =+L21-M21 -> 0
A22: SEI0442 | B22: IP INNOVACION | C22: Chavez Pedraza Samuel | D22: 1060.4 | E22: 675 | G22: =+N22 -> 0 | H22: =SUM(D22:G22) -> 1735.4 | J22: =VLOOKUP(C22,'IP PITS'!$B$6:$D$86,3,0) -> 0 | K22: 14000 | L22: =(((+K22/30)*J22)*30%) -> 0 | M22: =VLOOKUP(C22,'IP PITS'!$B$6:$I$86,8,0) -> 0 | N22: =+L22-M22 -> 0
A23: SEI0462 | B23: IP INNOVACION | C23: Chavez Saucedo Jorge Arturo | D23: 387.54 | E23: 224.25 | G23: =+N23 -> 0 | H23: =SUM(D23:G23) -> 611.79 | J23: =VLOOKUP(C23,'IP PITS'!$B$6:$D$86,3,0) -> 1 | K23: 8000 | L23: =(((+K23/30)*J23)*30%) -> 80 | M23: =VLOOKUP(C23,'IP PITS'!$B$6:$I$86,8,0) -> 80 | N23: =+L23-M23 -> 0
A24: SEI0456 | B24: IP INNOVACION | C24: Chavira Garcia David Fernando | D24: 602.4 | E24: 121.5 | G24: =+N24 -> 0 | H24: =SUM(D24:G24) -> 723.9 | J24: =VLOOKUP(C24,'IP PITS'!$B$6:$D$86,3,0) -> 0 | K24: 10000 | L24: =(((+K24/30)*J24)*30%) -> 0 | M24: =VLOOKUP(C24,'IP PITS'!$B$6:$I$86,8,0) -> 0 | N24: =+L24-M24 -> 0
A25: SEI0538 | B25: IP INNOVACION | C25: Coronado Vega Carlos Eduardo | D25: 107.2 | G25: =+N25 -> 0 | H25: =SUM(D25:G25) -> 107.2 | J25: =VLOOKUP(C25,'IP PITS'!$B$6:$D$86,3,0) -> 0 | K25: 6300 | L25: =(((+K25/30)*J25)*30%) -> 0 | M25: =VLOOKUP(C25,'IP PITS'!$B$6:$I$86,8,0) -> 0 | N25: =+L25-M25 -> 0
A26: SEI0015 | B26: IP INNOVACION | C26: Cota Jaramillo Miguel Angel | D26: 139 | E26: 378 | G26: =+N26 -> 0 | H26: =SUM(D26:G26) -> 517 | J26: =VLOOKUP(C26,'IP PITS'!$B$6:$D$86,3,0) -> 0 | K26: 6000 | L26: =(((+K26/30)*J26)*30%) -> 0 | M26: =VLOOKUP(C26,'IP PITS'!$B$6:$I$86,8,0) -> 0 | N26: =+L26-M26 -> 0
A27: SEI0413 | B27: IP INNOVACION | C27: Courtenay Gutierrez Barry Vladimir | D27: 56.6 | E27: 395.5 | G27: =+N27 -> 0 | H27: =SUM(D27:G27) -> 452.1 | J27: =VLOOKUP(C27,'IP PITS'!$B$6:$D$86,3,0) -> 0 | K27: 5000 | L27: =(((+K27/30)*J27)*30%) -> 0 | M27: =VLOOKUP(C27,'IP PITS'!$B$6:$I$86,8,0) -> 0 | N27: =+L27-M27 -> 0
A28: SEI0501 | B28: IP INNOVACION | C28: Cruz Herrera Roberto | D28: 1673.44 | E28: 226.5 | G28: =+N28 -> 0 | H28: =SUM(D28:G28) -> 1899.94 | J28: =VLOOKUP(C28,'IP PITS'!$B$6:$D$86,3,0) -> 0 | K28: 10000 | L28: =(((+K28/30)*J28)*30%) -> 0 | M28: =VLOOKUP(C28,'IP PITS'!$B$6:$I$86,8,0) -> 0 | N28: =+L28-M28 -> 0
A29: SEI479 | B29: IP INNOVACION | C29: Cruz Perez Alejandro Nezahualcoyotl | D29: 423 | E29: 474 | G29: =+N29 -> 0 | H29: =SUM(D29:G29) -> 897 | J29: =VLOOKUP(C29,'IP PITS'!$B$6:$D$86,3,0) -> 0 | K29: 8000 | L29: =(((+K29/30)*J29)*30%) -> 0 | M29: =VLOOKUP(C29,'IP PITS'!$B$6:$I$86,8,0) -> 0 | N29: =+L29-M29 -> 0
A30: SEI0401 | B30: CONSULTORIA | C30: De La Torre Zambara Francisco Ernesto | D30: 1562.75 | E30: 243.5 | G30: =+N30 -> 45.75 | H30: =SUM(D30:G30) -> 1852 | J30: =VLOOKUP(C30,'CPD PITS'!$B$6:$D$24,3,0) -> 1 | K30: 10150 | L30: =(((+K30/30)*J30)*30%) -> 101.5 | M30: =VLOOKUP(C30,'CPD PITS'!$B$6:$I$24,8,0) -> 55.75 | N30: =+L30-M30 -> 45.75
A31: SEI0530 | B31: IP INNOVACION | C31: Del Pilar Mendez Lucio | D31: 1744.6 | E31: 400 | G31: =+N31 -> 0 | H31: =SUM(D31:G31) -> 2144.6 | J31: =VLOOKUP(C31,'IP PITS'!$B$6:$D$86,3,0) -> 0 | K31: 6000 | L31: =(((+K31/30)*J31)*30%) -> 0 | M31: =VLOOKUP(C31,'IP PITS'!$B$6:$I$86,8,0) -> 0 | N31: =+L31-M31 -> 0
A32: SEI0543 | B32: IP INNOVACION | C32: Diaz Ortiz Hiram Guillermo | D32: 194.52 | G32: =+N32 -> 0 | H32: =SUM(D32:G32) -> 194.52 | J32: =VLOOKUP(C32,'IP PITS'!$B$6:$D$86,3,0) -> 0 | K32: 6300 | L32: =(((+K32/30)*J32)*30%) -> 0 | M32: =VLOOKUP(C32,'IP PITS'!$B$6:$I$86,8,0) -> 0 | N32: =+L32-M32 -> 0
A33: SEI0364 | B33: IP INNOVACION | C33: Dominguez Lopez Mayeli Del Pilar | D33: 1423.33 | E33: 1250 | G33: =+N33 -> 0 | H33: =SUM(D33:G33) -> 2673.33 | J33: =VLOOKUP(C33,'IP PITS'!$B$6:$D$86,3,0) -> 0 | K33: 10000 | L33: =(((+K33/30)*J33)*30%) -> 0 | M33: =VLOOKUP(C33,'IP PITS'!$B$6:$I$86,8,0) -> 0 | N33: =+L33-M33 -> 0
A34: SEI0474 | B34: IP INNOVACION | C34: Enriquez Zamora Jessica Del Rocio | D34: 140.4 | E34: 292.5 | G34: =+N34 -> 0 | H34: =SUM(D34:G34) -> 432.9 | J34: =VLOOKUP(C34,'IP PITS'!$B$6:$D$86,3,0) -> 0 | K34: 6000 | L34: =(((+K34/30)*J34)*30%) -> 0 | M34: =VLOOKUP(C34,'IP PITS'!$B$6:$I$86,8,0) -> 0 | N34: =+L34-M34 -> 0
A35: SEI0489 | B35: IP INNOVACION | C35: Escobedo Olivares Juan Guadalupe | D35: 3727 | E35: 166.67 | G35: =+N35 -> 0 | H35: =SUM(D35:G35) -> 3893.67 | J35: =VLOOKUP(C35,'IP PITS'!$B$6:$D$86,3,0) -> 0 | K35: 14000 | L35: =(((+K35/30)*J35)*30%) -> 0 | M35: =VLOOKUP(C35,'IP PITS'!$B$6:$I$86,8,0) -> 0 | N35: =+L35-M35 -> 0
A36: SEI0449 | B36: IP INNOVACION | C36: Flores Cerrillos Jorge Humberto | D36: 423 | E36: 287 | G36: =+N36 -> 0 | H36: =SUM(D36:G36) -> 710 | J36: =VLOOKUP(C36,'IP PITS'!$B$6:$D$86,3,0) -> 0 | K36: 8000 | L36: =(((+K36/30)*J36)*30%) -> 0 | M36: =VLOOKUP(C36,'IP PITS'!$B$6:$I$86,8,0) -> 0 | N36: =+L36-M36 -> 0
A37: SEI0461 | B37: IP INNOVACION | C37: Flores Franco Marco | D37: 458.205 | E37: 1200 | G37: =+N37 -> 0 | H37: =SUM(D37:G37) -> 1658.205 | J37: =VLOOKUP(C37,'IP PITS'!$B$6:$D$86,3,0) -> 0 | K37: 8500.01 | L37: =(((+K37/30)*J37)*30%) -> 0 | M37: =VLOOKUP(C37,'IP PITS'!$B$6:$I$86,8,0) -> 0 | N37: =+L37-M37 -> 0
A38: SEI0500 | B38: IP INNOVACION | C38: Garcia Gutierrez Jose Juan | D38: 3140.2 | E38: 399.5 | G38: =+N38 -> 0 | H38: =SUM(D38:G38) -> 3539.7 | J38: =VLOOKUP(C38,'IP PITS'!$B$6:$D$86,3,0) -> 0 | K38: 12000 | L38: =(((+K38/30)*J38)*30%) -> 0 | M38: =VLOOKUP(C38,'IP PITS'!$B$6:$I$86,8,0) -> 0 | N38: =+L38-M38 -> 0
A39: SEI0099 | B39: CONSULTORIA | C39: Garcia Villicaña Ricardo Pascual | D39: 2607.2 | E39: 216.5 | G39: =+N39 -> 0 | H39: =SUM(D39:G39) -> 2823.7 | J39: =VLOOKUP(C39,'CPD PITS'!$B$6:$D$24,3,0) -> 0 | K39: 15000 | L39: =(((+K39/30)*J39)*30%) -> 0 | M39: =VLOOKUP(C39,'CPD PITS'!$B$6:$I$24,8,0) -> 0 | N39: =+L39-M39 -> 0
A40: SEI0534 | B40: IP INNOVACION | C40: Gonzalez Ramirez Paul | D40: 139.2 | E40: 292.5 | G40: =+N40 -> 0 | H40: =SUM(D40:G40) -> 431.7 | J40: =VLOOKUP(C40,'IP PITS'!$B$6:$D$86,3,0) -> 0 | K40: 6000 | L40: =(((+K40/30)*J40)*30%) -> 0 | M40: =VLOOKUP(C40,'IP PITS'!$B$6:$I$86,8,0) -> 0 | N40: =+L40-M40 -> 0
A41: SEI0019 | B41: IP INNOVACION | C41: Gonzalez Rasgado Miguel Isaias | D41: 815.6 | E41: 937.5 | G41: =+N41 -> 0 | H41: =SUM(D41:G41) -> 1753.1 | J41: =VLOOKUP(C41,'IP PITS'!$B$6:$D$86,3,0) -> 0 | K41: 12000 | L41: =(((+K41/30)*J41)*30%) -> 0 | M41: =VLOOKUP(C41,'IP PITS'!$B$6:$I$86,8,0) -> 0 | N41: =+L41-M41 -> 0
A42: SEI0457 | B42: IP INNOVACION | C42: Guerrero Lara Cesar Adrian | D42: 423.15 | E42: 183.5 | G42: =+N42 -> 0 | H42: =SUM(D42:G42) -> 606.65 | J42: =VLOOKUP(C42,'IP PITS'!$B$6:$D$86,3,0) -> 0 | K42: 8000 | L42: =(((+K42/30)*J42)*30%) -> 0 | M42: =VLOOKUP(C42,'IP PITS'!$B$6:$I$86,8,0) -> 0 | N42: =+L42-M42 -> 0
A43: SEI0509 | B43: IP INNOVACION | C43: Gutierrez Castillo Jose De Jesus | D43: 289.2 | E43: 811 | G43: =+N43 -> 0 | H43: =SUM(D43:G43) -> 1100.2 | J43: =VLOOKUP(C43,'IP PITS'!$B$6:$D$86,3,0) -> 0 | K43: 6300 | L43: =(((+K43/30)*J43)*30%) -> 0 | M43: =VLOOKUP(C43,'IP PITS'!$B$6:$I$86,8,0) -> 0 | N43: =+L43-M43 -> 0
A44: SEI0009 | B44: CONSULTORIA | C44: Gutierrez Gutierrez Luis Arturo | D44: 1479 | E44: 288.5 | G44: =+N44 -> 0 | H44: =SUM(D44:G44) -> 1767.5 | J44: =VLOOKUP(C44,'CPD PITS'!$B$6:$D$24,3,0) -> 0 | K44: 8500 | L44: =(((+K44/30)*J44)*30%) -> 0 | M44: =VLOOKUP(C44,'CPD PITS'!$B$6:$I$24,8,0) -> 0 | N44: =+L44-M44 -> 0
A45: SEI0483 | B45: IP INNOVACION | C45: Gutierrez Muñoz Carlos Alejandro | D45: 2890.54 | G45: =+N45 -> 0 | H45: =SUM(D45:G45) -> 2890.54 | J45: =VLOOKUP(C45,'IP PITS'!$B$6:$D$86,3,0) -> 0 | K45: 12000 | L45: =(((+K45/30)*J45)*30%) -> 0 | M45: =VLOOKUP(C45,'IP PITS'!$B$6:$I$86,8,0) -> 0 | N45: =+L45-M45 -> 0
A46: SEI0476 | B46: IP INNOVACION | C46: Hernandez Garcia Manuel Alejandro | D46: 421.4 | E46: 359 | G46: =+N46 -> 0 | H46: =SUM(D46:G46) -> 780.4 | J46: =VLOOKUP(C46,'IP PITS'!$B$6:$D$86,3,0) -> 0 | K46: 8000 | L46: =(((+K46/30)*J46)*30%) -> 0 | M46: =VLOOKUP(C46,'IP PITS'!$B$6:$I$86,8,0) -> 0 | N46: =+L46-M46 -> 0
A47: SEI0127 | B47: CONSULTORIA | C47: Hernandez Ochoa Eduardo | D47: 2607.4 | E47: 468 | G47: =+N47 -> 0 | H47: =SUM(D47:G47) -> 3075.4 | J47: =VLOOKUP(C47,'CPD PITS'!$B$6:$D$24,3,0) -> 0 | K47: 15000 | L47: =(((+K47/30)*J47)*30%) -> 0 | M47: =VLOOKUP(C47,'CPD PITS'!$B$6:$I$24,8,0) -> 0 | N47: =+L47-M47 -> 0
A48: SEI0536 | B48: IP INNOVACION | C48: Hernandez Ojeda Julio Cesar | D48: 2562.2 | G48: =+N48 -> 0 | H48: =SUM(D48:G48) -> 2562.2 | J48: =VLOOKUP(C48,'IP PITS'!$B$6:$D$86,3,0) -> 0 | K48: 7000 | L48: =(((+K48/30)*J48)*30%) -> 0 | M48: =VLOOKUP(C48,'IP PITS'!$B$6:$I$86,8,0) -> 0 | N48: =+L48-M48 -> 0
A49: SEI0523 | B49: IP INNOVACION | C49: Hernandez Rodriguez Jorge | D49: 228.47 | E49: 300 | G49: =+N49 -> 0 | H49: =SUM(D49:G49) -> 528.47 | J49: =VLOOKUP(C49,'IP PITS'!$B$6:$D$86,3,0) -> 0 | K49: 7000 | L49: =(((+K49/30)*J49)*30%) -> 0 | M49: =VLOOKUP(C49,'IP PITS'!$B$6:$I$86,8,0) -> 0 | N49: =+L49-M49 -> 0
A50: SEI0464 | B50: IP INNOVACION | C50: Hueramo Hueramo Jesus Daniel | D50: 1050.905 | E50: 306 | G50: =+N50 -> 0 | H50: =SUM(D50:G50) -> 1356.905 | J50: =VLOOKUP(C50,'IP PITS'!$B$6:$D$86,3,0) -> 0 | K50: 8500.01 | L50: =(((+K50/30)*J50)*30%) -> 0 | M50: =VLOOKUP(C50,'IP PITS'!$B$6:$I$86,8,0) -> 0 | N50: =+L50-M50 -> 0
A51: SEI0028 | B51: IP INNOVACION | C51: Jimenez Alcaraz Elizabeth | D51: 590.4 | G51: =+N51 -> 0 | H51: =SUM(D51:G51) -> 590.4 | J51: =VLOOKUP(C51,'IP PITS'!$B$6:$D$86,3,0) -> 0 | K51: 6900 | L51: =(((+K51/30)*J51)*30%) -> 0 | M51: =VLOOKUP(C51,'IP PITS'!$B$6:$I$86,8,0) -> 0 | N51: =+L51-M51 -> 0
A52: SEI0511 | B52: IP INNOVACION | C52: Lizaran Maceda Jose Guadalupe | D52: 57.2 | E52: 305.5 | G52: =+N52 -> 0 | H52: =SUM(D52:G52) -> 362.7 | J52: =VLOOKUP(C52,'IP PITS'!$B$6:$D$86,3,0) -> 0 | K52: 5000 | L52: =(((+K52/30)*J52)*30%) -> 0 | M52: =VLOOKUP(C52,'IP PITS'!$B$6:$I$86,8,0) -> 0 | N52: =+L52-M52 -> 0
A53: SEI0525 | B53: IP INNOVACION | C53: Lizaran Maceda Jesus | D53: 493.2 | G53: =+N53 -> 0 | H53: =SUM(D53:G53) -> 493.2 | J53: =VLOOKUP(C53,'IP PITS'!$B$6:$D$86,3,0) -> 0 | K53: 6300 | L53: =(((+K53/30)*J53)*30%) -> 0 | M53: =VLOOKUP(C53,'IP PITS'!$B$6:$I$86,8,0) -> 0 | N53: =+L53-M53 -> 0
A54: SEI0438 | B54: IP INNOVACION | C54: Lopez Terron Roberto Porfirio | D54: 1060.4 | E54: 200 | G54: =+N54 -> 0 | H54: =SUM(D54:G54) -> 1260.4 | J54: =VLOOKUP(C54,'IP PITS'!$B$6:$D$86,3,0) -> 0 | K54: 14000 | L54: =(((+K54/30)*J54)*30%) -> 0 | M54: =VLOOKUP(C54,'IP PITS'!$B$6:$I$86,8,0) -> 0 | N54: =+L54-M54 -> 0
A55: SEI0517 | B55: IP INNOVACION | C55: Macias Torres Enrique | D55: 6527.2 | E55: 2102.5 | G55: =+N55 -> 0 | H55: =SUM(D55:G55) -> 8629.7 | J55: =VLOOKUP(C55,'IP PITS'!$B$6:$D$86,3,0) -> 0 | K55: 19950 | L55: =(((+K55/30)*J55)*30%) -> 0 | M55: =VLOOKUP(C55,'IP PITS'!$B$6:$I$86,8,0) -> 0 | N55: =+L55-M55 -> 0
A56: SEI0020 | B56: IP INNOVACION | C56: Mar Marquez Cesar Eduardo | D56: 421.4 | E56: 168.5 | G56: =+N56 -> 0 | H56: =SUM(D56:G56) -> 589.9 | J56: =VLOOKUP(C56,'IP PITS'!$B$6:$D$86,3,0) -> 0 | K56: 8000 | L56: =(((+K56/30)*J56)*30%) -> 0 | M56: =VLOOKUP(C56,'IP PITS'!$B$6:$I$86,8,0) -> 0 | N56: =+L56-M56 -> 0
A57: SEI0117 | B57: CONSULTORIA | C57: Mariscal Romero Luis Adrian | D57: 2757.8 | E57: 250 | G57: =+N57 -> 0 | H57: =SUM(D57:G57) -> 3007.8 | J57: =VLOOKUP(C57,'CPD PITS'!$B$6:$D$24,3,0) -> 0 | K57: 15000 | L57: =(((+K57/30)*J57)*30%) -> 0 | M57: =VLOOKUP(C57,'CPD PITS'!$B$6:$I$24,8,0) -> 0 | N57: =+L57-M57 -> 0
A58: SEI0444 | B58: IP INNOVACION | C58: Marquez Hernandez Rogelio | D58: 423.2 | E58: 326 | G58: =+N58 -> 0 | H58: =SUM(D58:G58) -> 749.2 | J58: =VLOOKUP(C58,'IP PITS'!$B$6:$D$86,3,0) -> 0 | K58: 8000 | L58: =(((+K58/30)*J58)*30%) -> 0 | M58: =VLOOKUP(C58,'IP PITS'!$B$6:$I$86,8,0) -> 0 | N58: =+L58-M58 -> 0
A59: SEI0428 | B59: IP INNOVACION | C59: Martinez Hernandez J. Antonio | D59: 423.2 | E59: 280 | G59: =+N59 -> 0 | H59: =SUM(D59:G59) -> 703.2 | J59: =VLOOKUP(C59,'IP PITS'!$B$6:$D$86,3,0) -> 0 | K59: 8000 | L59: =(((+K59/30)*J59)*30%) -> 0 | M59: =VLOOKUP(C59,'IP PITS'!$B$6:$I$86,8,0) -> 0 | N59: =+L59-M59 -> 0
A60: SEI0504 | B60: IP INNOVACION | C60: Martinez Malo Cesar | D60: 1699.1 | E60: 382 | G60: =+N60 -> 0 | H60: =SUM(D60:G60) -> 2081.1 | J60: =VLOOKUP(C60,'IP PITS'!$B$6:$D$86,3,0) -> 0 | K60: 9000 | L60: =(((+K60/30)*J60)*30%) -> 0 | M60: =VLOOKUP(C60,'IP PITS'!$B$6:$I$86,8,0) -> 0 | N60: =+L60-M60 -> 0
A61: SEI0469 | B61: IP INNOVACION | C61: Martinez Morales Jose Martin | D61: 1060.4 | E61: 303.5 | G61: =+N61 -> 0 | H61: =SUM(D61:G61) -> 1363.9 | J61: =VLOOKUP(C61,'IP PITS'!$B$6:$D$86,3,0) -> 0 | K61: 14000 | L61: =(((+K61/30)*J61)*30%) -> 0 | M61: =VLOOKUP(C61,'IP PITS'!$B$6:$I$86,8,0) -> 0 | N61: =+L61-M61 -> 0
A62: SEI0493 | B62: IP INNOVACION | C62: Martinez Morales Tomas | D62: 3347.5 | E62: 244 | G62: =+N62 -> 0 | H62: =SUM(D62:G62) -> 3591.5 | J62: =VLOOKUP(C62,'IP PITS'!$B$6:$D$86,3,0) -> 0 | K62: 15000 | L62: =(((+K62/30)*J62)*30%) -> 0 | M62: =VLOOKUP(C62,'IP PITS'!$B$6:$I$86,8,0) -> 0 | N62: =+L62-M62 -> 0
A63: SEI0503 | B63: IP INNOVACION | C63: Martinez Rodriguez Paulo Cesar | D63: 2556.6 | E63: 250 | G63: =+N63 -> 0 | H63: =SUM(D63:G63) -> 2806.6 | J63: =VLOOKUP(C63,'IP PITS'!$B$6:$D$86,3,0) -> 0 | K63: 10000 | L63: =(((+K63/30)*J63)*30%) -> 0 | M63: =VLOOKUP(C63,'IP PITS'!$B$6:$I$86,8,0) -> 0 | N63: =+L63-M63 -> 0
A64: SEI0458 | B64: IP INNOVACION | C64: Martinez Zamora Gerardo Mario | D64: 558.505 | E64: 858.5 | G64: =+N64 -> 0 | H64: =SUM(D64:G64) -> 1417.005 | J64: =VLOOKUP(C64,'IP PITS'!$B$6:$D$86,3,0) -> 0 | K64: 9550.01 | L64: =(((+K64/30)*J64)*30%) -> 0 | M64: =VLOOKUP(C64,'IP PITS'!$B$6:$I$86,8,0) -> 0 | N64: =+L64-M64 -> 0
A65: SEI0494 | B65: IP INNOVACION | C65: Medellin Colunga Ruben Dario | D65: 4347.44 | E65: 484.38 | G65: =+N65 -> 0 | H65: =SUM(D65:G65) -> 4831.82 | J65: =VLOOKUP(C65,'IP PITS'!$B$6:$D$86,3,0) -> 0 | K65: 17000 | L65: =(((+K65/30)*J65)*30%) -> 0 | M65: =VLOOKUP(C65,'IP PITS'!$B$6:$I$86,8,0) -> 0 | N65: =+L65-M65 -> 0
A66: SEI0506 | B66: IP INNOVACION | C66: Mejia Duarte Jose Luis | D66: 3557.4 | E66: 552 | G66: =+N66 -> 0 | H66: =SUM(D66:G66) -> 4109.4 | J66: =VLOOKUP(C66,'IP PITS'!$B$6:$D$86,3,0) -> 0 | K66: 12000 | L66: =(((+K66/30)*J66)*30%) -> 0 | M66: =VLOOKUP(C66,'IP PITS'!$B$6:$I$86,8,0) -> 0 | N66: =+L66-M66 -> 0
A67: SEI0513 | B67: IP INNOVACION | C67: Mendez Rivera Ivan Israel | D67: 56.64 | E67: 338.5 | G67: =+N67 -> 0 | H67: =SUM(D67:G67) -> 395.14 | J67: =VLOOKUP(C67,'IP PITS'!$B$6:$D$86,3,0) -> 0 | K67: 5000 | L67: =(((+K67/30)*J67)*30%) -> 0 | M67: =VLOOKUP(C67,'IP PITS'!$B$6:$I$86,8,0) -> 0 | N67: =+L67-M67 -> 0
A68: SEI0488 | B68: IP INNOVACION | C68: Mireles Casillas Brenda Cristina | D68: 2266 | G68: =+N68 -> 0 | H68: =SUM(D68:G68) -> 2266 | J68: =VLOOKUP(C68,'IP PITS'!$B$6:$D$86,3,0) -> 0 | K68: 9000 | L68: =(((+K68/30)*J68)*30%) -> 0 | M68: =VLOOKUP(C68,'IP PITS'!$B$6:$I$86,8,0) -> 0 | N68: =+L68-M68 -> 0
A69: SEI0485 | B69: IP INNOVACION | C69: Molina Ramirez Gerardo Daniel | D69: 3029 | E69: 450 | G69: =+N69 -> 0 | H69: =SUM(D69:G69) -> 3479 | J69: =VLOOKUP(C69,'IP PITS'!$B$6:$D$86,3,0) -> 0 | K69: 9000 | L69: =(((+K69/30)*J69)*30%) -> 0 | M69: =VLOOKUP(C69,'IP PITS'!$B$6:$I$86,8,0) -> 0 | N69: =+L69-M69 -> 0
A70: SEI0014 | B70: IP INNOVACION | C70: Montoya Portillo Carlos Alberto | D70: 421.2 | E70: 121.5 | G70: 0 | H70: =SUM(D70:G70) -> 542.7 | J70: =VLOOKUP(C70,'IP PITS'!$B$6:$D$86,3,0) -> 0 | K70: 8000 | L70: =(((+K70/30)*J70)*30%) -> 0 | M70: =VLOOKUP(C70,'IP PITS'!$B$6:$I$86,8,0) -> 0 | N70: =+L70-M70 -> 0
A71: SEI0040 | B71: CONSULTORIA | C71: Mora Ramirez Acal Aldo Isidro | D71: 2469.4 | E71: 1000 | G71: =+N71 -> 0 | H71: =SUM(D71:G71) -> 3469.4 | J71: =VLOOKUP(C71,'CPD PITS'!$B$6:$D$24,3,0) -> 0 | K71: 13000 | L71: =(((+K71/30)*J71)*30%) -> 0 | M71: =VLOOKUP(C71,'CPD PITS'!$B$6:$I$24,8,0) -> 0 | N71: =+L71-M71 -> 0
A72: SEI0540 | B72: IP INNOVACION | C72: Morales Martinez Eduardo | D72: 180.8 | G72: =+N72 -> 0 | H72: =SUM(D72:G72) -> 180.8 | J72: =VLOOKUP(C72,'IP PITS'!$B$6:$D$86,3,0) -> 0 | K72: 6300 | L72: =(((+K72/30)*J72)*30%) -> 0 | M72: =VLOOKUP(C72,'IP PITS'!$B$6:$I$86,8,0) -> 0 | N72: =+L72-M72 -> 0
A73: SEI0475 | B73: IP INNOVACION | C73: Moreno Quiroga Ana Sarahi | D73: 423.2 | E73: 1250 | G73: =+N73 -> 0 | H73: =SUM(D73:G73) -> 1673.2 | J73: =VLOOKUP(C73,'IP PITS'!$B$6:$D$86,3,0) -> 0 | K73: 8000 | L73: =(((+K73/30)*J73)*30%) -> 0 | M73: =VLOOKUP(C73,'IP PITS'!$B$6:$I$86,8,0) -> 0 | N73: =+L73-M73 -> 0
A74: SEI0088 | B74: CONSULTORIA | C74: Morgado Fernandez Martin | D74: 2607.2 | E74: 281.5 | G74: =+N74 -> 0 | H74: =SUM(D74:G74) -> 2888.7 | J74: =VLOOKUP(C74,'CPD PITS'!$B$6:$D$24,3,0) -> 0 | K74: 15000 | L74: =(((+K74/30)*J74)*30%) -> 0 | M74: =VLOOKUP(C74,'CPD PITS'!$B$6:$I$24,8,0) -> 0 | N74: =+L74-M74 -> 0
A75: SEI0445 | B75: CONSULTORIA | C75: Muñoz Melgoza Gabriel | D75: 2777.47 | E75: 250 | G75: =+N75 -> 0 | H75: =SUM(D75:G75) -> 3027.47 | J75: =VLOOKUP(C75,'CPD PITS'!$B$6:$D$24,3,0) -> 0 | K75: 15400 | M75: =VLOOKUP(C75,'CPD PITS'!$B$6:$I$24,8,0) -> 0
A76: SEI0017 | B76: IP INNOVACION | C76: Muñoz Reyes Luis Eduardo | D76: 421.41 | E76: 358.5 | G76: =+N76 -> 0 | H76: =SUM(D76:G76) -> 779.91 | J76: =VLOOKUP(C76,'IP PITS'!$B$6:$D$86,3,0) -> 0 | K76: 8000 | L76: =(((+K76/30)*J76)*30%) -> 0 | M76: =VLOOKUP(C76,'IP PITS'!$B$6:$I$86,8,0) -> 0 | N76: =+L76-M76 -> 0
A77: SEI0022 | B77: IP INNOVACION | C77: Najera Lopez Raul | D77: 602.4 | E77: 121.5 | G77: =+N77 -> 0 | H77: =SUM(D77:G77) -> 723.9 | J77: =VLOOKUP(C77,'IP PITS'!$B$6:$D$86,3,0) -> 0 | K77: 10000 | L77: =(((+K77/30)*J77)*30%) -> 0 | M77: =VLOOKUP(C77,'IP PITS'!$B$6:$I$86,8,0) -> 0 | N77: =+L77-M77 -> 0
A78: SEI0173 | B78: CONSULTORIA | C78: Nieto Ortiz Jose Luis | D78: 1487.7 | E78: 83 | G78: =+N78 -> 0 | H78: =SUM(D78:G78) -> 1570.7 | J78: =VLOOKUP(C78,'CPD PITS'!$B$6:$D$24,3,0) -> 0 | K78: 10000 | L78: =(((+K78/30)*J78)*30%) -> 0 | M78: =VLOOKUP(C78,'CPD PITS'!$B$6:$I$24,8,0) -> 0 | N78: =+L78-M78 -> 0
A79: SEI0524 | B79: IP INNOVACION | C79: Orea Gonzalez Concepcion Esteban | D79: 180.8 | E79: 843.75 | G79: =+N79 -> 0 | H79: =SUM(D79:G79) -> 1024.55 | J79: =VLOOKUP(C79,'IP PITS'!$B$6:$D$86,3,0) -> 0 | K79: 6300 | L79: =(((+K79/30)*J79)*30%) -> 0 | M79: =VLOOKUP(C79,'IP PITS'!$B$6:$I$86,8,0) -> 0 | N79: =+L79-M79 -> 0
A80: SEI0424 | B80: IP INNOVACION | C80: Palacios Ramos Jesus | D80: 423.2 | E80: 349 | G80: =+N80 -> 0 | H80: =SUM(D80:G80) -> 772.2 | J80: =VLOOKUP(C80,'IP PITS'!$B$6:$D$86,3,0) -> 0 | K80: 8000 | L80: =(((+K80/30)*J80)*30%) -> 0 | M80: =VLOOKUP(C80,'IP PITS'!$B$6:$I$86,8,0) -> 0 | N80: =+L80-M80 -> 0
A81: SEI0519 | B81: IP INNOVACION | C81: Palacios Vega Luis Rosendo | D81: 56.4 | E81: 186.5 | G81: =+N81 -> 0 | H81: =SUM(D81:G81) -> 242.9 | J81: =VLOOKUP(C81,'IP PITS'!$B$6:$D$86,3,0) -> 0 | K81: 5000 | L81: =(((+K81/30)*J81)*30%) -> 0 | M81: =VLOOKUP(C81,'IP PITS'!$B$6:$I$86,8,0) -> 0 | N81: =+L81-M81 -> 0
A82: SEI0026 | B82: CONSULTORIA | C82: Patricio Aguilar Jhonattan Cristian | D82: 1591.8 | E82: 375 | G82: =+N82 -> 0 | H82: =SUM(D82:G82) -> 1966.8 | J82: =VLOOKUP(C82,'CPD PITS'!$B$6:$D$24,3,0) -> 0 | K82: 9000 | L82: =(((+K82/30)*J82)*30%) -> 0 | M82: =VLOOKUP(C82,'CPD PITS'!$B$6:$I$24,8,0) -> 0 | N82: =+L82-M82 -> 0
A83: SEI0522 | B83: IP INNOVACION | C83: Peña Lopez Abigail | D83: 221.6 | G83: =+N83 -> 0 | H83: =SUM(D83:G83) -> 221.6 | J83: =VLOOKUP(C83,'IP PITS'!$B$6:$D$86,3,0) -> 0 | K83: 6900 | L83: =(((+K83/30)*J83)*30%) -> 0 | M83: =VLOOKUP(C83,'IP PITS'!$B$6:$I$86,8,0) -> 0 | N83: =+L83-M83 -> 0
A84: SEI0505 | B84: IP INNOVACION | C84: Perez Balboa Cesar | D84: 2199.19 | E84: 84 | G84: =+N84 -> 0 | H84: =SUM(D84:G84) -> 2283.19 | J84: =VLOOKUP(C84,'IP PITS'!$B$6:$D$86,3,0) -> 0 | K84: 10000 | L84: =(((+K84/30)*J84)*30%) -> 0 | M84: =VLOOKUP(C84,'IP PITS'!$B$6:$I$86,8,0) -> 0 | N84: =+L84-M84 -> 0
A85: SEI0455 | B85: IP INNOVACION | C85: Perez Garcia Andres Alvaro | D85: 389.14 | E85: 140 | G85: =+N85 -> 0 | H85: =SUM(D85:G85) -> 529.14 | J85: =VLOOKUP(C85,'IP PITS'!$B$6:$D$86,3,0) -> 0 | K85: 8000 | L85: =(((+K85/30)*J85)*30%) -> 0 | M85: =VLOOKUP(C85,'IP PITS'!$B$6:$I$86,8,0) -> 0 | N85: =+L85-M85 -> 0
A86: SEI0023 | B86: IP INNOVACION | C86: Puente Murguia Luis Felipe | D86: 228.4 | E86: 253.25 | G86: =+N86 -> 0 | H86: =SUM(D86:G86) -> 481.65 | J86: =VLOOKUP(C86,'IP PITS'!$B$6:$D$86,3,0) -> 0 | K86: 7000 | L86: =(((+K86/30)*J86)*30%) -> 0 | M86: =VLOOKUP(C86,'IP PITS'!$B$6:$I$86,8,0) -> 0 | N86: =+L86-M86 -> 0
A87: SEI0221 | B87: CONSULTORIA | C87: Rogel Teran Marco Antonio | D87: 12643.25 | G87: =+N87 -> 281.75 | H87: =SUM(D87:G87) -> 12925 | J87: =VLOOKUP(C87,'CPD PITS'!$B$6:$D$24,3,0) -> 1 | K87: 60000 | L87: =(((+K87/30)*J87)*30%) -> 600 | M87: =VLOOKUP(C87,'CPD PITS'!$B$6:$I$24,8,0) -> 318.25 | N87: =+L87-M87 -> 281.75
A88: SEI0521 | B88: IP INNOVACION | C88: Rondero Savin Jacinto | D88: 227.2 | G88: =+N88 -> 0 | H88: =SUM(D88:G88) -> 227.2 | J88: =VLOOKUP(C88,'IP PITS'!$B$6:$D$86,3,0) -> 0 | K88: 7000 | L88: =(((+K88/30)*J88)*30%) -> 0 | M88: =VLOOKUP(C88,'IP PITS'!$B$6:$I$86,8,0) -> 0 | N88: =+L88-M88 -> 0
A89: SEI0515 | B89: IP INNOVACION | C89: Ruiz Flores Aldo Tomas | D89: 140.27 | E89: 337.5 | G89: =+N89 -> 0 | H89: =SUM(D89:G89) -> 477.77 | J89: =VLOOKUP(C89,'IP PITS'!$B$6:$D$86,3,0) -> 0 | K89: 6000 | L89: =(((+K89/30)*J89)*30%) -> 0 | M89: =VLOOKUP(C89,'IP PITS'!$B$6:$I$86,8,0) -> 0 | N89: =+L89-M89 -> 0
A90: SEI0465 | B90: IP INNOVACION | C90: Sandoval Garcia Luis | D90: 423.2 | E90: 262.5 | G90: =+N90 -> 0 | H90: =SUM(D90:G90) -> 685.7 | J90: =VLOOKUP(C90,'IP PITS'!$B$6:$D$86,3,0) -> 0 | K90: 8000 | L90: =(((+K90/30)*J90)*30%) -> 0 | M90: =VLOOKUP(C90,'IP PITS'!$B$6:$I$86,8,0) -> 0 | N90: =+L90-M90 -> 0
A91: SEI0477 | B91: IP INNOVACION | C91: Sandoval Medina Demetrio | D91: 421.2 | E91: 450 | G91: =+N91 -> 0 | H91: =SUM(D91:G91) -> 871.2 | J91: =VLOOKUP(C91,'IP PITS'!$B$6:$D$86,3,0) -> 0 | K91: 8000 | L91: =(((+K91/30)*J91)*30%) -> 0 | M91: =VLOOKUP(C91,'IP PITS'!$B$6:$I$86,8,0) -> 0 | N91: =+L91-M91 -> 0
A92: SEI0537 | B92: IP INNOVACION | C92: Serrano Esquivel Armando | D92: 1707.38 | E92: 675 | G92: =+N92 -> 0 | H92: =SUM(D92:G92) -> 2382.38 | J92: =VLOOKUP(C92,'IP PITS'!$B$6:$D$86,3,0) -> 0 | K92: 7000 | L92: =(((+K92/30)*J92)*30%) -> 0 | M92: =VLOOKUP(C92,'IP PITS'!$B$6:$I$86,8,0) -> 0 | N92: =+L92-M92 -> 0
A93: SEI0442 | B93: CONSULTORIA | C93: Sierra Escamilla Daniela | D93: 2469.4 | E93: 1000 | G93: =+N93 -> 0 | H93: =SUM(D93:G93) -> 3469.4 | J93: =VLOOKUP(C93,'CPD PITS'!$B$6:$D$24,3,0) -> 0 | K93: 13000 | L93: =(((+K93/30)*J93)*30%) -> 0 | M93: =VLOOKUP(C93,'CPD PITS'!$B$6:$I$24,8,0) -> 0 | N93: =+L93-M93 -> 0
A94: SEI0498 | B94: IP INNOVACION | C94: Tenorio Alvarez Alberto Antonio | D94: 2796 | E94: 417 | G94: =+N94 -> 0 | H94: =SUM(D94:G94) -> 3213 | J94: =VLOOKUP(C94,'IP PITS'!$B$6:$D$86,3,0) -> 0 | K94: 10000 | L94: =(((+K94/30)*J94)*30%) -> 0 | M94: =VLOOKUP(C94,'IP PITS'!$B$6:$I$86,8,0) -> 0 | N94: =+L94-M94 -> 0
A95: SEI0495 | B95: IP INNOVACION | C95: Torres Perez Carlos Alberto | D95: 1923.4 | E95: 1421.88 | G95: =+N95 -> 0 | H95: =SUM(D95:G95) -> 3345.28 | J95: =VLOOKUP(C95,'IP PITS'!$B$6:$D$86,3,0) -> 0 | K95: 10500 | L95: =(((+K95/30)*J95)*30%) -> 0 | M95: =VLOOKUP(C95,'IP PITS'!$B$6:$I$86,8,0) -> 0 | N95: =+L95-M95 -> 0
A96: SEI0010 | B96: IP INNOVACION | C96: Torres Ricardez Alfredo | D96: 421.2 | E96: 258.5 | G96: =+N96 -> 0 | H96: =SUM(D96:G96) -> 679.7 | J96: =VLOOKUP(C96,'IP PITS'!$B$6:$D$86,3,0) -> 0 | K96: 8000 | L96: =(((+K96/30)*J96)*30%) -> 0 | M96: =VLOOKUP(C96,'IP PITS'!$B$6:$I$86,8,0) -> 0 | N96: =+L96-M96 -> 0
A97: SEI0473 | B97: IP INNOVACION | C97: Torres Velazquez Juan Antonio | D97: 423 | E97: 546 | G97: =+N97 -> 0 | H97: =SUM(D97:G97) -> 969 | J97: =VLOOKUP(C97,'IP PITS'!$B$6:$D$86,3,0) -> 0 | K97: 8000 | L97: =(((+K97/30)*J97)*30%) -> 0 | M97: =VLOOKUP(C97,'IP PITS'!$B$6:$I$86,8,0) -> 0 | N97: =+L97-M97 -> 0
A98: SEI0497 | B98: IP INNOVACION | C98: Treviño Alvarez Jorge Alberto | D98: 2673.37 | G98: =+N98 -> 0 | H98: =SUM(D98:G98) -> 2673.37 | J98: =VLOOKUP(C98,'IP PITS'!$B$6:$D$86,3,0) -> 0 | K98: 12000 | L98: =(((+K98/30)*J98)*30%) -> 0 | M98: =VLOOKUP(C98,'IP PITS'!$B$6:$I$86,8,0) -> 0 | N98: =+L98-M98 -> 0
A99: SEI0467 | B99: IP INNOVACION | C99: Vaca Valdez Guillermo | D99: 423.25 | E99: 471 | G99: =+N99 -> 0 | H99: =SUM(D99:G99) -> 894.25 | J99: =VLOOKUP(C99,'IP PITS'!$B$6:$D$86,3,0) -> 0 | K99: 8000 | L99: =(((+K99/30)*J99)*30%) -> 0 | M99: =VLOOKUP(C99,'IP PITS'!$B$6:$I$86,8,0) -> 0 | N99: =+L99-M99 -> 0
A100: SEI0545 | B100: IP INNOVACION | C100: Vallarta Fonseca Mayra Karina | D100: 181 | H100: =SUM(D100:G100) -> 181 | J100: =VLOOKUP(C100,'IP PITS'!$B$6:$D$86,3,0) -> 0 | K100: 6000 | L100: =(((+K100/30)*J100)*30%) -> 0 | M100: =VLOOKUP(C100,'IP PITS'!$B$6:$I$86,8,0) -> 0 | N100: =+L100-M100 -> 0
...

Sheet RESUMEN
A2: SUELDOS Y SALARIOS | G2: SINDICATO | K2: NETOS | O2: EXTRAS
A3: CLAVE | B3: EMPRESA | C3: NOMBRE | D3: NETO CPD | E3: NETO IP | F3: A | G3: PAGO SINDICATO | H3: COMISION | I3: PRIMA VACACIONAL SINDICATO | J3: B | K3: NETO A PAGAR | L3: NETO MENSUAL | M3: NETO QUINCENAL SEITON | N3: C | O3: prima vacacional | P3: COMISION Y PRIMA VACACIONAL | Q3: INFONAVIT | R3: INFONAVIT | S3: INFONAVIT | T3: INFONAVIT | U3: PRESTAMO | V3: APORTACION | W3: DESCUENTOS | X3: D | Y3: TOTAL GENERAL | Z3: DIFERENCIAS | AA3: OBSERVACIONES | AB3: CC
A4: SEI0009 | B4: SEITON - (CONSULTORIA II) | C4: Gutierrez Gutierrez Luis Arturo | D4: =VLOOKUP(C4,[1]CPD!$B$9:$Y$35,24,0) -> 2774.6 | G4: =VLOOKUP(C4,#REF!,4,0) -> #REF! | H4: =VLOOKUP(C4,#REF!,5,0) -> #REF! | I4: =VLOOKUP(C4,#REF!,6,0) -> #REF! | K4: =+D4+E4+G4+H4+I4 -> #REF! | L4: =VLOOKUP(C4,[2]ABC!$A$3:$B$88,2,0) -> 8500 | M4: =+L4/2 -> 4250 | O4: =VLOOKUP(C4,[1]CPD!$B$9:$I$35,8,0) -> 0 | P4: =+H4+I4 -> #REF! | Q4: =VLOOKUP(C4,[1]CPD!$B$9:$R$35,17,0) -> 0 | R4: =VLOOKUP(C4,[1]CPD!$B$9:$Q$35,16,0) -> 0 | S4: =VLOOKUP(C4,[2]CPD!$B$9:$S$35,18,0) -> 0 | T4: =VLOOKUP(C4,[1]CPD!$B$9:$T$35,19,0) -> 0 | W4: =VLOOKUP(C4,[1]CPD!$B$9:$V$35,21,0) -> 0 | Y4: =+K4-O4-P4+Q4+R4+S4+T4+U4+V4+W4 -> #REF! | Z4: =+M4-Y4 -> #REF! | AB4: =VLOOKUP(C4,[2]SINDICATO!$C$7:$Q$141,15,0) -> #N/A
A5: SEI0010 | B5: SEITON - (CONSULTORIA II) | C5: Compean Tobias Braulio Gerardo | D5: =VLOOKUP(C5,[1]CPD!$B$9:$Y$35,24,0) -> 4005.2 | G5: =VLOOKUP(C5,#REF!,4,0) -> #REF! | H5: =VLOOKUP(C5,#REF!,5,0) -> #REF! | I5: =VLOOKUP(C5,#REF!,6,0) -> #REF! | K5: =+D5+E5+G5+H5+I5 -> #REF! | L5: =VLOOKUP(C5,[2]ABC!$A$3:$B$88,2,0) -> 18000 | M5: =+L5/2 -> 9000 | O5: =VLOOKUP(C5,[1]CPD!$B$9:$I$35,8,0) -> 0 | P5: =+H5+I5 -> #REF! | Q5: =VLOOKUP(C5,[1]CPD!$B$9:$R$35,17,0) -> 1333.87 | R5: =VLOOKUP(C5,[1]CPD!$B$9:$Q$35,16,0) -> 0 | S5: =VLOOKUP(C5,[2]CPD!$B$9:$S$35,18,0) -> 0 | T5: =VLOOKUP(C5,[1]CPD!$B$9:$T$35,19,0) -> 15 | W5: =VLOOKUP(C5,[1]CPD!$B$9:$V$35,21,0) -> 0 | Y5: =+K5-O5-P5+Q5+R5+S5+T5+U5+V5+W5 -> #REF! | Z5: =+M5-Y5 -> #REF! | AB5: =VLOOKUP(C5,[2]SINDICATO!$C$7:$Q$141,15,0) -> 0
A6: SEI0026 | B6: SEITON - (CONSULTORIA II) | C6: Patricio Aguilar Jhonattan Cristian | D6: =VLOOKUP(C6,[1]CPD!$B$9:$Y$35,24,0) -> 2911.8 | G6: =VLOOKUP(C6,#REF!,4,0) -> #REF! | H6: =VLOOKUP(C6,#REF!,5,0) -> #REF! | I6: =VLOOKUP(C6,#REF!,6,0) -> #REF! | K6: =+D6+E6+G6+H6+I6 -> #REF! | L6: =VLOOKUP(C6,[2]ABC!$A$3:$B$88,2,0) -> 9000 | M6: =+L6/2 -> 4500 | O6: =VLOOKUP(C6,[1]CPD!$B$9:$I$35,8,0) -> 0 | P6: =+H6+I6 -> #REF! | Q6: =VLOOKUP(C6,[1]CPD!$B$9:$R$35,17,0) -> 0 | R6: =VLOOKUP(C6,[1]CPD!$B$9:$Q$35,16,0) -> 0 | S6: =VLOOKUP(C6,[2]CPD!$B$9:$S$35,18,0) -> 0 | T6: =VLOOKUP(C6,[1]CPD!$B$9:$T$35,19,0) -> 0 | W6: =VLOOKUP(C6,[1]CPD!$B$9:$V$35,21,0) -> 0 | Y6: =+K6-O6-P6+Q6+R6+S6+T6+U6+V6+W6 -> #REF! | Z6: =+M6-Y6 -> #REF! | AB6: =VLOOKUP(C6,[2]SINDICATO!$C$7:$Q$141,15,0) -> #N/A
A7: SEI0040 | B7: SEITON - (CONSULTORIA II) | C7: Mora Ramirez Acal Aldo Isidro | D7: =VLOOKUP(C7,[1]CPD!$B$9:$Y$35,24,0) -> 4036 | G7: =VLOOKUP(C7,#REF!,4,0) -> #REF! | H7: =VLOOKUP(C7,#REF!,5,0) -> #REF! | I7: =VLOOKUP(C7,#REF!,6,0) -> #REF! | K7: =+D7+E7+G7+H7+I7 -> #REF! | L7: 13000 | M7: =+L7/2 -> 6500 | O7: =VLOOKUP(C7,[1]CPD!$B$9:$I$35,8,0) -> 0 | P7: =+H7+I7 -> #REF! | Q7: =VLOOKUP(C7,[1]CPD!$B$9:$R$35,17,0) -> 0 | R7: =VLOOKUP(C7,[1]CPD!$B$9:$Q$35,16,0) -> 0 | S7: =VLOOKUP(C7,[2]CPD!$B$9:$S$35,18,0) -> 0 | T7: =VLOOKUP(C7,[1]CPD!$B$9:$T$35,19,0) -> 0 | W7: =VLOOKUP(C7,[1]CPD!$B$9:$V$35,21,0) -> 0 | Y7: =+K7-O7-P7+Q7+R7+S7+T7+U7+V7+W7 -> #REF! | Z7: =+M7-Y7 -> #REF! | AB7: =VLOOKUP(C7,[2]SINDICATO!$C$7:$Q$141,15,0) -> #N/A
A8: SEI0041 | B8: SEITON - (CONSULTORIA II) | C8: Vazquez Perez Miguel Angel | D8: =VLOOKUP(C8,[1]CPD!$B$9:$Y$35,24,0) -> 5074 | G8: =VLOOKUP(C8,#REF!,4,0) -> #REF! | H8: =VLOOKUP(C8,#REF!,5,0) -> #REF! | I8: =VLOOKUP(C8,#REF!,6,0) -> #REF! | K8: =+D8+E8+G8+H8+I8 -> #REF! | L8: =VLOOKUP(C8,[2]ABC!$A$3:$B$88,2,0) -> 18500 | M8: =+L8/2 -> 9250 | O8: =VLOOKUP(C8,[1]CPD!$B$9:$I$35,8,0) -> 0 | P8: =+H8+I8 -> #REF! | Q8: =VLOOKUP(C8,[1]CPD!$B$9:$R$35,17,0) -> 0 | R8: =VLOOKUP(C8,[1]CPD!$B$9:$Q$35,16,0) -> 0 | S8: =VLOOKUP(C8,[2]CPD!$B$9:$S$35,18,0) -> 0 | T8: =VLOOKUP(C8,[1]CPD!$B$9:$T$35,19,0) -> 0 | W8: =VLOOKUP(C8,[1]CPD!$B$9:$V$35,21,0) -> 0 | Y8: =+K8-O8-P8+Q8+R8+S8+T8+U8+V8+W8 -> #REF! | Z8: =+M8-Y8 -> #REF! | AB8: =VLOOKUP(C8,[2]SINDICATO!$C$7:$Q$141,15,0) -> #N/A
A9: SEI0088 | B9: SEITON - (CONSULTORIA II) | C9: Morgado Fernandez Martin | D9: =VLOOKUP(C9,[1]CPD!$B$9:$Y$35,24,0) -> 4899.6 | G9: =VLOOKUP(C9,#REF!,4,0) -> #REF! | H9: =VLOOKUP(C9,#REF!,5,0) -> #REF! | I9: =VLOOKUP(C9,#REF!,6,0) -> #REF! | K9: =+D9+E9+G9+H9+I9 -> #REF! | L9: =VLOOKUP(C9,[2]ABC!$A$3:$B$88,2,0) -> 15000 | M9: =+L9/2 -> 7500 | O9: =VLOOKUP(C9,[1]CPD!$B$9:$I$35,8,0) -> 0 | P9: =+H9+I9 -> #REF! | Q9: =VLOOKUP(C9,[1]CPD!$B$9:$R$35,17,0) -> 0 | R9: =VLOOKUP(C9,[1]CPD!$B$9:$Q$35,16,0) -> 0 | S9: =VLOOKUP(C9,[2]CPD!$B$9:$S$35,18,0) -> 0 | T9: =VLOOKUP(C9,[1]CPD!$B$9:$T$35,19,0) -> 0 | W9: =VLOOKUP(C9,[1]CPD!$B$9:$V$35,21,0) -> 0 | Y9: =+K9-O9-P9+Q9+R9+S9+T9+U9+V9+W9 -> #REF! | Z9: =+M9-Y9 -> #REF! | AB9: =VLOOKUP(C9,[2]SINDICATO!$C$7:$Q$141,15,0) -> #N/A
A10: SEI0097 | B10: SEITON - (CONSULTORIA II) | C10: Arreola Jimenez Jose Nieves | D10: =VLOOKUP(C10,[1]CPD!$B$9:$Y$35,24,0) -> 1927.6 | G10: =VLOOKUP(C10,#REF!,4,0) -> #REF! | H10: =VLOOKUP(C10,#REF!,5,0) -> #REF! | I10: =VLOOKUP(C10,#REF!,6,0) -> #REF! | K10: =+D10+E10+G10+H10+I10 -> #REF! | L10: =VLOOKUP(C10,[2]ABC!$A$3:$B$88,2,0) -> 10150 | M10: =+L10/2 -> 5075 | O10: =VLOOKUP(C10,[1]CPD!$B$9:$I$35,8,0) -> 0 | P10: =+H10+I10 -> #REF! | Q10: =VLOOKUP(C10,[1]CPD!$B$9:$R$35,17,0) -> 1574.29 | R10: =VLOOKUP(C10,[1]CPD!$B$9:$Q$35,16,0) -> 0 | S10: =VLOOKUP(C10,[2]CPD!$B$9:$S$35,18,0) -> 0 | T10: =VLOOKUP(C10,[1]CPD!$B$9:$T$35,19,0) -> 15 | W10: =VLOOKUP(C10,[1]CPD!$B$9:$V$35,21,0) -> 0 | Y10: =+K10-O10-P10+Q10+R10+S10+T10+U10+V10+W10 -> #REF! | Z10: =+M10-Y10 -> #REF! | AB10: =VLOOKUP(C10,[2]SINDICATO!$C$7:$Q$141,15,0) -> #N/A
A11: SEI0099 | B11: SEITON - (CONSULTORIA II) | C11: Garcia Villicaña Ricardo Pascual | D11: =VLOOKUP(C11,[1]CPD!$B$9:$Y$35,24,0) -> 4899.8 | G11: =VLOOKUP(C11,#REF!,4,0) -> #REF! | H11: =VLOOKUP(C11,#REF!,5,0) -> #REF! | I11: =VLOOKUP(C11,#REF!,6,0) -> #REF! | K11: =+D11+E11+G11+H11+I11 -> #REF! | L11: =VLOOKUP(C11,[2]ABC!$A$3:$B$88,2,0) -> 15000 | M11: =+L11/2 -> 7500 | O11: =VLOOKUP(C11,[1]CPD!$B$9:$I$35,8,0) -> 0 | P11: =+H11+I11 -> #REF! | Q11: =VLOOKUP(C11,[1]CPD!$B$9:$R$35,17,0) -> 0 | R11: =VLOOKUP(C11,[1]CPD!$B$9:$Q$35,16,0) -> 0 | S11: =VLOOKUP(C11,[2]CPD!$B$9:$S$35,18,0) -> 0 | T11: =VLOOKUP(C11,[1]CPD!$B$9:$T$35,19,0) -> 0 | W11: =VLOOKUP(C11,[1]CPD!$B$9:$V$35,21,0) -> 0 | Y11: =+K11-O11-P11+Q11+R11+S11+T11+U11+V11+W11 -> #REF! | Z11: =+M11-Y11 -> #REF! | AB11: =VLOOKUP(C11,[2]SINDICATO!$C$7:$Q$141,15,0) -> #N/A
A12: SEI0108 | B12: SEITON - (CONSULTORIA II) | C12: Caballero Diaz Francisco Javier | D12: =VLOOKUP(C12,[1]CPD!$B$9:$Y$35,24,0) -> 1675.4 | G12: =VLOOKUP(C12,#REF!,4,0) -> #REF! | H12: =VLOOKUP(C12,#REF!,5,0) -> #REF! | I12: =VLOOKUP(C12,#REF!,6,0) -> #REF! | K12: =+D12+E12+G12+H12+I12 -> #REF! | L12: =VLOOKUP(C12,[2]ABC!$A$3:$B$88,2,0) -> 10150 | M12: =+L12/2 -> 5075 | O12: =VLOOKUP(C12,[1]CPD!$B$9:$I$35,8,0) -> 0 | P12: =+H12+I12 -> #REF! | Q12: =VLOOKUP(C12,[1]CPD!$B$9:$R$35,17,0) -> 1826.51 | R12: =VLOOKUP(C12,[1]CPD!$B$9:$Q$35,16,0) -> 0 | S12: =VLOOKUP(C12,[2]CPD!$B$9:$S$35,18,0) -> 0 | T12: =VLOOKUP(C12,[1]CPD!$B$9:$T$35,19,0) -> 15 | W12: =VLOOKUP(C12,[1]CPD!$B$9:$V$35,21,0) -> 0 | Y12: =+K12-O12-P12+Q12+R12+S12+T12+U12+V12+W12 -> #REF! | Z12: =+M12-Y12 -> #REF! | AB12: =VLOOKUP(C12,[2]SINDICATO!$C$7:$Q$141,15,0) -> #N/A
A13: SEI0116 | B13: SEITON - (CONSULTORIA II) | C13: Casillas Cardona Cesar Alejandro | D13: =VLOOKUP(C13,[1]CPD!$B$9:$Y$35,24,0) -> 3336.6 | G13: =VLOOKUP(C13,#REF!,4,0) -> #REF! | H13: =VLOOKUP(C13,#REF!,5,0) -> #REF! | I13: =VLOOKUP(C13,#REF!,6,0) -> #REF! | K13: =+D13+E13+G13+H13+I13 -> #REF! | L13: =VLOOKUP(C13,[2]ABC!$A$3:$B$88,2,0) -> 12000 | M13: =+L13/2 -> 6000 | O13: =VLOOKUP(C13,[1]CPD!$B$9:$I$35,8,0) -> 0 | P13: =+H13+I13 -> #REF! | Q13: =VLOOKUP(C13,[1]CPD!$B$9:$R$35,17,0) -> 757.32 | R13: =VLOOKUP(C13,[1]CPD!$B$9:$Q$35,16,0) -> 0 | S13: =VLOOKUP(C13,[2]CPD!$B$9:$S$35,18,0) -> 0 | T13: =VLOOKUP(C13,[1]CPD!$B$9:$T$35,19,0) -> 15 | W13: =VLOOKUP(C13,[1]CPD!$B$9:$V$35,21,0) -> 0 | Y13: =+K13-O13-P13+Q13+R13+S13+T13+U13+V13+W13 -> #REF! | Z13: =+M13-Y13 -> #REF! | AB13: =VLOOKUP(C13,[2]SINDICATO!$C$7:$Q$141,15,0) -> #N/A
A14: SEI0117 | B14: SEITON - (CONSULTORIA II) | C14: Mariscal Romero Luis Adrian | D14: =VLOOKUP(C14,[1]CPD!$B$9:$Y$35,24,0) -> 3060 | G14: =VLOOKUP(C14,#REF!,4,0) -> #REF! | H14: =VLOOKUP(C14,#REF!,5,0) -> #REF! | I14: =VLOOKUP(C14,#REF!,6,0) -> #REF! | K14: =+D14+E14+G14+H14+I14 -> #REF! | L14: 15000 | M14: =+L14/2 -> 7500 | O14: =VLOOKUP(C14,[1]CPD!$B$9:$I$35,8,0) -> 0 | P14: =+H14+I14 -> #REF! | Q14: =VLOOKUP(C14,[1]CPD!$B$9:$R$35,17,0) -> 1674 | R14: =VLOOKUP(C14,[1]CPD!$B$9:$Q$35,16,0) -> 0 | S14: =VLOOKUP(C14,[2]CPD!$B$9:$S$35,18,0) -> 0 | T14: =VLOOKUP(C14,[1]CPD!$B$9:$T$35,19,0) -> 15 | W14: =VLOOKUP(C14,[1]CPD!$B$9:$V$35,21,0) -> 0 | Y14: =+K14-O14-P14+Q14+R14+S14+T14+U14+V14+W14 -> #REF! | Z14: =+M14-Y14 -> #REF! | AB14: =VLOOKUP(C14,[2]SINDICATO!$C$7:$Q$141,15,0) -> #N/A
A15: SEI0118 | B15: SEITON - (CONSULTORIA II) | C15: Arroyo Ramirez Hector Hugo | D15: =VLOOKUP(C15,[1]CPD!$B$9:$Y$35,24,0) -> 2967.4 | G15: =VLOOKUP(C15,#REF!,4,0) -> #REF! | H15: =VLOOKUP(C15,#REF!,5,0) -> #REF! | I15: =VLOOKUP(C15,#REF!,6,0) -> #REF! | K15: =+D15+E15+G15+H15+I15 -> #REF! | L15: =VLOOKUP(C15,[2]ABC!$A$3:$B$88,2,0) -> 13000 | M15: =+L15/2 -> 6500 | O15: =VLOOKUP(C15,[1]CPD!$B$9:$I$35,8,0) -> 285.99 | P15: =+H15+I15 -> #REF! | Q15: =VLOOKUP(C15,[1]CPD!$B$9:$R$35,17,0) -> 1432.4 | R15: =VLOOKUP(C15,[1]CPD!$B$9:$Q$35,16,0) -> 0 | S15: =VLOOKUP(C15,[2]CPD!$B$9:$S$35,18,0) -> 0 | T15: =VLOOKUP(C15,[1]CPD!$B$9:$T$35,19,0) -> 15 | W15: =VLOOKUP(C15,[1]CPD!$B$9:$V$35,21,0) -> 268.35 | Y15: =+K15-O15-P15+Q15+R15+S15+T15+U15+V15+W15 -> #REF! | Z15: =+M15-Y15 -> #REF! | AB15: =VLOOKUP(C15,[2]SINDICATO!$C$7:$Q$141,15,0) -> #N/A
A16: SEI0119 | B16: SEITON - (CONSULTORIA II) | C16: Dominguez Lopez Maria De Jesus | D16: =VLOOKUP(C16,[1]CPD!$B$9:$Y$35,24,0) -> 4635.4 | G16: =VLOOKUP(C16,#REF!,4,0) -> #REF! | H16: =VLOOKUP(C16,#REF!,5,0) -> #REF! | I16: =VLOOKUP(C16,#REF!,6,0) -> #REF! | J16: 0 | K16: =+D16+E16+G16+H16+I16 -> #REF! | L16: 13000 | M16: =+L16/2 -> 6500 | O16: =VLOOKUP(C16,[1]CPD!$B$9:$I$35,8,0) -> 786.49 | P16: =+H16+I16 -> #REF! | Q16: =VLOOKUP(C16,[1]CPD!$B$9:$R$35,17,0) -> 0 | R16: =VLOOKUP(C16,[1]CPD!$B$9:$Q$35,16,0) -> 533.16 | S16: =VLOOKUP(C16,[2]CPD!$B$9:$S$35,18,0) -> 0 | T16: =VLOOKUP(C16,[1]CPD!$B$9:$T$35,19,0) -> 15 | W16: =VLOOKUP(C16,[1]CPD!$B$9:$V$35,21,0) -> 0 | X16: 0 | Y16: =+K16-O16-P16+Q16+R16+S16+T16+U16+V16+W16 -> #REF! | Z16: =+M16-Y16 -> #REF! | AB16: =VLOOKUP(C16,[2]SINDICATO!$C$7:$Q$141,15,0) -> 0
A17: SEI0127 | B17: SEITON - (CONSULTORIA II) | C17: Hernandez Ochoa Eduardo | D17: =VLOOKUP(C17,[1]CPD!$B$9:$Y$35,24,0) -> 4899.8 | G17: =VLOOKUP(C17,#REF!,4,0) -> #REF! | H17: =VLOOKUP(C17,#REF!,5,0) -> #REF! | I17: =VLOOKUP(C17,#REF!,6,0) -> #REF! | K17: =+D17+E17+G17+H17+I17 -> #REF! | L17: =VLOOKUP(C17,[2]ABC!$A$3:$B$88,2,0) -> 15000 | M17: =+L17/2 -> 7500 | O17: =VLOOKUP(C17,[1]CPD!$B$9:$I$35,8,0) -> 0 | P17: =+H17+I17 -> #REF! | Q17: =VLOOKUP(C17,[1]CPD!$B$9:$R$35,17,0) -> 0 | R17: =VLOOKUP(C17,[1]CPD!$B$9:$Q$35,16,0) -> 0 | S17: =VLOOKUP(C17,[2]CPD!$B$9:$S$35,18,0) -> 0 | T17: =VLOOKUP(C17,[1]CPD!$B$9:$T$35,19,0) -> 0 | W17: =VLOOKUP(C17,[1]CPD!$B$9:$V$35,21,0) -> 0 | Y17: =+K17-O17-P17+Q17+R17+S17+T17+U17+V17+W17 -> #REF! | Z17: =+M17-Y17 -> #REF! | AB17: =VLOOKUP(C17,[2]SINDICATO!$C$7:$Q$141,15,0) -> #N/A
A18: SEI0147 | B18: SEITON - (CONSULTORIA II) | C18: Diaz Munguia Martha Liliana | D18: =VLOOKUP(C18,[1]CPD!$B$9:$Y$35,24,0) -> 5056.2 | G18: =VLOOKUP(C18,#REF!,4,0) -> #REF! | H18: =VLOOKUP(C18,#REF!,5,0) -> #REF! | I18: =VLOOKUP(C18,#REF!,6,0) -> #REF! | K18: =+D18+E18+G18+H18+I18 -> #REF! | L18: 25000 | M18: =+L18/2 -> 12500 | O18: =VLOOKUP(C18,[1]CPD!$B$9:$I$35,8,0) -> 0 | P18: =+H18+I18 -> #REF! | Q18: =VLOOKUP(C18,[1]CPD!$B$9:$R$35,17,0) -> 419.76 | R18: =VLOOKUP(C18,[1]CPD!$B$9:$Q$35,16,0) -> 0 | S18: =VLOOKUP(C18,[2]CPD!$B$9:$S$35,18,0) -> 0 | T18: =VLOOKUP(C18,[1]CPD!$B$9:$T$35,19,0) -> 15 | W18: =VLOOKUP(C18,[1]CPD!$B$9:$V$35,21,0) -> 0 | Y18: =+K18-O18-P18+Q18+R18+S18+T18+U18+V18+W18 -> #REF! | Z18: =+M18-Y18 -> #REF! | AB18: =VLOOKUP(C18,[2]SINDICATO!$C$7:$Q$141,15,0) -> 0
A19: SEI0173 | B19: SEITON - (CONSULTORIA II) | C19: Nieto Ortiz Jose Luis | D19: =VLOOKUP(C19,[1]CPD!$B$9:$Y$35,24,0) -> 1332.2 | G19: =VLOOKUP(C19,#REF!,4,0) -> #REF! | H19: =VLOOKUP(C19,#REF!,5,0) -> #REF! | I19: =VLOOKUP(C19,#REF!,6,0) -> #REF! | K19: =+D19+E19+G19+H19+I19 -> #REF! | L19: =VLOOKUP(C19,[2]ABC!$A$3:$B$88,2,0) -> 10000 | M19: =+L19/2 -> 5000 | O19: =VLOOKUP(C19,[1]CPD!$B$9:$I$35,8,0) -> 0 | P19: =+H19+I19 -> #REF! | Q19: =VLOOKUP(C19,[1]CPD!$B$9:$R$35,17,0) -> 2169.67 | R19: =VLOOKUP(C19,[1]CPD!$B$9:$Q$35,16,0) -> 0 | S19: =VLOOKUP(C19,[2]CPD!$B$9:$S$35,18,0) -> 0 | T19: =VLOOKUP(C19,[1]CPD!$B$9:$T$35,19,0) -> 15 | W19: =VLOOKUP(C19,[1]CPD!$B$9:$V$35,21,0) -> 0 | Y19: =+K19-O19-P19+Q19+R19+S19+T19+U19+V19+W19 -> #REF! | Z19: =+M19-Y19 -> #REF! | AB19: =VLOOKUP(C19,[2]SINDICATO!$C$7:$Q$141,15,0) -> #N/A
A20: SEI0221 | B20: SEITON - (CONSULTORIA II) | C20: Rogel Teran Marco Antonio | D20: =VLOOKUP(C20,[1]CPD!$B$9:$Y$35,24,0) -> 16969.2 | G20: =VLOOKUP(C20,#REF!,4,0) -> #REF! | H20: =VLOOKUP(C20,#REF!,5,0) -> #REF! | I20: =VLOOKUP(C20,#REF!,6,0) -> #REF! | K20: =+D20+E20+G20+H20+I20 -> #REF! | L20: 60000 | M20: =+L20/2 -> 30000 | O20: =VLOOKUP(C20,[1]CPD!$B$9:$I$35,8,0) -> 0 | P20: =+H20+I20 -> #REF! | Q20: =VLOOKUP(C20,[1]CPD!$B$9:$R$35,17,0) -> 0 | R20: =VLOOKUP(C20,[1]CPD!$B$9:$Q$35,16,0) -> 0 | S20: =VLOOKUP(C20,[2]CPD!$B$9:$S$35,18,0) -> 0 | T20: =VLOOKUP(C20,[1]CPD!$B$9:$T$35,19,0) -> 0 | W20: =VLOOKUP(C20,[1]CPD!$B$9:$V$35,21,0) -> 417.6 | Y20: =+K20-O20-P20+Q20+R20+S20+T20+U20+V20+W20 -> #REF! | Z20: =+M20-Y20 -> #REF! | AB20: =VLOOKUP(C20,[2]SINDICATO!$C$7:$Q$141,15,0) -> #N/A
A21: SEI0222 | B21: SEITON - (CONSULTORIA II) | C21: Saucedo Duran Jesus Alfredo | D21: =VLOOKUP(C21,[1]CPD!$B$9:$Y$35,24,0) -> 4241.4 | G21: =VLOOKUP(C21,#REF!,4,0) -> #REF! | H21: =VLOOKUP(C21,#REF!,5,0) -> #REF! | I21: =VLOOKUP(C21,#REF!,6,0) -> #REF! | K21: =+D21+E21+G21+H21+I21 -> #REF! | L21: 12000 | M21: =+L21/2 -> 6000 | O21: =VLOOKUP(C21,[1]CPD!$B$9:$I$35,8,0) -> 132.5 | P21: =+H21+I21 -> #REF! | Q21: =VLOOKUP(C21,[1]CPD!$B$9:$R$35,17,0) -> 0 | R21: =VLOOKUP(C21,[1]CPD!$B$9:$Q$35,16,0) -> 0 | S21: =VLOOKUP(C21,[2]CPD!$B$9:$S$35,18,0) -> 0 | T21: =VLOOKUP(C21,[1]CPD!$B$9:$T$35,19,0) -> 0 | W21: =VLOOKUP(C21,[1]CPD!$B$9:$V$35,21,0) -> 0 | Y21: =+K21-O21-P21+Q21+R21+S21+T21+U21+V21+W21 -> #REF! | Z21: =+M21-Y21 -> #REF! | AB21: =VLOOKUP(C21,[2]SINDICATO!$C$7:$Q$141,15,0) -> 0
A22: SEI032 | B22: SEITON - (CONSULTORIA II) | C22: Camarena Quiroz Erick Frank | D22: =VLOOKUP(C22,[1]CPD!$B$9:$Y$35,24,0) -> 2911.8 | G22: =VLOOKUP(C22,#REF!,4,0) -> #REF! | H22: =VLOOKUP(C22,#REF!,5,0) -> #REF! | I22: =VLOOKUP(C22,#REF!,6,0) -> #REF! | K22: =+D22+E22+G22+H22+I22 -> #REF! | L22: =VLOOKUP(C22,[2]ABC!$A$3:$B$88,2,0) -> 9000 | M22: =+L22/2 -> 4500 | O22: =VLOOKUP(C22,[1]CPD!$B$9:$I$35,8,0) -> 0 | P22: =+H22+I22 -> #REF! | Q22: =VLOOKUP(C22,[1]CPD!$B$9:$R$35,17,0) -> 0 | R22: =VLOOKUP(C22,[1]CPD!$B$9:$Q$35,16,0) -> 0 | S22: =VLOOKUP(C22,[2]CPD!$B$9:$S$35,18,0) -> 0 | T22: =VLOOKUP(C22,[1]CPD!$B$9:$T$35,19,0) -> 0 | W22: =VLOOKUP(C22,[1]CPD!$B$9:$V$35,21,0) -> 0 | Y22: =+K22-O22-P22+Q22+R22+S22+T22+U22+V22+W22 -> #REF! | Z22: =+M22-Y22 -> #REF! | AB22: =VLOOKUP(C22,[2]SINDICATO!$C$7:$Q$141,15,0) -> 0
A23: SEI0401 | B23: SEITON - (CONSULTORIA II) | C23: De La Torre Zambara Francisco Ernesto | D23: =VLOOKUP(C23,[1]CPD!$B$9:$Y$35,24,0) -> 3203.8 | G23: =VLOOKUP(C23,#REF!,4,0) -> #REF! | H23: =VLOOKUP(C23,#REF!,5,0) -> #REF! | I23: =VLOOKUP(C23,#REF!,6,0) -> #REF! | K23: =+D23+E23+G23+H23+I23 -> #REF! | L23: =VLOOKUP(C23,[2]ABC!$A$3:$B$88,2,0) -> 10150 | M23: =+L23/2 -> 5075 | O23: =VLOOKUP(C23,[1]CPD!$B$9:$I$35,8,0) -> 0 | P23: =+H23+I23 -> #REF! | Q23: =VLOOKUP(C23,[1]CPD!$B$9:$R$35,17,0) -> 0 | R23: =VLOOKUP(C23,[1]CPD!$B$9:$Q$35,16,0) -> 0 | S23: =VLOOKUP(C23,[2]CPD!$B$9:$S$35,18,0) -> 0 | T23: =VLOOKUP(C23,[1]CPD!$B$9:$T$35,19,0) -> 0 | W23: =VLOOKUP(C23,[1]CPD!$B$9:$V$35,21,0) -> 313.2 | Y23: =+K23-O23-P23+Q23+R23+S23+T23+U23+V23+W23 -> #REF! | Z23: =+M23-Y23 -> #REF! | AB23: =VLOOKUP(C23,[2]SINDICATO!$C$7:$Q$141,15,0) -> #N/A
A24: SEI0425 | B24: SEITON - (CONSULTORIA II) | C24: Carbajal Cabuto Jose Luis | D24: =VLOOKUP(C24,[1]CPD!$B$9:$Y$35,24,0) -> 1995.4 | G24: =VLOOKUP(C24,#REF!,4,0) -> #REF! | H24: =VLOOKUP(C24,#REF!,5,0) -> #REF! | I24: =VLOOKUP(C24,#REF!,6,0) -> #REF! | K24: =+D24+E24+G24+H24+I24 -> #REF! | L24: =VLOOKUP(C24,[2]ABC!$A$3:$B$88,2,0) -> 10250 | M24: =+L24/2 -> 5125 | O24: =VLOOKUP(C24,[1]CPD!$B$9:$I$35,8,0) -> 0 | P24: =+H24+I24 -> #REF! | Q24: =VLOOKUP(C24,[1]CPD!$B$9:$R$35,17,0) -> 1506.5 | R24: =VLOOKUP(C24,[1]CPD!$B$9:$Q$35,16,0) -> 0 | S24: =VLOOKUP(C24,[2]CPD!$B$9:$S$35,18,0) -> 0 | T24: =VLOOKUP(C24,[1]CPD!$B$9:$T$35,19,0) -> 15 | W24: =VLOOKUP(C24,[1]CPD!$B$9:$V$35,21,0) -> 0 | Y24: =+K24-O24-P24+Q24+R24+S24+T24+U24+V24+W24 -> #REF! | Z24: =+M24-Y24 -> #REF! | AB24: =VLOOKUP(C24,[2]SINDICATO!$C$7:$Q$141,15,0) -> #N/A
A25: SEI0435 | B25: SEITON - (CONSULTORIA II) | C25: Benavides Herrera Alejandra | D25: =VLOOKUP(C25,[1]CPD!$B$9:$Y$35,24,0) -> 3196.8 | G25: =VLOOKUP(C25,#REF!,4,0) -> #REF! | H25: =VLOOKUP(C25,#REF!,5,0) -> #REF! | I25: =VLOOKUP(C25,#REF!,6,0) -> #REF! | K25: =+D25+E25+G25+H25+I25 -> #REF! | L25: 40000 | M25: =+L25/2 -> 20000 | O25: =VLOOKUP(C25,[1]CPD!$B$9:$I$35,8,0) -> 0 | P25: =+H25+I25 -> #REF! | Q25: =VLOOKUP(C25,[1]CPD!$B$9:$R$35,17,0) -> 0 | R25: =VLOOKUP(C25,[1]CPD!$B$9:$Q$35,16,0) -> 0 | S25: =VLOOKUP(C25,[2]CPD!$B$9:$S$35,18,0) -> 0 | T25: =VLOOKUP(C25,[1]CPD!$B$9:$T$35,19,0) -> 0 | W25: =VLOOKUP(C25,[1]CPD!$B$9:$V$35,21,0) -> 0 | Y25: =+K25-O25-P25+Q25+R25+S25+T25+U25+V25+W25 -> #REF! | Z25: =+M25-Y25 -> #REF! | AB25: =VLOOKUP(C25,[2]SINDICATO!$C$7:$Q$141,15,0) -> #N/A
A26: SEI0437 | B26: SEITON - (CONSULTORIA II) | C26: Leal Montaño Diego | D26: =VLOOKUP(C26,[1]CPD!$B$9:$Y$35,24,0) -> 2782.8 | G26: =VLOOKUP(C26,#REF!,4,0) -> #REF! | H26: =VLOOKUP(C26,#REF!,5,0) -> #REF! | I26: =VLOOKUP(C26,#REF!,6,0) -> #REF! | K26: =+D26+E26+G26+H26+I26 -> #REF! | L26: 10000 | M26: =+L26/2 -> 5000 | O26: =VLOOKUP(C26,[1]CPD!$B$9:$I$35,8,0) -> 0 | P26: =+H26+I26 -> #REF! | Q26: =VLOOKUP(C26,[1]CPD!$B$9:$R$35,17,0) -> 398.98 | R26: =VLOOKUP(C26,[1]CPD!$B$9:$Q$35,16,0) -> 0 | S26: =VLOOKUP(C26,[2]CPD!$B$9:$S$35,18,0) -> 0 | T26: =VLOOKUP(C26,[1]CPD!$B$9:$T$35,19,0) -> 15 | W26: =VLOOKUP(C26,[1]CPD!$B$9:$V$35,21,0) -> 0 | Y26: =+K26-O26-P26+Q26+R26+S26+T26+U26+V26+W26 -> #REF! | Z26: =+M26-Y26 -> #REF! | AB26: =VLOOKUP(C26,[2]SINDICATO!$C$7:$Q$141,15,0) -> 0
A27: SEI0440 | B27: SEITON - (CONSULTORIA II) | C27: Leija Arevalo Guadalupe | D27: =VLOOKUP(C27,[1]CPD!$B$9:$Y$35,24,0) -> 1003 | G27: =VLOOKUP(C27,#REF!,4,0) -> #REF! | H27: =VLOOKUP(C27,#REF!,5,0) -> #REF! | I27: =VLOOKUP(C27,#REF!,6,0) -> #REF! | K27: =+D27+E27+G27+H27+I27 -> #REF! | L27: 4000 | M27: =+L27/2 -> 2000 | O27: =VLOOKUP(C27,[1]CPD!$B$9:$I$35,8,0) -> 0 | P27: =+H27+I27 -> #REF! | Q27: =VLOOKUP(C27,[1]CPD!$B$9:$R$35,17,0) -> 1005.81 | R27: =VLOOKUP(C27,[1]CPD!$B$9:$Q$35,16,0) -> 0 | S27: =VLOOKUP(C27,[2]CPD!$B$9:$S$35,18,0) -> 0 | T27: =VLOOKUP(C27,[1]CPD!$B$9:$T$35,19,0) -> 15 | W27: =VLOOKUP(C27,[1]CPD!$B$9:$V$35,21,0) -> 0 | Y27: =+K27-O27-P27+Q27+R27+S27+T27+U27+V27+W27 -> #REF! | Z27: =+M27-Y27 -> #REF! | AA27: subsidio | AB27: =VLOOKUP(C27,[2]SINDICATO!$C$7:$Q$141,15,0) -> 0
A28: SEI0442 | B28: SEITON - (CONSULTORIA II) | C28: Sierra Escamilla Daniela | D28: =VLOOKUP(C28,[1]CPD!$B$9:$Y$35,24,0) -> 4036 | G28: =VLOOKUP(C28,#REF!,4,0) -> #REF! | H28: =VLOOKUP(C28,#REF!,5,0) -> #REF! | I28: =VLOOKUP(C28,#REF!,6,0) -> #REF! | K28: =+D28+E28+G28+H28+I28 -> #REF! | L28: 13000 | M28: =+L28/2 -> 6500 | O28: =VLOOKUP(C28,[1]CPD!$B$9:$I$35,8,0) -> 0 | P28: =+H28+I28 -> #REF! | Q28: =VLOOKUP(C28,[1]CPD!$B$9:$R$35,17,0) -> 0 | R28: =VLOOKUP(C28,[1]CPD!$B$9:$Q$35,16,0) -> 0 | S28: =VLOOKUP(C28,[2]CPD!$B$9:$S$35,18,0) -> 0 | T28: =VLOOKUP(C28,[1]CPD!$B$9:$T$35,19,0) -> 0 | W28: =VLOOKUP(C28,[1]CPD!$B$9:$V$35,21,0) -> 0 | Y28: =+K28-O28-P28+Q28+R28+S28+T28+U28+V28+W28 -> #REF! | Z28: =+M28-Y28 -> #REF! | AB28: =VLOOKUP(C28,[2]SINDICATO!$C$7:$Q$141,15,0) -> #N/A
A29: SEI0445 | B29: SEITON - (CONSULTORIA II) | C29: Muñoz Melgoza Gabriel | D29: =VLOOKUP(C29,[1]CPD!$B$9:$Y$35,24,0) -> 4609.4 | G29: =VLOOKUP(C29,#REF!,4,0) -> #REF! | H29: =VLOOKUP(C29,#REF!,5,0) -> #REF! | I29: =VLOOKUP(C29,#REF!,6,0) -> #REF! | K29: =+D29+E29+G29+H29+I29 -> #REF! | L29: 15400 | M29: =+L29/2 -> 7700 | O29: =VLOOKUP(C29,[1]CPD!$B$9:$I$35,8,0) -> 0 | P29: =+H29+I29 -> #REF! | Q29: =VLOOKUP(C29,[1]CPD!$B$9:$R$35,17,0) -> 0 | R29: =VLOOKUP(C29,[1]CPD!$B$9:$Q$35,16,0) -> 0 | S29: =VLOOKUP(C29,[2]CPD!$B$9:$S$35,18,0) -> 0 | T29: =VLOOKUP(C29,[1]CPD!$B$9:$T$35,19,0) -> 0 | W29: =VLOOKUP(C29,[1]CPD!$B$9:$V$35,21,0) -> 0 | Y29: =+K29-O29-P29+Q29+R29+S29+T29+U29+V29+W29 -> #REF! | Z29: =+M29-Y29 -> #REF! | AB29: =VLOOKUP(C29,[2]SINDICATO!$C$7:$Q$141,15,0) -> #N/A
A30: SEI0448 | B30: SEITON - (CONSULTORIA II) | C30: Rodriguez Chavez Oswaldo Emmanuel | D30: =VLOOKUP(C30,[1]CPD!$B$9:$Y$35,24,0) -> 4327.4 | G30: =VLOOKUP(C30,#REF!,4,0) -> #REF! | H30: =VLOOKUP(C30,#REF!,5,0) -> #REF! | I30: =VLOOKUP(C30,#REF!,6,0) -> #REF! | K30: =+D30+E30+G30+H30+I30 -> #REF! | L30: 14000 | M30: =+L30/2 -> 7000 | O30: =VLOOKUP(C30,[1]CPD!$B$9:$I$35,8,0) -> 0 | P30: =+H30+I30 -> #REF! | Q30: =VLOOKUP(C30,[1]CPD!$B$9:$R$35,17,0) -> 0 | R30: =VLOOKUP(C30,[1]CPD!$B$9:$Q$35,16,0) -> 0 | S30: =VLOOKUP(C30,[2]CPD!$B$9:$S$35,18,0) -> 0 | T30: =VLOOKUP(C30,[1]CPD!$B$9:$T$35,19,0) -> 0 | W30: =VLOOKUP(C30,[1]CPD!$B$9:$V$35,21,0) -> 0 | Y30: =+K30-O30-P30+Q30+R30+S30+T30+U30+V30+W30 -> #REF! | Z30: =+M30-Y30 -> #REF! | AB30: =VLOOKUP(C30,[2]SINDICATO!$C$7:$Q$141,15,0) -> 0
A31: SEI0010 | B31: SEITON (IP INNOVA II) | C31: Torres Ricardez Alfredo | E31: =VLOOKUP(C31,[1]IP!$B$9:$V$116,21,0) -> 3585.4 | G31: =VLOOKUP(C31,#REF!,4,0) -> #REF! | H31: =VLOOKUP(C31,#REF!,5,0) -> #REF! | I31: =VLOOKUP(C31,#REF!,6,0) -> #REF! | K31: =+D31+E31+G31+H31+I31 -> #REF! | L31: =VLOOKUP(C31,[2]ABC!$A$3:$B$88,2,0) -> 8000 | M31: =+L31/2 -> 4000 | O31: =VLOOKUP(C31,[1]IP!$B$9:$I$116,8,0) -> 0 | P31: =+H31+I31 -> #REF! | Q31: =VLOOKUP(C31,[1]IP!$B$9:$N$116,13,0) -> 0 | R31: =VLOOKUP(C31,[1]IP!$B$9:$O$116,14,0) -> 0 | T31: =VLOOKUP(C31,[1]IP!$B$9:$P$116,15,0) -> 0 | U31: =VLOOKUP(C31,[1]IP!$B$9:$Q$116,16,0) -> 0 | V31: =VLOOKUP(C31,[1]IP!$B$9:$S$116,18,0) -> 0 | W31: =VLOOKUP(C31,[1]IP!$B$9:$R$116,17,0) -> 0 | Y31: =+K31-O31-P31+Q31+R31+S31+T31+U31+V31+W31 -> #REF! | Z31: =+M31-Y31 -> #REF! | AB31: =VLOOKUP(C31,[2]SINDICATO!$C$7:$Q$141,15,0) -> #N/A
A32: SEI0014 | B32: SEITON (IP INNOVA II) | C32: Montoya Portillo Carlos Alberto | E32: =VLOOKUP(C32,[1]IP!$B$9:$V$116,21,0) -> 3585.2 | G32: =VLOOKUP(C32,#REF!,4,0) -> #REF! | H32: =VLOOKUP(C32,#REF!,5,0) -> #REF! | I32: =VLOOKUP(C32,#REF!,6,0) -> #REF! | K32: =+D32+E32+G32+H32+I32 -> #REF! | L32: 8000 | M32: =+L32/2 -> 4000 | O32: =VLOOKUP(C32,[1]IP!$B$9:$I$116,8,0) -> 0 | P32: =+H32+I32 -> #REF! | Q32: =VLOOKUP(C32,[1]IP!$B$9:$N$116,13,0) -> 0 | R32: =VLOOKUP(C32,[1]IP!$B$9:$O$116,14,0) -> 0 | T32: =VLOOKUP(C32,[1]IP!$B$9:$P$116,15,0) -> 0 | U32: =VLOOKUP(C32,[1]IP!$B$9:$Q$116,16,0) -> 0 | V32: =VLOOKUP(C32,[1]IP!$B$9:$S$116,18,0) -> 0 | W32: =VLOOKUP(C32,[1]IP!$B$9:$R$116,17,0) -> 0 | Y32: =+K32-O32-P32+Q32+R32+S32+T32+U32+V32+W32 -> #REF! | Z32: =+M32-Y32 -> #REF! | AB32: =VLOOKUP(C32,[2]SINDICATO!$C$7:$Q$141,15,0) -> #N/A
A33: SEI0016 | B33: SEITON (IP INNOVA II) | C33: Negrete Bejar Aide Sarai | E33: =VLOOKUP(C33,[1]IP!$B$9:$V$116,21,0) -> 1278 | G33: =VLOOKUP(C33,#REF!,4,0) -> #REF! | H33: =VLOOKUP(C33,#REF!,5,0) -> #REF! | I33: =VLOOKUP(C33,#REF!,6,0) -> #REF! | K33: =+D33+E33+G33+H33+I33 -> #REF! | L33: =VLOOKUP(C33,[2]ABC!$A$3:$B$88,2,0) -> 4620 | M33: =+L33/2 -> 2310 | O33: =VLOOKUP(C33,[1]IP!$B$9:$I$116,8,0) -> 0 | P33: =+H33+I33 -> #REF! | Q33: =VLOOKUP(C33,[1]IP!$B$9:$N$116,13,0) -> 999.51 | R33: =VLOOKUP(C33,[1]IP!$B$9:$O$116,14,0) -> 0 | T33: =VLOOKUP(C33,[1]IP!$B$9:$P$116,15,0) -> 15 | U33: =VLOOKUP(C33,[1]IP!$B$9:$Q$116,16,0) -> 0 | V33: =VLOOKUP(C33,[1]IP!$B$9:$S$116,18,0) -> 0 | W33: =VLOOKUP(C33,[1]IP!$B$9:$R$116,17,0) -> 0 | Y33: =+K33-O33-P33+Q33+R33+S33+T33+U33+V33+W33 -> #REF! | Z33: =+M33-Y33 -> #REF! | AB33: =VLOOKUP(C33,[2]SINDICATO!$C$7:$Q$141,15,0) -> 0
A34: SEI0017 | B34: SEITON (IP INNOVA II) | C34: Muñoz Reyes Luis Eduardo | E34: =VLOOKUP(C34,[1]IP!$B$9:$V$116,21,0) -> 2692.8 | G34: =VLOOKUP(C34,#REF!,4,0) -> #REF! | H34: =VLOOKUP(C34,#REF!,5,0) -> #REF! | I34: =VLOOKUP(C34,#REF!,6,0) -> #REF! | K34: =+D34+E34+G34+H34+I34 -> #REF! | L34: =VLOOKUP(C34,[2]ABC!$A$3:$B$88,2,0) -> 8000 | M34: =+L34/2 -> 4000 | O34: =VLOOKUP(C34,[1]IP!$B$9:$I$116,8,0) -> 0 | P34: =+H34+I34 -> #REF! | Q34: =VLOOKUP(C34,[1]IP!$B$9:$N$116,13,0) -> 877.59 | R34: =VLOOKUP(C34,[1]IP!$B$9:$O$116,14,0) -> 0 | T34: =VLOOKUP(C34,[1]IP!$B$9:$P$116,15,0) -> 15 | U34: =VLOOKUP(C34,[1]IP!$B$9:$Q$116,16,0) -> 0 | V34: =VLOOKUP(C34,[1]IP!$B$9:$S$116,18,0) -> 0 | W34: =VLOOKUP(C34,[1]IP!$B$9:$R$116,17,0) -> 0 | Y34: =+K34-O34-P34+Q34+R34+S34+T34+U34+V34+W34 -> #REF! | Z34: =+M34-Y34 -> #REF! | AB34: =VLOOKUP(C34,[2]SINDICATO!$C$7:$Q$141,15,0) -> #N/A
A35: SEI0019 | B35: SEITON (IP INNOVA II) | C35: Gonzalez Rasgado Miguel Isaias | E35: =VLOOKUP(C35,[1]IP!$B$9:$V$116,21,0) -> 5195.2 | G35: =VLOOKUP(C35,#REF!,4,0) -> #REF! | H35: =VLOOKUP(C35,#REF!,5,0) -> #REF! | I35: =VLOOKUP(C35,#REF!,6,0) -> #REF! | K35: =+D35+E35+G35+H35+I35 -> #REF! | L35: =VLOOKUP(C35,[2]ABC!$A$3:$B$88,2,0) -> 12000 | M35: =+L35/2 -> 6000 | O35: =VLOOKUP(C35,[1]IP!$B$9:$I$116,8,0) -> 0 | P35: =+H35+I35 -> #REF! | Q35: =VLOOKUP(C35,[1]IP!$B$9:$N$116,13,0) -> 0 | R35: =VLOOKUP(C35,[1]IP!$B$9:$O$116,14,0) -> 0 | T35: =VLOOKUP(C35,[1]IP!$B$9:$P$116,15,0) -> 0 | U35: =VLOOKUP(C35,[1]IP!$B$9:$Q$116,16,0) -> 0 | V35: =VLOOKUP(C35,[1]IP!$B$9:$S$116,18,0) -> 0 | W35: =VLOOKUP(C35,[1]IP!$B$9:$R$116,17,0) -> 0 | Y35: =+K35-O35-P35+Q35+R35+S35+T35+U35+V35+W35 -> #REF! | Z35: =+M35-Y35 -> #REF! | AB35: =VLOOKUP(C35,[2]SINDICATO!$C$7:$Q$141,15,0) -> #N/A
A36: SEI0020 | B36: SEITON (IP INNOVA II) | C36: Mar Marquez Cesar Eduardo | E36: =VLOOKUP(C36,[1]IP!$B$9:$V$116,21,0) -> 3585.4 | G36: =VLOOKUP(C36,#REF!,4,0) -> #REF! | H36: =VLOOKUP(C36,#REF!,5,0) -> #REF! | I36: =VLOOKUP(C36,#REF!,6,0) -> #REF! | K36: =+D36+E36+G36+H36+I36 -> #REF! | L36: 8000 | M36: =+L36/2 -> 4000 | O36: =VLOOKUP(C36,[1]IP!$B$9:$I$116,8,0) -> 0 | P36: =+H36+I36 -> #REF! | Q36: =VLOOKUP(C36,[1]IP!$B$9:$N$116,13,0) -> 0 | R36: =VLOOKUP(C36,[1]IP!$B$9:$O$116,14,0) -> 0 | T36: =VLOOKUP(C36,[1]IP!$B$9:$P$116,15,0) -> 0 | U36: =VLOOKUP(C36,[1]IP!$B$9:$Q$116,16,0) -> 0 | V36: =VLOOKUP(C36,[1]IP!$B$9:$S$116,18,0) -> 0 | W36: =VLOOKUP(C36,[1]IP!$B$9:$R$116,17,0) -> 0 | Y36: =+K36-O36-P36+Q36+R36+S36+T36+U36+V36+W36 -> #REF! | Z36: =+M36-Y36 -> #REF! | AB36: =VLOOKUP(C36,[2]SINDICATO!$C$7:$Q$141,15,0) -> #N/A
A37: SEI0021 | B37: SEITON (IP INNOVA II) | C37: Velez Rodriguez Jaime | E37: =VLOOKUP(C37,[1]IP!$B$9:$V$116,21,0) -> 1490.6 | G37: =VLOOKUP(C37,#REF!,4,0) -> #REF! | H37: =VLOOKUP(C37,#REF!,5,0) -> #REF! | I37: =VLOOKUP(C37,#REF!,6,0) -> #REF! | K37: =+D37+E37+G37+H37+I37 -> #REF! | L37: 8000 | M37: =+L37/2 -> 4000 | O37: =VLOOKUP(C37,[1]IP!$B$9:$I$116,8,0) -> 0 | P37: =+H37+I37 -> #REF! | Q37: =VLOOKUP(C37,[1]IP!$B$9:$N$116,13,0) -> 1359.23 | R37: =VLOOKUP(C37,[1]IP!$B$9:$O$116,14,0) -> 0 | T37: =VLOOKUP(C37,[1]IP!$B$9:$P$116,15,0) -> 15 | U37: =VLOOKUP(C37,[1]IP!$B$9:$Q$116,16,0) -> 0 | V37: =VLOOKUP(C37,[1]IP!$B$9:$S$116,18,0) -> 0 | W37: =VLOOKUP(C37,[1]IP!$B$9:$R$116,17,0) -> 0 | Y37: =+K37-O37-P37+Q37+R37+S37+T37+U37+V37+W37 -> #REF! | Z37: =+M37-Y37 -> #REF! | AB37: =VLOOKUP(C37,[2]SINDICATO!$C$7:$Q$141,15,0) -> #N/A
A38: SEI0022 | B38: SEITON (IP INNOVA II) | C38: Najera Lopez Raul | E38: =VLOOKUP(C38,[1]IP!$B$9:$V$116,21,0) -> 4406.4 | G38: =VLOOKUP(C38,#REF!,4,0) -> #REF! | H38: =VLOOKUP(C38,#REF!,5,0) -> #REF! | I38: =VLOOKUP(C38,#REF!,6,0) -> #REF! | K38: =+D38+E38+G38+H38+I38 -> #REF! | L38: =VLOOKUP(C38,[2]ABC!$A$3:$B$88,2,0) -> 10000 | M38: =+L38/2 -> 5000 | O38: =VLOOKUP(C38,[1]IP!$B$9:$I$116,8,0) -> 0 | P38: =+H38+I38 -> #REF! | Q38: =VLOOKUP(C38,[1]IP!$B$9:$N$116,13,0) -> 0 | R38: =VLOOKUP(C38,[1]IP!$B$9:$O$116,14,0) -> 0 | T38: =VLOOKUP(C38,[1]IP!$B$9:$P$116,15,0) -> 0 | U38: =VLOOKUP(C38,[1]IP!$B$9:$Q$116,16,0) -> 0 | V38: =VLOOKUP(C38,[1]IP!$B$9:$S$116,18,0) -> 0 | W38: =VLOOKUP(C38,[1]IP!$B$9:$R$116,17,0) -> 0 | Y38: =+K38-O38-P38+Q38+R38+S38+T38+U38+V38+W38 -> #REF! | Z38: =+M38-Y38 -> #REF! | AB38: =VLOOKUP(C38,[2]SINDICATO!$C$7:$Q$141,15,0) -> #N/A
A39: SEI0023 | B39: SEITON (IP INNOVA II) | C39: Puente Murguia Luis Felipe | E39: =VLOOKUP(C39,[1]IP!$B$9:$V$116,21,0) -> 3277.4 | G39: =VLOOKUP(C39,#REF!,4,0) -> #REF! | H39: =VLOOKUP(C39,#REF!,5,0) -> #REF! | I39: =VLOOKUP(C39,#REF!,6,0) -> #REF! | K39: =+D39+E39+G39+H39+I39 -> #REF! | L39: =VLOOKUP(C39,[2]ABC!$A$3:$B$88,2,0) -> 7000 | M39: =+L39/2 -> 3500 | O39: =VLOOKUP(C39,[1]IP!$B$9:$I$116,8,0) -> 0 | P39: =+H39+I39 -> #REF! | Q39: =VLOOKUP(C39,[1]IP!$B$9:$N$116,13,0) -> 0 | R39: =VLOOKUP(C39,[1]IP!$B$9:$O$116,14,0) -> 0 | T39: =VLOOKUP(C39,[1]IP!$B$9:$P$116,15,0) -> 0 | U39: =VLOOKUP(C39,[1]IP!$B$9:$Q$116,16,0) -> 0 | V39: =VLOOKUP(C39,[1]IP!$B$9:$S$116,18,0) -> 0 | W39: =VLOOKUP(C39,[1]IP!$B$9:$R$116,17,0) -> 0 | Y39: =+K39-O39-P39+Q39+R39+S39+T39+U39+V39+W39 -> #REF! | Z39: =+M39-Y39 -> #REF! | AB39: =VLOOKUP(C39,[2]SINDICATO!$C$7:$Q$141,15,0) -> #N/A
A40: SEI0029 | B40: SEITON (IP INNOVA II) | C40: Arceo Garcia Manuel Federico | E40: =VLOOKUP(C40,[1]IP!$B$9:$V$116,21,0) -> 2090.2 | G40: =VLOOKUP(C40,#REF!,4,0) -> #REF! | H40: =VLOOKUP(C40,#REF!,5,0) -> #REF! | I40: =VLOOKUP(C40,#REF!,6,0) -> #REF! | K40: =+D40+E40+G40+H40+I40 -> #REF! | L40: =VLOOKUP(C40,[2]ABC!$A$3:$B$88,2,0) -> 6000 | M40: =+L40/2 -> 3000 | O40: =VLOOKUP(C40,[1]IP!$B$9:$I$116,8,0) -> 0 | P40: =+H40+I40 -> #REF! | Q40: =VLOOKUP(C40,[1]IP!$B$9:$N$116,13,0) -> 0 | R40: =VLOOKUP(C40,[1]IP!$B$9:$O$116,14,0) -> 0 | T40: =VLOOKUP(C40,[1]IP!$B$9:$P$116,15,0) -> 0 | U40: =VLOOKUP(C40,[1]IP!$B$9:$Q$116,16,0) -> 600 | V40: =VLOOKUP(C40,[1]IP!$B$9:$S$116,18,0) -> 0 | W40: =VLOOKUP(C40,[1]IP!$B$9:$R$116,17,0) -> 0 | Y40: =+K40-O40-P40+Q40+R40+S40+T40+U40+V40+W40 -> #REF! | Z40: =+M40-Y40 -> #REF! | AB40: =VLOOKUP(C40,[2]SINDICATO!$C$7:$Q$141,15,0) -> #N/A
A41: SEI0031 | B41: SEITON (IP INNOVA II) | C41: Contreras Zetina Victor Hugo | E41: =VLOOKUP(C41,[1]IP!$B$9:$V$116,21,0) -> 3234.2 | G41: =VLOOKUP(C41,#REF!,4,0) -> #REF! | H41: =VLOOKUP(C41,#REF!,5,0) -> #REF! | I41: =VLOOKUP(C41,#REF!,6,0) -> #REF! | K41: =+D41+E41+G41+H41+I41 -> #REF! | L41: =VLOOKUP(C41,[2]ABC!$A$3:$B$88,2,0) -> 6900 | M41: =+L41/2 -> 3450 | O41: =VLOOKUP(C41,[1]IP!$B$9:$I$116,8,0) -> 0 | P41: =+H41+I41 -> #REF! | Q41: =VLOOKUP(C41,[1]IP!$B$9:$N$116,13,0) -> 0 | R41: =VLOOKUP(C41,[1]IP!$B$9:$O$116,14,0) -> 0 | T41: =VLOOKUP(C41,[1]IP!$B$9:$P$116,15,0) -> 0 | U41: =VLOOKUP(C41,[1]IP!$B$9:$Q$116,16,0) -> 0 | V41: =VLOOKUP(C41,[1]IP!$B$9:$S$116,18,0) -> 0 | W41: =VLOOKUP(C41,[1]IP!$B$9:$R$116,17,0) -> 0 | Y41: =+K41-O41-P41+Q41+R41+S41+T41+U41+V41+W41 -> #REF! | Z41: =+M41-Y41 -> #REF! | AB41: =VLOOKUP(C41,[2]SINDICATO!$C$7:$Q$141,15,0) -> 0
A42: SEI0037 | B42: SEITON (IP INNOVA II) | C42: Gomez Oliveros Alin | E42: =VLOOKUP(C42,[1]IP!$B$9:$V$116,21,0) -> 2864.8 | G42: =VLOOKUP(C42,#REF!,4,0) -> #REF! | H42: =VLOOKUP(C42,#REF!,5,0) -> #REF! | I42: =VLOOKUP(C42,#REF!,6,0) -> #REF! | K42: =+D42+E42+G42+H42+I42 -> #REF! | L42: 10000 | M42: =+L42/2 -> 5000 | O42: =VLOOKUP(C42,[1]IP!$B$9:$I$116,8,0) -> 0 | P42: =+H42+I42 -> #REF! | Q42: =VLOOKUP(C42,[1]IP!$B$9:$N$116,13,0) -> 0 | R42: =VLOOKUP(C42,[1]IP!$B$9:$O$116,14,0) -> 0 | T42: =VLOOKUP(C42,[1]IP!$B$9:$P$116,15,0) -> 0 | U42: =VLOOKUP(C42,[1]IP!$B$9:$Q$116,16,0) -> 0 | V42: =VLOOKUP(C42,[1]IP!$B$9:$S$116,18,0) -> 0 | W42: =VLOOKUP(C42,[1]IP!$B$9:$R$116,17,0) -> 0 | Y42: =+K42-O42-P42+Q42+R42+S42+T42+U42+V42+W42 -> #REF! | Z42: =+M42-Y42 -> #REF! | AB42: =VLOOKUP(C42,[2]SINDICATO!$C$7:$Q$141,15,0) -> 0
A43: SEI0078 | B43: SEITON (IP INNOVA II) | C43: Aguilar Leal Karina Livier | E43: =VLOOKUP(C43,[1]IP!$B$9:$V$116,21,0) -> 3583.6 | G43: =VLOOKUP(C43,#REF!,4,0) -> #REF! | H43: =VLOOKUP(C43,#REF!,5,0) -> #REF! | I43: =VLOOKUP(C43,#REF!,6,0) -> #REF! | K43: =+D43+E43+G43+H43+I43 -> #REF! | L43: 9000 | M43: =+L43/2 -> 4500 | O43: =VLOOKUP(C43,[1]IP!$B$9:$I$116,8,0) -> 0 | P43: =+H43+I43 -> #REF! | Q43: =VLOOKUP(C43,[1]IP!$B$9:$N$116,13,0) -> 0 | R43: =VLOOKUP(C43,[1]IP!$B$9:$O$116,14,0) -> 0 | T43: =VLOOKUP(C43,[1]IP!$B$9:$P$116,15,0) -> 0 | U43: =VLOOKUP(C43,[1]IP!$B$9:$Q$116,16,0) -> 0 | V43: =VLOOKUP(C43,[1]IP!$B$9:$S$116,18,0) -> 0 | W43: =VLOOKUP(C43,[1]IP!$B$9:$R$116,17,0) -> 0 | Y43: =+K43-O43-P43+Q43+R43+S43+T43+U43+V43+W43 -> #REF! | AB43: =VLOOKUP(C43,[2]SINDICATO!$C$7:$Q$141,15,0) -> 0
A44: SEI0079 | B44: SEITON (IP INNOVA II) | C44: Amezcua Contreras Martha Frine | E44: =VLOOKUP(C44,[1]IP!$B$9:$V$116,21,0) -> 7087.8 | G44: =VLOOKUP(C44,#REF!,4,0) -> #REF! | H44: =VLOOKUP(C44,#REF!,5,0) -> #REF! | I44: =VLOOKUP(C44,#REF!,6,0) -> #REF! | K44: =+D44+E44+G44+H44+I44 -> #REF! | L44: =VLOOKUP(C44,[2]ABC!$A$3:$B$88,2,0) -> 18500 | M44: =+L44/2 -> 9250 | O44: =VLOOKUP(C44,[1]IP!$B$9:$I$116,8,0) -> 0 | P44: =+H44+I44 -> #REF! | Q44: =VLOOKUP(C44,[1]IP!$B$9:$N$116,13,0) -> 0 | R44: =VLOOKUP(C44,[1]IP!$B$9:$O$116,14,0) -> 0 | T44: =VLOOKUP(C44,[1]IP!$B$9:$P$116,15,0) -> 0 | U44: =VLOOKUP(C44,[1]IP!$B$9:$Q$116,16,0) -> 0 | V44: =VLOOKUP(C44,[1]IP!$B$9:$S$116,18,0) -> 0 | W44: =VLOOKUP(C44,[1]IP!$B$9:$R$116,17,0) -> 0 | Y44: =+K44-O44-P44+Q44+R44+S44+T44+U44+V44+W44 -> #REF! | Z44: =+M44-Y44 -> #REF! | AB44: =VLOOKUP(C44,[2]SINDICATO!$C$7:$Q$141,15,0) -> 0
A45: SEI0081 | B45: SEITON (IP INNOVA II) | C45: Guizar Perez Sergio | E45: =VLOOKUP(C45,[1]IP!$B$9:$V$116,21,0) -> 3518.2 | G45: =VLOOKUP(C45,#REF!,4,0) -> #REF! | H45: =VLOOKUP(C45,#REF!,5,0) -> #REF! | I45: =VLOOKUP(C45,#REF!,6,0) -> #REF! | K45: =+D45+E45+G45+H45+I45 -> #REF! | L45: =VLOOKUP(C45,[2]ABC!$A$3:$B$88,2,0) -> 8500 | M45: =+L45/2 -> 4250 | O45: =VLOOKUP(C45,[1]IP!$B$9:$I$116,8,0) -> 150 | P45: =+H45+I45 -> #REF! | Q45: =VLOOKUP(C45,[1]IP!$B$9:$N$116,13,0) -> 0 | R45: =VLOOKUP(C45,[1]IP!$B$9:$O$116,14,0) -> 0 | T45: =VLOOKUP(C45,[1]IP!$B$9:$P$116,15,0) -> 0 | U45: =VLOOKUP(C45,[1]IP!$B$9:$Q$116,16,0) -> 0 | V45: =VLOOKUP(C45,[1]IP!$B$9:$S$116,18,0) -> 0 | W45: =VLOOKUP(C45,[1]IP!$B$9:$R$116,17,0) -> 0 | Y45: =+K45-O45-P45+Q45+R45+S45+T45+U45+V45+W45 -> #REF! | Z45: =+M45-Y45 -> #REF! | AB45: =VLOOKUP(C45,[2]SINDICATO!$C$7:$Q$141,15,0) -> 0
A46: SEI0100 | B46: SEITON (IP INNOVA II) | C46: Quinto Valle Martin | E46: =VLOOKUP(C46,[1]IP!$B$9:$V$116,21,0) -> 3906.4 | G46: =VLOOKUP(C46,#REF!,4,0) -> #REF! | H46: =VLOOKUP(C46,#REF!,5,0) -> #REF! | I46: =VLOOKUP(C46,#REF!,6,0) -> #REF! | K46: =+D46+E46+G46+H46+I46 -> #REF! | L46: =VLOOKUP(C46,[2]ABC!$A$3:$B$88,2,0) -> 10000 | M46: =+L46/2 -> 5000 | O46: =VLOOKUP(C46,[1]IP!$B$9:$I$116,8,0) -> 0 | P46: =+H46+I46 -> #REF! | Q46: =VLOOKUP(C46,[1]IP!$B$9:$N$116,13,0) -> 0 | R46: =VLOOKUP(C46,[1]IP!$B$9:$O$116,14,0) -> 0 | T46: =VLOOKUP(C46,[1]IP!$B$9:$P$116,15,0) -> 0 | U46: =VLOOKUP(C46,[1]IP!$B$9:$Q$116,16,0) -> 0 | V46: =VLOOKUP(C46,[1]IP!$B$9:$S$116,18,0) -> 500 | W46: =VLOOKUP(C46,[1]IP!$B$9:$R$116,17,0) -> 0 | Y46: =+K46-O46-P46+Q46+R46+S46+T46+U46+V46+W46 -> #REF! | Z46: =+M46-Y46 -> #REF! | AB46: =VLOOKUP(C46,[2]SINDICATO!$C$7:$Q$141,15,0) -> 0
A47: SEI0109 | B47: SEITON (IP INNOVA II) | C47: Negrete Renteria Jose Luis | E47: =VLOOKUP(C47,[1]IP!$B$9:$V$116,21,0) -> 2125.2 | G47: =VLOOKUP(C47,#REF!,4,0) -> #REF! | H47: =VLOOKUP(C47,#REF!,5,0) -> #REF! | I47: =VLOOKUP(C47,#REF!,6,0) -> #REF! | K47: =+D47+E47+G47+H47+I47 -> #REF! | L47: =VLOOKUP(C47,[2]ABC!$A$3:$B$88,2,0) -> 9800 | M47: =+L47/2 -> 4900 | O47: =VLOOKUP(C47,[1]IP!$B$9:$I$116,8,0) -> 0 | P47: =+H47+I47 -> #REF! | Q47: =VLOOKUP(C47,[1]IP!$B$9:$N$116,13,0) -> 1637.48 | R47: =VLOOKUP(C47,[1]IP!$B$9:$O$116,14,0) -> 0 | T47: =VLOOKUP(C47,[1]IP!$B$9:$P$116,15,0) -> 15 | U47: =VLOOKUP(C47,[1]IP!$B$9:$Q$116,16,0) -> 0 | V47: =VLOOKUP(C47,[1]IP!$B$9:$S$116,18,0) -> 0 | W47: =VLOOKUP(C47,[1]IP!$B$9:$R$116,17,0) -> 0 | Y47: =+K47-O47-P47+Q47+R47+S47+T47+U47+V47+W47 -> #REF! | Z47: =+M47-Y47 -> #REF! | AB47: =VLOOKUP(C47,[2]SINDICATO!$C$7:$Q$141,15,0) -> 0
A48: SEI0126 | B48: SEITON (IP INNOVA II) | C48: Alonso Flores Beda | E48: =VLOOKUP(C48,[1]IP!$B$9:$V$116,21,0) -> 4810.8 | G48: =VLOOKUP(C48,#REF!,4,0) -> #REF! | H48: =VLOOKUP(C48,#REF!,5,0) -> #REF! | I48: =VLOOKUP(C48,#REF!,6,0) -> #REF! | K48: =+D48+E48+G48+H48+I48 -> #REF! | L48: 9000 | M48: =+L48/2 -> 4500 | O48: =VLOOKUP(C48,[1]IP!$B$9:$I$116,8,0) -> 307.22 | P48: =+H48+I48 -> #REF! | Q48: =VLOOKUP(C48,[1]IP!$B$9:$N$116,13,0) -> 0 | R48: =VLOOKUP(C48,[1]IP!$B$9:$O$116,14,0) -> 0 | T48: =VLOOKUP(C48,[1]IP!$B$9:$P$116,15,0) -> 0 | U48: =VLOOKUP(C48,[1]IP!$B$9:$Q$116,16,0) -> 0 | V48: =VLOOKUP(C48,[1]IP!$B$9:$S$116,18,0) -> 0 | W48: =VLOOKUP(C48,[1]IP!$B$9:$R$116,17,0) -> 0 | Y48: =+K48-O48-P48+Q48+R48+S48+T48+U48+V48+W48 -> #REF! | Z48: =+M48-Y48 -> #REF! | AA48: 100% IMSS | AB48: =VLOOKUP(C48,[2]SINDICATO!$C$7:$Q$141,15,0) -> 0
A49: SEI0133 | B49: SEITON (IP INNOVA II) | C49: Romero Mayoral Lorenzo | E49: =VLOOKUP(C49,[1]IP!$B$9:$V$116,21,0) -> 2480.2 | G49: =VLOOKUP(C49,#REF!,4,0) -> #REF! | H49: =VLOOKUP(C49,#REF!,5,0) -> #REF! | I49: =VLOOKUP(C49,#REF!,6,0) -> #REF! | K49: =+D49+E49+G49+H49+I49 -> #REF! | L49: =VLOOKUP(C49,[2]ABC!$A$3:$B$88,2,0) -> 11500 | M49: =+L49/2 -> 5750 | O49: =VLOOKUP(C49,[1]IP!$B$9:$I$116,8,0) -> 0 | P49: =+H49+I49 -> #REF! | Q49: =VLOOKUP(C49,[1]IP!$B$9:$N$116,13,0) -> 1088.47 | R49: =VLOOKUP(C49,[1]IP!$B$9:$O$116,14,0) -> 0 | T49: =VLOOKUP(C49,[1]IP!$B$9:$P$116,15,0) -> 15 | U49: =VLOOKUP(C49,[1]IP!$B$9:$Q$116,16,0) -> 0 | V49: =VLOOKUP(C49,[1]IP!$B$9:$S$116,18,0) -> 0 | W49: =VLOOKUP(C49,[1]IP!$B$9:$R$116,17,0) -> 0 | Y49: =+K49-O49-P49+Q49+R49+S49+T49+U49+V49+W49 -> #REF! | Z49: =+M49-Y49 -> #REF! | AB49: =VLOOKUP(C49,[2]SINDICATO!$C$7:$Q$141,15,0) -> 0
A50: SEI0146 | B50: SEITON (IP INNOVA II) | C50: Ramirez Vera Maria Del Carmen | E50: =VLOOKUP(C50,[1]IP!$B$9:$V$116,21,0) -> 2929.8 | G50: =VLOOKUP(C50,#REF!,4,0) -> #REF! | H50: =VLOOKUP(C50,#REF!,5,0) -> #REF! | I50: =VLOOKUP(C50,#REF!,6,0) -> #REF! | K50: =+D50+E50+G50+H50+I50 -> #REF! | L50: =VLOOKUP(C50,[2]ABC!$A$3:$B$88,2,0) -> 10000 | M50: =+L50/2 -> 5000 | O50: =VLOOKUP(C50,[1]IP!$B$9:$I$116,8,0) -> 240 | P50: =+H50+I50 -> #REF! | Q50: =VLOOKUP(C50,[1]IP!$B$9:$N$116,13,0) -> 878.84 | R50: =VLOOKUP(C50,[1]IP!$B$9:$O$116,14,0) -> 0 | T50: =VLOOKUP(C50,[1]IP!$B$9:$P$116,15,0) -> 15 | U50: =VLOOKUP(C50,[1]IP!$B$9:$Q$116,16,0) -> 0 | V50: =VLOOKUP(C50,[1]IP!$B$9:$S$116,18,0) -> 0 | W50: =VLOOKUP(C50,[1]IP!$B$9:$R$116,17,0) -> 0 | Y50: =+K50-O50-P50+Q50+R50+S50+T50+U50+V50+W50 -> #REF! | Z50: =+M50-Y50 -> #REF! | AB50: =VLOOKUP(C50,[2]SINDICATO!$C$7:$Q$141,15,0) -> 0
A51: SEI0230 | B51: SEITON (IP INNOVA II) | C51: Bueno Herrera Mariana Guadalupe | E51: =VLOOKUP(C51,[1]IP!$B$9:$V$116,21,0) -> 3583.6 | G51: =VLOOKUP(C51,#REF!,4,0) -> #REF! | H51: =VLOOKUP(C51,#REF!,5,0) -> #REF! | I51: =VLOOKUP(C51,#REF!,6,0) -> #REF! | K51: =+D51+E51+G51+H51+I51 -> #REF! | L51: 12600 | M51: =+L51/2 -> 6300 | O51: =VLOOKUP(C51,[1]IP!$B$9:$I$116,8,0) -> 0 | P51: =+H51+I51 -> #REF! | Q51: =VLOOKUP(C51,[1]IP!$B$9:$N$116,13,0) -> 0 | R51: =VLOOKUP(C51,[1]IP!$B$9:$O$116,14,0) -> 0 | T51: =VLOOKUP(C51,[1]IP!$B$9:$P$116,15,0) -> 0 | U51: =VLOOKUP(C51,[1]IP!$B$9:$Q$116,16,0) -> 0 | V51: =VLOOKUP(C51,[1]IP!$B$9:$S$116,18,0) -> 0 | W51: =VLOOKUP(C51,[1]IP!$B$9:$R$116,17,0) -> 0 | Y51: =+K51-O51-P51+Q51+R51+S51+T51+U51+V51+W51 -> #REF! | Z51: =+M51-Y51 -> #REF! | AB51: =VLOOKUP(C51,[2]SINDICATO!$C$7:$Q$141,15,0) -> 0
A52: SEI0332 | B52: SEITON (IP INNOVA II) | C52: Lara Campos Maximino | E52: =VLOOKUP(C52,[1]IP!$B$9:$V$116,21,0) -> 4753.8 | G52: =VLOOKUP(C52,#REF!,4,0) -> #REF! | H52: =VLOOKUP(C52,#REF!,5,0) -> #REF! | I52: =VLOOKUP(C52,#REF!,6,0) -> #REF! | K52: =+D52+E52+G52+H52+I52 -> #REF! | L52: =VLOOKUP(C52,[2]ABC!$A$3:$B$88,2,0) -> 9500 | M52: =+L52/2 -> 4750 | O52: =VLOOKUP(C52,[1]IP!$B$9:$I$116,8,0) -> 0 | P52: =+H52+I52 -> #REF! | Q52: =VLOOKUP(C52,[1]IP!$B$9:$N$116,13,0) -> 0 | R52: =VLOOKUP(C52,[1]IP!$B$9:$O$116,14,0) -> 0 | T52: =VLOOKUP(C52,[1]IP!$B$9:$P$116,15,0) -> 0 | U52: =VLOOKUP(C52,[1]IP!$B$9:$Q$116,16,0) -> 0 | V52: =VLOOKUP(C52,[1]IP!$B$9:$S$116,18,0) -> 0 | W52: =VLOOKUP(C52,[1]IP!$B$9:$R$116,17,0) -> 0 | Y52: =+K52-O52-P52+Q52+R52+S52+T52+U52+V52+W52 -> #REF! | Z52: =+M52-Y52 -> #REF! | AA52: 100% IMSS | AB52: =VLOOKUP(C52,[2]SINDICATO!$C$7:$Q$141,15,0) -> 0
A53: SEI0345 | B53: SEITON (IP INNOVA II) | C53: Rodriguez Diaz Cesar Salvador | E53: =VLOOKUP(C53,[1]IP!$B$9:$V$116,21,0) -> 3003.4 | G53: =VLOOKUP(C53,#REF!,4,0) -> #REF! | H53: =VLOOKUP(C53,#REF!,5,0) -> #REF! | I53: =VLOOKUP(C53,#REF!,6,0) -> #REF! | K53: =+D53+E53+G53+H53+I53 -> #REF! | L53: 9050 | M53: =+L53/2 -> 4525 | O53: =VLOOKUP(C53,[1]IP!$B$9:$I$116,8,0) -> 0 | P53: =+H53+I53 -> #REF! | Q53: =VLOOKUP(C53,[1]IP!$B$9:$N$116,13,0) -> 565.24 | R53: =VLOOKUP(C53,[1]IP!$B$9:$O$116,14,0) -> 0 | T53: =VLOOKUP(C53,[1]IP!$B$9:$P$116,15,0) -> 15 | U53: =VLOOKUP(C53,[1]IP!$B$9:$Q$116,16,0) -> 0 | V53: =VLOOKUP(C53,[1]IP!$B$9:$S$116,18,0) -> 0 | W53: =VLOOKUP(C53,[1]IP!$B$9:$R$116,17,0) -> 0 | Y53: =+K53-O53-P53+Q53+R53+S53+T53+U53+V53+W53 -> #REF! | Z53: =+M53-Y53 -> #REF! | AB53: =VLOOKUP(C53,[2]SINDICATO!$C$7:$Q$141,15,0) -> 0
A54: SEI0364 | B54: SEITON (IP INNOVA II) | C54: Dominguez Lopez Mayeli Del Pilar | E54: =VLOOKUP(C54,[1]IP!$B$9:$V$116,21,0) -> 1917 | G54: =VLOOKUP(C54,#REF!,4,0) -> #REF! | H54: =VLOOKUP(C54,#REF!,5,0) -> #REF! | I54: =VLOOKUP(C54,#REF!,6,0) -> #REF! | K54: =+D54+E54+G54+H54+I54 -> #REF! | L54: =VLOOKUP(C54,[2]ABC!$A$3:$B$88,2,0) -> 10000 | M54: =+L54/2 -> 5000 | O54: =VLOOKUP(C54,[1]IP!$B$9:$I$116,8,0) -> 0 | P54: =+H54+I54 -> #REF! | Q54: =VLOOKUP(C54,[1]IP!$B$9:$N$116,13,0) -> 0 | R54: =VLOOKUP(C54,[1]IP!$B$9:$O$116,14,0) -> 0 | T54: =VLOOKUP(C54,[1]IP!$B$9:$P$116,15,0) -> 0 | U54: =VLOOKUP(C54,[1]IP!$B$9:$Q$116,16,0) -> 0 | V54: =VLOOKUP(C54,[1]IP!$B$9:$S$116,18,0) -> 0 | W54: =VLOOKUP(C54,[1]IP!$B$9:$R$116,17,0) -> 1666.67 | Y54: =+K54-O54-P54+Q54+R54+S54+T54+U54+V54+W54 -> #REF! | Z54: =+M54-Y54 -> #REF! | AB54: =VLOOKUP(C54,[2]SINDICATO!$C$7:$Q$141,15,0) -> #N/A
A55: SEI0376 | B55: SEITON (IP INNOVA II) | C55: Marquez Alcaraz Martin | E55: =VLOOKUP(C55,[1]IP!$B$9:$V$116,21,0) -> 2351 | G55: =VLOOKUP(C55,#REF!,4,0) -> #REF! | H55: =VLOOKUP(C55,#REF!,5,0) -> #REF! | I55: =VLOOKUP(C55,#REF!,6,0) -> #REF! | K55: =+D55+E55+G55+H55+I55 -> #REF! | L55: 9050 | M55: =+L55/2 -> 4525 | O55: =VLOOKUP(C55,[1]IP!$B$9:$I$116,8,0) -> 0 | P55: =+H55+I55 -> #REF! | Q55: =VLOOKUP(C55,[1]IP!$B$9:$N$116,13,0) -> 0 | R55: =VLOOKUP(C55,[1]IP!$B$9:$O$116,14,0) -> 1217.6 | T55: =VLOOKUP(C55,[1]IP!$B$9:$P$116,15,0) -> 15 | U55: =VLOOKUP(C55,[1]IP!$B$9:$Q$116,16,0) -> 0 | V55: =VLOOKUP(C55,[1]IP!$B$9:$S$116,18,0) -> 0 | W55: =VLOOKUP(C55,[1]IP!$B$9:$R$116,17,0) -> 0 | Y55: =+K55-O55-P55+Q55+R55+S55+T55+U55+V55+W55 -> #REF! | Z55: =+M55-Y55 -> #REF! | AB55: =VLOOKUP(C55,[2]SINDICATO!$C$7:$Q$141,15,0) -> 0
A56: SEI0412 | B56: SEITON (IP INNOVA II) | C56: Rojo Avelar Adrian | E56: =VLOOKUP(C56,[1]IP!$B$9:$V$116,21,0) -> 1773.8 | G56: =VLOOKUP(C56,#REF!,4,0) -> #REF! | H56: =VLOOKUP(C56,#REF!,5,0) -> #REF! | I56: =VLOOKUP(C56,#REF!,6,0) -> #REF! | K56: =+D56+E56+G56+H56+I56 -> #REF! | L56: =VLOOKUP(C56,[2]ABC!$A$3:$B$88,2,0) -> 7500 | M56: =+L56/2 -> 3750 | O56: =VLOOKUP(C56,[1]IP!$B$9:$I$116,8,0) -> 0 | P56: =+H56+I56 -> #REF! | Q56: =VLOOKUP(C56,[1]IP!$B$9:$N$116,13,0) -> 1075.99 | R56: =VLOOKUP(C56,[1]IP!$B$9:$O$116,14,0) -> 0 | T56: =VLOOKUP(C56,[1]IP!$B$9:$P$116,15,0) -> 15 | U56: =VLOOKUP(C56,[1]IP!$B$9:$Q$116,16,0) -> 0 | V56: =VLOOKUP(C56,[1]IP!$B$9:$S$116,18,0) -> 0 | W56: =VLOOKUP(C56,[1]IP!$B$9:$R$116,17,0) -> 0 | Y56: =+K56-O56-P56+Q56+R56+S56+T56+U56+V56+W56 -> #REF! | Z56: =+M56-Y56 -> #REF! | AB56: =VLOOKUP(C56,[2]SINDICATO!$C$7:$Q$141,15,0) -> 0
A57: SEI0413 | B57: SEITON (IP INNOVA II) | C57: Courtenay Gutierrez Barry Vladimir | E57: =VLOOKUP(C57,[1]IP!$B$9:$V$116,21,0) -> 2447.6 | G57: =VLOOKUP(C57,#REF!,4,0) -> #REF! | H57: =VLOOKUP(C57,#REF!,5,0) -> #REF! | I57: =VLOOKUP(C57,#REF!,6,0) -> #REF! | K57: =+D57+E57+G57+H57+I57 -> #REF! | L57: 5000 | M57: =+L57/2 -> 2500 | O57: =VLOOKUP(C57,[1]IP!$B$9:$I$116,8,0) -> 0 | P57: =+H57+I57 -> #REF! | Q57: =VLOOKUP(C57,[1]IP!$B$9:$N$116,13,0) -> 0 | R57: =VLOOKUP(C57,[1]IP!$B$9:$O$116,14,0) -> 0 | T57: =VLOOKUP(C57,[1]IP!$B$9:$P$116,15,0) -> 0 | U57: =VLOOKUP(C57,[1]IP!$B$9:$Q$116,16,0) -> 0 | V57: =VLOOKUP(C57,[1]IP!$B$9:$S$116,18,0) -> 0 | W57: =VLOOKUP(C57,[1]IP!$B$9:$R$116,17,0) -> 0 | Y57: =+K57-O57-P57+Q57+R57+S57+T57+U57+V57+W57 -> #REF! | Z57: =+M57-Y57 -> #REF! | AB57: =VLOOKUP(C57,[2]SINDICATO!$C$7:$Q$141,15,0) -> #N/A
A58: SEI0421 | B58: SEITON (IP INNOVA II) | C58: Marin Avila Hector | E58: =VLOOKUP(C58,[1]IP!$B$9:$V$116,21,0) -> 3693.2 | G58: =VLOOKUP(C58,#REF!,4,0) -> #REF! | H58: =VLOOKUP(C58,#REF!,5,0) -> #REF! | I58: =VLOOKUP(C58,#REF!,6,0) -> #REF! | K58: =+D58+E58+G58+H58+I58 -> #REF! | L58: 8800 | M58: =+L58/2 -> 4400 | O58: =VLOOKUP(C58,[1]IP!$B$9:$I$116,8,0) -> 0 | P58: =+H58+I58 -> #REF! | Q58: =VLOOKUP(C58,[1]IP!$B$9:$N$116,13,0) -> 0 | R58: =VLOOKUP(C58,[1]IP!$B$9:$O$116,14,0) -> 0 | T58: =VLOOKUP(C58,[1]IP!$B$9:$P$116,15,0) -> 0 | U58: =VLOOKUP(C58,[1]IP!$B$9:$Q$116,16,0) -> 0 | V58: =VLOOKUP(C58,[1]IP!$B$9:$S$116,18,0) -> 0 | W58: =VLOOKUP(C58,[1]IP!$B$9:$R$116,17,0) -> 0 | Y58: =+K58-O58-P58+Q58+R58+S58+T58+U58+V58+W58 -> #REF! | Z58: =+M58-Y58 -> #REF! | AB58: =VLOOKUP(C58,[2]SINDICATO!$C$7:$Q$141,15,0) -> 0
A59: SEI0424 | B59: SEITON (IP INNOVA II) | C59: Palacios Ramos Jesus | E59: =VLOOKUP(C59,[1]IP!$B$9:$V$116,21,0) -> 3583.6 | G59: =VLOOKUP(C59,#REF!,4,0) -> #REF! | H59: =VLOOKUP(C59,#REF!,5,0) -> #REF! | I59: =VLOOKUP(C59,#REF!,6,0) -> #REF! | K59: =+D59+E59+G59+H59+I59 -> #REF! | L59: 8000 | M59: =+L59/2 -> 4000 | O59: =VLOOKUP(C59,[1]IP!$B$9:$I$116,8,0) -> 0 | P59: =+H59+I59 -> #REF! | Q59: =VLOOKUP(C59,[1]IP!$B$9:$N$116,13,0) -> 0 | R59: =VLOOKUP(C59,[1]IP!$B$9:$O$116,14,0) -> 0 | T59: =VLOOKUP(C59,[1]IP!$B$9:$P$116,15,0) -> 0 | U59: =VLOOKUP(C59,[1]IP!$B$9:$Q$116,16,0) -> 0 | V59: =VLOOKUP(C59,[1]IP!$B$9:$S$116,18,0) -> 0 | W59: =VLOOKUP(C59,[1]IP!$B$9:$R$116,17,0) -> 0 | Y59: =+K59-O59-P59+Q59+R59+S59+T59+U59+V59+W59 -> #REF! | Z59: =+M59-Y59 -> #REF! | AB59: =VLOOKUP(C59,[2]SINDICATO!$C$7:$Q$141,15,0) -> #N/A
A60: SEI0428 | B60: SEITON (IP INNOVA II) | C60: Martinez Hernandez J. Antonio | E60: =VLOOKUP(C60,[1]IP!$B$9:$V$116,21,0) -> 3583.8 | G60: =VLOOKUP(C60,#REF!,4,0) -> #REF! | H60: =VLOOKUP(C60,#REF!,5,0) -> #REF! | I60: =VLOOKUP(C60,#REF!,6,0) -> #REF! | K60: =+D60+E60+G60+H60+I60 -> #REF! | L60: 8000 | M60: =+L60/2 -> 4000 | O60: =VLOOKUP(C60,[1]IP!$B$9:$I$116,8,0) -> 0 | P60: =+H60+I60 -> #REF! | Q60: =VLOOKUP(C60,[1]IP!$B$9:$N$116,13,0) -> 0 | R60: =VLOOKUP(C60,[1]IP!$B$9:$O$116,14,0) -> 0 | T60: =VLOOKUP(C60,[1]IP!$B$9:$P$116,15,0) -> 0 | U60: =VLOOKUP(C60,[1]IP!$B$9:$Q$116,16,0) -> 0 | V60: =VLOOKUP(C60,[1]IP!$B$9:$S$116,18,0) -> 0 | W60: =VLOOKUP(C60,[1]IP!$B$9:$R$116,17,0) -> 0 | Y60: =+K60-O60-P60+Q60+R60+S60+T60+U60+V60+W60 -> #REF! | Z60: =+M60-Y60 -> #REF! | AB60: =VLOOKUP(C60,[2]SINDICATO!$C$7:$Q$141,15,0) -> #N/A
A61: SEI0431 | B61: SEITON (IP INNOVA II) | C61: Alcaraz Conde Zabdi Guadalupe | E61: =VLOOKUP(C61,[1]IP!$B$9:$V$116,21,0) -> 1129.4 | G61: =VLOOKUP(C61,#REF!,4,0) -> #REF! | H61: =VLOOKUP(C61,#REF!,5,0) -> #REF! | I61: =VLOOKUP(C61,#REF!,6,0) -> #REF! | K61: =+D61+E61+G61+H61+I61 -> #REF! | L61: 6000 | M61: =+L61/2 -> 3000 | O61: =VLOOKUP(C61,[1]IP!$B$9:$I$116,8,0) -> 0 | P61: =+H61+I61 -> #REF! | Q61: =VLOOKUP(C61,[1]IP!$B$9:$N$116,13,0) -> 0 | R61: =VLOOKUP(C61,[1]IP!$B$9:$O$116,14,0) -> 1120.4 | T61: =VLOOKUP(C61,[1]IP!$B$9:$P$116,15,0) -> 15 | U61: =VLOOKUP(C61,[1]IP!$B$9:$Q$116,16,0) -> 600 | V61: =VLOOKUP(C61,[1]IP!$B$9:$S$116,18,0) -> 0 | W61: =VLOOKUP(C61,[1]IP!$B$9:$R$116,17,0) -> 0 | Y61: =+K61-O61-P61+Q61+R61+S61+T61+U61+V61+W61 -> #REF! | Z61: =+M61-Y61 -> #REF! | AB61: =VLOOKUP(C61,[2]SINDICATO!$C$7:$Q$141,15,0) -> #N/A
A62: SEI0438 | B62: SEITON (IP INNOVA II) | C62: Lopez Terron Roberto Porfirio | E62: =VLOOKUP(C62,[1]IP!$B$9:$V$116,21,0) -> 5952.2 | G62: =VLOOKUP(C62,#REF!,4,0) -> #REF! | H62: =VLOOKUP(C62,#REF!,5,0) -> #REF! | I62: =VLOOKUP(C62,#REF!,6,0) -> #REF! | K62: =+D62+E62+G62+H62+I62 -> #REF! | L62: 14000 | M62: =+L62/2 -> 7000 | O62: =VLOOKUP(C62,[1]IP!$B$9:$I$116,8,0) -> 0 | P62: =+H62+I62 -> #REF! | Q62: =VLOOKUP(C62,[1]IP!$B$9:$N$116,13,0) -> 0 | R62: =VLOOKUP(C62,[1]IP!$B$9:$O$116,14,0) -> 0 | T62: =VLOOKUP(C62,[1]IP!$B$9:$P$116,15,0) -> 0 | U62: =VLOOKUP(C62,[1]IP!$B$9:$Q$116,16,0) -> 0 | V62: =VLOOKUP(C62,[1]IP!$B$9:$S$116,18,0) -> 0 | W62: =VLOOKUP(C62,[1]IP!$B$9:$R$116,17,0) -> 0 | Y62: =+K62-O62-P62+Q62+R62+S62+T62+U62+V62+W62 -> #REF! | Z62: =+M62-Y62 -> #REF! | AB62: =VLOOKUP(C62,[2]SINDICATO!$C$7:$Q$141,15,0) -> #N/A
A63: SEI0442 | B63: SEITON (IP INNOVA II) | C63: Chavez Pedraza Samuel | E63: =VLOOKUP(C63,[1]IP!$B$9:$V$116,21,0) -> 5952.2 | G63: =VLOOKUP(C63,#REF!,4,0) -> #REF! | H63: =VLOOKUP(C63,#REF!,5,0) -> #REF! | I63: =VLOOKUP(C63,#REF!,6,0) -> #REF! | K63: =+D63+E63+G63+H63+I63 -> #REF! | L63: 14000 | M63: =+L63/2 -> 7000 | O63: =VLOOKUP(C63,[1]IP!$B$9:$I$116,8,0) -> 0 | P63: =+H63+I63 -> #REF! | Q63: =VLOOKUP(C63,[1]IP!$B$9:$N$116,13,0) -> 0 | R63: =VLOOKUP(C63,[1]IP!$B$9:$O$116,14,0) -> 0 | T63: =VLOOKUP(C63,[1]IP!$B$9:$P$116,15,0) -> 0 | U63: =VLOOKUP(C63,[1]IP!$B$9:$Q$116,16,0) -> 0 | V63: =VLOOKUP(C63,[1]IP!$B$9:$S$116,18,0) -> 0 | W63: =VLOOKUP(C63,[1]IP!$B$9:$R$116,17,0) -> 0 | Y63: =+K63-O63-P63+Q63+R63+S63+T63+U63+V63+W63 -> #REF! | Z63: =+M63-Y63 -> #REF! | AB63: =VLOOKUP(C63,[2]SINDICATO!$C$7:$Q$141,15,0) -> #N/A
A64: SEI0443 | B64: SEITON (IP INNOVA II) | C64: Castillo Nungaray Nestor Roman | E64: =VLOOKUP(C64,[1]IP!$B$9:$V$116,21,0) -> 2864.8 | G64: =VLOOKUP(C64,#REF!,4,0) -> #REF! | H64: =VLOOKUP(C64,#REF!,5,0) -> #REF! | I64: =VLOOKUP(C64,#REF!,6,0) -> #REF! | K64: =+D64+E64+G64+H64+I64 -> #REF! | L64: 6000 | M64: =+L64/2 -> 3000 | O64: =VLOOKUP(C64,[1]IP!$B$9:$I$116,8,0) -> 0 | P64: =+H64+I64 -> #REF! | Q64: =VLOOKUP(C64,[1]IP!$B$9:$N$116,13,0) -> 0 | R64: =VLOOKUP(C64,[1]IP!$B$9:$O$116,14,0) -> 0 | T64: =VLOOKUP(C64,[1]IP!$B$9:$P$116,15,0) -> 0 | U64: =VLOOKUP(C64,[1]IP!$B$9:$Q$116,16,0) -> 0 | V64: =VLOOKUP(C64,[1]IP!$B$9:$S$116,18,0) -> 0 | W64: =VLOOKUP(C64,[1]IP!$B$9:$R$116,17,0) -> 0 | Y64: =+K64-O64-P64+Q64+R64+S64+T64+U64+V64+W64 -> #REF! | Z64: =+M64-Y64 -> #REF! | AB64: =VLOOKUP(C64,[2]SINDICATO!$C$7:$Q$141,15,0) -> #N/A
A65: SEI0444 | B65: SEITON (IP INNOVA II) | C65: Marquez Hernandez Rogelio | E65: =VLOOKUP(C65,[1]IP!$B$9:$V$116,21,0) -> 3583.6 | G65: =VLOOKUP(C65,#REF!,4,0) -> #REF! | H65: =VLOOKUP(C65,#REF!,5,0) -> #REF! | I65: =VLOOKUP(C65,#REF!,6,0) -> #REF! | K65: =+D65+E65+G65+H65+I65 -> #REF! | L65: 8000 | M65: =+L65/2 -> 4000 | O65: =VLOOKUP(C65,[1]IP!$B$9:$I$116,8,0) -> 0 | P65: =+H65+I65 -> #REF! | Q65: =VLOOKUP(C65,[1]IP!$B$9:$N$116,13,0) -> 0 | R65: =VLOOKUP(C65,[1]IP!$B$9:$O$116,14,0) -> 0 | T65: =VLOOKUP(C65,[1]IP!$B$9:$P$116,15,0) -> 0 | U65: =VLOOKUP(C65,[1]IP!$B$9:$Q$116,16,0) -> 0 | V65: =VLOOKUP(C65,[1]IP!$B$9:$S$116,18,0) -> 0 | W65: =VLOOKUP(C65,[1]IP!$B$9:$R$116,17,0) -> 0 | Y65: =+K65-O65-P65+Q65+R65+S65+T65+U65+V65+W65 -> #REF! | Z65: =+M65-Y65 -> #REF! | AB65: =VLOOKUP(C65,[2]SINDICATO!$C$7:$Q$141,15,0) -> #N/A
A66: SEI0449 | B66: SEITON (IP INNOVA II) | C66: Flores Cerrillos Jorge Humberto | E66: =VLOOKUP(C66,[1]IP!$B$9:$V$116,21,0) -> 3583.6 | G66: =VLOOKUP(C66,#REF!,4,0) -> #REF! | H66: =VLOOKUP(C66,#REF!,5,0) -> #REF! | I66: =VLOOKUP(C66,#REF!,6,0) -> #REF! | K66: =+D66+E66+G66+H66+I66 -> #REF! | L66: 8000 | M66: =+L66/2 -> 4000 | O66: =VLOOKUP(C66,[1]IP!$B$9:$I$116,8,0) -> 0 | P66: =+H66+I66 -> #REF! | Q66: =VLOOKUP(C66,[1]IP!$B$9:$N$116,13,0) -> 0 | R66: =VLOOKUP(C66,[1]IP!$B$9:$O$116,14,0) -> 0 | T66: =VLOOKUP(C66,[1]IP!$B$9:$P$116,15,0) -> 0 | U66: =VLOOKUP(C66,[1]IP!$B$9:$Q$116,16,0) -> 0 | V66: =VLOOKUP(C66,[1]IP!$B$9:$S$116,18,0) -> 0 | W66: =VLOOKUP(C66,[1]IP!$B$9:$R$116,17,0) -> 0 | Y66: =+K66-O66-P66+Q66+R66+S66+T66+U66+V66+W66 -> #REF! | Z66: =+M66-Y66 -> #REF! | AB66: =VLOOKUP(C66,[2]SINDICATO!$C$7:$Q$141,15,0) -> #N/A
A67: SEI0451 | B67: SEITON (IP INNOVA II) | C67: Hurtado Avalos J.jesus | E67: =VLOOKUP(C67,[1]IP!$B$9:$V$116,21,0) -> 2864.6 | G67: =VLOOKUP(C67,#REF!,4,0) -> #REF! | H67: =VLOOKUP(C67,#REF!,5,0) -> #REF! | I67: =VLOOKUP(C67,#REF!,6,0) -> #REF! | K67: =+D67+E67+G67+H67+I67 -> #REF! | L67: 6000 | M67: =+L67/2 -> 3000 | O67: =VLOOKUP(C67,[1]IP!$B$9:$I$116,8,0) -> 0 | P67: =+H67+I67 -> #REF! | Q67: =VLOOKUP(C67,[1]IP!$B$9:$N$116,13,0) -> 0 | R67: =VLOOKUP(C67,[1]IP!$B$9:$O$116,14,0) -> 0 | T67: =VLOOKUP(C67,[1]IP!$B$9:$P$116,15,0) -> 0 | U67: =VLOOKUP(C67,[1]IP!$B$9:$Q$116,16,0) -> 0 | V67: =VLOOKUP(C67,[1]IP!$B$9:$S$116,18,0) -> 0 | W67: =VLOOKUP(C67,[1]IP!$B$9:$R$116,17,0) -> 0 | Y67: =+K67-O67-P67+Q67+R67+S67+T67+U67+V67+W67 -> #REF! | Z67: =+M67-Y67 -> #REF! | AB67: =VLOOKUP(C67,[2]SINDICATO!$C$7:$Q$141,15,0) -> 0
A68: SEI0453 | B68: SEITON (IP INNOVA II) | C68: Mora Cavazos Roberto Manuel | E68: =VLOOKUP(C68,[1]IP!$B$9:$V$116,21,0) -> 3583.8 | G68: =VLOOKUP(C68,#REF!,4,0) -> #REF! | H68: =VLOOKUP(C68,#REF!,5,0) -> #REF! | I68: =VLOOKUP(C68,#REF!,6,0) -> #REF! | K68: =+D68+E68+G68+H68+I68 -> #REF! | L68: 8000 | M68: =+L68/2 -> 4000 | O68: =VLOOKUP(C68,[1]IP!$B$9:$I$116,8,0) -> 0 | P68: =+H68+I68 -> #REF! | Q68: =VLOOKUP(C68,[1]IP!$B$9:$N$116,13,0) -> 0 | R68: =VLOOKUP(C68,[1]IP!$B$9:$O$116,14,0) -> 0 | T68: =VLOOKUP(C68,[1]IP!$B$9:$P$116,15,0) -> 0 | U68: =VLOOKUP(C68,[1]IP!$B$9:$Q$116,16,0) -> 0 | V68: =VLOOKUP(C68,[1]IP!$B$9:$S$116,18,0) -> 0 | W68: =VLOOKUP(C68,[1]IP!$B$9:$R$116,17,0) -> 0 | Y68: =+K68-O68-P68+Q68+R68+S68+T68+U68+V68+W68 -> #REF! | Z68: =+M68-Y68 -> #REF! | AB68: =VLOOKUP(C68,[2]SINDICATO!$C$7:$Q$141,15,0) -> 0
A69: SEI0454 | B69: SEITON (IP INNOVA II) | C69: Martinez Rivera Maria Teresa | E69: =VLOOKUP(C69,[1]IP!$B$9:$V$116,21,0) -> 4503.4 | G69: =VLOOKUP(C69,#REF!,4,0) -> #REF! | H69: =VLOOKUP(C69,#REF!,5,0) -> #REF! | I69: =VLOOKUP(C69,#REF!,6,0) -> #REF! | K69: =+D69+E69+G69+H69+I69 -> #REF! | L69: 9000 | M69: =+L69/2 -> 4500 | O69: =VLOOKUP(C69,[1]IP!$B$9:$I$116,8,0) -> 0 | P69: =+H69+I69 -> #REF! | Q69: =VLOOKUP(C69,[1]IP!$B$9:$N$116,13,0) -> 0 | R69: =VLOOKUP(C69,[1]IP!$B$9:$O$116,14,0) -> 0 | T69: =VLOOKUP(C69,[1]IP!$B$9:$P$116,15,0) -> 0 | U69: =VLOOKUP(C69,[1]IP!$B$9:$Q$116,16,0) -> 0 | V69: =VLOOKUP(C69,[1]IP!$B$9:$S$116,18,0) -> 0 | W69: =VLOOKUP(C69,[1]IP!$B$9:$R$116,17,0) -> 0 | Y69: =+K69-O69-P69+Q69+R69+S69+T69+U69+V69+W69 -> #REF! | Z69: =+M69-Y69 -> #REF! | AA69: 100% IMSS | AB69: =VLOOKUP(C69,[2]SINDICATO!$C$7:$Q$141,15,0) -> 0
A70: SEI0455 | B70: SEITON (IP INNOVA II) | C70: Perez Garcia Andres Alvaro | E70: =VLOOKUP(C70,[1]IP!$B$9:$V$116,21,0) -> 3583.6 | G70: =VLOOKUP(C70,#REF!,4,0) -> #REF! | H70: =VLOOKUP(C70,#REF!,5,0) -> #REF! | I70: =VLOOKUP(C70,#REF!,6,0) -> #REF! | K70: =+D70+E70+G70+H70+I70 -> #REF! | L70: 8000 | M70: =+L70/2 -> 4000 | O70: =VLOOKUP(C70,[1]IP!$B$9:$I$116,8,0) -> 0 | P70: =+H70+I70 -> #REF! | Q70: =VLOOKUP(C70,[1]IP!$B$9:$N$116,13,0) -> 0 | R70: =VLOOKUP(C70,[1]IP!$B$9:$O$116,14,0) -> 0 | T70: =VLOOKUP(C70,[1]IP!$B$9:$P$116,15,0) -> 0 | U70: =VLOOKUP(C70,[1]IP!$B$9:$Q$116,16,0) -> 0 | V70: =VLOOKUP(C70,[1]IP!$B$9:$S$116,18,0) -> 0 | W70: =VLOOKUP(C70,[1]IP!$B$9:$R$116,17,0) -> 0 | Y70: =+K70-O70-P70+Q70+R70+S70+T70+U70+V70+W70 -> #REF! | Z70: =+M70-Y70 -> #REF! | AB70: =VLOOKUP(C70,[2]SINDICATO!$C$7:$Q$141,15,0) -> #N/A
A71: SEI0456 | B71: SEITON (IP INNOVA II) | C71: Chavira Garcia David Fernando | E71: =VLOOKUP(C71,[1]IP!$B$9:$V$116,21,0) -> 4406.4 | G71: =VLOOKUP(C71,#REF!,4,0) -> #REF! | H71: =VLOOKUP(C71,#REF!,5,0) -> #REF! | I71: =VLOOKUP(C71,#REF!,6,0) -> #REF! | K71: =+D71+E71+G71+H71+I71 -> #REF! | L71: 10000 | M71: =+L71/2 -> 5000 | O71: =VLOOKUP(C71,[1]IP!$B$9:$I$116,8,0) -> 0 | P71: =+H71+I71 -> #REF! | Q71: =VLOOKUP(C71,[1]IP!$B$9:$N$116,13,0) -> 0 | R71: =VLOOKUP(C71,[1]IP!$B$9:$O$116,14,0) -> 0 | T71: =VLOOKUP(C71,[1]IP!$B$9:$P$116,15,0) -> 0 | U71: =VLOOKUP(C71,[1]IP!$B$9:$Q$116,16,0) -> 0 | V71: =VLOOKUP(C71,[1]IP!$B$9:$S$116,18,0) -> 0 | W71: =VLOOKUP(C71,[1]IP!$B$9:$R$116,17,0) -> 0 | Y71: =+K71-O71-P71+Q71+R71+S71+T71+U71+V71+W71 -> #REF! | Z71: =+M71-Y71 -> #REF! | AB71: =VLOOKUP(C71,[2]SINDICATO!$C$7:$Q$141,15,0) -> #N/A
A72: SEI0457 | B72: SEITON (IP INNOVA II) | C72: Guerrero Lara Cesar Adrian | E72: =VLOOKUP(C72,[1]IP!$B$9:$V$116,21,0) -> 3238.4 | G72: =VLOOKUP(C72,#REF!,4,0) -> #REF! | H72: =VLOOKUP(C72,#REF!,5,0) -> #REF! | I72: =VLOOKUP(C72,#REF!,6,0) -> #REF! | K72: =+D72+E72+G72+H72+I72 -> #REF! | L72: 8000 | M72: =+L72/2 -> 4000 | O72: =VLOOKUP(C72,[1]IP!$B$9:$I$116,8,0) -> 0 | P72: =+H72+I72 -> #REF! | Q72: =VLOOKUP(C72,[1]IP!$B$9:$N$116,13,0) -> 0 | R72: =VLOOKUP(C72,[1]IP!$B$9:$O$116,14,0) -> 0 | T72: =VLOOKUP(C72,[1]IP!$B$9:$P$116,15,0) -> 0 | U72: =VLOOKUP(C72,[1]IP!$B$9:$Q$116,16,0) -> 0 | V72: =VLOOKUP(C72,[1]IP!$B$9:$S$116,18,0) -> 0 | W72: =VLOOKUP(C72,[1]IP!$B$9:$R$116,17,0) -> 345.25 | Y72: =+K72-O72-P72+Q72+R72+S72+T72+U72+V72+W72 -> #REF! | Z72: =+M72-Y72 -> #REF! | AB72: =VLOOKUP(C72,[2]SINDICATO!$C$7:$Q$141,15,0) -> #N/A
A73: SEI0458 | B73: SEITON (IP INNOVA II) | C73: Martinez Zamora Gerardo Mario | E73: =VLOOKUP(C73,[1]IP!$B$9:$V$116,21,0) -> 2681.6 | G73: =VLOOKUP(C73,#REF!,4,0) -> #REF! | H73: =VLOOKUP(C73,#REF!,5,0) -> #REF! | I73: =VLOOKUP(C73,#REF!,6,0) -> #REF! | K73: =+D73+E73+G73+H73+I73 -> #REF! | L73: 9550.01 | M73: =+L73/2 -> 4775.005 | O73: =VLOOKUP(C73,[1]IP!$B$9:$I$116,8,0) -> 0 | P73: =+H73+I73 -> #REF! | Q73: =VLOOKUP(C73,[1]IP!$B$9:$N$116,13,0) -> 1528.5 | R73: =VLOOKUP(C73,[1]IP!$B$9:$O$116,14,0) -> 0 | T73: =VLOOKUP(C73,[1]IP!$B$9:$P$116,15,0) -> 15 | U73: =VLOOKUP(C73,[1]IP!$B$9:$Q$116,16,0) -> 0 | V73: =VLOOKUP(C73,[1]IP!$B$9:$S$116,18,0) -> 0 | W73: =VLOOKUP(C73,[1]IP!$B$9:$R$116,17,0) -> 0 | Y73: =+K73-O73-P73+Q73+R73+S73+T73+U73+V73+W73 -> #REF! | Z73: =+M73-Y73 -> #REF! | AB73: =VLOOKUP(C73,[2]SINDICATO!$C$7:$Q$141,15,0) -> #N/A
A74: SEI0460 | B74: SEITON (IP INNOVA II) | C74: Castellon Ramos Rene | E74: =VLOOKUP(C74,[1]IP!$B$9:$V$116,21,0) -> 1157.8 | G74: =VLOOKUP(C74,#REF!,4,0) -> #REF! | H74: =VLOOKUP(C74,#REF!,5,0) -> #REF! | I74: =VLOOKUP(C74,#REF!,6,0) -> #REF! | K74: =+D74+E74+G74+H74+I74 -> #REF! | L74: 7505.99 | M74: =+L74/2 -> 3752.995 | O74: =VLOOKUP(C74,[1]IP!$B$9:$I$116,8,0) -> 0 | P74: =+H74+I74 -> #REF! | Q74: =VLOOKUP(C74,[1]IP!$B$9:$N$116,13,0) -> 0 | R74: =VLOOKUP(C74,[1]IP!$B$9:$O$116,14,0) -> 1346.54 | T74: =VLOOKUP(C74,[1]IP!$B$9:$P$116,15,0) -> 15 | U74: =VLOOKUP(C74,[1]IP!$B$9:$Q$116,16,0) -> 0 | V74: =VLOOKUP(C74,[1]IP!$B$9:$S$116,18,0) -> 0 | W74: =VLOOKUP(C74,[1]IP!$B$9:$R$116,17,0) -> 848.88 | Y74: =+K74-O74-P74+Q74+R74+S74+T74+U74+V74+W74 -> #REF! | Z74: =+M74-Y74 -> #REF! | AB74: =VLOOKUP(C74,[2]SINDICATO!$C$7:$Q$141,15,0) -> #N/A
A75: SEI0461 | B75: SEITON (IP INNOVA II) | C75: Flores Franco Marco | E75: =VLOOKUP(C75,[1]IP!$B$9:$V$116,21,0) -> 3799 | G75: =VLOOKUP(C75,#REF!,4,0) -> #REF! | H75: =VLOOKUP(C75,#REF!,5,0) -> #REF! | I75: =VLOOKUP(C75,#REF!,6,0) -> #REF! | K75: =+D75+E75+G75+H75+I75 -> #REF! | L75: 8500.01 | M75: =+L75/2 -> 4250.005 | O75: =VLOOKUP(C75,[1]IP!$B$9:$I$116,8,0) -> 0 | P75: =+H75+I75 -> #REF! | Q75: =VLOOKUP(C75,[1]IP!$B$9:$N$116,13,0) -> 0 | R75: =VLOOKUP(C75,[1]IP!$B$9:$O$116,14,0) -> 0 | T75: =VLOOKUP(C75,[1]IP!$B$9:$P$116,15,0) -> 0 | U75: =VLOOKUP(C75,[1]IP!$B$9:$Q$116,16,0) -> 0 | V75: =VLOOKUP(C75,[1]IP!$B$9:$S$116,18,0) -> 0 | W75: =VLOOKUP(C75,[1]IP!$B$9:$R$116,17,0) -> 0 | Y75: =+K75-O75-P75+Q75+R75+S75+T75+U75+V75+W75 -> #REF! | Z75: =+M75-Y75 -> #REF! | AB75: =VLOOKUP(C75,[2]SINDICATO!$C$7:$Q$141,15,0) -> #N/A
A76: SEI0462 | B76: SEITON (IP INNOVA II) | C76: Chavez Saucedo Jorge Arturo | E76: =VLOOKUP(C76,[1]IP!$B$9:$V$116,21,0) -> 3585.4 | G76: =VLOOKUP(C76,#REF!,4,0) -> #REF! | H76: =VLOOKUP(C76,#REF!,5,0) -> #REF! | I76: =VLOOKUP(C76,#REF!,6,0) -> #REF! | K76: =+D76+E76+G76+H76+I76 -> #REF! | L76: 8000 | M76: =+L76/2 -> 4000 | O76: =VLOOKUP(C76,[1]IP!$B$9:$I$116,8,0) -> 0 | P76: =+H76+I76 -> #REF! | Q76: =VLOOKUP(C76,[1]IP!$B$9:$N$116,13,0) -> 0 | R76: =VLOOKUP(C76,[1]IP!$B$9:$O$116,14,0) -> 0 | T76: =VLOOKUP(C76,[1]IP!$B$9:$P$116,15,0) -> 0 | U76: =VLOOKUP(C76,[1]IP!$B$9:$Q$116,16,0) -> 0 | V76: =VLOOKUP(C76,[1]IP!$B$9:$S$116,18,0) -> 0 | W76: =VLOOKUP(C76,[1]IP!$B$9:$R$116,17,0) -> 0 | Y76: =+K76-O76-P76+Q76+R76+S76+T76+U76+V76+W76 -> #REF! | Z76: =+M76-Y76 -> #REF! | AB76: =VLOOKUP(C76,[2]SINDICATO!$C$7:$Q$141,15,0) -> #N/A
A77: SEI0464 | B77: SEITON (IP INNOVA II) | C77: Hueramo Hueramo Jesus Daniel | E77: =VLOOKUP(C77,[1]IP!$B$9:$V$116,21,0) -> 2869 | G77: =VLOOKUP(C77,#REF!,4,0) -> #REF! | H77: =VLOOKUP(C77,#REF!,5,0) -> #REF! | I77: =VLOOKUP(C77,#REF!,6,0) -> #REF! | K77: =+D77+E77+G77+H77+I77 -> #REF! | L77: 8500.01 | M77: =+L77/2 -> 4250.005 | O77: =VLOOKUP(C77,[1]IP!$B$9:$I$116,8,0) -> 0 | P77: =+H77+I77 -> #REF! | Q77: =VLOOKUP(C77,[1]IP!$B$9:$N$116,13,0) -> 0 | R77: =VLOOKUP(C77,[1]IP!$B$9:$O$116,14,0) -> 592.54 | T77: =VLOOKUP(C77,[1]IP!$B$9:$P$116,15,0) -> 15 | U77: =VLOOKUP(C77,[1]IP!$B$9:$Q$116,16,0) -> 0 | V77: =VLOOKUP(C77,[1]IP!$B$9:$S$116,18,0) -> 0 | W77: =VLOOKUP(C77,[1]IP!$B$9:$R$116,17,0) -> 322.5 | Y77: =+K77-O77-P77+Q77+R77+S77+T77+U77+V77+W77 -> #REF! | Z77: =+M77-Y77 -> #REF! | AB77: =VLOOKUP(C77,[2]SINDICATO!$C$7:$Q$141,15,0) -> #N/A
A78: SEI0465 | B78: SEITON (IP INNOVA II) | C78: Sandoval Garcia Luis | E78: =VLOOKUP(C78,[1]IP!$B$9:$V$116,21,0) -> 3583.6 | G78: =VLOOKUP(C78,#REF!,4,0) -> #REF! | H78: =VLOOKUP(C78,#REF!,5,0) -> #REF! | I78: =VLOOKUP(C78,#REF!,6,0) -> #REF! | K78: =+D78+E78+G78+H78+I78 -> #REF! | L78: 8000 | M78: =+L78/2 -> 4000 | O78: =VLOOKUP(C78,[1]IP!$B$9:$I$116,8,0) -> 0 | P78: =+H78+I78 -> #REF! | Q78: =VLOOKUP(C78,[1]IP!$B$9:$N$116,13,0) -> 0 | R78: =VLOOKUP(C78,[1]IP!$B$9:$O$116,14,0) -> 0 | T78: =VLOOKUP(C78,[1]IP!$B$9:$P$116,15,0) -> 0 | U78: =VLOOKUP(C78,[1]IP!$B$9:$Q$116,16,0) -> 0 | V78: =VLOOKUP(C78,[1]IP!$B$9:$S$116,18,0) -> 0 | W78: =VLOOKUP(C78,[1]IP!$B$9:$R$116,17,0) -> 0 | Y78: =+K78-O78-P78+Q78+R78+S78+T78+U78+V78+W78 -> #REF! | Z78: =+M78-Y78 -> #REF! | AB78: =VLOOKUP(C78,[2]SINDICATO!$C$7:$Q$141,15,0) -> #N/A
A79: SEI0467 | B79: SEITON (IP INNOVA II) | C79: Vaca Valdez Guillermo | E79: =VLOOKUP(C79,[1]IP!$B$9:$V$116,21,0) -> 1320.4 | G79: =VLOOKUP(C79,#REF!,4,0) -> #REF! | H79: =VLOOKUP(C79,#REF!,5,0) -> #REF! | I79: =VLOOKUP(C79,#REF!,6,0) -> #REF! | K79: =+D79+E79+G79+H79+I79 -> #REF! | L79: 8000 | M79: =+L79/2 -> 4000 | O79: =VLOOKUP(C79,[1]IP!$B$9:$I$116,8,0) -> 0 | P79: =+H79+I79 -> #REF! | Q79: =VLOOKUP(C79,[1]IP!$B$9:$N$116,13,0) -> 1848.35 | R79: =VLOOKUP(C79,[1]IP!$B$9:$O$116,14,0) -> 0 | T79: =VLOOKUP(C79,[1]IP!$B$9:$P$116,15,0) -> 15 | U79: =VLOOKUP(C79,[1]IP!$B$9:$Q$116,16,0) -> 0 | V79: =VLOOKUP(C79,[1]IP!$B$9:$S$116,18,0) -> 0 | W79: =VLOOKUP(C79,[1]IP!$B$9:$R$116,17,0) -> 400 | Y79: =+K79-O79-P79+Q79+R79+S79+T79+U79+V79+W79 -> #REF! | Z79: =+M79-Y79 -> #REF! | AB79: =VLOOKUP(C79,[2]SINDICATO!$C$7:$Q$141,15,0) -> #N/A
A80: SEI0468 | B80: SEITON (IP INNOVA II) | C80: Ramirez Vera Eustolia | E80: =VLOOKUP(C80,[1]IP!$B$9:$V$116,21,0) -> 3561.4 | G80: =VLOOKUP(C80,#REF!,4,0) -> #REF! | H80: =VLOOKUP(C80,#REF!,5,0) -> #REF! | I80: =VLOOKUP(C80,#REF!,6,0) -> #REF! | K80: =+D80+E80+G80+H80+I80 -> #REF! | L80: 7900 | M80: =+L80/2 -> 3950 | O80: =VLOOKUP(C80,[1]IP!$B$9:$I$116,8,0) -> 0 | P80: =+H80+I80 -> #REF! | Q80: =VLOOKUP(C80,[1]IP!$B$9:$N$116,13,0) -> 428.6 | R80: =VLOOKUP(C80,[1]IP!$B$9:$O$116,14,0) -> 0 | T80: =VLOOKUP(C80,[1]IP!$B$9:$P$116,15,0) -> 15 | U80: =VLOOKUP(C80,[1]IP!$B$9:$Q$116,16,0) -> 0 | V80: =VLOOKUP(C80,[1]IP!$B$9:$S$116,18,0) -> 0 | W80: =VLOOKUP(C80,[1]IP!$B$9:$R$116,17,0) -> 0 | Y80: =+K80-O80-P80+Q80+R80+S80+T80+U80+V80+W80 -> #REF! | Z80: =+M80-Y80 -> #REF! | AA80: subsidio | AB80: =VLOOKUP(C80,[2]SINDICATO!$C$7:$Q$141,15,0) -> 0
A81: SEI0469 | B81: SEITON (IP INNOVA II) | C81: Martinez Morales Jose Martin | E81: =VLOOKUP(C81,[1]IP!$B$9:$V$116,21,0) -> 5952.2 | G81: =VLOOKUP(C81,#REF!,4,0) -> #REF! | H81: =VLOOKUP(C81,#REF!,5,0) -> #REF! | I81: =VLOOKUP(C81,#REF!,6,0) -> #REF! | K81: =+D81+E81+G81+H81+I81 -> #REF! | L81: 14000 | M81: =+L81/2 -> 7000 | O81: =VLOOKUP(C81,[1]IP!$B$9:$I$116,8,0) -> 0 | P81: =+H81+I81 -> #REF! | Q81: =VLOOKUP(C81,[1]IP!$B$9:$N$116,13,0) -> 0 | R81: =VLOOKUP(C81,[1]IP!$B$9:$O$116,14,0) -> 0 | T81: =VLOOKUP(C81,[1]IP!$B$9:$P$116,15,0) -> 0 | U81: =VLOOKUP(C81,[1]IP!$B$9:$Q$116,16,0) -> 0 | V81: =VLOOKUP(C81,[1]IP!$B$9:$S$116,18,0) -> 0 | W81: =VLOOKUP(C81,[1]IP!$B$9:$R$116,17,0) -> 0 | Y81: =+K81-O81-P81+Q81+R81+S81+T81+U81+V81+W81 -> #REF! | Z81: =+M81-Y81 -> #REF! | AB81: =VLOOKUP(C81,[2]SINDICATO!$C$7:$Q$141,15,0) -> #N/A
A82: SEI0472 | B82: SEITON (IP INNOVA II) | C82: Arzate Gil Juan Sebastian | E82: =VLOOKUP(C82,[1]IP!$B$9:$V$116,21,0) -> 2895 | G82: =VLOOKUP(C82,#REF!,4,0) -> #REF! | H82: =VLOOKUP(C82,#REF!,5,0) -> #REF! | I82: =VLOOKUP(C82,#REF!,6,0) -> #REF! | K82: =+D82+E82+G82+H82+I82 -> #REF! | L82: 8000 | M82: =+L82/2 -> 4000 | O82: =VLOOKUP(C82,[1]IP!$B$9:$I$116,8,0) -> 0 | P82: =+H82+I82 -> #REF! | Q82: =VLOOKUP(C82,[1]IP!$B$9:$N$116,13,0) -> 0 | R82: =VLOOKUP(C82,[1]IP!$B$9:$O$116,14,0) -> 0 | T82: =VLOOKUP(C82,[1]IP!$B$9:$P$116,15,0) -> 0 | U82: =VLOOKUP(C82,[1]IP!$B$9:$Q$116,16,0) -> 0 | V82: =VLOOKUP(C82,[1]IP!$B$9:$S$116,18,0) -> 0 | W82: =VLOOKUP(C82,[1]IP!$B$9:$R$116,17,0) -> 688.8 | Y82: =+K82-O82-P82+Q82+R82+S82+T82+U82+V82+W82 -> #REF! | Z82: =+M82-Y82 -> #REF! | AB82: =VLOOKUP(C82,[2]SINDICATO!$C$7:$Q$141,15,0) -> #N/A
A83: SEI0473 | B83: SEITON (IP INNOVA II) | C83: Torres Velazquez Juan Antonio | E83: =VLOOKUP(C83,[1]IP!$B$9:$V$116,21,0) -> 3583.6 | G83: =VLOOKUP(C83,#REF!,4,0) -> #REF! | H83: =VLOOKUP(C83,#REF!,5,0) -> #REF! | I83: =VLOOKUP(C83,#REF!,6,0) -> #REF! | K83: =+D83+E83+G83+H83+I83 -> #REF! | L83: 8000 | M83: =+L83/2 -> 4000 | O83: =VLOOKUP(C83,[1]IP!$B$9:$I$116,8,0) -> 0 | P83: =+H83+I83 -> #REF! | Q83: =VLOOKUP(C83,[1]IP!$B$9:$N$116,13,0) -> 0 | R83: =VLOOKUP(C83,[1]IP!$B$9:$O$116,14,0) -> 0 | T83: =VLOOKUP(C83,[1]IP!$B$9:$P$116,15,0) -> 0 | U83: =VLOOKUP(C83,[1]IP!$B$9:$Q$116,16,0) -> 0 | V83: =VLOOKUP(C83,[1]IP!$B$9:$S$116,18,0) -> 0 | W83: =VLOOKUP(C83,[1]IP!$B$9:$R$116,17,0) -> 0 | Y83: =+K83-O83-P83+Q83+R83+S83+T83+U83+V83+W83 -> #REF! | Z83: =+M83-Y83 -> #REF! | AB83: =VLOOKUP(C83,[2]SINDICATO!$C$7:$Q$141,15,0) -> #N/A
A84: SEI0474 | B84: SEITON (IP INNOVA II) | C84: Enriquez Zamora Jessica Del Rocio | E84: =VLOOKUP(C84,[1]IP!$B$9:$V$116,21,0) -> 2864.8 | G84: =VLOOKUP(C84,#REF!,4,0) -> #REF! | H84: =VLOOKUP(C84,#REF!,5,0) -> #REF! | I84: =VLOOKUP(C84,#REF!,6,0) -> #REF! | K84: =+D84+E84+G84+H84+I84 -> #REF! | L84: 6000 | M84: =+L84/2 -> 3000 | O84: =VLOOKUP(C84,[1]IP!$B$9:$I$116,8,0) -> 0 | P84: =+H84+I84 -> #REF! | Q84: =VLOOKUP(C84,[1]IP!$B$9:$N$116,13,0) -> 0 | R84: =VLOOKUP(C84,[1]IP!$B$9:$O$116,14,0) -> 0 | T84: =VLOOKUP(C84,[1]IP!$B$9:$P$116,15,0) -> 0 | U84: =VLOOKUP(C84,[1]IP!$B$9:$Q$116,16,0) -> 0 | V84: =VLOOKUP(C84,[1]IP!$B$9:$S$116,18,0) -> 0 | W84: =VLOOKUP(C84,[1]IP!$B$9:$R$116,17,0) -> 0 | Y84: =+K84-O84-P84+Q84+R84+S84+T84+U84+V84+W84 -> #REF! | AB84: =VLOOKUP(C84,[2]SINDICATO!$C$7:$Q$141,15,0) -> #N/A
A85: SEI0475 | B85: SEITON (IP INNOVA II) | C85: Moreno Quiroga Ana Sarahi | E85: =VLOOKUP(C85,[1]IP!$B$9:$V$116,21,0) -> 3583.8 | G85: =VLOOKUP(C85,#REF!,4,0) -> #REF! | H85: =VLOOKUP(C85,#REF!,5,0) -> #REF! | I85: =VLOOKUP(C85,#REF!,6,0) -> #REF! | K85: =+D85+E85+G85+H85+I85 -> #REF! | L85: 8000 | M85: =+L85/2 -> 4000 | O85: =VLOOKUP(C85,[1]IP!$B$9:$I$116,8,0) -> 0 | P85: =+H85+I85 -> #REF! | Q85: =VLOOKUP(C85,[1]IP!$B$9:$N$116,13,0) -> 0 | R85: =VLOOKUP(C85,[1]IP!$B$9:$O$116,14,0) -> 0 | T85: =VLOOKUP(C85,[1]IP!$B$9:$P$116,15,0) -> 0 | U85: =VLOOKUP(C85,[1]IP!$B$9:$Q$116,16,0) -> 0 | V85: =VLOOKUP(C85,[1]IP!$B$9:$S$116,18,0) -> 0 | W85: =VLOOKUP(C85,[1]IP!$B$9:$R$116,17,0) -> 0 | Y85: =+K85-O85-P85+Q85+R85+S85+T85+U85+V85+W85 -> #REF! | Z85: =+M85-Y85 -> #REF! | AB85: =VLOOKUP(C85,[2]SINDICATO!$C$7:$Q$141,15,0) -> #N/A
A86: SEI0476 | B86: SEITON (IP INNOVA II) | C86: Hernandez Garcia Manuel Alejandro | E86: =VLOOKUP(C86,[1]IP!$B$9:$V$116,21,0) -> 3585.4 | G86: =VLOOKUP(C86,#REF!,4,0) -> #REF! | H86: =VLOOKUP(C86,#REF!,5,0) -> #REF! | I86: =VLOOKUP(C86,#REF!,6,0) -> #REF! | K86: =+D86+E86+G86+H86+I86 -> #REF! | L86: 8000 | M86: =+L86/2 -> 4000 | O86: =VLOOKUP(C86,[1]IP!$B$9:$I$116,8,0) -> 0 | P86: =+H86+I86 -> #REF! | Q86: =VLOOKUP(C86,[1]IP!$B$9:$N$116,13,0) -> 0 | R86: =VLOOKUP(C86,[1]IP!$B$9:$O$116,14,0) -> 0 | T86: =VLOOKUP(C86,[1]IP!$B$9:$P$116,15,0) -> 0 | U86: =VLOOKUP(C86,[1]IP!$B$9:$Q$116,16,0) -> 0 | V86: =VLOOKUP(C86,[1]IP!$B$9:$S$116,18,0) -> 0 | W86: =VLOOKUP(C86,[1]IP!$B$9:$R$116,17,0) -> 0 | Y86: =+K86-O86-P86+Q86+R86+S86+T86+U86+V86+W86 -> #REF! | Z86: =+M86-Y86 -> #REF! | AB86: =VLOOKUP(C86,[2]SINDICATO!$C$7:$Q$141,15,0) -> #N/A
A87: SEI0477 | B87: SEITON (IP INNOVA II) | C87: Sandoval Medina Demetrio | E87: =VLOOKUP(C87,[1]IP!$B$9:$V$116,21,0) -> 3585.4 | G87: =VLOOKUP(C87,#REF!,4,0) -> #REF! | H87: =VLOOKUP(C87,#REF!,5,0) -> #REF! | I87: =VLOOKUP(C87,#REF!,6,0) -> #REF! | K87: =+D87+E87+G87+H87+I87 -> #REF! | L87: 8000 | M87: =+L87/2 -> 4000 | O87: =VLOOKUP(C87,[1]IP!$B$9:$I$116,8,0) -> 0 | P87: =+H87+I87 -> #REF! | Q87: =VLOOKUP(C87,[1]IP!$B$9:$N$116,13,0) -> 0 | R87: =VLOOKUP(C87,[1]IP!$B$9:$O$116,14,0) -> 0 | T87: =VLOOKUP(C87,[1]IP!$B$9:$P$116,15,0) -> 0 | U87: =VLOOKUP(C87,[1]IP!$B$9:$Q$116,16,0) -> 0 | V87: =VLOOKUP(C87,[1]IP!$B$9:$S$116,18,0) -> 0 | W87: =VLOOKUP(C87,[1]IP!$B$9:$R$116,17,0) -> 0 | Y87: =+K87-O87-P87+Q87+R87+S87+T87+U87+V87+W87 -> #REF! | Z87: =+M87-Y87 -> #REF! | AB87: =VLOOKUP(C87,[2]SINDICATO!$C$7:$Q$141,15,0) -> #N/A
A88: SEI0478 | B88: SEITON (IP INNOVA II) | C88: Leal Montaño Francisco | E88: =VLOOKUP(C88,[1]IP!$B$9:$V$116,21,0) -> 1831 | G88: =VLOOKUP(C88,#REF!,4,0) -> #REF! | H88: =VLOOKUP(C88,#REF!,5,0) -> #REF! | I88: =VLOOKUP(C88,#REF!,6,0) -> #REF! | K88: =+D88+E88+G88+H88+I88 -> #REF! | L88: 6000 | M88: =+L88/2 -> 3000 | O88: =VLOOKUP(C88,[1]IP!$B$9:$I$116,8,0) -> 0 | P88: =+H88+I88 -> #REF! | Q88: =VLOOKUP(C88,[1]IP!$B$9:$N$116,13,0) -> 1018.71 | R88: =VLOOKUP(C88,[1]IP!$B$9:$O$116,14,0) -> 0 | T88: =VLOOKUP(C88,[1]IP!$B$9:$P$116,15,0) -> 15 | U88: =VLOOKUP(C88,[1]IP!$B$9:$Q$116,16,0) -> 0 | V88: =VLOOKUP(C88,[1]IP!$B$9:$S$116,18,0) -> 0 | W88: =VLOOKUP(C88,[1]IP!$B$9:$R$116,17,0) -> 0 | Y88: =+K88-O88-P88+Q88+R88+S88+T88+U88+V88+W88 -> #REF! | Z88: =+M88-Y88 -> #REF! | AB88: =VLOOKUP(C88,[2]SINDICATO!$C$7:$Q$141,15,0) -> 0
A89: SEI479 | B89: SEITON (IP INNOVA II) | C89: Cruz Perez Alejandro Nezahualcoyotl | E89: =VLOOKUP(C89,[1]IP!$B$9:$V$116,21,0) -> 3583.6 | G89: =VLOOKUP(C89,#REF!,4,0) -> #REF! | H89: =VLOOKUP(C89,#REF!,5,0) -> #REF! | I89: =VLOOKUP(C89,#REF!,6,0) -> #REF! | K89: =+D89+E89+G89+H89+I89 -> #REF! | L89: 8000 | M89: =+L89/2 -> 4000 | O89: =VLOOKUP(C89,[1]IP!$B$9:$I$116,8,0) -> 0 | P89: =+H89+I89 -> #REF! | Q89: =VLOOKUP(C89,[1]IP!$B$9:$N$116,13,0) -> 0 | R89: =VLOOKUP(C89,[1]IP!$B$9:$O$116,14,0) -> 0 | T89: =VLOOKUP(C89,[1]IP!$B$9:$P$116,15,0) -> 0 | U89: =VLOOKUP(C89,[1]IP!$B$9:$Q$116,16,0) -> 0 | V89: =VLOOKUP(C89,[1]IP!$B$9:$S$116,18,0) -> 0 | W89: =VLOOKUP(C89,[1]IP!$B$9:$R$116,17,0) -> 0 | Y89: =+K89-O89-P89+Q89+R89+S89+T89+U89+V89+W89 -> #REF! | Z89: =+M89-Y89 -> #REF! | AB89: =VLOOKUP(C89,[2]SINDICATO!$C$7:$Q$141,15,0) -> #N/A
A90: SEI0415 | B90: SEITON (IP INNOVA II) | C90: Mireles Casillas Brenda Cristina | E90: =VLOOKUP(C90,[1]IP!$B$9:$V$116,21,0) -> 2237.8 | G90: =VLOOKUP(C90,#REF!,4,0) -> #REF! | H90: =VLOOKUP(C90,#REF!,5,0) -> #REF! | I90: =VLOOKUP(C90,#REF!,6,0) -> #REF! | K90: =+D90+E90+G90+H90+I90 -> #REF! | L90: 9000 | M90: =+L90/2 -> 4500 | O90: =VLOOKUP(C90,[1]IP!$B$9:$I$116,8,0) -> 0 | P90: =+H90+I90 -> #REF! | Q90: =VLOOKUP(C90,[1]IP!$B$9:$N$116,13,0) -> 0 | R90: =VLOOKUP(C90,[1]IP!$B$9:$O$116,14,0) -> 0 | T90: =VLOOKUP(C90,[1]IP!$B$9:$P$116,15,0) -> 0 | U90: =VLOOKUP(C90,[1]IP!$B$9:$Q$116,16,0) -> 0 | V90: =VLOOKUP(C90,[1]IP!$B$9:$S$116,18,0) -> 0 | W90: =VLOOKUP(C90,[1]IP!$B$9:$R$116,17,0) -> 0 | Y90: =+K90-O90-P90+Q90+R90+S90+T90+U90+V90+W90 -> #REF! | Z90: =+M90-Y90 -> #REF! | AB90: =VLOOKUP(C90,[2]SINDICATO!$C$7:$Q$141,15,0) -> #N/A
A91: SEI0033 | B91: SEITON (IP INNOVA II) | C91: Molina Ramirez Gerardo Daniel | E91: =VLOOKUP(C91,[1]IP!$B$9:$V$116,21,0) -> 1459.6 | G91: =VLOOKUP(C91,#REF!,4,0) -> #REF! | H91: =VLOOKUP(C91,#REF!,5,0) -> #REF! | I91: =VLOOKUP(C91,#REF!,6,0) -> #REF! | K91: =+D91+E91+G91+H91+I91 -> #REF! | L91: =VLOOKUP(C91,[2]ABC!$A$3:$B$88,2,0) -> 9000 | M91: =+L91/2 -> 4500 | O91: =VLOOKUP(C91,[1]IP!$B$9:$I$116,8,0) -> 0 | P91: =+H91+I91 -> #REF! | Q91: =VLOOKUP(C91,[1]IP!$B$9:$N$116,13,0) -> 0 | R91: =VLOOKUP(C91,[1]IP!$B$9:$O$116,14,0) -> 763.03 | T91: =VLOOKUP(C91,[1]IP!$B$9:$P$116,15,0) -> 15 | U91: =VLOOKUP(C91,[1]IP!$B$9:$Q$116,16,0) -> 0 | V91: =VLOOKUP(C91,[1]IP!$B$9:$S$116,18,0) -> 0 | W91: =VLOOKUP(C91,[1]IP!$B$9:$R$116,17,0) -> 0 | Y91: =+K91-O91-P91+Q91+R91+S91+T91+U91+V91+W91 -> #REF! | Z91: =+M91-Y91 -> #REF! | AB91: =VLOOKUP(C91,[2]SINDICATO!$C$7:$Q$141,15,0) -> #N/A
A92: SEI0095 | B92: SEITON (IP INNOVA II) | C92: Gutierrez Muñoz Carlos Alejandro | E92: =VLOOKUP(C92,[1]IP!$B$9:$V$116,21,0) -> 1065.8 | G92: =VLOOKUP(C92,#REF!,4,0) -> #REF! | H92: =VLOOKUP(C92,#REF!,5,0) -> #REF! | I92: =VLOOKUP(C92,#REF!,6,0) -> #REF! | K92: =+D92+E92+G92+H92+I92 -> #REF! | L92: =VLOOKUP(C92,[2]ABC!$A$3:$B$88,2,0) -> 12000 | M92: =+L92/2 -> 6000 | O92: =VLOOKUP(C92,[1]IP!$B$9:$I$116,8,0) -> 0 | P92: =+H92+I92 -> #REF! | Q92: =VLOOKUP(C92,[1]IP!$B$9:$N$116,13,0) -> 2034.26 | R92: =VLOOKUP(C92,[1]IP!$B$9:$O$116,14,0) -> 0 | T92: =VLOOKUP(C92,[1]IP!$B$9:$P$116,15,0) -> 15 | U92: =VLOOKUP(C92,[1]IP!$B$9:$Q$116,16,0) -> 0 | V92: =VLOOKUP(C92,[1]IP!$B$9:$S$116,18,0) -> 0 | W92: =VLOOKUP(C92,[1]IP!$B$9:$R$116,17,0) -> 0 | Y92: =+K92-O92-P92+Q92+R92+S92+T92+U92+V92+W92 -> #REF! | Z92: =+M92-Y92 -> #REF! | AB92: =VLOOKUP(C92,[2]SINDICATO!$C$7:$Q$141,15,0) -> #N/A
A93: SEI0096 | B93: SEITON (IP INNOVA II) | C93: Camarillo Canela Reynaldo | E93: =VLOOKUP(C93,[1]IP!$B$9:$V$116,21,0) -> 1314 | G93: =VLOOKUP(C93,#REF!,4,0) -> #REF! | H93: =VLOOKUP(C93,#REF!,5,0) -> #REF! | I93: =VLOOKUP(C93,#REF!,6,0) -> #REF! | K93: =+D93+E93+G93+H93+I93 -> #REF! | L93: =VLOOKUP(C93,[2]ABC!$A$3:$B$88,2,0) -> 9800 | M93: =+L93/2 -> 4900 | O93: =VLOOKUP(C93,[1]IP!$B$9:$I$116,8,0) -> 0 | P93: =+H93+I93 -> #REF! | Q93: =VLOOKUP(C93,[1]IP!$B$9:$N$116,13,0) -> 1366.67 | R93: =VLOOKUP(C93,[1]IP!$B$9:$O$116,14,0) -> 0 | T93: =VLOOKUP(C93,[1]IP!$B$9:$P$116,15,0) -> 0 | U93: =VLOOKUP(C93,[1]IP!$B$9:$Q$116,16,0) -> 0 | V93: =VLOOKUP(C93,[1]IP!$B$9:$S$116,18,0) -> 0 | W93: =VLOOKUP(C93,[1]IP!$B$9:$R$116,17,0) -> 0 | Y93: =+K93-O93-P93+Q93+R93+S93+T93+U93+V93+W93 -> #REF! | Z93: =+M93-Y93 -> #REF! | AB93: =VLOOKUP(C93,[2]SINDICATO!$C$7:$Q$141,15,0) -> 0
A94: SEI0416 | B94: SEITON (IP INNOVA II) | C94: Escobedo Olivares Juan Guadalupe | E94: =VLOOKUP(C94,[1]IP!$B$9:$V$116,21,0) -> 3278.8 | G94: =VLOOKUP(C94,#REF!,4,0) -> #REF! | H94: =VLOOKUP(C94,#REF!,5,0) -> #REF! | I94: =VLOOKUP(C94,#REF!,6,0) -> #REF! | K94: =+D94+E94+G94+H94+I94 -> #REF! | L94: 14000 | M94: =+L94/2 -> 7000 | O94: =VLOOKUP(C94,[1]IP!$B$9:$I$116,8,0) -> 0 | P94: =+H94+I94 -> #REF! | Q94: =VLOOKUP(C94,[1]IP!$B$9:$N$116,13,0) -> 0 | R94: =VLOOKUP(C94,[1]IP!$B$9:$O$116,14,0) -> 0 | T94: =VLOOKUP(C94,[1]IP!$B$9:$P$116,15,0) -> 0 | U94: =VLOOKUP(C94,[1]IP!$B$9:$Q$116,16,0) -> 0 | V94: =VLOOKUP(C94,[1]IP!$B$9:$S$116,18,0) -> 0 | W94: =VLOOKUP(C94,[1]IP!$B$9:$R$116,17,0) -> 0 | Y94: =+K94-O94-P94+Q94+R94+S94+T94+U94+V94+W94 -> #REF! | Z94: =+M94-Y94 -> #REF! | AB94: =VLOOKUP(C94,[2]SINDICATO!$C$7:$Q$141,15,0) -> #N/A
A95: SEI0417 | B95: SEITON (IP INNOVA II) | C95: Castillo Ramirez Hector Ivan | E95: =VLOOKUP(C95,[1]IP!$B$9:$V$116,21,0) -> 2727.8 | G95: =VLOOKUP(C95,#REF!,4,0) -> #REF! | H95: =VLOOKUP(C95,#REF!,5,0) -> #REF! | I95: =VLOOKUP(C95,#REF!,6,0) -> #REF! | K95: =+D95+E95+G95+H95+I95 -> #REF! | L95: 14000 | M95: =+L95/2 -> 7000 | O95: =VLOOKUP(C95,[1]IP!$B$9:$I$116,8,0) -> 0 | P95: =+H95+I95 -> #REF! | Q95: =VLOOKUP(C95,[1]IP!$B$9:$N$116,13,0) -> 0 | R95: =VLOOKUP(C95,[1]IP!$B$9:$O$116,14,0) -> 0 | T95: =VLOOKUP(C95,[1]IP!$B$9:$P$116,15,0) -> 0 | U95: =VLOOKUP(C95,[1]IP!$B$9:$Q$116,16,0) -> 0 | V95: =VLOOKUP(C95,[1]IP!$B$9:$S$116,18,0) -> 0 | W95: =VLOOKUP(C95,[1]IP!$B$9:$R$116,17,0) -> 550.83 | Y95: =+K95-O95-P95+Q95+R95+S95+T95+U95+V95+W95 -> #REF! | Z95: =+M95-Y95 -> #REF! | AB95: =VLOOKUP(C95,[2]SINDICATO!$C$7:$Q$141,15,0) -> #N/A
A96: SEI0420 | B96: SEITON (IP INNOVA II) | C96: Martinez Morales Tomas | E96: =VLOOKUP(C96,[1]IP!$B$9:$V$116,21,0) -> 1962.8 | G96: =VLOOKUP(C96,#REF!,4,0) -> #REF! | H96: =VLOOKUP(C96,#REF!,5,0) -> #REF! | I96: =VLOOKUP(C96,#REF!,6,0) -> #REF! | K96: =+D96+E96+G96+H96+I96 -> #REF! | L96: 15000 | M96: =+L96/2 -> 7500 | O96: =VLOOKUP(C96,[1]IP!$B$9:$I$116,8,0) -> 0 | P96: =+H96+I96 -> #REF! | Q96: =VLOOKUP(C96,[1]IP!$B$9:$N$116,13,0) -> 1881.2 | R96: =VLOOKUP(C96,[1]IP!$B$9:$O$116,14,0) -> 0 | T96: =VLOOKUP(C96,[1]IP!$B$9:$P$116,15,0) -> 15 | U96: =VLOOKUP(C96,[1]IP!$B$9:$Q$116,16,0) -> 0 | V96: =VLOOKUP(C96,[1]IP!$B$9:$S$116,18,0) -> 0 | W96: =VLOOKUP(C96,[1]IP!$B$9:$R$116,17,0) -> 301.5 | Y96: =+K96-O96-P96+Q96+R96+S96+T96+U96+V96+W96 -> #REF! | Z96: =+M96-Y96 -> #REF! | AB96: =VLOOKUP(C96,[2]SINDICATO!$C$7:$Q$141,15,0) -> #N/A
A97: SEI0421 | B97: SEITON (IP INNOVA II) | C97: Medellin Colunga Ruben Dario | E97: =VLOOKUP(C97,[1]IP!$B$9:$V$116,21,0) -> 1572.4 | G97: =VLOOKUP(C97,#REF!,4,0) -> #REF! | H97: =VLOOKUP(C97,#REF!,5,0) -> #REF! | I97: =VLOOKUP(C97,#REF!,6,0) -> #REF! | K97: =+D97+E97+G97+H97+I97 -> #REF! | L97: 17000 | M97: =+L97/2 -> 8500 | O97: =VLOOKUP(C97,[1]IP!$B$9:$I$116,8,0) -> 0 | P97: =+H97+I97 -> #REF! | Q97: =VLOOKUP(C97,[1]IP!$B$9:$N$116,13,0) -> 2177.34 | R97: =VLOOKUP(C97,[1]IP!$B$9:$O$116,14,0) -> 0 | T97: =VLOOKUP(C97,[1]IP!$B$9:$P$116,15,0) -> 15 | U97: =VLOOKUP(C97,[1]IP!$B$9:$Q$116,16,0) -> 0 | V97: =VLOOKUP(C97,[1]IP!$B$9:$S$116,18,0) -> 0 | W97: =VLOOKUP(C97,[1]IP!$B$9:$R$116,17,0) -> 395.82 | Y97: =+K97-O97-P97+Q97+R97+S97+T97+U97+V97+W97 -> #REF! | Z97: =+M97-Y97 -> #REF! | AB97: =VLOOKUP(C97,[2]SINDICATO!$C$7:$Q$141,15,0) -> #N/A
A98: SEI0422 | B98: SEITON (IP INNOVA II) | C98: Torres Perez Carlos Alberto | E98: =VLOOKUP(C98,[1]IP!$B$9:$V$116,21,0) -> 3079.2 | G98: =VLOOKUP(C98,#REF!,4,0) -> #REF! | H98: =VLOOKUP(C98,#REF!,5,0) -> #REF! | I98: =VLOOKUP(C98,#REF!,6,0) -> #REF! | K98: =+D98+E98+G98+H98+I98 -> #REF! | L98: 10500 | M98: =+L98/2 -> 5250 | O98: =VLOOKUP(C98,[1]IP!$B$9:$I$116,8,0) -> 0 | P98: =+H98+I98 -> #REF! | Q98: =VLOOKUP(C98,[1]IP!$B$9:$N$116,13,0) -> 0 | R98: =VLOOKUP(C98,[1]IP!$B$9:$O$116,14,0) -> 0 | T98: =VLOOKUP(C98,[1]IP!$B$9:$P$116,15,0) -> 0 | U98: =VLOOKUP(C98,[1]IP!$B$9:$Q$116,16,0) -> 0 | V98: =VLOOKUP(C98,[1]IP!$B$9:$S$116,18,0) -> 0 | W98: =VLOOKUP(C98,[1]IP!$B$9:$R$116,17,0) -> 253.5 | Y98: =+K98-O98-P98+Q98+R98+S98+T98+U98+V98+W98 -> #REF! | Z98: =+M98-Y98 -> #REF! | AB98: =VLOOKUP(C98,[2]SINDICATO!$C$7:$Q$141,15,0) -> #N/A
A99: SEI0424 | B99: SEITON (IP INNOVA II) | C99: Treviño Alvarez Jorge Alberto | E99: =VLOOKUP(C99,[1]IP!$B$9:$V$116,21,0) -> 1805.2 | G99: =VLOOKUP(C99,#REF!,4,0) -> #REF! | H99: =VLOOKUP(C99,#REF!,5,0) -> #REF! | I99: =VLOOKUP(C99,#REF!,6,0) -> #REF! | K99: =+D99+E99+G99+H99+I99 -> #REF! | L99: 12000 | M99: =+L99/2 -> 6000 | O99: =VLOOKUP(C99,[1]IP!$B$9:$I$116,8,0) -> 0 | P99: =+H99+I99 -> #REF! | Q99: =VLOOKUP(C99,[1]IP!$B$9:$N$116,13,0) -> 1202.43 | R99: =VLOOKUP(C99,[1]IP!$B$9:$O$116,14,0) -> 0 | T99: =VLOOKUP(C99,[1]IP!$B$9:$P$116,15,0) -> 15 | U99: =VLOOKUP(C99,[1]IP!$B$9:$Q$116,16,0) -> 0 | V99: =VLOOKUP(C99,[1]IP!$B$9:$S$116,18,0) -> 0 | W99: =VLOOKUP(C99,[1]IP!$B$9:$R$116,17,0) -> 310 | Y99: =+K99-O99-P99+Q99+R99+S99+T99+U99+V99+W99 -> #REF! | Z99: =+M99-Y99 -> #REF! | AB99: =VLOOKUP(C99,[2]SINDICATO!$C$7:$Q$141,15,0) -> #N/A
A100: SEI0425 | B100: SEITON (IP INNOVA II) | C100: Tenorio Alvarez Alberto Antonio | E100: =VLOOKUP(C100,[1]IP!$B$9:$V$116,21,0) -> 2195 | G100: =VLOOKUP(C100,#REF!,4,0) -> #REF! | H100: =VLOOKUP(C100,#REF!,5,0) -> #REF! | I100: =VLOOKUP(C100,#REF!,6,0) -> #REF! | K100: =+D100+E100+G100+H100+I100 -> #REF! | L100: 10000 | M100: =+L100/2 -> 5000 | O100: =VLOOKUP(C100,[1]IP!$B$9:$I$116,8,0) -> 0 | P100: =+H100+I100 -> #REF! | Q100: =VLOOKUP(C100,[1]IP!$B$9:$N$116,13,0) -> 0 | R100: =VLOOKUP(C100,[1]IP!$B$9:$O$116,14,0) -> 1122.63 | T100: =VLOOKUP(C100,[1]IP!$B$9:$P$116,15,0) -> 15 | U100: =VLOOKUP(C100,[1]IP!$B$9:$Q$116,16,0) -> 0 | V100: =VLOOKUP(C100,[1]IP!$B$9:$S$116,18,0) -> 0 | W100: =VLOOKUP(C100,[1]IP!$B$9:$R$116,17,0) -> 0 | Y100: =+K100-O100-P100+Q100+R100+S100+T100+U100+V100+W100 -> #REF! | Z100: =+M100-Y100 -> #REF! | AB100: =VLOOKUP(C100,[2]SINDICATO!$C$7:$Q$141,15,0) -> #N/A
A101: SEI0426 | B101: SEITON (IP INNOVA II) | C101: Chavez Dominguez Salvador | E101: =VLOOKUP(C101,[1]IP!$B$9:$V$116,21,0) -> 3332.6 | G101: =VLOOKUP(C101,#REF!,4,0) -> #REF! | H101: =VLOOKUP(C101,#REF!,5,0) -> #REF! | I101: =VLOOKUP(C101,#REF!,6,0) -> #REF! | K101: =+D101+E101+G101+H101+I101 -> #REF! | L101: 12000 | M101: =+L101/2 -> 6000 | O101: =VLOOKUP(C101,[1]IP!$B$9:$I$116,8,0) -> 0 | P101: =+H101+I101 -> #REF! | Q101: =VLOOKUP(C101,[1]IP!$B$9:$N$116,13,0) -> 0 | R101: =VLOOKUP(C101,[1]IP!$B$9:$O$116,14,0) -> 0 | T101: =VLOOKUP(C101,[1]IP!$B$9:$P$116,15,0) -> 0 | U101: =VLOOKUP(C101,[1]IP!$B$9:$Q$116,16,0) -> 0 | V101: =VLOOKUP(C101,[1]IP!$B$9:$S$116,18,0) -> 0 | W101: =VLOOKUP(C101,[1]IP!$B$9:$R$116,17,0) -> 0 | Y101: =+K101-O101-P101+Q101+R101+S101+T101+U101+V101+W101 -> #REF! | Z101: =+M101-Y101 -> #REF! | AB101: =VLOOKUP(C101,[2]SINDICATO!$C$7:$Q$141,15,0) -> #N/A
...

Sheet RESUMEN PITS
F1: SINDICATO
A2: CLAVE | B2: EMPRESA | C2: NOMBRE | D2: NETO CPD | F2: SUELDO SINDICATO | G2: BONO | H2: COMISION | I2: PRIMA VACACIONAL SINDICATO | J2: B | K2: NETO A PAGAR | L2: NETO MENSUAL | M2: NETO QUINCENAL SEITON | N2: C | O2: prima vacacional | P2: COMISION Y PRIMA VACACIONAL | Q2: INFONAVIT | R2: FONACOT | S2: DESCUENTOS | T2: D | U2: TOTAL GENERAL | V2: DIFERENCIAS | W2: OBSERVACIONES
A3: SEI0009 | B3: CONSULTORIA | C3: Gutierrez Gutierrez Luis Arturo | D3: =VLOOKUP(C3,'CPD PITS'!$B$6:$V$24,21,0) -> 2771 | F3: =VLOOKUP(C3,'SIND PITS'!$C$3:$D$102,2,0) -> 1479 | G3: =VLOOKUP(C3,'SIND PITS'!$C$3:$E$102,3,0) -> 288.5 | H3: =VLOOKUP(C3,'SIND PITS'!$C$3:$F$102,4,0) -> 0 | I3: =VLOOKUP(C3,'SIND PITS'!$C$3:$G$102,5,0) -> 0 | K3: =SUM(D3:I3) -> 4538.5 | L3: 8500 | M3: 4250 | O3: =VLOOKUP(C3,'CPD PITS'!$B$6:$I$24,8,0) -> 0 | P3: =+G3+H3+I3 -> 288.5 | Q3: =VLOOKUP(C3,'CPD PITS'!$B$6:$R$24,17,0)+VLOOKUP('RESUMEN PITS'!C3,'CPD PITS'!$B$6:$Q$24,16,0) -> 0 | S3: =VLOOKUP(C3,'CPD PITS'!B6:S24,18,0) -> 0 | U3: =+K3-O3-P3+Q3+R3+S3 -> 4250 | V3: =+M3-U3 -> 0 | X3: SEI0009
A4: SEI0026 | B4: CONSULTORIA | C4: Patricio Aguilar Jhonattan Cristian | D4: =VLOOKUP(C4,'CPD PITS'!$B$6:$V$24,21,0) -> 2908.2 | F4: =VLOOKUP(C4,'SIND PITS'!$C$3:$D$102,2,0) -> 1591.8 | G4: =VLOOKUP(C4,'SIND PITS'!$C$3:$E$102,3,0) -> 375 | H4: =VLOOKUP(C4,'SIND PITS'!$C$3:$F$102,4,0) -> 0 | I4: =VLOOKUP(C4,'SIND PITS'!$C$3:$G$102,5,0) -> 0 | K4: =SUM(D4:I4) -> 4875 | L4: 9000 | M4: 4500 | O4: =VLOOKUP(C4,'CPD PITS'!$B$6:$I$24,8,0) -> 0 | P4: =+G4+H4+I4 -> 375 | Q4: =VLOOKUP(C4,'CPD PITS'!$B$6:$R$24,17,0)+VLOOKUP('RESUMEN PITS'!C4,'CPD PITS'!$B$6:$Q$24,16,0) -> 0 | S4: =VLOOKUP(C4,'CPD PITS'!B7:S25,18,0) -> 0 | U4: =+K4-O4-P4+Q4+R4+S4 -> 4500 | V4: =+M4-U4 -> 0 | X4: SEI0026
A5: SEI0040 | B5: CONSULTORIA | C5: Mora Ramirez Acal Aldo Isidro | D5: =VLOOKUP(C5,'CPD PITS'!$B$6:$V$24,21,0) -> 4030.6 | F5: =VLOOKUP(C5,'SIND PITS'!$C$3:$D$102,2,0) -> 2469.4 | G5: =VLOOKUP(C5,'SIND PITS'!$C$3:$E$102,3,0) -> 1000 | H5: =VLOOKUP(C5,'SIND PITS'!$C$3:$F$102,4,0) -> 0 | I5: =VLOOKUP(C5,'SIND PITS'!$C$3:$G$102,5,0) -> 0 | K5: =SUM(D5:I5) -> 7500 | L5: 13000 | M5: 6500 | O5: =VLOOKUP(C5,'CPD PITS'!$B$6:$I$24,8,0) -> 0 | P5: =+G5+H5+I5 -> 1000 | Q5: =VLOOKUP(C5,'CPD PITS'!$B$6:$R$24,17,0)+VLOOKUP('RESUMEN PITS'!C5,'CPD PITS'!$B$6:$Q$24,16,0) -> 0 | S5: =VLOOKUP(C5,'CPD PITS'!B8:S26,18,0) -> 0 | U5: =+K5-O5-P5+Q5+R5+S5 -> 6500 | V5: =+M5-U5 -> 0 | X5: SEI0040
A6: SEI0041 | B6: CONSULTORIA | C6: Vazquez Perez Miguel Angel | D6: =VLOOKUP(C6,'CPD PITS'!$B$6:$V$24,21,0) -> 5066.8 | F6: =VLOOKUP(C6,'SIND PITS'!$C$3:$D$102,2,0) -> 4183.2 | G6: =VLOOKUP(C6,'SIND PITS'!$C$3:$E$102,3,0) -> 750 | H6: =VLOOKUP(C6,'SIND PITS'!$C$3:$F$102,4,0) -> 0 | I6: =VLOOKUP(C6,'SIND PITS'!$C$3:$G$102,5,0) -> 0 | K6: =SUM(D6:I6) -> 10000 | L6: 18500 | M6: 9250 | O6: =VLOOKUP(C6,'CPD PITS'!$B$6:$I$24,8,0) -> 0 | P6: =+G6+H6+I6 -> 750 | Q6: =VLOOKUP(C6,'CPD PITS'!$B$6:$R$24,17,0)+VLOOKUP('RESUMEN PITS'!C6,'CPD PITS'!$B$6:$Q$24,16,0) -> 0 | S6: =VLOOKUP(C6,'CPD PITS'!B9:S27,18,0) -> 0 | U6: =+K6-O6-P6+Q6+R6+S6 -> 9250 | V6: =+M6-U6 -> 0 | X6: SEI0041
A7: SEI0088 | B7: CONSULTORIA | C7: Morgado Fernandez Martin | D7: =VLOOKUP(C7,'CPD PITS'!$B$6:$V$24,21,0) -> 4892.8 | F7: =VLOOKUP(C7,'SIND PITS'!$C$3:$D$102,2,0) -> 2607.2 | G7: =VLOOKUP(C7,'SIND PITS'!$C$3:$E$102,3,0) -> 281.5 | H7: =VLOOKUP(C7,'SIND PITS'!$C$3:$F$102,4,0) -> 0 | I7: =VLOOKUP(C7,'SIND PITS'!$C$3:$G$102,5,0) -> 0 | K7: =SUM(D7:I7) -> 7781.5 | L7: 15000 | M7: 7500 | O7: =VLOOKUP(C7,'CPD PITS'!$B$6:$I$24,8,0) -> 0 | P7: =+G7+H7+I7 -> 281.5 | Q7: =VLOOKUP(C7,'CPD PITS'!$B$6:$R$24,17,0)+VLOOKUP('RESUMEN PITS'!C7,'CPD PITS'!$B$6:$Q$24,16,0) -> 0 | S7: =VLOOKUP(C7,'CPD PITS'!B10:S28,18,0) -> 0 | U7: =+K7-O7-P7+Q7+R7+S7 -> 7500 | V7: =+M7-U7 -> 0 | X7: SEI0088
A8: SEI0097 | B8: CONSULTORIA | C8: Arreola Jimenez Jose Nieves | D8: =VLOOKUP(C8,'CPD PITS'!$B$6:$V$24,21,0) -> 1818 | F8: =VLOOKUP(C8,'SIND PITS'!$C$3:$D$102,2,0) -> 1562.71 | G8: =VLOOKUP(C8,'SIND PITS'!$C$3:$E$102,3,0) -> 501 | H8: =VLOOKUP(C8,'SIND PITS'!$C$3:$F$102,4,0) -> 0 | I8: =VLOOKUP(C8,'SIND PITS'!$C$3:$G$102,5,0) -> 0 | K8: =SUM(D8:I8) -> 3881.71 | L8: 10150 | M8: 5075 | O8: =VLOOKUP(C8,'CPD PITS'!$B$6:$I$24,8,0) -> 0 | P8: =+G8+H8+I8 -> 501 | Q8: =VLOOKUP(C8,'CPD PITS'!$B$6:$R$24,17,0)+VLOOKUP('RESUMEN PITS'!C8,'CPD PITS'!$B$6:$Q$24,16,0) -> 1574.29 | S8: =VLOOKUP(C8,'CPD PITS'!B11:S29,18,0) -> 120 | U8: =+K8-O8-P8+Q8+R8+S8 -> 5075 | V8: =+M8-U8 -> 0 | X8: SEI0097
A9: SEI0099 | B9: CONSULTORIA | C9: Garcia Villicaña Ricardo Pascual | D9: =VLOOKUP(C9,'CPD PITS'!$B$6:$V$24,21,0) -> 4892.8 | F9: =VLOOKUP(C9,'SIND PITS'!$C$3:$D$102,2,0) -> 2607.2 | G9: =VLOOKUP(C9,'SIND PITS'!$C$3:$E$102,3,0) -> 216.5 | H9: =VLOOKUP(C9,'SIND PITS'!$C$3:$F$102,4,0) -> 0 | I9: =VLOOKUP(C9,'SIND PITS'!$C$3:$G$102,5,0) -> 0 | K9: =SUM(D9:I9) -> 7716.5 | L9: 15000 | M9: 7500 | O9: =VLOOKUP(C9,'CPD PITS'!$B$6:$I$24,8,0) -> 0 | P9: =+G9+H9+I9 -> 216.5 | Q9: =VLOOKUP(C9,'CPD PITS'!$B$6:$R$24,17,0)+VLOOKUP('RESUMEN PITS'!C9,'CPD PITS'!$B$6:$Q$24,16,0) -> 0 | S9: =VLOOKUP(C9,'CPD PITS'!B12:S30,18,0) -> 0 | U9: =+K9-O9-P9+Q9+R9+S9 -> 7500 | V9: =+M9-U9 -> 0 | X9: SEI0099
A10: SEI0108 | B10: CONSULTORIA | C10: Caballero Diaz Francisco Javier | D10: =VLOOKUP(C10,'CPD PITS'!$B$6:$V$24,21,0) -> 1685.8 | F10: =VLOOKUP(C10,'SIND PITS'!$C$3:$D$102,2,0) -> 1562.69 | G10: =VLOOKUP(C10,'SIND PITS'!$C$3:$E$102,3,0) -> 346 | H10: =VLOOKUP(C10,'SIND PITS'!$C$3:$F$102,4,0) -> 0 | I10: =VLOOKUP(C10,'SIND PITS'!$C$3:$G$102,5,0) -> 0 | K10: =SUM(D10:I10) -> 3594.49 | L10: 10150 | M10: 5075 | O10: =VLOOKUP(C10,'CPD PITS'!$B$6:$I$24,8,0) -> 0 | P10: =+G10+H10+I10 -> 346 | Q10: =VLOOKUP(C10,'CPD PITS'!$B$6:$R$24,17,0)+VLOOKUP('RESUMEN PITS'!C10,'CPD PITS'!$B$6:$Q$24,16,0) -> 1826.51 | S10: =VLOOKUP(C10,'CPD PITS'!B13:S31,18,0) -> 0 | U10: =+K10-O10-P10+Q10+R10+S10 -> 5075 | V10: =+M10-U10 -> 0 | X10: SEI0108
A11: SEI0116 | B11: CONSULTORIA | C11: Casillas Cardona Cesar Alejandro | D11: =VLOOKUP(C11,'CPD PITS'!$B$6:$V$24,21,0) -> 3206.6 | F11: =VLOOKUP(C11,'SIND PITS'!$C$3:$D$102,2,0) -> 1896.8 | G11: =VLOOKUP(C11,'SIND PITS'!$C$3:$E$102,3,0) -> 0 | H11: =VLOOKUP(C11,'SIND PITS'!$C$3:$F$102,4,0) -> 0 | I11: =VLOOKUP(C11,'SIND PITS'!$C$3:$G$102,5,0) -> 0 | K11: =SUM(D11:I11) -> 5103.4 | L11: 12000 | M11: 6000 | O11: =VLOOKUP(C11,'CPD PITS'!$B$6:$I$24,8,0) -> 0 | P11: =+G11+H11+I11 -> 0 | Q11: =VLOOKUP(C11,'CPD PITS'!$B$6:$R$24,17,0)+VLOOKUP('RESUMEN PITS'!C11,'CPD PITS'!$B$6:$Q$24,16,0) -> 896.6 | S11: =VLOOKUP(C11,'CPD PITS'!B14:S32,18,0) -> 0 | U11: =+K11-O11-P11+Q11+R11+S11 -> 6000 | V11: =+M11-U11 -> 0 | X11: SEI0116
A12: SEI0117 | B12: CONSULTORIA | C12: Mariscal Romero Luis Adrian | D12: =VLOOKUP(C12,'CPD PITS'!$B$6:$V$24,21,0) -> 3068.2 | F12: =VLOOKUP(C12,'SIND PITS'!$C$3:$D$102,2,0) -> 2757.8 | G12: =VLOOKUP(C12,'SIND PITS'!$C$3:$E$102,3,0) -> 250 | H12: =VLOOKUP(C12,'SIND PITS'!$C$3:$F$102,4,0) -> 0 | I12: =VLOOKUP(C12,'SIND PITS'!$C$3:$G$102,5,0) -> 0 | K12: =SUM(D12:I12) -> 6076 | L12: 15000 | M12: 7500 | O12: =VLOOKUP(C12,'CPD PITS'!$B$6:$I$24,8,0) -> 0 | P12: =+G12+H12+I12 -> 250 | Q12: =VLOOKUP(C12,'CPD PITS'!$B$6:$R$24,17,0)+VLOOKUP('RESUMEN PITS'!C12,'CPD PITS'!$B$6:$Q$24,16,0) -> 1674 | S12: =VLOOKUP(C12,'CPD PITS'!B15:S33,18,0) -> 0 | U12: =+K12-O12-P12+Q12+R12+S12 -> 7500 | V12: =+M12-U12 -> 0 | X12: SEI0117
A13: SEI0118 | B13: CONSULTORIA | C13: Arroyo Ramirez Hector Hugo | D13: =VLOOKUP(C13,'CPD PITS'!$B$6:$V$24,21,0) -> 2690.4 | F13: =VLOOKUP(C13,'SIND PITS'!$C$3:$D$102,2,0) -> 2108.85 | G13: =VLOOKUP(C13,'SIND PITS'!$C$3:$E$102,3,0) -> 0 | H13: =VLOOKUP(C13,'SIND PITS'!$C$3:$F$102,4,0) -> 0 | I13: =VLOOKUP(C13,'SIND PITS'!$C$3:$G$102,5,0) -> 0 | K13: =SUM(D13:I13) -> 4799.25 | L13: 13000 | M13: 6500 | O13: =VLOOKUP(C13,'CPD PITS'!$B$6:$I$24,8,0) -> 0 | P13: =+G13+H13+I13 -> 0 | Q13: =VLOOKUP(C13,'CPD PITS'!$B$6:$R$24,17,0)+VLOOKUP('RESUMEN PITS'!C13,'CPD PITS'!$B$6:$Q$24,16,0) -> 1432.4 | S13: =VLOOKUP(C13,'CPD PITS'!B16:S34,18,0) -> 268.35 | U13: =+K13-O13-P13+Q13+R13+S13 -> 6500 | V13: =+M13-U13 -> 0 | X13: SEI0118
A14: SEI0127 | B14: CONSULTORIA | C14: Hernandez Ochoa Eduardo | D14: =VLOOKUP(C14,'CPD PITS'!$B$6:$V$24,21,0) -> 4892.6 | F14: =VLOOKUP(C14,'SIND PITS'!$C$3:$D$102,2,0) -> 2607.4 | G14: =VLOOKUP(C14,'SIND PITS'!$C$3:$E$102,3,0) -> 468 | H14: =VLOOKUP(C14,'SIND PITS'!$C$3:$F$102,4,0) -> 0 | I14: =VLOOKUP(C14,'SIND PITS'!$C$3:$G$102,5,0) -> 0 | K14: =SUM(D14:I14) -> 7968 | L14: 15000 | M14: 7500 | O14: =VLOOKUP(C14,'CPD PITS'!$B$6:$I$24,8,0) -> 0 | P14: =+G14+H14+I14 -> 468 | Q14: =VLOOKUP(C14,'CPD PITS'!$B$6:$R$24,17,0)+VLOOKUP('RESUMEN PITS'!C14,'CPD PITS'!$B$6:$Q$24,16,0) -> 0 | S14: =VLOOKUP(C14,'CPD PITS'!B17:S35,18,0) -> 0 | U14: =+K14-O14-P14+Q14+R14+S14 -> 7500 | V14: =+M14-U14 -> 0 | X14: SEI0127
... A18: SEI0425 | B18: CONSULTORIA | C18: Carbajal Cabuto Jose Luis | D18: =VLOOKUP(C18,'CPD PITS'!$B$6:$V$24,21,0) -> 2005.6 | F18: =VLOOKUP(C18,'SIND PITS'!$C$3:$D$102,2,0) -> 1612.9 | G18: =VLOOKUP(C18,'SIND PITS'!$C$3:$E$102,3,0) -> 357 | H18: =VLOOKUP(C18,'SIND PITS'!$C$3:$F$102,4,0) -> 0 | I18: =VLOOKUP(C18,'SIND PITS'!$C$3:$G$102,5,0) -> 0 | K18: =SUM(D18:I18) -> 3975.5 | L18: 10250 | M18: 5125 | O18: =VLOOKUP(C18,'CPD PITS'!$B$6:$I$24,8,0) -> 0 | P18: =+G18+H18+I18 -> 357 | Q18: =VLOOKUP(C18,'CPD PITS'!$B$6:$R$24,17,0)+VLOOKUP('RESUMEN PITS'!C18,'CPD PITS'!$B$6:$Q$24,16,0) -> 1506.5 | S18: =VLOOKUP(C18,'CPD PITS'!B21:S39,18,0) -> 0 | U18: =+K18-O18-P18+Q18+R18+S18 -> 5125 | V18: =+M18-U18 -> 0 | X18: SEI0453
A19: SEI0435 | B19: CONSULTORIA | C19: Benavides Herrera Alejandra | D19: =VLOOKUP(C19,'CPD PITS'!$B$6:$V$24,21,0) -> 3192.4 | F19: =VLOOKUP(C19,'SIND PITS'!$C$3:$D$102,2,0) -> 16807.6 | G19: =VLOOKUP(C19,'SIND PITS'!$C$3:$E$102,3,0) -> 0 | H19: =VLOOKUP(C19,'SIND PITS'!$C$3:$F$102,4,0) -> 0 | I19: =VLOOKUP(C19,'SIND PITS'!$C$3:$G$102,5,0) -> 0 | K19: =SUM(D19:I19) -> 20000 | L19: 40000 | M19: 20000 | O19: =VLOOKUP(C19,'CPD PITS'!$B$6:$I$24,8,0) -> 0 | P19: =+G19+H19+I19 -> 0 | Q19: =VLOOKUP(C19,'CPD PITS'!$B$6:$R$24,17,0)+VLOOKUP('RESUMEN PITS'!C19,'CPD PITS'!$B$6:$Q$24,16,0) -> 0 | S19: =VLOOKUP(C19,'CPD PITS'!B22:S41,18,0) -> 0 | U19: =+K19-O19-P19+Q19+R19+S19 -> 20000 | V19: =+M19-U19 -> 0 | X19: SEI0377
A20: SEI0442 | B20: CONSULTORIA | C20: Sierra Escamilla Daniela | D20: =VLOOKUP(C20,'CPD PITS'!$B$6:$V$24,21,0) -> 4030.6 | F20: =VLOOKUP(C20,'SIND PITS'!$C$3:$D$102,2,0) -> 2469.4 | G20: =VLOOKUP(C20,'SIND PITS'!$C$3:$E$102,3,0) -> 1000 | H20: =VLOOKUP(C20,'SIND PITS'!$C$3:$F$102,4,0) -> 0 | I20: =VLOOKUP(C20,'SIND PITS'!$C$3:$G$102,5,0) -> 0 | K20: =SUM(D20:I20) -> 7500 | L20: 13000 | M20: 6500 | O20: =VLOOKUP(C20,'CPD PITS'!$B$6:$I$24,8,0) -> 0 | P20: =+G20+H20+I20 -> 1000 | Q20: =VLOOKUP(C20,'CPD PITS'!$B$6:$R$24,17,0)+VLOOKUP('RESUMEN PITS'!C20,'CPD PITS'!$B$6:$Q$24,16,0) -> 0 | S20: =VLOOKUP(C20,'CPD PITS'!B23:S42,18,0) -> 0 | U20: =+K20-O20-P20+Q20+R20+S20 -> 6500 | V20: =+M20-U20 -> 0 | X20: SEI0618
A21: SEI0445 | B21: CONSULTORIA | C21: Muñoz Melgoza Gabriel | D21: =VLOOKUP(C21,'CPD PITS'!$B$6:$V$24,21,0) -> 4409.2 | F21: =VLOOKUP(C21,'SIND PITS'!$C$3:$D$102,2,0) -> 2777.47 | G21: =VLOOKUP(C21,'SIND PITS'!$C$3:$E$102,3,0) -> 250 | H21: =VLOOKUP(C21,'SIND PITS'!$C$3:$F$102,4,0) -> 0 | I21: =VLOOKUP(C21,'SIND PITS'!$C$3:$G$102,5,0) -> 0 | K21: =SUM(D21:I21) -> 7436.67 | L21: 15400 | M21: 7700 | O21: =VLOOKUP(C21,'CPD PITS'!$B$6:$I$24,8,0) -> 0 | P21: =+G21+H21+I21 -> 250 | Q21: =VLOOKUP(C21,'CPD PITS'!$B$6:$R$24,17,0)+VLOOKUP('RESUMEN PITS'!C21,'CPD PITS'!$B$6:$Q$24,16,0) -> 0 | S21: =VLOOKUP(C21,'CPD PITS'!B24:S43,18,0) -> 0 | U21: =+K21-O21-P21+Q21+R21+S21 -> 7186.67 | V21: =+M21-U21 -> 513.33 | W21: 1 FALTA | X21: SEI0632
A22: SEI0010 | B22: IP INNOVACION | C22: Torres Ricardez Alfredo | D22: =VLOOKUP(C22,'IP PITS'!$B$6:$V$86,21,0) -> 3578.8 | F22: =VLOOKUP(C22,'SIND PITS'!$C$3:$D$102,2,0) -> 421.2 | G22: =VLOOKUP(C22,'SIND PITS'!$C$3:$E$102,3,0) -> 258.5 | H22: =VLOOKUP(C22,'SIND PITS'!$C$3:$F$102,4,0) -> 0 | I22: =VLOOKUP(C22,'SIND PITS'!$C$3:$G$102,5,0) -> 0 | K22: =SUM(D22:I22) -> 4258.5 | L22: 8000 | M22: 4000 | O22: =VLOOKUP(C22,'IP PITS'!$B$6:$I$86,8,0) -> 0 | P22: =+G22+H22+I22 -> 258.5 | Q22: =VLOOKUP(C22,'IP PITS'!$B$6:$N$86,13,0) -> 0 | R22: =VLOOKUP(C22,'IP PITS'!$B$6:$Q$86,16,0) -> 0 | S22: =VLOOKUP(C22,'IP PITS'!$B$6:$R$86,17,0) -> 0 | U22: =+K22-O22-P22+Q22+R22+S22 -> 4000 | V22: =+M22-U22 -> 0 | X22: SEI0010
A23: SEI0014 | B23: IP INNOVACION | C23: Montoya Portillo Carlos Alberto | D23: =VLOOKUP(C23,'IP PITS'!$B$6:$V$86,21,0) -> 3578.8 | F23: =VLOOKUP(C23,'SIND PITS'!$C$3:$D$102,2,0) -> 421.2 | G23: =VLOOKUP(C23,'SIND PITS'!$C$3:$E$102,3,0) -> 121.5 | H23: =VLOOKUP(C23,'SIND PITS'!$C$3:$F$102,4,0) -> 0 | I23: =VLOOKUP(C23,'SIND PITS'!$C$3:$G$102,5,0) -> 0 | K23: =SUM(D23:I23) -> 4121.5 | L23: 8000 | M23: 4000 | O23: =VLOOKUP(C23,'IP PITS'!$B$6:$I$86,8,0) -> 0 | P23: =+G23+H23+I23 -> 121.5 | Q23: =VLOOKUP(C23,'IP PITS'!$B$6:$N$86,13,0) -> 0 | R23: =VLOOKUP(C23,'IP PITS'!$B$6:$Q$86,16,0) -> 0 | S23: =VLOOKUP(C23,'IP PITS'!$B$6:$R$86,17,0) -> 0 | U23: =+K23-O23-P23+Q23+R23+S23 -> 4000 | V23: =+M23-U23 -> 0 | X23: SEI0014
A24: SEI0017 | B24: IP INNOVACION | C24: Muñoz Reyes Luis Eduardo | D24: =VLOOKUP(C24,'IP PITS'!$B$6:$V$86,21,0) -> 2701 | F24: =VLOOKUP(C24,'SIND PITS'!$C$3:$D$102,2,0) -> 421.41 | G24: =VLOOKUP(C24,'SIND PITS'!$C$3:$E$102,3,0) -> 358.5 | H24: =VLOOKUP(C24,'SIND PITS'!$C$3:$F$102,4,0) -> 0 | I24: =VLOOKUP(C24,'SIND PITS'!$C$3:$G$102,5,0) -> 0 | K24: =SUM(D24:I24) -> 3480.91 | L24: 8000 | M24: 4000 | O24: =VLOOKUP(C24,'IP PITS'!$B$6:$I$86,8,0) -> 0 | P24: =+G24+H24+I24 -> 358.5 | Q24: =VLOOKUP(C24,'IP PITS'!$B$6:$N$86,13,0) -> 877.59 | R24: =VLOOKUP(C24,'IP PITS'!$B$6:$Q$86,16,0) -> 0 | S24: =VLOOKUP(C24,'IP PITS'!$B$6:$R$86,17,0) -> 0 | U24: =+K24-O24-P24+Q24+R24+S24 -> 4000 | V24: =+M24-U24 -> 0 | X24: SEI0017
A25: SEI0019 | B25: IP INNOVACION | C25: Gonzalez Rasgado Miguel Isaias | D25: =VLOOKUP(C25,'IP PITS'!$B$6:$V$86,21,0) -> 5184.4 | F25: =VLOOKUP(C25,'SIND PITS'!$C$3:$D$102,2,0) -> 815.6 | G25: =VLOOKUP(C25,'SIND PITS'!$C$3:$E$102,3,0) -> 937.5 | H25: =VLOOKUP(C25,'SIND PITS'!$C$3:$F$102,4,0) -> 0 | I25: =VLOOKUP(C25,'SIND PITS'!$C$3:$G$102,5,0) -> 0 | K25: =SUM(D25:I25) -> 6937.5 | L25: 12000 | M25: 6000 | O25: =VLOOKUP(C25,'IP PITS'!$B$6:$I$86,8,0) -> 0 | P25: =+G25+H25+I25 -> 937.5 | Q25: =VLOOKUP(C25,'IP PITS'!$B$6:$N$86,13,0) -> 0 | R25: =VLOOKUP(C25,'IP PITS'!$B$6:$Q$86,16,0) -> 0 | S25: =VLOOKUP(C25,'IP PITS'!$B$6:$R$86,17,0) -> 0 | U25: =+K25-O25-P25+Q25+R25+S25 -> 6000 | V25: =+M25-U25 -> 0 | X25: SEI0019 | Y25: aumento 13125 marzo
A26: SEI0020 | B26: IP INNOVACION | C26: Mar Marquez Cesar Eduardo | D26: =VLOOKUP(C26,'IP PITS'!$B$6:$V$86,21,0) -> 3578.6 | F26: =VLOOKUP(C26,'SIND PITS'!$C$3:$D$102,2,0) -> 421.4 | G26: =VLOOKUP(C26,'SIND PITS'!$C$3:$E$102,3,0) -> 168.5 | H26: =VLOOKUP(C26,'SIND PITS'!$C$3:$F$102,4,0) -> 0 | I26: =VLOOKUP(C26,'SIND PITS'!$C$3:$G$102,5,0) -> 0 | K26: =SUM(D26:I26) -> 4168.5 | L26: 8000 | M26: 4000 | O26: =VLOOKUP(C26,'IP PITS'!$B$6:$I$86,8,0) -> 0 | P26: =+G26+H26+I26 -> 168.5 | Q26: =VLOOKUP(C26,'IP PITS'!$B$6:$N$86,13,0) -> 0 | R26: =VLOOKUP(C26,'IP PITS'!$B$6:$Q$86,16,0) -> 0 | S26: =VLOOKUP(C26,'IP PITS'!$B$6:$R$86,17,0) -> 0 | U26: =+K26-O26-P26+Q26+R26+S26 -> 4000 | V26: =+M26-U26 -> 0 | X26: SEI0020
A27: SEI0021 | B27: IP INNOVACION | C27: Velez Rodriguez Jaime | D27: =VLOOKUP(C27,'IP PITS'!$B$6:$V$86,21,0) -> 1560.4 | F27: =VLOOKUP(C27,'SIND PITS'!$C$3:$D$102,2,0) -> 1140.37 | G27: =VLOOKUP(C27,'SIND PITS'!$C$3:$E$102,3,0) -> 0 | H27: =VLOOKUP(C27,'SIND PITS'!$C$3:$F$102,4,0) -> 0 | I27: =VLOOKUP(C27,'SIND PITS'!$C$3:$G$102,5,0) -> 20 | K27: =SUM(D27:I27) -> 2720.77 | L27: 8000 | M27: 4000 | O27: =VLOOKUP(C27,'IP PITS'!$B$6:$I$86,8,0) -> 60 | P27: =+G27+H27+I27 -> 20 | Q27: =VLOOKUP(C27,'IP PITS'!$B$6:$N$86,13,0) -> 1359.23 | R27: =VLOOKUP(C27,'IP PITS'!$B$6:$Q$86,16,0) -> 0 | S27: =VLOOKUP(C27,'IP PITS'!$B$6:$R$86,17,0) -> 0 | U27: =+K27-O27-P27+Q27+R27+S27 -> 4000 | V27: =+M27-U27 -> 0 | X27: SEI0021
A28: SEI0022 | B28: IP INNOVACION | C28: Najera Lopez Raul | D28: =VLOOKUP(C28,'IP PITS'!$B$6:$V$86,21,0) -> 4397.6 | F28: =VLOOKUP(C28,'SIND PITS'!$C$3:$D$102,2,0) -> 602.4 | G28: =VLOOKUP(C28,'SIND PITS'!$C$3:$E$102,3,0) -> 121.5 | H28: =VLOOKUP(C28,'SIND PITS'!$C$3:$F$102,4,0) -> 0 | I28: =VLOOKUP(C28,'SIND PITS'!$C$3:$G$102,5,0) -> 0 | K28: =SUM(D28:I28) -> 5121.5 | L28: 10000 | M28: 5000 | O28: =VLOOKUP(C28,'IP PITS'!$B$6:$I$86,8,0) -> 0 | P28: =+G28+H28+I28 -> 121.5 | Q28: =VLOOKUP(C28,'IP PITS'!$B$6:$N$86,13,0) -> 0 | R28: =VLOOKUP(C28,'IP PITS'!$B$6:$Q$86,16,0) -> 0 | S28: =VLOOKUP(C28,'IP PITS'!$B$6:$R$86,17,0) -> 0 | U28: =+K28-O28-P28+Q28+R28+S28 -> 5000 | V28: =+M28-U28 -> 0 | X28: SEI0022
A29: SEI0023 | B29: IP INNOVACION | C29: Puente Murguia Luis Felipe | D29: =VLOOKUP(C29,'IP PITS'!$B$6:$V$86,21,0) -> 3271.6 | F29: =VLOOKUP(C29,'SIND PITS'!$C$3:$D$102,2,0) -> 228.4 | G29: =VLOOKUP(C29,'SIND PITS'!$C$3:$E$102,3,0) -> 253.25 | H29: =VLOOKUP(C29,'SIND PITS'!$C$3:$F$102,4,0) -> 0 | I29: =VLOOKUP(C29,'SIND PITS'!$C$3:$G$102,5,0) -> 0 | K29: =SUM(D29:I29) -> 3753.25 | L29: 7000 | M29: 3500 | O29: =VLOOKUP(C29,'IP PITS'!$B$6:$I$86,8,0) -> 0 | P29: =+G29+H29+I29 -> 253.25 | Q29: =VLOOKUP(C29,'IP PITS'!$B$6:$N$86,13,0) -> 0 | R29: =VLOOKUP(C29,'IP PITS'!$B$6:$Q$86,16,0) -> 0 | S29: =VLOOKUP(C29,'IP PITS'!$B$6:$R$86,17,0) -> 0 | U29: =+K29-O29-P29+Q29+R29+S29 -> 3500 | V29: =+M29-U29 -> 0 | X29: SEI0023
A30: SEI0029 | B30: IP INNOVACION | C30: Arceo Garcia Manuel Federico | D30: =VLOOKUP(C30,'IP PITS'!$B$6:$V$86,21,0) -> 2259.8 | F30: =VLOOKUP(C30,'SIND PITS'!$C$3:$D$102,2,0) -> 140.2 | G30: =VLOOKUP(C30,'SIND PITS'!$C$3:$E$102,3,0) -> 487.5 | H30: =VLOOKUP(C30,'SIND PITS'!$C$3:$F$102,4,0) -> 0 | I30: =VLOOKUP(C30,'SIND PITS'!$C$3:$G$102,5,0) -> 0 | K30: =SUM(D30:I30) -> 2887.5 | L30: 6000 | M30: 3000 | O30: =VLOOKUP(C30,'IP PITS'!$B$6:$I$86,8,0) -> 0 | P30: =+G30+H30+I30 -> 487.5 | Q30: =VLOOKUP(C30,'IP PITS'!$B$6:$N$86,13,0) -> 0 | R30: =VLOOKUP(C30,'IP PITS'!$B$6:$Q$86,16,0) -> 600 | S30: =VLOOKUP(C30,'IP PITS'!$B$6:$R$86,17,0) -> 0 | U30: =+K30-O30-P30+Q30+R30+S30 -> 3000 | V30: =+M30-U30 -> 0 | X30: SEI0029
A31: SEI0364 | B31: IP INNOVACION | C31: Dominguez Lopez Mayeli Del Pilar | D31: =VLOOKUP(C31,'IP PITS'!$B$6:$V$86,21,0) -> 1910 | F31: =VLOOKUP(C31,'SIND PITS'!$C$3:$D$102,2,0) -> 1423.33 | G31: =VLOOKUP(C31,'SIND PITS'!$C$3:$E$102,3,0) -> 1250 | H31: =VLOOKUP(C31,'SIND PITS'!$C$3:$F$102,4,0) -> 0 | I31: =VLOOKUP(C31,'SIND PITS'!$C$3:$G$102,5,0) -> 0 | K31: =SUM(D31:I31) -> 4583.33 | L31: 10000 | M31: 5000 | O31: =VLOOKUP(C31,'IP PITS'!$B$6:$I$86,8,0) -> 0 | P31: =+G31+H31+I31 -> 1250 | Q31: =VLOOKUP(C31,'IP PITS'!$B$6:$N$86,13,0) -> 0 | R31: =VLOOKUP(C31,'IP PITS'!$B$6:$Q$86,16,0) -> 0 | S31: =VLOOKUP(C31,'IP PITS'!$B$6:$R$86,17,0) -> 1666.67 | U31: =+K31-O31-P31+Q31+R31+S31 -> 5000 | V31: =+M31-U31 -> 0 | X31: SEI0364
A32: SEI0413 | B32: IP INNOVACION | C32: Courtenay Gutierrez Barry Vladimir | D32: =VLOOKUP(C32,'IP PITS'!$B$6:$V$86,21,0) -> 2443.4 | F32: =VLOOKUP(C32,'SIND PITS'!$C$3:$D$102,2,0) -> 56.6 | G32: =VLOOKUP(C32,'SIND PITS'!$C$3:$E$102,3,0) -> 395.5 | H32: =VLOOKUP(C32,'SIND PITS'!$C$3:$F$102,4,0) -> 0 | I32: =VLOOKUP(C32,'SIND PITS'!$C$3:$G$102,5,0) -> 0 | K32: =SUM(D32:I32) -> 2895.5 | L32: 5000 | M32: 2500 | O32: =VLOOKUP(C32,'IP PITS'!$B$6:$I$86,8,0) -> 0 | P32: =+G32+H32+I32 -> 395.5 | Q32: =VLOOKUP(C32,'IP PITS'!$B$6:$N$86,13,0) -> 0 | R32: =VLOOKUP(C32,'IP PITS'!$B$6:$Q$86,16,0) -> 0 | S32: =VLOOKUP(C32,'IP PITS'!$B$6:$R$86,17,0) -> 0 | U32: =+K32-O32-P32+Q32+R32+S32 -> 2500 | V32: =+M32-U32 -> 0 | X32: SEI0436
A33: SEI0424 | B33: IP INNOVACION | C33: Palacios Ramos Jesus | D33: =VLOOKUP(C33,'IP PITS'!$B$6:$V$86,21,0) -> 3576.8 | F33: =VLOOKUP(C33,'SIND PITS'!$C$3:$D$102,2,0) -> 423.2 | G33: =VLOOKUP(C33,'SIND PITS'!$C$3:$E$102,3,0) -> 349 | H33: =VLOOKUP(C33,'SIND PITS'!$C$3:$F$102,4,0) -> 0 | I33: =VLOOKUP(C33,'SIND PITS'!$C$3:$G$102,5,0) -> 0 | K33: =SUM(D33:I33) -> 4349 | L33: 8000 | M33: 4000 | O33: =VLOOKUP(C33,'IP PITS'!$B$6:$I$86,8,0) -> 0 | P33: =+G33+H33+I33 -> 349 | Q33: =VLOOKUP(C33,'IP PITS'!$B$6:$N$86,13,0) -> 0 | R33: =VLOOKUP(C33,'IP PITS'!$B$6:$Q$86,16,0) -> 0 | S33: =VLOOKUP(C33,'IP PITS'!$B$6:$R$86,17,0) -> 0 | U33: =+K33-O33-P33+Q33+R33+S33 -> 4000 | V33: =+M33-U33 -> 0 | X33: SEI0424
A34: SEI0428 | B34: IP INNOVACION | C34: Martinez Hernandez J. Antonio | D34: =VLOOKUP(C34,'IP PITS'!$B$6:$V$86,21,0) -> 3576.8 | F34: =VLOOKUP(C34,'SIND PITS'!$C$3:$D$102,2,0) -> 423.2 | G34: =VLOOKUP(C34,'SIND PITS'!$C$3:$E$102,3,0) -> 280 | H34: =VLOOKUP(C34,'SIND PITS'!$C$3:$F$102,4,0) -> 0 | I34: =VLOOKUP(C34,'SIND PITS'!$C$3:$G$102,5,0) -> 0 | K34: =SUM(D34:I34) -> 4280 | L34: 8000 | M34: 4000 | O34: =VLOOKUP(C34,'IP PITS'!$B$6:$I$86,8,0) -> 0 | P34: =+G34+H34+I34 -> 280 | Q34: =VLOOKUP(C34,'IP PITS'!$B$6:$N$86,13,0) -> 0 | R34: =VLOOKUP(C34,'IP PITS'!$B$6:$Q$86,16,0) -> 0 | S34: =VLOOKUP(C34,'IP PITS'!$B$6:$R$86,17,0) -> 0 | U34: =+K34-O34-P34+Q34+R34+S34 -> 4000 | V34: =+M34-U34 -> 0 | X34: SEI0452
A35: SEI0431 | B35: IP INNOVACION | C35: Alcaraz Conde Zabdi Guadalupe | D35: =VLOOKUP(C35,'IP PITS'!$B$6:$V$86,21,0) -> 1139.4 | F35: =VLOOKUP(C35,'SIND PITS'!$C$3:$D$102,2,0) -> 1260.6 | G35: =VLOOKUP(C35,'SIND PITS'!$C$3:$E$102,3,0) -> 292.5 | H35: =VLOOKUP(C35,'SIND PITS'!$C$3:$F$102,4,0) -> 0 | I35: =VLOOKUP(C35,'SIND PITS'!$C$3:$G$102,5,0) -> 0 | K35: =SUM(D35:I35) -> 2692.5 | L35: 6000 | M35: 3000 | O35: =VLOOKUP(C35,'IP PITS'!$B$6:$I$86,8,0) -> 0 | P35: =+G35+H35+I35 -> 292.5 | Q35: =VLOOKUP(C35,'IP PITS'!$B$6:$N$86,13,0) -> 0 | R35: =VLOOKUP(C35,'IP PITS'!$B$6:$Q$86,16,0) -> 600 | S35: =VLOOKUP(C35,'IP PITS'!$B$6:$R$86,17,0) -> 0 | U35: =+K35-O35-P35+Q35+R35+S35 -> 3000 | V35: =+M35-U35 -> 0 | X35: SEI0456
A36: SEI0438 | B36: IP INNOVACION | C36: Lopez Terron Roberto Porfirio | D36: =VLOOKUP(C36,'IP PITS'!$B$6:$V$86,21,0) -> 5939.6 | F36: =VLOOKUP(C36,'SIND PITS'!$C$3:$D$102,2,0) -> 1060.4 | G36: =VLOOKUP(C36,'SIND PITS'!$C$3:$E$102,3,0) -> 200 | H36: =VLOOKUP(C36,'SIND PITS'!$C$3:$F$102,4,0) -> 0 | I36: =VLOOKUP(C36,'SIND PITS'!$C$3:$G$102,5,0) -> 0 | K36: =SUM(D36:I36) -> 7200 | L36: 14000 | M36: 7000 | O36: =VLOOKUP(C36,'IP PITS'!$B$6:$I$86,8,0) -> 0 | P36: =+G36+H36+I36 -> 200 | Q36: =VLOOKUP(C36,'IP PITS'!$B$6:$N$86,13,0) -> 0 | R36: =VLOOKUP(C36,'IP PITS'!$B$6:$Q$86,16,0) -> 0 | S36: =VLOOKUP(C36,'IP PITS'!$B$6:$R$86,17,0) -> 0 | U36: =+K36-O36-P36+Q36+R36+S36 -> 7000 | V36: =+M36-U36 -> 0 | X36: SEI0463
A37: SEI0442 | B37: IP INNOVACION | C37: Chavez Pedraza Samuel | D37: =VLOOKUP(C37,'IP PITS'!$B$6:$V$86,21,0) -> 5939.6 | F37: =VLOOKUP(C37,'SIND PITS'!$C$3:$D$102,2,0) -> 1060.4 | G37: =VLOOKUP(C37,'SIND PITS'!$C$3:$E$102,3,0) -> 675 | H37: =VLOOKUP(C37,'SIND PITS'!$C$3:$F$102,4,0) -> 0 | I37: =VLOOKUP(C37,'SIND PITS'!$C$3:$G$102,5,0) -> 0 | K37: =SUM(D37:I37) -> 7675 | L37: 14000 | M37: 7000 | O37: =VLOOKUP(C37,'IP PITS'!$B$6:$I$86,8,0) -> 0 | P37: =+G37+H37+I37 -> 675 | Q37: =VLOOKUP(C37,'IP PITS'!$B$6:$N$86,13,0) -> 0 | R37: =VLOOKUP(C37,'IP PITS'!$B$6:$Q$86,16,0) -> 0 | S37: =VLOOKUP(C37,'IP PITS'!$B$6:$R$86,17,0) -> 0 | U37: =+K37-O37-P37+Q37+R37+S37 -> 7000 | V37: =+M37-U37 -> 0 | X37: SEI0467
... A40: SEI0449 | B40: IP INNOVACION | C40: Flores Cerrillos Jorge Humberto | D40: =VLOOKUP(C40,'IP PITS'!$B$6:$V$86,21,0) -> 3577 | F40: =VLOOKUP(C40,'SIND PITS'!$C$3:$D$102,2,0) -> 423 | G40: =VLOOKUP(C40,'SIND PITS'!$C$3:$E$102,3,0) -> 287 | H40: =VLOOKUP(C40,'SIND PITS'!$C$3:$F$102,4,0) -> 0 | I40: =VLOOKUP(C40,'SIND PITS'!$C$3:$G$102,5,0) -> 0 | K40: =SUM(D40:I40) -> 4287 | L40: 8000 | M40: 4000 | O40: =VLOOKUP(C40,'IP PITS'!$B$6:$I$86,8,0) -> 0 | P40: =+G40+H40+I40 -> 287 | Q40: =VLOOKUP(C40,'IP PITS'!$B$6:$N$86,13,0) -> 0 | R40: =VLOOKUP(C40,'IP PITS'!$B$6:$Q$86,16,0) -> 0 | S40: =VLOOKUP(C40,'IP PITS'!$B$6:$R$86,17,0) -> 0 | U40: =+K40-O40-P40+Q40+R40+S40 -> 4000 | V40: =+M40-U40 -> 0 | X40: SEI0474
A41: SEI0455 | B41: IP INNOVACION | C41: Perez Garcia Andres Alvaro | D41: =VLOOKUP(C41,'IP PITS'!$B$6:$V$86,21,0) -> 3344.2 | F41: =VLOOKUP(C41,'SIND PITS'!$C$3:$D$102,2,0) -> 389.14 | G41: =VLOOKUP(C41,'SIND PITS'!$C$3:$E$102,3,0) -> 140 | H41: =VLOOKUP(C41,'SIND PITS'!$C$3:$F$102,4,0) -> 0 | I41: =VLOOKUP(C41,'SIND PITS'!$C$3:$G$102,5,0) -> 0 | K41: =SUM(D41:I41) -> 3873.34 | L41: 8000 | M41: 4000 | O41: =VLOOKUP(C41,'IP PITS'!$B$6:$I$86,8,0) -> 0 | P41: =+G41+H41+I41 -> 140 | Q41: =VLOOKUP(C41,'IP PITS'!$B$6:$N$86,13,0) -> 0 | R41: =VLOOKUP(C41,'IP PITS'!$B$6:$Q$86,16,0) -> 0 | S41: =VLOOKUP(C41,'IP PITS'!$B$6:$R$86,17,0) -> 0 | U41: =+K41-O41-P41+Q41+R41+S41 -> 3733.34 | V41: =+M41-U41 -> 266.66 | W41: 1 FALTA | X41: SEI0494
A42: SEI0456 | B42: IP INNOVACION | C42: Chavira Garcia David Fernando | D42: =VLOOKUP(C42,'IP PITS'!$B$6:$V$86,21,0) -> 4397.6 | F42: =VLOOKUP(C42,'SIND PITS'!$C$3:$D$102,2,0) -> 602.4 | G42: =VLOOKUP(C42,'SIND PITS'!$C$3:$E$102,3,0) -> 121.5 | H42: =VLOOKUP(C42,'SIND PITS'!$C$3:$F$102,4,0) -> 0 | I42: =VLOOKUP(C42,'SIND PITS'!$C$3:$G$102,5,0) -> 0 | K42: =SUM(D42:I42) -> 5121.5 | L42: 10000 | M42: 5000 | O42: =VLOOKUP(C42,'IP PITS'!$B$6:$I$86,8,0) -> 0 | P42: =+G42+H42+I42 -> 121.5 | Q42: =VLOOKUP(C42,'IP PITS'!$B$6:$N$86,13,0) -> 0 | R42: =VLOOKUP(C42,'IP PITS'!$B$6:$Q$86,16,0) -> 0 | S42: =VLOOKUP(C42,'IP PITS'!$B$6:$R$86,17,0) -> 0 | U42: =+K42-O42-P42+Q42+R42+S42 -> 5000 | V42: =+M42-U42 -> 0 | X42: SEI0495
A43: SEI0457 | B43: IP INNOVACION | C43: Guerrero Lara Cesar Adrian | D43: =VLOOKUP(C43,'IP PITS'!$B$6:$V$86,21,0) -> 3231.6 | F43: =VLOOKUP(C43,'SIND PITS'!$C$3:$D$102,2,0) -> 423.15 | G43: =VLOOKUP(C43,'SIND PITS'!$C$3:$E$102,3,0) -> 183.5 | H43: =VLOOKUP(C43,'SIND PITS'!$C$3:$F$102,4,0) -> 0 | I43: =VLOOKUP(C43,'SIND PITS'!$C$3:$G$102,5,0) -> 0 | K43: =SUM(D43:I43) -> 3838.25 | L43: 8000 | M43: 4000 | O43: =VLOOKUP(C43,'IP PITS'!$B$6:$I$86,8,0) -> 0 | P43: =+G43+H43+I43 -> 183.5 | Q43: =VLOOKUP(C43,'IP PITS'!$B$6:$N$86,13,0) -> 0 | R43: =VLOOKUP(C43,'IP PITS'!$B$6:$Q$86,16,0) -> 0 | S43: =VLOOKUP(C43,'IP PITS'!$B$6:$R$86,17,0) -> 345.25 | U43: =+K43-O43-P43+Q43+R43+S43 -> 4000 | V43: =+M43-U43 -> 0 | X43: SEI0496
A44: SEI0458 | B44: IP INNOVACION | C44: Martinez Zamora Gerardo Mario | D44: =VLOOKUP(C44,'IP PITS'!$B$6:$V$86,21,0) -> 1825.8 | F44: =VLOOKUP(C44,'SIND PITS'!$C$3:$D$102,2,0) -> 558.505 | G44: =VLOOKUP(C44,'SIND PITS'!$C$3:$E$102,3,0) -> 858.5 | H44: =VLOOKUP(C44,'SIND PITS'!$C$3:$F$102,4,0) -> 0 | I44: =VLOOKUP(C44,'SIND PITS'!$C$3:$G$102,5,0) -> 0 | K44: =SUM(D44:I44) -> 3242.805 | L44: 9550.01 | M44: 4775.005 | O44: =VLOOKUP(C44,'IP PITS'!$B$6:$I$86,8,0) -> 0 | P44: =+G44+H44+I44 -> 858.5 | Q44: =VLOOKUP(C44,'IP PITS'!$B$6:$N$86,13,0) -> 1528.5 | R44: =VLOOKUP(C44,'IP PITS'!$B$6:$Q$86,16,0) -> 0 | S44: =VLOOKUP(C44,'IP PITS'!$B$6:$R$86,17,0) -> 862.2 | U44: =+K44-O44-P44+Q44+R44+S44 -> 4775.005 | V44: =+M44-U44 -> 0 | X44: SEI0497
A45: SEI0460 | B45: IP INNOVACION | C45: Castellon Ramos Rene | D45: =VLOOKUP(C45,'IP PITS'!$B$6:$V$86,21,0) -> 1076.6 | F45: =VLOOKUP(C45,'SIND PITS'!$C$3:$D$102,2,0) -> 1827.515 | G45: =VLOOKUP(C45,'SIND PITS'!$C$3:$E$102,3,0) -> 150 | H45: =VLOOKUP(C45,'SIND PITS'!$C$3:$F$102,4,0) -> 0 | I45: =VLOOKUP(C45,'SIND PITS'!$C$3:$G$102,5,0) -> 0 | K45: =SUM(D45:I45) -> 3054.115 | L45: 7505.99 | M45: 3752.995 | O45: =VLOOKUP(C45,'IP PITS'!$B$6:$I$86,8,0) -> 0 | P45: =+G45+H45+I45 -> 150 | Q45: =VLOOKUP(C45,'IP PITS'!$B$6:$N$86,13,0) -> 0 | R45: =VLOOKUP(C45,'IP PITS'!$B$6:$Q$86,16,0) -> 0 | S45: =VLOOKUP(C45,'IP PITS'!$B$6:$R$86,17,0) -> 848.88 | U45: =+K45-O45-P45+Q45+R45+S45 -> 3752.995 | V45: =+M45-U45 -> 0 | X45: SEI0499
A46: SEI0461 | B46: IP INNOVACION | C46: Flores Franco Marco | D46: =VLOOKUP(C46,'IP PITS'!$B$6:$V$86,21,0) -> 3791.8 | F46: =VLOOKUP(C46,'SIND PITS'!$C$3:$D$102,2,0) -> 458.205 | G46: =VLOOKUP(C46,'SIND PITS'!$C$3:$E$102,3,0) -> 1200 | H46: =VLOOKUP(C46,'SIND PITS'!$C$3:$F$102,4,0) -> 0 | I46: =VLOOKUP(C46,'SIND PITS'!$C$3:$G$102,5,0) -> 0 | K46: =SUM(D46:I46) -> 5450.005 | L46: 8500.01 | M46: 4250.005 | O46: =VLOOKUP(C46,'IP PITS'!$B$6:$I$86,8,0) -> 0 | P46: =+G46+H46+I46 -> 1200 | Q46: =VLOOKUP(C46,'IP PITS'!$B$6:$N$86,13,0) -> 0 | R46: =VLOOKUP(C46,'IP PITS'!$B$6:$Q$86,16,0) -> 0 | S46: =VLOOKUP(C46,'IP PITS'!$B$6:$R$86,17,0) -> 0 | U46: =+K46-O46-P46+Q46+R46+S46 -> 4250.005 | V46: =+M46-U46 -> 0 | X46: SEI0500
A47: SEI0462 | B47: IP INNOVACION | C47: Chavez Saucedo Jorge Arturo | D47: =VLOOKUP(C47,'IP PITS'!$B$6:$V$86,21,0) -> 3425.8 | F47: =VLOOKUP(C47,'SIND PITS'!$C$3:$D$102,2,0) -> 387.54 | G47: =VLOOKUP(C47,'SIND PITS'!$C$3:$E$102,3,0) -> 224.25 | H47: =VLOOKUP(C47,'SIND PITS'!$C$3:$F$102,4,0) -> 0 | I47: =VLOOKUP(C47,'SIND PITS'!$C$3:$G$102,5,0) -> 0 | K47: =SUM(D47:I47) -> 4037.59 | L47: 8000 | M47: 4000 | O47: =VLOOKUP(C47,'IP PITS'!$B$6:$I$86,8,0) -> 80 | P47: =+G47+H47+I47 -> 224.25 | Q47: =VLOOKUP(C47,'IP PITS'!$B$6:$N$86,13,0) -> 0 | R47: =VLOOKUP(C47,'IP PITS'!$B$6:$Q$86,16,0) -> 0 | S47: =VLOOKUP(C47,'IP PITS'!$B$6:$R$86,17,0) -> 0 | U47: =+K47-O47-P47+Q47+R47+S47 -> 3733.34 | V47: =+M47-U47 -> 266.66 | W47: 1 FALTA | X47: SEI0516
A48: SEI0464 | B48: IP INNOVACION | C48: Hueramo Hueramo Jesus Daniel | D48: =VLOOKUP(C48,'IP PITS'!$B$6:$V$86,21,0) -> 2876.6 | F48: =VLOOKUP(C48,'SIND PITS'!$C$3:$D$102,2,0) -> 1050.905 | G48: =VLOOKUP(C48,'SIND PITS'!$C$3:$E$102,3,0) -> 306 | H48: =VLOOKUP(C48,'SIND PITS'!$C$3:$F$102,4,0) -> 0 | I48: =VLOOKUP(C48,'SIND PITS'!$C$3:$G$102,5,0) -> 0 | K48: =SUM(D48:I48) -> 4233.505 | L48: 8500.01 | M48: 4250.005 | O48: =VLOOKUP(C48,'IP PITS'!$B$6:$I$86,8,0) -> 0 | P48: =+G48+H48+I48 -> 306 | Q48: =VLOOKUP(C48,'IP PITS'!$B$6:$N$86,13,0) -> 0 | R48: =VLOOKUP(C48,'IP PITS'!$B$6:$Q$86,16,0) -> 0 | S48: =VLOOKUP(C48,'IP PITS'!$B$6:$R$86,17,0) -> 322.5 | U48: =+K48-O48-P48+Q48+R48+S48 -> 4250.005 | V48: =+M48-U48 -> 0 | X48: SEI 502
A49: SEI0465 | B49: IP INNOVACION | C49: Sandoval Garcia Luis | D49: =VLOOKUP(C49,'IP PITS'!$B$6:$V$86,21,0) -> 3576.8 | F49: =VLOOKUP(C49,'SIND PITS'!$C$3:$D$102,2,0) -> 423.2 | G49: =VLOOKUP(C49,'SIND PITS'!$C$3:$E$102,3,0) -> 262.5 | H49: =VLOOKUP(C49,'SIND PITS'!$C$3:$F$102,4,0) -> 0 | I49: =VLOOKUP(C49,'SIND PITS'!$C$3:$G$102,5,0) -> 0 | K49: =SUM(D49:I49) -> 4262.5 | L49: 8000 | M49: 4000 | O49: =VLOOKUP(C49,'IP PITS'!$B$6:$I$86,8,0) -> 0 | P49: =+G49+H49+I49 -> 262.5 | Q49: =VLOOKUP(C49,'IP PITS'!$B$6:$N$86,13,0) -> 0 | R49: =VLOOKUP(C49,'IP PITS'!$B$6:$Q$86,16,0) -> 0 | S49: =VLOOKUP(C49,'IP PITS'!$B$6:$R$86,17,0) -> 0 | U49: =+K49-O49-P49+Q49+R49+S49 -> 4000 | V49: =+M49-U49 -> 0 | X49: SEI0503
A50: SEI0467 | B50: IP INNOVACION | C50: Vaca Valdez Guillermo | D50: =VLOOKUP(C50,'IP PITS'!$B$6:$V$86,21,0) -> 1328.4 | F50: =VLOOKUP(C50,'SIND PITS'!$C$3:$D$102,2,0) -> 423.25 | G50: =VLOOKUP(C50,'SIND PITS'!$C$3:$E$102,3,0) -> 471 | H50: =VLOOKUP(C50,'SIND PITS'!$C$3:$F$102,4,0) -> 0 | I50: =VLOOKUP(C50,'SIND PITS'!$C$3:$G$102,5,0) -> 0 | K50: =SUM(D50:I50) -> 2222.65 | L50: 8000 | M50: 4000 | O50: =VLOOKUP(C50,'IP PITS'!$B$6:$I$86,8,0) -> 0 | P50: =+G50+H50+I50 -> 471 | Q50: =VLOOKUP(C50,'IP PITS'!$B$6:$N$86,13,0) -> 1848.35 | R50: =VLOOKUP(C50,'IP PITS'!$B$6:$Q$86,16,0) -> 0 | S50: =VLOOKUP(C50,'IP PITS'!$B$6:$R$86,17,0) -> 400 | U50: =+K50-O50-P50+Q50+R50+S50 -> 4000 | V50: =+M50-U50 -> 0 | X50: SEI0505
A51: SEI0469 | B51: IP INNOVACION | C51: Martinez Morales Jose Martin | D51: =VLOOKUP(C51,'IP PITS'!$B$6:$V$86,21,0) -> 5939.6 | F51: =VLOOKUP(C51,'SIND PITS'!$C$3:$D$102,2,0) -> 1060.4 | G51: =VLOOKUP(C51,'SIND PITS'!$C$3:$E$102,3,0) -> 303.5 | H51: =VLOOKUP(C51,'SIND PITS'!$C$3:$F$102,4,0) -> 0 | I51: =VLOOKUP(C51,'SIND PITS'!$C$3:$G$102,5,0) -> 0 | K51: =SUM(D51:I51) -> 7303.5 | L51: 14000 | M51: 7000 | O51: =VLOOKUP(C51,'IP PITS'!$B$6:$I$86,8,0) -> 0 | P51: =+G51+H51+I51 -> 303.5 | Q51: =VLOOKUP(C51,'IP PITS'!$B$6:$N$86,13,0) -> 0 | R51: =VLOOKUP(C51,'IP PITS'!$B$6:$Q$86,16,0) -> 0 | S51: =VLOOKUP(C51,'IP PITS'!$B$6:$R$86,17,0) -> 0 | U51: =+K51-O51-P51+Q51+R51+S51 -> 7000 | V51: =+M51-U51 -> 0 | X51: SEI0511
A52: SEI0472 | B52: IP INNOVACION | C52: Arzate Gil Juan Sebastian | D52: =VLOOKUP(C52,'IP PITS'!$B$6:$V$86,21,0) -> 2888.4 | F52: =VLOOKUP(C52,'SIND PITS'!$C$3:$D$102,2,0) -> 423.3 | G52: =VLOOKUP(C52,'SIND PITS'!$C$3:$E$102,3,0) -> 463 | H52: =VLOOKUP(C52,'SIND PITS'!$C$3:$F$102,4,0) -> 0 | I52: =VLOOKUP(C52,'SIND PITS'!$C$3:$G$102,5,0) -> 0 | K52: =SUM(D52:I52) -> 3774.7 | L52: 8000 | M52: 4000 | O52: =VLOOKUP(C52,'IP PITS'!$B$6:$I$86,8,0) -> 0 | P52: =+G52+H52+I52 -> 463 | Q52: =VLOOKUP(C52,'IP PITS'!$B$6:$N$86,13,0) -> 0 | R52: =VLOOKUP(C52,'IP PITS'!$B$6:$Q$86,16,0) -> 0 | S52: =VLOOKUP(C52,'IP PITS'!$B$6:$R$86,17,0) -> 688.3 | U52: =+K52-O52-P52+Q52+R52+S52 -> 4000 | V52: =+M52-U52 -> 0 | X52: SEI0550
A53: SEI0473 | B53: IP INNOVACION | C53: Torres Velazquez Juan Antonio | D53: =VLOOKUP(C53,'IP PITS'!$B$6:$V$86,21,0) -> 3577 | F53: =VLOOKUP(C53,'SIND PITS'!$C$3:$D$102,2,0) -> 423 | G53: =VLOOKUP(C53,'SIND PITS'!$C$3:$E$102,3,0) -> 546 | H53: =VLOOKUP(C53,'SIND PITS'!$C$3:$F$102,4,0) -> 0 | I53: =VLOOKUP(C53,'SIND PITS'!$C$3:$G$102,5,0) -> 0 | K53: =SUM(D53:I53) -> 4546 | L53: 8000 | M53: 4000 | O53: =VLOOKUP(C53,'IP PITS'!$B$6:$I$86,8,0) -> 0 | P53: =+G53+H53+I53 -> 546 | Q53: =VLOOKUP(C53,'IP PITS'!$B$6:$N$86,13,0) -> 0 | R53: =VLOOKUP(C53,'IP PITS'!$B$6:$Q$86,16,0) -> 0 | S53: =VLOOKUP(C53,'IP PITS'!$B$6:$R$86,17,0) -> 0 | U53: =+K53-O53-P53+Q53+R53+S53 -> 4000 | V53: =+M53-U53 -> 0 | X53: SEI0604
A54: SEI0474 | B54: IP INNOVACION | C54: Enriquez Zamora Jessica Del Rocio | D54: =VLOOKUP(C54,'IP PITS'!$B$6:$V$86,21,0) -> 2859.6 | F54: =VLOOKUP(C54,'SIND PITS'!$C$3:$D$102,2,0) -> 140.4 | G54: =VLOOKUP(C54,'SIND PITS'!$C$3:$E$102,3,0) -> 292.5 | H54: =VLOOKUP(C54,'SIND PITS'!$C$3:$F$102,4,0) -> 0 | I54: =VLOOKUP(C54,'SIND PITS'!$C$3:$G$102,5,0) -> 0 | K54: =SUM(D54:I54) -> 3292.5 | L54: 6000 | M54: 3000 | O54: =VLOOKUP(C54,'IP PITS'!$B$6:$I$86,8,0) -> 0 | P54: =+G54+H54+I54 -> 292.5 | Q54: =VLOOKUP(C54,'IP PITS'!$B$6:$N$86,13,0) -> 0 | R54: =VLOOKUP(C54,'IP PITS'!$B$6:$Q$86,16,0) -> 0 | S54: =VLOOKUP(C54,'IP PITS'!$B$6:$R$86,17,0) -> 0 | U54: =+K54-O54-P54+Q54+R54+S54 -> 3000 | V54: =+M54-U54 -> 0 | X54: SEI0600
A55: SEI0475 | B55: IP INNOVACION | C55: Moreno Quiroga Ana Sarahi | D55: =VLOOKUP(C55,'IP PITS'!$B$6:$V$86,21,0) -> 3576.8 | F55: =VLOOKUP(C55,'SIND PITS'!$C$3:$D$102,2,0) -> 423.2 | G55: =VLOOKUP(C55,'SIND PITS'!$C$3:$E$102,3,0) -> 1250 | H55: =VLOOKUP(C55,'SIND PITS'!$C$3:$F$102,4,0) -> 0 | I55: =VLOOKUP(C55,'SIND PITS'!$C$3:$G$102,5,0) -> 0 | K55: =SUM(D55:I55) -> 5250 | L55: 8000 | M55: 4000 | O55: =VLOOKUP(C55,'IP PITS'!$B$6:$I$86,8,0) -> 0 | P55: =+G55+H55+I55 -> 1250 | Q55: =VLOOKUP(C55,'IP PITS'!$B$6:$N$86,13,0) -> 0 | R55: =VLOOKUP(C55,'IP PITS'!$B$6:$Q$86,16,0) -> 0 | S55: =VLOOKUP(C55,'IP PITS'!$B$6:$R$86,17,0) -> 0 | U55: =+K55-O55-P55+Q55+R55+S55 -> 4000 | V55: =+M55-U55 -> 0 | X55: SEI0601
A56: SEI0476 | B56: IP INNOVACION | C56: Hernandez Garcia Manuel Alejandro | D56: =VLOOKUP(C56,'IP PITS'!$B$6:$V$86,21,0) -> 3578.6 | F56: =VLOOKUP(C56,'SIND PITS'!$C$3:$D$102,2,0) -> 421.4 | G56: =VLOOKUP(C56,'SIND PITS'!$C$3:$E$102,3,0) -> 359 | H56: =VLOOKUP(C56,'SIND PITS'!$C$3:$F$102,4,0) -> 0 | I56: =VLOOKUP(C56,'SIND PITS'!$C$3:$G$102,5,0) -> 0 | K56: =SUM(D56:I56) -> 4359 | L56: 8000 | M56: 4000 | O56: =VLOOKUP(C56,'IP PITS'!$B$6:$I$86,8,0) -> 0 | P56: =+G56+H56+I56 -> 359 | Q56: =VLOOKUP(C56,'IP PITS'!$B$6:$N$86,13,0) -> 0 | R56: =VLOOKUP(C56,'IP PITS'!$B$6:$Q$86,16,0) -> 0 | S56: =VLOOKUP(C56,'IP PITS'!$B$6:$R$86,17,0) -> 0 | U56: =+K56-O56-P56+Q56+R56+S56 -> 4000 | V56: =+M56-U56 -> 0 | X56: SEI0602
A57: SEI0477 | B57: IP INNOVACION | C57: Sandoval Medina Demetrio | D57: =VLOOKUP(C57,'IP PITS'!$B$6:$V$86,21,0) -> 3578.8 | F57: =VLOOKUP(C57,'SIND PITS'!$C$3:$D$102,2,0) -> 421.2 | G57: =VLOOKUP(C57,'SIND PITS'!$C$3:$E$102,3,0) -> 450 | H57: =VLOOKUP(C57,'SIND PITS'!$C$3:$F$102,4,0) -> 0 | I57: =VLOOKUP(C57,'SIND PITS'!$C$3:$G$102,5,0) -> 0 | K57: =SUM(D57:I57) -> 4450 | L57: 8000 | M57: 4000 | O57: =VLOOKUP(C57,'IP PITS'!$B$6:$I$86,8,0) -> 0 | P57: =+G57+H57+I57 -> 450 | Q57: =VLOOKUP(C57,'IP PITS'!$B$6:$N$86,13,0) -> 0 | R57: =VLOOKUP(C57,'IP PITS'!$B$6:$Q$86,16,0) -> 0 | S57: =VLOOKUP(C57,'IP PITS'!$B$6:$R$86,17,0) -> 0 | U57: =+K57-O57-P57+Q57+R57+S57 -> 4000 | V57: =+M57-U57 -> 0 | X57: SEI0603
A58: SEI479 | B58: IP INNOVACION | C58: Cruz Perez Alejandro Nezahualcoyotl | D58: =VLOOKUP(C58,'IP PITS'!$B$6:$V$86,21,0) -> 3577 | F58: =VLOOKUP(C58,'SIND PITS'!$C$3:$D$102,2,0) -> 423 | G58: =VLOOKUP(C58,'SIND PITS'!$C$3:$E$102,3,0) -> 474 | H58: =VLOOKUP(C58,'SIND PITS'!$C$3:$F$102,4,0) -> 0 | I58: =VLOOKUP(C58,'SIND PITS'!$C$3:$G$102,5,0) -> 0 | K58: =SUM(D58:I58) -> 4474 | L58: 8000 | M58: 4000 | O58: =VLOOKUP(C58,'IP PITS'!$B$6:$I$86,8,0) -> 0 | P58: =+G58+H58+I58 -> 474 | Q58: =VLOOKUP(C58,'IP PITS'!$B$6:$N$86,13,0) -> 0 | R58: =VLOOKUP(C58,'IP PITS'!$B$6:$Q$86,16,0) -> 0 | S58: =VLOOKUP(C58,'IP PITS'!$B$6:$R$86,17,0) -> 0 | U58: =+K58-O58-P58+Q58+R58+S58 -> 4000 | V58: =+M58-U58 -> 0 | X58: SEI0606
A59: SEI0415 | B59: IP INNOVACION | C59: Mireles Casillas Brenda Cristina | D59: =VLOOKUP(C59,'IP PITS'!$B$6:$V$86,21,0) -> 2234 | F59: =VLOOKUP(C59,'SIND PITS'!$C$3:$D$102,2,0) -> 2266 | G59: =VLOOKUP(C59,'SIND PITS'!$C$3:$E$102,3,0) -> 0 | H59: =VLOOKUP(C59,'SIND PITS'!$C$3:$F$102,4,0) -> 0 | I59: =VLOOKUP(C59,'SIND PITS'!$C$3:$G$102,5,0) -> 0 | K59: =SUM(D59:I59) -> 4500 | L59: 9000 | M59: 4500 | O59: =VLOOKUP(C59,'IP PITS'!$B$6:$I$86,8,0) -> 0 | P59: =+G59+H59+I59 -> 0 | Q59: =VLOOKUP(C59,'IP PITS'!$B$6:$N$86,13,0) -> 0 | R59: =VLOOKUP(C59,'IP PITS'!$B$6:$Q$86,16,0) -> 0 | S59: =VLOOKUP(C59,'IP PITS'!$B$6:$R$86,17,0) -> 0 | U59: =+K59-O59-P59+Q59+R59+S59 -> 4500 | V59: =+M59-U59 -> 0 | X59: SEI0446
... A79: SEI0515 | B79: IP INNOVACION | C79: Ruiz Flores Aldo Tomas | D79: =VLOOKUP(C79,'IP PITS'!$B$6:$V$86,21,0) -> 2278 | F79: =VLOOKUP(C79,'SIND PITS'!$C$3:$D$102,2,0) -> 140.27 | G79: =VLOOKUP(C79,'SIND PITS'!$C$3:$E$102,3,0) -> 337.5 | H79: =VLOOKUP(C79,'SIND PITS'!$C$3:$F$102,4,0) -> 0 | I79: =VLOOKUP(C79,'SIND PITS'!$C$3:$G$102,5,0) -> 0 | K79: =SUM(D79:I79) -> 2755.77 | L79: 6000 | M79: 3000 | O79: =VLOOKUP(C79,'IP PITS'!$B$6:$I$86,8,0) -> 0 | P79: =+G79+H79+I79 -> 337.5 | Q79: =VLOOKUP(C79,'IP PITS'!$B$6:$N$86,13,0) -> 0 | R79: =VLOOKUP(C79,'IP PITS'!$B$6:$Q$86,16,0) -> 581.73 | S79: =VLOOKUP(C79,'IP PITS'!$B$6:$R$86,17,0) -> 0 | U79: =+K79-O79-P79+Q79+R79+S79 -> 3000 | V79: =+M79-U79 -> 0 | X79: SEI0615
A80: SEI0028 | B80: IP INNOVACION | C80: Jimenez Alcaraz Elizabeth | D80: =VLOOKUP(C80,'IP PITS'!$B$6:$V$86,21,0) -> 2859.6 | F80: =VLOOKUP(C80,'SIND PITS'!$C$3:$D$102,2,0) -> 590.4 | G80: =VLOOKUP(C80,'SIND PITS'!$C$3:$E$102,3,0) -> 0 | H80: =VLOOKUP(C80,'SIND PITS'!$C$3:$F$102,4,0) -> 0 | I80: =VLOOKUP(C80,'SIND PITS'!$C$3:$G$102,5,0) -> 0 | K80: =SUM(D80:I80) -> 3450 | L80: 6900 | M80: 3450 | N80: 0 | O80: =VLOOKUP(C80,'IP PITS'!$B$6:$I$86,8,0) -> 0 | P80: =+G80+H80+I80 -> 0 | Q80: =VLOOKUP(C80,'IP PITS'!$B$6:$N$86,13,0) -> 0 | R80: =VLOOKUP(C80,'IP PITS'!$B$6:$Q$86,16,0) -> 0 | S80: =VLOOKUP(C80,'IP PITS'!$B$6:$R$86,17,0) -> 0 | U80: =+K80-O80-P80+Q80+R80+S80 -> 3450 | V80: =+M80-U80 -> 0 | X80: SEI0028
A81: SEI0517 | B81: IP INNOVACION | C81: Macias Torres Enrique | D81: =VLOOKUP(C81,'IP PITS'!$B$6:$V$86,21,0) -> 3447.8 | F81: =VLOOKUP(C81,'SIND PITS'!$C$3:$D$102,2,0) -> 6527.2 | G81: =VLOOKUP(C81,'SIND PITS'!$C$3:$E$102,3,0) -> 2102.5 | H81: =VLOOKUP(C81,'SIND PITS'!$C$3:$F$102,4,0) -> 0 | I81: =VLOOKUP(C81,'SIND PITS'!$C$3:$G$102,5,0) -> 0 | K81: =SUM(D81:I81) -> 12077.5 | L81: 19950 | M81: 9975 | O81: =VLOOKUP(C81,'IP PITS'!$B$6:$I$86,8,0) -> 0 | P81: =+G81+H81+I81 -> 2102.5 | Q81: =VLOOKUP(C81,'IP PITS'!$B$6:$N$86,13,0) -> 0 | R81: =VLOOKUP(C81,'IP PITS'!$B$6:$Q$86,16,0) -> 0 | S81: =VLOOKUP(C81,'IP PITS'!$B$6:$R$86,17,0) -> 0 | U81: =+K81-O81-P81+Q81+R81+S81 -> 9975 | V81: =+M81-U81 -> 0 | X81: SEI0120
A82: SEI0519 | B82: IP INNOVACION | C82: Palacios Vega Luis Rosendo | D82: =VLOOKUP(C82,'IP PITS'!$B$6:$V$86,21,0) -> 2443.6 | F82: =VLOOKUP(C82,'SIND PITS'!$C$3:$D$102,2,0) -> 56.4 | G82: =VLOOKUP(C82,'SIND PITS'!$C$3:$E$102,3,0) -> 186.5 | H82: =VLOOKUP(C82,'SIND PITS'!$C$3:$F$102,4,0) -> 0 | I82: =VLOOKUP(C82,'SIND PITS'!$C$3:$G$102,5,0) -> 0 | K82: =SUM(D82:I82) -> 2686.5 | L82: 5000 | M82: 2500 | O82: =VLOOKUP(C82,'IP PITS'!$B$6:$I$86,8,0) -> 0 | P82: =+G82+H82+I82 -> 186.5 | Q82: =VLOOKUP(C82,'IP PITS'!$B$6:$N$86,13,0) -> 0 | R82: =VLOOKUP(C82,'IP PITS'!$B$6:$Q$86,16,0) -> 0 | S82: =VLOOKUP(C82,'IP PITS'!$B$6:$R$86,17,0) -> 0 | U82: =+K82-O82-P82+Q82+R82+S82 -> 2500 | V82: =+M82-U82 -> 0 | X82: SEI0519
A83: SEI0521 | B83: IP INNOVACION | C83: Rondero Savin Jacinto | D83: =VLOOKUP(C83,'IP PITS'!$B$6:$V$86,21,0) -> 3272.8 | F83: =VLOOKUP(C83,'SIND PITS'!$C$3:$D$102,2,0) -> 227.2 | G83: =VLOOKUP(C83,'SIND PITS'!$C$3:$E$102,3,0) -> 0 | H83: =VLOOKUP(C83,'SIND PITS'!$C$3:$F$102,4,0) -> 0 | I83: =VLOOKUP(C83,'SIND PITS'!$C$3:$G$102,5,0) -> 0 | K83: =SUM(D83:I83) -> 3500 | L83: 7000 | M83: 3500 | O83: =VLOOKUP(C83,'IP PITS'!$B$6:$I$86,8,0) -> 0 | P83: =+G83+H83+I83 -> 0 | Q83: =VLOOKUP(C83,'IP PITS'!$B$6:$N$86,13,0) -> 0 | R83: =VLOOKUP(C83,'IP PITS'!$B$6:$Q$86,16,0) -> 0 | S83: =VLOOKUP(C83,'IP PITS'!$B$6:$R$86,17,0) -> 0 | U83: =+K83-O83-P83+Q83+R83+S83 -> 3500 | V83: =+M83-U83 -> 0 | X83: SEI0622
A84: SEI0522 | B84: IP INNOVACION | C84: Peña Lopez Abigail | D84: =VLOOKUP(C84,'IP PITS'!$B$6:$V$86,21,0) -> 3228.4 | F84: =VLOOKUP(C84,'SIND PITS'!$C$3:$D$102,2,0) -> 221.6 | G84: =VLOOKUP(C84,'SIND PITS'!$C$3:$E$102,3,0) -> 0 | H84: =VLOOKUP(C84,'SIND PITS'!$C$3:$F$102,4,0) -> 0 | I84: =VLOOKUP(C84,'SIND PITS'!$C$3:$G$102,5,0) -> 0 | K84: =SUM(D84:I84) -> 3450 | L84: 6900 | M84: 3450 | O84: =VLOOKUP(C84,'IP PITS'!$B$6:$I$86,8,0) -> 0 | P84: =+G84+H84+I84 -> 0 | Q84: =VLOOKUP(C84,'IP PITS'!$B$6:$N$86,13,0) -> 0 | R84: =VLOOKUP(C84,'IP PITS'!$B$6:$Q$86,16,0) -> 0 | S84: =VLOOKUP(C84,'IP PITS'!$B$6:$R$86,17,0) -> 0 | U84: =+K84-O84-P84+Q84+R84+S84 -> 3450 | V84: =+M84-U84 -> 0 | X84: SEI0623
A85: SEI0523 | B85: IP INNOVACION | C85: Hernandez Rodriguez Jorge | D85: =VLOOKUP(C85,'IP PITS'!$B$6:$V$86,21,0) -> 1808.4 | F85: =VLOOKUP(C85,'SIND PITS'!$C$3:$D$102,2,0) -> 228.47 | G85: =VLOOKUP(C85,'SIND PITS'!$C$3:$E$102,3,0) -> 300 | H85: =VLOOKUP(C85,'SIND PITS'!$C$3:$F$102,4,0) -> 0 | I85: =VLOOKUP(C85,'SIND PITS'!$C$3:$G$102,5,0) -> 0 | K85: =SUM(D85:I85) -> 2336.87 | L85: 7000 | M85: 3500 | O85: =VLOOKUP(C85,'IP PITS'!$B$6:$I$86,8,0) -> 0 | P85: =+G85+H85+I85 -> 300 | Q85: =VLOOKUP(C85,'IP PITS'!$B$6:$N$86,13,0) -> 1463.13 | R85: =VLOOKUP(C85,'IP PITS'!$B$6:$Q$86,16,0) -> 0 | S85: =VLOOKUP(C85,'IP PITS'!$B$6:$R$86,17,0) -> 0 | U85: =+K85-O85-P85+Q85+R85+S85 -> 3500 | V85: =+M85-U85 -> 0 | X85: SEI0624
A86: SEI0524 | B86: IP INNOVACION | C86: Orea Gonzalez Concepcion Esteban | D86: =VLOOKUP(C86,'IP PITS'!$B$6:$V$86,21,0) -> 2969.2 | F86: =VLOOKUP(C86,'SIND PITS'!$C$3:$D$102,2,0) -> 180.8 | G86: =VLOOKUP(C86,'SIND PITS'!$C$3:$E$102,3,0) -> 843.75 | H86: =VLOOKUP(C86,'SIND PITS'!$C$3:$F$102,4,0) -> 0 | I86: =VLOOKUP(C86,'SIND PITS'!$C$3:$G$102,5,0) -> 0 | K86: =SUM(D86:I86) -> 3993.75 | L86: 6300 | M86: 3150 | O86: =VLOOKUP(C86,'IP PITS'!$B$6:$I$86,8,0) -> 0 | P86: =+G86+H86+I86 -> 843.75 | Q86: =VLOOKUP(C86,'IP PITS'!$B$6:$N$86,13,0) -> 0 | R86: =VLOOKUP(C86,'IP PITS'!$B$6:$Q$86,16,0) -> 0 | S86: =VLOOKUP(C86,'IP PITS'!$B$6:$R$86,17,0) -> 0 | U86: =+K86-O86-P86+Q86+R86+S86 -> 3150 | V86: =+M86-U86 -> 0 | X86: SEI0625
A87: SEI0525 | B87: IP INNOVACION | C87: Lizaran Maceda Jesus | D87: =VLOOKUP(C87,'IP PITS'!$B$6:$V$86,21,0) -> 2656.8 | F87: =VLOOKUP(C87,'SIND PITS'!$C$3:$D$102,2,0) -> 493.2 | G87: =VLOOKUP(C87,'SIND PITS'!$C$3:$E$102,3,0) -> 0 | H87: =VLOOKUP(C87,'SIND PITS'!$C$3:$F$102,4,0) -> 0 | I87: =VLOOKUP(C87,'SIND PITS'!$C$3:$G$102,5,0) -> 0 | K87: =SUM(D87:I87) -> 3150 | L87: 6300 | M87: 3150 | O87: =VLOOKUP(C87,'IP PITS'!$B$6:$I$86,8,0) -> 0 | P87: =+G87+H87+I87 -> 0 | Q87: =VLOOKUP(C87,'IP PITS'!$B$6:$N$86,13,0) -> 0 | R87: =VLOOKUP(C87,'IP PITS'!$B$6:$Q$86,16,0) -> 0 | S87: =VLOOKUP(C87,'IP PITS'!$B$6:$R$86,17,0) -> 0 | U87: =+K87-O87-P87+Q87+R87+S87 -> 3150 | V87: =+M87-U87 -> 0 | X87: SEI0626
A88: SEI0527 | B88: IP INNOVACION | C88: Alejandro Peña Deivi | D88: =VLOOKUP(C88,'IP PITS'!$B$6:$V$86,21,0) -> 2969.2 | F88: =VLOOKUP(C88,'SIND PITS'!$C$3:$D$102,2,0) -> 180.8 | G88: =VLOOKUP(C88,'SIND PITS'!$C$3:$E$102,3,0) -> 618.75 | H88: =VLOOKUP(C88,'SIND PITS'!$C$3:$F$102,4,0) -> 0 | I88: =VLOOKUP(C88,'SIND PITS'!$C$3:$G$102,5,0) -> 0 | K88: =SUM(D88:I88) -> 3768.75 | L88: 6300 | M88: 3150 | O88: =VLOOKUP(C88,'IP PITS'!$B$6:$I$86,8,0) -> 0 | P88: =+G88+H88+I88 -> 618.75 | Q88: =VLOOKUP(C88,'IP PITS'!$B$6:$N$86,13,0) -> 0 | R88: =VLOOKUP(C88,'IP PITS'!$B$6:$Q$86,16,0) -> 0 | S88: =VLOOKUP(C88,'IP PITS'!$B$6:$R$86,17,0) -> 0 | U88: =+K88-O88-P88+Q88+R88+S88 -> 3150 | V88: =+M88-U88 -> 0 | X88: SEI0628
A89: SEI0528 | B89: IP INNOVACION | C89: Casas Chavarria Rafael | D89: =VLOOKUP(C89,'IP PITS'!$B$6:$V$86,21,0) -> 2007.2 | F89: =VLOOKUP(C89,'SIND PITS'!$C$3:$D$102,2,0) -> 1142.8 | G89: =VLOOKUP(C89,'SIND PITS'!$C$3:$E$102,3,0) -> 480 | H89: =VLOOKUP(C89,'SIND PITS'!$C$3:$F$102,4,0) -> 0 | I89: =VLOOKUP(C89,'SIND PITS'!$C$3:$G$102,5,0) -> 0 | K89: =SUM(D89:I89) -> 3630 | L89: 6300 | M89: 3150 | O89: =VLOOKUP(C89,'IP PITS'!$B$6:$I$86,8,0) -> 0 | P89: =+G89+H89+I89 -> 480 | Q89: =VLOOKUP(C89,'IP PITS'!$B$6:$N$86,13,0) -> 0 | R89: =VLOOKUP(C89,'IP PITS'!$B$6:$Q$86,16,0) -> 0 | S89: =VLOOKUP(C89,'IP PITS'!$B$6:$R$86,17,0) -> 0 | U89: =+K89-O89-P89+Q89+R89+S89 -> 3150 | V89: =+M89-U89 -> 0 | X89: SEI0629
A90: SEI0530 | B90: IP INNOVACION | C90: Del Pilar Mendez Lucio | D90: =VLOOKUP(C90,'IP PITS'!$B$6:$V$86,21,0) -> 1255.4 | F90: =VLOOKUP(C90,'SIND PITS'!$C$3:$D$102,2,0) -> 1744.6 | G90: =VLOOKUP(C90,'SIND PITS'!$C$3:$E$102,3,0) -> 400 | H90: =VLOOKUP(C90,'SIND PITS'!$C$3:$F$102,4,0) -> 0 | I90: =VLOOKUP(C90,'SIND PITS'!$C$3:$G$102,5,0) -> 0 | K90: =SUM(D90:I90) -> 3400 | L90: 6000 | M90: 3000 | O90: =VLOOKUP(C90,'IP PITS'!$B$6:$I$86,8,0) -> 0 | P90: =+G90+H90+I90 -> 400 | Q90: =VLOOKUP(C90,'IP PITS'!$B$6:$N$86,13,0) -> 0 | R90: =VLOOKUP(C90,'IP PITS'!$B$6:$Q$86,16,0) -> 0 | S90: =VLOOKUP(C90,'IP PITS'!$B$6:$R$86,17,0) -> 0 | U90: =+K90-O90-P90+Q90+R90+S90 -> 3000 | V90: =+M90-U90 -> 0 | X90: SEI0630
A91: SEI0534 | B91: IP INNOVACION | C91: Gonzalez Ramirez Paul | D91: =VLOOKUP(C91,'IP PITS'!$B$6:$V$86,21,0) -> 2860.8 | F91: =VLOOKUP(C91,'SIND PITS'!$C$3:$D$102,2,0) -> 139.2 | G91: =VLOOKUP(C91,'SIND PITS'!$C$3:$E$102,3,0) -> 292.5 | H91: =VLOOKUP(C91,'SIND PITS'!$C$3:$F$102,4,0) -> 0 | I91: =VLOOKUP(C91,'SIND PITS'!$C$3:$G$102,5,0) -> 0 | K91: =SUM(D91:I91) -> 3292.5 | L91: 6000 | M91: 3000 | O91: =VLOOKUP(C91,'IP PITS'!$B$6:$I$86,8,0) -> 0 | P91: =+G91+H91+I91 -> 292.5 | Q91: =VLOOKUP(C91,'IP PITS'!$B$6:$N$86,13,0) -> 0 | R91: =VLOOKUP(C91,'IP PITS'!$B$6:$Q$86,16,0) -> 0 | S91: =VLOOKUP(C91,'IP PITS'!$B$6:$R$86,17,0) -> 0 | U91: =+K91-O91-P91+Q91+R91+S91 -> 3000 | V91: =+M91-U91 -> 0 | X91: 0SEI0635
A92: SEI0500 | B92: IP INNOVACION | C92: Garcia Gutierrez Jose Juan | D92: =VLOOKUP(C92,'IP PITS'!$B$6:$V$86,21,0) -> 2859.8 | F92: =VLOOKUP(C92,'SIND PITS'!$C$3:$D$102,2,0) -> 3140.2 | G92: =VLOOKUP(C92,'SIND PITS'!$C$3:$E$102,3,0) -> 399.5 | H92: =VLOOKUP(C92,'SIND PITS'!$C$3:$F$102,4,0) -> 0 | I92: =VLOOKUP(C92,'SIND PITS'!$C$3:$G$102,5,0) -> 0 | K92: =SUM(D92:I92) -> 6399.5 | L92: 12000 | M92: 6000 | O92: =VLOOKUP(C92,'IP PITS'!$B$6:$I$86,8,0) -> 0 | P92: =+G92+H92+I92 -> 399.5 | Q92: =VLOOKUP(C92,'IP PITS'!$B$6:$N$86,13,0) -> 0 | R92: =VLOOKUP(C92,'IP PITS'!$B$6:$Q$86,16,0) -> 0 | S92: =VLOOKUP(C92,'IP PITS'!$B$6:$R$86,17,0) -> 0 | U92: =+K92-O92-P92+Q92+R92+S92 -> 6000 | V92: =+M92-U92 -> 0 | X92: SEI0484
... A95: SEI0537 | B95: IP INNOVACION | C95: Serrano Esquivel Armando | D95: =VLOOKUP(C95,'IP PITS'!$B$6:$V$86,21,0) -> 991.6 | F95: =VLOOKUP(C95,'SIND PITS'!$C$3:$D$102,2,0) -> 1707.38 | G95: =VLOOKUP(C95,'SIND PITS'!$C$3:$E$102,3,0) -> 675 | H95: =VLOOKUP(C95,'SIND PITS'!$C$3:$F$102,4,0) -> 0 | I95: =VLOOKUP(C95,'SIND PITS'!$C$3:$G$102,5,0) -> 0 | K95: =SUM(D95:I95) -> 3373.98 | L95: 7000 | M95: 3500 | O95: =VLOOKUP(C95,'IP PITS'!$B$6:$I$86,8,0) -> 0 | P95: =+G95+H95+I95 -> 675 | Q95: =VLOOKUP(C95,'IP PITS'!$B$6:$N$86,13,0) -> 801.02 | R95: =VLOOKUP(C95,'IP PITS'!$B$6:$Q$86,16,0) -> 0 | S95: =VLOOKUP(C95,'IP PITS'!$B$6:$R$86,17,0) -> 0 | U95: =+K95-O95-P95+Q95+R95+S95 -> 3500 | V95: =+M95-U95 -> 0 | X95: SEI0641
A96: SEI0538 | B96: IP INNOVACION | C96: Coronado Vega Carlos Eduardo | D96: =VLOOKUP(C96,'IP PITS'!$B$6:$V$86,21,0) -> 2622.8 | F96: =VLOOKUP(C96,'SIND PITS'!$C$3:$D$102,2,0) -> 107.2 | G96: =VLOOKUP(C96,'SIND PITS'!$C$3:$E$102,3,0) -> 0 | H96: =VLOOKUP(C96,'SIND PITS'!$C$3:$F$102,4,0) -> 0 | I96: =VLOOKUP(C96,'SIND PITS'!$C$3:$G$102,5,0) -> 0 | K96: =SUM(D96:I96) -> 2730 | L96: 6300 | M96: 3150 | O96: =VLOOKUP(C96,'IP PITS'!$B$6:$I$86,8,0) -> 0 | P96: =+G96+H96+I96 -> 0 | Q96: =VLOOKUP(C96,'IP PITS'!$B$6:$N$86,13,0) -> 0 | R96: =VLOOKUP(C96,'IP PITS'!$B$6:$Q$86,16,0) -> 0 | S96: =VLOOKUP(C96,'IP PITS'!$B$6:$R$86,17,0) -> 0 | U96: =+K96-O96-P96+Q96+R96+S96 -> 2730 | V96: =+M96-U96 -> 420 | W96: 2 FALTAS | X96: SEI0642
A97: SEI0015 | B97: IP INNOVACION | C97: Cota Jaramillo Miguel Angel | D97: =VLOOKUP(C97,'IP PITS'!$B$6:$V$86,21,0) -> 2861 | F97: =VLOOKUP(C97,'SIND PITS'!$C$3:$D$102,2,0) -> 139 | G97: =VLOOKUP(C97,'SIND PITS'!$C$3:$E$102,3,0) -> 378 | H97: =VLOOKUP(C97,'SIND PITS'!$C$3:$F$102,4,0) -> 0 | I97: =VLOOKUP(C97,'SIND PITS'!$C$3:$G$102,5,0) -> 0 | K97: =SUM(D97:I97) -> 3378 | L97: 6000 | M97: 3000 | O97: =VLOOKUP(C97,'IP PITS'!$B$6:$I$86,8,0) -> 0 | P97: =+G97+H97+I97 -> 378 | Q97: =VLOOKUP(C97,'IP PITS'!$B$6:$N$86,13,0) -> 0 | R97: =VLOOKUP(C97,'IP PITS'!$B$6:$Q$86,16,0) -> 0 | S97: =VLOOKUP(C97,'IP PITS'!$B$6:$R$86,17,0) -> 0 | U97: =+K97-O97-P97+Q97+R97+S97 -> 3000 | V97: =+M97-U97 -> 0 | X97: SEI0015
A98: SEI0540 | B98: IP INNOVACION | C98: Morales Martinez Eduardo | D98: =VLOOKUP(C98,'IP PITS'!$B$6:$V$86,21,0) -> 2969.2 | F98: =VLOOKUP(C98,'SIND PITS'!$C$3:$D$102,2,0) -> 180.8 | G98: =VLOOKUP(C98,'SIND PITS'!$C$3:$E$102,3,0) -> 0 | H98: =VLOOKUP(C98,'SIND PITS'!$C$3:$F$102,4,0) -> 0 | I98: =VLOOKUP(C98,'SIND PITS'!$C$3:$G$102,5,0) -> 0 | K98: =SUM(D98:I98) -> 3150 | L98: 6300 | M98: 3150 | O98: =VLOOKUP(C98,'IP PITS'!$B$6:$I$86,8,0) -> 0 | P98: =+G98+H98+I98 -> 0 | Q98: =VLOOKUP(C98,'IP PITS'!$B$6:$N$86,13,0) -> 0 | R98: =VLOOKUP(C98,'IP PITS'!$B$6:$Q$86,16,0) -> 0 | S98: =VLOOKUP(C98,'IP PITS'!$B$6:$R$86,17,0) -> 0 | U98: =+K98-O98-P98+Q98+R98+S98 -> 3150 | V98: =+M98-U98 -> 0 | X98: SEI0648
A99: SEI0541 | B99: IP INNOVACION | C99: Chavez Govea Edgar Aram | D99: =VLOOKUP(C99,'IP PITS'!$B$6:$V$86,21,0) -> 3271.4 | F99: =VLOOKUP(C99,'SIND PITS'!$C$3:$D$102,2,0) -> 228.6 | G99: =VLOOKUP(C99,'SIND PITS'!$C$3:$E$102,3,0) -> 0 | H99: =VLOOKUP(C99,'SIND PITS'!$C$3:$F$102,4,0) -> 0 | I99: =VLOOKUP(C99,'SIND PITS'!$C$3:$G$102,5,0) -> 0 | K99: =SUM(D99:I99) -> 3500 | L99: 7000 | M99: 3500 | O99: =VLOOKUP(C99,'IP PITS'!$B$6:$I$86,8,0) -> 0 | P99: =+G99+H99+I99 -> 0 | Q99: =VLOOKUP(C99,'IP PITS'!$B$6:$N$86,13,0) -> 0 | R99: =VLOOKUP(C99,'IP PITS'!$B$6:$Q$86,16,0) -> 0 | S99: =VLOOKUP(C99,'IP PITS'!$B$6:$R$86,17,0) -> 0 | U99: =+K99-O99-P99+Q99+R99+S99 -> 3500 | V99: =+M99-U99 -> 0 | X99: SEI0644
A100: SEI0543 | B100: IP INNOVACION | C100: Diaz Ortiz Hiram Guillermo | D100: =VLOOKUP(C100,'IP PITS'!$B$6:$V$86,21,0) -> 1810.8 | F100: =VLOOKUP(C100,'SIND PITS'!$C$3:$D$102,2,0) -> 194.52 | G100: =VLOOKUP(C100,'SIND PITS'!$C$3:$E$102,3,0) -> 0 | H100: =VLOOKUP(C100,'SIND PITS'!$C$3:$F$102,4,0) -> 0 | I100: =VLOOKUP(C100,'SIND PITS'!$C$3:$G$102,5,0) -> 0 | K100: =SUM(D100:I100) -> 2005.32 | L100: 6300 | M100: 3150 | O100: =VLOOKUP(C100,'IP PITS'!$B$6:$I$86,8,0) -> 0 | P100: =+G100+H100+I100 -> 0 | Q100: =VLOOKUP(C100,'IP PITS'!$B$6:$N$86,13,0) -> 1144.68 | R100: =VLOOKUP(C100,'IP PITS'!$B$6:$Q$86,16,0) -> 0 | S100: =VLOOKUP(C100,'IP PITS'!$B$6:$R$86,17,0) -> 0 | U100: =+K100-O100-P100+Q100+R100+S100 -> 3150 | V100: =+M100-U100 -> 0 | X100: SEI0646
A101: SEI0544 | B101: IP INNOVACION | C101: Aguilar Aguirre Alfonso | D101: =VLOOKUP(C101,'IP PITS'!$B$6:$V$86,21,0) -> 2859.8 | F101: =VLOOKUP(C101,'SIND PITS'!$C$3:$D$102,2,0) -> 920.2 | G101: =VLOOKUP(C101,'SIND PITS'!$C$3:$E$102,3,0) -> 0 | H101: =VLOOKUP(C101,'SIND PITS'!$C$3:$F$102,4,0) -> 0 | I101: =VLOOKUP(C101,'SIND PITS'!$C$3:$G$102,5,0) -> 0 | K101: =SUM(D101:I101) -> 3780 | L101: 6000 | M101: 3150 | P101: =+G101+H101+I101 -> 0 | Q101: =VLOOKUP(C101,'IP PITS'!$B$6:$N$86,13,0) -> 0 | R101: =VLOOKUP(C101,'IP PITS'!$B$6:$Q$86,16,0) -> 0 | S101: =VLOOKUP(C101,'IP PITS'!$B$6:$R$86,17,0) -> 0 | U101: =+K101-O101-P101+Q101+R101+S101 -> 3780 | V101: =+M101-U101 -> -630 | W101: 43537 | X101: SEI0652
A102: SEI0545 | B102: IP INNOVACION | C102: Vallarta Fonseca Mayra Karina | D102: =VLOOKUP(C102,'IP PITS'!$B$6:$V$86,21,0) -> 1178.2 | F102: =VLOOKUP(C102,'SIND PITS'!$C$3:$D$102,2,0) -> 181 | G102: =VLOOKUP(C102,'SIND PITS'!$C$3:$E$102,3,0) -> 0 | H102: =VLOOKUP(C102,'SIND PITS'!$C$3:$F$102,4,0) -> 0 | I102: =VLOOKUP(C102,'SIND PITS'!$C$3:$G$102,5,0) -> 0 | K102: =SUM(D102:I102) -> 1359.2 | L102: 6000 | M102: 3150 | P102: =+G102+H102+I102 -> 0 | Q102: =VLOOKUP(C102,'IP PITS'!$B$6:$N$86,13,0) -> 524.15 | R102: =VLOOKUP(C102,'IP PITS'!$B$6:$Q$86,16,0) -> 636.6 | S102: =VLOOKUP(C102,'IP PITS'!$B$6:$R$86,17,0) -> 0 | U102: =+K102-O102-P102+Q102+R102+S102 -> 2519.95 | V102: =+M102-U102 -> 630.05 | W102: 43543 | X102: SEI0653
C103: TOTAL GENERAL | D103: =SUM(D3:D100) -> 299415.4 | F103: =SUM(F3:F100) -> 160179.5 | H103: =SUM(H3:H100) -> 0 | I103: =SUM(I3:I100) -> 347.5 | J103: =SUM(J3:J100) -> 0 | K103: =SUM(K3:K100) -> 499029.83 | L103: =SUM(L3:L102) -> 1016806 | M103: =SUM(M3:M100) -> 502403.01 | N103: =SUM(N3:N100) -> 0 | O103: =SUM(O3:O100) -> 574 | P103: =SUM(P3:P100) -> 39434.93 | Q103: =SUM(Q3:Q100) -> 30316.33 | R103: =SUM(R3:R100) -> 1781.73 | S103: =SUM(S3:S100) -> 9817.4 | T103: =SUM(T3:T100) -> 0 | ... W103: =SUM(W3:W100) -> 0 | X103: =SUM(X30:X100) -> 0 | Y103: =SUM(Y30:Y100) -> 0 | Z103: =SUM(Z30:Z100) -> 0 | AA103: =SUM(AA30:AA100) -> 0 | AB103: =SUM(AB30:AB100) -> 0 | AC103: =SUM(AC3:AC93) -> 0 | AD103: =SUM(AD3:AD93) -> 0 | AE103: =SUM(AE3:AE93) -> 0 | AF103: =SUM(AF3:AF93) -> 0

Sheet FACTURACION
D8: TOTAL FACTURACION NOMINA | H8: TOTAL PROV AGUINALDOS
D9: TOTAL CPD | E9: =+'CPD PITS'!M40 -> 171268.45 | H9: TOTAL CPD | I9: =+'CPD PITS'!M50 -> 6396.3315
D10: TOTAL IP | E10: =+'IP PITS'!J103 -> 450773.6 | H10: TOTAL IP | I10: =+'IP PITS'!J113 -> 19104.565
D11: TOTAL SINDICATO | E11: =+'SIND PITS'!H113 -> 237486.73
E12: =+E9+E10+E11 -> 859528.79 | I12: =+I9+I10+I11 -> 25500.896
D14: PORCENTAJES POR EMPRESA | H14: PORCENTAJES POR EMPRESA
D15: EM 4% | E15: =+E12*4% -> 34381.151 | H15: EM 4% | I15: =+I12*4% -> 1020.0359
D16: CPD 12% | E16: =+E12*12% -> 103143.45 | H16: CPD 12% | I16: =+I12*12% -> 3060.1076
D17: IP 11% | E17: =+E12*11% -> 94548.167 | H17: IP 11% | I17: =+I12*11% -> 2805.0986
D18: ITA 73% | E18: =+E12*73% -> 627456.01 | H18: ITA 73% | I18: =+I12*73% -> 18615.654
E19: =SUM(E15:E18) -> 859528.79 | I19: =SUM(I15:I18) -> 25500.896

Sheet NETOS
A5: CLAVE | B5: SUCURSAL | C5: NOMBRE | D5: NETO SALARIOS | E5: INFONAVIT | F5: NETO SINDICATO | G5: NETO A PAGAR
C6: ARCEO GARCIA MANUEL FEDERICO | D6: 2847.47 | F6: 152.53 | G6: =+F6+D6+E6 -> 3000
A7: SEI0003 | B7: SEITON (IP INNOVA II) | C7: ARELLANO LOPEZ ADRIANA ISELA | D7: 3215.9033 | E7: 0 | F7: 234.1 | G7: =+F7+D7+E7 -> 3450.0033
A8: SEI0097 | B8: SEITON - (CONSULTORIA II) | C8: ARREOLA JIMENEZ JOSE NIEVES | D8: 2105.51 | E8: 1394.18 | F8: 1000.31 | G8: =+F8+D8+E8 -> 4500
A9: SEI0118 | B9: SEITON - (CONSULTORIA II) | C9: ARROYO RAMIREZ HECTOR HUGO | D9: 3109.74 | E9: 1268.65 | F9: 1121.6 | G9: =+F9+D9+E9 -> 5499.99
A10: SEI0108 | B10: SEITON - (CONSULTORIA II) | C10: CABALLERO DIAZ FRANCISCO JAVIER | D10: 1882.39 | E10: 1617.3 | F10: 1000.31 | G10: =+F10+D10+E10 -> 4500
A11: SEI0425 | B11: SEITON - (CONSULTORIA II) | C11: CARBAJAL CABUTO JOSE LUIS | D11: 2165.48 | E11: 1334.21 | F11: 725.31 | G11: =+F11+D11+E11 -> 4225
A12: SEI0116 | B12: SEITON - (CONSULTORIA II) | C12: CASILLAS CARDONA CESAR ALEJANDRO | D12: 3156.22 | E12: 934.91 | F12: 907.87 | G12: =+F12+D12+E12 -> 4999
