Workbook

Sheet FACTURACION SINDICATO
B2: codigo | C2: empres | D2: nombre | E2: PAGO POR SINDICATO | F2: comision y bono | G2: prima vacaciones | H2: TOTAL | I2: CC
B3: SEI0097 | C3: SEITON - (CONSULTORIA II) | D3: Arreola Jimenez Jose Nieves | E3: 1558.05 | F3: 2975 | G3: 0 | H3: 4533.05 | I3: AA
B4: SEI0118 | C4: SEITON - (CONSULTORIA II) | D4: Arroyo Ramirez Hector Hugo | E4: 2103.54 | G4: 234 | H4: 2337.54 | I4: AA
B5: SEI0108 | C5: SEITON - (CONSULTORIA II) | D5: Caballero Diaz Francisco Javier | E5: 1558.01 | G5: 0 | H5: 1558.01 | I5: AA
B6: SEI0425 | C6: SEITON - (CONSULTORIA II) | D6: Carbajal Cabuto Jose Luis | E6: 1608.07 | G6: 0 | H6: 1608.07 | I6: AA
B7: SEI0116 | C7: SEITON - (CONSULTORIA II) | D7: Casillas Cardona Cesar Alejandro | E7: 1891.22 | G7: 0 | H7: 1891.22 | I7: AA
B8: SEI0401 | C8: SEITON - (CONSULTORIA II) | D8: De La Torre Zambara Francisco Ernesto | E8: 78.08 | G8: 0 | H8: 78.08 | I8: AA
B9: SEI0119 | C9: SEITON - (CONSULTORIA II) | D9: Dominguez Lopez Maria De Jesus | E9: 0 | G9: 0 | H9: 0 | I9: AA
B10: SEI0099 | C10: SEITON - (CONSULTORIA II) | D10: Garcia Villicaña Ricardo Pascual | E10: 2600.8 | F10: 600 | G10: 0 | H10: 3200.8 | I10: AA
B11: SEI0009 | C11: SEITON - (CONSULTORIA II) | D11: Gutierrez Gutierrez Luis Arturo | E11: 1474.6 | G11: 0 | H11: 1474.6 | I11: AA
B12: SEI0127 | C12: SEITON - (CONSULTORIA II) | D12: Hernandez Ochoa Eduardo | E12: 2601 | G12: 0 | H12: 2601 | I12: AA
B13: SEI0088 | C13: SEITON - (CONSULTORIA II) | D13: Morgado Fernandez Martin | E13: 2601 | F13: 1125 | G13: 0 | H13: 3726 | I13: AA
B14: SEI0173 | C14: SEITON - (CONSULTORIA II) | D14: Nieto Ortiz Jose Luis | E14: 1483.15 | F14: 1232 | G14: 0 | H14: 2715.15 | I14: AA
B15: SEI0026 | C15: SEITON - (CONSULTORIA II) | D15: Patricio Aguilar Jhonattan Cristian | E15: 1588 | G15: 0 | H15: 1588 | I15: AA
B16: SEI0027 | C16: SEITON - (CONSULTORIA II) | D16: Tavares Guzman Jose Enrique | E16: 2378.2 | G16: 0 | H16: 2378.2 | I16: AA
B17: SEI032 | C17: SEITON - (CONSULTORIA II) | D17: Camarena Quiroz Erick Frank | E17: 1588 | F17: 225 | G17: 0 | H17: 1813 | I17: AA
B18: SEI0438 | C18: SEITON - (CONSULTORIA II) | D18: Valdes Arrioja Karla Naborina | E18: 1803.2 | H18: 1803.2 | I18: AA
B19: SEI0482 | C19: SEITON (IP INNOVA II) | D19: Camarillo Canela Reynaldo | E19: 2236.64 | F19: 2150 | G19: 0 | H19: 4386.64 | I19: AA
B20: SEI0485 | C20: SEITON (IP INNOVA II) | D20: Molina Ramirez Gerardo Daniel | E20: 2271.77 | G20: 0 | H20: 2271.77 | I20: AA
B21: SEI0488 | C21: SEITON (IP INNOVA II) | D21: Mireles Casillas Brenda Cristina | E21: 2257 | G21: 0 | H21: 2257 | I21: AA
B22: SEI0489 | C22: SEITON (IP INNOVA II) | D22: Escobedo Olivares Juan Guadalupe | E22: 3723.8 | G22: 0 | H22: 3723.8 | I22: AA
B23: SEI0490 | C23: SEITON (IP INNOVA II) | D23: Castillo Ramirez Hector Ivan | E23: 3753.78 | F23: 1280 | G23: 0 | H23: 5033.78 | I23: AA
B24: SEI0492 | C24: SEITON (IP INNOVA II) | D24: Cadena Ramirez Hugo | E24: 2513.4 | G24: 0 | H24: 2513.4 | I24: AA
B25: SEI0493 | C25: SEITON (IP INNOVA II) | D25: Martinez Morales Tomas | E25: 3397.14 | F25: 1320 | G25: 0 | H25: 4717.14 | I25: AA
B26: SEI0494 | C26: SEITON (IP INNOVA II) | D26: Medellin Colunga Ruben Dario | E26: 4412.14 | F26: 2320 | G26: 0 | H26: 6732.14 | I26: AA
B27: SEI0495 | C27: SEITON (IP INNOVA II) | D27: Torres Perez Carlos Alberto | E27: 1685.3 | F27: 4495 | G27: 0 | H27: 6180.3 | I27: AA
B28: SEI0496 | C28: SEITON (IP INNOVA II) | D28: Velazquez Herrera Nayeli | E28: 3382.26 | F28: 950 | G28: 56.14 | H28: 4388.4 | I28: AA
B29: SEI0497 | C29: SEITON (IP INNOVA II) | D29: Treviño Alvarez Jorge Alberto | E29: 2700.29 | F29: 680 | G29: 0 | H29: 3380.29 | I29: AA
B30: SEI0498 | C30: SEITON (IP INNOVA II) | D30: Tenorio Alvarez Alberto Antonio | E30: 1685.2 | G30: 0 | H30: 1685.2 | I30: AA
B31: SEI0499 | C31: SEITON (IP INNOVA II) | D31: Chavez Dominguez Salvador | E31: 2685.2 | G31: 0 | H31: 2685.2 | I31: AA
B32: SEI0500 | C32: SEITON (IP INNOVA II) | D32: Garcia Gutierrez Jose Juan | E32: 1685.2 | G32: 0 | H32: 1685.2 | I32: AA
B33: SEI0501 | C33: SEITON (IP INNOVA II) | D33: Cruz Herrera Roberto | E33: 1670.2 | G33: 0 | H33: 1670.2 | I33: AA
B34: SEI0502 | C34: SEITON (IP INNOVA II) | D34: Dominguez Escamilla Victor Hugo | E34: 2700.14 | G34: 0 | H34: 2700.14 | I34: AA
B35: SEI0503 | C35: SEITON (IP INNOVA II) | D35: Martinez Rodriguez Paulo Cesar | E35: 2554.8 | G35: 0 | H35: 2554.8 | I35: AA
B36: SEI0504 | C36: SEITON (IP INNOVA II) | D36: Martinez Malo Cesar | E36: 1711.46 | G36: 0 | H36: 1711.46 | I36: AA
B37: SEI0505 | C37: SEITON (IP INNOVA II) | D37: Perez Balboa Cesar | E37: 2211.65 | G37: 0 | H37: 2211.65 | I37: AA
B38: SEI0506 | C38: SEITON (IP INNOVA II) | D38: Mejia Duarte Jose Luis | E38: 2570.57 | G38: 0 | H38: 2570.57 | I38: AA
B39: SEI0507 | C39: SEITON (IP INNOVA II) | D39: Diaz Saldierna Leonel Gonzalo | E39: 2585.53 | G39: 0 | H39: 2585.53 | I39: AA
B40: SEI0508 | C40: SEITON (IP INNOVA II) | D40: Cerro Garcia Elvis | E40: 2570.6 | F40: 2125 | G40: 0 | H40: 4695.6 | I40: AA
B41: SEI0078 | C41: SEITON (IP INNOVA II) | D41: Aguilar Leal Karina Livier | E41: 952.25 | F41: 16065.1 | G41: 10 | H41: 17027.35 | I41: AA
B42: SEI0126 | C42: SEITON (IP INNOVA II) | D42: Alonso Flores Beda | E42: 1102.59 | G42: 0 | H42: 1102.59 | I42: AA
B43: SEI0029 | C43: SEITON (IP INNOVA II) | D43: Arceo Garcia Manuel Federico | E43: 152.5 | G43: 0 | H43: 152.5 | I43: AA
B44: SEI0003 | C44: SEITON (IP INNOVA II) | D44: Arellano Lopez Adriana Isela | E44: 231.8 | G44: 0 | H44: 231.8 | I44: AA
B45: SEI0230 | C45: SEITON (IP INNOVA II) | D45: Bueno Herrera Mariana Guadalupe | E45: 1452.1 | F45: 2269.72 | G45: 0 | H45: 3721.82 | I45: AA
B46: SEI0013 | C46: SEITON (IP INNOVA II) | D46: Castillo Sanchez Miguel Angel | E46: 1549.97 | F46: 960 | G46: 0 | H46: 2509.97 | I46: AA
B47: SEI0031 | C47: SEITON (IP INNOVA II) | D47: Contreras Zetina Victor Hugo | E47: 233.2 | G47: 0 | H47: 233.2 | I47: AA
B48: SEI0015 | C48: SEITON (IP INNOVA II) | D48: Cota Jaramillo Miguel Angel | E48: 151.4 | G48: 0 | H48: 151.4 | I48: AA
B49: SEI0413 | C49: SEITON (IP INNOVA II) | D49: Courtenay Gutierrez Barry Vladimir | E49: 69.74 | F49: 3360 | G49: 0 | H49: 3429.74 | I49: AA
B50: SEI0364 | C50: SEITON (IP INNOVA II) | D50: Dominguez Lopez Mayeli Del Pilar | E50: 1437.13 | G50: 0 | H50: 1437.13 | I50: AA
B51: SEI0018 | C51: SEITON (IP INNOVA II) | D51: Dominguez Mendez Victor Manuel | E51: 550 | G51: 0 | H51: 550 | I51: AA
B52: SEI0037 | C52: SEITON (IP INNOVA II) | D52: Gomez Oliveros Alin | E52: 602.6 | F52: 1843.07 | G52: 0 | H52: 2445.67 | I52: AA
B53: SEI0019 | C53: SEITON (IP INNOVA II) | D53: Gonzalez Rasgado Miguel Isaias | E53: 896.4 | G53: 0 | H53: 896.4 | I53: AA
B54: SEI0081 | C54: SEITON (IP INNOVA II) | D54: Guizar Perez Sergio | E54: 904.8 | G54: 0 | H54: 904.8 | I54: AA
B55: SEI0012 | C55: SEITON (IP INNOVA II) | D55: Hernandez Renteria Javier Fernando | E55: 550 | G55: 0 | H55: 550 | I55: AA
B56: SEI0332 | C56: SEITON (IP INNOVA II) | D56: Lara Campos Maximino | E56: 1475.2 | G56: 0 | H56: 1475.2 | I56: AA
B57: SEI0020 | C57: SEITON (IP INNOVA II) | D57: Mar Marquez Cesar Eduardo | E57: 435.4 | G57: 0 | H57: 435.4 | I57: AA
B58: SEI0376 | C58: SEITON (IP INNOVA II) | D58: Marquez Alcaraz Martin | E58: 977.35 | G58: 0 | H58: 977.35 | I58: AA
B59: SEI0030 | C59: SEITON (IP INNOVA II) | D59: Marquez Altamirano Marco Antonio | E59: 452.2 | F59: 260 | G59: 0 | H59: 712.2 | I59: AA
B60: SEI0014 | C60: SEITON (IP INNOVA II) | D60: Montoya Portillo Carlos Alberto | E60: 450.4 | F60: 1550 | G60: 0 | H60: 2000.4 | I60: AA
B61: SEI0017 | C61: SEITON (IP INNOVA II) | D61: Muñoz Reyes Luis Eduardo | E61: 465.38 | G61: 0 | H61: 465.38 | I61: AA
B62: SEI0022 | C62: SEITON (IP INNOVA II) | D62: Najera Lopez Raul | E62: 656.13 | F62: 1120 | G62: 0 | H62: 1776.13 | I62: AA
B63: SEI0016 | C63: SEITON (IP INNOVA II) | D63: Negrete Bejar Aide Sarai | E63: 14.8 | G63: 0 | H63: 14.8 | I63: AA
B64: SEI0109 | C64: SEITON (IP INNOVA II) | D64: Negrete Renteria Jose Luis | E64: 1169.97 | G64: 0 | H64: 1169.97 | I64: AA
B65: SEI0023 | C65: SEITON (IP INNOVA II) | D65: Puente Murguia Luis Felipe | E65: 240.2 | G65: 0 | H65: 240.2 | I65: AA
B66: SEI0100 | C66: SEITON (IP INNOVA II) | D66: Quinto Valle Martin | E66: 641.2 | F66: 350 | G66: 0 | H66: 991.2 | I66: AA
B67: SEI0146 | C67: SEITON (IP INNOVA II) | D67: Ramirez Vera Maria Del Carmen | E67: 1467.19 | G67: 0 | H67: 1467.19 | I67: AA
B68: SEI0345 | C68: SEITON (IP INNOVA II) | D68: Rodriguez Diaz Cesar Salvador | E68: 992.07 | G68: 0 | H68: 992.07 | I68: AA
B69: SEI0412 | C69: SEITON (IP INNOVA II) | D69: Rojo Avelar Adrian | E69: 917.5 | G69: 0 | H69: 917.5 | I69: AA
B70: SEI0133 | C70: SEITON (IP INNOVA II) | D70: Romero Mayoral Lorenzo | E70: 2202.21 | G70: 0 | H70: 2202.21 | I70: AA
B71: SEI0010 | C71: SEITON (IP INNOVA II) | D71: Torres Ricardez Alfredo | E71: 450.4 | G71: 0 | H71: 450.4 | I71: AA
B72: SEI0021 | C72: SEITON (IP INNOVA II) | D72: Velez Rodriguez Jaime | E72: 1167.55 | G72: 20 | H72: 1187.55 | I72: AA
B73: SEI0421 | C73: SEITON (IP INNOVA II) | D73: Marin Avila Hector | E73: 734.1 | F73: 1325 | G73: 5.5 | H73: 2064.6 | I73: AA
B74: SEI0422 | C74: SEITON (IP INNOVA II) | D74: Mulgado Guzman Ernesto | E74: 755.07 | F74: 1275 | G74: 0 | H74: 2030.07 | I74: AA
B75: SEI0424 | C75: SEITON (IP INNOVA II) | D75: Palacios Ramos Jesus | E75: 452.2 | F75: 1375 | G75: 0 | H75: 1827.2 | I75: AA
B76: SEI0429 | C76: SEITON (IP INNOVA II) | D76: Torres Gomez Valeria | E76: 22.6 | G76: 0 | H76: 22.6 | I76: AA
B77: SEI0431 | C77: SEITON (IP INNOVA II) | D77: Alcaraz Conde Zabdi Guadalupe | E77: 152.5 | G77: 0 | H77: 152.5 | I77: AA
B78: SEI0428 | C78: SEITON (IP INNOVA II) | D78: Martinez Hernandez J. Antonio | E78: 452.2 | F78: 2900 | G78: 0 | H78: 3352.2 | I78: AA
B79: SEI0433 | C79: SEITON (IP INNOVA II) | D79: Garza Herrera Yareci Anel | E79: 452.4 | G79: 0 | H79: 452.4 | I79: AA
B80: SEI0438 | C80: SEITON (IP INNOVA II) | D80: Lopez Terron Roberto Porfirio | E80: 1139.4 | G80: 0 | H80: 1139.4 | I80: AA
B81: SEI0441 | C81: SEITON (IP INNOVA II) | D81: Ramirez Romero Jose Luis | E81: 1139.4 | G81: 0 | H81: 1139.4 | I81: AA
B82: SEI0442 | C82: SEITON (IP INNOVA II) | D82: Chavez Pedraza Samuel | E82: 1139.4 | G82: 0 | H82: 1139.4 | I82: AA
B83: SEI0443 | C83: SEITON (IP INNOVA II) | D83: Castillo Nungaray Nestor Roman | E83: 152.4 | G83: 0 | H83: 152.4 | I83: AA
B84: SEI0444 | C84: SEITON (IP INNOVA II) | D84: Marquez Hernandez Rogelio | E84: 452.2 | F84: 3050 | G84: 0 | H84: 3502.2 | I84: AA
B85: SEI0448 | C85: SEITON (IP INNOVA II) | D85: Picazo Gutierrez Jose Alfonso | E85: 70.6 | G85: 0 | H85: 70.6 | I85: AA
B86: SEI0449 | C86: SEITON (IP INNOVA II) | D86: Flores Cerrillos Jorge Humberto | E86: 452.2 | G86: 0 | H86: 452.2 | I86: AA
B87: SEI0451 | C87: SEITON (IP INNOVA II) | D87: Hurtado Avalos J.jesus | E87: 137.6 | G87: 0 | H87: 137.6 | I87: AA
B88: SEI0452 | C88: SEITON (IP INNOVA II) | D88: Leija Arevalo Guadalupe | E88: 248.205 | G88: 0 | H88: 248.205 | I88: AA
B89: SEI0453 | C89: SEITON (IP INNOVA II) | D89: Mora Cavazos Roberto Manuel | E89: 452.2 | G89: 0 | H89: 452.2 | I89: AA
B90: SEI0454 | C90: SEITON (IP INNOVA II) | D90: Martinez Rivera Maria Teresa | E90: 442.8 | G90: 0 | H90: 442.8 | I90: AA
B91: SEI0455 | C91: SEITON (IP INNOVA II) | D91: Perez Garcia Andres Alvaro | E91: 452.2 | F91: 860 | G91: 0 | H91: 1312.2 | I91: AA
B92: SEI0456 | C92: SEITON (IP INNOVA II) | D92: Chavira Garcia David Fernando | E92: 656.2 | G92: 0 | H92: 656.2 | I92: AA
B93: SEI0457 | C93: SEITON (IP INNOVA II) | D93: Guerrero Lara Cesar Adrian | E93: 437.2 | G93: 0 | H93: 437.2 | I93: AA
B94: SEI0458 | C94: SEITON (IP INNOVA II) | D94: Martinez Zamora Gerardo Mario | E94: 609.225 | F94: 1550 | G94: 0 | H94: 2159.225 | I94: AA
B95: SEI0460 | C95: SEITON (IP INNOVA II) | D95: Castellon Ramos Rene | E95: 422.955 | F95: 1875 | G95: 0 | H95: 2297.955 | I95: AA
B96: SEI0461 | C96: SEITON (IP INNOVA II) | D96: Flores Franco Marco | E96: 499.655 | F96: 125 | G96: 0 | H96: 624.655 | I96: AA
B97: SEI0462 | C97: SEITON (IP INNOVA II) | D97: Chavez Saucedo Jorge Arturo | E97: 450.6 | H97: 450.6 | I97: AA
B98: SEI0463 | C98: SEITON (IP INNOVA II) | D98: Hernandez Rangel Daniel | E98: 436.95 | F98: 4510 | G98: 0 | H98: 4946.95 | I98: AA
B99: SEI0464 | C99: SEITON (IP INNOVA II) | D99: Hueramo Hueramo Jesus Daniel | E99: 514.685 | G99: 0 | H99: 514.685 | I99: AA
B100: SEI0465 | C100: SEITON (IP INNOVA II) | D100: Sandoval Garcia Luis | E100: 437.2 | G100: 0 | H100: 437.2 | I100: AA
B101: SEI0467 | C101: SEITON (IP INNOVA II) | D101: Vaca Valdez Guillermo | E101: 452.2 | G101: 0 | H101: 452.2 | I101: AA
...

Sheet CPD PITS
B2: CONSULTORIA EN PROYECTOS DINAMICOS S DE RL DE CV
B3: Lista de Raya (forma tabular)
B4: Reg Pat IMSS: Z2940859106
B5: RFC: CPD -150911-FA3
A8: Código | B8: Empleado | C8: Dias Laborados | D8: Dias Vacaciones | E8: Salario Diario | F8: Salario Diario Integrado | G8: Sueldo | H8: Vacaciones a tiempo | I8: Prima de vacaciones a tiempo | J8: Ayuda de Transporte | K8: Ayuda Alimentaria | L8: Ayuda de Renta | M8: *TOTAL* *PERCEPCIONES* | N8: I.S.R. (sp) | O8: Subsidio al Empleo (sp) | P8: I.M.S.S. | Q8: Préstamo Infonavit | R8: Préstamo Infonavit (vsm) | S8: Préstamo Infonavit (cf) | T8: Seguro de vivienda Infonavit | U8: Prestamo Empresa | V8: Deduccion general | W8: Ajuste al neto | X8: *TOTAL* *DEDUCCIONES* | Y8: *NETO* | Z8: Ret. Inv. Y Vida | AA8: Ret. Cesantia | AB8: Ret. Enf. y Mat. obrero | AC8: Subs al Empleo acreditado | AD8: I.S.R. antes de Subs al Empleo | AE8: isr 2 | AF8: Invalidez y Vida | AG8: Cesantia y Vejez | AH8: Enf. y Mat. Patron | AI8: Total Percepciones | AJ8: 2% Fondo retiro SAR (8) | AK8: 2% Impuesto estatal | AL8: Riesgo de trabajo (9) | AM8: I.M.S.S. empresa | AN8: Infonavit empresa | AO8: Guarderia I.M.S.S. (7) | AP8: Proporcion Aguinaldo | AQ8: FACTURACION
A9: SEI0009 | B9: Gutierrez Gutierrez Luis Arturo | C9: 15 | D9: 0 | E9: 141.67 | F9: 150.25 | G9: 2125.05 | H9: 0 | I9: 0 | J9: 212.51 | K9: 212.51 | L9: 212.51 | M9: 2762.58 | N9: 0 | O9: -65.5 | P9: 53.52 | Q9: 0 | R9: 0 | T9: 0 | V9: 0 | W9: -0.04 | X9: -12.02 | Y9: 2774.6 | Z9: 14.09 | AA9: 25.35 | AB9: 14.08 | AC9: -188.71 | AD9: 123.22 | AF9: 39.44 | AG9: 70.99 | AH9: 297.98 | AI9: 2762.58 | AJ9: 254.91 | AK9: 55.25 | AL9: 11.27 | AM9: 408.41 | AN9: 112.69 | AO9: 232.37 | AP9: 151.27396 | AQ9: PITSS
A10: SEI0026 | B10: Patricio Aguilar Jhonattan Cristian | C10: 15 | D10: 0 | E10: 150 | F10: 159.07 | G10: 2250 | H10: 0 | I10: 0 | J10: 225 | K10: 225 | L10: 225 | M10: 2925 | N10: 0 | O10: -43.57 | P10: 56.67 | Q10: 0 | R10: 0 | T10: 0 | V10: 0 | W10: 0.1 | X10: 13.2 | Y10: 2911.8 | Z10: 14.91 | AA10: 26.84 | AB10: 14.92 | AC10: -174.78 | AD10: 131.21 | AF10: 41.76 | AG10: 75.16 | AH10: 300.29 | AI10: 2925 | AJ10: 257.55 | AK10: 58.5 | AL10: 11.93 | AM10: 417.21 | AN10: 119.31 | AO10: 233.69 | AP10: 160.16866 | AQ10: PITSS
A11: SEI0040 | B11: Mora Ramirez Acal Aldo Isidro | C11: 15 | D11: 0 | E11: 216.67 | F11: 229.79 | G11: 3250.05 | H11: 0 | I11: 0 | J11: 325.01 | K11: 325.01 | L11: 325.01 | M11: 4225.08 | N11: 107.17 | O11: 0 | P11: 81.87 | Q11: 0 | R11: 0 | T11: 0 | V11: 0 | W11: 0.04 | X11: 189.08 | Y11: 4036 | Z11: 21.54 | AA11: 38.78 | AB11: 21.55 | AC11: -125.1 | AD11: 232.27 | AF11: 60.32 | AG11: 108.58 | AH11: 318.86 | AI11: 4225.08 | AJ11: 278.77 | AK11: 84.5 | AL11: 17.23 | AM11: 487.76 | AN11: 172.34 | AO11: 244.3 | AP11: 231.35828 | AQ11: PITSS
A12: SEI0041 | B12: Vazquez Perez Miguel Angel | C12: 15 | D12: 0 | E12: 283.33 | F12: 300.49 | G12: 4249.95 | H12: 0 | I12: 0 | J12: 425 | K12: 425 | L12: 425 | M12: 5524.95 | N12: 341.06 | O12: 0 | P12: 109.87 | Q12: 0 | R12: 0 | T12: 0 | V12: 0 | W12: 0.02 | X12: 450.95 | Y12: 5074 | Z12: 28.17 | AA12: 50.71 | AB12: 30.99 | AC12: 0 | AD12: 341.06 | AF12: 78.88 | AG12: 141.98 | AH12: 345.18 | AI12: 5524.95 | AJ12: 299.98 | AK12: 110.5 | AL12: 22.54 | AM12: 566.04 | AN12: 225.37 | AO12: 254.9 | AP12: 302.53724 | AQ12: PITSS
A13: SEI0088 | B13: Morgado Fernandez Martin | C13: 15 | D13: 0 | E13: 273.33 | F13: 289.87 | G13: 4099.95 | H13: 0 | I13: 0 | J13: 410 | K13: 410 | L13: 410 | M13: 5329.95 | N13: 324.74 | O13: 0 | P13: 105.46 | Q13: 0 | R13: 0 | T13: 0 | V13: 0 | W13: 0.15 | X13: 430.35 | Y13: 4899.6 | Z13: 27.18 | AA13: 48.92 | AB13: 29.36 | AC13: 0 | AD13: 324.74 | AF13: 76.09 | AG13: 136.96 | AH13: 340.64 | AI13: 5329.95 | AJ13: 296.79 | AK13: 106.6 | AL13: 21.74 | AM13: 553.69 | AN13: 217.4 | AO13: 253.31 | AP13: 291.85933 | AQ13: PITSS
A14: SEI0097 | B14: Arreola Jimenez Jose Nieves | C14: 15 | D14: 0 | E14: 185.83 | F14: 197.07 | G14: 2787.45 | H14: 0 | I14: 0 | J14: 278.75 | K14: 278.75 | L14: 278.75 | M14: 3623.7 | N14: 36.57 | O14: 0 | P14: 70.22 | Q14: 0 | R14: 1574.29 | T14: 15 | V14: 0 | W14: 0.02 | X14: 1696.1 | Y14: 1927.6 | Z14: 18.48 | AA14: 33.26 | AB14: 18.48 | AC14: -145.38 | AD14: 181.94 | AF14: 51.73 | AG14: 93.12 | AH14: 310.27 | AI14: 3623.7 | AJ14: 268.95 | AK14: 72.47 | AL14: 14.78 | AM14: 455.12 | AN14: 147.8 | AO14: 239.39 | AP14: 198.42761 | AQ14: PITSS
A15: SEI0099 | B15: Garcia Villicaña Ricardo Pascual | C15: 15 | D15: 0 | E15: 273.33 | F15: 289.87 | G15: 4099.95 | H15: 0 | I15: 0 | J15: 410 | K15: 410 | L15: 410 | M15: 5329.95 | N15: 324.74 | O15: 0 | P15: 105.46 | Q15: 0 | R15: 0 | T15: 0 | V15: 0 | W15: -0.05 | X15: 430.15 | Y15: 4899.8 | Z15: 27.18 | AA15: 48.92 | AB15: 29.36 | AC15: 0 | AD15: 324.74 | AF15: 76.09 | AG15: 136.96 | AH15: 340.64 | AI15: 5329.95 | AJ15: 296.79 | AK15: 106.6 | AL15: 21.74 | AM15: 553.69 | AN15: 217.4 | AO15: 253.31 | AP15: 291.85933 | AQ15: PITSS
A16: SEI0108 | B16: Caballero Diaz Francisco Javier | C16: 15 | D16: 0 | E16: 185.83 | F16: 197.07 | G16: 2787.45 | H16: 0 | I16: 0 | J16: 278.75 | K16: 278.75 | L16: 278.75 | M16: 3623.7 | N16: 36.57 | O16: 0 | P16: 70.22 | Q16: 0 | R16: 1826.51 | T16: 15 | V16: 0 | W16: 0 | X16: 1948.3 | Y16: 1675.4 | Z16: 18.48 | AA16: 33.26 | AB16: 18.48 | AC16: -145.38 | AD16: 181.94 | AF16: 51.73 | AG16: 93.12 | AH16: 310.27 | AI16: 3623.7 | AJ16: 268.95 | AK16: 72.47 | AL16: 14.78 | AM16: 455.12 | AN16: 147.8 | AO16: 239.39 | AP16: 198.42761 | AQ16: PITSS
A17: SEI0116 | B17: Casillas Cardona Cesar Alejandro | C17: 15 | D17: 0 | E17: 220.83 | F17: 234.19 | G17: 3312.45 | H17: 0 | I17: 0 | J17: 331.25 | K17: 331.25 | L17: 331.25 | M17: 4306.2 | N17: 113.96 | O17: 0 | P17: 83.43 | Q17: 0 | R17: 757.32 | T17: 15 | V17: 0 | W17: -0.11 | X17: 969.6 | Y17: 3336.6 | Z17: 21.96 | AA17: 39.52 | AB17: 21.95 | AC17: -125.1 | AD17: 239.06 | AF17: 61.47 | AG17: 110.65 | AH17: 320.01 | AI17: 4306.2 | AJ17: 280.09 | AK17: 86.12 | AL17: 17.56 | AM17: 492.13 | AN17: 175.64 | AO17: 244.96 | AP17: 235.8003 | AQ17: PITSS
A18: SEI0117 | B18: Mariscal Romero Luis Adrian | C18: 15 | D18: 0 | E18: 264.58 | F18: 276.54 | G18: 3968.7 | H18: 0 | I18: 0 | J18: 396.87 | K18: 396.87 | L18: 396.87 | M18: 5159.31 | N18: 310.46 | O18: 0 | P18: 99.91 | Q18: 0 | R18: 1674 | T18: 15 | V18: 0 | W18: -0.06 | X18: 2099.31 | Y18: 3060 | Z18: 25.93 | AA18: 46.67 | AB18: 27.31 | AC18: 0 | AD18: 310.46 | AF18: 72.59 | AG18: 130.66 | AH18: 334.94 | AI18: 5159.31 | AJ18: 292.79 | AK18: 103.19 | AL18: 20.74 | AM18: 538.19 | AN18: 207.4 | AO18: 251.31 | AP18: 282.51615 | AQ18: PITSS
A19: SEI0118 | B19: Arroyo Ramirez Hector Hugo | C19: 15 | D19: 0 | E19: 238.33 | F19: 252.75 | G19: 3574.95 | H19: 0 | I19: 285.99 | J19: 357.5 | K19: 357.5 | L19: 357.5 | M19: 4933.44 | N19: 160.25 | O19: 0 | P19: 90.05 | Q19: 0 | R19: 1432.4 | T19: 15 | V19: 268.35 | W19: -0.01 | X19: 1966.04 | Y19: 2967.4 | Z19: 23.7 | AA19: 42.65 | AB19: 23.7 | AC19: -107.37 | AD19: 267.62 | AF19: 66.35 | AG19: 119.42 | AH19: 324.89 | AI19: 4933.44 | AJ19: 285.65 | AK19: 98.67 | AL19: 18.96 | AM19: 510.66 | AN19: 189.56 | AO19: 247.74 | AP19: 254.48664 | AQ19: PITSS
A20: SEI0127 | B20: Hernandez Ochoa Eduardo | C20: 15 | D20: 0 | E20: 273.33 | F20: 289.87 | G20: 4099.95 | H20: 0 | I20: 0 | J20: 410 | K20: 410 | L20: 410 | M20: 5329.95 | N20: 324.74 | O20: 0 | P20: 105.46 | Q20: 0 | R20: 0 | T20: 0 | V20: 0 | W20: -0.05 | X20: 430.15 | Y20: 4899.8 | Z20: 27.18 | AA20: 48.92 | AB20: 29.36 | AC20: 0 | AD20: 324.74 | AF20: 76.09 | AG20: 136.96 | AH20: 340.64 | AI20: 5329.95 | AJ20: 296.79 | AK20: 106.6 | AL20: 21.74 | AM20: 553.69 | AN20: 217.4 | AO20: 253.31 | AP20: 291.85933 | AQ20: PITSS
... A27: SEI0445 | B27: Muñoz Melgoza Gabriel | C27: 15 | D27: 0 | E27: 256.67 | F27: 272.21 | G27: 3850.05 | H27: 0 | I27: 0 | J27: 385.01 | K27: 385.01 | L27: 385.01 | M27: 5005.08 | N27: 297.55 | O27: 0 | P27: 98.1 | Q27: 0 | R27: 0 | T27: 0 | V27: 0 | W27: 0.03 | X27: 395.68 | Y27: 4609.4 | Z27: 25.52 | AA27: 45.94 | AB27: 26.64 | AC27: 0 | AD27: 297.55 | AF27: 71.46 | AG27: 128.62 | AH27: 333.08 | AI27: 5005.08 | AJ27: 291.49 | AK27: 100.1 | AL27: 20.42 | AM27: 533.16 | AN27: 204.16 | AO27: 250.66 | AP27: 274.06993 | AQ27: PITSS
A28: Total Depto | C28: ----------------------- | D28: ----------------------- | E28: ----------------------- | F28: ----------------------- | G28: ----------------------- | H28: ----------------------- | I28: ----------------------- | J28: ----------------------- | K28: ----------------------- | L28: ----------------------- | M28: ----------------------- | N28: ----------------------- | O28: ----------------------- | P28: ----------------------- | Q28: ----------------------- | R28: ----------------------- | S28: ----------------------- | T28: ----------------------- | U28: ----------------------- | V28: ----------------------- | W28: ----------------------- | X28: ----------------------- | Y28: ----------------------- | Z28: ----------------------- | AA28: ----------------------- | AB28: ----------------------- | AC28: ----------------------- | AD28: ----------------------- | AF28: ----------------------- | AG28: ----------------------- | AH28: ----------------------- | AI28: ----------------------- | AJ28: ----------------------- | AK28: ----------------------- | AL28: ----------------------- | AM28: ----------------------- | AN28: ----------------------- | AO28: ----------------------- | AP28: -----------------------
A29: =SUM(A9:A28) -> 0 | B29: =SUM(B9:B28) -> 0 | C29: =SUM(C9:C28) -> 285 | D29: =SUM(D9:D28) -> 0 | E29: =SUM(E9:E28) -> 4965.39 | F29: =SUM(F9:F28) -> 5261.86 | G29: =SUM(G9:G28) -> 74480.85 | H29: =SUM(H9:H28) -> 0 | ... AP29: =SUM(AP9:AP28) -> 5301.999
L31: FACTURACON PITS | O31: PROVISION AGUINALDO
L32: Devengado Salario | M32: =+Y29 -> 77805.4 | O32: FACTURACION PITS
L33: RETORNOS | M33: =+V29 -> 999.15 | O33: Subtotal 1 | P33: =+AP29 -> 5301.999
L34: Infonavit | M34: =+S29+R29+Q29+T29 -> 11045.69 | O34: Comision | P34: =+P33*2% -> 106.03998
L35: Prestamo Prospera | M35: =+U29 -> 0 | O35: Subtotal 2 | P35: =+P33+P34 -> 5408.0389
L36: Subtotal 1 | M36: =SUM(M32:M35) -> 89850.24 | O36: 2% Sobre Nomina | P36: =+P33*2% -> 106.03998
L37: Comision | M37: =+M36*2% -> 1797.0048 | O37: Importe de Factura | P37: =+P35+P36 -> 5514.0789
L38: Subtotal 2 | M38: =+M36+M37 -> 91647.245 | O38: IVA | P38: =+P37*16% -> 882.25263
L39: Costo Patronal Imss | M39: =+P29+AF29+AG29+AH29+AJ29+AL29+AN29+AO29 -> 26958.66 | O39: TOTAL | P39: =+P37+P38 -> 6396.3315
L40: 2% Sobre Nomina | M40: =+M29*2% -> 1942.227
L41: Importe de Factura | M41: =+M38+M39+M40 -> 120548.13
L42: IVA | M42: =+M41*16% -> 19287.701
L43: TOTAL | M43: =+M41+M42 -> 139835.83
H44: FACTURACION EM | K44: FACTURACION CPD | N44: FACTURACION IP | Q44: FACTURACION IT
H45: Importe de Factura | I45: =+M41*4% -> 4821.9253 | K45: Importe de Factura | L45: =+M41*12% -> 14465.776 | N45: Importe de Factura | O45: =+M41*11% -> 13260.294 | Q45: Importe de Factura | R45: =+M41*73% -> 88000.136
H46: IVA | I46: =+I45*16% -> 771.50804 | K46: IVA | L46: =+L45*16% -> 2314.5241 | N46: IVA | O46: =+O45*16% -> 2121.6471 | Q46: IVA | R46: =+R45*16% -> 14080.022
H47: TOTAL | I47: =+I45+I46 -> 5593.4333 | K47: TOTAL | L47: =+L45+L46 -> 16780.3 | N47: TOTAL | O47: =+O45+O46 -> 15381.942 | Q47: TOTAL | R47: =+R45+R46 -> 102080.16
H50: FACTURACION EM | K50: FACTURACION CPD | N50: FACTURACION IP | Q50: FACTURACION IT
H51: Importe de Factura | I51: =+P37*4% -> 220.56316 | K51: Importe de Factura | L51: =+P37*12% -> 661.68947 | N51: Importe de Factura | O51: =+P37*11% -> 606.54868 | Q51: Importe de Factura | R51: =+P37*73% -> 4025.2776
H52: IVA | I52: =+I51*16% -> 35.290105 | K52: IVA | L52: =+L51*16% -> 105.87032 | N52: IVA | O52: =+O51*16% -> 97.047789 | Q52: IVA | R52: =+R51*16% -> 644.04442
H53: TOTAL | I53: =+I51+I52 -> 255.85326 | K53: TOTAL | L53: =+L51+L52 -> 767.55979 | N53: TOTAL | O53: =+O51+O52 -> 703.59647 | Q53: TOTAL | R53: =+R51+R52 -> 4669.322

Sheet IP PITS
B2: IP INNOVACION EN PROYECTOS S DE RL DE CV
B3: Lista de Raya (forma tabular)
B4: Reg Pat IMSS: Z2942442109
B5: RFC: IIP -150923-DT7
A8: Código | B8: Empleado | C8: Dias Laborados | D8: Dias Vacaciones | E8: Salario Diario | F8: Salario Diario Integrado | G8: Sueldo | H8: Vacaciones a tiempo | I8: Prima de vacaciones a tiempo | J8: *TOTAL* *PERCEPCIONES* | K8: I.S.R. (sp) | L8: Subsidio al Empleo (sp) | M8: I.M.S.S. | N8: Préstamo Infonavit (vsm) | O8: Préstamo Infonavit (cf) | P8: Seguro de vivienda Infonavit | Q8: Prestamo FONACOT | R8: Deduccion general | S8: Aportación voluntaria SAR | T8: Ajuste al neto | U8: *TOTAL* *DEDUCCIONES* | V8: *NETO* | W8: Ret. Inv. Y Vida | X8: Ret. Cesantia | Y8: Ret. Enf. y Mat. obrero | Z8: Subs al Empleo acreditado | AA8: I.S.R. antes de Subs al Empleo | AB8: isr 2 | AC8: Invalidez y Vida | AD8: Cesantia y Vejez | AE8: Enf. y Mat. Patron | AF8: Total Percepciones | AG8: 2% Fondo retiro SAR (8) | AH8: 2% Impuesto estatal | AI8: Riesgo de trabajo (9) | AJ8: I.M.S.S. empresa | AK8: Infonavit empresa | AL8: Guarderia I.M.S.S. (7) | AM8: Proporcion Aguinaldo | AN8: CC
A9: SEI0010 | B9: Torres Ricardez Alfredo | C9: 15 | D9: 0 | E9: 266.67 | F9: 278.72 | G9: 4000.05 | H9: 0 | I9: 0 | J9: 4000.05 | K9: 313.87 | L9: 0 | M9: 100.81 | N9: 0 | O9: 0 | P9: 0 | Q9: 0 | R9: 0 | T9: -0.03 | U9: 414.65 | V9: 3585.4 | W9: 26.13 | X9: 47.03 | Y9: 27.65 | Z9: 0 | AA9: 313.87 | AC9: 73.16 | AD9: 131.7 | AE9: 335.88 | AF9: 4000.05 | AG9: 268.34 | AH9: 80 | AI9: 33.3 | AJ9: 540.74 | AK9: 209.04 | AL9: 226.53 | AM9: 219.0368 | AN9: PITSS
A10: SEI0014 | B10: Montoya Portillo Carlos Alberto | C10: 15 | D10: 0 | E10: 266.67 | F10: 278.72 | G10: 4000.05 | H10: 0 | I10: 0 | J10: 4000.05 | K10: 313.87 | L10: 0 | M10: 100.81 | N10: 0 | O10: 0 | P10: 0 | Q10: 0 | R10: 0 | T10: 0.17 | U10: 414.85 | V10: 3585.2 | W10: 26.13 | X10: 47.03 | Y10: 27.65 | Z10: 0 | AA10: 313.87 | AC10: 73.16 | AD10: 131.7 | AE10: 335.88 | AF10: 4000.05 | AG10: 268.34 | AH10: 80 | AI10: 33.3 | AJ10: 540.74 | AK10: 209.04 | AL10: 226.53 | AM10: 219.0368 | AN10: PITSS
A11: SEI0015 | B11: Cota Jaramillo Miguel Angel | C11: 15 | D11: 0 | E11: 200 | F11: 209.04 | G11: 3000 | H11: 0 | I11: 0 | J11: 3000 | K11: 59.69 | L11: 0 | M11: 74.48 | N11: 0 | O11: 0 | P11: 0 | Q11: 0 | R11: 0 | T11: 0.03 | U11: 134.2 | V11: 2865.8 | W11: 19.6 | X11: 35.28 | Y11: 19.6 | Z11: -145.38 | AA11: 205.07 | AC11: 54.87 | AD11: 98.77 | AE11: 313.41 | AF11: 3000 | AG11: 247.43 | AH11: 60 | AI11: 24.98 | AJ11: 467.05 | AK11: 156.78 | AL11: 216.08 | AM11: 164.27554 | AN11: PITSS
A12: SEI0017 | B12: Muñoz Reyes Luis Eduardo | C12: 15 | D12: 0 | E12: 266.67 | F12: 278.72 | G12: 4000.05 | H12: 0 | I12: 0 | J12: 4000.05 | K12: 313.87 | L12: 0 | M12: 100.81 | N12: 877.59 | O12: 0 | P12: 15 | Q12: 0 | R12: 0 | T12: -0.02 | U12: 1307.25 | V12: 2692.8 | W12: 26.13 | X12: 47.03 | Y12: 27.65 | Z12: 0 | AA12: 313.87 | AC12: 73.16 | AD12: 131.7 | AE12: 335.88 | AF12: 4000.05 | AG12: 268.34 | AH12: 80 | AI12: 33.3 | AJ12: 540.74 | AK12: 209.04 | AL12: 226.53 | AM12: 219.0368 | AN12: PITSS
A13: SEI0019 | B13: Gonzalez Rasgado Miguel Isaias | C13: 15 | D13: 0 | E13: 400 | F13: 424.2 | G13: 6000 | H13: 0 | I13: 0 | J13: 6000 | K13: 643.38 | L13: 0 | M13: 161.36 | N13: 0 | O13: 0 | P13: 0 | Q13: 0 | R13: 0 | T13: 0.06 | U13: 804.8 | V13: 5195.2 | W13: 39.77 | X13: 71.58 | Y13: 50.01 | Z13: 0 | AA13: 643.38 | AC13: 111.35 | AD13: 200.43 | AE13: 398.06 | AF13: 6000 | AG13: 311.98 | AH13: 120 | AI13: 50.69 | AJ13: 709.84 | AK13: 318.15 | AL13: 248.35 | AM13: 328.55109 | AN13: PITSS
A14: SEI0020 | B14: Mar Marquez Cesar Eduardo | C14: 15 | D14: 0 | E14: 266.67 | F14: 278.72 | G14: 4000.05 | H14: 0 | I14: 0 | J14: 4000.05 | K14: 313.87 | L14: 0 | M14: 100.81 | N14: 0 | O14: 0 | P14: 0 | Q14: 0 | R14: 0 | T14: -0.03 | U14: 414.65 | V14: 3585.4 | W14: 26.13 | X14: 47.03 | Y14: 27.65 | Z14: 0 | AA14: 313.87 | AC14: 73.16 | AD14: 131.7 | AE14: 335.88 | AF14: 4000.05 | AG14: 268.34 | AH14: 80 | AI14: 33.3 | AJ14: 540.74 | AK14: 209.04 | AL14: 226.53 | AM14: 219.0368 | AN14: PITSS
A15: SEI0021 | B15: Velez Rodriguez Jaime | C15: 15 | D15: 0 | E15: 200 | F15: 212.1 | G15: 3000 | H15: 0 | I15: 0 | J15: 3000 | K15: 59.69 | L15: 0 | M15: 75.55 | N15: 1359.23 | O15: 0 | P15: 15 | Q15: 0 | R15: 0 | T15: -0.07 | U15: 1509.4 | V15: 1490.6 | W15: 19.88 | X15: 35.79 | Y15: 19.88 | Z15: -145.38 | AA15: 205.07 | AC15: 55.68 | AD15: 100.22 | AE15: 314.22 | AF15: 3000 | AG15: 248.35 | AH15: 60 | AI15: 25.34 | AJ15: 470.12 | AK15: 159.08 | AL15: 216.54 | AM15: 164.27554 | AN15: PITSS
A16: SEI0022 | B16: Najera Lopez Raul | C16: 15 | D16: 0 | E16: 333.33 | F16: 353.5 | G16: 4999.95 | H16: 0 | I16: 0 | J16: 4999.95 | K16: 461.63 | L16: 0 | M16: 131.93 | N16: 0 | O16: 0 | P16: 0 | Q16: 0 | R16: 0 | T16: -0.01 | U16: 593.55 | V16: 4406.4 | W16: 33.14 | X16: 59.65 | Y16: 39.14 | Z16: 0 | AA16: 461.63 | AC16: 92.79 | AD16: 167.03 | AE16: 367.84 | AF16: 4999.95 | AG16: 290.77 | AH16: 100 | AI16: 42.24 | AJ16: 627.66 | AK16: 265.12 | AL16: 237.74 | AM16: 273.78984 | AN16: PITSS
A17: SEI0023 | B17: Puente Murguia Luis Felipe | C17: 15 | D17: 0 | E17: 233.33 | F17: 247.45 | G17: 3499.95 | H17: 0 | I17: 0 | J17: 3499.95 | K17: 134.36 | L17: 0 | M17: 88.16 | N17: 0 | O17: 0 | P17: 0 | Q17: 0 | R17: 0 | T17: 0.03 | U17: 222.55 | V17: 3277.4 | W17: 23.2 | X17: 41.76 | Y17: 23.2 | Z17: -125.1 | AA17: 259.46 | AC17: 64.95 | AD17: 116.92 | AE17: 323.49 | AF17: 3499.95 | AG17: 258.95 | AH17: 70 | AI17: 29.57 | AJ17: 505.36 | AK17: 185.58 | AL17: 221.84 | AM17: 191.65206 | AN17: PITSS
A18: SEI0028 | B18: Jimenez Alcaraz Elizabeth | C18: 15 | D18: 0 | E18: 200 | F18: 212.11 | G18: 3000 | H18: 0 | I18: 0 | J18: 3000 | K18: 59.69 | L18: 0 | M18: 75.56 | N18: 0 | O18: 0 | P18: 0 | Q18: 0 | R18: 0 | T18: -0.05 | U18: 135.2 | V18: 2864.8 | W18: 19.89 | X18: 35.79 | Y18: 19.88 | Z18: -145.38 | AA18: 205.07 | AC18: 55.68 | AD18: 100.22 | AE18: 314.22 | AF18: 3000 | AG18: 248.35 | AH18: 60 | AI18: 25.34 | AJ18: 470.12 | AK18: 159.08 | AL18: 216.54 | AM18: 164.27554 | AN18: PITSS
A19: SEI0029 | B19: Arceo Garcia Manuel Federico | C19: 14 | D19: 0 | E19: 200 | F19: 212.1 | G19: 2800 | H19: 0 | I19: 0 | J19: 2800 | K19: 37.93 | L19: 0 | M19: 71.85 | N19: 0 | O19: 0 | P19: 0 | Q19: 600 | R19: 0 | T19: 0.02 | U19: 709.8 | V19: 2090.2 | W19: 18.56 | X19: 33.41 | Y19: 19.88 | Z19: -145.38 | AA19: 183.31 | AC19: 55.68 | AD19: 100.22 | AE19: 314.22 | AF19: 2800 | AG19: 248.35 | AH19: 56 | AI19: 25.34 | AJ19: 470.12 | AK19: 159.08 | AL19: 216.54 | AM19: 164.27554 | AN19: PITSS
A20: SEI0364 | B20: Dominguez Lopez Mayeli Del Pilar | C20: 15 | D20: 0 | E20: 266.67 | F20: 282.81 | G20: 4000.05 | H20: 0 | I20: 0 | J20: 4000.05 | K20: 313.87 | L20: 0 | M20: 102.51 | N20: 0 | O20: 0 | P20: 0 | Q20: 0 | R20: 1666.67 | T20: 0 | U20: 2083.05 | V20: 1917 | W20: 26.51 | X20: 47.72 | Y20: 28.28 | Z20: 0 | AA20: 313.87 | AC20: 74.24 | AD20: 133.63 | AE20: 337.62 | AF20: 4000.05 | AG20: 269.56 | AH20: 80 | AI20: 33.79 | AJ20: 545.49 | AK20: 212.11 | AL20: 227.14 | AM20: 219.0368 | AN20: PITSS
... A78: SEI0530 | B78: Del Pilar Mendez Lucio | C78: 15 | D78: 0 | E78: 200 | F78: 209.04 | G78: 3000 | H78: 0 | I78: 0 | J78: 3000 | K78: 59.69 | L78: 0 | M78: 74.48 | N78: 0 | O78: 1605.6 | P78: 15 | Q78: 0 | R78: 0 | T78: 0.03 | U78: 1754.8 | V78: 1245.2 | W78: 19.6 | X78: 35.28 | Y78: 19.6 | Z78: -145.38 | AA78: 205.07 | AC78: 54.87 | AD78: 98.77 | AE78: 313.41 | AF78: 3000 | AG78: 247.43 | AH78: 60 | AI78: 24.98 | AJ78: 467.05 | AK78: 156.78 | AL78: 216.08 | AM78: 164.27554 | AN78: PITSS
A79: SEI0531 | B79: Garcia Valderrama Jose De Jesus | C79: 7 | D79: 0 | E79: 200 | F79: 209.04 | G79: 1400 | H79: 0 | I79: 0 | J79: 1400 | K79: 0 | L79: -123.82 | M79: 45.21 | N79: 0 | O79: 0 | P79: 0 | Q79: 0 | R79: 0 | S79: 0 | T79: 0.01 | U79: -78.6 | V79: 1478.6 | W79: 9.15 | X79: 16.46 | Y79: 19.6 | Z79: -200.63 | AA79: 76.81 | AC79: 54.87 | AD79: 98.77 | AE79: 313.41 | AF79: 1400 | AG79: 62.71 | AH79: 28 | AI79: 24.98 | AJ79: 467.05 | AK79: 156.78 | AL79: 31.36 | AM79: 164.28 | AN79: PITSS
A80: SEI0534 | B80: Gonzalez Ramirez Paul | C80: 15 | D80: 0 | E80: 200 | F80: 209.04 | G80: 3000 | H80: 0 | I80: 0 | J80: 3000 | K80: 59.69 | L80: 0 | M80: 74.48 | N80: 0 | O80: 0 | P80: 0 | Q80: 0 | R80: 0 | T80: 0.03 | U80: 134.2 | V80: 2865.8 | W80: 19.6 | X80: 35.28 | Y80: 19.6 | Z80: -145.38 | AA80: 205.07 | AC80: 54.87 | AD80: 98.77 | AE80: 313.41 | AF80: 3000 | AG80: 247.43 | AH80: 60 | AI80: 24.98 | AJ80: 467.05 | AK80: 156.78 | AL80: 216.08 | AM80: 164.27554 | AN80: PITSS
A81: SEI0535 | B81: Alejandro Vazquez Erasmo Miguel | C81: 15 | D81: 0 | E81: 200 | F81: 212.11 | G81: 3000 | H81: 0 | I81: 0 | J81: 3000 | K81: 59.69 | L81: 0 | M81: 75.56 | N81: 0 | O81: 477.81 | P81: 15 | Q81: 0 | R81: 0 | T81: -0.06 | U81: 628 | V81: 2372 | W81: 19.89 | X81: 35.79 | Y81: 19.88 | Z81: -145.38 | AA81: 205.07 | AC81: 55.68 | AD81: 100.22 | AE81: 314.22 | AF81: 3000 | AG81: 248.35 | AH81: 60 | AI81: 25.34 | AJ81: 470.12 | AK81: 159.08 | AL81: 216.54 | AM81: 164.27554 | AN81: PITSS
A82: SEI0536 | B82: Hernandez Ojeda Julio Cesar | C82: 15 | D82: 0 | E82: 116.67 | F82: 123.73 | G82: 1750.05 | H82: 0 | I82: 0 | J82: 1750.05 | K82: 0 | L82: -89.5 | M82: 44.08 | N82: 0 | O82: 854.85 | P82: 15 | Q82: 0 | R82: 0 | T82: 0.02 | U82: 824.45 | V82: 925.6 | W82: 11.6 | X82: 20.88 | Y82: 11.6 | Z82: -188.71 | AA82: 99.22 | AC82: 32.48 | AD82: 58.46 | AE82: 291.02 | AF82: 1750.05 | AG82: 221.84 | AH82: 35 | AI82: 14.78 | AJ82: 381.96 | AK82: 92.8 | AL82: 203.28 | AM82: 95.830139 | AN82: PITSS
A83: SEI0537 | B83: Serrano Esquivel Armando | C83: 15 | D83: 0 | E83: 116.67 | F83: 123.73 | G83: 1750.05 | H83: 0 | I83: 0 | J83: 1750.05 | K83: 0 | L83: -89.5 | M83: 44.08 | N83: 801.02 | O83: 0 | P83: 15 | Q83: 0 | R83: 0 | T83: 0.05 | U83: 770.65 | V83: 979.4 | W83: 11.6 | X83: 20.88 | Y83: 11.6 | Z83: -188.71 | AA83: 99.22 | AC83: 32.48 | AD83: 58.46 | AE83: 291.02 | AF83: 1750.05 | AG83: 221.84 | AH83: 35 | AI83: 14.78 | AJ83: 381.96 | AK83: 92.8 | AL83: 203.28 | AM83: 95.830139 | AN83: PITSS
A84: SEI0538 | B84: Coronado Vega Carlos Eduardo | C84: 15 | D84: 0 | E84: 210 | F84: 222.72 | G84: 3150 | H84: 0 | I84: 0 | J84: 3150 | K84: 96.29 | L84: 0 | M84: 79.34 | N84: 0 | O84: 0 | P84: 0 | Q84: 0 | R84: 0 | T84: -0.03 | U84: 175.6 | V84: 2974.4 | W84: 20.88 | X84: 37.58 | Y84: 20.88 | Z84: -125.1 | AA84: 221.39 | AC84: 58.46 | AD84: 105.24 | AE84: 317.01 | AF84: 3150 | AG84: 251.54 | AH84: 63 | AI84: 26.61 | AJ84: 480.71 | AK84: 167.04 | AL84: 218.13 | AM84: 86.244661 | AN84: PITSS
A85: SEI0539 | B85: Montes De Oca Trujillo Gloria | C85: 15 | D85: 0 | E85: 166.67 | F85: 176.76 | G85: 2500.05 | H85: 0 | I85: 0 | J85: 2500.05 | K85: 0 | L85: -9.62 | M85: 62.97 | N85: 0 | O85: 0 | P85: 0 | Q85: 0 | R85: 0 | T85: 0.1 | U85: 53.45 | V85: 2446.6 | W85: 16.57 | X85: 29.83 | Y85: 16.57 | Z85: -160.3 | AA85: 150.67 | AC85: 46.4 | AD85: 83.52 | AE85: 304.94 | AF85: 2500.05 | AG85: 237.75 | AH85: 50 | AI85: 21.12 | AJ85: 434.86 | AK85: 132.57 | AL85: 211.23 | AM85: 136.9 | AN85: PITSS
A86: SEI0540 | B86: Morales Martinez Eduardo | C86: 15 | D86: 0 | E86: 210 | F86: 222.72 | G86: 3150 | H86: 0 | I86: 0 | J86: 3150 | K86: 96.29 | L86: 0 | M86: 79.34 | N86: 0 | O86: 0 | P86: 0 | Q86: 0 | R86: 0 | T86: 0.17 | U86: 175.8 | V86: 2974.2 | W86: 20.88 | X86: 37.58 | Y86: 20.88 | Z86: -125.1 | AA86: 221.39 | AC86: 58.46 | AD86: 105.24 | AE86: 317.01 | AF86: 3150 | AG86: 251.54 | AH86: 63 | AI86: 26.61 | AJ86: 480.71 | AK86: 167.04 | AL86: 218.13 | AM86: 172.49 | AN86: PITSS
A87: SEI0541 | B87: Chavez Govea Edgar Aram | C87: 15 | D87: 0 | E87: 233.33 | F87: 247.46 | G87: 3499.95 | H87: 0 | I87: 0 | J87: 3499.95 | K87: 134.36 | L87: 0 | M87: 88.16 | N87: 0 | O87: 0 | P87: 0 | Q87: 0 | R87: 0 | T87: -0.17 | U87: 222.35 | V87: 3277.6 | W87: 23.2 | X87: 41.76 | Y87: 23.2 | Z87: -125.1 | AA87: 259.46 | AC87: 64.96 | AD87: 116.92 | AE87: 323.5 | AF87: 3499.95 | AG87: 258.96 | AH87: 70 | AI87: 29.57 | AJ87: 505.38 | AK87: 185.6 | AL87: 221.84 | AM87: 191.65 | AN87: PITSS
A88: SEI0542 | B88: Ramirez Elizalde Karen Viridiana | C88: 15 | D88: 0 | E88: 200 | F88: 209.04 | G88: 3000 | H88: 0 | I88: 0 | J88: 3000 | K88: 59.69 | L88: 0 | M88: 74.48 | N88: 0 | O88: 0 | P88: 0 | Q88: 0 | R88: 0 | T88: 0.03 | U88: 134.2 | V88: 2865.8 | W88: 19.6 | X88: 35.28 | Y88: 19.6 | Z88: -145.38 | AA88: 205.07 | AC88: 54.87 | AD88: 98.77 | AE88: 313.41 | AF88: 3000 | AG88: 247.43 | AH88: 60 | AI88: 24.98 | AJ88: 467.05 | AK88: 156.78 | AL88: 216.08 | AM88: 164.28 | AN88: PITSS
A89: SEI479 | B89: Cruz Perez Alejandro Nezahualcoyotl | C89: 15 | D89: 0 | E89: 266.67 | F89: 282.81 | G89: 4000.05 | H89: 0 | I89: 0 | J89: 4000.05 | K89: 313.87 | L89: 0 | M89: 102.51 | N89: 0 | O89: 0 | P89: 0 | Q89: 0 | R89: 0 | T89: 0.07 | U89: 416.45 | V89: 3583.6 | W89: 26.51 | X89: 47.72 | Y89: 28.28 | Z89: 0 | AA89: 313.87 | AC89: 74.24 | AD89: 133.63 | AE89: 337.62 | AF89: 4000.05 | AG89: 269.56 | AH89: 80 | AI89: 33.79 | AJ89: 545.49 | AK89: 212.11 | AL89: 227.14 | AM89: 219.0368 | AN89: PITSS
A90: SEI0543 | B90: Diaz Ortiz Hiram Guillermo | C90: 12 | D90: 0 | E90: 210 | F90: 219.49 | G90: 2520 | H90: 0 | I90: 0 | J90: 2520 | K90: 0 | L90: -7.45 | M90: 62.55 | N90: 600 | O90: 0 | P90: 0 | Q90: 0 | R90: 0 | T90: 0.1 | U90: 655.2 | V90: 1864.8 | W90: 16.46 | X90: 29.63 | Y90: 16.46 | Z90: -160.3 | AA90: 152.84 | AC90: 46.09 | AD90: 82.97 | AE90: 252.93 | AF90: 2520 | AG90: 237.4 | AH90: 50.4 | AI90: 20.98 | AJ90: 381.99 | AK90: 131.7 | AL90: 211.06 | AM90: 90.25 | AN90: PITSS
A91: Total Depto | C91: ----------------------- | D91: ----------------------- | E91: ----------------------- | F91: ----------------------- | G91: ----------------------- | H91: ----------------------- | I91: ----------------------- | J91: ----------------------- | K91: ----------------------- | L91: ----------------------- | M91: ----------------------- | N91: ----------------------- | O91: ----------------------- | P91: ----------------------- | Q91: ----------------------- | R91: ----------------------- | S91: ----------------------- | T91: ----------------------- | U91: ----------------------- | V91: ----------------------- | W91: ----------------------- | X91: ----------------------- | Y91: ----------------------- | Z91: ----------------------- | AA91: ----------------------- | AC91: ----------------------- | AD91: ----------------------- | AE91: ----------------------- | AF91: ----------------------- | AG91: ----------------------- | AH91: ----------------------- | AI91: ----------------------- | AJ91: ----------------------- | AK91: ----------------------- | AL91: ----------------------- | AM91: -----------------------
A92: =SUM(A9:A91) -> 0 | B92: =SUM(B9:B91) -> 0 | C92: =SUM(C9:C91) -> 1213 | D92: =SUM(D9:D91) -> 0 | E92: =SUM(E9:E91) -> 19589.93 | F92: =SUM(F9:F91) -> 20665.45 | G92: =SUM(G9:G91) -> 290189.19 | H92: =SUM(H9:H91) -> 0 | ... AM92: =SUM(AM9:AM91) -> 15922.257
I93: FACTURACION PITS | K93: PROVISION AGUINALDO
I94: Devengado Salario | J94: =+V92 -> 229673.73 | K94: FACTURACION PITS
I95: Retornos | J95: =+R92 -> 7609.9 | K95: Subtotal 1 | L95: =+AM92 -> 15922.257
I96: Infonavit | J96: =+N92+O92+P92 -> 28208.99 | K96: Comision | L96: =+L95*2% -> 318.44513
I97: Prestamo Prospera | J97: =+Q92 -> 1781.73 | K97: Subtotal 2 | L97: =+L95+L96 -> 16240.702
I98: aportacion voluntaria | J98: =+S92 -> 0 | K98: 2% Sobre Nomina | L98: =+L95*2% -> 318.44513
I99: Subtotal 1 | J99: =SUM(J94:J98) -> 267274.35 | K99: Importe de Factura | L99: =+L97+L98 -> 16559.147
I100: Comision | J100: =+J99*2% -> 5345.487 | K100: IVA | L100: =+L99*16% -> 2649.4635
I101: Subtotal 2 | J101: =+J99+J100 -> 272619.84 | K101: TOTAL | L101: =+L99+L100 -> 19208.61
I102: Costo Patronal Imss | J102: =+M92+AC92+AD92+AE92+AG92+AI92+AL92+AK92 -> 106591.39
I103: 2% Sobre Nomina | J103: =+J92*2% -> 5803.7838
I104: Importe de Factura | J104: =+J101+J102+J103 -> 385015.01
I105: certificacion de cheque | J105: 0
I106: IVA | J106: =(+J104+J105)*0.16 -> 61602.402
I107: TOTAL | J107: =+J104+J105+J106 -> 446617.41
G109: FACTURACION EM | J109: FACTURACION CPD | M109: FACTURACION IP | P109: FACTURACION IT
G110: Importe de Factura | H110: =+J104*4% -> 15400.6 | J110: Importe de Factura | K110: =+J104*12% -> 46201.801 | M110: Importe de Factura | N110: =+J104*11% -> 42351.651 | P110: Importe de Factura | Q110: =+J104*73% -> 281060.96
G111: IVA | H111: =+H110*16% -> 2464.0961 | J111: IVA | K111: =+K110*16% -> 7392.2882 | M111: IVA | N111: =+N110*16% -> 6776.2642 | P111: IVA | Q111: =+Q110*16% -> 44969.753
G112: TOTAL | H112: =+H110+H111 -> 17864.697 | J112: TOTAL | K112: =+K110+K111 -> 53594.09 | M112: TOTAL | N112: =+N110+N111 -> 49127.915 | P112: TOTAL | Q112: =+Q110+Q111 -> 326030.71
G115: FACTURACION EM | J115: FACTURACION CPD | M115: FACTURACION IP | P115: FACTURACION IT
G116: Importe de Factura | H116: =+L99*4% -> 662.36588 | J116: Importe de Factura | K116: =+L99*12% -> 1987.0976 | M116: Importe de Factura | N116: =+L99*11% -> 1821.5062 | P116: Importe de Factura | Q116: =+L99*73% -> 12088.177
G117: IVA | H117: =+H116*16% -> 105.97854 | J117: IVA | K117: =+K116*16% -> 317.93562 | M117: IVA | N117: =+N116*16% -> 291.44099 | P117: IVA | Q117: =+Q116*16% -> 1934.1084
G118: TOTAL | H118: =+H116+H117 -> 768.34442 | J118: TOTAL | K118: =+K116+K117 -> 2305.0332 | M118: TOTAL | N118: =+N116+N117 -> 2112.9471 | P118: TOTAL | Q118: =+Q116+Q117 -> 14022.286

Sheet SIND PITS
A5: 1 | B5: 2 | C5: 3 | D5: 4 | E5: 5 | F5: 6
A6: CLAVE | B6: EMPRESA | C6: NOMBRE | D6: PAGO POR SINDICATO | E6: comision y bono | F6: prima vacaciones | G6: TOTAL | H6: DIAS DE VACACIONES | I6: SUELDO NETO MENSUAL | J6: MONTO PRIMA TOTAL | K6: MENOS PRIMA IMSS | L6: PRIMA A PAGAR SINDICATO | M6: FACTURACION
A7: SEI0442 | B7: SEITON - (CONSULTORIA II) | C7: Sierra Escamilla Daniela | D7: 2464 | E7: 1000 | F7: =+L7 -> 0 | G7: =+D7+E7+F7 -> 3464 | H7: =VLOOKUP(C7,'CPD PITS'!$B$9:$D$27,3,0) -> 0 | I7: =VLOOKUP(C7,[1]RESUMEN!$C$4:$L$113,10,) -> 13000 | J7: =(((+I7/30)*H7)*30%) -> 0 | K7: =VLOOKUP(C7,[1]CPD!$B$9:$I$35,8,0) -> 0 | L7: =+J7-K7 -> 0 | M7: PITSS
A8: SEI0431 | B8: SEITON (IP INNOVA II) | C8: Alcaraz Conde Zabdi Guadalupe | D8: 135.2 | E8: 292.5 | F8: =+L8 -> 0 | G8: =+D8+E8+F8 -> 427.7 | H8: =VLOOKUP(C8,'IP PITS'!$B$9:$D$90,3,0) -> 0 | I8: =VLOOKUP(C8,[1]RESUMEN!$C$31:$L$127,10,0) -> 6000 | J8: =(((+I8/30)*H8)*30%) -> 0 | K8: =VLOOKUP(C8,[1]IP!$B$9:$I$116,8,0) -> 0 | L8: =+J8-K8 -> 0 | M8: PITSS
A9: SEI0527 | B9: SEITON (IP INNOVA II) | C9: Alejandro Peña Deivi | D9: 175.8 | E9: 618.75 | F9: =+L9 -> 0 | G9: =+D9+E9+F9 -> 794.55 | H9: =VLOOKUP(C9,'IP PITS'!$B$9:$D$90,3,0) -> 0 | I9: =VLOOKUP(C9,[1]RESUMEN!$C$31:$L$127,10,0) -> 6300 | J9: =(((+I9/30)*H9)*30%) -> 0 | K9: =VLOOKUP(C9,[1]IP!$B$9:$I$116,8,0) -> 0 | L9: =+J9-K9 -> 0 | M9: PITSS
A10: SEI0535 | B10: SEITON (IP INNOVA II) | C10: Alejandro Vazquez Erasmo Miguel | D10: 3135.19 | E10: 1750 | F10: =+L10 -> 0 | G10: =+D10+E10+F10 -> 4885.19 | H10: =VLOOKUP(C10,'IP PITS'!$B$9:$D$90,3,0) -> 0 | I10: 12000 | J10: =(((+I10/30)*H10)*30%) -> 0 | K10: =VLOOKUP(C10,[1]IP!$B$9:$I$116,8,0) -> 0 | L10: =+J10-K10 -> 0 | M10: PITSS
A11: SEI0029 | B11: SEITON (IP INNOVA II) | C11: Arceo Garcia Manuel Federico | D11: 109.8 | E11: 487.5 | F11: =+L11 -> 0 | G11: =+D11+E11+F11 -> 597.3 | H11: =VLOOKUP(C11,'IP PITS'!$B$9:$D$90,3,0) -> 0 | I11: =VLOOKUP(C11,[1]RESUMEN!$C$31:$L$127,10,0) -> 6000 | J11: =(((+I11/30)*H11)*30%) -> 0 | K11: =VLOOKUP(C11,[1]IP!$B$9:$I$116,8,0) -> 0 | L11: =+J11-K11 -> 0 | M11: PITSS
A12: SEI0097 | B12: SEITON - (CONSULTORIA II) | C12: Arreola Jimenez Jose Nieves | D12: 1558.11 | E12: 501 | F12: =+L12 -> 0 | G12: =+D12+E12+F12 -> 2059.11 | H12: =VLOOKUP(C12,'CPD PITS'!$B$9:$D$27,3,0) -> 0 | I12: =VLOOKUP(C12,[1]RESUMEN!$C$4:$L$113,10,) -> 10150 | J12: =(((+I12/30)*H12)*30%) -> 0 | K12: =VLOOKUP(C12,[1]CPD!$B$9:$I$35,8,0) -> 0 | L12: =+J12-K12 -> 0 | M12: PITSS
A13: SEI0118 | B13: SEITON - (CONSULTORIA II) | C13: Arroyo Ramirez Hector Hugo | D13: 2102.84 | F13: =+L13 -> 234.01 | G13: =+D13+E13+F13 -> 2336.85 | H13: 4 | I13: =VLOOKUP(C13,[1]RESUMEN!$C$4:$L$113,10,) -> 13000 | J13: =(((+I13/30)*H13)*30%) -> 520 | K13: =VLOOKUP(C13,[1]CPD!$B$9:$I$35,8,0) -> 285.99 | L13: =+J13-K13 -> 234.01 | M13: PITSS
A14: SEI0472 | B14: SEITON (IP INNOVA II) | C14: Arzate Gil Juan Sebastian | D14: 416.2 | E14: 463 | F14: =+L14 -> 0 | G14: =+D14+E14+F14 -> 879.2 | H14: =VLOOKUP(C14,'IP PITS'!$B$9:$D$90,3,0) -> 0 | I14: =VLOOKUP(C14,[1]RESUMEN!$C$31:$L$127,10,0) -> 8000 | J14: =(((+I14/30)*H14)*30%) -> 0 | K14: =VLOOKUP(C14,[1]IP!$B$9:$I$116,8,0) -> 0 | L14: =+J14-K14 -> 0 | M14: PITSS
A15: SEI0377 | B15: SEITON - (CONSULTORIA II) | C15: Benavides Herrera Alejandra | D15: 16803.2 | F15: =+L15 -> 0 | G15: =+D15+E15+F15 -> 16803.2 | H15: =VLOOKUP(C15,'CPD PITS'!$B$9:$D$27,3,0) -> 0 | I15: =VLOOKUP(C15,[1]RESUMEN!$C$4:$L$113,10,) -> 40000 | J15: =(((+I15/30)*H15)*30%) -> 0 | K15: =VLOOKUP(C15,[1]CPD!$B$9:$I$35,8,0) -> 0 | L15: =+J15-K15 -> 0 | M15: PITSS
A16: SEI0108 | B16: SEITON - (CONSULTORIA II) | C16: Caballero Diaz Francisco Javier | D16: 1558.09 | E16: =346+720 -> 1066 | F16: =+L16 -> 0 | G16: =+D16+E16+F16 -> 2624.09 | H16: =VLOOKUP(C16,'CPD PITS'!$B$9:$D$27,3,0) -> 0 | I16: =VLOOKUP(C16,[1]RESUMEN!$C$4:$L$113,10,) -> 10150 | J16: =(((+I16/30)*H16)*30%) -> 0 | K16: =VLOOKUP(C16,[1]CPD!$B$9:$I$35,8,0) -> 0 | L16: =+J16-K16 -> 0 | M16: PITSS
A17: SEI0425 | B17: SEITON - (CONSULTORIA II) | C17: Carbajal Cabuto Jose Luis | D17: 1608.1 | E17: =357+3080 -> 3437 | F17: =+L17 -> 0 | G17: =+D17+E17+F17 -> 5045.1 | H17: =VLOOKUP(C17,'CPD PITS'!$B$9:$D$27,3,0) -> 0 | I17: =VLOOKUP(C17,[1]RESUMEN!$C$4:$L$113,10,) -> 10250 | J17: =(((+I17/30)*H17)*30%) -> 0 | K17: =VLOOKUP(C17,[1]CPD!$B$9:$I$35,8,0) -> 0 | L17: =+J17-K17 -> 0 | M17: PITSS
A18: SEI0528 | B18: SEITON (IP INNOVA II) | C18: Casas Chavarria Rafael | D18: 175.61 | E18: 480 | F18: =+L18 -> 0 | G18: =+D18+E18+F18 -> 655.61 | H18: =VLOOKUP(C18,'IP PITS'!$B$9:$D$90,3,0) -> 0 | I18: =VLOOKUP(C18,[1]RESUMEN!$C$31:$L$127,10,0) -> 6300 | J18: =(((+I18/30)*H18)*30%) -> 0 | K18: =VLOOKUP(C18,[1]IP!$B$9:$I$116,8,0) -> 0 | L18: =+J18-K18 -> 0 | M18: PITSS
A19: SEI0116 | B19: SEITON - (CONSULTORIA II) | C19: Casillas Cardona Cesar Alejandro | D19: 1891.08 | F19: =+L19 -> 0 | G19: =+D19+E19+F19 -> 1891.08 | H19: =VLOOKUP(C19,'CPD PITS'!$B$9:$D$27,3,0) -> 0 | I19: =VLOOKUP(C19,[1]RESUMEN!$C$4:$L$113,10,) -> 12000 | J19: =(((+I19/30)*H19)*30%) -> 0 | K19: =VLOOKUP(C19,[1]CPD!$B$9:$I$35,8,0) -> 0 | L19: =+J19-K19 -> 0 | M19: PITSS
A20: SEI0460 | B20: SEITON (IP INNOVA II) | C20: Castellon Ramos Rene | D20: 384.775 | E20: 150 | F20: =+L20 -> 0 | G20: =+D20+E20+F20 -> 534.775 | H20: =VLOOKUP(C20,'IP PITS'!$B$9:$D$90,3,0) -> 0 | I20: =VLOOKUP(C20,[1]RESUMEN!$C$31:$L$127,10,0) -> 7505.99 | J20: =(((+I20/30)*H20)*30%) -> 0 | K20: =VLOOKUP(C20,[1]IP!$B$9:$I$116,8,0) -> 0 | L20: =+J20-K20 -> 0 | M20: PITSS
A21: SEI0443 | B21: SEITON (IP INNOVA II) | C21: Castillo Nungaray Nestor Roman | D21: 135.2 | E21: 1500 | F21: =+L21 -> 0 | G21: =+D21+E21+F21 -> 1635.2 | H21: =VLOOKUP(C21,'IP PITS'!$B$9:$D$90,3,0) -> 0 | I21: =VLOOKUP(C21,[1]RESUMEN!$C$31:$L$127,10,0) -> 6000 | J21: =(((+I21/30)*H21)*30%) -> 0 | K21: =VLOOKUP(C21,[1]IP!$B$9:$I$116,8,0) -> 0 | L21: =+J21-K21 -> 0 | M21: PITSS
A22: SEI0490 | B22: SEITON (IP INNOVA II) | C22: Castillo Ramirez Hector Ivan | D22: 3721.37 | E22: 208.5 | F22: =+L22 -> 0 | G22: =+D22+E22+F22 -> 3929.87 | H22: =VLOOKUP(C22,'IP PITS'!$B$9:$D$90,3,0) -> 0 | I22: =VLOOKUP(C22,[1]RESUMEN!$C$31:$L$127,10,0) -> 14000 | J22: =(((+I22/30)*H22)*30%) -> 0 | K22: =VLOOKUP(C22,[1]IP!$B$9:$I$116,8,0) -> 0 | L22: =+J22-K22 -> 0 | M22: PITSS
A23: SEI0508 | B23: SEITON (IP INNOVA II) | C23: Cerro Garcia Elvis | D23: 2553.4 | E23: 200 | F23: =+L23 -> 0 | G23: =+D23+E23+F23 -> 2753.4 | H23: =VLOOKUP(C23,'IP PITS'!$B$9:$D$90,3,0) -> 0 | I23: =VLOOKUP(C23,[1]RESUMEN!$C$31:$L$127,10,0) -> 10000 | J23: =(((+I23/30)*H23)*30%) -> 0 | K23: =VLOOKUP(C23,[1]IP!$B$9:$I$116,8,0) -> 0 | L23: =+J23-K23 -> 0 | M23: PITSS
A24: SEI0499 | B24: SEITON (IP INNOVA II) | C24: Chavez Dominguez Salvador | D24: 2667.4 | E24: 1054.5 | F24: =+L24 -> 0 | G24: =+D24+E24+F24 -> 3721.9 | H24: =VLOOKUP(C24,'IP PITS'!$B$9:$D$90,3,0) -> 0 | I24: =VLOOKUP(C24,[1]RESUMEN!$C$31:$L$127,10,0) -> 12000 | J24: =(((+I24/30)*H24)*30%) -> 0 | K24: =VLOOKUP(C24,[1]IP!$B$9:$I$116,8,0) -> 0 | L24: =+J24-K24 -> 0 | M24: PITSS
A25: SEI0541 | B25: SEITON (IP INNOVA II) | C25: Chavez Govea Edgar Aram | D25: 222.4 | F25: =+L25 -> 0 | G25: =+D25+E25+F25 -> 222.4 | H25: =VLOOKUP(C25,'IP PITS'!$B$9:$D$90,3,0) -> 0 | I25: 7000 | J25: =(((+I25/30)*H25)*30%) -> 0 | K25: =VLOOKUP(C25,[1]IP!$B$9:$I$116,8,0) -> 0 | L25: =+J25-K25 -> 0 | M25: PITSS
A26: SEI0442 | B26: SEITON (IP INNOVA II) | C26: Chavez Pedraza Samuel | D26: 1047.8 | E26: =420+675 -> 1095 | F26: =+L26 -> 0 | G26: =+D26+E26+F26 -> 2142.8 | H26: =VLOOKUP(C26,'IP PITS'!$B$9:$D$90,3,0) -> 0 | I26: =VLOOKUP(C26,[1]RESUMEN!$C$31:$L$127,10,0) -> 14000 | J26: =(((+I26/30)*H26)*30%) -> 0 | K26: =VLOOKUP(C26,[1]IP!$B$9:$I$116,8,0) -> 0 | L26: =+J26-K26 -> 0 | M26: PITSS
A27: SEI0462 | B27: SEITON (IP INNOVA II) | C27: Chavez Saucedo Jorge Arturo | D27: 414.6 | E27: 224.25 | F27: =+L27 -> 0 | G27: =+D27+E27+F27 -> 638.85 | H27: =VLOOKUP(C27,'IP PITS'!$B$9:$D$90,3,0) -> 0 | I27: =VLOOKUP(C27,[1]RESUMEN!$C$31:$L$127,10,0) -> 8000 | J27: =(((+I27/30)*H27)*30%) -> 0 | K27: =VLOOKUP(C27,[1]IP!$B$9:$I$116,8,0) -> 0 | L27: =+J27-K27 -> 0 | M27: PITSS
A28: SEI0456 | B28: SEITON (IP INNOVA II) | C28: Chavira Garcia David Fernando | D28: 593.6 | E28: 121.5 | F28: =+L28 -> 0 | G28: =+D28+E28+F28 -> 715.1 | H28: =VLOOKUP(C28,'IP PITS'!$B$9:$D$90,3,0) -> 0 | I28: =VLOOKUP(C28,[1]RESUMEN!$C$31:$L$127,10,0) -> 10000 | J28: =(((+I28/30)*H28)*30%) -> 0 | K28: =VLOOKUP(C28,[1]IP!$B$9:$I$116,8,0) -> 0 | L28: =+J28-K28 -> 0 | M28: PITSS
A29: SEI0538 | B29: SEITON (IP INNOVA II) | C29: Coronado Vega Carlos Eduardo | D29: 175.6 | F29: =+L29 -> 0 | G29: =+D29+E29+F29 -> 175.6 | H29: =VLOOKUP(C29,'IP PITS'!$B$9:$D$90,3,0) -> 0 | I29: 6300 | J29: =(((+I29/30)*H29)*30%) -> 0 | K29: =VLOOKUP(C29,[1]IP!$B$9:$I$116,8,0) -> 0 | L29: =+J29-K29 -> 0 | M29: PITSS
A30: SEI0015 | B30: SEITON (IP INNOVA II) | C30: Cota Jaramillo Miguel Angel | D30: 134.2 | E30: 378 | F30: =+L30 -> 0 | G30: =+D30+E30+F30 -> 512.2 | H30: =VLOOKUP(C30,'IP PITS'!$B$9:$D$90,3,0) -> 0 | I30: 6000 | J30: =(((+I30/30)*H30)*30%) -> 0 | K30: =VLOOKUP(C30,[1]IP!$B$9:$I$116,8,0) -> 0 | L30: =+J30-K30 -> 0 | M30: PITSS
A31: SEI0413 | B31: SEITON (IP INNOVA II) | C31: Courtenay Gutierrez Barry Vladimir | D31: 52.4 | E31: =3430+395.5 -> 3825.5 | F31: =+L31 -> 0 | G31: =+D31+E31+F31 -> 3877.9 | H31: =VLOOKUP(C31,'IP PITS'!$B$9:$D$90,3,0) -> 0 | I31: =VLOOKUP(C31,[1]RESUMEN!$C$31:$L$127,10,0) -> 5000 | J31: =(((+I31/30)*H31)*30%) -> 0 | K31: =VLOOKUP(C31,[1]IP!$B$9:$I$116,8,0) -> 0 | L31: =+J31-K31 -> 0 | M31: PITSS
A32: SEI0501 | B32: SEITON (IP INNOVA II) | C32: Cruz Herrera Roberto | D32: 1667.47 | E32: 226.5 | F32: =+L32 -> 0 | G32: =+D32+E32+F32 -> 1893.97 | H32: =VLOOKUP(C32,'IP PITS'!$B$9:$D$90,3,0) -> 0 | I32: =VLOOKUP(C32,[1]RESUMEN!$C$31:$L$127,10,0) -> 10000 | J32: =(((+I32/30)*H32)*30%) -> 0 | K32: =VLOOKUP(C32,[1]IP!$B$9:$I$116,8,0) -> 0 | L32: =+J32-K32 -> 0 | M32: PITSS
A33: SEI479 | B33: SEITON (IP INNOVA II) | C33: Cruz Perez Alejandro Nezahualcoyotl | D33: 416.4 | E33: 474 | F33: =+L33 -> 0 | G33: =+D33+E33+F33 -> 890.4 | H33: =VLOOKUP(C33,'IP PITS'!$B$9:$D$90,3,0) -> 0 | I33: =VLOOKUP(C33,[1]RESUMEN!$C$31:$L$127,10,0) -> 8000 | J33: =(((+I33/30)*H33)*30%) -> 0 | K33: =VLOOKUP(C33,[1]IP!$B$9:$I$116,8,0) -> 0 | L33: =+J33-K33 -> 0 | M33: PITSS
A34: SEI0401 | B34: SEITON - (CONSULTORIA II) | C34: De La Torre Zambara Francisco Ernesto | D34: 1558 | E34: =243.5+440 -> 683.5 | F34: =+L34 -> 0 | G34: =+D34+E34+F34 -> 2241.5 | H34: =VLOOKUP(C34,'CPD PITS'!$B$9:$D$27,3,0) -> 0 | I34: =VLOOKUP(C34,[1]RESUMEN!$C$4:$L$113,10,) -> 10150 | J34: =(((+I34/30)*H34)*30%) -> 0 | K34: =VLOOKUP(C34,[1]CPD!$B$9:$I$35,8,0) -> 0 | L34: =+J34-K34 -> 0 | M34: PITSS
A35: SEI0530 | B35: SEITON (IP INNOVA II) | C35: Del Pilar Mendez Lucio | D35: 134.2 | E35: 400 | F35: =+L35 -> 0 | G35: =+D35+E35+F35 -> 534.2 | H35: =VLOOKUP(C35,'IP PITS'!$B$9:$D$90,3,0) -> 0 | I35: =VLOOKUP(C35,[1]RESUMEN!$C$31:$L$127,10,0) -> 6000 | J35: =(((+I35/30)*H35)*30%) -> 0 | K35: =VLOOKUP(C35,[1]IP!$B$9:$I$116,8,0) -> 0 | L35: =+J35-K35 -> 0 | M35: PITSS
A36: SEI0543 | B36: SEITON (IP INNOVA II) | C36: Diaz Ortiz Hiram Guillermo | D36: 52.2 | F36: =+L36 -> 0 | G36: =+D36+E36+F36 -> 52.2 | H36: =VLOOKUP(C36,'IP PITS'!$B$9:$D$90,3,0) -> 0 | I36: 6300 | J36: =(((+I36/30)*H36)*30%) -> 0 | K36: =VLOOKUP(C36,[1]IP!$B$9:$I$116,8,0) -> 0 | L36: =+J36-K36 -> 0 | M36: PITSS
A37: SEI0364 | B37: SEITON (IP INNOVA II) | C37: Dominguez Lopez Mayeli Del Pilar | D37: 1416.33 | E37: 1250 | F37: =+L37 -> 0 | G37: =+D37+E37+F37 -> 2666.33 | H37: =VLOOKUP(C37,'IP PITS'!$B$9:$D$90,3,0) -> 0 | I37: =VLOOKUP(C37,[1]RESUMEN!$C$31:$L$127,10,0) -> 10000 | J37: =(((+I37/30)*H37)*30%) -> 0 | K37: =VLOOKUP(C37,[1]IP!$B$9:$I$116,8,0) -> 0 | L37: =+J37-K37 -> 0 | M37: PITSS
A38: SEI0474 | B38: SEITON (IP INNOVA II) | C38: Enriquez Zamora Jessica Del Rocio | D38: =109.8+25.42 -> 135.22 | E38: 292.5 | F38: =+L38 -> 0 | G38: =+D38+E38+F38 -> 427.72 | H38: =VLOOKUP(C38,'IP PITS'!$B$9:$D$90,3,0) -> 0 | I38: =VLOOKUP(C38,[1]RESUMEN!$C$31:$L$127,10,0) -> 6000 | J38: =(((+I38/30)*H38)*30%) -> 0 | K38: =VLOOKUP(C38,[1]IP!$B$9:$I$116,8,0) -> 0 | L38: =+J38-K38 -> 0 | M38: PITSS
A39: SEI0489 | B39: SEITON (IP INNOVA II) | C39: Escobedo Olivares Juan Guadalupe | D39: 3721.2 | E39: 166.67 | F39: =+L39 -> 0 | G39: =+D39+E39+F39 -> 3887.87 | H39: =VLOOKUP(C39,'IP PITS'!$B$9:$D$90,3,0) -> 0 | I39: =VLOOKUP(C39,[1]RESUMEN!$C$31:$L$127,10,0) -> 14000 | J39: =(((+I39/30)*H39)*30%) -> 0 | K39: =VLOOKUP(C39,[1]IP!$B$9:$I$116,8,0) -> 0 | L39: =+J39-K39 -> 0 | M39: PITSS
A40: SEI0449 | B40: SEITON (IP INNOVA II) | C40: Flores Cerrillos Jorge Humberto | D40: 416.4 | E40: 287 | F40: =+L40 -> 0 | G40: =+D40+E40+F40 -> 703.4 | H40: =VLOOKUP(C40,'IP PITS'!$B$9:$D$90,3,0) -> 0 | I40: =VLOOKUP(C40,[1]RESUMEN!$C$31:$L$127,10,0) -> 8000 | J40: =(((+I40/30)*H40)*30%) -> 0 | K40: =VLOOKUP(C40,[1]IP!$B$9:$I$116,8,0) -> 0 | L40: =+J40-K40 -> 0 | M40: PITSS
A41: SEI0461 | B41: SEITON (IP INNOVA II) | C41: Flores Franco Marco | D41: 451.005 | E41: 1200 | F41: =+L41 -> 0 | G41: =+D41+E41+F41 -> 1651.005 | H41: =VLOOKUP(C41,'IP PITS'!$B$9:$D$90,3,0) -> 0 | I41: =VLOOKUP(C41,[1]RESUMEN!$C$31:$L$127,10,0) -> 8500.01 | J41: =(((+I41/30)*H41)*30%) -> 0 | K41: =VLOOKUP(C41,[1]IP!$B$9:$I$116,8,0) -> 0 | L41: =+J41-K41 -> 0 | M41: PITSS
A42: SEI0500 | B42: SEITON (IP INNOVA II) | C42: Garcia Gutierrez Jose Juan | D42: 3135.2 | E42: 399.5 | F42: =+L42 -> 0 | G42: =+D42+E42+F42 -> 3534.7 | H42: =VLOOKUP(C42,'IP PITS'!$B$9:$D$90,3,0) -> 0 | I42: 12000 | J42: =(((+I42/30)*H42)*30%) -> 0 | K42: =VLOOKUP(C42,[1]IP!$B$9:$I$116,8,0) -> 0 | L42: =+J42-K42 -> 0 | M42: PITSS
A43: SEI0099 | B43: SEITON - (CONSULTORIA II) | C43: Garcia Villicaña Ricardo Pascual | D43: 2600.2 | E43: 216.5 | F43: =+L43 -> 0 | G43: =+D43+E43+F43 -> 2816.7 | H43: =VLOOKUP(C43,'CPD PITS'!$B$9:$D$27,3,0) -> 0 | I43: =VLOOKUP(C43,[1]RESUMEN!$C$4:$L$113,10,) -> 15000 | J43: =(((+I43/30)*H43)*30%) -> 0 | K43: =VLOOKUP(C43,[1]CPD!$B$9:$I$35,8,0) -> 0 | L43: =+J43-K43 -> 0 | M43: PITSS
A44: SEI0534 | B44: SEITON (IP INNOVA II) | C44: Gonzalez Ramirez Paul | D44: 134.2 | E44: 292.5 | F44: =+L44 -> 0 | G44: =+D44+E44+F44 -> 426.7 | H44: =VLOOKUP(C44,'IP PITS'!$B$9:$D$90,3,0) -> 0 | I44: =VLOOKUP(C44,[1]RESUMEN!$C$31:$L$127,10,0) -> 6000 | J44: =(((+I44/30)*H44)*30%) -> 0 | K44: =VLOOKUP(C44,[1]IP!$B$9:$I$116,8,0) -> 0 | L44: =+J44-K44 -> 0 | M44: PITSS
A45: SEI0019 | B45: SEITON (IP INNOVA II) | C45: Gonzalez Rasgado Miguel Isaias | D45: 804.8 | E45: =1480+937.5 -> 2417.5 | F45: =+L45 -> 0 | G45: =+D45+E45+F45 -> 3222.3 | H45: =VLOOKUP(C45,'IP PITS'!$B$9:$D$90,3,0) -> 0 | I45: =VLOOKUP(C45,[1]RESUMEN!$C$31:$L$127,10,0) -> 12000 | J45: =(((+I45/30)*H45)*30%) -> 0 | K45: =VLOOKUP(C45,[1]IP!$B$9:$I$116,8,0) -> 0 | L45: =+J45-K45 -> 0 | M45: PITSS
A46: SEI0457 | B46: SEITON (IP INNOVA II) | C46: Guerrero Lara Cesar Adrian | D46: 416.35 | E46: =1540+183.5 -> 1723.5 | F46: =+L46 -> 0 | G46: =+D46+E46+F46 -> 2139.85 | H46: =VLOOKUP(C46,'IP PITS'!$B$9:$D$90,3,0) -> 0 | I46: =VLOOKUP(C46,[1]RESUMEN!$C$31:$L$127,10,0) -> 8000 | J46: =(((+I46/30)*H46)*30%) -> 0 | K46: =VLOOKUP(C46,[1]IP!$B$9:$I$116,8,0) -> 0 | L46: =+J46-K46 -> 0 | M46: PITSS
A47: SEI0509 | B47: SEITON (IP INNOVA II) | C47: Gutierrez Castillo Jose De Jesus | D47: 284.2 | E47: =811 -> 811 | F47: =+L47 -> 0 | G47: =+D47+E47+F47 -> 1095.2 | H47: =VLOOKUP(C47,'IP PITS'!$B$9:$D$90,3,0) -> 0 | I47: =VLOOKUP(C47,[1]RESUMEN!$C$31:$L$127,10,0) -> 6300 | J47: =(((+I47/30)*H47)*30%) -> 0 | K47: =VLOOKUP(C47,[1]IP!$B$9:$I$116,8,0) -> 0 | L47: =+J47-K47 -> 0 | M47: PITSS
A48: SEI0009 | B48: SEITON - (CONSULTORIA II) | C48: Gutierrez Gutierrez Luis Arturo | D48: 1475.4 | F48: =+L48 -> 0 | G48: =+D48+E48+F48 -> 1475.4 | H48: =VLOOKUP(C48,'CPD PITS'!$B$9:$D$27,3,0) -> 0 | I48: =VLOOKUP(C48,[1]RESUMEN!$C$4:$L$113,10,) -> 8500 | J48: =(((+I48/30)*H48)*30%) -> 0 | K48: =VLOOKUP(C48,[1]CPD!$B$9:$I$35,8,0) -> 0 | L48: =+J48-K48 -> 0 | M48: PITSS
A49: SEI0483 | B49: SEITON (IP INNOVA II) | C49: Gutierrez Muñoz Carlos Alejandro | D49: 2884.94 | F49: =+L49 -> 0 | G49: =+D49+E49+F49 -> 2884.94 | H49: =VLOOKUP(C49,'IP PITS'!$B$9:$D$90,3,0) -> 0 | I49: =VLOOKUP(C49,[1]RESUMEN!$C$31:$L$127,10,0) -> 12000 | J49: =(((+I49/30)*H49)*30%) -> 0 | K49: =VLOOKUP(C49,[1]IP!$B$9:$I$116,8,0) -> 0 | L49: =+J49-K49 -> 0 | M49: PITSS
A50: SEI0476 | B50: SEITON (IP INNOVA II) | C50: Hernandez Garcia Manuel Alejandro | D50: 414.6 | E50: 359 | F50: =+L50 -> 0 | G50: =+D50+E50+F50 -> 773.6 | H50: =VLOOKUP(C50,'IP PITS'!$B$9:$D$90,3,0) -> 0 | I50: =VLOOKUP(C50,[1]RESUMEN!$C$31:$L$127,10,0) -> 8000 | J50: =(((+I50/30)*H50)*30%) -> 0 | K50: =VLOOKUP(C50,[1]IP!$B$9:$I$116,8,0) -> 0 | L50: =+J50-K50 -> 0 | M50: PITSS
A51: SEI0127 | B51: SEITON - (CONSULTORIA II) | C51: Hernandez Ochoa Eduardo | D51: 2600.2 | E51: =468+1600 -> 2068 | F51: =+L51 -> 0 | G51: =+D51+E51+F51 -> 4668.2 | H51: =VLOOKUP(C51,'CPD PITS'!$B$9:$D$27,3,0) -> 0 | I51: =VLOOKUP(C51,[1]RESUMEN!$C$4:$L$113,10,) -> 15000 | J51: =(((+I51/30)*H51)*30%) -> 0 | K51: =VLOOKUP(C51,[1]CPD!$B$9:$I$35,8,0) -> 0 | L51: =+J51-K51 -> 0 | M51: PITSS
A52: SEI0536 | B52: SEITON (IP INNOVA II) | C52: Hernandez Ojeda Julio Cesar | D52: 1704.55 | F52: =+L52 -> 0 | G52: =+D52+E52+F52 -> 1704.55 | H52: =VLOOKUP(C52,'IP PITS'!$B$9:$D$90,3,0) -> 0 | I52: 7000 | J52: =(((+I52/30)*H52)*30%) -> 0 | K52: =VLOOKUP(C52,[1]IP!$B$9:$I$116,8,0) -> 0 | L52: =+J52-K52 -> 0 | M52: PITSS
A53: SEI0523 | B53: SEITON (IP INNOVA II) | C53: Hernandez Rodriguez Jorge | D53: 222.47 | E53: =2228+300 -> 2528 | F53: =+L53 -> 0 | G53: =+D53+E53+F53 -> 2750.47 | H53: =VLOOKUP(C53,'IP PITS'!$B$9:$D$90,3,0) -> 0 | I53: =VLOOKUP(C53,[1]RESUMEN!$C$31:$L$127,10,0) -> 7000 | J53: =(((+I53/30)*H53)*30%) -> 0 | K53: =VLOOKUP(C53,[1]IP!$B$9:$I$116,8,0) -> 0 | L53: =+J53-K53 -> 0 | M53: PITSS
A54: SEI0464 | B54: SEITON (IP INNOVA II) | C54: Hueramo Hueramo Jesus Daniel | D54: 450.965 | E54: =520+306 -> 826 | F54: =+L54 -> 0 | G54: =+D54+E54+F54 -> 1276.965 | H54: =VLOOKUP(C54,'IP PITS'!$B$9:$D$90,3,0) -> 0 | I54: =VLOOKUP(C54,[1]RESUMEN!$C$31:$L$127,10,0) -> 8500.01 | J54: =(((+I54/30)*H54)*30%) -> 0 | K54: =VLOOKUP(C54,[1]IP!$B$9:$I$116,8,0) -> 0 | L54: =+J54-K54 -> 0 | M54: PITSS
A55: SEI0028 | B55: SEITON (IP INNOVA II) | C55: Jimenez Alcaraz Elizabeth | D55: 585.2 | F55: =+L55 -> 0 | G55: =+D55+E55+F55 -> 585.2 | H55: =VLOOKUP(C55,'IP PITS'!$B$9:$D$90,3,0) -> 0 | I55: =VLOOKUP(C55,[1]RESUMEN!$C$31:$L$127,10,0) -> 6900 | J55: =(((+I55/30)*H55)*30%) -> 0 | K55: =VLOOKUP(C55,[1]IP!$B$9:$I$116,8,0) -> 0 | L55: =+J55-K55 -> 0 | M55: PITSS
A56: SEI0511 | B56: SEITON (IP INNOVA II) | C56: Lizaran Maceda Jose Guadalupe | D56: 52.8 | E56: 305.5 | F56: =+L56 -> 0 | G56: =+D56+E56+F56 -> 358.3 | H56: =VLOOKUP(C56,'IP PITS'!$B$9:$D$90,3,0) -> 0 | I56: =VLOOKUP(C56,[1]RESUMEN!$C$31:$L$127,10,0) -> 5000 | J56: =(((+I56/30)*H56)*30%) -> 0 | K56: =VLOOKUP(C56,[1]IP!$B$9:$I$116,8,0) -> 0 | L56: =+J56-K56 -> 0 | M56: PITSS
A57: SEI0525 | B57: SEITON (IP INNOVA II) | C57: Lizaran Maceda Jesus | D57: 175.65 | F57: =+L57 -> 0 | G57: =+D57+E57+F57 -> 175.65 | H57: =VLOOKUP(C57,'IP PITS'!$B$9:$D$90,3,0) -> 0 | I57: =VLOOKUP(C57,[1]RESUMEN!$C$31:$L$127,10,0) -> 6300 | J57: =(((+I57/30)*H57)*30%) -> 0 | K57: =VLOOKUP(C57,[1]IP!$B$9:$I$116,8,0) -> 0 | L57: =+J57-K57 -> 0 | M57: PITSS
A58: SEI0438 | B58: SEITON (IP INNOVA II) | C58: Lopez Terron Roberto Porfirio | D58: 1047.8 | E58: =1268+1600+200 -> 3068 | F58: =+L58 -> 0 | G58: =+D58+E58+F58 -> 4115.8 | H58: =VLOOKUP(C58,'IP PITS'!$B$9:$D$90,3,0) -> 0 | I58: =VLOOKUP(C58,[1]RESUMEN!$C$31:$L$127,10,0) -> 14000 | J58: =(((+I58/30)*H58)*30%) -> 0 | K58: =VLOOKUP(C58,[1]IP!$B$9:$I$116,8,0) -> 0 | L58: =+J58-K58 -> 0 | M58: PITSS
A59: SEI0517 | B59: SEITON (IP INNOVA II) | C59: Macias Torres Enrique | D59: 5513.35 | E59: 2102.5 | F59: =+L59 -> 0 | G59: =+D59+E59+F59 -> 7615.85 | H59: =VLOOKUP(C59,'IP PITS'!$B$9:$D$90,3,0) -> 0 | I59: =VLOOKUP(C59,[1]RESUMEN!$C$31:$L$127,10,0) -> 19950 | J59: =(((+I59/30)*H59)*30%) -> 0 | K59: =VLOOKUP(C59,[1]IP!$B$9:$I$116,8,0) -> 0 | L59: =+J59-K59 -> 0 | M59: PITSS
A60: SEI0020 | B60: SEITON (IP INNOVA II) | C60: Mar Marquez Cesar Eduardo | D60: 414.6 | E60: 168.5 | F60: =+L60 -> 0 | G60: =+D60+E60+F60 -> 583.1 | H60: =VLOOKUP(C60,'IP PITS'!$B$9:$D$90,3,0) -> 0 | I60: =VLOOKUP(C60,[1]RESUMEN!$C$31:$L$127,10,0) -> 8000 | J60: =(((+I60/30)*H60)*30%) -> 0 | K60: =VLOOKUP(C60,[1]IP!$B$9:$I$116,8,0) -> 0 | L60: =+J60-K60 -> 0 | M60: PITSS
A61: SEI0117 | B61: SEITON - (CONSULTORIA II) | C61: Mariscal Romero Luis Adrian | D61: 2751 | E61: 250 | F61: =+L61 -> 0 | G61: =+D61+E61+F61 -> 3001 | H61: =VLOOKUP(C61,'CPD PITS'!$B$9:$D$27,3,0) -> 0 | I61: =VLOOKUP(C61,[1]RESUMEN!$C$4:$L$113,10,) -> 15000 | J61: =(((+I61/30)*H61)*30%) -> 0 | K61: =VLOOKUP(C61,[1]CPD!$B$9:$I$35,8,0) -> 0 | L61: =+J61-K61 -> 0 | M61: PITSS
A62: SEI0444 | B62: SEITON (IP INNOVA II) | C62: Marquez Hernandez Rogelio | D62: 416.4 | E62: =500+326 -> 826 | F62: =+L62 -> 0 | G62: =+D62+E62+F62 -> 1242.4 | H62: =VLOOKUP(C62,'IP PITS'!$B$9:$D$90,3,0) -> 0 | I62: =VLOOKUP(C62,[1]RESUMEN!$C$31:$L$127,10,0) -> 8000 | J62: =(((+I62/30)*H62)*30%) -> 0 | K62: =VLOOKUP(C62,[1]IP!$B$9:$I$116,8,0) -> 0 | L62: =+J62-K62 -> 0 | M62: PITSS
A63: SEI0428 | B63: SEITON (IP INNOVA II) | C63: Martinez Hernandez J. Antonio | D63: 416.2 | E63: 280 | F63: =+L63 -> 0 | G63: =+D63+E63+F63 -> 696.2 | H63: =VLOOKUP(C63,'IP PITS'!$B$9:$D$90,3,0) -> 0 | I63: =VLOOKUP(C63,[1]RESUMEN!$C$31:$L$127,10,0) -> 8000 | J63: =(((+I63/30)*H63)*30%) -> 0 | K63: =VLOOKUP(C63,[1]IP!$B$9:$I$116,8,0) -> 0 | L63: =+J63-K63 -> 0 | M63: PITSS
A64: SEI0504 | B64: SEITON (IP INNOVA II) | C64: Martinez Malo Cesar | D64: 1694.1 | E64: 382 | F64: =+L64 -> 0 | G64: =+D64+E64+F64 -> 2076.1 | H64: =VLOOKUP(C64,'IP PITS'!$B$9:$D$90,3,0) -> 0 | I64: =VLOOKUP(C64,[1]RESUMEN!$C$31:$L$127,10,0) -> 9000 | J64: =(((+I64/30)*H64)*30%) -> 0 | K64: =VLOOKUP(C64,[1]IP!$B$9:$I$116,8,0) -> 0 | L64: =+J64-K64 -> 0 | M64: PITSS
A65: SEI0469 | B65: SEITON (IP INNOVA II) | C65: Martinez Morales Jose Martin | D65: 1047.8 | E65: 303.5 | F65: =+L65 -> 0 | G65: =+D65+E65+F65 -> 1351.3 | H65: =VLOOKUP(C65,'IP PITS'!$B$9:$D$90,3,0) -> 0 | I65: =VLOOKUP(C65,[1]RESUMEN!$C$31:$L$127,10,0) -> 14000 | J65: =(((+I65/30)*H65)*30%) -> 0 | K65: =VLOOKUP(C65,[1]IP!$B$9:$I$116,8,0) -> 0 | L65: =+J65-K65 -> 0 | M65: PITSS
A66: SEI0493 | B66: SEITON (IP INNOVA II) | C66: Martinez Morales Tomas | D66: 3339.5 | E66: =2488+244 -> 2732 | F66: =+L66 -> 0 | G66: =+D66+E66+F66 -> 6071.5 | H66: =VLOOKUP(C66,'IP PITS'!$B$9:$D$90,3,0) -> 0 | I66: =VLOOKUP(C66,[1]RESUMEN!$C$31:$L$127,10,0) -> 15000 | J66: =(((+I66/30)*H66)*30%) -> 0 | K66: =VLOOKUP(C66,[1]IP!$B$9:$I$116,8,0) -> 0 | L66: =+J66-K66 -> 0 | M66: PITSS
A67: SEI0503 | B67: SEITON (IP INNOVA II) | C67: Martinez Rodriguez Paulo Cesar | D67: 2552.4 | E67: 250 | F67: =+L67 -> 0 | G67: =+D67+E67+F67 -> 2802.4 | H67: =VLOOKUP(C67,'IP PITS'!$B$9:$D$90,3,0) -> 0 | I67: =VLOOKUP(C67,[1]RESUMEN!$C$31:$L$127,10,0) -> 10000 | J67: =(((+I67/30)*H67)*30%) -> 0 | K67: =VLOOKUP(C67,[1]IP!$B$9:$I$116,8,0) -> 0 | L67: =+J67-K67 -> 0 | M67: PITSS
A68: SEI0458 | B68: SEITON (IP INNOVA II) | C68: Martinez Zamora Gerardo Mario | D68: 549.905 | E68: 858.5 | F68: =+L68 -> 0 | G68: =+D68+E68+F68 -> 1408.405 | H68: =VLOOKUP(C68,'IP PITS'!$B$9:$D$90,3,0) -> 0 | I68: =VLOOKUP(C68,[1]RESUMEN!$C$31:$L$127,10,0) -> 9550.01 | J68: =(((+I68/30)*H68)*30%) -> 0 | K68: =VLOOKUP(C68,[1]IP!$B$9:$I$116,8,0) -> 0 | L68: =+J68-K68 -> 0 | M68: PITSS
A69: SEI0494 | B69: SEITON (IP INNOVA II) | C69: Medellin Colunga Ruben Dario | D69: 4339.44 | E69: =1480+484.38 -> 1964.38 | F69: =+L69 -> 0 | G69: =+D69+E69+F69 -> 6303.82 | H69: =VLOOKUP(C69,'IP PITS'!$B$9:$D$90,3,0) -> 0 | I69: =VLOOKUP(C69,[1]RESUMEN!$C$31:$L$127,10,0) -> 17000 | J69: =(((+I69/30)*H69)*30%) -> 0 | K69: =VLOOKUP(C69,[1]IP!$B$9:$I$116,8,0) -> 0 | L69: =+J69-K69 -> 0 | M69: PITSS
A70: SEI0506 | B70: SEITON (IP INNOVA II) | C70: Mejia Duarte Jose Luis | D70: 3553.4 | E70: =260+552 -> 812 | F70: =+L70 -> 0 | G70: =+D70+E70+F70 -> 4365.4 | H70: =VLOOKUP(C70,'IP PITS'!$B$9:$D$90,3,0) -> 0 | I70: =VLOOKUP(C70,[1]RESUMEN!$C$31:$L$127,10,0) -> 12000 | J70: =(((+I70/30)*H70)*30%) -> 0 | K70: =VLOOKUP(C70,[1]IP!$B$9:$I$116,8,0) -> 0 | L70: =+J70-K70 -> 0 | M70: PITSS
A71: SEI0513 | B71: SEITON (IP INNOVA II) | C71: Mendez Rivera Ivan Israel | D71: 52.44 | E71: 338.5 | F71: =+L71 -> 0 | G71: =+D71+E71+F71 -> 390.94 | H71: =VLOOKUP(C71,'IP PITS'!$B$9:$D$90,3,0) -> 0 | I71: =VLOOKUP(C71,[1]RESUMEN!$C$31:$L$127,10,0) -> 5000 | J71: =(((+I71/30)*H71)*30%) -> 0 | K71: =VLOOKUP(C71,[1]IP!$B$9:$I$116,8,0) -> 0 | L71: =+J71-K71 -> 0 | M71: PITSS
A72: SEI0488 | B72: SEITON (IP INNOVA II) | C72: Mireles Casillas Brenda Cristina | D72: 2262.2 | F72: =+L72 -> 0 | G72: =+D72+E72+F72 -> 2262.2 | H72: =VLOOKUP(C72,'IP PITS'!$B$9:$D$90,3,0) -> 0 | I72: =VLOOKUP(C72,[1]RESUMEN!$C$31:$L$127,10,0) -> 9000 | J72: =(((+I72/30)*H72)*30%) -> 0 | K72: =VLOOKUP(C72,[1]IP!$B$9:$I$116,8,0) -> 0 | L72: =+J72-K72 -> 0 | M72: PITSS
A73: SEI0485 | B73: SEITON (IP INNOVA II) | C73: Molina Ramirez Gerardo Daniel | D73: 2262.37 | E73: 450 | F73: =+L73 -> 0 | G73: =+D73+E73+F73 -> 2712.37 | H73: =VLOOKUP(C73,'IP PITS'!$B$9:$D$90,3,0) -> 0 | I73: =VLOOKUP(C73,[1]RESUMEN!$C$31:$L$127,10,0) -> 9000 | J73: =(((+I73/30)*H73)*30%) -> 0 | K73: =VLOOKUP(C73,[1]IP!$B$9:$I$116,8,0) -> 0 | L73: =+J73-K73 -> 0 | M73: PITSS
A74: SEI0539 | B74: SEITON (IP INNOVA II) | C74: Montes De Oca Trujillo Gloria | D74: 53.4 | F74: =+L74 -> 0 | G74: =+D74+E74+F74 -> 53.4 | H74: =VLOOKUP(C74,'IP PITS'!$B$9:$D$90,3,0) -> 0 | I74: 5000 | J74: =(((+I74/30)*H74)*30%) -> 0 | K74: =VLOOKUP(C74,[1]IP!$B$9:$I$116,8,0) -> 0 | L74: =+J74-K74 -> 0 | M74: PITSS
A75: SEI0014 | B75: SEITON (IP INNOVA II) | C75: Montoya Portillo Carlos Alberto | D75: 414.8 | E75: 121.5 | F75: 0 | G75: =+D75+E75+F75 -> 536.3 | H75: =VLOOKUP(C75,'IP PITS'!$B$9:$D$90,3,0) -> 0 | I75: =VLOOKUP(C75,[1]RESUMEN!$C$31:$L$127,10,0) -> 8000 | J75: =(((+I75/30)*H75)*30%) -> 0 | K75: =VLOOKUP(C75,[1]IP!$B$9:$I$116,8,0) -> 0 | L75: =+J75-K75 -> 0 | M75: PITSS
A76: SEI0040 | B76: SEITON - (CONSULTORIA II) | C76: Mora Ramirez Acal Aldo Isidro | D76: 2464 | E76: 1000 | F76: =+L76 -> 0 | G76: =+D76+E76+F76 -> 3464 | H76: =VLOOKUP(C76,'CPD PITS'!$B$9:$D$27,3,0) -> 0 | I76: =VLOOKUP(C76,[1]RESUMEN!$C$4:$L$113,10,) -> 13000 | J76: =(((+I76/30)*H76)*30%) -> 0 | K76: =VLOOKUP(C76,[1]CPD!$B$9:$I$35,8,0) -> 0 | L76: =+J76-K76 -> 0 | M76: PITSS
A77: SEI0540 | B77: SEITON (IP INNOVA II) | C77: Morales Martinez Eduardo | D77: 175.8 | F77: =+L77 -> 0 | G77: =+D77+E77+F77 -> 175.8 | H77: =VLOOKUP(C77,'IP PITS'!$B$9:$D$90,3,0) -> 0 | I77: 6300 | J77: =(((+I77/30)*H77)*30%) -> 0 | K77: =VLOOKUP(C77,[1]IP!$B$9:$I$116,8,0) -> 0 | L77: =+J77-K77 -> 0 | M77: PITSS
A78: SEI0475 | B78: SEITON (IP INNOVA II) | C78: Moreno Quiroga Ana Sarahi | D78: 416.2 | E78: 1250 | F78: =+L78 -> 0 | G78: =+D78+E78+F78 -> 1666.2 | H78: =VLOOKUP(C78,'IP PITS'!$B$9:$D$90,3,0) -> 0 | I78: =VLOOKUP(C78,[1]RESUMEN!$C$31:$L$127,10,0) -> 8000 | J78: =(((+I78/30)*H78)*30%) -> 0 | K78: =VLOOKUP(C78,[1]IP!$B$9:$I$116,8,0) -> 0 | L78: =+J78-K78 -> 0 | M78: PITSS
A79: SEI0088 | B79: SEITON - (CONSULTORIA II) | C79: Morgado Fernandez Martin | D79: 2600.4 | E79: =281.5+840 -> 1121.5 | F79: =+L79 -> 0 | G79: =+D79+E79+F79 -> 3721.9 | H79: =VLOOKUP(C79,'CPD PITS'!$B$9:$D$27,3,0) -> 0 | I79: =VLOOKUP(C79,[1]RESUMEN!$C$4:$L$113,10,) -> 15000 | J79: =(((+I79/30)*H79)*30%) -> 0 | K79: =VLOOKUP(C79,[1]CPD!$B$9:$I$35,8,0) -> 0 | L79: =+J79-K79 -> 0 | M79: PITSS
A80: SEI0445 | B80: SEITON - (CONSULTORIA II) | C80: Muñoz Melgoza Gabriel | D80: 3090.6 | E80: 250 | F80: =+L80 -> 0 | G80: =+D80+E80+F80 -> 3340.6 | H80: =VLOOKUP(C80,'CPD PITS'!$B$9:$D$27,3,0) -> 0 | I80: 15400 | K80: =VLOOKUP(C80,[1]CPD!$B$9:$I$35,8,0) -> 0 | M80: PITSS
A81: SEI0017 | B81: SEITON (IP INNOVA II) | C81: Muñoz Reyes Luis Eduardo | D81: 414.61 | E81: 358.5 | F81: =+L81 -> 0 | G81: =+D81+E81+F81 -> 773.11 | H81: =VLOOKUP(C81,'IP PITS'!$B$9:$D$90,3,0) -> 0 | I81: =VLOOKUP(C81,[1]RESUMEN!$C$31:$L$127,10,0) -> 8000 | J81: =(((+I81/30)*H81)*30%) -> 0 | K81: =VLOOKUP(C81,[1]IP!$B$9:$I$116,8,0) -> 0 | L81: =+J81-K81 -> 0 | M81: PITSS
A82: SEI0022 | B82: SEITON (IP INNOVA II) | C82: Najera Lopez Raul | D82: 593.6 | E82: 121.5 | F82: =+L82 -> 0 | G82: =+D82+E82+F82 -> 715.1 | H82: =VLOOKUP(C82,'IP PITS'!$B$9:$D$90,3,0) -> 0 | I82: =VLOOKUP(C82,[1]RESUMEN!$C$31:$L$127,10,0) -> 10000 | J82: =(((+I82/30)*H82)*30%) -> 0 | K82: =VLOOKUP(C82,[1]IP!$B$9:$I$116,8,0) -> 0 | L82: =+J82-K82 -> 0 | M82: PITSS
A83: SEI0173 | B83: SEITON - (CONSULTORIA II) | C83: Nieto Ortiz Jose Luis | D83: 1483.13 | E83: 83 | F83: =+L83 -> 0 | G83: =+D83+E83+F83 -> 1566.13 | H83: =VLOOKUP(C83,'CPD PITS'!$B$9:$D$27,3,0) -> 0 | I83: =VLOOKUP(C83,[1]RESUMEN!$C$4:$L$113,10,) -> 10000 | J83: =(((+I83/30)*H83)*30%) -> 0 | K83: =VLOOKUP(C83,[1]CPD!$B$9:$I$35,8,0) -> 0 | L83: =+J83-K83 -> 0 | M83: PITSS
A84: SEI0524 | B84: SEITON (IP INNOVA II) | C84: Orea Gonzalez Concepcion Esteban | D84: 175.8 | E84: 843.75 | F84: =+L84 -> 0 | G84: =+D84+E84+F84 -> 1019.55 | H84: =VLOOKUP(C84,'IP PITS'!$B$9:$D$90,3,0) -> 0 | I84: =VLOOKUP(C84,[1]RESUMEN!$C$31:$L$127,10,0) -> 6300 | J84: =(((+I84/30)*H84)*30%) -> 0 | K84: =VLOOKUP(C84,[1]IP!$B$9:$I$116,8,0) -> 0 | L84: =+J84-K84 -> 0 | M84: PITSS
A85: SEI0424 | B85: SEITON (IP INNOVA II) | C85: Palacios Ramos Jesus | D85: 416.4 | E85: =1332+349 -> 1681 | F85: =+L85 -> 0 | G85: =+D85+E85+F85 -> 2097.4 | H85: =VLOOKUP(C85,'IP PITS'!$B$9:$D$90,3,0) -> 0 | I85: =VLOOKUP(C85,[1]RESUMEN!$C$31:$L$127,10,0) -> 8000 | J85: =(((+I85/30)*H85)*30%) -> 0 | K85: =VLOOKUP(C85,[1]IP!$B$9:$I$116,8,0) -> 0 | L85: =+J85-K85 -> 0 | M85: PITSS
A86: SEI0519 | B86: SEITON (IP INNOVA II) | C86: Palacios Vega Luis Rosendo | D86: 52.4 | E86: =910+186.5 -> 1096.5 | F86: =+L86 -> 0 | G86: =+D86+E86+F86 -> 1148.9 | H86: =VLOOKUP(C86,'IP PITS'!$B$9:$D$90,3,0) -> 0 | I86: =VLOOKUP(C86,[1]RESUMEN!$C$31:$L$127,10,0) -> 5000 | J86: =(((+I86/30)*H86)*30%) -> 0 | K86: =VLOOKUP(C86,[1]IP!$B$9:$I$116,8,0) -> 0 | L86: =+J86-K86 -> 0 | M86: PITSS
A87: SEI0026 | B87: SEITON - (CONSULTORIA II) | C87: Patricio Aguilar Jhonattan Cristian | D87: 1588.2 | E87: 375 | F87: =+L87 -> 0 | G87: =+D87+E87+F87 -> 1963.2 | H87: =VLOOKUP(C87,'CPD PITS'!$B$9:$D$27,3,0) -> 0 | I87: =VLOOKUP(C87,[1]RESUMEN!$C$4:$L$113,10,) -> 9000 | J87: =(((+I87/30)*H87)*30%) -> 0 | K87: =VLOOKUP(C87,[1]CPD!$B$9:$I$35,8,0) -> 0 | L87: =+J87-K87 -> 0 | M87: PITSS
A88: SEI0522 | B88: SEITON (IP INNOVA II) | C88: Peña Lopez Abigail | D88: 215.8 | F88: =+L88 -> 0 | G88: =+D88+E88+F88 -> 215.8 | H88: =VLOOKUP(C88,'IP PITS'!$B$9:$D$90,3,0) -> 0 | I88: =VLOOKUP(C88,[1]RESUMEN!$C$31:$L$127,10,0) -> 6900 | J88: =(((+I88/30)*H88)*30%) -> 0 | K88: =VLOOKUP(C88,[1]IP!$B$9:$I$116,8,0) -> 0 | L88: =+J88-K88 -> 0 | M88: PITSS
A89: SEI0505 | B89: SEITON (IP INNOVA II) | C89: Perez Balboa Cesar | D89: 2194.19 | E89: 84 | F89: =+L89 -> 0 | G89: =+D89+E89+F89 -> 2278.19 | H89: =VLOOKUP(C89,'IP PITS'!$B$9:$D$90,3,0) -> 0 | I89: =VLOOKUP(C89,[1]RESUMEN!$C$31:$L$127,10,0) -> 10000 | J89: =(((+I89/30)*H89)*30%) -> 0 | K89: =VLOOKUP(C89,[1]IP!$B$9:$I$116,8,0) -> 0 | L89: =+J89-K89 -> 0 | M89: PITSS
A90: SEI0455 | B90: SEITON (IP INNOVA II) | C90: Perez Garcia Andres Alvaro | D90: 416.4 | E90: =600+140 -> 740 | F90: =+L90 -> 0 | G90: =+D90+E90+F90 -> 1156.4 | H90: =VLOOKUP(C90,'IP PITS'!$B$9:$D$90,3,0) -> 0 | I90: =VLOOKUP(C90,[1]RESUMEN!$C$31:$L$127,10,0) -> 8000 | J90: =(((+I90/30)*H90)*30%) -> 0 | K90: =VLOOKUP(C90,[1]IP!$B$9:$I$116,8,0) -> 0 | L90: =+J90-K90 -> 0 | M90: PITSS
A91: SEI0023 | B91: SEITON (IP INNOVA II) | C91: Puente Murguia Luis Felipe | D91: 222.6 | E91: 253.25 | F91: =+L91 -> 0 | G91: =+D91+E91+F91 -> 475.85 | H91: =VLOOKUP(C91,'IP PITS'!$B$9:$D$90,3,0) -> 0 | I91: =VLOOKUP(C91,[1]RESUMEN!$C$31:$L$127,10,0) -> 7000 | J91: =(((+I91/30)*H91)*30%) -> 0 | K91: =VLOOKUP(C91,[1]IP!$B$9:$I$116,8,0) -> 0 | L91: =+J91-K91 -> 0 | M91: PITSS
A92: SEI0542 | B92: SEITON (IP INNOVA II) | C92: Ramirez Elizalde Karen Viridiana | D92: 134.2 | F92: =+L92 -> 0 | G92: =+D92+E92+F92 -> 134.2 | H92: =VLOOKUP(C92,'IP PITS'!$B$9:$D$90,3,0) -> 0 | I92: 6000 | J92: =(((+I92/30)*H92)*30%) -> 0 | K92: =VLOOKUP(C92,[1]IP!$B$9:$I$116,8,0) -> 0 | L92: =+J92-K92 -> 0 | M92: PITSS
A93: SEI0221 | B93: SEITON - (CONSULTORIA II) | C93: Rogel Teran Marco Antonio | D93: 12613.2 | F93: =+L93 -> 0 | G93: =+D93+E93+F93 -> 12613.2 | H93: =VLOOKUP(C93,'CPD PITS'!$B$9:$D$27,3,0) -> 0 | I93: =VLOOKUP(C93,[1]RESUMEN!$C$4:$L$113,10,) -> 60000 | J93: =(((+I93/30)*H93)*30%) -> 0 | K93: =VLOOKUP(C93,[1]CPD!$B$9:$I$35,8,0) -> 0 | L93: =+J93-K93 -> 0 | M93: PITSS
A94: SEI0521 | B94: SEITON (IP INNOVA II) | C94: Rondero Savin Jacinto | D94: 221.2 | F94: =+L94 -> 0 | G94: =+D94+E94+F94 -> 221.2 | H94: =VLOOKUP(C94,'IP PITS'!$B$9:$D$90,3,0) -> 0 | I94: =VLOOKUP(C94,[1]RESUMEN!$C$31:$L$127,10,0) -> 7000 | J94: =(((+I94/30)*H94)*30%) -> 0 | K94: =VLOOKUP(C94,[1]IP!$B$9:$I$116,8,0) -> 0 | L94: =+J94-K94 -> 0 | M94: PITSS
A95: SEI0515 | B95: SEITON (IP INNOVA II) | C95: Ruiz Flores Aldo Tomas | D95: 135.27 | E95: 337.5 | F95: =+L95 -> 0 | G95: =+D95+E95+F95 -> 472.77 | H95: =VLOOKUP(C95,'IP PITS'!$B$9:$D$90,3,0) -> 0 | I95: =VLOOKUP(C95,[1]RESUMEN!$C$31:$L$127,10,0) -> 6000 | J95: =(((+I95/30)*H95)*30%) -> 0 | K95: =VLOOKUP(C95,[1]IP!$B$9:$I$116,8,0) -> 0 | L95: =+J95-K95 -> 0 | M95: PITSS
A96: SEI0465 | B96: SEITON (IP INNOVA II) | C96: Sandoval Garcia Luis | D96: 416.4 | E96: 262.5 | F96: =+L96 -> 0 | G96: =+D96+E96+F96 -> 678.9 | H96: =VLOOKUP(C96,'IP PITS'!$B$9:$D$90,3,0) -> 0 | I96: =VLOOKUP(C96,[1]RESUMEN!$C$31:$L$127,10,0) -> 8000 | J96: =(((+I96/30)*H96)*30%) -> 0 | K96: =VLOOKUP(C96,[1]IP!$B$9:$I$116,8,0) -> 0 | L96: =+J96-K96 -> 0 | M96: PITSS
A97: SEI0477 | B97: SEITON (IP INNOVA II) | C97: Sandoval Medina Demetrio | D97: 414.6 | E97: 450 | F97: =+L97 -> 0 | G97: =+D97+E97+F97 -> 864.6 | H97: =VLOOKUP(C97,'IP PITS'!$B$9:$D$90,3,0) -> 0 | I97: =VLOOKUP(C97,[1]RESUMEN!$C$31:$L$127,10,0) -> 8000 | J97: =(((+I97/30)*H97)*30%) -> 0 | K97: =VLOOKUP(C97,[1]IP!$B$9:$I$116,8,0) -> 0 | L97: =+J97-K97 -> 0 | M97: PITSS
A98: SEI0537 | B98: SEITON (IP INNOVA II) | C98: Serrano Esquivel Armando | D98: 1704.58 | E98: 675 | F98: =+L98 -> 0 | G98: =+D98+E98+F98 -> 2379.58 | H98: =VLOOKUP(C98,'IP PITS'!$B$9:$D$90,3,0) -> 0 | I98: 7000 | J98: =(((+I98/30)*H98)*30%) -> 0 | K98: =VLOOKUP(C98,[1]IP!$B$9:$I$116,8,0) -> 0 | L98: =+J98-K98 -> 0 | M98: PITSS
A99: SEI0498 | B99: SEITON (IP INNOVA II) | C99: Tenorio Alvarez Alberto Antonio | D99: 1667.37 | E99: =1000+417 -> 1417 | F99: =+L99 -> 0 | G99: =+D99+E99+F99 -> 3084.37 | H99: =VLOOKUP(C99,'IP PITS'!$B$9:$D$90,3,0) -> 0 | I99: =VLOOKUP(C99,[1]RESUMEN!$C$31:$L$127,10,0) -> 10000 | J99: =(((+I99/30)*H99)*30%) -> 0 | K99: =VLOOKUP(C99,[1]IP!$B$9:$I$116,8,0) -> 0 | L99: =+J99-K99 -> 0 | M99: PITSS
A100: SEI0495 | B100: SEITON (IP INNOVA II) | C100: Torres Perez Carlos Alberto | D100: 1917.3 | E100: =3728+1421.88 -> 5149.88 | F100: =+L100 -> 0 | G100: =+D100+E100+F100 -> 7067.18 | H100: =VLOOKUP(C100,'IP PITS'!$B$9:$D$90,3,0) -> 0 | I100: =VLOOKUP(C100,[1]RESUMEN!$C$31:$L$127,10,0) -> 10500 | J100: =(((+I100/30)*H100)*30%) -> 0 | K100: =VLOOKUP(C100,[1]IP!$B$9:$I$116,8,0) -> 0 | L100: =+J100-K100 -> 0 | M100: PITSS
A101: SEI0010 | B101: SEITON (IP INNOVA II) | C101: Torres Ricardez Alfredo | D101: 414.6 | E101: 258.5 | F101: =+L101 -> 0 | G101: =+D101+E101+F101 -> 673.1 | H101: =VLOOKUP(C101,'IP PITS'!$B$9:$D$90,3,0) -> 0 | I101: =VLOOKUP(C101,[1]RESUMEN!$C$31:$L$127,10,0) -> 8000 | J101: =(((+I101/30)*H101)*30%) -> 0 | K101: =VLOOKUP(C101,[1]IP!$B$9:$I$116,8,0) -> 0 | L101: =+J101-K101 -> 0 | M101: PITSS
A102: SEI0473 | B102: SEITON (IP INNOVA II) | C102: Torres Velazquez Juan Antonio | D102: 416.4 | E102: 546 | F102: =+L102 -> 0 | G102: =+D102+E102+F102 -> 962.4 | H102: =VLOOKUP(C102,'IP PITS'!$B$9:$D$90,3,0) -> 0 | I102: =VLOOKUP(C102,[1]RESUMEN!$C$31:$L$127,10,0) -> 8000 | J102: =(((+I102/30)*H102)*30%) -> 0 | K102: =VLOOKUP(C102,[1]IP!$B$9:$I$116,8,0) -> 0 | L102: =+J102-K102 -> 0 | M102: PITSS
A103: SEI0497 | B103: SEITON (IP INNOVA II) | C103: Treviño Alvarez Jorge Alberto | D103: 2050.17 | E103: 1280 | F103: =+L103 -> 0 | G103: =+D103+E103+F103 -> 3330.17 | H103: =VLOOKUP(C103,'IP PITS'!$B$9:$D$90,3,0) -> 0 | I103: =VLOOKUP(C103,[1]RESUMEN!$C$31:$L$127,10,0) -> 12000 | J103: =(((+I103/30)*H103)*30%) -> 0 | K103: =VLOOKUP(C103,[1]IP!$B$9:$I$116,8,0) -> 0 | L103: =+J103-K103 -> 0 | M103: PITSS
A104: SEI0467 | B104: SEITON (IP INNOVA II) | C104: Vaca Valdez Guillermo | D104: 416.25 | E104: 471 | F104: =+L104 -> 0 | G104: =+D104+E104+F104 -> 887.25 | H104: =VLOOKUP(C104,'IP PITS'!$B$9:$D$90,3,0) -> 0 | I104: =VLOOKUP(C104,[1]RESUMEN!$C$31:$L$127,10,0) -> 8000 | J104: =(((+I104/30)*H104)*30%) -> 0 | K104: =VLOOKUP(C104,[1]IP!$B$9:$I$116,8,0) -> 0 | L104: =+J104-K104 -> 0 | M104: PITSS
...

Sheet RESUMEN
A2: SUELDOS Y SALARIOS | G2: SINDICATO | K2: NETOS | O2: EXTRAS
A3: CLAVE | B3: EMPRESA | C3: NOMBRE | D3: NETO CPD | E3: NETO IP | F3: A | G3: PAGO SINDICATO | H3: COMISION | I3: PRIMA VACACIONAL SINDICATO | J3: B | K3: NETO A PAGAR | L3: NETO MENSUAL | M3: NETO QUINCENAL SEITON | N3: C | O3: prima vacacional | P3: COMISION Y PRIMA VACACIONAL | Q3: INFONAVIT | R3: INFONAVIT | S3: INFONAVIT | T3: INFONAVIT | U3: PRESTAMO | V3: APORTACION | W3: DESCUENTOS | X3: D | Y3: TOTAL GENERAL | Z3: DIFERENCIAS | AA3: OBSERVACIONES | AB3: CC
A4: SEI0009 | B4: SEITON - (CONSULTORIA II) | C4: Gutierrez Gutierrez Luis Arturo | D4: =VLOOKUP(C4,[2]CPD!$B$9:$Y$35,24,0) -> 2774.6 | G4: =VLOOKUP(C4,#REF!,4,0) -> #REF! | H4: =VLOOKUP(C4,#REF!,5,0) -> #REF! | I4: =VLOOKUP(C4,#REF!,6,0) -> #REF! | K4: =+D4+E4+G4+H4+I4 -> #REF! | L4: =VLOOKUP(C4,[1]ABC!$A$3:$B$88,2,0) -> 8500 | M4: =+L4/2 -> 4250 | O4: =VLOOKUP(C4,[2]CPD!$B$9:$I$35,8,0) -> 0 | P4: =+H4+I4 -> #REF! | Q4: =VLOOKUP(C4,[2]CPD!$B$9:$R$35,17,0) -> 0 | R4: =VLOOKUP(C4,[2]CPD!$B$9:$Q$35,16,0) -> 0 | S4: =VLOOKUP(C4,[1]CPD!$B$9:$S$35,18,0) -> 0 | T4: =VLOOKUP(C4,[2]CPD!$B$9:$T$35,19,0) -> 0 | W4: =VLOOKUP(C4,[2]CPD!$B$9:$V$35,21,0) -> 0 | Y4: =+K4-O4-P4+Q4+R4+S4+T4+U4+V4+W4 -> #REF! | Z4: =+M4-Y4 -> #REF! | AB4: =VLOOKUP(C4,[1]SINDICATO!$C$7:$Q$141,15,0) -> #N/A
A5: SEI0010 | B5: SEITON - (CONSULTORIA II) | C5: Compean Tobias Braulio Gerardo | D5: =VLOOKUP(C5,[2]CPD!$B$9:$Y$35,24,0) -> 4005.2 | G5: =VLOOKUP(C5,#REF!,4,0) -> #REF! | H5: =VLOOKUP(C5,#REF!,5,0) -> #REF! | I5: =VLOOKUP(C5,#REF!,6,0) -> #REF! | K5: =+D5+E5+G5+H5+I5 -> #REF! | L5: =VLOOKUP(C5,[1]ABC!$A$3:$B$88,2,0) -> 18000 | M5: =+L5/2 -> 9000 | O5: =VLOOKUP(C5,[2]CPD!$B$9:$I$35,8,0) -> 0 | P5: =+H5+I5 -> #REF! | Q5: =VLOOKUP(C5,[2]CPD!$B$9:$R$35,17,0) -> 1333.87 | R5: =VLOOKUP(C5,[2]CPD!$B$9:$Q$35,16,0) -> 0 | S5: =VLOOKUP(C5,[1]CPD!$B$9:$S$35,18,0) -> 0 | T5: =VLOOKUP(C5,[2]CPD!$B$9:$T$35,19,0) -> 15 | W5: =VLOOKUP(C5,[2]CPD!$B$9:$V$35,21,0) -> 0 | Y5: =+K5-O5-P5+Q5+R5+S5+T5+U5+V5+W5 -> #REF! | Z5: =+M5-Y5 -> #REF! | AB5: =VLOOKUP(C5,[1]SINDICATO!$C$7:$Q$141,15,0) -> 0
A6: SEI0026 | B6: SEITON - (CONSULTORIA II) | C6: Patricio Aguilar Jhonattan Cristian | D6: =VLOOKUP(C6,[2]CPD!$B$9:$Y$35,24,0) -> 2911.8 | G6: =VLOOKUP(C6,#REF!,4,0) -> #REF! | H6: =VLOOKUP(C6,#REF!,5,0) -> #REF! | I6: =VLOOKUP(C6,#REF!,6,0) -> #REF! | K6: =+D6+E6+G6+H6+I6 -> #REF! | L6: =VLOOKUP(C6,[1]ABC!$A$3:$B$88,2,0) -> 9000 | M6: =+L6/2 -> 4500 | O6: =VLOOKUP(C6,[2]CPD!$B$9:$I$35,8,0) -> 0 | P6: =+H6+I6 -> #REF! | Q6: =VLOOKUP(C6,[2]CPD!$B$9:$R$35,17,0) -> 0 | R6: =VLOOKUP(C6,[2]CPD!$B$9:$Q$35,16,0) -> 0 | S6: =VLOOKUP(C6,[1]CPD!$B$9:$S$35,18,0) -> 0 | T6: =VLOOKUP(C6,[2]CPD!$B$9:$T$35,19,0) -> 0 | W6: =VLOOKUP(C6,[2]CPD!$B$9:$V$35,21,0) -> 0 | Y6: =+K6-O6-P6+Q6+R6+S6+T6+U6+V6+W6 -> #REF! | Z6: =+M6-Y6 -> #REF! | AB6: =VLOOKUP(C6,[1]SINDICATO!$C$7:$Q$141,15,0) -> #N/A
A7: SEI0040 | B7: SEITON - (CONSULTORIA II) | C7: Mora Ramirez Acal Aldo Isidro | D7: =VLOOKUP(C7,[2]CPD!$B$9:$Y$35,24,0) -> 4036 | G7: =VLOOKUP(C7,#REF!,4,0) -> #REF! | H7: =VLOOKUP(C7,#REF!,5,0) -> #REF! | I7: =VLOOKUP(C7,#REF!,6,0) -> #REF! | K7: =+D7+E7+G7+H7+I7 -> #REF! | L7: 13000 | M7: =+L7/2 -> 6500 | O7: =VLOOKUP(C7,[2]CPD!$B$9:$I$35,8,0) -> 0 | P7: =+H7+I7 -> #REF! | Q7: =VLOOKUP(C7,[2]CPD!$B$9:$R$35,17,0) -> 0 | R7: =VLOOKUP(C7,[2]CPD!$B$9:$Q$35,16,0) -> 0 | S7: =VLOOKUP(C7,[1]CPD!$B$9:$S$35,18,0) -> 0 | T7: =VLOOKUP(C7,[2]CPD!$B$9:$T$35,19,0) -> 0 | W7: =VLOOKUP(C7,[2]CPD!$B$9:$V$35,21,0) -> 0 | Y7: =+K7-O7-P7+Q7+R7+S7+T7+U7+V7+W7 -> #REF! | Z7: =+M7-Y7 -> #REF! | AB7: =VLOOKUP(C7,[1]SINDICATO!$C$7:$Q$141,15,0) -> #N/A
A8: SEI0041 | B8: SEITON - (CONSULTORIA II) | C8: Vazquez Perez Miguel Angel | D8: =VLOOKUP(C8,[2]CPD!$B$9:$Y$35,24,0) -> 5074 | G8: =VLOOKUP(C8,#REF!,4,0) -> #REF! | H8: =VLOOKUP(C8,#REF!,5,0) -> #REF! | I8: =VLOOKUP(C8,#REF!,6,0) -> #REF! | K8: =+D8+E8+G8+H8+I8 -> #REF! | L8: =VLOOKUP(C8,[1]ABC!$A$3:$B$88,2,0) -> 18500 | M8: =+L8/2 -> 9250 | O8: =VLOOKUP(C8,[2]CPD!$B$9:$I$35,8,0) -> 0 | P8: =+H8+I8 -> #REF! | Q8: =VLOOKUP(C8,[2]CPD!$B$9:$R$35,17,0) -> 0 | R8: =VLOOKUP(C8,[2]CPD!$B$9:$Q$35,16,0) -> 0 | S8: =VLOOKUP(C8,[1]CPD!$B$9:$S$35,18,0) -> 0 | T8: =VLOOKUP(C8,[2]CPD!$B$9:$T$35,19,0) -> 0 | W8: =VLOOKUP(C8,[2]CPD!$B$9:$V$35,21,0) -> 0 | Y8: =+K8-O8-P8+Q8+R8+S8+T8+U8+V8+W8 -> #REF! | Z8: =+M8-Y8 -> #REF! | AB8: =VLOOKUP(C8,[1]SINDICATO!$C$7:$Q$141,15,0) -> #N/A
A9: SEI0088 | B9: SEITON - (CONSULTORIA II) | C9: Morgado Fernandez Martin | D9: =VLOOKUP(C9,[2]CPD!$B$9:$Y$35,24,0) -> 4899.6 | G9: =VLOOKUP(C9,#REF!,4,0) -> #REF! | H9: =VLOOKUP(C9,#REF!,5,0) -> #REF! | I9: =VLOOKUP(C9,#REF!,6,0) -> #REF! | K9: =+D9+E9+G9+H9+I9 -> #REF! | L9: =VLOOKUP(C9,[1]ABC!$A$3:$B$88,2,0) -> 15000 | M9: =+L9/2 -> 7500 | O9: =VLOOKUP(C9,[2]CPD!$B$9:$I$35,8,0) -> 0 | P9: =+H9+I9 -> #REF! | Q9: =VLOOKUP(C9,[2]CPD!$B$9:$R$35,17,0) -> 0 | R9: =VLOOKUP(C9,[2]CPD!$B$9:$Q$35,16,0) -> 0 | S9: =VLOOKUP(C9,[1]CPD!$B$9:$S$35,18,0) -> 0 | T9: =VLOOKUP(C9,[2]CPD!$B$9:$T$35,19,0) -> 0 | W9: =VLOOKUP(C9,[2]CPD!$B$9:$V$35,21,0) -> 0 | Y9: =+K9-O9-P9+Q9+R9+S9+T9+U9+V9+W9 -> #REF! | Z9: =+M9-Y9 -> #REF! | AB9: =VLOOKUP(C9,[1]SINDICATO!$C$7:$Q$141,15,0) -> #N/A
A10: SEI0097 | B10: SEITON - (CONSULTORIA II) | C10: Arreola Jimenez Jose Nieves | D10: =VLOOKUP(C10,[2]CPD!$B$9:$Y$35,24,0) -> 1927.6 | G10: =VLOOKUP(C10,#REF!,4,0) -> #REF! | H10: =VLOOKUP(C10,#REF!,5,0) -> #REF! | I10: =VLOOKUP(C10,#REF!,6,0) -> #REF! | K10: =+D10+E10+G10+H10+I10 -> #REF! | L10: =VLOOKUP(C10,[1]ABC!$A$3:$B$88,2,0) -> 10150 | M10: =+L10/2 -> 5075 | O10: =VLOOKUP(C10,[2]CPD!$B$9:$I$35,8,0) -> 0 | P10: =+H10+I10 -> #REF! | Q10: =VLOOKUP(C10,[2]CPD!$B$9:$R$35,17,0) -> 1574.29 | R10: =VLOOKUP(C10,[2]CPD!$B$9:$Q$35,16,0) -> 0 | S10: =VLOOKUP(C10,[1]CPD!$B$9:$S$35,18,0) -> 0 | T10: =VLOOKUP(C10,[2]CPD!$B$9:$T$35,19,0) -> 15 | W10: =VLOOKUP(C10,[2]CPD!$B$9:$V$35,21,0) -> 0 | Y10: =+K10-O10-P10+Q10+R10+S10+T10+U10+V10+W10 -> #REF! | Z10: =+M10-Y10 -> #REF! | AB10: =VLOOKUP(C10,[1]SINDICATO!$C$7:$Q$141,15,0) -> #N/A
A11: SEI0099 | B11: SEITON - (CONSULTORIA II) | C11: Garcia Villicaña Ricardo Pascual | D11: =VLOOKUP(C11,[2]CPD!$B$9:$Y$35,24,0) -> 4899.8 | G11: =VLOOKUP(C11,#REF!,4,0) -> #REF! | H11: =VLOOKUP(C11,#REF!,5,0) -> #REF! | I11: =VLOOKUP(C11,#REF!,6,0) -> #REF! | K11: =+D11+E11+G11+H11+I11 -> #REF! | L11: =VLOOKUP(C11,[1]ABC!$A$3:$B$88,2,0) -> 15000 | M11: =+L11/2 -> 7500 | O11: =VLOOKUP(C11,[2]CPD!$B$9:$I$35,8,0) -> 0 | P11: =+H11+I11 -> #REF! | Q11: =VLOOKUP(C11,[2]CPD!$B$9:$R$35,17,0) -> 0 | R11: =VLOOKUP(C11,[2]CPD!$B$9:$Q$35,16,0) -> 0 | S11: =VLOOKUP(C11,[1]CPD!$B$9:$S$35,18,0) -> 0 | T11: =VLOOKUP(C11,[2]CPD!$B$9:$T$35,19,0) -> 0 | W11: =VLOOKUP(C11,[2]CPD!$B$9:$V$35,21,0) -> 0 | Y11: =+K11-O11-P11+Q11+R11+S11+T11+U11+V11+W11 -> #REF! | Z11: =+M11-Y11 -> #REF! | AB11: =VLOOKUP(C11,[1]SINDICATO!$C$7:$Q$141,15,0) -> #N/A
A12: SEI0108 | B12: SEITON - (CONSULTORIA II) | C12: Caballero Diaz Francisco Javier | D12: =VLOOKUP(C12,[2]CPD!$B$9:$Y$35,24,0) -> 1675.4 | G12: =VLOOKUP(C12,#REF!,4,0) -> #REF! | H12: =VLOOKUP(C12,#REF!,5,0) -> #REF! | I12: =VLOOKUP(C12,#REF!,6,0) -> #REF! | K12: =+D12+E12+G12+H12+I12 -> #REF! | L12: =VLOOKUP(C12,[1]ABC!$A$3:$B$88,2,0) -> 10150 | M12: =+L12/2 -> 5075 | O12: =VLOOKUP(C12,[2]CPD!$B$9:$I$35,8,0) -> 0 | P12: =+H12+I12 -> #REF! | Q12: =VLOOKUP(C12,[2]CPD!$B$9:$R$35,17,0) -> 1826.51 | R12: =VLOOKUP(C12,[2]CPD!$B$9:$Q$35,16,0) -> 0 | S12: =VLOOKUP(C12,[1]CPD!$B$9:$S$35,18,0) -> 0 | T12: =VLOOKUP(C12,[2]CPD!$B$9:$T$35,19,0) -> 15 | W12: =VLOOKUP(C12,[2]CPD!$B$9:$V$35,21,0) -> 0 | Y12: =+K12-O12-P12+Q12+R12+S12+T12+U12+V12+W12 -> #REF! | Z12: =+M12-Y12 -> #REF! | AB12: =VLOOKUP(C12,[1]SINDICATO!$C$7:$Q$141,15,0) -> #N/A
A13: SEI0116 | B13: SEITON - (CONSULTORIA II) | C13: Casillas Cardona Cesar Alejandro | D13: =VLOOKUP(C13,[2]CPD!$B$9:$Y$35,24,0) -> 3336.6 | G13: =VLOOKUP(C13,#REF!,4,0) -> #REF! | H13: =VLOOKUP(C13,#REF!,5,0) -> #REF! | I13: =VLOOKUP(C13,#REF!,6,0) -> #REF! | K13: =+D13+E13+G13+H13+I13 -> #REF! | L13: =VLOOKUP(C13,[1]ABC!$A$3:$B$88,2,0) -> 12000 | M13: =+L13/2 -> 6000 | O13: =VLOOKUP(C13,[2]CPD!$B$9:$I$35,8,0) -> 0 | P13: =+H13+I13 -> #REF! | Q13: =VLOOKUP(C13,[2]CPD!$B$9:$R$35,17,0) -> 757.32 | R13: =VLOOKUP(C13,[2]CPD!$B$9:$Q$35,16,0) -> 0 | S13: =VLOOKUP(C13,[1]CPD!$B$9:$S$35,18,0) -> 0 | T13: =VLOOKUP(C13,[2]CPD!$B$9:$T$35,19,0) -> 15 | W13: =VLOOKUP(C13,[2]CPD!$B$9:$V$35,21,0) -> 0 | Y13: =+K13-O13-P13+Q13+R13+S13+T13+U13+V13+W13 -> #REF! | Z13: =+M13-Y13 -> #REF! | AB13: =VLOOKUP(C13,[1]SINDICATO!$C$7:$Q$141,15,0) -> #N/A
A14: SEI0117 | B14: SEITON - (CONSULTORIA II) | C14: Mariscal Romero Luis Adrian | D14: =VLOOKUP(C14,[2]CPD!$B$9:$Y$35,24,0) -> 3060 | G14: =VLOOKUP(C14,#REF!,4,0) -> #REF! | H14: =VLOOKUP(C14,#REF!,5,0) -> #REF! | I14: =VLOOKUP(C14,#REF!,6,0) -> #REF! | K14: =+D14+E14+G14+H14+I14 -> #REF! | L14: 15000 | M14: =+L14/2 -> 7500 | O14: =VLOOKUP(C14,[2]CPD!$B$9:$I$35,8,0) -> 0 | P14: =+H14+I14 -> #REF! | Q14: =VLOOKUP(C14,[2]CPD!$B$9:$R$35,17,0) -> 1674 | R14: =VLOOKUP(C14,[2]CPD!$B$9:$Q$35,16,0) -> 0 | S14: =VLOOKUP(C14,[1]CPD!$B$9:$S$35,18,0) -> 0 | T14: =VLOOKUP(C14,[2]CPD!$B$9:$T$35,19,0) -> 15 | W14: =VLOOKUP(C14,[2]CPD!$B$9:$V$35,21,0) -> 0 | Y14: =+K14-O14-P14+Q14+R14+S14+T14+U14+V14+W14 -> #REF! | Z14: =+M14-Y14 -> #REF! | AB14: =VLOOKUP(C14,[1]SINDICATO!$C$7:$Q$141,15,0) -> #N/A
A15: SEI0118 | B15: SEITON - (CONSULTORIA II) | C15: Arroyo Ramirez Hector Hugo | D15: =VLOOKUP(C15,[2]CPD!$B$9:$Y$35,24,0) -> 2967.4 | G15: =VLOOKUP(C15,#REF!,4,0) -> #REF! | H15: =VLOOKUP(C15,#REF!,5,0) -> #REF! | I15: =VLOOKUP(C15,#REF!,6,0) -> #REF! | K15: =+D15+E15+G15+H15+I15 -> #REF! | L15: =VLOOKUP(C15,[1]ABC!$A$3:$B$88,2,0) -> 13000 | M15: =+L15/2 -> 6500 | O15: =VLOOKUP(C15,[2]CPD!$B$9:$I$35,8,0) -> 285.99 | P15: =+H15+I15 -> #REF! | Q15: =VLOOKUP(C15,[2]CPD!$B$9:$R$35,17,0) -> 1432.4 | R15: =VLOOKUP(C15,[2]CPD!$B$9:$Q$35,16,0) -> 0 | S15: =VLOOKUP(C15,[1]CPD!$B$9:$S$35,18,0) -> 0 | T15: =VLOOKUP(C15,[2]CPD!$B$9:$T$35,19,0) -> 15 | W15: =VLOOKUP(C15,[2]CPD!$B$9:$V$35,21,0) -> 268.35 | Y15: =+K15-O15-P15+Q15+R15+S15+T15+U15+V15+W15 -> #REF! | Z15: =+M15-Y15 -> #REF! | AB15: =VLOOKUP(C15,[1]SINDICATO!$C$7:$Q$141,15,0) -> #N/A
A16: SEI0119 | B16: SEITON - (CONSULTORIA II) | C16: Dominguez Lopez Maria De Jesus | D16: =VLOOKUP(C16,[2]CPD!$B$9:$Y$35,24,0) -> 4635.4 | G16: =VLOOKUP(C16,#REF!,4,0) -> #REF! | H16: =VLOOKUP(C16,#REF!,5,0) -> #REF! | I16: =VLOOKUP(C16,#REF!,6,0) -> #REF! | J16: 0 | K16: =+D16+E16+G16+H16+I16 -> #REF! | L16: 13000 | M16: =+L16/2 -> 6500 | O16: =VLOOKUP(C16,[2]CPD!$B$9:$I$35,8,0) -> 786.49 | P16: =+H16+I16 -> #REF! | Q16: =VLOOKUP(C16,[2]CPD!$B$9:$R$35,17,0) -> 0 | R16: =VLOOKUP(C16,[2]CPD!$B$9:$Q$35,16,0) -> 533.16 | S16: =VLOOKUP(C16,[1]CPD!$B$9:$S$35,18,0) -> 0 | T16: =VLOOKUP(C16,[2]CPD!$B$9:$T$35,19,0) -> 15 | W16: =VLOOKUP(C16,[2]CPD!$B$9:$V$35,21,0) -> 0 | X16: 0 | Y16: =+K16-O16-P16+Q16+R16+S16+T16+U16+V16+W16 -> #REF! | Z16: =+M16-Y16 -> #REF! | AB16: =VLOOKUP(C16,[1]SINDICATO!$C$7:$Q$141,15,0) -> 0
A17: SEI0127 | B17: SEITON - (CONSULTORIA II) | C17: Hernandez Ochoa Eduardo | D17: =VLOOKUP(C17,[2]CPD!$B$9:$Y$35,24,0) -> 4899.8 | G17: =VLOOKUP(C17,#REF!,4,0) -> #REF! | H17: =VLOOKUP(C17,#REF!,5,0) -> #REF! | I17: =VLOOKUP(C17,#REF!,6,0) -> #REF! | K17: =+D17+E17+G17+H17+I17 -> #REF! | L17: =VLOOKUP(C17,[1]ABC!$A$3:$B$88,2,0) -> 15000 | M17: =+L17/2 -> 7500 | O17: =VLOOKUP(C17,[2]CPD!$B$9:$I$35,8,0) -> 0 | P17: =+H17+I17 -> #REF! | Q17: =VLOOKUP(C17,[2]CPD!$B$9:$R$35,17,0) -> 0 | R17: =VLOOKUP(C17,[2]CPD!$B$9:$Q$35,16,0) -> 0 | S17: =VLOOKUP(C17,[1]CPD!$B$9:$S$35,18,0) -> 0 | T17: =VLOOKUP(C17,[2]CPD!$B$9:$T$35,19,0) -> 0 | W17: =VLOOKUP(C17,[2]CPD!$B$9:$V$35,21,0) -> 0 | Y17: =+K17-O17-P17+Q17+R17+S17+T17+U17+V17+W17 -> #REF! | Z17: =+M17-Y17 -> #REF! | AB17: =VLOOKUP(C17,[1]SINDICATO!$C$7:$Q$141,15,0) -> #N/A
A18: SEI0147 | B18: SEITON - (CONSULTORIA II) | C18: Diaz Munguia Martha Liliana | D18: =VLOOKUP(C18,[2]CPD!$B$9:$Y$35,24,0) -> 5056.2 | G18: =VLOOKUP(C18,#REF!,4,0) -> #REF! | H18: =VLOOKUP(C18,#REF!,5,0) -> #REF! | I18: =VLOOKUP(C18,#REF!,6,0) -> #REF! | K18: =+D18+E18+G18+H18+I18 -> #REF! | L18: 25000 | M18: =+L18/2 -> 12500 | O18: =VLOOKUP(C18,[2]CPD!$B$9:$I$35,8,0) -> 0 | P18: =+H18+I18 -> #REF! | Q18: =VLOOKUP(C18,[2]CPD!$B$9:$R$35,17,0) -> 419.76 | R18: =VLOOKUP(C18,[2]CPD!$B$9:$Q$35,16,0) -> 0 | S18: =VLOOKUP(C18,[1]CPD!$B$9:$S$35,18,0) -> 0 | T18: =VLOOKUP(C18,[2]CPD!$B$9:$T$35,19,0) -> 15 | W18: =VLOOKUP(C18,[2]CPD!$B$9:$V$35,21,0) -> 0 | Y18: =+K18-O18-P18+Q18+R18+S18+T18+U18+V18+W18 -> #REF! | Z18: =+M18-Y18 -> #REF! | AB18: =VLOOKUP(C18,[1]SINDICATO!$C$7:$Q$141,15,0) -> 0
A19: SEI0173 | B19: SEITON - (CONSULTORIA II) | C19: Nieto Ortiz Jose Luis | D19: =VLOOKUP(C19,[2]CPD!$B$9:$Y$35,24,0) -> 1332.2 | G19: =VLOOKUP(C19,#REF!,4,0) -> #REF! | H19: =VLOOKUP(C19,#REF!,5,0) -> #REF! | I19: =VLOOKUP(C19,#REF!,6,0) -> #REF! | K19: =+D19+E19+G19+H19+I19 -> #REF! | L19: =VLOOKUP(C19,[1]ABC!$A$3:$B$88,2,0) -> 10000 | M19: =+L19/2 -> 5000 | O19: =VLOOKUP(C19,[2]CPD!$B$9:$I$35,8,0) -> 0 | P19: =+H19+I19 -> #REF! | Q19: =VLOOKUP(C19,[2]CPD!$B$9:$R$35,17,0) -> 2169.67 | R19: =VLOOKUP(C19,[2]CPD!$B$9:$Q$35,16,0) -> 0 | S19: =VLOOKUP(C19,[1]CPD!$B$9:$S$35,18,0) -> 0 | T19: =VLOOKUP(C19,[2]CPD!$B$9:$T$35,19,0) -> 15 | W19: =VLOOKUP(C19,[2]CPD!$B$9:$V$35,21,0) -> 0 | Y19: =+K19-O19-P19+Q19+R19+S19+T19+U19+V19+W19 -> #REF! | Z19: =+M19-Y19 -> #REF! | AB19: =VLOOKUP(C19,[1]SINDICATO!$C$7:$Q$141,15,0) -> #N/A
A20: SEI0221 | B20: SEITON - (CONSULTORIA II) | C20: Rogel Teran Marco Antonio | D20: =VLOOKUP(C20,[2]CPD!$B$9:$Y$35,24,0) -> 16969.2 | G20: =VLOOKUP(C20,#REF!,4,0) -> #REF! | H20: =VLOOKUP(C20,#REF!,5,0) -> #REF! | I20: =VLOOKUP(C20,#REF!,6,0) -> #REF! | K20: =+D20+E20+G20+H20+I20 -> #REF! | L20: 60000 | M20: =+L20/2 -> 30000 | O20: =VLOOKUP(C20,[2]CPD!$B$9:$I$35,8,0) -> 0 | P20: =+H20+I20 -> #REF! | Q20: =VLOOKUP(C20,[2]CPD!$B$9:$R$35,17,0) -> 0 | R20: =VLOOKUP(C20,[2]CPD!$B$9:$Q$35,16,0) -> 0 | S20: =VLOOKUP(C20,[1]CPD!$B$9:$S$35,18,0) -> 0 | T20: =VLOOKUP(C20,[2]CPD!$B$9:$T$35,19,0) -> 0 | W20: =VLOOKUP(C20,[2]CPD!$B$9:$V$35,21,0) -> 417.6 | Y20: =+K20-O20-P20+Q20+R20+S20+T20+U20+V20+W20 -> #REF! | Z20: =+M20-Y20 -> #REF! | AB20: =VLOOKUP(C20,[1]SINDICATO!$C$7:$Q$141,15,0) -> #N/A
A21: SEI0222 | B21: SEITON - (CONSULTORIA II) | C21: Saucedo Duran Jesus Alfredo | D21: =VLOOKUP(C21,[2]CPD!$B$9:$Y$35,24,0) -> 4241.4 | G21: =VLOOKUP(C21,#REF!,4,0) -> #REF! | H21: =VLOOKUP(C21,#REF!,5,0) -> #REF! | I21: =VLOOKUP(C21,#REF!,6,0) -> #REF! | K21: =+D21+E21+G21+H21+I21 -> #REF! | L21: 12000 | M21: =+L21/2 -> 6000 | O21: =VLOOKUP(C21,[2]CPD!$B$9:$I$35,8,0) -> 132.5 | P21: =+H21+I21 -> #REF! | Q21: =VLOOKUP(C21,[2]CPD!$B$9:$R$35,17,0) -> 0 | R21: =VLOOKUP(C21,[2]CPD!$B$9:$Q$35,16,0) -> 0 | S21: =VLOOKUP(C21,[1]CPD!$B$9:$S$35,18,0) -> 0 | T21: =VLOOKUP(C21,[2]CPD!$B$9:$T$35,19,0) -> 0 | W21: =VLOOKUP(C21,[2]CPD!$B$9:$V$35,21,0) -> 0 | Y21: =+K21-O21-P21+Q21+R21+S21+T21+U21+V21+W21 -> #REF! | Z21: =+M21-Y21 -> #REF! | AB21: =VLOOKUP(C21,[1]SINDICATO!$C$7:$Q$141,15,0) -> 0
A22: SEI032 | B22: SEITON - (CONSULTORIA II) | C22: Camarena Quiroz Erick Frank | D22: =VLOOKUP(C22,[2]CPD!$B$9:$Y$35,24,0) -> 2911.8 | G22: =VLOOKUP(C22,#REF!,4,0) -> #REF! | H22: =VLOOKUP(C22,#REF!,5,0) -> #REF! | I22: =VLOOKUP(C22,#REF!,6,0) -> #REF! | K22: =+D22+E22+G22+H22+I22 -> #REF! | L22: =VLOOKUP(C22,[1]ABC!$A$3:$B$88,2,0) -> 9000 | M22: =+L22/2 -> 4500 | O22: =VLOOKUP(C22,[2]CPD!$B$9:$I$35,8,0) -> 0 | P22: =+H22+I22 -> #REF! | Q22: =VLOOKUP(C22,[2]CPD!$B$9:$R$35,17,0) -> 0 | R22: =VLOOKUP(C22,[2]CPD!$B$9:$Q$35,16,0) -> 0 | S22: =VLOOKUP(C22,[1]CPD!$B$9:$S$35,18,0) -> 0 | T22: =VLOOKUP(C22,[2]CPD!$B$9:$T$35,19,0) -> 0 | W22: =VLOOKUP(C22,[2]CPD!$B$9:$V$35,21,0) -> 0 | Y22: =+K22-O22-P22+Q22+R22+S22+T22+U22+V22+W22 -> #REF! | Z22: =+M22-Y22 -> #REF! | AB22: =VLOOKUP(C22,[1]SINDICATO!$C$7:$Q$141,15,0) -> 0
A23: SEI0401 | B23: SEITON - (CONSULTORIA II) | C23: De La Torre Zambara Francisco Ernesto | D23: =VLOOKUP(C23,[2]CPD!$B$9:$Y$35,24,0) -> 3203.8 | G23: =VLOOKUP(C23,#REF!,4,0) -> #REF! | H23: =VLOOKUP(C23,#REF!,5,0) -> #REF! | I23: =VLOOKUP(C23,#REF!,6,0) -> #REF! | K23: =+D23+E23+G23+H23+I23 -> #REF! | L23: =VLOOKUP(C23,[1]ABC!$A$3:$B$88,2,0) -> 10150 | M23: =+L23/2 -> 5075 | O23: =VLOOKUP(C23,[2]CPD!$B$9:$I$35,8,0) -> 0 | P23: =+H23+I23 -> #REF! | Q23: =VLOOKUP(C23,[2]CPD!$B$9:$R$35,17,0) -> 0 | R23: =VLOOKUP(C23,[2]CPD!$B$9:$Q$35,16,0) -> 0 | S23: =VLOOKUP(C23,[1]CPD!$B$9:$S$35,18,0) -> 0 | T23: =VLOOKUP(C23,[2]CPD!$B$9:$T$35,19,0) -> 0 | W23: =VLOOKUP(C23,[2]CPD!$B$9:$V$35,21,0) -> 313.2 | Y23: =+K23-O23-P23+Q23+R23+S23+T23+U23+V23+W23 -> #REF! | Z23: =+M23-Y23 -> #REF! | AB23: =VLOOKUP(C23,[1]SINDICATO!$C$7:$Q$141,15,0) -> #N/A
A24: SEI0425 | B24: SEITON - (CONSULTORIA II) | C24: Carbajal Cabuto Jose Luis | D24: =VLOOKUP(C24,[2]CPD!$B$9:$Y$35,24,0) -> 1995.4 | G24: =VLOOKUP(C24,#REF!,4,0) -> #REF! | H24: =VLOOKUP(C24,#REF!,5,0) -> #REF! | I24: =VLOOKUP(C24,#REF!,6,0) -> #REF! | K24: =+D24+E24+G24+H24+I24 -> #REF! | L24: =VLOOKUP(C24,[1]ABC!$A$3:$B$88,2,0) -> 10250 | M24: =+L24/2 -> 5125 | O24: =VLOOKUP(C24,[2]CPD!$B$9:$I$35,8,0) -> 0 | P24: =+H24+I24 -> #REF! | Q24: =VLOOKUP(C24,[2]CPD!$B$9:$R$35,17,0) -> 1506.5 | R24: =VLOOKUP(C24,[2]CPD!$B$9:$Q$35,16,0) -> 0 | S24: =VLOOKUP(C24,[1]CPD!$B$9:$S$35,18,0) -> 0 | T24: =VLOOKUP(C24,[2]CPD!$B$9:$T$35,19,0) -> 15 | W24: =VLOOKUP(C24,[2]CPD!$B$9:$V$35,21,0) -> 0 | Y24: =+K24-O24-P24+Q24+R24+S24+T24+U24+V24+W24 -> #REF! | Z24: =+M24-Y24 -> #REF! | AB24: =VLOOKUP(C24,[1]SINDICATO!$C$7:$Q$141,15,0) -> #N/A
A25: SEI0435 | B25: SEITON - (CONSULTORIA II) | C25: Benavides Herrera Alejandra | D25: =VLOOKUP(C25,[2]CPD!$B$9:$Y$35,24,0) -> 3196.8 | G25: =VLOOKUP(C25,#REF!,4,0) -> #REF! | H25: =VLOOKUP(C25,#REF!,5,0) -> #REF! | I25: =VLOOKUP(C25,#REF!,6,0) -> #REF! | K25: =+D25+E25+G25+H25+I25 -> #REF! | L25: 40000 | M25: =+L25/2 -> 20000 | O25: =VLOOKUP(C25,[2]CPD!$B$9:$I$35,8,0) -> 0 | P25: =+H25+I25 -> #REF! | Q25: =VLOOKUP(C25,[2]CPD!$B$9:$R$35,17,0) -> 0 | R25: =VLOOKUP(C25,[2]CPD!$B$9:$Q$35,16,0) -> 0 | S25: =VLOOKUP(C25,[1]CPD!$B$9:$S$35,18,0) -> 0 | T25: =VLOOKUP(C25,[2]CPD!$B$9:$T$35,19,0) -> 0 | W25: =VLOOKUP(C25,[2]CPD!$B$9:$V$35,21,0) -> 0 | Y25: =+K25-O25-P25+Q25+R25+S25+T25+U25+V25+W25 -> #REF! | Z25: =+M25-Y25 -> #REF! | AB25: =VLOOKUP(C25,[1]SINDICATO!$C$7:$Q$141,15,0) -> #N/A
A26: SEI0437 | B26: SEITON - (CONSULTORIA II) | C26: Leal Montaño Diego | D26: =VLOOKUP(C26,[2]CPD!$B$9:$Y$35,24,0) -> 2782.8 | G26: =VLOOKUP(C26,#REF!,4,0) -> #REF! | H26: =VLOOKUP(C26,#REF!,5,0) -> #REF! | I26: =VLOOKUP(C26,#REF!,6,0) -> #REF! | K26: =+D26+E26+G26+H26+I26 -> #REF! | L26: 10000 | M26: =+L26/2 -> 5000 | O26: =VLOOKUP(C26,[2]CPD!$B$9:$I$35,8,0) -> 0 | P26: =+H26+I26 -> #REF! | Q26: =VLOOKUP(C26,[2]CPD!$B$9:$R$35,17,0) -> 398.98 | R26: =VLOOKUP(C26,[2]CPD!$B$9:$Q$35,16,0) -> 0 | S26: =VLOOKUP(C26,[1]CPD!$B$9:$S$35,18,0) -> 0 | T26: =VLOOKUP(C26,[2]CPD!$B$9:$T$35,19,0) -> 15 | W26: =VLOOKUP(C26,[2]CPD!$B$9:$V$35,21,0) -> 0 | Y26: =+K26-O26-P26+Q26+R26+S26+T26+U26+V26+W26 -> #REF! | Z26: =+M26-Y26 -> #REF! | AB26: =VLOOKUP(C26,[1]SINDICATO!$C$7:$Q$141,15,0) -> 0
A27: SEI0440 | B27: SEITON - (CONSULTORIA II) | C27: Leija Arevalo Guadalupe | D27: =VLOOKUP(C27,[2]CPD!$B$9:$Y$35,24,0) -> 1003 | G27: =VLOOKUP(C27,#REF!,4,0) -> #REF! | H27: =VLOOKUP(C27,#REF!,5,0) -> #REF! | I27: =VLOOKUP(C27,#REF!,6,0) -> #REF! | K27: =+D27+E27+G27+H27+I27 -> #REF! | L27: 4000 | M27: =+L27/2 -> 2000 | O27: =VLOOKUP(C27,[2]CPD!$B$9:$I$35,8,0) -> 0 | P27: =+H27+I27 -> #REF! | Q27: =VLOOKUP(C27,[2]CPD!$B$9:$R$35,17,0) -> 1005.81 | R27: =VLOOKUP(C27,[2]CPD!$B$9:$Q$35,16,0) -> 0 | S27: =VLOOKUP(C27,[1]CPD!$B$9:$S$35,18,0) -> 0 | T27: =VLOOKUP(C27,[2]CPD!$B$9:$T$35,19,0) -> 15 | W27: =VLOOKUP(C27,[2]CPD!$B$9:$V$35,21,0) -> 0 | Y27: =+K27-O27-P27+Q27+R27+S27+T27+U27+V27+W27 -> #REF! | Z27: =+M27-Y27 -> #REF! | AA27: subsidio | AB27: =VLOOKUP(C27,[1]SINDICATO!$C$7:$Q$141,15,0) -> 0
A28: SEI0442 | B28: SEITON - (CONSULTORIA II) | C28: Sierra Escamilla Daniela | D28: =VLOOKUP(C28,[2]CPD!$B$9:$Y$35,24,0) -> 4036 | G28: =VLOOKUP(C28,#REF!,4,0) -> #REF! | H28: =VLOOKUP(C28,#REF!,5,0) -> #REF! | I28: =VLOOKUP(C28,#REF!,6,0) -> #REF! | K28: =+D28+E28+G28+H28+I28 -> #REF! | L28: 13000 | M28: =+L28/2 -> 6500 | O28: =VLOOKUP(C28,[2]CPD!$B$9:$I$35,8,0) -> 0 | P28: =+H28+I28 -> #REF! | Q28: =VLOOKUP(C28,[2]CPD!$B$9:$R$35,17,0) -> 0 | R28: =VLOOKUP(C28,[2]CPD!$B$9:$Q$35,16,0) -> 0 | S28: =VLOOKUP(C28,[1]CPD!$B$9:$S$35,18,0) -> 0 | T28: =VLOOKUP(C28,[2]CPD!$B$9:$T$35,19,0) -> 0 | W28: =VLOOKUP(C28,[2]CPD!$B$9:$V$35,21,0) -> 0 | Y28: =+K28-O28-P28+Q28+R28+S28+T28+U28+V28+W28 -> #REF! | Z28: =+M28-Y28 -> #REF! | AB28: =VLOOKUP(C28,[1]SINDICATO!$C$7:$Q$141,15,0) -> #N/A
A29: SEI0445 | B29: SEITON - (CONSULTORIA II) | C29: Muñoz Melgoza Gabriel | D29: =VLOOKUP(C29,[2]CPD!$B$9:$Y$35,24,0) -> 4609.4 | G29: =VLOOKUP(C29,#REF!,4,0) -> #REF! | H29: =VLOOKUP(C29,#REF!,5,0) -> #REF! | I29: =VLOOKUP(C29,#REF!,6,0) -> #REF! | K29: =+D29+E29+G29+H29+I29 -> #REF! | L29: 15400 | M29: =+L29/2 -> 7700 | O29: =VLOOKUP(C29,[2]CPD!$B$9:$I$35,8,0) -> 0 | P29: =+H29+I29 -> #REF! | Q29: =VLOOKUP(C29,[2]CPD!$B$9:$R$35,17,0) -> 0 | R29: =VLOOKUP(C29,[2]CPD!$B$9:$Q$35,16,0) -> 0 | S29: =VLOOKUP(C29,[1]CPD!$B$9:$S$35,18,0) -> 0 | T29: =VLOOKUP(C29,[2]CPD!$B$9:$T$35,19,0) -> 0 | W29: =VLOOKUP(C29,[2]CPD!$B$9:$V$35,21,0) -> 0 | Y29: =+K29-O29-P29+Q29+R29+S29+T29+U29+V29+W29 -> #REF! | Z29: =+M29-Y29 -> #REF! | AB29: =VLOOKUP(C29,[1]SINDICATO!$C$7:$Q$141,15,0) -> #N/A
A30: SEI0448 | B30: SEITON - (CONSULTORIA II) | C30: Rodriguez Chavez Oswaldo Emmanuel | D30: =VLOOKUP(C30,[2]CPD!$B$9:$Y$35,24,0) -> 4327.4 | G30: =VLOOKUP(C30,#REF!,4,0) -> #REF! | H30: =VLOOKUP(C30,#REF!,5,0) -> #REF! | I30: =VLOOKUP(C30,#REF!,6,0) -> #REF! | K30: =+D30+E30+G30+H30+I30 -> #REF! | L30: 14000 | M30: =+L30/2 -> 7000 | O30: =VLOOKUP(C30,[2]CPD!$B$9:$I$35,8,0) -> 0 | P30: =+H30+I30 -> #REF! | Q30: =VLOOKUP(C30,[2]CPD!$B$9:$R$35,17,0) -> 0 | R30: =VLOOKUP(C30,[2]CPD!$B$9:$Q$35,16,0) -> 0 | S30: =VLOOKUP(C30,[1]CPD!$B$9:$S$35,18,0) -> 0 | T30: =VLOOKUP(C30,[2]CPD!$B$9:$T$35,19,0) -> 0 | W30: =VLOOKUP(C30,[2]CPD!$B$9:$V$35,21,0) -> 0 | Y30: =+K30-O30-P30+Q30+R30+S30+T30+U30+V30+W30 -> #REF! | Z30: =+M30-Y30 -> #REF! | AB30: =VLOOKUP(C30,[1]SINDICATO!$C$7:$Q$141,15,0) -> 0
A31: SEI0010 | B31: SEITON (IP INNOVA II) | C31: Torres Ricardez Alfredo | E31: =VLOOKUP(C31,[2]IP!$B$9:$V$116,21,0) -> 3585.4 | G31: =VLOOKUP(C31,#REF!,4,0) -> #REF! | H31: =VLOOKUP(C31,#REF!,5,0) -> #REF! | I31: =VLOOKUP(C31,#REF!,6,0) -> #REF! | K31: =+D31+E31+G31+H31+I31 -> #REF! | L31: =VLOOKUP(C31,[1]ABC!$A$3:$B$88,2,0) -> 8000 | M31: =+L31/2 -> 4000 | O31: =VLOOKUP(C31,[2]IP!$B$9:$I$116,8,0) -> 0 | P31: =+H31+I31 -> #REF! | Q31: =VLOOKUP(C31,[2]IP!$B$9:$N$116,13,0) -> 0 | R31: =VLOOKUP(C31,[2]IP!$B$9:$O$116,14,0) -> 0 | T31: =VLOOKUP(C31,[2]IP!$B$9:$P$116,15,0) -> 0 | U31: =VLOOKUP(C31,[2]IP!$B$9:$Q$116,16,0) -> 0 | V31: =VLOOKUP(C31,[2]IP!$B$9:$S$116,18,0) -> 0 | W31: =VLOOKUP(C31,[2]IP!$B$9:$R$116,17,0) -> 0 | Y31: =+K31-O31-P31+Q31+R31+S31+T31+U31+V31+W31 -> #REF! | Z31: =+M31-Y31 -> #REF! | AB31: =VLOOKUP(C31,[1]SINDICATO!$C$7:$Q$141,15,0) -> #N/A
A32: SEI0014 | B32: SEITON (IP INNOVA II) | C32: Montoya Portillo Carlos Alberto | E32: =VLOOKUP(C32,[2]IP!$B$9:$V$116,21,0) -> 3585.2 | G32: =VLOOKUP(C32,#REF!,4,0) -> #REF! | H32: =VLOOKUP(C32,#REF!,5,0) -> #REF! | I32: =VLOOKUP(C32,#REF!,6,0) -> #REF! | K32: =+D32+E32+G32+H32+I32 -> #REF! | L32: 8000 | M32: =+L32/2 -> 4000 | O32: =VLOOKUP(C32,[2]IP!$B$9:$I$116,8,0) -> 0 | P32: =+H32+I32 -> #REF! | Q32: =VLOOKUP(C32,[2]IP!$B$9:$N$116,13,0) -> 0 | R32: =VLOOKUP(C32,[2]IP!$B$9:$O$116,14,0) -> 0 | T32: =VLOOKUP(C32,[2]IP!$B$9:$P$116,15,0) -> 0 | U32: =VLOOKUP(C32,[2]IP!$B$9:$Q$116,16,0) -> 0 | V32: =VLOOKUP(C32,[2]IP!$B$9:$S$116,18,0) -> 0 | W32: =VLOOKUP(C32,[2]IP!$B$9:$R$116,17,0) -> 0 | Y32: =+K32-O32-P32+Q32+R32+S32+T32+U32+V32+W32 -> #REF! | Z32: =+M32-Y32 -> #REF! | AB32: =VLOOKUP(C32,[1]SINDICATO!$C$7:$Q$141,15,0) -> #N/A
A33: SEI0016 | B33: SEITON (IP INNOVA II) | C33: Negrete Bejar Aide Sarai | E33: =VLOOKUP(C33,[2]IP!$B$9:$V$116,21,0) -> 1278 | G33: =VLOOKUP(C33,#REF!,4,0) -> #REF! | H33: =VLOOKUP(C33,#REF!,5,0) -> #REF! | I33: =VLOOKUP(C33,#REF!,6,0) -> #REF! | K33: =+D33+E33+G33+H33+I33 -> #REF! | L33: =VLOOKUP(C33,[1]ABC!$A$3:$B$88,2,0) -> 4620 | M33: =+L33/2 -> 2310 | O33: =VLOOKUP(C33,[2]IP!$B$9:$I$116,8,0) -> 0 | P33: =+H33+I33 -> #REF! | Q33: =VLOOKUP(C33,[2]IP!$B$9:$N$116,13,0) -> 999.51 | R33: =VLOOKUP(C33,[2]IP!$B$9:$O$116,14,0) -> 0 | T33: =VLOOKUP(C33,[2]IP!$B$9:$P$116,15,0) -> 15 | U33: =VLOOKUP(C33,[2]IP!$B$9:$Q$116,16,0) -> 0 | V33: =VLOOKUP(C33,[2]IP!$B$9:$S$116,18,0) -> 0 | W33: =VLOOKUP(C33,[2]IP!$B$9:$R$116,17,0) -> 0 | Y33: =+K33-O33-P33+Q33+R33+S33+T33+U33+V33+W33 -> #REF! | Z33: =+M33-Y33 -> #REF! | AB33: =VLOOKUP(C33,[1]SINDICATO!$C$7:$Q$141,15,0) -> 0
A34: SEI0017 | B34: SEITON (IP INNOVA II) | C34: Muñoz Reyes Luis Eduardo | E34: =VLOOKUP(C34,[2]IP!$B$9:$V$116,21,0) -> 2692.8 | G34: =VLOOKUP(C34,#REF!,4,0) -> #REF! | H34: =VLOOKUP(C34,#REF!,5,0) -> #REF! | I34: =VLOOKUP(C34,#REF!,6,0) -> #REF! | K34: =+D34+E34+G34+H34+I34 -> #REF! | L34: =VLOOKUP(C34,[1]ABC!$A$3:$B$88,2,0) -> 8000 | M34: =+L34/2 -> 4000 | O34: =VLOOKUP(C34,[2]IP!$B$9:$I$116,8,0) -> 0 | P34: =+H34+I34 -> #REF! | Q34: =VLOOKUP(C34,[2]IP!$B$9:$N$116,13,0) -> 877.59 | R34: =VLOOKUP(C34,[2]IP!$B$9:$O$116,14,0) -> 0 | T34: =VLOOKUP(C34,[2]IP!$B$9:$P$116,15,0) -> 15 | U34: =VLOOKUP(C34,[2]IP!$B$9:$Q$116,16,0) -> 0 | V34: =VLOOKUP(C34,[2]IP!$B$9:$S$116,18,0) -> 0 | W34: =VLOOKUP(C34,[2]IP!$B$9:$R$116,17,0) -> 0 | Y34: =+K34-O34-P34+Q34+R34+S34+T34+U34+V34+W34 -> #REF! | Z34: =+M34-Y34 -> #REF! | AB34: =VLOOKUP(C34,[1]SINDICATO!$C$7:$Q$141,15,0) -> #N/A
A35: SEI0019 | B35: SEITON (IP INNOVA II) | C35: Gonzalez Rasgado Miguel Isaias | E35: =VLOOKUP(C35,[2]IP!$B$9:$V$116,21,0) -> 5195.2 | G35: =VLOOKUP(C35,#REF!,4,0) -> #REF! | H35: =VLOOKUP(C35,#REF!,5,0) -> #REF! | I35: =VLOOKUP(C35,#REF!,6,0) -> #REF! | K35: =+D35+E35+G35+H35+I35 -> #REF! | L35: =VLOOKUP(C35,[1]ABC!$A$3:$B$88,2,0) -> 12000 | M35: =+L35/2 -> 6000 | O35: =VLOOKUP(C35,[2]IP!$B$9:$I$116,8,0) -> 0 | P35: =+H35+I35 -> #REF! | Q35: =VLOOKUP(C35,[2]IP!$B$9:$N$116,13,0) -> 0 | R35: =VLOOKUP(C35,[2]IP!$B$9:$O$116,14,0) -> 0 | T35: =VLOOKUP(C35,[2]IP!$B$9:$P$116,15,0) -> 0 | U35: =VLOOKUP(C35,[2]IP!$B$9:$Q$116,16,0) -> 0 | V35: =VLOOKUP(C35,[2]IP!$B$9:$S$116,18,0) -> 0 | W35: =VLOOKUP(C35,[2]IP!$B$9:$R$116,17,0) -> 0 | Y35: =+K35-O35-P35+Q35+R35+S35+T35+U35+V35+W35 -> #REF! | Z35: =+M35-Y35 -> #REF! | AB35: =VLOOKUP(C35,[1]SINDICATO!$C$7:$Q$141,15,0) -> #N/A
A36: SEI0020 | B36: SEITON (IP INNOVA II) | C36: Mar Marquez Cesar Eduardo | E36: =VLOOKUP(C36,[2]IP!$B$9:$V$116,21,0) -> 3585.4 | G36: =VLOOKUP(C36,#REF!,4,0) -> #REF! | H36: =VLOOKUP(C36,#REF!,5,0) -> #REF! | I36: =VLOOKUP(C36,#REF!,6,0) -> #REF! | K36: =+D36+E36+G36+H36+I36 -> #REF! | L36: 8000 | M36: =+L36/2 -> 4000 | O36: =VLOOKUP(C36,[2]IP!$B$9:$I$116,8,0) -> 0 | P36: =+H36+I36 -> #REF! | Q36: =VLOOKUP(C36,[2]IP!$B$9:$N$116,13,0) -> 0 | R36: =VLOOKUP(C36,[2]IP!$B$9:$O$116,14,0) -> 0 | T36: =VLOOKUP(C36,[2]IP!$B$9:$P$116,15,0) -> 0 | U36: =VLOOKUP(C36,[2]IP!$B$9:$Q$116,16,0) -> 0 | V36: =VLOOKUP(C36,[2]IP!$B$9:$S$116,18,0) -> 0 | W36: =VLOOKUP(C36,[2]IP!$B$9:$R$116,17,0) -> 0 | Y36: =+K36-O36-P36+Q36+R36+S36+T36+U36+V36+W36 -> #REF! | Z36: =+M36-Y36 -> #REF! | AB36: =VLOOKUP(C36,[1]SINDICATO!$C$7:$Q$141,15,0) -> #N/A
A37: SEI0021 | B37: SEITON (IP INNOVA II) | C37: Velez Rodriguez Jaime | E37: =VLOOKUP(C37,[2]IP!$B$9:$V$116,21,0) -> 1490.6 | G37: =VLOOKUP(C37,#REF!,4,0) -> #REF! | H37: =VLOOKUP(C37,#REF!,5,0) -> #REF! | I37: =VLOOKUP(C37,#REF!,6,0) -> #REF! | K37: =+D37+E37+G37+H37+I37 -> #REF! | L37: 8000 | M37: =+L37/2 -> 4000 | O37: =VLOOKUP(C37,[2]IP!$B$9:$I$116,8,0) -> 0 | P37: =+H37+I37 -> #REF! | Q37: =VLOOKUP(C37,[2]IP!$B$9:$N$116,13,0) -> 1359.23 | R37: =VLOOKUP(C37,[2]IP!$B$9:$O$116,14,0) -> 0 | T37: =VLOOKUP(C37,[2]IP!$B$9:$P$116,15,0) -> 15 | U37: =VLOOKUP(C37,[2]IP!$B$9:$Q$116,16,0) -> 0 | V37: =VLOOKUP(C37,[2]IP!$B$9:$S$116,18,0) -> 0 | W37: =VLOOKUP(C37,[2]IP!$B$9:$R$116,17,0) -> 0 | Y37: =+K37-O37-P37+Q37+R37+S37+T37+U37+V37+W37 -> #REF! | Z37: =+M37-Y37 -> #REF! | AB37: =VLOOKUP(C37,[1]SINDICATO!$C$7:$Q$141,15,0) -> #N/A
A38: SEI0022 | B38: SEITON (IP INNOVA II) | C38: Najera Lopez Raul | E38: =VLOOKUP(C38,[2]IP!$B$9:$V$116,21,0) -> 4406.4 | G38: =VLOOKUP(C38,#REF!,4,0) -> #REF! | H38: =VLOOKUP(C38,#REF!,5,0) -> #REF! | I38: =VLOOKUP(C38,#REF!,6,0) -> #REF! | K38: =+D38+E38+G38+H38+I38 -> #REF! | L38: =VLOOKUP(C38,[1]ABC!$A$3:$B$88,2,0) -> 10000 | M38: =+L38/2 -> 5000 | O38: =VLOOKUP(C38,[2]IP!$B$9:$I$116,8,0) -> 0 | P38: =+H38+I38 -> #REF! | Q38: =VLOOKUP(C38,[2]IP!$B$9:$N$116,13,0) -> 0 | R38: =VLOOKUP(C38,[2]IP!$B$9:$O$116,14,0) -> 0 | T38: =VLOOKUP(C38,[2]IP!$B$9:$P$116,15,0) -> 0 | U38: =VLOOKUP(C38,[2]IP!$B$9:$Q$116,16,0) -> 0 | V38: =VLOOKUP(C38,[2]IP!$B$9:$S$116,18,0) -> 0 | W38: =VLOOKUP(C38,[2]IP!$B$9:$R$116,17,0) -> 0 | Y38: =+K38-O38-P38+Q38+R38+S38+T38+U38+V38+W38 -> #REF! | Z38: =+M38-Y38 -> #REF! | AB38: =VLOOKUP(C38,[1]SINDICATO!$C$7:$Q$141,15,0) -> #N/A
A39: SEI0023 | B39: SEITON (IP INNOVA II) | C39: Puente Murguia Luis Felipe | E39: =VLOOKUP(C39,[2]IP!$B$9:$V$116,21,0) -> 3277.4 | G39: =VLOOKUP(C39,#REF!,4,0) -> #REF! | H39: =VLOOKUP(C39,#REF!,5,0) -> #REF! | I39: =VLOOKUP(C39,#REF!,6,0) -> #REF! | K39: =+D39+E39+G39+H39+I39 -> #REF! | L39: =VLOOKUP(C39,[1]ABC!$A$3:$B$88,2,0) -> 7000 | M39: =+L39/2 -> 3500 | O39: =VLOOKUP(C39,[2]IP!$B$9:$I$116,8,0) -> 0 | P39: =+H39+I39 -> #REF! | Q39: =VLOOKUP(C39,[2]IP!$B$9:$N$116,13,0) -> 0 | R39: =VLOOKUP(C39,[2]IP!$B$9:$O$116,14,0) -> 0 | T39: =VLOOKUP(C39,[2]IP!$B$9:$P$116,15,0) -> 0 | U39: =VLOOKUP(C39,[2]IP!$B$9:$Q$116,16,0) -> 0 | V39: =VLOOKUP(C39,[2]IP!$B$9:$S$116,18,0) -> 0 | W39: =VLOOKUP(C39,[2]IP!$B$9:$R$116,17,0) -> 0 | Y39: =+K39-O39-P39+Q39+R39+S39+T39+U39+V39+W39 -> #REF! | Z39: =+M39-Y39 -> #REF! | AB39: =VLOOKUP(C39,[1]SINDICATO!$C$7:$Q$141,15,0) -> #N/A
A40: SEI0029 | B40: SEITON (IP INNOVA II) | C40: Arceo Garcia Manuel Federico | E40: =VLOOKUP(C40,[2]IP!$B$9:$V$116,21,0) -> 2090.2 | G40: =VLOOKUP(C40,#REF!,4,0) -> #REF! | H40: =VLOOKUP(C40,#REF!,5,0) -> #REF! | I40: =VLOOKUP(C40,#REF!,6,0) -> #REF! | K40: =+D40+E40+G40+H40+I40 -> #REF! | L40: =VLOOKUP(C40,[1]ABC!$A$3:$B$88,2,0) -> 6000 | M40: =+L40/2 -> 3000 | O40: =VLOOKUP(C40,[2]IP!$B$9:$I$116,8,0) -> 0 | P40: =+H40+I40 -> #REF! | Q40: =VLOOKUP(C40,[2]IP!$B$9:$N$116,13,0) -> 0 | R40: =VLOOKUP(C40,[2]IP!$B$9:$O$116,14,0) -> 0 | T40: =VLOOKUP(C40,[2]IP!$B$9:$P$116,15,0) -> 0 | U40: =VLOOKUP(C40,[2]IP!$B$9:$Q$116,16,0) -> 600 | V40: =VLOOKUP(C40,[2]IP!$B$9:$S$116,18,0) -> 0 | W40: =VLOOKUP(C40,[2]IP!$B$9:$R$116,17,0) -> 0 | Y40: =+K40-O40-P40+Q40+R40+S40+T40+U40+V40+W40 -> #REF! | Z40: =+M40-Y40 -> #REF! | AB40: =VLOOKUP(C40,[1]SINDICATO!$C$7:$Q$141,15,0) -> #N/A
A41: SEI0031 | B41: SEITON (IP INNOVA II) | C41: Contreras Zetina Victor Hugo | E41: =VLOOKUP(C41,[2]IP!$B$9:$V$116,21,0) -> 3234.2 | G41: =VLOOKUP(C41,#REF!,4,0) -> #REF! | H41: =VLOOKUP(C41,#REF!,5,0) -> #REF! | I41: =VLOOKUP(C41,#REF!,6,0) -> #REF! | K41: =+D41+E41+G41+H41+I41 -> #REF! | L41: =VLOOKUP(C41,[1]ABC!$A$3:$B$88,2,0) -> 6900 | M41: =+L41/2 -> 3450 | O41: =VLOOKUP(C41,[2]IP!$B$9:$I$116,8,0) -> 0 | P41: =+H41+I41 -> #REF! | Q41: =VLOOKUP(C41,[2]IP!$B$9:$N$116,13,0) -> 0 | R41: =VLOOKUP(C41,[2]IP!$B$9:$O$116,14,0) -> 0 | T41: =VLOOKUP(C41,[2]IP!$B$9:$P$116,15,0) -> 0 | U41: =VLOOKUP(C41,[2]IP!$B$9:$Q$116,16,0) -> 0 | V41: =VLOOKUP(C41,[2]IP!$B$9:$S$116,18,0) -> 0 | W41: =VLOOKUP(C41,[2]IP!$B$9:$R$116,17,0) -> 0 | Y41: =+K41-O41-P41+Q41+R41+S41+T41+U41+V41+W41 -> #REF! | Z41: =+M41-Y41 -> #REF! | AB41: =VLOOKUP(C41,[1]SINDICATO!$C$7:$Q$141,15,0) -> 0
A42: SEI0037 | B42: SEITON (IP INNOVA II) | C42: Gomez Oliveros Alin | E42: =VLOOKUP(C42,[2]IP!$B$9:$V$116,21,0) -> 2864.8 | G42: =VLOOKUP(C42,#REF!,4,0) -> #REF! | H42: =VLOOKUP(C42,#REF!,5,0) -> #REF! | I42: =VLOOKUP(C42,#REF!,6,0) -> #REF! | K42: =+D42+E42+G42+H42+I42 -> #REF! | L42: 10000 | M42: =+L42/2 -> 5000 | O42: =VLOOKUP(C42,[2]IP!$B$9:$I$116,8,0) -> 0 | P42: =+H42+I42 -> #REF! | Q42: =VLOOKUP(C42,[2]IP!$B$9:$N$116,13,0) -> 0 | R42: =VLOOKUP(C42,[2]IP!$B$9:$O$116,14,0) -> 0 | T42: =VLOOKUP(C42,[2]IP!$B$9:$P$116,15,0) -> 0 | U42: =VLOOKUP(C42,[2]IP!$B$9:$Q$116,16,0) -> 0 | V42: =VLOOKUP(C42,[2]IP!$B$9:$S$116,18,0) -> 0 | W42: =VLOOKUP(C42,[2]IP!$B$9:$R$116,17,0) -> 0 | Y42: =+K42-O42-P42+Q42+R42+S42+T42+U42+V42+W42 -> #REF! | Z42: =+M42-Y42 -> #REF! | AB42: =VLOOKUP(C42,[1]SINDICATO!$C$7:$Q$141,15,0) -> 0
A43: SEI0078 | B43: SEITON (IP INNOVA II) | C43: Aguilar Leal Karina Livier | E43: =VLOOKUP(C43,[2]IP!$B$9:$V$116,21,0) -> 3583.6 | G43: =VLOOKUP(C43,#REF!,4,0) -> #REF! | H43: =VLOOKUP(C43,#REF!,5,0) -> #REF! | I43: =VLOOKUP(C43,#REF!,6,0) -> #REF! | K43: =+D43+E43+G43+H43+I43 -> #REF! | L43: 9000 | M43: =+L43/2 -> 4500 | O43: =VLOOKUP(C43,[2]IP!$B$9:$I$116,8,0) -> 0 | P43: =+H43+I43 -> #REF! | Q43: =VLOOKUP(C43,[2]IP!$B$9:$N$116,13,0) -> 0 | R43: =VLOOKUP(C43,[2]IP!$B$9:$O$116,14,0) -> 0 | T43: =VLOOKUP(C43,[2]IP!$B$9:$P$116,15,0) -> 0 | U43: =VLOOKUP(C43,[2]IP!$B$9:$Q$116,16,0) -> 0 | V43: =VLOOKUP(C43,[2]IP!$B$9:$S$116,18,0) -> 0 | W43: =VLOOKUP(C43,[2]IP!$B$9:$R$116,17,0) -> 0 | Y43: =+K43-O43-P43+Q43+R43+S43+T43+U43+V43+W43 -> #REF! | AB43: =VLOOKUP(C43,[1]SINDICATO!$C$7:$Q$141,15,0) -> 0
A44: SEI0079 | B44: SEITON (IP INNOVA II) | C44: Amezcua Contreras Martha Frine | E44: =VLOOKUP(C44,[2]IP!$B$9:$V$116,21,0) -> 7087.8 | G44: =VLOOKUP(C44,#REF!,4,0) -> #REF! | H44: =VLOOKUP(C44,#REF!,5,0) -> #REF! | I44: =VLOOKUP(C44,#REF!,6,0) -> #REF! | K44: =+D44+E44+G44+H44+I44 -> #REF! | L44: =VLOOKUP(C44,[1]ABC!$A$3:$B$88,2,0) -> 18500 | M44: =+L44/2 -> 9250 | O44: =VLOOKUP(C44,[2]IP!$B$9:$I$116,8,0) -> 0 | P44: =+H44+I44 -> #REF! | Q44: =VLOOKUP(C44,[2]IP!$B$9:$N$116,13,0) -> 0 | R44: =VLOOKUP(C44,[2]IP!$B$9:$O$116,14,0) -> 0 | T44: =VLOOKUP(C44,[2]IP!$B$9:$P$116,15,0) -> 0 | U44: =VLOOKUP(C44,[2]IP!$B$9:$Q$116,16,0) -> 0 | V44: =VLOOKUP(C44,[2]IP!$B$9:$S$116,18,0) -> 0 | W44: =VLOOKUP(C44,[2]IP!$B$9:$R$116,17,0) -> 0 | Y44: =+K44-O44-P44+Q44+R44+S44+T44+U44+V44+W44 -> #REF! | Z44: =+M44-Y44 -> #REF! | AB44: =VLOOKUP(C44,[1]SINDICATO!$C$7:$Q$141,15,0) -> 0
A45: SEI0081 | B45: SEITON (IP INNOVA II) | C45: Guizar Perez Sergio | E45: =VLOOKUP(C45,[2]IP!$B$9:$V$116,21,0) -> 3518.2 | G45: =VLOOKUP(C45,#REF!,4,0) -> #REF! | H45: =VLOOKUP(C45,#REF!,5,0) -> #REF! | I45: =VLOOKUP(C45,#REF!,6,0) -> #REF! | K45: =+D45+E45+G45+H45+I45 -> #REF! | L45: =VLOOKUP(C45,[1]ABC!$A$3:$B$88,2,0) -> 8500 | M45: =+L45/2 -> 4250 | O45: =VLOOKUP(C45,[2]IP!$B$9:$I$116,8,0) -> 150 | P45: =+H45+I45 -> #REF! | Q45: =VLOOKUP(C45,[2]IP!$B$9:$N$116,13,0) -> 0 | R45: =VLOOKUP(C45,[2]IP!$B$9:$O$116,14,0) -> 0 | T45: =VLOOKUP(C45,[2]IP!$B$9:$P$116,15,0) -> 0 | U45: =VLOOKUP(C45,[2]IP!$B$9:$Q$116,16,0) -> 0 | V45: =VLOOKUP(C45,[2]IP!$B$9:$S$116,18,0) -> 0 | W45: =VLOOKUP(C45,[2]IP!$B$9:$R$116,17,0) -> 0 | Y45: =+K45-O45-P45+Q45+R45+S45+T45+U45+V45+W45 -> #REF! | Z45: =+M45-Y45 -> #REF! | AB45: =VLOOKUP(C45,[1]SINDICATO!$C$7:$Q$141,15,0) -> 0
A46: SEI0100 | B46: SEITON (IP INNOVA II) | C46: Quinto Valle Martin | E46: =VLOOKUP(C46,[2]IP!$B$9:$V$116,21,0) -> 3906.4 | G46: =VLOOKUP(C46,#REF!,4,0) -> #REF! | H46: =VLOOKUP(C46,#REF!,5,0) -> #REF! | I46: =VLOOKUP(C46,#REF!,6,0) -> #REF! | K46: =+D46+E46+G46+H46+I46 -> #REF! | L46: =VLOOKUP(C46,[1]ABC!$A$3:$B$88,2,0) -> 10000 | M46: =+L46/2 -> 5000 | O46: =VLOOKUP(C46,[2]IP!$B$9:$I$116,8,0) -> 0 | P46: =+H46+I46 -> #REF! | Q46: =VLOOKUP(C46,[2]IP!$B$9:$N$116,13,0) -> 0 | R46: =VLOOKUP(C46,[2]IP!$B$9:$O$116,14,0) -> 0 | T46: =VLOOKUP(C46,[2]IP!$B$9:$P$116,15,0) -> 0 | U46: =VLOOKUP(C46,[2]IP!$B$9:$Q$116,16,0) -> 0 | V46: =VLOOKUP(C46,[2]IP!$B$9:$S$116,18,0) -> 500 | W46: =VLOOKUP(C46,[2]IP!$B$9:$R$116,17,0) -> 0 | Y46: =+K46-O46-P46+Q46+R46+S46+T46+U46+V46+W46 -> #REF! | Z46: =+M46-Y46 -> #REF! | AB46: =VLOOKUP(C46,[1]SINDICATO!$C$7:$Q$141,15,0) -> 0
A47: SEI0109 | B47: SEITON (IP INNOVA II) | C47: Negrete Renteria Jose Luis | E47: =VLOOKUP(C47,[2]IP!$B$9:$V$116,21,0) -> 2125.2 | G47: =VLOOKUP(C47,#REF!,4,0) -> #REF! | H47: =VLOOKUP(C47,#REF!,5,0) -> #REF! | I47: =VLOOKUP(C47,#REF!,6,0) -> #REF! | K47: =+D47+E47+G47+H47+I47 -> #REF! | L47: =VLOOKUP(C47,[1]ABC!$A$3:$B$88,2,0) -> 9800 | M47: =+L47/2 -> 4900 | O47: =VLOOKUP(C47,[2]IP!$B$9:$I$116,8,0) -> 0 | P47: =+H47+I47 -> #REF! | Q47: =VLOOKUP(C47,[2]IP!$B$9:$N$116,13,0) -> 1637.48 | R47: =VLOOKUP(C47,[2]IP!$B$9:$O$116,14,0) -> 0 | T47: =VLOOKUP(C47,[2]IP!$B$9:$P$116,15,0) -> 15 | U47: =VLOOKUP(C47,[2]IP!$B$9:$Q$116,16,0) -> 0 | V47: =VLOOKUP(C47,[2]IP!$B$9:$S$116,18,0) -> 0 | W47: =VLOOKUP(C47,[2]IP!$B$9:$R$116,17,0) -> 0 | Y47: =+K47-O47-P47+Q47+R47+S47+T47+U47+V47+W47 -> #REF! | Z47: =+M47-Y47 -> #REF! | AB47: =VLOOKUP(C47,[1]SINDICATO!$C$7:$Q$141,15,0) -> 0
A48: SEI0126 | B48: SEITON (IP INNOVA II) | C48: Alonso Flores Beda | E48: =VLOOKUP(C48,[2]IP!$B$9:$V$116,21,0) -> 4810.8 | G48: =VLOOKUP(C48,#REF!,4,0) -> #REF! | H48: =VLOOKUP(C48,#REF!,5,0) -> #REF! | I48: =VLOOKUP(C48,#REF!,6,0) -> #REF! | K48: =+D48+E48+G48+H48+I48 -> #REF! | L48: 9000 | M48: =+L48/2 -> 4500 | O48: =VLOOKUP(C48,[2]IP!$B$9:$I$116,8,0) -> 307.22 | P48: =+H48+I48 -> #REF! | Q48: =VLOOKUP(C48,[2]IP!$B$9:$N$116,13,0) -> 0 | R48: =VLOOKUP(C48,[2]IP!$B$9:$O$116,14,0) -> 0 | T48: =VLOOKUP(C48,[2]IP!$B$9:$P$116,15,0) -> 0 | U48: =VLOOKUP(C48,[2]IP!$B$9:$Q$116,16,0) -> 0 | V48: =VLOOKUP(C48,[2]IP!$B$9:$S$116,18,0) -> 0 | W48: =VLOOKUP(C48,[2]IP!$B$9:$R$116,17,0) -> 0 | Y48: =+K48-O48-P48+Q48+R48+S48+T48+U48+V48+W48 -> #REF! | Z48: =+M48-Y48 -> #REF! | AA48: 100% IMSS | AB48: =VLOOKUP(C48,[1]SINDICATO!$C$7:$Q$141,15,0) -> 0
A49: SEI0133 | B49: SEITON (IP INNOVA II) | C49: Romero Mayoral Lorenzo | E49: =VLOOKUP(C49,[2]IP!$B$9:$V$116,21,0) -> 2480.2 | G49: =VLOOKUP(C49,#REF!,4,0) -> #REF! | H49: =VLOOKUP(C49,#REF!,5,0) -> #REF! | I49: =VLOOKUP(C49,#REF!,6,0) -> #REF! | K49: =+D49+E49+G49+H49+I49 -> #REF! | L49: =VLOOKUP(C49,[1]ABC!$A$3:$B$88,2,0) -> 11500 | M49: =+L49/2 -> 5750 | O49: =VLOOKUP(C49,[2]IP!$B$9:$I$116,8,0) -> 0 | P49: =+H49+I49 -> #REF! | Q49: =VLOOKUP(C49,[2]IP!$B$9:$N$116,13,0) -> 1088.47 | R49: =VLOOKUP(C49,[2]IP!$B$9:$O$116,14,0) -> 0 | T49: =VLOOKUP(C49,[2]IP!$B$9:$P$116,15,0) -> 15 | U49: =VLOOKUP(C49,[2]IP!$B$9:$Q$116,16,0) -> 0 | V49: =VLOOKUP(C49,[2]IP!$B$9:$S$116,18,0) -> 0 | W49: =VLOOKUP(C49,[2]IP!$B$9:$R$116,17,0) -> 0 | Y49: =+K49-O49-P49+Q49+R49+S49+T49+U49+V49+W49 -> #REF! | Z49: =+M49-Y49 -> #REF! | AB49: =VLOOKUP(C49,[1]SINDICATO!$C$7:$Q$141,15,0) -> 0
A50: SEI0146 | B50: SEITON (IP INNOVA II) | C50: Ramirez Vera Maria Del Carmen | E50: =VLOOKUP(C50,[2]IP!$B$9:$V$116,21,0) -> 2929.8 | G50: =VLOOKUP(C50,#REF!,4,0) -> #REF! | H50: =VLOOKUP(C50,#REF!,5,0) -> #REF! | I50: =VLOOKUP(C50,#REF!,6,0) -> #REF! | K50: =+D50+E50+G50+H50+I50 -> #REF! | L50: =VLOOKUP(C50,[1]ABC!$A$3:$B$88,2,0) -> 10000 | M50: =+L50/2 -> 5000 | O50: =VLOOKUP(C50,[2]IP!$B$9:$I$116,8,0) -> 240 | P50: =+H50+I50 -> #REF! | Q50: =VLOOKUP(C50,[2]IP!$B$9:$N$116,13,0) -> 878.84 | R50: =VLOOKUP(C50,[2]IP!$B$9:$O$116,14,0) -> 0 | T50: =VLOOKUP(C50,[2]IP!$B$9:$P$116,15,0) -> 15 | U50: =VLOOKUP(C50,[2]IP!$B$9:$Q$116,16,0) -> 0 | V50: =VLOOKUP(C50,[2]IP!$B$9:$S$116,18,0) -> 0 | W50: =VLOOKUP(C50,[2]IP!$B$9:$R$116,17,0) -> 0 | Y50: =+K50-O50-P50+Q50+R50+S50+T50+U50+V50+W50 -> #REF! | Z50: =+M50-Y50 -> #REF! | AB50: =VLOOKUP(C50,[1]SINDICATO!$C$7:$Q$141,15,0) -> 0
A51: SEI0230 | B51: SEITON (IP INNOVA II) | C51: Bueno Herrera Mariana Guadalupe | E51: =VLOOKUP(C51,[2]IP!$B$9:$V$116,21,0) -> 3583.6 | G51: =VLOOKUP(C51,#REF!,4,0) -> #REF! | H51: =VLOOKUP(C51,#REF!,5,0) -> #REF! | I51: =VLOOKUP(C51,#REF!,6,0) -> #REF! | K51: =+D51+E51+G51+H51+I51 -> #REF! | L51: 12600 | M51: =+L51/2 -> 6300 | O51: =VLOOKUP(C51,[2]IP!$B$9:$I$116,8,0) -> 0 | P51: =+H51+I51 -> #REF! | Q51: =VLOOKUP(C51,[2]IP!$B$9:$N$116,13,0) -> 0 | R51: =VLOOKUP(C51,[2]IP!$B$9:$O$116,14,0) -> 0 | T51: =VLOOKUP(C51,[2]IP!$B$9:$P$116,15,0) -> 0 | U51: =VLOOKUP(C51,[2]IP!$B$9:$Q$116,16,0) -> 0 | V51: =VLOOKUP(C51,[2]IP!$B$9:$S$116,18,0) -> 0 | W51: =VLOOKUP(C51,[2]IP!$B$9:$R$116,17,0) -> 0 | Y51: =+K51-O51-P51+Q51+R51+S51+T51+U51+V51+W51 -> #REF! | Z51: =+M51-Y51 -> #REF! | AB51: =VLOOKUP(C51,[1]SINDICATO!$C$7:$Q$141,15,0) -> 0
A52: SEI0332 | B52: SEITON (IP INNOVA II) | C52: Lara Campos Maximino | E52: =VLOOKUP(C52,[2]IP!$B$9:$V$116,21,0) -> 4753.8 | G52: =VLOOKUP(C52,#REF!,4,0) -> #REF! | H52: =VLOOKUP(C52,#REF!,5,0) -> #REF! | I52: =VLOOKUP(C52,#REF!,6,0) -> #REF! | K52: =+D52+E52+G52+H52+I52 -> #REF! | L52: =VLOOKUP(C52,[1]ABC!$A$3:$B$88,2,0) -> 9500 | M52: =+L52/2 -> 4750 | O52: =VLOOKUP(C52,[2]IP!$B$9:$I$116,8,0) -> 0 | P52: =+H52+I52 -> #REF! | Q52: =VLOOKUP(C52,[2]IP!$B$9:$N$116,13,0) -> 0 | R52: =VLOOKUP(C52,[2]IP!$B$9:$O$116,14,0) -> 0 | T52: =VLOOKUP(C52,[2]IP!$B$9:$P$116,15,0) -> 0 | U52: =VLOOKUP(C52,[2]IP!$B$9:$Q$116,16,0) -> 0 | V52: =VLOOKUP(C52,[2]IP!$B$9:$S$116,18,0) -> 0 | W52: =VLOOKUP(C52,[2]IP!$B$9:$R$116,17,0) -> 0 | Y52: =+K52-O52-P52+Q52+R52+S52+T52+U52+V52+W52 -> #REF! | Z52: =+M52-Y52 -> #REF! | AA52: 100% IMSS | AB52: =VLOOKUP(C52,[1]SINDICATO!$C$7:$Q$141,15,0) -> 0
A53: SEI0345 | B53: SEITON (IP INNOVA II) | C53: Rodriguez Diaz Cesar Salvador | E53: =VLOOKUP(C53,[2]IP!$B$9:$V$116,21,0) -> 3003.4 | G53: =VLOOKUP(C53,#REF!,4,0) -> #REF! | H53: =VLOOKUP(C53,#REF!,5,0) -> #REF! | I53: =VLOOKUP(C53,#REF!,6,0) -> #REF! | K53: =+D53+E53+G53+H53+I53 -> #REF! | L53: 9050 | M53: =+L53/2 -> 4525 | O53: =VLOOKUP(C53,[2]IP!$B$9:$I$116,8,0) -> 0 | P53: =+H53+I53 -> #REF! | Q53: =VLOOKUP(C53,[2]IP!$B$9:$N$116,13,0) -> 565.24 | R53: =VLOOKUP(C53,[2]IP!$B$9:$O$116,14,0) -> 0 | T53: =VLOOKUP(C53,[2]IP!$B$9:$P$116,15,0) -> 15 | U53: =VLOOKUP(C53,[2]IP!$B$9:$Q$116,16,0) -> 0 | V53: =VLOOKUP(C53,[2]IP!$B$9:$S$116,18,0) -> 0 | W53: =VLOOKUP(C53,[2]IP!$B$9:$R$116,17,0) -> 0 | Y53: =+K53-O53-P53+Q53+R53+S53+T53+U53+V53+W53 -> #REF! | Z53: =+M53-Y53 -> #REF! | AB53: =VLOOKUP(C53,[1]SINDICATO!$C$7:$Q$141,15,0) -> 0
A54: SEI0364 | B54: SEITON (IP INNOVA II) | C54: Dominguez Lopez Mayeli Del Pilar | E54: =VLOOKUP(C54,[2]IP!$B$9:$V$116,21,0) -> 1917 | G54: =VLOOKUP(C54,#REF!,4,0) -> #REF! | H54: =VLOOKUP(C54,#REF!,5,0) -> #REF! | I54: =VLOOKUP(C54,#REF!,6,0) -> #REF! | K54: =+D54+E54+G54+H54+I54 -> #REF! | L54: =VLOOKUP(C54,[1]ABC!$A$3:$B$88,2,0) -> 10000 | M54: =+L54/2 -> 5000 | O54: =VLOOKUP(C54,[2]IP!$B$9:$I$116,8,0) -> 0 | P54: =+H54+I54 -> #REF! | Q54: =VLOOKUP(C54,[2]IP!$B$9:$N$116,13,0) -> 0 | R54: =VLOOKUP(C54,[2]IP!$B$9:$O$116,14,0) -> 0 | T54: =VLOOKUP(C54,[2]IP!$B$9:$P$116,15,0) -> 0 | U54: =VLOOKUP(C54,[2]IP!$B$9:$Q$116,16,0) -> 0 | V54: =VLOOKUP(C54,[2]IP!$B$9:$S$116,18,0) -> 0 | W54: =VLOOKUP(C54,[2]IP!$B$9:$R$116,17,0) -> 1666.67 | Y54: =+K54-O54-P54+Q54+R54+S54+T54+U54+V54+W54 -> #REF! | Z54: =+M54-Y54 -> #REF! | AB54: =VLOOKUP(C54,[1]SINDICATO!$C$7:$Q$141,15,0) -> #N/A
A55: SEI0376 | B55: SEITON (IP INNOVA II) | C55: Marquez Alcaraz Martin | E55: =VLOOKUP(C55,[2]IP!$B$9:$V$116,21,0) -> 2351 | G55: =VLOOKUP(C55,#REF!,4,0) -> #REF! | H55: =VLOOKUP(C55,#REF!,5,0) -> #REF! | I55: =VLOOKUP(C55,#REF!,6,0) -> #REF! | K55: =+D55+E55+G55+H55+I55 -> #REF! | L55: 9050 | M55: =+L55/2 -> 4525 | O55: =VLOOKUP(C55,[2]IP!$B$9:$I$116,8,0) -> 0 | P55: =+H55+I55 -> #REF! | Q55: =VLOOKUP(C55,[2]IP!$B$9:$N$116,13,0) -> 0 | R55: =VLOOKUP(C55,[2]IP!$B$9:$O$116,14,0) -> 1217.6 | T55: =VLOOKUP(C55,[2]IP!$B$9:$P$116,15,0) -> 15 | U55: =VLOOKUP(C55,[2]IP!$B$9:$Q$116,16,0) -> 0 | V55: =VLOOKUP(C55,[2]IP!$B$9:$S$116,18,0) -> 0 | W55: =VLOOKUP(C55,[2]IP!$B$9:$R$116,17,0) -> 0 | Y55: =+K55-O55-P55+Q55+R55+S55+T55+U55+V55+W55 -> #REF! | Z55: =+M55-Y55 -> #REF! | AB55: =VLOOKUP(C55,[1]SINDICATO!$C$7:$Q$141,15,0) -> 0
A56: SEI0412 | B56: SEITON (IP INNOVA II) | C56: Rojo Avelar Adrian | E56: =VLOOKUP(C56,[2]IP!$B$9:$V$116,21,0) -> 1773.8 | G56: =VLOOKUP(C56,#REF!,4,0) -> #REF! | H56: =VLOOKUP(C56,#REF!,5,0) -> #REF! | I56: =VLOOKUP(C56,#REF!,6,0) -> #REF! | K56: =+D56+E56+G56+H56+I56 -> #REF! | L56: =VLOOKUP(C56,[1]ABC!$A$3:$B$88,2,0) -> 7500 | M56: =+L56/2 -> 3750 | O56: =VLOOKUP(C56,[2]IP!$B$9:$I$116,8,0) -> 0 | P56: =+H56+I56 -> #REF! | Q56: =VLOOKUP(C56,[2]IP!$B$9:$N$116,13,0) -> 1075.99 | R56: =VLOOKUP(C56,[2]IP!$B$9:$O$116,14,0) -> 0 | T56: =VLOOKUP(C56,[2]IP!$B$9:$P$116,15,0) -> 15 | U56: =VLOOKUP(C56,[2]IP!$B$9:$Q$116,16,0) -> 0 | V56: =VLOOKUP(C56,[2]IP!$B$9:$S$116,18,0) -> 0 | W56: =VLOOKUP(C56,[2]IP!$B$9:$R$116,17,0) -> 0 | Y56: =+K56-O56-P56+Q56+R56+S56+T56+U56+V56+W56 -> #REF! | Z56: =+M56-Y56 -> #REF! | AB56: =VLOOKUP(C56,[1]SINDICATO!$C$7:$Q$141,15,0) -> 0
A57: SEI0413 | B57: SEITON (IP INNOVA II) | C57: Courtenay Gutierrez Barry Vladimir | E57: =VLOOKUP(C57,[2]IP!$B$9:$V$116,21,0) -> 2447.6 | G57: =VLOOKUP(C57,#REF!,4,0) -> #REF! | H57: =VLOOKUP(C57,#REF!,5,0) -> #REF! | I57: =VLOOKUP(C57,#REF!,6,0) -> #REF! | K57: =+D57+E57+G57+H57+I57 -> #REF! | L57: 5000 | M57: =+L57/2 -> 2500 | O57: =VLOOKUP(C57,[2]IP!$B$9:$I$116,8,0) -> 0 | P57: =+H57+I57 -> #REF! | Q57: =VLOOKUP(C57,[2]IP!$B$9:$N$116,13,0) -> 0 | R57: =VLOOKUP(C57,[2]IP!$B$9:$O$116,14,0) -> 0 | T57: =VLOOKUP(C57,[2]IP!$B$9:$P$116,15,0) -> 0 | U57: =VLOOKUP(C57,[2]IP!$B$9:$Q$116,16,0) -> 0 | V57: =VLOOKUP(C57,[2]IP!$B$9:$S$116,18,0) -> 0 | W57: =VLOOKUP(C57,[2]IP!$B$9:$R$116,17,0) -> 0 | Y57: =+K57-O57-P57+Q57+R57+S57+T57+U57+V57+W57 -> #REF! | Z57: =+M57-Y57 -> #REF! | AB57: =VLOOKUP(C57,[1]SINDICATO!$C$7:$Q$141,15,0) -> #N/A
A58: SEI0421 | B58: SEITON (IP INNOVA II) | C58: Marin Avila Hector | E58: =VLOOKUP(C58,[2]IP!$B$9:$V$116,21,0) -> 3693.2 | G58: =VLOOKUP(C58,#REF!,4,0) -> #REF! | H58: =VLOOKUP(C58,#REF!,5,0) -> #REF! | I58: =VLOOKUP(C58,#REF!,6,0) -> #REF! | K58: =+D58+E58+G58+H58+I58 -> #REF! | L58: 8800 | M58: =+L58/2 -> 4400 | O58: =VLOOKUP(C58,[2]IP!$B$9:$I$116,8,0) -> 0 | P58: =+H58+I58 -> #REF! | Q58: =VLOOKUP(C58,[2]IP!$B$9:$N$116,13,0) -> 0 | R58: =VLOOKUP(C58,[2]IP!$B$9:$O$116,14,0) -> 0 | T58: =VLOOKUP(C58,[2]IP!$B$9:$P$116,15,0) -> 0 | U58: =VLOOKUP(C58,[2]IP!$B$9:$Q$116,16,0) -> 0 | V58: =VLOOKUP(C58,[2]IP!$B$9:$S$116,18,0) -> 0 | W58: =VLOOKUP(C58,[2]IP!$B$9:$R$116,17,0) -> 0 | Y58: =+K58-O58-P58+Q58+R58+S58+T58+U58+V58+W58 -> #REF! | Z58: =+M58-Y58 -> #REF! | AB58: =VLOOKUP(C58,[1]SINDICATO!$C$7:$Q$141,15,0) -> 0
A59: SEI0424 | B59: SEITON (IP INNOVA II) | C59: Palacios Ramos Jesus | E59: =VLOOKUP(C59,[2]IP!$B$9:$V$116,21,0) -> 3583.6 | G59: =VLOOKUP(C59,#REF!,4,0) -> #REF! | H59: =VLOOKUP(C59,#REF!,5,0) -> #REF! | I59: =VLOOKUP(C59,#REF!,6,0) -> #REF! | K59: =+D59+E59+G59+H59+I59 -> #REF! | L59: 8000 | M59: =+L59/2 -> 4000 | O59: =VLOOKUP(C59,[2]IP!$B$9:$I$116,8,0) -> 0 | P59: =+H59+I59 -> #REF! | Q59: =VLOOKUP(C59,[2]IP!$B$9:$N$116,13,0) -> 0 | R59: =VLOOKUP(C59,[2]IP!$B$9:$O$116,14,0) -> 0 | T59: =VLOOKUP(C59,[2]IP!$B$9:$P$116,15,0) -> 0 | U59: =VLOOKUP(C59,[2]IP!$B$9:$Q$116,16,0) -> 0 | V59: =VLOOKUP(C59,[2]IP!$B$9:$S$116,18,0) -> 0 | W59: =VLOOKUP(C59,[2]IP!$B$9:$R$116,17,0) -> 0 | Y59: =+K59-O59-P59+Q59+R59+S59+T59+U59+V59+W59 -> #REF! | Z59: =+M59-Y59 -> #REF! | AB59: =VLOOKUP(C59,[1]SINDICATO!$C$7:$Q$141,15,0) -> #N/A
A60: SEI0428 | B60: SEITON (IP INNOVA II) | C60: Martinez Hernandez J. Antonio | E60: =VLOOKUP(C60,[2]IP!$B$9:$V$116,21,0) -> 3583.8 | G60: =VLOOKUP(C60,#REF!,4,0) -> #REF! | H60: =VLOOKUP(C60,#REF!,5,0) -> #REF! | I60: =VLOOKUP(C60,#REF!,6,0) -> #REF! | K60: =+D60+E60+G60+H60+I60 -> #REF! | L60: 8000 | M60: =+L60/2 -> 4000 | O60: =VLOOKUP(C60,[2]IP!$B$9:$I$116,8,0) -> 0 | P60: =+H60+I60 -> #REF! | Q60: =VLOOKUP(C60,[2]IP!$B$9:$N$116,13,0) -> 0 | R60: =VLOOKUP(C60,[2]IP!$B$9:$O$116,14,0) -> 0 | T60: =VLOOKUP(C60,[2]IP!$B$9:$P$116,15,0) -> 0 | U60: =VLOOKUP(C60,[2]IP!$B$9:$Q$116,16,0) -> 0 | V60: =VLOOKUP(C60,[2]IP!$B$9:$S$116,18,0) -> 0 | W60: =VLOOKUP(C60,[2]IP!$B$9:$R$116,17,0) -> 0 | Y60: =+K60-O60-P60+Q60+R60+S60+T60+U60+V60+W60 -> #REF! | Z60: =+M60-Y60 -> #REF! | AB60: =VLOOKUP(C60,[1]SINDICATO!$C$7:$Q$141,15,0) -> #N/A
A61: SEI0431 | B61: SEITON (IP INNOVA II) | C61: Alcaraz Conde Zabdi Guadalupe | E61: =VLOOKUP(C61,[2]IP!$B$9:$V$116,21,0) -> 1129.4 | G61: =VLOOKUP(C61,#REF!,4,0) -> #REF! | H61: =VLOOKUP(C61,#REF!,5,0) -> #REF! | I61: =VLOOKUP(C61,#REF!,6,0) -> #REF! | K61: =+D61+E61+G61+H61+I61 -> #REF! | L61: 6000 | M61: =+L61/2 -> 3000 | O61: =VLOOKUP(C61,[2]IP!$B$9:$I$116,8,0) -> 0 | P61: =+H61+I61 -> #REF! | Q61: =VLOOKUP(C61,[2]IP!$B$9:$N$116,13,0) -> 0 | R61: =VLOOKUP(C61,[2]IP!$B$9:$O$116,14,0) -> 1120.4 | T61: =VLOOKUP(C61,[2]IP!$B$9:$P$116,15,0) -> 15 | U61: =VLOOKUP(C61,[2]IP!$B$9:$Q$116,16,0) -> 600 | V61: =VLOOKUP(C61,[2]IP!$B$9:$S$116,18,0) -> 0 | W61: =VLOOKUP(C61,[2]IP!$B$9:$R$116,17,0) -> 0 | Y61: =+K61-O61-P61+Q61+R61+S61+T61+U61+V61+W61 -> #REF! | Z61: =+M61-Y61 -> #REF! | AB61: =VLOOKUP(C61,[1]SINDICATO!$C$7:$Q$141,15,0) -> #N/A
A62: SEI0438 | B62: SEITON (IP INNOVA II) | C62: Lopez Terron Roberto Porfirio | E62: =VLOOKUP(C62,[2]IP!$B$9:$V$116,21,0) -> 5952.2 | G62: =VLOOKUP(C62,#REF!,4,0) -> #REF! | H62: =VLOOKUP(C62,#REF!,5,0) -> #REF! | I62: =VLOOKUP(C62,#REF!,6,0) -> #REF! | K62: =+D62+E62+G62+H62+I62 -> #REF! | L62: 14000 | M62: =+L62/2 -> 7000 | O62: =VLOOKUP(C62,[2]IP!$B$9:$I$116,8,0) -> 0 | P62: =+H62+I62 -> #REF! | Q62: =VLOOKUP(C62,[2]IP!$B$9:$N$116,13,0) -> 0 | R62: =VLOOKUP(C62,[2]IP!$B$9:$O$116,14,0) -> 0 | T62: =VLOOKUP(C62,[2]IP!$B$9:$P$116,15,0) -> 0 | U62: =VLOOKUP(C62,[2]IP!$B$9:$Q$116,16,0) -> 0 | V62: =VLOOKUP(C62,[2]IP!$B$9:$S$116,18,0) -> 0 | W62: =VLOOKUP(C62,[2]IP!$B$9:$R$116,17,0) -> 0 | Y62: =+K62-O62-P62+Q62+R62+S62+T62+U62+V62+W62 -> #REF! | Z62: =+M62-Y62 -> #REF! | AB62: =VLOOKUP(C62,[1]SINDICATO!$C$7:$Q$141,15,0) -> #N/A
A63: SEI0442 | B63: SEITON (IP INNOVA II) | C63: Chavez Pedraza Samuel | E63: =VLOOKUP(C63,[2]IP!$B$9:$V$116,21,0) -> 5952.2 | G63: =VLOOKUP(C63,#REF!,4,0) -> #REF! | H63: =VLOOKUP(C63,#REF!,5,0) -> #REF! | I63: =VLOOKUP(C63,#REF!,6,0) -> #REF! | K63: =+D63+E63+G63+H63+I63 -> #REF! | L63: 14000 | M63: =+L63/2 -> 7000 | O63: =VLOOKUP(C63,[2]IP!$B$9:$I$116,8,0) -> 0 | P63: =+H63+I63 -> #REF! | Q63: =VLOOKUP(C63,[2]IP!$B$9:$N$116,13,0) -> 0 | R63: =VLOOKUP(C63,[2]IP!$B$9:$O$116,14,0) -> 0 | T63: =VLOOKUP(C63,[2]IP!$B$9:$P$116,15,0) -> 0 | U63: =VLOOKUP(C63,[2]IP!$B$9:$Q$116,16,0) -> 0 | V63: =VLOOKUP(C63,[2]IP!$B$9:$S$116,18,0) -> 0 | W63: =VLOOKUP(C63,[2]IP!$B$9:$R$116,17,0) -> 0 | Y63: =+K63-O63-P63+Q63+R63+S63+T63+U63+V63+W63 -> #REF! | Z63: =+M63-Y63 -> #REF! | AB63: =VLOOKUP(C63,[1]SINDICATO!$C$7:$Q$141,15,0) -> #N/A
A64: SEI0443 | B64: SEITON (IP INNOVA II) | C64: Castillo Nungaray Nestor Roman | E64: =VLOOKUP(C64,[2]IP!$B$9:$V$116,21,0) -> 2864.8 | G64: =VLOOKUP(C64,#REF!,4,0) -> #REF! | H64: =VLOOKUP(C64,#REF!,5,0) -> #REF! | I64: =VLOOKUP(C64,#REF!,6,0) -> #REF! | K64: =+D64+E64+G64+H64+I64 -> #REF! | L64: 6000 | M64: =+L64/2 -> 3000 | O64: =VLOOKUP(C64,[2]IP!$B$9:$I$116,8,0) -> 0 | P64: =+H64+I64 -> #REF! | Q64: =VLOOKUP(C64,[2]IP!$B$9:$N$116,13,0) -> 0 | R64: =VLOOKUP(C64,[2]IP!$B$9:$O$116,14,0) -> 0 | T64: =VLOOKUP(C64,[2]IP!$B$9:$P$116,15,0) -> 0 | U64: =VLOOKUP(C64,[2]IP!$B$9:$Q$116,16,0) -> 0 | V64: =VLOOKUP(C64,[2]IP!$B$9:$S$116,18,0) -> 0 | W64: =VLOOKUP(C64,[2]IP!$B$9:$R$116,17,0) -> 0 | Y64: =+K64-O64-P64+Q64+R64+S64+T64+U64+V64+W64 -> #REF! | Z64: =+M64-Y64 -> #REF! | AB64: =VLOOKUP(C64,[1]SINDICATO!$C$7:$Q$141,15,0) -> #N/A
A65: SEI0444 | B65: SEITON (IP INNOVA II) | C65: Marquez Hernandez Rogelio | E65: =VLOOKUP(C65,[2]IP!$B$9:$V$116,21,0) -> 3583.6 | G65: =VLOOKUP(C65,#REF!,4,0) -> #REF! | H65: =VLOOKUP(C65,#REF!,5,0) -> #REF! | I65: =VLOOKUP(C65,#REF!,6,0) -> #REF! | K65: =+D65+E65+G65+H65+I65 -> #REF! | L65: 8000 | M65: =+L65/2 -> 4000 | O65: =VLOOKUP(C65,[2]IP!$B$9:$I$116,8,0) -> 0 | P65: =+H65+I65 -> #REF! | Q65: =VLOOKUP(C65,[2]IP!$B$9:$N$116,13,0) -> 0 | R65: =VLOOKUP(C65,[2]IP!$B$9:$O$116,14,0) -> 0 | T65: =VLOOKUP(C65,[2]IP!$B$9:$P$116,15,0) -> 0 | U65: =VLOOKUP(C65,[2]IP!$B$9:$Q$116,16,0) -> 0 | V65: =VLOOKUP(C65,[2]IP!$B$9:$S$116,18,0) -> 0 | W65: =VLOOKUP(C65,[2]IP!$B$9:$R$116,17,0) -> 0 | Y65: =+K65-O65-P65+Q65+R65+S65+T65+U65+V65+W65 -> #REF! | Z65: =+M65-Y65 -> #REF! | AB65: =VLOOKUP(C65,[1]SINDICATO!$C$7:$Q$141,15,0) -> #N/A
A66: SEI0449 | B66: SEITON (IP INNOVA II) | C66: Flores Cerrillos Jorge Humberto | E66: =VLOOKUP(C66,[2]IP!$B$9:$V$116,21,0) -> 3583.6 | G66: =VLOOKUP(C66,#REF!,4,0) -> #REF! | H66: =VLOOKUP(C66,#REF!,5,0) -> #REF! | I66: =VLOOKUP(C66,#REF!,6,0) -> #REF! | K66: =+D66+E66+G66+H66+I66 -> #REF! | L66: 8000 | M66: =+L66/2 -> 4000 | O66: =VLOOKUP(C66,[2]IP!$B$9:$I$116,8,0) -> 0 | P66: =+H66+I66 -> #REF! | Q66: =VLOOKUP(C66,[2]IP!$B$9:$N$116,13,0) -> 0 | R66: =VLOOKUP(C66,[2]IP!$B$9:$O$116,14,0) -> 0 | T66: =VLOOKUP(C66,[2]IP!$B$9:$P$116,15,0) -> 0 | U66: =VLOOKUP(C66,[2]IP!$B$9:$Q$116,16,0) -> 0 | V66: =VLOOKUP(C66,[2]IP!$B$9:$S$116,18,0) -> 0 | W66: =VLOOKUP(C66,[2]IP!$B$9:$R$116,17,0) -> 0 | Y66: =+K66-O66-P66+Q66+R66+S66+T66+U66+V66+W66 -> #REF! | Z66: =+M66-Y66 -> #REF! | AB66: =VLOOKUP(C66,[1]SINDICATO!$C$7:$Q$141,15,0) -> #N/A
A67: SEI0451 | B67: SEITON (IP INNOVA II) | C67: Hurtado Avalos J.jesus | E67: =VLOOKUP(C67,[2]IP!$B$9:$V$116,21,0) -> 2864.6 | G67: =VLOOKUP(C67,#REF!,4,0) -> #REF! | H67: =VLOOKUP(C67,#REF!,5,0) -> #REF! | I67: =VLOOKUP(C67,#REF!,6,0) -> #REF! | K67: =+D67+E67+G67+H67+I67 -> #REF! | L67: 6000 | M67: =+L67/2 -> 3000 | O67: =VLOOKUP(C67,[2]IP!$B$9:$I$116,8,0) -> 0 | P67: =+H67+I67 -> #REF! | Q67: =VLOOKUP(C67,[2]IP!$B$9:$N$116,13,0) -> 0 | R67: =VLOOKUP(C67,[2]IP!$B$9:$O$116,14,0) -> 0 | T67: =VLOOKUP(C67,[2]IP!$B$9:$P$116,15,0) -> 0 | U67: =VLOOKUP(C67,[2]IP!$B$9:$Q$116,16,0) -> 0 | V67: =VLOOKUP(C67,[2]IP!$B$9:$S$116,18,0) -> 0 | W67: =VLOOKUP(C67,[2]IP!$B$9:$R$116,17,0) -> 0 | Y67: =+K67-O67-P67+Q67+R67+S67+T67+U67+V67+W67 -> #REF! | Z67: =+M67-Y67 -> #REF! | AB67: =VLOOKUP(C67,[1]SINDICATO!$C$7:$Q$141,15,0) -> 0
A68: SEI0453 | B68: SEITON (IP INNOVA II) | C68: Mora Cavazos Roberto Manuel | E68: =VLOOKUP(C68,[2]IP!$B$9:$V$116,21,0) -> 3583.8 | G68: =VLOOKUP(C68,#REF!,4,0) -> #REF! | H68: =VLOOKUP(C68,#REF!,5,0) -> #REF! | I68: =VLOOKUP(C68,#REF!,6,0) -> #REF! | K68: =+D68+E68+G68+H68+I68 -> #REF! | L68: 8000 | M68: =+L68/2 -> 4000 | O68: =VLOOKUP(C68,[2]IP!$B$9:$I$116,8,0) -> 0 | P68: =+H68+I68 -> #REF! | Q68: =VLOOKUP(C68,[2]IP!$B$9:$N$116,13,0) -> 0 | R68: =VLOOKUP(C68,[2]IP!$B$9:$O$116,14,0) -> 0 | T68: =VLOOKUP(C68,[2]IP!$B$9:$P$116,15,0) -> 0 | U68: =VLOOKUP(C68,[2]IP!$B$9:$Q$116,16,0) -> 0 | V68: =VLOOKUP(C68,[2]IP!$B$9:$S$116,18,0) -> 0 | W68: =VLOOKUP(C68,[2]IP!$B$9:$R$116,17,0) -> 0 | Y68: =+K68-O68-P68+Q68+R68+S68+T68+U68+V68+W68 -> #REF! | Z68: =+M68-Y68 -> #REF! | AB68: =VLOOKUP(C68,[1]SINDICATO!$C$7:$Q$141,15,0) -> 0
A69: SEI0454 | B69: SEITON (IP INNOVA II) | C69: Martinez Rivera Maria Teresa | E69: =VLOOKUP(C69,[2]IP!$B$9:$V$116,21,0) -> 4503.4 | G69: =VLOOKUP(C69,#REF!,4,0) -> #REF! | H69: =VLOOKUP(C69,#REF!,5,0) -> #REF! | I69: =VLOOKUP(C69,#REF!,6,0) -> #REF! | K69: =+D69+E69+G69+H69+I69 -> #REF! | L69: 9000 | M69: =+L69/2 -> 4500 | O69: =VLOOKUP(C69,[2]IP!$B$9:$I$116,8,0) -> 0 | P69: =+H69+I69 -> #REF! | Q69: =VLOOKUP(C69,[2]IP!$B$9:$N$116,13,0) -> 0 | R69: =VLOOKUP(C69,[2]IP!$B$9:$O$116,14,0) -> 0 | T69: =VLOOKUP(C69,[2]IP!$B$9:$P$116,15,0) -> 0 | U69: =VLOOKUP(C69,[2]IP!$B$9:$Q$116,16,0) -> 0 | V69: =VLOOKUP(C69,[2]IP!$B$9:$S$116,18,0) -> 0 | W69: =VLOOKUP(C69,[2]IP!$B$9:$R$116,17,0) -> 0 | Y69: =+K69-O69-P69+Q69+R69+S69+T69+U69+V69+W69 -> #REF! | Z69: =+M69-Y69 -> #REF! | AA69: 100% IMSS | AB69: =VLOOKUP(C69,[1]SINDICATO!$C$7:$Q$141,15,0) -> 0
A70: SEI0455 | B70: SEITON (IP INNOVA II) | C70: Perez Garcia Andres Alvaro | E70: =VLOOKUP(C70,[2]IP!$B$9:$V$116,21,0) -> 3583.6 | G70: =VLOOKUP(C70,#REF!,4,0) -> #REF! | H70: =VLOOKUP(C70,#REF!,5,0) -> #REF! | I70: =VLOOKUP(C70,#REF!,6,0) -> #REF! | K70: =+D70+E70+G70+H70+I70 -> #REF! | L70: 8000 | M70: =+L70/2 -> 4000 | O70: =VLOOKUP(C70,[2]IP!$B$9:$I$116,8,0) -> 0 | P70: =+H70+I70 -> #REF! | Q70: =VLOOKUP(C70,[2]IP!$B$9:$N$116,13,0) -> 0 | R70: =VLOOKUP(C70,[2]IP!$B$9:$O$116,14,0) -> 0 | T70: =VLOOKUP(C70,[2]IP!$B$9:$P$116,15,0) -> 0 | U70: =VLOOKUP(C70,[2]IP!$B$9:$Q$116,16,0) -> 0 | V70: =VLOOKUP(C70,[2]IP!$B$9:$S$116,18,0) -> 0 | W70: =VLOOKUP(C70,[2]IP!$B$9:$R$116,17,0) -> 0 | Y70: =+K70-O70-P70+Q70+R70+S70+T70+U70+V70+W70 -> #REF! | Z70: =+M70-Y70 -> #REF! | AB70: =VLOOKUP(C70,[1]SINDICATO!$C$7:$Q$141,15,0) -> #N/A
A71: SEI0456 | B71: SEITON (IP INNOVA II) | C71: Chavira Garcia David Fernando | E71: =VLOOKUP(C71,[2]IP!$B$9:$V$116,21,0) -> 4406.4 | G71: =VLOOKUP(C71,#REF!,4,0) -> #REF! | H71: =VLOOKUP(C71,#REF!,5,0) -> #REF! | I71: =VLOOKUP(C71,#REF!,6,0) -> #REF! | K71: =+D71+E71+G71+H71+I71 -> #REF! | L71: 10000 | M71: =+L71/2 -> 5000 | O71: =VLOOKUP(C71,[2]IP!$B$9:$I$116,8,0) -> 0 | P71: =+H71+I71 -> #REF! | Q71: =VLOOKUP(C71,[2]IP!$B$9:$N$116,13,0) -> 0 | R71: =VLOOKUP(C71,[2]IP!$B$9:$O$116,14,0) -> 0 | T71: =VLOOKUP(C71,[2]IP!$B$9:$P$116,15,0) -> 0 | U71: =VLOOKUP(C71,[2]IP!$B$9:$Q$116,16,0) -> 0 | V71: =VLOOKUP(C71,[2]IP!$B$9:$S$116,18,0) -> 0 | W71: =VLOOKUP(C71,[2]IP!$B$9:$R$116,17,0) -> 0 | Y71: =+K71-O71-P71+Q71+R71+S71+T71+U71+V71+W71 -> #REF! | Z71: =+M71-Y71 -> #REF! | AB71: =VLOOKUP(C71,[1]SINDICATO!$C$7:$Q$141,15,0) -> #N/A
A72: SEI0457 | B72: SEITON (IP INNOVA II) | C72: Guerrero Lara Cesar Adrian | E72: =VLOOKUP(C72,[2]IP!$B$9:$V$116,21,0) -> 3238.4 | G72: =VLOOKUP(C72,#REF!,4,0) -> #REF! | H72: =VLOOKUP(C72,#REF!,5,0) -> #REF! | I72: =VLOOKUP(C72,#REF!,6,0) -> #REF! | K72: =+D72+E72+G72+H72+I72 -> #REF! | L72: 8000 | M72: =+L72/2 -> 4000 | O72: =VLOOKUP(C72,[2]IP!$B$9:$I$116,8,0) -> 0 | P72: =+H72+I72 -> #REF! | Q72: =VLOOKUP(C72,[2]IP!$B$9:$N$116,13,0) -> 0 | R72: =VLOOKUP(C72,[2]IP!$B$9:$O$116,14,0) -> 0 | T72: =VLOOKUP(C72,[2]IP!$B$9:$P$116,15,0) -> 0 | U72: =VLOOKUP(C72,[2]IP!$B$9:$Q$116,16,0) -> 0 | V72: =VLOOKUP(C72,[2]IP!$B$9:$S$116,18,0) -> 0 | W72: =VLOOKUP(C72,[2]IP!$B$9:$R$116,17,0) -> 345.25 | Y72: =+K72-O72-P72+Q72+R72+S72+T72+U72+V72+W72 -> #REF! | Z72: =+M72-Y72 -> #REF! | AB72: =VLOOKUP(C72,[1]SINDICATO!$C$7:$Q$141,15,0) -> #N/A
A73: SEI0458 | B73: SEITON (IP INNOVA II) | C73: Martinez Zamora Gerardo Mario | E73: =VLOOKUP(C73,[2]IP!$B$9:$V$116,21,0) -> 2681.6 | G73: =VLOOKUP(C73,#REF!,4,0) -> #REF! | H73: =VLOOKUP(C73,#REF!,5,0) -> #REF! | I73: =VLOOKUP(C73,#REF!,6,0) -> #REF! | K73: =+D73+E73+G73+H73+I73 -> #REF! | L73: 9550.01 | M73: =+L73/2 -> 4775.005 | O73: =VLOOKUP(C73,[2]IP!$B$9:$I$116,8,0) -> 0 | P73: =+H73+I73 -> #REF! | Q73: =VLOOKUP(C73,[2]IP!$B$9:$N$116,13,0) -> 1528.5 | R73: =VLOOKUP(C73,[2]IP!$B$9:$O$116,14,0) -> 0 | T73: =VLOOKUP(C73,[2]IP!$B$9:$P$116,15,0) -> 15 | U73: =VLOOKUP(C73,[2]IP!$B$9:$Q$116,16,0) -> 0 | V73: =VLOOKUP(C73,[2]IP!$B$9:$S$116,18,0) -> 0 | W73: =VLOOKUP(C73,[2]IP!$B$9:$R$116,17,0) -> 0 | Y73: =+K73-O73-P73+Q73+R73+S73+T73+U73+V73+W73 -> #REF! | Z73: =+M73-Y73 -> #REF! | AB73: =VLOOKUP(C73,[1]SINDICATO!$C$7:$Q$141,15,0) -> #N/A
A74: SEI0460 | B74: SEITON (IP INNOVA II) | C74: Castellon Ramos Rene | E74: =VLOOKUP(C74,[2]IP!$B$9:$V$116,21,0) -> 1157.8 | G74: =VLOOKUP(C74,#REF!,4,0) -> #REF! | H74: =VLOOKUP(C74,#REF!,5,0) -> #REF! | I74: =VLOOKUP(C74,#REF!,6,0) -> #REF! | K74: =+D74+E74+G74+H74+I74 -> #REF! | L74: 7505.99 | M74: =+L74/2 -> 3752.995 | O74: =VLOOKUP(C74,[2]IP!$B$9:$I$116,8,0) -> 0 | P74: =+H74+I74 -> #REF! | Q74: =VLOOKUP(C74,[2]IP!$B$9:$N$116,13,0) -> 0 | R74: =VLOOKUP(C74,[2]IP!$B$9:$O$116,14,0) -> 1346.54 | T74: =VLOOKUP(C74,[2]IP!$B$9:$P$116,15,0) -> 15 | U74: =VLOOKUP(C74,[2]IP!$B$9:$Q$116,16,0) -> 0 | V74: =VLOOKUP(C74,[2]IP!$B$9:$S$116,18,0) -> 0 | W74: =VLOOKUP(C74,[2]IP!$B$9:$R$116,17,0) -> 848.88 | Y74: =+K74-O74-P74+Q74+R74+S74+T74+U74+V74+W74 -> #REF! | Z74: =+M74-Y74 -> #REF! | AB74: =VLOOKUP(C74,[1]SINDICATO!$C$7:$Q$141,15,0) -> #N/A
A75: SEI0461 | B75: SEITON (IP INNOVA II) | C75: Flores Franco Marco | E75: =VLOOKUP(C75,[2]IP!$B$9:$V$116,21,0) -> 3799 | G75: =VLOOKUP(C75,#REF!,4,0) -> #REF! | H75: =VLOOKUP(C75,#REF!,5,0) -> #REF! | I75: =VLOOKUP(C75,#REF!,6,0) -> #REF! | K75: =+D75+E75+G75+H75+I75 -> #REF! | L75: 8500.01 | M75: =+L75/2 -> 4250.005 | O75: =VLOOKUP(C75,[2]IP!$B$9:$I$116,8,0) -> 0 | P75: =+H75+I75 -> #REF! | Q75: =VLOOKUP(C75,[2]IP!$B$9:$N$116,13,0) -> 0 | R75: =VLOOKUP(C75,[2]IP!$B$9:$O$116,14,0) -> 0 | T75: =VLOOKUP(C75,[2]IP!$B$9:$P$116,15,0) -> 0 | U75: =VLOOKUP(C75,[2]IP!$B$9:$Q$116,16,0) -> 0 | V75: =VLOOKUP(C75,[2]IP!$B$9:$S$116,18,0) -> 0 | W75: =VLOOKUP(C75,[2]IP!$B$9:$R$116,17,0) -> 0 | Y75: =+K75-O75-P75+Q75+R75+S75+T75+U75+V75+W75 -> #REF! | Z75: =+M75-Y75 -> #REF! | AB75: =VLOOKUP(C75,[1]SINDICATO!$C$7:$Q$141,15,0) -> #N/A
A76: SEI0462 | B76: SEITON (IP INNOVA II) | C76: Chavez Saucedo Jorge Arturo | E76: =VLOOKUP(C76,[2]IP!$B$9:$V$116,21,0) -> 3585.4 | G76: =VLOOKUP(C76,#REF!,4,0) -> #REF! | H76: =VLOOKUP(C76,#REF!,5,0) -> #REF! | I76: =VLOOKUP(C76,#REF!,6,0) -> #REF! | K76: =+D76+E76+G76+H76+I76 -> #REF! | L76: 8000 | M76: =+L76/2 -> 4000 | O76: =VLOOKUP(C76,[2]IP!$B$9:$I$116,8,0) -> 0 | P76: =+H76+I76 -> #REF! | Q76: =VLOOKUP(C76,[2]IP!$B$9:$N$116,13,0) -> 0 | R76: =VLOOKUP(C76,[2]IP!$B$9:$O$116,14,0) -> 0 | T76: =VLOOKUP(C76,[2]IP!$B$9:$P$116,15,0) -> 0 | U76: =VLOOKUP(C76,[2]IP!$B$9:$Q$116,16,0) -> 0 | V76: =VLOOKUP(C76,[2]IP!$B$9:$S$116,18,0) -> 0 | W76: =VLOOKUP(C76,[2]IP!$B$9:$R$116,17,0) -> 0 | Y76: =+K76-O76-P76+Q76+R76+S76+T76+U76+V76+W76 -> #REF! | Z76: =+M76-Y76 -> #REF! | AB76: =VLOOKUP(C76,[1]SINDICATO!$C$7:$Q$141,15,0) -> #N/A
A77: SEI0464 | B77: SEITON (IP INNOVA II) | C77: Hueramo Hueramo Jesus Daniel | E77: =VLOOKUP(C77,[2]IP!$B$9:$V$116,21,0) -> 2869 | G77: =VLOOKUP(C77,#REF!,4,0) -> #REF! | H77: =VLOOKUP(C77,#REF!,5,0) -> #REF! | I77: =VLOOKUP(C77,#REF!,6,0) -> #REF! | K77: =+D77+E77+G77+H77+I77 -> #REF! | L77: 8500.01 | M77: =+L77/2 -> 4250.005 | O77: =VLOOKUP(C77,[2]IP!$B$9:$I$116,8,0) -> 0 | P77: =+H77+I77 -> #REF! | Q77: =VLOOKUP(C77,[2]IP!$B$9:$N$116,13,0) -> 0 | R77: =VLOOKUP(C77,[2]IP!$B$9:$O$116,14,0) -> 592.54 | T77: =VLOOKUP(C77,[2]IP!$B$9:$P$116,15,0) -> 15 | U77: =VLOOKUP(C77,[2]IP!$B$9:$Q$116,16,0) -> 0 | V77: =VLOOKUP(C77,[2]IP!$B$9:$S$116,18,0) -> 0 | W77: =VLOOKUP(C77,[2]IP!$B$9:$R$116,17,0) -> 322.5 | Y77: =+K77-O77-P77+Q77+R77+S77+T77+U77+V77+W77 -> #REF! | Z77: =+M77-Y77 -> #REF! | AB77: =VLOOKUP(C77,[1]SINDICATO!$C$7:$Q$141,15,0) -> #N/A
A78: SEI0465 | B78: SEITON (IP INNOVA II) | C78: Sandoval Garcia Luis | E78: =VLOOKUP(C78,[2]IP!$B$9:$V$116,21,0) -> 3583.6 | G78: =VLOOKUP(C78,#REF!,4,0) -> #REF! | H78: =VLOOKUP(C78,#REF!,5,0) -> #REF! | I78: =VLOOKUP(C78,#REF!,6,0) -> #REF! | K78: =+D78+E78+G78+H78+I78 -> #REF! | L78: 8000 | M78: =+L78/2 -> 4000 | O78: =VLOOKUP(C78,[2]IP!$B$9:$I$116,8,0) -> 0 | P78: =+H78+I78 -> #REF! | Q78: =VLOOKUP(C78,[2]IP!$B$9:$N$116,13,0) -> 0 | R78: =VLOOKUP(C78,[2]IP!$B$9:$O$116,14,0) -> 0 | T78: =VLOOKUP(C78,[2]IP!$B$9:$P$116,15,0) -> 0 | U78: =VLOOKUP(C78,[2]IP!$B$9:$Q$116,16,0) -> 0 | V78: =VLOOKUP(C78,[2]IP!$B$9:$S$116,18,0) -> 0 | W78: =VLOOKUP(C78,[2]IP!$B$9:$R$116,17,0) -> 0 | Y78: =+K78-O78-P78+Q78+R78+S78+T78+U78+V78+W78 -> #REF! | Z78: =+M78-Y78 -> #REF! | AB78: =VLOOKUP(C78,[1]SINDICATO!$C$7:$Q$141,15,0) -> #N/A
A79: SEI0467 | B79: SEITON (IP INNOVA II) | C79: Vaca Valdez Guillermo | E79: =VLOOKUP(C79,[2]IP!$B$9:$V$116,21,0) -> 1320.4 | G79: =VLOOKUP(C79,#REF!,4,0) -> #REF! | H79: =VLOOKUP(C79,#REF!,5,0) -> #REF! | I79: =VLOOKUP(C79,#REF!,6,0) -> #REF! | K79: =+D79+E79+G79+H79+I79 -> #REF! | L79: 8000 | M79: =+L79/2 -> 4000 | O79: =VLOOKUP(C79,[2]IP!$B$9:$I$116,8,0) -> 0 | P79: =+H79+I79 -> #REF! | Q79: =VLOOKUP(C79,[2]IP!$B$9:$N$116,13,0) -> 1848.35 | R79: =VLOOKUP(C79,[2]IP!$B$9:$O$116,14,0) -> 0 | T79: =VLOOKUP(C79,[2]IP!$B$9:$P$116,15,0) -> 15 | U79: =VLOOKUP(C79,[2]IP!$B$9:$Q$116,16,0) -> 0 | V79: =VLOOKUP(C79,[2]IP!$B$9:$S$116,18,0) -> 0 | W79: =VLOOKUP(C79,[2]IP!$B$9:$R$116,17,0) -> 400 | Y79: =+K79-O79-P79+Q79+R79+S79+T79+U79+V79+W79 -> #REF! | Z79: =+M79-Y79 -> #REF! | AB79: =VLOOKUP(C79,[1]SINDICATO!$C$7:$Q$141,15,0) -> #N/A
A80: SEI0468 | B80: SEITON (IP INNOVA II) | C80: Ramirez Vera Eustolia | E80: =VLOOKUP(C80,[2]IP!$B$9:$V$116,21,0) -> 3561.4 | G80: =VLOOKUP(C80,#REF!,4,0) -> #REF! | H80: =VLOOKUP(C80,#REF!,5,0) -> #REF! | I80: =VLOOKUP(C80,#REF!,6,0) -> #REF! | K80: =+D80+E80+G80+H80+I80 -> #REF! | L80: 7900 | M80: =+L80/2 -> 3950 | O80: =VLOOKUP(C80,[2]IP!$B$9:$I$116,8,0) -> 0 | P80: =+H80+I80 -> #REF! | Q80: =VLOOKUP(C80,[2]IP!$B$9:$N$116,13,0) -> 428.6 | R80: =VLOOKUP(C80,[2]IP!$B$9:$O$116,14,0) -> 0 | T80: =VLOOKUP(C80,[2]IP!$B$9:$P$116,15,0) -> 15 | U80: =VLOOKUP(C80,[2]IP!$B$9:$Q$116,16,0) -> 0 | V80: =VLOOKUP(C80,[2]IP!$B$9:$S$116,18,0) -> 0 | W80: =VLOOKUP(C80,[2]IP!$B$9:$R$116,17,0) -> 0 | Y80: =+K80-O80-P80+Q80+R80+S80+T80+U80+V80+W80 -> #REF! | Z80: =+M80-Y80 -> #REF! | AA80: subsidio | AB80: =VLOOKUP(C80,[1]SINDICATO!$C$7:$Q$141,15,0) -> 0
A81: SEI0469 | B81: SEITON (IP INNOVA II) | C81: Martinez Morales Jose Martin | E81: =VLOOKUP(C81,[2]IP!$B$9:$V$116,21,0) -> 5952.2 | G81: =VLOOKUP(C81,#REF!,4,0) -> #REF! | H81: =VLOOKUP(C81,#REF!,5,0) -> #REF! | I81: =VLOOKUP(C81,#REF!,6,0) -> #REF! | K81: =+D81+E81+G81+H81+I81 -> #REF! | L81: 14000 | M81: =+L81/2 -> 7000 | O81: =VLOOKUP(C81,[2]IP!$B$9:$I$116,8,0) -> 0 | P81: =+H81+I81 -> #REF! | Q81: =VLOOKUP(C81,[2]IP!$B$9:$N$116,13,0) -> 0 | R81: =VLOOKUP(C81,[2]IP!$B$9:$O$116,14,0) -> 0 | T81: =VLOOKUP(C81,[2]IP!$B$9:$P$116,15,0) -> 0 | U81: =VLOOKUP(C81,[2]IP!$B$9:$Q$116,16,0) -> 0 | V81: =VLOOKUP(C81,[2]IP!$B$9:$S$116,18,0) -> 0 | W81: =VLOOKUP(C81,[2]IP!$B$9:$R$116,17,0) -> 0 | Y81: =+K81-O81-P81+Q81+R81+S81+T81+U81+V81+W81 -> #REF! | Z81: =+M81-Y81 -> #REF! | AB81: =VLOOKUP(C81,[1]SINDICATO!$C$7:$Q$141,15,0) -> #N/A
A82: SEI0472 | B82: SEITON (IP INNOVA II) | C82: Arzate Gil Juan Sebastian | E82: =VLOOKUP(C82,[2]IP!$B$9:$V$116,21,0) -> 2895 | G82: =VLOOKUP(C82,#REF!,4,0) -> #REF! | H82: =VLOOKUP(C82,#REF!,5,0) -> #REF! | I82: =VLOOKUP(C82,#REF!,6,0) -> #REF! | K82: =+D82+E82+G82+H82+I82 -> #REF! | L82: 8000 | M82: =+L82/2 -> 4000 | O82: =VLOOKUP(C82,[2]IP!$B$9:$I$116,8,0) -> 0 | P82: =+H82+I82 -> #REF! | Q82: =VLOOKUP(C82,[2]IP!$B$9:$N$116,13,0) -> 0 | R82: =VLOOKUP(C82,[2]IP!$B$9:$O$116,14,0) -> 0 | T82: =VLOOKUP(C82,[2]IP!$B$9:$P$116,15,0) -> 0 | U82: =VLOOKUP(C82,[2]IP!$B$9:$Q$116,16,0) -> 0 | V82: =VLOOKUP(C82,[2]IP!$B$9:$S$116,18,0) -> 0 | W82: =VLOOKUP(C82,[2]IP!$B$9:$R$116,17,0) -> 688.8 | Y82: =+K82-O82-P82+Q82+R82+S82+T82+U82+V82+W82 -> #REF! | Z82: =+M82-Y82 -> #REF! | AB82: =VLOOKUP(C82,[1]SINDICATO!$C$7:$Q$141,15,0) -> #N/A
A83: SEI0473 | B83: SEITON (IP INNOVA II) | C83: Torres Velazquez Juan Antonio | E83: =VLOOKUP(C83,[2]IP!$B$9:$V$116,21,0) -> 3583.6 | G83: =VLOOKUP(C83,#REF!,4,0) -> #REF! | H83: =VLOOKUP(C83,#REF!,5,0) -> #REF! | I83: =VLOOKUP(C83,#REF!,6,0) -> #REF! | K83: =+D83+E83+G83+H83+I83 -> #REF! | L83: 8000 | M83: =+L83/2 -> 4000 | O83: =VLOOKUP(C83,[2]IP!$B$9:$I$116,8,0) -> 0 | P83: =+H83+I83 -> #REF! | Q83: =VLOOKUP(C83,[2]IP!$B$9:$N$116,13,0) -> 0 | R83: =VLOOKUP(C83,[2]IP!$B$9:$O$116,14,0) -> 0 | T83: =VLOOKUP(C83,[2]IP!$B$9:$P$116,15,0) -> 0 | U83: =VLOOKUP(C83,[2]IP!$B$9:$Q$116,16,0) -> 0 | V83: =VLOOKUP(C83,[2]IP!$B$9:$S$116,18,0) -> 0 | W83: =VLOOKUP(C83,[2]IP!$B$9:$R$116,17,0) -> 0 | Y83: =+K83-O83-P83+Q83+R83+S83+T83+U83+V83+W83 -> #REF! | Z83: =+M83-Y83 -> #REF! | AB83: =VLOOKUP(C83,[1]SINDICATO!$C$7:$Q$141,15,0) -> #N/A
A84: SEI0474 | B84: SEITON (IP INNOVA II) | C84: Enriquez Zamora Jessica Del Rocio | E84: =VLOOKUP(C84,[2]IP!$B$9:$V$116,21,0) -> 2864.8 | G84: =VLOOKUP(C84,#REF!,4,0) -> #REF! | H84: =VLOOKUP(C84,#REF!,5,0) -> #REF! | I84: =VLOOKUP(C84,#REF!,6,0) -> #REF! | K84: =+D84+E84+G84+H84+I84 -> #REF! | L84: 6000 | M84: =+L84/2 -> 3000 | O84: =VLOOKUP(C84,[2]IP!$B$9:$I$116,8,0) -> 0 | P84: =+H84+I84 -> #REF! | Q84: =VLOOKUP(C84,[2]IP!$B$9:$N$116,13,0) -> 0 | R84: =VLOOKUP(C84,[2]IP!$B$9:$O$116,14,0) -> 0 | T84: =VLOOKUP(C84,[2]IP!$B$9:$P$116,15,0) -> 0 | U84: =VLOOKUP(C84,[2]IP!$B$9:$Q$116,16,0) -> 0 | V84: =VLOOKUP(C84,[2]IP!$B$9:$S$116,18,0) -> 0 | W84: =VLOOKUP(C84,[2]IP!$B$9:$R$116,17,0) -> 0 | Y84: =+K84-O84-P84+Q84+R84+S84+T84+U84+V84+W84 -> #REF! | AB84: =VLOOKUP(C84,[1]SINDICATO!$C$7:$Q$141,15,0) -> #N/A
A85: SEI0475 | B85: SEITON (IP INNOVA II) | C85: Moreno Quiroga Ana Sarahi | E85: =VLOOKUP(C85,[2]IP!$B$9:$V$116,21,0) -> 3583.8 | G85: =VLOOKUP(C85,#REF!,4,0) -> #REF! | H85: =VLOOKUP(C85,#REF!,5,0) -> #REF! | I85: =VLOOKUP(C85,#REF!,6,0) -> #REF! | K85: =+D85+E85+G85+H85+I85 -> #REF! | L85: 8000 | M85: =+L85/2 -> 4000 | O85: =VLOOKUP(C85,[2]IP!$B$9:$I$116,8,0) -> 0 | P85: =+H85+I85 -> #REF! | Q85: =VLOOKUP(C85,[2]IP!$B$9:$N$116,13,0) -> 0 | R85: =VLOOKUP(C85,[2]IP!$B$9:$O$116,14,0) -> 0 | T85: =VLOOKUP(C85,[2]IP!$B$9:$P$116,15,0) -> 0 | U85: =VLOOKUP(C85,[2]IP!$B$9:$Q$116,16,0) -> 0 | V85: =VLOOKUP(C85,[2]IP!$B$9:$S$116,18,0) -> 0 | W85: =VLOOKUP(C85,[2]IP!$B$9:$R$116,17,0) -> 0 | Y85: =+K85-O85-P85+Q85+R85+S85+T85+U85+V85+W85 -> #REF! | Z85: =+M85-Y85 -> #REF! | AB85: =VLOOKUP(C85,[1]SINDICATO!$C$7:$Q$141,15,0) -> #N/A
A86: SEI0476 | B86: SEITON (IP INNOVA II) | C86: Hernandez Garcia Manuel Alejandro | E86: =VLOOKUP(C86,[2]IP!$B$9:$V$116,21,0) -> 3585.4 | G86: =VLOOKUP(C86,#REF!,4,0) -> #REF! | H86: =VLOOKUP(C86,#REF!,5,0) -> #REF! | I86: =VLOOKUP(C86,#REF!,6,0) -> #REF! | K86: =+D86+E86+G86+H86+I86 -> #REF! | L86: 8000 | M86: =+L86/2 -> 4000 | O86: =VLOOKUP(C86,[2]IP!$B$9:$I$116,8,0) -> 0 | P86: =+H86+I86 -> #REF! | Q86: =VLOOKUP(C86,[2]IP!$B$9:$N$116,13,0) -> 0 | R86: =VLOOKUP(C86,[2]IP!$B$9:$O$116,14,0) -> 0 | T86: =VLOOKUP(C86,[2]IP!$B$9:$P$116,15,0) -> 0 | U86: =VLOOKUP(C86,[2]IP!$B$9:$Q$116,16,0) -> 0 | V86: =VLOOKUP(C86,[2]IP!$B$9:$S$116,18,0) -> 0 | W86: =VLOOKUP(C86,[2]IP!$B$9:$R$116,17,0) -> 0 | Y86: =+K86-O86-P86+Q86+R86+S86+T86+U86+V86+W86 -> #REF! | Z86: =+M86-Y86 -> #REF! | AB86: =VLOOKUP(C86,[1]SINDICATO!$C$7:$Q$141,15,0) -> #N/A
A87: SEI0477 | B87: SEITON (IP INNOVA II) | C87: Sandoval Medina Demetrio | E87: =VLOOKUP(C87,[2]IP!$B$9:$V$116,21,0) -> 3585.4 | G87: =VLOOKUP(C87,#REF!,4,0) -> #REF! | H87: =VLOOKUP(C87,#REF!,5,0) -> #REF! | I87: =VLOOKUP(C87,#REF!,6,0) -> #REF! | K87: =+D87+E87+G87+H87+I87 -> #REF! | L87: 8000 | M87: =+L87/2 -> 4000 | O87: =VLOOKUP(C87,[2]IP!$B$9:$I$116,8,0) -> 0 | P87: =+H87+I87 -> #REF! | Q87: =VLOOKUP(C87,[2]IP!$B$9:$N$116,13,0) -> 0 | R87: =VLOOKUP(C87,[2]IP!$B$9:$O$116,14,0) -> 0 | T87: =VLOOKUP(C87,[2]IP!$B$9:$P$116,15,0) -> 0 | U87: =VLOOKUP(C87,[2]IP!$B$9:$Q$116,16,0) -> 0 | V87: =VLOOKUP(C87,[2]IP!$B$9:$S$116,18,0) -> 0 | W87: =VLOOKUP(C87,[2]IP!$B$9:$R$116,17,0) -> 0 | Y87: =+K87-O87-P87+Q87+R87+S87+T87+U87+V87+W87 -> #REF! | Z87: =+M87-Y87 -> #REF! | AB87: =VLOOKUP(C87,[1]SINDICATO!$C$7:$Q$141,15,0) -> #N/A
A88: SEI0478 | B88: SEITON (IP INNOVA II) | C88: Leal Montaño Francisco | E88: =VLOOKUP(C88,[2]IP!$B$9:$V$116,21,0) -> 1831 | G88: =VLOOKUP(C88,#REF!,4,0) -> #REF! | H88: =VLOOKUP(C88,#REF!,5,0) -> #REF! | I88: =VLOOKUP(C88,#REF!,6,0) -> #REF! | K88: =+D88+E88+G88+H88+I88 -> #REF! | L88: 6000 | M88: =+L88/2 -> 3000 | O88: =VLOOKUP(C88,[2]IP!$B$9:$I$116,8,0) -> 0 | P88: =+H88+I88 -> #REF! | Q88: =VLOOKUP(C88,[2]IP!$B$9:$N$116,13,0) -> 1018.71 | R88: =VLOOKUP(C88,[2]IP!$B$9:$O$116,14,0) -> 0 | T88: =VLOOKUP(C88,[2]IP!$B$9:$P$116,15,0) -> 15 | U88: =VLOOKUP(C88,[2]IP!$B$9:$Q$116,16,0) -> 0 | V88: =VLOOKUP(C88,[2]IP!$B$9:$S$116,18,0) -> 0 | W88: =VLOOKUP(C88,[2]IP!$B$9:$R$116,17,0) -> 0 | Y88: =+K88-O88-P88+Q88+R88+S88+T88+U88+V88+W88 -> #REF! | Z88: =+M88-Y88 -> #REF! | AB88: =VLOOKUP(C88,[1]SINDICATO!$C$7:$Q$141,15,0) -> 0
A89: SEI479 | B89: SEITON (IP INNOVA II) | C89: Cruz Perez Alejandro Nezahualcoyotl | E89: =VLOOKUP(C89,[2]IP!$B$9:$V$116,21,0) -> 3583.6 | G89: =VLOOKUP(C89,#REF!,4,0) -> #REF! | H89: =VLOOKUP(C89,#REF!,5,0) -> #REF! | I89: =VLOOKUP(C89,#REF!,6,0) -> #REF! | K89: =+D89+E89+G89+H89+I89 -> #REF! | L89: 8000 | M89: =+L89/2 -> 4000 | O89: =VLOOKUP(C89,[2]IP!$B$9:$I$116,8,0) -> 0 | P89: =+H89+I89 -> #REF! | Q89: =VLOOKUP(C89,[2]IP!$B$9:$N$116,13,0) -> 0 | R89: =VLOOKUP(C89,[2]IP!$B$9:$O$116,14,0) -> 0 | T89: =VLOOKUP(C89,[2]IP!$B$9:$P$116,15,0) -> 0 | U89: =VLOOKUP(C89,[2]IP!$B$9:$Q$116,16,0) -> 0 | V89: =VLOOKUP(C89,[2]IP!$B$9:$S$116,18,0) -> 0 | W89: =VLOOKUP(C89,[2]IP!$B$9:$R$116,17,0) -> 0 | Y89: =+K89-O89-P89+Q89+R89+S89+T89+U89+V89+W89 -> #REF! | Z89: =+M89-Y89 -> #REF! | AB89: =VLOOKUP(C89,[1]SINDICATO!$C$7:$Q$141,15,0) -> #N/A
A90: SEI0415 | B90: SEITON (IP INNOVA II) | C90: Mireles Casillas Brenda Cristina | E90: =VLOOKUP(C90,[2]IP!$B$9:$V$116,21,0) -> 2237.8 | G90: =VLOOKUP(C90,#REF!,4,0) -> #REF! | H90: =VLOOKUP(C90,#REF!,5,0) -> #REF! | I90: =VLOOKUP(C90,#REF!,6,0) -> #REF! | K90: =+D90+E90+G90+H90+I90 -> #REF! | L90: 9000 | M90: =+L90/2 -> 4500 | O90: =VLOOKUP(C90,[2]IP!$B$9:$I$116,8,0) -> 0 | P90: =+H90+I90 -> #REF! | Q90: =VLOOKUP(C90,[2]IP!$B$9:$N$116,13,0) -> 0 | R90: =VLOOKUP(C90,[2]IP!$B$9:$O$116,14,0) -> 0 | T90: =VLOOKUP(C90,[2]IP!$B$9:$P$116,15,0) -> 0 | U90: =VLOOKUP(C90,[2]IP!$B$9:$Q$116,16,0) -> 0 | V90: =VLOOKUP(C90,[2]IP!$B$9:$S$116,18,0) -> 0 | W90: =VLOOKUP(C90,[2]IP!$B$9:$R$116,17,0) -> 0 | Y90: =+K90-O90-P90+Q90+R90+S90+T90+U90+V90+W90 -> #REF! | Z90: =+M90-Y90 -> #REF! | AB90: =VLOOKUP(C90,[1]SINDICATO!$C$7:$Q$141,15,0) -> #N/A
A91: SEI0033 | B91: SEITON (IP INNOVA II) | C91: Molina Ramirez Gerardo Daniel | E91: =VLOOKUP(C91,[2]IP!$B$9:$V$116,21,0) -> 1459.6 | G91: =VLOOKUP(C91,#REF!,4,0) -> #REF! | H91: =VLOOKUP(C91,#REF!,5,0) -> #REF! | I91: =VLOOKUP(C91,#REF!,6,0) -> #REF! | K91: =+D91+E91+G91+H91+I91 -> #REF! | L91: =VLOOKUP(C91,[1]ABC!$A$3:$B$88,2,0) -> 9000 | M91: =+L91/2 -> 4500 | O91: =VLOOKUP(C91,[2]IP!$B$9:$I$116,8,0) -> 0 | P91: =+H91+I91 -> #REF! | Q91: =VLOOKUP(C91,[2]IP!$B$9:$N$116,13,0) -> 0 | R91: =VLOOKUP(C91,[2]IP!$B$9:$O$116,14,0) -> 763.03 | T91: =VLOOKUP(C91,[2]IP!$B$9:$P$116,15,0) -> 15 | U91: =VLOOKUP(C91,[2]IP!$B$9:$Q$116,16,0) -> 0 | V91: =VLOOKUP(C91,[2]IP!$B$9:$S$116,18,0) -> 0 | W91: =VLOOKUP(C91,[2]IP!$B$9:$R$116,17,0) -> 0 | Y91: =+K91-O91-P91+Q91+R91+S91+T91+U91+V91+W91 -> #REF! | Z91: =+M91-Y91 -> #REF! | AB91: =VLOOKUP(C91,[1]SINDICATO!$C$7:$Q$141,15,0) -> #N/A
A92: SEI0095 | B92: SEITON (IP INNOVA II) | C92: Gutierrez Muñoz Carlos Alejandro | E92: =VLOOKUP(C92,[2]IP!$B$9:$V$116,21,0) -> 1065.8 | G92: =VLOOKUP(C92,#REF!,4,0) -> #REF! | H92: =VLOOKUP(C92,#REF!,5,0) -> #REF! | I92: =VLOOKUP(C92,#REF!,6,0) -> #REF! | K92: =+D92+E92+G92+H92+I92 -> #REF! | L92: =VLOOKUP(C92,[1]ABC!$A$3:$B$88,2,0) -> 12000 | M92: =+L92/2 -> 6000 | O92: =VLOOKUP(C92,[2]IP!$B$9:$I$116,8,0) -> 0 | P92: =+H92+I92 -> #REF! | Q92: =VLOOKUP(C92,[2]IP!$B$9:$N$116,13,0) -> 2034.26 | R92: =VLOOKUP(C92,[2]IP!$B$9:$O$116,14,0) -> 0 | T92: =VLOOKUP(C92,[2]IP!$B$9:$P$116,15,0) -> 15 | U92: =VLOOKUP(C92,[2]IP!$B$9:$Q$116,16,0) -> 0 | V92: =VLOOKUP(C92,[2]IP!$B$9:$S$116,18,0) -> 0 | W92: =VLOOKUP(C92,[2]IP!$B$9:$R$116,17,0) -> 0 | Y92: =+K92-O92-P92+Q92+R92+S92+T92+U92+V92+W92 -> #REF! | Z92: =+M92-Y92 -> #REF! | AB92: =VLOOKUP(C92,[1]SINDICATO!$C$7:$Q$141,15,0) -> #N/A
A93: SEI0096 | B93: SEITON (IP INNOVA II) | C93: Camarillo Canela Reynaldo | E93: =VLOOKUP(C93,[2]IP!$B$9:$V$116,21,0) -> 1314 | G93: =VLOOKUP(C93,#REF!,4,0) -> #REF! | H93: =VLOOKUP(C93,#REF!,5,0) -> #REF! | I93: =VLOOKUP(C93,#REF!,6,0) -> #REF! | K93: =+D93+E93+G93+H93+I93 -> #REF! | L93: =VLOOKUP(C93,[1]ABC!$A$3:$B$88,2,0) -> 9800 | M93: =+L93/2 -> 4900 | O93: =VLOOKUP(C93,[2]IP!$B$9:$I$116,8,0) -> 0 | P93: =+H93+I93 -> #REF! | Q93: =VLOOKUP(C93,[2]IP!$B$9:$N$116,13,0) -> 1366.67 | R93: =VLOOKUP(C93,[2]IP!$B$9:$O$116,14,0) -> 0 | T93: =VLOOKUP(C93,[2]IP!$B$9:$P$116,15,0) -> 0 | U93: =VLOOKUP(C93,[2]IP!$B$9:$Q$116,16,0) -> 0 | V93: =VLOOKUP(C93,[2]IP!$B$9:$S$116,18,0) -> 0 | W93: =VLOOKUP(C93,[2]IP!$B$9:$R$116,17,0) -> 0 | Y93: =+K93-O93-P93+Q93+R93+S93+T93+U93+V93+W93 -> #REF! | Z93: =+M93-Y93 -> #REF! | AB93: =VLOOKUP(C93,[1]SINDICATO!$C$7:$Q$141,15,0) -> 0
A94: SEI0416 | B94: SEITON (IP INNOVA II) | C94: Escobedo Olivares Juan Guadalupe | E94: =VLOOKUP(C94,[2]IP!$B$9:$V$116,21,0) -> 3278.8 | G94: =VLOOKUP(C94,#REF!,4,0) -> #REF! | H94: =VLOOKUP(C94,#REF!,5,0) -> #REF! | I94: =VLOOKUP(C94,#REF!,6,0) -> #REF! | K94: =+D94+E94+G94+H94+I94 -> #REF! | L94: 14000 | M94: =+L94/2 -> 7000 | O94: =VLOOKUP(C94,[2]IP!$B$9:$I$116,8,0) -> 0 | P94: =+H94+I94 -> #REF! | Q94: =VLOOKUP(C94,[2]IP!$B$9:$N$116,13,0) -> 0 | R94: =VLOOKUP(C94,[2]IP!$B$9:$O$116,14,0) -> 0 | T94: =VLOOKUP(C94,[2]IP!$B$9:$P$116,15,0) -> 0 | U94: =VLOOKUP(C94,[2]IP!$B$9:$Q$116,16,0) -> 0 | V94: =VLOOKUP(C94,[2]IP!$B$9:$S$116,18,0) -> 0 | W94: =VLOOKUP(C94,[2]IP!$B$9:$R$116,17,0) -> 0 | Y94: =+K94-O94-P94+Q94+R94+S94+T94+U94+V94+W94 -> #REF! | Z94: =+M94-Y94 -> #REF! | AB94: =VLOOKUP(C94,[1]SINDICATO!$C$7:$Q$141,15,0) -> #N/A
A95: SEI0417 | B95: SEITON (IP INNOVA II) | C95: Castillo Ramirez Hector Ivan | E95: =VLOOKUP(C95,[2]IP!$B$9:$V$116,21,0) -> 2727.8 | G95: =VLOOKUP(C95,#REF!,4,0) -> #REF! | H95: =VLOOKUP(C95,#REF!,5,0) -> #REF! | I95: =VLOOKUP(C95,#REF!,6,0) -> #REF! | K95: =+D95+E95+G95+H95+I95 -> #REF! | L95: 14000 | M95: =+L95/2 -> 7000 | O95: =VLOOKUP(C95,[2]IP!$B$9:$I$116,8,0) -> 0 | P95: =+H95+I95 -> #REF! | Q95: =VLOOKUP(C95,[2]IP!$B$9:$N$116,13,0) -> 0 | R95: =VLOOKUP(C95,[2]IP!$B$9:$O$116,14,0) -> 0 | T95: =VLOOKUP(C95,[2]IP!$B$9:$P$116,15,0) -> 0 | U95: =VLOOKUP(C95,[2]IP!$B$9:$Q$116,16,0) -> 0 | V95: =VLOOKUP(C95,[2]IP!$B$9:$S$116,18,0) -> 0 | W95: =VLOOKUP(C95,[2]IP!$B$9:$R$116,17,0) -> 550.83 | Y95: =+K95-O95-P95+Q95+R95+S95+T95+U95+V95+W95 -> #REF! | Z95: =+M95-Y95 -> #REF! | AB95: =VLOOKUP(C95,[1]SINDICATO!$C$7:$Q$141,15,0) -> #N/A
A96: SEI0420 | B96: SEITON (IP INNOVA II) | C96: Martinez Morales Tomas | E96: =VLOOKUP(C96,[2]IP!$B$9:$V$116,21,0) -> 1962.8 | G96: =VLOOKUP(C96,#REF!,4,0) -> #REF! | H96: =VLOOKUP(C96,#REF!,5,0) -> #REF! | I96: =VLOOKUP(C96,#REF!,6,0) -> #REF! | K96: =+D96+E96+G96+H96+I96 -> #REF! | L96: 15000 | M96: =+L96/2 -> 7500 | O96: =VLOOKUP(C96,[2]IP!$B$9:$I$116,8,0) -> 0 | P96: =+H96+I96 -> #REF! | Q96: =VLOOKUP(C96,[2]IP!$B$9:$N$116,13,0) -> 1881.2 | R96: =VLOOKUP(C96,[2]IP!$B$9:$O$116,14,0) -> 0 | T96: =VLOOKUP(C96,[2]IP!$B$9:$P$116,15,0) -> 15 | U96: =VLOOKUP(C96,[2]IP!$B$9:$Q$116,16,0) -> 0 | V96: =VLOOKUP(C96,[2]IP!$B$9:$S$116,18,0) -> 0 | W96: =VLOOKUP(C96,[2]IP!$B$9:$R$116,17,0) -> 301.5 | Y96: =+K96-O96-P96+Q96+R96+S96+T96+U96+V96+W96 -> #REF! | Z96: =+M96-Y96 -> #REF! | AB96: =VLOOKUP(C96,[1]SINDICATO!$C$7:$Q$141,15,0) -> #N/A
A97: SEI0421 | B97: SEITON (IP INNOVA II) | C97: Medellin Colunga Ruben Dario | E97: =VLOOKUP(C97,[2]IP!$B$9:$V$116,21,0) -> 1572.4 | G97: =VLOOKUP(C97,#REF!,4,0) -> #REF! | H97: =VLOOKUP(C97,#REF!,5,0) -> #REF! | I97: =VLOOKUP(C97,#REF!,6,0) -> #REF! | K97: =+D97+E97+G97+H97+I97 -> #REF! | L97: 17000 | M97: =+L97/2 -> 8500 | O97: =VLOOKUP(C97,[2]IP!$B$9:$I$116,8,0) -> 0 | P97: =+H97+I97 -> #REF! | Q97: =VLOOKUP(C97,[2]IP!$B$9:$N$116,13,0) -> 2177.34 | R97: =VLOOKUP(C97,[2]IP!$B$9:$O$116,14,0) -> 0 | T97: =VLOOKUP(C97,[2]IP!$B$9:$P$116,15,0) -> 15 | U97: =VLOOKUP(C97,[2]IP!$B$9:$Q$116,16,0) -> 0 | V97: =VLOOKUP(C97,[2]IP!$B$9:$S$116,18,0) -> 0 | W97: =VLOOKUP(C97,[2]IP!$B$9:$R$116,17,0) -> 395.82 | Y97: =+K97-O97-P97+Q97+R97+S97+T97+U97+V97+W97 -> #REF! | Z97: =+M97-Y97 -> #REF! | AB97: =VLOOKUP(C97,[1]SINDICATO!$C$7:$Q$141,15,0) -> #N/A
A98: SEI0422 | B98: SEITON (IP INNOVA II) | C98: Torres Perez Carlos Alberto | E98: =VLOOKUP(C98,[2]IP!$B$9:$V$116,21,0) -> 3079.2 | G98: =VLOOKUP(C98,#REF!,4,0) -> #REF! | H98: =VLOOKUP(C98,#REF!,5,0) -> #REF! | I98: =VLOOKUP(C98,#REF!,6,0) -> #REF! | K98: =+D98+E98+G98+H98+I98 -> #REF! | L98: 10500 | M98: =+L98/2 -> 5250 | O98: =VLOOKUP(C98,[2]IP!$B$9:$I$116,8,0) -> 0 | P98: =+H98+I98 -> #REF! | Q98: =VLOOKUP(C98,[2]IP!$B$9:$N$116,13,0) -> 0 | R98: =VLOOKUP(C98,[2]IP!$B$9:$O$116,14,0) -> 0 | T98: =VLOOKUP(C98,[2]IP!$B$9:$P$116,15,0) -> 0 | U98: =VLOOKUP(C98,[2]IP!$B$9:$Q$116,16,0) -> 0 | V98: =VLOOKUP(C98,[2]IP!$B$9:$S$116,18,0) -> 0 | W98: =VLOOKUP(C98,[2]IP!$B$9:$R$116,17,0) -> 253.5 | Y98: =+K98-O98-P98+Q98+R98+S98+T98+U98+V98+W98 -> #REF! | Z98: =+M98-Y98 -> #REF! | AB98: =VLOOKUP(C98,[1]SINDICATO!$C$7:$Q$141,15,0) -> #N/A
A99: SEI0424 | B99: SEITON (IP INNOVA II) | C99: Treviño Alvarez Jorge Alberto | E99: =VLOOKUP(C99,[2]IP!$B$9:$V$116,21,0) -> 1805.2 | G99: =VLOOKUP(C99,#REF!,4,0) -> #REF! | H99: =VLOOKUP(C99,#REF!,5,0) -> #REF! | I99: =VLOOKUP(C99,#REF!,6,0) -> #REF! | K99: =+D99+E99+G99+H99+I99 -> #REF! | L99: 12000 | M99: =+L99/2 -> 6000 | O99: =VLOOKUP(C99,[2]IP!$B$9:$I$116,8,0) -> 0 | P99: =+H99+I99 -> #REF! | Q99: =VLOOKUP(C99,[2]IP!$B$9:$N$116,13,0) -> 1202.43 | R99: =VLOOKUP(C99,[2]IP!$B$9:$O$116,14,0) -> 0 | T99: =VLOOKUP(C99,[2]IP!$B$9:$P$116,15,0) -> 15 | U99: =VLOOKUP(C99,[2]IP!$B$9:$Q$116,16,0) -> 0 | V99: =VLOOKUP(C99,[2]IP!$B$9:$S$116,18,0) -> 0 | W99: =VLOOKUP(C99,[2]IP!$B$9:$R$116,17,0) -> 310 | Y99: =+K99-O99-P99+Q99+R99+S99+T99+U99+V99+W99 -> #REF! | Z99: =+M99-Y99 -> #REF! | AB99: =VLOOKUP(C99,[1]SINDICATO!$C$7:$Q$141,15,0) -> #N/A
A100: SEI0425 | B100: SEITON (IP INNOVA II) | C100: Tenorio Alvarez Alberto Antonio | E100: =VLOOKUP(C100,[2]IP!$B$9:$V$116,21,0) -> 2195 | G100: =VLOOKUP(C100,#REF!,4,0) -> #REF! | H100: =VLOOKUP(C100,#REF!,5,0) -> #REF! | I100: =VLOOKUP(C100,#REF!,6,0) -> #REF! | K100: =+D100+E100+G100+H100+I100 -> #REF! | L100: 10000 | M100: =+L100/2 -> 5000 | O100: =VLOOKUP(C100,[2]IP!$B$9:$I$116,8,0) -> 0 | P100: =+H100+I100 -> #REF! | Q100: =VLOOKUP(C100,[2]IP!$B$9:$N$116,13,0) -> 0 | R100: =VLOOKUP(C100,[2]IP!$B$9:$O$116,14,0) -> 1122.63 | T100: =VLOOKUP(C100,[2]IP!$B$9:$P$116,15,0) -> 15 | U100: =VLOOKUP(C100,[2]IP!$B$9:$Q$116,16,0) -> 0 | V100: =VLOOKUP(C100,[2]IP!$B$9:$S$116,18,0) -> 0 | W100: =VLOOKUP(C100,[2]IP!$B$9:$R$116,17,0) -> 0 | Y100: =+K100-O100-P100+Q100+R100+S100+T100+U100+V100+W100 -> #REF! | Z100: =+M100-Y100 -> #REF! | AB100: =VLOOKUP(C100,[1]SINDICATO!$C$7:$Q$141,15,0) -> #N/A
A101: SEI0426 | B101: SEITON (IP INNOVA II) | C101: Chavez Dominguez Salvador | E101: =VLOOKUP(C101,[2]IP!$B$9:$V$116,21,0) -> 3332.6 | G101: =VLOOKUP(C101,#REF!,4,0) -> #REF! | H101: =VLOOKUP(C101,#REF!,5,0) -> #REF! | I101: =VLOOKUP(C101,#REF!,6,0) -> #REF! | K101: =+D101+E101+G101+H101+I101 -> #REF! | L101: 12000 | M101: =+L101/2 -> 6000 | O101: =VLOOKUP(C101,[2]IP!$B$9:$I$116,8,0) -> 0 | P101: =+H101+I101 -> #REF! | Q101: =VLOOKUP(C101,[2]IP!$B$9:$N$116,13,0) -> 0 | R101: =VLOOKUP(C101,[2]IP!$B$9:$O$116,14,0) -> 0 | T101: =VLOOKUP(C101,[2]IP!$B$9:$P$116,15,0) -> 0 | U101: =VLOOKUP(C101,[2]IP!$B$9:$Q$116,16,0) -> 0 | V101: =VLOOKUP(C101,[2]IP!$B$9:$S$116,18,0) -> 0 | W101: =VLOOKUP(C101,[2]IP!$B$9:$R$116,17,0) -> 0 | Y101: =+K101-O101-P101+Q101+R101+S101+T101+U101+V101+W101 -> #REF! | Z101: =+M101-Y101 -> #REF! | AB101: =VLOOKUP(C101,[1]SINDICATO!$C$7:$Q$141,15,0) -> #N/A
...

Sheet RESUMEN PITS
A2: SUELDOS Y SALARIOS | G2: SINDICATO | K2: NETOS | O2: EXTRAS
A3: CLAVE | B3: EMPRESA | C3: NOMBRE | D3: NETO CPD | E3: NETO IP | F3: A | G3: PAGO SINDICATO | H3: COMISION | I3: PRIMA VACACIONAL SINDICATO | J3: B | K3: NETO A PAGAR | L3: NETO MENSUAL | M3: NETO QUINCENAL SEITON | N3: C | O3: prima vacacional | P3: COMISION Y PRIMA VACACIONAL | Q3: INFONAVIT | R3: INFONAVIT | S3: INFONAVIT | T3: INFONAVIT | U3: PRESTAMO | V3: APORTACION | W3: DESCUENTOS | X3: D | Y3: TOTAL GENERAL | Z3: DIFERENCIAS | AA3: OBSERVACIONES | AB3: CC
A4: SEI0009 | B4: SEITON - (CONSULTORIA II) | C4: Gutierrez Gutierrez Luis Arturo | D4: =VLOOKUP(C4,'CPD PITS'!$B$9:$Y$27,24,0) -> 2774.6 | G4: =VLOOKUP(C4,'SIND PITS'!$C$7:$D$106,2,0) -> 1475.4 | H4: =VLOOKUP(C4,'SIND PITS'!$C$7:$E$106,3,0) -> 0 | I4: =VLOOKUP(C4,'SIND PITS'!$C$7:$F$105,4,0) -> 0 | K4: =+D4+E4+G4+H4+I4 -> 4250 | L4: 8500 | M4: 4250 | O4: =VLOOKUP(C4,'CPD PITS'!$B$9:$I$27,8,0) -> 0 | P4: =+H4+I4 -> 0 | Q4: =VLOOKUP(C4,'CPD PITS'!$B$9:$R$27,17,0) -> 0 | R4: =VLOOKUP(C4,'CPD PITS'!$B$9:$Q$27,16,0) -> 0 | S4: 0 | T4: =VLOOKUP(C4,'CPD PITS'!$B$9:$T$27,19,0) -> 0 | W4: =VLOOKUP(C4,'CPD PITS'!$B$9:$V$27,21,0) -> 0 | Y4: =+K4-O4-P4+Q4+R4+S4+T4+U4+V4+W4 -> 4250 | Z4: =+M4-Y4 -> 0 | AB4: PITS
A5: SEI0026 | B5: SEITON - (CONSULTORIA II) | C5: Patricio Aguilar Jhonattan Cristian | D5: =VLOOKUP(C5,'CPD PITS'!$B$9:$Y$27,24,0) -> 2911.8 | G5: =VLOOKUP(C5,'SIND PITS'!$C$7:$D$106,2,0) -> 1588.2 | H5: =VLOOKUP(C5,'SIND PITS'!$C$7:$E$106,3,0) -> 375 | I5: =VLOOKUP(C5,'SIND PITS'!$C$7:$F$105,4,0) -> 0 | K5: =+D5+E5+G5+H5+I5 -> 4875 | L5: 9000 | M5: 4500 | O5: =VLOOKUP(C5,'CPD PITS'!$B$9:$I$27,8,0) -> 0 | P5: =+H5+I5 -> 375 | Q5: =VLOOKUP(C5,'CPD PITS'!$B$9:$R$27,17,0) -> 0 | R5: =VLOOKUP(C5,'CPD PITS'!$B$9:$Q$27,16,0) -> 0 | S5: 0 | T5: =VLOOKUP(C5,'CPD PITS'!$B$9:$T$27,19,0) -> 0 | W5: =VLOOKUP(C5,'CPD PITS'!$B$9:$V$27,21,0) -> 0 | Y5: =+K5-O5-P5+Q5+R5+S5+T5+U5+V5+W5 -> 4500 | Z5: =+M5-Y5 -> 0 | AB5: PITS
A6: SEI0040 | B6: SEITON - (CONSULTORIA II) | C6: Mora Ramirez Acal Aldo Isidro | D6: =VLOOKUP(C6,'CPD PITS'!$B$9:$Y$27,24,0) -> 4036 | G6: =VLOOKUP(C6,'SIND PITS'!$C$7:$D$106,2,0) -> 2464 | H6: =VLOOKUP(C6,'SIND PITS'!$C$7:$E$106,3,0) -> 1000 | I6: =VLOOKUP(C6,'SIND PITS'!$C$7:$F$105,4,0) -> 0 | K6: =+D6+E6+G6+H6+I6 -> 7500 | L6: 13000 | M6: 6500 | O6: =VLOOKUP(C6,'CPD PITS'!$B$9:$I$27,8,0) -> 0 | P6: =+H6+I6 -> 1000 | Q6: =VLOOKUP(C6,'CPD PITS'!$B$9:$R$27,17,0) -> 0 | R6: =VLOOKUP(C6,'CPD PITS'!$B$9:$Q$27,16,0) -> 0 | S6: 0 | T6: =VLOOKUP(C6,'CPD PITS'!$B$9:$T$27,19,0) -> 0 | W6: =VLOOKUP(C6,'CPD PITS'!$B$9:$V$27,21,0) -> 0 | Y6: =+K6-O6-P6+Q6+R6+S6+T6+U6+V6+W6 -> 6500 | Z6: =+M6-Y6 -> 0 | AB6: PITS
A7: SEI0041 | B7: SEITON - (CONSULTORIA II) | C7: Vazquez Perez Miguel Angel | D7: =VLOOKUP(C7,'CPD PITS'!$B$9:$Y$27,24,0) -> 5074 | G7: =VLOOKUP(C7,'SIND PITS'!$C$7:$D$106,2,0) -> 4176 | H7: =VLOOKUP(C7,'SIND PITS'!$C$7:$E$106,3,0) -> 750 | I7: =VLOOKUP(C7,'SIND PITS'!$C$7:$F$105,4,0) -> 0 | K7: =+D7+E7+G7+H7+I7 -> 10000 | L7: 18500 | M7: 9250 | O7: =VLOOKUP(C7,'CPD PITS'!$B$9:$I$27,8,0) -> 0 | P7: =+H7+I7 -> 750 | Q7: =VLOOKUP(C7,'CPD PITS'!$B$9:$R$27,17,0) -> 0 | R7: =VLOOKUP(C7,'CPD PITS'!$B$9:$Q$27,16,0) -> 0 | S7: 0 | T7: =VLOOKUP(C7,'CPD PITS'!$B$9:$T$27,19,0) -> 0 | W7: =VLOOKUP(C7,'CPD PITS'!$B$9:$V$27,21,0) -> 0 | Y7: =+K7-O7-P7+Q7+R7+S7+T7+U7+V7+W7 -> 9250 | Z7: =+M7-Y7 -> 0 | AB7: PITS
A8: SEI0088 | B8: SEITON - (CONSULTORIA II) | C8: Morgado Fernandez Martin | D8: =VLOOKUP(C8,'CPD PITS'!$B$9:$Y$27,24,0) -> 4899.6 | G8: =VLOOKUP(C8,'SIND PITS'!$C$7:$D$106,2,0) -> 2600.4 | H8: =VLOOKUP(C8,'SIND PITS'!$C$7:$E$106,3,0) -> 1121.5 | I8: =VLOOKUP(C8,'SIND PITS'!$C$7:$F$105,4,0) -> 0 | K8: =+D8+E8+G8+H8+I8 -> 8621.5 | L8: 15000 | M8: 7500 | O8: =VLOOKUP(C8,'CPD PITS'!$B$9:$I$27,8,0) -> 0 | P8: =+H8+I8 -> 1121.5 | Q8: =VLOOKUP(C8,'CPD PITS'!$B$9:$R$27,17,0) -> 0 | R8: =VLOOKUP(C8,'CPD PITS'!$B$9:$Q$27,16,0) -> 0 | S8: 0 | T8: =VLOOKUP(C8,'CPD PITS'!$B$9:$T$27,19,0) -> 0 | W8: =VLOOKUP(C8,'CPD PITS'!$B$9:$V$27,21,0) -> 0 | Y8: =+K8-O8-P8+Q8+R8+S8+T8+U8+V8+W8 -> 7500 | Z8: =+M8-Y8 -> 0 | AB8: PITS
A9: SEI0097 | B9: SEITON - (CONSULTORIA II) | C9: Arreola Jimenez Jose Nieves | D9: =VLOOKUP(C9,'CPD PITS'!$B$9:$Y$27,24,0) -> 1927.6 | G9: =VLOOKUP(C9,'SIND PITS'!$C$7:$D$106,2,0) -> 1558.11 | H9: =VLOOKUP(C9,'SIND PITS'!$C$7:$E$106,3,0) -> 501 | I9: =VLOOKUP(C9,'SIND PITS'!$C$7:$F$105,4,0) -> 0 | K9: =+D9+E9+G9+H9+I9 -> 3986.71 | L9: 10150 | M9: 5075 | O9: =VLOOKUP(C9,'CPD PITS'!$B$9:$I$27,8,0) -> 0 | P9: =+H9+I9 -> 501 | Q9: =VLOOKUP(C9,'CPD PITS'!$B$9:$R$27,17,0) -> 1574.29 | R9: =VLOOKUP(C9,'CPD PITS'!$B$9:$Q$27,16,0) -> 0 | S9: 0 | T9: =VLOOKUP(C9,'CPD PITS'!$B$9:$T$27,19,0) -> 15 | W9: =VLOOKUP(C9,'CPD PITS'!$B$9:$V$27,21,0) -> 0 | Y9: =+K9-O9-P9+Q9+R9+S9+T9+U9+V9+W9 -> 5075 | Z9: =+M9-Y9 -> 0 | AB9: PITS
A10: SEI0099 | B10: SEITON - (CONSULTORIA II) | C10: Garcia Villicaña Ricardo Pascual | D10: =VLOOKUP(C10,'CPD PITS'!$B$9:$Y$27,24,0) -> 4899.8 | G10: =VLOOKUP(C10,'SIND PITS'!$C$7:$D$106,2,0) -> 2600.2 | H10: =VLOOKUP(C10,'SIND PITS'!$C$7:$E$106,3,0) -> 216.5 | I10: =VLOOKUP(C10,'SIND PITS'!$C$7:$F$105,4,0) -> 0 | K10: =+D10+E10+G10+H10+I10 -> 7716.5 | L10: 15000 | M10: 7500 | O10: =VLOOKUP(C10,'CPD PITS'!$B$9:$I$27,8,0) -> 0 | P10: =+H10+I10 -> 216.5 | Q10: =VLOOKUP(C10,'CPD PITS'!$B$9:$R$27,17,0) -> 0 | R10: =VLOOKUP(C10,'CPD PITS'!$B$9:$Q$27,16,0) -> 0 | S10: 0 | T10: =VLOOKUP(C10,'CPD PITS'!$B$9:$T$27,19,0) -> 0 | W10: =VLOOKUP(C10,'CPD PITS'!$B$9:$V$27,21,0) -> 0 | Y10: =+K10-O10-P10+Q10+R10+S10+T10+U10+V10+W10 -> 7500 | Z10: =+M10-Y10 -> 0 | AB10: PITS
A11: SEI0108 | B11: SEITON - (CONSULTORIA II) | C11: Caballero Diaz Francisco Javier | D11: =VLOOKUP(C11,'CPD PITS'!$B$9:$Y$27,24,0) -> 1675.4 | G11: =VLOOKUP(C11,'SIND PITS'!$C$7:$D$106,2,0) -> 1558.09 | H11: =VLOOKUP(C11,'SIND PITS'!$C$7:$E$106,3,0) -> 1066 | I11: =VLOOKUP(C11,'SIND PITS'!$C$7:$F$105,4,0) -> 0 | K11: =+D11+E11+G11+H11+I11 -> 4299.49 | L11: 10150 | M11: 5075 | O11: =VLOOKUP(C11,'CPD PITS'!$B$9:$I$27,8,0) -> 0 | P11: =+H11+I11 -> 1066 | Q11: =VLOOKUP(C11,'CPD PITS'!$B$9:$R$27,17,0) -> 1826.51 | R11: =VLOOKUP(C11,'CPD PITS'!$B$9:$Q$27,16,0) -> 0 | S11: 0 | T11: =VLOOKUP(C11,'CPD PITS'!$B$9:$T$27,19,0) -> 15 | W11: =VLOOKUP(C11,'CPD PITS'!$B$9:$V$27,21,0) -> 0 | Y11: =+K11-O11-P11+Q11+R11+S11+T11+U11+V11+W11 -> 5075 | Z11: =+M11-Y11 -> 0 | AB11: PITS
A12: SEI0116 | B12: SEITON - (CONSULTORIA II) | C12: Casillas Cardona Cesar Alejandro | D12: =VLOOKUP(C12,'CPD PITS'!$B$9:$Y$27,24,0) -> 3336.6 | G12: =VLOOKUP(C12,'SIND PITS'!$C$7:$D$106,2,0) -> 1891.08 | H12: =VLOOKUP(C12,'SIND PITS'!$C$7:$E$106,3,0) -> 0 | I12: =VLOOKUP(C12,'SIND PITS'!$C$7:$F$105,4,0) -> 0 | K12: =+D12+E12+G12+H12+I12 -> 5227.68 | L12: 12000 | M12: 6000 | O12: =VLOOKUP(C12,'CPD PITS'!$B$9:$I$27,8,0) -> 0 | P12: =+H12+I12 -> 0 | Q12: =VLOOKUP(C12,'CPD PITS'!$B$9:$R$27,17,0) -> 757.32 | R12: =VLOOKUP(C12,'CPD PITS'!$B$9:$Q$27,16,0) -> 0 | S12: 0 | T12: =VLOOKUP(C12,'CPD PITS'!$B$9:$T$27,19,0) -> 15 | W12: =VLOOKUP(C12,'CPD PITS'!$B$9:$V$27,21,0) -> 0 | Y12: =+K12-O12-P12+Q12+R12+S12+T12+U12+V12+W12 -> 6000 | Z12: =+M12-Y12 -> 0 | AB12: PITS
A13: SEI0117 | B13: SEITON - (CONSULTORIA II) | C13: Mariscal Romero Luis Adrian | D13: =VLOOKUP(C13,'CPD PITS'!$B$9:$Y$27,24,0) -> 3060 | G13: =VLOOKUP(C13,'SIND PITS'!$C$7:$D$106,2,0) -> 2751 | H13: =VLOOKUP(C13,'SIND PITS'!$C$7:$E$106,3,0) -> 250 | I13: =VLOOKUP(C13,'SIND PITS'!$C$7:$F$105,4,0) -> 0 | K13: =+D13+E13+G13+H13+I13 -> 6061 | L13: 15000 | M13: 7500 | O13: =VLOOKUP(C13,'CPD PITS'!$B$9:$I$27,8,0) -> 0 | P13: =+H13+I13 -> 250 | Q13: =VLOOKUP(C13,'CPD PITS'!$B$9:$R$27,17,0) -> 1674 | R13: =VLOOKUP(C13,'CPD PITS'!$B$9:$Q$27,16,0) -> 0 | S13: 0 | T13: =VLOOKUP(C13,'CPD PITS'!$B$9:$T$27,19,0) -> 15 | W13: =VLOOKUP(C13,'CPD PITS'!$B$9:$V$27,21,0) -> 0 | Y13: =+K13-O13-P13+Q13+R13+S13+T13+U13+V13+W13 -> 7500 | Z13: =+M13-Y13 -> 0 | AB13: PITS
A14: SEI0118 | B14: SEITON - (CONSULTORIA II) | C14: Arroyo Ramirez Hector Hugo | D14: =VLOOKUP(C14,'CPD PITS'!$B$9:$Y$27,24,0) -> 2967.4 | G14: =VLOOKUP(C14,'SIND PITS'!$C$7:$D$106,2,0) -> 2102.84 | H14: =VLOOKUP(C14,'SIND PITS'!$C$7:$E$106,3,0) -> 0 | I14: =VLOOKUP(C14,'SIND PITS'!$C$7:$F$105,4,0) -> 234.01 | K14: =+D14+E14+G14+H14+I14 -> 5304.25 | L14: 13000 | M14: 6500 | O14: =VLOOKUP(C14,'CPD PITS'!$B$9:$I$27,8,0) -> 285.99 | P14: =+H14+I14 -> 234.01 | Q14: =VLOOKUP(C14,'CPD PITS'!$B$9:$R$27,17,0) -> 1432.4 | R14: =VLOOKUP(C14,'CPD PITS'!$B$9:$Q$27,16,0) -> 0 | S14: 0 | T14: =VLOOKUP(C14,'CPD PITS'!$B$9:$T$27,19,0) -> 15 | W14: =VLOOKUP(C14,'CPD PITS'!$B$9:$V$27,21,0) -> 268.35 | Y14: =+K14-O14-P14+Q14+R14+S14+T14+U14+V14+W14 -> 6500 | Z14: =+M14-Y14 -> 0 | AB14: PITS
A15: SEI0127 | B15: SEITON - (CONSULTORIA II) | C15: Hernandez Ochoa Eduardo | D15: =VLOOKUP(C15,'CPD PITS'!$B$9:$Y$27,24,0) -> 4899.8 | G15: =VLOOKUP(C15,'SIND PITS'!$C$7:$D$106,2,0) -> 2600.2 | H15: =VLOOKUP(C15,'SIND PITS'!$C$7:$E$106,3,0) -> 2068 | I15: =VLOOKUP(C15,'SIND PITS'!$C$7:$F$105,4,0) -> 0 | K15: =+D15+E15+G15+H15+I15 -> 9568 | L15: 15000 | M15: 7500 | O15: =VLOOKUP(C15,'CPD PITS'!$B$9:$I$27,8,0) -> 0 | P15: =+H15+I15 -> 2068 | Q15: =VLOOKUP(C15,'CPD PITS'!$B$9:$R$27,17,0) -> 0 | R15: =VLOOKUP(C15,'CPD PITS'!$B$9:$Q$27,16,0) -> 0 | S15: 0 | T15: =VLOOKUP(C15,'CPD PITS'!$B$9:$T$27,19,0) -> 0 | W15: =VLOOKUP(C15,'CPD PITS'!$B$9:$V$27,21,0) -> 0 | Y15: =+K15-O15-P15+Q15+R15+S15+T15+U15+V15+W15 -> 7500 | Z15: =+M15-Y15 -> 0 | AB15: PITS
... A22: SEI0445 | B22: SEITON - (CONSULTORIA II) | C22: Muñoz Melgoza Gabriel | D22: =VLOOKUP(C22,'CPD PITS'!$B$9:$Y$27,24,0) -> 4609.4 | G22: =VLOOKUP(C22,'SIND PITS'!$C$7:$D$106,2,0) -> 3090.6 | H22: =VLOOKUP(C22,'SIND PITS'!$C$7:$E$106,3,0) -> 250 | I22: =VLOOKUP(C22,'SIND PITS'!$C$7:$F$105,4,0) -> 0 | K22: =+D22+E22+G22+H22+I22 -> 7950 | L22: 15400 | M22: 7700 | O22: =VLOOKUP(C22,'CPD PITS'!$B$9:$I$27,8,0) -> 0 | P22: =+H22+I22 -> 250 | Q22: =VLOOKUP(C22,'CPD PITS'!$B$9:$R$27,17,0) -> 0 | R22: =VLOOKUP(C22,'CPD PITS'!$B$9:$Q$27,16,0) -> 0 | S22: 0 | T22: =VLOOKUP(C22,'CPD PITS'!$B$9:$T$27,19,0) -> 0 | W22: =VLOOKUP(C22,'CPD PITS'!$B$9:$V$27,21,0) -> 0 | Y22: =+K22-O22-P22+Q22+R22+S22+T22+U22+V22+W22 -> 7700 | Z22: =+M22-Y22 -> 0 | AB22: PITS
A23: SEI0010 | B23: SEITON (IP INNOVA II) | C23: Torres Ricardez Alfredo | E23: =VLOOKUP(C23,'IP PITS'!$B$9:$V$90,21,0) -> 3585.4 | G23: =VLOOKUP(C23,'SIND PITS'!$C$7:$D$106,2,0) -> 414.6 | H23: =VLOOKUP(C23,'SIND PITS'!$C$7:$E$106,3,0) -> 258.5 | I23: =VLOOKUP(C23,'SIND PITS'!$C$7:$F$105,4,0) -> 0 | K23: =+D23+E23+G23+H23+I23 -> 4258.5 | L23: 8000 | M23: 4000 | O23: =VLOOKUP(C23,'IP PITS'!$B$9:$I$90,8,0) -> 0 | P23: =+H23+I23 -> 258.5 | Q23: =VLOOKUP(C23,'IP PITS'!$B$9:$N$90,13,0) -> 0 | R23: =VLOOKUP(C23,'IP PITS'!$B$9:$O$90,14,0) -> 0 | T23: =VLOOKUP(C23,'IP PITS'!$B$9:$P$90,15,0) -> 0 | U23: =VLOOKUP(C23,'IP PITS'!$B$9:$Q$90,16,0) -> 0 | V23: 0 | W23: =VLOOKUP(C23,'IP PITS'!$B$9:$R$90,17,0) -> 0 | Y23: =+K23-O23-P23+Q23+R23+S23+T23+U23+V23+W23 -> 4000 | Z23: =+M23-Y23 -> 0 | AB23: PITS
A24: SEI0014 | B24: SEITON (IP INNOVA II) | C24: Montoya Portillo Carlos Alberto | E24: =VLOOKUP(C24,'IP PITS'!$B$9:$V$90,21,0) -> 3585.2 | G24: =VLOOKUP(C24,'SIND PITS'!$C$7:$D$106,2,0) -> 414.8 | H24: =VLOOKUP(C24,'SIND PITS'!$C$7:$E$106,3,0) -> 121.5 | I24: =VLOOKUP(C24,'SIND PITS'!$C$7:$F$105,4,0) -> 0 | K24: =+D24+E24+G24+H24+I24 -> 4121.5 | L24: 8000 | M24: 4000 | O24: =VLOOKUP(C24,'IP PITS'!$B$9:$I$90,8,0) -> 0 | P24: =+H24+I24 -> 121.5 | Q24: =VLOOKUP(C24,'IP PITS'!$B$9:$N$90,13,0) -> 0 | R24: =VLOOKUP(C24,'IP PITS'!$B$9:$O$90,14,0) -> 0 | T24: =VLOOKUP(C24,'IP PITS'!$B$9:$P$90,15,0) -> 0 | U24: =VLOOKUP(C24,'IP PITS'!$B$9:$Q$90,16,0) -> 0 | V24: 0 | W24: =VLOOKUP(C24,'IP PITS'!$B$9:$R$90,17,0) -> 0 | Y24: =+K24-O24-P24+Q24+R24+S24+T24+U24+V24+W24 -> 4000 | Z24: =+M24-Y24 -> 0 | AB24: PITS
A25: SEI0017 | B25: SEITON (IP INNOVA II) | C25: Muñoz Reyes Luis Eduardo | E25: =VLOOKUP(C25,'IP PITS'!$B$9:$V$90,21,0) -> 2692.8 | G25: =VLOOKUP(C25,'SIND PITS'!$C$7:$D$106,2,0) -> 414.61 | H25: =VLOOKUP(C25,'SIND PITS'!$C$7:$E$106,3,0) -> 358.5 | I25: =VLOOKUP(C25,'SIND PITS'!$C$7:$F$105,4,0) -> 0 | K25: =+D25+E25+G25+H25+I25 -> 3465.91 | L25: 8000 | M25: 4000 | O25: =VLOOKUP(C25,'IP PITS'!$B$9:$I$90,8,0) -> 0 | P25: =+H25+I25 -> 358.5 | Q25: =VLOOKUP(C25,'IP PITS'!$B$9:$N$90,13,0) -> 877.59 | R25: =VLOOKUP(C25,'IP PITS'!$B$9:$O$90,14,0) -> 0 | T25: =VLOOKUP(C25,'IP PITS'!$B$9:$P$90,15,0) -> 15 | U25: =VLOOKUP(C25,'IP PITS'!$B$9:$Q$90,16,0) -> 0 | V25: 0 | W25: =VLOOKUP(C25,'IP PITS'!$B$9:$R$90,17,0) -> 0 | Y25: =+K25-O25-P25+Q25+R25+S25+T25+U25+V25+W25 -> 4000 | Z25: =+M25-Y25 -> 0 | AB25: PITS
A26: SEI0019 | B26: SEITON (IP INNOVA II) | C26: Gonzalez Rasgado Miguel Isaias | E26: =VLOOKUP(C26,'IP PITS'!$B$9:$V$90,21,0) -> 5195.2 | G26: =VLOOKUP(C26,'SIND PITS'!$C$7:$D$106,2,0) -> 804.8 | H26: =VLOOKUP(C26,'SIND PITS'!$C$7:$E$106,3,0) -> 2417.5 | I26: =VLOOKUP(C26,'SIND PITS'!$C$7:$F$105,4,0) -> 0 | K26: =+D26+E26+G26+H26+I26 -> 8417.5 | L26: 12000 | M26: 6000 | O26: =VLOOKUP(C26,'IP PITS'!$B$9:$I$90,8,0) -> 0 | P26: =+H26+I26 -> 2417.5 | Q26: =VLOOKUP(C26,'IP PITS'!$B$9:$N$90,13,0) -> 0 | R26: =VLOOKUP(C26,'IP PITS'!$B$9:$O$90,14,0) -> 0 | T26: =VLOOKUP(C26,'IP PITS'!$B$9:$P$90,15,0) -> 0 | U26: =VLOOKUP(C26,'IP PITS'!$B$9:$Q$90,16,0) -> 0 | V26: 0 | W26: =VLOOKUP(C26,'IP PITS'!$B$9:$R$90,17,0) -> 0 | Y26: =+K26-O26-P26+Q26+R26+S26+T26+U26+V26+W26 -> 6000 | Z26: =+M26-Y26 -> 0 | AB26: PITS
A27: SEI0020 | B27: SEITON (IP INNOVA II) | C27: Mar Marquez Cesar Eduardo | E27: =VLOOKUP(C27,'IP PITS'!$B$9:$V$90,21,0) -> 3585.4 | G27: =VLOOKUP(C27,'SIND PITS'!$C$7:$D$106,2,0) -> 414.6 | H27: =VLOOKUP(C27,'SIND PITS'!$C$7:$E$106,3,0) -> 168.5 | I27: =VLOOKUP(C27,'SIND PITS'!$C$7:$F$105,4,0) -> 0 | K27: =+D27+E27+G27+H27+I27 -> 4168.5 | L27: 8000 | M27: 4000 | O27: =VLOOKUP(C27,'IP PITS'!$B$9:$I$90,8,0) -> 0 | P27: =+H27+I27 -> 168.5 | Q27: =VLOOKUP(C27,'IP PITS'!$B$9:$N$90,13,0) -> 0 | R27: =VLOOKUP(C27,'IP PITS'!$B$9:$O$90,14,0) -> 0 | T27: =VLOOKUP(C27,'IP PITS'!$B$9:$P$90,15,0) -> 0 | U27: =VLOOKUP(C27,'IP PITS'!$B$9:$Q$90,16,0) -> 0 | V27: 0 | W27: =VLOOKUP(C27,'IP PITS'!$B$9:$R$90,17,0) -> 0 | Y27: =+K27-O27-P27+Q27+R27+S27+T27+U27+V27+W27 -> 4000 | Z27: =+M27-Y27 -> 0 | AB27: PITS
A28: SEI0021 | B28: SEITON (IP INNOVA II) | C28: Velez Rodriguez Jaime | E28: =VLOOKUP(C28,'IP PITS'!$B$9:$V$90,21,0) -> 1490.6 | G28: =VLOOKUP(C28,'SIND PITS'!$C$7:$D$106,2,0) -> 1135.17 | H28: =VLOOKUP(C28,'SIND PITS'!$C$7:$E$106,3,0) -> 0 | I28: 0 | K28: =+D28+E28+G28+H28+I28 -> 2625.77 | L28: 8000 | M28: 4000 | O28: =VLOOKUP(C28,'IP PITS'!$B$9:$I$90,8,0) -> 0 | P28: =+H28+I28 -> 0 | Q28: =VLOOKUP(C28,'IP PITS'!$B$9:$N$90,13,0) -> 1359.23 | R28: =VLOOKUP(C28,'IP PITS'!$B$9:$O$90,14,0) -> 0 | T28: =VLOOKUP(C28,'IP PITS'!$B$9:$P$90,15,0) -> 15 | U28: =VLOOKUP(C28,'IP PITS'!$B$9:$Q$90,16,0) -> 0 | V28: 0 | W28: =VLOOKUP(C28,'IP PITS'!$B$9:$R$90,17,0) -> 0 | Y28: =+K28-O28-P28+Q28+R28+S28+T28+U28+V28+W28 -> 4000 | Z28: =+M28-Y28 -> 0 | AB28: PITS
A29: SEI0022 | B29: SEITON (IP INNOVA II) | C29: Najera Lopez Raul | E29: =VLOOKUP(C29,'IP PITS'!$B$9:$V$90,21,0) -> 4406.4 | G29: =VLOOKUP(C29,'SIND PITS'!$C$7:$D$106,2,0) -> 593.6 | H29: =VLOOKUP(C29,'SIND PITS'!$C$7:$E$106,3,0) -> 121.5 | I29: =VLOOKUP(C29,'SIND PITS'!$C$7:$F$105,4,0) -> 0 | K29: =+D29+E29+G29+H29+I29 -> 5121.5 | L29: 10000 | M29: 5000 | O29: =VLOOKUP(C29,'IP PITS'!$B$9:$I$90,8,0) -> 0 | P29: =+H29+I29 -> 121.5 | Q29: =VLOOKUP(C29,'IP PITS'!$B$9:$N$90,13,0) -> 0 | R29: =VLOOKUP(C29,'IP PITS'!$B$9:$O$90,14,0) -> 0 | T29: =VLOOKUP(C29,'IP PITS'!$B$9:$P$90,15,0) -> 0 | U29: =VLOOKUP(C29,'IP PITS'!$B$9:$Q$90,16,0) -> 0 | V29: 0 | W29: =VLOOKUP(C29,'IP PITS'!$B$9:$R$90,17,0) -> 0 | Y29: =+K29-O29-P29+Q29+R29+S29+T29+U29+V29+W29 -> 5000 | Z29: =+M29-Y29 -> 0 | AB29: PITS
A30: SEI0023 | B30: SEITON (IP INNOVA II) | C30: Puente Murguia Luis Felipe | E30: =VLOOKUP(C30,'IP PITS'!$B$9:$V$90,21,0) -> 3277.4 | G30: =VLOOKUP(C30,'SIND PITS'!$C$7:$D$106,2,0) -> 222.6 | H30: =VLOOKUP(C30,'SIND PITS'!$C$7:$E$106,3,0) -> 253.25 | I30: =VLOOKUP(C30,'SIND PITS'!$C$7:$F$105,4,0) -> 0 | K30: =+D30+E30+G30+H30+I30 -> 3753.25 | L30: 7000 | M30: 3500 | O30: =VLOOKUP(C30,'IP PITS'!$B$9:$I$90,8,0) -> 0 | P30: =+H30+I30 -> 253.25 | Q30: =VLOOKUP(C30,'IP PITS'!$B$9:$N$90,13,0) -> 0 | R30: =VLOOKUP(C30,'IP PITS'!$B$9:$O$90,14,0) -> 0 | T30: =VLOOKUP(C30,'IP PITS'!$B$9:$P$90,15,0) -> 0 | U30: =VLOOKUP(C30,'IP PITS'!$B$9:$Q$90,16,0) -> 0 | V30: 0 | W30: =VLOOKUP(C30,'IP PITS'!$B$9:$R$90,17,0) -> 0 | Y30: =+K30-O30-P30+Q30+R30+S30+T30+U30+V30+W30 -> 3500 | Z30: =+M30-Y30 -> 0 | AB30: PITS
A31: SEI0029 | B31: SEITON (IP INNOVA II) | C31: Arceo Garcia Manuel Federico | E31: =VLOOKUP(C31,'IP PITS'!$B$9:$V$90,21,0) -> 2090.2 | G31: =VLOOKUP(C31,'SIND PITS'!$C$7:$D$106,2,0) -> 109.8 | H31: =VLOOKUP(C31,'SIND PITS'!$C$7:$E$106,3,0) -> 487.5 | I31: =VLOOKUP(C31,'SIND PITS'!$C$7:$F$105,4,0) -> 0 | K31: =+D31+E31+G31+H31+I31 -> 2687.5 | L31: 6000 | M31: 3000 | O31: =VLOOKUP(C31,'IP PITS'!$B$9:$I$90,8,0) -> 0 | P31: =+H31+I31 -> 487.5 | Q31: =VLOOKUP(C31,'IP PITS'!$B$9:$N$90,13,0) -> 0 | R31: =VLOOKUP(C31,'IP PITS'!$B$9:$O$90,14,0) -> 0 | T31: =VLOOKUP(C31,'IP PITS'!$B$9:$P$90,15,0) -> 0 | U31: =VLOOKUP(C31,'IP PITS'!$B$9:$Q$90,16,0) -> 600 | V31: 0 | W31: =VLOOKUP(C31,'IP PITS'!$B$9:$R$90,17,0) -> 0 | Y31: =+K31-O31-P31+Q31+R31+S31+T31+U31+V31+W31 -> 2800 | Z31: =+M31-Y31 -> 200 | AA31: falta | AB31: PITS
A32: SEI0364 | B32: SEITON (IP INNOVA II) | C32: Dominguez Lopez Mayeli Del Pilar | E32: =VLOOKUP(C32,'IP PITS'!$B$9:$V$90,21,0) -> 1917 | G32: =VLOOKUP(C32,'SIND PITS'!$C$7:$D$106,2,0) -> 1416.33 | H32: =VLOOKUP(C32,'SIND PITS'!$C$7:$E$106,3,0) -> 1250 | I32: =VLOOKUP(C32,'SIND PITS'!$C$7:$F$105,4,0) -> 0 | K32: =+D32+E32+G32+H32+I32 -> 4583.33 | L32: 10000 | M32: 5000 | O32: =VLOOKUP(C32,'IP PITS'!$B$9:$I$90,8,0) -> 0 | P32: =+H32+I32 -> 1250 | Q32: =VLOOKUP(C32,'IP PITS'!$B$9:$N$90,13,0) -> 0 | R32: =VLOOKUP(C32,'IP PITS'!$B$9:$O$90,14,0) -> 0 | T32: =VLOOKUP(C32,'IP PITS'!$B$9:$P$90,15,0) -> 0 | U32: =VLOOKUP(C32,'IP PITS'!$B$9:$Q$90,16,0) -> 0 | V32: 0 | W32: =VLOOKUP(C32,'IP PITS'!$B$9:$R$90,17,0) -> 1666.67 | Y32: =+K32-O32-P32+Q32+R32+S32+T32+U32+V32+W32 -> 5000 | Z32: =+M32-Y32 -> 0 | AB32: PITS
A33: SEI0413 | B33: SEITON (IP INNOVA II) | C33: Courtenay Gutierrez Barry Vladimir | E33: =VLOOKUP(C33,'IP PITS'!$B$9:$V$90,21,0) -> 2447.6 | G33: =VLOOKUP(C33,'SIND PITS'!$C$7:$D$106,2,0) -> 52.4 | H33: =VLOOKUP(C33,'SIND PITS'!$C$7:$E$106,3,0) -> 3825.5 | I33: =VLOOKUP(C33,'SIND PITS'!$C$7:$F$105,4,0) -> 0 | K33: =+D33+E33+G33+H33+I33 -> 6325.5 | L33: 5000 | M33: 2500 | O33: =VLOOKUP(C33,'IP PITS'!$B$9:$I$90,8,0) -> 0 | P33: =+H33+I33 -> 3825.5 | Q33: =VLOOKUP(C33,'IP PITS'!$B$9:$N$90,13,0) -> 0 | R33: =VLOOKUP(C33,'IP PITS'!$B$9:$O$90,14,0) -> 0 | T33: =VLOOKUP(C33,'IP PITS'!$B$9:$P$90,15,0) -> 0 | U33: =VLOOKUP(C33,'IP PITS'!$B$9:$Q$90,16,0) -> 0 | V33: 0 | W33: =VLOOKUP(C33,'IP PITS'!$B$9:$R$90,17,0) -> 0 | Y33: =+K33-O33-P33+Q33+R33+S33+T33+U33+V33+W33 -> 2500 | Z33: =+M33-Y33 -> 0 | AB33: PITS
A34: SEI0424 | B34: SEITON (IP INNOVA II) | C34: Palacios Ramos Jesus | E34: =VLOOKUP(C34,'IP PITS'!$B$9:$V$90,21,0) -> 3583.6 | G34: =VLOOKUP(C34,'SIND PITS'!$C$7:$D$106,2,0) -> 416.4 | H34: =VLOOKUP(C34,'SIND PITS'!$C$7:$E$106,3,0) -> 1681 | I34: =VLOOKUP(C34,'SIND PITS'!$C$7:$F$105,4,0) -> 0 | K34: =+D34+E34+G34+H34+I34 -> 5681 | L34: 8000 | M34: 4000 | O34: =VLOOKUP(C34,'IP PITS'!$B$9:$I$90,8,0) -> 0 | P34: =+H34+I34 -> 1681 | Q34: =VLOOKUP(C34,'IP PITS'!$B$9:$N$90,13,0) -> 0 | R34: =VLOOKUP(C34,'IP PITS'!$B$9:$O$90,14,0) -> 0 | T34: =VLOOKUP(C34,'IP PITS'!$B$9:$P$90,15,0) -> 0 | U34: =VLOOKUP(C34,'IP PITS'!$B$9:$Q$90,16,0) -> 0 | V34: 0 | W34: =VLOOKUP(C34,'IP PITS'!$B$9:$R$90,17,0) -> 0 | Y34: =+K34-O34-P34+Q34+R34+S34+T34+U34+V34+W34 -> 4000 | Z34: =+M34-Y34 -> 0 | AB34: PITS
A35: SEI0428 | B35: SEITON (IP INNOVA II) | C35: Martinez Hernandez J. Antonio | E35: =VLOOKUP(C35,'IP PITS'!$B$9:$V$90,21,0) -> 3583.8 | G35: =VLOOKUP(C35,'SIND PITS'!$C$7:$D$106,2,0) -> 416.2 | H35: =VLOOKUP(C35,'SIND PITS'!$C$7:$E$106,3,0) -> 280 | I35: =VLOOKUP(C35,'SIND PITS'!$C$7:$F$105,4,0) -> 0 | K35: =+D35+E35+G35+H35+I35 -> 4280 | L35: 8000 | M35: 4000 | O35: =VLOOKUP(C35,'IP PITS'!$B$9:$I$90,8,0) -> 0 | P35: =+H35+I35 -> 280 | Q35: =VLOOKUP(C35,'IP PITS'!$B$9:$N$90,13,0) -> 0 | R35: =VLOOKUP(C35,'IP PITS'!$B$9:$O$90,14,0) -> 0 | T35: =VLOOKUP(C35,'IP PITS'!$B$9:$P$90,15,0) -> 0 | U35: =VLOOKUP(C35,'IP PITS'!$B$9:$Q$90,16,0) -> 0 | V35: 0 | W35: =VLOOKUP(C35,'IP PITS'!$B$9:$R$90,17,0) -> 0 | Y35: =+K35-O35-P35+Q35+R35+S35+T35+U35+V35+W35 -> 4000 | Z35: =+M35-Y35 -> 0 | AB35: PITS
A36: SEI0431 | B36: SEITON (IP INNOVA II) | C36: Alcaraz Conde Zabdi Guadalupe | E36: =VLOOKUP(C36,'IP PITS'!$B$9:$V$90,21,0) -> 1129.4 | G36: =VLOOKUP(C36,'SIND PITS'!$C$7:$D$106,2,0) -> 135.2 | H36: =VLOOKUP(C36,'SIND PITS'!$C$7:$E$106,3,0) -> 292.5 | I36: =VLOOKUP(C36,'SIND PITS'!$C$7:$F$105,4,0) -> 0 | K36: =+D36+E36+G36+H36+I36 -> 1557.1 | L36: 6000 | M36: 3000 | O36: =VLOOKUP(C36,'IP PITS'!$B$9:$I$90,8,0) -> 0 | P36: =+H36+I36 -> 292.5 | Q36: =VLOOKUP(C36,'IP PITS'!$B$9:$N$90,13,0) -> 0 | R36: =VLOOKUP(C36,'IP PITS'!$B$9:$O$90,14,0) -> 1120.4 | T36: =VLOOKUP(C36,'IP PITS'!$B$9:$P$90,15,0) -> 15 | U36: =VLOOKUP(C36,'IP PITS'!$B$9:$Q$90,16,0) -> 600 | V36: 0 | W36: =VLOOKUP(C36,'IP PITS'!$B$9:$R$90,17,0) -> 0 | Y36: =+K36-O36-P36+Q36+R36+S36+T36+U36+V36+W36 -> 3000 | Z36: =+M36-Y36 -> 0 | AB36: PITS
A37: SEI0438 | B37: SEITON (IP INNOVA II) | C37: Lopez Terron Roberto Porfirio | E37: =VLOOKUP(C37,'IP PITS'!$B$9:$V$90,21,0) -> 5952.2 | G37: =VLOOKUP(C37,'SIND PITS'!$C$7:$D$106,2,0) -> 1047.8 | H37: =VLOOKUP(C37,'SIND PITS'!$C$7:$E$106,3,0) -> 3068 | I37: =VLOOKUP(C37,'SIND PITS'!$C$7:$F$105,4,0) -> 0 | K37: =+D37+E37+G37+H37+I37 -> 10068 | L37: 14000 | M37: 7000 | O37: =VLOOKUP(C37,'IP PITS'!$B$9:$I$90,8,0) -> 0 | P37: =+H37+I37 -> 3068 | Q37: =VLOOKUP(C37,'IP PITS'!$B$9:$N$90,13,0) -> 0 | R37: =VLOOKUP(C37,'IP PITS'!$B$9:$O$90,14,0) -> 0 | T37: =VLOOKUP(C37,'IP PITS'!$B$9:$P$90,15,0) -> 0 | U37: =VLOOKUP(C37,'IP PITS'!$B$9:$Q$90,16,0) -> 0 | V37: 0 | W37: =VLOOKUP(C37,'IP PITS'!$B$9:$R$90,17,0) -> 0 | Y37: =+K37-O37-P37+Q37+R37+S37+T37+U37+V37+W37 -> 7000 | Z37: =+M37-Y37 -> 0 | AB37: PITS
A38: SEI0442 | B38: SEITON (IP INNOVA II) | C38: Chavez Pedraza Samuel | E38: =VLOOKUP(C38,'IP PITS'!$B$9:$V$90,21,0) -> 5952.2 | G38: =VLOOKUP(C38,'SIND PITS'!$C$7:$D$106,2,0) -> 1047.8 | H38: =VLOOKUP(C38,'SIND PITS'!$C$7:$E$106,3,0) -> 1095 | I38: =VLOOKUP(C38,'SIND PITS'!$C$7:$F$105,4,0) -> 0 | K38: =+D38+E38+G38+H38+I38 -> 8095 | L38: 14000 | M38: 7000 | O38: =VLOOKUP(C38,'IP PITS'!$B$9:$I$90,8,0) -> 0 | P38: =+H38+I38 -> 1095 | Q38: =VLOOKUP(C38,'IP PITS'!$B$9:$N$90,13,0) -> 0 | R38: =VLOOKUP(C38,'IP PITS'!$B$9:$O$90,14,0) -> 0 | T38: =VLOOKUP(C38,'IP PITS'!$B$9:$P$90,15,0) -> 0 | U38: =VLOOKUP(C38,'IP PITS'!$B$9:$Q$90,16,0) -> 0 | V38: 0 | W38: =VLOOKUP(C38,'IP PITS'!$B$9:$R$90,17,0) -> 0 | Y38: =+K38-O38-P38+Q38+R38+S38+T38+U38+V38+W38 -> 7000 | Z38: =+M38-Y38 -> 0 | AB38: PITS
A39: SEI0443 | B39: SEITON (IP INNOVA II) | C39: Castillo Nungaray Nestor Roman | E39: =VLOOKUP(C39,'IP PITS'!$B$9:$V$90,21,0) -> 2864.8 | G39: =VLOOKUP(C39,'SIND PITS'!$C$7:$D$106,2,0) -> 135.2 | H39: =VLOOKUP(C39,'SIND PITS'!$C$7:$E$106,3,0) -> 1500 | I39: =VLOOKUP(C39,'SIND PITS'!$C$7:$F$105,4,0) -> 0 | K39: =+D39+E39+G39+H39+I39 -> 4500 | L39: 6000 | M39: 3000 | O39: =VLOOKUP(C39,'IP PITS'!$B$9:$I$90,8,0) -> 0 | P39: =+H39+I39 -> 1500 | Q39: =VLOOKUP(C39,'IP PITS'!$B$9:$N$90,13,0) -> 0 | R39: =VLOOKUP(C39,'IP PITS'!$B$9:$O$90,14,0) -> 0 | T39: =VLOOKUP(C39,'IP PITS'!$B$9:$P$90,15,0) -> 0 | U39: =VLOOKUP(C39,'IP PITS'!$B$9:$Q$90,16,0) -> 0 | V39: 0 | W39: =VLOOKUP(C39,'IP PITS'!$B$9:$R$90,17,0) -> 0 | Y39: =+K39-O39-P39+Q39+R39+S39+T39+U39+V39+W39 -> 3000 | Z39: =+M39-Y39 -> 0 | AB39: PITS
A40: SEI0444 | B40: SEITON (IP INNOVA II) | C40: Marquez Hernandez Rogelio | E40: =VLOOKUP(C40,'IP PITS'!$B$9:$V$90,21,0) -> 3583.6 | G40: =VLOOKUP(C40,'SIND PITS'!$C$7:$D$106,2,0) -> 416.4 | H40: =VLOOKUP(C40,'SIND PITS'!$C$7:$E$106,3,0) -> 826 | I40: =VLOOKUP(C40,'SIND PITS'!$C$7:$F$105,4,0) -> 0 | K40: =+D40+E40+G40+H40+I40 -> 4826 | L40: 8000 | M40: 4000 | O40: =VLOOKUP(C40,'IP PITS'!$B$9:$I$90,8,0) -> 0 | P40: =+H40+I40 -> 826 | Q40: =VLOOKUP(C40,'IP PITS'!$B$9:$N$90,13,0) -> 0 | R40: =VLOOKUP(C40,'IP PITS'!$B$9:$O$90,14,0) -> 0 | T40: =VLOOKUP(C40,'IP PITS'!$B$9:$P$90,15,0) -> 0 | U40: =VLOOKUP(C40,'IP PITS'!$B$9:$Q$90,16,0) -> 0 | V40: 0 | W40: =VLOOKUP(C40,'IP PITS'!$B$9:$R$90,17,0) -> 0 | Y40: =+K40-O40-P40+Q40+R40+S40+T40+U40+V40+W40 -> 4000 | Z40: =+M40-Y40 -> 0 | AB40: PITS
A41: SEI0449 | B41: SEITON (IP INNOVA II) | C41: Flores Cerrillos Jorge Humberto | E41: =VLOOKUP(C41,'IP PITS'!$B$9:$V$90,21,0) -> 3583.6 | G41: =VLOOKUP(C41,'SIND PITS'!$C$7:$D$106,2,0) -> 416.4 | H41: =VLOOKUP(C41,'SIND PITS'!$C$7:$E$106,3,0) -> 287 | I41: =VLOOKUP(C41,'SIND PITS'!$C$7:$F$105,4,0) -> 0 | K41: =+D41+E41+G41+H41+I41 -> 4287 | L41: 8000 | M41: 4000 | O41: =VLOOKUP(C41,'IP PITS'!$B$9:$I$90,8,0) -> 0 | P41: =+H41+I41 -> 287 | Q41: =VLOOKUP(C41,'IP PITS'!$B$9:$N$90,13,0) -> 0 | R41: =VLOOKUP(C41,'IP PITS'!$B$9:$O$90,14,0) -> 0 | T41: =VLOOKUP(C41,'IP PITS'!$B$9:$P$90,15,0) -> 0 | U41: =VLOOKUP(C41,'IP PITS'!$B$9:$Q$90,16,0) -> 0 | V41: 0 | W41: =VLOOKUP(C41,'IP PITS'!$B$9:$R$90,17,0) -> 0 | Y41: =+K41-O41-P41+Q41+R41+S41+T41+U41+V41+W41 -> 4000 | Z41: =+M41-Y41 -> 0 | AB41: PITS
A42: SEI0455 | B42: SEITON (IP INNOVA II) | C42: Perez Garcia Andres Alvaro | E42: =VLOOKUP(C42,'IP PITS'!$B$9:$V$90,21,0) -> 3583.6 | G42: =VLOOKUP(C42,'SIND PITS'!$C$7:$D$106,2,0) -> 416.4 | H42: =VLOOKUP(C42,'SIND PITS'!$C$7:$E$106,3,0) -> 740 | I42: =VLOOKUP(C42,'SIND PITS'!$C$7:$F$105,4,0) -> 0 | K42: =+D42+E42+G42+H42+I42 -> 4740 | L42: 8000 | M42: 4000 | O42: =VLOOKUP(C42,'IP PITS'!$B$9:$I$90,8,0) -> 0 | P42: =+H42+I42 -> 740 | Q42: =VLOOKUP(C42,'IP PITS'!$B$9:$N$90,13,0) -> 0 | R42: =VLOOKUP(C42,'IP PITS'!$B$9:$O$90,14,0) -> 0 | T42: =VLOOKUP(C42,'IP PITS'!$B$9:$P$90,15,0) -> 0 | U42: =VLOOKUP(C42,'IP PITS'!$B$9:$Q$90,16,0) -> 0 | V42: 0 | W42: =VLOOKUP(C42,'IP PITS'!$B$9:$R$90,17,0) -> 0 | Y42: =+K42-O42-P42+Q42+R42+S42+T42+U42+V42+W42 -> 4000 | Z42: =+M42-Y42 -> 0 | AB42: PITS
A43: SEI0456 | B43: SEITON (IP INNOVA II) | C43: Chavira Garcia David Fernando | E43: =VLOOKUP(C43,'IP PITS'!$B$9:$V$90,21,0) -> 4406.4 | G43: =VLOOKUP(C43,'SIND PITS'!$C$7:$D$106,2,0) -> 593.6 | H43: =VLOOKUP(C43,'SIND PITS'!$C$7:$E$106,3,0) -> 121.5 | I43: =VLOOKUP(C43,'SIND PITS'!$C$7:$F$105,4,0) -> 0 | K43: =+D43+E43+G43+H43+I43 -> 5121.5 | L43: 10000 | M43: 5000 | O43: =VLOOKUP(C43,'IP PITS'!$B$9:$I$90,8,0) -> 0 | P43: =+H43+I43 -> 121.5 | Q43: =VLOOKUP(C43,'IP PITS'!$B$9:$N$90,13,0) -> 0 | R43: =VLOOKUP(C43,'IP PITS'!$B$9:$O$90,14,0) -> 0 | T43: =VLOOKUP(C43,'IP PITS'!$B$9:$P$90,15,0) -> 0 | U43: =VLOOKUP(C43,'IP PITS'!$B$9:$Q$90,16,0) -> 0 | V43: 0 | W43: =VLOOKUP(C43,'IP PITS'!$B$9:$R$90,17,0) -> 0 | Y43: =+K43-O43-P43+Q43+R43+S43+T43+U43+V43+W43 -> 5000 | Z43: =+M43-Y43 -> 0 | AB43: PITS
... A67: SEI0422 | B67: SEITON (IP INNOVA II) | C67: Torres Perez Carlos Alberto | E67: =VLOOKUP(C67,'IP PITS'!$B$9:$V$90,21,0) -> 3079.2 | G67: =VLOOKUP(C67,'SIND PITS'!$C$7:$D$106,2,0) -> 1917.3 | H67: =VLOOKUP(C67,'SIND PITS'!$C$7:$E$106,3,0) -> 5149.88 | I67: =VLOOKUP(C67,'SIND PITS'!$C$7:$F$105,4,0) -> 0 | K67: =+D67+E67+G67+H67+I67 -> 10146.38 | L67: 10500 | M67: 5250 | O67: =VLOOKUP(C67,'IP PITS'!$B$9:$I$90,8,0) -> 0 | P67: =+H67+I67 -> 5149.88 | Q67: =VLOOKUP(C67,'IP PITS'!$B$9:$N$90,13,0) -> 0 | R67: =VLOOKUP(C67,'IP PITS'!$B$9:$O$90,14,0) -> 0 | T67: =VLOOKUP(C67,'IP PITS'!$B$9:$P$90,15,0) -> 0 | U67: =VLOOKUP(C67,'IP PITS'!$B$9:$Q$90,16,0) -> 0 | V67: 0 | W67: =VLOOKUP(C67,'IP PITS'!$B$9:$R$90,17,0) -> 253.5 | Y67: =+K67-O67-P67+Q67+R67+S67+T67+U67+V67+W67 -> 5250 | Z67: =+M67-Y67 -> 0 | AB67: PITS
A68: SEI0424 | B68: SEITON (IP INNOVA II) | C68: Treviño Alvarez Jorge Alberto | E68: =VLOOKUP(C68,'IP PITS'!$B$9:$V$90,21,0) -> 1222.4 | G68: =VLOOKUP(C68,'SIND PITS'!$C$7:$D$106,2,0) -> 2050.17 | H68: =VLOOKUP(C68,'SIND PITS'!$C$7:$E$106,3,0) -> 1280 | I68: =VLOOKUP(C68,'SIND PITS'!$C$7:$F$105,4,0) -> 0 | K68: =+D68+E68+G68+H68+I68 -> 4552.57 | L68: 12000 | M68: 6000 | O68: =VLOOKUP(C68,'IP PITS'!$B$9:$I$90,8,0) -> 0 | P68: =+H68+I68 -> 1280 | Q68: =VLOOKUP(C68,'IP PITS'!$B$9:$N$90,13,0) -> 1202.43 | R68: =VLOOKUP(C68,'IP PITS'!$B$9:$O$90,14,0) -> 0 | T68: =VLOOKUP(C68,'IP PITS'!$B$9:$P$90,15,0) -> 15 | U68: =VLOOKUP(C68,'IP PITS'!$B$9:$Q$90,16,0) -> 0 | V68: 0 | W68: =VLOOKUP(C68,'IP PITS'!$B$9:$R$90,17,0) -> 310 | Y68: =+K68-O68-P68+Q68+R68+S68+T68+U68+V68+W68 -> 4800 | Z68: =+M68-Y68 -> 1200 | AA68: incapacidad | AB68: PITS
A69: SEI0425 | B69: SEITON (IP INNOVA II) | C69: Tenorio Alvarez Alberto Antonio | E69: =VLOOKUP(C69,'IP PITS'!$B$9:$V$90,21,0) -> 2195 | G69: =VLOOKUP(C69,'SIND PITS'!$C$7:$D$106,2,0) -> 1667.37 | H69: =VLOOKUP(C69,'SIND PITS'!$C$7:$E$106,3,0) -> 1417 | I69: =VLOOKUP(C69,'SIND PITS'!$C$7:$F$105,4,0) -> 0 | K69: =+D69+E69+G69+H69+I69 -> 5279.37 | L69: 10000 | M69: 5000 | O69: =VLOOKUP(C69,'IP PITS'!$B$9:$I$90,8,0) -> 0 | P69: =+H69+I69 -> 1417 | Q69: =VLOOKUP(C69,'IP PITS'!$B$9:$N$90,13,0) -> 0 | R69: =VLOOKUP(C69,'IP PITS'!$B$9:$O$90,14,0) -> 1122.63 | T69: =VLOOKUP(C69,'IP PITS'!$B$9:$P$90,15,0) -> 15 | U69: =VLOOKUP(C69,'IP PITS'!$B$9:$Q$90,16,0) -> 0 | V69: 0 | W69: =VLOOKUP(C69,'IP PITS'!$B$9:$R$90,17,0) -> 0 | Y69: =+K69-O69-P69+Q69+R69+S69+T69+U69+V69+W69 -> 5000 | Z69: =+M69-Y69 -> 0 | AB69: PITS
A70: SEI0426 | B70: SEITON (IP INNOVA II) | C70: Chavez Dominguez Salvador | E70: =VLOOKUP(C70,'IP PITS'!$B$9:$V$90,21,0) -> 3332.6 | G70: =VLOOKUP(C70,'SIND PITS'!$C$7:$D$106,2,0) -> 2667.4 | H70: =VLOOKUP(C70,'SIND PITS'!$C$7:$E$106,3,0) -> 1054.5 | I70: =VLOOKUP(C70,'SIND PITS'!$C$7:$F$105,4,0) -> 0 | K70: =+D70+E70+G70+H70+I70 -> 7054.5 | L70: 12000 | M70: 6000 | O70: =VLOOKUP(C70,'IP PITS'!$B$9:$I$90,8,0) -> 0 | P70: =+H70+I70 -> 1054.5 | Q70: =VLOOKUP(C70,'IP PITS'!$B$9:$N$90,13,0) -> 0 | R70: =VLOOKUP(C70,'IP PITS'!$B$9:$O$90,14,0) -> 0 | T70: =VLOOKUP(C70,'IP PITS'!$B$9:$P$90,15,0) -> 0 | U70: =VLOOKUP(C70,'IP PITS'!$B$9:$Q$90,16,0) -> 0 | V70: 0 | W70: =VLOOKUP(C70,'IP PITS'!$B$9:$R$90,17,0) -> 0 | Y70: =+K70-O70-P70+Q70+R70+S70+T70+U70+V70+W70 -> 6000 | Z70: =+M70-Y70 -> 0 | AB70: PITS
A71: SEI0428 | B71: SEITON (IP INNOVA II) | C71: Cruz Herrera Roberto | E71: =VLOOKUP(C71,'IP PITS'!$B$9:$V$90,21,0) -> 2073.8 | G71: =VLOOKUP(C71,'SIND PITS'!$C$7:$D$106,2,0) -> 1667.47 | H71: =VLOOKUP(C71,'SIND PITS'!$C$7:$E$106,3,0) -> 226.5 | I71: =VLOOKUP(C71,'SIND PITS'!$C$7:$F$105,4,0) -> 0 | K71: =+D71+E71+G71+H71+I71 -> 3967.77 | L71: 10000 | M71: 5000 | O71: =VLOOKUP(C71,'IP PITS'!$B$9:$I$90,8,0) -> 0 | P71: =+H71+I71 -> 226.5 | Q71: =VLOOKUP(C71,'IP PITS'!$B$9:$N$90,13,0) -> 692.93 | R71: =VLOOKUP(C71,'IP PITS'!$B$9:$O$90,14,0) -> 0 | T71: =VLOOKUP(C71,'IP PITS'!$B$9:$P$90,15,0) -> 15 | U71: =VLOOKUP(C71,'IP PITS'!$B$9:$Q$90,16,0) -> 0 | V71: 0 | W71: =VLOOKUP(C71,'IP PITS'!$B$9:$R$90,17,0) -> 550.83 | Y71: =+K71-O71-P71+Q71+R71+S71+T71+U71+V71+W71 -> 5000.03 | Z71: =+M71-Y71 -> -0.03 | AB71: PITS
A72: SEI0430 | B72: SEITON (IP INNOVA II) | C72: Martinez Rodriguez Paulo Cesar | E72: =VLOOKUP(C72,'IP PITS'!$B$9:$V$90,21,0) -> 2447.6 | G72: =VLOOKUP(C72,'SIND PITS'!$C$7:$D$106,2,0) -> 2552.4 | H72: =VLOOKUP(C72,'SIND PITS'!$C$7:$E$106,3,0) -> 250 | I72: =VLOOKUP(C72,'SIND PITS'!$C$7:$F$105,4,0) -> 0 | K72: =+D72+E72+G72+H72+I72 -> 5250 | L72: 10000 | M72: 5000 | O72: =VLOOKUP(C72,'IP PITS'!$B$9:$I$90,8,0) -> 0 | P72: =+H72+I72 -> 250 | Q72: =VLOOKUP(C72,'IP PITS'!$B$9:$N$90,13,0) -> 0 | R72: =VLOOKUP(C72,'IP PITS'!$B$9:$O$90,14,0) -> 0 | T72: =VLOOKUP(C72,'IP PITS'!$B$9:$P$90,15,0) -> 0 | U72: =VLOOKUP(C72,'IP PITS'!$B$9:$Q$90,16,0) -> 0 | V72: 0 | W72: =VLOOKUP(C72,'IP PITS'!$B$9:$R$90,17,0) -> 0 | Y72: =+K72-O72-P72+Q72+R72+S72+T72+U72+V72+W72 -> 5000 | Z72: =+M72-Y72 -> 0 | AB72: PITS
A73: SEI0431 | B73: SEITON (IP INNOVA II) | C73: Martinez Malo Cesar | E73: =VLOOKUP(C73,'IP PITS'!$B$9:$V$90,21,0) -> 1892.4 | G73: =VLOOKUP(C73,'SIND PITS'!$C$7:$D$106,2,0) -> 1694.1 | H73: =VLOOKUP(C73,'SIND PITS'!$C$7:$E$106,3,0) -> 382 | I73: =VLOOKUP(C73,'SIND PITS'!$C$7:$F$105,4,0) -> 0 | K73: =+D73+E73+G73+H73+I73 -> 3968.5 | L73: 9000 | M73: 4500 | O73: =VLOOKUP(C73,'IP PITS'!$B$9:$I$90,8,0) -> 0 | P73: =+H73+I73 -> 382 | Q73: =VLOOKUP(C73,'IP PITS'!$B$9:$N$90,13,0) -> 898.5 | R73: =VLOOKUP(C73,'IP PITS'!$B$9:$O$90,14,0) -> 0 | T73: =VLOOKUP(C73,'IP PITS'!$B$9:$P$90,15,0) -> 15 | U73: =VLOOKUP(C73,'IP PITS'!$B$9:$Q$90,16,0) -> 0 | V73: 0 | W73: =VLOOKUP(C73,'IP PITS'!$B$9:$R$90,17,0) -> 0 | Y73: =+K73-O73-P73+Q73+R73+S73+T73+U73+V73+W73 -> 4500 | Z73: =+M73-Y73 -> 0 | AB73: PITS
A74: SEI0432 | B74: SEITON (IP INNOVA II) | C74: Perez Balboa Cesar | E74: =VLOOKUP(C74,'IP PITS'!$B$9:$V$90,21,0) -> 1881.6 | G74: =VLOOKUP(C74,'SIND PITS'!$C$7:$D$106,2,0) -> 2194.19 | H74: =VLOOKUP(C74,'SIND PITS'!$C$7:$E$106,3,0) -> 84 | I74: =VLOOKUP(C74,'SIND PITS'!$C$7:$F$105,4,0) -> 0 | K74: =+D74+E74+G74+H74+I74 -> 4159.79 | L74: 10000 | M74: 5000 | O74: =VLOOKUP(C74,'IP PITS'!$B$9:$I$90,8,0) -> 0 | P74: =+H74+I74 -> 84 | Q74: =VLOOKUP(C74,'IP PITS'!$B$9:$N$90,13,0) -> 909.21 | R74: =VLOOKUP(C74,'IP PITS'!$B$9:$O$90,14,0) -> 0 | T74: =VLOOKUP(C74,'IP PITS'!$B$9:$P$90,15,0) -> 15 | U74: =VLOOKUP(C74,'IP PITS'!$B$9:$Q$90,16,0) -> 0 | V74: 0 | W74: =VLOOKUP(C74,'IP PITS'!$B$9:$R$90,17,0) -> 0 | Y74: =+K74-O74-P74+Q74+R74+S74+T74+U74+V74+W74 -> 5000 | Z74: =+M74-Y74 -> 0 | AB74: PITS
A75: SEI0435 | B75: SEITON (IP INNOVA II) | C75: Cerro Garcia Elvis | E75: =VLOOKUP(C75,'IP PITS'!$B$9:$V$90,21,0) -> 2446.6 | G75: =VLOOKUP(C75,'SIND PITS'!$C$7:$D$106,2,0) -> 2553.4 | H75: =VLOOKUP(C75,'SIND PITS'!$C$7:$E$106,3,0) -> 200 | I75: =VLOOKUP(C75,'SIND PITS'!$C$7:$F$105,4,0) -> 0 | K75: =+D75+E75+G75+H75+I75 -> 5200 | L75: 10000 | M75: 5000 | O75: =VLOOKUP(C75,'IP PITS'!$B$9:$I$90,8,0) -> 0 | P75: =+H75+I75 -> 200 | Q75: =VLOOKUP(C75,'IP PITS'!$B$9:$N$90,13,0) -> 0 | R75: =VLOOKUP(C75,'IP PITS'!$B$9:$O$90,14,0) -> 0 | T75: =VLOOKUP(C75,'IP PITS'!$B$9:$P$90,15,0) -> 0 | U75: =VLOOKUP(C75,'IP PITS'!$B$9:$Q$90,16,0) -> 0 | V75: 0 | W75: =VLOOKUP(C75,'IP PITS'!$B$9:$R$90,17,0) -> 0 | Y75: =+K75-O75-P75+Q75+R75+S75+T75+U75+V75+W75 -> 5000 | Z75: =+M75-Y75 -> 0 | AB75: PITS
A76: SEI0509 | B76: SEITON (IP INNOVA II) | C76: Gutierrez Castillo Jose De Jesus | E76: =VLOOKUP(C76,'IP PITS'!$B$9:$V$90,21,0) -> 2865.8 | G76: =VLOOKUP(C76,'SIND PITS'!$C$7:$D$106,2,0) -> 284.2 | H76: =VLOOKUP(C76,'SIND PITS'!$C$7:$E$106,3,0) -> 811 | I76: =VLOOKUP(C76,'SIND PITS'!$C$7:$F$105,4,0) -> 0 | K76: =+D76+E76+G76+H76+I76 -> 3961 | L76: 6300 | M76: 3150 | O76: =VLOOKUP(C76,'IP PITS'!$B$9:$I$90,8,0) -> 0 | P76: =+H76+I76 -> 811 | Q76: =VLOOKUP(C76,'IP PITS'!$B$9:$N$90,13,0) -> 0 | R76: =VLOOKUP(C76,'IP PITS'!$B$9:$O$90,14,0) -> 0 | T76: =VLOOKUP(C76,'IP PITS'!$B$9:$P$90,15,0) -> 0 | U76: =VLOOKUP(C76,'IP PITS'!$B$9:$Q$90,16,0) -> 0 | V76: 0 | W76: =VLOOKUP(C76,'IP PITS'!$B$9:$R$90,17,0) -> 0 | Y76: =+K76-O76-P76+Q76+R76+S76+T76+U76+V76+W76 -> 3150 | Z76: =+M76-Y76 -> 0 | AB76: PITS
A77: SEI0433 | B77: SEITON (IP INNOVA II) | C77: Mejia Duarte Jose Luis | E77: =VLOOKUP(C77,'IP PITS'!$B$9:$V$90,21,0) -> 2446.6 | G77: =VLOOKUP(C77,'SIND PITS'!$C$7:$D$106,2,0) -> 3553.4 | H77: =VLOOKUP(C77,'SIND PITS'!$C$7:$E$106,3,0) -> 812 | I77: =VLOOKUP(C77,'SIND PITS'!$C$7:$F$105,4,0) -> 0 | K77: =+D77+E77+G77+H77+I77 -> 6812 | L77: 12000 | M77: 6000 | O77: =VLOOKUP(C77,'IP PITS'!$B$9:$I$90,8,0) -> 0 | P77: =+H77+I77 -> 812 | Q77: =VLOOKUP(C77,'IP PITS'!$B$9:$N$90,13,0) -> 0 | R77: =VLOOKUP(C77,'IP PITS'!$B$9:$O$90,14,0) -> 0 | T77: =VLOOKUP(C77,'IP PITS'!$B$9:$P$90,15,0) -> 0 | U77: =VLOOKUP(C77,'IP PITS'!$B$9:$Q$90,16,0) -> 0 | V77: 0 | W77: =VLOOKUP(C77,'IP PITS'!$B$9:$R$90,17,0) -> 0 | Y77: =+K77-O77-P77+Q77+R77+S77+T77+U77+V77+W77 -> 6000 | Z77: =+M77-Y77 -> 0 | AB77: PITS
A78: SEI0511 | B78: SEITON (IP INNOVA II) | C78: Lizaran Maceda Jose Guadalupe | E78: =VLOOKUP(C78,'IP PITS'!$B$9:$V$90,21,0) -> 2447.2 | G78: =VLOOKUP(C78,'SIND PITS'!$C$7:$D$106,2,0) -> 52.8 | H78: =VLOOKUP(C78,'SIND PITS'!$C$7:$E$106,3,0) -> 305.5 | I78: =VLOOKUP(C78,'SIND PITS'!$C$7:$F$105,4,0) -> 0 | K78: =+D78+E78+G78+H78+I78 -> 2805.5 | L78: 5000 | M78: 2500 | O78: =VLOOKUP(C78,'IP PITS'!$B$9:$I$90,8,0) -> 0 | P78: =+H78+I78 -> 305.5 | Q78: =VLOOKUP(C78,'IP PITS'!$B$9:$N$90,13,0) -> 0 | R78: =VLOOKUP(C78,'IP PITS'!$B$9:$O$90,14,0) -> 0 | T78: =VLOOKUP(C78,'IP PITS'!$B$9:$P$90,15,0) -> 0 | U78: =VLOOKUP(C78,'IP PITS'!$B$9:$Q$90,16,0) -> 0 | V78: 0 | W78: =VLOOKUP(C78,'IP PITS'!$B$9:$R$90,17,0) -> 0 | Y78: =+K78-O78-P78+Q78+R78+S78+T78+U78+V78+W78 -> 2500 | Z78: =+M78-Y78 -> 0 | AB78: PITS
A79: SEI0513 | B79: SEITON (IP INNOVA II) | C79: Mendez Rivera Ivan Israel | E79: =VLOOKUP(C79,'IP PITS'!$B$9:$V$90,21,0) -> 2014.8 | G79: =VLOOKUP(C79,'SIND PITS'!$C$7:$D$106,2,0) -> 52.44 | H79: =VLOOKUP(C79,'SIND PITS'!$C$7:$E$106,3,0) -> 338.5 | I79: =VLOOKUP(C79,'SIND PITS'!$C$7:$F$105,4,0) -> 0 | K79: =+D79+E79+G79+H79+I79 -> 2405.74 | L79: 5000 | M79: 2500 | O79: =VLOOKUP(C79,'IP PITS'!$B$9:$I$90,8,0) -> 0 | P79: =+H79+I79 -> 338.5 | Q79: =VLOOKUP(C79,'IP PITS'!$B$9:$N$90,13,0) -> 417.76 | R79: =VLOOKUP(C79,'IP PITS'!$B$9:$O$90,14,0) -> 0 | T79: =VLOOKUP(C79,'IP PITS'!$B$9:$P$90,15,0) -> 15 | U79: =VLOOKUP(C79,'IP PITS'!$B$9:$Q$90,16,0) -> 0 | V79: 0 | W79: =VLOOKUP(C79,'IP PITS'!$B$9:$R$90,17,0) -> 0 | Y79: =+K79-O79-P79+Q79+R79+S79+T79+U79+V79+W79 -> 2500 | Z79: =+M79-Y79 -> 0 | AB79: PITS
